// 
// Decompiled by Procyon v0.5.36
// 

package kotlin.collections;

import java.util.TreeSet;
import java.util.SortedSet;
import kotlin.TypeCastException;
import java.util.Iterator;
import kotlin.PublishedApi;
import kotlin.jvm.JvmName;
import kotlin.SinceKotlin;
import kotlin.internal.PlatformImplementationsKt;
import java.util.Arrays;
import java.util.Comparator;
import java.util.Collection;
import java.util.ArrayList;
import kotlin.jvm.internal.Intrinsics;
import java.util.List;
import kotlin.internal.InlineOnly;
import org.jetbrains.annotations.NotNull;
import kotlin.Metadata;

@Metadata(mv = { 1, 1, 15 }, bv = { 1, 0, 3 }, k = 5, xi = 1, d1 = { "\u0000\u0096\u0001\n\u0000\n\u0002\u0010 \n\u0000\n\u0002\u0010\u0011\n\u0000\n\u0002\u0010\u000b\n\u0002\u0010\u0018\n\u0002\u0010\u0005\n\u0002\u0010\u0012\n\u0002\u0010\f\n\u0002\u0010\u0019\n\u0002\u0010\u0006\n\u0002\u0010\u0013\n\u0002\u0010\u0007\n\u0002\u0010\u0014\n\u0002\u0010\b\n\u0002\u0010\u0015\n\u0002\u0010\t\n\u0002\u0010\u0016\n\u0002\u0010\n\n\u0002\u0010\u0017\n\u0002\b\u0003\n\u0002\u0018\u0002\n\u0002\u0018\u0002\n\u0002\b\f\n\u0002\u0010\u000e\n\u0002\b\u0017\n\u0002\u0010\u0002\n\u0002\b\u0004\n\u0002\u0018\u0002\n\u0002\b\u0003\n\u0002\u0010\u001f\n\u0002\b\u0005\n\u0002\u0010\u001e\n\u0002\b\u0004\n\u0002\u0010\u000f\n\u0002\b\u0006\n\u0002\u0018\u0002\n\u0002\b\f\u001a#\u0010\u0000\u001a\b\u0012\u0004\u0012\u0002H\u00020\u0001\"\u0004\b\u0000\u0010\u0002*\n\u0012\u0006\b\u0001\u0012\u0002H\u00020\u0003¢\u0006\u0002\u0010\u0004\u001a\u0010\u0010\u0000\u001a\b\u0012\u0004\u0012\u00020\u00050\u0001*\u00020\u0006\u001a\u0010\u0010\u0000\u001a\b\u0012\u0004\u0012\u00020\u00070\u0001*\u00020\b\u001a\u0010\u0010\u0000\u001a\b\u0012\u0004\u0012\u00020\t0\u0001*\u00020\n\u001a\u0010\u0010\u0000\u001a\b\u0012\u0004\u0012\u00020\u000b0\u0001*\u00020\f\u001a\u0010\u0010\u0000\u001a\b\u0012\u0004\u0012\u00020\r0\u0001*\u00020\u000e\u001a\u0010\u0010\u0000\u001a\b\u0012\u0004\u0012\u00020\u000f0\u0001*\u00020\u0010\u001a\u0010\u0010\u0000\u001a\b\u0012\u0004\u0012\u00020\u00110\u0001*\u00020\u0012\u001a\u0010\u0010\u0000\u001a\b\u0012\u0004\u0012\u00020\u00130\u0001*\u00020\u0014\u001aU\u0010\u0015\u001a\u00020\u000f\"\u0004\b\u0000\u0010\u0002*\n\u0012\u0006\b\u0001\u0012\u0002H\u00020\u00032\u0006\u0010\u0016\u001a\u0002H\u00022\u001a\u0010\u0017\u001a\u0016\u0012\u0006\b\u0000\u0012\u0002H\u00020\u0018j\n\u0012\u0006\b\u0000\u0012\u0002H\u0002`\u00192\b\b\u0002\u0010\u001a\u001a\u00020\u000f2\b\b\u0002\u0010\u001b\u001a\u00020\u000f¢\u0006\u0002\u0010\u001c\u001a9\u0010\u0015\u001a\u00020\u000f\"\u0004\b\u0000\u0010\u0002*\n\u0012\u0006\b\u0001\u0012\u0002H\u00020\u00032\u0006\u0010\u0016\u001a\u0002H\u00022\b\b\u0002\u0010\u001a\u001a\u00020\u000f2\b\b\u0002\u0010\u001b\u001a\u00020\u000f¢\u0006\u0002\u0010\u001d\u001a&\u0010\u0015\u001a\u00020\u000f*\u00020\b2\u0006\u0010\u0016\u001a\u00020\u00072\b\b\u0002\u0010\u001a\u001a\u00020\u000f2\b\b\u0002\u0010\u001b\u001a\u00020\u000f\u001a&\u0010\u0015\u001a\u00020\u000f*\u00020\n2\u0006\u0010\u0016\u001a\u00020\t2\b\b\u0002\u0010\u001a\u001a\u00020\u000f2\b\b\u0002\u0010\u001b\u001a\u00020\u000f\u001a&\u0010\u0015\u001a\u00020\u000f*\u00020\f2\u0006\u0010\u0016\u001a\u00020\u000b2\b\b\u0002\u0010\u001a\u001a\u00020\u000f2\b\b\u0002\u0010\u001b\u001a\u00020\u000f\u001a&\u0010\u0015\u001a\u00020\u000f*\u00020\u000e2\u0006\u0010\u0016\u001a\u00020\r2\b\b\u0002\u0010\u001a\u001a\u00020\u000f2\b\b\u0002\u0010\u001b\u001a\u00020\u000f\u001a&\u0010\u0015\u001a\u00020\u000f*\u00020\u00102\u0006\u0010\u0016\u001a\u00020\u000f2\b\b\u0002\u0010\u001a\u001a\u00020\u000f2\b\b\u0002\u0010\u001b\u001a\u00020\u000f\u001a&\u0010\u0015\u001a\u00020\u000f*\u00020\u00122\u0006\u0010\u0016\u001a\u00020\u00112\b\b\u0002\u0010\u001a\u001a\u00020\u000f2\b\b\u0002\u0010\u001b\u001a\u00020\u000f\u001a&\u0010\u0015\u001a\u00020\u000f*\u00020\u00142\u0006\u0010\u0016\u001a\u00020\u00132\b\b\u0002\u0010\u001a\u001a\u00020\u000f2\b\b\u0002\u0010\u001b\u001a\u00020\u000f\u001a2\u0010\u001e\u001a\u00020\u0005\"\u0004\b\u0000\u0010\u0002*\n\u0012\u0006\b\u0001\u0012\u0002H\u00020\u00032\u000e\u0010\u001f\u001a\n\u0012\u0006\b\u0001\u0012\u0002H\u00020\u0003H\u0087\f¢\u0006\u0004\b \u0010!\u001a\"\u0010\"\u001a\u00020\u000f\"\u0004\b\u0000\u0010\u0002*\n\u0012\u0006\b\u0001\u0012\u0002H\u00020\u0003H\u0087\b¢\u0006\u0004\b#\u0010$\u001a\"\u0010%\u001a\u00020&\"\u0004\b\u0000\u0010\u0002*\n\u0012\u0006\b\u0001\u0012\u0002H\u00020\u0003H\u0087\b¢\u0006\u0004\b'\u0010(\u001a0\u0010)\u001a\u00020\u0005\"\u0004\b\u0000\u0010\u0002*\n\u0012\u0006\b\u0001\u0012\u0002H\u00020\u00032\u000e\u0010\u001f\u001a\n\u0012\u0006\b\u0001\u0012\u0002H\u00020\u0003H\u0087\f¢\u0006\u0002\u0010!\u001a\u0015\u0010)\u001a\u00020\u0005*\u00020\u00062\u0006\u0010\u001f\u001a\u00020\u0006H\u0087\f\u001a\u0015\u0010)\u001a\u00020\u0005*\u00020\b2\u0006\u0010\u001f\u001a\u00020\bH\u0087\f\u001a\u0015\u0010)\u001a\u00020\u0005*\u00020\n2\u0006\u0010\u001f\u001a\u00020\nH\u0087\f\u001a\u0015\u0010)\u001a\u00020\u0005*\u00020\f2\u0006\u0010\u001f\u001a\u00020\fH\u0087\f\u001a\u0015\u0010)\u001a\u00020\u0005*\u00020\u000e2\u0006\u0010\u001f\u001a\u00020\u000eH\u0087\f\u001a\u0015\u0010)\u001a\u00020\u0005*\u00020\u00102\u0006\u0010\u001f\u001a\u00020\u0010H\u0087\f\u001a\u0015\u0010)\u001a\u00020\u0005*\u00020\u00122\u0006\u0010\u001f\u001a\u00020\u0012H\u0087\f\u001a\u0015\u0010)\u001a\u00020\u0005*\u00020\u00142\u0006\u0010\u001f\u001a\u00020\u0014H\u0087\f\u001a \u0010*\u001a\u00020\u000f\"\u0004\b\u0000\u0010\u0002*\n\u0012\u0006\b\u0001\u0012\u0002H\u00020\u0003H\u0087\b¢\u0006\u0002\u0010$\u001a\r\u0010*\u001a\u00020\u000f*\u00020\u0006H\u0087\b\u001a\r\u0010*\u001a\u00020\u000f*\u00020\bH\u0087\b\u001a\r\u0010*\u001a\u00020\u000f*\u00020\nH\u0087\b\u001a\r\u0010*\u001a\u00020\u000f*\u00020\fH\u0087\b\u001a\r\u0010*\u001a\u00020\u000f*\u00020\u000eH\u0087\b\u001a\r\u0010*\u001a\u00020\u000f*\u00020\u0010H\u0087\b\u001a\r\u0010*\u001a\u00020\u000f*\u00020\u0012H\u0087\b\u001a\r\u0010*\u001a\u00020\u000f*\u00020\u0014H\u0087\b\u001a \u0010+\u001a\u00020&\"\u0004\b\u0000\u0010\u0002*\n\u0012\u0006\b\u0001\u0012\u0002H\u00020\u0003H\u0087\b¢\u0006\u0002\u0010(\u001a\r\u0010+\u001a\u00020&*\u00020\u0006H\u0087\b\u001a\r\u0010+\u001a\u00020&*\u00020\bH\u0087\b\u001a\r\u0010+\u001a\u00020&*\u00020\nH\u0087\b\u001a\r\u0010+\u001a\u00020&*\u00020\fH\u0087\b\u001a\r\u0010+\u001a\u00020&*\u00020\u000eH\u0087\b\u001a\r\u0010+\u001a\u00020&*\u00020\u0010H\u0087\b\u001a\r\u0010+\u001a\u00020&*\u00020\u0012H\u0087\b\u001a\r\u0010+\u001a\u00020&*\u00020\u0014H\u0087\b\u001aQ\u0010,\u001a\b\u0012\u0004\u0012\u0002H\u00020\u0003\"\u0004\b\u0000\u0010\u0002*\n\u0012\u0006\b\u0001\u0012\u0002H\u00020\u00032\f\u0010-\u001a\b\u0012\u0004\u0012\u0002H\u00020\u00032\b\b\u0002\u0010.\u001a\u00020\u000f2\b\b\u0002\u0010/\u001a\u00020\u000f2\b\b\u0002\u00100\u001a\u00020\u000fH\u0007¢\u0006\u0002\u00101\u001a2\u0010,\u001a\u00020\u0006*\u00020\u00062\u0006\u0010-\u001a\u00020\u00062\b\b\u0002\u0010.\u001a\u00020\u000f2\b\b\u0002\u0010/\u001a\u00020\u000f2\b\b\u0002\u00100\u001a\u00020\u000fH\u0007\u001a2\u0010,\u001a\u00020\b*\u00020\b2\u0006\u0010-\u001a\u00020\b2\b\b\u0002\u0010.\u001a\u00020\u000f2\b\b\u0002\u0010/\u001a\u00020\u000f2\b\b\u0002\u00100\u001a\u00020\u000fH\u0007\u001a2\u0010,\u001a\u00020\n*\u00020\n2\u0006\u0010-\u001a\u00020\n2\b\b\u0002\u0010.\u001a\u00020\u000f2\b\b\u0002\u0010/\u001a\u00020\u000f2\b\b\u0002\u00100\u001a\u00020\u000fH\u0007\u001a2\u0010,\u001a\u00020\f*\u00020\f2\u0006\u0010-\u001a\u00020\f2\b\b\u0002\u0010.\u001a\u00020\u000f2\b\b\u0002\u0010/\u001a\u00020\u000f2\b\b\u0002\u00100\u001a\u00020\u000fH\u0007\u001a2\u0010,\u001a\u00020\u000e*\u00020\u000e2\u0006\u0010-\u001a\u00020\u000e2\b\b\u0002\u0010.\u001a\u00020\u000f2\b\b\u0002\u0010/\u001a\u00020\u000f2\b\b\u0002\u00100\u001a\u00020\u000fH\u0007\u001a2\u0010,\u001a\u00020\u0010*\u00020\u00102\u0006\u0010-\u001a\u00020\u00102\b\b\u0002\u0010.\u001a\u00020\u000f2\b\b\u0002\u0010/\u001a\u00020\u000f2\b\b\u0002\u00100\u001a\u00020\u000fH\u0007\u001a2\u0010,\u001a\u00020\u0012*\u00020\u00122\u0006\u0010-\u001a\u00020\u00122\b\b\u0002\u0010.\u001a\u00020\u000f2\b\b\u0002\u0010/\u001a\u00020\u000f2\b\b\u0002\u00100\u001a\u00020\u000fH\u0007\u001a2\u0010,\u001a\u00020\u0014*\u00020\u00142\u0006\u0010-\u001a\u00020\u00142\b\b\u0002\u0010.\u001a\u00020\u000f2\b\b\u0002\u0010/\u001a\u00020\u000f2\b\b\u0002\u00100\u001a\u00020\u000fH\u0007\u001a$\u00102\u001a\b\u0012\u0004\u0012\u0002H\u00020\u0003\"\u0004\b\u0000\u0010\u0002*\b\u0012\u0004\u0012\u0002H\u00020\u0003H\u0087\b¢\u0006\u0002\u00103\u001a.\u00102\u001a\n\u0012\u0006\u0012\u0004\u0018\u0001H\u00020\u0003\"\u0004\b\u0000\u0010\u0002*\b\u0012\u0004\u0012\u0002H\u00020\u00032\u0006\u00104\u001a\u00020\u000fH\u0087\b¢\u0006\u0002\u00105\u001a\r\u00102\u001a\u00020\u0006*\u00020\u0006H\u0087\b\u001a\u0015\u00102\u001a\u00020\u0006*\u00020\u00062\u0006\u00104\u001a\u00020\u000fH\u0087\b\u001a\r\u00102\u001a\u00020\b*\u00020\bH\u0087\b\u001a\u0015\u00102\u001a\u00020\b*\u00020\b2\u0006\u00104\u001a\u00020\u000fH\u0087\b\u001a\r\u00102\u001a\u00020\n*\u00020\nH\u0087\b\u001a\u0015\u00102\u001a\u00020\n*\u00020\n2\u0006\u00104\u001a\u00020\u000fH\u0087\b\u001a\r\u00102\u001a\u00020\f*\u00020\fH\u0087\b\u001a\u0015\u00102\u001a\u00020\f*\u00020\f2\u0006\u00104\u001a\u00020\u000fH\u0087\b\u001a\r\u00102\u001a\u00020\u000e*\u00020\u000eH\u0087\b\u001a\u0015\u00102\u001a\u00020\u000e*\u00020\u000e2\u0006\u00104\u001a\u00020\u000fH\u0087\b\u001a\r\u00102\u001a\u00020\u0010*\u00020\u0010H\u0087\b\u001a\u0015\u00102\u001a\u00020\u0010*\u00020\u00102\u0006\u00104\u001a\u00020\u000fH\u0087\b\u001a\r\u00102\u001a\u00020\u0012*\u00020\u0012H\u0087\b\u001a\u0015\u00102\u001a\u00020\u0012*\u00020\u00122\u0006\u00104\u001a\u00020\u000fH\u0087\b\u001a\r\u00102\u001a\u00020\u0014*\u00020\u0014H\u0087\b\u001a\u0015\u00102\u001a\u00020\u0014*\u00020\u00142\u0006\u00104\u001a\u00020\u000fH\u0087\b\u001a6\u00106\u001a\b\u0012\u0004\u0012\u0002H\u00020\u0003\"\u0004\b\u0000\u0010\u0002*\b\u0012\u0004\u0012\u0002H\u00020\u00032\u0006\u0010\u001a\u001a\u00020\u000f2\u0006\u0010\u001b\u001a\u00020\u000fH\u0087\b¢\u0006\u0004\b7\u00108\u001a\"\u00106\u001a\u00020\u0006*\u00020\u00062\u0006\u0010\u001a\u001a\u00020\u000f2\u0006\u0010\u001b\u001a\u00020\u000fH\u0087\b¢\u0006\u0002\b7\u001a\"\u00106\u001a\u00020\b*\u00020\b2\u0006\u0010\u001a\u001a\u00020\u000f2\u0006\u0010\u001b\u001a\u00020\u000fH\u0087\b¢\u0006\u0002\b7\u001a\"\u00106\u001a\u00020\n*\u00020\n2\u0006\u0010\u001a\u001a\u00020\u000f2\u0006\u0010\u001b\u001a\u00020\u000fH\u0087\b¢\u0006\u0002\b7\u001a\"\u00106\u001a\u00020\f*\u00020\f2\u0006\u0010\u001a\u001a\u00020\u000f2\u0006\u0010\u001b\u001a\u00020\u000fH\u0087\b¢\u0006\u0002\b7\u001a\"\u00106\u001a\u00020\u000e*\u00020\u000e2\u0006\u0010\u001a\u001a\u00020\u000f2\u0006\u0010\u001b\u001a\u00020\u000fH\u0087\b¢\u0006\u0002\b7\u001a\"\u00106\u001a\u00020\u0010*\u00020\u00102\u0006\u0010\u001a\u001a\u00020\u000f2\u0006\u0010\u001b\u001a\u00020\u000fH\u0087\b¢\u0006\u0002\b7\u001a\"\u00106\u001a\u00020\u0012*\u00020\u00122\u0006\u0010\u001a\u001a\u00020\u000f2\u0006\u0010\u001b\u001a\u00020\u000fH\u0087\b¢\u0006\u0002\b7\u001a\"\u00106\u001a\u00020\u0014*\u00020\u00142\u0006\u0010\u001a\u001a\u00020\u000f2\u0006\u0010\u001b\u001a\u00020\u000fH\u0087\b¢\u0006\u0002\b7\u001a5\u00109\u001a\b\u0012\u0004\u0012\u0002H\u00020\u0003\"\u0004\b\u0000\u0010\u0002*\b\u0012\u0004\u0012\u0002H\u00020\u00032\u0006\u0010\u001a\u001a\u00020\u000f2\u0006\u0010\u001b\u001a\u00020\u000fH\u0001¢\u0006\u0004\b6\u00108\u001a!\u00109\u001a\u00020\u0006*\u00020\u00062\u0006\u0010\u001a\u001a\u00020\u000f2\u0006\u0010\u001b\u001a\u00020\u000fH\u0001¢\u0006\u0002\b6\u001a!\u00109\u001a\u00020\b*\u00020\b2\u0006\u0010\u001a\u001a\u00020\u000f2\u0006\u0010\u001b\u001a\u00020\u000fH\u0001¢\u0006\u0002\b6\u001a!\u00109\u001a\u00020\n*\u00020\n2\u0006\u0010\u001a\u001a\u00020\u000f2\u0006\u0010\u001b\u001a\u00020\u000fH\u0001¢\u0006\u0002\b6\u001a!\u00109\u001a\u00020\f*\u00020\f2\u0006\u0010\u001a\u001a\u00020\u000f2\u0006\u0010\u001b\u001a\u00020\u000fH\u0001¢\u0006\u0002\b6\u001a!\u00109\u001a\u00020\u000e*\u00020\u000e2\u0006\u0010\u001a\u001a\u00020\u000f2\u0006\u0010\u001b\u001a\u00020\u000fH\u0001¢\u0006\u0002\b6\u001a!\u00109\u001a\u00020\u0010*\u00020\u00102\u0006\u0010\u001a\u001a\u00020\u000f2\u0006\u0010\u001b\u001a\u00020\u000fH\u0001¢\u0006\u0002\b6\u001a!\u00109\u001a\u00020\u0012*\u00020\u00122\u0006\u0010\u001a\u001a\u00020\u000f2\u0006\u0010\u001b\u001a\u00020\u000fH\u0001¢\u0006\u0002\b6\u001a!\u00109\u001a\u00020\u0014*\u00020\u00142\u0006\u0010\u001a\u001a\u00020\u000f2\u0006\u0010\u001b\u001a\u00020\u000fH\u0001¢\u0006\u0002\b6\u001a(\u0010:\u001a\u0002H\u0002\"\u0004\b\u0000\u0010\u0002*\n\u0012\u0006\b\u0001\u0012\u0002H\u00020\u00032\u0006\u0010;\u001a\u00020\u000fH\u0087\b¢\u0006\u0002\u0010<\u001a\u0015\u0010:\u001a\u00020\u0005*\u00020\u00062\u0006\u0010;\u001a\u00020\u000fH\u0087\b\u001a\u0015\u0010:\u001a\u00020\u0007*\u00020\b2\u0006\u0010;\u001a\u00020\u000fH\u0087\b\u001a\u0015\u0010:\u001a\u00020\t*\u00020\n2\u0006\u0010;\u001a\u00020\u000fH\u0087\b\u001a\u0015\u0010:\u001a\u00020\u000b*\u00020\f2\u0006\u0010;\u001a\u00020\u000fH\u0087\b\u001a\u0015\u0010:\u001a\u00020\r*\u00020\u000e2\u0006\u0010;\u001a\u00020\u000fH\u0087\b\u001a\u0015\u0010:\u001a\u00020\u000f*\u00020\u00102\u0006\u0010;\u001a\u00020\u000fH\u0087\b\u001a\u0015\u0010:\u001a\u00020\u0011*\u00020\u00122\u0006\u0010;\u001a\u00020\u000fH\u0087\b\u001a\u0015\u0010:\u001a\u00020\u0013*\u00020\u00142\u0006\u0010;\u001a\u00020\u000fH\u0087\b\u001a7\u0010=\u001a\u00020>\"\u0004\b\u0000\u0010\u0002*\b\u0012\u0004\u0012\u0002H\u00020\u00032\u0006\u0010\u0016\u001a\u0002H\u00022\b\b\u0002\u0010\u001a\u001a\u00020\u000f2\b\b\u0002\u0010\u001b\u001a\u00020\u000f¢\u0006\u0002\u0010?\u001a&\u0010=\u001a\u00020>*\u00020\u00062\u0006\u0010\u0016\u001a\u00020\u00052\b\b\u0002\u0010\u001a\u001a\u00020\u000f2\b\b\u0002\u0010\u001b\u001a\u00020\u000f\u001a&\u0010=\u001a\u00020>*\u00020\b2\u0006\u0010\u0016\u001a\u00020\u00072\b\b\u0002\u0010\u001a\u001a\u00020\u000f2\b\b\u0002\u0010\u001b\u001a\u00020\u000f\u001a&\u0010=\u001a\u00020>*\u00020\n2\u0006\u0010\u0016\u001a\u00020\t2\b\b\u0002\u0010\u001a\u001a\u00020\u000f2\b\b\u0002\u0010\u001b\u001a\u00020\u000f\u001a&\u0010=\u001a\u00020>*\u00020\f2\u0006\u0010\u0016\u001a\u00020\u000b2\b\b\u0002\u0010\u001a\u001a\u00020\u000f2\b\b\u0002\u0010\u001b\u001a\u00020\u000f\u001a&\u0010=\u001a\u00020>*\u00020\u000e2\u0006\u0010\u0016\u001a\u00020\r2\b\b\u0002\u0010\u001a\u001a\u00020\u000f2\b\b\u0002\u0010\u001b\u001a\u00020\u000f\u001a&\u0010=\u001a\u00020>*\u00020\u00102\u0006\u0010\u0016\u001a\u00020\u000f2\b\b\u0002\u0010\u001a\u001a\u00020\u000f2\b\b\u0002\u0010\u001b\u001a\u00020\u000f\u001a&\u0010=\u001a\u00020>*\u00020\u00122\u0006\u0010\u0016\u001a\u00020\u00112\b\b\u0002\u0010\u001a\u001a\u00020\u000f2\b\b\u0002\u0010\u001b\u001a\u00020\u000f\u001a&\u0010=\u001a\u00020>*\u00020\u00142\u0006\u0010\u0016\u001a\u00020\u00132\b\b\u0002\u0010\u001a\u001a\u00020\u000f2\b\b\u0002\u0010\u001b\u001a\u00020\u000f\u001a-\u0010@\u001a\b\u0012\u0004\u0012\u0002HA0\u0001\"\u0004\b\u0000\u0010A*\u0006\u0012\u0002\b\u00030\u00032\f\u0010B\u001a\b\u0012\u0004\u0012\u0002HA0C¢\u0006\u0002\u0010D\u001aA\u0010E\u001a\u0002HF\"\u0010\b\u0000\u0010F*\n\u0012\u0006\b\u0000\u0012\u0002HA0G\"\u0004\b\u0001\u0010A*\u0006\u0012\u0002\b\u00030\u00032\u0006\u0010-\u001a\u0002HF2\f\u0010B\u001a\b\u0012\u0004\u0012\u0002HA0C¢\u0006\u0002\u0010H\u001a,\u0010I\u001a\b\u0012\u0004\u0012\u0002H\u00020\u0003\"\u0004\b\u0000\u0010\u0002*\b\u0012\u0004\u0012\u0002H\u00020\u00032\u0006\u0010\u0016\u001a\u0002H\u0002H\u0086\u0002¢\u0006\u0002\u0010J\u001a4\u0010I\u001a\b\u0012\u0004\u0012\u0002H\u00020\u0003\"\u0004\b\u0000\u0010\u0002*\b\u0012\u0004\u0012\u0002H\u00020\u00032\u000e\u0010K\u001a\n\u0012\u0006\b\u0001\u0012\u0002H\u00020\u0003H\u0086\u0002¢\u0006\u0002\u0010L\u001a2\u0010I\u001a\b\u0012\u0004\u0012\u0002H\u00020\u0003\"\u0004\b\u0000\u0010\u0002*\b\u0012\u0004\u0012\u0002H\u00020\u00032\f\u0010K\u001a\b\u0012\u0004\u0012\u0002H\u00020MH\u0086\u0002¢\u0006\u0002\u0010N\u001a\u0015\u0010I\u001a\u00020\u0006*\u00020\u00062\u0006\u0010\u0016\u001a\u00020\u0005H\u0086\u0002\u001a\u0015\u0010I\u001a\u00020\u0006*\u00020\u00062\u0006\u0010K\u001a\u00020\u0006H\u0086\u0002\u001a\u001b\u0010I\u001a\u00020\u0006*\u00020\u00062\f\u0010K\u001a\b\u0012\u0004\u0012\u00020\u00050MH\u0086\u0002\u001a\u0015\u0010I\u001a\u00020\b*\u00020\b2\u0006\u0010\u0016\u001a\u00020\u0007H\u0086\u0002\u001a\u0015\u0010I\u001a\u00020\b*\u00020\b2\u0006\u0010K\u001a\u00020\bH\u0086\u0002\u001a\u001b\u0010I\u001a\u00020\b*\u00020\b2\f\u0010K\u001a\b\u0012\u0004\u0012\u00020\u00070MH\u0086\u0002\u001a\u0015\u0010I\u001a\u00020\n*\u00020\n2\u0006\u0010\u0016\u001a\u00020\tH\u0086\u0002\u001a\u0015\u0010I\u001a\u00020\n*\u00020\n2\u0006\u0010K\u001a\u00020\nH\u0086\u0002\u001a\u001b\u0010I\u001a\u00020\n*\u00020\n2\f\u0010K\u001a\b\u0012\u0004\u0012\u00020\t0MH\u0086\u0002\u001a\u0015\u0010I\u001a\u00020\f*\u00020\f2\u0006\u0010\u0016\u001a\u00020\u000bH\u0086\u0002\u001a\u0015\u0010I\u001a\u00020\f*\u00020\f2\u0006\u0010K\u001a\u00020\fH\u0086\u0002\u001a\u001b\u0010I\u001a\u00020\f*\u00020\f2\f\u0010K\u001a\b\u0012\u0004\u0012\u00020\u000b0MH\u0086\u0002\u001a\u0015\u0010I\u001a\u00020\u000e*\u00020\u000e2\u0006\u0010\u0016\u001a\u00020\rH\u0086\u0002\u001a\u0015\u0010I\u001a\u00020\u000e*\u00020\u000e2\u0006\u0010K\u001a\u00020\u000eH\u0086\u0002\u001a\u001b\u0010I\u001a\u00020\u000e*\u00020\u000e2\f\u0010K\u001a\b\u0012\u0004\u0012\u00020\r0MH\u0086\u0002\u001a\u0015\u0010I\u001a\u00020\u0010*\u00020\u00102\u0006\u0010\u0016\u001a\u00020\u000fH\u0086\u0002\u001a\u0015\u0010I\u001a\u00020\u0010*\u00020\u00102\u0006\u0010K\u001a\u00020\u0010H\u0086\u0002\u001a\u001b\u0010I\u001a\u00020\u0010*\u00020\u00102\f\u0010K\u001a\b\u0012\u0004\u0012\u00020\u000f0MH\u0086\u0002\u001a\u0015\u0010I\u001a\u00020\u0012*\u00020\u00122\u0006\u0010\u0016\u001a\u00020\u0011H\u0086\u0002\u001a\u0015\u0010I\u001a\u00020\u0012*\u00020\u00122\u0006\u0010K\u001a\u00020\u0012H\u0086\u0002\u001a\u001b\u0010I\u001a\u00020\u0012*\u00020\u00122\f\u0010K\u001a\b\u0012\u0004\u0012\u00020\u00110MH\u0086\u0002\u001a\u0015\u0010I\u001a\u00020\u0014*\u00020\u00142\u0006\u0010\u0016\u001a\u00020\u0013H\u0086\u0002\u001a\u0015\u0010I\u001a\u00020\u0014*\u00020\u00142\u0006\u0010K\u001a\u00020\u0014H\u0086\u0002\u001a\u001b\u0010I\u001a\u00020\u0014*\u00020\u00142\f\u0010K\u001a\b\u0012\u0004\u0012\u00020\u00130MH\u0086\u0002\u001a,\u0010O\u001a\b\u0012\u0004\u0012\u0002H\u00020\u0003\"\u0004\b\u0000\u0010\u0002*\b\u0012\u0004\u0012\u0002H\u00020\u00032\u0006\u0010\u0016\u001a\u0002H\u0002H\u0087\b¢\u0006\u0002\u0010J\u001a\u001d\u0010P\u001a\u00020>\"\u0004\b\u0000\u0010\u0002*\n\u0012\u0006\b\u0001\u0012\u0002H\u00020\u0003¢\u0006\u0002\u0010Q\u001a*\u0010P\u001a\u00020>\"\u000e\b\u0000\u0010\u0002*\b\u0012\u0004\u0012\u0002H\u00020R*\n\u0012\u0006\b\u0001\u0012\u0002H\u00020\u0003H\u0087\b¢\u0006\u0002\u0010S\u001a1\u0010P\u001a\u00020>\"\u0004\b\u0000\u0010\u0002*\n\u0012\u0006\b\u0001\u0012\u0002H\u00020\u00032\b\b\u0002\u0010\u001a\u001a\u00020\u000f2\b\b\u0002\u0010\u001b\u001a\u00020\u000f¢\u0006\u0002\u0010T\u001a\n\u0010P\u001a\u00020>*\u00020\b\u001a\u001e\u0010P\u001a\u00020>*\u00020\b2\b\b\u0002\u0010\u001a\u001a\u00020\u000f2\b\b\u0002\u0010\u001b\u001a\u00020\u000f\u001a\n\u0010P\u001a\u00020>*\u00020\n\u001a\u001e\u0010P\u001a\u00020>*\u00020\n2\b\b\u0002\u0010\u001a\u001a\u00020\u000f2\b\b\u0002\u0010\u001b\u001a\u00020\u000f\u001a\n\u0010P\u001a\u00020>*\u00020\f\u001a\u001e\u0010P\u001a\u00020>*\u00020\f2\b\b\u0002\u0010\u001a\u001a\u00020\u000f2\b\b\u0002\u0010\u001b\u001a\u00020\u000f\u001a\n\u0010P\u001a\u00020>*\u00020\u000e\u001a\u001e\u0010P\u001a\u00020>*\u00020\u000e2\b\b\u0002\u0010\u001a\u001a\u00020\u000f2\b\b\u0002\u0010\u001b\u001a\u00020\u000f\u001a\n\u0010P\u001a\u00020>*\u00020\u0010\u001a\u001e\u0010P\u001a\u00020>*\u00020\u00102\b\b\u0002\u0010\u001a\u001a\u00020\u000f2\b\b\u0002\u0010\u001b\u001a\u00020\u000f\u001a\n\u0010P\u001a\u00020>*\u00020\u0012\u001a\u001e\u0010P\u001a\u00020>*\u00020\u00122\b\b\u0002\u0010\u001a\u001a\u00020\u000f2\b\b\u0002\u0010\u001b\u001a\u00020\u000f\u001a\n\u0010P\u001a\u00020>*\u00020\u0014\u001a\u001e\u0010P\u001a\u00020>*\u00020\u00142\b\b\u0002\u0010\u001a\u001a\u00020\u000f2\b\b\u0002\u0010\u001b\u001a\u00020\u000f\u001a9\u0010U\u001a\u00020>\"\u0004\b\u0000\u0010\u0002*\n\u0012\u0006\b\u0001\u0012\u0002H\u00020\u00032\u001a\u0010\u0017\u001a\u0016\u0012\u0006\b\u0000\u0012\u0002H\u00020\u0018j\n\u0012\u0006\b\u0000\u0012\u0002H\u0002`\u0019¢\u0006\u0002\u0010V\u001aM\u0010U\u001a\u00020>\"\u0004\b\u0000\u0010\u0002*\n\u0012\u0006\b\u0001\u0012\u0002H\u00020\u00032\u001a\u0010\u0017\u001a\u0016\u0012\u0006\b\u0000\u0012\u0002H\u00020\u0018j\n\u0012\u0006\b\u0000\u0012\u0002H\u0002`\u00192\b\b\u0002\u0010\u001a\u001a\u00020\u000f2\b\b\u0002\u0010\u001b\u001a\u00020\u000f¢\u0006\u0002\u0010W\u001a-\u0010X\u001a\b\u0012\u0004\u0012\u0002H\u00020Y\"\u000e\b\u0000\u0010\u0002*\b\u0012\u0004\u0012\u0002H\u00020R*\n\u0012\u0006\b\u0001\u0012\u0002H\u00020\u0003¢\u0006\u0002\u0010Z\u001a?\u0010X\u001a\b\u0012\u0004\u0012\u0002H\u00020Y\"\u0004\b\u0000\u0010\u0002*\n\u0012\u0006\b\u0001\u0012\u0002H\u00020\u00032\u001a\u0010\u0017\u001a\u0016\u0012\u0006\b\u0000\u0012\u0002H\u00020\u0018j\n\u0012\u0006\b\u0000\u0012\u0002H\u0002`\u0019¢\u0006\u0002\u0010[\u001a\u0010\u0010X\u001a\b\u0012\u0004\u0012\u00020\u00050Y*\u00020\u0006\u001a\u0010\u0010X\u001a\b\u0012\u0004\u0012\u00020\u00070Y*\u00020\b\u001a\u0010\u0010X\u001a\b\u0012\u0004\u0012\u00020\t0Y*\u00020\n\u001a\u0010\u0010X\u001a\b\u0012\u0004\u0012\u00020\u000b0Y*\u00020\f\u001a\u0010\u0010X\u001a\b\u0012\u0004\u0012\u00020\r0Y*\u00020\u000e\u001a\u0010\u0010X\u001a\b\u0012\u0004\u0012\u00020\u000f0Y*\u00020\u0010\u001a\u0010\u0010X\u001a\b\u0012\u0004\u0012\u00020\u00110Y*\u00020\u0012\u001a\u0010\u0010X\u001a\b\u0012\u0004\u0012\u00020\u00130Y*\u00020\u0014\u001a\u0015\u0010\\\u001a\b\u0012\u0004\u0012\u00020\u00050\u0003*\u00020\u0006¢\u0006\u0002\u0010]\u001a\u0015\u0010\\\u001a\b\u0012\u0004\u0012\u00020\u00070\u0003*\u00020\b¢\u0006\u0002\u0010^\u001a\u0015\u0010\\\u001a\b\u0012\u0004\u0012\u00020\t0\u0003*\u00020\n¢\u0006\u0002\u0010_\u001a\u0015\u0010\\\u001a\b\u0012\u0004\u0012\u00020\u000b0\u0003*\u00020\f¢\u0006\u0002\u0010`\u001a\u0015\u0010\\\u001a\b\u0012\u0004\u0012\u00020\r0\u0003*\u00020\u000e¢\u0006\u0002\u0010a\u001a\u0015\u0010\\\u001a\b\u0012\u0004\u0012\u00020\u000f0\u0003*\u00020\u0010¢\u0006\u0002\u0010b\u001a\u0015\u0010\\\u001a\b\u0012\u0004\u0012\u00020\u00110\u0003*\u00020\u0012¢\u0006\u0002\u0010c\u001a\u0015\u0010\\\u001a\b\u0012\u0004\u0012\u00020\u00130\u0003*\u00020\u0014¢\u0006\u0002\u0010d¨\u0006e" }, d2 = { "asList", "", "T", "", "([Ljava/lang/Object;)Ljava/util/List;", "", "", "", "", "", "", "", "", "", "", "", "", "", "", "", "", "binarySearch", "element", "comparator", "Ljava/util/Comparator;", "Lkotlin/Comparator;", "fromIndex", "toIndex", "([Ljava/lang/Object;Ljava/lang/Object;Ljava/util/Comparator;II)I", "([Ljava/lang/Object;Ljava/lang/Object;II)I", "contentDeepEquals", "other", "contentDeepEqualsInline", "([Ljava/lang/Object;[Ljava/lang/Object;)Z", "contentDeepHashCode", "contentDeepHashCodeInline", "([Ljava/lang/Object;)I", "contentDeepToString", "", "contentDeepToStringInline", "([Ljava/lang/Object;)Ljava/lang/String;", "contentEquals", "contentHashCode", "contentToString", "copyInto", "destination", "destinationOffset", "startIndex", "endIndex", "([Ljava/lang/Object;[Ljava/lang/Object;III)[Ljava/lang/Object;", "copyOf", "([Ljava/lang/Object;)[Ljava/lang/Object;", "newSize", "([Ljava/lang/Object;I)[Ljava/lang/Object;", "copyOfRange", "copyOfRangeInline", "([Ljava/lang/Object;II)[Ljava/lang/Object;", "copyOfRangeImpl", "elementAt", "index", "([Ljava/lang/Object;I)Ljava/lang/Object;", "fill", "", "([Ljava/lang/Object;Ljava/lang/Object;II)V", "filterIsInstance", "R", "klass", "Ljava/lang/Class;", "([Ljava/lang/Object;Ljava/lang/Class;)Ljava/util/List;", "filterIsInstanceTo", "C", "", "([Ljava/lang/Object;Ljava/util/Collection;Ljava/lang/Class;)Ljava/util/Collection;", "plus", "([Ljava/lang/Object;Ljava/lang/Object;)[Ljava/lang/Object;", "elements", "([Ljava/lang/Object;[Ljava/lang/Object;)[Ljava/lang/Object;", "", "([Ljava/lang/Object;Ljava/util/Collection;)[Ljava/lang/Object;", "plusElement", "sort", "([Ljava/lang/Object;)V", "", "([Ljava/lang/Comparable;)V", "([Ljava/lang/Object;II)V", "sortWith", "([Ljava/lang/Object;Ljava/util/Comparator;)V", "([Ljava/lang/Object;Ljava/util/Comparator;II)V", "toSortedSet", "Ljava/util/SortedSet;", "([Ljava/lang/Comparable;)Ljava/util/SortedSet;", "([Ljava/lang/Object;Ljava/util/Comparator;)Ljava/util/SortedSet;", "toTypedArray", "([Z)[Ljava/lang/Boolean;", "([B)[Ljava/lang/Byte;", "([C)[Ljava/lang/Character;", "([D)[Ljava/lang/Double;", "([F)[Ljava/lang/Float;", "([I)[Ljava/lang/Integer;", "([J)[Ljava/lang/Long;", "([S)[Ljava/lang/Short;", "kotlin-stdlib" }, xs = "kotlin/collections/ArraysKt")
class ArraysKt___ArraysJvmKt extends ArraysKt__ArraysKt
{
    @InlineOnly
    private static final <T> T elementAt(@NotNull final T[] $this$elementAt, final int index) {
        final int $i$f$elementAt = 0;
        return $this$elementAt[index];
    }
    
    @InlineOnly
    private static final byte elementAt(@NotNull final byte[] $this$elementAt, final int index) {
        final int $i$f$elementAt = 0;
        return $this$elementAt[index];
    }
    
    @InlineOnly
    private static final short elementAt(@NotNull final short[] $this$elementAt, final int index) {
        final int $i$f$elementAt = 0;
        return $this$elementAt[index];
    }
    
    @InlineOnly
    private static final int elementAt(@NotNull final int[] $this$elementAt, final int index) {
        final int $i$f$elementAt = 0;
        return $this$elementAt[index];
    }
    
    @InlineOnly
    private static final long elementAt(@NotNull final long[] $this$elementAt, final int index) {
        final int $i$f$elementAt = 0;
        return $this$elementAt[index];
    }
    
    @InlineOnly
    private static final float elementAt(@NotNull final float[] $this$elementAt, final int index) {
        final int $i$f$elementAt = 0;
        return $this$elementAt[index];
    }
    
    @InlineOnly
    private static final double elementAt(@NotNull final double[] $this$elementAt, final int index) {
        final int $i$f$elementAt = 0;
        return $this$elementAt[index];
    }
    
    @InlineOnly
    private static final boolean elementAt(@NotNull final boolean[] $this$elementAt, final int index) {
        final int $i$f$elementAt = 0;
        return $this$elementAt[index];
    }
    
    @InlineOnly
    private static final char elementAt(@NotNull final char[] $this$elementAt, final int index) {
        final int $i$f$elementAt = 0;
        return $this$elementAt[index];
    }
    
    @NotNull
    public static final <R> List<R> filterIsInstance(@NotNull final Object[] $this$filterIsInstance, @NotNull final Class<R> klass) {
        Intrinsics.checkParameterIsNotNull($this$filterIsInstance, "$this$filterIsInstance");
        Intrinsics.checkParameterIsNotNull(klass, "klass");
        return filterIsInstanceTo($this$filterIsInstance, new ArrayList<R>(), klass);
    }
    
    @NotNull
    public static final <C extends Collection<? super R>, R> C filterIsInstanceTo(@NotNull final Object[] $this$filterIsInstanceTo, @NotNull final C destination, @NotNull final Class<R> klass) {
        Intrinsics.checkParameterIsNotNull($this$filterIsInstanceTo, "$this$filterIsInstanceTo");
        Intrinsics.checkParameterIsNotNull(destination, "destination");
        Intrinsics.checkParameterIsNotNull(klass, "klass");
        for (final Object element : $this$filterIsInstanceTo) {
            if (klass.isInstance(element)) {
                destination.add((Object)element);
            }
        }
        return destination;
    }
    
    @NotNull
    public static final <T> List<T> asList(@NotNull final T[] $this$asList) {
        Intrinsics.checkParameterIsNotNull($this$asList, "$this$asList");
        final List<T> list = ArraysUtilJVM.asList($this$asList);
        Intrinsics.checkExpressionValueIsNotNull(list, "ArraysUtilJVM.asList(this)");
        return list;
    }
    
    @NotNull
    public static final List<Byte> asList(@NotNull final byte[] $this$asList) {
        Intrinsics.checkParameterIsNotNull($this$asList, "$this$asList");
        return (List<Byte>)new ArraysKt___ArraysJvmKt$asList.ArraysKt___ArraysJvmKt$asList$1($this$asList);
    }
    
    @NotNull
    public static final List<Short> asList(@NotNull final short[] $this$asList) {
        Intrinsics.checkParameterIsNotNull($this$asList, "$this$asList");
        return (List<Short>)new ArraysKt___ArraysJvmKt$asList.ArraysKt___ArraysJvmKt$asList$2($this$asList);
    }
    
    @NotNull
    public static final List<Integer> asList(@NotNull final int[] $this$asList) {
        Intrinsics.checkParameterIsNotNull($this$asList, "$this$asList");
        return (List<Integer>)new ArraysKt___ArraysJvmKt$asList.ArraysKt___ArraysJvmKt$asList$3($this$asList);
    }
    
    @NotNull
    public static final List<Long> asList(@NotNull final long[] $this$asList) {
        Intrinsics.checkParameterIsNotNull($this$asList, "$this$asList");
        return (List<Long>)new ArraysKt___ArraysJvmKt$asList.ArraysKt___ArraysJvmKt$asList$4($this$asList);
    }
    
    @NotNull
    public static final List<Float> asList(@NotNull final float[] $this$asList) {
        Intrinsics.checkParameterIsNotNull($this$asList, "$this$asList");
        return (List<Float>)new ArraysKt___ArraysJvmKt$asList.ArraysKt___ArraysJvmKt$asList$5($this$asList);
    }
    
    @NotNull
    public static final List<Double> asList(@NotNull final double[] $this$asList) {
        Intrinsics.checkParameterIsNotNull($this$asList, "$this$asList");
        return (List<Double>)new ArraysKt___ArraysJvmKt$asList.ArraysKt___ArraysJvmKt$asList$6($this$asList);
    }
    
    @NotNull
    public static final List<Boolean> asList(@NotNull final boolean[] $this$asList) {
        Intrinsics.checkParameterIsNotNull($this$asList, "$this$asList");
        return (List<Boolean>)new ArraysKt___ArraysJvmKt$asList.ArraysKt___ArraysJvmKt$asList$7($this$asList);
    }
    
    @NotNull
    public static final List<Character> asList(@NotNull final char[] $this$asList) {
        Intrinsics.checkParameterIsNotNull($this$asList, "$this$asList");
        return (List<Character>)new ArraysKt___ArraysJvmKt$asList.ArraysKt___ArraysJvmKt$asList$8($this$asList);
    }
    
    public static final <T> int binarySearch(@NotNull final T[] $this$binarySearch, final T element, @NotNull final Comparator<? super T> comparator, final int fromIndex, final int toIndex) {
        Intrinsics.checkParameterIsNotNull($this$binarySearch, "$this$binarySearch");
        Intrinsics.checkParameterIsNotNull(comparator, "comparator");
        return Arrays.binarySearch($this$binarySearch, fromIndex, toIndex, element, comparator);
    }
    
    public static final <T> int binarySearch(@NotNull final T[] $this$binarySearch, final T element, final int fromIndex, final int toIndex) {
        Intrinsics.checkParameterIsNotNull($this$binarySearch, "$this$binarySearch");
        return Arrays.binarySearch($this$binarySearch, fromIndex, toIndex, element);
    }
    
    public static final int binarySearch(@NotNull final byte[] $this$binarySearch, final byte element, final int fromIndex, final int toIndex) {
        Intrinsics.checkParameterIsNotNull($this$binarySearch, "$this$binarySearch");
        return Arrays.binarySearch($this$binarySearch, fromIndex, toIndex, element);
    }
    
    public static final int binarySearch(@NotNull final short[] $this$binarySearch, final short element, final int fromIndex, final int toIndex) {
        Intrinsics.checkParameterIsNotNull($this$binarySearch, "$this$binarySearch");
        return Arrays.binarySearch($this$binarySearch, fromIndex, toIndex, element);
    }
    
    public static final int binarySearch(@NotNull final int[] $this$binarySearch, final int element, final int fromIndex, final int toIndex) {
        Intrinsics.checkParameterIsNotNull($this$binarySearch, "$this$binarySearch");
        return Arrays.binarySearch($this$binarySearch, fromIndex, toIndex, element);
    }
    
    public static final int binarySearch(@NotNull final long[] $this$binarySearch, final long element, final int fromIndex, final int toIndex) {
        Intrinsics.checkParameterIsNotNull($this$binarySearch, "$this$binarySearch");
        return Arrays.binarySearch($this$binarySearch, fromIndex, toIndex, element);
    }
    
    public static final int binarySearch(@NotNull final float[] $this$binarySearch, final float element, final int fromIndex, final int toIndex) {
        Intrinsics.checkParameterIsNotNull($this$binarySearch, "$this$binarySearch");
        return Arrays.binarySearch($this$binarySearch, fromIndex, toIndex, element);
    }
    
    public static final int binarySearch(@NotNull final double[] $this$binarySearch, final double element, final int fromIndex, final int toIndex) {
        Intrinsics.checkParameterIsNotNull($this$binarySearch, "$this$binarySearch");
        return Arrays.binarySearch($this$binarySearch, fromIndex, toIndex, element);
    }
    
    public static final int binarySearch(@NotNull final char[] $this$binarySearch, final char element, final int fromIndex, final int toIndex) {
        Intrinsics.checkParameterIsNotNull($this$binarySearch, "$this$binarySearch");
        return Arrays.binarySearch($this$binarySearch, fromIndex, toIndex, element);
    }
    
    @SinceKotlin(version = "1.1")
    @JvmName(name = "contentDeepEqualsInline")
    @InlineOnly
    private static final <T> boolean contentDeepEqualsInline(@NotNull final T[] $this$contentDeepEquals, final T[] other) {
        final int $i$f$contentDeepEqualsInline = 0;
        if (PlatformImplementationsKt.apiVersionIsAtLeast(1, 3, 0)) {
            return ArraysKt__ArraysKt.contentDeepEquals($this$contentDeepEquals, other);
        }
        return Arrays.deepEquals($this$contentDeepEquals, other);
    }
    
    @SinceKotlin(version = "1.1")
    @JvmName(name = "contentDeepHashCodeInline")
    @InlineOnly
    private static final <T> int contentDeepHashCodeInline(@NotNull final T[] $this$contentDeepHashCode) {
        final int $i$f$contentDeepHashCodeInline = 0;
        if (PlatformImplementationsKt.apiVersionIsAtLeast(1, 3, 0)) {
            return ArraysKt__ArraysJVMKt.contentDeepHashCode($this$contentDeepHashCode);
        }
        return Arrays.deepHashCode($this$contentDeepHashCode);
    }
    
    @SinceKotlin(version = "1.1")
    @JvmName(name = "contentDeepToStringInline")
    @InlineOnly
    private static final <T> String contentDeepToStringInline(@NotNull final T[] $this$contentDeepToString) {
        final int $i$f$contentDeepToStringInline = 0;
        if (PlatformImplementationsKt.apiVersionIsAtLeast(1, 3, 0)) {
            return ArraysKt__ArraysKt.contentDeepToString($this$contentDeepToString);
        }
        final String deepToString = Arrays.deepToString($this$contentDeepToString);
        Intrinsics.checkExpressionValueIsNotNull(deepToString, "java.util.Arrays.deepToString(this)");
        return deepToString;
    }
    
    @SinceKotlin(version = "1.1")
    @InlineOnly
    private static final <T> boolean contentEquals(@NotNull final T[] $this$contentEquals, final T[] other) {
        final int $i$f$contentEquals = 0;
        return Arrays.equals($this$contentEquals, other);
    }
    
    @SinceKotlin(version = "1.1")
    @InlineOnly
    private static final boolean contentEquals(@NotNull final byte[] $this$contentEquals, final byte[] other) {
        final int $i$f$contentEquals = 0;
        return Arrays.equals($this$contentEquals, other);
    }
    
    @SinceKotlin(version = "1.1")
    @InlineOnly
    private static final boolean contentEquals(@NotNull final short[] $this$contentEquals, final short[] other) {
        final int $i$f$contentEquals = 0;
        return Arrays.equals($this$contentEquals, other);
    }
    
    @SinceKotlin(version = "1.1")
    @InlineOnly
    private static final boolean contentEquals(@NotNull final int[] $this$contentEquals, final int[] other) {
        final int $i$f$contentEquals = 0;
        return Arrays.equals($this$contentEquals, other);
    }
    
    @SinceKotlin(version = "1.1")
    @InlineOnly
    private static final boolean contentEquals(@NotNull final long[] $this$contentEquals, final long[] other) {
        final int $i$f$contentEquals = 0;
        return Arrays.equals($this$contentEquals, other);
    }
    
    @SinceKotlin(version = "1.1")
    @InlineOnly
    private static final boolean contentEquals(@NotNull final float[] $this$contentEquals, final float[] other) {
        final int $i$f$contentEquals = 0;
        return Arrays.equals($this$contentEquals, other);
    }
    
    @SinceKotlin(version = "1.1")
    @InlineOnly
    private static final boolean contentEquals(@NotNull final double[] $this$contentEquals, final double[] other) {
        final int $i$f$contentEquals = 0;
        return Arrays.equals($this$contentEquals, other);
    }
    
    @SinceKotlin(version = "1.1")
    @InlineOnly
    private static final boolean contentEquals(@NotNull final boolean[] $this$contentEquals, final boolean[] other) {
        final int $i$f$contentEquals = 0;
        return Arrays.equals($this$contentEquals, other);
    }
    
    @SinceKotlin(version = "1.1")
    @InlineOnly
    private static final boolean contentEquals(@NotNull final char[] $this$contentEquals, final char[] other) {
        final int $i$f$contentEquals = 0;
        return Arrays.equals($this$contentEquals, other);
    }
    
    @SinceKotlin(version = "1.1")
    @InlineOnly
    private static final <T> int contentHashCode(@NotNull final T[] $this$contentHashCode) {
        final int $i$f$contentHashCode = 0;
        return Arrays.hashCode($this$contentHashCode);
    }
    
    @SinceKotlin(version = "1.1")
    @InlineOnly
    private static final int contentHashCode(@NotNull final byte[] $this$contentHashCode) {
        final int $i$f$contentHashCode = 0;
        return Arrays.hashCode($this$contentHashCode);
    }
    
    @SinceKotlin(version = "1.1")
    @InlineOnly
    private static final int contentHashCode(@NotNull final short[] $this$contentHashCode) {
        final int $i$f$contentHashCode = 0;
        return Arrays.hashCode($this$contentHashCode);
    }
    
    @SinceKotlin(version = "1.1")
    @InlineOnly
    private static final int contentHashCode(@NotNull final int[] $this$contentHashCode) {
        final int $i$f$contentHashCode = 0;
        return Arrays.hashCode($this$contentHashCode);
    }
    
    @SinceKotlin(version = "1.1")
    @InlineOnly
    private static final int contentHashCode(@NotNull final long[] $this$contentHashCode) {
        final int $i$f$contentHashCode = 0;
        return Arrays.hashCode($this$contentHashCode);
    }
    
    @SinceKotlin(version = "1.1")
    @InlineOnly
    private static final int contentHashCode(@NotNull final float[] $this$contentHashCode) {
        final int $i$f$contentHashCode = 0;
        return Arrays.hashCode($this$contentHashCode);
    }
    
    @SinceKotlin(version = "1.1")
    @InlineOnly
    private static final int contentHashCode(@NotNull final double[] $this$contentHashCode) {
        final int $i$f$contentHashCode = 0;
        return Arrays.hashCode($this$contentHashCode);
    }
    
    @SinceKotlin(version = "1.1")
    @InlineOnly
    private static final int contentHashCode(@NotNull final boolean[] $this$contentHashCode) {
        final int $i$f$contentHashCode = 0;
        return Arrays.hashCode($this$contentHashCode);
    }
    
    @SinceKotlin(version = "1.1")
    @InlineOnly
    private static final int contentHashCode(@NotNull final char[] $this$contentHashCode) {
        final int $i$f$contentHashCode = 0;
        return Arrays.hashCode($this$contentHashCode);
    }
    
    @SinceKotlin(version = "1.1")
    @InlineOnly
    private static final <T> String contentToString(@NotNull final T[] $this$contentToString) {
        final int $i$f$contentToString = 0;
        final String string = Arrays.toString($this$contentToString);
        Intrinsics.checkExpressionValueIsNotNull(string, "java.util.Arrays.toString(this)");
        return string;
    }
    
    @SinceKotlin(version = "1.1")
    @InlineOnly
    private static final String contentToString(@NotNull final byte[] $this$contentToString) {
        final int $i$f$contentToString = 0;
        final String string = Arrays.toString($this$contentToString);
        Intrinsics.checkExpressionValueIsNotNull(string, "java.util.Arrays.toString(this)");
        return string;
    }
    
    @SinceKotlin(version = "1.1")
    @InlineOnly
    private static final String contentToString(@NotNull final short[] $this$contentToString) {
        final int $i$f$contentToString = 0;
        final String string = Arrays.toString($this$contentToString);
        Intrinsics.checkExpressionValueIsNotNull(string, "java.util.Arrays.toString(this)");
        return string;
    }
    
    @SinceKotlin(version = "1.1")
    @InlineOnly
    private static final String contentToString(@NotNull final int[] $this$contentToString) {
        final int $i$f$contentToString = 0;
        final String string = Arrays.toString($this$contentToString);
        Intrinsics.checkExpressionValueIsNotNull(string, "java.util.Arrays.toString(this)");
        return string;
    }
    
    @SinceKotlin(version = "1.1")
    @InlineOnly
    private static final String contentToString(@NotNull final long[] $this$contentToString) {
        final int $i$f$contentToString = 0;
        final String string = Arrays.toString($this$contentToString);
        Intrinsics.checkExpressionValueIsNotNull(string, "java.util.Arrays.toString(this)");
        return string;
    }
    
    @SinceKotlin(version = "1.1")
    @InlineOnly
    private static final String contentToString(@NotNull final float[] $this$contentToString) {
        final int $i$f$contentToString = 0;
        final String string = Arrays.toString($this$contentToString);
        Intrinsics.checkExpressionValueIsNotNull(string, "java.util.Arrays.toString(this)");
        return string;
    }
    
    @SinceKotlin(version = "1.1")
    @InlineOnly
    private static final String contentToString(@NotNull final double[] $this$contentToString) {
        final int $i$f$contentToString = 0;
        final String string = Arrays.toString($this$contentToString);
        Intrinsics.checkExpressionValueIsNotNull(string, "java.util.Arrays.toString(this)");
        return string;
    }
    
    @SinceKotlin(version = "1.1")
    @InlineOnly
    private static final String contentToString(@NotNull final boolean[] $this$contentToString) {
        final int $i$f$contentToString = 0;
        final String string = Arrays.toString($this$contentToString);
        Intrinsics.checkExpressionValueIsNotNull(string, "java.util.Arrays.toString(this)");
        return string;
    }
    
    @SinceKotlin(version = "1.1")
    @InlineOnly
    private static final String contentToString(@NotNull final char[] $this$contentToString) {
        final int $i$f$contentToString = 0;
        final String string = Arrays.toString($this$contentToString);
        Intrinsics.checkExpressionValueIsNotNull(string, "java.util.Arrays.toString(this)");
        return string;
    }
    
    @SinceKotlin(version = "1.3")
    @NotNull
    public static final <T> T[] copyInto(@NotNull final T[] $this$copyInto, @NotNull final T[] destination, final int destinationOffset, final int startIndex, final int endIndex) {
        Intrinsics.checkParameterIsNotNull($this$copyInto, "$this$copyInto");
        Intrinsics.checkParameterIsNotNull(destination, "destination");
        System.arraycopy($this$copyInto, startIndex, destination, destinationOffset, endIndex - startIndex);
        return destination;
    }
    
    @SinceKotlin(version = "1.3")
    @NotNull
    public static final byte[] copyInto(@NotNull final byte[] $this$copyInto, @NotNull final byte[] destination, final int destinationOffset, final int startIndex, final int endIndex) {
        Intrinsics.checkParameterIsNotNull($this$copyInto, "$this$copyInto");
        Intrinsics.checkParameterIsNotNull(destination, "destination");
        System.arraycopy($this$copyInto, startIndex, destination, destinationOffset, endIndex - startIndex);
        return destination;
    }
    
    @SinceKotlin(version = "1.3")
    @NotNull
    public static final short[] copyInto(@NotNull final short[] $this$copyInto, @NotNull final short[] destination, final int destinationOffset, final int startIndex, final int endIndex) {
        Intrinsics.checkParameterIsNotNull($this$copyInto, "$this$copyInto");
        Intrinsics.checkParameterIsNotNull(destination, "destination");
        System.arraycopy($this$copyInto, startIndex, destination, destinationOffset, endIndex - startIndex);
        return destination;
    }
    
    @SinceKotlin(version = "1.3")
    @NotNull
    public static final int[] copyInto(@NotNull final int[] $this$copyInto, @NotNull final int[] destination, final int destinationOffset, final int startIndex, final int endIndex) {
        Intrinsics.checkParameterIsNotNull($this$copyInto, "$this$copyInto");
        Intrinsics.checkParameterIsNotNull(destination, "destination");
        System.arraycopy($this$copyInto, startIndex, destination, destinationOffset, endIndex - startIndex);
        return destination;
    }
    
    @SinceKotlin(version = "1.3")
    @NotNull
    public static final long[] copyInto(@NotNull final long[] $this$copyInto, @NotNull final long[] destination, final int destinationOffset, final int startIndex, final int endIndex) {
        Intrinsics.checkParameterIsNotNull($this$copyInto, "$this$copyInto");
        Intrinsics.checkParameterIsNotNull(destination, "destination");
        System.arraycopy($this$copyInto, startIndex, destination, destinationOffset, endIndex - startIndex);
        return destination;
    }
    
    @SinceKotlin(version = "1.3")
    @NotNull
    public static final float[] copyInto(@NotNull final float[] $this$copyInto, @NotNull final float[] destination, final int destinationOffset, final int startIndex, final int endIndex) {
        Intrinsics.checkParameterIsNotNull($this$copyInto, "$this$copyInto");
        Intrinsics.checkParameterIsNotNull(destination, "destination");
        System.arraycopy($this$copyInto, startIndex, destination, destinationOffset, endIndex - startIndex);
        return destination;
    }
    
    @SinceKotlin(version = "1.3")
    @NotNull
    public static final double[] copyInto(@NotNull final double[] $this$copyInto, @NotNull final double[] destination, final int destinationOffset, final int startIndex, final int endIndex) {
        Intrinsics.checkParameterIsNotNull($this$copyInto, "$this$copyInto");
        Intrinsics.checkParameterIsNotNull(destination, "destination");
        System.arraycopy($this$copyInto, startIndex, destination, destinationOffset, endIndex - startIndex);
        return destination;
    }
    
    @SinceKotlin(version = "1.3")
    @NotNull
    public static final boolean[] copyInto(@NotNull final boolean[] $this$copyInto, @NotNull final boolean[] destination, final int destinationOffset, final int startIndex, final int endIndex) {
        Intrinsics.checkParameterIsNotNull($this$copyInto, "$this$copyInto");
        Intrinsics.checkParameterIsNotNull(destination, "destination");
        System.arraycopy($this$copyInto, startIndex, destination, destinationOffset, endIndex - startIndex);
        return destination;
    }
    
    @SinceKotlin(version = "1.3")
    @NotNull
    public static final char[] copyInto(@NotNull final char[] $this$copyInto, @NotNull final char[] destination, final int destinationOffset, final int startIndex, final int endIndex) {
        Intrinsics.checkParameterIsNotNull($this$copyInto, "$this$copyInto");
        Intrinsics.checkParameterIsNotNull(destination, "destination");
        System.arraycopy($this$copyInto, startIndex, destination, destinationOffset, endIndex - startIndex);
        return destination;
    }
    
    @InlineOnly
    private static final <T> T[] copyOf(@NotNull final T[] $this$copyOf) {
        final int $i$f$copyOf = 0;
        final T[] copy = Arrays.copyOf($this$copyOf, $this$copyOf.length);
        Intrinsics.checkExpressionValueIsNotNull(copy, "java.util.Arrays.copyOf(this, size)");
        return copy;
    }
    
    @InlineOnly
    private static final byte[] copyOf(@NotNull final byte[] $this$copyOf) {
        final int $i$f$copyOf = 0;
        final byte[] copy = Arrays.copyOf($this$copyOf, $this$copyOf.length);
        Intrinsics.checkExpressionValueIsNotNull(copy, "java.util.Arrays.copyOf(this, size)");
        return copy;
    }
    
    @InlineOnly
    private static final short[] copyOf(@NotNull final short[] $this$copyOf) {
        final int $i$f$copyOf = 0;
        final short[] copy = Arrays.copyOf($this$copyOf, $this$copyOf.length);
        Intrinsics.checkExpressionValueIsNotNull(copy, "java.util.Arrays.copyOf(this, size)");
        return copy;
    }
    
    @InlineOnly
    private static final int[] copyOf(@NotNull final int[] $this$copyOf) {
        final int $i$f$copyOf = 0;
        final int[] copy = Arrays.copyOf($this$copyOf, $this$copyOf.length);
        Intrinsics.checkExpressionValueIsNotNull(copy, "java.util.Arrays.copyOf(this, size)");
        return copy;
    }
    
    @InlineOnly
    private static final long[] copyOf(@NotNull final long[] $this$copyOf) {
        final int $i$f$copyOf = 0;
        final long[] copy = Arrays.copyOf($this$copyOf, $this$copyOf.length);
        Intrinsics.checkExpressionValueIsNotNull(copy, "java.util.Arrays.copyOf(this, size)");
        return copy;
    }
    
    @InlineOnly
    private static final float[] copyOf(@NotNull final float[] $this$copyOf) {
        final int $i$f$copyOf = 0;
        final float[] copy = Arrays.copyOf($this$copyOf, $this$copyOf.length);
        Intrinsics.checkExpressionValueIsNotNull(copy, "java.util.Arrays.copyOf(this, size)");
        return copy;
    }
    
    @InlineOnly
    private static final double[] copyOf(@NotNull final double[] $this$copyOf) {
        final int $i$f$copyOf = 0;
        final double[] copy = Arrays.copyOf($this$copyOf, $this$copyOf.length);
        Intrinsics.checkExpressionValueIsNotNull(copy, "java.util.Arrays.copyOf(this, size)");
        return copy;
    }
    
    @InlineOnly
    private static final boolean[] copyOf(@NotNull final boolean[] $this$copyOf) {
        final int $i$f$copyOf = 0;
        final boolean[] copy = Arrays.copyOf($this$copyOf, $this$copyOf.length);
        Intrinsics.checkExpressionValueIsNotNull(copy, "java.util.Arrays.copyOf(this, size)");
        return copy;
    }
    
    @InlineOnly
    private static final char[] copyOf(@NotNull final char[] $this$copyOf) {
        final int $i$f$copyOf = 0;
        final char[] copy = Arrays.copyOf($this$copyOf, $this$copyOf.length);
        Intrinsics.checkExpressionValueIsNotNull(copy, "java.util.Arrays.copyOf(this, size)");
        return copy;
    }
    
    @InlineOnly
    private static final byte[] copyOf(@NotNull final byte[] $this$copyOf, final int newSize) {
        final int $i$f$copyOf = 0;
        final byte[] copy = Arrays.copyOf($this$copyOf, newSize);
        Intrinsics.checkExpressionValueIsNotNull(copy, "java.util.Arrays.copyOf(this, newSize)");
        return copy;
    }
    
    @InlineOnly
    private static final short[] copyOf(@NotNull final short[] $this$copyOf, final int newSize) {
        final int $i$f$copyOf = 0;
        final short[] copy = Arrays.copyOf($this$copyOf, newSize);
        Intrinsics.checkExpressionValueIsNotNull(copy, "java.util.Arrays.copyOf(this, newSize)");
        return copy;
    }
    
    @InlineOnly
    private static final int[] copyOf(@NotNull final int[] $this$copyOf, final int newSize) {
        final int $i$f$copyOf = 0;
        final int[] copy = Arrays.copyOf($this$copyOf, newSize);
        Intrinsics.checkExpressionValueIsNotNull(copy, "java.util.Arrays.copyOf(this, newSize)");
        return copy;
    }
    
    @InlineOnly
    private static final long[] copyOf(@NotNull final long[] $this$copyOf, final int newSize) {
        final int $i$f$copyOf = 0;
        final long[] copy = Arrays.copyOf($this$copyOf, newSize);
        Intrinsics.checkExpressionValueIsNotNull(copy, "java.util.Arrays.copyOf(this, newSize)");
        return copy;
    }
    
    @InlineOnly
    private static final float[] copyOf(@NotNull final float[] $this$copyOf, final int newSize) {
        final int $i$f$copyOf = 0;
        final float[] copy = Arrays.copyOf($this$copyOf, newSize);
        Intrinsics.checkExpressionValueIsNotNull(copy, "java.util.Arrays.copyOf(this, newSize)");
        return copy;
    }
    
    @InlineOnly
    private static final double[] copyOf(@NotNull final double[] $this$copyOf, final int newSize) {
        final int $i$f$copyOf = 0;
        final double[] copy = Arrays.copyOf($this$copyOf, newSize);
        Intrinsics.checkExpressionValueIsNotNull(copy, "java.util.Arrays.copyOf(this, newSize)");
        return copy;
    }
    
    @InlineOnly
    private static final boolean[] copyOf(@NotNull final boolean[] $this$copyOf, final int newSize) {
        final int $i$f$copyOf = 0;
        final boolean[] copy = Arrays.copyOf($this$copyOf, newSize);
        Intrinsics.checkExpressionValueIsNotNull(copy, "java.util.Arrays.copyOf(this, newSize)");
        return copy;
    }
    
    @InlineOnly
    private static final char[] copyOf(@NotNull final char[] $this$copyOf, final int newSize) {
        final int $i$f$copyOf = 0;
        final char[] copy = Arrays.copyOf($this$copyOf, newSize);
        Intrinsics.checkExpressionValueIsNotNull(copy, "java.util.Arrays.copyOf(this, newSize)");
        return copy;
    }
    
    @InlineOnly
    private static final <T> T[] copyOf(@NotNull final T[] $this$copyOf, final int newSize) {
        final int $i$f$copyOf = 0;
        final T[] copy = Arrays.copyOf($this$copyOf, newSize);
        Intrinsics.checkExpressionValueIsNotNull(copy, "java.util.Arrays.copyOf(this, newSize)");
        return copy;
    }
    
    @JvmName(name = "copyOfRangeInline")
    @InlineOnly
    private static final <T> T[] copyOfRangeInline(@NotNull final T[] $this$copyOfRange, final int fromIndex, final int toIndex) {
        final int $i$f$copyOfRangeInline = 0;
        Object[] array;
        if (PlatformImplementationsKt.apiVersionIsAtLeast(1, 3, 0)) {
            array = copyOfRange((Object[])$this$copyOfRange, fromIndex, toIndex);
        }
        else {
            if (toIndex > $this$copyOfRange.length) {
                throw new IndexOutOfBoundsException("toIndex: " + toIndex + ", size: " + $this$copyOfRange.length);
            }
            Intrinsics.checkExpressionValueIsNotNull(array = Arrays.copyOfRange($this$copyOfRange, fromIndex, toIndex), "java.util.Arrays.copyOfR\u2026this, fromIndex, toIndex)");
        }
        return (T[])array;
    }
    
    @JvmName(name = "copyOfRangeInline")
    @InlineOnly
    private static final byte[] copyOfRangeInline(@NotNull final byte[] $this$copyOfRange, final int fromIndex, final int toIndex) {
        final int $i$f$copyOfRangeInline = 0;
        byte[] array;
        if (PlatformImplementationsKt.apiVersionIsAtLeast(1, 3, 0)) {
            array = copyOfRange($this$copyOfRange, fromIndex, toIndex);
        }
        else {
            if (toIndex > $this$copyOfRange.length) {
                throw new IndexOutOfBoundsException("toIndex: " + toIndex + ", size: " + $this$copyOfRange.length);
            }
            Intrinsics.checkExpressionValueIsNotNull(array = Arrays.copyOfRange($this$copyOfRange, fromIndex, toIndex), "java.util.Arrays.copyOfR\u2026this, fromIndex, toIndex)");
        }
        return array;
    }
    
    @JvmName(name = "copyOfRangeInline")
    @InlineOnly
    private static final short[] copyOfRangeInline(@NotNull final short[] $this$copyOfRange, final int fromIndex, final int toIndex) {
        final int $i$f$copyOfRangeInline = 0;
        short[] array;
        if (PlatformImplementationsKt.apiVersionIsAtLeast(1, 3, 0)) {
            array = copyOfRange($this$copyOfRange, fromIndex, toIndex);
        }
        else {
            if (toIndex > $this$copyOfRange.length) {
                throw new IndexOutOfBoundsException("toIndex: " + toIndex + ", size: " + $this$copyOfRange.length);
            }
            Intrinsics.checkExpressionValueIsNotNull(array = Arrays.copyOfRange($this$copyOfRange, fromIndex, toIndex), "java.util.Arrays.copyOfR\u2026this, fromIndex, toIndex)");
        }
        return array;
    }
    
    @JvmName(name = "copyOfRangeInline")
    @InlineOnly
    private static final int[] copyOfRangeInline(@NotNull final int[] $this$copyOfRange, final int fromIndex, final int toIndex) {
        final int $i$f$copyOfRangeInline = 0;
        int[] array;
        if (PlatformImplementationsKt.apiVersionIsAtLeast(1, 3, 0)) {
            array = copyOfRange($this$copyOfRange, fromIndex, toIndex);
        }
        else {
            if (toIndex > $this$copyOfRange.length) {
                throw new IndexOutOfBoundsException("toIndex: " + toIndex + ", size: " + $this$copyOfRange.length);
            }
            Intrinsics.checkExpressionValueIsNotNull(array = Arrays.copyOfRange($this$copyOfRange, fromIndex, toIndex), "java.util.Arrays.copyOfR\u2026this, fromIndex, toIndex)");
        }
        return array;
    }
    
    @JvmName(name = "copyOfRangeInline")
    @InlineOnly
    private static final long[] copyOfRangeInline(@NotNull final long[] $this$copyOfRange, final int fromIndex, final int toIndex) {
        final int $i$f$copyOfRangeInline = 0;
        long[] array;
        if (PlatformImplementationsKt.apiVersionIsAtLeast(1, 3, 0)) {
            array = copyOfRange($this$copyOfRange, fromIndex, toIndex);
        }
        else {
            if (toIndex > $this$copyOfRange.length) {
                throw new IndexOutOfBoundsException("toIndex: " + toIndex + ", size: " + $this$copyOfRange.length);
            }
            Intrinsics.checkExpressionValueIsNotNull(array = Arrays.copyOfRange($this$copyOfRange, fromIndex, toIndex), "java.util.Arrays.copyOfR\u2026this, fromIndex, toIndex)");
        }
        return array;
    }
    
    @JvmName(name = "copyOfRangeInline")
    @InlineOnly
    private static final float[] copyOfRangeInline(@NotNull final float[] $this$copyOfRange, final int fromIndex, final int toIndex) {
        final int $i$f$copyOfRangeInline = 0;
        float[] array;
        if (PlatformImplementationsKt.apiVersionIsAtLeast(1, 3, 0)) {
            array = copyOfRange($this$copyOfRange, fromIndex, toIndex);
        }
        else {
            if (toIndex > $this$copyOfRange.length) {
                throw new IndexOutOfBoundsException("toIndex: " + toIndex + ", size: " + $this$copyOfRange.length);
            }
            Intrinsics.checkExpressionValueIsNotNull(array = Arrays.copyOfRange($this$copyOfRange, fromIndex, toIndex), "java.util.Arrays.copyOfR\u2026this, fromIndex, toIndex)");
        }
        return array;
    }
    
    @JvmName(name = "copyOfRangeInline")
    @InlineOnly
    private static final double[] copyOfRangeInline(@NotNull final double[] $this$copyOfRange, final int fromIndex, final int toIndex) {
        final int $i$f$copyOfRangeInline = 0;
        double[] array;
        if (PlatformImplementationsKt.apiVersionIsAtLeast(1, 3, 0)) {
            array = copyOfRange($this$copyOfRange, fromIndex, toIndex);
        }
        else {
            if (toIndex > $this$copyOfRange.length) {
                throw new IndexOutOfBoundsException("toIndex: " + toIndex + ", size: " + $this$copyOfRange.length);
            }
            Intrinsics.checkExpressionValueIsNotNull(array = Arrays.copyOfRange($this$copyOfRange, fromIndex, toIndex), "java.util.Arrays.copyOfR\u2026this, fromIndex, toIndex)");
        }
        return array;
    }
    
    @JvmName(name = "copyOfRangeInline")
    @InlineOnly
    private static final boolean[] copyOfRangeInline(@NotNull final boolean[] $this$copyOfRange, final int fromIndex, final int toIndex) {
        final int $i$f$copyOfRangeInline = 0;
        boolean[] array;
        if (PlatformImplementationsKt.apiVersionIsAtLeast(1, 3, 0)) {
            array = copyOfRange($this$copyOfRange, fromIndex, toIndex);
        }
        else {
            if (toIndex > $this$copyOfRange.length) {
                throw new IndexOutOfBoundsException("toIndex: " + toIndex + ", size: " + $this$copyOfRange.length);
            }
            Intrinsics.checkExpressionValueIsNotNull(array = Arrays.copyOfRange($this$copyOfRange, fromIndex, toIndex), "java.util.Arrays.copyOfR\u2026this, fromIndex, toIndex)");
        }
        return array;
    }
    
    @JvmName(name = "copyOfRangeInline")
    @InlineOnly
    private static final char[] copyOfRangeInline(@NotNull final char[] $this$copyOfRange, final int fromIndex, final int toIndex) {
        final int $i$f$copyOfRangeInline = 0;
        char[] array;
        if (PlatformImplementationsKt.apiVersionIsAtLeast(1, 3, 0)) {
            array = copyOfRange($this$copyOfRange, fromIndex, toIndex);
        }
        else {
            if (toIndex > $this$copyOfRange.length) {
                throw new IndexOutOfBoundsException("toIndex: " + toIndex + ", size: " + $this$copyOfRange.length);
            }
            Intrinsics.checkExpressionValueIsNotNull(array = Arrays.copyOfRange($this$copyOfRange, fromIndex, toIndex), "java.util.Arrays.copyOfR\u2026this, fromIndex, toIndex)");
        }
        return array;
    }
    
    @SinceKotlin(version = "1.3")
    @PublishedApi
    @JvmName(name = "copyOfRange")
    @NotNull
    public static final <T> T[] copyOfRange(@NotNull final T[] $this$copyOfRangeImpl, final int fromIndex, final int toIndex) {
        Intrinsics.checkParameterIsNotNull($this$copyOfRangeImpl, "$this$copyOfRangeImpl");
        ArraysKt__ArraysJVMKt.copyOfRangeToIndexCheck(toIndex, $this$copyOfRangeImpl.length);
        final T[] copyOfRange = Arrays.copyOfRange($this$copyOfRangeImpl, fromIndex, toIndex);
        Intrinsics.checkExpressionValueIsNotNull(copyOfRange, "java.util.Arrays.copyOfR\u2026this, fromIndex, toIndex)");
        return copyOfRange;
    }
    
    @SinceKotlin(version = "1.3")
    @PublishedApi
    @JvmName(name = "copyOfRange")
    @NotNull
    public static final byte[] copyOfRange(@NotNull final byte[] $this$copyOfRangeImpl, final int fromIndex, final int toIndex) {
        Intrinsics.checkParameterIsNotNull($this$copyOfRangeImpl, "$this$copyOfRangeImpl");
        ArraysKt__ArraysJVMKt.copyOfRangeToIndexCheck(toIndex, $this$copyOfRangeImpl.length);
        final byte[] copyOfRange = Arrays.copyOfRange($this$copyOfRangeImpl, fromIndex, toIndex);
        Intrinsics.checkExpressionValueIsNotNull(copyOfRange, "java.util.Arrays.copyOfR\u2026this, fromIndex, toIndex)");
        return copyOfRange;
    }
    
    @SinceKotlin(version = "1.3")
    @PublishedApi
    @JvmName(name = "copyOfRange")
    @NotNull
    public static final short[] copyOfRange(@NotNull final short[] $this$copyOfRangeImpl, final int fromIndex, final int toIndex) {
        Intrinsics.checkParameterIsNotNull($this$copyOfRangeImpl, "$this$copyOfRangeImpl");
        ArraysKt__ArraysJVMKt.copyOfRangeToIndexCheck(toIndex, $this$copyOfRangeImpl.length);
        final short[] copyOfRange = Arrays.copyOfRange($this$copyOfRangeImpl, fromIndex, toIndex);
        Intrinsics.checkExpressionValueIsNotNull(copyOfRange, "java.util.Arrays.copyOfR\u2026this, fromIndex, toIndex)");
        return copyOfRange;
    }
    
    @SinceKotlin(version = "1.3")
    @PublishedApi
    @JvmName(name = "copyOfRange")
    @NotNull
    public static final int[] copyOfRange(@NotNull final int[] $this$copyOfRangeImpl, final int fromIndex, final int toIndex) {
        Intrinsics.checkParameterIsNotNull($this$copyOfRangeImpl, "$this$copyOfRangeImpl");
        ArraysKt__ArraysJVMKt.copyOfRangeToIndexCheck(toIndex, $this$copyOfRangeImpl.length);
        final int[] copyOfRange = Arrays.copyOfRange($this$copyOfRangeImpl, fromIndex, toIndex);
        Intrinsics.checkExpressionValueIsNotNull(copyOfRange, "java.util.Arrays.copyOfR\u2026this, fromIndex, toIndex)");
        return copyOfRange;
    }
    
    @SinceKotlin(version = "1.3")
    @PublishedApi
    @JvmName(name = "copyOfRange")
    @NotNull
    public static final long[] copyOfRange(@NotNull final long[] $this$copyOfRangeImpl, final int fromIndex, final int toIndex) {
        Intrinsics.checkParameterIsNotNull($this$copyOfRangeImpl, "$this$copyOfRangeImpl");
        ArraysKt__ArraysJVMKt.copyOfRangeToIndexCheck(toIndex, $this$copyOfRangeImpl.length);
        final long[] copyOfRange = Arrays.copyOfRange($this$copyOfRangeImpl, fromIndex, toIndex);
        Intrinsics.checkExpressionValueIsNotNull(copyOfRange, "java.util.Arrays.copyOfR\u2026this, fromIndex, toIndex)");
        return copyOfRange;
    }
    
    @SinceKotlin(version = "1.3")
    @PublishedApi
    @JvmName(name = "copyOfRange")
    @NotNull
    public static final float[] copyOfRange(@NotNull final float[] $this$copyOfRangeImpl, final int fromIndex, final int toIndex) {
        Intrinsics.checkParameterIsNotNull($this$copyOfRangeImpl, "$this$copyOfRangeImpl");
        ArraysKt__ArraysJVMKt.copyOfRangeToIndexCheck(toIndex, $this$copyOfRangeImpl.length);
        final float[] copyOfRange = Arrays.copyOfRange($this$copyOfRangeImpl, fromIndex, toIndex);
        Intrinsics.checkExpressionValueIsNotNull(copyOfRange, "java.util.Arrays.copyOfR\u2026this, fromIndex, toIndex)");
        return copyOfRange;
    }
    
    @SinceKotlin(version = "1.3")
    @PublishedApi
    @JvmName(name = "copyOfRange")
    @NotNull
    public static final double[] copyOfRange(@NotNull final double[] $this$copyOfRangeImpl, final int fromIndex, final int toIndex) {
        Intrinsics.checkParameterIsNotNull($this$copyOfRangeImpl, "$this$copyOfRangeImpl");
        ArraysKt__ArraysJVMKt.copyOfRangeToIndexCheck(toIndex, $this$copyOfRangeImpl.length);
        final double[] copyOfRange = Arrays.copyOfRange($this$copyOfRangeImpl, fromIndex, toIndex);
        Intrinsics.checkExpressionValueIsNotNull(copyOfRange, "java.util.Arrays.copyOfR\u2026this, fromIndex, toIndex)");
        return copyOfRange;
    }
    
    @SinceKotlin(version = "1.3")
    @PublishedApi
    @JvmName(name = "copyOfRange")
    @NotNull
    public static final boolean[] copyOfRange(@NotNull final boolean[] $this$copyOfRangeImpl, final int fromIndex, final int toIndex) {
        Intrinsics.checkParameterIsNotNull($this$copyOfRangeImpl, "$this$copyOfRangeImpl");
        ArraysKt__ArraysJVMKt.copyOfRangeToIndexCheck(toIndex, $this$copyOfRangeImpl.length);
        final boolean[] copyOfRange = Arrays.copyOfRange($this$copyOfRangeImpl, fromIndex, toIndex);
        Intrinsics.checkExpressionValueIsNotNull(copyOfRange, "java.util.Arrays.copyOfR\u2026this, fromIndex, toIndex)");
        return copyOfRange;
    }
    
    @SinceKotlin(version = "1.3")
    @PublishedApi
    @JvmName(name = "copyOfRange")
    @NotNull
    public static final char[] copyOfRange(@NotNull final char[] $this$copyOfRangeImpl, final int fromIndex, final int toIndex) {
        Intrinsics.checkParameterIsNotNull($this$copyOfRangeImpl, "$this$copyOfRangeImpl");
        ArraysKt__ArraysJVMKt.copyOfRangeToIndexCheck(toIndex, $this$copyOfRangeImpl.length);
        final char[] copyOfRange = Arrays.copyOfRange($this$copyOfRangeImpl, fromIndex, toIndex);
        Intrinsics.checkExpressionValueIsNotNull(copyOfRange, "java.util.Arrays.copyOfR\u2026this, fromIndex, toIndex)");
        return copyOfRange;
    }
    
    public static final <T> void fill(@NotNull final T[] $this$fill, final T element, final int fromIndex, final int toIndex) {
        Intrinsics.checkParameterIsNotNull($this$fill, "$this$fill");
        Arrays.fill($this$fill, fromIndex, toIndex, element);
    }
    
    public static final void fill(@NotNull final byte[] $this$fill, final byte element, final int fromIndex, final int toIndex) {
        Intrinsics.checkParameterIsNotNull($this$fill, "$this$fill");
        Arrays.fill($this$fill, fromIndex, toIndex, element);
    }
    
    public static final void fill(@NotNull final short[] $this$fill, final short element, final int fromIndex, final int toIndex) {
        Intrinsics.checkParameterIsNotNull($this$fill, "$this$fill");
        Arrays.fill($this$fill, fromIndex, toIndex, element);
    }
    
    public static final void fill(@NotNull final int[] $this$fill, final int element, final int fromIndex, final int toIndex) {
        Intrinsics.checkParameterIsNotNull($this$fill, "$this$fill");
        Arrays.fill($this$fill, fromIndex, toIndex, element);
    }
    
    public static final void fill(@NotNull final long[] $this$fill, final long element, final int fromIndex, final int toIndex) {
        Intrinsics.checkParameterIsNotNull($this$fill, "$this$fill");
        Arrays.fill($this$fill, fromIndex, toIndex, element);
    }
    
    public static final void fill(@NotNull final float[] $this$fill, final float element, final int fromIndex, final int toIndex) {
        Intrinsics.checkParameterIsNotNull($this$fill, "$this$fill");
        Arrays.fill($this$fill, fromIndex, toIndex, element);
    }
    
    public static final void fill(@NotNull final double[] $this$fill, final double element, final int fromIndex, final int toIndex) {
        Intrinsics.checkParameterIsNotNull($this$fill, "$this$fill");
        Arrays.fill($this$fill, fromIndex, toIndex, element);
    }
    
    public static final void fill(@NotNull final boolean[] $this$fill, final boolean element, final int fromIndex, final int toIndex) {
        Intrinsics.checkParameterIsNotNull($this$fill, "$this$fill");
        Arrays.fill($this$fill, fromIndex, toIndex, element);
    }
    
    public static final void fill(@NotNull final char[] $this$fill, final char element, final int fromIndex, final int toIndex) {
        Intrinsics.checkParameterIsNotNull($this$fill, "$this$fill");
        Arrays.fill($this$fill, fromIndex, toIndex, element);
    }
    
    @NotNull
    public static final <T> T[] plus(@NotNull final T[] $this$plus, final T element) {
        Intrinsics.checkParameterIsNotNull($this$plus, "$this$plus");
        final int index = $this$plus.length;
        final Object[] result = Arrays.copyOf($this$plus, index + 1);
        result[index] = element;
        final Object[] value = result;
        Intrinsics.checkExpressionValueIsNotNull(value, "result");
        return (T[])value;
    }
    
    @NotNull
    public static final byte[] plus(@NotNull final byte[] $this$plus, final byte element) {
        Intrinsics.checkParameterIsNotNull($this$plus, "$this$plus");
        final int index = $this$plus.length;
        final byte[] result = Arrays.copyOf($this$plus, index + 1);
        result[index] = element;
        final byte[] value = result;
        Intrinsics.checkExpressionValueIsNotNull(value, "result");
        return value;
    }
    
    @NotNull
    public static final short[] plus(@NotNull final short[] $this$plus, final short element) {
        Intrinsics.checkParameterIsNotNull($this$plus, "$this$plus");
        final int index = $this$plus.length;
        final short[] result = Arrays.copyOf($this$plus, index + 1);
        result[index] = element;
        final short[] value = result;
        Intrinsics.checkExpressionValueIsNotNull(value, "result");
        return value;
    }
    
    @NotNull
    public static final int[] plus(@NotNull final int[] $this$plus, final int element) {
        Intrinsics.checkParameterIsNotNull($this$plus, "$this$plus");
        final int index = $this$plus.length;
        final int[] result = Arrays.copyOf($this$plus, index + 1);
        result[index] = element;
        final int[] value = result;
        Intrinsics.checkExpressionValueIsNotNull(value, "result");
        return value;
    }
    
    @NotNull
    public static final long[] plus(@NotNull final long[] $this$plus, final long element) {
        Intrinsics.checkParameterIsNotNull($this$plus, "$this$plus");
        final int index = $this$plus.length;
        final long[] result = Arrays.copyOf($this$plus, index + 1);
        result[index] = element;
        final long[] value = result;
        Intrinsics.checkExpressionValueIsNotNull(value, "result");
        return value;
    }
    
    @NotNull
    public static final float[] plus(@NotNull final float[] $this$plus, final float element) {
        Intrinsics.checkParameterIsNotNull($this$plus, "$this$plus");
        final int index = $this$plus.length;
        final float[] result = Arrays.copyOf($this$plus, index + 1);
        result[index] = element;
        final float[] value = result;
        Intrinsics.checkExpressionValueIsNotNull(value, "result");
        return value;
    }
    
    @NotNull
    public static final double[] plus(@NotNull final double[] $this$plus, final double element) {
        Intrinsics.checkParameterIsNotNull($this$plus, "$this$plus");
        final int index = $this$plus.length;
        final double[] result = Arrays.copyOf($this$plus, index + 1);
        result[index] = element;
        final double[] value = result;
        Intrinsics.checkExpressionValueIsNotNull(value, "result");
        return value;
    }
    
    @NotNull
    public static final boolean[] plus(@NotNull final boolean[] $this$plus, final boolean element) {
        Intrinsics.checkParameterIsNotNull($this$plus, "$this$plus");
        final int index = $this$plus.length;
        final boolean[] result = Arrays.copyOf($this$plus, index + 1);
        result[index] = element;
        final boolean[] value = result;
        Intrinsics.checkExpressionValueIsNotNull(value, "result");
        return value;
    }
    
    @NotNull
    public static final char[] plus(@NotNull final char[] $this$plus, final char element) {
        Intrinsics.checkParameterIsNotNull($this$plus, "$this$plus");
        final int index = $this$plus.length;
        final char[] result = Arrays.copyOf($this$plus, index + 1);
        result[index] = element;
        final char[] value = result;
        Intrinsics.checkExpressionValueIsNotNull(value, "result");
        return value;
    }
    
    @NotNull
    public static final <T> T[] plus(@NotNull final T[] $this$plus, @NotNull final Collection<? extends T> elements) {
        Intrinsics.checkParameterIsNotNull($this$plus, "$this$plus");
        Intrinsics.checkParameterIsNotNull(elements, "elements");
        int index = $this$plus.length;
        final Object[] result = Arrays.copyOf($this$plus, index + elements.size());
        for (final Object element : elements) {
            result[index++] = element;
        }
        final Object[] value = result;
        Intrinsics.checkExpressionValueIsNotNull(value, "result");
        return (T[])value;
    }
    
    @NotNull
    public static final byte[] plus(@NotNull final byte[] $this$plus, @NotNull final Collection<Byte> elements) {
        Intrinsics.checkParameterIsNotNull($this$plus, "$this$plus");
        Intrinsics.checkParameterIsNotNull(elements, "elements");
        int index = $this$plus.length;
        final byte[] result = Arrays.copyOf($this$plus, index + elements.size());
        final Iterator<Byte> iterator = elements.iterator();
        while (iterator.hasNext()) {
            final byte element = iterator.next().byteValue();
            result[index++] = element;
        }
        final byte[] value = result;
        Intrinsics.checkExpressionValueIsNotNull(value, "result");
        return value;
    }
    
    @NotNull
    public static final short[] plus(@NotNull final short[] $this$plus, @NotNull final Collection<Short> elements) {
        Intrinsics.checkParameterIsNotNull($this$plus, "$this$plus");
        Intrinsics.checkParameterIsNotNull(elements, "elements");
        int index = $this$plus.length;
        final short[] result = Arrays.copyOf($this$plus, index + elements.size());
        final Iterator<Short> iterator = elements.iterator();
        while (iterator.hasNext()) {
            final short element = iterator.next().shortValue();
            result[index++] = element;
        }
        final short[] value = result;
        Intrinsics.checkExpressionValueIsNotNull(value, "result");
        return value;
    }
    
    @NotNull
    public static final int[] plus(@NotNull final int[] $this$plus, @NotNull final Collection<Integer> elements) {
        Intrinsics.checkParameterIsNotNull($this$plus, "$this$plus");
        Intrinsics.checkParameterIsNotNull(elements, "elements");
        int index = $this$plus.length;
        final int[] result = Arrays.copyOf($this$plus, index + elements.size());
        final Iterator<Integer> iterator = elements.iterator();
        while (iterator.hasNext()) {
            final int element = iterator.next().intValue();
            result[index++] = element;
        }
        final int[] value = result;
        Intrinsics.checkExpressionValueIsNotNull(value, "result");
        return value;
    }
    
    @NotNull
    public static final long[] plus(@NotNull final long[] $this$plus, @NotNull final Collection<Long> elements) {
        Intrinsics.checkParameterIsNotNull($this$plus, "$this$plus");
        Intrinsics.checkParameterIsNotNull(elements, "elements");
        int index = $this$plus.length;
        final long[] result = Arrays.copyOf($this$plus, index + elements.size());
        final Iterator<Long> iterator = elements.iterator();
        while (iterator.hasNext()) {
            final long element = iterator.next().longValue();
            result[index++] = element;
        }
        final long[] value = result;
        Intrinsics.checkExpressionValueIsNotNull(value, "result");
        return value;
    }
    
    @NotNull
    public static final float[] plus(@NotNull final float[] $this$plus, @NotNull final Collection<Float> elements) {
        Intrinsics.checkParameterIsNotNull($this$plus, "$this$plus");
        Intrinsics.checkParameterIsNotNull(elements, "elements");
        int index = $this$plus.length;
        final float[] result = Arrays.copyOf($this$plus, index + elements.size());
        final Iterator<Float> iterator = elements.iterator();
        while (iterator.hasNext()) {
            final float element = iterator.next().floatValue();
            result[index++] = element;
        }
        final float[] value = result;
        Intrinsics.checkExpressionValueIsNotNull(value, "result");
        return value;
    }
    
    @NotNull
    public static final double[] plus(@NotNull final double[] $this$plus, @NotNull final Collection<Double> elements) {
        Intrinsics.checkParameterIsNotNull($this$plus, "$this$plus");
        Intrinsics.checkParameterIsNotNull(elements, "elements");
        int index = $this$plus.length;
        final double[] result = Arrays.copyOf($this$plus, index + elements.size());
        final Iterator<Double> iterator = elements.iterator();
        while (iterator.hasNext()) {
            final double element = iterator.next().doubleValue();
            result[index++] = element;
        }
        final double[] value = result;
        Intrinsics.checkExpressionValueIsNotNull(value, "result");
        return value;
    }
    
    @NotNull
    public static final boolean[] plus(@NotNull final boolean[] $this$plus, @NotNull final Collection<Boolean> elements) {
        Intrinsics.checkParameterIsNotNull($this$plus, "$this$plus");
        Intrinsics.checkParameterIsNotNull(elements, "elements");
        int index = $this$plus.length;
        final boolean[] result = Arrays.copyOf($this$plus, index + elements.size());
        for (final boolean element : elements) {
            result[index++] = element;
        }
        final boolean[] value = result;
        Intrinsics.checkExpressionValueIsNotNull(value, "result");
        return value;
    }
    
    @NotNull
    public static final char[] plus(@NotNull final char[] $this$plus, @NotNull final Collection<Character> elements) {
        Intrinsics.checkParameterIsNotNull($this$plus, "$this$plus");
        Intrinsics.checkParameterIsNotNull(elements, "elements");
        int index = $this$plus.length;
        final char[] result = Arrays.copyOf($this$plus, index + elements.size());
        for (final char element : elements) {
            result[index++] = element;
        }
        final char[] value = result;
        Intrinsics.checkExpressionValueIsNotNull(value, "result");
        return value;
    }
    
    @NotNull
    public static final <T> T[] plus(@NotNull final T[] $this$plus, @NotNull final T[] elements) {
        Intrinsics.checkParameterIsNotNull($this$plus, "$this$plus");
        Intrinsics.checkParameterIsNotNull(elements, "elements");
        final int thisSize = $this$plus.length;
        final int arraySize = elements.length;
        final Object[] result = Arrays.copyOf($this$plus, thisSize + arraySize);
        System.arraycopy(elements, 0, result, thisSize, arraySize);
        final Object[] value = result;
        Intrinsics.checkExpressionValueIsNotNull(value, "result");
        return (T[])value;
    }
    
    @NotNull
    public static final byte[] plus(@NotNull final byte[] $this$plus, @NotNull final byte[] elements) {
        Intrinsics.checkParameterIsNotNull($this$plus, "$this$plus");
        Intrinsics.checkParameterIsNotNull(elements, "elements");
        final int thisSize = $this$plus.length;
        final int arraySize = elements.length;
        final byte[] result = Arrays.copyOf($this$plus, thisSize + arraySize);
        System.arraycopy(elements, 0, result, thisSize, arraySize);
        final byte[] value = result;
        Intrinsics.checkExpressionValueIsNotNull(value, "result");
        return value;
    }
    
    @NotNull
    public static final short[] plus(@NotNull final short[] $this$plus, @NotNull final short[] elements) {
        Intrinsics.checkParameterIsNotNull($this$plus, "$this$plus");
        Intrinsics.checkParameterIsNotNull(elements, "elements");
        final int thisSize = $this$plus.length;
        final int arraySize = elements.length;
        final short[] result = Arrays.copyOf($this$plus, thisSize + arraySize);
        System.arraycopy(elements, 0, result, thisSize, arraySize);
        final short[] value = result;
        Intrinsics.checkExpressionValueIsNotNull(value, "result");
        return value;
    }
    
    @NotNull
    public static final int[] plus(@NotNull final int[] $this$plus, @NotNull final int[] elements) {
        Intrinsics.checkParameterIsNotNull($this$plus, "$this$plus");
        Intrinsics.checkParameterIsNotNull(elements, "elements");
        final int thisSize = $this$plus.length;
        final int arraySize = elements.length;
        final int[] result = Arrays.copyOf($this$plus, thisSize + arraySize);
        System.arraycopy(elements, 0, result, thisSize, arraySize);
        final int[] value = result;
        Intrinsics.checkExpressionValueIsNotNull(value, "result");
        return value;
    }
    
    @NotNull
    public static final long[] plus(@NotNull final long[] $this$plus, @NotNull final long[] elements) {
        Intrinsics.checkParameterIsNotNull($this$plus, "$this$plus");
        Intrinsics.checkParameterIsNotNull(elements, "elements");
        final int thisSize = $this$plus.length;
        final int arraySize = elements.length;
        final long[] result = Arrays.copyOf($this$plus, thisSize + arraySize);
        System.arraycopy(elements, 0, result, thisSize, arraySize);
        final long[] value = result;
        Intrinsics.checkExpressionValueIsNotNull(value, "result");
        return value;
    }
    
    @NotNull
    public static final float[] plus(@NotNull final float[] $this$plus, @NotNull final float[] elements) {
        Intrinsics.checkParameterIsNotNull($this$plus, "$this$plus");
        Intrinsics.checkParameterIsNotNull(elements, "elements");
        final int thisSize = $this$plus.length;
        final int arraySize = elements.length;
        final float[] result = Arrays.copyOf($this$plus, thisSize + arraySize);
        System.arraycopy(elements, 0, result, thisSize, arraySize);
        final float[] value = result;
        Intrinsics.checkExpressionValueIsNotNull(value, "result");
        return value;
    }
    
    @NotNull
    public static final double[] plus(@NotNull final double[] $this$plus, @NotNull final double[] elements) {
        Intrinsics.checkParameterIsNotNull($this$plus, "$this$plus");
        Intrinsics.checkParameterIsNotNull(elements, "elements");
        final int thisSize = $this$plus.length;
        final int arraySize = elements.length;
        final double[] result = Arrays.copyOf($this$plus, thisSize + arraySize);
        System.arraycopy(elements, 0, result, thisSize, arraySize);
        final double[] value = result;
        Intrinsics.checkExpressionValueIsNotNull(value, "result");
        return value;
    }
    
    @NotNull
    public static final boolean[] plus(@NotNull final boolean[] $this$plus, @NotNull final boolean[] elements) {
        Intrinsics.checkParameterIsNotNull($this$plus, "$this$plus");
        Intrinsics.checkParameterIsNotNull(elements, "elements");
        final int thisSize = $this$plus.length;
        final int arraySize = elements.length;
        final boolean[] result = Arrays.copyOf($this$plus, thisSize + arraySize);
        System.arraycopy(elements, 0, result, thisSize, arraySize);
        final boolean[] value = result;
        Intrinsics.checkExpressionValueIsNotNull(value, "result");
        return value;
    }
    
    @NotNull
    public static final char[] plus(@NotNull final char[] $this$plus, @NotNull final char[] elements) {
        Intrinsics.checkParameterIsNotNull($this$plus, "$this$plus");
        Intrinsics.checkParameterIsNotNull(elements, "elements");
        final int thisSize = $this$plus.length;
        final int arraySize = elements.length;
        final char[] result = Arrays.copyOf($this$plus, thisSize + arraySize);
        System.arraycopy(elements, 0, result, thisSize, arraySize);
        final char[] value = result;
        Intrinsics.checkExpressionValueIsNotNull(value, "result");
        return value;
    }
    
    @InlineOnly
    private static final <T> T[] plusElement(@NotNull final T[] $this$plusElement, final T element) {
        final int $i$f$plusElement = 0;
        return (T[])plus($this$plusElement, (Object)element);
    }
    
    public static final void sort(@NotNull final int[] $this$sort) {
        Intrinsics.checkParameterIsNotNull($this$sort, "$this$sort");
        if ($this$sort.length > 1) {
            Arrays.sort($this$sort);
        }
    }
    
    public static final void sort(@NotNull final long[] $this$sort) {
        Intrinsics.checkParameterIsNotNull($this$sort, "$this$sort");
        if ($this$sort.length > 1) {
            Arrays.sort($this$sort);
        }
    }
    
    public static final void sort(@NotNull final byte[] $this$sort) {
        Intrinsics.checkParameterIsNotNull($this$sort, "$this$sort");
        if ($this$sort.length > 1) {
            Arrays.sort($this$sort);
        }
    }
    
    public static final void sort(@NotNull final short[] $this$sort) {
        Intrinsics.checkParameterIsNotNull($this$sort, "$this$sort");
        if ($this$sort.length > 1) {
            Arrays.sort($this$sort);
        }
    }
    
    public static final void sort(@NotNull final double[] $this$sort) {
        Intrinsics.checkParameterIsNotNull($this$sort, "$this$sort");
        if ($this$sort.length > 1) {
            Arrays.sort($this$sort);
        }
    }
    
    public static final void sort(@NotNull final float[] $this$sort) {
        Intrinsics.checkParameterIsNotNull($this$sort, "$this$sort");
        if ($this$sort.length > 1) {
            Arrays.sort($this$sort);
        }
    }
    
    public static final void sort(@NotNull final char[] $this$sort) {
        Intrinsics.checkParameterIsNotNull($this$sort, "$this$sort");
        if ($this$sort.length > 1) {
            Arrays.sort($this$sort);
        }
    }
    
    @InlineOnly
    private static final <T extends Comparable<? super T>> void sort(@NotNull final T[] $this$sort) {
        final int $i$f$sort = 0;
        if ($this$sort == null) {
            throw new TypeCastException("null cannot be cast to non-null type kotlin.Array<kotlin.Any?>");
        }
        sort((T[])$this$sort);
    }
    
    public static final <T> void sort(@NotNull final T[] $this$sort) {
        Intrinsics.checkParameterIsNotNull($this$sort, "$this$sort");
        if ($this$sort.length > 1) {
            Arrays.sort($this$sort);
        }
    }
    
    public static final <T> void sort(@NotNull final T[] $this$sort, final int fromIndex, final int toIndex) {
        Intrinsics.checkParameterIsNotNull($this$sort, "$this$sort");
        Arrays.sort($this$sort, fromIndex, toIndex);
    }
    
    public static final void sort(@NotNull final byte[] $this$sort, final int fromIndex, final int toIndex) {
        Intrinsics.checkParameterIsNotNull($this$sort, "$this$sort");
        Arrays.sort($this$sort, fromIndex, toIndex);
    }
    
    public static final void sort(@NotNull final short[] $this$sort, final int fromIndex, final int toIndex) {
        Intrinsics.checkParameterIsNotNull($this$sort, "$this$sort");
        Arrays.sort($this$sort, fromIndex, toIndex);
    }
    
    public static final void sort(@NotNull final int[] $this$sort, final int fromIndex, final int toIndex) {
        Intrinsics.checkParameterIsNotNull($this$sort, "$this$sort");
        Arrays.sort($this$sort, fromIndex, toIndex);
    }
    
    public static final void sort(@NotNull final long[] $this$sort, final int fromIndex, final int toIndex) {
        Intrinsics.checkParameterIsNotNull($this$sort, "$this$sort");
        Arrays.sort($this$sort, fromIndex, toIndex);
    }
    
    public static final void sort(@NotNull final float[] $this$sort, final int fromIndex, final int toIndex) {
        Intrinsics.checkParameterIsNotNull($this$sort, "$this$sort");
        Arrays.sort($this$sort, fromIndex, toIndex);
    }
    
    public static final void sort(@NotNull final double[] $this$sort, final int fromIndex, final int toIndex) {
        Intrinsics.checkParameterIsNotNull($this$sort, "$this$sort");
        Arrays.sort($this$sort, fromIndex, toIndex);
    }
    
    public static final void sort(@NotNull final char[] $this$sort, final int fromIndex, final int toIndex) {
        Intrinsics.checkParameterIsNotNull($this$sort, "$this$sort");
        Arrays.sort($this$sort, fromIndex, toIndex);
    }
    
    public static final <T> void sortWith(@NotNull final T[] $this$sortWith, @NotNull final Comparator<? super T> comparator) {
        Intrinsics.checkParameterIsNotNull($this$sortWith, "$this$sortWith");
        Intrinsics.checkParameterIsNotNull(comparator, "comparator");
        if ($this$sortWith.length > 1) {
            Arrays.sort($this$sortWith, comparator);
        }
    }
    
    public static final <T> void sortWith(@NotNull final T[] $this$sortWith, @NotNull final Comparator<? super T> comparator, final int fromIndex, final int toIndex) {
        Intrinsics.checkParameterIsNotNull($this$sortWith, "$this$sortWith");
        Intrinsics.checkParameterIsNotNull(comparator, "comparator");
        Arrays.sort($this$sortWith, fromIndex, toIndex, comparator);
    }
    
    @NotNull
    public static final Byte[] toTypedArray(@NotNull final byte[] $this$toTypedArray) {
        // 
        // This method could not be decompiled.
        // 
        // Original Bytecode:
        // 
        //     1: ldc_w           "$this$toTypedArray"
        //     4: invokestatic    kotlin/jvm/internal/Intrinsics.checkParameterIsNotNull:(Ljava/lang/Object;Ljava/lang/String;)V
        //     7: aload_0         /* $this$toTypedArray */
        //     8: arraylength    
        //     9: anewarray       Ljava/lang/Byte;
        //    12: astore_1        /* result */
        //    13: iconst_0       
        //    14: istore_2       
        //    15: aload_0         /* $this$toTypedArray */
        //    16: arraylength    
        //    17: istore_3       
        //    18: iload_2        
        //    19: iload_3        
        //    20: if_icmpge       38
        //    23: aload_1         /* result */
        //    24: iload_2         /* index */
        //    25: aload_0         /* $this$toTypedArray */
        //    26: iload_2         /* index */
        //    27: baload         
        //    28: invokestatic    java/lang/Byte.valueOf:(B)Ljava/lang/Byte;
        //    31: aastore        
        //    32: iinc            index, 1
        //    35: goto            18
        //    38: aload_1         /* result */
        //    39: areturn        
        //    StackMapTable: 00 02 FE 00 12 07 03 2C 01 01 13
        // 
        // The error that occurred was:
        // 
        // java.lang.NullPointerException
        // 
        throw new IllegalStateException("An error occurred while decompiling this method.");
    }
    
    @NotNull
    public static final Short[] toTypedArray(@NotNull final short[] $this$toTypedArray) {
        // 
        // This method could not be decompiled.
        // 
        // Original Bytecode:
        // 
        //     1: ldc_w           "$this$toTypedArray"
        //     4: invokestatic    kotlin/jvm/internal/Intrinsics.checkParameterIsNotNull:(Ljava/lang/Object;Ljava/lang/String;)V
        //     7: aload_0         /* $this$toTypedArray */
        //     8: arraylength    
        //     9: anewarray       Ljava/lang/Short;
        //    12: astore_1        /* result */
        //    13: iconst_0       
        //    14: istore_2       
        //    15: aload_0         /* $this$toTypedArray */
        //    16: arraylength    
        //    17: istore_3       
        //    18: iload_2        
        //    19: iload_3        
        //    20: if_icmpge       38
        //    23: aload_1         /* result */
        //    24: iload_2         /* index */
        //    25: aload_0         /* $this$toTypedArray */
        //    26: iload_2         /* index */
        //    27: saload         
        //    28: invokestatic    java/lang/Short.valueOf:(S)Ljava/lang/Short;
        //    31: aastore        
        //    32: iinc            index, 1
        //    35: goto            18
        //    38: aload_1         /* result */
        //    39: areturn        
        //    StackMapTable: 00 02 FE 00 12 07 03 34 01 01 13
        // 
        // The error that occurred was:
        // 
        // java.lang.NullPointerException
        // 
        throw new IllegalStateException("An error occurred while decompiling this method.");
    }
    
    @NotNull
    public static final Integer[] toTypedArray(@NotNull final int[] $this$toTypedArray) {
        // 
        // This method could not be decompiled.
        // 
        // Original Bytecode:
        // 
        //     1: ldc_w           "$this$toTypedArray"
        //     4: invokestatic    kotlin/jvm/internal/Intrinsics.checkParameterIsNotNull:(Ljava/lang/Object;Ljava/lang/String;)V
        //     7: aload_0         /* $this$toTypedArray */
        //     8: arraylength    
        //     9: anewarray       Ljava/lang/Integer;
        //    12: astore_1        /* result */
        //    13: iconst_0       
        //    14: istore_2       
        //    15: aload_0         /* $this$toTypedArray */
        //    16: arraylength    
        //    17: istore_3       
        //    18: iload_2        
        //    19: iload_3        
        //    20: if_icmpge       38
        //    23: aload_1         /* result */
        //    24: iload_2         /* index */
        //    25: aload_0         /* $this$toTypedArray */
        //    26: iload_2         /* index */
        //    27: iaload         
        //    28: invokestatic    java/lang/Integer.valueOf:(I)Ljava/lang/Integer;
        //    31: aastore        
        //    32: iinc            index, 1
        //    35: goto            18
        //    38: aload_1         /* result */
        //    39: areturn        
        //    StackMapTable: 00 02 FE 00 12 07 03 3B 01 01 13
        // 
        // The error that occurred was:
        // 
        // java.lang.NullPointerException
        // 
        throw new IllegalStateException("An error occurred while decompiling this method.");
    }
    
    @NotNull
    public static final Long[] toTypedArray(@NotNull final long[] $this$toTypedArray) {
        // 
        // This method could not be decompiled.
        // 
        // Original Bytecode:
        // 
        //     1: ldc_w           "$this$toTypedArray"
        //     4: invokestatic    kotlin/jvm/internal/Intrinsics.checkParameterIsNotNull:(Ljava/lang/Object;Ljava/lang/String;)V
        //     7: aload_0         /* $this$toTypedArray */
        //     8: arraylength    
        //     9: anewarray       Ljava/lang/Long;
        //    12: astore_1        /* result */
        //    13: iconst_0       
        //    14: istore_2       
        //    15: aload_0         /* $this$toTypedArray */
        //    16: arraylength    
        //    17: istore_3       
        //    18: iload_2        
        //    19: iload_3        
        //    20: if_icmpge       38
        //    23: aload_1         /* result */
        //    24: iload_2         /* index */
        //    25: aload_0         /* $this$toTypedArray */
        //    26: iload_2         /* index */
        //    27: laload         
        //    28: invokestatic    java/lang/Long.valueOf:(J)Ljava/lang/Long;
        //    31: aastore        
        //    32: iinc            index, 1
        //    35: goto            18
        //    38: aload_1         /* result */
        //    39: areturn        
        //    StackMapTable: 00 02 FE 00 12 07 03 42 01 01 13
        // 
        // The error that occurred was:
        // 
        // java.lang.NullPointerException
        // 
        throw new IllegalStateException("An error occurred while decompiling this method.");
    }
    
    @NotNull
    public static final Float[] toTypedArray(@NotNull final float[] $this$toTypedArray) {
        // 
        // This method could not be decompiled.
        // 
        // Original Bytecode:
        // 
        //     1: ldc_w           "$this$toTypedArray"
        //     4: invokestatic    kotlin/jvm/internal/Intrinsics.checkParameterIsNotNull:(Ljava/lang/Object;Ljava/lang/String;)V
        //     7: aload_0         /* $this$toTypedArray */
        //     8: arraylength    
        //     9: anewarray       Ljava/lang/Float;
        //    12: astore_1        /* result */
        //    13: iconst_0       
        //    14: istore_2       
        //    15: aload_0         /* $this$toTypedArray */
        //    16: arraylength    
        //    17: istore_3       
        //    18: iload_2        
        //    19: iload_3        
        //    20: if_icmpge       38
        //    23: aload_1         /* result */
        //    24: iload_2         /* index */
        //    25: aload_0         /* $this$toTypedArray */
        //    26: iload_2         /* index */
        //    27: faload         
        //    28: invokestatic    java/lang/Float.valueOf:(F)Ljava/lang/Float;
        //    31: aastore        
        //    32: iinc            index, 1
        //    35: goto            18
        //    38: aload_1         /* result */
        //    39: areturn        
        //    StackMapTable: 00 02 FE 00 12 07 03 49 01 01 13
        // 
        // The error that occurred was:
        // 
        // java.lang.NullPointerException
        // 
        throw new IllegalStateException("An error occurred while decompiling this method.");
    }
    
    @NotNull
    public static final Double[] toTypedArray(@NotNull final double[] $this$toTypedArray) {
        // 
        // This method could not be decompiled.
        // 
        // Original Bytecode:
        // 
        //     1: ldc_w           "$this$toTypedArray"
        //     4: invokestatic    kotlin/jvm/internal/Intrinsics.checkParameterIsNotNull:(Ljava/lang/Object;Ljava/lang/String;)V
        //     7: aload_0         /* $this$toTypedArray */
        //     8: arraylength    
        //     9: anewarray       Ljava/lang/Double;
        //    12: astore_1        /* result */
        //    13: iconst_0       
        //    14: istore_2       
        //    15: aload_0         /* $this$toTypedArray */
        //    16: arraylength    
        //    17: istore_3       
        //    18: iload_2        
        //    19: iload_3        
        //    20: if_icmpge       38
        //    23: aload_1         /* result */
        //    24: iload_2         /* index */
        //    25: aload_0         /* $this$toTypedArray */
        //    26: iload_2         /* index */
        //    27: daload         
        //    28: invokestatic    java/lang/Double.valueOf:(D)Ljava/lang/Double;
        //    31: aastore        
        //    32: iinc            index, 1
        //    35: goto            18
        //    38: aload_1         /* result */
        //    39: areturn        
        //    StackMapTable: 00 02 FE 00 12 07 03 50 01 01 13
        // 
        // The error that occurred was:
        // 
        // java.lang.NullPointerException
        // 
        throw new IllegalStateException("An error occurred while decompiling this method.");
    }
    
    @NotNull
    public static final Boolean[] toTypedArray(@NotNull final boolean[] $this$toTypedArray) {
        // 
        // This method could not be decompiled.
        // 
        // Original Bytecode:
        // 
        //     1: ldc_w           "$this$toTypedArray"
        //     4: invokestatic    kotlin/jvm/internal/Intrinsics.checkParameterIsNotNull:(Ljava/lang/Object;Ljava/lang/String;)V
        //     7: aload_0         /* $this$toTypedArray */
        //     8: arraylength    
        //     9: anewarray       Ljava/lang/Boolean;
        //    12: astore_1        /* result */
        //    13: iconst_0       
        //    14: istore_2       
        //    15: aload_0         /* $this$toTypedArray */
        //    16: arraylength    
        //    17: istore_3       
        //    18: iload_2        
        //    19: iload_3        
        //    20: if_icmpge       38
        //    23: aload_1         /* result */
        //    24: iload_2         /* index */
        //    25: aload_0         /* $this$toTypedArray */
        //    26: iload_2         /* index */
        //    27: baload         
        //    28: invokestatic    java/lang/Boolean.valueOf:(Z)Ljava/lang/Boolean;
        //    31: aastore        
        //    32: iinc            index, 1
        //    35: goto            18
        //    38: aload_1         /* result */
        //    39: areturn        
        //    StackMapTable: 00 02 FE 00 12 07 03 55 01 01 13
        // 
        // The error that occurred was:
        // 
        // java.lang.NullPointerException
        // 
        throw new IllegalStateException("An error occurred while decompiling this method.");
    }
    
    @NotNull
    public static final Character[] toTypedArray(@NotNull final char[] $this$toTypedArray) {
        // 
        // This method could not be decompiled.
        // 
        // Original Bytecode:
        // 
        //     1: ldc_w           "$this$toTypedArray"
        //     4: invokestatic    kotlin/jvm/internal/Intrinsics.checkParameterIsNotNull:(Ljava/lang/Object;Ljava/lang/String;)V
        //     7: aload_0         /* $this$toTypedArray */
        //     8: arraylength    
        //     9: anewarray       Ljava/lang/Character;
        //    12: astore_1        /* result */
        //    13: iconst_0       
        //    14: istore_2       
        //    15: aload_0         /* $this$toTypedArray */
        //    16: arraylength    
        //    17: istore_3       
        //    18: iload_2        
        //    19: iload_3        
        //    20: if_icmpge       38
        //    23: aload_1         /* result */
        //    24: iload_2         /* index */
        //    25: aload_0         /* $this$toTypedArray */
        //    26: iload_2         /* index */
        //    27: caload         
        //    28: invokestatic    java/lang/Character.valueOf:(C)Ljava/lang/Character;
        //    31: aastore        
        //    32: iinc            index, 1
        //    35: goto            18
        //    38: aload_1         /* result */
        //    39: areturn        
        //    StackMapTable: 00 02 FE 00 12 07 03 5A 01 01 13
        // 
        // The error that occurred was:
        // 
        // java.lang.NullPointerException
        // 
        throw new IllegalStateException("An error occurred while decompiling this method.");
    }
    
    @NotNull
    public static final <T extends Comparable<? super T>> SortedSet<T> toSortedSet(@NotNull final T[] $this$toSortedSet) {
        Intrinsics.checkParameterIsNotNull($this$toSortedSet, "$this$toSortedSet");
        return ArraysKt___ArraysKt.toCollection($this$toSortedSet, new TreeSet<T>());
    }
    
    @NotNull
    public static final SortedSet<Byte> toSortedSet(@NotNull final byte[] $this$toSortedSet) {
        Intrinsics.checkParameterIsNotNull($this$toSortedSet, "$this$toSortedSet");
        return ArraysKt___ArraysKt.toCollection($this$toSortedSet, new TreeSet<Byte>());
    }
    
    @NotNull
    public static final SortedSet<Short> toSortedSet(@NotNull final short[] $this$toSortedSet) {
        Intrinsics.checkParameterIsNotNull($this$toSortedSet, "$this$toSortedSet");
        return ArraysKt___ArraysKt.toCollection($this$toSortedSet, new TreeSet<Short>());
    }
    
    @NotNull
    public static final SortedSet<Integer> toSortedSet(@NotNull final int[] $this$toSortedSet) {
        Intrinsics.checkParameterIsNotNull($this$toSortedSet, "$this$toSortedSet");
        return ArraysKt___ArraysKt.toCollection($this$toSortedSet, new TreeSet<Integer>());
    }
    
    @NotNull
    public static final SortedSet<Long> toSortedSet(@NotNull final long[] $this$toSortedSet) {
        Intrinsics.checkParameterIsNotNull($this$toSortedSet, "$this$toSortedSet");
        return ArraysKt___ArraysKt.toCollection($this$toSortedSet, new TreeSet<Long>());
    }
    
    @NotNull
    public static final SortedSet<Float> toSortedSet(@NotNull final float[] $this$toSortedSet) {
        Intrinsics.checkParameterIsNotNull($this$toSortedSet, "$this$toSortedSet");
        return ArraysKt___ArraysKt.toCollection($this$toSortedSet, new TreeSet<Float>());
    }
    
    @NotNull
    public static final SortedSet<Double> toSortedSet(@NotNull final double[] $this$toSortedSet) {
        Intrinsics.checkParameterIsNotNull($this$toSortedSet, "$this$toSortedSet");
        return ArraysKt___ArraysKt.toCollection($this$toSortedSet, new TreeSet<Double>());
    }
    
    @NotNull
    public static final SortedSet<Boolean> toSortedSet(@NotNull final boolean[] $this$toSortedSet) {
        Intrinsics.checkParameterIsNotNull($this$toSortedSet, "$this$toSortedSet");
        return ArraysKt___ArraysKt.toCollection($this$toSortedSet, new TreeSet<Boolean>());
    }
    
    @NotNull
    public static final SortedSet<Character> toSortedSet(@NotNull final char[] $this$toSortedSet) {
        Intrinsics.checkParameterIsNotNull($this$toSortedSet, "$this$toSortedSet");
        return ArraysKt___ArraysKt.toCollection($this$toSortedSet, new TreeSet<Character>());
    }
    
    @NotNull
    public static final <T> SortedSet<T> toSortedSet(@NotNull final T[] $this$toSortedSet, @NotNull final Comparator<? super T> comparator) {
        Intrinsics.checkParameterIsNotNull($this$toSortedSet, "$this$toSortedSet");
        Intrinsics.checkParameterIsNotNull(comparator, "comparator");
        return ArraysKt___ArraysKt.toCollection($this$toSortedSet, new TreeSet<T>(comparator));
    }
    
    public ArraysKt___ArraysJvmKt() {
    }
}
