// 
// Decompiled by Procyon v0.5.36
// 

package kotlin.collections;

import kotlin.jvm.JvmName;
import kotlin.PublishedApi;
import kotlin.jvm.functions.Function0;
import kotlin.internal.InlineOnly;
import kotlin.SinceKotlin;
import org.jetbrains.annotations.Nullable;
import kotlin.TuplesKt;
import java.util.ArrayList;
import kotlin.jvm.internal.Intrinsics;
import kotlin.Pair;
import java.util.List;
import org.jetbrains.annotations.NotNull;
import kotlin.Metadata;

@Metadata(mv = { 1, 1, 15 }, bv = { 1, 0, 3 }, k = 5, xi = 1, d1 = { "\u0000H\n\u0000\n\u0002\u0010\u000b\n\u0000\n\u0002\u0010\u0011\n\u0002\b\u0004\n\u0002\u0010\u000e\n\u0002\b\u0003\n\u0002\u0010\u0002\n\u0000\n\u0002\u0018\u0002\n\u0002\u0018\u0002\n\u0000\n\u0002\u0010!\n\u0002\b\u0003\n\u0002\u0010 \n\u0002\b\u0005\n\u0002\u0018\u0002\n\u0002\b\u0004\n\u0002\u0018\u0002\n\u0002\b\u0002\u001a1\u0010\u0000\u001a\u00020\u0001\"\u0004\b\u0000\u0010\u0002*\n\u0012\u0006\b\u0001\u0012\u0002H\u00020\u00032\u000e\u0010\u0004\u001a\n\u0012\u0006\b\u0001\u0012\u0002H\u00020\u0003H\u0001¢\u0006\u0004\b\u0005\u0010\u0006\u001a!\u0010\u0007\u001a\u00020\b\"\u0004\b\u0000\u0010\u0002*\n\u0012\u0006\b\u0001\u0012\u0002H\u00020\u0003H\u0001¢\u0006\u0004\b\t\u0010\n\u001a?\u0010\u000b\u001a\u00020\f\"\u0004\b\u0000\u0010\u0002*\n\u0012\u0006\b\u0001\u0012\u0002H\u00020\u00032\n\u0010\r\u001a\u00060\u000ej\u0002`\u000f2\u0010\u0010\u0010\u001a\f\u0012\b\u0012\u0006\u0012\u0002\b\u00030\u00030\u0011H\u0002¢\u0006\u0004\b\u0012\u0010\u0013\u001a+\u0010\u0014\u001a\b\u0012\u0004\u0012\u0002H\u00020\u0015\"\u0004\b\u0000\u0010\u0002*\u0012\u0012\u000e\b\u0001\u0012\n\u0012\u0006\b\u0001\u0012\u0002H\u00020\u00030\u0003¢\u0006\u0002\u0010\u0016\u001a8\u0010\u0017\u001a\u0002H\u0018\"\u0010\b\u0000\u0010\u0019*\u0006\u0012\u0002\b\u00030\u0003*\u0002H\u0018\"\u0004\b\u0001\u0010\u0018*\u0002H\u00192\f\u0010\u001a\u001a\b\u0012\u0004\u0012\u0002H\u00180\u001bH\u0087\b¢\u0006\u0002\u0010\u001c\u001a)\u0010\u001d\u001a\u00020\u0001*\b\u0012\u0002\b\u0003\u0018\u00010\u0003H\u0087\b\u0082\u0002\u000e\n\f\b\u0000\u0012\u0002\u0018\u0001\u001a\u0004\b\u0003\u0010\u0000¢\u0006\u0002\u0010\u001e\u001aG\u0010\u001f\u001a\u001a\u0012\n\u0012\b\u0012\u0004\u0012\u0002H\u00020\u0015\u0012\n\u0012\b\u0012\u0004\u0012\u0002H\u00180\u00150 \"\u0004\b\u0000\u0010\u0002\"\u0004\b\u0001\u0010\u0018*\u0016\u0012\u0012\b\u0001\u0012\u000e\u0012\u0004\u0012\u0002H\u0002\u0012\u0004\u0012\u0002H\u00180 0\u0003¢\u0006\u0002\u0010!¨\u0006\"" }, d2 = { "contentDeepEqualsImpl", "", "T", "", "other", "contentDeepEquals", "([Ljava/lang/Object;[Ljava/lang/Object;)Z", "contentDeepToStringImpl", "", "contentDeepToString", "([Ljava/lang/Object;)Ljava/lang/String;", "contentDeepToStringInternal", "", "result", "Ljava/lang/StringBuilder;", "Lkotlin/text/StringBuilder;", "processed", "", "contentDeepToStringInternal$ArraysKt__ArraysKt", "([Ljava/lang/Object;Ljava/lang/StringBuilder;Ljava/util/List;)V", "flatten", "", "([[Ljava/lang/Object;)Ljava/util/List;", "ifEmpty", "R", "C", "defaultValue", "Lkotlin/Function0;", "([Ljava/lang/Object;Lkotlin/jvm/functions/Function0;)Ljava/lang/Object;", "isNullOrEmpty", "([Ljava/lang/Object;)Z", "unzip", "Lkotlin/Pair;", "([Lkotlin/Pair;)Lkotlin/Pair;", "kotlin-stdlib" }, xs = "kotlin/collections/ArraysKt")
class ArraysKt__ArraysKt extends ArraysKt__ArraysJVMKt
{
    @NotNull
    public static final <T> List<T> flatten(@NotNull final T[][] $this$flatten) {
        // 
        // This method could not be decompiled.
        // 
        // Original Bytecode:
        // 
        //     1: ldc             "$this$flatten"
        //     3: invokestatic    kotlin/jvm/internal/Intrinsics.checkParameterIsNotNull:(Ljava/lang/Object;Ljava/lang/String;)V
        //     6: aload_0         /* $this$flatten */
        //     7: checkcast       [Ljava/lang/Object;
        //    10: astore_2        /* $this$sumBy$iv */
        //    11: iconst_0       
        //    12: istore_3        /* $i$f$sumBy */
        //    13: iconst_0       
        //    14: istore          sum$iv
        //    16: aload_2         /* $this$sumBy$iv */
        //    17: astore          5
        //    19: aload           5
        //    21: arraylength    
        //    22: istore          6
        //    24: iconst_0       
        //    25: istore          7
        //    27: iload           7
        //    29: iload           6
        //    31: if_icmpge       73
        //    34: aload           5
        //    36: iload           7
        //    38: aaload         
        //    39: astore          element$iv
        //    41: iload           sum$iv
        //    43: aload           element$iv
        //    45: checkcast       [Ljava/lang/Object;
        //    48: astore          9
        //    50: istore          13
        //    52: iconst_0       
        //    53: istore          $i$a$-sumBy-ArraysKt__ArraysKt$flatten$result$1
        //    55: aload           it
        //    57: arraylength    
        //    58: istore          14
        //    60: iload           13
        //    62: iload           14
        //    64: iadd           
        //    65: istore          sum$iv
        //    67: iinc            7, 1
        //    70: goto            27
        //    73: iload           sum$iv
        //    75: istore          13
        //    77: iload           13
        //    79: istore          15
        //    81: new             Ljava/util/ArrayList;
        //    84: dup            
        //    85: iload           15
        //    87: invokespecial   java/util/ArrayList.<init>:(I)V
        //    90: astore_1        /* result */
        //    91: aload_0         /* $this$flatten */
        //    92: astore          4
        //    94: aload           4
        //    96: arraylength    
        //    97: istore          5
        //    99: iconst_0       
        //   100: istore_3       
        //   101: iload_3        
        //   102: iload           5
        //   104: if_icmpge       127
        //   107: aload           4
        //   109: iload_3        
        //   110: aaload         
        //   111: astore_2        /* element */
        //   112: aload_1         /* result */
        //   113: checkcast       Ljava/util/Collection;
        //   116: aload_2         /* element */
        //   117: invokestatic    kotlin/collections/CollectionsKt.addAll:(Ljava/util/Collection;[Ljava/lang/Object;)Z
        //   120: pop            
        //   121: iinc            3, 1
        //   124: goto            101
        //   127: aload_1         /* result */
        //   128: checkcast       Ljava/util/List;
        //   131: areturn        
        //    Signature:
        //  <T:Ljava/lang/Object;>([[TT;)Ljava/util/List<TT;>;
        //    StackMapTable: 00 04 FF 00 1B 00 08 07 00 3F 00 07 00 3D 01 01 07 00 3D 01 01 00 00 2D FF 00 1B 00 10 07 00 3F 07 00 41 07 00 3D 01 07 00 3F 01 01 01 00 00 00 00 00 01 00 01 00 00 19
        // 
        // The error that occurred was:
        // 
        // java.lang.NullPointerException
        // 
        throw new IllegalStateException("An error occurred while decompiling this method.");
    }
    
    @NotNull
    public static final <T, R> Pair<List<T>, List<R>> unzip(@NotNull final Pair<? extends T, ? extends R>[] $this$unzip) {
        Intrinsics.checkParameterIsNotNull($this$unzip, "$this$unzip");
        final ArrayList listT = new ArrayList($this$unzip.length);
        final ArrayList listR = new ArrayList($this$unzip.length);
        for (final Pair pair : $this$unzip) {
            listT.add(pair.getFirst());
            listR.add(pair.getSecond());
        }
        return TuplesKt.to((List<T>)listT, (List<R>)listR);
    }
    
    @SinceKotlin(version = "1.3")
    @InlineOnly
    private static final boolean isNullOrEmpty(@Nullable final Object[] $this$isNullOrEmpty) {
        final int $i$f$isNullOrEmpty = 0;
        return $this$isNullOrEmpty == null || $this$isNullOrEmpty.length == 0;
    }
    
    @SinceKotlin(version = "1.3")
    @InlineOnly
    private static final <C extends Object[], R> R ifEmpty(final C $this$ifEmpty, final Function0<? extends R> defaultValue) {
        // 
        // This method could not be decompiled.
        // 
        // Original Bytecode:
        // 
        //     2: istore_2        /* $i$f$ifEmpty */
        //     3: aload_0         /* $this$ifEmpty */
        //     4: astore_3       
        //     5: iconst_0       
        //     6: istore          4
        //     8: aload_3        
        //     9: arraylength    
        //    10: ifne            17
        //    13: iconst_1       
        //    14: goto            18
        //    17: iconst_0       
        //    18: ifeq            30
        //    21: aload_1         /* defaultValue */
        //    22: invokeinterface kotlin/jvm/functions/Function0.invoke:()Ljava/lang/Object;
        //    27: goto            31
        //    30: aload_0         /* $this$ifEmpty */
        //    31: areturn        
        //    Signature:
        //  <C:[Ljava/lang/Object;:TR;R:Ljava/lang/Object;>(TC;Lkotlin/jvm/functions/Function0<+TR;>;)TR;
        //    StackMapTable: 00 04 FE 00 11 01 07 00 3D 01 40 01 0B 40 07 00 81
        // 
        // The error that occurred was:
        // 
        // java.lang.StackOverflowError
        //     at com.strobel.assembler.metadata.MetadataHelper.isSubType(MetadataHelper.java:1283)
        //     at com.strobel.assembler.metadata.MetadataHelper.isSubType(MetadataHelper.java:1283)
        //     at com.strobel.assembler.metadata.MetadataHelper.isSubType(MetadataHelper.java:1283)
        //     at com.strobel.assembler.metadata.MetadataHelper.isSubType(MetadataHelper.java:1283)
        //     at com.strobel.assembler.metadata.MetadataHelper.isSubType(MetadataHelper.java:1283)
        //     at com.strobel.assembler.metadata.MetadataHelper.isSubType(MetadataHelper.java:1283)
        //     at com.strobel.assembler.metadata.MetadataHelper.isSubType(MetadataHelper.java:1283)
        //     at com.strobel.assembler.metadata.MetadataHelper.isSubType(MetadataHelper.java:1283)
        //     at com.strobel.assembler.metadata.MetadataHelper.isSubType(MetadataHelper.java:1283)
        //     at com.strobel.assembler.metadata.MetadataHelper.isSubType(MetadataHelper.java:1283)
        //     at com.strobel.assembler.metadata.MetadataHelper.isSubType(MetadataHelper.java:1283)
        //     at com.strobel.assembler.metadata.MetadataHelper.isSubType(MetadataHelper.java:1283)
        //     at com.strobel.assembler.metadata.MetadataHelper.isSubType(MetadataHelper.java:1283)
        //     at com.strobel.assembler.metadata.MetadataHelper.isSubType(MetadataHelper.java:1283)
        //     at com.strobel.assembler.metadata.MetadataHelper.isSubType(MetadataHelper.java:1283)
        //     at com.strobel.assembler.metadata.MetadataHelper.isSubType(MetadataHelper.java:1283)
        //     at com.strobel.assembler.metadata.MetadataHelper.isSubType(MetadataHelper.java:1283)
        //     at com.strobel.assembler.metadata.MetadataHelper.isSubType(MetadataHelper.java:1283)
        //     at com.strobel.assembler.metadata.MetadataHelper.isSubType(MetadataHelper.java:1283)
        //     at com.strobel.assembler.metadata.MetadataHelper.isSubType(MetadataHelper.java:1283)
        //     at com.strobel.assembler.metadata.MetadataHelper.isSubType(MetadataHelper.java:1283)
        //     at com.strobel.assembler.metadata.MetadataHelper.isSubType(MetadataHelper.java:1283)
        //     at com.strobel.assembler.metadata.MetadataHelper.isSubType(MetadataHelper.java:1283)
        //     at com.strobel.assembler.metadata.MetadataHelper.isSubType(MetadataHelper.java:1283)
        //     at com.strobel.assembler.metadata.MetadataHelper.isSubType(MetadataHelper.java:1283)
        //     at com.strobel.assembler.metadata.MetadataHelper.isSubType(MetadataHelper.java:1283)
        //     at com.strobel.assembler.metadata.MetadataHelper.isSubType(MetadataHelper.java:1283)
        //     at com.strobel.assembler.metadata.MetadataHelper.isSubType(MetadataHelper.java:1283)
        //     at com.strobel.assembler.metadata.MetadataHelper.isSubType(MetadataHelper.java:1283)
        //     at com.strobel.assembler.metadata.MetadataHelper.isSubType(MetadataHelper.java:1283)
        //     at com.strobel.assembler.metadata.MetadataHelper.isSubType(MetadataHelper.java:1283)
        //     at com.strobel.assembler.metadata.MetadataHelper.isSubType(MetadataHelper.java:1283)
        //     at com.strobel.assembler.metadata.MetadataHelper.isSubType(MetadataHelper.java:1283)
        //     at com.strobel.assembler.metadata.MetadataHelper.isSubType(MetadataHelper.java:1283)
        //     at com.strobel.assembler.metadata.MetadataHelper.isSubType(MetadataHelper.java:1283)
        //     at com.strobel.assembler.metadata.MetadataHelper.isSubType(MetadataHelper.java:1283)
        //     at com.strobel.assembler.metadata.MetadataHelper.isSubType(MetadataHelper.java:1283)
        //     at com.strobel.assembler.metadata.MetadataHelper.isSubType(MetadataHelper.java:1283)
        //     at com.strobel.assembler.metadata.MetadataHelper.isSubType(MetadataHelper.java:1283)
        //     at com.strobel.assembler.metadata.MetadataHelper.isSubType(MetadataHelper.java:1283)
        //     at com.strobel.assembler.metadata.MetadataHelper.isSubType(MetadataHelper.java:1283)
        //     at com.strobel.assembler.metadata.MetadataHelper.isSubType(MetadataHelper.java:1283)
        //     at com.strobel.assembler.metadata.MetadataHelper.isSubType(MetadataHelper.java:1283)
        //     at com.strobel.assembler.metadata.MetadataHelper.isSubType(MetadataHelper.java:1283)
        //     at com.strobel.assembler.metadata.MetadataHelper.isSubType(MetadataHelper.java:1283)
        //     at com.strobel.assembler.metadata.MetadataHelper.isSubType(MetadataHelper.java:1283)
        //     at com.strobel.assembler.metadata.MetadataHelper.isSubType(MetadataHelper.java:1283)
        //     at com.strobel.assembler.metadata.MetadataHelper.isSubType(MetadataHelper.java:1283)
        //     at com.strobel.assembler.metadata.MetadataHelper.isSubType(MetadataHelper.java:1283)
        //     at com.strobel.assembler.metadata.MetadataHelper.isSubType(MetadataHelper.java:1283)
        //     at com.strobel.assembler.metadata.MetadataHelper.isSubType(MetadataHelper.java:1283)
        //     at com.strobel.assembler.metadata.MetadataHelper.isSubType(MetadataHelper.java:1283)
        //     at com.strobel.assembler.metadata.MetadataHelper.isSubType(MetadataHelper.java:1283)
        //     at com.strobel.assembler.metadata.MetadataHelper.isSubType(MetadataHelper.java:1283)
        //     at com.strobel.assembler.metadata.MetadataHelper.isSubType(MetadataHelper.java:1283)
        //     at com.strobel.assembler.metadata.MetadataHelper.isSubType(MetadataHelper.java:1283)
        //     at com.strobel.assembler.metadata.MetadataHelper.isSubType(MetadataHelper.java:1283)
        //     at com.strobel.assembler.metadata.MetadataHelper.isSubType(MetadataHelper.java:1283)
        //     at com.strobel.assembler.metadata.MetadataHelper.isSubType(MetadataHelper.java:1283)
        //     at com.strobel.assembler.metadata.MetadataHelper.isSubType(MetadataHelper.java:1283)
        //     at com.strobel.assembler.metadata.MetadataHelper.isSubType(MetadataHelper.java:1283)
        //     at com.strobel.assembler.metadata.MetadataHelper.isSubType(MetadataHelper.java:1283)
        //     at com.strobel.assembler.metadata.MetadataHelper.isSubType(MetadataHelper.java:1283)
        //     at com.strobel.assembler.metadata.MetadataHelper.isSubType(MetadataHelper.java:1283)
        //     at com.strobel.assembler.metadata.MetadataHelper.isSubType(MetadataHelper.java:1283)
        //     at com.strobel.assembler.metadata.MetadataHelper.isSubType(MetadataHelper.java:1283)
        //     at com.strobel.assembler.metadata.MetadataHelper.isSubType(MetadataHelper.java:1283)
        //     at com.strobel.assembler.metadata.MetadataHelper.isSubType(MetadataHelper.java:1283)
        //     at com.strobel.assembler.metadata.MetadataHelper.isSubType(MetadataHelper.java:1283)
        //     at com.strobel.assembler.metadata.MetadataHelper.isSubType(MetadataHelper.java:1283)
        //     at com.strobel.assembler.metadata.MetadataHelper.isSubType(MetadataHelper.java:1283)
        //     at com.strobel.assembler.metadata.MetadataHelper.isSubType(MetadataHelper.java:1283)
        //     at com.strobel.assembler.metadata.MetadataHelper.isSubType(MetadataHelper.java:1283)
        //     at com.strobel.assembler.metadata.MetadataHelper.isSubType(MetadataHelper.java:1283)
        //     at com.strobel.assembler.metadata.MetadataHelper.isSubType(MetadataHelper.java:1283)
        //     at com.strobel.assembler.metadata.MetadataHelper.isSubType(MetadataHelper.java:1283)
        //     at com.strobel.assembler.metadata.MetadataHelper.isSubType(MetadataHelper.java:1283)
        //     at com.strobel.assembler.metadata.MetadataHelper.isSubType(MetadataHelper.java:1283)
        //     at com.strobel.assembler.metadata.MetadataHelper.isSubType(MetadataHelper.java:1283)
        //     at com.strobel.assembler.metadata.MetadataHelper.isSubType(MetadataHelper.java:1283)
        //     at com.strobel.assembler.metadata.MetadataHelper.isSubType(MetadataHelper.java:1283)
        //     at com.strobel.assembler.metadata.MetadataHelper.isSubType(MetadataHelper.java:1283)
        //     at com.strobel.assembler.metadata.MetadataHelper.isSubType(MetadataHelper.java:1283)
        //     at com.strobel.assembler.metadata.MetadataHelper.isSubType(MetadataHelper.java:1283)
        //     at com.strobel.assembler.metadata.MetadataHelper.isSubType(MetadataHelper.java:1283)
        //     at com.strobel.assembler.metadata.MetadataHelper.isSubType(MetadataHelper.java:1283)
        //     at com.strobel.assembler.metadata.MetadataHelper.isSubType(MetadataHelper.java:1283)
        //     at com.strobel.assembler.metadata.MetadataHelper.isSubType(MetadataHelper.java:1283)
        //     at com.strobel.assembler.metadata.MetadataHelper.isSubType(MetadataHelper.java:1283)
        //     at com.strobel.assembler.metadata.MetadataHelper.isSubType(MetadataHelper.java:1283)
        //     at com.strobel.assembler.metadata.MetadataHelper.isSubType(MetadataHelper.java:1283)
        //     at com.strobel.assembler.metadata.MetadataHelper.isSubType(MetadataHelper.java:1283)
        //     at com.strobel.assembler.metadata.MetadataHelper.isSubType(MetadataHelper.java:1283)
        //     at com.strobel.assembler.metadata.MetadataHelper.isSubType(MetadataHelper.java:1283)
        //     at com.strobel.assembler.metadata.MetadataHelper.isSubType(MetadataHelper.java:1283)
        //     at com.strobel.assembler.metadata.MetadataHelper.isSubType(MetadataHelper.java:1283)
        //     at com.strobel.assembler.metadata.MetadataHelper.isSubType(MetadataHelper.java:1283)
        //     at com.strobel.assembler.metadata.MetadataHelper.isSubType(MetadataHelper.java:1283)
        //     at com.strobel.assembler.metadata.MetadataHelper.isSubType(MetadataHelper.java:1283)
        //     at com.strobel.assembler.metadata.MetadataHelper.isSubType(MetadataHelper.java:1283)
        //     at com.strobel.assembler.metadata.MetadataHelper.isSubType(MetadataHelper.java:1283)
        //     at com.strobel.assembler.metadata.MetadataHelper.isSubType(MetadataHelper.java:1283)
        //     at com.strobel.assembler.metadata.MetadataHelper.isSubType(MetadataHelper.java:1283)
        //     at com.strobel.assembler.metadata.MetadataHelper.isSubType(MetadataHelper.java:1283)
        //     at com.strobel.assembler.metadata.MetadataHelper.isSubType(MetadataHelper.java:1283)
        //     at com.strobel.assembler.metadata.MetadataHelper.isSubType(MetadataHelper.java:1283)
        //     at com.strobel.assembler.metadata.MetadataHelper.isSubType(MetadataHelper.java:1283)
        //     at com.strobel.assembler.metadata.MetadataHelper.isSubType(MetadataHelper.java:1283)
        //     at com.strobel.assembler.metadata.MetadataHelper.isSubType(MetadataHelper.java:1283)
        //     at com.strobel.assembler.metadata.MetadataHelper.isSubType(MetadataHelper.java:1283)
        //     at com.strobel.assembler.metadata.MetadataHelper.isSubType(MetadataHelper.java:1283)
        //     at com.strobel.assembler.metadata.MetadataHelper.isSubType(MetadataHelper.java:1283)
        //     at com.strobel.assembler.metadata.MetadataHelper.isSubType(MetadataHelper.java:1283)
        //     at com.strobel.assembler.metadata.MetadataHelper.isSubType(MetadataHelper.java:1283)
        //     at com.strobel.assembler.metadata.MetadataHelper.isSubType(MetadataHelper.java:1283)
        //     at com.strobel.assembler.metadata.MetadataHelper.isSubType(MetadataHelper.java:1283)
        //     at com.strobel.assembler.metadata.MetadataHelper.isSubType(MetadataHelper.java:1283)
        //     at com.strobel.assembler.metadata.MetadataHelper.isSubType(MetadataHelper.java:1283)
        //     at com.strobel.assembler.metadata.MetadataHelper.isSubType(MetadataHelper.java:1283)
        //     at com.strobel.assembler.metadata.MetadataHelper.isSubType(MetadataHelper.java:1283)
        //     at com.strobel.assembler.metadata.MetadataHelper.isSubType(MetadataHelper.java:1283)
        //     at com.strobel.assembler.metadata.MetadataHelper.isSubType(MetadataHelper.java:1283)
        //     at com.strobel.assembler.metadata.MetadataHelper.isSubType(MetadataHelper.java:1283)
        //     at com.strobel.assembler.metadata.MetadataHelper.isSubType(MetadataHelper.java:1283)
        //     at com.strobel.assembler.metadata.MetadataHelper.isSubType(MetadataHelper.java:1283)
        //     at com.strobel.assembler.metadata.MetadataHelper.isSubType(MetadataHelper.java:1283)
        //     at com.strobel.assembler.metadata.MetadataHelper.isSubType(MetadataHelper.java:1283)
        //     at com.strobel.assembler.metadata.MetadataHelper.isSubType(MetadataHelper.java:1283)
        //     at com.strobel.assembler.metadata.MetadataHelper.isSubType(MetadataHelper.java:1283)
        //     at com.strobel.assembler.metadata.MetadataHelper.isSubType(MetadataHelper.java:1283)
        //     at com.strobel.assembler.metadata.MetadataHelper.isSubType(MetadataHelper.java:1283)
        //     at com.strobel.assembler.metadata.MetadataHelper.isSubType(MetadataHelper.java:1283)
        //     at com.strobel.assembler.metadata.MetadataHelper.isSubType(MetadataHelper.java:1283)
        //     at com.strobel.assembler.metadata.MetadataHelper.isSubType(MetadataHelper.java:1283)
        //     at com.strobel.assembler.metadata.MetadataHelper.isSubType(MetadataHelper.java:1283)
        //     at com.strobel.assembler.metadata.MetadataHelper.isSubType(MetadataHelper.java:1283)
        //     at com.strobel.assembler.metadata.MetadataHelper.isSubType(MetadataHelper.java:1283)
        //     at com.strobel.assembler.metadata.MetadataHelper.isSubType(MetadataHelper.java:1283)
        //     at com.strobel.assembler.metadata.MetadataHelper.isSubType(MetadataHelper.java:1283)
        //     at com.strobel.assembler.metadata.MetadataHelper.isSubType(MetadataHelper.java:1283)
        //     at com.strobel.assembler.metadata.MetadataHelper.isSubType(MetadataHelper.java:1283)
        //     at com.strobel.assembler.metadata.MetadataHelper.isSubType(MetadataHelper.java:1283)
        //     at com.strobel.assembler.metadata.MetadataHelper.isSubType(MetadataHelper.java:1283)
        //     at com.strobel.assembler.metadata.MetadataHelper.isSubType(MetadataHelper.java:1283)
        //     at com.strobel.assembler.metadata.MetadataHelper.isSubType(MetadataHelper.java:1283)
        //     at com.strobel.assembler.metadata.MetadataHelper.isSubType(MetadataHelper.java:1283)
        //     at com.strobel.assembler.metadata.MetadataHelper.isSubType(MetadataHelper.java:1283)
        //     at com.strobel.assembler.metadata.MetadataHelper.isSubType(MetadataHelper.java:1283)
        //     at com.strobel.assembler.metadata.MetadataHelper.isSubType(MetadataHelper.java:1283)
        //     at com.strobel.assembler.metadata.MetadataHelper.isSubType(MetadataHelper.java:1283)
        //     at com.strobel.assembler.metadata.MetadataHelper.isSubType(MetadataHelper.java:1283)
        //     at com.strobel.assembler.metadata.MetadataHelper.isSubType(MetadataHelper.java:1283)
        //     at com.strobel.assembler.metadata.MetadataHelper.isSubType(MetadataHelper.java:1283)
        //     at com.strobel.assembler.metadata.MetadataHelper.isSubType(MetadataHelper.java:1283)
        //     at com.strobel.assembler.metadata.MetadataHelper.isSubType(MetadataHelper.java:1283)
        //     at com.strobel.assembler.metadata.MetadataHelper.isSubType(MetadataHelper.java:1283)
        //     at com.strobel.assembler.metadata.MetadataHelper.isSubType(MetadataHelper.java:1283)
        //     at com.strobel.assembler.metadata.MetadataHelper.isSubType(MetadataHelper.java:1283)
        //     at com.strobel.assembler.metadata.MetadataHelper.isSubType(MetadataHelper.java:1283)
        //     at com.strobel.assembler.metadata.MetadataHelper.isSubType(MetadataHelper.java:1283)
        //     at com.strobel.assembler.metadata.MetadataHelper.isSubType(MetadataHelper.java:1283)
        //     at com.strobel.assembler.metadata.MetadataHelper.isSubType(MetadataHelper.java:1283)
        //     at com.strobel.assembler.metadata.MetadataHelper.isSubType(MetadataHelper.java:1283)
        //     at com.strobel.assembler.metadata.MetadataHelper.isSubType(MetadataHelper.java:1283)
        //     at com.strobel.assembler.metadata.MetadataHelper.isSubType(MetadataHelper.java:1283)
        //     at com.strobel.assembler.metadata.MetadataHelper.isSubType(MetadataHelper.java:1283)
        //     at com.strobel.assembler.metadata.MetadataHelper.isSubType(MetadataHelper.java:1283)
        //     at com.strobel.assembler.metadata.MetadataHelper.isSubType(MetadataHelper.java:1283)
        //     at com.strobel.assembler.metadata.MetadataHelper.isSubType(MetadataHelper.java:1283)
        //     at com.strobel.assembler.metadata.MetadataHelper.isSubType(MetadataHelper.java:1283)
        //     at com.strobel.assembler.metadata.MetadataHelper.isSubType(MetadataHelper.java:1283)
        //     at com.strobel.assembler.metadata.MetadataHelper.isSubType(MetadataHelper.java:1283)
        //     at com.strobel.assembler.metadata.MetadataHelper.isSubType(MetadataHelper.java:1283)
        //     at com.strobel.assembler.metadata.MetadataHelper.isSubType(MetadataHelper.java:1283)
        //     at com.strobel.assembler.metadata.MetadataHelper.isSubType(MetadataHelper.java:1283)
        //     at com.strobel.assembler.metadata.MetadataHelper.isSubType(MetadataHelper.java:1283)
        //     at com.strobel.assembler.metadata.MetadataHelper.isSubType(MetadataHelper.java:1283)
        //     at com.strobel.assembler.metadata.MetadataHelper.isSubType(MetadataHelper.java:1283)
        //     at com.strobel.assembler.metadata.MetadataHelper.isSubType(MetadataHelper.java:1283)
        //     at com.strobel.assembler.metadata.MetadataHelper.isSubType(MetadataHelper.java:1283)
        //     at com.strobel.assembler.metadata.MetadataHelper.isSubType(MetadataHelper.java:1283)
        //     at com.strobel.assembler.metadata.MetadataHelper.isSubType(MetadataHelper.java:1283)
        //     at com.strobel.assembler.metadata.MetadataHelper.isSubType(MetadataHelper.java:1283)
        //     at com.strobel.assembler.metadata.MetadataHelper.isSubType(MetadataHelper.java:1283)
        //     at com.strobel.assembler.metadata.MetadataHelper.isSubType(MetadataHelper.java:1283)
        //     at com.strobel.assembler.metadata.MetadataHelper.isSubType(MetadataHelper.java:1283)
        //     at com.strobel.assembler.metadata.MetadataHelper.isSubType(MetadataHelper.java:1283)
        //     at com.strobel.assembler.metadata.MetadataHelper.isSubType(MetadataHelper.java:1283)
        //     at com.strobel.assembler.metadata.MetadataHelper.isSubType(MetadataHelper.java:1283)
        //     at com.strobel.assembler.metadata.MetadataHelper.isSubType(MetadataHelper.java:1283)
        //     at com.strobel.assembler.metadata.MetadataHelper.isSubType(MetadataHelper.java:1283)
        //     at com.strobel.assembler.metadata.MetadataHelper.isSubType(MetadataHelper.java:1283)
        //     at com.strobel.assembler.metadata.MetadataHelper.isSubType(MetadataHelper.java:1283)
        //     at com.strobel.assembler.metadata.MetadataHelper.isSubType(MetadataHelper.java:1283)
        //     at com.strobel.assembler.metadata.MetadataHelper.isSubType(MetadataHelper.java:1283)
        //     at com.strobel.assembler.metadata.MetadataHelper.isSubType(MetadataHelper.java:1283)
        //     at com.strobel.assembler.metadata.MetadataHelper.isSubType(MetadataHelper.java:1283)
        //     at com.strobel.assembler.metadata.MetadataHelper.isSubType(MetadataHelper.java:1283)
        //     at com.strobel.assembler.metadata.MetadataHelper.isSubType(MetadataHelper.java:1283)
        //     at com.strobel.assembler.metadata.MetadataHelper.isSubType(MetadataHelper.java:1283)
        //     at com.strobel.assembler.metadata.MetadataHelper.isSubType(MetadataHelper.java:1283)
        //     at com.strobel.assembler.metadata.MetadataHelper.isSubType(MetadataHelper.java:1283)
        //     at com.strobel.assembler.metadata.MetadataHelper.isSubType(MetadataHelper.java:1283)
        //     at com.strobel.assembler.metadata.MetadataHelper.isSubType(MetadataHelper.java:1283)
        //     at com.strobel.assembler.metadata.MetadataHelper.isSubType(MetadataHelper.java:1283)
        //     at com.strobel.assembler.metadata.MetadataHelper.isSubType(MetadataHelper.java:1283)
        //     at com.strobel.assembler.metadata.MetadataHelper.isSubType(MetadataHelper.java:1283)
        //     at com.strobel.assembler.metadata.MetadataHelper.isSubType(MetadataHelper.java:1283)
        //     at com.strobel.assembler.metadata.MetadataHelper.isSubType(MetadataHelper.java:1283)
        //     at com.strobel.assembler.metadata.MetadataHelper.isSubType(MetadataHelper.java:1283)
        //     at com.strobel.assembler.metadata.MetadataHelper.isSubType(MetadataHelper.java:1283)
        //     at com.strobel.assembler.metadata.MetadataHelper.isSubType(MetadataHelper.java:1283)
        //     at com.strobel.assembler.metadata.MetadataHelper.isSubType(MetadataHelper.java:1283)
        //     at com.strobel.assembler.metadata.MetadataHelper.isSubType(MetadataHelper.java:1283)
        //     at com.strobel.assembler.metadata.MetadataHelper.isSubType(MetadataHelper.java:1283)
        //     at com.strobel.assembler.metadata.MetadataHelper.isSubType(MetadataHelper.java:1283)
        //     at com.strobel.assembler.metadata.MetadataHelper.isSubType(MetadataHelper.java:1283)
        //     at com.strobel.assembler.metadata.MetadataHelper.isSubType(MetadataHelper.java:1283)
        //     at com.strobel.assembler.metadata.MetadataHelper.isSubType(MetadataHelper.java:1283)
        //     at com.strobel.assembler.metadata.MetadataHelper.isSubType(MetadataHelper.java:1283)
        //     at com.strobel.assembler.metadata.MetadataHelper.isSubType(MetadataHelper.java:1283)
        //     at com.strobel.assembler.metadata.MetadataHelper.isSubType(MetadataHelper.java:1283)
        //     at com.strobel.assembler.metadata.MetadataHelper.isSubType(MetadataHelper.java:1283)
        //     at com.strobel.assembler.metadata.MetadataHelper.isSubType(MetadataHelper.java:1283)
        //     at com.strobel.assembler.metadata.MetadataHelper.isSubType(MetadataHelper.java:1283)
        //     at com.strobel.assembler.metadata.MetadataHelper.isSubType(MetadataHelper.java:1283)
        //     at com.strobel.assembler.metadata.MetadataHelper.isSubType(MetadataHelper.java:1283)
        //     at com.strobel.assembler.metadata.MetadataHelper.isSubType(MetadataHelper.java:1283)
        //     at com.strobel.assembler.metadata.MetadataHelper.isSubType(MetadataHelper.java:1283)
        //     at com.strobel.assembler.metadata.MetadataHelper.isSubType(MetadataHelper.java:1283)
        //     at com.strobel.assembler.metadata.MetadataHelper.isSubType(MetadataHelper.java:1283)
        //     at com.strobel.assembler.metadata.MetadataHelper.isSubType(MetadataHelper.java:1283)
        //     at com.strobel.assembler.metadata.MetadataHelper.isSubType(MetadataHelper.java:1283)
        //     at com.strobel.assembler.metadata.MetadataHelper.isSubType(MetadataHelper.java:1283)
        //     at com.strobel.assembler.metadata.MetadataHelper.isSubType(MetadataHelper.java:1283)
        //     at com.strobel.assembler.metadata.MetadataHelper.isSubType(MetadataHelper.java:1283)
        //     at com.strobel.assembler.metadata.MetadataHelper.isSubType(MetadataHelper.java:1283)
        //     at com.strobel.assembler.metadata.MetadataHelper.isSubType(MetadataHelper.java:1283)
        //     at com.strobel.assembler.metadata.MetadataHelper.isSubType(MetadataHelper.java:1283)
        //     at com.strobel.assembler.metadata.MetadataHelper.isSubType(MetadataHelper.java:1283)
        //     at com.strobel.assembler.metadata.MetadataHelper.isSubType(MetadataHelper.java:1283)
        //     at com.strobel.assembler.metadata.MetadataHelper.isSubType(MetadataHelper.java:1283)
        //     at com.strobel.assembler.metadata.MetadataHelper.isSubType(MetadataHelper.java:1283)
        //     at com.strobel.assembler.metadata.MetadataHelper.isSubType(MetadataHelper.java:1283)
        //     at com.strobel.assembler.metadata.MetadataHelper.isSubType(MetadataHelper.java:1283)
        //     at com.strobel.assembler.metadata.MetadataHelper.isSubType(MetadataHelper.java:1283)
        //     at com.strobel.assembler.metadata.MetadataHelper.isSubType(MetadataHelper.java:1283)
        //     at com.strobel.assembler.metadata.MetadataHelper.isSubType(MetadataHelper.java:1283)
        //     at com.strobel.assembler.metadata.MetadataHelper.isSubType(MetadataHelper.java:1283)
        //     at com.strobel.assembler.metadata.MetadataHelper.isSubType(MetadataHelper.java:1283)
        //     at com.strobel.assembler.metadata.MetadataHelper.isSubType(MetadataHelper.java:1283)
        //     at com.strobel.assembler.metadata.MetadataHelper.isSubType(MetadataHelper.java:1283)
        //     at com.strobel.assembler.metadata.MetadataHelper.isSubType(MetadataHelper.java:1283)
        //     at com.strobel.assembler.metadata.MetadataHelper.isSubType(MetadataHelper.java:1283)
        //     at com.strobel.assembler.metadata.MetadataHelper.isSubType(MetadataHelper.java:1283)
        //     at com.strobel.assembler.metadata.MetadataHelper.isSubType(MetadataHelper.java:1283)
        //     at com.strobel.assembler.metadata.MetadataHelper.isSubType(MetadataHelper.java:1283)
        //     at com.strobel.assembler.metadata.MetadataHelper.isSubType(MetadataHelper.java:1283)
        //     at com.strobel.assembler.metadata.MetadataHelper.isSubType(MetadataHelper.java:1283)
        //     at com.strobel.assembler.metadata.MetadataHelper.isSubType(MetadataHelper.java:1283)
        //     at com.strobel.assembler.metadata.MetadataHelper.isSubType(MetadataHelper.java:1283)
        //     at com.strobel.assembler.metadata.MetadataHelper.isSubType(MetadataHelper.java:1283)
        //     at com.strobel.assembler.metadata.MetadataHelper.isSubType(MetadataHelper.java:1283)
        //     at com.strobel.assembler.metadata.MetadataHelper.isSubType(MetadataHelper.java:1283)
        //     at com.strobel.assembler.metadata.MetadataHelper.isSubType(MetadataHelper.java:1283)
        //     at com.strobel.assembler.metadata.MetadataHelper.isSubType(MetadataHelper.java:1283)
        //     at com.strobel.assembler.metadata.MetadataHelper.isSubType(MetadataHelper.java:1283)
        //     at com.strobel.assembler.metadata.MetadataHelper.isSubType(MetadataHelper.java:1283)
        //     at com.strobel.assembler.metadata.MetadataHelper.isSubType(MetadataHelper.java:1283)
        //     at com.strobel.assembler.metadata.MetadataHelper.isSubType(MetadataHelper.java:1283)
        //     at com.strobel.assembler.metadata.MetadataHelper.isSubType(MetadataHelper.java:1283)
        //     at com.strobel.assembler.metadata.MetadataHelper.isSubType(MetadataHelper.java:1283)
        //     at com.strobel.assembler.metadata.MetadataHelper.isSubType(MetadataHelper.java:1283)
        //     at com.strobel.assembler.metadata.MetadataHelper.isSubType(MetadataHelper.java:1283)
        //     at com.strobel.assembler.metadata.MetadataHelper.isSubType(MetadataHelper.java:1283)
        //     at com.strobel.assembler.metadata.MetadataHelper.isSubType(MetadataHelper.java:1283)
        //     at com.strobel.assembler.metadata.MetadataHelper.isSubType(MetadataHelper.java:1283)
        //     at com.strobel.assembler.metadata.MetadataHelper.isSubType(MetadataHelper.java:1283)
        //     at com.strobel.assembler.metadata.MetadataHelper.isSubType(MetadataHelper.java:1283)
        //     at com.strobel.assembler.metadata.MetadataHelper.isSubType(MetadataHelper.java:1283)
        //     at com.strobel.assembler.metadata.MetadataHelper.isSubType(MetadataHelper.java:1283)
        //     at com.strobel.assembler.metadata.MetadataHelper.isSubType(MetadataHelper.java:1283)
        //     at com.strobel.assembler.metadata.MetadataHelper.isSubType(MetadataHelper.java:1283)
        //     at com.strobel.assembler.metadata.MetadataHelper.isSubType(MetadataHelper.java:1283)
        //     at com.strobel.assembler.metadata.MetadataHelper.isSubType(MetadataHelper.java:1283)
        //     at com.strobel.assembler.metadata.MetadataHelper.isSubType(MetadataHelper.java:1283)
        //     at com.strobel.assembler.metadata.MetadataHelper.isSubType(MetadataHelper.java:1283)
        //     at com.strobel.assembler.metadata.MetadataHelper.isSubType(MetadataHelper.java:1283)
        //     at com.strobel.assembler.metadata.MetadataHelper.isSubType(MetadataHelper.java:1283)
        //     at com.strobel.assembler.metadata.MetadataHelper.isSubType(MetadataHelper.java:1283)
        //     at com.strobel.assembler.metadata.MetadataHelper.isSubType(MetadataHelper.java:1283)
        //     at com.strobel.assembler.metadata.MetadataHelper.isSubType(MetadataHelper.java:1283)
        //     at com.strobel.assembler.metadata.MetadataHelper.isSubType(MetadataHelper.java:1283)
        //     at com.strobel.assembler.metadata.MetadataHelper.isSubType(MetadataHelper.java:1283)
        //     at com.strobel.assembler.metadata.MetadataHelper.isSubType(MetadataHelper.java:1283)
        //     at com.strobel.assembler.metadata.MetadataHelper.isSubType(MetadataHelper.java:1283)
        //     at com.strobel.assembler.metadata.MetadataHelper.isSubType(MetadataHelper.java:1283)
        //     at com.strobel.assembler.metadata.MetadataHelper.isSubType(MetadataHelper.java:1283)
        //     at com.strobel.assembler.metadata.MetadataHelper.isSubType(MetadataHelper.java:1283)
        //     at com.strobel.assembler.metadata.MetadataHelper.isSubType(MetadataHelper.java:1283)
        //     at com.strobel.assembler.metadata.MetadataHelper.isSubType(MetadataHelper.java:1283)
        //     at com.strobel.assembler.metadata.MetadataHelper.isSubType(MetadataHelper.java:1283)
        //     at com.strobel.assembler.metadata.MetadataHelper.isSubType(MetadataHelper.java:1283)
        //     at com.strobel.assembler.metadata.MetadataHelper.isSubType(MetadataHelper.java:1283)
        //     at com.strobel.assembler.metadata.MetadataHelper.isSubType(MetadataHelper.java:1283)
        //     at com.strobel.assembler.metadata.MetadataHelper.isSubType(MetadataHelper.java:1283)
        //     at com.strobel.assembler.metadata.MetadataHelper.isSubType(MetadataHelper.java:1283)
        //     at com.strobel.assembler.metadata.MetadataHelper.isSubType(MetadataHelper.java:1283)
        //     at com.strobel.assembler.metadata.MetadataHelper.isSubType(MetadataHelper.java:1283)
        //     at com.strobel.assembler.metadata.MetadataHelper.isSubType(MetadataHelper.java:1283)
        //     at com.strobel.assembler.metadata.MetadataHelper.isSubType(MetadataHelper.java:1283)
        //     at com.strobel.assembler.metadata.MetadataHelper.isSubType(MetadataHelper.java:1283)
        //     at com.strobel.assembler.metadata.MetadataHelper.isSubType(MetadataHelper.java:1283)
        //     at com.strobel.assembler.metadata.MetadataHelper.isSubType(MetadataHelper.java:1283)
        //     at com.strobel.assembler.metadata.MetadataHelper.isSubType(MetadataHelper.java:1283)
        //     at com.strobel.assembler.metadata.MetadataHelper.isSubType(MetadataHelper.java:1283)
        //     at com.strobel.assembler.metadata.MetadataHelper.isSubType(MetadataHelper.java:1283)
        //     at com.strobel.assembler.metadata.MetadataHelper.isSubType(MetadataHelper.java:1283)
        //     at com.strobel.assembler.metadata.MetadataHelper.isSubType(MetadataHelper.java:1283)
        //     at com.strobel.assembler.metadata.MetadataHelper.isSubType(MetadataHelper.java:1283)
        //     at com.strobel.assembler.metadata.MetadataHelper.isSubType(MetadataHelper.java:1283)
        //     at com.strobel.assembler.metadata.MetadataHelper.isSubType(MetadataHelper.java:1283)
        //     at com.strobel.assembler.metadata.MetadataHelper.isSubType(MetadataHelper.java:1283)
        //     at com.strobel.assembler.metadata.MetadataHelper.isSubType(MetadataHelper.java:1283)
        //     at com.strobel.assembler.metadata.MetadataHelper.isSubType(MetadataHelper.java:1283)
        //     at com.strobel.assembler.metadata.MetadataHelper.isSubType(MetadataHelper.java:1283)
        //     at com.strobel.assembler.metadata.MetadataHelper.isSubType(MetadataHelper.java:1283)
        //     at com.strobel.assembler.metadata.MetadataHelper.isSubType(MetadataHelper.java:1283)
        //     at com.strobel.assembler.metadata.MetadataHelper.isSubType(MetadataHelper.java:1283)
        //     at com.strobel.assembler.metadata.MetadataHelper.isSubType(MetadataHelper.java:1283)
        //     at com.strobel.assembler.metadata.MetadataHelper.isSubType(MetadataHelper.java:1283)
        //     at com.strobel.assembler.metadata.MetadataHelper.isSubType(MetadataHelper.java:1283)
        //     at com.strobel.assembler.metadata.MetadataHelper.isSubType(MetadataHelper.java:1283)
        //     at com.strobel.assembler.metadata.MetadataHelper.isSubType(MetadataHelper.java:1283)
        //     at com.strobel.assembler.metadata.MetadataHelper.isSubType(MetadataHelper.java:1283)
        //     at com.strobel.assembler.metadata.MetadataHelper.isSubType(MetadataHelper.java:1283)
        //     at com.strobel.assembler.metadata.MetadataHelper.isSubType(MetadataHelper.java:1283)
        //     at com.strobel.assembler.metadata.MetadataHelper.isSubType(MetadataHelper.java:1283)
        //     at com.strobel.assembler.metadata.MetadataHelper.isSubType(MetadataHelper.java:1283)
        //     at com.strobel.assembler.metadata.MetadataHelper.isSubType(MetadataHelper.java:1283)
        //     at com.strobel.assembler.metadata.MetadataHelper.isSubType(MetadataHelper.java:1283)
        //     at com.strobel.assembler.metadata.MetadataHelper.isSubType(MetadataHelper.java:1283)
        //     at com.strobel.assembler.metadata.MetadataHelper.isSubType(MetadataHelper.java:1283)
        //     at com.strobel.assembler.metadata.MetadataHelper.isSubType(MetadataHelper.java:1283)
        //     at com.strobel.assembler.metadata.MetadataHelper.isSubType(MetadataHelper.java:1283)
        //     at com.strobel.assembler.metadata.MetadataHelper.isSubType(MetadataHelper.java:1283)
        //     at com.strobel.assembler.metadata.MetadataHelper.isSubType(MetadataHelper.java:1283)
        //     at com.strobel.assembler.metadata.MetadataHelper.isSubType(MetadataHelper.java:1283)
        //     at com.strobel.assembler.metadata.MetadataHelper.isSubType(MetadataHelper.java:1283)
        //     at com.strobel.assembler.metadata.MetadataHelper.isSubType(MetadataHelper.java:1283)
        //     at com.strobel.assembler.metadata.MetadataHelper.isSubType(MetadataHelper.java:1283)
        //     at com.strobel.assembler.metadata.MetadataHelper.isSubType(MetadataHelper.java:1283)
        //     at com.strobel.assembler.metadata.MetadataHelper.isSubType(MetadataHelper.java:1283)
        //     at com.strobel.assembler.metadata.MetadataHelper.isSubType(MetadataHelper.java:1283)
        //     at com.strobel.assembler.metadata.MetadataHelper.isSubType(MetadataHelper.java:1283)
        //     at com.strobel.assembler.metadata.MetadataHelper.isSubType(MetadataHelper.java:1283)
        //     at com.strobel.assembler.metadata.MetadataHelper.isSubType(MetadataHelper.java:1283)
        //     at com.strobel.assembler.metadata.MetadataHelper.isSubType(MetadataHelper.java:1283)
        //     at com.strobel.assembler.metadata.MetadataHelper.isSubType(MetadataHelper.java:1283)
        //     at com.strobel.assembler.metadata.MetadataHelper.isSubType(MetadataHelper.java:1283)
        //     at com.strobel.assembler.metadata.MetadataHelper.isSubType(MetadataHelper.java:1283)
        //     at com.strobel.assembler.metadata.MetadataHelper.isSubType(MetadataHelper.java:1283)
        //     at com.strobel.assembler.metadata.MetadataHelper.isSubType(MetadataHelper.java:1283)
        //     at com.strobel.assembler.metadata.MetadataHelper.isSubType(MetadataHelper.java:1283)
        //     at com.strobel.assembler.metadata.MetadataHelper.isSubType(MetadataHelper.java:1283)
        //     at com.strobel.assembler.metadata.MetadataHelper.isSubType(MetadataHelper.java:1283)
        //     at com.strobel.assembler.metadata.MetadataHelper.isSubType(MetadataHelper.java:1283)
        //     at com.strobel.assembler.metadata.MetadataHelper.isSubType(MetadataHelper.java:1283)
        //     at com.strobel.assembler.metadata.MetadataHelper.isSubType(MetadataHelper.java:1283)
        //     at com.strobel.assembler.metadata.MetadataHelper.isSubType(MetadataHelper.java:1283)
        //     at com.strobel.assembler.metadata.MetadataHelper.isSubType(MetadataHelper.java:1283)
        //     at com.strobel.assembler.metadata.MetadataHelper.isSubType(MetadataHelper.java:1283)
        //     at com.strobel.assembler.metadata.MetadataHelper.isSubType(MetadataHelper.java:1283)
        //     at com.strobel.assembler.metadata.MetadataHelper.isSubType(MetadataHelper.java:1283)
        //     at com.strobel.assembler.metadata.MetadataHelper.isSubType(MetadataHelper.java:1283)
        //     at com.strobel.assembler.metadata.MetadataHelper.isSubType(MetadataHelper.java:1283)
        //     at com.strobel.assembler.metadata.MetadataHelper.isSubType(MetadataHelper.java:1283)
        //     at com.strobel.assembler.metadata.MetadataHelper.isSubType(MetadataHelper.java:1283)
        //     at com.strobel.assembler.metadata.MetadataHelper.isSubType(MetadataHelper.java:1283)
        //     at com.strobel.assembler.metadata.MetadataHelper.isSubType(MetadataHelper.java:1283)
        //     at com.strobel.assembler.metadata.MetadataHelper.isSubType(MetadataHelper.java:1283)
        //     at com.strobel.assembler.metadata.MetadataHelper.isSubType(MetadataHelper.java:1283)
        //     at com.strobel.assembler.metadata.MetadataHelper.isSubType(MetadataHelper.java:1283)
        //     at com.strobel.assembler.metadata.MetadataHelper.isSubType(MetadataHelper.java:1283)
        //     at com.strobel.assembler.metadata.MetadataHelper.isSubType(MetadataHelper.java:1283)
        //     at com.strobel.assembler.metadata.MetadataHelper.isSubType(MetadataHelper.java:1283)
        //     at com.strobel.assembler.metadata.MetadataHelper.isSubType(MetadataHelper.java:1283)
        //     at com.strobel.assembler.metadata.MetadataHelper.isSubType(MetadataHelper.java:1283)
        //     at com.strobel.assembler.metadata.MetadataHelper.isSubType(MetadataHelper.java:1283)
        //     at com.strobel.assembler.metadata.MetadataHelper.isSubType(MetadataHelper.java:1283)
        //     at com.strobel.assembler.metadata.MetadataHelper.isSubType(MetadataHelper.java:1283)
        //     at com.strobel.assembler.metadata.MetadataHelper.isSubType(MetadataHelper.java:1283)
        //     at com.strobel.assembler.metadata.MetadataHelper.isSubType(MetadataHelper.java:1283)
        //     at com.strobel.assembler.metadata.MetadataHelper.isSubType(MetadataHelper.java:1283)
        //     at com.strobel.assembler.metadata.MetadataHelper.isSubType(MetadataHelper.java:1283)
        //     at com.strobel.assembler.metadata.MetadataHelper.isSubType(MetadataHelper.java:1283)
        //     at com.strobel.assembler.metadata.MetadataHelper.isSubType(MetadataHelper.java:1283)
        //     at com.strobel.assembler.metadata.MetadataHelper.isSubType(MetadataHelper.java:1283)
        //     at com.strobel.assembler.metadata.MetadataHelper.isSubType(MetadataHelper.java:1283)
        //     at com.strobel.assembler.metadata.MetadataHelper.isSubType(MetadataHelper.java:1283)
        //     at com.strobel.assembler.metadata.MetadataHelper.isSubType(MetadataHelper.java:1283)
        //     at com.strobel.assembler.metadata.MetadataHelper.isSubType(MetadataHelper.java:1283)
        //     at com.strobel.assembler.metadata.MetadataHelper.isSubType(MetadataHelper.java:1283)
        //     at com.strobel.assembler.metadata.MetadataHelper.isSubType(MetadataHelper.java:1283)
        //     at com.strobel.assembler.metadata.MetadataHelper.isSubType(MetadataHelper.java:1283)
        //     at com.strobel.assembler.metadata.MetadataHelper.isSubType(MetadataHelper.java:1283)
        //     at com.strobel.assembler.metadata.MetadataHelper.isSubType(MetadataHelper.java:1283)
        //     at com.strobel.assembler.metadata.MetadataHelper.isSubType(MetadataHelper.java:1283)
        //     at com.strobel.assembler.metadata.MetadataHelper.isSubType(MetadataHelper.java:1283)
        //     at com.strobel.assembler.metadata.MetadataHelper.isSubType(MetadataHelper.java:1283)
        //     at com.strobel.assembler.metadata.MetadataHelper.isSubType(MetadataHelper.java:1283)
        //     at com.strobel.assembler.metadata.MetadataHelper.isSubType(MetadataHelper.java:1283)
        //     at com.strobel.assembler.metadata.MetadataHelper.isSubType(MetadataHelper.java:1283)
        //     at com.strobel.assembler.metadata.MetadataHelper.isSubType(MetadataHelper.java:1283)
        //     at com.strobel.assembler.metadata.MetadataHelper.isSubType(MetadataHelper.java:1283)
        //     at com.strobel.assembler.metadata.MetadataHelper.isSubType(MetadataHelper.java:1283)
        //     at com.strobel.assembler.metadata.MetadataHelper.isSubType(MetadataHelper.java:1283)
        //     at com.strobel.assembler.metadata.MetadataHelper.isSubType(MetadataHelper.java:1283)
        //     at com.strobel.assembler.metadata.MetadataHelper.isSubType(MetadataHelper.java:1283)
        //     at com.strobel.assembler.metadata.MetadataHelper.isSubType(MetadataHelper.java:1283)
        //     at com.strobel.assembler.metadata.MetadataHelper.isSubType(MetadataHelper.java:1283)
        //     at com.strobel.assembler.metadata.MetadataHelper.isSubType(MetadataHelper.java:1283)
        //     at com.strobel.assembler.metadata.MetadataHelper.isSubType(MetadataHelper.java:1283)
        //     at com.strobel.assembler.metadata.MetadataHelper.isSubType(MetadataHelper.java:1283)
        //     at com.strobel.assembler.metadata.MetadataHelper.isSubType(MetadataHelper.java:1283)
        //     at com.strobel.assembler.metadata.MetadataHelper.isSubType(MetadataHelper.java:1283)
        //     at com.strobel.assembler.metadata.MetadataHelper.isSubType(MetadataHelper.java:1283)
        //     at com.strobel.assembler.metadata.MetadataHelper.isSubType(MetadataHelper.java:1283)
        //     at com.strobel.assembler.metadata.MetadataHelper.isSubType(MetadataHelper.java:1283)
        //     at com.strobel.assembler.metadata.MetadataHelper.isSubType(MetadataHelper.java:1283)
        //     at com.strobel.assembler.metadata.MetadataHelper.isSubType(MetadataHelper.java:1283)
        //     at com.strobel.assembler.metadata.MetadataHelper.isSubType(MetadataHelper.java:1283)
        //     at com.strobel.assembler.metadata.MetadataHelper.isSubType(MetadataHelper.java:1283)
        //     at com.strobel.assembler.metadata.MetadataHelper.isSubType(MetadataHelper.java:1283)
        //     at com.strobel.assembler.metadata.MetadataHelper.isSubType(MetadataHelper.java:1283)
        //     at com.strobel.assembler.metadata.MetadataHelper.isSubType(MetadataHelper.java:1283)
        //     at com.strobel.assembler.metadata.MetadataHelper.isSubType(MetadataHelper.java:1283)
        //     at com.strobel.assembler.metadata.MetadataHelper.isSubType(MetadataHelper.java:1283)
        //     at com.strobel.assembler.metadata.MetadataHelper.isSubType(MetadataHelper.java:1283)
        //     at com.strobel.assembler.metadata.MetadataHelper.isSubType(MetadataHelper.java:1283)
        //     at com.strobel.assembler.metadata.MetadataHelper.isSubType(MetadataHelper.java:1283)
        //     at com.strobel.assembler.metadata.MetadataHelper.isSubType(MetadataHelper.java:1283)
        //     at com.strobel.assembler.metadata.MetadataHelper.isSubType(MetadataHelper.java:1283)
        //     at com.strobel.assembler.metadata.MetadataHelper.isSubType(MetadataHelper.java:1283)
        //     at com.strobel.assembler.metadata.MetadataHelper.isSubType(MetadataHelper.java:1283)
        //     at com.strobel.assembler.metadata.MetadataHelper.isSubType(MetadataHelper.java:1283)
        //     at com.strobel.assembler.metadata.MetadataHelper.isSubType(MetadataHelper.java:1283)
        //     at com.strobel.assembler.metadata.MetadataHelper.isSubType(MetadataHelper.java:1283)
        //     at com.strobel.assembler.metadata.MetadataHelper.isSubType(MetadataHelper.java:1283)
        //     at com.strobel.assembler.metadata.MetadataHelper.isSubType(MetadataHelper.java:1283)
        //     at com.strobel.assembler.metadata.MetadataHelper.isSubType(MetadataHelper.java:1283)
        //     at com.strobel.assembler.metadata.MetadataHelper.isSubType(MetadataHelper.java:1283)
        //     at com.strobel.assembler.metadata.MetadataHelper.isSubType(MetadataHelper.java:1283)
        //     at com.strobel.assembler.metadata.MetadataHelper.isSubType(MetadataHelper.java:1283)
        //     at com.strobel.assembler.metadata.MetadataHelper.isSubType(MetadataHelper.java:1283)
        //     at com.strobel.assembler.metadata.MetadataHelper.isSubType(MetadataHelper.java:1283)
        //     at com.strobel.assembler.metadata.MetadataHelper.isSubType(MetadataHelper.java:1283)
        //     at com.strobel.assembler.metadata.MetadataHelper.isSubType(MetadataHelper.java:1283)
        //     at com.strobel.assembler.metadata.MetadataHelper.isSubType(MetadataHelper.java:1283)
        //     at com.strobel.assembler.metadata.MetadataHelper.isSubType(MetadataHelper.java:1283)
        //     at com.strobel.assembler.metadata.MetadataHelper.isSubType(MetadataHelper.java:1283)
        //     at com.strobel.assembler.metadata.MetadataHelper.isSubType(MetadataHelper.java:1283)
        //     at com.strobel.assembler.metadata.MetadataHelper.isSubType(MetadataHelper.java:1283)
        //     at com.strobel.assembler.metadata.MetadataHelper.isSubType(MetadataHelper.java:1283)
        //     at com.strobel.assembler.metadata.MetadataHelper.isSubType(MetadataHelper.java:1283)
        //     at com.strobel.assembler.metadata.MetadataHelper.isSubType(MetadataHelper.java:1283)
        //     at com.strobel.assembler.metadata.MetadataHelper.isSubType(MetadataHelper.java:1283)
        //     at com.strobel.assembler.metadata.MetadataHelper.isSubType(MetadataHelper.java:1283)
        //     at com.strobel.assembler.metadata.MetadataHelper.isSubType(MetadataHelper.java:1283)
        //     at com.strobel.assembler.metadata.MetadataHelper.isSubType(MetadataHelper.java:1283)
        //     at com.strobel.assembler.metadata.MetadataHelper.isSubType(MetadataHelper.java:1283)
        //     at com.strobel.assembler.metadata.MetadataHelper.isSubType(MetadataHelper.java:1283)
        //     at com.strobel.assembler.metadata.MetadataHelper.isSubType(MetadataHelper.java:1283)
        //     at com.strobel.assembler.metadata.MetadataHelper.isSubType(MetadataHelper.java:1283)
        //     at com.strobel.assembler.metadata.MetadataHelper.isSubType(MetadataHelper.java:1283)
        //     at com.strobel.assembler.metadata.MetadataHelper.isSubType(MetadataHelper.java:1283)
        //     at com.strobel.assembler.metadata.MetadataHelper.isSubType(MetadataHelper.java:1283)
        //     at com.strobel.assembler.metadata.MetadataHelper.isSubType(MetadataHelper.java:1283)
        //     at com.strobel.assembler.metadata.MetadataHelper.isSubType(MetadataHelper.java:1283)
        //     at com.strobel.assembler.metadata.MetadataHelper.isSubType(MetadataHelper.java:1283)
        //     at com.strobel.assembler.metadata.MetadataHelper.isSubType(MetadataHelper.java:1283)
        //     at com.strobel.assembler.metadata.MetadataHelper.isSubType(MetadataHelper.java:1283)
        //     at com.strobel.assembler.metadata.MetadataHelper.isSubType(MetadataHelper.java:1283)
        //     at com.strobel.assembler.metadata.MetadataHelper.isSubType(MetadataHelper.java:1283)
        //     at com.strobel.assembler.metadata.MetadataHelper.isSubType(MetadataHelper.java:1283)
        //     at com.strobel.assembler.metadata.MetadataHelper.isSubType(MetadataHelper.java:1283)
        //     at com.strobel.assembler.metadata.MetadataHelper.isSubType(MetadataHelper.java:1283)
        //     at com.strobel.assembler.metadata.MetadataHelper.isSubType(MetadataHelper.java:1283)
        //     at com.strobel.assembler.metadata.MetadataHelper.isSubType(MetadataHelper.java:1283)
        //     at com.strobel.assembler.metadata.MetadataHelper.isSubType(MetadataHelper.java:1283)
        //     at com.strobel.assembler.metadata.MetadataHelper.isSubType(MetadataHelper.java:1283)
        //     at com.strobel.assembler.metadata.MetadataHelper.isSubType(MetadataHelper.java:1283)
        //     at com.strobel.assembler.metadata.MetadataHelper.isSubType(MetadataHelper.java:1283)
        //     at com.strobel.assembler.metadata.MetadataHelper.isSubType(MetadataHelper.java:1283)
        //     at com.strobel.assembler.metadata.MetadataHelper.isSubType(MetadataHelper.java:1283)
        //     at com.strobel.assembler.metadata.MetadataHelper.isSubType(MetadataHelper.java:1283)
        //     at com.strobel.assembler.metadata.MetadataHelper.isSubType(MetadataHelper.java:1283)
        //     at com.strobel.assembler.metadata.MetadataHelper.isSubType(MetadataHelper.java:1283)
        //     at com.strobel.assembler.metadata.MetadataHelper.isSubType(MetadataHelper.java:1283)
        //     at com.strobel.assembler.metadata.MetadataHelper.isSubType(MetadataHelper.java:1283)
        //     at com.strobel.assembler.metadata.MetadataHelper.isSubType(MetadataHelper.java:1283)
        //     at com.strobel.assembler.metadata.MetadataHelper.isSubType(MetadataHelper.java:1283)
        //     at com.strobel.assembler.metadata.MetadataHelper.isSubType(MetadataHelper.java:1283)
        //     at com.strobel.assembler.metadata.MetadataHelper.isSubType(MetadataHelper.java:1283)
        //     at com.strobel.assembler.metadata.MetadataHelper.isSubType(MetadataHelper.java:1283)
        //     at com.strobel.assembler.metadata.MetadataHelper.isSubType(MetadataHelper.java:1283)
        //     at com.strobel.assembler.metadata.MetadataHelper.isSubType(MetadataHelper.java:1283)
        //     at com.strobel.assembler.metadata.MetadataHelper.isSubType(MetadataHelper.java:1283)
        //     at com.strobel.assembler.metadata.MetadataHelper.isSubType(MetadataHelper.java:1283)
        //     at com.strobel.assembler.metadata.MetadataHelper.isSubType(MetadataHelper.java:1283)
        //     at com.strobel.assembler.metadata.MetadataHelper.isSubType(MetadataHelper.java:1283)
        //     at com.strobel.assembler.metadata.MetadataHelper.isSubType(MetadataHelper.java:1283)
        //     at com.strobel.assembler.metadata.MetadataHelper.isSubType(MetadataHelper.java:1283)
        //     at com.strobel.assembler.metadata.MetadataHelper.isSubType(MetadataHelper.java:1283)
        //     at com.strobel.assembler.metadata.MetadataHelper.isSubType(MetadataHelper.java:1283)
        //     at com.strobel.assembler.metadata.MetadataHelper.isSubType(MetadataHelper.java:1283)
        //     at com.strobel.assembler.metadata.MetadataHelper.isSubType(MetadataHelper.java:1283)
        //     at com.strobel.assembler.metadata.MetadataHelper.isSubType(MetadataHelper.java:1283)
        //     at com.strobel.assembler.metadata.MetadataHelper.isSubType(MetadataHelper.java:1283)
        //     at com.strobel.assembler.metadata.MetadataHelper.isSubType(MetadataHelper.java:1283)
        //     at com.strobel.assembler.metadata.MetadataHelper.isSubType(MetadataHelper.java:1283)
        //     at com.strobel.assembler.metadata.MetadataHelper.isSubType(MetadataHelper.java:1283)
        //     at com.strobel.assembler.metadata.MetadataHelper.isSubType(MetadataHelper.java:1283)
        //     at com.strobel.assembler.metadata.MetadataHelper.isSubType(MetadataHelper.java:1283)
        //     at com.strobel.assembler.metadata.MetadataHelper.isSubType(MetadataHelper.java:1283)
        //     at com.strobel.assembler.metadata.MetadataHelper.isSubType(MetadataHelper.java:1283)
        //     at com.strobel.assembler.metadata.MetadataHelper.isSubType(MetadataHelper.java:1283)
        //     at com.strobel.assembler.metadata.MetadataHelper.isSubType(MetadataHelper.java:1283)
        //     at com.strobel.assembler.metadata.MetadataHelper.isSubType(MetadataHelper.java:1283)
        //     at com.strobel.assembler.metadata.MetadataHelper.isSubType(MetadataHelper.java:1283)
        //     at com.strobel.assembler.metadata.MetadataHelper.isSubType(MetadataHelper.java:1283)
        //     at com.strobel.assembler.metadata.MetadataHelper.isSubType(MetadataHelper.java:1283)
        //     at com.strobel.assembler.metadata.MetadataHelper.isSubType(MetadataHelper.java:1283)
        //     at com.strobel.assembler.metadata.MetadataHelper.isSubType(MetadataHelper.java:1283)
        //     at com.strobel.assembler.metadata.MetadataHelper.isSubType(MetadataHelper.java:1283)
        //     at com.strobel.assembler.metadata.MetadataHelper.isSubType(MetadataHelper.java:1283)
        //     at com.strobel.assembler.metadata.MetadataHelper.isSubType(MetadataHelper.java:1283)
        //     at com.strobel.assembler.metadata.MetadataHelper.isSubType(MetadataHelper.java:1283)
        //     at com.strobel.assembler.metadata.MetadataHelper.isSubType(MetadataHelper.java:1283)
        //     at com.strobel.assembler.metadata.MetadataHelper.isSubType(MetadataHelper.java:1283)
        //     at com.strobel.assembler.metadata.MetadataHelper.isSubType(MetadataHelper.java:1283)
        //     at com.strobel.assembler.metadata.MetadataHelper.isSubType(MetadataHelper.java:1283)
        //     at com.strobel.assembler.metadata.MetadataHelper.isSubType(MetadataHelper.java:1283)
        //     at com.strobel.assembler.metadata.MetadataHelper.isSubType(MetadataHelper.java:1283)
        //     at com.strobel.assembler.metadata.MetadataHelper.isSubType(MetadataHelper.java:1283)
        //     at com.strobel.assembler.metadata.MetadataHelper.isSubType(MetadataHelper.java:1283)
        //     at com.strobel.assembler.metadata.MetadataHelper.isSubType(MetadataHelper.java:1283)
        //     at com.strobel.assembler.metadata.MetadataHelper.isSubType(MetadataHelper.java:1283)
        //     at com.strobel.assembler.metadata.MetadataHelper.isSubType(MetadataHelper.java:1283)
        //     at com.strobel.assembler.metadata.MetadataHelper.isSubType(MetadataHelper.java:1283)
        //     at com.strobel.assembler.metadata.MetadataHelper.isSubType(MetadataHelper.java:1283)
        //     at com.strobel.assembler.metadata.MetadataHelper.isSubType(MetadataHelper.java:1283)
        //     at com.strobel.assembler.metadata.MetadataHelper.isSubType(MetadataHelper.java:1283)
        //     at com.strobel.assembler.metadata.MetadataHelper.isSubType(MetadataHelper.java:1283)
        //     at com.strobel.assembler.metadata.MetadataHelper.isSubType(MetadataHelper.java:1283)
        //     at com.strobel.assembler.metadata.MetadataHelper.isSubType(MetadataHelper.java:1283)
        //     at com.strobel.assembler.metadata.MetadataHelper.isSubType(MetadataHelper.java:1283)
        //     at com.strobel.assembler.metadata.MetadataHelper.isSubType(MetadataHelper.java:1283)
        //     at com.strobel.assembler.metadata.MetadataHelper.isSubType(MetadataHelper.java:1283)
        //     at com.strobel.assembler.metadata.MetadataHelper.isSubType(MetadataHelper.java:1283)
        //     at com.strobel.assembler.metadata.MetadataHelper.isSubType(MetadataHelper.java:1283)
        //     at com.strobel.assembler.metadata.MetadataHelper.isSubType(MetadataHelper.java:1283)
        //     at com.strobel.assembler.metadata.MetadataHelper.isSubType(MetadataHelper.java:1283)
        //     at com.strobel.assembler.metadata.MetadataHelper.isSubType(MetadataHelper.java:1283)
        //     at com.strobel.assembler.metadata.MetadataHelper.isSubType(MetadataHelper.java:1283)
        //     at com.strobel.assembler.metadata.MetadataHelper.isSubType(MetadataHelper.java:1283)
        //     at com.strobel.assembler.metadata.MetadataHelper.isSubType(MetadataHelper.java:1283)
        //     at com.strobel.assembler.metadata.MetadataHelper.isSubType(MetadataHelper.java:1283)
        //     at com.strobel.assembler.metadata.MetadataHelper.isSubType(MetadataHelper.java:1283)
        //     at com.strobel.assembler.metadata.MetadataHelper.isSubType(MetadataHelper.java:1283)
        //     at com.strobel.assembler.metadata.MetadataHelper.isSubType(MetadataHelper.java:1283)
        //     at com.strobel.assembler.metadata.MetadataHelper.isSubType(MetadataHelper.java:1283)
        //     at com.strobel.assembler.metadata.MetadataHelper.isSubType(MetadataHelper.java:1283)
        //     at com.strobel.assembler.metadata.MetadataHelper.isSubType(MetadataHelper.java:1283)
        //     at com.strobel.assembler.metadata.MetadataHelper.isSubType(MetadataHelper.java:1283)
        //     at com.strobel.assembler.metadata.MetadataHelper.isSubType(MetadataHelper.java:1283)
        //     at com.strobel.assembler.metadata.MetadataHelper.isSubType(MetadataHelper.java:1283)
        //     at com.strobel.assembler.metadata.MetadataHelper.isSubType(MetadataHelper.java:1283)
        //     at com.strobel.assembler.metadata.MetadataHelper.isSubType(MetadataHelper.java:1283)
        //     at com.strobel.assembler.metadata.MetadataHelper.isSubType(MetadataHelper.java:1283)
        //     at com.strobel.assembler.metadata.MetadataHelper.isSubType(MetadataHelper.java:1283)
        //     at com.strobel.assembler.metadata.MetadataHelper.isSubType(MetadataHelper.java:1283)
        //     at com.strobel.assembler.metadata.MetadataHelper.isSubType(MetadataHelper.java:1283)
        //     at com.strobel.assembler.metadata.MetadataHelper.isSubType(MetadataHelper.java:1283)
        //     at com.strobel.assembler.metadata.MetadataHelper.isSubType(MetadataHelper.java:1283)
        //     at com.strobel.assembler.metadata.MetadataHelper.isSubType(MetadataHelper.java:1283)
        //     at com.strobel.assembler.metadata.MetadataHelper.isSubType(MetadataHelper.java:1283)
        //     at com.strobel.assembler.metadata.MetadataHelper.isSubType(MetadataHelper.java:1283)
        //     at com.strobel.assembler.metadata.MetadataHelper.isSubType(MetadataHelper.java:1283)
        //     at com.strobel.assembler.metadata.MetadataHelper.isSubType(MetadataHelper.java:1283)
        //     at com.strobel.assembler.metadata.MetadataHelper.isSubType(MetadataHelper.java:1283)
        //     at com.strobel.assembler.metadata.MetadataHelper.isSubType(MetadataHelper.java:1283)
        //     at com.strobel.assembler.metadata.MetadataHelper.isSubType(MetadataHelper.java:1283)
        //     at com.strobel.assembler.metadata.MetadataHelper.isSubType(MetadataHelper.java:1283)
        //     at com.strobel.assembler.metadata.MetadataHelper.isSubType(MetadataHelper.java:1283)
        //     at com.strobel.assembler.metadata.MetadataHelper.isSubType(MetadataHelper.java:1283)
        //     at com.strobel.assembler.metadata.MetadataHelper.isSubType(MetadataHelper.java:1283)
        //     at com.strobel.assembler.metadata.MetadataHelper.isSubType(MetadataHelper.java:1283)
        //     at com.strobel.assembler.metadata.MetadataHelper.isSubType(MetadataHelper.java:1283)
        //     at com.strobel.assembler.metadata.MetadataHelper.isSubType(MetadataHelper.java:1283)
        //     at com.strobel.assembler.metadata.MetadataHelper.isSubType(MetadataHelper.java:1283)
        //     at com.strobel.assembler.metadata.MetadataHelper.isSubType(MetadataHelper.java:1283)
        //     at com.strobel.assembler.metadata.MetadataHelper.isSubType(MetadataHelper.java:1283)
        //     at com.strobel.assembler.metadata.MetadataHelper.isSubType(MetadataHelper.java:1283)
        //     at com.strobel.assembler.metadata.MetadataHelper.isSubType(MetadataHelper.java:1283)
        //     at com.strobel.assembler.metadata.MetadataHelper.isSubType(MetadataHelper.java:1283)
        //     at com.strobel.assembler.metadata.MetadataHelper.isSubType(MetadataHelper.java:1283)
        //     at com.strobel.assembler.metadata.MetadataHelper.isSubType(MetadataHelper.java:1283)
        //     at com.strobel.assembler.metadata.MetadataHelper.isSubType(MetadataHelper.java:1283)
        //     at com.strobel.assembler.metadata.MetadataHelper.isSubType(MetadataHelper.java:1283)
        //     at com.strobel.assembler.metadata.MetadataHelper.isSubType(MetadataHelper.java:1283)
        //     at com.strobel.assembler.metadata.MetadataHelper.isSubType(MetadataHelper.java:1283)
        //     at com.strobel.assembler.metadata.MetadataHelper.isSubType(MetadataHelper.java:1283)
        //     at com.strobel.assembler.metadata.MetadataHelper.isSubType(MetadataHelper.java:1283)
        //     at com.strobel.assembler.metadata.MetadataHelper.isSubType(MetadataHelper.java:1283)
        //     at com.strobel.assembler.metadata.MetadataHelper.isSubType(MetadataHelper.java:1283)
        //     at com.strobel.assembler.metadata.MetadataHelper.isSubType(MetadataHelper.java:1283)
        //     at com.strobel.assembler.metadata.MetadataHelper.isSubType(MetadataHelper.java:1283)
        //     at com.strobel.assembler.metadata.MetadataHelper.isSubType(MetadataHelper.java:1283)
        //     at com.strobel.assembler.metadata.MetadataHelper.isSubType(MetadataHelper.java:1283)
        //     at com.strobel.assembler.metadata.MetadataHelper.isSubType(MetadataHelper.java:1283)
        //     at com.strobel.assembler.metadata.MetadataHelper.isSubType(MetadataHelper.java:1283)
        //     at com.strobel.assembler.metadata.MetadataHelper.isSubType(MetadataHelper.java:1283)
        //     at com.strobel.assembler.metadata.MetadataHelper.isSubType(MetadataHelper.java:1283)
        //     at com.strobel.assembler.metadata.MetadataHelper.isSubType(MetadataHelper.java:1283)
        //     at com.strobel.assembler.metadata.MetadataHelper.isSubType(MetadataHelper.java:1283)
        //     at com.strobel.assembler.metadata.MetadataHelper.isSubType(MetadataHelper.java:1283)
        //     at com.strobel.assembler.metadata.MetadataHelper.isSubType(MetadataHelper.java:1283)
        //     at com.strobel.assembler.metadata.MetadataHelper.isSubType(MetadataHelper.java:1283)
        //     at com.strobel.assembler.metadata.MetadataHelper.isSubType(MetadataHelper.java:1283)
        //     at com.strobel.assembler.metadata.MetadataHelper.isSubType(MetadataHelper.java:1283)
        //     at com.strobel.assembler.metadata.MetadataHelper.isSubType(MetadataHelper.java:1283)
        //     at com.strobel.assembler.metadata.MetadataHelper.isSubType(MetadataHelper.java:1283)
        //     at com.strobel.assembler.metadata.MetadataHelper.isSubType(MetadataHelper.java:1283)
        //     at com.strobel.assembler.metadata.MetadataHelper.isSubType(MetadataHelper.java:1283)
        //     at com.strobel.assembler.metadata.MetadataHelper.isSubType(MetadataHelper.java:1283)
        //     at com.strobel.assembler.metadata.MetadataHelper.isSubType(MetadataHelper.java:1283)
        //     at com.strobel.assembler.metadata.MetadataHelper.isSubType(MetadataHelper.java:1283)
        //     at com.strobel.assembler.metadata.MetadataHelper.isSubType(MetadataHelper.java:1283)
        //     at com.strobel.assembler.metadata.MetadataHelper.isSubType(MetadataHelper.java:1283)
        //     at com.strobel.assembler.metadata.MetadataHelper.isSubType(MetadataHelper.java:1283)
        //     at com.strobel.assembler.metadata.MetadataHelper.isSubType(MetadataHelper.java:1283)
        //     at com.strobel.assembler.metadata.MetadataHelper.isSubType(MetadataHelper.java:1283)
        //     at com.strobel.assembler.metadata.MetadataHelper.isSubType(MetadataHelper.java:1283)
        //     at com.strobel.assembler.metadata.MetadataHelper.isSubType(MetadataHelper.java:1283)
        //     at com.strobel.assembler.metadata.MetadataHelper.isSubType(MetadataHelper.java:1283)
        //     at com.strobel.assembler.metadata.MetadataHelper.isSubType(MetadataHelper.java:1283)
        //     at com.strobel.assembler.metadata.MetadataHelper.isSubType(MetadataHelper.java:1283)
        //     at com.strobel.assembler.metadata.MetadataHelper.isSubType(MetadataHelper.java:1283)
        //     at com.strobel.assembler.metadata.MetadataHelper.isSubType(MetadataHelper.java:1283)
        //     at com.strobel.assembler.metadata.MetadataHelper.isSubType(MetadataHelper.java:1283)
        //     at com.strobel.assembler.metadata.MetadataHelper.isSubType(MetadataHelper.java:1283)
        //     at com.strobel.assembler.metadata.MetadataHelper.isSubType(MetadataHelper.java:1283)
        //     at com.strobel.assembler.metadata.MetadataHelper.isSubType(MetadataHelper.java:1283)
        //     at com.strobel.assembler.metadata.MetadataHelper.isSubType(MetadataHelper.java:1283)
        //     at com.strobel.assembler.metadata.MetadataHelper.isSubType(MetadataHelper.java:1283)
        //     at com.strobel.assembler.metadata.MetadataHelper.isSubType(MetadataHelper.java:1283)
        //     at com.strobel.assembler.metadata.MetadataHelper.isSubType(MetadataHelper.java:1283)
        //     at com.strobel.assembler.metadata.MetadataHelper.isSubType(MetadataHelper.java:1283)
        //     at com.strobel.assembler.metadata.MetadataHelper.isSubType(MetadataHelper.java:1283)
        //     at com.strobel.assembler.metadata.MetadataHelper.isSubType(MetadataHelper.java:1283)
        //     at com.strobel.assembler.metadata.MetadataHelper.isSubType(MetadataHelper.java:1283)
        //     at com.strobel.assembler.metadata.MetadataHelper.isSubType(MetadataHelper.java:1283)
        //     at com.strobel.assembler.metadata.MetadataHelper.isSubType(MetadataHelper.java:1283)
        //     at com.strobel.assembler.metadata.MetadataHelper.isSubType(MetadataHelper.java:1283)
        //     at com.strobel.assembler.metadata.MetadataHelper.isSubType(MetadataHelper.java:1283)
        //     at com.strobel.assembler.metadata.MetadataHelper.isSubType(MetadataHelper.java:1283)
        //     at com.strobel.assembler.metadata.MetadataHelper.isSubType(MetadataHelper.java:1283)
        //     at com.strobel.assembler.metadata.MetadataHelper.isSubType(MetadataHelper.java:1283)
        //     at com.strobel.assembler.metadata.MetadataHelper.isSubType(MetadataHelper.java:1283)
        //     at com.strobel.assembler.metadata.MetadataHelper.isSubType(MetadataHelper.java:1283)
        //     at com.strobel.assembler.metadata.MetadataHelper.isSubType(MetadataHelper.java:1283)
        //     at com.strobel.assembler.metadata.MetadataHelper.isSubType(MetadataHelper.java:1283)
        //     at com.strobel.assembler.metadata.MetadataHelper.isSubType(MetadataHelper.java:1283)
        //     at com.strobel.assembler.metadata.MetadataHelper.isSubType(MetadataHelper.java:1283)
        //     at com.strobel.assembler.metadata.MetadataHelper.isSubType(MetadataHelper.java:1283)
        //     at com.strobel.assembler.metadata.MetadataHelper.isSubType(MetadataHelper.java:1283)
        //     at com.strobel.assembler.metadata.MetadataHelper.isSubType(MetadataHelper.java:1283)
        //     at com.strobel.assembler.metadata.MetadataHelper.isSubType(MetadataHelper.java:1283)
        //     at com.strobel.assembler.metadata.MetadataHelper.isSubType(MetadataHelper.java:1283)
        //     at com.strobel.assembler.metadata.MetadataHelper.isSubType(MetadataHelper.java:1283)
        //     at com.strobel.assembler.metadata.MetadataHelper.isSubType(MetadataHelper.java:1283)
        //     at com.strobel.assembler.metadata.MetadataHelper.isSubType(MetadataHelper.java:1283)
        //     at com.strobel.assembler.metadata.MetadataHelper.isSubType(MetadataHelper.java:1283)
        //     at com.strobel.assembler.metadata.MetadataHelper.isSubType(MetadataHelper.java:1283)
        //     at com.strobel.assembler.metadata.MetadataHelper.isSubType(MetadataHelper.java:1283)
        //     at com.strobel.assembler.metadata.MetadataHelper.isSubType(MetadataHelper.java:1283)
        //     at com.strobel.assembler.metadata.MetadataHelper.isSubType(MetadataHelper.java:1283)
        //     at com.strobel.assembler.metadata.MetadataHelper.isSubType(MetadataHelper.java:1283)
        //     at com.strobel.assembler.metadata.MetadataHelper.isSubType(MetadataHelper.java:1283)
        //     at com.strobel.assembler.metadata.MetadataHelper.isSubType(MetadataHelper.java:1283)
        //     at com.strobel.assembler.metadata.MetadataHelper.isSubType(MetadataHelper.java:1283)
        //     at com.strobel.assembler.metadata.MetadataHelper.isSubType(MetadataHelper.java:1283)
        //     at com.strobel.assembler.metadata.MetadataHelper.isSubType(MetadataHelper.java:1283)
        //     at com.strobel.assembler.metadata.MetadataHelper.isSubType(MetadataHelper.java:1283)
        //     at com.strobel.assembler.metadata.MetadataHelper.isSubType(MetadataHelper.java:1283)
        //     at com.strobel.assembler.metadata.MetadataHelper.isSubType(MetadataHelper.java:1283)
        //     at com.strobel.assembler.metadata.MetadataHelper.isSubType(MetadataHelper.java:1283)
        //     at com.strobel.assembler.metadata.MetadataHelper.isSubType(MetadataHelper.java:1283)
        //     at com.strobel.assembler.metadata.MetadataHelper.isSubType(MetadataHelper.java:1283)
        //     at com.strobel.assembler.metadata.MetadataHelper.isSubType(MetadataHelper.java:1283)
        //     at com.strobel.assembler.metadata.MetadataHelper.isSubType(MetadataHelper.java:1283)
        //     at com.strobel.assembler.metadata.MetadataHelper.isSubType(MetadataHelper.java:1283)
        //     at com.strobel.assembler.metadata.MetadataHelper.isSubType(MetadataHelper.java:1283)
        //     at com.strobel.assembler.metadata.MetadataHelper.isSubType(MetadataHelper.java:1283)
        //     at com.strobel.assembler.metadata.MetadataHelper.isSubType(MetadataHelper.java:1283)
        //     at com.strobel.assembler.metadata.MetadataHelper.isSubType(MetadataHelper.java:1283)
        //     at com.strobel.assembler.metadata.MetadataHelper.isSubType(MetadataHelper.java:1283)
        //     at com.strobel.assembler.metadata.MetadataHelper.isSubType(MetadataHelper.java:1283)
        //     at com.strobel.assembler.metadata.MetadataHelper.isSubType(MetadataHelper.java:1283)
        //     at com.strobel.assembler.metadata.MetadataHelper.isSubType(MetadataHelper.java:1283)
        //     at com.strobel.assembler.metadata.MetadataHelper.isSubType(MetadataHelper.java:1283)
        //     at com.strobel.assembler.metadata.MetadataHelper.isSubType(MetadataHelper.java:1283)
        //     at com.strobel.assembler.metadata.MetadataHelper.isSubType(MetadataHelper.java:1283)
        //     at com.strobel.assembler.metadata.MetadataHelper.isSubType(MetadataHelper.java:1283)
        //     at com.strobel.assembler.metadata.MetadataHelper.isSubType(MetadataHelper.java:1283)
        //     at com.strobel.assembler.metadata.MetadataHelper.isSubType(MetadataHelper.java:1283)
        //     at com.strobel.assembler.metadata.MetadataHelper.isSubType(MetadataHelper.java:1283)
        //     at com.strobel.assembler.metadata.MetadataHelper.isSubType(MetadataHelper.java:1283)
        //     at com.strobel.assembler.metadata.MetadataHelper.isSubType(MetadataHelper.java:1283)
        //     at com.strobel.assembler.metadata.MetadataHelper.isSubType(MetadataHelper.java:1283)
        //     at com.strobel.assembler.metadata.MetadataHelper.isSubType(MetadataHelper.java:1283)
        //     at com.strobel.assembler.metadata.MetadataHelper.isSubType(MetadataHelper.java:1283)
        //     at com.strobel.assembler.metadata.MetadataHelper.isSubType(MetadataHelper.java:1283)
        //     at com.strobel.assembler.metadata.MetadataHelper.isSubType(MetadataHelper.java:1283)
        //     at com.strobel.assembler.metadata.MetadataHelper.isSubType(MetadataHelper.java:1283)
        //     at com.strobel.assembler.metadata.MetadataHelper.isSubType(MetadataHelper.java:1283)
        //     at com.strobel.assembler.metadata.MetadataHelper.isSubType(MetadataHelper.java:1283)
        //     at com.strobel.assembler.metadata.MetadataHelper.isSubType(MetadataHelper.java:1283)
        //     at com.strobel.assembler.metadata.MetadataHelper.isSubType(MetadataHelper.java:1283)
        //     at com.strobel.assembler.metadata.MetadataHelper.isSubType(MetadataHelper.java:1283)
        //     at com.strobel.assembler.metadata.MetadataHelper.isSubType(MetadataHelper.java:1283)
        //     at com.strobel.assembler.metadata.MetadataHelper.isSubType(MetadataHelper.java:1283)
        //     at com.strobel.assembler.metadata.MetadataHelper.isSubType(MetadataHelper.java:1283)
        //     at com.strobel.assembler.metadata.MetadataHelper.isSubType(MetadataHelper.java:1283)
        //     at com.strobel.assembler.metadata.MetadataHelper.isSubType(MetadataHelper.java:1283)
        //     at com.strobel.assembler.metadata.MetadataHelper.isSubType(MetadataHelper.java:1283)
        //     at com.strobel.assembler.metadata.MetadataHelper.isSubType(MetadataHelper.java:1283)
        //     at com.strobel.assembler.metadata.MetadataHelper.isSubType(MetadataHelper.java:1283)
        //     at com.strobel.assembler.metadata.MetadataHelper.isSubType(MetadataHelper.java:1283)
        //     at com.strobel.assembler.metadata.MetadataHelper.isSubType(MetadataHelper.java:1283)
        //     at com.strobel.assembler.metadata.MetadataHelper.isSubType(MetadataHelper.java:1283)
        //     at com.strobel.assembler.metadata.MetadataHelper.isSubType(MetadataHelper.java:1283)
        //     at com.strobel.assembler.metadata.MetadataHelper.isSubType(MetadataHelper.java:1283)
        //     at com.strobel.assembler.metadata.MetadataHelper.isSubType(MetadataHelper.java:1283)
        //     at com.strobel.assembler.metadata.MetadataHelper.isSubType(MetadataHelper.java:1283)
        //     at com.strobel.assembler.metadata.MetadataHelper.isSubType(MetadataHelper.java:1283)
        //     at com.strobel.assembler.metadata.MetadataHelper.isSubType(MetadataHelper.java:1283)
        //     at com.strobel.assembler.metadata.MetadataHelper.isSubType(MetadataHelper.java:1283)
        //     at com.strobel.assembler.metadata.MetadataHelper.isSubType(MetadataHelper.java:1283)
        //     at com.strobel.assembler.metadata.MetadataHelper.isSubType(MetadataHelper.java:1283)
        //     at com.strobel.assembler.metadata.MetadataHelper.isSubType(MetadataHelper.java:1283)
        //     at com.strobel.assembler.metadata.MetadataHelper.isSubType(MetadataHelper.java:1283)
        //     at com.strobel.assembler.metadata.MetadataHelper.isSubType(MetadataHelper.java:1283)
        //     at com.strobel.assembler.metadata.MetadataHelper.isSubType(MetadataHelper.java:1283)
        //     at com.strobel.assembler.metadata.MetadataHelper.isSubType(MetadataHelper.java:1283)
        //     at com.strobel.assembler.metadata.MetadataHelper.isSubType(MetadataHelper.java:1283)
        //     at com.strobel.assembler.metadata.MetadataHelper.isSubType(MetadataHelper.java:1283)
        //     at com.strobel.assembler.metadata.MetadataHelper.isSubType(MetadataHelper.java:1283)
        //     at com.strobel.assembler.metadata.MetadataHelper.isSubType(MetadataHelper.java:1283)
        //     at com.strobel.assembler.metadata.MetadataHelper.isSubType(MetadataHelper.java:1283)
        //     at com.strobel.assembler.metadata.MetadataHelper.isSubType(MetadataHelper.java:1283)
        //     at com.strobel.assembler.metadata.MetadataHelper.isSubType(MetadataHelper.java:1283)
        //     at com.strobel.assembler.metadata.MetadataHelper.isSubType(MetadataHelper.java:1283)
        //     at com.strobel.assembler.metadata.MetadataHelper.isSubType(MetadataHelper.java:1283)
        //     at com.strobel.assembler.metadata.MetadataHelper.isSubType(MetadataHelper.java:1283)
        //     at com.strobel.assembler.metadata.MetadataHelper.isSubType(MetadataHelper.java:1283)
        //     at com.strobel.assembler.metadata.MetadataHelper.isSubType(MetadataHelper.java:1283)
        //     at com.strobel.assembler.metadata.MetadataHelper.isSubType(MetadataHelper.java:1283)
        //     at com.strobel.assembler.metadata.MetadataHelper.isSubType(MetadataHelper.java:1283)
        //     at com.strobel.assembler.metadata.MetadataHelper.isSubType(MetadataHelper.java:1283)
        //     at com.strobel.assembler.metadata.MetadataHelper.isSubType(MetadataHelper.java:1283)
        //     at com.strobel.assembler.metadata.MetadataHelper.isSubType(MetadataHelper.java:1283)
        //     at com.strobel.assembler.metadata.MetadataHelper.isSubType(MetadataHelper.java:1283)
        //     at com.strobel.assembler.metadata.MetadataHelper.isSubType(MetadataHelper.java:1283)
        //     at com.strobel.assembler.metadata.MetadataHelper.isSubType(MetadataHelper.java:1283)
        //     at com.strobel.assembler.metadata.MetadataHelper.isSubType(MetadataHelper.java:1283)
        //     at com.strobel.assembler.metadata.MetadataHelper.isSubType(MetadataHelper.java:1283)
        //     at com.strobel.assembler.metadata.MetadataHelper.isSubType(MetadataHelper.java:1283)
        //     at com.strobel.assembler.metadata.MetadataHelper.isSubType(MetadataHelper.java:1283)
        //     at com.strobel.assembler.metadata.MetadataHelper.isSubType(MetadataHelper.java:1283)
        //     at com.strobel.assembler.metadata.MetadataHelper.isSubType(MetadataHelper.java:1283)
        //     at com.strobel.assembler.metadata.MetadataHelper.isSubType(MetadataHelper.java:1283)
        //     at com.strobel.assembler.metadata.MetadataHelper.isSubType(MetadataHelper.java:1283)
        //     at com.strobel.assembler.metadata.MetadataHelper.isSubType(MetadataHelper.java:1283)
        //     at com.strobel.assembler.metadata.MetadataHelper.isSubType(MetadataHelper.java:1283)
        //     at com.strobel.assembler.metadata.MetadataHelper.isSubType(MetadataHelper.java:1283)
        //     at com.strobel.assembler.metadata.MetadataHelper.isSubType(MetadataHelper.java:1283)
        //     at com.strobel.assembler.metadata.MetadataHelper.isSubType(MetadataHelper.java:1283)
        //     at com.strobel.assembler.metadata.MetadataHelper.isSubType(MetadataHelper.java:1283)
        //     at com.strobel.assembler.metadata.MetadataHelper.isSubType(MetadataHelper.java:1283)
        //     at com.strobel.assembler.metadata.MetadataHelper.isSubType(MetadataHelper.java:1283)
        //     at com.strobel.assembler.metadata.MetadataHelper.isSubType(MetadataHelper.java:1283)
        //     at com.strobel.assembler.metadata.MetadataHelper.isSubType(MetadataHelper.java:1283)
        //     at com.strobel.assembler.metadata.MetadataHelper.isSubType(MetadataHelper.java:1283)
        //     at com.strobel.assembler.metadata.MetadataHelper.isSubType(MetadataHelper.java:1283)
        //     at com.strobel.assembler.metadata.MetadataHelper.isSubType(MetadataHelper.java:1283)
        //     at com.strobel.assembler.metadata.MetadataHelper.isSubType(MetadataHelper.java:1283)
        //     at com.strobel.assembler.metadata.MetadataHelper.isSubType(MetadataHelper.java:1283)
        //     at com.strobel.assembler.metadata.MetadataHelper.isSubType(MetadataHelper.java:1283)
        //     at com.strobel.assembler.metadata.MetadataHelper.isSubType(MetadataHelper.java:1283)
        //     at com.strobel.assembler.metadata.MetadataHelper.isSubType(MetadataHelper.java:1283)
        //     at com.strobel.assembler.metadata.MetadataHelper.isSubType(MetadataHelper.java:1283)
        //     at com.strobel.assembler.metadata.MetadataHelper.isSubType(MetadataHelper.java:1283)
        //     at com.strobel.assembler.metadata.MetadataHelper.isSubType(MetadataHelper.java:1283)
        //     at com.strobel.assembler.metadata.MetadataHelper.isSubType(MetadataHelper.java:1283)
        //     at com.strobel.assembler.metadata.MetadataHelper.isSubType(MetadataHelper.java:1283)
        //     at com.strobel.assembler.metadata.MetadataHelper.isSubType(MetadataHelper.java:1283)
        //     at com.strobel.assembler.metadata.MetadataHelper.isSubType(MetadataHelper.java:1283)
        //     at com.strobel.assembler.metadata.MetadataHelper.isSubType(MetadataHelper.java:1283)
        //     at com.strobel.assembler.metadata.MetadataHelper.isSubType(MetadataHelper.java:1283)
        //     at com.strobel.assembler.metadata.MetadataHelper.isSubType(MetadataHelper.java:1283)
        //     at com.strobel.assembler.metadata.MetadataHelper.isSubType(MetadataHelper.java:1283)
        //     at com.strobel.assembler.metadata.MetadataHelper.isSubType(MetadataHelper.java:1283)
        //     at com.strobel.assembler.metadata.MetadataHelper.isSubType(MetadataHelper.java:1283)
        //     at com.strobel.assembler.metadata.MetadataHelper.isSubType(MetadataHelper.java:1283)
        //     at com.strobel.assembler.metadata.MetadataHelper.isSubType(MetadataHelper.java:1283)
        //     at com.strobel.assembler.metadata.MetadataHelper.isSubType(MetadataHelper.java:1283)
        //     at com.strobel.assembler.metadata.MetadataHelper.isSubType(MetadataHelper.java:1283)
        //     at com.strobel.assembler.metadata.MetadataHelper.isSubType(MetadataHelper.java:1283)
        //     at com.strobel.assembler.metadata.MetadataHelper.isSubType(MetadataHelper.java:1283)
        //     at com.strobel.assembler.metadata.MetadataHelper.isSubType(MetadataHelper.java:1283)
        //     at com.strobel.assembler.metadata.MetadataHelper.isSubType(MetadataHelper.java:1283)
        //     at com.strobel.assembler.metadata.MetadataHelper.isSubType(MetadataHelper.java:1283)
        //     at com.strobel.assembler.metadata.MetadataHelper.isSubType(MetadataHelper.java:1283)
        //     at com.strobel.assembler.metadata.MetadataHelper.isSubType(MetadataHelper.java:1283)
        //     at com.strobel.assembler.metadata.MetadataHelper.isSubType(MetadataHelper.java:1283)
        //     at com.strobel.assembler.metadata.MetadataHelper.isSubType(MetadataHelper.java:1283)
        //     at com.strobel.assembler.metadata.MetadataHelper.isSubType(MetadataHelper.java:1283)
        //     at com.strobel.assembler.metadata.MetadataHelper.isSubType(MetadataHelper.java:1283)
        //     at com.strobel.assembler.metadata.MetadataHelper.isSubType(MetadataHelper.java:1283)
        //     at com.strobel.assembler.metadata.MetadataHelper.isSubType(MetadataHelper.java:1283)
        //     at com.strobel.assembler.metadata.MetadataHelper.isSubType(MetadataHelper.java:1283)
        //     at com.strobel.assembler.metadata.MetadataHelper.isSubType(MetadataHelper.java:1283)
        //     at com.strobel.assembler.metadata.MetadataHelper.isSubType(MetadataHelper.java:1283)
        //     at com.strobel.assembler.metadata.MetadataHelper.isSubType(MetadataHelper.java:1283)
        //     at com.strobel.assembler.metadata.MetadataHelper.isSubType(MetadataHelper.java:1283)
        //     at com.strobel.assembler.metadata.MetadataHelper.isSubType(MetadataHelper.java:1283)
        //     at com.strobel.assembler.metadata.MetadataHelper.isSubType(MetadataHelper.java:1283)
        //     at com.strobel.assembler.metadata.MetadataHelper.isSubType(MetadataHelper.java:1283)
        //     at com.strobel.assembler.metadata.MetadataHelper.isSubType(MetadataHelper.java:1283)
        //     at com.strobel.assembler.metadata.MetadataHelper.isSubType(MetadataHelper.java:1283)
        //     at com.strobel.assembler.metadata.MetadataHelper.isSubType(MetadataHelper.java:1283)
        //     at com.strobel.assembler.metadata.MetadataHelper.isSubType(MetadataHelper.java:1283)
        //     at com.strobel.assembler.metadata.MetadataHelper.isSubType(MetadataHelper.java:1283)
        //     at com.strobel.assembler.metadata.MetadataHelper.isSubType(MetadataHelper.java:1283)
        //     at com.strobel.assembler.metadata.MetadataHelper.isSubType(MetadataHelper.java:1283)
        //     at com.strobel.assembler.metadata.MetadataHelper.isSubType(MetadataHelper.java:1283)
        //     at com.strobel.assembler.metadata.MetadataHelper.isSubType(MetadataHelper.java:1283)
        //     at com.strobel.assembler.metadata.MetadataHelper.isSubType(MetadataHelper.java:1283)
        //     at com.strobel.assembler.metadata.MetadataHelper.isSubType(MetadataHelper.java:1283)
        //     at com.strobel.assembler.metadata.MetadataHelper.isSubType(MetadataHelper.java:1283)
        //     at com.strobel.assembler.metadata.MetadataHelper.isSubType(MetadataHelper.java:1283)
        //     at com.strobel.assembler.metadata.MetadataHelper.isSubType(MetadataHelper.java:1283)
        //     at com.strobel.assembler.metadata.MetadataHelper.isSubType(MetadataHelper.java:1283)
        //     at com.strobel.assembler.metadata.MetadataHelper.isSubType(MetadataHelper.java:1283)
        //     at com.strobel.assembler.metadata.MetadataHelper.isSubType(MetadataHelper.java:1283)
        //     at com.strobel.assembler.metadata.MetadataHelper.isSubType(MetadataHelper.java:1283)
        //     at com.strobel.assembler.metadata.MetadataHelper.isSubType(MetadataHelper.java:1283)
        //     at com.strobel.assembler.metadata.MetadataHelper.isSubType(MetadataHelper.java:1283)
        //     at com.strobel.assembler.metadata.MetadataHelper.isSubType(MetadataHelper.java:1283)
        //     at com.strobel.assembler.metadata.MetadataHelper.isSubType(MetadataHelper.java:1283)
        //     at com.strobel.assembler.metadata.MetadataHelper.isSubType(MetadataHelper.java:1283)
        //     at com.strobel.assembler.metadata.MetadataHelper.isSubType(MetadataHelper.java:1283)
        //     at com.strobel.assembler.metadata.MetadataHelper.isSubType(MetadataHelper.java:1283)
        //     at com.strobel.assembler.metadata.MetadataHelper.isSubType(MetadataHelper.java:1283)
        //     at com.strobel.assembler.metadata.MetadataHelper.isSubType(MetadataHelper.java:1283)
        //     at com.strobel.assembler.metadata.MetadataHelper.isSubType(MetadataHelper.java:1283)
        //     at com.strobel.assembler.metadata.MetadataHelper.isSubType(MetadataHelper.java:1283)
        //     at com.strobel.assembler.metadata.MetadataHelper.isSubType(MetadataHelper.java:1283)
        //     at com.strobel.assembler.metadata.MetadataHelper.isSubType(MetadataHelper.java:1283)
        //     at com.strobel.assembler.metadata.MetadataHelper.isSubType(MetadataHelper.java:1283)
        //     at com.strobel.assembler.metadata.MetadataHelper.isSubType(MetadataHelper.java:1283)
        //     at com.strobel.assembler.metadata.MetadataHelper.isSubType(MetadataHelper.java:1283)
        //     at com.strobel.assembler.metadata.MetadataHelper.isSubType(MetadataHelper.java:1283)
        //     at com.strobel.assembler.metadata.MetadataHelper.isSubType(MetadataHelper.java:1283)
        //     at com.strobel.assembler.metadata.MetadataHelper.isSubType(MetadataHelper.java:1283)
        //     at com.strobel.assembler.metadata.MetadataHelper.isSubType(MetadataHelper.java:1283)
        //     at com.strobel.assembler.metadata.MetadataHelper.isSubType(MetadataHelper.java:1283)
        //     at com.strobel.assembler.metadata.MetadataHelper.isSubType(MetadataHelper.java:1283)
        //     at com.strobel.assembler.metadata.MetadataHelper.isSubType(MetadataHelper.java:1283)
        //     at com.strobel.assembler.metadata.MetadataHelper.isSubType(MetadataHelper.java:1283)
        //     at com.strobel.assembler.metadata.MetadataHelper.isSubType(MetadataHelper.java:1283)
        //     at com.strobel.assembler.metadata.MetadataHelper.isSubType(MetadataHelper.java:1283)
        //     at com.strobel.assembler.metadata.MetadataHelper.isSubType(MetadataHelper.java:1283)
        //     at com.strobel.assembler.metadata.MetadataHelper.isSubType(MetadataHelper.java:1283)
        //     at com.strobel.assembler.metadata.MetadataHelper.isSubType(MetadataHelper.java:1283)
        //     at com.strobel.assembler.metadata.MetadataHelper.isSubType(MetadataHelper.java:1283)
        //     at com.strobel.assembler.metadata.MetadataHelper.isSubType(MetadataHelper.java:1283)
        //     at com.strobel.assembler.metadata.MetadataHelper.isSubType(MetadataHelper.java:1283)
        //     at com.strobel.assembler.metadata.MetadataHelper.isSubType(MetadataHelper.java:1283)
        //     at com.strobel.assembler.metadata.MetadataHelper.isSubType(MetadataHelper.java:1283)
        //     at com.strobel.assembler.metadata.MetadataHelper.isSubType(MetadataHelper.java:1283)
        //     at com.strobel.assembler.metadata.MetadataHelper.isSubType(MetadataHelper.java:1283)
        //     at com.strobel.assembler.metadata.MetadataHelper.isSubType(MetadataHelper.java:1283)
        //     at com.strobel.assembler.metadata.MetadataHelper.isSubType(MetadataHelper.java:1283)
        //     at com.strobel.assembler.metadata.MetadataHelper.isSubType(MetadataHelper.java:1283)
        //     at com.strobel.assembler.metadata.MetadataHelper.isSubType(MetadataHelper.java:1283)
        //     at com.strobel.assembler.metadata.MetadataHelper.isSubType(MetadataHelper.java:1283)
        //     at com.strobel.assembler.metadata.MetadataHelper.isSubType(MetadataHelper.java:1283)
        //     at com.strobel.assembler.metadata.MetadataHelper.isSubType(MetadataHelper.java:1283)
        //     at com.strobel.assembler.metadata.MetadataHelper.isSubType(MetadataHelper.java:1283)
        //     at com.strobel.assembler.metadata.MetadataHelper.isSubType(MetadataHelper.java:1283)
        //     at com.strobel.assembler.metadata.MetadataHelper.isSubType(MetadataHelper.java:1283)
        //     at com.strobel.assembler.metadata.MetadataHelper.isSubType(MetadataHelper.java:1283)
        //     at com.strobel.assembler.metadata.MetadataHelper.isSubType(MetadataHelper.java:1283)
        //     at com.strobel.assembler.metadata.MetadataHelper.isSubType(MetadataHelper.java:1283)
        //     at com.strobel.assembler.metadata.MetadataHelper.isSubType(MetadataHelper.java:1283)
        //     at com.strobel.assembler.metadata.MetadataHelper.isSubType(MetadataHelper.java:1283)
        //     at com.strobel.assembler.metadata.MetadataHelper.isSubType(MetadataHelper.java:1283)
        //     at com.strobel.assembler.metadata.MetadataHelper.isSubType(MetadataHelper.java:1283)
        //     at com.strobel.assembler.metadata.MetadataHelper.isSubType(MetadataHelper.java:1283)
        //     at com.strobel.assembler.metadata.MetadataHelper.isSubType(MetadataHelper.java:1283)
        //     at com.strobel.assembler.metadata.MetadataHelper.isSubType(MetadataHelper.java:1283)
        //     at com.strobel.assembler.metadata.MetadataHelper.isSubType(MetadataHelper.java:1283)
        //     at com.strobel.assembler.metadata.MetadataHelper.isSubType(MetadataHelper.java:1283)
        //     at com.strobel.assembler.metadata.MetadataHelper.isSubType(MetadataHelper.java:1283)
        //     at com.strobel.assembler.metadata.MetadataHelper.isSubType(MetadataHelper.java:1283)
        //     at com.strobel.assembler.metadata.MetadataHelper.isSubType(MetadataHelper.java:1283)
        //     at com.strobel.assembler.metadata.MetadataHelper.isSubType(MetadataHelper.java:1283)
        //     at com.strobel.assembler.metadata.MetadataHelper.isSubType(MetadataHelper.java:1283)
        //     at com.strobel.assembler.metadata.MetadataHelper.isSubType(MetadataHelper.java:1283)
        //     at com.strobel.assembler.metadata.MetadataHelper.isSubType(MetadataHelper.java:1283)
        //     at com.strobel.assembler.metadata.MetadataHelper.isSubType(MetadataHelper.java:1283)
        //     at com.strobel.assembler.metadata.MetadataHelper.isSubType(MetadataHelper.java:1283)
        //     at com.strobel.assembler.metadata.MetadataHelper.isSubType(MetadataHelper.java:1283)
        //     at com.strobel.assembler.metadata.MetadataHelper.isSubType(MetadataHelper.java:1283)
        //     at com.strobel.assembler.metadata.MetadataHelper.isSubType(MetadataHelper.java:1283)
        //     at com.strobel.assembler.metadata.MetadataHelper.isSubType(MetadataHelper.java:1283)
        //     at com.strobel.assembler.metadata.MetadataHelper.isSubType(MetadataHelper.java:1283)
        //     at com.strobel.assembler.metadata.MetadataHelper.isSubType(MetadataHelper.java:1283)
        //     at com.strobel.assembler.metadata.MetadataHelper.isSubType(MetadataHelper.java:1283)
        //     at com.strobel.assembler.metadata.MetadataHelper.isSubType(MetadataHelper.java:1283)
        //     at com.strobel.assembler.metadata.MetadataHelper.isSubType(MetadataHelper.java:1283)
        //     at com.strobel.assembler.metadata.MetadataHelper.isSubType(MetadataHelper.java:1283)
        //     at com.strobel.assembler.metadata.MetadataHelper.isSubType(MetadataHelper.java:1283)
        //     at com.strobel.assembler.metadata.MetadataHelper.isSubType(MetadataHelper.java:1283)
        //     at com.strobel.assembler.metadata.MetadataHelper.isSubType(MetadataHelper.java:1283)
        //     at com.strobel.assembler.metadata.MetadataHelper.isSubType(MetadataHelper.java:1283)
        //     at com.strobel.assembler.metadata.MetadataHelper.isSubType(MetadataHelper.java:1283)
        //     at com.strobel.assembler.metadata.MetadataHelper.isSubType(MetadataHelper.java:1283)
        //     at com.strobel.assembler.metadata.MetadataHelper.isSubType(MetadataHelper.java:1283)
        //     at com.strobel.assembler.metadata.MetadataHelper.isSubType(MetadataHelper.java:1283)
        //     at com.strobel.assembler.metadata.MetadataHelper.isSubType(MetadataHelper.java:1283)
        //     at com.strobel.assembler.metadata.MetadataHelper.isSubType(MetadataHelper.java:1283)
        //     at com.strobel.assembler.metadata.MetadataHelper.isSubType(MetadataHelper.java:1283)
        //     at com.strobel.assembler.metadata.MetadataHelper.isSubType(MetadataHelper.java:1283)
        //     at com.strobel.assembler.metadata.MetadataHelper.isSubType(MetadataHelper.java:1283)
        //     at com.strobel.assembler.metadata.MetadataHelper.isSubType(MetadataHelper.java:1283)
        //     at com.strobel.assembler.metadata.MetadataHelper.isSubType(MetadataHelper.java:1283)
        //     at com.strobel.assembler.metadata.MetadataHelper.isSubType(MetadataHelper.java:1283)
        //     at com.strobel.assembler.metadata.MetadataHelper.isSubType(MetadataHelper.java:1283)
        //     at com.strobel.assembler.metadata.MetadataHelper.isSubType(MetadataHelper.java:1283)
        //     at com.strobel.assembler.metadata.MetadataHelper.isSubType(MetadataHelper.java:1283)
        //     at com.strobel.assembler.metadata.MetadataHelper.isSubType(MetadataHelper.java:1283)
        //     at com.strobel.assembler.metadata.MetadataHelper.isSubType(MetadataHelper.java:1283)
        //     at com.strobel.assembler.metadata.MetadataHelper.isSubType(MetadataHelper.java:1283)
        //     at com.strobel.assembler.metadata.MetadataHelper.isSubType(MetadataHelper.java:1283)
        //     at com.strobel.assembler.metadata.MetadataHelper.isSubType(MetadataHelper.java:1283)
        //     at com.strobel.assembler.metadata.MetadataHelper.isSubType(MetadataHelper.java:1283)
        //     at com.strobel.assembler.metadata.MetadataHelper.isSubType(MetadataHelper.java:1283)
        //     at com.strobel.assembler.metadata.MetadataHelper.isSubType(MetadataHelper.java:1283)
        //     at com.strobel.assembler.metadata.MetadataHelper.isSubType(MetadataHelper.java:1283)
        //     at com.strobel.assembler.metadata.MetadataHelper.isSubType(MetadataHelper.java:1283)
        //     at com.strobel.assembler.metadata.MetadataHelper.isSubType(MetadataHelper.java:1283)
        //     at com.strobel.assembler.metadata.MetadataHelper.isSubType(MetadataHelper.java:1283)
        //     at com.strobel.assembler.metadata.MetadataHelper.isSubType(MetadataHelper.java:1283)
        //     at com.strobel.assembler.metadata.MetadataHelper.isSubType(MetadataHelper.java:1283)
        //     at com.strobel.assembler.metadata.MetadataHelper.isSubType(MetadataHelper.java:1283)
        //     at com.strobel.assembler.metadata.MetadataHelper.isSubType(MetadataHelper.java:1283)
        //     at com.strobel.assembler.metadata.MetadataHelper.isSubType(MetadataHelper.java:1283)
        //     at com.strobel.assembler.metadata.MetadataHelper.isSubType(MetadataHelper.java:1283)
        //     at com.strobel.assembler.metadata.MetadataHelper.isSubType(MetadataHelper.java:1283)
        //     at com.strobel.assembler.metadata.MetadataHelper.isSubType(MetadataHelper.java:1283)
        //     at com.strobel.assembler.metadata.MetadataHelper.isSubType(MetadataHelper.java:1283)
        //     at com.strobel.assembler.metadata.MetadataHelper.isSubType(MetadataHelper.java:1283)
        //     at com.strobel.assembler.metadata.MetadataHelper.isSubType(MetadataHelper.java:1283)
        //     at com.strobel.assembler.metadata.MetadataHelper.isSubType(MetadataHelper.java:1283)
        //     at com.strobel.assembler.metadata.MetadataHelper.isSubType(MetadataHelper.java:1283)
        //     at com.strobel.assembler.metadata.MetadataHelper.isSubType(MetadataHelper.java:1283)
        //     at com.strobel.assembler.metadata.MetadataHelper.isSubType(MetadataHelper.java:1283)
        //     at com.strobel.assembler.metadata.MetadataHelper.isSubType(MetadataHelper.java:1283)
        //     at com.strobel.assembler.metadata.MetadataHelper.isSubType(MetadataHelper.java:1283)
        //     at com.strobel.assembler.metadata.MetadataHelper.isSubType(MetadataHelper.java:1283)
        //     at com.strobel.assembler.metadata.MetadataHelper.isSubType(MetadataHelper.java:1283)
        //     at com.strobel.assembler.metadata.MetadataHelper.isSubType(MetadataHelper.java:1283)
        //     at com.strobel.assembler.metadata.MetadataHelper.isSubType(MetadataHelper.java:1283)
        //     at com.strobel.assembler.metadata.MetadataHelper.isSubType(MetadataHelper.java:1283)
        //     at com.strobel.assembler.metadata.MetadataHelper.isSubType(MetadataHelper.java:1283)
        //     at com.strobel.assembler.metadata.MetadataHelper.isSubType(MetadataHelper.java:1283)
        //     at com.strobel.assembler.metadata.MetadataHelper.isSubType(MetadataHelper.java:1283)
        //     at com.strobel.assembler.metadata.MetadataHelper.isSubType(MetadataHelper.java:1283)
        //     at com.strobel.assembler.metadata.MetadataHelper.isSubType(MetadataHelper.java:1283)
        //     at com.strobel.assembler.metadata.MetadataHelper.isSubType(MetadataHelper.java:1283)
        //     at com.strobel.assembler.metadata.MetadataHelper.isSubType(MetadataHelper.java:1283)
        //     at com.strobel.assembler.metadata.MetadataHelper.isSubType(MetadataHelper.java:1283)
        //     at com.strobel.assembler.metadata.MetadataHelper.isSubType(MetadataHelper.java:1283)
        //     at com.strobel.assembler.metadata.MetadataHelper.isSubType(MetadataHelper.java:1283)
        //     at com.strobel.assembler.metadata.MetadataHelper.isSubType(MetadataHelper.java:1283)
        //     at com.strobel.assembler.metadata.MetadataHelper.isSubType(MetadataHelper.java:1283)
        //     at com.strobel.assembler.metadata.MetadataHelper.isSubType(MetadataHelper.java:1283)
        //     at com.strobel.assembler.metadata.MetadataHelper.isSubType(MetadataHelper.java:1283)
        //     at com.strobel.assembler.metadata.MetadataHelper.isSubType(MetadataHelper.java:1283)
        //     at com.strobel.assembler.metadata.MetadataHelper.isSubType(MetadataHelper.java:1283)
        //     at com.strobel.assembler.metadata.MetadataHelper.isSubType(MetadataHelper.java:1283)
        //     at com.strobel.assembler.metadata.MetadataHelper.isSubType(MetadataHelper.java:1283)
        //     at com.strobel.assembler.metadata.MetadataHelper.isSubType(MetadataHelper.java:1283)
        //     at com.strobel.assembler.metadata.MetadataHelper.isSubType(MetadataHelper.java:1283)
        //     at com.strobel.assembler.metadata.MetadataHelper.isSubType(MetadataHelper.java:1283)
        //     at com.strobel.assembler.metadata.MetadataHelper.isSubType(MetadataHelper.java:1283)
        //     at com.strobel.assembler.metadata.MetadataHelper.isSubType(MetadataHelper.java:1283)
        //     at com.strobel.assembler.metadata.MetadataHelper.isSubType(MetadataHelper.java:1283)
        //     at com.strobel.assembler.metadata.MetadataHelper.isSubType(MetadataHelper.java:1283)
        //     at com.strobel.assembler.metadata.MetadataHelper.isSubType(MetadataHelper.java:1283)
        //     at com.strobel.assembler.metadata.MetadataHelper.isSubType(MetadataHelper.java:1283)
        //     at com.strobel.assembler.metadata.MetadataHelper.isSubType(MetadataHelper.java:1283)
        //     at com.strobel.assembler.metadata.MetadataHelper.isSubType(MetadataHelper.java:1283)
        //     at com.strobel.assembler.metadata.MetadataHelper.isSubType(MetadataHelper.java:1283)
        //     at com.strobel.assembler.metadata.MetadataHelper.isSubType(MetadataHelper.java:1283)
        //     at com.strobel.assembler.metadata.MetadataHelper.isSubType(MetadataHelper.java:1283)
        //     at com.strobel.assembler.metadata.MetadataHelper.isSubType(MetadataHelper.java:1283)
        //     at com.strobel.assembler.metadata.MetadataHelper.isSubType(MetadataHelper.java:1283)
        //     at com.strobel.assembler.metadata.MetadataHelper.isSubType(MetadataHelper.java:1283)
        //     at com.strobel.assembler.metadata.MetadataHelper.isSubType(MetadataHelper.java:1283)
        // 
        throw new IllegalStateException("An error occurred while decompiling this method.");
    }
    
    @SinceKotlin(version = "1.3")
    @PublishedApi
    @JvmName(name = "contentDeepEquals")
    public static final <T> boolean contentDeepEquals(@NotNull final T[] $this$contentDeepEqualsImpl, @NotNull final T[] other) {
        // 
        // This method could not be decompiled.
        // 
        // Original Bytecode:
        // 
        //     1: ldc             "$this$contentDeepEqualsImpl"
        //     3: invokestatic    kotlin/jvm/internal/Intrinsics.checkParameterIsNotNull:(Ljava/lang/Object;Ljava/lang/String;)V
        //     6: aload_1         /* other */
        //     7: ldc             "other"
        //     9: invokestatic    kotlin/jvm/internal/Intrinsics.checkParameterIsNotNull:(Ljava/lang/Object;Ljava/lang/String;)V
        //    12: aload_0         /* $this$contentDeepEqualsImpl */
        //    13: aload_1         /* other */
        //    14: if_acmpne       19
        //    17: iconst_1       
        //    18: ireturn        
        //    19: aload_0         /* $this$contentDeepEqualsImpl */
        //    20: arraylength    
        //    21: aload_1         /* other */
        //    22: arraylength    
        //    23: if_icmpeq       28
        //    26: iconst_0       
        //    27: ireturn        
        //    28: iconst_0       
        //    29: istore_2       
        //    30: aload_0         /* $this$contentDeepEqualsImpl */
        //    31: arraylength    
        //    32: istore_3       
        //    33: iload_2        
        //    34: iload_3        
        //    35: if_icmpge       620
        //    38: aload_0         /* $this$contentDeepEqualsImpl */
        //    39: iload_2         /* i */
        //    40: aaload         
        //    41: astore          v1
        //    43: aload_1         /* other */
        //    44: iload_2         /* i */
        //    45: aaload         
        //    46: astore          v2
        //    48: aload           v1
        //    50: aload           v2
        //    52: if_acmpne       58
        //    55: goto            614
        //    58: aload           v1
        //    60: ifnull          68
        //    63: aload           v2
        //    65: ifnonnull       70
        //    68: iconst_0       
        //    69: ireturn        
        //    70: nop            
        //    71: aload           v1
        //    73: instanceof      [Ljava/lang/Object;
        //    76: ifeq            112
        //    79: aload           v2
        //    81: instanceof      [Ljava/lang/Object;
        //    84: ifeq            112
        //    87: aload           v1
        //    89: checkcast       [Ljava/lang/Object;
        //    92: astore          6
        //    94: iconst_0       
        //    95: istore          7
        //    97: aload           6
        //    99: aload           v2
        //   101: checkcast       [Ljava/lang/Object;
        //   104: invokestatic    kotlin/collections/ArraysKt.contentDeepEquals:([Ljava/lang/Object;[Ljava/lang/Object;)Z
        //   107: ifne            614
        //   110: iconst_0       
        //   111: ireturn        
        //   112: aload           v1
        //   114: instanceof      [B
        //   117: ifeq            153
        //   120: aload           v2
        //   122: instanceof      [B
        //   125: ifeq            153
        //   128: aload           v1
        //   130: checkcast       [B
        //   133: astore          6
        //   135: iconst_0       
        //   136: istore          7
        //   138: aload           6
        //   140: aload           v2
        //   142: checkcast       [B
        //   145: invokestatic    java/util/Arrays.equals:([B[B)Z
        //   148: ifne            614
        //   151: iconst_0       
        //   152: ireturn        
        //   153: aload           v1
        //   155: instanceof      [S
        //   158: ifeq            194
        //   161: aload           v2
        //   163: instanceof      [S
        //   166: ifeq            194
        //   169: aload           v1
        //   171: checkcast       [S
        //   174: astore          6
        //   176: iconst_0       
        //   177: istore          7
        //   179: aload           6
        //   181: aload           v2
        //   183: checkcast       [S
        //   186: invokestatic    java/util/Arrays.equals:([S[S)Z
        //   189: ifne            614
        //   192: iconst_0       
        //   193: ireturn        
        //   194: aload           v1
        //   196: instanceof      [I
        //   199: ifeq            235
        //   202: aload           v2
        //   204: instanceof      [I
        //   207: ifeq            235
        //   210: aload           v1
        //   212: checkcast       [I
        //   215: astore          6
        //   217: iconst_0       
        //   218: istore          7
        //   220: aload           6
        //   222: aload           v2
        //   224: checkcast       [I
        //   227: invokestatic    java/util/Arrays.equals:([I[I)Z
        //   230: ifne            614
        //   233: iconst_0       
        //   234: ireturn        
        //   235: aload           v1
        //   237: instanceof      [J
        //   240: ifeq            276
        //   243: aload           v2
        //   245: instanceof      [J
        //   248: ifeq            276
        //   251: aload           v1
        //   253: checkcast       [J
        //   256: astore          6
        //   258: iconst_0       
        //   259: istore          7
        //   261: aload           6
        //   263: aload           v2
        //   265: checkcast       [J
        //   268: invokestatic    java/util/Arrays.equals:([J[J)Z
        //   271: ifne            614
        //   274: iconst_0       
        //   275: ireturn        
        //   276: aload           v1
        //   278: instanceof      [F
        //   281: ifeq            317
        //   284: aload           v2
        //   286: instanceof      [F
        //   289: ifeq            317
        //   292: aload           v1
        //   294: checkcast       [F
        //   297: astore          6
        //   299: iconst_0       
        //   300: istore          7
        //   302: aload           6
        //   304: aload           v2
        //   306: checkcast       [F
        //   309: invokestatic    java/util/Arrays.equals:([F[F)Z
        //   312: ifne            614
        //   315: iconst_0       
        //   316: ireturn        
        //   317: aload           v1
        //   319: instanceof      [D
        //   322: ifeq            358
        //   325: aload           v2
        //   327: instanceof      [D
        //   330: ifeq            358
        //   333: aload           v1
        //   335: checkcast       [D
        //   338: astore          6
        //   340: iconst_0       
        //   341: istore          7
        //   343: aload           6
        //   345: aload           v2
        //   347: checkcast       [D
        //   350: invokestatic    java/util/Arrays.equals:([D[D)Z
        //   353: ifne            614
        //   356: iconst_0       
        //   357: ireturn        
        //   358: aload           v1
        //   360: instanceof      [C
        //   363: ifeq            399
        //   366: aload           v2
        //   368: instanceof      [C
        //   371: ifeq            399
        //   374: aload           v1
        //   376: checkcast       [C
        //   379: astore          6
        //   381: iconst_0       
        //   382: istore          7
        //   384: aload           6
        //   386: aload           v2
        //   388: checkcast       [C
        //   391: invokestatic    java/util/Arrays.equals:([C[C)Z
        //   394: ifne            614
        //   397: iconst_0       
        //   398: ireturn        
        //   399: aload           v1
        //   401: instanceof      [Z
        //   404: ifeq            440
        //   407: aload           v2
        //   409: instanceof      [Z
        //   412: ifeq            440
        //   415: aload           v1
        //   417: checkcast       [Z
        //   420: astore          6
        //   422: iconst_0       
        //   423: istore          7
        //   425: aload           6
        //   427: aload           v2
        //   429: checkcast       [Z
        //   432: invokestatic    java/util/Arrays.equals:([Z[Z)Z
        //   435: ifne            614
        //   438: iconst_0       
        //   439: ireturn        
        //   440: aload           v1
        //   442: instanceof      Lkotlin/UByteArray;
        //   445: ifeq            480
        //   448: aload           v2
        //   450: instanceof      Lkotlin/UByteArray;
        //   453: ifeq            480
        //   456: aload           v1
        //   458: checkcast       Lkotlin/UByteArray;
        //   461: invokevirtual   kotlin/UByteArray.unbox-impl:()[B
        //   464: aload           v2
        //   466: checkcast       Lkotlin/UByteArray;
        //   469: invokevirtual   kotlin/UByteArray.unbox-impl:()[B
        //   472: invokestatic    kotlin/collections/unsigned/UArraysKt.contentEquals-kdPth3s:([B[B)Z
        //   475: ifne            614
        //   478: iconst_0       
        //   479: ireturn        
        //   480: aload           v1
        //   482: instanceof      Lkotlin/UShortArray;
        //   485: ifeq            520
        //   488: aload           v2
        //   490: instanceof      Lkotlin/UShortArray;
        //   493: ifeq            520
        //   496: aload           v1
        //   498: checkcast       Lkotlin/UShortArray;
        //   501: invokevirtual   kotlin/UShortArray.unbox-impl:()[S
        //   504: aload           v2
        //   506: checkcast       Lkotlin/UShortArray;
        //   509: invokevirtual   kotlin/UShortArray.unbox-impl:()[S
        //   512: invokestatic    kotlin/collections/unsigned/UArraysKt.contentEquals-mazbYpA:([S[S)Z
        //   515: ifne            614
        //   518: iconst_0       
        //   519: ireturn        
        //   520: aload           v1
        //   522: instanceof      Lkotlin/UIntArray;
        //   525: ifeq            560
        //   528: aload           v2
        //   530: instanceof      Lkotlin/UIntArray;
        //   533: ifeq            560
        //   536: aload           v1
        //   538: checkcast       Lkotlin/UIntArray;
        //   541: invokevirtual   kotlin/UIntArray.unbox-impl:()[I
        //   544: aload           v2
        //   546: checkcast       Lkotlin/UIntArray;
        //   549: invokevirtual   kotlin/UIntArray.unbox-impl:()[I
        //   552: invokestatic    kotlin/collections/unsigned/UArraysKt.contentEquals-ctEhBpI:([I[I)Z
        //   555: ifne            614
        //   558: iconst_0       
        //   559: ireturn        
        //   560: aload           v1
        //   562: instanceof      Lkotlin/ULongArray;
        //   565: ifeq            600
        //   568: aload           v2
        //   570: instanceof      Lkotlin/ULongArray;
        //   573: ifeq            600
        //   576: aload           v1
        //   578: checkcast       Lkotlin/ULongArray;
        //   581: invokevirtual   kotlin/ULongArray.unbox-impl:()[J
        //   584: aload           v2
        //   586: checkcast       Lkotlin/ULongArray;
        //   589: invokevirtual   kotlin/ULongArray.unbox-impl:()[J
        //   592: invokestatic    kotlin/collections/unsigned/UArraysKt.contentEquals-us8wMrg:([J[J)Z
        //   595: ifne            614
        //   598: iconst_0       
        //   599: ireturn        
        //   600: aload           v1
        //   602: aload           v2
        //   604: invokestatic    kotlin/jvm/internal/Intrinsics.areEqual:(Ljava/lang/Object;Ljava/lang/Object;)Z
        //   607: iconst_1       
        //   608: ixor           
        //   609: ifeq            614
        //   612: iconst_0       
        //   613: ireturn        
        //   614: iinc            i, 1
        //   617: goto            33
        //   620: iconst_1       
        //   621: ireturn        
        //    Signature:
        //  <T:Ljava/lang/Object;>([TT;[TT;)Z
        //    StackMapTable: 00 15 13 08 FD 00 04 01 01 FD 00 18 07 00 81 07 00 81 09 01 29 28 28 28 28 28 28 28 28 27 27 27 27 0D F9 00 05
        // 
        // The error that occurred was:
        // 
        // java.lang.NullPointerException
        // 
        throw new IllegalStateException("An error occurred while decompiling this method.");
    }
    
    @SinceKotlin(version = "1.3")
    @PublishedApi
    @JvmName(name = "contentDeepToString")
    @NotNull
    public static final <T> String contentDeepToString(@NotNull final T[] $this$contentDeepToStringImpl) {
        Intrinsics.checkParameterIsNotNull($this$contentDeepToStringImpl, "$this$contentDeepToStringImpl");
        final int length = RangesKt___RangesKt.coerceAtMost($this$contentDeepToStringImpl.length, 429496729) * 5 + 2;
        final StringBuilder $this$buildString = new StringBuilder(length);
        final int n = 0;
        contentDeepToStringInternal$ArraysKt__ArraysKt($this$contentDeepToStringImpl, $this$buildString, new ArrayList<Object[]>());
        final String string = $this$buildString.toString();
        Intrinsics.checkExpressionValueIsNotNull(string, "StringBuilder(capacity).\u2026builderAction).toString()");
        return string;
    }
    
    private static final <T> void contentDeepToStringInternal$ArraysKt__ArraysKt(@NotNull final T[] $this$contentDeepToStringInternal, final StringBuilder result, final List<Object[]> processed) {
        // 
        // This method could not be decompiled.
        // 
        // Original Bytecode:
        // 
        //     1: aload_0         /* $this$contentDeepToStringInternal */
        //     2: invokeinterface java/util/List.contains:(Ljava/lang/Object;)Z
        //     7: ifeq            19
        //    10: aload_1         /* result */
        //    11: ldc_w           "[...]"
        //    14: invokevirtual   java/lang/StringBuilder.append:(Ljava/lang/String;)Ljava/lang/StringBuilder;
        //    17: pop            
        //    18: return         
        //    19: aload_2         /* processed */
        //    20: aload_0         /* $this$contentDeepToStringInternal */
        //    21: invokeinterface java/util/List.add:(Ljava/lang/Object;)Z
        //    26: pop            
        //    27: aload_1         /* result */
        //    28: bipush          91
        //    30: invokevirtual   java/lang/StringBuilder.append:(C)Ljava/lang/StringBuilder;
        //    33: pop            
        //    34: iconst_0       
        //    35: istore_3       
        //    36: aload_0         /* $this$contentDeepToStringInternal */
        //    37: arraylength    
        //    38: istore          4
        //    40: iload_3        
        //    41: iload           4
        //    43: if_icmpge       596
        //    46: iload_3         /* i */
        //    47: ifeq            58
        //    50: aload_1         /* result */
        //    51: ldc_w           ", "
        //    54: invokevirtual   java/lang/StringBuilder.append:(Ljava/lang/String;)Ljava/lang/StringBuilder;
        //    57: pop            
        //    58: aload_0         /* $this$contentDeepToStringInternal */
        //    59: iload_3         /* i */
        //    60: aaload         
        //    61: astore          element
        //    63: aload           element
        //    65: astore          6
        //    67: aload           6
        //    69: ifnonnull       83
        //    72: aload_1         /* result */
        //    73: ldc_w           "null"
        //    76: invokevirtual   java/lang/StringBuilder.append:(Ljava/lang/String;)Ljava/lang/StringBuilder;
        //    79: pop            
        //    80: goto            590
        //    83: aload           6
        //    85: instanceof      [Ljava/lang/Object;
        //    88: ifeq            104
        //    91: aload           element
        //    93: checkcast       [Ljava/lang/Object;
        //    96: aload_1         /* result */
        //    97: aload_2         /* processed */
        //    98: invokestatic    kotlin/collections/ArraysKt__ArraysKt.contentDeepToStringInternal$ArraysKt__ArraysKt:([Ljava/lang/Object;Ljava/lang/StringBuilder;Ljava/util/List;)V
        //   101: goto            590
        //   104: aload           6
        //   106: instanceof      [B
        //   109: ifeq            150
        //   112: aload_1         /* result */
        //   113: aload           element
        //   115: checkcast       [B
        //   118: astore          7
        //   120: astore          9
        //   122: iconst_0       
        //   123: istore          8
        //   125: aload           7
        //   127: invokestatic    java/util/Arrays.toString:([B)Ljava/lang/String;
        //   130: dup            
        //   131: ldc_w           "java.util.Arrays.toString(this)"
        //   134: invokestatic    kotlin/jvm/internal/Intrinsics.checkExpressionValueIsNotNull:(Ljava/lang/Object;Ljava/lang/String;)V
        //   137: astore          10
        //   139: aload           9
        //   141: aload           10
        //   143: invokevirtual   java/lang/StringBuilder.append:(Ljava/lang/String;)Ljava/lang/StringBuilder;
        //   146: pop            
        //   147: goto            590
        //   150: aload           6
        //   152: instanceof      [S
        //   155: ifeq            196
        //   158: aload_1         /* result */
        //   159: aload           element
        //   161: checkcast       [S
        //   164: astore          7
        //   166: astore          9
        //   168: iconst_0       
        //   169: istore          8
        //   171: aload           7
        //   173: invokestatic    java/util/Arrays.toString:([S)Ljava/lang/String;
        //   176: dup            
        //   177: ldc_w           "java.util.Arrays.toString(this)"
        //   180: invokestatic    kotlin/jvm/internal/Intrinsics.checkExpressionValueIsNotNull:(Ljava/lang/Object;Ljava/lang/String;)V
        //   183: astore          10
        //   185: aload           9
        //   187: aload           10
        //   189: invokevirtual   java/lang/StringBuilder.append:(Ljava/lang/String;)Ljava/lang/StringBuilder;
        //   192: pop            
        //   193: goto            590
        //   196: aload           6
        //   198: instanceof      [I
        //   201: ifeq            242
        //   204: aload_1         /* result */
        //   205: aload           element
        //   207: checkcast       [I
        //   210: astore          7
        //   212: astore          9
        //   214: iconst_0       
        //   215: istore          8
        //   217: aload           7
        //   219: invokestatic    java/util/Arrays.toString:([I)Ljava/lang/String;
        //   222: dup            
        //   223: ldc_w           "java.util.Arrays.toString(this)"
        //   226: invokestatic    kotlin/jvm/internal/Intrinsics.checkExpressionValueIsNotNull:(Ljava/lang/Object;Ljava/lang/String;)V
        //   229: astore          10
        //   231: aload           9
        //   233: aload           10
        //   235: invokevirtual   java/lang/StringBuilder.append:(Ljava/lang/String;)Ljava/lang/StringBuilder;
        //   238: pop            
        //   239: goto            590
        //   242: aload           6
        //   244: instanceof      [J
        //   247: ifeq            288
        //   250: aload_1         /* result */
        //   251: aload           element
        //   253: checkcast       [J
        //   256: astore          7
        //   258: astore          9
        //   260: iconst_0       
        //   261: istore          8
        //   263: aload           7
        //   265: invokestatic    java/util/Arrays.toString:([J)Ljava/lang/String;
        //   268: dup            
        //   269: ldc_w           "java.util.Arrays.toString(this)"
        //   272: invokestatic    kotlin/jvm/internal/Intrinsics.checkExpressionValueIsNotNull:(Ljava/lang/Object;Ljava/lang/String;)V
        //   275: astore          10
        //   277: aload           9
        //   279: aload           10
        //   281: invokevirtual   java/lang/StringBuilder.append:(Ljava/lang/String;)Ljava/lang/StringBuilder;
        //   284: pop            
        //   285: goto            590
        //   288: aload           6
        //   290: instanceof      [F
        //   293: ifeq            334
        //   296: aload_1         /* result */
        //   297: aload           element
        //   299: checkcast       [F
        //   302: astore          7
        //   304: astore          9
        //   306: iconst_0       
        //   307: istore          8
        //   309: aload           7
        //   311: invokestatic    java/util/Arrays.toString:([F)Ljava/lang/String;
        //   314: dup            
        //   315: ldc_w           "java.util.Arrays.toString(this)"
        //   318: invokestatic    kotlin/jvm/internal/Intrinsics.checkExpressionValueIsNotNull:(Ljava/lang/Object;Ljava/lang/String;)V
        //   321: astore          10
        //   323: aload           9
        //   325: aload           10
        //   327: invokevirtual   java/lang/StringBuilder.append:(Ljava/lang/String;)Ljava/lang/StringBuilder;
        //   330: pop            
        //   331: goto            590
        //   334: aload           6
        //   336: instanceof      [D
        //   339: ifeq            380
        //   342: aload_1         /* result */
        //   343: aload           element
        //   345: checkcast       [D
        //   348: astore          7
        //   350: astore          9
        //   352: iconst_0       
        //   353: istore          8
        //   355: aload           7
        //   357: invokestatic    java/util/Arrays.toString:([D)Ljava/lang/String;
        //   360: dup            
        //   361: ldc_w           "java.util.Arrays.toString(this)"
        //   364: invokestatic    kotlin/jvm/internal/Intrinsics.checkExpressionValueIsNotNull:(Ljava/lang/Object;Ljava/lang/String;)V
        //   367: astore          10
        //   369: aload           9
        //   371: aload           10
        //   373: invokevirtual   java/lang/StringBuilder.append:(Ljava/lang/String;)Ljava/lang/StringBuilder;
        //   376: pop            
        //   377: goto            590
        //   380: aload           6
        //   382: instanceof      [C
        //   385: ifeq            426
        //   388: aload_1         /* result */
        //   389: aload           element
        //   391: checkcast       [C
        //   394: astore          7
        //   396: astore          9
        //   398: iconst_0       
        //   399: istore          8
        //   401: aload           7
        //   403: invokestatic    java/util/Arrays.toString:([C)Ljava/lang/String;
        //   406: dup            
        //   407: ldc_w           "java.util.Arrays.toString(this)"
        //   410: invokestatic    kotlin/jvm/internal/Intrinsics.checkExpressionValueIsNotNull:(Ljava/lang/Object;Ljava/lang/String;)V
        //   413: astore          10
        //   415: aload           9
        //   417: aload           10
        //   419: invokevirtual   java/lang/StringBuilder.append:(Ljava/lang/String;)Ljava/lang/StringBuilder;
        //   422: pop            
        //   423: goto            590
        //   426: aload           6
        //   428: instanceof      [Z
        //   431: ifeq            472
        //   434: aload_1         /* result */
        //   435: aload           element
        //   437: checkcast       [Z
        //   440: astore          7
        //   442: astore          9
        //   444: iconst_0       
        //   445: istore          8
        //   447: aload           7
        //   449: invokestatic    java/util/Arrays.toString:([Z)Ljava/lang/String;
        //   452: dup            
        //   453: ldc_w           "java.util.Arrays.toString(this)"
        //   456: invokestatic    kotlin/jvm/internal/Intrinsics.checkExpressionValueIsNotNull:(Ljava/lang/Object;Ljava/lang/String;)V
        //   459: astore          10
        //   461: aload           9
        //   463: aload           10
        //   465: invokevirtual   java/lang/StringBuilder.append:(Ljava/lang/String;)Ljava/lang/StringBuilder;
        //   468: pop            
        //   469: goto            590
        //   472: aload           6
        //   474: instanceof      Lkotlin/UByteArray;
        //   477: ifeq            499
        //   480: aload_1         /* result */
        //   481: aload           element
        //   483: checkcast       Lkotlin/UByteArray;
        //   486: invokevirtual   kotlin/UByteArray.unbox-impl:()[B
        //   489: invokestatic    kotlin/collections/unsigned/UArraysKt.contentToString-GBYM_sE:([B)Ljava/lang/String;
        //   492: invokevirtual   java/lang/StringBuilder.append:(Ljava/lang/String;)Ljava/lang/StringBuilder;
        //   495: pop            
        //   496: goto            590
        //   499: aload           6
        //   501: instanceof      Lkotlin/UShortArray;
        //   504: ifeq            526
        //   507: aload_1         /* result */
        //   508: aload           element
        //   510: checkcast       Lkotlin/UShortArray;
        //   513: invokevirtual   kotlin/UShortArray.unbox-impl:()[S
        //   516: invokestatic    kotlin/collections/unsigned/UArraysKt.contentToString-rL5Bavg:([S)Ljava/lang/String;
        //   519: invokevirtual   java/lang/StringBuilder.append:(Ljava/lang/String;)Ljava/lang/StringBuilder;
        //   522: pop            
        //   523: goto            590
        //   526: aload           6
        //   528: instanceof      Lkotlin/UIntArray;
        //   531: ifeq            553
        //   534: aload_1         /* result */
        //   535: aload           element
        //   537: checkcast       Lkotlin/UIntArray;
        //   540: invokevirtual   kotlin/UIntArray.unbox-impl:()[I
        //   543: invokestatic    kotlin/collections/unsigned/UArraysKt.contentToString--ajY-9A:([I)Ljava/lang/String;
        //   546: invokevirtual   java/lang/StringBuilder.append:(Ljava/lang/String;)Ljava/lang/StringBuilder;
        //   549: pop            
        //   550: goto            590
        //   553: aload           6
        //   555: instanceof      Lkotlin/ULongArray;
        //   558: ifeq            580
        //   561: aload_1         /* result */
        //   562: aload           element
        //   564: checkcast       Lkotlin/ULongArray;
        //   567: invokevirtual   kotlin/ULongArray.unbox-impl:()[J
        //   570: invokestatic    kotlin/collections/unsigned/UArraysKt.contentToString-QwZRm1k:([J)Ljava/lang/String;
        //   573: invokevirtual   java/lang/StringBuilder.append:(Ljava/lang/String;)Ljava/lang/StringBuilder;
        //   576: pop            
        //   577: goto            590
        //   580: aload_1         /* result */
        //   581: aload           element
        //   583: invokevirtual   java/lang/Object.toString:()Ljava/lang/String;
        //   586: invokevirtual   java/lang/StringBuilder.append:(Ljava/lang/String;)Ljava/lang/StringBuilder;
        //   589: pop            
        //   590: iinc            i, 1
        //   593: goto            40
        //   596: aload_1         /* result */
        //   597: bipush          93
        //   599: invokevirtual   java/lang/StringBuilder.append:(C)Ljava/lang/StringBuilder;
        //   602: pop            
        //   603: aload_2         /* processed */
        //   604: aload_2         /* processed */
        //   605: invokestatic    kotlin/collections/CollectionsKt.getLastIndex:(Ljava/util/List;)I
        //   608: invokeinterface java/util/List.remove:(I)Ljava/lang/Object;
        //   613: pop            
        //   614: return         
        //    Signature:
        //  <T:Ljava/lang/Object;>([TT;Ljava/lang/StringBuilder;Ljava/util/List<[Ljava/lang/Object;>;)V
        //    StackMapTable: 00 13 13 FD 00 14 01 01 11 FD 00 18 07 00 81 07 00 81 14 2D 2D 2D 2D 2D 2D 2D 2D 1A 1A 1A 1A 09 F9 00 05
        // 
        // The error that occurred was:
        // 
        // java.lang.NullPointerException
        // 
        throw new IllegalStateException("An error occurred while decompiling this method.");
    }
    
    public ArraysKt__ArraysKt() {
    }
}
