// 
// Decompiled by Procyon v0.5.36
// 

package kotlin.collections;

import java.util.Set;
import java.util.List;
import java.util.Collection;
import kotlin.sequences.Sequence;
import kotlin.jvm.functions.Function1;
import kotlin.jvm.JvmName;
import java.util.Iterator;
import kotlin.jvm.internal.TypeIntrinsics;
import kotlin.jvm.functions.Function0;
import org.jetbrains.annotations.Nullable;
import kotlin.PublishedApi;
import java.util.HashMap;
import kotlin.SinceKotlin;
import kotlin.internal.InlineOnly;
import java.util.LinkedHashMap;
import kotlin.jvm.internal.Intrinsics;
import kotlin.Pair;
import org.jetbrains.annotations.NotNull;
import kotlin.TypeCastException;
import java.util.Map;
import kotlin.Metadata;

@Metadata(mv = { 1, 1, 15 }, bv = { 1, 0, 3 }, k = 5, xi = 1, d1 = { "\u0000~\n\u0000\n\u0002\u0010\b\n\u0000\n\u0002\u0010$\n\u0002\b\u0003\n\u0002\u0018\u0002\n\u0002\u0018\u0002\n\u0000\n\u0002\u0010\u0011\n\u0002\u0018\u0002\n\u0002\b\u0002\n\u0002\u0018\u0002\n\u0002\u0018\u0002\n\u0002\b\u0006\n\u0002\u0010%\n\u0000\n\u0002\u0010&\n\u0002\b\u0003\n\u0002\u0010\u000b\n\u0002\u0018\u0002\n\u0002\b\u0007\n\u0002\u0018\u0002\n\u0002\b\f\n\u0002\u0018\u0002\n\u0002\b\n\n\u0002\u0010(\n\u0002\u0010)\n\u0002\u0010'\n\u0002\b\n\n\u0002\u0010\u001c\n\u0002\u0018\u0002\n\u0000\n\u0002\u0010\u0002\n\u0002\b\u0016\u001a\u001e\u0010\u0002\u001a\u000e\u0012\u0004\u0012\u0002H\u0004\u0012\u0004\u0012\u0002H\u00050\u0003\"\u0004\b\u0000\u0010\u0004\"\u0004\b\u0001\u0010\u0005\u001a1\u0010\u0006\u001a\u001e\u0012\u0004\u0012\u0002H\u0004\u0012\u0004\u0012\u0002H\u00050\u0007j\u000e\u0012\u0004\u0012\u0002H\u0004\u0012\u0004\u0012\u0002H\u0005`\b\"\u0004\b\u0000\u0010\u0004\"\u0004\b\u0001\u0010\u0005H\u0087\b\u001a_\u0010\u0006\u001a\u001e\u0012\u0004\u0012\u0002H\u0004\u0012\u0004\u0012\u0002H\u00050\u0007j\u000e\u0012\u0004\u0012\u0002H\u0004\u0012\u0004\u0012\u0002H\u0005`\b\"\u0004\b\u0000\u0010\u0004\"\u0004\b\u0001\u0010\u00052*\u0010\t\u001a\u0016\u0012\u0012\b\u0001\u0012\u000e\u0012\u0004\u0012\u0002H\u0004\u0012\u0004\u0012\u0002H\u00050\u000b0\n\"\u000e\u0012\u0004\u0012\u0002H\u0004\u0012\u0004\u0012\u0002H\u00050\u000b¢\u0006\u0002\u0010\f\u001a1\u0010\r\u001a\u001e\u0012\u0004\u0012\u0002H\u0004\u0012\u0004\u0012\u0002H\u00050\u000ej\u000e\u0012\u0004\u0012\u0002H\u0004\u0012\u0004\u0012\u0002H\u0005`\u000f\"\u0004\b\u0000\u0010\u0004\"\u0004\b\u0001\u0010\u0005H\u0087\b\u001a_\u0010\r\u001a\u001e\u0012\u0004\u0012\u0002H\u0004\u0012\u0004\u0012\u0002H\u00050\u000ej\u000e\u0012\u0004\u0012\u0002H\u0004\u0012\u0004\u0012\u0002H\u0005`\u000f\"\u0004\b\u0000\u0010\u0004\"\u0004\b\u0001\u0010\u00052*\u0010\t\u001a\u0016\u0012\u0012\b\u0001\u0012\u000e\u0012\u0004\u0012\u0002H\u0004\u0012\u0004\u0012\u0002H\u00050\u000b0\n\"\u000e\u0012\u0004\u0012\u0002H\u0004\u0012\u0004\u0012\u0002H\u00050\u000b¢\u0006\u0002\u0010\u0010\u001a\u0010\u0010\u0011\u001a\u00020\u00012\u0006\u0010\u0012\u001a\u00020\u0001H\u0001\u001a!\u0010\u0013\u001a\u000e\u0012\u0004\u0012\u0002H\u0004\u0012\u0004\u0012\u0002H\u00050\u0003\"\u0004\b\u0000\u0010\u0004\"\u0004\b\u0001\u0010\u0005H\u0087\b\u001aO\u0010\u0013\u001a\u000e\u0012\u0004\u0012\u0002H\u0004\u0012\u0004\u0012\u0002H\u00050\u0003\"\u0004\b\u0000\u0010\u0004\"\u0004\b\u0001\u0010\u00052*\u0010\t\u001a\u0016\u0012\u0012\b\u0001\u0012\u000e\u0012\u0004\u0012\u0002H\u0004\u0012\u0004\u0012\u0002H\u00050\u000b0\n\"\u000e\u0012\u0004\u0012\u0002H\u0004\u0012\u0004\u0012\u0002H\u00050\u000b¢\u0006\u0002\u0010\u0014\u001a!\u0010\u0015\u001a\u000e\u0012\u0004\u0012\u0002H\u0004\u0012\u0004\u0012\u0002H\u00050\u0016\"\u0004\b\u0000\u0010\u0004\"\u0004\b\u0001\u0010\u0005H\u0087\b\u001aO\u0010\u0015\u001a\u000e\u0012\u0004\u0012\u0002H\u0004\u0012\u0004\u0012\u0002H\u00050\u0016\"\u0004\b\u0000\u0010\u0004\"\u0004\b\u0001\u0010\u00052*\u0010\t\u001a\u0016\u0012\u0012\b\u0001\u0012\u000e\u0012\u0004\u0012\u0002H\u0004\u0012\u0004\u0012\u0002H\u00050\u000b0\n\"\u000e\u0012\u0004\u0012\u0002H\u0004\u0012\u0004\u0012\u0002H\u00050\u000b¢\u0006\u0002\u0010\u0014\u001a*\u0010\u0017\u001a\u0002H\u0004\"\u0004\b\u0000\u0010\u0004\"\u0004\b\u0001\u0010\u0005*\u000e\u0012\u0004\u0012\u0002H\u0004\u0012\u0004\u0012\u0002H\u00050\u0018H\u0087\n¢\u0006\u0002\u0010\u0019\u001a*\u0010\u001a\u001a\u0002H\u0005\"\u0004\b\u0000\u0010\u0004\"\u0004\b\u0001\u0010\u0005*\u000e\u0012\u0004\u0012\u0002H\u0004\u0012\u0004\u0012\u0002H\u00050\u0018H\u0087\n¢\u0006\u0002\u0010\u0019\u001a9\u0010\u001b\u001a\u00020\u001c\"\t\b\u0000\u0010\u0004¢\u0006\u0002\b\u001d\"\u0004\b\u0001\u0010\u0005*\u0010\u0012\u0006\b\u0001\u0012\u0002H\u0004\u0012\u0004\u0012\u0002H\u00050\u00032\u0006\u0010\u001e\u001a\u0002H\u0004H\u0087\n¢\u0006\u0002\u0010\u001f\u001a1\u0010 \u001a\u00020\u001c\"\t\b\u0000\u0010\u0004¢\u0006\u0002\b\u001d*\u000e\u0012\u0006\b\u0001\u0012\u0002H\u0004\u0012\u0002\b\u00030\u00032\u0006\u0010\u001e\u001a\u0002H\u0004H\u0087\b¢\u0006\u0002\u0010\u001f\u001a7\u0010!\u001a\u00020\u001c\"\u0004\b\u0000\u0010\u0004\"\t\b\u0001\u0010\u0005¢\u0006\u0002\b\u001d*\u000e\u0012\u0004\u0012\u0002H\u0004\u0012\u0004\u0012\u0002H\u00050\u00032\u0006\u0010\"\u001a\u0002H\u0005H\u0087\b¢\u0006\u0002\u0010\u001f\u001aS\u0010#\u001a\u000e\u0012\u0004\u0012\u0002H\u0004\u0012\u0004\u0012\u0002H\u00050\u0003\"\u0004\b\u0000\u0010\u0004\"\u0004\b\u0001\u0010\u0005*\u0010\u0012\u0006\b\u0001\u0012\u0002H\u0004\u0012\u0004\u0012\u0002H\u00050\u00032\u001e\u0010$\u001a\u001a\u0012\u0010\u0012\u000e\u0012\u0004\u0012\u0002H\u0004\u0012\u0004\u0012\u0002H\u00050\u0018\u0012\u0004\u0012\u00020\u001c0%H\u0086\b\u001aG\u0010&\u001a\u000e\u0012\u0004\u0012\u0002H\u0004\u0012\u0004\u0012\u0002H\u00050\u0003\"\u0004\b\u0000\u0010\u0004\"\u0004\b\u0001\u0010\u0005*\u0010\u0012\u0006\b\u0001\u0012\u0002H\u0004\u0012\u0004\u0012\u0002H\u00050\u00032\u0012\u0010$\u001a\u000e\u0012\u0004\u0012\u0002H\u0004\u0012\u0004\u0012\u00020\u001c0%H\u0086\b\u001aS\u0010'\u001a\u000e\u0012\u0004\u0012\u0002H\u0004\u0012\u0004\u0012\u0002H\u00050\u0003\"\u0004\b\u0000\u0010\u0004\"\u0004\b\u0001\u0010\u0005*\u0010\u0012\u0006\b\u0001\u0012\u0002H\u0004\u0012\u0004\u0012\u0002H\u00050\u00032\u001e\u0010$\u001a\u001a\u0012\u0010\u0012\u000e\u0012\u0004\u0012\u0002H\u0004\u0012\u0004\u0012\u0002H\u00050\u0018\u0012\u0004\u0012\u00020\u001c0%H\u0086\b\u001an\u0010(\u001a\u0002H)\"\u0004\b\u0000\u0010\u0004\"\u0004\b\u0001\u0010\u0005\"\u0018\b\u0002\u0010)*\u0012\u0012\u0006\b\u0000\u0012\u0002H\u0004\u0012\u0006\b\u0000\u0012\u0002H\u00050\u0016*\u0010\u0012\u0006\b\u0001\u0012\u0002H\u0004\u0012\u0004\u0012\u0002H\u00050\u00032\u0006\u0010*\u001a\u0002H)2\u001e\u0010$\u001a\u001a\u0012\u0010\u0012\u000e\u0012\u0004\u0012\u0002H\u0004\u0012\u0004\u0012\u0002H\u00050\u0018\u0012\u0004\u0012\u00020\u001c0%H\u0086\b¢\u0006\u0002\u0010+\u001an\u0010,\u001a\u0002H)\"\u0004\b\u0000\u0010\u0004\"\u0004\b\u0001\u0010\u0005\"\u0018\b\u0002\u0010)*\u0012\u0012\u0006\b\u0000\u0012\u0002H\u0004\u0012\u0006\b\u0000\u0012\u0002H\u00050\u0016*\u0010\u0012\u0006\b\u0001\u0012\u0002H\u0004\u0012\u0004\u0012\u0002H\u00050\u00032\u0006\u0010*\u001a\u0002H)2\u001e\u0010$\u001a\u001a\u0012\u0010\u0012\u000e\u0012\u0004\u0012\u0002H\u0004\u0012\u0004\u0012\u0002H\u00050\u0018\u0012\u0004\u0012\u00020\u001c0%H\u0086\b¢\u0006\u0002\u0010+\u001aG\u0010-\u001a\u000e\u0012\u0004\u0012\u0002H\u0004\u0012\u0004\u0012\u0002H\u00050\u0003\"\u0004\b\u0000\u0010\u0004\"\u0004\b\u0001\u0010\u0005*\u0010\u0012\u0006\b\u0001\u0012\u0002H\u0004\u0012\u0004\u0012\u0002H\u00050\u00032\u0012\u0010$\u001a\u000e\u0012\u0004\u0012\u0002H\u0005\u0012\u0004\u0012\u00020\u001c0%H\u0086\b\u001a;\u0010.\u001a\u0004\u0018\u0001H\u0005\"\t\b\u0000\u0010\u0004¢\u0006\u0002\b\u001d\"\u0004\b\u0001\u0010\u0005*\u0010\u0012\u0006\b\u0001\u0012\u0002H\u0004\u0012\u0004\u0012\u0002H\u00050\u00032\u0006\u0010\u001e\u001a\u0002H\u0004H\u0087\n¢\u0006\u0002\u0010/\u001a@\u00100\u001a\u0002H\u0005\"\u0004\b\u0000\u0010\u0004\"\u0004\b\u0001\u0010\u0005*\u000e\u0012\u0004\u0012\u0002H\u0004\u0012\u0004\u0012\u0002H\u00050\u00032\u0006\u0010\u001e\u001a\u0002H\u00042\f\u00101\u001a\b\u0012\u0004\u0012\u0002H\u000502H\u0087\b¢\u0006\u0002\u00103\u001a@\u00104\u001a\u0002H\u0005\"\u0004\b\u0000\u0010\u0004\"\u0004\b\u0001\u0010\u0005*\u000e\u0012\u0004\u0012\u0002H\u0004\u0012\u0004\u0012\u0002H\u00050\u00032\u0006\u0010\u001e\u001a\u0002H\u00042\f\u00101\u001a\b\u0012\u0004\u0012\u0002H\u000502H\u0080\b¢\u0006\u0002\u00103\u001a@\u00105\u001a\u0002H\u0005\"\u0004\b\u0000\u0010\u0004\"\u0004\b\u0001\u0010\u0005*\u000e\u0012\u0004\u0012\u0002H\u0004\u0012\u0004\u0012\u0002H\u00050\u00162\u0006\u0010\u001e\u001a\u0002H\u00042\f\u00101\u001a\b\u0012\u0004\u0012\u0002H\u000502H\u0086\b¢\u0006\u0002\u00103\u001a1\u00106\u001a\u0002H\u0005\"\u0004\b\u0000\u0010\u0004\"\u0004\b\u0001\u0010\u0005*\u000e\u0012\u0004\u0012\u0002H\u0004\u0012\u0004\u0012\u0002H\u00050\u00032\u0006\u0010\u001e\u001a\u0002H\u0004H\u0007¢\u0006\u0002\u0010/\u001a<\u00107\u001a\u0002H8\"\u0014\b\u0000\u0010)*\n\u0012\u0002\b\u0003\u0012\u0002\b\u00030\u0003*\u0002H8\"\u0004\b\u0001\u00108*\u0002H)2\f\u00101\u001a\b\u0012\u0004\u0012\u0002H802H\u0087\b¢\u0006\u0002\u00109\u001a'\u0010:\u001a\u00020\u001c\"\u0004\b\u0000\u0010\u0004\"\u0004\b\u0001\u0010\u0005*\u0010\u0012\u0006\b\u0001\u0012\u0002H\u0004\u0012\u0004\u0012\u0002H\u00050\u0003H\u0087\b\u001a:\u0010;\u001a\u00020\u001c\"\u0004\b\u0000\u0010\u0004\"\u0004\b\u0001\u0010\u0005*\u0012\u0012\u0006\b\u0001\u0012\u0002H\u0004\u0012\u0004\u0012\u0002H\u0005\u0018\u00010\u0003H\u0087\b\u0082\u0002\u000e\n\f\b\u0000\u0012\u0002\u0018\u0001\u001a\u0004\b\u0003\u0010\u0000\u001a9\u0010<\u001a\u0014\u0012\u0010\u0012\u000e\u0012\u0004\u0012\u0002H\u0004\u0012\u0004\u0012\u0002H\u00050\u00180=\"\u0004\b\u0000\u0010\u0004\"\u0004\b\u0001\u0010\u0005*\u0010\u0012\u0006\b\u0001\u0012\u0002H\u0004\u0012\u0004\u0012\u0002H\u00050\u0003H\u0087\n\u001a<\u0010<\u001a\u0014\u0012\u0010\u0012\u000e\u0012\u0004\u0012\u0002H\u0004\u0012\u0004\u0012\u0002H\u00050?0>\"\u0004\b\u0000\u0010\u0004\"\u0004\b\u0001\u0010\u0005*\u000e\u0012\u0004\u0012\u0002H\u0004\u0012\u0004\u0012\u0002H\u00050\u0016H\u0087\n¢\u0006\u0002\b@\u001aY\u0010A\u001a\u000e\u0012\u0004\u0012\u0002H8\u0012\u0004\u0012\u0002H\u00050\u0003\"\u0004\b\u0000\u0010\u0004\"\u0004\b\u0001\u0010\u0005\"\u0004\b\u0002\u00108*\u0010\u0012\u0006\b\u0001\u0012\u0002H\u0004\u0012\u0004\u0012\u0002H\u00050\u00032\u001e\u0010B\u001a\u001a\u0012\u0010\u0012\u000e\u0012\u0004\u0012\u0002H\u0004\u0012\u0004\u0012\u0002H\u00050\u0018\u0012\u0004\u0012\u0002H80%H\u0086\b\u001at\u0010C\u001a\u0002H)\"\u0004\b\u0000\u0010\u0004\"\u0004\b\u0001\u0010\u0005\"\u0004\b\u0002\u00108\"\u0018\b\u0003\u0010)*\u0012\u0012\u0006\b\u0000\u0012\u0002H8\u0012\u0006\b\u0000\u0012\u0002H\u00050\u0016*\u0010\u0012\u0006\b\u0001\u0012\u0002H\u0004\u0012\u0004\u0012\u0002H\u00050\u00032\u0006\u0010*\u001a\u0002H)2\u001e\u0010B\u001a\u001a\u0012\u0010\u0012\u000e\u0012\u0004\u0012\u0002H\u0004\u0012\u0004\u0012\u0002H\u00050\u0018\u0012\u0004\u0012\u0002H80%H\u0086\b¢\u0006\u0002\u0010+\u001aY\u0010D\u001a\u000e\u0012\u0004\u0012\u0002H\u0004\u0012\u0004\u0012\u0002H80\u0003\"\u0004\b\u0000\u0010\u0004\"\u0004\b\u0001\u0010\u0005\"\u0004\b\u0002\u00108*\u0010\u0012\u0006\b\u0001\u0012\u0002H\u0004\u0012\u0004\u0012\u0002H\u00050\u00032\u001e\u0010B\u001a\u001a\u0012\u0010\u0012\u000e\u0012\u0004\u0012\u0002H\u0004\u0012\u0004\u0012\u0002H\u00050\u0018\u0012\u0004\u0012\u0002H80%H\u0086\b\u001at\u0010E\u001a\u0002H)\"\u0004\b\u0000\u0010\u0004\"\u0004\b\u0001\u0010\u0005\"\u0004\b\u0002\u00108\"\u0018\b\u0003\u0010)*\u0012\u0012\u0006\b\u0000\u0012\u0002H\u0004\u0012\u0006\b\u0000\u0012\u0002H80\u0016*\u0010\u0012\u0006\b\u0001\u0012\u0002H\u0004\u0012\u0004\u0012\u0002H\u00050\u00032\u0006\u0010*\u001a\u0002H)2\u001e\u0010B\u001a\u001a\u0012\u0010\u0012\u000e\u0012\u0004\u0012\u0002H\u0004\u0012\u0004\u0012\u0002H\u00050\u0018\u0012\u0004\u0012\u0002H80%H\u0086\b¢\u0006\u0002\u0010+\u001a@\u0010F\u001a\u000e\u0012\u0004\u0012\u0002H\u0004\u0012\u0004\u0012\u0002H\u00050\u0003\"\u0004\b\u0000\u0010\u0004\"\u0004\b\u0001\u0010\u0005*\u0010\u0012\u0006\b\u0001\u0012\u0002H\u0004\u0012\u0004\u0012\u0002H\u00050\u00032\u0006\u0010\u001e\u001a\u0002H\u0004H\u0087\u0002¢\u0006\u0002\u0010G\u001aH\u0010F\u001a\u000e\u0012\u0004\u0012\u0002H\u0004\u0012\u0004\u0012\u0002H\u00050\u0003\"\u0004\b\u0000\u0010\u0004\"\u0004\b\u0001\u0010\u0005*\u0010\u0012\u0006\b\u0001\u0012\u0002H\u0004\u0012\u0004\u0012\u0002H\u00050\u00032\u000e\u0010H\u001a\n\u0012\u0006\b\u0001\u0012\u0002H\u00040\nH\u0087\u0002¢\u0006\u0002\u0010I\u001aA\u0010F\u001a\u000e\u0012\u0004\u0012\u0002H\u0004\u0012\u0004\u0012\u0002H\u00050\u0003\"\u0004\b\u0000\u0010\u0004\"\u0004\b\u0001\u0010\u0005*\u0010\u0012\u0006\b\u0001\u0012\u0002H\u0004\u0012\u0004\u0012\u0002H\u00050\u00032\f\u0010H\u001a\b\u0012\u0004\u0012\u0002H\u00040JH\u0087\u0002\u001aA\u0010F\u001a\u000e\u0012\u0004\u0012\u0002H\u0004\u0012\u0004\u0012\u0002H\u00050\u0003\"\u0004\b\u0000\u0010\u0004\"\u0004\b\u0001\u0010\u0005*\u0010\u0012\u0006\b\u0001\u0012\u0002H\u0004\u0012\u0004\u0012\u0002H\u00050\u00032\f\u0010H\u001a\b\u0012\u0004\u0012\u0002H\u00040KH\u0087\u0002\u001a2\u0010L\u001a\u00020M\"\u0004\b\u0000\u0010\u0004\"\u0004\b\u0001\u0010\u0005*\u000e\u0012\u0004\u0012\u0002H\u0004\u0012\u0004\u0012\u0002H\u00050\u00162\u0006\u0010\u001e\u001a\u0002H\u0004H\u0087\n¢\u0006\u0002\u0010N\u001a:\u0010L\u001a\u00020M\"\u0004\b\u0000\u0010\u0004\"\u0004\b\u0001\u0010\u0005*\u000e\u0012\u0004\u0012\u0002H\u0004\u0012\u0004\u0012\u0002H\u00050\u00162\u000e\u0010H\u001a\n\u0012\u0006\b\u0001\u0012\u0002H\u00040\nH\u0087\n¢\u0006\u0002\u0010O\u001a3\u0010L\u001a\u00020M\"\u0004\b\u0000\u0010\u0004\"\u0004\b\u0001\u0010\u0005*\u000e\u0012\u0004\u0012\u0002H\u0004\u0012\u0004\u0012\u0002H\u00050\u00162\f\u0010H\u001a\b\u0012\u0004\u0012\u0002H\u00040JH\u0087\n\u001a3\u0010L\u001a\u00020M\"\u0004\b\u0000\u0010\u0004\"\u0004\b\u0001\u0010\u0005*\u000e\u0012\u0004\u0012\u0002H\u0004\u0012\u0004\u0012\u0002H\u00050\u00162\f\u0010H\u001a\b\u0012\u0004\u0012\u0002H\u00040KH\u0087\n\u001a0\u0010P\u001a\u000e\u0012\u0004\u0012\u0002H\u0004\u0012\u0004\u0012\u0002H\u00050\u0003\"\u0004\b\u0000\u0010\u0004\"\u0004\b\u0001\u0010\u0005*\u000e\u0012\u0004\u0012\u0002H\u0004\u0012\u0004\u0012\u0002H\u00050\u0003H\u0000\u001a3\u0010Q\u001a\u000e\u0012\u0004\u0012\u0002H\u0004\u0012\u0004\u0012\u0002H\u00050\u0003\"\u0004\b\u0000\u0010\u0004\"\u0004\b\u0001\u0010\u0005*\u0010\u0012\u0004\u0012\u0002H\u0004\u0012\u0004\u0012\u0002H\u0005\u0018\u00010\u0003H\u0087\b\u001aT\u0010R\u001a\u000e\u0012\u0004\u0012\u0002H\u0004\u0012\u0004\u0012\u0002H\u00050\u0003\"\u0004\b\u0000\u0010\u0004\"\u0004\b\u0001\u0010\u0005*\u0010\u0012\u0006\b\u0001\u0012\u0002H\u0004\u0012\u0004\u0012\u0002H\u00050\u00032\u001a\u0010\t\u001a\u0016\u0012\u0012\b\u0001\u0012\u000e\u0012\u0004\u0012\u0002H\u0004\u0012\u0004\u0012\u0002H\u00050\u000b0\nH\u0086\u0002¢\u0006\u0002\u0010S\u001aG\u0010R\u001a\u000e\u0012\u0004\u0012\u0002H\u0004\u0012\u0004\u0012\u0002H\u00050\u0003\"\u0004\b\u0000\u0010\u0004\"\u0004\b\u0001\u0010\u0005*\u0010\u0012\u0006\b\u0001\u0012\u0002H\u0004\u0012\u0004\u0012\u0002H\u00050\u00032\u0012\u0010T\u001a\u000e\u0012\u0004\u0012\u0002H\u0004\u0012\u0004\u0012\u0002H\u00050\u000bH\u0086\u0002\u001aM\u0010R\u001a\u000e\u0012\u0004\u0012\u0002H\u0004\u0012\u0004\u0012\u0002H\u00050\u0003\"\u0004\b\u0000\u0010\u0004\"\u0004\b\u0001\u0010\u0005*\u0010\u0012\u0006\b\u0001\u0012\u0002H\u0004\u0012\u0004\u0012\u0002H\u00050\u00032\u0018\u0010\t\u001a\u0014\u0012\u0010\u0012\u000e\u0012\u0004\u0012\u0002H\u0004\u0012\u0004\u0012\u0002H\u00050\u000b0JH\u0086\u0002\u001aI\u0010R\u001a\u000e\u0012\u0004\u0012\u0002H\u0004\u0012\u0004\u0012\u0002H\u00050\u0003\"\u0004\b\u0000\u0010\u0004\"\u0004\b\u0001\u0010\u0005*\u0010\u0012\u0006\b\u0001\u0012\u0002H\u0004\u0012\u0004\u0012\u0002H\u00050\u00032\u0014\u0010U\u001a\u0010\u0012\u0006\b\u0001\u0012\u0002H\u0004\u0012\u0004\u0012\u0002H\u00050\u0003H\u0086\u0002\u001aM\u0010R\u001a\u000e\u0012\u0004\u0012\u0002H\u0004\u0012\u0004\u0012\u0002H\u00050\u0003\"\u0004\b\u0000\u0010\u0004\"\u0004\b\u0001\u0010\u0005*\u0010\u0012\u0006\b\u0001\u0012\u0002H\u0004\u0012\u0004\u0012\u0002H\u00050\u00032\u0018\u0010\t\u001a\u0014\u0012\u0010\u0012\u000e\u0012\u0004\u0012\u0002H\u0004\u0012\u0004\u0012\u0002H\u00050\u000b0KH\u0086\u0002\u001aJ\u0010V\u001a\u00020M\"\u0004\b\u0000\u0010\u0004\"\u0004\b\u0001\u0010\u0005*\u0012\u0012\u0006\b\u0000\u0012\u0002H\u0004\u0012\u0006\b\u0000\u0012\u0002H\u00050\u00162\u001a\u0010\t\u001a\u0016\u0012\u0012\b\u0001\u0012\u000e\u0012\u0004\u0012\u0002H\u0004\u0012\u0004\u0012\u0002H\u00050\u000b0\nH\u0087\n¢\u0006\u0002\u0010W\u001a=\u0010V\u001a\u00020M\"\u0004\b\u0000\u0010\u0004\"\u0004\b\u0001\u0010\u0005*\u0012\u0012\u0006\b\u0000\u0012\u0002H\u0004\u0012\u0006\b\u0000\u0012\u0002H\u00050\u00162\u0012\u0010T\u001a\u000e\u0012\u0004\u0012\u0002H\u0004\u0012\u0004\u0012\u0002H\u00050\u000bH\u0087\n\u001aC\u0010V\u001a\u00020M\"\u0004\b\u0000\u0010\u0004\"\u0004\b\u0001\u0010\u0005*\u0012\u0012\u0006\b\u0000\u0012\u0002H\u0004\u0012\u0006\b\u0000\u0012\u0002H\u00050\u00162\u0018\u0010\t\u001a\u0014\u0012\u0010\u0012\u000e\u0012\u0004\u0012\u0002H\u0004\u0012\u0004\u0012\u0002H\u00050\u000b0JH\u0087\n\u001a=\u0010V\u001a\u00020M\"\u0004\b\u0000\u0010\u0004\"\u0004\b\u0001\u0010\u0005*\u0012\u0012\u0006\b\u0000\u0012\u0002H\u0004\u0012\u0006\b\u0000\u0012\u0002H\u00050\u00162\u0012\u0010U\u001a\u000e\u0012\u0004\u0012\u0002H\u0004\u0012\u0004\u0012\u0002H\u00050\u0003H\u0087\n\u001aC\u0010V\u001a\u00020M\"\u0004\b\u0000\u0010\u0004\"\u0004\b\u0001\u0010\u0005*\u0012\u0012\u0006\b\u0000\u0012\u0002H\u0004\u0012\u0006\b\u0000\u0012\u0002H\u00050\u00162\u0018\u0010\t\u001a\u0014\u0012\u0010\u0012\u000e\u0012\u0004\u0012\u0002H\u0004\u0012\u0004\u0012\u0002H\u00050\u000b0KH\u0087\n\u001aG\u0010X\u001a\u00020M\"\u0004\b\u0000\u0010\u0004\"\u0004\b\u0001\u0010\u0005*\u0012\u0012\u0006\b\u0000\u0012\u0002H\u0004\u0012\u0006\b\u0000\u0012\u0002H\u00050\u00162\u001a\u0010\t\u001a\u0016\u0012\u0012\b\u0001\u0012\u000e\u0012\u0004\u0012\u0002H\u0004\u0012\u0004\u0012\u0002H\u00050\u000b0\n¢\u0006\u0002\u0010W\u001a@\u0010X\u001a\u00020M\"\u0004\b\u0000\u0010\u0004\"\u0004\b\u0001\u0010\u0005*\u0012\u0012\u0006\b\u0000\u0012\u0002H\u0004\u0012\u0006\b\u0000\u0012\u0002H\u00050\u00162\u0018\u0010\t\u001a\u0014\u0012\u0010\u0012\u000e\u0012\u0004\u0012\u0002H\u0004\u0012\u0004\u0012\u0002H\u00050\u000b0J\u001a@\u0010X\u001a\u00020M\"\u0004\b\u0000\u0010\u0004\"\u0004\b\u0001\u0010\u0005*\u0012\u0012\u0006\b\u0000\u0012\u0002H\u0004\u0012\u0006\b\u0000\u0012\u0002H\u00050\u00162\u0018\u0010\t\u001a\u0014\u0012\u0010\u0012\u000e\u0012\u0004\u0012\u0002H\u0004\u0012\u0004\u0012\u0002H\u00050\u000b0K\u001a;\u0010Y\u001a\u0004\u0018\u0001H\u0005\"\t\b\u0000\u0010\u0004¢\u0006\u0002\b\u001d\"\u0004\b\u0001\u0010\u0005*\u0010\u0012\u0006\b\u0001\u0012\u0002H\u0004\u0012\u0004\u0012\u0002H\u00050\u00162\u0006\u0010\u001e\u001a\u0002H\u0004H\u0087\b¢\u0006\u0002\u0010/\u001a:\u0010Z\u001a\u00020M\"\u0004\b\u0000\u0010\u0004\"\u0004\b\u0001\u0010\u0005*\u000e\u0012\u0004\u0012\u0002H\u0004\u0012\u0004\u0012\u0002H\u00050\u00162\u0006\u0010\u001e\u001a\u0002H\u00042\u0006\u0010\"\u001a\u0002H\u0005H\u0087\n¢\u0006\u0002\u0010[\u001a;\u0010\\\u001a\u000e\u0012\u0004\u0012\u0002H\u0004\u0012\u0004\u0012\u0002H\u00050\u0003\"\u0004\b\u0000\u0010\u0004\"\u0004\b\u0001\u0010\u0005*\u0016\u0012\u0012\b\u0001\u0012\u000e\u0012\u0004\u0012\u0002H\u0004\u0012\u0004\u0012\u0002H\u00050\u000b0\n¢\u0006\u0002\u0010\u0014\u001aQ\u0010\\\u001a\u0002H)\"\u0004\b\u0000\u0010\u0004\"\u0004\b\u0001\u0010\u0005\"\u0018\b\u0002\u0010)*\u0012\u0012\u0006\b\u0000\u0012\u0002H\u0004\u0012\u0006\b\u0000\u0012\u0002H\u00050\u0016*\u0016\u0012\u0012\b\u0001\u0012\u000e\u0012\u0004\u0012\u0002H\u0004\u0012\u0004\u0012\u0002H\u00050\u000b0\n2\u0006\u0010*\u001a\u0002H)¢\u0006\u0002\u0010]\u001a4\u0010\\\u001a\u000e\u0012\u0004\u0012\u0002H\u0004\u0012\u0004\u0012\u0002H\u00050\u0003\"\u0004\b\u0000\u0010\u0004\"\u0004\b\u0001\u0010\u0005*\u0014\u0012\u0010\u0012\u000e\u0012\u0004\u0012\u0002H\u0004\u0012\u0004\u0012\u0002H\u00050\u000b0J\u001aO\u0010\\\u001a\u0002H)\"\u0004\b\u0000\u0010\u0004\"\u0004\b\u0001\u0010\u0005\"\u0018\b\u0002\u0010)*\u0012\u0012\u0006\b\u0000\u0012\u0002H\u0004\u0012\u0006\b\u0000\u0012\u0002H\u00050\u0016*\u0014\u0012\u0010\u0012\u000e\u0012\u0004\u0012\u0002H\u0004\u0012\u0004\u0012\u0002H\u00050\u000b0J2\u0006\u0010*\u001a\u0002H)¢\u0006\u0002\u0010^\u001a2\u0010\\\u001a\u000e\u0012\u0004\u0012\u0002H\u0004\u0012\u0004\u0012\u0002H\u00050\u0003\"\u0004\b\u0000\u0010\u0004\"\u0004\b\u0001\u0010\u0005*\u0010\u0012\u0006\b\u0001\u0012\u0002H\u0004\u0012\u0004\u0012\u0002H\u00050\u0003H\u0007\u001aM\u0010\\\u001a\u0002H)\"\u0004\b\u0000\u0010\u0004\"\u0004\b\u0001\u0010\u0005\"\u0018\b\u0002\u0010)*\u0012\u0012\u0006\b\u0000\u0012\u0002H\u0004\u0012\u0006\b\u0000\u0012\u0002H\u00050\u0016*\u0010\u0012\u0006\b\u0001\u0012\u0002H\u0004\u0012\u0004\u0012\u0002H\u00050\u00032\u0006\u0010*\u001a\u0002H)H\u0007¢\u0006\u0002\u0010_\u001a4\u0010\\\u001a\u000e\u0012\u0004\u0012\u0002H\u0004\u0012\u0004\u0012\u0002H\u00050\u0003\"\u0004\b\u0000\u0010\u0004\"\u0004\b\u0001\u0010\u0005*\u0014\u0012\u0010\u0012\u000e\u0012\u0004\u0012\u0002H\u0004\u0012\u0004\u0012\u0002H\u00050\u000b0K\u001aO\u0010\\\u001a\u0002H)\"\u0004\b\u0000\u0010\u0004\"\u0004\b\u0001\u0010\u0005\"\u0018\b\u0002\u0010)*\u0012\u0012\u0006\b\u0000\u0012\u0002H\u0004\u0012\u0006\b\u0000\u0012\u0002H\u00050\u0016*\u0014\u0012\u0010\u0012\u000e\u0012\u0004\u0012\u0002H\u0004\u0012\u0004\u0012\u0002H\u00050\u000b0K2\u0006\u0010*\u001a\u0002H)¢\u0006\u0002\u0010`\u001a2\u0010a\u001a\u000e\u0012\u0004\u0012\u0002H\u0004\u0012\u0004\u0012\u0002H\u00050\u0016\"\u0004\b\u0000\u0010\u0004\"\u0004\b\u0001\u0010\u0005*\u0010\u0012\u0006\b\u0001\u0012\u0002H\u0004\u0012\u0004\u0012\u0002H\u00050\u0003H\u0007\u001a1\u0010b\u001a\u000e\u0012\u0004\u0012\u0002H\u0004\u0012\u0004\u0012\u0002H\u00050\u000b\"\u0004\b\u0000\u0010\u0004\"\u0004\b\u0001\u0010\u0005*\u000e\u0012\u0004\u0012\u0002H\u0004\u0012\u0004\u0012\u0002H\u00050\u0018H\u0087\b\"\u000e\u0010\u0000\u001a\u00020\u0001X\u0082T¢\u0006\u0002\n\u0000¨\u0006c" }, d2 = { "INT_MAX_POWER_OF_TWO", "", "emptyMap", "", "K", "V", "hashMapOf", "Ljava/util/HashMap;", "Lkotlin/collections/HashMap;", "pairs", "", "Lkotlin/Pair;", "([Lkotlin/Pair;)Ljava/util/HashMap;", "linkedMapOf", "Ljava/util/LinkedHashMap;", "Lkotlin/collections/LinkedHashMap;", "([Lkotlin/Pair;)Ljava/util/LinkedHashMap;", "mapCapacity", "expectedSize", "mapOf", "([Lkotlin/Pair;)Ljava/util/Map;", "mutableMapOf", "", "component1", "", "(Ljava/util/Map$Entry;)Ljava/lang/Object;", "component2", "contains", "", "Lkotlin/internal/OnlyInputTypes;", "key", "(Ljava/util/Map;Ljava/lang/Object;)Z", "containsKey", "containsValue", "value", "filter", "predicate", "Lkotlin/Function1;", "filterKeys", "filterNot", "filterNotTo", "M", "destination", "(Ljava/util/Map;Ljava/util/Map;Lkotlin/jvm/functions/Function1;)Ljava/util/Map;", "filterTo", "filterValues", "get", "(Ljava/util/Map;Ljava/lang/Object;)Ljava/lang/Object;", "getOrElse", "defaultValue", "Lkotlin/Function0;", "(Ljava/util/Map;Ljava/lang/Object;Lkotlin/jvm/functions/Function0;)Ljava/lang/Object;", "getOrElseNullable", "getOrPut", "getValue", "ifEmpty", "R", "(Ljava/util/Map;Lkotlin/jvm/functions/Function0;)Ljava/lang/Object;", "isNotEmpty", "isNullOrEmpty", "iterator", "", "", "", "mutableIterator", "mapKeys", "transform", "mapKeysTo", "mapValues", "mapValuesTo", "minus", "(Ljava/util/Map;Ljava/lang/Object;)Ljava/util/Map;", "keys", "(Ljava/util/Map;[Ljava/lang/Object;)Ljava/util/Map;", "", "Lkotlin/sequences/Sequence;", "minusAssign", "", "(Ljava/util/Map;Ljava/lang/Object;)V", "(Ljava/util/Map;[Ljava/lang/Object;)V", "optimizeReadOnlyMap", "orEmpty", "plus", "(Ljava/util/Map;[Lkotlin/Pair;)Ljava/util/Map;", "pair", "map", "plusAssign", "(Ljava/util/Map;[Lkotlin/Pair;)V", "putAll", "remove", "set", "(Ljava/util/Map;Ljava/lang/Object;Ljava/lang/Object;)V", "toMap", "([Lkotlin/Pair;Ljava/util/Map;)Ljava/util/Map;", "(Ljava/lang/Iterable;Ljava/util/Map;)Ljava/util/Map;", "(Ljava/util/Map;Ljava/util/Map;)Ljava/util/Map;", "(Lkotlin/sequences/Sequence;Ljava/util/Map;)Ljava/util/Map;", "toMutableMap", "toPair", "kotlin-stdlib" }, xs = "kotlin/collections/MapsKt")
class MapsKt__MapsKt extends MapsKt__MapsJVMKt
{
    private static final int INT_MAX_POWER_OF_TWO = 1073741824;
    
    @NotNull
    public static final <K, V> Map<K, V> emptyMap() {
        final EmptyMap instance = EmptyMap.INSTANCE;
        if (instance == null) {
            throw new TypeCastException("null cannot be cast to non-null type kotlin.collections.Map<K, V>");
        }
        return (Map<K, V>)instance;
    }
    
    @NotNull
    public static final <K, V> Map<K, V> mapOf(@NotNull final Pair<? extends K, ? extends V>... pairs) {
        Intrinsics.checkParameterIsNotNull(pairs, "pairs");
        return (((Pair<? extends K, ? extends V>[])pairs).length > 0) ? toMap((Pair<?, ?>[])pairs, (LinkedHashMap)new LinkedHashMap(mapCapacity(((Pair<? extends K, ? extends V>[])pairs).length))) : emptyMap();
    }
    
    @InlineOnly
    private static final <K, V> Map<K, V> mapOf() {
        final int $i$f$mapOf = 0;
        return (Map<K, V>)emptyMap();
    }
    
    @SinceKotlin(version = "1.1")
    @InlineOnly
    private static final <K, V> Map<K, V> mutableMapOf() {
        final int $i$f$mutableMapOf = 0;
        return new LinkedHashMap<K, V>();
    }
    
    @NotNull
    public static final <K, V> Map<K, V> mutableMapOf(@NotNull final Pair<? extends K, ? extends V>... pairs) {
        Intrinsics.checkParameterIsNotNull(pairs, "pairs");
        final LinkedHashMap $this$apply;
        final LinkedHashMap linkedHashMap = $this$apply = new LinkedHashMap(mapCapacity(pairs.length));
        final int n = 0;
        putAll((Map<? super Object, ? super Object>)$this$apply, (Pair<?, ?>[])pairs);
        return (LinkedHashMap<K, V>)linkedHashMap;
    }
    
    @SinceKotlin(version = "1.1")
    @InlineOnly
    private static final <K, V> HashMap<K, V> hashMapOf() {
        final int $i$f$hashMapOf = 0;
        return new HashMap<K, V>();
    }
    
    @NotNull
    public static final <K, V> HashMap<K, V> hashMapOf(@NotNull final Pair<? extends K, ? extends V>... pairs) {
        Intrinsics.checkParameterIsNotNull(pairs, "pairs");
        final HashMap $this$apply;
        final HashMap hashMap = $this$apply = new HashMap(mapCapacity(pairs.length));
        final int n = 0;
        putAll((Map<? super Object, ? super Object>)$this$apply, (Pair<?, ?>[])pairs);
        return (HashMap<K, V>)hashMap;
    }
    
    @SinceKotlin(version = "1.1")
    @InlineOnly
    private static final <K, V> LinkedHashMap<K, V> linkedMapOf() {
        final int $i$f$linkedMapOf = 0;
        return new LinkedHashMap<K, V>();
    }
    
    @NotNull
    public static final <K, V> LinkedHashMap<K, V> linkedMapOf(@NotNull final Pair<? extends K, ? extends V>... pairs) {
        Intrinsics.checkParameterIsNotNull(pairs, "pairs");
        return toMap((Pair<?, ?>[])pairs, (LinkedHashMap<K, V>)new LinkedHashMap<Object, Object>(mapCapacity(((Pair<? extends K, ? extends V>[])pairs).length)));
    }
    
    @PublishedApi
    public static final int mapCapacity(final int expectedSize) {
        if (expectedSize < 3) {
            return expectedSize + 1;
        }
        if (expectedSize < 1073741824) {
            return expectedSize + expectedSize / 3;
        }
        return Integer.MAX_VALUE;
    }
    
    @InlineOnly
    private static final <K, V> boolean isNotEmpty(@NotNull final Map<? extends K, ? extends V> $this$isNotEmpty) {
        final int $i$f$isNotEmpty = 0;
        return !$this$isNotEmpty.isEmpty();
    }
    
    @SinceKotlin(version = "1.3")
    @InlineOnly
    private static final <K, V> boolean isNullOrEmpty(@Nullable final Map<? extends K, ? extends V> $this$isNullOrEmpty) {
        final int $i$f$isNullOrEmpty = 0;
        return $this$isNullOrEmpty == null || $this$isNullOrEmpty.isEmpty();
    }
    
    @InlineOnly
    private static final <K, V> Map<K, V> orEmpty(@Nullable final Map<K, ? extends V> $this$orEmpty) {
        final int $i$f$orEmpty = 0;
        Map<K, V> emptyMap = (Map<K, V>)$this$orEmpty;
        if ($this$orEmpty == null) {
            emptyMap = emptyMap();
        }
        return emptyMap;
    }
    
    @SinceKotlin(version = "1.3")
    @InlineOnly
    private static final <M extends java.util.Map, R> R ifEmpty(final M $this$ifEmpty, final Function0<? extends R> defaultValue) {
        // 
        // This method could not be decompiled.
        // 
        // Original Bytecode:
        // 
        //     2: istore_2        /* $i$f$ifEmpty */
        //     3: aload_0         /* $this$ifEmpty */
        //     4: invokeinterface java/util/Map.isEmpty:()Z
        //     9: ifeq            21
        //    12: aload_1         /* defaultValue */
        //    13: invokeinterface kotlin/jvm/functions/Function0.invoke:()Ljava/lang/Object;
        //    18: goto            22
        //    21: aload_0         /* $this$ifEmpty */
        //    22: areturn        
        //    Signature:
        //  <M::Ljava/util/Map<**>;:TR;R:Ljava/lang/Object;>(TM;Lkotlin/jvm/functions/Function0<+TR;>;)TR;
        //    StackMapTable: 00 02 FC 00 15 01 40 07 00 C6
        // 
        // The error that occurred was:
        // 
        // java.lang.StackOverflowError
        //     at com.strobel.assembler.metadata.MetadataHelper.isSubType(MetadataHelper.java:1283)
        //     at com.strobel.assembler.metadata.MetadataHelper.isSubType(MetadataHelper.java:1283)
        //     at com.strobel.assembler.metadata.MetadataHelper.isSubType(MetadataHelper.java:1283)
        //     at com.strobel.assembler.metadata.MetadataHelper.isSubType(MetadataHelper.java:1283)
        //     at com.strobel.assembler.metadata.MetadataHelper.isSubType(MetadataHelper.java:1283)
        //     at com.strobel.assembler.metadata.MetadataHelper.isSubType(MetadataHelper.java:1283)
        //     at com.strobel.assembler.metadata.MetadataHelper.isSubType(MetadataHelper.java:1283)
        //     at com.strobel.assembler.metadata.MetadataHelper.isSubType(MetadataHelper.java:1283)
        //     at com.strobel.assembler.metadata.MetadataHelper.isSubType(MetadataHelper.java:1283)
        //     at com.strobel.assembler.metadata.MetadataHelper.isSubType(MetadataHelper.java:1283)
        //     at com.strobel.assembler.metadata.MetadataHelper.isSubType(MetadataHelper.java:1283)
        //     at com.strobel.assembler.metadata.MetadataHelper.isSubType(MetadataHelper.java:1283)
        //     at com.strobel.assembler.metadata.MetadataHelper.isSubType(MetadataHelper.java:1283)
        //     at com.strobel.assembler.metadata.MetadataHelper.isSubType(MetadataHelper.java:1283)
        //     at com.strobel.assembler.metadata.MetadataHelper.isSubType(MetadataHelper.java:1283)
        //     at com.strobel.assembler.metadata.MetadataHelper.isSubType(MetadataHelper.java:1283)
        //     at com.strobel.assembler.metadata.MetadataHelper.isSubType(MetadataHelper.java:1283)
        //     at com.strobel.assembler.metadata.MetadataHelper.isSubType(MetadataHelper.java:1283)
        //     at com.strobel.assembler.metadata.MetadataHelper.isSubType(MetadataHelper.java:1283)
        //     at com.strobel.assembler.metadata.MetadataHelper.isSubType(MetadataHelper.java:1283)
        //     at com.strobel.assembler.metadata.MetadataHelper.isSubType(MetadataHelper.java:1283)
        //     at com.strobel.assembler.metadata.MetadataHelper.isSubType(MetadataHelper.java:1283)
        //     at com.strobel.assembler.metadata.MetadataHelper.isSubType(MetadataHelper.java:1283)
        //     at com.strobel.assembler.metadata.MetadataHelper.isSubType(MetadataHelper.java:1283)
        //     at com.strobel.assembler.metadata.MetadataHelper.isSubType(MetadataHelper.java:1283)
        //     at com.strobel.assembler.metadata.MetadataHelper.isSubType(MetadataHelper.java:1283)
        //     at com.strobel.assembler.metadata.MetadataHelper.isSubType(MetadataHelper.java:1283)
        //     at com.strobel.assembler.metadata.MetadataHelper.isSubType(MetadataHelper.java:1283)
        //     at com.strobel.assembler.metadata.MetadataHelper.isSubType(MetadataHelper.java:1283)
        //     at com.strobel.assembler.metadata.MetadataHelper.isSubType(MetadataHelper.java:1283)
        //     at com.strobel.assembler.metadata.MetadataHelper.isSubType(MetadataHelper.java:1283)
        //     at com.strobel.assembler.metadata.MetadataHelper.isSubType(MetadataHelper.java:1283)
        //     at com.strobel.assembler.metadata.MetadataHelper.isSubType(MetadataHelper.java:1283)
        //     at com.strobel.assembler.metadata.MetadataHelper.isSubType(MetadataHelper.java:1283)
        //     at com.strobel.assembler.metadata.MetadataHelper.isSubType(MetadataHelper.java:1283)
        //     at com.strobel.assembler.metadata.MetadataHelper.isSubType(MetadataHelper.java:1283)
        //     at com.strobel.assembler.metadata.MetadataHelper.isSubType(MetadataHelper.java:1283)
        //     at com.strobel.assembler.metadata.MetadataHelper.isSubType(MetadataHelper.java:1283)
        //     at com.strobel.assembler.metadata.MetadataHelper.isSubType(MetadataHelper.java:1283)
        //     at com.strobel.assembler.metadata.MetadataHelper.isSubType(MetadataHelper.java:1283)
        //     at com.strobel.assembler.metadata.MetadataHelper.isSubType(MetadataHelper.java:1283)
        //     at com.strobel.assembler.metadata.MetadataHelper.isSubType(MetadataHelper.java:1283)
        //     at com.strobel.assembler.metadata.MetadataHelper.isSubType(MetadataHelper.java:1283)
        //     at com.strobel.assembler.metadata.MetadataHelper.isSubType(MetadataHelper.java:1283)
        //     at com.strobel.assembler.metadata.MetadataHelper.isSubType(MetadataHelper.java:1283)
        //     at com.strobel.assembler.metadata.MetadataHelper.isSubType(MetadataHelper.java:1283)
        //     at com.strobel.assembler.metadata.MetadataHelper.isSubType(MetadataHelper.java:1283)
        //     at com.strobel.assembler.metadata.MetadataHelper.isSubType(MetadataHelper.java:1283)
        //     at com.strobel.assembler.metadata.MetadataHelper.isSubType(MetadataHelper.java:1283)
        //     at com.strobel.assembler.metadata.MetadataHelper.isSubType(MetadataHelper.java:1283)
        //     at com.strobel.assembler.metadata.MetadataHelper.isSubType(MetadataHelper.java:1283)
        //     at com.strobel.assembler.metadata.MetadataHelper.isSubType(MetadataHelper.java:1283)
        //     at com.strobel.assembler.metadata.MetadataHelper.isSubType(MetadataHelper.java:1283)
        //     at com.strobel.assembler.metadata.MetadataHelper.isSubType(MetadataHelper.java:1283)
        //     at com.strobel.assembler.metadata.MetadataHelper.isSubType(MetadataHelper.java:1283)
        //     at com.strobel.assembler.metadata.MetadataHelper.isSubType(MetadataHelper.java:1283)
        //     at com.strobel.assembler.metadata.MetadataHelper.isSubType(MetadataHelper.java:1283)
        //     at com.strobel.assembler.metadata.MetadataHelper.isSubType(MetadataHelper.java:1283)
        //     at com.strobel.assembler.metadata.MetadataHelper.isSubType(MetadataHelper.java:1283)
        //     at com.strobel.assembler.metadata.MetadataHelper.isSubType(MetadataHelper.java:1283)
        //     at com.strobel.assembler.metadata.MetadataHelper.isSubType(MetadataHelper.java:1283)
        //     at com.strobel.assembler.metadata.MetadataHelper.isSubType(MetadataHelper.java:1283)
        //     at com.strobel.assembler.metadata.MetadataHelper.isSubType(MetadataHelper.java:1283)
        //     at com.strobel.assembler.metadata.MetadataHelper.isSubType(MetadataHelper.java:1283)
        //     at com.strobel.assembler.metadata.MetadataHelper.isSubType(MetadataHelper.java:1283)
        //     at com.strobel.assembler.metadata.MetadataHelper.isSubType(MetadataHelper.java:1283)
        //     at com.strobel.assembler.metadata.MetadataHelper.isSubType(MetadataHelper.java:1283)
        //     at com.strobel.assembler.metadata.MetadataHelper.isSubType(MetadataHelper.java:1283)
        //     at com.strobel.assembler.metadata.MetadataHelper.isSubType(MetadataHelper.java:1283)
        //     at com.strobel.assembler.metadata.MetadataHelper.isSubType(MetadataHelper.java:1283)
        //     at com.strobel.assembler.metadata.MetadataHelper.isSubType(MetadataHelper.java:1283)
        //     at com.strobel.assembler.metadata.MetadataHelper.isSubType(MetadataHelper.java:1283)
        //     at com.strobel.assembler.metadata.MetadataHelper.isSubType(MetadataHelper.java:1283)
        //     at com.strobel.assembler.metadata.MetadataHelper.isSubType(MetadataHelper.java:1283)
        //     at com.strobel.assembler.metadata.MetadataHelper.isSubType(MetadataHelper.java:1283)
        //     at com.strobel.assembler.metadata.MetadataHelper.isSubType(MetadataHelper.java:1283)
        //     at com.strobel.assembler.metadata.MetadataHelper.isSubType(MetadataHelper.java:1283)
        //     at com.strobel.assembler.metadata.MetadataHelper.isSubType(MetadataHelper.java:1283)
        //     at com.strobel.assembler.metadata.MetadataHelper.isSubType(MetadataHelper.java:1283)
        //     at com.strobel.assembler.metadata.MetadataHelper.isSubType(MetadataHelper.java:1283)
        //     at com.strobel.assembler.metadata.MetadataHelper.isSubType(MetadataHelper.java:1283)
        //     at com.strobel.assembler.metadata.MetadataHelper.isSubType(MetadataHelper.java:1283)
        //     at com.strobel.assembler.metadata.MetadataHelper.isSubType(MetadataHelper.java:1283)
        //     at com.strobel.assembler.metadata.MetadataHelper.isSubType(MetadataHelper.java:1283)
        //     at com.strobel.assembler.metadata.MetadataHelper.isSubType(MetadataHelper.java:1283)
        //     at com.strobel.assembler.metadata.MetadataHelper.isSubType(MetadataHelper.java:1283)
        //     at com.strobel.assembler.metadata.MetadataHelper.isSubType(MetadataHelper.java:1283)
        //     at com.strobel.assembler.metadata.MetadataHelper.isSubType(MetadataHelper.java:1283)
        //     at com.strobel.assembler.metadata.MetadataHelper.isSubType(MetadataHelper.java:1283)
        //     at com.strobel.assembler.metadata.MetadataHelper.isSubType(MetadataHelper.java:1283)
        //     at com.strobel.assembler.metadata.MetadataHelper.isSubType(MetadataHelper.java:1283)
        //     at com.strobel.assembler.metadata.MetadataHelper.isSubType(MetadataHelper.java:1283)
        //     at com.strobel.assembler.metadata.MetadataHelper.isSubType(MetadataHelper.java:1283)
        //     at com.strobel.assembler.metadata.MetadataHelper.isSubType(MetadataHelper.java:1283)
        //     at com.strobel.assembler.metadata.MetadataHelper.isSubType(MetadataHelper.java:1283)
        //     at com.strobel.assembler.metadata.MetadataHelper.isSubType(MetadataHelper.java:1283)
        //     at com.strobel.assembler.metadata.MetadataHelper.isSubType(MetadataHelper.java:1283)
        //     at com.strobel.assembler.metadata.MetadataHelper.isSubType(MetadataHelper.java:1283)
        //     at com.strobel.assembler.metadata.MetadataHelper.isSubType(MetadataHelper.java:1283)
        //     at com.strobel.assembler.metadata.MetadataHelper.isSubType(MetadataHelper.java:1283)
        //     at com.strobel.assembler.metadata.MetadataHelper.isSubType(MetadataHelper.java:1283)
        //     at com.strobel.assembler.metadata.MetadataHelper.isSubType(MetadataHelper.java:1283)
        //     at com.strobel.assembler.metadata.MetadataHelper.isSubType(MetadataHelper.java:1283)
        //     at com.strobel.assembler.metadata.MetadataHelper.isSubType(MetadataHelper.java:1283)
        //     at com.strobel.assembler.metadata.MetadataHelper.isSubType(MetadataHelper.java:1283)
        //     at com.strobel.assembler.metadata.MetadataHelper.isSubType(MetadataHelper.java:1283)
        //     at com.strobel.assembler.metadata.MetadataHelper.isSubType(MetadataHelper.java:1283)
        //     at com.strobel.assembler.metadata.MetadataHelper.isSubType(MetadataHelper.java:1283)
        //     at com.strobel.assembler.metadata.MetadataHelper.isSubType(MetadataHelper.java:1283)
        //     at com.strobel.assembler.metadata.MetadataHelper.isSubType(MetadataHelper.java:1283)
        //     at com.strobel.assembler.metadata.MetadataHelper.isSubType(MetadataHelper.java:1283)
        //     at com.strobel.assembler.metadata.MetadataHelper.isSubType(MetadataHelper.java:1283)
        //     at com.strobel.assembler.metadata.MetadataHelper.isSubType(MetadataHelper.java:1283)
        //     at com.strobel.assembler.metadata.MetadataHelper.isSubType(MetadataHelper.java:1283)
        //     at com.strobel.assembler.metadata.MetadataHelper.isSubType(MetadataHelper.java:1283)
        //     at com.strobel.assembler.metadata.MetadataHelper.isSubType(MetadataHelper.java:1283)
        //     at com.strobel.assembler.metadata.MetadataHelper.isSubType(MetadataHelper.java:1283)
        //     at com.strobel.assembler.metadata.MetadataHelper.isSubType(MetadataHelper.java:1283)
        //     at com.strobel.assembler.metadata.MetadataHelper.isSubType(MetadataHelper.java:1283)
        //     at com.strobel.assembler.metadata.MetadataHelper.isSubType(MetadataHelper.java:1283)
        //     at com.strobel.assembler.metadata.MetadataHelper.isSubType(MetadataHelper.java:1283)
        //     at com.strobel.assembler.metadata.MetadataHelper.isSubType(MetadataHelper.java:1283)
        //     at com.strobel.assembler.metadata.MetadataHelper.isSubType(MetadataHelper.java:1283)
        //     at com.strobel.assembler.metadata.MetadataHelper.isSubType(MetadataHelper.java:1283)
        //     at com.strobel.assembler.metadata.MetadataHelper.isSubType(MetadataHelper.java:1283)
        //     at com.strobel.assembler.metadata.MetadataHelper.isSubType(MetadataHelper.java:1283)
        //     at com.strobel.assembler.metadata.MetadataHelper.isSubType(MetadataHelper.java:1283)
        //     at com.strobel.assembler.metadata.MetadataHelper.isSubType(MetadataHelper.java:1283)
        //     at com.strobel.assembler.metadata.MetadataHelper.isSubType(MetadataHelper.java:1283)
        //     at com.strobel.assembler.metadata.MetadataHelper.isSubType(MetadataHelper.java:1283)
        //     at com.strobel.assembler.metadata.MetadataHelper.isSubType(MetadataHelper.java:1283)
        //     at com.strobel.assembler.metadata.MetadataHelper.isSubType(MetadataHelper.java:1283)
        //     at com.strobel.assembler.metadata.MetadataHelper.isSubType(MetadataHelper.java:1283)
        //     at com.strobel.assembler.metadata.MetadataHelper.isSubType(MetadataHelper.java:1283)
        //     at com.strobel.assembler.metadata.MetadataHelper.isSubType(MetadataHelper.java:1283)
        //     at com.strobel.assembler.metadata.MetadataHelper.isSubType(MetadataHelper.java:1283)
        //     at com.strobel.assembler.metadata.MetadataHelper.isSubType(MetadataHelper.java:1283)
        //     at com.strobel.assembler.metadata.MetadataHelper.isSubType(MetadataHelper.java:1283)
        //     at com.strobel.assembler.metadata.MetadataHelper.isSubType(MetadataHelper.java:1283)
        //     at com.strobel.assembler.metadata.MetadataHelper.isSubType(MetadataHelper.java:1283)
        //     at com.strobel.assembler.metadata.MetadataHelper.isSubType(MetadataHelper.java:1283)
        //     at com.strobel.assembler.metadata.MetadataHelper.isSubType(MetadataHelper.java:1283)
        //     at com.strobel.assembler.metadata.MetadataHelper.isSubType(MetadataHelper.java:1283)
        //     at com.strobel.assembler.metadata.MetadataHelper.isSubType(MetadataHelper.java:1283)
        //     at com.strobel.assembler.metadata.MetadataHelper.isSubType(MetadataHelper.java:1283)
        //     at com.strobel.assembler.metadata.MetadataHelper.isSubType(MetadataHelper.java:1283)
        //     at com.strobel.assembler.metadata.MetadataHelper.isSubType(MetadataHelper.java:1283)
        //     at com.strobel.assembler.metadata.MetadataHelper.isSubType(MetadataHelper.java:1283)
        //     at com.strobel.assembler.metadata.MetadataHelper.isSubType(MetadataHelper.java:1283)
        //     at com.strobel.assembler.metadata.MetadataHelper.isSubType(MetadataHelper.java:1283)
        //     at com.strobel.assembler.metadata.MetadataHelper.isSubType(MetadataHelper.java:1283)
        //     at com.strobel.assembler.metadata.MetadataHelper.isSubType(MetadataHelper.java:1283)
        //     at com.strobel.assembler.metadata.MetadataHelper.isSubType(MetadataHelper.java:1283)
        //     at com.strobel.assembler.metadata.MetadataHelper.isSubType(MetadataHelper.java:1283)
        //     at com.strobel.assembler.metadata.MetadataHelper.isSubType(MetadataHelper.java:1283)
        //     at com.strobel.assembler.metadata.MetadataHelper.isSubType(MetadataHelper.java:1283)
        //     at com.strobel.assembler.metadata.MetadataHelper.isSubType(MetadataHelper.java:1283)
        //     at com.strobel.assembler.metadata.MetadataHelper.isSubType(MetadataHelper.java:1283)
        //     at com.strobel.assembler.metadata.MetadataHelper.isSubType(MetadataHelper.java:1283)
        //     at com.strobel.assembler.metadata.MetadataHelper.isSubType(MetadataHelper.java:1283)
        //     at com.strobel.assembler.metadata.MetadataHelper.isSubType(MetadataHelper.java:1283)
        //     at com.strobel.assembler.metadata.MetadataHelper.isSubType(MetadataHelper.java:1283)
        //     at com.strobel.assembler.metadata.MetadataHelper.isSubType(MetadataHelper.java:1283)
        //     at com.strobel.assembler.metadata.MetadataHelper.isSubType(MetadataHelper.java:1283)
        //     at com.strobel.assembler.metadata.MetadataHelper.isSubType(MetadataHelper.java:1283)
        //     at com.strobel.assembler.metadata.MetadataHelper.isSubType(MetadataHelper.java:1283)
        //     at com.strobel.assembler.metadata.MetadataHelper.isSubType(MetadataHelper.java:1283)
        //     at com.strobel.assembler.metadata.MetadataHelper.isSubType(MetadataHelper.java:1283)
        //     at com.strobel.assembler.metadata.MetadataHelper.isSubType(MetadataHelper.java:1283)
        //     at com.strobel.assembler.metadata.MetadataHelper.isSubType(MetadataHelper.java:1283)
        //     at com.strobel.assembler.metadata.MetadataHelper.isSubType(MetadataHelper.java:1283)
        //     at com.strobel.assembler.metadata.MetadataHelper.isSubType(MetadataHelper.java:1283)
        //     at com.strobel.assembler.metadata.MetadataHelper.isSubType(MetadataHelper.java:1283)
        //     at com.strobel.assembler.metadata.MetadataHelper.isSubType(MetadataHelper.java:1283)
        //     at com.strobel.assembler.metadata.MetadataHelper.isSubType(MetadataHelper.java:1283)
        //     at com.strobel.assembler.metadata.MetadataHelper.isSubType(MetadataHelper.java:1283)
        //     at com.strobel.assembler.metadata.MetadataHelper.isSubType(MetadataHelper.java:1283)
        //     at com.strobel.assembler.metadata.MetadataHelper.isSubType(MetadataHelper.java:1283)
        //     at com.strobel.assembler.metadata.MetadataHelper.isSubType(MetadataHelper.java:1283)
        //     at com.strobel.assembler.metadata.MetadataHelper.isSubType(MetadataHelper.java:1283)
        //     at com.strobel.assembler.metadata.MetadataHelper.isSubType(MetadataHelper.java:1283)
        //     at com.strobel.assembler.metadata.MetadataHelper.isSubType(MetadataHelper.java:1283)
        //     at com.strobel.assembler.metadata.MetadataHelper.isSubType(MetadataHelper.java:1283)
        //     at com.strobel.assembler.metadata.MetadataHelper.isSubType(MetadataHelper.java:1283)
        //     at com.strobel.assembler.metadata.MetadataHelper.isSubType(MetadataHelper.java:1283)
        //     at com.strobel.assembler.metadata.MetadataHelper.isSubType(MetadataHelper.java:1283)
        //     at com.strobel.assembler.metadata.MetadataHelper.isSubType(MetadataHelper.java:1283)
        //     at com.strobel.assembler.metadata.MetadataHelper.isSubType(MetadataHelper.java:1283)
        //     at com.strobel.assembler.metadata.MetadataHelper.isSubType(MetadataHelper.java:1283)
        //     at com.strobel.assembler.metadata.MetadataHelper.isSubType(MetadataHelper.java:1283)
        //     at com.strobel.assembler.metadata.MetadataHelper.isSubType(MetadataHelper.java:1283)
        //     at com.strobel.assembler.metadata.MetadataHelper.isSubType(MetadataHelper.java:1283)
        //     at com.strobel.assembler.metadata.MetadataHelper.isSubType(MetadataHelper.java:1283)
        //     at com.strobel.assembler.metadata.MetadataHelper.isSubType(MetadataHelper.java:1283)
        //     at com.strobel.assembler.metadata.MetadataHelper.isSubType(MetadataHelper.java:1283)
        //     at com.strobel.assembler.metadata.MetadataHelper.isSubType(MetadataHelper.java:1283)
        //     at com.strobel.assembler.metadata.MetadataHelper.isSubType(MetadataHelper.java:1283)
        //     at com.strobel.assembler.metadata.MetadataHelper.isSubType(MetadataHelper.java:1283)
        //     at com.strobel.assembler.metadata.MetadataHelper.isSubType(MetadataHelper.java:1283)
        //     at com.strobel.assembler.metadata.MetadataHelper.isSubType(MetadataHelper.java:1283)
        //     at com.strobel.assembler.metadata.MetadataHelper.isSubType(MetadataHelper.java:1283)
        //     at com.strobel.assembler.metadata.MetadataHelper.isSubType(MetadataHelper.java:1283)
        //     at com.strobel.assembler.metadata.MetadataHelper.isSubType(MetadataHelper.java:1283)
        //     at com.strobel.assembler.metadata.MetadataHelper.isSubType(MetadataHelper.java:1283)
        //     at com.strobel.assembler.metadata.MetadataHelper.isSubType(MetadataHelper.java:1283)
        //     at com.strobel.assembler.metadata.MetadataHelper.isSubType(MetadataHelper.java:1283)
        //     at com.strobel.assembler.metadata.MetadataHelper.isSubType(MetadataHelper.java:1283)
        //     at com.strobel.assembler.metadata.MetadataHelper.isSubType(MetadataHelper.java:1283)
        //     at com.strobel.assembler.metadata.MetadataHelper.isSubType(MetadataHelper.java:1283)
        //     at com.strobel.assembler.metadata.MetadataHelper.isSubType(MetadataHelper.java:1283)
        //     at com.strobel.assembler.metadata.MetadataHelper.isSubType(MetadataHelper.java:1283)
        //     at com.strobel.assembler.metadata.MetadataHelper.isSubType(MetadataHelper.java:1283)
        //     at com.strobel.assembler.metadata.MetadataHelper.isSubType(MetadataHelper.java:1283)
        //     at com.strobel.assembler.metadata.MetadataHelper.isSubType(MetadataHelper.java:1283)
        //     at com.strobel.assembler.metadata.MetadataHelper.isSubType(MetadataHelper.java:1283)
        //     at com.strobel.assembler.metadata.MetadataHelper.isSubType(MetadataHelper.java:1283)
        //     at com.strobel.assembler.metadata.MetadataHelper.isSubType(MetadataHelper.java:1283)
        //     at com.strobel.assembler.metadata.MetadataHelper.isSubType(MetadataHelper.java:1283)
        //     at com.strobel.assembler.metadata.MetadataHelper.isSubType(MetadataHelper.java:1283)
        //     at com.strobel.assembler.metadata.MetadataHelper.isSubType(MetadataHelper.java:1283)
        //     at com.strobel.assembler.metadata.MetadataHelper.isSubType(MetadataHelper.java:1283)
        //     at com.strobel.assembler.metadata.MetadataHelper.isSubType(MetadataHelper.java:1283)
        //     at com.strobel.assembler.metadata.MetadataHelper.isSubType(MetadataHelper.java:1283)
        //     at com.strobel.assembler.metadata.MetadataHelper.isSubType(MetadataHelper.java:1283)
        //     at com.strobel.assembler.metadata.MetadataHelper.isSubType(MetadataHelper.java:1283)
        //     at com.strobel.assembler.metadata.MetadataHelper.isSubType(MetadataHelper.java:1283)
        //     at com.strobel.assembler.metadata.MetadataHelper.isSubType(MetadataHelper.java:1283)
        //     at com.strobel.assembler.metadata.MetadataHelper.isSubType(MetadataHelper.java:1283)
        //     at com.strobel.assembler.metadata.MetadataHelper.isSubType(MetadataHelper.java:1283)
        //     at com.strobel.assembler.metadata.MetadataHelper.isSubType(MetadataHelper.java:1283)
        //     at com.strobel.assembler.metadata.MetadataHelper.isSubType(MetadataHelper.java:1283)
        //     at com.strobel.assembler.metadata.MetadataHelper.isSubType(MetadataHelper.java:1283)
        //     at com.strobel.assembler.metadata.MetadataHelper.isSubType(MetadataHelper.java:1283)
        //     at com.strobel.assembler.metadata.MetadataHelper.isSubType(MetadataHelper.java:1283)
        //     at com.strobel.assembler.metadata.MetadataHelper.isSubType(MetadataHelper.java:1283)
        //     at com.strobel.assembler.metadata.MetadataHelper.isSubType(MetadataHelper.java:1283)
        //     at com.strobel.assembler.metadata.MetadataHelper.isSubType(MetadataHelper.java:1283)
        //     at com.strobel.assembler.metadata.MetadataHelper.isSubType(MetadataHelper.java:1283)
        //     at com.strobel.assembler.metadata.MetadataHelper.isSubType(MetadataHelper.java:1283)
        //     at com.strobel.assembler.metadata.MetadataHelper.isSubType(MetadataHelper.java:1283)
        //     at com.strobel.assembler.metadata.MetadataHelper.isSubType(MetadataHelper.java:1283)
        //     at com.strobel.assembler.metadata.MetadataHelper.isSubType(MetadataHelper.java:1283)
        //     at com.strobel.assembler.metadata.MetadataHelper.isSubType(MetadataHelper.java:1283)
        //     at com.strobel.assembler.metadata.MetadataHelper.isSubType(MetadataHelper.java:1283)
        //     at com.strobel.assembler.metadata.MetadataHelper.isSubType(MetadataHelper.java:1283)
        //     at com.strobel.assembler.metadata.MetadataHelper.isSubType(MetadataHelper.java:1283)
        //     at com.strobel.assembler.metadata.MetadataHelper.isSubType(MetadataHelper.java:1283)
        //     at com.strobel.assembler.metadata.MetadataHelper.isSubType(MetadataHelper.java:1283)
        //     at com.strobel.assembler.metadata.MetadataHelper.isSubType(MetadataHelper.java:1283)
        //     at com.strobel.assembler.metadata.MetadataHelper.isSubType(MetadataHelper.java:1283)
        //     at com.strobel.assembler.metadata.MetadataHelper.isSubType(MetadataHelper.java:1283)
        //     at com.strobel.assembler.metadata.MetadataHelper.isSubType(MetadataHelper.java:1283)
        //     at com.strobel.assembler.metadata.MetadataHelper.isSubType(MetadataHelper.java:1283)
        //     at com.strobel.assembler.metadata.MetadataHelper.isSubType(MetadataHelper.java:1283)
        //     at com.strobel.assembler.metadata.MetadataHelper.isSubType(MetadataHelper.java:1283)
        //     at com.strobel.assembler.metadata.MetadataHelper.isSubType(MetadataHelper.java:1283)
        //     at com.strobel.assembler.metadata.MetadataHelper.isSubType(MetadataHelper.java:1283)
        //     at com.strobel.assembler.metadata.MetadataHelper.isSubType(MetadataHelper.java:1283)
        //     at com.strobel.assembler.metadata.MetadataHelper.isSubType(MetadataHelper.java:1283)
        //     at com.strobel.assembler.metadata.MetadataHelper.isSubType(MetadataHelper.java:1283)
        //     at com.strobel.assembler.metadata.MetadataHelper.isSubType(MetadataHelper.java:1283)
        //     at com.strobel.assembler.metadata.MetadataHelper.isSubType(MetadataHelper.java:1283)
        //     at com.strobel.assembler.metadata.MetadataHelper.isSubType(MetadataHelper.java:1283)
        //     at com.strobel.assembler.metadata.MetadataHelper.isSubType(MetadataHelper.java:1283)
        //     at com.strobel.assembler.metadata.MetadataHelper.isSubType(MetadataHelper.java:1283)
        //     at com.strobel.assembler.metadata.MetadataHelper.isSubType(MetadataHelper.java:1283)
        //     at com.strobel.assembler.metadata.MetadataHelper.isSubType(MetadataHelper.java:1283)
        //     at com.strobel.assembler.metadata.MetadataHelper.isSubType(MetadataHelper.java:1283)
        //     at com.strobel.assembler.metadata.MetadataHelper.isSubType(MetadataHelper.java:1283)
        //     at com.strobel.assembler.metadata.MetadataHelper.isSubType(MetadataHelper.java:1283)
        //     at com.strobel.assembler.metadata.MetadataHelper.isSubType(MetadataHelper.java:1283)
        //     at com.strobel.assembler.metadata.MetadataHelper.isSubType(MetadataHelper.java:1283)
        //     at com.strobel.assembler.metadata.MetadataHelper.isSubType(MetadataHelper.java:1283)
        //     at com.strobel.assembler.metadata.MetadataHelper.isSubType(MetadataHelper.java:1283)
        //     at com.strobel.assembler.metadata.MetadataHelper.isSubType(MetadataHelper.java:1283)
        //     at com.strobel.assembler.metadata.MetadataHelper.isSubType(MetadataHelper.java:1283)
        //     at com.strobel.assembler.metadata.MetadataHelper.isSubType(MetadataHelper.java:1283)
        //     at com.strobel.assembler.metadata.MetadataHelper.isSubType(MetadataHelper.java:1283)
        //     at com.strobel.assembler.metadata.MetadataHelper.isSubType(MetadataHelper.java:1283)
        //     at com.strobel.assembler.metadata.MetadataHelper.isSubType(MetadataHelper.java:1283)
        //     at com.strobel.assembler.metadata.MetadataHelper.isSubType(MetadataHelper.java:1283)
        //     at com.strobel.assembler.metadata.MetadataHelper.isSubType(MetadataHelper.java:1283)
        //     at com.strobel.assembler.metadata.MetadataHelper.isSubType(MetadataHelper.java:1283)
        //     at com.strobel.assembler.metadata.MetadataHelper.isSubType(MetadataHelper.java:1283)
        //     at com.strobel.assembler.metadata.MetadataHelper.isSubType(MetadataHelper.java:1283)
        //     at com.strobel.assembler.metadata.MetadataHelper.isSubType(MetadataHelper.java:1283)
        //     at com.strobel.assembler.metadata.MetadataHelper.isSubType(MetadataHelper.java:1283)
        //     at com.strobel.assembler.metadata.MetadataHelper.isSubType(MetadataHelper.java:1283)
        //     at com.strobel.assembler.metadata.MetadataHelper.isSubType(MetadataHelper.java:1283)
        //     at com.strobel.assembler.metadata.MetadataHelper.isSubType(MetadataHelper.java:1283)
        //     at com.strobel.assembler.metadata.MetadataHelper.isSubType(MetadataHelper.java:1283)
        //     at com.strobel.assembler.metadata.MetadataHelper.isSubType(MetadataHelper.java:1283)
        //     at com.strobel.assembler.metadata.MetadataHelper.isSubType(MetadataHelper.java:1283)
        //     at com.strobel.assembler.metadata.MetadataHelper.isSubType(MetadataHelper.java:1283)
        //     at com.strobel.assembler.metadata.MetadataHelper.isSubType(MetadataHelper.java:1283)
        //     at com.strobel.assembler.metadata.MetadataHelper.isSubType(MetadataHelper.java:1283)
        //     at com.strobel.assembler.metadata.MetadataHelper.isSubType(MetadataHelper.java:1283)
        //     at com.strobel.assembler.metadata.MetadataHelper.isSubType(MetadataHelper.java:1283)
        //     at com.strobel.assembler.metadata.MetadataHelper.isSubType(MetadataHelper.java:1283)
        //     at com.strobel.assembler.metadata.MetadataHelper.isSubType(MetadataHelper.java:1283)
        //     at com.strobel.assembler.metadata.MetadataHelper.isSubType(MetadataHelper.java:1283)
        //     at com.strobel.assembler.metadata.MetadataHelper.isSubType(MetadataHelper.java:1283)
        //     at com.strobel.assembler.metadata.MetadataHelper.isSubType(MetadataHelper.java:1283)
        //     at com.strobel.assembler.metadata.MetadataHelper.isSubType(MetadataHelper.java:1283)
        //     at com.strobel.assembler.metadata.MetadataHelper.isSubType(MetadataHelper.java:1283)
        //     at com.strobel.assembler.metadata.MetadataHelper.isSubType(MetadataHelper.java:1283)
        //     at com.strobel.assembler.metadata.MetadataHelper.isSubType(MetadataHelper.java:1283)
        //     at com.strobel.assembler.metadata.MetadataHelper.isSubType(MetadataHelper.java:1283)
        //     at com.strobel.assembler.metadata.MetadataHelper.isSubType(MetadataHelper.java:1283)
        //     at com.strobel.assembler.metadata.MetadataHelper.isSubType(MetadataHelper.java:1283)
        //     at com.strobel.assembler.metadata.MetadataHelper.isSubType(MetadataHelper.java:1283)
        //     at com.strobel.assembler.metadata.MetadataHelper.isSubType(MetadataHelper.java:1283)
        //     at com.strobel.assembler.metadata.MetadataHelper.isSubType(MetadataHelper.java:1283)
        //     at com.strobel.assembler.metadata.MetadataHelper.isSubType(MetadataHelper.java:1283)
        //     at com.strobel.assembler.metadata.MetadataHelper.isSubType(MetadataHelper.java:1283)
        //     at com.strobel.assembler.metadata.MetadataHelper.isSubType(MetadataHelper.java:1283)
        //     at com.strobel.assembler.metadata.MetadataHelper.isSubType(MetadataHelper.java:1283)
        //     at com.strobel.assembler.metadata.MetadataHelper.isSubType(MetadataHelper.java:1283)
        //     at com.strobel.assembler.metadata.MetadataHelper.isSubType(MetadataHelper.java:1283)
        //     at com.strobel.assembler.metadata.MetadataHelper.isSubType(MetadataHelper.java:1283)
        //     at com.strobel.assembler.metadata.MetadataHelper.isSubType(MetadataHelper.java:1283)
        //     at com.strobel.assembler.metadata.MetadataHelper.isSubType(MetadataHelper.java:1283)
        //     at com.strobel.assembler.metadata.MetadataHelper.isSubType(MetadataHelper.java:1283)
        //     at com.strobel.assembler.metadata.MetadataHelper.isSubType(MetadataHelper.java:1283)
        //     at com.strobel.assembler.metadata.MetadataHelper.isSubType(MetadataHelper.java:1283)
        //     at com.strobel.assembler.metadata.MetadataHelper.isSubType(MetadataHelper.java:1283)
        //     at com.strobel.assembler.metadata.MetadataHelper.isSubType(MetadataHelper.java:1283)
        //     at com.strobel.assembler.metadata.MetadataHelper.isSubType(MetadataHelper.java:1283)
        //     at com.strobel.assembler.metadata.MetadataHelper.isSubType(MetadataHelper.java:1283)
        //     at com.strobel.assembler.metadata.MetadataHelper.isSubType(MetadataHelper.java:1283)
        //     at com.strobel.assembler.metadata.MetadataHelper.isSubType(MetadataHelper.java:1283)
        //     at com.strobel.assembler.metadata.MetadataHelper.isSubType(MetadataHelper.java:1283)
        //     at com.strobel.assembler.metadata.MetadataHelper.isSubType(MetadataHelper.java:1283)
        //     at com.strobel.assembler.metadata.MetadataHelper.isSubType(MetadataHelper.java:1283)
        //     at com.strobel.assembler.metadata.MetadataHelper.isSubType(MetadataHelper.java:1283)
        //     at com.strobel.assembler.metadata.MetadataHelper.isSubType(MetadataHelper.java:1283)
        //     at com.strobel.assembler.metadata.MetadataHelper.isSubType(MetadataHelper.java:1283)
        //     at com.strobel.assembler.metadata.MetadataHelper.isSubType(MetadataHelper.java:1283)
        //     at com.strobel.assembler.metadata.MetadataHelper.isSubType(MetadataHelper.java:1283)
        //     at com.strobel.assembler.metadata.MetadataHelper.isSubType(MetadataHelper.java:1283)
        //     at com.strobel.assembler.metadata.MetadataHelper.isSubType(MetadataHelper.java:1283)
        //     at com.strobel.assembler.metadata.MetadataHelper.isSubType(MetadataHelper.java:1283)
        //     at com.strobel.assembler.metadata.MetadataHelper.isSubType(MetadataHelper.java:1283)
        //     at com.strobel.assembler.metadata.MetadataHelper.isSubType(MetadataHelper.java:1283)
        //     at com.strobel.assembler.metadata.MetadataHelper.isSubType(MetadataHelper.java:1283)
        //     at com.strobel.assembler.metadata.MetadataHelper.isSubType(MetadataHelper.java:1283)
        //     at com.strobel.assembler.metadata.MetadataHelper.isSubType(MetadataHelper.java:1283)
        //     at com.strobel.assembler.metadata.MetadataHelper.isSubType(MetadataHelper.java:1283)
        //     at com.strobel.assembler.metadata.MetadataHelper.isSubType(MetadataHelper.java:1283)
        //     at com.strobel.assembler.metadata.MetadataHelper.isSubType(MetadataHelper.java:1283)
        //     at com.strobel.assembler.metadata.MetadataHelper.isSubType(MetadataHelper.java:1283)
        //     at com.strobel.assembler.metadata.MetadataHelper.isSubType(MetadataHelper.java:1283)
        //     at com.strobel.assembler.metadata.MetadataHelper.isSubType(MetadataHelper.java:1283)
        //     at com.strobel.assembler.metadata.MetadataHelper.isSubType(MetadataHelper.java:1283)
        //     at com.strobel.assembler.metadata.MetadataHelper.isSubType(MetadataHelper.java:1283)
        //     at com.strobel.assembler.metadata.MetadataHelper.isSubType(MetadataHelper.java:1283)
        //     at com.strobel.assembler.metadata.MetadataHelper.isSubType(MetadataHelper.java:1283)
        //     at com.strobel.assembler.metadata.MetadataHelper.isSubType(MetadataHelper.java:1283)
        //     at com.strobel.assembler.metadata.MetadataHelper.isSubType(MetadataHelper.java:1283)
        //     at com.strobel.assembler.metadata.MetadataHelper.isSubType(MetadataHelper.java:1283)
        //     at com.strobel.assembler.metadata.MetadataHelper.isSubType(MetadataHelper.java:1283)
        //     at com.strobel.assembler.metadata.MetadataHelper.isSubType(MetadataHelper.java:1283)
        //     at com.strobel.assembler.metadata.MetadataHelper.isSubType(MetadataHelper.java:1283)
        //     at com.strobel.assembler.metadata.MetadataHelper.isSubType(MetadataHelper.java:1283)
        //     at com.strobel.assembler.metadata.MetadataHelper.isSubType(MetadataHelper.java:1283)
        //     at com.strobel.assembler.metadata.MetadataHelper.isSubType(MetadataHelper.java:1283)
        //     at com.strobel.assembler.metadata.MetadataHelper.isSubType(MetadataHelper.java:1283)
        //     at com.strobel.assembler.metadata.MetadataHelper.isSubType(MetadataHelper.java:1283)
        //     at com.strobel.assembler.metadata.MetadataHelper.isSubType(MetadataHelper.java:1283)
        //     at com.strobel.assembler.metadata.MetadataHelper.isSubType(MetadataHelper.java:1283)
        //     at com.strobel.assembler.metadata.MetadataHelper.isSubType(MetadataHelper.java:1283)
        //     at com.strobel.assembler.metadata.MetadataHelper.isSubType(MetadataHelper.java:1283)
        //     at com.strobel.assembler.metadata.MetadataHelper.isSubType(MetadataHelper.java:1283)
        //     at com.strobel.assembler.metadata.MetadataHelper.isSubType(MetadataHelper.java:1283)
        //     at com.strobel.assembler.metadata.MetadataHelper.isSubType(MetadataHelper.java:1283)
        //     at com.strobel.assembler.metadata.MetadataHelper.isSubType(MetadataHelper.java:1283)
        //     at com.strobel.assembler.metadata.MetadataHelper.isSubType(MetadataHelper.java:1283)
        //     at com.strobel.assembler.metadata.MetadataHelper.isSubType(MetadataHelper.java:1283)
        //     at com.strobel.assembler.metadata.MetadataHelper.isSubType(MetadataHelper.java:1283)
        //     at com.strobel.assembler.metadata.MetadataHelper.isSubType(MetadataHelper.java:1283)
        //     at com.strobel.assembler.metadata.MetadataHelper.isSubType(MetadataHelper.java:1283)
        //     at com.strobel.assembler.metadata.MetadataHelper.isSubType(MetadataHelper.java:1283)
        //     at com.strobel.assembler.metadata.MetadataHelper.isSubType(MetadataHelper.java:1283)
        //     at com.strobel.assembler.metadata.MetadataHelper.isSubType(MetadataHelper.java:1283)
        //     at com.strobel.assembler.metadata.MetadataHelper.isSubType(MetadataHelper.java:1283)
        //     at com.strobel.assembler.metadata.MetadataHelper.isSubType(MetadataHelper.java:1283)
        //     at com.strobel.assembler.metadata.MetadataHelper.isSubType(MetadataHelper.java:1283)
        //     at com.strobel.assembler.metadata.MetadataHelper.isSubType(MetadataHelper.java:1283)
        //     at com.strobel.assembler.metadata.MetadataHelper.isSubType(MetadataHelper.java:1283)
        //     at com.strobel.assembler.metadata.MetadataHelper.isSubType(MetadataHelper.java:1283)
        //     at com.strobel.assembler.metadata.MetadataHelper.isSubType(MetadataHelper.java:1283)
        //     at com.strobel.assembler.metadata.MetadataHelper.isSubType(MetadataHelper.java:1283)
        //     at com.strobel.assembler.metadata.MetadataHelper.isSubType(MetadataHelper.java:1283)
        //     at com.strobel.assembler.metadata.MetadataHelper.isSubType(MetadataHelper.java:1283)
        //     at com.strobel.assembler.metadata.MetadataHelper.isSubType(MetadataHelper.java:1283)
        //     at com.strobel.assembler.metadata.MetadataHelper.isSubType(MetadataHelper.java:1283)
        //     at com.strobel.assembler.metadata.MetadataHelper.isSubType(MetadataHelper.java:1283)
        //     at com.strobel.assembler.metadata.MetadataHelper.isSubType(MetadataHelper.java:1283)
        //     at com.strobel.assembler.metadata.MetadataHelper.isSubType(MetadataHelper.java:1283)
        //     at com.strobel.assembler.metadata.MetadataHelper.isSubType(MetadataHelper.java:1283)
        //     at com.strobel.assembler.metadata.MetadataHelper.isSubType(MetadataHelper.java:1283)
        //     at com.strobel.assembler.metadata.MetadataHelper.isSubType(MetadataHelper.java:1283)
        //     at com.strobel.assembler.metadata.MetadataHelper.isSubType(MetadataHelper.java:1283)
        //     at com.strobel.assembler.metadata.MetadataHelper.isSubType(MetadataHelper.java:1283)
        //     at com.strobel.assembler.metadata.MetadataHelper.isSubType(MetadataHelper.java:1283)
        //     at com.strobel.assembler.metadata.MetadataHelper.isSubType(MetadataHelper.java:1283)
        //     at com.strobel.assembler.metadata.MetadataHelper.isSubType(MetadataHelper.java:1283)
        //     at com.strobel.assembler.metadata.MetadataHelper.isSubType(MetadataHelper.java:1283)
        //     at com.strobel.assembler.metadata.MetadataHelper.isSubType(MetadataHelper.java:1283)
        //     at com.strobel.assembler.metadata.MetadataHelper.isSubType(MetadataHelper.java:1283)
        //     at com.strobel.assembler.metadata.MetadataHelper.isSubType(MetadataHelper.java:1283)
        //     at com.strobel.assembler.metadata.MetadataHelper.isSubType(MetadataHelper.java:1283)
        //     at com.strobel.assembler.metadata.MetadataHelper.isSubType(MetadataHelper.java:1283)
        //     at com.strobel.assembler.metadata.MetadataHelper.isSubType(MetadataHelper.java:1283)
        //     at com.strobel.assembler.metadata.MetadataHelper.isSubType(MetadataHelper.java:1283)
        //     at com.strobel.assembler.metadata.MetadataHelper.isSubType(MetadataHelper.java:1283)
        //     at com.strobel.assembler.metadata.MetadataHelper.isSubType(MetadataHelper.java:1283)
        //     at com.strobel.assembler.metadata.MetadataHelper.isSubType(MetadataHelper.java:1283)
        //     at com.strobel.assembler.metadata.MetadataHelper.isSubType(MetadataHelper.java:1283)
        //     at com.strobel.assembler.metadata.MetadataHelper.isSubType(MetadataHelper.java:1283)
        //     at com.strobel.assembler.metadata.MetadataHelper.isSubType(MetadataHelper.java:1283)
        //     at com.strobel.assembler.metadata.MetadataHelper.isSubType(MetadataHelper.java:1283)
        //     at com.strobel.assembler.metadata.MetadataHelper.isSubType(MetadataHelper.java:1283)
        //     at com.strobel.assembler.metadata.MetadataHelper.isSubType(MetadataHelper.java:1283)
        //     at com.strobel.assembler.metadata.MetadataHelper.isSubType(MetadataHelper.java:1283)
        //     at com.strobel.assembler.metadata.MetadataHelper.isSubType(MetadataHelper.java:1283)
        //     at com.strobel.assembler.metadata.MetadataHelper.isSubType(MetadataHelper.java:1283)
        //     at com.strobel.assembler.metadata.MetadataHelper.isSubType(MetadataHelper.java:1283)
        //     at com.strobel.assembler.metadata.MetadataHelper.isSubType(MetadataHelper.java:1283)
        //     at com.strobel.assembler.metadata.MetadataHelper.isSubType(MetadataHelper.java:1283)
        //     at com.strobel.assembler.metadata.MetadataHelper.isSubType(MetadataHelper.java:1283)
        //     at com.strobel.assembler.metadata.MetadataHelper.isSubType(MetadataHelper.java:1283)
        //     at com.strobel.assembler.metadata.MetadataHelper.isSubType(MetadataHelper.java:1283)
        //     at com.strobel.assembler.metadata.MetadataHelper.isSubType(MetadataHelper.java:1283)
        //     at com.strobel.assembler.metadata.MetadataHelper.isSubType(MetadataHelper.java:1283)
        //     at com.strobel.assembler.metadata.MetadataHelper.isSubType(MetadataHelper.java:1283)
        //     at com.strobel.assembler.metadata.MetadataHelper.isSubType(MetadataHelper.java:1283)
        //     at com.strobel.assembler.metadata.MetadataHelper.isSubType(MetadataHelper.java:1283)
        //     at com.strobel.assembler.metadata.MetadataHelper.isSubType(MetadataHelper.java:1283)
        //     at com.strobel.assembler.metadata.MetadataHelper.isSubType(MetadataHelper.java:1283)
        //     at com.strobel.assembler.metadata.MetadataHelper.isSubType(MetadataHelper.java:1283)
        //     at com.strobel.assembler.metadata.MetadataHelper.isSubType(MetadataHelper.java:1283)
        //     at com.strobel.assembler.metadata.MetadataHelper.isSubType(MetadataHelper.java:1283)
        //     at com.strobel.assembler.metadata.MetadataHelper.isSubType(MetadataHelper.java:1283)
        //     at com.strobel.assembler.metadata.MetadataHelper.isSubType(MetadataHelper.java:1283)
        //     at com.strobel.assembler.metadata.MetadataHelper.isSubType(MetadataHelper.java:1283)
        //     at com.strobel.assembler.metadata.MetadataHelper.isSubType(MetadataHelper.java:1283)
        //     at com.strobel.assembler.metadata.MetadataHelper.isSubType(MetadataHelper.java:1283)
        //     at com.strobel.assembler.metadata.MetadataHelper.isSubType(MetadataHelper.java:1283)
        //     at com.strobel.assembler.metadata.MetadataHelper.isSubType(MetadataHelper.java:1283)
        //     at com.strobel.assembler.metadata.MetadataHelper.isSubType(MetadataHelper.java:1283)
        //     at com.strobel.assembler.metadata.MetadataHelper.isSubType(MetadataHelper.java:1283)
        //     at com.strobel.assembler.metadata.MetadataHelper.isSubType(MetadataHelper.java:1283)
        //     at com.strobel.assembler.metadata.MetadataHelper.isSubType(MetadataHelper.java:1283)
        //     at com.strobel.assembler.metadata.MetadataHelper.isSubType(MetadataHelper.java:1283)
        //     at com.strobel.assembler.metadata.MetadataHelper.isSubType(MetadataHelper.java:1283)
        //     at com.strobel.assembler.metadata.MetadataHelper.isSubType(MetadataHelper.java:1283)
        //     at com.strobel.assembler.metadata.MetadataHelper.isSubType(MetadataHelper.java:1283)
        //     at com.strobel.assembler.metadata.MetadataHelper.isSubType(MetadataHelper.java:1283)
        //     at com.strobel.assembler.metadata.MetadataHelper.isSubType(MetadataHelper.java:1283)
        //     at com.strobel.assembler.metadata.MetadataHelper.isSubType(MetadataHelper.java:1283)
        //     at com.strobel.assembler.metadata.MetadataHelper.isSubType(MetadataHelper.java:1283)
        //     at com.strobel.assembler.metadata.MetadataHelper.isSubType(MetadataHelper.java:1283)
        //     at com.strobel.assembler.metadata.MetadataHelper.isSubType(MetadataHelper.java:1283)
        //     at com.strobel.assembler.metadata.MetadataHelper.isSubType(MetadataHelper.java:1283)
        //     at com.strobel.assembler.metadata.MetadataHelper.isSubType(MetadataHelper.java:1283)
        //     at com.strobel.assembler.metadata.MetadataHelper.isSubType(MetadataHelper.java:1283)
        //     at com.strobel.assembler.metadata.MetadataHelper.isSubType(MetadataHelper.java:1283)
        //     at com.strobel.assembler.metadata.MetadataHelper.isSubType(MetadataHelper.java:1283)
        //     at com.strobel.assembler.metadata.MetadataHelper.isSubType(MetadataHelper.java:1283)
        //     at com.strobel.assembler.metadata.MetadataHelper.isSubType(MetadataHelper.java:1283)
        //     at com.strobel.assembler.metadata.MetadataHelper.isSubType(MetadataHelper.java:1283)
        //     at com.strobel.assembler.metadata.MetadataHelper.isSubType(MetadataHelper.java:1283)
        //     at com.strobel.assembler.metadata.MetadataHelper.isSubType(MetadataHelper.java:1283)
        //     at com.strobel.assembler.metadata.MetadataHelper.isSubType(MetadataHelper.java:1283)
        //     at com.strobel.assembler.metadata.MetadataHelper.isSubType(MetadataHelper.java:1283)
        //     at com.strobel.assembler.metadata.MetadataHelper.isSubType(MetadataHelper.java:1283)
        //     at com.strobel.assembler.metadata.MetadataHelper.isSubType(MetadataHelper.java:1283)
        //     at com.strobel.assembler.metadata.MetadataHelper.isSubType(MetadataHelper.java:1283)
        //     at com.strobel.assembler.metadata.MetadataHelper.isSubType(MetadataHelper.java:1283)
        //     at com.strobel.assembler.metadata.MetadataHelper.isSubType(MetadataHelper.java:1283)
        //     at com.strobel.assembler.metadata.MetadataHelper.isSubType(MetadataHelper.java:1283)
        //     at com.strobel.assembler.metadata.MetadataHelper.isSubType(MetadataHelper.java:1283)
        //     at com.strobel.assembler.metadata.MetadataHelper.isSubType(MetadataHelper.java:1283)
        //     at com.strobel.assembler.metadata.MetadataHelper.isSubType(MetadataHelper.java:1283)
        //     at com.strobel.assembler.metadata.MetadataHelper.isSubType(MetadataHelper.java:1283)
        //     at com.strobel.assembler.metadata.MetadataHelper.isSubType(MetadataHelper.java:1283)
        //     at com.strobel.assembler.metadata.MetadataHelper.isSubType(MetadataHelper.java:1283)
        //     at com.strobel.assembler.metadata.MetadataHelper.isSubType(MetadataHelper.java:1283)
        //     at com.strobel.assembler.metadata.MetadataHelper.isSubType(MetadataHelper.java:1283)
        //     at com.strobel.assembler.metadata.MetadataHelper.isSubType(MetadataHelper.java:1283)
        //     at com.strobel.assembler.metadata.MetadataHelper.isSubType(MetadataHelper.java:1283)
        //     at com.strobel.assembler.metadata.MetadataHelper.isSubType(MetadataHelper.java:1283)
        //     at com.strobel.assembler.metadata.MetadataHelper.isSubType(MetadataHelper.java:1283)
        //     at com.strobel.assembler.metadata.MetadataHelper.isSubType(MetadataHelper.java:1283)
        //     at com.strobel.assembler.metadata.MetadataHelper.isSubType(MetadataHelper.java:1283)
        //     at com.strobel.assembler.metadata.MetadataHelper.isSubType(MetadataHelper.java:1283)
        //     at com.strobel.assembler.metadata.MetadataHelper.isSubType(MetadataHelper.java:1283)
        //     at com.strobel.assembler.metadata.MetadataHelper.isSubType(MetadataHelper.java:1283)
        //     at com.strobel.assembler.metadata.MetadataHelper.isSubType(MetadataHelper.java:1283)
        //     at com.strobel.assembler.metadata.MetadataHelper.isSubType(MetadataHelper.java:1283)
        //     at com.strobel.assembler.metadata.MetadataHelper.isSubType(MetadataHelper.java:1283)
        //     at com.strobel.assembler.metadata.MetadataHelper.isSubType(MetadataHelper.java:1283)
        //     at com.strobel.assembler.metadata.MetadataHelper.isSubType(MetadataHelper.java:1283)
        //     at com.strobel.assembler.metadata.MetadataHelper.isSubType(MetadataHelper.java:1283)
        //     at com.strobel.assembler.metadata.MetadataHelper.isSubType(MetadataHelper.java:1283)
        //     at com.strobel.assembler.metadata.MetadataHelper.isSubType(MetadataHelper.java:1283)
        //     at com.strobel.assembler.metadata.MetadataHelper.isSubType(MetadataHelper.java:1283)
        //     at com.strobel.assembler.metadata.MetadataHelper.isSubType(MetadataHelper.java:1283)
        //     at com.strobel.assembler.metadata.MetadataHelper.isSubType(MetadataHelper.java:1283)
        //     at com.strobel.assembler.metadata.MetadataHelper.isSubType(MetadataHelper.java:1283)
        //     at com.strobel.assembler.metadata.MetadataHelper.isSubType(MetadataHelper.java:1283)
        //     at com.strobel.assembler.metadata.MetadataHelper.isSubType(MetadataHelper.java:1283)
        //     at com.strobel.assembler.metadata.MetadataHelper.isSubType(MetadataHelper.java:1283)
        //     at com.strobel.assembler.metadata.MetadataHelper.isSubType(MetadataHelper.java:1283)
        //     at com.strobel.assembler.metadata.MetadataHelper.isSubType(MetadataHelper.java:1283)
        //     at com.strobel.assembler.metadata.MetadataHelper.isSubType(MetadataHelper.java:1283)
        //     at com.strobel.assembler.metadata.MetadataHelper.isSubType(MetadataHelper.java:1283)
        //     at com.strobel.assembler.metadata.MetadataHelper.isSubType(MetadataHelper.java:1283)
        //     at com.strobel.assembler.metadata.MetadataHelper.isSubType(MetadataHelper.java:1283)
        //     at com.strobel.assembler.metadata.MetadataHelper.isSubType(MetadataHelper.java:1283)
        //     at com.strobel.assembler.metadata.MetadataHelper.isSubType(MetadataHelper.java:1283)
        //     at com.strobel.assembler.metadata.MetadataHelper.isSubType(MetadataHelper.java:1283)
        //     at com.strobel.assembler.metadata.MetadataHelper.isSubType(MetadataHelper.java:1283)
        //     at com.strobel.assembler.metadata.MetadataHelper.isSubType(MetadataHelper.java:1283)
        //     at com.strobel.assembler.metadata.MetadataHelper.isSubType(MetadataHelper.java:1283)
        //     at com.strobel.assembler.metadata.MetadataHelper.isSubType(MetadataHelper.java:1283)
        //     at com.strobel.assembler.metadata.MetadataHelper.isSubType(MetadataHelper.java:1283)
        //     at com.strobel.assembler.metadata.MetadataHelper.isSubType(MetadataHelper.java:1283)
        //     at com.strobel.assembler.metadata.MetadataHelper.isSubType(MetadataHelper.java:1283)
        //     at com.strobel.assembler.metadata.MetadataHelper.isSubType(MetadataHelper.java:1283)
        //     at com.strobel.assembler.metadata.MetadataHelper.isSubType(MetadataHelper.java:1283)
        //     at com.strobel.assembler.metadata.MetadataHelper.isSubType(MetadataHelper.java:1283)
        //     at com.strobel.assembler.metadata.MetadataHelper.isSubType(MetadataHelper.java:1283)
        //     at com.strobel.assembler.metadata.MetadataHelper.isSubType(MetadataHelper.java:1283)
        //     at com.strobel.assembler.metadata.MetadataHelper.isSubType(MetadataHelper.java:1283)
        //     at com.strobel.assembler.metadata.MetadataHelper.isSubType(MetadataHelper.java:1283)
        //     at com.strobel.assembler.metadata.MetadataHelper.isSubType(MetadataHelper.java:1283)
        //     at com.strobel.assembler.metadata.MetadataHelper.isSubType(MetadataHelper.java:1283)
        //     at com.strobel.assembler.metadata.MetadataHelper.isSubType(MetadataHelper.java:1283)
        //     at com.strobel.assembler.metadata.MetadataHelper.isSubType(MetadataHelper.java:1283)
        //     at com.strobel.assembler.metadata.MetadataHelper.isSubType(MetadataHelper.java:1283)
        //     at com.strobel.assembler.metadata.MetadataHelper.isSubType(MetadataHelper.java:1283)
        //     at com.strobel.assembler.metadata.MetadataHelper.isSubType(MetadataHelper.java:1283)
        //     at com.strobel.assembler.metadata.MetadataHelper.isSubType(MetadataHelper.java:1283)
        //     at com.strobel.assembler.metadata.MetadataHelper.isSubType(MetadataHelper.java:1283)
        //     at com.strobel.assembler.metadata.MetadataHelper.isSubType(MetadataHelper.java:1283)
        //     at com.strobel.assembler.metadata.MetadataHelper.isSubType(MetadataHelper.java:1283)
        //     at com.strobel.assembler.metadata.MetadataHelper.isSubType(MetadataHelper.java:1283)
        //     at com.strobel.assembler.metadata.MetadataHelper.isSubType(MetadataHelper.java:1283)
        //     at com.strobel.assembler.metadata.MetadataHelper.isSubType(MetadataHelper.java:1283)
        //     at com.strobel.assembler.metadata.MetadataHelper.isSubType(MetadataHelper.java:1283)
        //     at com.strobel.assembler.metadata.MetadataHelper.isSubType(MetadataHelper.java:1283)
        //     at com.strobel.assembler.metadata.MetadataHelper.isSubType(MetadataHelper.java:1283)
        //     at com.strobel.assembler.metadata.MetadataHelper.isSubType(MetadataHelper.java:1283)
        //     at com.strobel.assembler.metadata.MetadataHelper.isSubType(MetadataHelper.java:1283)
        //     at com.strobel.assembler.metadata.MetadataHelper.isSubType(MetadataHelper.java:1283)
        //     at com.strobel.assembler.metadata.MetadataHelper.isSubType(MetadataHelper.java:1283)
        //     at com.strobel.assembler.metadata.MetadataHelper.isSubType(MetadataHelper.java:1283)
        //     at com.strobel.assembler.metadata.MetadataHelper.isSubType(MetadataHelper.java:1283)
        //     at com.strobel.assembler.metadata.MetadataHelper.isSubType(MetadataHelper.java:1283)
        //     at com.strobel.assembler.metadata.MetadataHelper.isSubType(MetadataHelper.java:1283)
        //     at com.strobel.assembler.metadata.MetadataHelper.isSubType(MetadataHelper.java:1283)
        //     at com.strobel.assembler.metadata.MetadataHelper.isSubType(MetadataHelper.java:1283)
        //     at com.strobel.assembler.metadata.MetadataHelper.isSubType(MetadataHelper.java:1283)
        //     at com.strobel.assembler.metadata.MetadataHelper.isSubType(MetadataHelper.java:1283)
        //     at com.strobel.assembler.metadata.MetadataHelper.isSubType(MetadataHelper.java:1283)
        //     at com.strobel.assembler.metadata.MetadataHelper.isSubType(MetadataHelper.java:1283)
        //     at com.strobel.assembler.metadata.MetadataHelper.isSubType(MetadataHelper.java:1283)
        //     at com.strobel.assembler.metadata.MetadataHelper.isSubType(MetadataHelper.java:1283)
        //     at com.strobel.assembler.metadata.MetadataHelper.isSubType(MetadataHelper.java:1283)
        //     at com.strobel.assembler.metadata.MetadataHelper.isSubType(MetadataHelper.java:1283)
        //     at com.strobel.assembler.metadata.MetadataHelper.isSubType(MetadataHelper.java:1283)
        //     at com.strobel.assembler.metadata.MetadataHelper.isSubType(MetadataHelper.java:1283)
        //     at com.strobel.assembler.metadata.MetadataHelper.isSubType(MetadataHelper.java:1283)
        //     at com.strobel.assembler.metadata.MetadataHelper.isSubType(MetadataHelper.java:1283)
        //     at com.strobel.assembler.metadata.MetadataHelper.isSubType(MetadataHelper.java:1283)
        //     at com.strobel.assembler.metadata.MetadataHelper.isSubType(MetadataHelper.java:1283)
        //     at com.strobel.assembler.metadata.MetadataHelper.isSubType(MetadataHelper.java:1283)
        //     at com.strobel.assembler.metadata.MetadataHelper.isSubType(MetadataHelper.java:1283)
        //     at com.strobel.assembler.metadata.MetadataHelper.isSubType(MetadataHelper.java:1283)
        //     at com.strobel.assembler.metadata.MetadataHelper.isSubType(MetadataHelper.java:1283)
        //     at com.strobel.assembler.metadata.MetadataHelper.isSubType(MetadataHelper.java:1283)
        //     at com.strobel.assembler.metadata.MetadataHelper.isSubType(MetadataHelper.java:1283)
        //     at com.strobel.assembler.metadata.MetadataHelper.isSubType(MetadataHelper.java:1283)
        //     at com.strobel.assembler.metadata.MetadataHelper.isSubType(MetadataHelper.java:1283)
        //     at com.strobel.assembler.metadata.MetadataHelper.isSubType(MetadataHelper.java:1283)
        //     at com.strobel.assembler.metadata.MetadataHelper.isSubType(MetadataHelper.java:1283)
        //     at com.strobel.assembler.metadata.MetadataHelper.isSubType(MetadataHelper.java:1283)
        //     at com.strobel.assembler.metadata.MetadataHelper.isSubType(MetadataHelper.java:1283)
        //     at com.strobel.assembler.metadata.MetadataHelper.isSubType(MetadataHelper.java:1283)
        //     at com.strobel.assembler.metadata.MetadataHelper.isSubType(MetadataHelper.java:1283)
        //     at com.strobel.assembler.metadata.MetadataHelper.isSubType(MetadataHelper.java:1283)
        //     at com.strobel.assembler.metadata.MetadataHelper.isSubType(MetadataHelper.java:1283)
        //     at com.strobel.assembler.metadata.MetadataHelper.isSubType(MetadataHelper.java:1283)
        //     at com.strobel.assembler.metadata.MetadataHelper.isSubType(MetadataHelper.java:1283)
        //     at com.strobel.assembler.metadata.MetadataHelper.isSubType(MetadataHelper.java:1283)
        //     at com.strobel.assembler.metadata.MetadataHelper.isSubType(MetadataHelper.java:1283)
        //     at com.strobel.assembler.metadata.MetadataHelper.isSubType(MetadataHelper.java:1283)
        //     at com.strobel.assembler.metadata.MetadataHelper.isSubType(MetadataHelper.java:1283)
        //     at com.strobel.assembler.metadata.MetadataHelper.isSubType(MetadataHelper.java:1283)
        //     at com.strobel.assembler.metadata.MetadataHelper.isSubType(MetadataHelper.java:1283)
        //     at com.strobel.assembler.metadata.MetadataHelper.isSubType(MetadataHelper.java:1283)
        //     at com.strobel.assembler.metadata.MetadataHelper.isSubType(MetadataHelper.java:1283)
        //     at com.strobel.assembler.metadata.MetadataHelper.isSubType(MetadataHelper.java:1283)
        //     at com.strobel.assembler.metadata.MetadataHelper.isSubType(MetadataHelper.java:1283)
        //     at com.strobel.assembler.metadata.MetadataHelper.isSubType(MetadataHelper.java:1283)
        //     at com.strobel.assembler.metadata.MetadataHelper.isSubType(MetadataHelper.java:1283)
        //     at com.strobel.assembler.metadata.MetadataHelper.isSubType(MetadataHelper.java:1283)
        //     at com.strobel.assembler.metadata.MetadataHelper.isSubType(MetadataHelper.java:1283)
        //     at com.strobel.assembler.metadata.MetadataHelper.isSubType(MetadataHelper.java:1283)
        //     at com.strobel.assembler.metadata.MetadataHelper.isSubType(MetadataHelper.java:1283)
        //     at com.strobel.assembler.metadata.MetadataHelper.isSubType(MetadataHelper.java:1283)
        //     at com.strobel.assembler.metadata.MetadataHelper.isSubType(MetadataHelper.java:1283)
        //     at com.strobel.assembler.metadata.MetadataHelper.isSubType(MetadataHelper.java:1283)
        //     at com.strobel.assembler.metadata.MetadataHelper.isSubType(MetadataHelper.java:1283)
        //     at com.strobel.assembler.metadata.MetadataHelper.isSubType(MetadataHelper.java:1283)
        //     at com.strobel.assembler.metadata.MetadataHelper.isSubType(MetadataHelper.java:1283)
        //     at com.strobel.assembler.metadata.MetadataHelper.isSubType(MetadataHelper.java:1283)
        //     at com.strobel.assembler.metadata.MetadataHelper.isSubType(MetadataHelper.java:1283)
        //     at com.strobel.assembler.metadata.MetadataHelper.isSubType(MetadataHelper.java:1283)
        //     at com.strobel.assembler.metadata.MetadataHelper.isSubType(MetadataHelper.java:1283)
        //     at com.strobel.assembler.metadata.MetadataHelper.isSubType(MetadataHelper.java:1283)
        //     at com.strobel.assembler.metadata.MetadataHelper.isSubType(MetadataHelper.java:1283)
        //     at com.strobel.assembler.metadata.MetadataHelper.isSubType(MetadataHelper.java:1283)
        //     at com.strobel.assembler.metadata.MetadataHelper.isSubType(MetadataHelper.java:1283)
        //     at com.strobel.assembler.metadata.MetadataHelper.isSubType(MetadataHelper.java:1283)
        //     at com.strobel.assembler.metadata.MetadataHelper.isSubType(MetadataHelper.java:1283)
        //     at com.strobel.assembler.metadata.MetadataHelper.isSubType(MetadataHelper.java:1283)
        //     at com.strobel.assembler.metadata.MetadataHelper.isSubType(MetadataHelper.java:1283)
        //     at com.strobel.assembler.metadata.MetadataHelper.isSubType(MetadataHelper.java:1283)
        //     at com.strobel.assembler.metadata.MetadataHelper.isSubType(MetadataHelper.java:1283)
        //     at com.strobel.assembler.metadata.MetadataHelper.isSubType(MetadataHelper.java:1283)
        //     at com.strobel.assembler.metadata.MetadataHelper.isSubType(MetadataHelper.java:1283)
        //     at com.strobel.assembler.metadata.MetadataHelper.isSubType(MetadataHelper.java:1283)
        //     at com.strobel.assembler.metadata.MetadataHelper.isSubType(MetadataHelper.java:1283)
        //     at com.strobel.assembler.metadata.MetadataHelper.isSubType(MetadataHelper.java:1283)
        //     at com.strobel.assembler.metadata.MetadataHelper.isSubType(MetadataHelper.java:1283)
        //     at com.strobel.assembler.metadata.MetadataHelper.isSubType(MetadataHelper.java:1283)
        //     at com.strobel.assembler.metadata.MetadataHelper.isSubType(MetadataHelper.java:1283)
        //     at com.strobel.assembler.metadata.MetadataHelper.isSubType(MetadataHelper.java:1283)
        //     at com.strobel.assembler.metadata.MetadataHelper.isSubType(MetadataHelper.java:1283)
        //     at com.strobel.assembler.metadata.MetadataHelper.isSubType(MetadataHelper.java:1283)
        //     at com.strobel.assembler.metadata.MetadataHelper.isSubType(MetadataHelper.java:1283)
        //     at com.strobel.assembler.metadata.MetadataHelper.isSubType(MetadataHelper.java:1283)
        //     at com.strobel.assembler.metadata.MetadataHelper.isSubType(MetadataHelper.java:1283)
        //     at com.strobel.assembler.metadata.MetadataHelper.isSubType(MetadataHelper.java:1283)
        //     at com.strobel.assembler.metadata.MetadataHelper.isSubType(MetadataHelper.java:1283)
        //     at com.strobel.assembler.metadata.MetadataHelper.isSubType(MetadataHelper.java:1283)
        //     at com.strobel.assembler.metadata.MetadataHelper.isSubType(MetadataHelper.java:1283)
        //     at com.strobel.assembler.metadata.MetadataHelper.isSubType(MetadataHelper.java:1283)
        //     at com.strobel.assembler.metadata.MetadataHelper.isSubType(MetadataHelper.java:1283)
        //     at com.strobel.assembler.metadata.MetadataHelper.isSubType(MetadataHelper.java:1283)
        //     at com.strobel.assembler.metadata.MetadataHelper.isSubType(MetadataHelper.java:1283)
        //     at com.strobel.assembler.metadata.MetadataHelper.isSubType(MetadataHelper.java:1283)
        //     at com.strobel.assembler.metadata.MetadataHelper.isSubType(MetadataHelper.java:1283)
        //     at com.strobel.assembler.metadata.MetadataHelper.isSubType(MetadataHelper.java:1283)
        //     at com.strobel.assembler.metadata.MetadataHelper.isSubType(MetadataHelper.java:1283)
        //     at com.strobel.assembler.metadata.MetadataHelper.isSubType(MetadataHelper.java:1283)
        //     at com.strobel.assembler.metadata.MetadataHelper.isSubType(MetadataHelper.java:1283)
        //     at com.strobel.assembler.metadata.MetadataHelper.isSubType(MetadataHelper.java:1283)
        //     at com.strobel.assembler.metadata.MetadataHelper.isSubType(MetadataHelper.java:1283)
        //     at com.strobel.assembler.metadata.MetadataHelper.isSubType(MetadataHelper.java:1283)
        //     at com.strobel.assembler.metadata.MetadataHelper.isSubType(MetadataHelper.java:1283)
        //     at com.strobel.assembler.metadata.MetadataHelper.isSubType(MetadataHelper.java:1283)
        //     at com.strobel.assembler.metadata.MetadataHelper.isSubType(MetadataHelper.java:1283)
        //     at com.strobel.assembler.metadata.MetadataHelper.isSubType(MetadataHelper.java:1283)
        //     at com.strobel.assembler.metadata.MetadataHelper.isSubType(MetadataHelper.java:1283)
        //     at com.strobel.assembler.metadata.MetadataHelper.isSubType(MetadataHelper.java:1283)
        //     at com.strobel.assembler.metadata.MetadataHelper.isSubType(MetadataHelper.java:1283)
        //     at com.strobel.assembler.metadata.MetadataHelper.isSubType(MetadataHelper.java:1283)
        //     at com.strobel.assembler.metadata.MetadataHelper.isSubType(MetadataHelper.java:1283)
        //     at com.strobel.assembler.metadata.MetadataHelper.isSubType(MetadataHelper.java:1283)
        //     at com.strobel.assembler.metadata.MetadataHelper.isSubType(MetadataHelper.java:1283)
        //     at com.strobel.assembler.metadata.MetadataHelper.isSubType(MetadataHelper.java:1283)
        //     at com.strobel.assembler.metadata.MetadataHelper.isSubType(MetadataHelper.java:1283)
        //     at com.strobel.assembler.metadata.MetadataHelper.isSubType(MetadataHelper.java:1283)
        //     at com.strobel.assembler.metadata.MetadataHelper.isSubType(MetadataHelper.java:1283)
        //     at com.strobel.assembler.metadata.MetadataHelper.isSubType(MetadataHelper.java:1283)
        //     at com.strobel.assembler.metadata.MetadataHelper.isSubType(MetadataHelper.java:1283)
        //     at com.strobel.assembler.metadata.MetadataHelper.isSubType(MetadataHelper.java:1283)
        //     at com.strobel.assembler.metadata.MetadataHelper.isSubType(MetadataHelper.java:1283)
        //     at com.strobel.assembler.metadata.MetadataHelper.isSubType(MetadataHelper.java:1283)
        //     at com.strobel.assembler.metadata.MetadataHelper.isSubType(MetadataHelper.java:1283)
        //     at com.strobel.assembler.metadata.MetadataHelper.isSubType(MetadataHelper.java:1283)
        //     at com.strobel.assembler.metadata.MetadataHelper.isSubType(MetadataHelper.java:1283)
        //     at com.strobel.assembler.metadata.MetadataHelper.isSubType(MetadataHelper.java:1283)
        //     at com.strobel.assembler.metadata.MetadataHelper.isSubType(MetadataHelper.java:1283)
        //     at com.strobel.assembler.metadata.MetadataHelper.isSubType(MetadataHelper.java:1283)
        //     at com.strobel.assembler.metadata.MetadataHelper.isSubType(MetadataHelper.java:1283)
        //     at com.strobel.assembler.metadata.MetadataHelper.isSubType(MetadataHelper.java:1283)
        //     at com.strobel.assembler.metadata.MetadataHelper.isSubType(MetadataHelper.java:1283)
        //     at com.strobel.assembler.metadata.MetadataHelper.isSubType(MetadataHelper.java:1283)
        //     at com.strobel.assembler.metadata.MetadataHelper.isSubType(MetadataHelper.java:1283)
        //     at com.strobel.assembler.metadata.MetadataHelper.isSubType(MetadataHelper.java:1283)
        //     at com.strobel.assembler.metadata.MetadataHelper.isSubType(MetadataHelper.java:1283)
        //     at com.strobel.assembler.metadata.MetadataHelper.isSubType(MetadataHelper.java:1283)
        //     at com.strobel.assembler.metadata.MetadataHelper.isSubType(MetadataHelper.java:1283)
        //     at com.strobel.assembler.metadata.MetadataHelper.isSubType(MetadataHelper.java:1283)
        //     at com.strobel.assembler.metadata.MetadataHelper.isSubType(MetadataHelper.java:1283)
        //     at com.strobel.assembler.metadata.MetadataHelper.isSubType(MetadataHelper.java:1283)
        //     at com.strobel.assembler.metadata.MetadataHelper.isSubType(MetadataHelper.java:1283)
        //     at com.strobel.assembler.metadata.MetadataHelper.isSubType(MetadataHelper.java:1283)
        //     at com.strobel.assembler.metadata.MetadataHelper.isSubType(MetadataHelper.java:1283)
        //     at com.strobel.assembler.metadata.MetadataHelper.isSubType(MetadataHelper.java:1283)
        //     at com.strobel.assembler.metadata.MetadataHelper.isSubType(MetadataHelper.java:1283)
        //     at com.strobel.assembler.metadata.MetadataHelper.isSubType(MetadataHelper.java:1283)
        //     at com.strobel.assembler.metadata.MetadataHelper.isSubType(MetadataHelper.java:1283)
        //     at com.strobel.assembler.metadata.MetadataHelper.isSubType(MetadataHelper.java:1283)
        //     at com.strobel.assembler.metadata.MetadataHelper.isSubType(MetadataHelper.java:1283)
        //     at com.strobel.assembler.metadata.MetadataHelper.isSubType(MetadataHelper.java:1283)
        //     at com.strobel.assembler.metadata.MetadataHelper.isSubType(MetadataHelper.java:1283)
        //     at com.strobel.assembler.metadata.MetadataHelper.isSubType(MetadataHelper.java:1283)
        //     at com.strobel.assembler.metadata.MetadataHelper.isSubType(MetadataHelper.java:1283)
        //     at com.strobel.assembler.metadata.MetadataHelper.isSubType(MetadataHelper.java:1283)
        //     at com.strobel.assembler.metadata.MetadataHelper.isSubType(MetadataHelper.java:1283)
        //     at com.strobel.assembler.metadata.MetadataHelper.isSubType(MetadataHelper.java:1283)
        //     at com.strobel.assembler.metadata.MetadataHelper.isSubType(MetadataHelper.java:1283)
        //     at com.strobel.assembler.metadata.MetadataHelper.isSubType(MetadataHelper.java:1283)
        //     at com.strobel.assembler.metadata.MetadataHelper.isSubType(MetadataHelper.java:1283)
        //     at com.strobel.assembler.metadata.MetadataHelper.isSubType(MetadataHelper.java:1283)
        //     at com.strobel.assembler.metadata.MetadataHelper.isSubType(MetadataHelper.java:1283)
        //     at com.strobel.assembler.metadata.MetadataHelper.isSubType(MetadataHelper.java:1283)
        //     at com.strobel.assembler.metadata.MetadataHelper.isSubType(MetadataHelper.java:1283)
        //     at com.strobel.assembler.metadata.MetadataHelper.isSubType(MetadataHelper.java:1283)
        //     at com.strobel.assembler.metadata.MetadataHelper.isSubType(MetadataHelper.java:1283)
        //     at com.strobel.assembler.metadata.MetadataHelper.isSubType(MetadataHelper.java:1283)
        //     at com.strobel.assembler.metadata.MetadataHelper.isSubType(MetadataHelper.java:1283)
        //     at com.strobel.assembler.metadata.MetadataHelper.isSubType(MetadataHelper.java:1283)
        //     at com.strobel.assembler.metadata.MetadataHelper.isSubType(MetadataHelper.java:1283)
        //     at com.strobel.assembler.metadata.MetadataHelper.isSubType(MetadataHelper.java:1283)
        //     at com.strobel.assembler.metadata.MetadataHelper.isSubType(MetadataHelper.java:1283)
        //     at com.strobel.assembler.metadata.MetadataHelper.isSubType(MetadataHelper.java:1283)
        //     at com.strobel.assembler.metadata.MetadataHelper.isSubType(MetadataHelper.java:1283)
        //     at com.strobel.assembler.metadata.MetadataHelper.isSubType(MetadataHelper.java:1283)
        //     at com.strobel.assembler.metadata.MetadataHelper.isSubType(MetadataHelper.java:1283)
        //     at com.strobel.assembler.metadata.MetadataHelper.isSubType(MetadataHelper.java:1283)
        //     at com.strobel.assembler.metadata.MetadataHelper.isSubType(MetadataHelper.java:1283)
        //     at com.strobel.assembler.metadata.MetadataHelper.isSubType(MetadataHelper.java:1283)
        //     at com.strobel.assembler.metadata.MetadataHelper.isSubType(MetadataHelper.java:1283)
        //     at com.strobel.assembler.metadata.MetadataHelper.isSubType(MetadataHelper.java:1283)
        //     at com.strobel.assembler.metadata.MetadataHelper.isSubType(MetadataHelper.java:1283)
        //     at com.strobel.assembler.metadata.MetadataHelper.isSubType(MetadataHelper.java:1283)
        //     at com.strobel.assembler.metadata.MetadataHelper.isSubType(MetadataHelper.java:1283)
        //     at com.strobel.assembler.metadata.MetadataHelper.isSubType(MetadataHelper.java:1283)
        //     at com.strobel.assembler.metadata.MetadataHelper.isSubType(MetadataHelper.java:1283)
        //     at com.strobel.assembler.metadata.MetadataHelper.isSubType(MetadataHelper.java:1283)
        //     at com.strobel.assembler.metadata.MetadataHelper.isSubType(MetadataHelper.java:1283)
        //     at com.strobel.assembler.metadata.MetadataHelper.isSubType(MetadataHelper.java:1283)
        //     at com.strobel.assembler.metadata.MetadataHelper.isSubType(MetadataHelper.java:1283)
        //     at com.strobel.assembler.metadata.MetadataHelper.isSubType(MetadataHelper.java:1283)
        //     at com.strobel.assembler.metadata.MetadataHelper.isSubType(MetadataHelper.java:1283)
        //     at com.strobel.assembler.metadata.MetadataHelper.isSubType(MetadataHelper.java:1283)
        //     at com.strobel.assembler.metadata.MetadataHelper.isSubType(MetadataHelper.java:1283)
        //     at com.strobel.assembler.metadata.MetadataHelper.isSubType(MetadataHelper.java:1283)
        //     at com.strobel.assembler.metadata.MetadataHelper.isSubType(MetadataHelper.java:1283)
        //     at com.strobel.assembler.metadata.MetadataHelper.isSubType(MetadataHelper.java:1283)
        //     at com.strobel.assembler.metadata.MetadataHelper.isSubType(MetadataHelper.java:1283)
        //     at com.strobel.assembler.metadata.MetadataHelper.isSubType(MetadataHelper.java:1283)
        //     at com.strobel.assembler.metadata.MetadataHelper.isSubType(MetadataHelper.java:1283)
        //     at com.strobel.assembler.metadata.MetadataHelper.isSubType(MetadataHelper.java:1283)
        //     at com.strobel.assembler.metadata.MetadataHelper.isSubType(MetadataHelper.java:1283)
        //     at com.strobel.assembler.metadata.MetadataHelper.isSubType(MetadataHelper.java:1283)
        //     at com.strobel.assembler.metadata.MetadataHelper.isSubType(MetadataHelper.java:1283)
        //     at com.strobel.assembler.metadata.MetadataHelper.isSubType(MetadataHelper.java:1283)
        //     at com.strobel.assembler.metadata.MetadataHelper.isSubType(MetadataHelper.java:1283)
        //     at com.strobel.assembler.metadata.MetadataHelper.isSubType(MetadataHelper.java:1283)
        //     at com.strobel.assembler.metadata.MetadataHelper.isSubType(MetadataHelper.java:1283)
        //     at com.strobel.assembler.metadata.MetadataHelper.isSubType(MetadataHelper.java:1283)
        //     at com.strobel.assembler.metadata.MetadataHelper.isSubType(MetadataHelper.java:1283)
        //     at com.strobel.assembler.metadata.MetadataHelper.isSubType(MetadataHelper.java:1283)
        //     at com.strobel.assembler.metadata.MetadataHelper.isSubType(MetadataHelper.java:1283)
        //     at com.strobel.assembler.metadata.MetadataHelper.isSubType(MetadataHelper.java:1283)
        //     at com.strobel.assembler.metadata.MetadataHelper.isSubType(MetadataHelper.java:1283)
        //     at com.strobel.assembler.metadata.MetadataHelper.isSubType(MetadataHelper.java:1283)
        //     at com.strobel.assembler.metadata.MetadataHelper.isSubType(MetadataHelper.java:1283)
        //     at com.strobel.assembler.metadata.MetadataHelper.isSubType(MetadataHelper.java:1283)
        //     at com.strobel.assembler.metadata.MetadataHelper.isSubType(MetadataHelper.java:1283)
        //     at com.strobel.assembler.metadata.MetadataHelper.isSubType(MetadataHelper.java:1283)
        //     at com.strobel.assembler.metadata.MetadataHelper.isSubType(MetadataHelper.java:1283)
        //     at com.strobel.assembler.metadata.MetadataHelper.isSubType(MetadataHelper.java:1283)
        //     at com.strobel.assembler.metadata.MetadataHelper.isSubType(MetadataHelper.java:1283)
        //     at com.strobel.assembler.metadata.MetadataHelper.isSubType(MetadataHelper.java:1283)
        //     at com.strobel.assembler.metadata.MetadataHelper.isSubType(MetadataHelper.java:1283)
        //     at com.strobel.assembler.metadata.MetadataHelper.isSubType(MetadataHelper.java:1283)
        //     at com.strobel.assembler.metadata.MetadataHelper.isSubType(MetadataHelper.java:1283)
        //     at com.strobel.assembler.metadata.MetadataHelper.isSubType(MetadataHelper.java:1283)
        //     at com.strobel.assembler.metadata.MetadataHelper.isSubType(MetadataHelper.java:1283)
        //     at com.strobel.assembler.metadata.MetadataHelper.isSubType(MetadataHelper.java:1283)
        //     at com.strobel.assembler.metadata.MetadataHelper.isSubType(MetadataHelper.java:1283)
        //     at com.strobel.assembler.metadata.MetadataHelper.isSubType(MetadataHelper.java:1283)
        //     at com.strobel.assembler.metadata.MetadataHelper.isSubType(MetadataHelper.java:1283)
        //     at com.strobel.assembler.metadata.MetadataHelper.isSubType(MetadataHelper.java:1283)
        //     at com.strobel.assembler.metadata.MetadataHelper.isSubType(MetadataHelper.java:1283)
        //     at com.strobel.assembler.metadata.MetadataHelper.isSubType(MetadataHelper.java:1283)
        //     at com.strobel.assembler.metadata.MetadataHelper.isSubType(MetadataHelper.java:1283)
        //     at com.strobel.assembler.metadata.MetadataHelper.isSubType(MetadataHelper.java:1283)
        //     at com.strobel.assembler.metadata.MetadataHelper.isSubType(MetadataHelper.java:1283)
        //     at com.strobel.assembler.metadata.MetadataHelper.isSubType(MetadataHelper.java:1283)
        //     at com.strobel.assembler.metadata.MetadataHelper.isSubType(MetadataHelper.java:1283)
        //     at com.strobel.assembler.metadata.MetadataHelper.isSubType(MetadataHelper.java:1283)
        //     at com.strobel.assembler.metadata.MetadataHelper.isSubType(MetadataHelper.java:1283)
        //     at com.strobel.assembler.metadata.MetadataHelper.isSubType(MetadataHelper.java:1283)
        //     at com.strobel.assembler.metadata.MetadataHelper.isSubType(MetadataHelper.java:1283)
        //     at com.strobel.assembler.metadata.MetadataHelper.isSubType(MetadataHelper.java:1283)
        //     at com.strobel.assembler.metadata.MetadataHelper.isSubType(MetadataHelper.java:1283)
        //     at com.strobel.assembler.metadata.MetadataHelper.isSubType(MetadataHelper.java:1283)
        //     at com.strobel.assembler.metadata.MetadataHelper.isSubType(MetadataHelper.java:1283)
        //     at com.strobel.assembler.metadata.MetadataHelper.isSubType(MetadataHelper.java:1283)
        //     at com.strobel.assembler.metadata.MetadataHelper.isSubType(MetadataHelper.java:1283)
        //     at com.strobel.assembler.metadata.MetadataHelper.isSubType(MetadataHelper.java:1283)
        //     at com.strobel.assembler.metadata.MetadataHelper.isSubType(MetadataHelper.java:1283)
        //     at com.strobel.assembler.metadata.MetadataHelper.isSubType(MetadataHelper.java:1283)
        //     at com.strobel.assembler.metadata.MetadataHelper.isSubType(MetadataHelper.java:1283)
        //     at com.strobel.assembler.metadata.MetadataHelper.isSubType(MetadataHelper.java:1283)
        //     at com.strobel.assembler.metadata.MetadataHelper.isSubType(MetadataHelper.java:1283)
        //     at com.strobel.assembler.metadata.MetadataHelper.isSubType(MetadataHelper.java:1283)
        //     at com.strobel.assembler.metadata.MetadataHelper.isSubType(MetadataHelper.java:1283)
        //     at com.strobel.assembler.metadata.MetadataHelper.isSubType(MetadataHelper.java:1283)
        //     at com.strobel.assembler.metadata.MetadataHelper.isSubType(MetadataHelper.java:1283)
        //     at com.strobel.assembler.metadata.MetadataHelper.isSubType(MetadataHelper.java:1283)
        //     at com.strobel.assembler.metadata.MetadataHelper.isSubType(MetadataHelper.java:1283)
        //     at com.strobel.assembler.metadata.MetadataHelper.isSubType(MetadataHelper.java:1283)
        //     at com.strobel.assembler.metadata.MetadataHelper.isSubType(MetadataHelper.java:1283)
        //     at com.strobel.assembler.metadata.MetadataHelper.isSubType(MetadataHelper.java:1283)
        //     at com.strobel.assembler.metadata.MetadataHelper.isSubType(MetadataHelper.java:1283)
        //     at com.strobel.assembler.metadata.MetadataHelper.isSubType(MetadataHelper.java:1283)
        //     at com.strobel.assembler.metadata.MetadataHelper.isSubType(MetadataHelper.java:1283)
        //     at com.strobel.assembler.metadata.MetadataHelper.isSubType(MetadataHelper.java:1283)
        //     at com.strobel.assembler.metadata.MetadataHelper.isSubType(MetadataHelper.java:1283)
        //     at com.strobel.assembler.metadata.MetadataHelper.isSubType(MetadataHelper.java:1283)
        //     at com.strobel.assembler.metadata.MetadataHelper.isSubType(MetadataHelper.java:1283)
        //     at com.strobel.assembler.metadata.MetadataHelper.isSubType(MetadataHelper.java:1283)
        //     at com.strobel.assembler.metadata.MetadataHelper.isSubType(MetadataHelper.java:1283)
        //     at com.strobel.assembler.metadata.MetadataHelper.isSubType(MetadataHelper.java:1283)
        //     at com.strobel.assembler.metadata.MetadataHelper.isSubType(MetadataHelper.java:1283)
        //     at com.strobel.assembler.metadata.MetadataHelper.isSubType(MetadataHelper.java:1283)
        //     at com.strobel.assembler.metadata.MetadataHelper.isSubType(MetadataHelper.java:1283)
        //     at com.strobel.assembler.metadata.MetadataHelper.isSubType(MetadataHelper.java:1283)
        //     at com.strobel.assembler.metadata.MetadataHelper.isSubType(MetadataHelper.java:1283)
        //     at com.strobel.assembler.metadata.MetadataHelper.isSubType(MetadataHelper.java:1283)
        //     at com.strobel.assembler.metadata.MetadataHelper.isSubType(MetadataHelper.java:1283)
        //     at com.strobel.assembler.metadata.MetadataHelper.isSubType(MetadataHelper.java:1283)
        //     at com.strobel.assembler.metadata.MetadataHelper.isSubType(MetadataHelper.java:1283)
        //     at com.strobel.assembler.metadata.MetadataHelper.isSubType(MetadataHelper.java:1283)
        //     at com.strobel.assembler.metadata.MetadataHelper.isSubType(MetadataHelper.java:1283)
        //     at com.strobel.assembler.metadata.MetadataHelper.isSubType(MetadataHelper.java:1283)
        //     at com.strobel.assembler.metadata.MetadataHelper.isSubType(MetadataHelper.java:1283)
        //     at com.strobel.assembler.metadata.MetadataHelper.isSubType(MetadataHelper.java:1283)
        //     at com.strobel.assembler.metadata.MetadataHelper.isSubType(MetadataHelper.java:1283)
        //     at com.strobel.assembler.metadata.MetadataHelper.isSubType(MetadataHelper.java:1283)
        //     at com.strobel.assembler.metadata.MetadataHelper.isSubType(MetadataHelper.java:1283)
        //     at com.strobel.assembler.metadata.MetadataHelper.isSubType(MetadataHelper.java:1283)
        //     at com.strobel.assembler.metadata.MetadataHelper.isSubType(MetadataHelper.java:1283)
        //     at com.strobel.assembler.metadata.MetadataHelper.isSubType(MetadataHelper.java:1283)
        //     at com.strobel.assembler.metadata.MetadataHelper.isSubType(MetadataHelper.java:1283)
        //     at com.strobel.assembler.metadata.MetadataHelper.isSubType(MetadataHelper.java:1283)
        //     at com.strobel.assembler.metadata.MetadataHelper.isSubType(MetadataHelper.java:1283)
        //     at com.strobel.assembler.metadata.MetadataHelper.isSubType(MetadataHelper.java:1283)
        //     at com.strobel.assembler.metadata.MetadataHelper.isSubType(MetadataHelper.java:1283)
        //     at com.strobel.assembler.metadata.MetadataHelper.isSubType(MetadataHelper.java:1283)
        //     at com.strobel.assembler.metadata.MetadataHelper.isSubType(MetadataHelper.java:1283)
        //     at com.strobel.assembler.metadata.MetadataHelper.isSubType(MetadataHelper.java:1283)
        //     at com.strobel.assembler.metadata.MetadataHelper.isSubType(MetadataHelper.java:1283)
        //     at com.strobel.assembler.metadata.MetadataHelper.isSubType(MetadataHelper.java:1283)
        //     at com.strobel.assembler.metadata.MetadataHelper.isSubType(MetadataHelper.java:1283)
        //     at com.strobel.assembler.metadata.MetadataHelper.isSubType(MetadataHelper.java:1283)
        //     at com.strobel.assembler.metadata.MetadataHelper.isSubType(MetadataHelper.java:1283)
        //     at com.strobel.assembler.metadata.MetadataHelper.isSubType(MetadataHelper.java:1283)
        //     at com.strobel.assembler.metadata.MetadataHelper.isSubType(MetadataHelper.java:1283)
        //     at com.strobel.assembler.metadata.MetadataHelper.isSubType(MetadataHelper.java:1283)
        //     at com.strobel.assembler.metadata.MetadataHelper.isSubType(MetadataHelper.java:1283)
        //     at com.strobel.assembler.metadata.MetadataHelper.isSubType(MetadataHelper.java:1283)
        //     at com.strobel.assembler.metadata.MetadataHelper.isSubType(MetadataHelper.java:1283)
        //     at com.strobel.assembler.metadata.MetadataHelper.isSubType(MetadataHelper.java:1283)
        //     at com.strobel.assembler.metadata.MetadataHelper.isSubType(MetadataHelper.java:1283)
        //     at com.strobel.assembler.metadata.MetadataHelper.isSubType(MetadataHelper.java:1283)
        //     at com.strobel.assembler.metadata.MetadataHelper.isSubType(MetadataHelper.java:1283)
        //     at com.strobel.assembler.metadata.MetadataHelper.isSubType(MetadataHelper.java:1283)
        //     at com.strobel.assembler.metadata.MetadataHelper.isSubType(MetadataHelper.java:1283)
        //     at com.strobel.assembler.metadata.MetadataHelper.isSubType(MetadataHelper.java:1283)
        //     at com.strobel.assembler.metadata.MetadataHelper.isSubType(MetadataHelper.java:1283)
        //     at com.strobel.assembler.metadata.MetadataHelper.isSubType(MetadataHelper.java:1283)
        //     at com.strobel.assembler.metadata.MetadataHelper.isSubType(MetadataHelper.java:1283)
        //     at com.strobel.assembler.metadata.MetadataHelper.isSubType(MetadataHelper.java:1283)
        //     at com.strobel.assembler.metadata.MetadataHelper.isSubType(MetadataHelper.java:1283)
        //     at com.strobel.assembler.metadata.MetadataHelper.isSubType(MetadataHelper.java:1283)
        //     at com.strobel.assembler.metadata.MetadataHelper.isSubType(MetadataHelper.java:1283)
        //     at com.strobel.assembler.metadata.MetadataHelper.isSubType(MetadataHelper.java:1283)
        //     at com.strobel.assembler.metadata.MetadataHelper.isSubType(MetadataHelper.java:1283)
        //     at com.strobel.assembler.metadata.MetadataHelper.isSubType(MetadataHelper.java:1283)
        //     at com.strobel.assembler.metadata.MetadataHelper.isSubType(MetadataHelper.java:1283)
        //     at com.strobel.assembler.metadata.MetadataHelper.isSubType(MetadataHelper.java:1283)
        //     at com.strobel.assembler.metadata.MetadataHelper.isSubType(MetadataHelper.java:1283)
        //     at com.strobel.assembler.metadata.MetadataHelper.isSubType(MetadataHelper.java:1283)
        //     at com.strobel.assembler.metadata.MetadataHelper.isSubType(MetadataHelper.java:1283)
        //     at com.strobel.assembler.metadata.MetadataHelper.isSubType(MetadataHelper.java:1283)
        //     at com.strobel.assembler.metadata.MetadataHelper.isSubType(MetadataHelper.java:1283)
        //     at com.strobel.assembler.metadata.MetadataHelper.isSubType(MetadataHelper.java:1283)
        //     at com.strobel.assembler.metadata.MetadataHelper.isSubType(MetadataHelper.java:1283)
        //     at com.strobel.assembler.metadata.MetadataHelper.isSubType(MetadataHelper.java:1283)
        //     at com.strobel.assembler.metadata.MetadataHelper.isSubType(MetadataHelper.java:1283)
        //     at com.strobel.assembler.metadata.MetadataHelper.isSubType(MetadataHelper.java:1283)
        //     at com.strobel.assembler.metadata.MetadataHelper.isSubType(MetadataHelper.java:1283)
        //     at com.strobel.assembler.metadata.MetadataHelper.isSubType(MetadataHelper.java:1283)
        //     at com.strobel.assembler.metadata.MetadataHelper.isSubType(MetadataHelper.java:1283)
        //     at com.strobel.assembler.metadata.MetadataHelper.isSubType(MetadataHelper.java:1283)
        //     at com.strobel.assembler.metadata.MetadataHelper.isSubType(MetadataHelper.java:1283)
        //     at com.strobel.assembler.metadata.MetadataHelper.isSubType(MetadataHelper.java:1283)
        //     at com.strobel.assembler.metadata.MetadataHelper.isSubType(MetadataHelper.java:1283)
        //     at com.strobel.assembler.metadata.MetadataHelper.isSubType(MetadataHelper.java:1283)
        //     at com.strobel.assembler.metadata.MetadataHelper.isSubType(MetadataHelper.java:1283)
        //     at com.strobel.assembler.metadata.MetadataHelper.isSubType(MetadataHelper.java:1283)
        //     at com.strobel.assembler.metadata.MetadataHelper.isSubType(MetadataHelper.java:1283)
        //     at com.strobel.assembler.metadata.MetadataHelper.isSubType(MetadataHelper.java:1283)
        //     at com.strobel.assembler.metadata.MetadataHelper.isSubType(MetadataHelper.java:1283)
        //     at com.strobel.assembler.metadata.MetadataHelper.isSubType(MetadataHelper.java:1283)
        //     at com.strobel.assembler.metadata.MetadataHelper.isSubType(MetadataHelper.java:1283)
        //     at com.strobel.assembler.metadata.MetadataHelper.isSubType(MetadataHelper.java:1283)
        //     at com.strobel.assembler.metadata.MetadataHelper.isSubType(MetadataHelper.java:1283)
        //     at com.strobel.assembler.metadata.MetadataHelper.isSubType(MetadataHelper.java:1283)
        //     at com.strobel.assembler.metadata.MetadataHelper.isSubType(MetadataHelper.java:1283)
        //     at com.strobel.assembler.metadata.MetadataHelper.isSubType(MetadataHelper.java:1283)
        //     at com.strobel.assembler.metadata.MetadataHelper.isSubType(MetadataHelper.java:1283)
        //     at com.strobel.assembler.metadata.MetadataHelper.isSubType(MetadataHelper.java:1283)
        //     at com.strobel.assembler.metadata.MetadataHelper.isSubType(MetadataHelper.java:1283)
        //     at com.strobel.assembler.metadata.MetadataHelper.isSubType(MetadataHelper.java:1283)
        //     at com.strobel.assembler.metadata.MetadataHelper.isSubType(MetadataHelper.java:1283)
        //     at com.strobel.assembler.metadata.MetadataHelper.isSubType(MetadataHelper.java:1283)
        //     at com.strobel.assembler.metadata.MetadataHelper.isSubType(MetadataHelper.java:1283)
        //     at com.strobel.assembler.metadata.MetadataHelper.isSubType(MetadataHelper.java:1283)
        //     at com.strobel.assembler.metadata.MetadataHelper.isSubType(MetadataHelper.java:1283)
        //     at com.strobel.assembler.metadata.MetadataHelper.isSubType(MetadataHelper.java:1283)
        //     at com.strobel.assembler.metadata.MetadataHelper.isSubType(MetadataHelper.java:1283)
        //     at com.strobel.assembler.metadata.MetadataHelper.isSubType(MetadataHelper.java:1283)
        //     at com.strobel.assembler.metadata.MetadataHelper.isSubType(MetadataHelper.java:1283)
        //     at com.strobel.assembler.metadata.MetadataHelper.isSubType(MetadataHelper.java:1283)
        //     at com.strobel.assembler.metadata.MetadataHelper.isSubType(MetadataHelper.java:1283)
        //     at com.strobel.assembler.metadata.MetadataHelper.isSubType(MetadataHelper.java:1283)
        //     at com.strobel.assembler.metadata.MetadataHelper.isSubType(MetadataHelper.java:1283)
        //     at com.strobel.assembler.metadata.MetadataHelper.isSubType(MetadataHelper.java:1283)
        //     at com.strobel.assembler.metadata.MetadataHelper.isSubType(MetadataHelper.java:1283)
        //     at com.strobel.assembler.metadata.MetadataHelper.isSubType(MetadataHelper.java:1283)
        //     at com.strobel.assembler.metadata.MetadataHelper.isSubType(MetadataHelper.java:1283)
        //     at com.strobel.assembler.metadata.MetadataHelper.isSubType(MetadataHelper.java:1283)
        //     at com.strobel.assembler.metadata.MetadataHelper.isSubType(MetadataHelper.java:1283)
        //     at com.strobel.assembler.metadata.MetadataHelper.isSubType(MetadataHelper.java:1283)
        //     at com.strobel.assembler.metadata.MetadataHelper.isSubType(MetadataHelper.java:1283)
        //     at com.strobel.assembler.metadata.MetadataHelper.isSubType(MetadataHelper.java:1283)
        //     at com.strobel.assembler.metadata.MetadataHelper.isSubType(MetadataHelper.java:1283)
        //     at com.strobel.assembler.metadata.MetadataHelper.isSubType(MetadataHelper.java:1283)
        //     at com.strobel.assembler.metadata.MetadataHelper.isSubType(MetadataHelper.java:1283)
        //     at com.strobel.assembler.metadata.MetadataHelper.isSubType(MetadataHelper.java:1283)
        //     at com.strobel.assembler.metadata.MetadataHelper.isSubType(MetadataHelper.java:1283)
        //     at com.strobel.assembler.metadata.MetadataHelper.isSubType(MetadataHelper.java:1283)
        //     at com.strobel.assembler.metadata.MetadataHelper.isSubType(MetadataHelper.java:1283)
        //     at com.strobel.assembler.metadata.MetadataHelper.isSubType(MetadataHelper.java:1283)
        //     at com.strobel.assembler.metadata.MetadataHelper.isSubType(MetadataHelper.java:1283)
        //     at com.strobel.assembler.metadata.MetadataHelper.isSubType(MetadataHelper.java:1283)
        //     at com.strobel.assembler.metadata.MetadataHelper.isSubType(MetadataHelper.java:1283)
        //     at com.strobel.assembler.metadata.MetadataHelper.isSubType(MetadataHelper.java:1283)
        //     at com.strobel.assembler.metadata.MetadataHelper.isSubType(MetadataHelper.java:1283)
        //     at com.strobel.assembler.metadata.MetadataHelper.isSubType(MetadataHelper.java:1283)
        //     at com.strobel.assembler.metadata.MetadataHelper.isSubType(MetadataHelper.java:1283)
        //     at com.strobel.assembler.metadata.MetadataHelper.isSubType(MetadataHelper.java:1283)
        //     at com.strobel.assembler.metadata.MetadataHelper.isSubType(MetadataHelper.java:1283)
        //     at com.strobel.assembler.metadata.MetadataHelper.isSubType(MetadataHelper.java:1283)
        //     at com.strobel.assembler.metadata.MetadataHelper.isSubType(MetadataHelper.java:1283)
        //     at com.strobel.assembler.metadata.MetadataHelper.isSubType(MetadataHelper.java:1283)
        //     at com.strobel.assembler.metadata.MetadataHelper.isSubType(MetadataHelper.java:1283)
        //     at com.strobel.assembler.metadata.MetadataHelper.isSubType(MetadataHelper.java:1283)
        //     at com.strobel.assembler.metadata.MetadataHelper.isSubType(MetadataHelper.java:1283)
        //     at com.strobel.assembler.metadata.MetadataHelper.isSubType(MetadataHelper.java:1283)
        //     at com.strobel.assembler.metadata.MetadataHelper.isSubType(MetadataHelper.java:1283)
        //     at com.strobel.assembler.metadata.MetadataHelper.isSubType(MetadataHelper.java:1283)
        //     at com.strobel.assembler.metadata.MetadataHelper.isSubType(MetadataHelper.java:1283)
        //     at com.strobel.assembler.metadata.MetadataHelper.isSubType(MetadataHelper.java:1283)
        //     at com.strobel.assembler.metadata.MetadataHelper.isSubType(MetadataHelper.java:1283)
        //     at com.strobel.assembler.metadata.MetadataHelper.isSubType(MetadataHelper.java:1283)
        //     at com.strobel.assembler.metadata.MetadataHelper.isSubType(MetadataHelper.java:1283)
        //     at com.strobel.assembler.metadata.MetadataHelper.isSubType(MetadataHelper.java:1283)
        //     at com.strobel.assembler.metadata.MetadataHelper.isSubType(MetadataHelper.java:1283)
        //     at com.strobel.assembler.metadata.MetadataHelper.isSubType(MetadataHelper.java:1283)
        //     at com.strobel.assembler.metadata.MetadataHelper.isSubType(MetadataHelper.java:1283)
        //     at com.strobel.assembler.metadata.MetadataHelper.isSubType(MetadataHelper.java:1283)
        //     at com.strobel.assembler.metadata.MetadataHelper.isSubType(MetadataHelper.java:1283)
        //     at com.strobel.assembler.metadata.MetadataHelper.isSubType(MetadataHelper.java:1283)
        //     at com.strobel.assembler.metadata.MetadataHelper.isSubType(MetadataHelper.java:1283)
        //     at com.strobel.assembler.metadata.MetadataHelper.isSubType(MetadataHelper.java:1283)
        //     at com.strobel.assembler.metadata.MetadataHelper.isSubType(MetadataHelper.java:1283)
        //     at com.strobel.assembler.metadata.MetadataHelper.isSubType(MetadataHelper.java:1283)
        //     at com.strobel.assembler.metadata.MetadataHelper.isSubType(MetadataHelper.java:1283)
        //     at com.strobel.assembler.metadata.MetadataHelper.isSubType(MetadataHelper.java:1283)
        //     at com.strobel.assembler.metadata.MetadataHelper.isSubType(MetadataHelper.java:1283)
        //     at com.strobel.assembler.metadata.MetadataHelper.isSubType(MetadataHelper.java:1283)
        //     at com.strobel.assembler.metadata.MetadataHelper.isSubType(MetadataHelper.java:1283)
        //     at com.strobel.assembler.metadata.MetadataHelper.isSubType(MetadataHelper.java:1283)
        //     at com.strobel.assembler.metadata.MetadataHelper.isSubType(MetadataHelper.java:1283)
        //     at com.strobel.assembler.metadata.MetadataHelper.isSubType(MetadataHelper.java:1283)
        //     at com.strobel.assembler.metadata.MetadataHelper.isSubType(MetadataHelper.java:1283)
        //     at com.strobel.assembler.metadata.MetadataHelper.isSubType(MetadataHelper.java:1283)
        //     at com.strobel.assembler.metadata.MetadataHelper.isSubType(MetadataHelper.java:1283)
        //     at com.strobel.assembler.metadata.MetadataHelper.isSubType(MetadataHelper.java:1283)
        //     at com.strobel.assembler.metadata.MetadataHelper.isSubType(MetadataHelper.java:1283)
        //     at com.strobel.assembler.metadata.MetadataHelper.isSubType(MetadataHelper.java:1283)
        //     at com.strobel.assembler.metadata.MetadataHelper.isSubType(MetadataHelper.java:1283)
        //     at com.strobel.assembler.metadata.MetadataHelper.isSubType(MetadataHelper.java:1283)
        //     at com.strobel.assembler.metadata.MetadataHelper.isSubType(MetadataHelper.java:1283)
        //     at com.strobel.assembler.metadata.MetadataHelper.isSubType(MetadataHelper.java:1283)
        //     at com.strobel.assembler.metadata.MetadataHelper.isSubType(MetadataHelper.java:1283)
        //     at com.strobel.assembler.metadata.MetadataHelper.isSubType(MetadataHelper.java:1283)
        //     at com.strobel.assembler.metadata.MetadataHelper.isSubType(MetadataHelper.java:1283)
        //     at com.strobel.assembler.metadata.MetadataHelper.isSubType(MetadataHelper.java:1283)
        //     at com.strobel.assembler.metadata.MetadataHelper.isSubType(MetadataHelper.java:1283)
        //     at com.strobel.assembler.metadata.MetadataHelper.isSubType(MetadataHelper.java:1283)
        //     at com.strobel.assembler.metadata.MetadataHelper.isSubType(MetadataHelper.java:1283)
        //     at com.strobel.assembler.metadata.MetadataHelper.isSubType(MetadataHelper.java:1283)
        //     at com.strobel.assembler.metadata.MetadataHelper.isSubType(MetadataHelper.java:1283)
        //     at com.strobel.assembler.metadata.MetadataHelper.isSubType(MetadataHelper.java:1283)
        //     at com.strobel.assembler.metadata.MetadataHelper.isSubType(MetadataHelper.java:1283)
        //     at com.strobel.assembler.metadata.MetadataHelper.isSubType(MetadataHelper.java:1283)
        //     at com.strobel.assembler.metadata.MetadataHelper.isSubType(MetadataHelper.java:1283)
        //     at com.strobel.assembler.metadata.MetadataHelper.isSubType(MetadataHelper.java:1283)
        //     at com.strobel.assembler.metadata.MetadataHelper.isSubType(MetadataHelper.java:1283)
        // 
        throw new IllegalStateException("An error occurred while decompiling this method.");
    }
    
    @InlineOnly
    private static final <K, V> boolean contains(@NotNull final Map<? extends K, ? extends V> $this$contains, final K key) {
        final int $i$f$contains = 0;
        Intrinsics.checkParameterIsNotNull($this$contains, "$this$contains");
        return $this$contains.containsKey(key);
    }
    
    @InlineOnly
    private static final <K, V> V get(@NotNull final Map<? extends K, ? extends V> $this$get, final K key) {
        final int $i$f$get = 0;
        Intrinsics.checkParameterIsNotNull($this$get, "$this$get");
        return (V)$this$get.get(key);
    }
    
    @InlineOnly
    private static final <K, V> void set(@NotNull final Map<K, V> $this$set, final K key, final V value) {
        final int $i$f$set = 0;
        Intrinsics.checkParameterIsNotNull($this$set, "$this$set");
        $this$set.put(key, value);
    }
    
    @InlineOnly
    private static final <K> boolean containsKey(@NotNull final Map<? extends K, ?> $this$containsKey, final K key) {
        final int $i$f$containsKey = 0;
        if ($this$containsKey == null) {
            throw new TypeCastException("null cannot be cast to non-null type kotlin.collections.Map<K, *>");
        }
        return $this$containsKey.containsKey(key);
    }
    
    @InlineOnly
    private static final <K, V> boolean containsValue(@NotNull final Map<K, ? extends V> $this$containsValue, final V value) {
        final int $i$f$containsValue = 0;
        return $this$containsValue.containsValue(value);
    }
    
    @InlineOnly
    private static final <K, V> V remove(@NotNull final Map<? extends K, V> $this$remove, final K key) {
        final int $i$f$remove = 0;
        if ($this$remove == null) {
            throw new TypeCastException("null cannot be cast to non-null type kotlin.collections.MutableMap<K, V>");
        }
        return TypeIntrinsics.asMutableMap($this$remove).remove(key);
    }
    
    @InlineOnly
    private static final <K, V> K component1(@NotNull final Map.Entry<? extends K, ? extends V> $this$component1) {
        final int $i$f$component1 = 0;
        Intrinsics.checkParameterIsNotNull($this$component1, "$this$component1");
        return (K)$this$component1.getKey();
    }
    
    @InlineOnly
    private static final <K, V> V component2(@NotNull final Map.Entry<? extends K, ? extends V> $this$component2) {
        final int $i$f$component2 = 0;
        Intrinsics.checkParameterIsNotNull($this$component2, "$this$component2");
        return (V)$this$component2.getValue();
    }
    
    @InlineOnly
    private static final <K, V> Pair<K, V> toPair(@NotNull final Map.Entry<? extends K, ? extends V> $this$toPair) {
        final int $i$f$toPair = 0;
        return new Pair<K, V>((K)$this$toPair.getKey(), (V)$this$toPair.getValue());
    }
    
    @InlineOnly
    private static final <K, V> V getOrElse(@NotNull final Map<K, ? extends V> $this$getOrElse, final K key, final Function0<? extends V> defaultValue) {
        final int $i$f$getOrElse = 0;
        V v;
        if ((v = (V)$this$getOrElse.get(key)) == null) {
            v = (V)defaultValue.invoke();
        }
        return v;
    }
    
    public static final <K, V> V getOrElseNullable(@NotNull final Map<K, ? extends V> $this$getOrElseNullable, final K key, @NotNull final Function0<? extends V> defaultValue) {
        final int $i$f$getOrElseNullable = 0;
        Intrinsics.checkParameterIsNotNull($this$getOrElseNullable, "$this$getOrElseNullable");
        Intrinsics.checkParameterIsNotNull(defaultValue, "defaultValue");
        final Object value = $this$getOrElseNullable.get(key);
        if (value == null && !$this$getOrElseNullable.containsKey(key)) {
            return (V)defaultValue.invoke();
        }
        return (V)value;
    }
    
    @SinceKotlin(version = "1.1")
    public static final <K, V> V getValue(@NotNull final Map<K, ? extends V> $this$getValue, final K key) {
        Intrinsics.checkParameterIsNotNull($this$getValue, "$this$getValue");
        return MapsKt__MapWithDefaultKt.getOrImplicitDefaultNullable($this$getValue, key);
    }
    
    public static final <K, V> V getOrPut(@NotNull final Map<K, V> $this$getOrPut, final K key, @NotNull final Function0<? extends V> defaultValue) {
        final int $i$f$getOrPut = 0;
        Intrinsics.checkParameterIsNotNull($this$getOrPut, "$this$getOrPut");
        Intrinsics.checkParameterIsNotNull(defaultValue, "defaultValue");
        final Object value = $this$getOrPut.get(key);
        Object o;
        if (value == null) {
            final Object answer = defaultValue.invoke();
            $this$getOrPut.put(key, (V)answer);
            o = answer;
        }
        else {
            o = value;
        }
        return (V)o;
    }
    
    @InlineOnly
    private static final <K, V> Iterator<Map.Entry<K, V>> iterator(@NotNull final Map<? extends K, ? extends V> $this$iterator) {
        final int $i$f$iterator = 0;
        Intrinsics.checkParameterIsNotNull($this$iterator, "$this$iterator");
        return (Iterator<Map.Entry<K, V>>)$this$iterator.entrySet().iterator();
    }
    
    @JvmName(name = "mutableIterator")
    @InlineOnly
    private static final <K, V> Iterator<Map.Entry<K, V>> mutableIterator(@NotNull final Map<K, V> $this$iterator) {
        final int $i$f$mutableIterator = 0;
        Intrinsics.checkParameterIsNotNull($this$iterator, "$this$iterator");
        return $this$iterator.entrySet().iterator();
    }
    
    @NotNull
    public static final <K, V, R, M extends Map<? super K, ? super R>> M mapValuesTo(@NotNull final Map<? extends K, ? extends V> $this$mapValuesTo, @NotNull final M destination, @NotNull final Function1<? super Map.Entry<? extends K, ? extends V>, ? extends R> transform) {
        // 
        // This method could not be decompiled.
        // 
        // Original Bytecode:
        // 
        //     2: istore_3        /* $i$f$mapValuesTo */
        //     3: aload_0         /* $this$mapValuesTo */
        //     4: ldc_w           "$this$mapValuesTo"
        //     7: invokestatic    kotlin/jvm/internal/Intrinsics.checkParameterIsNotNull:(Ljava/lang/Object;Ljava/lang/String;)V
        //    10: aload_1         /* destination */
        //    11: ldc_w           "destination"
        //    14: invokestatic    kotlin/jvm/internal/Intrinsics.checkParameterIsNotNull:(Ljava/lang/Object;Ljava/lang/String;)V
        //    17: aload_2         /* transform */
        //    18: ldc_w           "transform"
        //    21: invokestatic    kotlin/jvm/internal/Intrinsics.checkParameterIsNotNull:(Ljava/lang/Object;Ljava/lang/String;)V
        //    24: aload_0         /* $this$mapValuesTo */
        //    25: invokeinterface java/util/Map.entrySet:()Ljava/util/Set;
        //    30: checkcast       Ljava/lang/Iterable;
        //    33: astore          $this$associateByTo$iv
        //    35: iconst_0       
        //    36: istore          $i$f$associateByTo
        //    38: aload           $this$associateByTo$iv
        //    40: invokeinterface java/lang/Iterable.iterator:()Ljava/util/Iterator;
        //    45: astore          6
        //    47: aload           6
        //    49: invokeinterface java/util/Iterator.hasNext:()Z
        //    54: ifeq            109
        //    57: aload           6
        //    59: invokeinterface java/util/Iterator.next:()Ljava/lang/Object;
        //    64: astore          element$iv
        //    66: aload_1         /* destination */
        //    67: aload           element$iv
        //    69: checkcast       Ljava/util/Map$Entry;
        //    72: astore          8
        //    74: astore          10
        //    76: iconst_0       
        //    77: istore          $i$a$-associateByTo-MapsKt__MapsKt$mapValuesTo$1
        //    79: aload           it
        //    81: invokeinterface java/util/Map$Entry.getKey:()Ljava/lang/Object;
        //    86: astore          11
        //    88: aload           10
        //    90: aload           11
        //    92: aload_2         /* transform */
        //    93: aload           element$iv
        //    95: invokeinterface kotlin/jvm/functions/Function1.invoke:(Ljava/lang/Object;)Ljava/lang/Object;
        //   100: invokeinterface java/util/Map.put:(Ljava/lang/Object;Ljava/lang/Object;)Ljava/lang/Object;
        //   105: pop            
        //   106: goto            47
        //   109: aload_1         /* destination */
        //   110: areturn        
        //    Signature:
        //  <K:Ljava/lang/Object;V:Ljava/lang/Object;R:Ljava/lang/Object;M::Ljava/util/Map<-TK;-TR;>;>(Ljava/util/Map<+TK;+TV;>;TM;Lkotlin/jvm/functions/Function1<-Ljava/util/Map$Entry<+TK;+TV;>;+TR;>;)TM;
        //    StackMapTable: 00 02 FF 00 2F 00 07 07 00 82 07 00 82 07 01 2F 01 07 01 2C 01 07 01 31 00 00 3D
        // 
        // The error that occurred was:
        // 
        // java.lang.NullPointerException
        // 
        throw new IllegalStateException("An error occurred while decompiling this method.");
    }
    
    @NotNull
    public static final <K, V, R, M extends Map<? super R, ? super V>> M mapKeysTo(@NotNull final Map<? extends K, ? extends V> $this$mapKeysTo, @NotNull final M destination, @NotNull final Function1<? super Map.Entry<? extends K, ? extends V>, ? extends R> transform) {
        // 
        // This method could not be decompiled.
        // 
        // Original Bytecode:
        // 
        //     2: istore_3        /* $i$f$mapKeysTo */
        //     3: aload_0         /* $this$mapKeysTo */
        //     4: ldc_w           "$this$mapKeysTo"
        //     7: invokestatic    kotlin/jvm/internal/Intrinsics.checkParameterIsNotNull:(Ljava/lang/Object;Ljava/lang/String;)V
        //    10: aload_1         /* destination */
        //    11: ldc_w           "destination"
        //    14: invokestatic    kotlin/jvm/internal/Intrinsics.checkParameterIsNotNull:(Ljava/lang/Object;Ljava/lang/String;)V
        //    17: aload_2         /* transform */
        //    18: ldc_w           "transform"
        //    21: invokestatic    kotlin/jvm/internal/Intrinsics.checkParameterIsNotNull:(Ljava/lang/Object;Ljava/lang/String;)V
        //    24: aload_0         /* $this$mapKeysTo */
        //    25: invokeinterface java/util/Map.entrySet:()Ljava/util/Set;
        //    30: checkcast       Ljava/lang/Iterable;
        //    33: astore          $this$associateByTo$iv
        //    35: iconst_0       
        //    36: istore          $i$f$associateByTo
        //    38: aload           $this$associateByTo$iv
        //    40: invokeinterface java/lang/Iterable.iterator:()Ljava/util/Iterator;
        //    45: astore          6
        //    47: aload           6
        //    49: invokeinterface java/util/Iterator.hasNext:()Z
        //    54: ifeq            113
        //    57: aload           6
        //    59: invokeinterface java/util/Iterator.next:()Ljava/lang/Object;
        //    64: astore          element$iv
        //    66: aload_1         /* destination */
        //    67: aload_2         /* transform */
        //    68: aload           element$iv
        //    70: invokeinterface kotlin/jvm/functions/Function1.invoke:(Ljava/lang/Object;)Ljava/lang/Object;
        //    75: aload           element$iv
        //    77: checkcast       Ljava/util/Map$Entry;
        //    80: astore          8
        //    82: astore          11
        //    84: astore          10
        //    86: iconst_0       
        //    87: istore          $i$a$-associateByTo-MapsKt__MapsKt$mapKeysTo$1
        //    89: aload           it
        //    91: invokeinterface java/util/Map$Entry.getValue:()Ljava/lang/Object;
        //    96: astore          12
        //    98: aload           10
        //   100: aload           11
        //   102: aload           12
        //   104: invokeinterface java/util/Map.put:(Ljava/lang/Object;Ljava/lang/Object;)Ljava/lang/Object;
        //   109: pop            
        //   110: goto            47
        //   113: aload_1         /* destination */
        //   114: areturn        
        //    Signature:
        //  <K:Ljava/lang/Object;V:Ljava/lang/Object;R:Ljava/lang/Object;M::Ljava/util/Map<-TR;-TV;>;>(Ljava/util/Map<+TK;+TV;>;TM;Lkotlin/jvm/functions/Function1<-Ljava/util/Map$Entry<+TK;+TV;>;+TR;>;)TM;
        //    StackMapTable: 00 02 FF 00 2F 00 07 07 00 82 07 00 82 07 01 2F 01 07 01 2C 01 07 01 31 00 00 FB 00 41
        // 
        // The error that occurred was:
        // 
        // java.lang.NullPointerException
        // 
        throw new IllegalStateException("An error occurred while decompiling this method.");
    }
    
    public static final <K, V> void putAll(@NotNull final Map<? super K, ? super V> $this$putAll, @NotNull final Pair<? extends K, ? extends V>[] pairs) {
        Intrinsics.checkParameterIsNotNull($this$putAll, "$this$putAll");
        Intrinsics.checkParameterIsNotNull(pairs, "pairs");
        for (final Pair<? extends K, ? extends V> pair : pairs) {
            final Object key = pair.component1();
            final Object value = pair.component2();
            $this$putAll.put((Object)key, (Object)value);
        }
    }
    
    public static final <K, V> void putAll(@NotNull final Map<? super K, ? super V> $this$putAll, @NotNull final Iterable<? extends Pair<? extends K, ? extends V>> pairs) {
        Intrinsics.checkParameterIsNotNull($this$putAll, "$this$putAll");
        Intrinsics.checkParameterIsNotNull(pairs, "pairs");
        for (final Pair<Object, B> pair : pairs) {
            final Object key = pair.component1();
            final Object value = pair.component2();
            $this$putAll.put((Object)key, (Object)value);
        }
    }
    
    public static final <K, V> void putAll(@NotNull final Map<? super K, ? super V> $this$putAll, @NotNull final Sequence<? extends Pair<? extends K, ? extends V>> pairs) {
        Intrinsics.checkParameterIsNotNull($this$putAll, "$this$putAll");
        Intrinsics.checkParameterIsNotNull(pairs, "pairs");
        for (final Pair<Object, B> pair : pairs) {
            final Object key = pair.component1();
            final Object value = pair.component2();
            $this$putAll.put((Object)key, (Object)value);
        }
    }
    
    @NotNull
    public static final <K, V, R> Map<K, R> mapValues(@NotNull final Map<? extends K, ? extends V> $this$mapValues, @NotNull final Function1<? super Map.Entry<? extends K, ? extends V>, ? extends R> transform) {
        // 
        // This method could not be decompiled.
        // 
        // Original Bytecode:
        // 
        //     2: istore_2        /* $i$f$mapValues */
        //     3: aload_0         /* $this$mapValues */
        //     4: ldc_w           "$this$mapValues"
        //     7: invokestatic    kotlin/jvm/internal/Intrinsics.checkParameterIsNotNull:(Ljava/lang/Object;Ljava/lang/String;)V
        //    10: aload_1         /* transform */
        //    11: ldc_w           "transform"
        //    14: invokestatic    kotlin/jvm/internal/Intrinsics.checkParameterIsNotNull:(Ljava/lang/Object;Ljava/lang/String;)V
        //    17: aload_0         /* $this$mapValues */
        //    18: astore_3       
        //    19: new             Ljava/util/LinkedHashMap;
        //    22: dup            
        //    23: aload_0         /* $this$mapValues */
        //    24: invokeinterface java/util/Map.size:()I
        //    29: invokestatic    kotlin/collections/MapsKt.mapCapacity:(I)I
        //    32: invokespecial   java/util/LinkedHashMap.<init>:(I)V
        //    35: checkcast       Ljava/util/Map;
        //    38: astore          destination$iv
        //    40: iconst_0       
        //    41: istore          $i$f$mapValuesTo
        //    43: aload_3         /* $this$mapValuesTo$iv */
        //    44: invokeinterface java/util/Map.entrySet:()Ljava/util/Set;
        //    49: checkcast       Ljava/lang/Iterable;
        //    52: astore          $this$associateByTo$iv$iv
        //    54: iconst_0       
        //    55: istore          $i$f$associateByTo
        //    57: aload           $this$associateByTo$iv$iv
        //    59: invokeinterface java/lang/Iterable.iterator:()Ljava/util/Iterator;
        //    64: astore          8
        //    66: aload           8
        //    68: invokeinterface java/util/Iterator.hasNext:()Z
        //    73: ifeq            129
        //    76: aload           8
        //    78: invokeinterface java/util/Iterator.next:()Ljava/lang/Object;
        //    83: astore          element$iv$iv
        //    85: aload           destination$iv
        //    87: aload           element$iv$iv
        //    89: checkcast       Ljava/util/Map$Entry;
        //    92: astore          10
        //    94: astore          11
        //    96: iconst_0       
        //    97: istore          $i$a$-associateByTo-MapsKt__MapsKt$mapValuesTo$1$iv
        //    99: aload           it$iv
        //   101: invokeinterface java/util/Map$Entry.getKey:()Ljava/lang/Object;
        //   106: astore          13
        //   108: aload           11
        //   110: aload           13
        //   112: aload_1         /* transform */
        //   113: aload           element$iv$iv
        //   115: invokeinterface kotlin/jvm/functions/Function1.invoke:(Ljava/lang/Object;)Ljava/lang/Object;
        //   120: invokeinterface java/util/Map.put:(Ljava/lang/Object;Ljava/lang/Object;)Ljava/lang/Object;
        //   125: pop            
        //   126: goto            66
        //   129: aload           destination$iv
        //   131: nop            
        //   132: areturn        
        //    Signature:
        //  <K:Ljava/lang/Object;V:Ljava/lang/Object;R:Ljava/lang/Object;>(Ljava/util/Map<+TK;+TV;>;Lkotlin/jvm/functions/Function1<-Ljava/util/Map$Entry<+TK;+TV;>;+TR;>;)Ljava/util/Map<TK;TR;>;
        //    StackMapTable: 00 02 FF 00 42 00 09 07 00 82 07 01 2F 01 07 00 82 07 00 82 01 07 01 2C 01 07 01 31 00 00 3E
        // 
        // The error that occurred was:
        // 
        // java.lang.NullPointerException
        // 
        throw new IllegalStateException("An error occurred while decompiling this method.");
    }
    
    @NotNull
    public static final <K, V, R> Map<R, V> mapKeys(@NotNull final Map<? extends K, ? extends V> $this$mapKeys, @NotNull final Function1<? super Map.Entry<? extends K, ? extends V>, ? extends R> transform) {
        // 
        // This method could not be decompiled.
        // 
        // Original Bytecode:
        // 
        //     2: istore_2        /* $i$f$mapKeys */
        //     3: aload_0         /* $this$mapKeys */
        //     4: ldc_w           "$this$mapKeys"
        //     7: invokestatic    kotlin/jvm/internal/Intrinsics.checkParameterIsNotNull:(Ljava/lang/Object;Ljava/lang/String;)V
        //    10: aload_1         /* transform */
        //    11: ldc_w           "transform"
        //    14: invokestatic    kotlin/jvm/internal/Intrinsics.checkParameterIsNotNull:(Ljava/lang/Object;Ljava/lang/String;)V
        //    17: aload_0         /* $this$mapKeys */
        //    18: astore_3       
        //    19: new             Ljava/util/LinkedHashMap;
        //    22: dup            
        //    23: aload_0         /* $this$mapKeys */
        //    24: invokeinterface java/util/Map.size:()I
        //    29: invokestatic    kotlin/collections/MapsKt.mapCapacity:(I)I
        //    32: invokespecial   java/util/LinkedHashMap.<init>:(I)V
        //    35: checkcast       Ljava/util/Map;
        //    38: astore          destination$iv
        //    40: iconst_0       
        //    41: istore          $i$f$mapKeysTo
        //    43: aload_3         /* $this$mapKeysTo$iv */
        //    44: invokeinterface java/util/Map.entrySet:()Ljava/util/Set;
        //    49: checkcast       Ljava/lang/Iterable;
        //    52: astore          $this$associateByTo$iv$iv
        //    54: iconst_0       
        //    55: istore          $i$f$associateByTo
        //    57: aload           $this$associateByTo$iv$iv
        //    59: invokeinterface java/lang/Iterable.iterator:()Ljava/util/Iterator;
        //    64: astore          8
        //    66: aload           8
        //    68: invokeinterface java/util/Iterator.hasNext:()Z
        //    73: ifeq            133
        //    76: aload           8
        //    78: invokeinterface java/util/Iterator.next:()Ljava/lang/Object;
        //    83: astore          element$iv$iv
        //    85: aload           destination$iv
        //    87: aload_1         /* transform */
        //    88: aload           element$iv$iv
        //    90: invokeinterface kotlin/jvm/functions/Function1.invoke:(Ljava/lang/Object;)Ljava/lang/Object;
        //    95: aload           element$iv$iv
        //    97: checkcast       Ljava/util/Map$Entry;
        //   100: astore          10
        //   102: astore          11
        //   104: astore          12
        //   106: iconst_0       
        //   107: istore          $i$a$-associateByTo-MapsKt__MapsKt$mapKeysTo$1$iv
        //   109: aload           it$iv
        //   111: invokeinterface java/util/Map$Entry.getValue:()Ljava/lang/Object;
        //   116: astore          14
        //   118: aload           12
        //   120: aload           11
        //   122: aload           14
        //   124: invokeinterface java/util/Map.put:(Ljava/lang/Object;Ljava/lang/Object;)Ljava/lang/Object;
        //   129: pop            
        //   130: goto            66
        //   133: aload           destination$iv
        //   135: nop            
        //   136: areturn        
        //    Signature:
        //  <K:Ljava/lang/Object;V:Ljava/lang/Object;R:Ljava/lang/Object;>(Ljava/util/Map<+TK;+TV;>;Lkotlin/jvm/functions/Function1<-Ljava/util/Map$Entry<+TK;+TV;>;+TR;>;)Ljava/util/Map<TR;TV;>;
        //    StackMapTable: 00 02 FF 00 42 00 09 07 00 82 07 01 2F 01 07 00 82 07 00 82 01 07 01 2C 01 07 01 31 00 00 FB 00 42
        // 
        // The error that occurred was:
        // 
        // java.lang.NullPointerException
        // 
        throw new IllegalStateException("An error occurred while decompiling this method.");
    }
    
    @NotNull
    public static final <K, V> Map<K, V> filterKeys(@NotNull final Map<? extends K, ? extends V> $this$filterKeys, @NotNull final Function1<? super K, Boolean> predicate) {
        final int $i$f$filterKeys = 0;
        Intrinsics.checkParameterIsNotNull($this$filterKeys, "$this$filterKeys");
        Intrinsics.checkParameterIsNotNull(predicate, "predicate");
        final LinkedHashMap result = new LinkedHashMap();
        for (final Map.Entry entry : $this$filterKeys.entrySet()) {
            if (predicate.invoke(entry.getKey())) {
                result.put(entry.getKey(), entry.getValue());
            }
        }
        return (Map<K, V>)result;
    }
    
    @NotNull
    public static final <K, V> Map<K, V> filterValues(@NotNull final Map<? extends K, ? extends V> $this$filterValues, @NotNull final Function1<? super V, Boolean> predicate) {
        final int $i$f$filterValues = 0;
        Intrinsics.checkParameterIsNotNull($this$filterValues, "$this$filterValues");
        Intrinsics.checkParameterIsNotNull(predicate, "predicate");
        final LinkedHashMap result = new LinkedHashMap();
        for (final Map.Entry entry : $this$filterValues.entrySet()) {
            if (predicate.invoke(entry.getValue())) {
                result.put(entry.getKey(), entry.getValue());
            }
        }
        return (Map<K, V>)result;
    }
    
    @NotNull
    public static final <K, V, M extends Map<? super K, ? super V>> M filterTo(@NotNull final Map<? extends K, ? extends V> $this$filterTo, @NotNull final M destination, @NotNull final Function1<? super Map.Entry<? extends K, ? extends V>, Boolean> predicate) {
        final int $i$f$filterTo = 0;
        Intrinsics.checkParameterIsNotNull($this$filterTo, "$this$filterTo");
        Intrinsics.checkParameterIsNotNull(destination, "destination");
        Intrinsics.checkParameterIsNotNull(predicate, "predicate");
        for (final Map.Entry element : $this$filterTo.entrySet()) {
            if (predicate.invoke((Object)element)) {
                destination.put(element.getKey(), element.getValue());
            }
        }
        return destination;
    }
    
    @NotNull
    public static final <K, V> Map<K, V> filter(@NotNull final Map<? extends K, ? extends V> $this$filter, @NotNull final Function1<? super Map.Entry<? extends K, ? extends V>, Boolean> predicate) {
        // 
        // This method could not be decompiled.
        // 
        // Original Bytecode:
        // 
        //     2: istore_2        /* $i$f$filter */
        //     3: aload_0         /* $this$filter */
        //     4: ldc_w           "$this$filter"
        //     7: invokestatic    kotlin/jvm/internal/Intrinsics.checkParameterIsNotNull:(Ljava/lang/Object;Ljava/lang/String;)V
        //    10: aload_1         /* predicate */
        //    11: ldc_w           "predicate"
        //    14: invokestatic    kotlin/jvm/internal/Intrinsics.checkParameterIsNotNull:(Ljava/lang/Object;Ljava/lang/String;)V
        //    17: aload_0         /* $this$filter */
        //    18: astore_3       
        //    19: new             Ljava/util/LinkedHashMap;
        //    22: dup            
        //    23: invokespecial   java/util/LinkedHashMap.<init>:()V
        //    26: checkcast       Ljava/util/Map;
        //    29: astore          destination$iv
        //    31: iconst_0       
        //    32: istore          $i$f$filterTo
        //    34: aload_3         /* $this$filterTo$iv */
        //    35: astore          6
        //    37: iconst_0       
        //    38: istore          7
        //    40: aload           6
        //    42: invokeinterface java/util/Map.entrySet:()Ljava/util/Set;
        //    47: invokeinterface java/util/Set.iterator:()Ljava/util/Iterator;
        //    52: astore          8
        //    54: aload           8
        //    56: invokeinterface java/util/Iterator.hasNext:()Z
        //    61: ifeq            118
        //    64: aload           8
        //    66: invokeinterface java/util/Iterator.next:()Ljava/lang/Object;
        //    71: checkcast       Ljava/util/Map$Entry;
        //    74: astore          element$iv
        //    76: aload_1         /* predicate */
        //    77: aload           element$iv
        //    79: invokeinterface kotlin/jvm/functions/Function1.invoke:(Ljava/lang/Object;)Ljava/lang/Object;
        //    84: checkcast       Ljava/lang/Boolean;
        //    87: invokevirtual   java/lang/Boolean.booleanValue:()Z
        //    90: ifeq            115
        //    93: aload           destination$iv
        //    95: aload           element$iv
        //    97: invokeinterface java/util/Map$Entry.getKey:()Ljava/lang/Object;
        //   102: aload           element$iv
        //   104: invokeinterface java/util/Map$Entry.getValue:()Ljava/lang/Object;
        //   109: invokeinterface java/util/Map.put:(Ljava/lang/Object;Ljava/lang/Object;)Ljava/lang/Object;
        //   114: pop            
        //   115: goto            54
        //   118: aload           destination$iv
        //   120: areturn        
        //    Signature:
        //  <K:Ljava/lang/Object;V:Ljava/lang/Object;>(Ljava/util/Map<+TK;+TV;>;Lkotlin/jvm/functions/Function1<-Ljava/util/Map$Entry<+TK;+TV;>;Ljava/lang/Boolean;>;)Ljava/util/Map<TK;TV;>;
        //    StackMapTable: 00 03 FF 00 36 00 09 07 00 82 07 01 2F 01 07 00 82 07 00 82 01 07 00 82 01 07 01 31 00 00 FC 00 3C 07 00 F5 FA 00 02
        // 
        // The error that occurred was:
        // 
        // java.lang.NullPointerException
        // 
        throw new IllegalStateException("An error occurred while decompiling this method.");
    }
    
    @NotNull
    public static final <K, V, M extends Map<? super K, ? super V>> M filterNotTo(@NotNull final Map<? extends K, ? extends V> $this$filterNotTo, @NotNull final M destination, @NotNull final Function1<? super Map.Entry<? extends K, ? extends V>, Boolean> predicate) {
        final int $i$f$filterNotTo = 0;
        Intrinsics.checkParameterIsNotNull($this$filterNotTo, "$this$filterNotTo");
        Intrinsics.checkParameterIsNotNull(destination, "destination");
        Intrinsics.checkParameterIsNotNull(predicate, "predicate");
        for (final Map.Entry element : $this$filterNotTo.entrySet()) {
            if (!predicate.invoke((Object)element)) {
                destination.put(element.getKey(), element.getValue());
            }
        }
        return destination;
    }
    
    @NotNull
    public static final <K, V> Map<K, V> filterNot(@NotNull final Map<? extends K, ? extends V> $this$filterNot, @NotNull final Function1<? super Map.Entry<? extends K, ? extends V>, Boolean> predicate) {
        // 
        // This method could not be decompiled.
        // 
        // Original Bytecode:
        // 
        //     2: istore_2        /* $i$f$filterNot */
        //     3: aload_0         /* $this$filterNot */
        //     4: ldc_w           "$this$filterNot"
        //     7: invokestatic    kotlin/jvm/internal/Intrinsics.checkParameterIsNotNull:(Ljava/lang/Object;Ljava/lang/String;)V
        //    10: aload_1         /* predicate */
        //    11: ldc_w           "predicate"
        //    14: invokestatic    kotlin/jvm/internal/Intrinsics.checkParameterIsNotNull:(Ljava/lang/Object;Ljava/lang/String;)V
        //    17: aload_0         /* $this$filterNot */
        //    18: astore_3       
        //    19: new             Ljava/util/LinkedHashMap;
        //    22: dup            
        //    23: invokespecial   java/util/LinkedHashMap.<init>:()V
        //    26: checkcast       Ljava/util/Map;
        //    29: astore          destination$iv
        //    31: iconst_0       
        //    32: istore          $i$f$filterNotTo
        //    34: aload_3         /* $this$filterNotTo$iv */
        //    35: astore          6
        //    37: iconst_0       
        //    38: istore          7
        //    40: aload           6
        //    42: invokeinterface java/util/Map.entrySet:()Ljava/util/Set;
        //    47: invokeinterface java/util/Set.iterator:()Ljava/util/Iterator;
        //    52: astore          8
        //    54: aload           8
        //    56: invokeinterface java/util/Iterator.hasNext:()Z
        //    61: ifeq            118
        //    64: aload           8
        //    66: invokeinterface java/util/Iterator.next:()Ljava/lang/Object;
        //    71: checkcast       Ljava/util/Map$Entry;
        //    74: astore          element$iv
        //    76: aload_1         /* predicate */
        //    77: aload           element$iv
        //    79: invokeinterface kotlin/jvm/functions/Function1.invoke:(Ljava/lang/Object;)Ljava/lang/Object;
        //    84: checkcast       Ljava/lang/Boolean;
        //    87: invokevirtual   java/lang/Boolean.booleanValue:()Z
        //    90: ifne            115
        //    93: aload           destination$iv
        //    95: aload           element$iv
        //    97: invokeinterface java/util/Map$Entry.getKey:()Ljava/lang/Object;
        //   102: aload           element$iv
        //   104: invokeinterface java/util/Map$Entry.getValue:()Ljava/lang/Object;
        //   109: invokeinterface java/util/Map.put:(Ljava/lang/Object;Ljava/lang/Object;)Ljava/lang/Object;
        //   114: pop            
        //   115: goto            54
        //   118: aload           destination$iv
        //   120: areturn        
        //    Signature:
        //  <K:Ljava/lang/Object;V:Ljava/lang/Object;>(Ljava/util/Map<+TK;+TV;>;Lkotlin/jvm/functions/Function1<-Ljava/util/Map$Entry<+TK;+TV;>;Ljava/lang/Boolean;>;)Ljava/util/Map<TK;TV;>;
        //    StackMapTable: 00 03 FF 00 36 00 09 07 00 82 07 01 2F 01 07 00 82 07 00 82 01 07 00 82 01 07 01 31 00 00 FC 00 3C 07 00 F5 FA 00 02
        // 
        // The error that occurred was:
        // 
        // java.lang.NullPointerException
        // 
        throw new IllegalStateException("An error occurred while decompiling this method.");
    }
    
    @NotNull
    public static final <K, V> Map<K, V> toMap(@NotNull final Iterable<? extends Pair<? extends K, ? extends V>> $this$toMap) {
        Intrinsics.checkParameterIsNotNull($this$toMap, "$this$toMap");
        if ($this$toMap instanceof Collection) {
            Map<K, V> map = null;
            switch (((Collection)$this$toMap).size()) {
                case 0: {
                    map = emptyMap();
                    break;
                }
                case 1: {
                    map = MapsKt__MapsJVMKt.mapOf((Pair<? extends K, ? extends V>)(($this$toMap instanceof List) ? ((List<Pair>)$this$toMap).get(0) : $this$toMap.iterator().next()));
                    break;
                }
                default: {
                    map = (Map<K, V>)toMap((Iterable<? extends Pair<?, ?>>)$this$toMap, (LinkedHashMap)new LinkedHashMap(mapCapacity(((List<Pair>)$this$toMap).size())));
                    break;
                }
            }
            return map;
        }
        return optimizeReadOnlyMap((Map<K, ? extends V>)toMap((Iterable<? extends Pair<?, ?>>)$this$toMap, (LinkedHashMap<K, ? extends V>)new LinkedHashMap<Object, Object>()));
    }
    
    @NotNull
    public static final <K, V, M extends Map<? super K, ? super V>> M toMap(@NotNull final Iterable<? extends Pair<? extends K, ? extends V>> $this$toMap, @NotNull final M destination) {
        Intrinsics.checkParameterIsNotNull($this$toMap, "$this$toMap");
        Intrinsics.checkParameterIsNotNull(destination, "destination");
        final Map $this$apply = destination;
        final int n = 0;
        putAll((Map<? super Object, ? super Object>)$this$apply, (Iterable<? extends Pair<?, ?>>)$this$toMap);
        return destination;
    }
    
    @NotNull
    public static final <K, V> Map<K, V> toMap(@NotNull final Pair<? extends K, ? extends V>[] $this$toMap) {
        Intrinsics.checkParameterIsNotNull($this$toMap, "$this$toMap");
        Map<K, V> map = null;
        switch (((Pair<? extends K, ? extends V>[])$this$toMap).length) {
            case 0: {
                map = emptyMap();
                break;
            }
            case 1: {
                map = MapsKt__MapsJVMKt.mapOf($this$toMap[0]);
                break;
            }
            default: {
                map = (Map<K, V>)toMap((Pair<?, ?>[])$this$toMap, (LinkedHashMap)new LinkedHashMap(mapCapacity(((Pair<? extends K, ? extends V>[])$this$toMap).length)));
                break;
            }
        }
        return map;
    }
    
    @NotNull
    public static final <K, V, M extends Map<? super K, ? super V>> M toMap(@NotNull final Pair<? extends K, ? extends V>[] $this$toMap, @NotNull final M destination) {
        Intrinsics.checkParameterIsNotNull($this$toMap, "$this$toMap");
        Intrinsics.checkParameterIsNotNull(destination, "destination");
        final Map $this$apply = destination;
        final int n = 0;
        putAll((Map<? super Object, ? super Object>)$this$apply, (Pair<?, ?>[])$this$toMap);
        return destination;
    }
    
    @NotNull
    public static final <K, V> Map<K, V> toMap(@NotNull final Sequence<? extends Pair<? extends K, ? extends V>> $this$toMap) {
        Intrinsics.checkParameterIsNotNull($this$toMap, "$this$toMap");
        return optimizeReadOnlyMap((Map<K, ? extends V>)toMap((Sequence<? extends Pair<?, ?>>)$this$toMap, (LinkedHashMap<K, ? extends V>)new LinkedHashMap<Object, Object>()));
    }
    
    @NotNull
    public static final <K, V, M extends Map<? super K, ? super V>> M toMap(@NotNull final Sequence<? extends Pair<? extends K, ? extends V>> $this$toMap, @NotNull final M destination) {
        Intrinsics.checkParameterIsNotNull($this$toMap, "$this$toMap");
        Intrinsics.checkParameterIsNotNull(destination, "destination");
        final Map $this$apply = destination;
        final int n = 0;
        putAll((Map<? super Object, ? super Object>)$this$apply, (Sequence<? extends Pair<?, ?>>)$this$toMap);
        return destination;
    }
    
    @SinceKotlin(version = "1.1")
    @NotNull
    public static final <K, V> Map<K, V> toMap(@NotNull final Map<? extends K, ? extends V> $this$toMap) {
        Intrinsics.checkParameterIsNotNull($this$toMap, "$this$toMap");
        Object o = null;
        switch ($this$toMap.size()) {
            case 0: {
                o = emptyMap();
                break;
            }
            case 1: {
                o = MapsKt__MapsJVMKt.toSingletonMap((Map<?, ?>)$this$toMap);
                break;
            }
            default: {
                o = toMutableMap((Map<?, ?>)$this$toMap);
                break;
            }
        }
        return (Map<K, V>)o;
    }
    
    @SinceKotlin(version = "1.1")
    @NotNull
    public static final <K, V> Map<K, V> toMutableMap(@NotNull final Map<? extends K, ? extends V> $this$toMutableMap) {
        Intrinsics.checkParameterIsNotNull($this$toMutableMap, "$this$toMutableMap");
        return new LinkedHashMap<K, V>($this$toMutableMap);
    }
    
    @SinceKotlin(version = "1.1")
    @NotNull
    public static final <K, V, M extends Map<? super K, ? super V>> M toMap(@NotNull final Map<? extends K, ? extends V> $this$toMap, @NotNull final M destination) {
        Intrinsics.checkParameterIsNotNull($this$toMap, "$this$toMap");
        Intrinsics.checkParameterIsNotNull(destination, "destination");
        final Map $this$apply = destination;
        final int n = 0;
        $this$apply.putAll($this$toMap);
        return destination;
    }
    
    @NotNull
    public static final <K, V> Map<K, V> plus(@NotNull final Map<? extends K, ? extends V> $this$plus, @NotNull final Pair<? extends K, ? extends V> pair) {
        Intrinsics.checkParameterIsNotNull($this$plus, "$this$plus");
        Intrinsics.checkParameterIsNotNull(pair, "pair");
        Map<K, V> map;
        if ($this$plus.isEmpty()) {
            map = MapsKt__MapsJVMKt.mapOf(pair);
        }
        else {
            final LinkedHashMap $this$apply;
            final LinkedHashMap linkedHashMap = $this$apply = new LinkedHashMap((Map<? extends K, ? extends V>)$this$plus);
            final int n = 0;
            $this$apply.put(pair.getFirst(), pair.getSecond());
            map = (LinkedHashMap<K, V>)linkedHashMap;
        }
        return map;
    }
    
    @NotNull
    public static final <K, V> Map<K, V> plus(@NotNull final Map<? extends K, ? extends V> $this$plus, @NotNull final Iterable<? extends Pair<? extends K, ? extends V>> pairs) {
        Intrinsics.checkParameterIsNotNull($this$plus, "$this$plus");
        Intrinsics.checkParameterIsNotNull(pairs, "pairs");
        Map<K, V> map;
        if ($this$plus.isEmpty()) {
            map = toMap(pairs);
        }
        else {
            final LinkedHashMap $this$apply;
            final LinkedHashMap linkedHashMap = $this$apply = new LinkedHashMap((Map<? extends K, ? extends V>)$this$plus);
            final int n = 0;
            putAll((Map<? super Object, ? super Object>)$this$apply, (Iterable<? extends Pair<?, ?>>)pairs);
            map = (LinkedHashMap<K, V>)linkedHashMap;
        }
        return map;
    }
    
    @NotNull
    public static final <K, V> Map<K, V> plus(@NotNull final Map<? extends K, ? extends V> $this$plus, @NotNull final Pair<? extends K, ? extends V>[] pairs) {
        Intrinsics.checkParameterIsNotNull($this$plus, "$this$plus");
        Intrinsics.checkParameterIsNotNull(pairs, "pairs");
        Map<K, V> map;
        if ($this$plus.isEmpty()) {
            map = toMap(pairs);
        }
        else {
            final LinkedHashMap $this$apply;
            final LinkedHashMap linkedHashMap = $this$apply = new LinkedHashMap((Map<? extends K, ? extends V>)$this$plus);
            final int n = 0;
            putAll((Map<? super Object, ? super Object>)$this$apply, (Pair<?, ?>[])pairs);
            map = (LinkedHashMap<K, V>)linkedHashMap;
        }
        return map;
    }
    
    @NotNull
    public static final <K, V> Map<K, V> plus(@NotNull final Map<? extends K, ? extends V> $this$plus, @NotNull final Sequence<? extends Pair<? extends K, ? extends V>> pairs) {
        Intrinsics.checkParameterIsNotNull($this$plus, "$this$plus");
        Intrinsics.checkParameterIsNotNull(pairs, "pairs");
        final LinkedHashMap $this$apply;
        final LinkedHashMap linkedHashMap = $this$apply = new LinkedHashMap((Map<? extends K, ? extends V>)$this$plus);
        final int n = 0;
        putAll((Map<? super Object, ? super Object>)$this$apply, (Sequence<? extends Pair<?, ?>>)pairs);
        return (Map<K, V>)optimizeReadOnlyMap((Map<K, ?>)linkedHashMap);
    }
    
    @NotNull
    public static final <K, V> Map<K, V> plus(@NotNull final Map<? extends K, ? extends V> $this$plus, @NotNull final Map<? extends K, ? extends V> map) {
        Intrinsics.checkParameterIsNotNull($this$plus, "$this$plus");
        Intrinsics.checkParameterIsNotNull(map, "map");
        final LinkedHashMap $this$apply;
        final LinkedHashMap linkedHashMap = $this$apply = new LinkedHashMap((Map<? extends K, ? extends V>)$this$plus);
        final int n = 0;
        $this$apply.putAll(map);
        return (LinkedHashMap<K, V>)linkedHashMap;
    }
    
    @InlineOnly
    private static final <K, V> void plusAssign(@NotNull final Map<? super K, ? super V> $this$plusAssign, final Pair<? extends K, ? extends V> pair) {
        final int $i$f$plusAssign = 0;
        Intrinsics.checkParameterIsNotNull($this$plusAssign, "$this$plusAssign");
        $this$plusAssign.put((Object)pair.getFirst(), (Object)pair.getSecond());
    }
    
    @InlineOnly
    private static final <K, V> void plusAssign(@NotNull final Map<? super K, ? super V> $this$plusAssign, final Iterable<? extends Pair<? extends K, ? extends V>> pairs) {
        final int $i$f$plusAssign = 0;
        Intrinsics.checkParameterIsNotNull($this$plusAssign, "$this$plusAssign");
        putAll((Map<? super Object, ? super Object>)$this$plusAssign, (Iterable<? extends Pair<?, ?>>)pairs);
    }
    
    @InlineOnly
    private static final <K, V> void plusAssign(@NotNull final Map<? super K, ? super V> $this$plusAssign, final Pair<? extends K, ? extends V>[] pairs) {
        final int $i$f$plusAssign = 0;
        Intrinsics.checkParameterIsNotNull($this$plusAssign, "$this$plusAssign");
        putAll((Map<? super Object, ? super Object>)$this$plusAssign, (Pair<?, ?>[])pairs);
    }
    
    @InlineOnly
    private static final <K, V> void plusAssign(@NotNull final Map<? super K, ? super V> $this$plusAssign, final Sequence<? extends Pair<? extends K, ? extends V>> pairs) {
        final int $i$f$plusAssign = 0;
        Intrinsics.checkParameterIsNotNull($this$plusAssign, "$this$plusAssign");
        putAll((Map<? super Object, ? super Object>)$this$plusAssign, (Sequence<? extends Pair<?, ?>>)pairs);
    }
    
    @InlineOnly
    private static final <K, V> void plusAssign(@NotNull final Map<? super K, ? super V> $this$plusAssign, final Map<K, ? extends V> map) {
        final int $i$f$plusAssign = 0;
        Intrinsics.checkParameterIsNotNull($this$plusAssign, "$this$plusAssign");
        $this$plusAssign.putAll((Map<? extends K, ? extends V>)map);
    }
    
    @SinceKotlin(version = "1.1")
    @NotNull
    public static final <K, V> Map<K, V> minus(@NotNull final Map<? extends K, ? extends V> $this$minus, final K key) {
        Intrinsics.checkParameterIsNotNull($this$minus, "$this$minus");
        final Map $this$apply;
        final Map $this$optimizeReadOnlyMap = $this$apply = toMutableMap((Map<?, ?>)$this$minus);
        final int n = 0;
        $this$apply.remove(key);
        return optimizeReadOnlyMap((Map<K, ? extends V>)$this$optimizeReadOnlyMap);
    }
    
    @SinceKotlin(version = "1.1")
    @NotNull
    public static final <K, V> Map<K, V> minus(@NotNull final Map<? extends K, ? extends V> $this$minus, @NotNull final Iterable<? extends K> keys) {
        Intrinsics.checkParameterIsNotNull($this$minus, "$this$minus");
        Intrinsics.checkParameterIsNotNull(keys, "keys");
        final Map $this$apply;
        final Map $this$optimizeReadOnlyMap = $this$apply = toMutableMap((Map<?, ?>)$this$minus);
        final int n = 0;
        CollectionsKt__MutableCollectionsKt.removeAll((Collection<? super Object>)$this$apply.keySet(), (Iterable<?>)keys);
        return optimizeReadOnlyMap((Map<K, ? extends V>)$this$optimizeReadOnlyMap);
    }
    
    @SinceKotlin(version = "1.1")
    @NotNull
    public static final <K, V> Map<K, V> minus(@NotNull final Map<? extends K, ? extends V> $this$minus, @NotNull final K[] keys) {
        Intrinsics.checkParameterIsNotNull($this$minus, "$this$minus");
        Intrinsics.checkParameterIsNotNull(keys, "keys");
        final Map $this$apply;
        final Map $this$optimizeReadOnlyMap = $this$apply = toMutableMap((Map<?, ?>)$this$minus);
        final int n = 0;
        CollectionsKt__MutableCollectionsKt.removeAll($this$apply.keySet(), keys);
        return optimizeReadOnlyMap((Map<K, ? extends V>)$this$optimizeReadOnlyMap);
    }
    
    @SinceKotlin(version = "1.1")
    @NotNull
    public static final <K, V> Map<K, V> minus(@NotNull final Map<? extends K, ? extends V> $this$minus, @NotNull final Sequence<? extends K> keys) {
        Intrinsics.checkParameterIsNotNull($this$minus, "$this$minus");
        Intrinsics.checkParameterIsNotNull(keys, "keys");
        final Map $this$apply;
        final Map $this$optimizeReadOnlyMap = $this$apply = toMutableMap((Map<?, ?>)$this$minus);
        final int n = 0;
        CollectionsKt__MutableCollectionsKt.removeAll((Collection<? super Object>)$this$apply.keySet(), (Sequence<?>)keys);
        return optimizeReadOnlyMap((Map<K, ? extends V>)$this$optimizeReadOnlyMap);
    }
    
    @SinceKotlin(version = "1.1")
    @InlineOnly
    private static final <K, V> void minusAssign(@NotNull final Map<K, V> $this$minusAssign, final K key) {
        final int $i$f$minusAssign = 0;
        Intrinsics.checkParameterIsNotNull($this$minusAssign, "$this$minusAssign");
        $this$minusAssign.remove(key);
    }
    
    @SinceKotlin(version = "1.1")
    @InlineOnly
    private static final <K, V> void minusAssign(@NotNull final Map<K, V> $this$minusAssign, final Iterable<? extends K> keys) {
        final int $i$f$minusAssign = 0;
        Intrinsics.checkParameterIsNotNull($this$minusAssign, "$this$minusAssign");
        CollectionsKt__MutableCollectionsKt.removeAll((Collection<? super Object>)$this$minusAssign.keySet(), (Iterable<?>)keys);
    }
    
    @SinceKotlin(version = "1.1")
    @InlineOnly
    private static final <K, V> void minusAssign(@NotNull final Map<K, V> $this$minusAssign, final K[] keys) {
        final int $i$f$minusAssign = 0;
        Intrinsics.checkParameterIsNotNull($this$minusAssign, "$this$minusAssign");
        CollectionsKt__MutableCollectionsKt.removeAll($this$minusAssign.keySet(), keys);
    }
    
    @SinceKotlin(version = "1.1")
    @InlineOnly
    private static final <K, V> void minusAssign(@NotNull final Map<K, V> $this$minusAssign, final Sequence<? extends K> keys) {
        final int $i$f$minusAssign = 0;
        Intrinsics.checkParameterIsNotNull($this$minusAssign, "$this$minusAssign");
        CollectionsKt__MutableCollectionsKt.removeAll((Collection<? super Object>)$this$minusAssign.keySet(), (Sequence<?>)keys);
    }
    
    @NotNull
    public static final <K, V> Map<K, V> optimizeReadOnlyMap(@NotNull final Map<K, ? extends V> $this$optimizeReadOnlyMap) {
        Intrinsics.checkParameterIsNotNull($this$optimizeReadOnlyMap, "$this$optimizeReadOnlyMap");
        Object o = null;
        switch ($this$optimizeReadOnlyMap.size()) {
            case 0: {
                o = emptyMap();
                break;
            }
            case 1: {
                o = MapsKt__MapsJVMKt.toSingletonMap((Map<?, ?>)$this$optimizeReadOnlyMap);
                break;
            }
            default: {
                o = $this$optimizeReadOnlyMap;
                break;
            }
        }
        return (Map<K, V>)o;
    }
    
    public MapsKt__MapsKt() {
    }
}
