// 
// Decompiled by Procyon v0.5.36
// 

package kotlin.sequences;

import kotlin.jvm.JvmName;
import kotlin.jvm.internal.DoubleCompanionObject;
import kotlin.jvm.internal.markers.KMappedMarker;
import kotlin.coroutines.Continuation;
import kotlin.collections.SlidingWindowKt;
import kotlin.Unit;
import kotlin.jvm.functions.Function3;
import kotlin.collections.IndexedValue;
import kotlin.collections.Grouping;
import java.util.LinkedHashSet;
import java.util.Set;
import java.util.ArrayList;
import java.util.List;
import java.util.HashSet;
import kotlin.SinceKotlin;
import java.util.LinkedHashMap;
import java.util.Map;
import kotlin.Pair;
import kotlin.comparisons.ComparisonsKt__ComparisonsKt$compareByDescending;
import java.util.Comparator;
import kotlin.comparisons.ComparisonsKt__ComparisonsKt$compareBy;
import kotlin.TypeCastException;
import java.util.Collection;
import kotlin.jvm.functions.Function2;
import kotlin.internal.PlatformImplementationsKt;
import kotlin.collections.CollectionsKt;
import java.util.NoSuchElementException;
import kotlin.internal.InlineOnly;
import org.jetbrains.annotations.Nullable;
import java.util.Iterator;
import kotlin.jvm.functions.Function1;
import kotlin.jvm.internal.Intrinsics;
import org.jetbrains.annotations.NotNull;
import kotlin.Metadata;

@Metadata(mv = { 1, 1, 15 }, bv = { 1, 0, 3 }, k = 5, xi = 1, d1 = { "\u0000\u0088\u0002\n\u0000\n\u0002\u0010\u000b\n\u0000\n\u0002\u0018\u0002\n\u0000\n\u0002\u0018\u0002\n\u0002\b\u0002\n\u0002\u0010\u001c\n\u0002\b\u0002\n\u0002\u0010$\n\u0002\b\u0003\n\u0002\u0018\u0002\n\u0002\b\u0005\n\u0002\u0010%\n\u0002\b\b\n\u0002\u0010\u0006\n\u0002\u0010\u0005\n\u0002\b\u0002\n\u0002\u0010\u0007\n\u0000\n\u0002\u0010\b\n\u0000\n\u0002\u0010\t\n\u0000\n\u0002\u0010\n\n\u0002\b\u0002\n\u0002\u0010 \n\u0002\b\u0003\n\u0002\u0018\u0002\n\u0002\b\u0012\n\u0002\u0018\u0002\n\u0002\u0018\u0002\n\u0002\b\u0003\n\u0002\u0010\u001f\n\u0002\b\u0002\n\u0002\u0018\u0002\n\u0002\b\u0004\n\u0002\u0010\u0000\n\u0002\b\u0012\n\u0002\u0018\u0002\n\u0002\b\u0002\n\u0002\u0010\u0002\n\u0002\b\u0004\n\u0002\u0010!\n\u0000\n\u0002\u0018\u0002\n\u0002\b\u0006\n\u0002\u0018\u0002\n\u0002\u0018\u0002\n\u0002\b\u0002\n\u0002\u0010\r\n\u0002\b\u0006\n\u0002\u0010\u000e\n\u0002\b\f\n\u0002\u0010\u000f\n\u0002\b\u0006\n\u0002\u0018\u0002\n\u0002\u0018\u0002\n\u0002\b\u0007\n\u0002\u0010\u0011\n\u0002\b!\n\u0002\u0018\u0002\n\u0002\u0018\u0002\n\u0002\b\u0003\n\u0002\u0010#\n\u0000\n\u0002\u0010\"\n\u0002\b\u0004\n\u0002\u0018\u0002\n\u0002\b\u0006\u001a-\u0010\u0000\u001a\u00020\u0001\"\u0004\b\u0000\u0010\u0002*\b\u0012\u0004\u0012\u0002H\u00020\u00032\u0012\u0010\u0004\u001a\u000e\u0012\u0004\u0012\u0002H\u0002\u0012\u0004\u0012\u00020\u00010\u0005H\u0086\b\u001a\u0016\u0010\u0006\u001a\u00020\u0001\"\u0004\b\u0000\u0010\u0002*\b\u0012\u0004\u0012\u0002H\u00020\u0003\u001a-\u0010\u0006\u001a\u00020\u0001\"\u0004\b\u0000\u0010\u0002*\b\u0012\u0004\u0012\u0002H\u00020\u00032\u0012\u0010\u0004\u001a\u000e\u0012\u0004\u0012\u0002H\u0002\u0012\u0004\u0012\u00020\u00010\u0005H\u0086\b\u001a\u001c\u0010\u0007\u001a\b\u0012\u0004\u0012\u0002H\u00020\b\"\u0004\b\u0000\u0010\u0002*\b\u0012\u0004\u0012\u0002H\u00020\u0003\u001a\u001f\u0010\t\u001a\b\u0012\u0004\u0012\u0002H\u00020\u0003\"\u0004\b\u0000\u0010\u0002*\b\u0012\u0004\u0012\u0002H\u00020\u0003H\u0087\b\u001aQ\u0010\n\u001a\u000e\u0012\u0004\u0012\u0002H\f\u0012\u0004\u0012\u0002H\r0\u000b\"\u0004\b\u0000\u0010\u0002\"\u0004\b\u0001\u0010\f\"\u0004\b\u0002\u0010\r*\b\u0012\u0004\u0012\u0002H\u00020\u00032\u001e\u0010\u000e\u001a\u001a\u0012\u0004\u0012\u0002H\u0002\u0012\u0010\u0012\u000e\u0012\u0004\u0012\u0002H\f\u0012\u0004\u0012\u0002H\r0\u000f0\u0005H\u0086\b\u001a?\u0010\u0010\u001a\u000e\u0012\u0004\u0012\u0002H\f\u0012\u0004\u0012\u0002H\u00020\u000b\"\u0004\b\u0000\u0010\u0002\"\u0004\b\u0001\u0010\f*\b\u0012\u0004\u0012\u0002H\u00020\u00032\u0012\u0010\u0011\u001a\u000e\u0012\u0004\u0012\u0002H\u0002\u0012\u0004\u0012\u0002H\f0\u0005H\u0086\b\u001aY\u0010\u0010\u001a\u000e\u0012\u0004\u0012\u0002H\f\u0012\u0004\u0012\u0002H\r0\u000b\"\u0004\b\u0000\u0010\u0002\"\u0004\b\u0001\u0010\f\"\u0004\b\u0002\u0010\r*\b\u0012\u0004\u0012\u0002H\u00020\u00032\u0012\u0010\u0011\u001a\u000e\u0012\u0004\u0012\u0002H\u0002\u0012\u0004\u0012\u0002H\f0\u00052\u0012\u0010\u0012\u001a\u000e\u0012\u0004\u0012\u0002H\u0002\u0012\u0004\u0012\u0002H\r0\u0005H\u0086\b\u001aZ\u0010\u0013\u001a\u0002H\u0014\"\u0004\b\u0000\u0010\u0002\"\u0004\b\u0001\u0010\f\"\u0018\b\u0002\u0010\u0014*\u0012\u0012\u0006\b\u0000\u0012\u0002H\f\u0012\u0006\b\u0000\u0012\u0002H\u00020\u0015*\b\u0012\u0004\u0012\u0002H\u00020\u00032\u0006\u0010\u0016\u001a\u0002H\u00142\u0012\u0010\u0011\u001a\u000e\u0012\u0004\u0012\u0002H\u0002\u0012\u0004\u0012\u0002H\f0\u0005H\u0086\b¢\u0006\u0002\u0010\u0017\u001at\u0010\u0013\u001a\u0002H\u0014\"\u0004\b\u0000\u0010\u0002\"\u0004\b\u0001\u0010\f\"\u0004\b\u0002\u0010\r\"\u0018\b\u0003\u0010\u0014*\u0012\u0012\u0006\b\u0000\u0012\u0002H\f\u0012\u0006\b\u0000\u0012\u0002H\r0\u0015*\b\u0012\u0004\u0012\u0002H\u00020\u00032\u0006\u0010\u0016\u001a\u0002H\u00142\u0012\u0010\u0011\u001a\u000e\u0012\u0004\u0012\u0002H\u0002\u0012\u0004\u0012\u0002H\f0\u00052\u0012\u0010\u0012\u001a\u000e\u0012\u0004\u0012\u0002H\u0002\u0012\u0004\u0012\u0002H\r0\u0005H\u0086\b¢\u0006\u0002\u0010\u0018\u001al\u0010\u0019\u001a\u0002H\u0014\"\u0004\b\u0000\u0010\u0002\"\u0004\b\u0001\u0010\f\"\u0004\b\u0002\u0010\r\"\u0018\b\u0003\u0010\u0014*\u0012\u0012\u0006\b\u0000\u0012\u0002H\f\u0012\u0006\b\u0000\u0012\u0002H\r0\u0015*\b\u0012\u0004\u0012\u0002H\u00020\u00032\u0006\u0010\u0016\u001a\u0002H\u00142\u001e\u0010\u000e\u001a\u001a\u0012\u0004\u0012\u0002H\u0002\u0012\u0010\u0012\u000e\u0012\u0004\u0012\u0002H\f\u0012\u0004\u0012\u0002H\r0\u000f0\u0005H\u0086\b¢\u0006\u0002\u0010\u0017\u001a?\u0010\u001a\u001a\u000e\u0012\u0004\u0012\u0002H\f\u0012\u0004\u0012\u0002H\r0\u000b\"\u0004\b\u0000\u0010\f\"\u0004\b\u0001\u0010\r*\b\u0012\u0004\u0012\u0002H\f0\u00032\u0012\u0010\u001b\u001a\u000e\u0012\u0004\u0012\u0002H\f\u0012\u0004\u0012\u0002H\r0\u0005H\u0087\b\u001aZ\u0010\u001c\u001a\u0002H\u0014\"\u0004\b\u0000\u0010\f\"\u0004\b\u0001\u0010\r\"\u0018\b\u0002\u0010\u0014*\u0012\u0012\u0006\b\u0000\u0012\u0002H\f\u0012\u0006\b\u0000\u0012\u0002H\r0\u0015*\b\u0012\u0004\u0012\u0002H\f0\u00032\u0006\u0010\u0016\u001a\u0002H\u00142\u0012\u0010\u001b\u001a\u000e\u0012\u0004\u0012\u0002H\f\u0012\u0004\u0012\u0002H\r0\u0005H\u0087\b¢\u0006\u0002\u0010\u0017\u001a\u0017\u0010\u001d\u001a\u00020\u001e*\b\u0012\u0004\u0012\u00020\u001f0\u0003H\u0007¢\u0006\u0002\b \u001a\u0017\u0010\u001d\u001a\u00020\u001e*\b\u0012\u0004\u0012\u00020\u001e0\u0003H\u0007¢\u0006\u0002\b!\u001a\u0017\u0010\u001d\u001a\u00020\u001e*\b\u0012\u0004\u0012\u00020\"0\u0003H\u0007¢\u0006\u0002\b#\u001a\u0017\u0010\u001d\u001a\u00020\u001e*\b\u0012\u0004\u0012\u00020$0\u0003H\u0007¢\u0006\u0002\b%\u001a\u0017\u0010\u001d\u001a\u00020\u001e*\b\u0012\u0004\u0012\u00020&0\u0003H\u0007¢\u0006\u0002\b'\u001a\u0017\u0010\u001d\u001a\u00020\u001e*\b\u0012\u0004\u0012\u00020(0\u0003H\u0007¢\u0006\u0002\b)\u001a,\u0010*\u001a\u000e\u0012\n\u0012\b\u0012\u0004\u0012\u0002H\u00020+0\u0003\"\u0004\b\u0000\u0010\u0002*\b\u0012\u0004\u0012\u0002H\u00020\u00032\u0006\u0010,\u001a\u00020$H\u0007\u001aF\u0010*\u001a\b\u0012\u0004\u0012\u0002H-0\u0003\"\u0004\b\u0000\u0010\u0002\"\u0004\b\u0001\u0010-*\b\u0012\u0004\u0012\u0002H\u00020\u00032\u0006\u0010,\u001a\u00020$2\u0018\u0010\u000e\u001a\u0014\u0012\n\u0012\b\u0012\u0004\u0012\u0002H\u00020+\u0012\u0004\u0012\u0002H-0\u0005H\u0007\u001a+\u0010.\u001a\u00020\u0001\"\t\b\u0000\u0010\u0002¢\u0006\u0002\b/*\b\u0012\u0004\u0012\u0002H\u00020\u00032\u0006\u00100\u001a\u0002H\u0002H\u0086\u0002¢\u0006\u0002\u00101\u001a\u0016\u00102\u001a\u00020$\"\u0004\b\u0000\u0010\u0002*\b\u0012\u0004\u0012\u0002H\u00020\u0003\u001a-\u00102\u001a\u00020$\"\u0004\b\u0000\u0010\u0002*\b\u0012\u0004\u0012\u0002H\u00020\u00032\u0012\u0010\u0004\u001a\u000e\u0012\u0004\u0012\u0002H\u0002\u0012\u0004\u0012\u00020\u00010\u0005H\u0086\b\u001a\u001c\u00103\u001a\b\u0012\u0004\u0012\u0002H\u00020\u0003\"\u0004\b\u0000\u0010\u0002*\b\u0012\u0004\u0012\u0002H\u00020\u0003\u001a6\u00104\u001a\b\u0012\u0004\u0012\u0002H\u00020\u0003\"\u0004\b\u0000\u0010\u0002\"\u0004\b\u0001\u0010\f*\b\u0012\u0004\u0012\u0002H\u00020\u00032\u0012\u00105\u001a\u000e\u0012\u0004\u0012\u0002H\u0002\u0012\u0004\u0012\u0002H\f0\u0005\u001a$\u00106\u001a\b\u0012\u0004\u0012\u0002H\u00020\u0003\"\u0004\b\u0000\u0010\u0002*\b\u0012\u0004\u0012\u0002H\u00020\u00032\u0006\u00107\u001a\u00020$\u001a0\u00108\u001a\b\u0012\u0004\u0012\u0002H\u00020\u0003\"\u0004\b\u0000\u0010\u0002*\b\u0012\u0004\u0012\u0002H\u00020\u00032\u0012\u0010\u0004\u001a\u000e\u0012\u0004\u0012\u0002H\u0002\u0012\u0004\u0012\u00020\u00010\u0005\u001a#\u00109\u001a\u0002H\u0002\"\u0004\b\u0000\u0010\u0002*\b\u0012\u0004\u0012\u0002H\u00020\u00032\u0006\u0010:\u001a\u00020$¢\u0006\u0002\u0010;\u001a7\u0010<\u001a\u0002H\u0002\"\u0004\b\u0000\u0010\u0002*\b\u0012\u0004\u0012\u0002H\u00020\u00032\u0006\u0010:\u001a\u00020$2\u0012\u0010=\u001a\u000e\u0012\u0004\u0012\u00020$\u0012\u0004\u0012\u0002H\u00020\u0005¢\u0006\u0002\u0010>\u001a%\u0010?\u001a\u0004\u0018\u0001H\u0002\"\u0004\b\u0000\u0010\u0002*\b\u0012\u0004\u0012\u0002H\u00020\u00032\u0006\u0010:\u001a\u00020$¢\u0006\u0002\u0010;\u001a0\u0010@\u001a\b\u0012\u0004\u0012\u0002H\u00020\u0003\"\u0004\b\u0000\u0010\u0002*\b\u0012\u0004\u0012\u0002H\u00020\u00032\u0012\u0010\u0004\u001a\u000e\u0012\u0004\u0012\u0002H\u0002\u0012\u0004\u0012\u00020\u00010\u0005\u001aE\u0010A\u001a\b\u0012\u0004\u0012\u0002H\u00020\u0003\"\u0004\b\u0000\u0010\u0002*\b\u0012\u0004\u0012\u0002H\u00020\u00032'\u0010\u0004\u001a#\u0012\u0013\u0012\u00110$¢\u0006\f\bC\u0012\b\bD\u0012\u0004\b\b(:\u0012\u0004\u0012\u0002H\u0002\u0012\u0004\u0012\u00020\u00010B\u001aa\u0010E\u001a\u0002HF\"\u0004\b\u0000\u0010\u0002\"\u0010\b\u0001\u0010F*\n\u0012\u0006\b\u0000\u0012\u0002H\u00020G*\b\u0012\u0004\u0012\u0002H\u00020\u00032\u0006\u0010\u0016\u001a\u0002HF2'\u0010\u0004\u001a#\u0012\u0013\u0012\u00110$¢\u0006\f\bC\u0012\b\bD\u0012\u0004\b\b(:\u0012\u0004\u0012\u0002H\u0002\u0012\u0004\u0012\u00020\u00010BH\u0086\b¢\u0006\u0002\u0010H\u001a$\u0010I\u001a\r\u0012\t\u0012\u0007H-¢\u0006\u0002\bJ0\u0003\"\u0006\b\u0000\u0010-\u0018\u0001*\u0006\u0012\u0002\b\u00030\u0003H\u0086\b\u001a8\u0010K\u001a\u0002HF\"\u0006\b\u0000\u0010-\u0018\u0001\"\u0010\b\u0001\u0010F*\n\u0012\u0006\b\u0000\u0012\u0002H-0G*\u0006\u0012\u0002\b\u00030\u00032\u0006\u0010\u0016\u001a\u0002HFH\u0086\b¢\u0006\u0002\u0010L\u001a0\u0010M\u001a\b\u0012\u0004\u0012\u0002H\u00020\u0003\"\u0004\b\u0000\u0010\u0002*\b\u0012\u0004\u0012\u0002H\u00020\u00032\u0012\u0010\u0004\u001a\u000e\u0012\u0004\u0012\u0002H\u0002\u0012\u0004\u0012\u00020\u00010\u0005\u001a\"\u0010N\u001a\b\u0012\u0004\u0012\u0002H\u00020\u0003\"\b\b\u0000\u0010\u0002*\u00020O*\n\u0012\u0006\u0012\u0004\u0018\u0001H\u00020\u0003\u001a;\u0010P\u001a\u0002HF\"\u0010\b\u0000\u0010F*\n\u0012\u0006\b\u0000\u0012\u0002H\u00020G\"\b\b\u0001\u0010\u0002*\u00020O*\n\u0012\u0006\u0012\u0004\u0018\u0001H\u00020\u00032\u0006\u0010\u0016\u001a\u0002HF¢\u0006\u0002\u0010L\u001aL\u0010Q\u001a\u0002HF\"\u0004\b\u0000\u0010\u0002\"\u0010\b\u0001\u0010F*\n\u0012\u0006\b\u0000\u0012\u0002H\u00020G*\b\u0012\u0004\u0012\u0002H\u00020\u00032\u0006\u0010\u0016\u001a\u0002HF2\u0012\u0010\u0004\u001a\u000e\u0012\u0004\u0012\u0002H\u0002\u0012\u0004\u0012\u00020\u00010\u0005H\u0086\b¢\u0006\u0002\u0010R\u001aL\u0010S\u001a\u0002HF\"\u0004\b\u0000\u0010\u0002\"\u0010\b\u0001\u0010F*\n\u0012\u0006\b\u0000\u0012\u0002H\u00020G*\b\u0012\u0004\u0012\u0002H\u00020\u00032\u0006\u0010\u0016\u001a\u0002HF2\u0012\u0010\u0004\u001a\u000e\u0012\u0004\u0012\u0002H\u0002\u0012\u0004\u0012\u00020\u00010\u0005H\u0086\b¢\u0006\u0002\u0010R\u001a4\u0010T\u001a\u0004\u0018\u0001H\u0002\"\u0004\b\u0000\u0010\u0002*\b\u0012\u0004\u0012\u0002H\u00020\u00032\u0012\u0010\u0004\u001a\u000e\u0012\u0004\u0012\u0002H\u0002\u0012\u0004\u0012\u00020\u00010\u0005H\u0087\b¢\u0006\u0002\u0010U\u001a4\u0010V\u001a\u0004\u0018\u0001H\u0002\"\u0004\b\u0000\u0010\u0002*\b\u0012\u0004\u0012\u0002H\u00020\u00032\u0012\u0010\u0004\u001a\u000e\u0012\u0004\u0012\u0002H\u0002\u0012\u0004\u0012\u00020\u00010\u0005H\u0087\b¢\u0006\u0002\u0010U\u001a\u001b\u0010W\u001a\u0002H\u0002\"\u0004\b\u0000\u0010\u0002*\b\u0012\u0004\u0012\u0002H\u00020\u0003¢\u0006\u0002\u0010X\u001a2\u0010W\u001a\u0002H\u0002\"\u0004\b\u0000\u0010\u0002*\b\u0012\u0004\u0012\u0002H\u00020\u00032\u0012\u0010\u0004\u001a\u000e\u0012\u0004\u0012\u0002H\u0002\u0012\u0004\u0012\u00020\u00010\u0005H\u0086\b¢\u0006\u0002\u0010U\u001a\u001d\u0010Y\u001a\u0004\u0018\u0001H\u0002\"\u0004\b\u0000\u0010\u0002*\b\u0012\u0004\u0012\u0002H\u00020\u0003¢\u0006\u0002\u0010X\u001a4\u0010Y\u001a\u0004\u0018\u0001H\u0002\"\u0004\b\u0000\u0010\u0002*\b\u0012\u0004\u0012\u0002H\u00020\u00032\u0012\u0010\u0004\u001a\u000e\u0012\u0004\u0012\u0002H\u0002\u0012\u0004\u0012\u00020\u00010\u0005H\u0086\b¢\u0006\u0002\u0010U\u001a<\u0010Z\u001a\b\u0012\u0004\u0012\u0002H-0\u0003\"\u0004\b\u0000\u0010\u0002\"\u0004\b\u0001\u0010-*\b\u0012\u0004\u0012\u0002H\u00020\u00032\u0018\u0010\u000e\u001a\u0014\u0012\u0004\u0012\u0002H\u0002\u0012\n\u0012\b\u0012\u0004\u0012\u0002H-0\u00030\u0005\u001aX\u0010[\u001a\u0002HF\"\u0004\b\u0000\u0010\u0002\"\u0004\b\u0001\u0010-\"\u0010\b\u0002\u0010F*\n\u0012\u0006\b\u0000\u0012\u0002H-0G*\b\u0012\u0004\u0012\u0002H\u00020\u00032\u0006\u0010\u0016\u001a\u0002HF2\u0018\u0010\u000e\u001a\u0014\u0012\u0004\u0012\u0002H\u0002\u0012\n\u0012\b\u0012\u0004\u0012\u0002H-0\u00030\u0005H\u0086\b¢\u0006\u0002\u0010R\u001aU\u0010\\\u001a\u0002H-\"\u0004\b\u0000\u0010\u0002\"\u0004\b\u0001\u0010-*\b\u0012\u0004\u0012\u0002H\u00020\u00032\u0006\u0010]\u001a\u0002H-2'\u0010^\u001a#\u0012\u0013\u0012\u0011H-¢\u0006\f\bC\u0012\b\bD\u0012\u0004\b\b(_\u0012\u0004\u0012\u0002H\u0002\u0012\u0004\u0012\u0002H-0BH\u0086\b¢\u0006\u0002\u0010`\u001aj\u0010a\u001a\u0002H-\"\u0004\b\u0000\u0010\u0002\"\u0004\b\u0001\u0010-*\b\u0012\u0004\u0012\u0002H\u00020\u00032\u0006\u0010]\u001a\u0002H-2<\u0010^\u001a8\u0012\u0013\u0012\u00110$¢\u0006\f\bC\u0012\b\bD\u0012\u0004\b\b(:\u0012\u0013\u0012\u0011H-¢\u0006\f\bC\u0012\b\bD\u0012\u0004\b\b(_\u0012\u0004\u0012\u0002H\u0002\u0012\u0004\u0012\u0002H-0bH\u0086\b¢\u0006\u0002\u0010c\u001a-\u0010d\u001a\u00020e\"\u0004\b\u0000\u0010\u0002*\b\u0012\u0004\u0012\u0002H\u00020\u00032\u0012\u0010f\u001a\u000e\u0012\u0004\u0012\u0002H\u0002\u0012\u0004\u0012\u00020e0\u0005H\u0086\b\u001aB\u0010g\u001a\u00020e\"\u0004\b\u0000\u0010\u0002*\b\u0012\u0004\u0012\u0002H\u00020\u00032'\u0010f\u001a#\u0012\u0013\u0012\u00110$¢\u0006\f\bC\u0012\b\bD\u0012\u0004\b\b(:\u0012\u0004\u0012\u0002H\u0002\u0012\u0004\u0012\u00020e0BH\u0086\b\u001aE\u0010h\u001a\u0014\u0012\u0004\u0012\u0002H\f\u0012\n\u0012\b\u0012\u0004\u0012\u0002H\u00020+0\u000b\"\u0004\b\u0000\u0010\u0002\"\u0004\b\u0001\u0010\f*\b\u0012\u0004\u0012\u0002H\u00020\u00032\u0012\u0010\u0011\u001a\u000e\u0012\u0004\u0012\u0002H\u0002\u0012\u0004\u0012\u0002H\f0\u0005H\u0086\b\u001a_\u0010h\u001a\u0014\u0012\u0004\u0012\u0002H\f\u0012\n\u0012\b\u0012\u0004\u0012\u0002H\r0+0\u000b\"\u0004\b\u0000\u0010\u0002\"\u0004\b\u0001\u0010\f\"\u0004\b\u0002\u0010\r*\b\u0012\u0004\u0012\u0002H\u00020\u00032\u0012\u0010\u0011\u001a\u000e\u0012\u0004\u0012\u0002H\u0002\u0012\u0004\u0012\u0002H\f0\u00052\u0012\u0010\u0012\u001a\u000e\u0012\u0004\u0012\u0002H\u0002\u0012\u0004\u0012\u0002H\r0\u0005H\u0086\b\u001a^\u0010i\u001a\u0002H\u0014\"\u0004\b\u0000\u0010\u0002\"\u0004\b\u0001\u0010\f\"\u001c\b\u0002\u0010\u0014*\u0016\u0012\u0006\b\u0000\u0012\u0002H\f\u0012\n\u0012\b\u0012\u0004\u0012\u0002H\u00020j0\u0015*\b\u0012\u0004\u0012\u0002H\u00020\u00032\u0006\u0010\u0016\u001a\u0002H\u00142\u0012\u0010\u0011\u001a\u000e\u0012\u0004\u0012\u0002H\u0002\u0012\u0004\u0012\u0002H\f0\u0005H\u0086\b¢\u0006\u0002\u0010\u0017\u001ax\u0010i\u001a\u0002H\u0014\"\u0004\b\u0000\u0010\u0002\"\u0004\b\u0001\u0010\f\"\u0004\b\u0002\u0010\r\"\u001c\b\u0003\u0010\u0014*\u0016\u0012\u0006\b\u0000\u0012\u0002H\f\u0012\n\u0012\b\u0012\u0004\u0012\u0002H\r0j0\u0015*\b\u0012\u0004\u0012\u0002H\u00020\u00032\u0006\u0010\u0016\u001a\u0002H\u00142\u0012\u0010\u0011\u001a\u000e\u0012\u0004\u0012\u0002H\u0002\u0012\u0004\u0012\u0002H\f0\u00052\u0012\u0010\u0012\u001a\u000e\u0012\u0004\u0012\u0002H\u0002\u0012\u0004\u0012\u0002H\r0\u0005H\u0086\b¢\u0006\u0002\u0010\u0018\u001aA\u0010k\u001a\u000e\u0012\u0004\u0012\u0002H\u0002\u0012\u0004\u0012\u0002H\f0l\"\u0004\b\u0000\u0010\u0002\"\u0004\b\u0001\u0010\f*\b\u0012\u0004\u0012\u0002H\u00020\u00032\u0014\b\u0004\u0010\u0011\u001a\u000e\u0012\u0004\u0012\u0002H\u0002\u0012\u0004\u0012\u0002H\f0\u0005H\u0087\b\u001a(\u0010m\u001a\u00020$\"\t\b\u0000\u0010\u0002¢\u0006\u0002\b/*\b\u0012\u0004\u0012\u0002H\u00020\u00032\u0006\u00100\u001a\u0002H\u0002¢\u0006\u0002\u0010n\u001a-\u0010o\u001a\u00020$\"\u0004\b\u0000\u0010\u0002*\b\u0012\u0004\u0012\u0002H\u00020\u00032\u0012\u0010\u0004\u001a\u000e\u0012\u0004\u0012\u0002H\u0002\u0012\u0004\u0012\u00020\u00010\u0005H\u0086\b\u001a-\u0010p\u001a\u00020$\"\u0004\b\u0000\u0010\u0002*\b\u0012\u0004\u0012\u0002H\u00020\u00032\u0012\u0010\u0004\u001a\u000e\u0012\u0004\u0012\u0002H\u0002\u0012\u0004\u0012\u00020\u00010\u0005H\u0086\b\u001a{\u0010q\u001a\u0002Hr\"\u0004\b\u0000\u0010\u0002\"\f\b\u0001\u0010r*\u00060sj\u0002`t*\b\u0012\u0004\u0012\u0002H\u00020\u00032\u0006\u0010u\u001a\u0002Hr2\b\b\u0002\u0010v\u001a\u00020w2\b\b\u0002\u0010x\u001a\u00020w2\b\b\u0002\u0010y\u001a\u00020w2\b\b\u0002\u0010z\u001a\u00020$2\b\b\u0002\u0010{\u001a\u00020w2\u0016\b\u0002\u0010\u000e\u001a\u0010\u0012\u0004\u0012\u0002H\u0002\u0012\u0004\u0012\u00020w\u0018\u00010\u0005¢\u0006\u0002\u0010|\u001a`\u0010}\u001a\u00020~\"\u0004\b\u0000\u0010\u0002*\b\u0012\u0004\u0012\u0002H\u00020\u00032\b\b\u0002\u0010v\u001a\u00020w2\b\b\u0002\u0010x\u001a\u00020w2\b\b\u0002\u0010y\u001a\u00020w2\b\b\u0002\u0010z\u001a\u00020$2\b\b\u0002\u0010{\u001a\u00020w2\u0016\b\u0002\u0010\u000e\u001a\u0010\u0012\u0004\u0012\u0002H\u0002\u0012\u0004\u0012\u00020w\u0018\u00010\u0005\u001a\u001b\u0010\u007f\u001a\u0002H\u0002\"\u0004\b\u0000\u0010\u0002*\b\u0012\u0004\u0012\u0002H\u00020\u0003¢\u0006\u0002\u0010X\u001a2\u0010\u007f\u001a\u0002H\u0002\"\u0004\b\u0000\u0010\u0002*\b\u0012\u0004\u0012\u0002H\u00020\u00032\u0012\u0010\u0004\u001a\u000e\u0012\u0004\u0012\u0002H\u0002\u0012\u0004\u0012\u00020\u00010\u0005H\u0086\b¢\u0006\u0002\u0010U\u001a)\u0010\u0080\u0001\u001a\u00020$\"\t\b\u0000\u0010\u0002¢\u0006\u0002\b/*\b\u0012\u0004\u0012\u0002H\u00020\u00032\u0006\u00100\u001a\u0002H\u0002¢\u0006\u0002\u0010n\u001a\u001e\u0010\u0081\u0001\u001a\u0004\u0018\u0001H\u0002\"\u0004\b\u0000\u0010\u0002*\b\u0012\u0004\u0012\u0002H\u00020\u0003¢\u0006\u0002\u0010X\u001a5\u0010\u0081\u0001\u001a\u0004\u0018\u0001H\u0002\"\u0004\b\u0000\u0010\u0002*\b\u0012\u0004\u0012\u0002H\u00020\u00032\u0012\u0010\u0004\u001a\u000e\u0012\u0004\u0012\u0002H\u0002\u0012\u0004\u0012\u00020\u00010\u0005H\u0086\b¢\u0006\u0002\u0010U\u001a7\u0010\u0082\u0001\u001a\b\u0012\u0004\u0012\u0002H-0\u0003\"\u0004\b\u0000\u0010\u0002\"\u0004\b\u0001\u0010-*\b\u0012\u0004\u0012\u0002H\u00020\u00032\u0012\u0010\u000e\u001a\u000e\u0012\u0004\u0012\u0002H\u0002\u0012\u0004\u0012\u0002H-0\u0005\u001aL\u0010\u0083\u0001\u001a\b\u0012\u0004\u0012\u0002H-0\u0003\"\u0004\b\u0000\u0010\u0002\"\u0004\b\u0001\u0010-*\b\u0012\u0004\u0012\u0002H\u00020\u00032'\u0010\u000e\u001a#\u0012\u0013\u0012\u00110$¢\u0006\f\bC\u0012\b\bD\u0012\u0004\b\b(:\u0012\u0004\u0012\u0002H\u0002\u0012\u0004\u0012\u0002H-0B\u001aR\u0010\u0084\u0001\u001a\b\u0012\u0004\u0012\u0002H-0\u0003\"\u0004\b\u0000\u0010\u0002\"\b\b\u0001\u0010-*\u00020O*\b\u0012\u0004\u0012\u0002H\u00020\u00032)\u0010\u000e\u001a%\u0012\u0013\u0012\u00110$¢\u0006\f\bC\u0012\b\bD\u0012\u0004\b\b(:\u0012\u0004\u0012\u0002H\u0002\u0012\u0006\u0012\u0004\u0018\u0001H-0B\u001an\u0010\u0085\u0001\u001a\u0002HF\"\u0004\b\u0000\u0010\u0002\"\b\b\u0001\u0010-*\u00020O\"\u0010\b\u0002\u0010F*\n\u0012\u0006\b\u0000\u0012\u0002H-0G*\b\u0012\u0004\u0012\u0002H\u00020\u00032\u0006\u0010\u0016\u001a\u0002HF2)\u0010\u000e\u001a%\u0012\u0013\u0012\u00110$¢\u0006\f\bC\u0012\b\bD\u0012\u0004\b\b(:\u0012\u0004\u0012\u0002H\u0002\u0012\u0006\u0012\u0004\u0018\u0001H-0BH\u0086\b¢\u0006\u0002\u0010H\u001ah\u0010\u0086\u0001\u001a\u0002HF\"\u0004\b\u0000\u0010\u0002\"\u0004\b\u0001\u0010-\"\u0010\b\u0002\u0010F*\n\u0012\u0006\b\u0000\u0012\u0002H-0G*\b\u0012\u0004\u0012\u0002H\u00020\u00032\u0006\u0010\u0016\u001a\u0002HF2'\u0010\u000e\u001a#\u0012\u0013\u0012\u00110$¢\u0006\f\bC\u0012\b\bD\u0012\u0004\b\b(:\u0012\u0004\u0012\u0002H\u0002\u0012\u0004\u0012\u0002H-0BH\u0086\b¢\u0006\u0002\u0010H\u001a=\u0010\u0087\u0001\u001a\b\u0012\u0004\u0012\u0002H-0\u0003\"\u0004\b\u0000\u0010\u0002\"\b\b\u0001\u0010-*\u00020O*\b\u0012\u0004\u0012\u0002H\u00020\u00032\u0014\u0010\u000e\u001a\u0010\u0012\u0004\u0012\u0002H\u0002\u0012\u0006\u0012\u0004\u0018\u0001H-0\u0005\u001aY\u0010\u0088\u0001\u001a\u0002HF\"\u0004\b\u0000\u0010\u0002\"\b\b\u0001\u0010-*\u00020O\"\u0010\b\u0002\u0010F*\n\u0012\u0006\b\u0000\u0012\u0002H-0G*\b\u0012\u0004\u0012\u0002H\u00020\u00032\u0006\u0010\u0016\u001a\u0002HF2\u0014\u0010\u000e\u001a\u0010\u0012\u0004\u0012\u0002H\u0002\u0012\u0006\u0012\u0004\u0018\u0001H-0\u0005H\u0086\b¢\u0006\u0002\u0010R\u001aS\u0010\u0089\u0001\u001a\u0002HF\"\u0004\b\u0000\u0010\u0002\"\u0004\b\u0001\u0010-\"\u0010\b\u0002\u0010F*\n\u0012\u0006\b\u0000\u0012\u0002H-0G*\b\u0012\u0004\u0012\u0002H\u00020\u00032\u0006\u0010\u0016\u001a\u0002HF2\u0012\u0010\u000e\u001a\u000e\u0012\u0004\u0012\u0002H\u0002\u0012\u0004\u0012\u0002H-0\u0005H\u0086\b¢\u0006\u0002\u0010R\u001a*\u0010\u008a\u0001\u001a\u0004\u0018\u0001H\u0002\"\u000f\b\u0000\u0010\u0002*\t\u0012\u0004\u0012\u0002H\u00020\u008b\u0001*\b\u0012\u0004\u0012\u0002H\u00020\u0003¢\u0006\u0003\u0010\u008c\u0001\u001a\u001b\u0010\u008a\u0001\u001a\u0004\u0018\u00010\u001e*\b\u0012\u0004\u0012\u00020\u001e0\u0003H\u0007¢\u0006\u0003\u0010\u008d\u0001\u001a\u001b\u0010\u008a\u0001\u001a\u0004\u0018\u00010\"*\b\u0012\u0004\u0012\u00020\"0\u0003H\u0007¢\u0006\u0003\u0010\u008e\u0001\u001aF\u0010\u008f\u0001\u001a\u0004\u0018\u0001H\u0002\"\u0004\b\u0000\u0010\u0002\"\u000f\b\u0001\u0010-*\t\u0012\u0004\u0012\u0002H-0\u008b\u0001*\b\u0012\u0004\u0012\u0002H\u00020\u00032\u0012\u00105\u001a\u000e\u0012\u0004\u0012\u0002H\u0002\u0012\u0004\u0012\u0002H-0\u0005H\u0086\b¢\u0006\u0002\u0010U\u001a>\u0010\u0090\u0001\u001a\u0004\u0018\u0001H\u0002\"\u0004\b\u0000\u0010\u0002*\b\u0012\u0004\u0012\u0002H\u00020\u00032\u001d\u0010\u0091\u0001\u001a\u0018\u0012\u0006\b\u0000\u0012\u0002H\u00020\u0092\u0001j\u000b\u0012\u0006\b\u0000\u0012\u0002H\u0002`\u0093\u0001¢\u0006\u0003\u0010\u0094\u0001\u001a*\u0010\u0095\u0001\u001a\u0004\u0018\u0001H\u0002\"\u000f\b\u0000\u0010\u0002*\t\u0012\u0004\u0012\u0002H\u00020\u008b\u0001*\b\u0012\u0004\u0012\u0002H\u00020\u0003¢\u0006\u0003\u0010\u008c\u0001\u001a\u001b\u0010\u0095\u0001\u001a\u0004\u0018\u00010\u001e*\b\u0012\u0004\u0012\u00020\u001e0\u0003H\u0007¢\u0006\u0003\u0010\u008d\u0001\u001a\u001b\u0010\u0095\u0001\u001a\u0004\u0018\u00010\"*\b\u0012\u0004\u0012\u00020\"0\u0003H\u0007¢\u0006\u0003\u0010\u008e\u0001\u001aF\u0010\u0096\u0001\u001a\u0004\u0018\u0001H\u0002\"\u0004\b\u0000\u0010\u0002\"\u000f\b\u0001\u0010-*\t\u0012\u0004\u0012\u0002H-0\u008b\u0001*\b\u0012\u0004\u0012\u0002H\u00020\u00032\u0012\u00105\u001a\u000e\u0012\u0004\u0012\u0002H\u0002\u0012\u0004\u0012\u0002H-0\u0005H\u0086\b¢\u0006\u0002\u0010U\u001a>\u0010\u0097\u0001\u001a\u0004\u0018\u0001H\u0002\"\u0004\b\u0000\u0010\u0002*\b\u0012\u0004\u0012\u0002H\u00020\u00032\u001d\u0010\u0091\u0001\u001a\u0018\u0012\u0006\b\u0000\u0012\u0002H\u00020\u0092\u0001j\u000b\u0012\u0006\b\u0000\u0012\u0002H\u0002`\u0093\u0001¢\u0006\u0003\u0010\u0094\u0001\u001a.\u0010\u0098\u0001\u001a\b\u0012\u0004\u0012\u0002H\u00020\u0003\"\u0004\b\u0000\u0010\u0002*\b\u0012\u0004\u0012\u0002H\u00020\u00032\u0006\u00100\u001a\u0002H\u0002H\u0086\u0002¢\u0006\u0003\u0010\u0099\u0001\u001a8\u0010\u0098\u0001\u001a\b\u0012\u0004\u0012\u0002H\u00020\u0003\"\u0004\b\u0000\u0010\u0002*\b\u0012\u0004\u0012\u0002H\u00020\u00032\u0010\u0010\u009a\u0001\u001a\u000b\u0012\u0006\b\u0001\u0012\u0002H\u00020\u009b\u0001H\u0086\u0002¢\u0006\u0003\u0010\u009c\u0001\u001a/\u0010\u0098\u0001\u001a\b\u0012\u0004\u0012\u0002H\u00020\u0003\"\u0004\b\u0000\u0010\u0002*\b\u0012\u0004\u0012\u0002H\u00020\u00032\r\u0010\u009a\u0001\u001a\b\u0012\u0004\u0012\u0002H\u00020\bH\u0086\u0002\u001a/\u0010\u0098\u0001\u001a\b\u0012\u0004\u0012\u0002H\u00020\u0003\"\u0004\b\u0000\u0010\u0002*\b\u0012\u0004\u0012\u0002H\u00020\u00032\r\u0010\u009a\u0001\u001a\b\u0012\u0004\u0012\u0002H\u00020\u0003H\u0086\u0002\u001a.\u0010\u009d\u0001\u001a\b\u0012\u0004\u0012\u0002H\u00020\u0003\"\u0004\b\u0000\u0010\u0002*\b\u0012\u0004\u0012\u0002H\u00020\u00032\u0006\u00100\u001a\u0002H\u0002H\u0087\b¢\u0006\u0003\u0010\u0099\u0001\u001a\u0017\u0010\u009e\u0001\u001a\u00020\u0001\"\u0004\b\u0000\u0010\u0002*\b\u0012\u0004\u0012\u0002H\u00020\u0003\u001a.\u0010\u009e\u0001\u001a\u00020\u0001\"\u0004\b\u0000\u0010\u0002*\b\u0012\u0004\u0012\u0002H\u00020\u00032\u0012\u0010\u0004\u001a\u000e\u0012\u0004\u0012\u0002H\u0002\u0012\u0004\u0012\u00020\u00010\u0005H\u0086\b\u001a3\u0010\u009f\u0001\u001a\b\u0012\u0004\u0012\u0002H\u00020\u0003\"\u0004\b\u0000\u0010\u0002*\b\u0012\u0004\u0012\u0002H\u00020\u00032\u0012\u0010f\u001a\u000e\u0012\u0004\u0012\u0002H\u0002\u0012\u0004\u0012\u00020e0\u0005H\u0007\u001aF\u0010 \u0001\u001a\u001a\u0012\n\u0012\b\u0012\u0004\u0012\u0002H\u00020+\u0012\n\u0012\b\u0012\u0004\u0012\u0002H\u00020+0\u000f\"\u0004\b\u0000\u0010\u0002*\b\u0012\u0004\u0012\u0002H\u00020\u00032\u0012\u0010\u0004\u001a\u000e\u0012\u0004\u0012\u0002H\u0002\u0012\u0004\u0012\u00020\u00010\u0005H\u0086\b\u001a.\u0010¡\u0001\u001a\b\u0012\u0004\u0012\u0002H\u00020\u0003\"\u0004\b\u0000\u0010\u0002*\b\u0012\u0004\u0012\u0002H\u00020\u00032\u0006\u00100\u001a\u0002H\u0002H\u0086\u0002¢\u0006\u0003\u0010\u0099\u0001\u001a8\u0010¡\u0001\u001a\b\u0012\u0004\u0012\u0002H\u00020\u0003\"\u0004\b\u0000\u0010\u0002*\b\u0012\u0004\u0012\u0002H\u00020\u00032\u0010\u0010\u009a\u0001\u001a\u000b\u0012\u0006\b\u0001\u0012\u0002H\u00020\u009b\u0001H\u0086\u0002¢\u0006\u0003\u0010\u009c\u0001\u001a/\u0010¡\u0001\u001a\b\u0012\u0004\u0012\u0002H\u00020\u0003\"\u0004\b\u0000\u0010\u0002*\b\u0012\u0004\u0012\u0002H\u00020\u00032\r\u0010\u009a\u0001\u001a\b\u0012\u0004\u0012\u0002H\u00020\bH\u0086\u0002\u001a/\u0010¡\u0001\u001a\b\u0012\u0004\u0012\u0002H\u00020\u0003\"\u0004\b\u0000\u0010\u0002*\b\u0012\u0004\u0012\u0002H\u00020\u00032\r\u0010\u009a\u0001\u001a\b\u0012\u0004\u0012\u0002H\u00020\u0003H\u0086\u0002\u001a.\u0010¢\u0001\u001a\b\u0012\u0004\u0012\u0002H\u00020\u0003\"\u0004\b\u0000\u0010\u0002*\b\u0012\u0004\u0012\u0002H\u00020\u00032\u0006\u00100\u001a\u0002H\u0002H\u0087\b¢\u0006\u0003\u0010\u0099\u0001\u001aX\u0010£\u0001\u001a\u0003H¤\u0001\"\u0005\b\u0000\u0010¤\u0001\"\t\b\u0001\u0010\u0002*\u0003H¤\u0001*\b\u0012\u0004\u0012\u0002H\u00020\u00032)\u0010^\u001a%\u0012\u0014\u0012\u0012H¤\u0001¢\u0006\f\bC\u0012\b\bD\u0012\u0004\b\b(_\u0012\u0004\u0012\u0002H\u0002\u0012\u0005\u0012\u0003H¤\u00010BH\u0086\b¢\u0006\u0003\u0010¥\u0001\u001am\u0010¦\u0001\u001a\u0003H¤\u0001\"\u0005\b\u0000\u0010¤\u0001\"\t\b\u0001\u0010\u0002*\u0003H¤\u0001*\b\u0012\u0004\u0012\u0002H\u00020\u00032>\u0010^\u001a:\u0012\u0013\u0012\u00110$¢\u0006\f\bC\u0012\b\bD\u0012\u0004\b\b(:\u0012\u0014\u0012\u0012H¤\u0001¢\u0006\f\bC\u0012\b\bD\u0012\u0004\b\b(_\u0012\u0004\u0012\u0002H\u0002\u0012\u0005\u0012\u0003H¤\u00010bH\u0086\b¢\u0006\u0003\u0010§\u0001\u001a#\u0010¨\u0001\u001a\b\u0012\u0004\u0012\u0002H\u00020\u0003\"\b\b\u0000\u0010\u0002*\u00020O*\n\u0012\u0006\u0012\u0004\u0018\u0001H\u00020\u0003\u001a\u001c\u0010©\u0001\u001a\u0002H\u0002\"\u0004\b\u0000\u0010\u0002*\b\u0012\u0004\u0012\u0002H\u00020\u0003¢\u0006\u0002\u0010X\u001a3\u0010©\u0001\u001a\u0002H\u0002\"\u0004\b\u0000\u0010\u0002*\b\u0012\u0004\u0012\u0002H\u00020\u00032\u0012\u0010\u0004\u001a\u000e\u0012\u0004\u0012\u0002H\u0002\u0012\u0004\u0012\u00020\u00010\u0005H\u0086\b¢\u0006\u0002\u0010U\u001a\u001e\u0010ª\u0001\u001a\u0004\u0018\u0001H\u0002\"\u0004\b\u0000\u0010\u0002*\b\u0012\u0004\u0012\u0002H\u00020\u0003¢\u0006\u0002\u0010X\u001a5\u0010ª\u0001\u001a\u0004\u0018\u0001H\u0002\"\u0004\b\u0000\u0010\u0002*\b\u0012\u0004\u0012\u0002H\u00020\u00032\u0012\u0010\u0004\u001a\u000e\u0012\u0004\u0012\u0002H\u0002\u0012\u0004\u0012\u00020\u00010\u0005H\u0086\b¢\u0006\u0002\u0010U\u001a(\u0010«\u0001\u001a\b\u0012\u0004\u0012\u0002H\u00020\u0003\"\u000f\b\u0000\u0010\u0002*\t\u0012\u0004\u0012\u0002H\u00020\u008b\u0001*\b\u0012\u0004\u0012\u0002H\u00020\u0003\u001aI\u0010¬\u0001\u001a\b\u0012\u0004\u0012\u0002H\u00020\u0003\"\u0004\b\u0000\u0010\u0002\"\u000f\b\u0001\u0010-*\t\u0012\u0004\u0012\u0002H-0\u008b\u0001*\b\u0012\u0004\u0012\u0002H\u00020\u00032\u0016\b\u0004\u00105\u001a\u0010\u0012\u0004\u0012\u0002H\u0002\u0012\u0006\u0012\u0004\u0018\u0001H-0\u0005H\u0086\b\u001aI\u0010\u00ad\u0001\u001a\b\u0012\u0004\u0012\u0002H\u00020\u0003\"\u0004\b\u0000\u0010\u0002\"\u000f\b\u0001\u0010-*\t\u0012\u0004\u0012\u0002H-0\u008b\u0001*\b\u0012\u0004\u0012\u0002H\u00020\u00032\u0016\b\u0004\u00105\u001a\u0010\u0012\u0004\u0012\u0002H\u0002\u0012\u0006\u0012\u0004\u0018\u0001H-0\u0005H\u0086\b\u001a(\u0010®\u0001\u001a\b\u0012\u0004\u0012\u0002H\u00020\u0003\"\u000f\b\u0000\u0010\u0002*\t\u0012\u0004\u0012\u0002H\u00020\u008b\u0001*\b\u0012\u0004\u0012\u0002H\u00020\u0003\u001a<\u0010¯\u0001\u001a\b\u0012\u0004\u0012\u0002H\u00020\u0003\"\u0004\b\u0000\u0010\u0002*\b\u0012\u0004\u0012\u0002H\u00020\u00032\u001d\u0010\u0091\u0001\u001a\u0018\u0012\u0006\b\u0000\u0012\u0002H\u00020\u0092\u0001j\u000b\u0012\u0006\b\u0000\u0012\u0002H\u0002`\u0093\u0001\u001a\u0019\u0010°\u0001\u001a\u00020$*\b\u0012\u0004\u0012\u00020\u001f0\u0003H\u0007¢\u0006\u0003\b±\u0001\u001a\u0019\u0010°\u0001\u001a\u00020\u001e*\b\u0012\u0004\u0012\u00020\u001e0\u0003H\u0007¢\u0006\u0003\b²\u0001\u001a\u0019\u0010°\u0001\u001a\u00020\"*\b\u0012\u0004\u0012\u00020\"0\u0003H\u0007¢\u0006\u0003\b³\u0001\u001a\u0019\u0010°\u0001\u001a\u00020$*\b\u0012\u0004\u0012\u00020$0\u0003H\u0007¢\u0006\u0003\b´\u0001\u001a\u0019\u0010°\u0001\u001a\u00020&*\b\u0012\u0004\u0012\u00020&0\u0003H\u0007¢\u0006\u0003\bµ\u0001\u001a\u0019\u0010°\u0001\u001a\u00020$*\b\u0012\u0004\u0012\u00020(0\u0003H\u0007¢\u0006\u0003\b¶\u0001\u001a.\u0010·\u0001\u001a\u00020$\"\u0004\b\u0000\u0010\u0002*\b\u0012\u0004\u0012\u0002H\u00020\u00032\u0012\u00105\u001a\u000e\u0012\u0004\u0012\u0002H\u0002\u0012\u0004\u0012\u00020$0\u0005H\u0086\b\u001a.\u0010¸\u0001\u001a\u00020\u001e\"\u0004\b\u0000\u0010\u0002*\b\u0012\u0004\u0012\u0002H\u00020\u00032\u0012\u00105\u001a\u000e\u0012\u0004\u0012\u0002H\u0002\u0012\u0004\u0012\u00020\u001e0\u0005H\u0086\b\u001a%\u0010¹\u0001\u001a\b\u0012\u0004\u0012\u0002H\u00020\u0003\"\u0004\b\u0000\u0010\u0002*\b\u0012\u0004\u0012\u0002H\u00020\u00032\u0006\u00107\u001a\u00020$\u001a1\u0010º\u0001\u001a\b\u0012\u0004\u0012\u0002H\u00020\u0003\"\u0004\b\u0000\u0010\u0002*\b\u0012\u0004\u0012\u0002H\u00020\u00032\u0012\u0010\u0004\u001a\u000e\u0012\u0004\u0012\u0002H\u0002\u0012\u0004\u0012\u00020\u00010\u0005\u001a6\u0010»\u0001\u001a\u0002HF\"\u0004\b\u0000\u0010\u0002\"\u0010\b\u0001\u0010F*\n\u0012\u0006\b\u0000\u0012\u0002H\u00020G*\b\u0012\u0004\u0012\u0002H\u00020\u00032\u0006\u0010\u0016\u001a\u0002HF¢\u0006\u0002\u0010L\u001a)\u0010¼\u0001\u001a\u0014\u0012\u0004\u0012\u0002H\u00020½\u0001j\t\u0012\u0004\u0012\u0002H\u0002`¾\u0001\"\u0004\b\u0000\u0010\u0002*\b\u0012\u0004\u0012\u0002H\u00020\u0003\u001a\u001d\u0010¿\u0001\u001a\b\u0012\u0004\u0012\u0002H\u00020+\"\u0004\b\u0000\u0010\u0002*\b\u0012\u0004\u0012\u0002H\u00020\u0003\u001a\u001d\u0010\u00c0\u0001\u001a\b\u0012\u0004\u0012\u0002H\u00020j\"\u0004\b\u0000\u0010\u0002*\b\u0012\u0004\u0012\u0002H\u00020\u0003\u001a\u001e\u0010\u00c1\u0001\u001a\t\u0012\u0004\u0012\u0002H\u00020\u00c2\u0001\"\u0004\b\u0000\u0010\u0002*\b\u0012\u0004\u0012\u0002H\u00020\u0003\u001a\u001e\u0010\u00c3\u0001\u001a\t\u0012\u0004\u0012\u0002H\u00020\u00c4\u0001\"\u0004\b\u0000\u0010\u0002*\b\u0012\u0004\u0012\u0002H\u00020\u0003\u001aC\u0010\u00c5\u0001\u001a\u000e\u0012\n\u0012\b\u0012\u0004\u0012\u0002H\u00020+0\u0003\"\u0004\b\u0000\u0010\u0002*\b\u0012\u0004\u0012\u0002H\u00020\u00032\u0006\u0010,\u001a\u00020$2\t\b\u0002\u0010\u00c6\u0001\u001a\u00020$2\t\b\u0002\u0010\u00c7\u0001\u001a\u00020\u0001H\u0007\u001a]\u0010\u00c5\u0001\u001a\b\u0012\u0004\u0012\u0002H-0\u0003\"\u0004\b\u0000\u0010\u0002\"\u0004\b\u0001\u0010-*\b\u0012\u0004\u0012\u0002H\u00020\u00032\u0006\u0010,\u001a\u00020$2\t\b\u0002\u0010\u00c6\u0001\u001a\u00020$2\t\b\u0002\u0010\u00c7\u0001\u001a\u00020\u00012\u0018\u0010\u000e\u001a\u0014\u0012\n\u0012\b\u0012\u0004\u0012\u0002H\u00020+\u0012\u0004\u0012\u0002H-0\u0005H\u0007\u001a$\u0010\u00c8\u0001\u001a\u000f\u0012\u000b\u0012\t\u0012\u0004\u0012\u0002H\u00020\u00c9\u00010\u0003\"\u0004\b\u0000\u0010\u0002*\b\u0012\u0004\u0012\u0002H\u00020\u0003\u001aA\u0010\u00ca\u0001\u001a\u0014\u0012\u0010\u0012\u000e\u0012\u0004\u0012\u0002H\u0002\u0012\u0004\u0012\u0002H-0\u000f0\u0003\"\u0004\b\u0000\u0010\u0002\"\u0004\b\u0001\u0010-*\b\u0012\u0004\u0012\u0002H\u00020\u00032\r\u0010\u00cb\u0001\u001a\b\u0012\u0004\u0012\u0002H-0\u0003H\u0086\u0004\u001ar\u0010\u00ca\u0001\u001a\b\u0012\u0004\u0012\u0002H\r0\u0003\"\u0004\b\u0000\u0010\u0002\"\u0004\b\u0001\u0010-\"\u0004\b\u0002\u0010\r*\b\u0012\u0004\u0012\u0002H\u00020\u00032\r\u0010\u00cb\u0001\u001a\b\u0012\u0004\u0012\u0002H-0\u000328\u0010\u000e\u001a4\u0012\u0014\u0012\u0012H\u0002¢\u0006\r\bC\u0012\t\bD\u0012\u0005\b\b(\u00cc\u0001\u0012\u0014\u0012\u0012H-¢\u0006\r\bC\u0012\t\bD\u0012\u0005\b\b(\u00cd\u0001\u0012\u0004\u0012\u0002H\r0B\u001a+\u0010\u00ce\u0001\u001a\u0014\u0012\u0010\u0012\u000e\u0012\u0004\u0012\u0002H\u0002\u0012\u0004\u0012\u0002H\u00020\u000f0\u0003\"\u0004\b\u0000\u0010\u0002*\b\u0012\u0004\u0012\u0002H\u00020\u0003H\u0007\u001a_\u0010\u00ce\u0001\u001a\b\u0012\u0004\u0012\u0002H-0\u0003\"\u0004\b\u0000\u0010\u0002\"\u0004\b\u0001\u0010-*\b\u0012\u0004\u0012\u0002H\u00020\u000328\u0010\u000e\u001a4\u0012\u0014\u0012\u0012H\u0002¢\u0006\r\bC\u0012\t\bD\u0012\u0005\b\b(\u00cc\u0001\u0012\u0014\u0012\u0012H\u0002¢\u0006\r\bC\u0012\t\bD\u0012\u0005\b\b(\u00cd\u0001\u0012\u0004\u0012\u0002H-0BH\u0007¨\u0006\u00cf\u0001" }, d2 = { "all", "", "T", "Lkotlin/sequences/Sequence;", "predicate", "Lkotlin/Function1;", "any", "asIterable", "", "asSequence", "associate", "", "K", "V", "transform", "Lkotlin/Pair;", "associateBy", "keySelector", "valueTransform", "associateByTo", "M", "", "destination", "(Lkotlin/sequences/Sequence;Ljava/util/Map;Lkotlin/jvm/functions/Function1;)Ljava/util/Map;", "(Lkotlin/sequences/Sequence;Ljava/util/Map;Lkotlin/jvm/functions/Function1;Lkotlin/jvm/functions/Function1;)Ljava/util/Map;", "associateTo", "associateWith", "valueSelector", "associateWithTo", "average", "", "", "averageOfByte", "averageOfDouble", "", "averageOfFloat", "", "averageOfInt", "", "averageOfLong", "", "averageOfShort", "chunked", "", "size", "R", "contains", "Lkotlin/internal/OnlyInputTypes;", "element", "(Lkotlin/sequences/Sequence;Ljava/lang/Object;)Z", "count", "distinct", "distinctBy", "selector", "drop", "n", "dropWhile", "elementAt", "index", "(Lkotlin/sequences/Sequence;I)Ljava/lang/Object;", "elementAtOrElse", "defaultValue", "(Lkotlin/sequences/Sequence;ILkotlin/jvm/functions/Function1;)Ljava/lang/Object;", "elementAtOrNull", "filter", "filterIndexed", "Lkotlin/Function2;", "Lkotlin/ParameterName;", "name", "filterIndexedTo", "C", "", "(Lkotlin/sequences/Sequence;Ljava/util/Collection;Lkotlin/jvm/functions/Function2;)Ljava/util/Collection;", "filterIsInstance", "Lkotlin/internal/NoInfer;", "filterIsInstanceTo", "(Lkotlin/sequences/Sequence;Ljava/util/Collection;)Ljava/util/Collection;", "filterNot", "filterNotNull", "", "filterNotNullTo", "filterNotTo", "(Lkotlin/sequences/Sequence;Ljava/util/Collection;Lkotlin/jvm/functions/Function1;)Ljava/util/Collection;", "filterTo", "find", "(Lkotlin/sequences/Sequence;Lkotlin/jvm/functions/Function1;)Ljava/lang/Object;", "findLast", "first", "(Lkotlin/sequences/Sequence;)Ljava/lang/Object;", "firstOrNull", "flatMap", "flatMapTo", "fold", "initial", "operation", "acc", "(Lkotlin/sequences/Sequence;Ljava/lang/Object;Lkotlin/jvm/functions/Function2;)Ljava/lang/Object;", "foldIndexed", "Lkotlin/Function3;", "(Lkotlin/sequences/Sequence;Ljava/lang/Object;Lkotlin/jvm/functions/Function3;)Ljava/lang/Object;", "forEach", "", "action", "forEachIndexed", "groupBy", "groupByTo", "", "groupingBy", "Lkotlin/collections/Grouping;", "indexOf", "(Lkotlin/sequences/Sequence;Ljava/lang/Object;)I", "indexOfFirst", "indexOfLast", "joinTo", "A", "Ljava/lang/Appendable;", "Lkotlin/text/Appendable;", "buffer", "separator", "", "prefix", "postfix", "limit", "truncated", "(Lkotlin/sequences/Sequence;Ljava/lang/Appendable;Ljava/lang/CharSequence;Ljava/lang/CharSequence;Ljava/lang/CharSequence;ILjava/lang/CharSequence;Lkotlin/jvm/functions/Function1;)Ljava/lang/Appendable;", "joinToString", "", "last", "lastIndexOf", "lastOrNull", "map", "mapIndexed", "mapIndexedNotNull", "mapIndexedNotNullTo", "mapIndexedTo", "mapNotNull", "mapNotNullTo", "mapTo", "max", "", "(Lkotlin/sequences/Sequence;)Ljava/lang/Comparable;", "(Lkotlin/sequences/Sequence;)Ljava/lang/Double;", "(Lkotlin/sequences/Sequence;)Ljava/lang/Float;", "maxBy", "maxWith", "comparator", "Ljava/util/Comparator;", "Lkotlin/Comparator;", "(Lkotlin/sequences/Sequence;Ljava/util/Comparator;)Ljava/lang/Object;", "min", "minBy", "minWith", "minus", "(Lkotlin/sequences/Sequence;Ljava/lang/Object;)Lkotlin/sequences/Sequence;", "elements", "", "(Lkotlin/sequences/Sequence;[Ljava/lang/Object;)Lkotlin/sequences/Sequence;", "minusElement", "none", "onEach", "partition", "plus", "plusElement", "reduce", "S", "(Lkotlin/sequences/Sequence;Lkotlin/jvm/functions/Function2;)Ljava/lang/Object;", "reduceIndexed", "(Lkotlin/sequences/Sequence;Lkotlin/jvm/functions/Function3;)Ljava/lang/Object;", "requireNoNulls", "single", "singleOrNull", "sorted", "sortedBy", "sortedByDescending", "sortedDescending", "sortedWith", "sum", "sumOfByte", "sumOfDouble", "sumOfFloat", "sumOfInt", "sumOfLong", "sumOfShort", "sumBy", "sumByDouble", "take", "takeWhile", "toCollection", "toHashSet", "Ljava/util/HashSet;", "Lkotlin/collections/HashSet;", "toList", "toMutableList", "toMutableSet", "", "toSet", "", "windowed", "step", "partialWindows", "withIndex", "Lkotlin/collections/IndexedValue;", "zip", "other", "a", "b", "zipWithNext", "kotlin-stdlib" }, xs = "kotlin/sequences/SequencesKt")
class SequencesKt___SequencesKt extends SequencesKt___SequencesJvmKt
{
    public static final <T> boolean contains(@NotNull final Sequence<? extends T> $this$contains, final T element) {
        Intrinsics.checkParameterIsNotNull($this$contains, "$this$contains");
        return indexOf($this$contains, element) >= 0;
    }
    
    public static final <T> T elementAt(@NotNull final Sequence<? extends T> $this$elementAt, final int index) {
        Intrinsics.checkParameterIsNotNull($this$elementAt, "$this$elementAt");
        return elementAtOrElse($this$elementAt, index, (Function1<? super Integer, ? extends T>)new SequencesKt___SequencesKt$elementAt.SequencesKt___SequencesKt$elementAt$1(index));
    }
    
    public static final <T> T elementAtOrElse(@NotNull final Sequence<? extends T> $this$elementAtOrElse, final int index, @NotNull final Function1<? super Integer, ? extends T> defaultValue) {
        Intrinsics.checkParameterIsNotNull($this$elementAtOrElse, "$this$elementAtOrElse");
        Intrinsics.checkParameterIsNotNull(defaultValue, "defaultValue");
        if (index < 0) {
            return (T)defaultValue.invoke(index);
        }
        final Iterator iterator = $this$elementAtOrElse.iterator();
        int count = 0;
        while (iterator.hasNext()) {
            final Object element = iterator.next();
            if (index == count++) {
                return (T)element;
            }
        }
        return (T)defaultValue.invoke(index);
    }
    
    @Nullable
    public static final <T> T elementAtOrNull(@NotNull final Sequence<? extends T> $this$elementAtOrNull, final int index) {
        Intrinsics.checkParameterIsNotNull($this$elementAtOrNull, "$this$elementAtOrNull");
        if (index < 0) {
            return null;
        }
        final Iterator iterator = $this$elementAtOrNull.iterator();
        int count = 0;
        while (iterator.hasNext()) {
            final Object element = iterator.next();
            if (index == count++) {
                return (T)element;
            }
        }
        return null;
    }
    
    @InlineOnly
    private static final <T> T find(@NotNull final Sequence<? extends T> $this$find, final Function1<? super T, Boolean> predicate) {
        final int $i$f$find = 0;
        final Sequence $this$firstOrNull$iv = $this$find;
        final int $i$f$firstOrNull = 0;
        for (final Object element$iv : $this$firstOrNull$iv) {
            if (predicate.invoke((Object)element$iv)) {
                final Object o = element$iv;
                return (T)o;
            }
        }
        final Object o = null;
        return (T)o;
    }
    
    @InlineOnly
    private static final <T> T findLast(@NotNull final Sequence<? extends T> $this$findLast, final Function1<? super T, Boolean> predicate) {
        final int $i$f$findLast = 0;
        final Sequence $this$lastOrNull$iv = $this$findLast;
        final int $i$f$lastOrNull = 0;
        Object last$iv = null;
        for (final Object element$iv : $this$lastOrNull$iv) {
            if (predicate.invoke((Object)element$iv)) {
                last$iv = element$iv;
            }
        }
        return (T)last$iv;
    }
    
    public static final <T> T first(@NotNull final Sequence<? extends T> $this$first) {
        Intrinsics.checkParameterIsNotNull($this$first, "$this$first");
        final Iterator iterator = $this$first.iterator();
        if (!iterator.hasNext()) {
            throw new NoSuchElementException("Sequence is empty.");
        }
        return iterator.next();
    }
    
    public static final <T> T first(@NotNull final Sequence<? extends T> $this$first, @NotNull final Function1<? super T, Boolean> predicate) {
        final int $i$f$first = 0;
        Intrinsics.checkParameterIsNotNull($this$first, "$this$first");
        Intrinsics.checkParameterIsNotNull(predicate, "predicate");
        for (final Object element : $this$first) {
            if (predicate.invoke((Object)element)) {
                return (T)element;
            }
        }
        throw new NoSuchElementException("Sequence contains no element matching the predicate.");
    }
    
    @Nullable
    public static final <T> T firstOrNull(@NotNull final Sequence<? extends T> $this$firstOrNull) {
        Intrinsics.checkParameterIsNotNull($this$firstOrNull, "$this$firstOrNull");
        final Iterator iterator = $this$firstOrNull.iterator();
        if (!iterator.hasNext()) {
            return null;
        }
        return iterator.next();
    }
    
    @Nullable
    public static final <T> T firstOrNull(@NotNull final Sequence<? extends T> $this$firstOrNull, @NotNull final Function1<? super T, Boolean> predicate) {
        final int $i$f$firstOrNull = 0;
        Intrinsics.checkParameterIsNotNull($this$firstOrNull, "$this$firstOrNull");
        Intrinsics.checkParameterIsNotNull(predicate, "predicate");
        for (final Object element : $this$firstOrNull) {
            if (predicate.invoke((Object)element)) {
                return (T)element;
            }
        }
        return null;
    }
    
    public static final <T> int indexOf(@NotNull final Sequence<? extends T> $this$indexOf, final T element) {
        Intrinsics.checkParameterIsNotNull($this$indexOf, "$this$indexOf");
        int index = 0;
        for (final Object item : $this$indexOf) {
            if (index < 0) {
                CollectionsKt.throwIndexOverflow();
            }
            if (Intrinsics.areEqual(element, item)) {
                return index;
            }
            ++index;
        }
        return -1;
    }
    
    public static final <T> int indexOfFirst(@NotNull final Sequence<? extends T> $this$indexOfFirst, @NotNull final Function1<? super T, Boolean> predicate) {
        final int $i$f$indexOfFirst = 0;
        Intrinsics.checkParameterIsNotNull($this$indexOfFirst, "$this$indexOfFirst");
        Intrinsics.checkParameterIsNotNull(predicate, "predicate");
        int index = 0;
        for (final Object item : $this$indexOfFirst) {
            if (index < 0) {
                if (!PlatformImplementationsKt.apiVersionIsAtLeast(1, 3, 0)) {
                    throw new ArithmeticException("Index overflow has happened.");
                }
                CollectionsKt.throwIndexOverflow();
            }
            if (predicate.invoke((Object)item)) {
                return index;
            }
            ++index;
        }
        return -1;
    }
    
    public static final <T> int indexOfLast(@NotNull final Sequence<? extends T> $this$indexOfLast, @NotNull final Function1<? super T, Boolean> predicate) {
        final int $i$f$indexOfLast = 0;
        Intrinsics.checkParameterIsNotNull($this$indexOfLast, "$this$indexOfLast");
        Intrinsics.checkParameterIsNotNull(predicate, "predicate");
        int lastIndex = -1;
        int index = 0;
        for (final Object item : $this$indexOfLast) {
            if (index < 0) {
                if (!PlatformImplementationsKt.apiVersionIsAtLeast(1, 3, 0)) {
                    throw new ArithmeticException("Index overflow has happened.");
                }
                CollectionsKt.throwIndexOverflow();
            }
            if (predicate.invoke((Object)item)) {
                lastIndex = index;
            }
            ++index;
        }
        return lastIndex;
    }
    
    public static final <T> T last(@NotNull final Sequence<? extends T> $this$last) {
        Intrinsics.checkParameterIsNotNull($this$last, "$this$last");
        final Iterator iterator = $this$last.iterator();
        if (!iterator.hasNext()) {
            throw new NoSuchElementException("Sequence is empty.");
        }
        Object last = iterator.next();
        while (iterator.hasNext()) {
            last = iterator.next();
        }
        return (T)last;
    }
    
    public static final <T> T last(@NotNull final Sequence<? extends T> $this$last, @NotNull final Function1<? super T, Boolean> predicate) {
        final int $i$f$last = 0;
        Intrinsics.checkParameterIsNotNull($this$last, "$this$last");
        Intrinsics.checkParameterIsNotNull(predicate, "predicate");
        Object last = null;
        boolean found = false;
        for (final Object element : $this$last) {
            if (predicate.invoke((Object)element)) {
                last = element;
                found = true;
            }
        }
        if (!found) {
            throw new NoSuchElementException("Sequence contains no element matching the predicate.");
        }
        return (T)last;
    }
    
    public static final <T> int lastIndexOf(@NotNull final Sequence<? extends T> $this$lastIndexOf, final T element) {
        Intrinsics.checkParameterIsNotNull($this$lastIndexOf, "$this$lastIndexOf");
        int lastIndex = -1;
        int index = 0;
        for (final Object item : $this$lastIndexOf) {
            if (index < 0) {
                CollectionsKt.throwIndexOverflow();
            }
            if (Intrinsics.areEqual(element, item)) {
                lastIndex = index;
            }
            ++index;
        }
        return lastIndex;
    }
    
    @Nullable
    public static final <T> T lastOrNull(@NotNull final Sequence<? extends T> $this$lastOrNull) {
        Intrinsics.checkParameterIsNotNull($this$lastOrNull, "$this$lastOrNull");
        final Iterator iterator = $this$lastOrNull.iterator();
        if (!iterator.hasNext()) {
            return null;
        }
        Object last = iterator.next();
        while (iterator.hasNext()) {
            last = iterator.next();
        }
        return (T)last;
    }
    
    @Nullable
    public static final <T> T lastOrNull(@NotNull final Sequence<? extends T> $this$lastOrNull, @NotNull final Function1<? super T, Boolean> predicate) {
        final int $i$f$lastOrNull = 0;
        Intrinsics.checkParameterIsNotNull($this$lastOrNull, "$this$lastOrNull");
        Intrinsics.checkParameterIsNotNull(predicate, "predicate");
        Object last = null;
        for (final Object element : $this$lastOrNull) {
            if (predicate.invoke((Object)element)) {
                last = element;
            }
        }
        return (T)last;
    }
    
    public static final <T> T single(@NotNull final Sequence<? extends T> $this$single) {
        Intrinsics.checkParameterIsNotNull($this$single, "$this$single");
        final Iterator iterator = $this$single.iterator();
        if (!iterator.hasNext()) {
            throw new NoSuchElementException("Sequence is empty.");
        }
        final Object single = iterator.next();
        if (iterator.hasNext()) {
            throw new IllegalArgumentException("Sequence has more than one element.");
        }
        return (T)single;
    }
    
    public static final <T> T single(@NotNull final Sequence<? extends T> $this$single, @NotNull final Function1<? super T, Boolean> predicate) {
        final int $i$f$single = 0;
        Intrinsics.checkParameterIsNotNull($this$single, "$this$single");
        Intrinsics.checkParameterIsNotNull(predicate, "predicate");
        Object single = null;
        boolean found = false;
        for (final Object element : $this$single) {
            if (predicate.invoke((Object)element)) {
                if (found) {
                    throw new IllegalArgumentException("Sequence contains more than one matching element.");
                }
                single = element;
                found = true;
            }
        }
        if (!found) {
            throw new NoSuchElementException("Sequence contains no element matching the predicate.");
        }
        return (T)single;
    }
    
    @Nullable
    public static final <T> T singleOrNull(@NotNull final Sequence<? extends T> $this$singleOrNull) {
        Intrinsics.checkParameterIsNotNull($this$singleOrNull, "$this$singleOrNull");
        final Iterator iterator = $this$singleOrNull.iterator();
        if (!iterator.hasNext()) {
            return null;
        }
        final Object single = iterator.next();
        if (iterator.hasNext()) {
            return null;
        }
        return (T)single;
    }
    
    @Nullable
    public static final <T> T singleOrNull(@NotNull final Sequence<? extends T> $this$singleOrNull, @NotNull final Function1<? super T, Boolean> predicate) {
        final int $i$f$singleOrNull = 0;
        Intrinsics.checkParameterIsNotNull($this$singleOrNull, "$this$singleOrNull");
        Intrinsics.checkParameterIsNotNull(predicate, "predicate");
        Object single = null;
        boolean found = false;
        for (final Object element : $this$singleOrNull) {
            if (predicate.invoke((Object)element)) {
                if (found) {
                    return null;
                }
                single = element;
                found = true;
            }
        }
        if (!found) {
            return null;
        }
        return (T)single;
    }
    
    @NotNull
    public static final <T> Sequence<T> drop(@NotNull final Sequence<? extends T> $this$drop, final int n) {
        Intrinsics.checkParameterIsNotNull($this$drop, "$this$drop");
        if (n < 0) {
            final int n2 = 0;
            throw new IllegalArgumentException(("Requested element count " + n + " is less than zero.").toString());
        }
        return (Sequence<T>)((n == 0) ? $this$drop : (($this$drop instanceof DropTakeSequence) ? ((DropTakeSequence<? extends T>)$this$drop).drop(n) : ((DropSequence<Object>)new DropSequence<Object>($this$drop, n))));
    }
    
    @NotNull
    public static final <T> Sequence<T> dropWhile(@NotNull final Sequence<? extends T> $this$dropWhile, @NotNull final Function1<? super T, Boolean> predicate) {
        Intrinsics.checkParameterIsNotNull($this$dropWhile, "$this$dropWhile");
        Intrinsics.checkParameterIsNotNull(predicate, "predicate");
        return new DropWhileSequence<T>($this$dropWhile, predicate);
    }
    
    @NotNull
    public static final <T> Sequence<T> filter(@NotNull final Sequence<? extends T> $this$filter, @NotNull final Function1<? super T, Boolean> predicate) {
        Intrinsics.checkParameterIsNotNull($this$filter, "$this$filter");
        Intrinsics.checkParameterIsNotNull(predicate, "predicate");
        return new FilteringSequence<T>($this$filter, true, predicate);
    }
    
    @NotNull
    public static final <T> Sequence<T> filterIndexed(@NotNull final Sequence<? extends T> $this$filterIndexed, @NotNull final Function2<? super Integer, ? super T, Boolean> predicate) {
        Intrinsics.checkParameterIsNotNull($this$filterIndexed, "$this$filterIndexed");
        Intrinsics.checkParameterIsNotNull(predicate, "predicate");
        return new TransformingSequence<Object, T>(new FilteringSequence<Object>(new IndexingSequence<Object>($this$filterIndexed), true, (Function1<?, Boolean>)new SequencesKt___SequencesKt$filterIndexed.SequencesKt___SequencesKt$filterIndexed$1((Function2)predicate)), (Function1<?, ? extends T>)SequencesKt___SequencesKt$filterIndexed.SequencesKt___SequencesKt$filterIndexed$2.INSTANCE);
    }
    
    @NotNull
    public static final <T, C extends Collection<? super T>> C filterIndexedTo(@NotNull final Sequence<? extends T> $this$filterIndexedTo, @NotNull final C destination, @NotNull final Function2<? super Integer, ? super T, Boolean> predicate) {
        // 
        // This method could not be decompiled.
        // 
        // Original Bytecode:
        // 
        //     2: istore_3        /* $i$f$filterIndexedTo */
        //     3: aload_0         /* $this$filterIndexedTo */
        //     4: ldc_w           "$this$filterIndexedTo"
        //     7: invokestatic    kotlin/jvm/internal/Intrinsics.checkParameterIsNotNull:(Ljava/lang/Object;Ljava/lang/String;)V
        //    10: aload_1         /* destination */
        //    11: ldc_w           "destination"
        //    14: invokestatic    kotlin/jvm/internal/Intrinsics.checkParameterIsNotNull:(Ljava/lang/Object;Ljava/lang/String;)V
        //    17: aload_2         /* predicate */
        //    18: ldc_w           "predicate"
        //    21: invokestatic    kotlin/jvm/internal/Intrinsics.checkParameterIsNotNull:(Ljava/lang/Object;Ljava/lang/String;)V
        //    24: aload_0         /* $this$filterIndexedTo */
        //    25: astore          $this$forEachIndexed$iv
        //    27: iconst_0       
        //    28: istore          $i$f$forEachIndexed
        //    30: iconst_0       
        //    31: istore          index$iv
        //    33: aload           $this$forEachIndexed$iv
        //    35: invokeinterface kotlin/sequences/Sequence.iterator:()Ljava/util/Iterator;
        //    40: astore          7
        //    42: aload           7
        //    44: invokeinterface java/util/Iterator.hasNext:()Z
        //    49: ifeq            155
        //    52: aload           7
        //    54: invokeinterface java/util/Iterator.next:()Ljava/lang/Object;
        //    59: astore          item$iv
        //    61: iload           index$iv
        //    63: iinc            index$iv, 1
        //    66: istore          9
        //    68: iconst_0       
        //    69: istore          10
        //    71: iload           9
        //    73: ifge            105
        //    76: iconst_1       
        //    77: iconst_3       
        //    78: iconst_0       
        //    79: invokestatic    kotlin/internal/PlatformImplementationsKt.apiVersionIsAtLeast:(III)Z
        //    82: ifeq            91
        //    85: invokestatic    kotlin/collections/CollectionsKt.throwIndexOverflow:()V
        //    88: goto            105
        //    91: new             Ljava/lang/ArithmeticException;
        //    94: dup            
        //    95: ldc_w           "Index overflow has happened."
        //    98: invokespecial   java/lang/ArithmeticException.<init>:(Ljava/lang/String;)V
        //   101: checkcast       Ljava/lang/Throwable;
        //   104: athrow         
        //   105: iload           9
        //   107: istore          11
        //   109: iload           11
        //   111: aload           item$iv
        //   113: astore          12
        //   115: istore          index
        //   117: iconst_0       
        //   118: istore          $i$a$-forEachIndexed-SequencesKt___SequencesKt$filterIndexedTo$1
        //   120: aload_2         /* predicate */
        //   121: iload           index
        //   123: invokestatic    java/lang/Integer.valueOf:(I)Ljava/lang/Integer;
        //   126: aload           element
        //   128: invokeinterface kotlin/jvm/functions/Function2.invoke:(Ljava/lang/Object;Ljava/lang/Object;)Ljava/lang/Object;
        //   133: checkcast       Ljava/lang/Boolean;
        //   136: invokevirtual   java/lang/Boolean.booleanValue:()Z
        //   139: ifeq            151
        //   142: aload_1         /* destination */
        //   143: aload           element
        //   145: invokeinterface java/util/Collection.add:(Ljava/lang/Object;)Z
        //   150: pop            
        //   151: nop            
        //   152: goto            42
        //   155: nop            
        //   156: aload_1         /* destination */
        //   157: areturn        
        //    Signature:
        //  <T:Ljava/lang/Object;C::Ljava/util/Collection<-TT;>;>(Lkotlin/sequences/Sequence<+TT;>;TC;Lkotlin/jvm/functions/Function2<-Ljava/lang/Integer;-TT;Ljava/lang/Boolean;>;)TC;
        //    StackMapTable: 00 05 FF 00 2A 00 08 07 01 1D 07 01 D2 07 01 D4 01 07 01 1D 01 01 07 01 23 00 00 FE 00 30 07 01 2D 01 01 0D FF 00 2D 00 0F 07 01 1D 07 01 D2 07 01 D4 01 07 01 1D 01 01 07 01 23 07 01 2D 01 01 01 07 01 2D 01 01 00 00 FF 00 03 00 08 07 01 1D 07 01 D2 07 01 D4 01 07 01 1D 01 01 07 01 23 00 00
        // 
        // The error that occurred was:
        // 
        // java.lang.NullPointerException
        // 
        throw new IllegalStateException("An error occurred while decompiling this method.");
    }
    
    @NotNull
    public static final <T> Sequence<T> filterNot(@NotNull final Sequence<? extends T> $this$filterNot, @NotNull final Function1<? super T, Boolean> predicate) {
        Intrinsics.checkParameterIsNotNull($this$filterNot, "$this$filterNot");
        Intrinsics.checkParameterIsNotNull(predicate, "predicate");
        return new FilteringSequence<T>($this$filterNot, false, predicate);
    }
    
    @NotNull
    public static final <T> Sequence<T> filterNotNull(@NotNull final Sequence<? extends T> $this$filterNotNull) {
        Intrinsics.checkParameterIsNotNull($this$filterNotNull, "$this$filterNotNull");
        final Sequence<Object> filterNot = (Sequence<Object>)filterNot($this$filterNotNull, (Function1<? super T, Boolean>)SequencesKt___SequencesKt$filterNotNull.SequencesKt___SequencesKt$filterNotNull$1.INSTANCE);
        if (filterNot == null) {
            throw new TypeCastException("null cannot be cast to non-null type kotlin.sequences.Sequence<T>");
        }
        return (Sequence<T>)filterNot;
    }
    
    @NotNull
    public static final <C extends Collection<? super T>, T> C filterNotNullTo(@NotNull final Sequence<? extends T> $this$filterNotNullTo, @NotNull final C destination) {
        Intrinsics.checkParameterIsNotNull($this$filterNotNullTo, "$this$filterNotNullTo");
        Intrinsics.checkParameterIsNotNull(destination, "destination");
        for (final Object element : $this$filterNotNullTo) {
            if (element != null) {
                destination.add((Object)element);
            }
        }
        return destination;
    }
    
    @NotNull
    public static final <T, C extends Collection<? super T>> C filterNotTo(@NotNull final Sequence<? extends T> $this$filterNotTo, @NotNull final C destination, @NotNull final Function1<? super T, Boolean> predicate) {
        final int $i$f$filterNotTo = 0;
        Intrinsics.checkParameterIsNotNull($this$filterNotTo, "$this$filterNotTo");
        Intrinsics.checkParameterIsNotNull(destination, "destination");
        Intrinsics.checkParameterIsNotNull(predicate, "predicate");
        for (final Object element : $this$filterNotTo) {
            if (!predicate.invoke((Object)element)) {
                destination.add((Object)element);
            }
        }
        return destination;
    }
    
    @NotNull
    public static final <T, C extends Collection<? super T>> C filterTo(@NotNull final Sequence<? extends T> $this$filterTo, @NotNull final C destination, @NotNull final Function1<? super T, Boolean> predicate) {
        final int $i$f$filterTo = 0;
        Intrinsics.checkParameterIsNotNull($this$filterTo, "$this$filterTo");
        Intrinsics.checkParameterIsNotNull(destination, "destination");
        Intrinsics.checkParameterIsNotNull(predicate, "predicate");
        for (final Object element : $this$filterTo) {
            if (predicate.invoke((Object)element)) {
                destination.add((Object)element);
            }
        }
        return destination;
    }
    
    @NotNull
    public static final <T> Sequence<T> take(@NotNull final Sequence<? extends T> $this$take, final int n) {
        Intrinsics.checkParameterIsNotNull($this$take, "$this$take");
        if (n < 0) {
            final int n2 = 0;
            throw new IllegalArgumentException(("Requested element count " + n + " is less than zero.").toString());
        }
        return (n == 0) ? SequencesKt__SequencesKt.emptySequence() : (($this$take instanceof DropTakeSequence) ? ((DropTakeSequence<T>)$this$take).take(n) : ((TakeSequence<T>)new TakeSequence<T>($this$take, n)));
    }
    
    @NotNull
    public static final <T> Sequence<T> takeWhile(@NotNull final Sequence<? extends T> $this$takeWhile, @NotNull final Function1<? super T, Boolean> predicate) {
        Intrinsics.checkParameterIsNotNull($this$takeWhile, "$this$takeWhile");
        Intrinsics.checkParameterIsNotNull(predicate, "predicate");
        return new TakeWhileSequence<T>($this$takeWhile, predicate);
    }
    
    @NotNull
    public static final <T extends Comparable<? super T>> Sequence<T> sorted(@NotNull final Sequence<? extends T> $this$sorted) {
        Intrinsics.checkParameterIsNotNull($this$sorted, "$this$sorted");
        return (Sequence<T>)new SequencesKt___SequencesKt$sorted.SequencesKt___SequencesKt$sorted$1((Sequence)$this$sorted);
    }
    
    @NotNull
    public static final <T, R extends Comparable<? super R>> Sequence<T> sortedBy(@NotNull final Sequence<? extends T> $this$sortedBy, @NotNull final Function1<? super T, ? extends R> selector) {
        final int $i$f$sortedBy = 0;
        Intrinsics.checkParameterIsNotNull($this$sortedBy, "$this$sortedBy");
        Intrinsics.checkParameterIsNotNull(selector, "selector");
        return sortedWith($this$sortedBy, (Comparator<? super T>)new Comparator<Object>(selector) {
            @Override
            public final int compare(final T a, final T b) {
                return ComparisonsKt__ComparisonsKt.compareValues(this.$selector.invoke(a), (Comparable)this.$selector.invoke(b));
            }
        });
    }
    
    @NotNull
    public static final <T, R extends Comparable<? super R>> Sequence<T> sortedByDescending(@NotNull final Sequence<? extends T> $this$sortedByDescending, @NotNull final Function1<? super T, ? extends R> selector) {
        final int $i$f$sortedByDescending = 0;
        Intrinsics.checkParameterIsNotNull($this$sortedByDescending, "$this$sortedByDescending");
        Intrinsics.checkParameterIsNotNull(selector, "selector");
        return sortedWith($this$sortedByDescending, (Comparator<? super T>)new Comparator<Object>(selector) {
            @Override
            public final int compare(final T a, final T b) {
                return ComparisonsKt__ComparisonsKt.compareValues(this.$selector.invoke(b), (Comparable)this.$selector.invoke(a));
            }
        });
    }
    
    @NotNull
    public static final <T extends Comparable<? super T>> Sequence<T> sortedDescending(@NotNull final Sequence<? extends T> $this$sortedDescending) {
        Intrinsics.checkParameterIsNotNull($this$sortedDescending, "$this$sortedDescending");
        return sortedWith($this$sortedDescending, ComparisonsKt__ComparisonsKt.reverseOrder());
    }
    
    @NotNull
    public static final <T> Sequence<T> sortedWith(@NotNull final Sequence<? extends T> $this$sortedWith, @NotNull final Comparator<? super T> comparator) {
        Intrinsics.checkParameterIsNotNull($this$sortedWith, "$this$sortedWith");
        Intrinsics.checkParameterIsNotNull(comparator, "comparator");
        return (Sequence<T>)new SequencesKt___SequencesKt$sortedWith.SequencesKt___SequencesKt$sortedWith$1((Sequence)$this$sortedWith, (Comparator)comparator);
    }
    
    @NotNull
    public static final <T, K, V> Map<K, V> associate(@NotNull final Sequence<? extends T> $this$associate, @NotNull final Function1<? super T, ? extends Pair<? extends K, ? extends V>> transform) {
        // 
        // This method could not be decompiled.
        // 
        // Original Bytecode:
        // 
        //     2: istore_2        /* $i$f$associate */
        //     3: aload_0         /* $this$associate */
        //     4: ldc_w           "$this$associate"
        //     7: invokestatic    kotlin/jvm/internal/Intrinsics.checkParameterIsNotNull:(Ljava/lang/Object;Ljava/lang/String;)V
        //    10: aload_1         /* transform */
        //    11: ldc_w           "transform"
        //    14: invokestatic    kotlin/jvm/internal/Intrinsics.checkParameterIsNotNull:(Ljava/lang/Object;Ljava/lang/String;)V
        //    17: aload_0         /* $this$associate */
        //    18: astore_3       
        //    19: new             Ljava/util/LinkedHashMap;
        //    22: dup            
        //    23: invokespecial   java/util/LinkedHashMap.<init>:()V
        //    26: checkcast       Ljava/util/Map;
        //    29: astore          destination$iv
        //    31: iconst_0       
        //    32: istore          $i$f$associateTo
        //    34: aload_3         /* $this$associateTo$iv */
        //    35: invokeinterface kotlin/sequences/Sequence.iterator:()Ljava/util/Iterator;
        //    40: astore          6
        //    42: aload           6
        //    44: invokeinterface java/util/Iterator.hasNext:()Z
        //    49: ifeq            102
        //    52: aload           6
        //    54: invokeinterface java/util/Iterator.next:()Ljava/lang/Object;
        //    59: astore          element$iv
        //    61: aload           destination$iv
        //    63: astore          8
        //    65: aload_1         /* transform */
        //    66: aload           element$iv
        //    68: invokeinterface kotlin/jvm/functions/Function1.invoke:(Ljava/lang/Object;)Ljava/lang/Object;
        //    73: checkcast       Lkotlin/Pair;
        //    76: astore          9
        //    78: iconst_0       
        //    79: istore          10
        //    81: aload           8
        //    83: aload           9
        //    85: invokevirtual   kotlin/Pair.getFirst:()Ljava/lang/Object;
        //    88: aload           9
        //    90: invokevirtual   kotlin/Pair.getSecond:()Ljava/lang/Object;
        //    93: invokeinterface java/util/Map.put:(Ljava/lang/Object;Ljava/lang/Object;)Ljava/lang/Object;
        //    98: pop            
        //    99: goto            42
        //   102: aload           destination$iv
        //   104: areturn        
        //    Signature:
        //  <T:Ljava/lang/Object;K:Ljava/lang/Object;V:Ljava/lang/Object;>(Lkotlin/sequences/Sequence<+TT;>;Lkotlin/jvm/functions/Function1<-TT;+Lkotlin/Pair<+TK;+TV;>;>;)Ljava/util/Map<TK;TV;>;
        //    StackMapTable: 00 02 FF 00 2A 00 07 07 01 1D 07 01 0B 01 07 01 1D 07 02 4D 01 07 01 23 00 00 3B
        // 
        // The error that occurred was:
        // 
        // java.lang.NullPointerException
        // 
        throw new IllegalStateException("An error occurred while decompiling this method.");
    }
    
    @NotNull
    public static final <T, K> Map<K, T> associateBy(@NotNull final Sequence<? extends T> $this$associateBy, @NotNull final Function1<? super T, ? extends K> keySelector) {
        // 
        // This method could not be decompiled.
        // 
        // Original Bytecode:
        // 
        //     2: istore_2        /* $i$f$associateBy */
        //     3: aload_0         /* $this$associateBy */
        //     4: ldc_w           "$this$associateBy"
        //     7: invokestatic    kotlin/jvm/internal/Intrinsics.checkParameterIsNotNull:(Ljava/lang/Object;Ljava/lang/String;)V
        //    10: aload_1         /* keySelector */
        //    11: ldc_w           "keySelector"
        //    14: invokestatic    kotlin/jvm/internal/Intrinsics.checkParameterIsNotNull:(Ljava/lang/Object;Ljava/lang/String;)V
        //    17: aload_0         /* $this$associateBy */
        //    18: astore_3       
        //    19: new             Ljava/util/LinkedHashMap;
        //    22: dup            
        //    23: invokespecial   java/util/LinkedHashMap.<init>:()V
        //    26: checkcast       Ljava/util/Map;
        //    29: astore          destination$iv
        //    31: iconst_0       
        //    32: istore          $i$f$associateByTo
        //    34: aload_3         /* $this$associateByTo$iv */
        //    35: invokeinterface kotlin/sequences/Sequence.iterator:()Ljava/util/Iterator;
        //    40: astore          6
        //    42: aload           6
        //    44: invokeinterface java/util/Iterator.hasNext:()Z
        //    49: ifeq            82
        //    52: aload           6
        //    54: invokeinterface java/util/Iterator.next:()Ljava/lang/Object;
        //    59: astore          element$iv
        //    61: aload           destination$iv
        //    63: aload_1         /* keySelector */
        //    64: aload           element$iv
        //    66: invokeinterface kotlin/jvm/functions/Function1.invoke:(Ljava/lang/Object;)Ljava/lang/Object;
        //    71: aload           element$iv
        //    73: invokeinterface java/util/Map.put:(Ljava/lang/Object;Ljava/lang/Object;)Ljava/lang/Object;
        //    78: pop            
        //    79: goto            42
        //    82: aload           destination$iv
        //    84: areturn        
        //    Signature:
        //  <T:Ljava/lang/Object;K:Ljava/lang/Object;>(Lkotlin/sequences/Sequence<+TT;>;Lkotlin/jvm/functions/Function1<-TT;+TK;>;)Ljava/util/Map<TK;TT;>;
        //    StackMapTable: 00 02 FF 00 2A 00 07 07 01 1D 07 01 0B 01 07 01 1D 07 02 4D 01 07 01 23 00 00 27
        // 
        // The error that occurred was:
        // 
        // java.lang.NullPointerException
        // 
        throw new IllegalStateException("An error occurred while decompiling this method.");
    }
    
    @NotNull
    public static final <T, K, V> Map<K, V> associateBy(@NotNull final Sequence<? extends T> $this$associateBy, @NotNull final Function1<? super T, ? extends K> keySelector, @NotNull final Function1<? super T, ? extends V> valueTransform) {
        // 
        // This method could not be decompiled.
        // 
        // Original Bytecode:
        // 
        //     2: istore_3        /* $i$f$associateBy */
        //     3: aload_0         /* $this$associateBy */
        //     4: ldc_w           "$this$associateBy"
        //     7: invokestatic    kotlin/jvm/internal/Intrinsics.checkParameterIsNotNull:(Ljava/lang/Object;Ljava/lang/String;)V
        //    10: aload_1         /* keySelector */
        //    11: ldc_w           "keySelector"
        //    14: invokestatic    kotlin/jvm/internal/Intrinsics.checkParameterIsNotNull:(Ljava/lang/Object;Ljava/lang/String;)V
        //    17: aload_2         /* valueTransform */
        //    18: ldc_w           "valueTransform"
        //    21: invokestatic    kotlin/jvm/internal/Intrinsics.checkParameterIsNotNull:(Ljava/lang/Object;Ljava/lang/String;)V
        //    24: aload_0         /* $this$associateBy */
        //    25: astore          4
        //    27: new             Ljava/util/LinkedHashMap;
        //    30: dup            
        //    31: invokespecial   java/util/LinkedHashMap.<init>:()V
        //    34: checkcast       Ljava/util/Map;
        //    37: astore          destination$iv
        //    39: iconst_0       
        //    40: istore          $i$f$associateByTo
        //    42: aload           $this$associateByTo$iv
        //    44: invokeinterface kotlin/sequences/Sequence.iterator:()Ljava/util/Iterator;
        //    49: astore          7
        //    51: aload           7
        //    53: invokeinterface java/util/Iterator.hasNext:()Z
        //    58: ifeq            97
        //    61: aload           7
        //    63: invokeinterface java/util/Iterator.next:()Ljava/lang/Object;
        //    68: astore          element$iv
        //    70: aload           destination$iv
        //    72: aload_1         /* keySelector */
        //    73: aload           element$iv
        //    75: invokeinterface kotlin/jvm/functions/Function1.invoke:(Ljava/lang/Object;)Ljava/lang/Object;
        //    80: aload_2         /* valueTransform */
        //    81: aload           element$iv
        //    83: invokeinterface kotlin/jvm/functions/Function1.invoke:(Ljava/lang/Object;)Ljava/lang/Object;
        //    88: invokeinterface java/util/Map.put:(Ljava/lang/Object;Ljava/lang/Object;)Ljava/lang/Object;
        //    93: pop            
        //    94: goto            51
        //    97: aload           destination$iv
        //    99: areturn        
        //    Signature:
        //  <T:Ljava/lang/Object;K:Ljava/lang/Object;V:Ljava/lang/Object;>(Lkotlin/sequences/Sequence<+TT;>;Lkotlin/jvm/functions/Function1<-TT;+TK;>;Lkotlin/jvm/functions/Function1<-TT;+TV;>;)Ljava/util/Map<TK;TV;>;
        //    StackMapTable: 00 02 FF 00 33 00 08 07 01 1D 07 01 0B 07 01 0B 01 07 01 1D 07 02 4D 01 07 01 23 00 00 2D
        // 
        // The error that occurred was:
        // 
        // java.lang.NullPointerException
        // 
        throw new IllegalStateException("An error occurred while decompiling this method.");
    }
    
    @NotNull
    public static final <T, K, M extends Map<? super K, ? super T>> M associateByTo(@NotNull final Sequence<? extends T> $this$associateByTo, @NotNull final M destination, @NotNull final Function1<? super T, ? extends K> keySelector) {
        final int $i$f$associateByTo = 0;
        Intrinsics.checkParameterIsNotNull($this$associateByTo, "$this$associateByTo");
        Intrinsics.checkParameterIsNotNull(destination, "destination");
        Intrinsics.checkParameterIsNotNull(keySelector, "keySelector");
        for (final Object element : $this$associateByTo) {
            destination.put((Object)keySelector.invoke((Object)element), (Object)element);
        }
        return destination;
    }
    
    @NotNull
    public static final <T, K, V, M extends Map<? super K, ? super V>> M associateByTo(@NotNull final Sequence<? extends T> $this$associateByTo, @NotNull final M destination, @NotNull final Function1<? super T, ? extends K> keySelector, @NotNull final Function1<? super T, ? extends V> valueTransform) {
        final int $i$f$associateByTo = 0;
        Intrinsics.checkParameterIsNotNull($this$associateByTo, "$this$associateByTo");
        Intrinsics.checkParameterIsNotNull(destination, "destination");
        Intrinsics.checkParameterIsNotNull(keySelector, "keySelector");
        Intrinsics.checkParameterIsNotNull(valueTransform, "valueTransform");
        for (final Object element : $this$associateByTo) {
            destination.put((Object)keySelector.invoke((Object)element), (Object)valueTransform.invoke((Object)element));
        }
        return destination;
    }
    
    @NotNull
    public static final <T, K, V, M extends Map<? super K, ? super V>> M associateTo(@NotNull final Sequence<? extends T> $this$associateTo, @NotNull final M destination, @NotNull final Function1<? super T, ? extends Pair<? extends K, ? extends V>> transform) {
        final int $i$f$associateTo = 0;
        Intrinsics.checkParameterIsNotNull($this$associateTo, "$this$associateTo");
        Intrinsics.checkParameterIsNotNull(destination, "destination");
        Intrinsics.checkParameterIsNotNull(transform, "transform");
        for (final Object element : $this$associateTo) {
            final Pair pair = (Pair)transform.invoke((Object)element);
            destination.put(pair.getFirst(), (Object)pair.getSecond());
        }
        return destination;
    }
    
    @SinceKotlin(version = "1.3")
    @NotNull
    public static final <K, V> Map<K, V> associateWith(@NotNull final Sequence<? extends K> $this$associateWith, @NotNull final Function1<? super K, ? extends V> valueSelector) {
        final int $i$f$associateWith = 0;
        Intrinsics.checkParameterIsNotNull($this$associateWith, "$this$associateWith");
        Intrinsics.checkParameterIsNotNull(valueSelector, "valueSelector");
        final LinkedHashMap result = new LinkedHashMap();
        final Sequence $this$associateWithTo$iv = $this$associateWith;
        final int $i$f$associateWithTo = 0;
        for (final Object element$iv : $this$associateWithTo$iv) {
            result.put(element$iv, valueSelector.invoke((Object)element$iv));
        }
        return (Map<K, V>)result;
    }
    
    @SinceKotlin(version = "1.3")
    @NotNull
    public static final <K, V, M extends Map<? super K, ? super V>> M associateWithTo(@NotNull final Sequence<? extends K> $this$associateWithTo, @NotNull final M destination, @NotNull final Function1<? super K, ? extends V> valueSelector) {
        final int $i$f$associateWithTo = 0;
        Intrinsics.checkParameterIsNotNull($this$associateWithTo, "$this$associateWithTo");
        Intrinsics.checkParameterIsNotNull(destination, "destination");
        Intrinsics.checkParameterIsNotNull(valueSelector, "valueSelector");
        for (final Object element : $this$associateWithTo) {
            destination.put((Object)element, (Object)valueSelector.invoke((Object)element));
        }
        return destination;
    }
    
    @NotNull
    public static final <T, C extends Collection<? super T>> C toCollection(@NotNull final Sequence<? extends T> $this$toCollection, @NotNull final C destination) {
        Intrinsics.checkParameterIsNotNull($this$toCollection, "$this$toCollection");
        Intrinsics.checkParameterIsNotNull(destination, "destination");
        for (final Object item : $this$toCollection) {
            destination.add((Object)item);
        }
        return destination;
    }
    
    @NotNull
    public static final <T> HashSet<T> toHashSet(@NotNull final Sequence<? extends T> $this$toHashSet) {
        Intrinsics.checkParameterIsNotNull($this$toHashSet, "$this$toHashSet");
        return toCollection((Sequence<?>)$this$toHashSet, (HashSet<T>)new HashSet<T>());
    }
    
    @NotNull
    public static final <T> List<T> toList(@NotNull final Sequence<? extends T> $this$toList) {
        Intrinsics.checkParameterIsNotNull($this$toList, "$this$toList");
        return CollectionsKt__CollectionsKt.optimizeReadOnlyList(toMutableList((Sequence<? extends T>)$this$toList));
    }
    
    @NotNull
    public static final <T> List<T> toMutableList(@NotNull final Sequence<? extends T> $this$toMutableList) {
        Intrinsics.checkParameterIsNotNull($this$toMutableList, "$this$toMutableList");
        return toCollection((Sequence<?>)$this$toMutableList, (ArrayList<T>)new ArrayList<T>());
    }
    
    @NotNull
    public static final <T> Set<T> toSet(@NotNull final Sequence<? extends T> $this$toSet) {
        Intrinsics.checkParameterIsNotNull($this$toSet, "$this$toSet");
        return SetsKt__SetsKt.optimizeReadOnlySet((Set<? extends T>)toCollection((Sequence<?>)$this$toSet, (LinkedHashSet<? extends T>)new LinkedHashSet<Object>()));
    }
    
    @NotNull
    public static final <T, R> Sequence<R> flatMap(@NotNull final Sequence<? extends T> $this$flatMap, @NotNull final Function1<? super T, ? extends Sequence<? extends R>> transform) {
        Intrinsics.checkParameterIsNotNull($this$flatMap, "$this$flatMap");
        Intrinsics.checkParameterIsNotNull(transform, "transform");
        return new FlatteningSequence<Object, Object, R>($this$flatMap, transform, (Function1<?, ? extends Iterator<? extends R>>)SequencesKt___SequencesKt$flatMap.SequencesKt___SequencesKt$flatMap$1.INSTANCE);
    }
    
    @NotNull
    public static final <T, R, C extends Collection<? super R>> C flatMapTo(@NotNull final Sequence<? extends T> $this$flatMapTo, @NotNull final C destination, @NotNull final Function1<? super T, ? extends Sequence<? extends R>> transform) {
        final int $i$f$flatMapTo = 0;
        Intrinsics.checkParameterIsNotNull($this$flatMapTo, "$this$flatMapTo");
        Intrinsics.checkParameterIsNotNull(destination, "destination");
        Intrinsics.checkParameterIsNotNull(transform, "transform");
        for (final Object element : $this$flatMapTo) {
            final Sequence list = (Sequence)transform.invoke((Object)element);
            CollectionsKt__MutableCollectionsKt.addAll((Collection<? super Object>)destination, (Sequence<?>)list);
        }
        return destination;
    }
    
    @NotNull
    public static final <T, K> Map<K, List<T>> groupBy(@NotNull final Sequence<? extends T> $this$groupBy, @NotNull final Function1<? super T, ? extends K> keySelector) {
        // 
        // This method could not be decompiled.
        // 
        // Original Bytecode:
        // 
        //     2: istore_2        /* $i$f$groupBy */
        //     3: aload_0         /* $this$groupBy */
        //     4: ldc_w           "$this$groupBy"
        //     7: invokestatic    kotlin/jvm/internal/Intrinsics.checkParameterIsNotNull:(Ljava/lang/Object;Ljava/lang/String;)V
        //    10: aload_1         /* keySelector */
        //    11: ldc_w           "keySelector"
        //    14: invokestatic    kotlin/jvm/internal/Intrinsics.checkParameterIsNotNull:(Ljava/lang/Object;Ljava/lang/String;)V
        //    17: aload_0         /* $this$groupBy */
        //    18: astore_3       
        //    19: new             Ljava/util/LinkedHashMap;
        //    22: dup            
        //    23: invokespecial   java/util/LinkedHashMap.<init>:()V
        //    26: checkcast       Ljava/util/Map;
        //    29: astore          destination$iv
        //    31: iconst_0       
        //    32: istore          $i$f$groupByTo
        //    34: aload_3         /* $this$groupByTo$iv */
        //    35: invokeinterface kotlin/sequences/Sequence.iterator:()Ljava/util/Iterator;
        //    40: astore          6
        //    42: aload           6
        //    44: invokeinterface java/util/Iterator.hasNext:()Z
        //    49: ifeq            144
        //    52: aload           6
        //    54: invokeinterface java/util/Iterator.next:()Ljava/lang/Object;
        //    59: astore          element$iv
        //    61: aload_1         /* keySelector */
        //    62: aload           element$iv
        //    64: invokeinterface kotlin/jvm/functions/Function1.invoke:(Ljava/lang/Object;)Ljava/lang/Object;
        //    69: astore          key$iv
        //    71: aload           destination$iv
        //    73: astore          $this$getOrPut$iv$iv
        //    75: iconst_0       
        //    76: istore          $i$f$getOrPut
        //    78: aload           $this$getOrPut$iv$iv
        //    80: aload           key$iv
        //    82: invokeinterface java/util/Map.get:(Ljava/lang/Object;)Ljava/lang/Object;
        //    87: astore          value$iv$iv
        //    89: aload           value$iv$iv
        //    91: ifnonnull       123
        //    94: iconst_0       
        //    95: istore          $i$a$-getOrPut-SequencesKt___SequencesKt$groupByTo$list$1$iv
        //    97: new             Ljava/util/ArrayList;
        //   100: dup            
        //   101: invokespecial   java/util/ArrayList.<init>:()V
        //   104: astore          answer$iv$iv
        //   106: aload           $this$getOrPut$iv$iv
        //   108: aload           key$iv
        //   110: aload           answer$iv$iv
        //   112: invokeinterface java/util/Map.put:(Ljava/lang/Object;Ljava/lang/Object;)Ljava/lang/Object;
        //   117: pop            
        //   118: aload           answer$iv$iv
        //   120: goto            125
        //   123: aload           value$iv$iv
        //   125: nop            
        //   126: checkcast       Ljava/util/List;
        //   129: astore          list$iv
        //   131: aload           list$iv
        //   133: aload           element$iv
        //   135: invokeinterface java/util/List.add:(Ljava/lang/Object;)Z
        //   140: pop            
        //   141: goto            42
        //   144: aload           destination$iv
        //   146: areturn        
        //    Signature:
        //  <T:Ljava/lang/Object;K:Ljava/lang/Object;>(Lkotlin/sequences/Sequence<+TT;>;Lkotlin/jvm/functions/Function1<-TT;+TK;>;)Ljava/util/Map<TK;Ljava/util/List<TT;>;>;
        //    StackMapTable: 00 04 FF 00 2A 00 07 07 01 1D 07 01 0B 01 07 01 1D 07 02 4D 01 07 01 23 00 00 FF 00 50 00 0C 07 01 1D 07 01 0B 01 07 01 1D 07 02 4D 01 07 01 23 07 01 2D 07 01 2D 07 02 4D 01 07 01 2D 00 00 41 07 01 2D FF 00 12 00 07 07 01 1D 07 01 0B 01 07 01 1D 07 02 4D 01 07 01 23 00 00
        // 
        // The error that occurred was:
        // 
        // java.lang.NullPointerException
        // 
        throw new IllegalStateException("An error occurred while decompiling this method.");
    }
    
    @NotNull
    public static final <T, K, V> Map<K, List<V>> groupBy(@NotNull final Sequence<? extends T> $this$groupBy, @NotNull final Function1<? super T, ? extends K> keySelector, @NotNull final Function1<? super T, ? extends V> valueTransform) {
        // 
        // This method could not be decompiled.
        // 
        // Original Bytecode:
        // 
        //     2: istore_3        /* $i$f$groupBy */
        //     3: aload_0         /* $this$groupBy */
        //     4: ldc_w           "$this$groupBy"
        //     7: invokestatic    kotlin/jvm/internal/Intrinsics.checkParameterIsNotNull:(Ljava/lang/Object;Ljava/lang/String;)V
        //    10: aload_1         /* keySelector */
        //    11: ldc_w           "keySelector"
        //    14: invokestatic    kotlin/jvm/internal/Intrinsics.checkParameterIsNotNull:(Ljava/lang/Object;Ljava/lang/String;)V
        //    17: aload_2         /* valueTransform */
        //    18: ldc_w           "valueTransform"
        //    21: invokestatic    kotlin/jvm/internal/Intrinsics.checkParameterIsNotNull:(Ljava/lang/Object;Ljava/lang/String;)V
        //    24: aload_0         /* $this$groupBy */
        //    25: astore          4
        //    27: new             Ljava/util/LinkedHashMap;
        //    30: dup            
        //    31: invokespecial   java/util/LinkedHashMap.<init>:()V
        //    34: checkcast       Ljava/util/Map;
        //    37: astore          destination$iv
        //    39: iconst_0       
        //    40: istore          $i$f$groupByTo
        //    42: aload           $this$groupByTo$iv
        //    44: invokeinterface kotlin/sequences/Sequence.iterator:()Ljava/util/Iterator;
        //    49: astore          7
        //    51: aload           7
        //    53: invokeinterface java/util/Iterator.hasNext:()Z
        //    58: ifeq            159
        //    61: aload           7
        //    63: invokeinterface java/util/Iterator.next:()Ljava/lang/Object;
        //    68: astore          element$iv
        //    70: aload_1         /* keySelector */
        //    71: aload           element$iv
        //    73: invokeinterface kotlin/jvm/functions/Function1.invoke:(Ljava/lang/Object;)Ljava/lang/Object;
        //    78: astore          key$iv
        //    80: aload           destination$iv
        //    82: astore          $this$getOrPut$iv$iv
        //    84: iconst_0       
        //    85: istore          $i$f$getOrPut
        //    87: aload           $this$getOrPut$iv$iv
        //    89: aload           key$iv
        //    91: invokeinterface java/util/Map.get:(Ljava/lang/Object;)Ljava/lang/Object;
        //    96: astore          value$iv$iv
        //    98: aload           value$iv$iv
        //   100: ifnonnull       132
        //   103: iconst_0       
        //   104: istore          $i$a$-getOrPut-SequencesKt___SequencesKt$groupByTo$list$2$iv
        //   106: new             Ljava/util/ArrayList;
        //   109: dup            
        //   110: invokespecial   java/util/ArrayList.<init>:()V
        //   113: astore          answer$iv$iv
        //   115: aload           $this$getOrPut$iv$iv
        //   117: aload           key$iv
        //   119: aload           answer$iv$iv
        //   121: invokeinterface java/util/Map.put:(Ljava/lang/Object;Ljava/lang/Object;)Ljava/lang/Object;
        //   126: pop            
        //   127: aload           answer$iv$iv
        //   129: goto            134
        //   132: aload           value$iv$iv
        //   134: nop            
        //   135: checkcast       Ljava/util/List;
        //   138: astore          list$iv
        //   140: aload           list$iv
        //   142: aload_2         /* valueTransform */
        //   143: aload           element$iv
        //   145: invokeinterface kotlin/jvm/functions/Function1.invoke:(Ljava/lang/Object;)Ljava/lang/Object;
        //   150: invokeinterface java/util/List.add:(Ljava/lang/Object;)Z
        //   155: pop            
        //   156: goto            51
        //   159: aload           destination$iv
        //   161: areturn        
        //    Signature:
        //  <T:Ljava/lang/Object;K:Ljava/lang/Object;V:Ljava/lang/Object;>(Lkotlin/sequences/Sequence<+TT;>;Lkotlin/jvm/functions/Function1<-TT;+TK;>;Lkotlin/jvm/functions/Function1<-TT;+TV;>;)Ljava/util/Map<TK;Ljava/util/List<TV;>;>;
        //    StackMapTable: 00 04 FF 00 33 00 08 07 01 1D 07 01 0B 07 01 0B 01 07 01 1D 07 02 4D 01 07 01 23 00 00 FF 00 50 00 0D 07 01 1D 07 01 0B 07 01 0B 01 07 01 1D 07 02 4D 01 07 01 23 07 01 2D 07 01 2D 07 02 4D 01 07 01 2D 00 00 41 07 01 2D FF 00 18 00 08 07 01 1D 07 01 0B 07 01 0B 01 07 01 1D 07 02 4D 01 07 01 23 00 00
        // 
        // The error that occurred was:
        // 
        // java.lang.NullPointerException
        // 
        throw new IllegalStateException("An error occurred while decompiling this method.");
    }
    
    @NotNull
    public static final <T, K, M extends Map<? super K, List<T>>> M groupByTo(@NotNull final Sequence<? extends T> $this$groupByTo, @NotNull final M destination, @NotNull final Function1<? super T, ? extends K> keySelector) {
        final int $i$f$groupByTo = 0;
        Intrinsics.checkParameterIsNotNull($this$groupByTo, "$this$groupByTo");
        Intrinsics.checkParameterIsNotNull(destination, "destination");
        Intrinsics.checkParameterIsNotNull(keySelector, "keySelector");
        for (final Object element : $this$groupByTo) {
            final Object key = keySelector.invoke((Object)element);
            final Map $this$getOrPut$iv = destination;
            final int $i$f$getOrPut = 0;
            final Object value$iv = $this$getOrPut$iv.get(key);
            Object o;
            if (value$iv == null) {
                final int n = 0;
                final Object answer$iv = new ArrayList();
                $this$getOrPut$iv.put(key, answer$iv);
                o = answer$iv;
            }
            else {
                o = value$iv;
            }
            final List list = (List)o;
            list.add(element);
        }
        return destination;
    }
    
    @NotNull
    public static final <T, K, V, M extends Map<? super K, List<V>>> M groupByTo(@NotNull final Sequence<? extends T> $this$groupByTo, @NotNull final M destination, @NotNull final Function1<? super T, ? extends K> keySelector, @NotNull final Function1<? super T, ? extends V> valueTransform) {
        final int $i$f$groupByTo = 0;
        Intrinsics.checkParameterIsNotNull($this$groupByTo, "$this$groupByTo");
        Intrinsics.checkParameterIsNotNull(destination, "destination");
        Intrinsics.checkParameterIsNotNull(keySelector, "keySelector");
        Intrinsics.checkParameterIsNotNull(valueTransform, "valueTransform");
        for (final Object element : $this$groupByTo) {
            final Object key = keySelector.invoke((Object)element);
            final Map $this$getOrPut$iv = destination;
            final int $i$f$getOrPut = 0;
            final Object value$iv = $this$getOrPut$iv.get(key);
            Object o;
            if (value$iv == null) {
                final int n = 0;
                final Object answer$iv = new ArrayList();
                $this$getOrPut$iv.put(key, answer$iv);
                o = answer$iv;
            }
            else {
                o = value$iv;
            }
            final List list = (List)o;
            list.add(valueTransform.invoke((Object)element));
        }
        return destination;
    }
    
    @SinceKotlin(version = "1.1")
    @NotNull
    public static final <T, K> Grouping<T, K> groupingBy(@NotNull final Sequence<? extends T> $this$groupingBy, @NotNull final Function1<? super T, ? extends K> keySelector) {
        final int $i$f$groupingBy = 0;
        Intrinsics.checkParameterIsNotNull($this$groupingBy, "$this$groupingBy");
        Intrinsics.checkParameterIsNotNull(keySelector, "keySelector");
        return (Grouping<T, K>)new SequencesKt___SequencesKt$groupingBy.SequencesKt___SequencesKt$groupingBy$1((Sequence)$this$groupingBy, (Function1)keySelector);
    }
    
    @NotNull
    public static final <T, R> Sequence<R> map(@NotNull final Sequence<? extends T> $this$map, @NotNull final Function1<? super T, ? extends R> transform) {
        Intrinsics.checkParameterIsNotNull($this$map, "$this$map");
        Intrinsics.checkParameterIsNotNull(transform, "transform");
        return new TransformingSequence<Object, R>($this$map, transform);
    }
    
    @NotNull
    public static final <T, R> Sequence<R> mapIndexed(@NotNull final Sequence<? extends T> $this$mapIndexed, @NotNull final Function2<? super Integer, ? super T, ? extends R> transform) {
        Intrinsics.checkParameterIsNotNull($this$mapIndexed, "$this$mapIndexed");
        Intrinsics.checkParameterIsNotNull(transform, "transform");
        return new TransformingIndexedSequence<Object, R>($this$mapIndexed, transform);
    }
    
    @NotNull
    public static final <T, R> Sequence<R> mapIndexedNotNull(@NotNull final Sequence<? extends T> $this$mapIndexedNotNull, @NotNull final Function2<? super Integer, ? super T, ? extends R> transform) {
        Intrinsics.checkParameterIsNotNull($this$mapIndexedNotNull, "$this$mapIndexedNotNull");
        Intrinsics.checkParameterIsNotNull(transform, "transform");
        return filterNotNull((Sequence<? extends R>)new TransformingIndexedSequence<Object, Object>($this$mapIndexedNotNull, (Function2<? super Integer, ? super Object, ?>)transform));
    }
    
    @NotNull
    public static final <T, R, C extends Collection<? super R>> C mapIndexedNotNullTo(@NotNull final Sequence<? extends T> $this$mapIndexedNotNullTo, @NotNull final C destination, @NotNull final Function2<? super Integer, ? super T, ? extends R> transform) {
        // 
        // This method could not be decompiled.
        // 
        // Original Bytecode:
        // 
        //     2: istore_3        /* $i$f$mapIndexedNotNullTo */
        //     3: aload_0         /* $this$mapIndexedNotNullTo */
        //     4: ldc_w           "$this$mapIndexedNotNullTo"
        //     7: invokestatic    kotlin/jvm/internal/Intrinsics.checkParameterIsNotNull:(Ljava/lang/Object;Ljava/lang/String;)V
        //    10: aload_1         /* destination */
        //    11: ldc_w           "destination"
        //    14: invokestatic    kotlin/jvm/internal/Intrinsics.checkParameterIsNotNull:(Ljava/lang/Object;Ljava/lang/String;)V
        //    17: aload_2         /* transform */
        //    18: ldc_w           "transform"
        //    21: invokestatic    kotlin/jvm/internal/Intrinsics.checkParameterIsNotNull:(Ljava/lang/Object;Ljava/lang/String;)V
        //    24: aload_0         /* $this$mapIndexedNotNullTo */
        //    25: astore          $this$forEachIndexed$iv
        //    27: iconst_0       
        //    28: istore          $i$f$forEachIndexed
        //    30: iconst_0       
        //    31: istore          index$iv
        //    33: aload           $this$forEachIndexed$iv
        //    35: invokeinterface kotlin/sequences/Sequence.iterator:()Ljava/util/Iterator;
        //    40: astore          7
        //    42: aload           7
        //    44: invokeinterface java/util/Iterator.hasNext:()Z
        //    49: ifeq            169
        //    52: aload           7
        //    54: invokeinterface java/util/Iterator.next:()Ljava/lang/Object;
        //    59: astore          item$iv
        //    61: iload           index$iv
        //    63: iinc            index$iv, 1
        //    66: istore          9
        //    68: iconst_0       
        //    69: istore          10
        //    71: iload           9
        //    73: ifge            105
        //    76: iconst_1       
        //    77: iconst_3       
        //    78: iconst_0       
        //    79: invokestatic    kotlin/internal/PlatformImplementationsKt.apiVersionIsAtLeast:(III)Z
        //    82: ifeq            91
        //    85: invokestatic    kotlin/collections/CollectionsKt.throwIndexOverflow:()V
        //    88: goto            105
        //    91: new             Ljava/lang/ArithmeticException;
        //    94: dup            
        //    95: ldc_w           "Index overflow has happened."
        //    98: invokespecial   java/lang/ArithmeticException.<init>:(Ljava/lang/String;)V
        //   101: checkcast       Ljava/lang/Throwable;
        //   104: athrow         
        //   105: iload           9
        //   107: istore          11
        //   109: iload           11
        //   111: aload           item$iv
        //   113: astore          12
        //   115: istore          index
        //   117: iconst_0       
        //   118: istore          $i$a$-forEachIndexed-SequencesKt___SequencesKt$mapIndexedNotNullTo$1
        //   120: aload_2         /* transform */
        //   121: iload           index
        //   123: invokestatic    java/lang/Integer.valueOf:(I)Ljava/lang/Integer;
        //   126: aload           element
        //   128: invokeinterface kotlin/jvm/functions/Function2.invoke:(Ljava/lang/Object;Ljava/lang/Object;)Ljava/lang/Object;
        //   133: dup            
        //   134: ifnull          164
        //   137: astore          15
        //   139: iconst_0       
        //   140: istore          16
        //   142: iconst_0       
        //   143: istore          17
        //   145: aload           15
        //   147: astore          it
        //   149: iconst_0       
        //   150: istore          $i$a$-let-SequencesKt___SequencesKt$mapIndexedNotNullTo$1$1
        //   152: aload_1         /* destination */
        //   153: aload           it
        //   155: invokeinterface java/util/Collection.add:(Ljava/lang/Object;)Z
        //   160: pop            
        //   161: goto            165
        //   164: pop            
        //   165: nop            
        //   166: goto            42
        //   169: nop            
        //   170: aload_1         /* destination */
        //   171: areturn        
        //    Signature:
        //  <T:Ljava/lang/Object;R:Ljava/lang/Object;C::Ljava/util/Collection<-TR;>;>(Lkotlin/sequences/Sequence<+TT;>;TC;Lkotlin/jvm/functions/Function2<-Ljava/lang/Integer;-TT;+TR;>;)TC;
        //    StackMapTable: 00 06 FF 00 2A 00 08 07 01 1D 07 01 D2 07 01 D4 01 07 01 1D 01 01 07 01 23 00 00 FE 00 30 07 01 2D 01 01 0D FF 00 3A 00 0F 07 01 1D 07 01 D2 07 01 D4 01 07 01 1D 01 01 07 01 23 07 01 2D 01 01 01 07 01 2D 01 01 00 01 07 01 2D 00 FF 00 03 00 08 07 01 1D 07 01 D2 07 01 D4 01 07 01 1D 01 01 07 01 23 00 00
        // 
        // The error that occurred was:
        // 
        // java.lang.NullPointerException
        // 
        throw new IllegalStateException("An error occurred while decompiling this method.");
    }
    
    @NotNull
    public static final <T, R, C extends Collection<? super R>> C mapIndexedTo(@NotNull final Sequence<? extends T> $this$mapIndexedTo, @NotNull final C destination, @NotNull final Function2<? super Integer, ? super T, ? extends R> transform) {
        final int $i$f$mapIndexedTo = 0;
        Intrinsics.checkParameterIsNotNull($this$mapIndexedTo, "$this$mapIndexedTo");
        Intrinsics.checkParameterIsNotNull(destination, "destination");
        Intrinsics.checkParameterIsNotNull(transform, "transform");
        int index = 0;
        for (final Object item : $this$mapIndexedTo) {
            final int i = index++;
            if (i < 0) {
                if (!PlatformImplementationsKt.apiVersionIsAtLeast(1, 3, 0)) {
                    throw new ArithmeticException("Index overflow has happened.");
                }
                CollectionsKt.throwIndexOverflow();
            }
            destination.add((Object)transform.invoke(Integer.valueOf(i), (Object)item));
        }
        return destination;
    }
    
    @NotNull
    public static final <T, R> Sequence<R> mapNotNull(@NotNull final Sequence<? extends T> $this$mapNotNull, @NotNull final Function1<? super T, ? extends R> transform) {
        Intrinsics.checkParameterIsNotNull($this$mapNotNull, "$this$mapNotNull");
        Intrinsics.checkParameterIsNotNull(transform, "transform");
        return filterNotNull((Sequence<? extends R>)new TransformingSequence<Object, Object>($this$mapNotNull, (Function1<? super Object, ?>)transform));
    }
    
    @NotNull
    public static final <T, R, C extends Collection<? super R>> C mapNotNullTo(@NotNull final Sequence<? extends T> $this$mapNotNullTo, @NotNull final C destination, @NotNull final Function1<? super T, ? extends R> transform) {
        final int $i$f$mapNotNullTo = 0;
        Intrinsics.checkParameterIsNotNull($this$mapNotNullTo, "$this$mapNotNullTo");
        Intrinsics.checkParameterIsNotNull(destination, "destination");
        Intrinsics.checkParameterIsNotNull(transform, "transform");
        final Sequence $this$forEach$iv = $this$mapNotNullTo;
        final int $i$f$forEach = 0;
        for (final Object element : $this$forEach$iv) {
            final Object element$iv = element;
            final int n = 0;
            final R invoke = (R)transform.invoke((Object)element);
            if (invoke != null) {
                final Object it = invoke;
                final int n2 = 0;
                destination.add((Object)it);
            }
        }
        return destination;
    }
    
    @NotNull
    public static final <T, R, C extends Collection<? super R>> C mapTo(@NotNull final Sequence<? extends T> $this$mapTo, @NotNull final C destination, @NotNull final Function1<? super T, ? extends R> transform) {
        final int $i$f$mapTo = 0;
        Intrinsics.checkParameterIsNotNull($this$mapTo, "$this$mapTo");
        Intrinsics.checkParameterIsNotNull(destination, "destination");
        Intrinsics.checkParameterIsNotNull(transform, "transform");
        for (final Object item : $this$mapTo) {
            destination.add((Object)transform.invoke((Object)item));
        }
        return destination;
    }
    
    @NotNull
    public static final <T> Sequence<IndexedValue<T>> withIndex(@NotNull final Sequence<? extends T> $this$withIndex) {
        Intrinsics.checkParameterIsNotNull($this$withIndex, "$this$withIndex");
        return (Sequence<IndexedValue<T>>)new IndexingSequence($this$withIndex);
    }
    
    @NotNull
    public static final <T> Sequence<T> distinct(@NotNull final Sequence<? extends T> $this$distinct) {
        Intrinsics.checkParameterIsNotNull($this$distinct, "$this$distinct");
        return distinctBy($this$distinct, (Function1<? super T, ?>)SequencesKt___SequencesKt$distinct.SequencesKt___SequencesKt$distinct$1.INSTANCE);
    }
    
    @NotNull
    public static final <T, K> Sequence<T> distinctBy(@NotNull final Sequence<? extends T> $this$distinctBy, @NotNull final Function1<? super T, ? extends K> selector) {
        Intrinsics.checkParameterIsNotNull($this$distinctBy, "$this$distinctBy");
        Intrinsics.checkParameterIsNotNull(selector, "selector");
        return new DistinctSequence<T, Object>($this$distinctBy, selector);
    }
    
    @NotNull
    public static final <T> Set<T> toMutableSet(@NotNull final Sequence<? extends T> $this$toMutableSet) {
        Intrinsics.checkParameterIsNotNull($this$toMutableSet, "$this$toMutableSet");
        final LinkedHashSet set = new LinkedHashSet();
        for (final Object item : $this$toMutableSet) {
            set.add(item);
        }
        return (Set<T>)set;
    }
    
    public static final <T> boolean all(@NotNull final Sequence<? extends T> $this$all, @NotNull final Function1<? super T, Boolean> predicate) {
        final int $i$f$all = 0;
        Intrinsics.checkParameterIsNotNull($this$all, "$this$all");
        Intrinsics.checkParameterIsNotNull(predicate, "predicate");
        for (final Object element : $this$all) {
            if (!predicate.invoke((Object)element)) {
                return false;
            }
        }
        return true;
    }
    
    public static final <T> boolean any(@NotNull final Sequence<? extends T> $this$any) {
        Intrinsics.checkParameterIsNotNull($this$any, "$this$any");
        return $this$any.iterator().hasNext();
    }
    
    public static final <T> boolean any(@NotNull final Sequence<? extends T> $this$any, @NotNull final Function1<? super T, Boolean> predicate) {
        final int $i$f$any = 0;
        Intrinsics.checkParameterIsNotNull($this$any, "$this$any");
        Intrinsics.checkParameterIsNotNull(predicate, "predicate");
        for (final Object element : $this$any) {
            if (predicate.invoke((Object)element)) {
                return true;
            }
        }
        return false;
    }
    
    public static final <T> int count(@NotNull final Sequence<? extends T> $this$count) {
        Intrinsics.checkParameterIsNotNull($this$count, "$this$count");
        int count = 0;
        for (final Object element : $this$count) {
            if (++count < 0) {
                CollectionsKt.throwCountOverflow();
            }
        }
        return count;
    }
    
    public static final <T> int count(@NotNull final Sequence<? extends T> $this$count, @NotNull final Function1<? super T, Boolean> predicate) {
        final int $i$f$count = 0;
        Intrinsics.checkParameterIsNotNull($this$count, "$this$count");
        Intrinsics.checkParameterIsNotNull(predicate, "predicate");
        int count = 0;
        for (final Object element : $this$count) {
            if (predicate.invoke((Object)element) && ++count < 0) {
                if (!PlatformImplementationsKt.apiVersionIsAtLeast(1, 3, 0)) {
                    throw new ArithmeticException("Count overflow has happened.");
                }
                CollectionsKt.throwCountOverflow();
            }
        }
        return count;
    }
    
    public static final <T, R> R fold(@NotNull final Sequence<? extends T> $this$fold, final R initial, @NotNull final Function2<? super R, ? super T, ? extends R> operation) {
        final int $i$f$fold = 0;
        Intrinsics.checkParameterIsNotNull($this$fold, "$this$fold");
        Intrinsics.checkParameterIsNotNull(operation, "operation");
        Object accumulator = initial;
        for (final Object element : $this$fold) {
            accumulator = operation.invoke((Object)accumulator, (Object)element);
        }
        return (R)accumulator;
    }
    
    public static final <T, R> R foldIndexed(@NotNull final Sequence<? extends T> $this$foldIndexed, final R initial, @NotNull final Function3<? super Integer, ? super R, ? super T, ? extends R> operation) {
        final int $i$f$foldIndexed = 0;
        Intrinsics.checkParameterIsNotNull($this$foldIndexed, "$this$foldIndexed");
        Intrinsics.checkParameterIsNotNull(operation, "operation");
        int index = 0;
        Object accumulator = initial;
        for (final Object element : $this$foldIndexed) {
            final int i = index++;
            if (i < 0) {
                if (!PlatformImplementationsKt.apiVersionIsAtLeast(1, 3, 0)) {
                    throw new ArithmeticException("Index overflow has happened.");
                }
                CollectionsKt.throwIndexOverflow();
            }
            accumulator = operation.invoke(Integer.valueOf(i), (Object)accumulator, (Object)element);
        }
        return (R)accumulator;
    }
    
    public static final <T> void forEach(@NotNull final Sequence<? extends T> $this$forEach, @NotNull final Function1<? super T, Unit> action) {
        final int $i$f$forEach = 0;
        Intrinsics.checkParameterIsNotNull($this$forEach, "$this$forEach");
        Intrinsics.checkParameterIsNotNull(action, "action");
        for (final Object element : $this$forEach) {
            action.invoke((Object)element);
        }
    }
    
    public static final <T> void forEachIndexed(@NotNull final Sequence<? extends T> $this$forEachIndexed, @NotNull final Function2<? super Integer, ? super T, Unit> action) {
        final int $i$f$forEachIndexed = 0;
        Intrinsics.checkParameterIsNotNull($this$forEachIndexed, "$this$forEachIndexed");
        Intrinsics.checkParameterIsNotNull(action, "action");
        int index = 0;
        for (final Object item : $this$forEachIndexed) {
            final int i = index++;
            if (i < 0) {
                if (!PlatformImplementationsKt.apiVersionIsAtLeast(1, 3, 0)) {
                    throw new ArithmeticException("Index overflow has happened.");
                }
                CollectionsKt.throwIndexOverflow();
            }
            action.invoke(Integer.valueOf(i), (Object)item);
        }
    }
    
    @SinceKotlin(version = "1.1")
    @Nullable
    public static final Double max(@NotNull final Sequence<Double> $this$max) {
        Intrinsics.checkParameterIsNotNull($this$max, "$this$max");
        final Iterator iterator = $this$max.iterator();
        if (!iterator.hasNext()) {
            return null;
        }
        double max = iterator.next().doubleValue();
        if (Double.isNaN(max)) {
            return max;
        }
        while (iterator.hasNext()) {
            final double e = iterator.next().doubleValue();
            if (Double.isNaN(e)) {
                return e;
            }
            if (max >= e) {
                continue;
            }
            max = e;
        }
        return max;
    }
    
    @SinceKotlin(version = "1.1")
    @Nullable
    public static final Float max(@NotNull final Sequence<Float> $this$max) {
        Intrinsics.checkParameterIsNotNull($this$max, "$this$max");
        final Iterator iterator = $this$max.iterator();
        if (!iterator.hasNext()) {
            return null;
        }
        float max = iterator.next().floatValue();
        if (Float.isNaN(max)) {
            return max;
        }
        while (iterator.hasNext()) {
            final float e = iterator.next().floatValue();
            if (Float.isNaN(e)) {
                return e;
            }
            if (max >= e) {
                continue;
            }
            max = e;
        }
        return max;
    }
    
    @Nullable
    public static final <T extends Comparable<? super T>> T max(@NotNull final Sequence<? extends T> $this$max) {
        Intrinsics.checkParameterIsNotNull($this$max, "$this$max");
        final Iterator iterator = $this$max.iterator();
        if (!iterator.hasNext()) {
            return null;
        }
        Comparable max = iterator.next();
        while (iterator.hasNext()) {
            final Comparable e = iterator.next();
            if (max.compareTo(e) < 0) {
                max = e;
            }
        }
        return (T)max;
    }
    
    @Nullable
    public static final <T, R extends Comparable<? super R>> T maxBy(@NotNull final Sequence<? extends T> $this$maxBy, @NotNull final Function1<? super T, ? extends R> selector) {
        final int $i$f$maxBy = 0;
        Intrinsics.checkParameterIsNotNull($this$maxBy, "$this$maxBy");
        Intrinsics.checkParameterIsNotNull(selector, "selector");
        final Iterator iterator = $this$maxBy.iterator();
        if (!iterator.hasNext()) {
            return null;
        }
        Object maxElem = iterator.next();
        if (!iterator.hasNext()) {
            return (T)maxElem;
        }
        Comparable maxValue = (Comparable)selector.invoke((Object)maxElem);
        do {
            final Object e = iterator.next();
            final Comparable v = (Comparable)selector.invoke((Object)e);
            if (maxValue.compareTo(v) < 0) {
                maxElem = e;
                maxValue = v;
            }
        } while (iterator.hasNext());
        return (T)maxElem;
    }
    
    @Nullable
    public static final <T> T maxWith(@NotNull final Sequence<? extends T> $this$maxWith, @NotNull final Comparator<? super T> comparator) {
        Intrinsics.checkParameterIsNotNull($this$maxWith, "$this$maxWith");
        Intrinsics.checkParameterIsNotNull(comparator, "comparator");
        final Iterator iterator = $this$maxWith.iterator();
        if (!iterator.hasNext()) {
            return null;
        }
        Object max = iterator.next();
        while (iterator.hasNext()) {
            final Object e = iterator.next();
            if (comparator.compare((Object)max, (Object)e) < 0) {
                max = e;
            }
        }
        return (T)max;
    }
    
    @SinceKotlin(version = "1.1")
    @Nullable
    public static final Double min(@NotNull final Sequence<Double> $this$min) {
        Intrinsics.checkParameterIsNotNull($this$min, "$this$min");
        final Iterator iterator = $this$min.iterator();
        if (!iterator.hasNext()) {
            return null;
        }
        double min = iterator.next().doubleValue();
        if (Double.isNaN(min)) {
            return min;
        }
        while (iterator.hasNext()) {
            final double e = iterator.next().doubleValue();
            if (Double.isNaN(e)) {
                return e;
            }
            if (min <= e) {
                continue;
            }
            min = e;
        }
        return min;
    }
    
    @SinceKotlin(version = "1.1")
    @Nullable
    public static final Float min(@NotNull final Sequence<Float> $this$min) {
        Intrinsics.checkParameterIsNotNull($this$min, "$this$min");
        final Iterator iterator = $this$min.iterator();
        if (!iterator.hasNext()) {
            return null;
        }
        float min = iterator.next().floatValue();
        if (Float.isNaN(min)) {
            return min;
        }
        while (iterator.hasNext()) {
            final float e = iterator.next().floatValue();
            if (Float.isNaN(e)) {
                return e;
            }
            if (min <= e) {
                continue;
            }
            min = e;
        }
        return min;
    }
    
    @Nullable
    public static final <T extends Comparable<? super T>> T min(@NotNull final Sequence<? extends T> $this$min) {
        Intrinsics.checkParameterIsNotNull($this$min, "$this$min");
        final Iterator iterator = $this$min.iterator();
        if (!iterator.hasNext()) {
            return null;
        }
        Comparable min = iterator.next();
        while (iterator.hasNext()) {
            final Comparable e = iterator.next();
            if (min.compareTo(e) > 0) {
                min = e;
            }
        }
        return (T)min;
    }
    
    @Nullable
    public static final <T, R extends Comparable<? super R>> T minBy(@NotNull final Sequence<? extends T> $this$minBy, @NotNull final Function1<? super T, ? extends R> selector) {
        final int $i$f$minBy = 0;
        Intrinsics.checkParameterIsNotNull($this$minBy, "$this$minBy");
        Intrinsics.checkParameterIsNotNull(selector, "selector");
        final Iterator iterator = $this$minBy.iterator();
        if (!iterator.hasNext()) {
            return null;
        }
        Object minElem = iterator.next();
        if (!iterator.hasNext()) {
            return (T)minElem;
        }
        Comparable minValue = (Comparable)selector.invoke((Object)minElem);
        do {
            final Object e = iterator.next();
            final Comparable v = (Comparable)selector.invoke((Object)e);
            if (minValue.compareTo(v) > 0) {
                minElem = e;
                minValue = v;
            }
        } while (iterator.hasNext());
        return (T)minElem;
    }
    
    @Nullable
    public static final <T> T minWith(@NotNull final Sequence<? extends T> $this$minWith, @NotNull final Comparator<? super T> comparator) {
        Intrinsics.checkParameterIsNotNull($this$minWith, "$this$minWith");
        Intrinsics.checkParameterIsNotNull(comparator, "comparator");
        final Iterator iterator = $this$minWith.iterator();
        if (!iterator.hasNext()) {
            return null;
        }
        Object min = iterator.next();
        while (iterator.hasNext()) {
            final Object e = iterator.next();
            if (comparator.compare((Object)min, (Object)e) > 0) {
                min = e;
            }
        }
        return (T)min;
    }
    
    public static final <T> boolean none(@NotNull final Sequence<? extends T> $this$none) {
        Intrinsics.checkParameterIsNotNull($this$none, "$this$none");
        return !$this$none.iterator().hasNext();
    }
    
    public static final <T> boolean none(@NotNull final Sequence<? extends T> $this$none, @NotNull final Function1<? super T, Boolean> predicate) {
        final int $i$f$none = 0;
        Intrinsics.checkParameterIsNotNull($this$none, "$this$none");
        Intrinsics.checkParameterIsNotNull(predicate, "predicate");
        for (final Object element : $this$none) {
            if (predicate.invoke((Object)element)) {
                return false;
            }
        }
        return true;
    }
    
    @SinceKotlin(version = "1.1")
    @NotNull
    public static final <T> Sequence<T> onEach(@NotNull final Sequence<? extends T> $this$onEach, @NotNull final Function1<? super T, Unit> action) {
        Intrinsics.checkParameterIsNotNull($this$onEach, "$this$onEach");
        Intrinsics.checkParameterIsNotNull(action, "action");
        return map((Sequence<?>)$this$onEach, (Function1<? super Object, ? extends T>)new SequencesKt___SequencesKt$onEach.SequencesKt___SequencesKt$onEach$1((Function1)action));
    }
    
    public static final <S, T extends S> S reduce(@NotNull final Sequence<? extends T> $this$reduce, @NotNull final Function2<? super S, ? super T, ? extends S> operation) {
        final int $i$f$reduce = 0;
        Intrinsics.checkParameterIsNotNull($this$reduce, "$this$reduce");
        Intrinsics.checkParameterIsNotNull(operation, "operation");
        final Iterator iterator = $this$reduce.iterator();
        if (!iterator.hasNext()) {
            throw new UnsupportedOperationException("Empty sequence can't be reduced.");
        }
        Object accumulator = iterator.next();
        while (iterator.hasNext()) {
            accumulator = operation.invoke((Object)accumulator, iterator.next());
        }
        return (S)accumulator;
    }
    
    public static final <S, T extends S> S reduceIndexed(@NotNull final Sequence<? extends T> $this$reduceIndexed, @NotNull final Function3<? super Integer, ? super S, ? super T, ? extends S> operation) {
        final int $i$f$reduceIndexed = 0;
        Intrinsics.checkParameterIsNotNull($this$reduceIndexed, "$this$reduceIndexed");
        Intrinsics.checkParameterIsNotNull(operation, "operation");
        final Iterator iterator = $this$reduceIndexed.iterator();
        if (!iterator.hasNext()) {
            throw new UnsupportedOperationException("Empty sequence can't be reduced.");
        }
        int index = 1;
        Object accumulator = iterator.next();
        while (iterator.hasNext()) {
            final int i = index++;
            if (i < 0) {
                if (!PlatformImplementationsKt.apiVersionIsAtLeast(1, 3, 0)) {
                    throw new ArithmeticException("Index overflow has happened.");
                }
                CollectionsKt.throwIndexOverflow();
            }
            accumulator = operation.invoke(Integer.valueOf(i), (Object)accumulator, iterator.next());
        }
        return (S)accumulator;
    }
    
    public static final <T> int sumBy(@NotNull final Sequence<? extends T> $this$sumBy, @NotNull final Function1<? super T, Integer> selector) {
        final int $i$f$sumBy = 0;
        Intrinsics.checkParameterIsNotNull($this$sumBy, "$this$sumBy");
        Intrinsics.checkParameterIsNotNull(selector, "selector");
        int sum = 0;
        for (final Object element : $this$sumBy) {
            sum += selector.invoke((Object)element).intValue();
        }
        return sum;
    }
    
    public static final <T> double sumByDouble(@NotNull final Sequence<? extends T> $this$sumByDouble, @NotNull final Function1<? super T, Double> selector) {
        final int $i$f$sumByDouble = 0;
        Intrinsics.checkParameterIsNotNull($this$sumByDouble, "$this$sumByDouble");
        Intrinsics.checkParameterIsNotNull(selector, "selector");
        double sum = 0.0;
        for (final Object element : $this$sumByDouble) {
            sum += selector.invoke((Object)element).doubleValue();
        }
        return sum;
    }
    
    @NotNull
    public static final <T> Sequence<T> requireNoNulls(@NotNull final Sequence<? extends T> $this$requireNoNulls) {
        Intrinsics.checkParameterIsNotNull($this$requireNoNulls, "$this$requireNoNulls");
        return map((Sequence<?>)$this$requireNoNulls, (Function1<? super Object, ? extends T>)new SequencesKt___SequencesKt$requireNoNulls.SequencesKt___SequencesKt$requireNoNulls$1((Sequence)$this$requireNoNulls));
    }
    
    @SinceKotlin(version = "1.2")
    @NotNull
    public static final <T> Sequence<List<T>> chunked(@NotNull final Sequence<? extends T> $this$chunked, final int size) {
        Intrinsics.checkParameterIsNotNull($this$chunked, "$this$chunked");
        return windowed($this$chunked, size, size, true);
    }
    
    @SinceKotlin(version = "1.2")
    @NotNull
    public static final <T, R> Sequence<R> chunked(@NotNull final Sequence<? extends T> $this$chunked, final int size, @NotNull final Function1<? super List<? extends T>, ? extends R> transform) {
        Intrinsics.checkParameterIsNotNull($this$chunked, "$this$chunked");
        Intrinsics.checkParameterIsNotNull(transform, "transform");
        return windowed((Sequence<?>)$this$chunked, size, size, true, (Function1<? super List<?>, ? extends R>)transform);
    }
    
    @NotNull
    public static final <T> Sequence<T> minus(@NotNull final Sequence<? extends T> $this$minus, final T element) {
        Intrinsics.checkParameterIsNotNull($this$minus, "$this$minus");
        return (Sequence<T>)new SequencesKt___SequencesKt$minus.SequencesKt___SequencesKt$minus$1((Sequence)$this$minus, (Object)element);
    }
    
    @NotNull
    public static final <T> Sequence<T> minus(@NotNull final Sequence<? extends T> $this$minus, @NotNull final T[] elements) {
        Intrinsics.checkParameterIsNotNull($this$minus, "$this$minus");
        Intrinsics.checkParameterIsNotNull(elements, "elements");
        if (elements.length == 0) {
            return (Sequence<T>)$this$minus;
        }
        return (Sequence<T>)new SequencesKt___SequencesKt$minus.SequencesKt___SequencesKt$minus$2((Sequence)$this$minus, (Object[])elements);
    }
    
    @NotNull
    public static final <T> Sequence<T> minus(@NotNull final Sequence<? extends T> $this$minus, @NotNull final Iterable<? extends T> elements) {
        Intrinsics.checkParameterIsNotNull($this$minus, "$this$minus");
        Intrinsics.checkParameterIsNotNull(elements, "elements");
        return (Sequence<T>)new SequencesKt___SequencesKt$minus.SequencesKt___SequencesKt$minus$3((Sequence)$this$minus, (Iterable)elements);
    }
    
    @NotNull
    public static final <T> Sequence<T> minus(@NotNull final Sequence<? extends T> $this$minus, @NotNull final Sequence<? extends T> elements) {
        Intrinsics.checkParameterIsNotNull($this$minus, "$this$minus");
        Intrinsics.checkParameterIsNotNull(elements, "elements");
        return (Sequence<T>)new SequencesKt___SequencesKt$minus.SequencesKt___SequencesKt$minus$4((Sequence)$this$minus, (Sequence)elements);
    }
    
    @InlineOnly
    private static final <T> Sequence<T> minusElement(@NotNull final Sequence<? extends T> $this$minusElement, final T element) {
        final int $i$f$minusElement = 0;
        return (Sequence<T>)minus($this$minusElement, (Object)element);
    }
    
    @NotNull
    public static final <T> Pair<List<T>, List<T>> partition(@NotNull final Sequence<? extends T> $this$partition, @NotNull final Function1<? super T, Boolean> predicate) {
        final int $i$f$partition = 0;
        Intrinsics.checkParameterIsNotNull($this$partition, "$this$partition");
        Intrinsics.checkParameterIsNotNull(predicate, "predicate");
        final ArrayList first = new ArrayList();
        final ArrayList second = new ArrayList();
        for (final Object element : $this$partition) {
            if (predicate.invoke((Object)element)) {
                first.add(element);
            }
            else {
                second.add(element);
            }
        }
        return new Pair<List<T>, List<T>>(first, second);
    }
    
    @NotNull
    public static final <T> Sequence<T> plus(@NotNull final Sequence<? extends T> $this$plus, final T element) {
        Intrinsics.checkParameterIsNotNull($this$plus, "$this$plus");
        return SequencesKt__SequencesKt.flatten((Sequence<? extends Sequence<? extends T>>)SequencesKt__SequencesKt.sequenceOf($this$plus, SequencesKt__SequencesKt.sequenceOf(element)));
    }
    
    @NotNull
    public static final <T> Sequence<T> plus(@NotNull final Sequence<? extends T> $this$plus, @NotNull final T[] elements) {
        Intrinsics.checkParameterIsNotNull($this$plus, "$this$plus");
        Intrinsics.checkParameterIsNotNull(elements, "elements");
        return plus($this$plus, (Iterable<? extends T>)ArraysKt___ArraysJvmKt.asList(elements));
    }
    
    @NotNull
    public static final <T> Sequence<T> plus(@NotNull final Sequence<? extends T> $this$plus, @NotNull final Iterable<? extends T> elements) {
        Intrinsics.checkParameterIsNotNull($this$plus, "$this$plus");
        Intrinsics.checkParameterIsNotNull(elements, "elements");
        return SequencesKt__SequencesKt.flatten((Sequence<? extends Sequence<? extends T>>)SequencesKt__SequencesKt.sequenceOf($this$plus, CollectionsKt___CollectionsKt.asSequence((Iterable<?>)elements)));
    }
    
    @NotNull
    public static final <T> Sequence<T> plus(@NotNull final Sequence<? extends T> $this$plus, @NotNull final Sequence<? extends T> elements) {
        Intrinsics.checkParameterIsNotNull($this$plus, "$this$plus");
        Intrinsics.checkParameterIsNotNull(elements, "elements");
        return SequencesKt__SequencesKt.flatten((Sequence<? extends Sequence<? extends T>>)SequencesKt__SequencesKt.sequenceOf($this$plus, elements));
    }
    
    @InlineOnly
    private static final <T> Sequence<T> plusElement(@NotNull final Sequence<? extends T> $this$plusElement, final T element) {
        final int $i$f$plusElement = 0;
        return (Sequence<T>)plus($this$plusElement, (Object)element);
    }
    
    @SinceKotlin(version = "1.2")
    @NotNull
    public static final <T> Sequence<List<T>> windowed(@NotNull final Sequence<? extends T> $this$windowed, final int size, final int step, final boolean partialWindows) {
        Intrinsics.checkParameterIsNotNull($this$windowed, "$this$windowed");
        return SlidingWindowKt.windowedSequence($this$windowed, size, step, partialWindows, false);
    }
    
    @SinceKotlin(version = "1.2")
    @NotNull
    public static final <T, R> Sequence<R> windowed(@NotNull final Sequence<? extends T> $this$windowed, final int size, final int step, final boolean partialWindows, @NotNull final Function1<? super List<? extends T>, ? extends R> transform) {
        Intrinsics.checkParameterIsNotNull($this$windowed, "$this$windowed");
        Intrinsics.checkParameterIsNotNull(transform, "transform");
        return map((Sequence<?>)SlidingWindowKt.windowedSequence((Sequence<?>)$this$windowed, size, step, partialWindows, true), (Function1<? super Object, ? extends R>)transform);
    }
    
    @NotNull
    public static final <T, R> Sequence<Pair<T, R>> zip(@NotNull final Sequence<? extends T> $this$zip, @NotNull final Sequence<? extends R> other) {
        Intrinsics.checkParameterIsNotNull($this$zip, "$this$zip");
        Intrinsics.checkParameterIsNotNull(other, "other");
        return new MergingSequence<Object, Object, Pair<T, R>>($this$zip, other, (Function2<?, ?, ? extends Pair<T, R>>)SequencesKt___SequencesKt$zip.SequencesKt___SequencesKt$zip$1.INSTANCE);
    }
    
    @NotNull
    public static final <T, R, V> Sequence<V> zip(@NotNull final Sequence<? extends T> $this$zip, @NotNull final Sequence<? extends R> other, @NotNull final Function2<? super T, ? super R, ? extends V> transform) {
        Intrinsics.checkParameterIsNotNull($this$zip, "$this$zip");
        Intrinsics.checkParameterIsNotNull(other, "other");
        Intrinsics.checkParameterIsNotNull(transform, "transform");
        return new MergingSequence<Object, Object, V>($this$zip, other, transform);
    }
    
    @SinceKotlin(version = "1.2")
    @NotNull
    public static final <T> Sequence<Pair<T, T>> zipWithNext(@NotNull final Sequence<? extends T> $this$zipWithNext) {
        Intrinsics.checkParameterIsNotNull($this$zipWithNext, "$this$zipWithNext");
        return zipWithNext((Sequence<?>)$this$zipWithNext, (Function2<? super Object, ? super Object, ? extends Pair<T, T>>)SequencesKt___SequencesKt$zipWithNext.SequencesKt___SequencesKt$zipWithNext$1.INSTANCE);
    }
    
    @SinceKotlin(version = "1.2")
    @NotNull
    public static final <T, R> Sequence<R> zipWithNext(@NotNull final Sequence<? extends T> $this$zipWithNext, @NotNull final Function2<? super T, ? super T, ? extends R> transform) {
        Intrinsics.checkParameterIsNotNull($this$zipWithNext, "$this$zipWithNext");
        Intrinsics.checkParameterIsNotNull(transform, "transform");
        return SequencesKt__SequenceBuilderKt.sequence((Function2<? super SequenceScope<? super R>, ? super Continuation<? super Unit>, ?>)new SequencesKt___SequencesKt$zipWithNext.SequencesKt___SequencesKt$zipWithNext$2((Sequence)$this$zipWithNext, (Function2)transform, (Continuation)null));
    }
    
    @NotNull
    public static final <T, A extends Appendable> A joinTo(@NotNull final Sequence<? extends T> $this$joinTo, @NotNull final A buffer, @NotNull final CharSequence separator, @NotNull final CharSequence prefix, @NotNull final CharSequence postfix, final int limit, @NotNull final CharSequence truncated, @Nullable final Function1<? super T, ? extends CharSequence> transform) {
        Intrinsics.checkParameterIsNotNull($this$joinTo, "$this$joinTo");
        Intrinsics.checkParameterIsNotNull(buffer, "buffer");
        Intrinsics.checkParameterIsNotNull(separator, "separator");
        Intrinsics.checkParameterIsNotNull(prefix, "prefix");
        Intrinsics.checkParameterIsNotNull(postfix, "postfix");
        Intrinsics.checkParameterIsNotNull(truncated, "truncated");
        buffer.append(prefix);
        int count = 0;
        for (final Object element : $this$joinTo) {
            if (++count > 1) {
                buffer.append(separator);
            }
            if (limit >= 0 && count > limit) {
                break;
            }
            StringsKt__StringBuilderKt.appendElement(buffer, element, (Function1<? super Object, ? extends CharSequence>)transform);
        }
        if (limit >= 0 && count > limit) {
            buffer.append(truncated);
        }
        buffer.append(postfix);
        return buffer;
    }
    
    @NotNull
    public static final <T> String joinToString(@NotNull final Sequence<? extends T> $this$joinToString, @NotNull final CharSequence separator, @NotNull final CharSequence prefix, @NotNull final CharSequence postfix, final int limit, @NotNull final CharSequence truncated, @Nullable final Function1<? super T, ? extends CharSequence> transform) {
        Intrinsics.checkParameterIsNotNull($this$joinToString, "$this$joinToString");
        Intrinsics.checkParameterIsNotNull(separator, "separator");
        Intrinsics.checkParameterIsNotNull(prefix, "prefix");
        Intrinsics.checkParameterIsNotNull(postfix, "postfix");
        Intrinsics.checkParameterIsNotNull(truncated, "truncated");
        final String string = joinTo((Sequence<?>)$this$joinToString, (StringBuilder)new StringBuilder(), separator, prefix, postfix, limit, truncated, (Function1<? super Object, ? extends CharSequence>)transform).toString();
        Intrinsics.checkExpressionValueIsNotNull(string, "joinTo(StringBuilder(), \u2026ed, transform).toString()");
        return string;
    }
    
    @NotNull
    public static final <T> Iterable<T> asIterable(@NotNull final Sequence<? extends T> $this$asIterable) {
        Intrinsics.checkParameterIsNotNull($this$asIterable, "$this$asIterable");
        return new Iterable<T>($this$asIterable) {
            @NotNull
            @Override
            public Iterator<T> iterator() {
                final int n = 0;
                return this.$this_asIterable$inlined.iterator();
            }
        };
    }
    
    @InlineOnly
    private static final <T> Sequence<T> asSequence(@NotNull final Sequence<? extends T> $this$asSequence) {
        final int $i$f$asSequence = 0;
        return (Sequence<T>)$this$asSequence;
    }
    
    @JvmName(name = "averageOfByte")
    public static final double averageOfByte(@NotNull final Sequence<Byte> $this$average) {
        Intrinsics.checkParameterIsNotNull($this$average, "$this$average");
        double sum = 0.0;
        int count = 0;
        final Iterator<Byte> iterator = $this$average.iterator();
        while (iterator.hasNext()) {
            final byte element = iterator.next().byteValue();
            sum += element;
            if (++count < 0) {
                CollectionsKt.throwCountOverflow();
            }
        }
        return (count == 0) ? DoubleCompanionObject.INSTANCE.getNaN() : (sum / count);
    }
    
    @JvmName(name = "averageOfShort")
    public static final double averageOfShort(@NotNull final Sequence<Short> $this$average) {
        Intrinsics.checkParameterIsNotNull($this$average, "$this$average");
        double sum = 0.0;
        int count = 0;
        final Iterator<Short> iterator = $this$average.iterator();
        while (iterator.hasNext()) {
            final short element = iterator.next().shortValue();
            sum += element;
            if (++count < 0) {
                CollectionsKt.throwCountOverflow();
            }
        }
        return (count == 0) ? DoubleCompanionObject.INSTANCE.getNaN() : (sum / count);
    }
    
    @JvmName(name = "averageOfInt")
    public static final double averageOfInt(@NotNull final Sequence<Integer> $this$average) {
        Intrinsics.checkParameterIsNotNull($this$average, "$this$average");
        double sum = 0.0;
        int count = 0;
        final Iterator<Integer> iterator = $this$average.iterator();
        while (iterator.hasNext()) {
            final int element = iterator.next().intValue();
            sum += element;
            if (++count < 0) {
                CollectionsKt.throwCountOverflow();
            }
        }
        return (count == 0) ? DoubleCompanionObject.INSTANCE.getNaN() : (sum / count);
    }
    
    @JvmName(name = "averageOfLong")
    public static final double averageOfLong(@NotNull final Sequence<Long> $this$average) {
        Intrinsics.checkParameterIsNotNull($this$average, "$this$average");
        double sum = 0.0;
        int count = 0;
        final Iterator<Long> iterator = $this$average.iterator();
        while (iterator.hasNext()) {
            final long element = iterator.next().longValue();
            sum += element;
            if (++count < 0) {
                CollectionsKt.throwCountOverflow();
            }
        }
        return (count == 0) ? DoubleCompanionObject.INSTANCE.getNaN() : (sum / count);
    }
    
    @JvmName(name = "averageOfFloat")
    public static final double averageOfFloat(@NotNull final Sequence<Float> $this$average) {
        Intrinsics.checkParameterIsNotNull($this$average, "$this$average");
        double sum = 0.0;
        int count = 0;
        final Iterator<Float> iterator = $this$average.iterator();
        while (iterator.hasNext()) {
            final float element = iterator.next().floatValue();
            sum += element;
            if (++count < 0) {
                CollectionsKt.throwCountOverflow();
            }
        }
        return (count == 0) ? DoubleCompanionObject.INSTANCE.getNaN() : (sum / count);
    }
    
    @JvmName(name = "averageOfDouble")
    public static final double averageOfDouble(@NotNull final Sequence<Double> $this$average) {
        Intrinsics.checkParameterIsNotNull($this$average, "$this$average");
        double sum = 0.0;
        int count = 0;
        final Iterator<Double> iterator = $this$average.iterator();
        while (iterator.hasNext()) {
            final double element = iterator.next().doubleValue();
            sum += element;
            if (++count < 0) {
                CollectionsKt.throwCountOverflow();
            }
        }
        return (count == 0) ? DoubleCompanionObject.INSTANCE.getNaN() : (sum / count);
    }
    
    @JvmName(name = "sumOfByte")
    public static final int sumOfByte(@NotNull final Sequence<Byte> $this$sum) {
        Intrinsics.checkParameterIsNotNull($this$sum, "$this$sum");
        int sum = 0;
        final Iterator<Byte> iterator = $this$sum.iterator();
        while (iterator.hasNext()) {
            final byte element = iterator.next().byteValue();
            sum += element;
        }
        return sum;
    }
    
    @JvmName(name = "sumOfShort")
    public static final int sumOfShort(@NotNull final Sequence<Short> $this$sum) {
        Intrinsics.checkParameterIsNotNull($this$sum, "$this$sum");
        int sum = 0;
        final Iterator<Short> iterator = $this$sum.iterator();
        while (iterator.hasNext()) {
            final short element = iterator.next().shortValue();
            sum += element;
        }
        return sum;
    }
    
    @JvmName(name = "sumOfInt")
    public static final int sumOfInt(@NotNull final Sequence<Integer> $this$sum) {
        Intrinsics.checkParameterIsNotNull($this$sum, "$this$sum");
        int sum = 0;
        final Iterator<Integer> iterator = $this$sum.iterator();
        while (iterator.hasNext()) {
            final int element = iterator.next().intValue();
            sum += element;
        }
        return sum;
    }
    
    @JvmName(name = "sumOfLong")
    public static final long sumOfLong(@NotNull final Sequence<Long> $this$sum) {
        Intrinsics.checkParameterIsNotNull($this$sum, "$this$sum");
        long sum = 0L;
        final Iterator<Long> iterator = $this$sum.iterator();
        while (iterator.hasNext()) {
            final long element = iterator.next().longValue();
            sum += element;
        }
        return sum;
    }
    
    @JvmName(name = "sumOfFloat")
    public static final float sumOfFloat(@NotNull final Sequence<Float> $this$sum) {
        Intrinsics.checkParameterIsNotNull($this$sum, "$this$sum");
        float sum = 0.0f;
        final Iterator<Float> iterator = $this$sum.iterator();
        while (iterator.hasNext()) {
            final float element = iterator.next().floatValue();
            sum += element;
        }
        return sum;
    }
    
    @JvmName(name = "sumOfDouble")
    public static final double sumOfDouble(@NotNull final Sequence<Double> $this$sum) {
        Intrinsics.checkParameterIsNotNull($this$sum, "$this$sum");
        double sum = 0.0;
        final Iterator<Double> iterator = $this$sum.iterator();
        while (iterator.hasNext()) {
            final double element = iterator.next().doubleValue();
            sum += element;
        }
        return sum;
    }
    
    public SequencesKt___SequencesKt() {
    }
}
