// 
// Decompiled by Procyon v0.5.36
// 

package dev.nuker.pyro;

import java.util.HashMap;
import java.util.concurrent.ConcurrentLinkedQueue;

public class f03 extends fbk
{
    public ConcurrentLinkedQueue<String> c;
    public HashMap<String, String> c;
    public fbu c;
    public static f03 c;
    
    public void 0() {
        fbS.dI(this, 1263584904);
    }
    
    public String 0(final String p0) {
        // 
        // This method could not be decompiled.
        // 
        // Original Bytecode:
        // 
        //     3: dup            
        //     4: ifnull          1343
        //     7: athrow         
        //     8: aconst_null    
        //     9: getstatic       dev/nuker/pyro/fc.1:I
        //    12: ifgt            1335
        //    15: pop            
        //    16: aconst_null    
        //    17: goto            1327
        //    20: nop            
        //    21: nop            
        //    22: nop            
        //    23: athrow         
        //    24: aload_0        
        //    25: getfield        dev/nuker/pyro/f03.c:Ljava/util/HashMap;
        //    28: getstatic       dev/nuker/pyro/fc.c:I
        //    31: ifge            39
        //    34: ldc             1985394023
        //    36: goto            41
        //    39: ldc             -501682112
        //    41: ldc             2130001576
        //    43: ixor           
        //    44: lookupswitch {
        //          -1662136600: 72
        //          144935887: 39
        //          default: 1284
        //        }
        //    72: aload_1        
        //    73: goto            77
        //    76: athrow         
        //    77: invokevirtual   java/util/HashMap.containsKey:(Ljava/lang/Object;)Z
        //    80: goto            84
        //    83: athrow         
        //    84: ifeq            235
        //    87: getstatic       dev/nuker/pyro/fc.c:I
        //    90: ifge            98
        //    93: ldc             -1147249616
        //    95: goto            100
        //    98: ldc             1551623837
        //   100: ldc             810456806
        //   102: ixor           
        //   103: lookupswitch {
        //          -1949250858: 98
        //          1815441531: 128
        //          default: 1282
        //        }
        //   128: aload_0        
        //   129: getfield        dev/nuker/pyro/f03.c:Ljava/util/HashMap;
        //   132: getstatic       dev/nuker/pyro/fc.0:I
        //   135: ifeq            143
        //   138: ldc             964874825
        //   140: goto            145
        //   143: ldc             562965720
        //   145: ldc             -817732791
        //   147: ixor           
        //   148: lookupswitch {
        //          -288600175: 176
        //          -155143936: 143
        //          default: 1312
        //        }
        //   176: aload_1        
        //   177: getstatic       dev/nuker/pyro/fc.0:I
        //   180: ifeq            188
        //   183: ldc             1196229110
        //   185: goto            190
        //   188: ldc             -159637629
        //   190: ldc             741429115
        //   192: ixor           
        //   193: lookupswitch {
        //          -632467208: 220
        //          1803308685: 188
        //          default: 1280
        //        }
        //   220: goto            224
        //   223: athrow         
        //   224: invokevirtual   java/util/HashMap.get:(Ljava/lang/Object;)Ljava/lang/Object;
        //   227: goto            231
        //   230: athrow         
        //   231: checkcast       Ljava/lang/String;
        //   234: areturn        
        //   235: aconst_null    
        //   236: getstatic       dev/nuker/pyro/fc.1:I
        //   239: ifeq            247
        //   242: ldc             -91812025
        //   244: goto            249
        //   247: ldc             932490373
        //   249: ldc             -1433560334
        //   251: ixor           
        //   252: lookupswitch {
        //          -1659292041: 280
        //          1342870965: 247
        //          default: 1304
        //        }
        //   280: astore_2       
        //   281: new             Ljava/net/URL;
        //   284: dup            
        //   285: new             Ljava/lang/StringBuilder;
        //   288: dup            
        //   289: goto            293
        //   292: athrow         
        //   293: invokespecial   java/lang/StringBuilder.<init>:()V
        //   296: goto            300
        //   299: athrow         
        //   300: ldc             "\u2329\u1487\u8a2c\ub18b\uceb3\ued7d\ub26b\ue65a\udb39\ueed6\ua7f4\u1e5f\ue138\uc7ea\u865a\u89af\u57a1\u77c2\ubf69\uc76a\u2bc1\uc275\u6ad5\u2f1b\ud0bb\u3545\u7d25\u897c\u821d\u8bf7\u846e\ufb3f\u7048\u9847\u1ce3\uf1b5\u496f\u88bd\uc8cb\uf84a\ub656\u41fe\ub928\ub104\u4b13\u8a37\u7c7b\ucef1\u7f0a\uedb5\ue656\u16c8\uee91\u35c3\u41cf\ue134\u0a1b\u8601\u1bd8"
        //   302: goto            306
        //   305: athrow         
        //   306: invokestatic    invokestatic   !!! ERROR
        //   309: goto            313
        //   312: athrow         
        //   313: goto            317
        //   316: athrow         
        //   317: invokevirtual   java/lang/StringBuilder.append:(Ljava/lang/String;)Ljava/lang/StringBuilder;
        //   320: goto            324
        //   323: athrow         
        //   324: getstatic       dev/nuker/pyro/fc.1:I
        //   327: ifeq            335
        //   330: ldc             -951445784
        //   332: goto            337
        //   335: ldc             -554299540
        //   337: ldc             1898239825
        //   339: ixor           
        //   340: lookupswitch {
        //          -1345136579: 368
        //          -1234255431: 335
        //          default: 1310
        //        }
        //   368: aload_1        
        //   369: goto            373
        //   372: athrow         
        //   373: invokevirtual   java/lang/StringBuilder.append:(Ljava/lang/String;)Ljava/lang/StringBuilder;
        //   376: goto            380
        //   379: athrow         
        //   380: goto            384
        //   383: athrow         
        //   384: invokevirtual   java/lang/StringBuilder.toString:()Ljava/lang/String;
        //   387: goto            391
        //   390: athrow         
        //   391: goto            395
        //   394: athrow         
        //   395: invokespecial   java/net/URL.<init>:(Ljava/lang/String;)V
        //   398: goto            402
        //   401: athrow         
        //   402: astore_3       
        //   403: new             Ljava/io/BufferedReader;
        //   406: dup            
        //   407: new             Ljava/io/InputStreamReader;
        //   410: dup            
        //   411: aload_3        
        //   412: goto            416
        //   415: athrow         
        //   416: invokevirtual   java/net/URL.openStream:()Ljava/io/InputStream;
        //   419: goto            423
        //   422: athrow         
        //   423: getstatic       dev/nuker/pyro/fc.c:I
        //   426: ifge            434
        //   429: ldc             1857333472
        //   431: goto            436
        //   434: ldc             -137629101
        //   436: ldc             -499913453
        //   438: ixor           
        //   439: lookupswitch {
        //          -1937291789: 434
        //          368582464: 464
        //          default: 1294
        //        }
        //   464: goto            468
        //   467: athrow         
        //   468: invokespecial   java/io/InputStreamReader.<init>:(Ljava/io/InputStream;)V
        //   471: goto            475
        //   474: athrow         
        //   475: getstatic       dev/nuker/pyro/fc.0:I
        //   478: ifeq            486
        //   481: ldc             -38745750
        //   483: goto            488
        //   486: ldc             1407558403
        //   488: ldc             -717605897
        //   490: ixor           
        //   491: lookupswitch {
        //          -947043513: 486
        //          680196765: 1286
        //          default: 516
        //        }
        //   516: goto            520
        //   519: athrow         
        //   520: invokespecial   java/io/BufferedReader.<init>:(Ljava/io/Reader;)V
        //   523: goto            527
        //   526: athrow         
        //   527: astore          4
        //   529: new             Ljava/lang/StringBuilder;
        //   532: dup            
        //   533: goto            537
        //   536: athrow         
        //   537: invokespecial   java/lang/StringBuilder.<init>:()V
        //   540: goto            544
        //   543: athrow         
        //   544: astore          5
        //   546: aload           4
        //   548: goto            552
        //   551: athrow         
        //   552: invokevirtual   java/io/BufferedReader.readLine:()Ljava/lang/String;
        //   555: goto            559
        //   558: athrow         
        //   559: dup            
        //   560: astore          6
        //   562: ifnull          803
        //   565: getstatic       dev/nuker/pyro/fc.1:I
        //   568: ifeq            576
        //   571: ldc             458574162
        //   573: goto            578
        //   576: ldc             1292037642
        //   578: ldc             824720132
        //   580: ixor           
        //   581: lookupswitch {
        //          712864342: 576
        //          2083181838: 608
        //          default: 1288
        //        }
        //   608: aload           5
        //   610: new             Ljava/lang/StringBuilder;
        //   613: dup            
        //   614: goto            618
        //   617: athrow         
        //   618: invokespecial   java/lang/StringBuilder.<init>:()V
        //   621: goto            625
        //   624: athrow         
        //   625: aload           6
        //   627: getstatic       dev/nuker/pyro/fc.0:I
        //   630: ifeq            638
        //   633: ldc             1274109137
        //   635: goto            640
        //   638: ldc             -1642737811
        //   640: ldc             -345904181
        //   642: ixor           
        //   643: lookupswitch {
        //          -1869054481: 638
        //          -1601128678: 1314
        //          default: 668
        //        }
        //   668: goto            672
        //   671: athrow         
        //   672: invokevirtual   java/lang/StringBuilder.append:(Ljava/lang/String;)Ljava/lang/StringBuilder;
        //   675: goto            679
        //   678: athrow         
        //   679: ldc             "\n"
        //   681: goto            685
        //   684: athrow         
        //   685: invokevirtual   java/lang/StringBuilder.append:(Ljava/lang/String;)Ljava/lang/StringBuilder;
        //   688: goto            692
        //   691: athrow         
        //   692: getstatic       dev/nuker/pyro/fc.c:I
        //   695: ifge            703
        //   698: ldc             -456190575
        //   700: goto            705
        //   703: ldc             1786511139
        //   705: ldc             1809975604
        //   707: ixor           
        //   708: lookupswitch {
        //          -1892868955: 1278
        //          -151104304: 703
        //          default: 736
        //        }
        //   736: goto            740
        //   739: athrow         
        //   740: invokevirtual   java/lang/StringBuilder.toString:()Ljava/lang/String;
        //   743: goto            747
        //   746: athrow         
        //   747: getstatic       dev/nuker/pyro/fc.1:I
        //   750: ifeq            758
        //   753: ldc             777954712
        //   755: goto            760
        //   758: ldc             759918222
        //   760: ldc             -938641292
        //   762: ixor           
        //   763: lookupswitch {
        //          -448391430: 788
        //          -430711316: 758
        //          default: 1316
        //        }
        //   788: goto            792
        //   791: athrow         
        //   792: invokevirtual   java/lang/StringBuilder.append:(Ljava/lang/String;)Ljava/lang/StringBuilder;
        //   795: goto            799
        //   798: athrow         
        //   799: pop            
        //   800: goto            546
        //   803: new             Lcom/google/gson/JsonParser;
        //   806: dup            
        //   807: getstatic       dev/nuker/pyro/fc.1:I
        //   810: ifeq            818
        //   813: ldc             -1197940153
        //   815: goto            820
        //   818: ldc             -1164060094
        //   820: ldc             1949820973
        //   822: ixor           
        //   823: lookupswitch {
        //          -860943766: 818
        //          -827706769: 848
        //          default: 1290
        //        }
        //   848: goto            852
        //   851: athrow         
        //   852: invokespecial   com/google/gson/JsonParser.<init>:()V
        //   855: goto            859
        //   858: athrow         
        //   859: astore          7
        //   861: getstatic       dev/nuker/pyro/fc.1:I
        //   864: ifeq            872
        //   867: ldc             -374458413
        //   869: goto            874
        //   872: ldc             -348138332
        //   874: ldc             761442383
        //   876: ixor           
        //   877: lookupswitch {
        //          -993228900: 872
        //          -966957845: 904
        //          default: 1298
        //        }
        //   904: aload           7
        //   906: aload           5
        //   908: goto            912
        //   911: athrow         
        //   912: invokevirtual   java/lang/StringBuilder.toString:()Ljava/lang/String;
        //   915: goto            919
        //   918: athrow         
        //   919: goto            923
        //   922: athrow         
        //   923: invokevirtual   java/lang/String.trim:()Ljava/lang/String;
        //   926: goto            930
        //   929: athrow         
        //   930: getstatic       dev/nuker/pyro/fc.1:I
        //   933: ifeq            941
        //   936: ldc             725891765
        //   938: goto            943
        //   941: ldc             592250028
        //   943: ldc             -1272639980
        //   945: ixor           
        //   946: lookupswitch {
        //          -1621019487: 1300
        //          -1209595756: 941
        //          default: 972
        //        }
        //   972: goto            976
        //   975: athrow         
        //   976: invokevirtual   com/google/gson/JsonParser.parse:(Ljava/lang/String;)Lcom/google/gson/JsonElement;
        //   979: goto            983
        //   982: athrow         
        //   983: astore          8
        //   985: aload           8
        //   987: getstatic       dev/nuker/pyro/fc.0:I
        //   990: ifeq            998
        //   993: ldc             -816136306
        //   995: goto            1000
        //   998: ldc             173719515
        //  1000: ldc             -2092516201
        //  1002: ixor           
        //  1003: lookupswitch {
        //          1276904217: 1296
        //          1674493434: 998
        //          default: 1028
        //        }
        //  1028: goto            1032
        //  1031: athrow         
        //  1032: invokevirtual   com/google/gson/JsonElement.getAsJsonObject:()Lcom/google/gson/JsonObject;
        //  1035: goto            1039
        //  1038: athrow         
        //  1039: ldc             "\u232f\u1492\u8a35\ub19e"
        //  1041: getstatic       dev/nuker/pyro/fc.1:I
        //  1044: ifeq            1052
        //  1047: ldc             -286093317
        //  1049: goto            1054
        //  1052: ldc             -1096850018
        //  1054: ldc             898098852
        //  1056: ixor           
        //  1057: lookupswitch {
        //          -1961327814: 1084
        //          -613062305: 1052
        //          default: 1302
        //        }
        //  1084: goto            1088
        //  1087: athrow         
        //  1088: invokestatic    invokestatic   !!! ERROR
        //  1091: goto            1095
        //  1094: athrow         
        //  1095: goto            1099
        //  1098: athrow         
        //  1099: invokevirtual   com/google/gson/JsonObject.get:(Ljava/lang/String;)Lcom/google/gson/JsonElement;
        //  1102: goto            1106
        //  1105: athrow         
        //  1106: goto            1110
        //  1109: athrow         
        //  1110: invokevirtual   com/google/gson/JsonElement.getAsString:()Ljava/lang/String;
        //  1113: goto            1117
        //  1116: athrow         
        //  1117: astore_2       
        //  1118: aload           4
        //  1120: getstatic       dev/nuker/pyro/fc.0:I
        //  1123: ifeq            1131
        //  1126: ldc             -611112883
        //  1128: goto            1133
        //  1131: ldc             911358320
        //  1133: ldc             745910700
        //  1135: ixor           
        //  1136: lookupswitch {
        //          -135882271: 1131
        //          438798556: 1164
        //          default: 1306
        //        }
        //  1164: goto            1168
        //  1167: athrow         
        //  1168: invokevirtual   java/io/BufferedReader.close:()V
        //  1171: goto            1175
        //  1174: athrow         
        //  1175: goto            1235
        //  1178: getstatic       dev/nuker/pyro/fc.c:I
        //  1181: ifge            1189
        //  1184: ldc             -1510028570
        //  1186: goto            1191
        //  1189: ldc             -605317706
        //  1191: ldc             -1115450282
        //  1193: ixor           
        //  1194: lookupswitch {
        //          -602845421: 1189
        //          410869424: 1308
        //          default: 1220
        //        }
        //  1220: astore_3       
        //  1221: aload_3        
        //  1222: goto            1226
        //  1225: athrow         
        //  1226: invokevirtual   java/lang/Exception.printStackTrace:()V
        //  1229: goto            1233
        //  1232: athrow         
        //  1233: aload_1        
        //  1234: astore_2       
        //  1235: getstatic       dev/nuker/pyro/fc.c:I
        //  1238: ifge            1246
        //  1241: ldc             -75004106
        //  1243: goto            1248
        //  1246: ldc             -450794019
        //  1248: ldc             -1408757724
        //  1250: ixor           
        //  1251: lookupswitch {
        //          -1671418272: 1246
        //          1469028114: 1292
        //          default: 1276
        //        }
        //  1276: aload_2        
        //  1277: areturn        
        //  1278: aconst_null    
        //  1279: athrow         
        //  1280: aconst_null    
        //  1281: athrow         
        //  1282: aconst_null    
        //  1283: athrow         
        //  1284: aconst_null    
        //  1285: athrow         
        //  1286: aconst_null    
        //  1287: athrow         
        //  1288: aconst_null    
        //  1289: athrow         
        //  1290: aconst_null    
        //  1291: athrow         
        //  1292: aconst_null    
        //  1293: athrow         
        //  1294: aconst_null    
        //  1295: athrow         
        //  1296: aconst_null    
        //  1297: athrow         
        //  1298: aconst_null    
        //  1299: athrow         
        //  1300: aconst_null    
        //  1301: athrow         
        //  1302: aconst_null    
        //  1303: athrow         
        //  1304: aconst_null    
        //  1305: athrow         
        //  1306: aconst_null    
        //  1307: athrow         
        //  1308: aconst_null    
        //  1309: athrow         
        //  1310: aconst_null    
        //  1311: athrow         
        //  1312: aconst_null    
        //  1313: athrow         
        //  1314: aconst_null    
        //  1315: athrow         
        //  1316: aconst_null    
        //  1317: athrow         
        //  1318: pop            
        //  1319: goto            24
        //  1322: pop            
        //  1323: aconst_null    
        //  1324: goto            1318
        //  1327: dup            
        //  1328: ifnull          1318
        //  1331: checkcast       Ljava/lang/Throwable;
        //  1334: athrow         
        //  1335: dup            
        //  1336: ifnull          1322
        //  1339: checkcast       Ljava/lang/Throwable;
        //  1342: athrow         
        //  1343: aconst_null    
        //  1344: athrow         
        //    StackMapTable: 00 CE 43 07 00 40 04 FF 00 0B 00 00 00 01 07 00 40 FD 00 03 07 00 03 07 00 5E 4E 07 00 49 FF 00 01 00 02 07 00 03 07 00 5E 00 02 07 00 49 01 5E 07 00 49 43 07 00 40 FF 00 00 00 02 07 00 03 07 00 5E 00 02 07 00 49 07 00 5E 45 07 00 40 40 01 0D 41 01 1B 4E 07 00 49 FF 00 01 00 02 07 00 03 07 00 5E 00 02 07 00 49 01 5E 07 00 49 FF 00 0B 00 02 07 00 03 07 00 5E 00 02 07 00 49 07 00 5E FF 00 01 00 02 07 00 03 07 00 5E 00 03 07 00 49 07 00 5E 01 FF 00 1D 00 02 07 00 03 07 00 5E 00 02 07 00 49 07 00 5E 42 07 00 20 FF 00 00 00 02 07 00 03 07 00 5E 00 02 07 00 49 07 00 5E 45 07 00 40 40 07 00 DA 03 4B 05 FF 00 01 00 02 07 00 03 07 00 5E 00 02 05 01 5E 05 FF 00 0B 00 00 00 01 07 00 40 FF 00 00 00 03 07 00 03 07 00 5E 05 00 04 08 01 19 08 01 19 08 01 1D 08 01 1D 45 07 00 40 FF 00 00 00 03 07 00 03 07 00 5E 05 00 03 08 01 19 08 01 19 07 00 65 44 07 00 20 FF 00 00 00 03 07 00 03 07 00 5E 05 00 04 08 01 19 08 01 19 07 00 65 07 00 5E 45 07 00 40 FF 00 00 00 03 07 00 03 07 00 5E 05 00 04 08 01 19 08 01 19 07 00 65 07 00 5E 42 07 00 40 FF 00 00 00 03 07 00 03 07 00 5E 05 00 04 08 01 19 08 01 19 07 00 65 07 00 5E 45 07 00 40 FF 00 00 00 03 07 00 03 07 00 5E 05 00 03 08 01 19 08 01 19 07 00 65 FF 00 0A 00 03 07 00 03 07 00 5E 05 00 03 08 01 19 08 01 19 07 00 65 FF 00 01 00 03 07 00 03 07 00 5E 05 00 04 08 01 19 08 01 19 07 00 65 01 FF 00 1E 00 03 07 00 03 07 00 5E 05 00 03 08 01 19 08 01 19 07 00 65 43 07 00 1A FF 00 00 00 03 07 00 03 07 00 5E 05 00 04 08 01 19 08 01 19 07 00 65 07 00 5E 45 07 00 40 FF 00 00 00 03 07 00 03 07 00 5E 05 00 03 08 01 19 08 01 19 07 00 65 42 07 00 40 FF 00 00 00 03 07 00 03 07 00 5E 05 00 03 08 01 19 08 01 19 07 00 65 45 07 00 40 FF 00 00 00 03 07 00 03 07 00 5E 05 00 03 08 01 19 08 01 19 07 00 5E FF 00 02 00 00 00 01 07 00 40 FF 00 00 00 03 07 00 03 07 00 5E 05 00 03 08 01 19 08 01 19 07 00 5E 45 07 00 40 40 07 00 63 FF 00 0C 00 04 07 00 03 07 00 5E 05 07 00 63 00 01 07 00 40 FF 00 00 00 04 07 00 03 07 00 5E 05 07 00 63 00 05 08 01 93 08 01 93 08 01 97 08 01 97 07 00 63 45 07 00 40 FF 00 00 00 04 07 00 03 07 00 5E 05 07 00 63 00 05 08 01 93 08 01 93 08 01 97 08 01 97 07 00 DC FF 00 0A 00 04 07 00 03 07 00 5E 05 07 00 63 00 05 08 01 93 08 01 93 08 01 97 08 01 97 07 00 DC FF 00 01 00 04 07 00 03 07 00 5E 05 07 00 63 00 06 08 01 93 08 01 93 08 01 97 08 01 97 07 00 DC 01 FF 00 1B 00 04 07 00 03 07 00 5E 05 07 00 63 00 05 08 01 93 08 01 93 08 01 97 08 01 97 07 00 DC 42 07 00 40 FF 00 00 00 04 07 00 03 07 00 5E 05 07 00 63 00 05 08 01 93 08 01 93 08 01 97 08 01 97 07 00 DC 45 07 00 40 FF 00 00 00 04 07 00 03 07 00 5E 05 07 00 63 00 03 08 01 93 08 01 93 07 00 80 FF 00 0A 00 04 07 00 03 07 00 5E 05 07 00 63 00 03 08 01 93 08 01 93 07 00 80 FF 00 01 00 04 07 00 03 07 00 5E 05 07 00 63 00 04 08 01 93 08 01 93 07 00 80 01 FF 00 1B 00 04 07 00 03 07 00 5E 05 07 00 63 00 03 08 01 93 08 01 93 07 00 80 42 07 00 20 FF 00 00 00 04 07 00 03 07 00 5E 05 07 00 63 00 03 08 01 93 08 01 93 07 00 80 45 07 00 40 40 07 00 7E FF 00 08 00 05 07 00 03 07 00 5E 05 07 00 63 07 00 7E 00 01 07 00 40 FF 00 00 00 05 07 00 03 07 00 5E 05 07 00 63 07 00 7E 00 02 08 02 11 08 02 11 45 07 00 40 40 07 00 65 FC 00 01 07 00 65 44 07 00 40 40 07 00 7E 45 07 00 40 40 07 00 5E FC 00 10 07 00 5E 41 01 1D 48 07 00 40 FF 00 00 00 07 07 00 03 07 00 5E 05 07 00 63 07 00 7E 07 00 65 07 00 5E 00 03 07 00 65 08 02 62 08 02 62 45 07 00 40 FF 00 00 00 07 07 00 03 07 00 5E 05 07 00 63 07 00 7E 07 00 65 07 00 5E 00 02 07 00 65 07 00 65 FF 00 0C 00 07 07 00 03 07 00 5E 05 07 00 63 07 00 7E 07 00 65 07 00 5E 00 03 07 00 65 07 00 65 07 00 5E FF 00 01 00 07 07 00 03 07 00 5E 05 07 00 63 07 00 7E 07 00 65 07 00 5E 00 04 07 00 65 07 00 65 07 00 5E 01 FF 00 1B 00 07 07 00 03 07 00 5E 05 07 00 63 07 00 7E 07 00 65 07 00 5E 00 03 07 00 65 07 00 65 07 00 5E 42 07 00 40 FF 00 00 00 07 07 00 03 07 00 5E 05 07 00 63 07 00 7E 07 00 65 07 00 5E 00 03 07 00 65 07 00 65 07 00 5E 45 07 00 40 FF 00 00 00 07 07 00 03 07 00 5E 05 07 00 63 07 00 7E 07 00 65 07 00 5E 00 02 07 00 65 07 00 65 44 07 00 1E FF 00 00 00 07 07 00 03 07 00 5E 05 07 00 63 07 00 7E 07 00 65 07 00 5E 00 03 07 00 65 07 00 65 07 00 5E 45 07 00 40 FF 00 00 00 07 07 00 03 07 00 5E 05 07 00 63 07 00 7E 07 00 65 07 00 5E 00 02 07 00 65 07 00 65 FF 00 0A 00 07 07 00 03 07 00 5E 05 07 00 63 07 00 7E 07 00 65 07 00 5E 00 02 07 00 65 07 00 65 FF 00 01 00 07 07 00 03 07 00 5E 05 07 00 63 07 00 7E 07 00 65 07 00 5E 00 03 07 00 65 07 00 65 01 FF 00 1E 00 07 07 00 03 07 00 5E 05 07 00 63 07 00 7E 07 00 65 07 00 5E 00 02 07 00 65 07 00 65 42 07 00 40 FF 00 00 00 07 07 00 03 07 00 5E 05 07 00 63 07 00 7E 07 00 65 07 00 5E 00 02 07 00 65 07 00 65 45 07 00 40 FF 00 00 00 07 07 00 03 07 00 5E 05 07 00 63 07 00 7E 07 00 65 07 00 5E 00 02 07 00 65 07 00 5E FF 00 0A 00 07 07 00 03 07 00 5E 05 07 00 63 07 00 7E 07 00 65 07 00 5E 00 02 07 00 65 07 00 5E FF 00 01 00 07 07 00 03 07 00 5E 05 07 00 63 07 00 7E 07 00 65 07 00 5E 00 03 07 00 65 07 00 5E 01 FF 00 1B 00 07 07 00 03 07 00 5E 05 07 00 63 07 00 7E 07 00 65 07 00 5E 00 02 07 00 65 07 00 5E 42 07 00 40 FF 00 00 00 07 07 00 03 07 00 5E 05 07 00 63 07 00 7E 07 00 65 07 00 5E 00 02 07 00 65 07 00 5E 45 07 00 40 40 07 00 65 03 FF 00 0E 00 07 07 00 03 07 00 5E 05 07 00 63 07 00 7E 07 00 65 07 00 5E 00 02 08 03 23 08 03 23 FF 00 01 00 07 07 00 03 07 00 5E 05 07 00 63 07 00 7E 07 00 65 07 00 5E 00 03 08 03 23 08 03 23 01 FF 00 1B 00 07 07 00 03 07 00 5E 05 07 00 63 07 00 7E 07 00 65 07 00 5E 00 02 08 03 23 08 03 23 42 07 00 40 FF 00 00 00 07 07 00 03 07 00 5E 05 07 00 63 07 00 7E 07 00 65 07 00 5E 00 02 08 03 23 08 03 23 45 07 00 40 40 07 00 A3 FC 00 0C 07 00 A3 41 01 1D FF 00 06 00 00 00 01 07 00 40 FF 00 00 00 08 07 00 03 07 00 5E 05 07 00 63 07 00 7E 07 00 65 07 00 5E 07 00 A3 00 02 07 00 A3 07 00 65 45 07 00 40 FF 00 00 00 08 07 00 03 07 00 5E 05 07 00 63 07 00 7E 07 00 65 07 00 5E 07 00 A3 00 02 07 00 A3 07 00 5E 42 07 00 20 FF 00 00 00 08 07 00 03 07 00 5E 05 07 00 63 07 00 7E 07 00 65 07 00 5E 07 00 A3 00 02 07 00 A3 07 00 5E 45 07 00 40 FF 00 00 00 08 07 00 03 07 00 5E 05 07 00 63 07 00 7E 07 00 65 07 00 5E 07 00 A3 00 02 07 00 A3 07 00 5E FF 00 0A 00 08 07 00 03 07 00 5E 05 07 00 63 07 00 7E 07 00 65 07 00 5E 07 00 A3 00 02 07 00 A3 07 00 5E FF 00 01 00 08 07 00 03 07 00 5E 05 07 00 63 07 00 7E 07 00 65 07 00 5E 07 00 A3 00 03 07 00 A3 07 00 5E 01 FF 00 1C 00 08 07 00 03 07 00 5E 05 07 00 63 07 00 7E 07 00 65 07 00 5E 07 00 A3 00 02 07 00 A3 07 00 5E FF 00 02 00 00 00 01 07 00 40 FF 00 00 00 08 07 00 03 07 00 5E 05 07 00 63 07 00 7E 07 00 65 07 00 5E 07 00 A3 00 02 07 00 A3 07 00 5E 45 07 00 40 40 07 00 B9 FF 00 0E 00 09 07 00 03 07 00 5E 05 07 00 63 07 00 7E 07 00 65 07 00 5E 07 00 A3 07 00 B9 00 01 07 00 B9 FF 00 01 00 09 07 00 03 07 00 5E 05 07 00 63 07 00 7E 07 00 65 07 00 5E 07 00 A3 07 00 B9 00 02 07 00 B9 01 5B 07 00 B9 42 07 00 40 40 07 00 B9 45 07 00 40 40 07 00 C4 FF 00 0C 00 09 07 00 03 07 00 5E 05 07 00 63 07 00 7E 07 00 65 07 00 5E 07 00 A3 07 00 B9 00 02 07 00 C4 07 00 5E FF 00 01 00 09 07 00 03 07 00 5E 05 07 00 63 07 00 7E 07 00 65 07 00 5E 07 00 A3 07 00 B9 00 03 07 00 C4 07 00 5E 01 FF 00 1D 00 09 07 00 03 07 00 5E 05 07 00 63 07 00 7E 07 00 65 07 00 5E 07 00 A3 07 00 B9 00 02 07 00 C4 07 00 5E 42 07 00 40 FF 00 00 00 09 07 00 03 07 00 5E 05 07 00 63 07 00 7E 07 00 65 07 00 5E 07 00 A3 07 00 B9 00 02 07 00 C4 07 00 5E 45 07 00 40 FF 00 00 00 09 07 00 03 07 00 5E 05 07 00 63 07 00 7E 07 00 65 07 00 5E 07 00 A3 07 00 B9 00 02 07 00 C4 07 00 5E 42 07 00 40 FF 00 00 00 09 07 00 03 07 00 5E 05 07 00 63 07 00 7E 07 00 65 07 00 5E 07 00 A3 07 00 B9 00 02 07 00 C4 07 00 5E 45 07 00 40 40 07 00 B9 42 07 00 30 40 07 00 B9 45 07 00 40 40 07 00 5E FF 00 0D 00 09 07 00 03 07 00 5E 07 00 5E 07 00 63 07 00 7E 07 00 65 07 00 5E 07 00 A3 07 00 B9 00 01 07 00 7E FF 00 01 00 09 07 00 03 07 00 5E 07 00 5E 07 00 63 07 00 7E 07 00 65 07 00 5E 07 00 A3 07 00 B9 00 02 07 00 7E 01 5E 07 00 7E 42 07 00 40 40 07 00 7E 45 07 00 40 00 FF 00 02 00 03 07 00 03 07 00 5E 07 00 5E 00 01 07 00 18 4A 07 00 18 FF 00 01 00 03 07 00 03 07 00 5E 07 00 5E 00 02 07 00 18 01 5C 07 00 18 FF 00 04 00 00 00 01 07 00 40 FF 00 00 00 04 07 00 03 07 00 5E 07 00 5E 07 00 18 00 01 07 00 18 45 07 00 40 00 FF 00 01 00 04 07 00 03 07 00 5E 07 00 5E 07 00 DA 00 00 0A 41 01 1B FF 00 01 00 07 07 00 03 07 00 5E 05 07 00 63 07 00 7E 07 00 65 07 00 5E 00 02 07 00 65 07 00 65 FF 00 01 00 02 07 00 03 07 00 5E 00 02 07 00 49 07 00 5E 01 41 07 00 49 FF 00 01 00 04 07 00 03 07 00 5E 05 07 00 63 00 03 08 01 93 08 01 93 07 00 80 FE 00 01 07 00 7E 07 00 65 07 00 5E FF 00 01 00 07 07 00 03 07 00 5E 05 07 00 63 07 00 7E 07 00 65 07 00 5E 00 02 08 03 23 08 03 23 FF 00 01 00 04 07 00 03 07 00 5E 07 00 5E 07 00 DA 00 00 FF 00 01 00 04 07 00 03 07 00 5E 05 07 00 63 00 05 08 01 93 08 01 93 08 01 97 08 01 97 07 00 DC FF 00 01 00 09 07 00 03 07 00 5E 05 07 00 63 07 00 7E 07 00 65 07 00 5E 07 00 A3 07 00 B9 00 01 07 00 B9 FA 00 01 FF 00 01 00 08 07 00 03 07 00 5E 05 07 00 63 07 00 7E 07 00 65 07 00 5E 07 00 A3 00 02 07 00 A3 07 00 5E FF 00 01 00 09 07 00 03 07 00 5E 05 07 00 63 07 00 7E 07 00 65 07 00 5E 07 00 A3 07 00 B9 00 02 07 00 C4 07 00 5E FF 00 01 00 02 07 00 03 07 00 5E 00 01 05 FF 00 01 00 09 07 00 03 07 00 5E 07 00 5E 07 00 63 07 00 7E 07 00 65 07 00 5E 07 00 A3 07 00 B9 00 01 07 00 7E FF 00 01 00 03 07 00 03 07 00 5E 07 00 5E 00 01 07 00 18 FF 00 01 00 03 07 00 03 07 00 5E 05 00 03 08 01 19 08 01 19 07 00 65 FF 00 01 00 02 07 00 03 07 00 5E 00 01 07 00 49 FF 00 01 00 07 07 00 03 07 00 5E 05 07 00 63 07 00 7E 07 00 65 07 00 5E 00 03 07 00 65 07 00 65 07 00 5E FF 00 01 00 07 07 00 03 07 00 5E 05 07 00 63 07 00 7E 07 00 65 07 00 5E 00 02 07 00 65 07 00 5E FF 00 01 00 02 07 00 03 07 00 5E 00 01 07 00 40 43 05 44 07 00 40 47 05 47 07 00 40
        //    Exceptions:
        //  Try           Handler
        //  Start  End    Start  End    Type                                       
        //  -----  -----  -----  -----  -------------------------------------------
        //  281    292    1178   1235   Ljava/lang/Exception;
        //  293    394    1178   1235   Ljava/lang/Exception;
        //  395    911    1178   1235   Ljava/lang/Exception;
        //  912    975    1178   1235   Ljava/lang/Exception;
        //  976    1175   1178   1235   Ljava/lang/Exception;
        //  8      20     1327   1335   Any
        //  1327   1335   1327   1335   Ljava/lang/AssertionError;
        //  1343   1345   3      8      Any
        //  76     83     83     84     Any
        //  77     83     76     77     Ljava/lang/ArrayIndexOutOfBoundsException;
        //  77     83     83     84     Any
        //  77     83     83     84     Any
        //  77     83     76     77     Any
        //  223    230    230    231    Any
        //  223    230    3      8      Ljava/lang/UnsupportedOperationException;
        //  224    230    3      8      Any
        //  224    230    223    224    Ljava/lang/RuntimeException;
        //  223    230    230    231    Ljava/lang/RuntimeException;
        //  293    299    299    300    Any
        //  293    299    3      8      Any
        //  293    299    299    300    Ljava/lang/UnsupportedOperationException;
        //  293    299    299    300    Ljava/lang/IllegalStateException;
        //  293    299    299    300    Ljava/lang/UnsupportedOperationException;
        //  305    312    312    313    Any
        //  305    312    305    306    Ljava/util/NoSuchElementException;
        //  306    312    312    313    Ljava/lang/IndexOutOfBoundsException;
        //  305    312    3      8      Ljava/lang/IllegalArgumentException;
        //  306    312    305    306    Ljava/lang/ClassCastException;
        //  316    323    323    324    Any
        //  317    323    316    317    Ljava/lang/ClassCastException;
        //  316    323    316    317    Any
        //  316    323    323    324    Ljava/lang/StringIndexOutOfBoundsException;
        //  316    323    316    317    Any
        //  372    379    379    380    Any
        //  372    379    3      8      Any
        //  372    379    379    380    Any
        //  372    379    372    373    Ljava/lang/AssertionError;
        //  372    379    379    380    Ljava/lang/ArithmeticException;
        //  383    390    390    391    Any
        //  383    390    390    391    Ljava/lang/IllegalArgumentException;
        //  384    390    383    384    Any
        //  383    390    3      8      Ljava/lang/AssertionError;
        //  384    390    383    384    Any
        //  395    401    401    402    Any
        //  395    401    401    402    Any
        //  395    401    401    402    Ljava/lang/NumberFormatException;
        //  395    401    3      8      Ljava/util/NoSuchElementException;
        //  395    401    3      8      Any
        //  415    422    422    423    Any
        //  416    422    422    423    Ljava/lang/NegativeArraySizeException;
        //  416    422    415    416    Ljava/lang/StringIndexOutOfBoundsException;
        //  415    422    3      8      Ljava/lang/UnsupportedOperationException;
        //  416    422    415    416    Any
        //  467    474    474    475    Any
        //  468    474    474    475    Ljava/lang/ArithmeticException;
        //  467    474    474    475    Ljava/lang/ArrayIndexOutOfBoundsException;
        //  468    474    467    468    Ljava/lang/StringIndexOutOfBoundsException;
        //  468    474    467    468    Any
        //  519    526    526    527    Any
        //  520    526    3      8      Ljava/lang/AssertionError;
        //  519    526    519    520    Ljava/lang/RuntimeException;
        //  519    526    3      8      Ljava/lang/IllegalArgumentException;
        //  520    526    3      8      Ljava/lang/IllegalArgumentException;
        //  536    543    543    544    Any
        //  537    543    543    544    Ljava/lang/NumberFormatException;
        //  536    543    536    537    Any
        //  536    543    543    544    Ljava/lang/NullPointerException;
        //  536    543    543    544    Any
        //  551    558    558    559    Any
        //  552    558    551    552    Ljava/lang/NullPointerException;
        //  552    558    558    559    Any
        //  551    558    551    552    Any
        //  552    558    3      8      Any
        //  617    624    624    625    Any
        //  617    624    624    625    Ljava/lang/IllegalStateException;
        //  618    624    617    618    Ljava/lang/AssertionError;
        //  618    624    617    618    Ljava/lang/NegativeArraySizeException;
        //  618    624    624    625    Any
        //  671    678    678    679    Any
        //  672    678    3      8      Ljava/util/NoSuchElementException;
        //  672    678    671    672    Ljava/lang/AssertionError;
        //  672    678    671    672    Any
        //  672    678    3      8      Ljava/util/NoSuchElementException;
        //  684    691    691    692    Any
        //  684    691    684    685    Ljava/lang/UnsupportedOperationException;
        //  685    691    3      8      Any
        //  684    691    691    692    Ljava/lang/NegativeArraySizeException;
        //  685    691    3      8      Any
        //  739    746    746    747    Any
        //  740    746    739    740    Ljava/lang/IllegalArgumentException;
        //  739    746    3      8      Any
        //  740    746    739    740    Any
        //  739    746    739    740    Ljava/lang/StringIndexOutOfBoundsException;
        //  791    798    798    799    Any
        //  792    798    3      8      Any
        //  791    798    798    799    Ljava/lang/IllegalStateException;
        //  792    798    791    792    Any
        //  791    798    791    792    Ljava/lang/StringIndexOutOfBoundsException;
        //  851    858    858    859    Any
        //  852    858    3      8      Any
        //  851    858    851    852    Any
        //  852    858    858    859    Any
        //  852    858    851    852    Ljava/lang/ArithmeticException;
        //  912    918    918    919    Any
        //  912    918    918    919    Ljava/lang/AssertionError;
        //  912    918    3      8      Any
        //  912    918    3      8      Ljava/lang/EnumConstantNotPresentException;
        //  912    918    918    919    Ljava/util/ConcurrentModificationException;
        //  922    929    929    930    Any
        //  922    929    929    930    Ljava/lang/ArrayIndexOutOfBoundsException;
        //  922    929    922    923    Ljava/lang/EnumConstantNotPresentException;
        //  923    929    922    923    Ljava/lang/ClassCastException;
        //  922    929    929    930    Any
        //  976    982    982    983    Any
        //  976    982    3      8      Any
        //  976    982    982    983    Any
        //  976    982    3      8      Any
        //  976    982    982    983    Any
        //  1031   1038   1038   1039   Any
        //  1032   1038   3      8      Any
        //  1032   1038   1031   1032   Any
        //  1031   1038   3      8      Ljava/lang/IllegalStateException;
        //  1031   1038   1038   1039   Ljava/lang/NullPointerException;
        //  1087   1094   1094   1095   Any
        //  1087   1094   3      8      Ljava/lang/AssertionError;
        //  1087   1094   3      8      Any
        //  1087   1094   1087   1088   Ljava/util/ConcurrentModificationException;
        //  1088   1094   1087   1088   Any
        //  1098   1105   1105   1106   Any
        //  1098   1105   1098   1099   Any
        //  1099   1105   3      8      Ljava/lang/NegativeArraySizeException;
        //  1098   1105   1105   1106   Ljava/lang/ArrayIndexOutOfBoundsException;
        //  1098   1105   3      8      Ljava/lang/EnumConstantNotPresentException;
        //  1109   1116   1116   1117   Any
        //  1110   1116   1116   1117   Ljava/lang/NegativeArraySizeException;
        //  1109   1116   1109   1110   Ljava/lang/NumberFormatException;
        //  1109   1116   1109   1110   Ljava/lang/NumberFormatException;
        //  1110   1116   1116   1117   Any
        //  1167   1174   1174   1175   Any
        //  1167   1174   1174   1175   Any
        //  1167   1174   3      8      Any
        //  1167   1174   1167   1168   Any
        //  1168   1174   1174   1175   Any
        //  1226   1232   1232   1233   Any
        //  1226   1232   3      8      Ljava/util/NoSuchElementException;
        //  1226   1232   1232   1233   Ljava/util/NoSuchElementException;
        //  1226   1232   1232   1233   Ljava/util/ConcurrentModificationException;
        //  1226   1232   3      8      Ljava/lang/IndexOutOfBoundsException;
        // 
        // The error that occurred was:
        // 
        // java.lang.IndexOutOfBoundsException: Index -1 out of bounds for length 0
        //     at java.base/jdk.internal.util.Preconditions.outOfBounds(Preconditions.java:64)
        //     at java.base/jdk.internal.util.Preconditions.outOfBoundsCheckIndex(Preconditions.java:70)
        //     at java.base/jdk.internal.util.Preconditions.checkIndex(Preconditions.java:248)
        //     at java.base/java.util.Objects.checkIndex(Objects.java:372)
        //     at java.base/java.util.ArrayList.remove(ArrayList.java:535)
        //     at com.strobel.assembler.ir.StackMappingVisitor.pop(StackMappingVisitor.java:267)
        //     at com.strobel.assembler.ir.StackMappingVisitor$InstructionAnalyzer.execute(StackMappingVisitor.java:577)
        //     at com.strobel.assembler.ir.StackMappingVisitor$InstructionAnalyzer.visit(StackMappingVisitor.java:398)
        //     at com.strobel.decompiler.ast.AstBuilder.performStackAnalysis(AstBuilder.java:2030)
        //     at com.strobel.decompiler.ast.AstBuilder.build(AstBuilder.java:108)
        //     at com.strobel.decompiler.languages.java.ast.AstMethodBodyBuilder.createMethodBody(AstMethodBodyBuilder.java:211)
        //     at com.strobel.decompiler.languages.java.ast.AstMethodBodyBuilder.createMethodBody(AstMethodBodyBuilder.java:99)
        //     at com.strobel.decompiler.languages.java.ast.AstBuilder.createMethodBody(AstBuilder.java:782)
        //     at com.strobel.decompiler.languages.java.ast.AstBuilder.createMethod(AstBuilder.java:675)
        //     at com.strobel.decompiler.languages.java.ast.AstBuilder.addTypeMembers(AstBuilder.java:552)
        //     at com.strobel.decompiler.languages.java.ast.AstBuilder.createTypeCore(AstBuilder.java:519)
        //     at com.strobel.decompiler.languages.java.ast.AstBuilder.createTypeNoCache(AstBuilder.java:161)
        //     at com.strobel.decompiler.languages.java.ast.AstBuilder.createType(AstBuilder.java:150)
        //     at com.strobel.decompiler.languages.java.ast.AstBuilder.addType(AstBuilder.java:125)
        //     at com.strobel.decompiler.languages.java.JavaLanguage.buildAst(JavaLanguage.java:71)
        //     at com.strobel.decompiler.languages.java.JavaLanguage.decompileType(JavaLanguage.java:59)
        //     at com.strobel.decompiler.DecompilerDriver.decompileType(DecompilerDriver.java:330)
        //     at com.strobel.decompiler.DecompilerDriver.decompileJar(DecompilerDriver.java:251)
        //     at com.strobel.decompiler.DecompilerDriver.main(DecompilerDriver.java:126)
        // 
        throw new IllegalStateException("An error occurred while decompiling this method.");
    }
    
    static {
        f03.c = new f03();
    }
    
    public f03() {
        while (true) {
            int n = 0;
            Label_0013: {
                if (fc.1 != 0) {
                    n = -1456650732;
                    break Label_0013;
                }
                n = -1552959760;
            }
            switch (n ^ 0x61CF7010) {
                case -536172904: {
                    continue;
                }
                default: {
                    while (true) {
                        int n2 = 0;
                        Label_0058: {
                            if (fc.c < 0) {
                                n2 = 1350961707;
                                break Label_0058;
                            }
                            n2 = 946850815;
                        }
                        switch (n2 ^ 0xE8C0CA19) {
                            case -1203322830: {
                                continue;
                            }
                            case -793837082: {
                                this.c = new ConcurrentLinkedQueue<String>();
                                while (true) {
                                    int n3 = 0;
                                    Label_0115: {
                                        if (fc.c < 0) {
                                            n3 = 1733025931;
                                            break Label_0115;
                                        }
                                        n3 = -1644129654;
                                    }
                                    switch (n3 ^ 0xC589B171) {
                                        case -31284252: {
                                            continue;
                                        }
                                        default: {
                                            this.c = new HashMap<String, String>();
                                            while (true) {
                                                int n4 = 0;
                                                Label_0168: {
                                                    if (fc.1 != 0) {
                                                        n4 = 201096799;
                                                        break Label_0168;
                                                    }
                                                    n4 = 1857644911;
                                                }
                                                switch (n4 ^ 0xC0EEB092) {
                                                    case -887959859: {
                                                        continue;
                                                    }
                                                    case -1369974275: {
                                                        while (true) {
                                                            int n5 = 0;
                                                            Label_0214: {
                                                                if (fc.c < 0) {
                                                                    n5 = -1348212187;
                                                                    break Label_0214;
                                                                }
                                                                n5 = -1002384820;
                                                            }
                                                            switch (n5 ^ 0x4FC0367B) {
                                                                case -530326434: {
                                                                    continue;
                                                                }
                                                                case -1954487241: {
                                                                    final fbu c = new fbu();
                                                                    while (true) {
                                                                        int n6 = 0;
                                                                        Label_0260: {
                                                                            if (fc.c < 0) {
                                                                                n6 = 898907866;
                                                                                break Label_0260;
                                                                            }
                                                                            n6 = 1416515385;
                                                                        }
                                                                        switch (n6 ^ 0x69F5B6A2) {
                                                                            case 1549895800: {
                                                                                continue;
                                                                            }
                                                                            case 1033632155: {
                                                                                this.c = c;
                                                                                while (true) {
                                                                                    int n7 = 0;
                                                                                    Label_0310: {
                                                                                        if (fc.0 != 0) {
                                                                                            n7 = 1260782327;
                                                                                            break Label_0310;
                                                                                        }
                                                                                        n7 = -304528107;
                                                                                    }
                                                                                    switch (n7 ^ 0x6F64298F) {
                                                                                        case 608316280: {
                                                                                            continue;
                                                                                        }
                                                                                        case -2101515110: {
                                                                                            final Thread thread = new Thread(this::0);
                                                                                            while (true) {
                                                                                                int n8 = 0;
                                                                                                Label_0364: {
                                                                                                    if (fc.1 != 0) {
                                                                                                        n8 = 210242797;
                                                                                                        break Label_0364;
                                                                                                    }
                                                                                                    n8 = 1457562376;
                                                                                                }
                                                                                                switch (n8 ^ 0x7401762F) {
                                                                                                    case 2022275778: {
                                                                                                        continue;
                                                                                                    }
                                                                                                    case 585225511: {
                                                                                                        thread.start();
                                                                                                        return;
                                                                                                    }
                                                                                                    default: {
                                                                                                        throw null;
                                                                                                    }
                                                                                                }
                                                                                                break;
                                                                                            }
                                                                                            break;
                                                                                        }
                                                                                        default: {
                                                                                            throw null;
                                                                                        }
                                                                                    }
                                                                                    break;
                                                                                }
                                                                                break;
                                                                            }
                                                                            default: {
                                                                                throw null;
                                                                            }
                                                                        }
                                                                        break;
                                                                    }
                                                                    break;
                                                                }
                                                                default: {
                                                                    throw null;
                                                                }
                                                            }
                                                            break;
                                                        }
                                                        break;
                                                    }
                                                    default: {
                                                        throw null;
                                                    }
                                                }
                                                break;
                                            }
                                            break;
                                        }
                                        case -1564323334: {
                                            throw null;
                                        }
                                    }
                                    break;
                                }
                                break;
                            }
                            default: {
                                throw null;
                            }
                        }
                        break;
                    }
                    break;
                }
                case -924699132: {
                    throw null;
                }
            }
            break;
        }
    }
    
    public void c() {
        fbS.dN(this, 1326765456);
    }
    
    public String c(final String p0) {
        // 
        // This method could not be decompiled.
        // 
        // Original Bytecode:
        // 
        //     3: dup            
        //     4: ifnull          364
        //     7: athrow         
        //     8: aconst_null    
        //     9: getstatic       dev/nuker/pyro/fc.0:I
        //    12: ifgt            356
        //    15: pop            
        //    16: aconst_null    
        //    17: goto            348
        //    20: nop            
        //    21: nop            
        //    22: nop            
        //    23: athrow         
        //    24: aload_0        
        //    25: getfield        dev/nuker/pyro/f03.c:Ljava/util/HashMap;
        //    28: aload_1        
        //    29: goto            33
        //    32: athrow         
        //    33: invokevirtual   java/util/HashMap.containsKey:(Ljava/lang/Object;)Z
        //    36: goto            40
        //    39: athrow         
        //    40: ifeq            108
        //    43: aload_0        
        //    44: getfield        dev/nuker/pyro/f03.c:Ljava/util/HashMap;
        //    47: getstatic       dev/nuker/pyro/fc.c:I
        //    50: ifge            59
        //    53: ldc_w           875565502
        //    56: goto            62
        //    59: ldc_w           -621794692
        //    62: ldc_w           -222669893
        //    65: ixor           
        //    66: lookupswitch {
        //          -964017659: 59
        //          675969479: 92
        //          default: 335
        //        }
        //    92: aload_1        
        //    93: goto            97
        //    96: athrow         
        //    97: invokevirtual   java/util/HashMap.get:(Ljava/lang/Object;)Ljava/lang/Object;
        //   100: goto            104
        //   103: athrow         
        //   104: checkcast       Ljava/lang/String;
        //   107: areturn        
        //   108: aload_0        
        //   109: getstatic       dev/nuker/pyro/fc.0:I
        //   112: ifeq            121
        //   115: ldc_w           -1975365869
        //   118: goto            124
        //   121: ldc_w           -1224901649
        //   124: ldc_w           1710912350
        //   127: ixor           
        //   128: lookupswitch {
        //          -754513743: 156
        //          -273138611: 121
        //          default: 333
        //        }
        //   156: getfield        dev/nuker/pyro/f03.c:Ljava/util/concurrent/ConcurrentLinkedQueue;
        //   159: aload_1        
        //   160: goto            164
        //   163: athrow         
        //   164: invokevirtual   java/util/concurrent/ConcurrentLinkedQueue.contains:(Ljava/lang/Object;)Z
        //   167: goto            171
        //   170: athrow         
        //   171: ifne            180
        //   174: ldc_w           -1674924787
        //   177: goto            183
        //   180: ldc_w           -1674924788
        //   183: ldc_w           -1277261681
        //   186: ixor           
        //   187: tableswitch {
        //          1609059076: 208
        //          1609059077: 316
        //          default: 174
        //        }
        //   208: getstatic       dev/nuker/pyro/fc.1:I
        //   211: ifeq            220
        //   214: ldc_w           -1812615910
        //   217: goto            223
        //   220: ldc_w           2033160447
        //   223: ldc_w           -374336154
        //   226: ixor           
        //   227: lookupswitch {
        //          -1308387892: 220
        //          2051389564: 337
        //          default: 252
        //        }
        //   252: aload_0        
        //   253: getfield        dev/nuker/pyro/f03.c:Ljava/util/concurrent/ConcurrentLinkedQueue;
        //   256: aload_1        
        //   257: getstatic       dev/nuker/pyro/fc.0:I
        //   260: ifeq            269
        //   263: ldc_w           -1377029394
        //   266: goto            272
        //   269: ldc_w           925501882
        //   272: ldc_w           -741471815
        //   275: ixor           
        //   276: lookupswitch {
        //          -454819837: 304
        //          2116172631: 269
        //          default: 331
        //        }
        //   304: goto            308
        //   307: athrow         
        //   308: invokevirtual   java/util/concurrent/ConcurrentLinkedQueue.add:(Ljava/lang/Object;)Z
        //   311: goto            315
        //   314: athrow         
        //   315: pop            
        //   316: ldc_w           "\u2302\u149c\u8a35\ub1d8\uce88\ued33\ub22d\ue61b\udb7e\ueea0\ua7a9\u1e02\ue17f"
        //   319: goto            323
        //   322: athrow         
        //   323: invokestatic    invokestatic   !!! ERROR
        //   326: goto            330
        //   329: athrow         
        //   330: areturn        
        //   331: aconst_null    
        //   332: athrow         
        //   333: aconst_null    
        //   334: athrow         
        //   335: aconst_null    
        //   336: athrow         
        //   337: aconst_null    
        //   338: athrow         
        //   339: pop            
        //   340: goto            24
        //   343: pop            
        //   344: aconst_null    
        //   345: goto            339
        //   348: dup            
        //   349: ifnull          339
        //   352: checkcast       Ljava/lang/Throwable;
        //   355: athrow         
        //   356: dup            
        //   357: ifnull          343
        //   360: checkcast       Ljava/lang/Throwable;
        //   363: athrow         
        //   364: aconst_null    
        //   365: athrow         
        //    StackMapTable: 00 33 43 07 00 40 04 FF 00 0B 00 00 00 01 07 00 40 FD 00 03 07 00 03 07 00 5E 47 07 00 1A FF 00 00 00 02 07 00 03 07 00 5E 00 02 07 00 49 07 00 5E 45 07 00 40 40 01 52 07 00 49 FF 00 02 00 02 07 00 03 07 00 5E 00 02 07 00 49 01 5D 07 00 49 43 07 00 40 FF 00 00 00 02 07 00 03 07 00 5E 00 02 07 00 49 07 00 5E 45 07 00 40 40 07 00 DA 03 4C 07 00 03 FF 00 02 00 02 07 00 03 07 00 5E 00 02 07 00 03 01 5F 07 00 03 46 07 00 38 FF 00 00 00 02 07 00 03 07 00 5E 00 02 07 00 E9 07 00 5E 45 07 00 40 40 01 02 05 42 01 18 0B 42 01 1C FF 00 10 00 02 07 00 03 07 00 5E 00 02 07 00 E9 07 00 5E FF 00 02 00 02 07 00 03 07 00 5E 00 03 07 00 E9 07 00 5E 01 FF 00 1F 00 02 07 00 03 07 00 5E 00 02 07 00 E9 07 00 5E 42 07 00 20 FF 00 00 00 02 07 00 03 07 00 5E 00 02 07 00 E9 07 00 5E 45 07 00 40 40 01 00 FF 00 05 00 00 00 01 07 00 40 FF 00 00 00 02 07 00 03 07 00 5E 00 01 07 00 5E 45 07 00 40 40 07 00 5E FF 00 00 00 02 07 00 03 07 00 5E 00 02 07 00 E9 07 00 5E 41 07 00 03 41 07 00 49 01 41 07 00 40 43 05 44 07 00 40 47 05 47 07 00 40
        //    Exceptions:
        //  Try           Handler
        //  Start  End    Start  End    Type                                       
        //  -----  -----  -----  -----  -------------------------------------------
        //  8      20     348    356    Any
        //  348    356    348    356    Any
        //  364    366    3      8      Any
        //  32     39     39     40     Any
        //  33     39     32     33     Ljava/lang/AssertionError;
        //  33     39     39     40     Ljava/util/ConcurrentModificationException;
        //  33     39     3      8      Ljava/lang/NumberFormatException;
        //  33     39     39     40     Any
        //  96     103    103    104    Any
        //  96     103    96     97     Ljava/lang/UnsupportedOperationException;
        //  97     103    96     97     Any
        //  96     103    96     97     Ljava/lang/IllegalStateException;
        //  97     103    96     97     Ljava/lang/IndexOutOfBoundsException;
        //  163    170    170    171    Any
        //  163    170    3      8      Any
        //  163    170    3      8      Any
        //  164    170    163    164    Ljava/util/ConcurrentModificationException;
        //  163    170    170    171    Ljava/lang/UnsupportedOperationException;
        //  307    314    314    315    Any
        //  307    314    307    308    Ljava/lang/ArrayIndexOutOfBoundsException;
        //  307    314    3      8      Any
        //  307    314    307    308    Ljava/lang/NullPointerException;
        //  308    314    314    315    Any
        //  323    329    329    330    Any
        //  323    329    329    330    Any
        //  323    329    3      8      Ljava/util/ConcurrentModificationException;
        //  323    329    3      8      Any
        //  323    329    329    330    Ljava/lang/IllegalArgumentException;
        // 
        // The error that occurred was:
        // 
        // java.lang.IndexOutOfBoundsException: Index -1 out of bounds for length 0
        //     at java.base/jdk.internal.util.Preconditions.outOfBounds(Preconditions.java:64)
        //     at java.base/jdk.internal.util.Preconditions.outOfBoundsCheckIndex(Preconditions.java:70)
        //     at java.base/jdk.internal.util.Preconditions.checkIndex(Preconditions.java:248)
        //     at java.base/java.util.Objects.checkIndex(Objects.java:372)
        //     at java.base/java.util.ArrayList.remove(ArrayList.java:535)
        //     at com.strobel.assembler.ir.StackMappingVisitor.pop(StackMappingVisitor.java:267)
        //     at com.strobel.assembler.ir.StackMappingVisitor$InstructionAnalyzer.execute(StackMappingVisitor.java:577)
        //     at com.strobel.assembler.ir.StackMappingVisitor$InstructionAnalyzer.visit(StackMappingVisitor.java:398)
        //     at com.strobel.decompiler.ast.AstBuilder.performStackAnalysis(AstBuilder.java:2030)
        //     at com.strobel.decompiler.ast.AstBuilder.build(AstBuilder.java:108)
        //     at com.strobel.decompiler.languages.java.ast.AstMethodBodyBuilder.createMethodBody(AstMethodBodyBuilder.java:211)
        //     at com.strobel.decompiler.languages.java.ast.AstMethodBodyBuilder.createMethodBody(AstMethodBodyBuilder.java:99)
        //     at com.strobel.decompiler.languages.java.ast.AstBuilder.createMethodBody(AstBuilder.java:782)
        //     at com.strobel.decompiler.languages.java.ast.AstBuilder.createMethod(AstBuilder.java:675)
        //     at com.strobel.decompiler.languages.java.ast.AstBuilder.addTypeMembers(AstBuilder.java:552)
        //     at com.strobel.decompiler.languages.java.ast.AstBuilder.createTypeCore(AstBuilder.java:519)
        //     at com.strobel.decompiler.languages.java.ast.AstBuilder.createTypeNoCache(AstBuilder.java:161)
        //     at com.strobel.decompiler.languages.java.ast.AstBuilder.createType(AstBuilder.java:150)
        //     at com.strobel.decompiler.languages.java.ast.AstBuilder.addType(AstBuilder.java:125)
        //     at com.strobel.decompiler.languages.java.JavaLanguage.buildAst(JavaLanguage.java:71)
        //     at com.strobel.decompiler.languages.java.JavaLanguage.decompileType(JavaLanguage.java:59)
        //     at com.strobel.decompiler.DecompilerDriver.decompileType(DecompilerDriver.java:330)
        //     at com.strobel.decompiler.DecompilerDriver.decompileJar(DecompilerDriver.java:251)
        //     at com.strobel.decompiler.DecompilerDriver.main(DecompilerDriver.java:126)
        // 
        throw new IllegalStateException("An error occurred while decompiling this method.");
    }
}
