// 
// Decompiled by Procyon v0.5.36
// 

package dev.nuker.pyro;

import java.lang.reflect.Method;
import org.jetbrains.annotations.NotNull;

public class f09 extends f08
{
    @NotNull
    public Class<?> c;
    public Object c;
    @NotNull
    public Method c;
    
    static {
        throw t;
    }
    
    @NotNull
    @Override
    public Class c() {
        // 
        // This method could not be decompiled.
        // 
        // Original Bytecode:
        // 
        //     1: getstatic       dev/nuker/pyro/fc.0:I
        //     4: ifgt            38
        //     7: pop            
        //     8: aconst_null    
        //     9: goto            30
        //    12: nop            
        //    13: nop            
        //    14: nop            
        //    15: athrow         
        //    16: aload_0        
        //    17: getfield        dev/nuker/pyro/f09.c:Ljava/lang/Class;
        //    20: areturn        
        //    21: pop            
        //    22: goto            16
        //    25: pop            
        //    26: aconst_null    
        //    27: goto            21
        //    30: dup            
        //    31: ifnull          21
        //    34: checkcast       Ljava/lang/Throwable;
        //    37: athrow         
        //    38: dup            
        //    39: ifnull          25
        //    42: checkcast       Ljava/lang/Throwable;
        //    45: athrow         
        //    StackMapTable: 00 06 FF 00 0C 00 00 00 01 07 00 16 FC 00 03 07 00 03 44 07 00 16 43 05 44 07 00 16 47 05
        //    Exceptions:
        //  Try           Handler
        //  Start  End    Start  End    Type
        //  -----  -----  -----  -----  ----
        //  0      12     30     38     Any
        //  30     38     30     38     Any
        // 
        // The error that occurred was:
        // 
        // java.lang.IndexOutOfBoundsException: Index -1 out of bounds for length 0
        //     at java.base/jdk.internal.util.Preconditions.outOfBounds(Preconditions.java:64)
        //     at java.base/jdk.internal.util.Preconditions.outOfBoundsCheckIndex(Preconditions.java:70)
        //     at java.base/jdk.internal.util.Preconditions.checkIndex(Preconditions.java:248)
        //     at java.base/java.util.Objects.checkIndex(Objects.java:372)
        //     at java.base/java.util.ArrayList.remove(ArrayList.java:535)
        //     at com.strobel.assembler.ir.StackMappingVisitor.pop(StackMappingVisitor.java:267)
        //     at com.strobel.assembler.ir.StackMappingVisitor$InstructionAnalyzer.execute(StackMappingVisitor.java:543)
        //     at com.strobel.assembler.ir.StackMappingVisitor$InstructionAnalyzer.visit(StackMappingVisitor.java:398)
        //     at com.strobel.decompiler.ast.AstBuilder.performStackAnalysis(AstBuilder.java:2030)
        //     at com.strobel.decompiler.ast.AstBuilder.build(AstBuilder.java:108)
        //     at com.strobel.decompiler.languages.java.ast.AstMethodBodyBuilder.createMethodBody(AstMethodBodyBuilder.java:211)
        //     at com.strobel.decompiler.languages.java.ast.AstMethodBodyBuilder.createMethodBody(AstMethodBodyBuilder.java:99)
        //     at com.strobel.decompiler.languages.java.ast.AstBuilder.createMethodBody(AstBuilder.java:782)
        //     at com.strobel.decompiler.languages.java.ast.AstBuilder.createMethod(AstBuilder.java:675)
        //     at com.strobel.decompiler.languages.java.ast.AstBuilder.addTypeMembers(AstBuilder.java:552)
        //     at com.strobel.decompiler.languages.java.ast.AstBuilder.createTypeCore(AstBuilder.java:519)
        //     at com.strobel.decompiler.languages.java.ast.AstBuilder.createTypeNoCache(AstBuilder.java:161)
        //     at com.strobel.decompiler.languages.java.ast.AstBuilder.createType(AstBuilder.java:150)
        //     at com.strobel.decompiler.languages.java.ast.AstBuilder.addType(AstBuilder.java:125)
        //     at com.strobel.decompiler.languages.java.JavaLanguage.buildAst(JavaLanguage.java:71)
        //     at com.strobel.decompiler.languages.java.JavaLanguage.decompileType(JavaLanguage.java:59)
        //     at com.strobel.decompiler.DecompilerDriver.decompileType(DecompilerDriver.java:330)
        //     at com.strobel.decompiler.DecompilerDriver.decompileJar(DecompilerDriver.java:251)
        //     at com.strobel.decompiler.DecompilerDriver.main(DecompilerDriver.java:126)
        // 
        throw new IllegalStateException("An error occurred while decompiling this method.");
    }
    
    @NotNull
    public Method c() {
        // 
        // This method could not be decompiled.
        // 
        // Original Bytecode:
        // 
        //     1: getstatic       dev/nuker/pyro/fc.c:I
        //     4: iflt            38
        //     7: pop            
        //     8: aconst_null    
        //     9: goto            30
        //    12: nop            
        //    13: nop            
        //    14: nop            
        //    15: athrow         
        //    16: aload_0        
        //    17: getfield        dev/nuker/pyro/f09.c:Ljava/lang/reflect/Method;
        //    20: areturn        
        //    21: pop            
        //    22: goto            16
        //    25: pop            
        //    26: aconst_null    
        //    27: goto            21
        //    30: dup            
        //    31: ifnull          21
        //    34: checkcast       Ljava/lang/Throwable;
        //    37: athrow         
        //    38: dup            
        //    39: ifnull          25
        //    42: checkcast       Ljava/lang/Throwable;
        //    45: athrow         
        //    StackMapTable: 00 06 FF 00 0C 00 00 00 01 07 00 16 FC 00 03 07 00 03 44 07 00 16 43 05 44 07 00 16 47 05
        //    Exceptions:
        //  Try           Handler
        //  Start  End    Start  End    Type                                  
        //  -----  -----  -----  -----  --------------------------------------
        //  0      12     30     38     Any
        //  30     38     30     38     Ljava/lang/NegativeArraySizeException;
        // 
        // The error that occurred was:
        // 
        // java.lang.IndexOutOfBoundsException: Index -1 out of bounds for length 0
        //     at java.base/jdk.internal.util.Preconditions.outOfBounds(Preconditions.java:64)
        //     at java.base/jdk.internal.util.Preconditions.outOfBoundsCheckIndex(Preconditions.java:70)
        //     at java.base/jdk.internal.util.Preconditions.checkIndex(Preconditions.java:248)
        //     at java.base/java.util.Objects.checkIndex(Objects.java:372)
        //     at java.base/java.util.ArrayList.remove(ArrayList.java:535)
        //     at com.strobel.assembler.ir.StackMappingVisitor.pop(StackMappingVisitor.java:267)
        //     at com.strobel.assembler.ir.StackMappingVisitor$InstructionAnalyzer.execute(StackMappingVisitor.java:543)
        //     at com.strobel.assembler.ir.StackMappingVisitor$InstructionAnalyzer.visit(StackMappingVisitor.java:398)
        //     at com.strobel.decompiler.ast.AstBuilder.performStackAnalysis(AstBuilder.java:2030)
        //     at com.strobel.decompiler.ast.AstBuilder.build(AstBuilder.java:108)
        //     at com.strobel.decompiler.languages.java.ast.AstMethodBodyBuilder.createMethodBody(AstMethodBodyBuilder.java:211)
        //     at com.strobel.decompiler.languages.java.ast.AstMethodBodyBuilder.createMethodBody(AstMethodBodyBuilder.java:99)
        //     at com.strobel.decompiler.languages.java.ast.AstBuilder.createMethodBody(AstBuilder.java:782)
        //     at com.strobel.decompiler.languages.java.ast.AstBuilder.createMethod(AstBuilder.java:675)
        //     at com.strobel.decompiler.languages.java.ast.AstBuilder.addTypeMembers(AstBuilder.java:552)
        //     at com.strobel.decompiler.languages.java.ast.AstBuilder.createTypeCore(AstBuilder.java:519)
        //     at com.strobel.decompiler.languages.java.ast.AstBuilder.createTypeNoCache(AstBuilder.java:161)
        //     at com.strobel.decompiler.languages.java.ast.AstBuilder.createType(AstBuilder.java:150)
        //     at com.strobel.decompiler.languages.java.ast.AstBuilder.addType(AstBuilder.java:125)
        //     at com.strobel.decompiler.languages.java.JavaLanguage.buildAst(JavaLanguage.java:71)
        //     at com.strobel.decompiler.languages.java.JavaLanguage.decompileType(JavaLanguage.java:59)
        //     at com.strobel.decompiler.DecompilerDriver.decompileType(DecompilerDriver.java:330)
        //     at com.strobel.decompiler.DecompilerDriver.decompileJar(DecompilerDriver.java:251)
        //     at com.strobel.decompiler.DecompilerDriver.main(DecompilerDriver.java:126)
        // 
        throw new IllegalStateException("An error occurred while decompiling this method.");
    }
    
    public f09(@NotNull final Object c, @NotNull final Method c2) {
        while (true) {
            int n = 0;
            Label_0015: {
                if (fc.0 != 0) {
                    n = 1064080641;
                    break Label_0015;
                }
                n = 1974188915;
            }
            switch (n ^ 0x1B7A6489) {
                case 605483400: {
                    continue;
                }
                case 1859248122: {
                    while (true) {
                        int n2 = 0;
                        Label_0065: {
                            if (fc.1 != 0) {
                                n2 = 1738963581;
                                break Label_0065;
                            }
                            n2 = 772116730;
                        }
                        switch (n2 ^ 0x21E6A1BE) {
                            case -487036847: {
                                continue;
                            }
                            default: {
                                this.c = c;
                                while (true) {
                                    int n3 = 0;
                                    Label_0114: {
                                        if (fc.c < 0) {
                                            n3 = -1331165649;
                                            break Label_0114;
                                        }
                                        n3 = 1164484385;
                                    }
                                    switch (n3 ^ 0x47FAA5D6) {
                                        case -1071557774: {
                                            continue;
                                        }
                                        default: {
                                            this.c = c2;
                                            while (true) {
                                                int n4 = 0;
                                                Label_0162: {
                                                    if (fc.1 != 0) {
                                                        n4 = -1445478637;
                                                        break Label_0162;
                                                    }
                                                    n4 = 845628880;
                                                }
                                                switch (n4 ^ 0x960F3DEA) {
                                                    case 1071153913: {
                                                        continue;
                                                    }
                                                    case -1536657350: {
                                                        this.c = this.c.getParameterTypes()[0];
                                                        return;
                                                    }
                                                    default: {
                                                        throw null;
                                                    }
                                                }
                                                break;
                                            }
                                            break;
                                        }
                                        case -145579015: {
                                            throw null;
                                        }
                                    }
                                    break;
                                }
                                break;
                            }
                            case 1178655683: {
                                throw null;
                            }
                        }
                        break;
                    }
                    break;
                }
                default: {
                    throw null;
                }
            }
            break;
        }
    }
    
    @Override
    public void accept(@NotNull final Object o) {
        fbS.2S(this, 591814945, o);
    }
}
