// 
// Decompiled by Procyon v0.5.36
// 

package dev.nuker.pyro;

import kotlin.jvm.JvmOverloads;
import org.jetbrains.annotations.Nullable;
import org.jetbrains.annotations.NotNull;
import com.google.gson.JsonElement;

public class f0d extends f0l
{
    public double c;
    public double 0;
    public double 1;
    
    @Override
    public void c(@NotNull final JsonElement jsonElement) {
        fbS.6Y(this, 1965031819, jsonElement);
    }
    
    @Override
    public double 1() {
        return fbS.9M(this, 1490650796);
    }
    
    @JvmOverloads
    public f0d(@NotNull final String s, @NotNull final String s2, @Nullable final String s3, final double n, final double n2, final double n3) {
        while (true) {
            int n4 = 0;
            Label_0013: {
                if (fc.1 != 0) {
                    n4 = 1612887632;
                    break Label_0013;
                }
                n4 = 1461701422;
            }
            switch (n4 ^ 0x5BE991FE) {
                case -795960193: {
                    continue;
                }
                default: {
                    while (true) {
                        int n5 = 0;
                        Label_0060: {
                            if (fc.0 != 0) {
                                n5 = -496548296;
                                break Label_0060;
                            }
                            n5 = -704644456;
                        }
                        switch (n5 ^ 0xAE1E550F) {
                            case 362778905: {
                                continue;
                            }
                            default: {
                                final double n6 = 0.0;
                                final int n7 = 64;
                                final DefaultConstructorMarker defaultConstructorMarker = null;
                                while (true) {
                                    int n8 = 0;
                                    Label_0112: {
                                        if (fc.0 != 0) {
                                            n8 = -1343331548;
                                            break Label_0112;
                                        }
                                        n8 = -239440195;
                                    }
                                    switch (n8 ^ 0x8A45D6A0) {
                                        case 20147877: {
                                            continue;
                                        }
                                        default: {
                                            this(s, s2, s3, n, n2, n3, n6, n7, defaultConstructorMarker);
                                            return;
                                        }
                                        case 632010116: {
                                            throw null;
                                        }
                                    }
                                    break;
                                }
                                break;
                            }
                            case 1283003191: {
                                throw null;
                            }
                        }
                        break;
                    }
                    break;
                }
                case 1003169710: {
                    throw null;
                }
            }
            break;
        }
    }
    
    @NotNull
    @Override
    public f0V 4() {
        Object o = null;
        Label_0008: {
            break Label_0008;
        Label_0061:
            while (true) {
                do {
                    while (true) {
                        break Label_0048;
                        try {
                            o = null;
                            if (fc.1 <= 0) {
                                null;
                                goto Label_0053;
                            }
                            continue Label_0061;
                            f0D f0D = null;
                            try {
                                f0D = new f0D(this);
                            }
                            catch (RuntimeException ex) {}
                            return f0D;
                            continue;
                        }
                        catch (ArithmeticException ex2) {}
                        break;
                    }
                    continue Label_0061;
                } while (o == null);
                break;
            }
        }
        throw (Throwable)o;
    }
    
    static {
        throw t;
    }
    
    public void 0(final double n) {
        fbS.f0(this, 1012262719, n);
    }
    
    @JvmOverloads
    public f0d(@NotNull final String s, @NotNull final String s2, @Nullable final String s3, final double d, final double c, final double 0, final double 2) {
        while (true) {
            int n = 0;
            Label_0013: {
                if (fc.0 != 0) {
                    n = 535107296;
                    break Label_0013;
                }
                n = 2112642877;
            }
            switch (n ^ 0x926A9021) {
                case -1919973695: {
                    continue;
                }
                case -276377828: {
                    while (true) {
                        int n2 = 0;
                        Label_0061: {
                            if (fc.c < 0) {
                                n2 = -1771223566;
                                break Label_0061;
                            }
                            n2 = -316098746;
                        }
                        switch (n2 ^ 0xB58E0C6B) {
                            case 1054645323: {
                                continue;
                            }
                            default: {
                                final Double value = d;
                                while (true) {
                                    int n3 = 0;
                                    Label_0114: {
                                        if (fc.0 != 0) {
                                            n3 = -1573426897;
                                            break Label_0114;
                                        }
                                        n3 = 881778758;
                                    }
                                    switch (n3 ^ 0x125B11B6) {
                                        case -1335068519: {
                                            continue;
                                        }
                                        case 651555312: {
                                            super(s, s2, s3, value);
                                            this.c = c;
                                            this.0 = 0;
                                            this.1 = 2;
                                            return;
                                        }
                                        default: {
                                            throw null;
                                        }
                                    }
                                    break;
                                }
                                break;
                            }
                            case 602098073: {
                                throw null;
                            }
                        }
                        break;
                    }
                    break;
                }
                default: {
                    throw null;
                }
            }
            break;
        }
    }
    
    public void 1(final double n) {
        fbS.f8(this, 337259962, n);
    }
    
    public double c() {
        return fbS.9T(this, 1464687019);
    }
    
    public f0d(final String s, final String s2, final String s3, final double n, final double n2, final double n3, double n4, final int n5, final DefaultConstructorMarker defaultConstructorMarker) {
        if ((n5 & 0x40) != 0x0) {
            n4 = n3 - n2;
        }
        while (true) {
            int n6 = 0;
            Label_0034: {
                if (fc.1 != 0) {
                    n6 = -1202930505;
                    break Label_0034;
                }
                n6 = 1511837700;
            }
            switch (n6 ^ 0x71FD6B9A) {
                case -911091923: {
                    continue;
                }
                case 736213918: {
                    while (true) {
                        int n7 = 0;
                        Label_0079: {
                            if (fc.0 != 0) {
                                n7 = -461483177;
                                break Label_0079;
                            }
                            n7 = 274251699;
                        }
                        switch (n7 ^ 0xCB2ECAC1) {
                            case 136563304: {
                                continue;
                            }
                            default: {
                                while (true) {
                                    int n8 = 0;
                                    Label_0123: {
                                        if (fc.1 != 0) {
                                            n8 = -82051893;
                                            break Label_0123;
                                        }
                                        n8 = 2096783779;
                                    }
                                    switch (n8 ^ 0x4A8C580C) {
                                        case -1315461945: {
                                            continue;
                                        }
                                        case 913717679: {
                                            this(s, s2, s3, n, n2, n3, n4);
                                            return;
                                        }
                                        default: {
                                            throw null;
                                        }
                                    }
                                    break;
                                }
                                break;
                            }
                            case 793811350: {
                                throw null;
                            }
                        }
                        break;
                    }
                    break;
                }
                default: {
                    throw null;
                }
            }
            break;
        }
    }
    
    public void c(final double n) {
        fbS.fc(this, 1774909550, n);
    }
    
    public double 0() {
        return fbS.9Q(this, 483913338);
    }
    
    @NotNull
    @Override
    public JsonElement c() {
        // 
        // This method could not be decompiled.
        // 
        // Original Bytecode:
        // 
        //     3: dup            
        //     4: ifnull          140
        //     7: athrow         
        //     8: aconst_null    
        //     9: getstatic       dev/nuker/pyro/fc.c:I
        //    12: iflt            132
        //    15: pop            
        //    16: aconst_null    
        //    17: goto            124
        //    20: nop            
        //    21: nop            
        //    22: nop            
        //    23: athrow         
        //    24: new             Lcom/google/gson/JsonPrimitive;
        //    27: dup            
        //    28: getstatic       dev/nuker/pyro/fc.c:I
        //    31: ifge            39
        //    34: ldc             -938649955
        //    36: goto            41
        //    39: ldc             -1821898443
        //    41: ldc             8675974
        //    43: ixor           
        //    44: lookupswitch {
        //          -1813222477: 72
        //          -930532325: 39
        //          default: 113
        //        }
        //    72: aload_0        
        //    73: goto            77
        //    76: athrow         
        //    77: invokevirtual   dev/nuker/pyro/f0d.5:()Ldev/nuker/pyro/fw;
        //    80: goto            84
        //    83: athrow         
        //    84: goto            88
        //    87: athrow         
        //    88: invokevirtual   dev/nuker/pyro/fw.0:()Ljava/lang/Object;
        //    91: goto            95
        //    94: athrow         
        //    95: checkcast       Ljava/lang/Number;
        //    98: goto            102
        //   101: athrow         
        //   102: invokespecial   com/google/gson/JsonPrimitive.<init>:(Ljava/lang/Number;)V
        //   105: goto            109
        //   108: athrow         
        //   109: checkcast       Lcom/google/gson/JsonElement;
        //   112: areturn        
        //   113: aconst_null    
        //   114: athrow         
        //   115: pop            
        //   116: goto            24
        //   119: pop            
        //   120: aconst_null    
        //   121: goto            115
        //   124: dup            
        //   125: ifnull          115
        //   128: checkcast       Ljava/lang/Throwable;
        //   131: athrow         
        //   132: dup            
        //   133: ifnull          119
        //   136: checkcast       Ljava/lang/Throwable;
        //   139: athrow         
        //   140: aconst_null    
        //   141: athrow         
        //    StackMapTable: 00 19 43 07 00 3D 04 FF 00 0B 00 00 00 01 07 00 3D FC 00 03 07 00 03 FF 00 0E 00 01 07 00 03 00 02 08 00 18 08 00 18 FF 00 01 00 01 07 00 03 00 03 08 00 18 08 00 18 01 FF 00 1E 00 01 07 00 03 00 02 08 00 18 08 00 18 43 07 00 3D FF 00 00 00 01 07 00 03 00 03 08 00 18 08 00 18 07 00 03 45 07 00 3D FF 00 00 00 01 07 00 03 00 03 08 00 18 08 00 18 07 00 96 42 07 00 3D FF 00 00 00 01 07 00 03 00 03 08 00 18 08 00 18 07 00 96 45 07 00 3D FF 00 00 00 01 07 00 03 00 03 08 00 18 08 00 18 07 00 A2 FF 00 05 00 00 00 01 07 00 3D FF 00 00 00 01 07 00 03 00 03 08 00 18 08 00 18 07 00 9B 45 07 00 3D 40 07 00 8D FF 00 03 00 01 07 00 03 00 02 08 00 18 08 00 18 41 07 00 3D 43 05 44 07 00 3D 47 05 47 07 00 3D
        //    Exceptions:
        //  Try           Handler
        //  Start  End    Start  End    Type                                 
        //  -----  -----  -----  -----  -------------------------------------
        //  8      20     124    132    Any
        //  124    132    124    132    Ljava/lang/IndexOutOfBoundsException;
        //  140    142    3      8      Any
        //  76     83     83     84     Any
        //  77     83     76     77     Any
        //  77     83     3      8      Any
        //  76     83     76     77     Ljava/lang/IndexOutOfBoundsException;
        //  76     83     76     77     Any
        //  87     94     94     95     Any
        //  88     94     3      8      Any
        //  88     94     87     88     Ljava/lang/IllegalStateException;
        //  87     94     87     88     Any
        //  88     94     94     95     Any
        //  102    108    108    109    Any
        //  102    108    3      8      Any
        //  102    108    3      8      Ljava/util/NoSuchElementException;
        //  102    108    108    109    Any
        //  102    108    108    109    Ljava/lang/ArithmeticException;
        // 
        // The error that occurred was:
        // 
        // java.lang.IndexOutOfBoundsException: Index 48 out of bounds for length 48
        //     at java.base/jdk.internal.util.Preconditions.outOfBounds(Preconditions.java:64)
        //     at java.base/jdk.internal.util.Preconditions.outOfBoundsCheckIndex(Preconditions.java:70)
        //     at java.base/jdk.internal.util.Preconditions.checkIndex(Preconditions.java:248)
        //     at java.base/java.util.Objects.checkIndex(Objects.java:372)
        //     at java.base/java.util.ArrayList.get(ArrayList.java:458)
        //     at com.strobel.decompiler.ast.AstBuilder.convertToAst(AstBuilder.java:3321)
        //     at com.strobel.decompiler.ast.AstBuilder.convertToAst(AstBuilder.java:3569)
        //     at com.strobel.decompiler.ast.AstBuilder.convertToAst(AstBuilder.java:3435)
        //     at com.strobel.decompiler.ast.AstBuilder.build(AstBuilder.java:113)
        //     at com.strobel.decompiler.languages.java.ast.AstMethodBodyBuilder.createMethodBody(AstMethodBodyBuilder.java:211)
        //     at com.strobel.decompiler.languages.java.ast.AstMethodBodyBuilder.createMethodBody(AstMethodBodyBuilder.java:99)
        //     at com.strobel.decompiler.languages.java.ast.AstBuilder.createMethodBody(AstBuilder.java:782)
        //     at com.strobel.decompiler.languages.java.ast.AstBuilder.createMethod(AstBuilder.java:675)
        //     at com.strobel.decompiler.languages.java.ast.AstBuilder.addTypeMembers(AstBuilder.java:552)
        //     at com.strobel.decompiler.languages.java.ast.AstBuilder.createTypeCore(AstBuilder.java:519)
        //     at com.strobel.decompiler.languages.java.ast.AstBuilder.createTypeNoCache(AstBuilder.java:161)
        //     at com.strobel.decompiler.languages.java.ast.AstBuilder.createType(AstBuilder.java:150)
        //     at com.strobel.decompiler.languages.java.ast.AstBuilder.addType(AstBuilder.java:125)
        //     at com.strobel.decompiler.languages.java.JavaLanguage.buildAst(JavaLanguage.java:71)
        //     at com.strobel.decompiler.languages.java.JavaLanguage.decompileType(JavaLanguage.java:59)
        //     at com.strobel.decompiler.DecompilerDriver.decompileType(DecompilerDriver.java:330)
        //     at com.strobel.decompiler.DecompilerDriver.decompileJar(DecompilerDriver.java:251)
        //     at com.strobel.decompiler.DecompilerDriver.main(DecompilerDriver.java:126)
        // 
        throw new IllegalStateException("An error occurred while decompiling this method.");
    }
}
