// 
// Decompiled by Procyon v0.5.36
// 

package dev.nuker.pyro;

import org.jetbrains.annotations.Nullable;
import org.jetbrains.annotations.NotNull;

public class f0I extends f0D
{
    public boolean 1;
    
    static {
        throw t;
    }
    
    @Override
    public void c() {
        fbS.dx(this, 1911824839);
    }
    
    public boolean c() {
        return fbS.eK(this, 83289506);
    }
    
    public f0I(@NotNull final f0g f0g) {
        // 
        // This method could not be decompiled.
        // 
        // Original Bytecode:
        // 
        //     1: pop            
        //     2: aload_0        
        //     3: aload_1        
        //     4: checkcast       Ldev/nuker/pyro/f0n;
        //     7: invokespecial   dev/nuker/pyro/f0D.<init>:(Ldev/nuker/pyro/f0n;)V
        //    10: aload_0        
        //    11: aload_1        
        //    12: invokevirtual   dev/nuker/pyro/f0g.c:()Ljava/lang/String;
        //    15: putfield        dev/nuker/pyro/f0I.c:Ljava/lang/String;
        //    18: aload_0        
        //    19: new             Ldev/nuker/pyro/fz;
        //    22: dup            
        //    23: getstatic       dev/nuker/pyro/fc.0:I
        //    26: ifeq            34
        //    29: ldc             -1822039021
        //    31: goto            36
        //    34: ldc             1589592740
        //    36: ldc             -500905991
        //    38: ixor           
        //    39: lookupswitch {
        //          -1130658467: 64
        //          1900094442: 34
        //          default: 426
        //        }
        //    64: aload_1        
        //    65: invokevirtual   dev/nuker/pyro/f0g.3:()Ljava/lang/Object;
        //    68: checkcast       Ljava/lang/Number;
        //    71: invokevirtual   java/lang/Number.intValue:()I
        //    74: i2d            
        //    75: getstatic       dev/nuker/pyro/fc.1:I
        //    78: ifeq            86
        //    81: ldc             -82538003
        //    83: goto            88
        //    86: ldc             1689893473
        //    88: ldc             -1658313777
        //    90: ixor           
        //    91: lookupswitch {
        //          -591131858: 86
        //          1715253794: 432
        //          default: 116
        //        }
        //   116: invokestatic    java/lang/Double.valueOf:(D)Ljava/lang/Double;
        //   119: new             Ldev/nuker/pyro/f0G;
        //   122: dup            
        //   123: aload_0        
        //   124: aload_1        
        //   125: invokespecial   dev/nuker/pyro/f0G.<init>:(Ldev/nuker/pyro/f0I;Ldev/nuker/pyro/f0g;)V
        //   128: checkcast       Ljava/util/function/Consumer;
        //   131: invokespecial   dev/nuker/pyro/fz.<init>:(Ljava/lang/Object;Ljava/util/function/Consumer;)V
        //   134: checkcast       Ldev/nuker/pyro/fw;
        //   137: putfield        dev/nuker/pyro/f0I.c:Ldev/nuker/pyro/fw;
        //   140: getstatic       dev/nuker/pyro/fc.c:I
        //   143: ifge            151
        //   146: ldc             -772593618
        //   148: goto            153
        //   151: ldc             960997267
        //   153: ldc             -1072643993
        //   155: ixor           
        //   156: lookupswitch {
        //          -111712268: 184
        //          300148809: 151
        //          default: 422
        //        }
        //   184: aload_0        
        //   185: new             Ldev/nuker/pyro/fz;
        //   188: dup            
        //   189: getstatic       dev/nuker/pyro/fc.0:I
        //   192: ifeq            200
        //   195: ldc             446390369
        //   197: goto            202
        //   200: ldc             380867588
        //   202: ldc             1504272298
        //   204: ixor           
        //   205: lookupswitch {
        //          1127366603: 200
        //          1327156142: 232
        //          default: 420
        //        }
        //   232: aload_1        
        //   233: invokevirtual   dev/nuker/pyro/f0g.3:()Ljava/lang/Object;
        //   236: checkcast       Ljava/lang/Number;
        //   239: getstatic       dev/nuker/pyro/fc.1:I
        //   242: ifeq            250
        //   245: ldc             1545791034
        //   247: goto            252
        //   250: ldc             447655686
        //   252: ldc             1202833172
        //   254: ixor           
        //   255: lookupswitch {
        //          462627118: 250
        //          1562339346: 280
        //          default: 424
        //        }
        //   280: invokevirtual   java/lang/Number.intValue:()I
        //   283: i2d            
        //   284: invokestatic    java/lang/Double.valueOf:(D)Ljava/lang/Double;
        //   287: new             Ldev/nuker/pyro/f0H;
        //   290: dup            
        //   291: aload_0        
        //   292: invokespecial   dev/nuker/pyro/f0H.<init>:(Ldev/nuker/pyro/f0I;)V
        //   295: checkcast       Ljava/util/function/Consumer;
        //   298: invokespecial   dev/nuker/pyro/fz.<init>:(Ljava/lang/Object;Ljava/util/function/Consumer;)V
        //   301: invokevirtual   dev/nuker/pyro/f0I.c:(Ldev/nuker/pyro/fz;)V
        //   304: getstatic       dev/nuker/pyro/fc.0:I
        //   307: ifeq            315
        //   310: ldc             2018001895
        //   312: goto            317
        //   315: ldc             -933265657
        //   317: ldc             -1253152919
        //   319: ixor           
        //   320: lookupswitch {
        //          -855235442: 428
        //          -219501679: 315
        //          default: 348
        //        }
        //   348: aload_0        
        //   349: aload_1        
        //   350: invokevirtual   dev/nuker/pyro/f0g.0:()I
        //   353: i2d            
        //   354: putfield        dev/nuker/pyro/f0I.c:D
        //   357: aload_0        
        //   358: aload_1        
        //   359: invokevirtual   dev/nuker/pyro/f0g.c:()I
        //   362: i2d            
        //   363: putfield        dev/nuker/pyro/f0I.0:D
        //   366: aload_0        
        //   367: aload_1        
        //   368: getstatic       dev/nuker/pyro/fc.c:I
        //   371: ifge            379
        //   374: ldc             573684107
        //   376: goto            381
        //   379: ldc             -795026894
        //   381: ldc             -1891053887
        //   383: ixor           
        //   384: lookupswitch {
        //          -1384548534: 379
        //          1607734515: 412
        //          default: 430
        //        }
        //   412: invokevirtual   dev/nuker/pyro/f0g.1:()I
        //   415: i2d            
        //   416: putfield        dev/nuker/pyro/f0I.1:D
        //   419: return         
        //   420: aconst_null    
        //   421: athrow         
        //   422: aconst_null    
        //   423: athrow         
        //   424: aconst_null    
        //   425: athrow         
        //   426: aconst_null    
        //   427: athrow         
        //   428: aconst_null    
        //   429: athrow         
        //   430: aconst_null    
        //   431: athrow         
        //   432: aconst_null    
        //   433: athrow         
        //    StackMapTable: 00 1C FF 00 22 00 02 07 00 03 07 00 22 00 03 07 00 03 08 00 13 08 00 13 FF 00 01 00 02 07 00 03 07 00 22 00 04 07 00 03 08 00 13 08 00 13 01 FF 00 1B 00 02 07 00 03 07 00 22 00 03 07 00 03 08 00 13 08 00 13 FF 00 15 00 02 07 00 03 07 00 22 00 04 07 00 03 08 00 13 08 00 13 03 FF 00 01 00 02 07 00 03 07 00 22 00 05 07 00 03 08 00 13 08 00 13 03 01 FF 00 1B 00 02 07 00 03 07 00 22 00 04 07 00 03 08 00 13 08 00 13 03 22 41 01 1E FF 00 0F 00 02 07 00 03 07 00 22 00 03 07 00 03 08 00 B9 08 00 B9 FF 00 01 00 02 07 00 03 07 00 22 00 04 07 00 03 08 00 B9 08 00 B9 01 FF 00 1D 00 02 07 00 03 07 00 22 00 03 07 00 03 08 00 B9 08 00 B9 FF 00 11 00 02 07 00 03 07 00 22 00 04 07 00 03 08 00 B9 08 00 B9 07 00 39 FF 00 01 00 02 07 00 03 07 00 22 00 05 07 00 03 08 00 B9 08 00 B9 07 00 39 01 FF 00 1B 00 02 07 00 03 07 00 22 00 04 07 00 03 08 00 B9 08 00 B9 07 00 39 22 41 01 1E FF 00 1E 00 02 07 00 03 07 00 22 00 02 07 00 03 07 00 22 FF 00 01 00 02 07 00 03 07 00 22 00 03 07 00 03 07 00 22 01 FF 00 1E 00 02 07 00 03 07 00 22 00 02 07 00 03 07 00 22 FF 00 07 00 02 07 00 03 07 00 22 00 03 07 00 03 08 00 B9 08 00 B9 01 FF 00 01 00 02 07 00 03 07 00 22 00 04 07 00 03 08 00 B9 08 00 B9 07 00 39 FF 00 01 00 02 07 00 03 07 00 22 00 03 07 00 03 08 00 13 08 00 13 01 FF 00 01 00 02 07 00 03 07 00 22 00 02 07 00 03 07 00 22 FF 00 01 00 02 07 00 03 07 00 22 00 04 07 00 03 08 00 13 08 00 13 03
        // 
        // The error that occurred was:
        // 
        // java.lang.NullPointerException
        //     at com.strobel.decompiler.languages.java.ast.AstBuilder.convertType(AstBuilder.java:344)
        //     at com.strobel.decompiler.languages.java.ast.AstBuilder.convertType(AstBuilder.java:173)
        //     at com.strobel.decompiler.languages.java.ast.AstBuilder.convertType(AstBuilder.java:169)
        //     at com.strobel.decompiler.languages.java.ast.AstMethodBodyBuilder.transformByteCode(AstMethodBodyBuilder.java:547)
        //     at com.strobel.decompiler.languages.java.ast.AstMethodBodyBuilder.transformExpression(AstMethodBodyBuilder.java:540)
        //     at com.strobel.decompiler.languages.java.ast.AstMethodBodyBuilder.transformByteCode(AstMethodBodyBuilder.java:554)
        //     at com.strobel.decompiler.languages.java.ast.AstMethodBodyBuilder.transformExpression(AstMethodBodyBuilder.java:540)
        //     at com.strobel.decompiler.languages.java.ast.AstMethodBodyBuilder.transformByteCode(AstMethodBodyBuilder.java:554)
        //     at com.strobel.decompiler.languages.java.ast.AstMethodBodyBuilder.transformExpression(AstMethodBodyBuilder.java:540)
        //     at com.strobel.decompiler.languages.java.ast.AstMethodBodyBuilder.transformByteCode(AstMethodBodyBuilder.java:554)
        //     at com.strobel.decompiler.languages.java.ast.AstMethodBodyBuilder.transformExpression(AstMethodBodyBuilder.java:540)
        //     at com.strobel.decompiler.languages.java.ast.AstMethodBodyBuilder.transformNode(AstMethodBodyBuilder.java:392)
        //     at com.strobel.decompiler.languages.java.ast.AstMethodBodyBuilder.transformBlock(AstMethodBodyBuilder.java:333)
        //     at com.strobel.decompiler.languages.java.ast.AstMethodBodyBuilder.transformNode(AstMethodBodyBuilder.java:480)
        //     at com.strobel.decompiler.languages.java.ast.AstMethodBodyBuilder.transformBlock(AstMethodBodyBuilder.java:333)
        //     at com.strobel.decompiler.languages.java.ast.AstMethodBodyBuilder.transformNode(AstMethodBodyBuilder.java:480)
        //     at com.strobel.decompiler.languages.java.ast.AstMethodBodyBuilder.transformBlock(AstMethodBodyBuilder.java:333)
        //     at com.strobel.decompiler.languages.java.ast.AstMethodBodyBuilder.createMethodBody(AstMethodBodyBuilder.java:294)
        //     at com.strobel.decompiler.languages.java.ast.AstMethodBodyBuilder.createMethodBody(AstMethodBodyBuilder.java:99)
        //     at com.strobel.decompiler.languages.java.ast.AstBuilder.createMethodBody(AstBuilder.java:782)
        //     at com.strobel.decompiler.languages.java.ast.AstBuilder.createConstructor(AstBuilder.java:713)
        //     at com.strobel.decompiler.languages.java.ast.AstBuilder.addTypeMembers(AstBuilder.java:549)
        //     at com.strobel.decompiler.languages.java.ast.AstBuilder.createTypeCore(AstBuilder.java:519)
        //     at com.strobel.decompiler.languages.java.ast.AstBuilder.createTypeNoCache(AstBuilder.java:161)
        //     at com.strobel.decompiler.languages.java.ast.AstBuilder.createType(AstBuilder.java:150)
        //     at com.strobel.decompiler.languages.java.ast.AstBuilder.addType(AstBuilder.java:125)
        //     at com.strobel.decompiler.languages.java.JavaLanguage.buildAst(JavaLanguage.java:71)
        //     at com.strobel.decompiler.languages.java.JavaLanguage.decompileType(JavaLanguage.java:59)
        //     at com.strobel.decompiler.DecompilerDriver.decompileType(DecompilerDriver.java:330)
        //     at com.strobel.decompiler.DecompilerDriver.decompileJar(DecompilerDriver.java:251)
        //     at com.strobel.decompiler.DecompilerDriver.main(DecompilerDriver.java:126)
        // 
        throw new IllegalStateException("An error occurred while decompiling this method.");
    }
    
    @Nullable
    @Override
    public String c(final double n) {
        return fbS.2t(this, 216214562, n);
    }
    
    public void 0(final boolean b) {
        fbS.4a(this, 228879197, b);
    }
    
    @Override
    public void 0(@NotNull final f0w f0w, @NotNull final f0y f0y, @NotNull final f0Z f0Z) {
        fbS.4N(this, 974761454, f0w, f0y, f0Z);
    }
}
