// 
// Decompiled by Procyon v0.5.36
// 

package dev.nuker.pyro;

import org.jetbrains.annotations.Nullable;

public class f0r
{
    public f0r(final DefaultConstructorMarker defaultConstructorMarker) {
        while (true) {
            int n = 0;
            Label_0013: {
                if (fc.0 != 0) {
                    n = 1533512048;
                    break Label_0013;
                }
                n = 1003351273;
            }
            switch (n ^ 0x79F0DABC) {
                case -1983131618: {
                    continue;
                }
                default: {
                    while (true) {
                        int n2 = 0;
                        Label_0058: {
                            if (fc.0 != 0) {
                                n2 = 319134930;
                                break Label_0058;
                            }
                            n2 = 1962209188;
                        }
                        switch (n2 ^ 0x116B1735) {
                            case 40799207: {
                                continue;
                            }
                            case 1704982673: {
                                this();
                                return;
                            }
                            default: {
                                throw null;
                            }
                        }
                        break;
                    }
                    break;
                }
                case 580342732: {
                    throw null;
                }
            }
            break;
        }
    }
    
    static {
        throw t;
    }
    
    public f0r() {
    }
    
    @Nullable
    public f0s c(final int p0, final int p1) {
        // 
        // This method could not be decompiled.
        // 
        // Original Bytecode:
        // 
        //     3: dup            
        //     4: ifnull          417
        //     7: athrow         
        //     8: aconst_null    
        //     9: getstatic       dev/nuker/pyro/fc.1:I
        //    12: ifgt            409
        //    15: pop            
        //    16: aconst_null    
        //    17: goto            401
        //    20: nop            
        //    21: nop            
        //    22: nop            
        //    23: athrow         
        //    24: getstatic       dev/nuker/pyro/fc.0:I
        //    27: ifeq            35
        //    30: ldc             -272947533
        //    32: goto            37
        //    35: ldc             1110150702
        //    37: ldc             1591914131
        //    39: ixor           
        //    40: lookupswitch {
        //          -1319532512: 388
        //          906562650: 35
        //          default: 68
        //        }
        //    68: goto            72
        //    71: athrow         
        //    72: invokestatic    dev/nuker/pyro/f0s.values:()[Ldev/nuker/pyro/f0s;
        //    75: goto            79
        //    78: athrow         
        //    79: astore          5
        //    81: aload           5
        //    83: arraylength    
        //    84: getstatic       dev/nuker/pyro/fc.0:I
        //    87: ifeq            95
        //    90: ldc             -1275695524
        //    92: goto            97
        //    95: ldc             -959458535
        //    97: ldc             -34349887
        //    99: ixor           
        //   100: lookupswitch {
        //          993791960: 128
        //          1308996253: 95
        //          default: 390
        //        }
        //   128: istore          6
        //   130: iconst_0       
        //   131: istore          4
        //   133: iload           4
        //   135: iload           6
        //   137: if_icmpge       380
        //   140: getstatic       dev/nuker/pyro/fc.0:I
        //   143: ifeq            151
        //   146: ldc             -1058850834
        //   148: goto            153
        //   151: ldc             670054405
        //   153: ldc             478115416
        //   155: ixor           
        //   156: lookupswitch {
        //          -593739338: 151
        //          999247453: 184
        //          default: 382
        //        }
        //   184: aload           5
        //   186: iload           4
        //   188: aaload         
        //   189: astore_3       
        //   190: getstatic       dev/nuker/pyro/fc.1:I
        //   193: ifeq            201
        //   196: ldc             1865715609
        //   198: goto            203
        //   201: ldc             -1309154298
        //   203: ldc             221841871
        //   205: ixor           
        //   206: lookupswitch {
        //          -1127289399: 232
        //          1645053526: 201
        //          default: 384
        //        }
        //   232: aload_3        
        //   233: goto            237
        //   236: athrow         
        //   237: invokevirtual   dev/nuker/pyro/f0s.0:()I
        //   240: goto            244
        //   243: athrow         
        //   244: iload_1        
        //   245: if_icmpne       253
        //   248: ldc             625955543
        //   250: goto            255
        //   253: ldc             625955540
        //   255: ldc             -403222274
        //   257: ixor           
        //   258: tableswitch {
        //          -2056256430: 280
        //          -2056256429: 374
        //          default: 248
        //        }
        //   280: aload_3        
        //   281: goto            285
        //   284: athrow         
        //   285: invokevirtual   dev/nuker/pyro/f0s.1:()I
        //   288: goto            292
        //   291: athrow         
        //   292: getstatic       dev/nuker/pyro/fc.0:I
        //   295: ifeq            303
        //   298: ldc             29321954
        //   300: goto            305
        //   303: ldc             -730274351
        //   305: ldc             1700493996
        //   307: ixor           
        //   308: lookupswitch {
        //          -1323065475: 336
        //          1692667982: 303
        //          default: 386
        //        }
        //   336: iload_2        
        //   337: if_icmpne       345
        //   340: ldc             -419806524
        //   342: goto            347
        //   345: ldc             -419806523
        //   347: ldc             -487972830
        //   349: ixor           
        //   350: tableswitch {
        //          136365516: 372
        //          136365517: 374
        //          default: 340
        //        }
        //   372: aload_3        
        //   373: areturn        
        //   374: iinc            4, 1
        //   377: goto            133
        //   380: aconst_null    
        //   381: areturn        
        //   382: aconst_null    
        //   383: athrow         
        //   384: aconst_null    
        //   385: athrow         
        //   386: aconst_null    
        //   387: athrow         
        //   388: aconst_null    
        //   389: athrow         
        //   390: aconst_null    
        //   391: athrow         
        //   392: pop            
        //   393: goto            24
        //   396: pop            
        //   397: aconst_null    
        //   398: goto            392
        //   401: dup            
        //   402: ifnull          392
        //   405: checkcast       Ljava/lang/Throwable;
        //   408: athrow         
        //   409: dup            
        //   410: ifnull          396
        //   413: checkcast       Ljava/lang/Throwable;
        //   416: athrow         
        //   417: aconst_null    
        //   418: athrow         
        //    StackMapTable: 00 34 43 07 00 35 04 FF 00 0B 00 00 00 01 07 00 35 FE 00 03 07 00 03 01 01 0A 41 01 1E 42 07 00 35 00 45 07 00 35 40 07 00 57 FF 00 0F 00 06 07 00 03 01 01 00 00 07 00 57 00 01 01 FF 00 01 00 06 07 00 03 01 01 00 00 07 00 57 00 02 01 01 5E 01 FF 00 04 00 07 07 00 03 01 01 00 01 07 00 57 01 00 00 11 41 01 1E FF 00 10 00 07 07 00 03 01 01 07 00 3A 01 07 00 57 01 00 00 41 01 1C 43 07 00 35 40 07 00 3A 45 07 00 35 40 01 03 04 41 01 18 FF 00 03 00 00 00 01 07 00 35 FF 00 00 00 07 07 00 03 01 01 07 00 3A 01 07 00 57 01 00 01 07 00 3A 45 07 00 35 40 01 4A 01 FF 00 01 00 07 07 00 03 01 01 07 00 3A 01 07 00 57 01 00 02 01 01 5E 01 03 04 41 01 18 01 FF 00 05 00 07 07 00 03 01 01 00 01 07 00 57 01 00 00 01 FF 00 01 00 07 07 00 03 01 01 07 00 3A 01 07 00 57 01 00 00 41 01 FF 00 01 00 03 07 00 03 01 01 00 00 FF 00 01 00 06 07 00 03 01 01 00 00 07 00 57 00 01 01 FF 00 01 00 03 07 00 03 01 01 00 01 07 00 59 43 05 44 07 00 59 47 05 47 07 00 35
        //    Exceptions:
        //  Try           Handler
        //  Start  End    Start  End    Type                                       
        //  -----  -----  -----  -----  -------------------------------------------
        //  8      20     401    409    Ljava/lang/NegativeArraySizeException;
        //  401    409    401    409    Ljava/lang/UnsupportedOperationException;
        //  417    419    3      8      Ljava/lang/IllegalArgumentException;
        //  71     78     78     79     Any
        //  72     78     71     72     Any
        //  71     78     3      8      Any
        //  71     78     78     79     Any
        //  72     78     3      8      Ljava/lang/NumberFormatException;
        //  236    243    243    244    Any
        //  236    243    236    237    Any
        //  236    243    3      8      Any
        //  236    243    3      8      Ljava/lang/EnumConstantNotPresentException;
        //  236    243    236    237    Ljava/lang/IndexOutOfBoundsException;
        //  285    291    291    292    Any
        //  285    291    291    292    Ljava/lang/AssertionError;
        //  285    291    3      8      Ljava/lang/ClassCastException;
        //  285    291    291    292    Ljava/util/ConcurrentModificationException;
        //  285    291    3      8      Ljava/lang/AssertionError;
        // 
        // The error that occurred was:
        // 
        // java.lang.IndexOutOfBoundsException: Index -1 out of bounds for length 0
        //     at java.base/jdk.internal.util.Preconditions.outOfBounds(Preconditions.java:64)
        //     at java.base/jdk.internal.util.Preconditions.outOfBoundsCheckIndex(Preconditions.java:70)
        //     at java.base/jdk.internal.util.Preconditions.checkIndex(Preconditions.java:248)
        //     at java.base/java.util.Objects.checkIndex(Objects.java:372)
        //     at java.base/java.util.ArrayList.remove(ArrayList.java:535)
        //     at com.strobel.assembler.ir.StackMappingVisitor.pop(StackMappingVisitor.java:267)
        //     at com.strobel.assembler.ir.StackMappingVisitor$InstructionAnalyzer.visitVariable(StackMappingVisitor.java:470)
        //     at com.strobel.assembler.ir.Instruction.accept(Instruction.java:556)
        //     at com.strobel.assembler.ir.StackMappingVisitor$InstructionAnalyzer.visit(StackMappingVisitor.java:403)
        //     at com.strobel.decompiler.ast.AstBuilder.performStackAnalysis(AstBuilder.java:2030)
        //     at com.strobel.decompiler.ast.AstBuilder.build(AstBuilder.java:108)
        //     at com.strobel.decompiler.languages.java.ast.AstMethodBodyBuilder.createMethodBody(AstMethodBodyBuilder.java:211)
        //     at com.strobel.decompiler.languages.java.ast.AstMethodBodyBuilder.createMethodBody(AstMethodBodyBuilder.java:99)
        //     at com.strobel.decompiler.languages.java.ast.AstBuilder.createMethodBody(AstBuilder.java:782)
        //     at com.strobel.decompiler.languages.java.ast.AstBuilder.createMethod(AstBuilder.java:675)
        //     at com.strobel.decompiler.languages.java.ast.AstBuilder.addTypeMembers(AstBuilder.java:552)
        //     at com.strobel.decompiler.languages.java.ast.AstBuilder.createTypeCore(AstBuilder.java:519)
        //     at com.strobel.decompiler.languages.java.ast.AstBuilder.createTypeNoCache(AstBuilder.java:161)
        //     at com.strobel.decompiler.languages.java.ast.AstBuilder.createType(AstBuilder.java:150)
        //     at com.strobel.decompiler.languages.java.ast.AstBuilder.addType(AstBuilder.java:125)
        //     at com.strobel.decompiler.languages.java.JavaLanguage.buildAst(JavaLanguage.java:71)
        //     at com.strobel.decompiler.languages.java.JavaLanguage.decompileType(JavaLanguage.java:59)
        //     at com.strobel.decompiler.DecompilerDriver.decompileType(DecompilerDriver.java:330)
        //     at com.strobel.decompiler.DecompilerDriver.decompileJar(DecompilerDriver.java:251)
        //     at com.strobel.decompiler.DecompilerDriver.main(DecompilerDriver.java:126)
        // 
        throw new IllegalStateException("An error occurred while decompiling this method.");
    }
}
