// 
// Decompiled by Procyon v0.5.36
// 

package dev.nuker.pyro;

public class f0v
{
    public f0v(final DefaultConstructorMarker defaultConstructorMarker) {
        while (true) {
            int n = 0;
            Label_0013: {
                if (fc.c < 0) {
                    n = -1123050571;
                    break Label_0013;
                }
                n = -378193412;
            }
            switch (n ^ 0xAEB6792F) {
                case -1870524655: {
                    continue;
                }
                default: {
                    this();
                }
                case 330949274: {
                    throw null;
                }
            }
            break;
        }
    }
    
    public void c(final int p0, final int p1, final int p2, final int p3, final int p4) {
        // 
        // This method could not be decompiled.
        // 
        // Original Bytecode:
        // 
        //     3: dup            
        //     4: ifnull          1523
        //     7: athrow         
        //     8: aconst_null    
        //     9: getstatic       dev/nuker/pyro/fc.1:I
        //    12: ifgt            1515
        //    15: pop            
        //    16: aconst_null    
        //    17: goto            1507
        //    20: nop            
        //    21: nop            
        //    22: nop            
        //    23: athrow         
        //    24: getstatic       dev/nuker/pyro/fc.0:I
        //    27: ifeq            35
        //    30: ldc             -1670492691
        //    32: goto            37
        //    35: ldc             -1438687827
        //    37: ldc             -613283362
        //    39: ixor           
        //    40: lookupswitch {
        //          1193034803: 1456
        //          1635167335: 35
        //          default: 68
        //        }
        //    68: iload_1        
        //    69: getstatic       dev/nuker/pyro/fc.0:I
        //    72: ifeq            80
        //    75: ldc             -149736882
        //    77: goto            82
        //    80: ldc             1094235166
        //    82: ldc             -25025382
        //    84: ixor           
        //    85: lookupswitch {
        //          160503508: 1482
        //          635622981: 80
        //          default: 112
        //        }
        //   112: istore          6
        //   114: iload_2        
        //   115: istore          7
        //   117: iload_3        
        //   118: istore          8
        //   120: iload           4
        //   122: istore          9
        //   124: iload           6
        //   126: iload           8
        //   128: if_icmpge       228
        //   131: iload           6
        //   133: getstatic       dev/nuker/pyro/fc.c:I
        //   136: ifge            144
        //   139: ldc             316932455
        //   141: goto            146
        //   144: ldc             2090532723
        //   146: ldc             619020646
        //   148: ixor           
        //   149: lookupswitch {
        //          906067969: 144
        //          1484750357: 176
        //          default: 1462
        //        }
        //   176: istore          10
        //   178: getstatic       dev/nuker/pyro/fc.1:I
        //   181: ifeq            189
        //   184: ldc             -1110346847
        //   186: goto            191
        //   189: ldc             -209839112
        //   191: ldc             2051911638
        //   193: ixor           
        //   194: lookupswitch {
        //          -1332432580: 189
        //          -946021257: 1474
        //          default: 220
        //        }
        //   220: iload           8
        //   222: istore          6
        //   224: iload           10
        //   226: istore          8
        //   228: iload           7
        //   230: getstatic       dev/nuker/pyro/fc.0:I
        //   233: ifeq            241
        //   236: ldc             -29278729
        //   238: goto            243
        //   241: ldc             -1841479125
        //   243: ldc             -1851186799
        //   245: ixor           
        //   246: lookupswitch {
        //          60056506: 272
        //          1877482598: 241
        //          default: 1454
        //        }
        //   272: iload           9
        //   274: if_icmpge       282
        //   277: ldc             1752246294
        //   279: goto            284
        //   282: ldc             1752246295
        //   284: ldc             -1080809376
        //   286: ixor           
        //   287: tableswitch {
        //          -1345715988: 308
        //          -1345715987: 450
        //          default: 277
        //        }
        //   308: getstatic       dev/nuker/pyro/fc.1:I
        //   311: ifeq            319
        //   314: ldc             867294336
        //   316: goto            321
        //   319: ldc             -15288868
        //   321: ldc             349072749
        //   323: ixor           
        //   324: lookupswitch {
        //          -338110287: 352
        //          662680045: 319
        //          default: 1492
        //        }
        //   352: iload           7
        //   354: istore          10
        //   356: getstatic       dev/nuker/pyro/fc.1:I
        //   359: ifeq            367
        //   362: ldc             -2079802799
        //   364: goto            369
        //   367: ldc             -1720341280
        //   369: ldc             -37731317
        //   371: ixor           
        //   372: lookupswitch {
        //          1689643243: 400
        //          2043215450: 367
        //          default: 1460
        //        }
        //   400: iload           9
        //   402: getstatic       dev/nuker/pyro/fc.1:I
        //   405: ifeq            413
        //   408: ldc             -1535408091
        //   410: goto            415
        //   413: ldc             -1072889057
        //   415: ldc             -398576559
        //   417: ixor           
        //   418: lookupswitch {
        //          26459768: 413
        //          1279638644: 1484
        //          default: 444
        //        }
        //   444: istore          7
        //   446: iload           10
        //   448: istore          9
        //   450: iload           5
        //   452: bipush          24
        //   454: ishr           
        //   455: sipush          255
        //   458: iand           
        //   459: i2f            
        //   460: ldc             255.0
        //   462: fdiv           
        //   463: getstatic       dev/nuker/pyro/fc.c:I
        //   466: ifge            474
        //   469: ldc             -137965746
        //   471: goto            476
        //   474: ldc             229455475
        //   476: ldc             -982916143
        //   478: ixor           
        //   479: lookupswitch {
        //          850341023: 1494
        //          1642563889: 474
        //          default: 504
        //        }
        //   504: fstore          10
        //   506: getstatic       dev/nuker/pyro/fc.1:I
        //   509: ifeq            517
        //   512: ldc             -930400475
        //   514: goto            519
        //   517: ldc             -1156425068
        //   519: ldc             2132273989
        //   521: ixor           
        //   522: lookupswitch {
        //          -1214456736: 1452
        //          -120012371: 517
        //          default: 548
        //        }
        //   548: iload           5
        //   550: bipush          16
        //   552: ishr           
        //   553: sipush          255
        //   556: iand           
        //   557: i2f            
        //   558: ldc             255.0
        //   560: fdiv           
        //   561: fstore          11
        //   563: iload           5
        //   565: bipush          8
        //   567: ishr           
        //   568: sipush          255
        //   571: iand           
        //   572: i2f            
        //   573: ldc             255.0
        //   575: fdiv           
        //   576: getstatic       dev/nuker/pyro/fc.0:I
        //   579: ifeq            587
        //   582: ldc             -2047185196
        //   584: goto            589
        //   587: ldc             934611469
        //   589: ldc             1260556738
        //   591: ixor           
        //   592: lookupswitch {
        //          -1300826563: 587
        //          -824639722: 1464
        //          default: 620
        //        }
        //   620: fstore          12
        //   622: iload           5
        //   624: sipush          255
        //   627: iand           
        //   628: i2f            
        //   629: ldc             255.0
        //   631: fdiv           
        //   632: fstore          13
        //   634: goto            638
        //   637: athrow         
        //   638: invokestatic    net/minecraft/client/renderer/Tessellator.func_178181_a:()Lnet/minecraft/client/renderer/Tessellator;
        //   641: goto            645
        //   644: athrow         
        //   645: astore          14
        //   647: aload           14
        //   649: dup            
        //   650: pop            
        //   651: goto            655
        //   654: athrow         
        //   655: invokevirtual   net/minecraft/client/renderer/Tessellator.func_178180_c:()Lnet/minecraft/client/renderer/BufferBuilder;
        //   658: goto            662
        //   661: athrow         
        //   662: astore          15
        //   664: goto            668
        //   667: athrow         
        //   668: invokestatic    net/minecraft/client/renderer/GlStateManager.func_179147_l:()V
        //   671: goto            675
        //   674: athrow         
        //   675: getstatic       dev/nuker/pyro/fc.c:I
        //   678: ifge            686
        //   681: ldc             -1329618331
        //   683: goto            688
        //   686: ldc             -1811649075
        //   688: ldc             494938113
        //   690: ixor           
        //   691: lookupswitch {
        //          -1987820084: 716
        //          -1388344732: 686
        //          default: 1476
        //        }
        //   716: goto            720
        //   719: athrow         
        //   720: invokestatic    net/minecraft/client/renderer/GlStateManager.func_179090_x:()V
        //   723: goto            727
        //   726: athrow         
        //   727: getstatic       dev/nuker/pyro/fc.c:I
        //   730: ifge            738
        //   733: ldc             1001229714
        //   735: goto            740
        //   738: ldc             1011160419
        //   740: ldc             1085918693
        //   742: ixor           
        //   743: lookupswitch {
        //          2064924791: 738
        //          2096945286: 768
        //          default: 1466
        //        }
        //   768: getstatic       net/minecraft/client/renderer/GlStateManager$SourceFactor.SRC_ALPHA:Lnet/minecraft/client/renderer/GlStateManager$SourceFactor;
        //   771: getstatic       dev/nuker/pyro/fc.c:I
        //   774: ifge            782
        //   777: ldc             1426453502
        //   779: goto            784
        //   782: ldc             -1680650424
        //   784: ldc             -1980659503
        //   786: ixor           
        //   787: lookupswitch {
        //          -587957457: 1468
        //          1701086704: 782
        //          default: 812
        //        }
        //   812: getstatic       net/minecraft/client/renderer/GlStateManager$DestFactor.ONE_MINUS_SRC_ALPHA:Lnet/minecraft/client/renderer/GlStateManager$DestFactor;
        //   815: getstatic       net/minecraft/client/renderer/GlStateManager$SourceFactor.ONE:Lnet/minecraft/client/renderer/GlStateManager$SourceFactor;
        //   818: getstatic       dev/nuker/pyro/fc.1:I
        //   821: ifeq            829
        //   824: ldc             -1121255911
        //   826: goto            831
        //   829: ldc             -389258248
        //   831: ldc             -1995889116
        //   833: ixor           
        //   834: lookupswitch {
        //          874764349: 829
        //          1640318428: 860
        //          default: 1486
        //        }
        //   860: getstatic       net/minecraft/client/renderer/GlStateManager$DestFactor.ZERO:Lnet/minecraft/client/renderer/GlStateManager$DestFactor;
        //   863: goto            867
        //   866: athrow         
        //   867: invokestatic    net/minecraft/client/renderer/GlStateManager.func_187428_a:(Lnet/minecraft/client/renderer/GlStateManager$SourceFactor;Lnet/minecraft/client/renderer/GlStateManager$DestFactor;Lnet/minecraft/client/renderer/GlStateManager$SourceFactor;Lnet/minecraft/client/renderer/GlStateManager$DestFactor;)V
        //   870: goto            874
        //   873: athrow         
        //   874: getstatic       dev/nuker/pyro/fc.0:I
        //   877: ifeq            885
        //   880: ldc             -299325362
        //   882: goto            887
        //   885: ldc             678501443
        //   887: ldc             -842378670
        //   889: ixor           
        //   890: lookupswitch {
        //          -440709615: 916
        //          602077724: 885
        //          default: 1496
        //        }
        //   916: fload           11
        //   918: fload           12
        //   920: fload           13
        //   922: fload           10
        //   924: goto            928
        //   927: athrow         
        //   928: invokestatic    net/minecraft/client/renderer/GlStateManager.func_179131_c:(FFFF)V
        //   931: goto            935
        //   934: athrow         
        //   935: aload           15
        //   937: bipush          7
        //   939: getstatic       net/minecraft/client/renderer/vertex/DefaultVertexFormats.field_181705_e:Lnet/minecraft/client/renderer/vertex/VertexFormat;
        //   942: goto            946
        //   945: athrow         
        //   946: invokevirtual   net/minecraft/client/renderer/BufferBuilder.func_181668_a:(ILnet/minecraft/client/renderer/vertex/VertexFormat;)V
        //   949: goto            953
        //   952: athrow         
        //   953: aload           15
        //   955: iload           6
        //   957: i2d            
        //   958: iload           9
        //   960: i2d            
        //   961: dconst_0       
        //   962: getstatic       dev/nuker/pyro/fc.c:I
        //   965: ifge            973
        //   968: ldc             -98915868
        //   970: goto            975
        //   973: ldc             -1390623725
        //   975: ldc             -2086620735
        //   977: ixor           
        //   978: lookupswitch {
        //          1975532819: 973
        //          2042239013: 1488
        //          default: 1004
        //        }
        //  1004: goto            1008
        //  1007: athrow         
        //  1008: invokevirtual   net/minecraft/client/renderer/BufferBuilder.func_181662_b:(DDD)Lnet/minecraft/client/renderer/BufferBuilder;
        //  1011: goto            1015
        //  1014: athrow         
        //  1015: goto            1019
        //  1018: athrow         
        //  1019: invokevirtual   net/minecraft/client/renderer/BufferBuilder.func_181675_d:()V
        //  1022: goto            1026
        //  1025: athrow         
        //  1026: getstatic       dev/nuker/pyro/fc.0:I
        //  1029: ifeq            1037
        //  1032: ldc             -459995957
        //  1034: goto            1039
        //  1037: ldc             1532608260
        //  1039: ldc             -1806193916
        //  1041: ixor           
        //  1042: lookupswitch {
        //          1891807183: 1478
        //          1974135914: 1037
        //          default: 1068
        //        }
        //  1068: aload           15
        //  1070: iload           8
        //  1072: i2d            
        //  1073: iload           9
        //  1075: i2d            
        //  1076: dconst_0       
        //  1077: goto            1081
        //  1080: athrow         
        //  1081: invokevirtual   net/minecraft/client/renderer/BufferBuilder.func_181662_b:(DDD)Lnet/minecraft/client/renderer/BufferBuilder;
        //  1084: goto            1088
        //  1087: athrow         
        //  1088: goto            1092
        //  1091: athrow         
        //  1092: invokevirtual   net/minecraft/client/renderer/BufferBuilder.func_181675_d:()V
        //  1095: goto            1099
        //  1098: athrow         
        //  1099: getstatic       dev/nuker/pyro/fc.0:I
        //  1102: ifeq            1110
        //  1105: ldc             -2031608770
        //  1107: goto            1112
        //  1110: ldc             1745474482
        //  1112: ldc             362611277
        //  1114: ixor           
        //  1115: lookupswitch {
        //          -1821041037: 1450
        //          1293778344: 1110
        //          default: 1140
        //        }
        //  1140: aload           15
        //  1142: iload           8
        //  1144: i2d            
        //  1145: iload           7
        //  1147: i2d            
        //  1148: dconst_0       
        //  1149: getstatic       dev/nuker/pyro/fc.0:I
        //  1152: ifeq            1160
        //  1155: ldc             649980418
        //  1157: goto            1162
        //  1160: ldc             -2011832542
        //  1162: ldc             -660106024
        //  1164: ixor           
        //  1165: lookupswitch {
        //          -31818022: 1490
        //          1444437155: 1160
        //          default: 1192
        //        }
        //  1192: goto            1196
        //  1195: athrow         
        //  1196: invokevirtual   net/minecraft/client/renderer/BufferBuilder.func_181662_b:(DDD)Lnet/minecraft/client/renderer/BufferBuilder;
        //  1199: goto            1203
        //  1202: athrow         
        //  1203: getstatic       dev/nuker/pyro/fc.c:I
        //  1206: ifge            1214
        //  1209: ldc             928579108
        //  1211: goto            1216
        //  1214: ldc             674431351
        //  1216: ldc             1658184300
        //  1218: ixor           
        //  1219: lookupswitch {
        //          1256645403: 1244
        //          1435311176: 1214
        //          default: 1480
        //        }
        //  1244: goto            1248
        //  1247: athrow         
        //  1248: invokevirtual   net/minecraft/client/renderer/BufferBuilder.func_181675_d:()V
        //  1251: goto            1255
        //  1254: athrow         
        //  1255: aload           15
        //  1257: getstatic       dev/nuker/pyro/fc.0:I
        //  1260: ifeq            1268
        //  1263: ldc             -1754159923
        //  1265: goto            1270
        //  1268: ldc             -871013252
        //  1270: ldc             -315612700
        //  1272: ixor           
        //  1273: lookupswitch {
        //          910822761: 1268
        //          2051114281: 1472
        //          default: 1300
        //        }
        //  1300: iload           6
        //  1302: i2d            
        //  1303: iload           7
        //  1305: i2d            
        //  1306: dconst_0       
        //  1307: goto            1311
        //  1310: athrow         
        //  1311: invokevirtual   net/minecraft/client/renderer/BufferBuilder.func_181662_b:(DDD)Lnet/minecraft/client/renderer/BufferBuilder;
        //  1314: goto            1318
        //  1317: athrow         
        //  1318: goto            1322
        //  1321: athrow         
        //  1322: invokevirtual   net/minecraft/client/renderer/BufferBuilder.func_181675_d:()V
        //  1325: goto            1329
        //  1328: athrow         
        //  1329: getstatic       dev/nuker/pyro/fc.0:I
        //  1332: ifeq            1340
        //  1335: ldc             -955243589
        //  1337: goto            1342
        //  1340: ldc             814827862
        //  1342: ldc             1938372017
        //  1344: ixor           
        //  1345: lookupswitch {
        //          -1265035766: 1458
        //          955664266: 1340
        //          default: 1372
        //        }
        //  1372: aload           14
        //  1374: getstatic       dev/nuker/pyro/fc.1:I
        //  1377: ifeq            1385
        //  1380: ldc             1526866961
        //  1382: goto            1387
        //  1385: ldc             515179137
        //  1387: ldc             -1539208741
        //  1389: ixor           
        //  1390: lookupswitch {
        //          -12341814: 1470
        //          1477361229: 1385
        //          default: 1416
        //        }
        //  1416: goto            1420
        //  1419: athrow         
        //  1420: invokevirtual   net/minecraft/client/renderer/Tessellator.func_78381_a:()V
        //  1423: goto            1427
        //  1426: athrow         
        //  1427: goto            1431
        //  1430: athrow         
        //  1431: invokestatic    net/minecraft/client/renderer/GlStateManager.func_179098_w:()V
        //  1434: goto            1438
        //  1437: athrow         
        //  1438: goto            1442
        //  1441: athrow         
        //  1442: invokestatic    net/minecraft/client/renderer/GlStateManager.func_179084_k:()V
        //  1445: goto            1449
        //  1448: athrow         
        //  1449: return         
        //  1450: aconst_null    
        //  1451: athrow         
        //  1452: aconst_null    
        //  1453: athrow         
        //  1454: aconst_null    
        //  1455: athrow         
        //  1456: aconst_null    
        //  1457: athrow         
        //  1458: aconst_null    
        //  1459: athrow         
        //  1460: aconst_null    
        //  1461: athrow         
        //  1462: aconst_null    
        //  1463: athrow         
        //  1464: aconst_null    
        //  1465: athrow         
        //  1466: aconst_null    
        //  1467: athrow         
        //  1468: aconst_null    
        //  1469: athrow         
        //  1470: aconst_null    
        //  1471: athrow         
        //  1472: aconst_null    
        //  1473: athrow         
        //  1474: aconst_null    
        //  1475: athrow         
        //  1476: aconst_null    
        //  1477: athrow         
        //  1478: aconst_null    
        //  1479: athrow         
        //  1480: aconst_null    
        //  1481: athrow         
        //  1482: aconst_null    
        //  1483: athrow         
        //  1484: aconst_null    
        //  1485: athrow         
        //  1486: aconst_null    
        //  1487: athrow         
        //  1488: aconst_null    
        //  1489: athrow         
        //  1490: aconst_null    
        //  1491: athrow         
        //  1492: aconst_null    
        //  1493: athrow         
        //  1494: aconst_null    
        //  1495: athrow         
        //  1496: aconst_null    
        //  1497: athrow         
        //  1498: pop            
        //  1499: goto            24
        //  1502: pop            
        //  1503: aconst_null    
        //  1504: goto            1498
        //  1507: dup            
        //  1508: ifnull          1498
        //  1511: checkcast       Ljava/lang/Throwable;
        //  1514: athrow         
        //  1515: dup            
        //  1516: ifnull          1502
        //  1519: checkcast       Ljava/lang/Throwable;
        //  1522: athrow         
        //  1523: aconst_null    
        //  1524: athrow         
        //    StackMapTable: 00 B7 FF 00 03 00 0E 07 00 03 01 01 01 01 01 01 01 01 01 02 02 02 02 00 01 07 00 39 FF 00 04 00 06 07 00 03 01 01 01 01 01 00 00 FF 00 0B 00 00 00 01 07 00 39 FF 00 03 00 06 07 00 03 01 01 01 01 01 00 00 0A 41 01 1E 4B 01 FF 00 01 00 06 07 00 03 01 01 01 01 01 00 02 01 01 5D 01 FF 00 1F 00 0A 07 00 03 01 01 01 01 01 01 01 01 01 00 01 01 FF 00 01 00 0A 07 00 03 01 01 01 01 01 01 01 01 01 00 02 01 01 5D 01 FC 00 0C 01 41 01 1C FA 00 07 4C 01 FF 00 01 00 0A 07 00 03 01 01 01 01 01 01 01 01 01 00 02 01 01 5C 01 04 04 41 01 17 0A 41 01 1E FC 00 0E 01 41 01 1E 4C 01 FF 00 01 00 0B 07 00 03 01 01 01 01 01 01 01 01 01 01 00 02 01 01 5C 01 FA 00 05 57 02 FF 00 01 00 0A 07 00 03 01 01 01 01 01 01 01 01 01 00 02 02 01 5B 02 FC 00 0C 02 41 01 1C FF 00 26 00 0C 07 00 03 01 01 01 01 01 01 01 01 01 02 02 00 01 02 FF 00 01 00 0C 07 00 03 01 01 01 01 01 01 01 01 01 02 02 00 02 02 01 5E 02 FF 00 10 00 00 00 01 07 00 39 FF 00 00 00 0E 07 00 03 01 01 01 01 01 01 01 01 01 02 02 02 02 00 00 45 07 00 39 40 07 00 63 FF 00 08 00 00 00 01 07 00 39 FF 00 00 00 0F 07 00 03 01 01 01 01 01 01 01 01 01 02 02 02 02 07 00 63 00 01 07 00 63 45 07 00 39 40 07 00 A4 FF 00 04 00 10 07 00 03 01 01 01 01 01 01 01 01 01 02 02 02 02 07 00 63 07 00 A4 00 01 07 00 39 00 45 07 00 39 00 0A 41 01 1B 42 07 00 39 00 45 07 00 39 00 0A 41 01 1B 4D 07 00 7B FF 00 01 00 10 07 00 03 01 01 01 01 01 01 01 01 01 02 02 02 02 07 00 63 07 00 A4 00 02 07 00 7B 01 5B 07 00 7B FF 00 10 00 10 07 00 03 01 01 01 01 01 01 01 01 01 02 02 02 02 07 00 63 07 00 A4 00 03 07 00 7B 07 00 84 07 00 7B FF 00 01 00 10 07 00 03 01 01 01 01 01 01 01 01 01 02 02 02 02 07 00 63 07 00 A4 00 04 07 00 7B 07 00 84 07 00 7B 01 FF 00 1C 00 10 07 00 03 01 01 01 01 01 01 01 01 01 02 02 02 02 07 00 63 07 00 A4 00 03 07 00 7B 07 00 84 07 00 7B 45 07 00 28 FF 00 00 00 10 07 00 03 01 01 01 01 01 01 01 01 01 02 02 02 02 07 00 63 07 00 A4 00 04 07 00 7B 07 00 84 07 00 7B 07 00 84 45 07 00 39 00 0A 41 01 1C 4A 07 00 22 FF 00 00 00 10 07 00 03 01 01 01 01 01 01 01 01 01 02 02 02 02 07 00 63 07 00 A4 00 04 02 02 02 02 45 07 00 39 00 49 07 00 20 FF 00 00 00 10 07 00 03 01 01 01 01 01 01 01 01 01 02 02 02 02 07 00 63 07 00 A4 00 03 07 00 A4 01 07 00 D2 45 07 00 39 00 FF 00 13 00 10 07 00 03 01 01 01 01 01 01 01 01 01 02 02 02 02 07 00 63 07 00 A4 00 04 07 00 A4 03 03 03 FF 00 01 00 10 07 00 03 01 01 01 01 01 01 01 01 01 02 02 02 02 07 00 63 07 00 A4 00 05 07 00 A4 03 03 03 01 FF 00 1C 00 10 07 00 03 01 01 01 01 01 01 01 01 01 02 02 02 02 07 00 63 07 00 A4 00 04 07 00 A4 03 03 03 42 07 00 39 FF 00 00 00 10 07 00 03 01 01 01 01 01 01 01 01 01 02 02 02 02 07 00 63 07 00 A4 00 04 07 00 A4 03 03 03 45 07 00 39 40 07 00 A4 42 07 00 30 40 07 00 A4 45 07 00 39 00 0A 41 01 1C 4B 07 00 39 FF 00 00 00 10 07 00 03 01 01 01 01 01 01 01 01 01 02 02 02 02 07 00 63 07 00 A4 00 04 07 00 A4 03 03 03 45 07 00 39 40 07 00 A4 42 07 00 28 40 07 00 A4 45 07 00 39 00 0A 41 01 1B FF 00 13 00 10 07 00 03 01 01 01 01 01 01 01 01 01 02 02 02 02 07 00 63 07 00 A4 00 04 07 00 A4 03 03 03 FF 00 01 00 10 07 00 03 01 01 01 01 01 01 01 01 01 02 02 02 02 07 00 63 07 00 A4 00 05 07 00 A4 03 03 03 01 FF 00 1D 00 10 07 00 03 01 01 01 01 01 01 01 01 01 02 02 02 02 07 00 63 07 00 A4 00 04 07 00 A4 03 03 03 42 07 00 39 FF 00 00 00 10 07 00 03 01 01 01 01 01 01 01 01 01 02 02 02 02 07 00 63 07 00 A4 00 04 07 00 A4 03 03 03 45 07 00 39 40 07 00 A4 4A 07 00 A4 FF 00 01 00 10 07 00 03 01 01 01 01 01 01 01 01 01 02 02 02 02 07 00 63 07 00 A4 00 02 07 00 A4 01 5B 07 00 A4 FF 00 02 00 00 00 01 07 00 39 FF 00 00 00 10 07 00 03 01 01 01 01 01 01 01 01 01 02 02 02 02 07 00 63 07 00 A4 00 01 07 00 A4 45 07 00 39 00 4C 07 00 A4 FF 00 01 00 10 07 00 03 01 01 01 01 01 01 01 01 01 02 02 02 02 07 00 63 07 00 A4 00 02 07 00 A4 01 5D 07 00 A4 49 07 00 28 FF 00 00 00 10 07 00 03 01 01 01 01 01 01 01 01 01 02 02 02 02 07 00 63 07 00 A4 00 04 07 00 A4 03 03 03 45 07 00 39 40 07 00 A4 42 07 00 32 40 07 00 A4 45 07 00 39 00 0A 41 01 1D 4C 07 00 63 FF 00 01 00 10 07 00 03 01 01 01 01 01 01 01 01 01 02 02 02 02 07 00 63 07 00 A4 00 02 07 00 63 01 5C 07 00 63 42 07 00 39 40 07 00 63 45 07 00 39 00 42 07 00 39 00 45 07 00 39 00 42 07 00 39 00 45 07 00 39 00 00 FF 00 01 00 0B 07 00 03 01 01 01 01 01 01 01 01 01 02 00 00 FF 00 01 00 0A 07 00 03 01 01 01 01 01 01 01 01 01 00 01 01 FF 00 01 00 06 07 00 03 01 01 01 01 01 00 00 FF 00 01 00 10 07 00 03 01 01 01 01 01 01 01 01 01 02 02 02 02 07 00 63 07 00 A4 00 00 FF 00 01 00 0B 07 00 03 01 01 01 01 01 01 01 01 01 01 00 00 FF 00 01 00 0A 07 00 03 01 01 01 01 01 01 01 01 01 00 01 01 FF 00 01 00 0C 07 00 03 01 01 01 01 01 01 01 01 01 02 02 00 01 02 FF 00 01 00 10 07 00 03 01 01 01 01 01 01 01 01 01 02 02 02 02 07 00 63 07 00 A4 00 00 41 07 00 7B 41 07 00 63 41 07 00 A4 FF 00 01 00 0B 07 00 03 01 01 01 01 01 01 01 01 01 01 00 00 FF 00 01 00 10 07 00 03 01 01 01 01 01 01 01 01 01 02 02 02 02 07 00 63 07 00 A4 00 00 01 41 07 00 A4 FF 00 01 00 06 07 00 03 01 01 01 01 01 00 01 01 FF 00 01 00 0B 07 00 03 01 01 01 01 01 01 01 01 01 01 00 01 01 FF 00 01 00 10 07 00 03 01 01 01 01 01 01 01 01 01 02 02 02 02 07 00 63 07 00 A4 00 03 07 00 7B 07 00 84 07 00 7B FF 00 01 00 10 07 00 03 01 01 01 01 01 01 01 01 01 02 02 02 02 07 00 63 07 00 A4 00 04 07 00 A4 03 03 03 FF 00 01 00 10 07 00 03 01 01 01 01 01 01 01 01 01 02 02 02 02 07 00 63 07 00 A4 00 04 07 00 A4 03 03 03 FF 00 01 00 0A 07 00 03 01 01 01 01 01 01 01 01 01 00 00 41 02 FF 00 01 00 10 07 00 03 01 01 01 01 01 01 01 01 01 02 02 02 02 07 00 63 07 00 A4 00 00 FF 00 01 00 06 07 00 03 01 01 01 01 01 00 01 07 00 28 43 05 44 07 00 28 47 05 FF 00 07 00 0E 07 00 03 01 01 01 01 01 01 01 01 01 02 02 02 02 00 01 07 00 39
        //    Exceptions:
        //  Try           Handler
        //  Start  End    Start  End    Type                                       
        //  -----  -----  -----  -----  -------------------------------------------
        //  8      20     1507   1515   Ljava/lang/ClassCastException;
        //  1507   1515   1507   1515   Ljava/lang/EnumConstantNotPresentException;
        //  1523   1525   3      8      Ljava/lang/AssertionError;
        //  638    644    644    645    Any
        //  638    644    3      8      Ljava/lang/ArrayIndexOutOfBoundsException;
        //  638    644    3      8      Ljava/lang/NumberFormatException;
        //  638    644    644    645    Any
        //  638    644    3      8      Any
        //  655    661    661    662    Any
        //  655    661    661    662    Any
        //  655    661    3      8      Ljava/lang/IndexOutOfBoundsException;
        //  655    661    3      8      Any
        //  655    661    661    662    Any
        //  667    674    674    675    Any
        //  668    674    3      8      Ljava/util/NoSuchElementException;
        //  668    674    3      8      Any
        //  667    674    667    668    Any
        //  668    674    667    668    Ljava/lang/NegativeArraySizeException;
        //  719    726    726    727    Any
        //  720    726    3      8      Ljava/lang/NullPointerException;
        //  720    726    719    720    Any
        //  719    726    719    720    Ljava/lang/RuntimeException;
        //  719    726    726    727    Any
        //  866    873    873    874    Any
        //  867    873    866    867    Ljava/lang/RuntimeException;
        //  867    873    866    867    Ljava/lang/ArithmeticException;
        //  867    873    873    874    Any
        //  867    873    873    874    Any
        //  927    934    934    935    Any
        //  927    934    934    935    Ljava/lang/UnsupportedOperationException;
        //  928    934    3      8      Any
        //  928    934    927    928    Ljava/util/NoSuchElementException;
        //  927    934    934    935    Any
        //  945    952    952    953    Any
        //  946    952    945    946    Ljava/lang/IndexOutOfBoundsException;
        //  946    952    3      8      Any
        //  945    952    952    953    Any
        //  946    952    952    953    Any
        //  1007   1014   1014   1015   Any
        //  1008   1014   1014   1015   Ljava/lang/StringIndexOutOfBoundsException;
        //  1008   1014   1014   1015   Any
        //  1008   1014   1014   1015   Any
        //  1008   1014   1007   1008   Any
        //  1018   1025   1025   1026   Any
        //  1018   1025   3      8      Any
        //  1018   1025   1025   1026   Any
        //  1019   1025   3      8      Ljava/lang/ClassCastException;
        //  1019   1025   1018   1019   Ljava/lang/IllegalStateException;
        //  1080   1087   1087   1088   Any
        //  1081   1087   1080   1081   Any
        //  1081   1087   1080   1081   Ljava/lang/RuntimeException;
        //  1081   1087   3      8      Ljava/lang/IllegalStateException;
        //  1081   1087   1080   1081   Any
        //  1091   1098   1098   1099   Any
        //  1092   1098   3      8      Any
        //  1091   1098   1098   1099   Ljava/lang/ClassCastException;
        //  1091   1098   1091   1092   Ljava/lang/ArithmeticException;
        //  1092   1098   1091   1092   Ljava/util/ConcurrentModificationException;
        //  1195   1202   1202   1203   Any
        //  1195   1202   1195   1196   Any
        //  1195   1202   1202   1203   Any
        //  1196   1202   1202   1203   Any
        //  1195   1202   3      8      Any
        //  1248   1254   1254   1255   Any
        //  1248   1254   3      8      Any
        //  1248   1254   3      8      Any
        //  1248   1254   3      8      Any
        //  1248   1254   3      8      Any
        //  1310   1317   1317   1318   Any
        //  1310   1317   1310   1311   Ljava/util/NoSuchElementException;
        //  1311   1317   3      8      Ljava/lang/AssertionError;
        //  1310   1317   1310   1311   Ljava/lang/NegativeArraySizeException;
        //  1311   1317   1317   1318   Ljava/lang/IllegalArgumentException;
        //  1321   1328   1328   1329   Any
        //  1322   1328   1321   1322   Ljava/util/ConcurrentModificationException;
        //  1322   1328   3      8      Any
        //  1321   1328   1328   1329   Ljava/lang/IllegalArgumentException;
        //  1322   1328   1328   1329   Ljava/lang/StringIndexOutOfBoundsException;
        //  1419   1426   1426   1427   Any
        //  1419   1426   1419   1420   Ljava/lang/ClassCastException;
        //  1419   1426   1419   1420   Any
        //  1419   1426   3      8      Any
        //  1420   1426   1419   1420   Any
        //  1430   1437   1437   1438   Any
        //  1430   1437   3      8      Any
        //  1430   1437   1430   1431   Ljava/lang/IndexOutOfBoundsException;
        //  1430   1437   1430   1431   Any
        //  1430   1437   1430   1431   Ljava/lang/IllegalStateException;
        //  1441   1448   1448   1449   Any
        //  1442   1448   1441   1442   Any
        //  1441   1448   1441   1442   Any
        //  1441   1448   3      8      Ljava/lang/NumberFormatException;
        //  1441   1448   1448   1449   Ljava/lang/EnumConstantNotPresentException;
        // 
        // The error that occurred was:
        // 
        // java.lang.IndexOutOfBoundsException: Index -1 out of bounds for length 0
        //     at java.base/jdk.internal.util.Preconditions.outOfBounds(Preconditions.java:64)
        //     at java.base/jdk.internal.util.Preconditions.outOfBoundsCheckIndex(Preconditions.java:70)
        //     at java.base/jdk.internal.util.Preconditions.checkIndex(Preconditions.java:248)
        //     at java.base/java.util.Objects.checkIndex(Objects.java:372)
        //     at java.base/java.util.ArrayList.remove(ArrayList.java:535)
        //     at com.strobel.assembler.ir.StackMappingVisitor.pop(StackMappingVisitor.java:267)
        //     at com.strobel.assembler.ir.StackMappingVisitor$InstructionAnalyzer.execute(StackMappingVisitor.java:776)
        //     at com.strobel.assembler.ir.StackMappingVisitor$InstructionAnalyzer.visit(StackMappingVisitor.java:398)
        //     at com.strobel.decompiler.ast.AstBuilder.performStackAnalysis(AstBuilder.java:2030)
        //     at com.strobel.decompiler.ast.AstBuilder.build(AstBuilder.java:108)
        //     at com.strobel.decompiler.languages.java.ast.AstMethodBodyBuilder.createMethodBody(AstMethodBodyBuilder.java:211)
        //     at com.strobel.decompiler.languages.java.ast.AstMethodBodyBuilder.createMethodBody(AstMethodBodyBuilder.java:99)
        //     at com.strobel.decompiler.languages.java.ast.AstBuilder.createMethodBody(AstBuilder.java:782)
        //     at com.strobel.decompiler.languages.java.ast.AstBuilder.createMethod(AstBuilder.java:675)
        //     at com.strobel.decompiler.languages.java.ast.AstBuilder.addTypeMembers(AstBuilder.java:552)
        //     at com.strobel.decompiler.languages.java.ast.AstBuilder.createTypeCore(AstBuilder.java:519)
        //     at com.strobel.decompiler.languages.java.ast.AstBuilder.createTypeNoCache(AstBuilder.java:161)
        //     at com.strobel.decompiler.languages.java.ast.AstBuilder.createType(AstBuilder.java:150)
        //     at com.strobel.decompiler.languages.java.ast.AstBuilder.addType(AstBuilder.java:125)
        //     at com.strobel.decompiler.languages.java.JavaLanguage.buildAst(JavaLanguage.java:71)
        //     at com.strobel.decompiler.languages.java.JavaLanguage.decompileType(JavaLanguage.java:59)
        //     at com.strobel.decompiler.DecompilerDriver.decompileType(DecompilerDriver.java:330)
        //     at com.strobel.decompiler.DecompilerDriver.decompileJar(DecompilerDriver.java:251)
        //     at com.strobel.decompiler.DecompilerDriver.main(DecompilerDriver.java:126)
        // 
        throw new IllegalStateException("An error occurred while decompiling this method.");
    }
    
    static {
        throw t;
    }
    
    public f0v() {
        while (true) {
            int n = 0;
            Label_0013: {
                if (fc.0 != 0) {
                    n = 935645075;
                    break Label_0013;
                }
                n = -142033831;
            }
            switch (n ^ 0x71AF3A63) {
                case 898514246: {
                    continue;
                }
                default: {}
                case 1181480432: {
                    throw null;
                }
            }
            break;
        }
    }
}
