// 
// Decompiled by Procyon v0.5.36
// 

package dev.nuker.pyro;

public class f3O extends f3T
{
    @Override
    public boolean c(final float n, final float n2, final float n3) {
        return fbS.e(this, 1287254081, n, n2, n3);
    }
    
    static {
        throw t;
    }
    
    @Override
    public String 7() {
        // 
        // This method could not be decompiled.
        // 
        // Original Bytecode:
        // 
        //     3: dup            
        //     4: ifnull          68
        //     7: athrow         
        //     8: aconst_null    
        //     9: getstatic       dev/nuker/pyro/fc.1:I
        //    12: ifgt            60
        //    15: pop            
        //    16: aconst_null    
        //    17: goto            52
        //    20: nop            
        //    21: nop            
        //    22: nop            
        //    23: athrow         
        //    24: aload_0        
        //    25: getfield        dev/nuker/pyro/f3O.c:Ldev/nuker/pyro/f0n;
        //    28: checkcast       Ldev/nuker/pyro/f0e;
        //    31: goto            35
        //    34: athrow         
        //    35: invokevirtual   dev/nuker/pyro/f0e.c:()Ljava/lang/String;
        //    38: goto            42
        //    41: athrow         
        //    42: areturn        
        //    43: pop            
        //    44: goto            24
        //    47: pop            
        //    48: aconst_null    
        //    49: goto            43
        //    52: dup            
        //    53: ifnull          43
        //    56: checkcast       Ljava/lang/Throwable;
        //    59: athrow         
        //    60: dup            
        //    61: ifnull          47
        //    64: checkcast       Ljava/lang/Throwable;
        //    67: athrow         
        //    68: aconst_null    
        //    69: athrow         
        //    StackMapTable: 00 0D 43 07 00 1E 04 FF 00 0B 00 00 00 01 07 00 1E FC 00 03 07 00 03 49 07 00 1E 40 07 00 23 45 07 00 1E 40 07 00 27 40 07 00 1E 43 05 44 07 00 1E 47 05 47 07 00 1E
        //    Exceptions:
        //  Try           Handler
        //  Start  End    Start  End    Type                             
        //  -----  -----  -----  -----  ---------------------------------
        //  8      20     52     60     Any
        //  52     60     52     60     Any
        //  68     70     3      8      Ljava/lang/NumberFormatException;
        //  34     41     41     42     Any
        //  35     41     3      8      Ljava/lang/NullPointerException;
        //  35     41     34     35     Any
        //  34     41     3      8      Any
        //  35     41     3      8      Any
        // 
        // The error that occurred was:
        // 
        // java.lang.IndexOutOfBoundsException: Index 27 out of bounds for length 27
        //     at java.base/jdk.internal.util.Preconditions.outOfBounds(Preconditions.java:64)
        //     at java.base/jdk.internal.util.Preconditions.outOfBoundsCheckIndex(Preconditions.java:70)
        //     at java.base/jdk.internal.util.Preconditions.checkIndex(Preconditions.java:248)
        //     at java.base/java.util.Objects.checkIndex(Objects.java:372)
        //     at java.base/java.util.ArrayList.get(ArrayList.java:458)
        //     at com.strobel.decompiler.ast.AstBuilder.convertToAst(AstBuilder.java:3321)
        //     at com.strobel.decompiler.ast.AstBuilder.convertToAst(AstBuilder.java:3569)
        //     at com.strobel.decompiler.ast.AstBuilder.convertToAst(AstBuilder.java:3435)
        //     at com.strobel.decompiler.ast.AstBuilder.convertToAst(AstBuilder.java:3435)
        //     at com.strobel.decompiler.ast.AstBuilder.build(AstBuilder.java:113)
        //     at com.strobel.decompiler.languages.java.ast.AstMethodBodyBuilder.createMethodBody(AstMethodBodyBuilder.java:211)
        //     at com.strobel.decompiler.languages.java.ast.AstMethodBodyBuilder.createMethodBody(AstMethodBodyBuilder.java:99)
        //     at com.strobel.decompiler.languages.java.ast.AstBuilder.createMethodBody(AstBuilder.java:782)
        //     at com.strobel.decompiler.languages.java.ast.AstBuilder.createMethod(AstBuilder.java:675)
        //     at com.strobel.decompiler.languages.java.ast.AstBuilder.addTypeMembers(AstBuilder.java:552)
        //     at com.strobel.decompiler.languages.java.ast.AstBuilder.createTypeCore(AstBuilder.java:519)
        //     at com.strobel.decompiler.languages.java.ast.AstBuilder.createTypeNoCache(AstBuilder.java:161)
        //     at com.strobel.decompiler.languages.java.ast.AstBuilder.createType(AstBuilder.java:150)
        //     at com.strobel.decompiler.languages.java.ast.AstBuilder.addType(AstBuilder.java:125)
        //     at com.strobel.decompiler.languages.java.JavaLanguage.buildAst(JavaLanguage.java:71)
        //     at com.strobel.decompiler.languages.java.JavaLanguage.decompileType(JavaLanguage.java:59)
        //     at com.strobel.decompiler.DecompilerDriver.decompileType(DecompilerDriver.java:330)
        //     at com.strobel.decompiler.DecompilerDriver.decompileJar(DecompilerDriver.java:251)
        //     at com.strobel.decompiler.DecompilerDriver.main(DecompilerDriver.java:126)
        // 
        throw new IllegalStateException("An error occurred while decompiling this method.");
    }
    
    @Override
    public void c(final int p0, final int p1, final int p2) {
        // 
        // This method could not be decompiled.
        // 
        // Original Bytecode:
        // 
        //     3: dup            
        //     4: ifnull          388
        //     7: athrow         
        //     8: aconst_null    
        //     9: getstatic       dev/nuker/pyro/fc.0:I
        //    12: ifgt            380
        //    15: pop            
        //    16: aconst_null    
        //    17: goto            372
        //    20: nop            
        //    21: nop            
        //    22: nop            
        //    23: athrow         
        //    24: aload_0        
        //    25: iload_1        
        //    26: iload_2        
        //    27: iload_3        
        //    28: getstatic       dev/nuker/pyro/fc.0:I
        //    31: ifeq            39
        //    34: ldc             15868285
        //    36: goto            41
        //    39: ldc             -1132111014
        //    41: ldc             1607656255
        //    43: ixor           
        //    44: lookupswitch {
        //          -194705616: 39
        //          1595982402: 353
        //          default: 72
        //        }
        //    72: goto            76
        //    75: athrow         
        //    76: invokespecial   dev/nuker/pyro/f3T.c:(III)V
        //    79: goto            83
        //    82: athrow         
        //    83: getstatic       dev/nuker/pyro/fc.c:I
        //    86: ifge            94
        //    89: ldc             830851180
        //    91: goto            96
        //    94: ldc             -1496520878
        //    96: ldc             -1257127202
        //    98: ixor           
        //    99: lookupswitch {
        //          -2070672718: 355
        //          1251050839: 94
        //          default: 124
        //        }
        //   124: iload_3        
        //   125: iconst_1       
        //   126: if_icmpne       352
        //   129: aload_0        
        //   130: getstatic       dev/nuker/pyro/fc.1:I
        //   133: ifeq            141
        //   136: ldc             2042245108
        //   138: goto            143
        //   141: ldc             -1045467368
        //   143: ldc             -1687700749
        //   145: ixor           
        //   146: lookupswitch {
        //          -488794873: 141
        //          1523111403: 172
        //          default: 359
        //        }
        //   172: goto            176
        //   175: athrow         
        //   176: invokevirtual   dev/nuker/pyro/f3O.4:()Ljava/util/List;
        //   179: goto            183
        //   182: athrow         
        //   183: goto            187
        //   186: athrow         
        //   187: invokeinterface java/util/List.isEmpty:()Z
        //   192: goto            196
        //   195: athrow         
        //   196: ifne            352
        //   199: aload_0        
        //   200: getstatic       dev/nuker/pyro/fc.0:I
        //   203: ifeq            211
        //   206: ldc             121610908
        //   208: goto            213
        //   211: ldc             -1501404962
        //   213: ldc             1603627760
        //   215: ixor           
        //   216: lookupswitch {
        //          -115930578: 244
        //          1487587436: 211
        //          default: 361
        //        }
        //   244: aload_0        
        //   245: getstatic       dev/nuker/pyro/fc.c:I
        //   248: ifge            256
        //   251: ldc             -1923471338
        //   253: goto            258
        //   256: ldc             -434141118
        //   258: ldc             225631208
        //   260: ixor           
        //   261: lookupswitch {
        //          -2144799746: 357
        //          1471440823: 256
        //          default: 288
        //        }
        //   288: goto            292
        //   291: athrow         
        //   292: invokevirtual   dev/nuker/pyro/f3O.0:()Z
        //   295: goto            299
        //   298: athrow         
        //   299: ifne            307
        //   302: ldc             270276494
        //   304: goto            309
        //   307: ldc             270276495
        //   309: ldc             -251972344
        //   311: ixor           
        //   312: tableswitch {
        //          -1043446516: 336
        //          -1043446515: 340
        //          default: 302
        //        }
        //   336: iconst_1       
        //   337: goto            341
        //   340: iconst_0       
        //   341: goto            345
        //   344: athrow         
        //   345: invokevirtual   dev/nuker/pyro/f3O.c:(Z)V
        //   348: goto            352
        //   351: athrow         
        //   352: return         
        //   353: aconst_null    
        //   354: athrow         
        //   355: aconst_null    
        //   356: athrow         
        //   357: aconst_null    
        //   358: athrow         
        //   359: aconst_null    
        //   360: athrow         
        //   361: aconst_null    
        //   362: athrow         
        //   363: pop            
        //   364: goto            24
        //   367: pop            
        //   368: aconst_null    
        //   369: goto            363
        //   372: dup            
        //   373: ifnull          363
        //   376: checkcast       Ljava/lang/Throwable;
        //   379: athrow         
        //   380: dup            
        //   381: ifnull          367
        //   384: checkcast       Ljava/lang/Throwable;
        //   387: athrow         
        //   388: aconst_null    
        //   389: athrow         
        //    StackMapTable: 00 37 43 07 00 1E 04 FF 00 0B 00 00 00 01 07 00 1E FF 00 03 00 04 07 00 03 01 01 01 00 00 FF 00 0E 00 04 07 00 03 01 01 01 00 04 07 00 03 01 01 01 FF 00 01 00 04 07 00 03 01 01 01 00 05 07 00 03 01 01 01 01 FF 00 1E 00 04 07 00 03 01 01 01 00 04 07 00 03 01 01 01 42 07 00 1E FF 00 00 00 04 07 00 03 01 01 01 00 04 07 00 03 01 01 01 45 07 00 1E 00 0A 41 01 1B 50 07 00 03 FF 00 01 00 04 07 00 03 01 01 01 00 02 07 00 03 01 5C 07 00 03 42 07 00 1E 40 07 00 03 45 07 00 1E 40 07 00 48 FF 00 02 00 00 00 01 07 00 1E FF 00 00 00 04 07 00 03 01 01 01 00 01 07 00 48 47 07 00 1E 40 01 4E 07 00 03 FF 00 01 00 04 07 00 03 01 01 01 00 02 07 00 03 01 5E 07 00 03 FF 00 0B 00 04 07 00 03 01 01 01 00 02 07 00 03 07 00 03 FF 00 01 00 04 07 00 03 01 01 01 00 03 07 00 03 07 00 03 01 FF 00 1D 00 04 07 00 03 01 01 01 00 02 07 00 03 07 00 03 42 07 00 1E FF 00 00 00 04 07 00 03 01 01 01 00 02 07 00 03 07 00 03 45 07 00 1E FF 00 00 00 04 07 00 03 01 01 01 00 02 07 00 03 01 42 07 00 03 44 07 00 03 FF 00 01 00 04 07 00 03 01 01 01 00 02 07 00 03 01 5A 07 00 03 43 07 00 03 FF 00 00 00 04 07 00 03 01 01 01 00 02 07 00 03 01 FF 00 02 00 00 00 01 07 00 1E FF 00 00 00 04 07 00 03 01 01 01 00 02 07 00 03 01 45 07 00 1E 00 FF 00 00 00 04 07 00 03 01 01 01 00 04 07 00 03 01 01 01 01 FF 00 01 00 04 07 00 03 01 01 01 00 02 07 00 03 07 00 03 41 07 00 03 41 07 00 03 41 07 00 1E 43 05 44 07 00 1E 47 05 47 07 00 1E
        //    Exceptions:
        //  Try           Handler
        //  Start  End    Start  End    Type                                       
        //  -----  -----  -----  -----  -------------------------------------------
        //  8      20     372    380    Any
        //  372    380    372    380    Ljava/lang/EnumConstantNotPresentException;
        //  388    390    3      8      Any
        //  75     82     82     83     Any
        //  76     82     3      8      Ljava/lang/UnsupportedOperationException;
        //  75     82     3      8      Any
        //  76     82     82     83     Any
        //  76     82     75     76     Any
        //  175    182    182    183    Any
        //  176    182    3      8      Ljava/lang/IllegalArgumentException;
        //  176    182    175    176    Any
        //  175    182    3      8      Any
        //  176    182    175    176    Any
        //  187    195    195    196    Any
        //  187    195    195    196    Ljava/lang/ClassCastException;
        //  187    195    3      8      Any
        //  187    195    195    196    Any
        //  187    195    195    196    Any
        //  291    298    298    299    Any
        //  291    298    291    292    Any
        //  291    298    291    292    Any
        //  292    298    298    299    Ljava/lang/NumberFormatException;
        //  291    298    291    292    Any
        //  345    351    351    352    Any
        //  345    351    351    352    Any
        //  345    351    3      8      Any
        //  345    351    3      8      Any
        //  345    351    351    352    Ljava/lang/AssertionError;
        // 
        // The error that occurred was:
        // 
        // java.lang.IndexOutOfBoundsException: Index -1 out of bounds for length 0
        //     at java.base/jdk.internal.util.Preconditions.outOfBounds(Preconditions.java:64)
        //     at java.base/jdk.internal.util.Preconditions.outOfBoundsCheckIndex(Preconditions.java:70)
        //     at java.base/jdk.internal.util.Preconditions.checkIndex(Preconditions.java:248)
        //     at java.base/java.util.Objects.checkIndex(Objects.java:372)
        //     at java.base/java.util.ArrayList.remove(ArrayList.java:535)
        //     at com.strobel.assembler.ir.StackMappingVisitor.pop(StackMappingVisitor.java:267)
        //     at com.strobel.assembler.ir.StackMappingVisitor$InstructionAnalyzer.execute(StackMappingVisitor.java:776)
        //     at com.strobel.assembler.ir.StackMappingVisitor$InstructionAnalyzer.visit(StackMappingVisitor.java:398)
        //     at com.strobel.decompiler.ast.AstBuilder.performStackAnalysis(AstBuilder.java:2030)
        //     at com.strobel.decompiler.ast.AstBuilder.build(AstBuilder.java:108)
        //     at com.strobel.decompiler.languages.java.ast.AstMethodBodyBuilder.createMethodBody(AstMethodBodyBuilder.java:211)
        //     at com.strobel.decompiler.languages.java.ast.AstMethodBodyBuilder.createMethodBody(AstMethodBodyBuilder.java:99)
        //     at com.strobel.decompiler.languages.java.ast.AstBuilder.createMethodBody(AstBuilder.java:782)
        //     at com.strobel.decompiler.languages.java.ast.AstBuilder.createMethod(AstBuilder.java:675)
        //     at com.strobel.decompiler.languages.java.ast.AstBuilder.addTypeMembers(AstBuilder.java:552)
        //     at com.strobel.decompiler.languages.java.ast.AstBuilder.createTypeCore(AstBuilder.java:519)
        //     at com.strobel.decompiler.languages.java.ast.AstBuilder.createTypeNoCache(AstBuilder.java:161)
        //     at com.strobel.decompiler.languages.java.ast.AstBuilder.createType(AstBuilder.java:150)
        //     at com.strobel.decompiler.languages.java.ast.AstBuilder.addType(AstBuilder.java:125)
        //     at com.strobel.decompiler.languages.java.JavaLanguage.buildAst(JavaLanguage.java:71)
        //     at com.strobel.decompiler.languages.java.JavaLanguage.decompileType(JavaLanguage.java:59)
        //     at com.strobel.decompiler.DecompilerDriver.decompileType(DecompilerDriver.java:330)
        //     at com.strobel.decompiler.DecompilerDriver.decompileJar(DecompilerDriver.java:251)
        //     at com.strobel.decompiler.DecompilerDriver.main(DecompilerDriver.java:126)
        // 
        throw new IllegalStateException("An error occurred while decompiling this method.");
    }
    
    public f3O(final f0n f0n, final float n, final float n2) {
        while (true) {
            int n3 = 0;
            Label_0017: {
                if (fc.c < 0) {
                    n3 = -596838180;
                    break Label_0017;
                }
                n3 = -1792121846;
            }
            switch (n3 ^ 0xB080A771) {
                case -1916361349: {
                    continue;
                }
                default: {
                    super(f0n, n, n2);
                }
                case 1827430317: {
                    throw null;
                }
            }
            break;
        }
    }
}
