// 
// Decompiled by Procyon v0.5.36
// 

package dev.nuker.pyro;

public class f3P extends f3T
{
    public f3Q c;
    public Object c;
    public boolean 1;
    public f3Q 0;
    
    public f3P(final f3Q 0, final f3Q c, final Object c2, final float n, final float n2) {
        while (true) {
            int n3 = 0;
            Label_0013: {
                if (fc.1 != 0) {
                    n3 = 479839881;
                    break Label_0013;
                }
                n3 = -289167391;
            }
            switch (n3 ^ 0x29DEB3D) {
                case 503590324: {
                    continue;
                }
                case -329364260: {
                    while (true) {
                        int n4 = 0;
                        Label_0058: {
                            if (fc.1 != 0) {
                                n4 = -711555123;
                                break Label_0058;
                            }
                            n4 = 1124248165;
                        }
                        switch (n4 ^ 0xEA850E79) {
                            case 1058245044: {
                                continue;
                            }
                            case -1450728420: {
                                while (true) {
                                    int n5 = 0;
                                    Label_0102: {
                                        if (fc.0 != 0) {
                                            n5 = 1224234197;
                                            break Label_0102;
                                        }
                                        n5 = -449708551;
                                    }
                                    switch (n5 ^ 0x99AEBAE8) {
                                        case 1929429544: {
                                            continue;
                                        }
                                        default: {
                                            this.0 = 0;
                                            while (true) {
                                                int n6 = 0;
                                                Label_0150: {
                                                    if (fc.1 != 0) {
                                                        n6 = 1481921911;
                                                        break Label_0150;
                                                    }
                                                    n6 = 1432275396;
                                                }
                                                switch (n6 ^ 0xE7748068) {
                                                    case -1088367329: {
                                                        continue;
                                                    }
                                                    case -1305851476: {
                                                        super(c.c(), n, n2);
                                                        while (true) {
                                                            int n7 = 0;
                                                            Label_0203: {
                                                                if (fc.1 != 0) {
                                                                    n7 = 1331347788;
                                                                    break Label_0203;
                                                                }
                                                                n7 = 895307577;
                                                            }
                                                            switch (n7 ^ 0x189ACE4D) {
                                                                case -2089785331: {
                                                                    continue;
                                                                }
                                                                default: {
                                                                    while (true) {
                                                                        int n8 = 0;
                                                                        Label_0246: {
                                                                            if (fc.1 != 0) {
                                                                                n8 = -1551920642;
                                                                                break Label_0246;
                                                                            }
                                                                            n8 = 648114252;
                                                                        }
                                                                        switch (n8 ^ 0xD1CB9060) {
                                                                            case 307591361: {
                                                                                continue;
                                                                            }
                                                                            default: {
                                                                                while (true) {
                                                                                    int n9 = 0;
                                                                                    Label_0290: {
                                                                                        if (fc.1 != 0) {
                                                                                            n9 = 431590639;
                                                                                            break Label_0290;
                                                                                        }
                                                                                        n9 = -1418371635;
                                                                                    }
                                                                                    switch (n9 ^ 0x4B8660E4) {
                                                                                        case 1379920907: {
                                                                                            continue;
                                                                                        }
                                                                                        case -520930007: {
                                                                                            this.c = c;
                                                                                            while (true) {
                                                                                                int n10 = 0;
                                                                                                Label_0337: {
                                                                                                    if (fc.1 != 0) {
                                                                                                        n10 = -1359458878;
                                                                                                        break Label_0337;
                                                                                                    }
                                                                                                    n10 = -781164174;
                                                                                                }
                                                                                                switch (n10 ^ 0x980F2874) {
                                                                                                    case 922183094: {
                                                                                                        continue;
                                                                                                    }
                                                                                                    case 1233078534: {
                                                                                                        this.c = c2;
                                                                                                        return;
                                                                                                    }
                                                                                                    default: {
                                                                                                        throw null;
                                                                                                    }
                                                                                                }
                                                                                                break;
                                                                                            }
                                                                                            break;
                                                                                        }
                                                                                        default: {
                                                                                            throw null;
                                                                                        }
                                                                                    }
                                                                                    break;
                                                                                }
                                                                                break;
                                                                            }
                                                                            case 1924399518: {
                                                                                throw null;
                                                                            }
                                                                        }
                                                                        break;
                                                                    }
                                                                    break;
                                                                }
                                                                case 1472204545: {
                                                                    throw null;
                                                                }
                                                            }
                                                            break;
                                                        }
                                                        break;
                                                    }
                                                    default: {
                                                        throw null;
                                                    }
                                                }
                                                break;
                                            }
                                            break;
                                        }
                                        case -782832067: {
                                            throw null;
                                        }
                                    }
                                    break;
                                }
                                break;
                            }
                            default: {
                                throw null;
                            }
                        }
                        break;
                    }
                    break;
                }
                default: {
                    throw null;
                }
            }
            break;
        }
    }
    
    public Object 0() {
        return fbS.3r(this, 1778951912);
    }
    
    @Override
    public boolean c(final float n, final float n2, final float n3) {
        return fbS.d(this, 1236311987, n, n2, n3);
    }
    
    static {
        throw t;
    }
    
    @Override
    public String 7() {
        return fbS.4Y(this, 1411007736);
    }
    
    public void 1(final boolean b) {
        fbS.4y(this, 1099163285, b);
    }
    
    @Override
    public void c(final int p0, final int p1, final int p2) {
        // 
        // This method could not be decompiled.
        // 
        // Original Bytecode:
        // 
        //     3: dup            
        //     4: ifnull          364
        //     7: athrow         
        //     8: aconst_null    
        //     9: getstatic       dev/nuker/pyro/fc.1:I
        //    12: ifgt            356
        //    15: pop            
        //    16: aconst_null    
        //    17: goto            348
        //    20: nop            
        //    21: nop            
        //    22: nop            
        //    23: athrow         
        //    24: aload_0        
        //    25: getstatic       dev/nuker/pyro/fc.c:I
        //    28: ifge            36
        //    31: ldc             -380380991
        //    33: goto            38
        //    36: ldc             1194046424
        //    38: ldc             1985145331
        //    40: ixor           
        //    41: lookupswitch {
        //          -1627311822: 331
        //          -892779038: 36
        //          default: 68
        //        }
        //    68: iload_1        
        //    69: iload_2        
        //    70: getstatic       dev/nuker/pyro/fc.1:I
        //    73: ifeq            81
        //    76: ldc             -243558724
        //    78: goto            83
        //    81: ldc             1597127086
        //    83: ldc             1626706886
        //    85: ixor           
        //    86: lookupswitch {
        //          -1852963462: 333
        //          -1605124191: 81
        //          default: 112
        //        }
        //   112: iload_3        
        //   113: goto            117
        //   116: athrow         
        //   117: invokespecial   dev/nuker/pyro/f3T.c:(III)V
        //   120: goto            124
        //   123: athrow         
        //   124: iload_3        
        //   125: ifne            133
        //   128: ldc             -345170293
        //   130: goto            135
        //   133: ldc             -345170296
        //   135: ldc             1563174986
        //   137: ixor           
        //   138: tableswitch {
        //          1820487042: 160
        //          1820487043: 179
        //          default: 128
        //        }
        //   160: aload_0        
        //   161: getfield        dev/nuker/pyro/f3P.c:Ldev/nuker/pyro/f3Q;
        //   164: aload_0        
        //   165: goto            169
        //   168: athrow         
        //   169: invokevirtual   dev/nuker/pyro/f3Q.c:(Ldev/nuker/pyro/f3P;)V
        //   172: goto            176
        //   175: athrow         
        //   176: goto            330
        //   179: iload_3        
        //   180: iconst_1       
        //   181: if_icmpne       330
        //   184: aload_0        
        //   185: getstatic       dev/nuker/pyro/fc.0:I
        //   188: ifeq            196
        //   191: ldc             -968629955
        //   193: goto            198
        //   196: ldc             -1945119168
        //   198: ldc             -321581195
        //   200: ixor           
        //   201: lookupswitch {
        //          -133530773: 196
        //          714534472: 335
        //          default: 228
        //        }
        //   228: goto            232
        //   231: athrow         
        //   232: invokevirtual   dev/nuker/pyro/f3P.4:()Ljava/util/List;
        //   235: goto            239
        //   238: athrow         
        //   239: goto            243
        //   242: athrow         
        //   243: invokeinterface java/util/List.isEmpty:()Z
        //   248: goto            252
        //   251: athrow         
        //   252: ifne            330
        //   255: aload_0        
        //   256: aload_0        
        //   257: getstatic       dev/nuker/pyro/fc.0:I
        //   260: ifeq            268
        //   263: ldc             493640950
        //   265: goto            270
        //   268: ldc             -790976185
        //   270: ldc             39303632
        //   272: ixor           
        //   273: lookupswitch {
        //          -762507113: 300
        //          524018982: 268
        //          default: 337
        //        }
        //   300: goto            304
        //   303: athrow         
        //   304: invokevirtual   dev/nuker/pyro/f3P.0:()Z
        //   307: goto            311
        //   310: athrow         
        //   311: ifne            318
        //   314: iconst_1       
        //   315: goto            319
        //   318: iconst_0       
        //   319: goto            323
        //   322: athrow         
        //   323: invokevirtual   dev/nuker/pyro/f3P.c:(Z)V
        //   326: goto            330
        //   329: athrow         
        //   330: return         
        //   331: aconst_null    
        //   332: athrow         
        //   333: aconst_null    
        //   334: athrow         
        //   335: aconst_null    
        //   336: athrow         
        //   337: aconst_null    
        //   338: athrow         
        //   339: pop            
        //   340: goto            24
        //   343: pop            
        //   344: aconst_null    
        //   345: goto            339
        //   348: dup            
        //   349: ifnull          339
        //   352: checkcast       Ljava/lang/Throwable;
        //   355: athrow         
        //   356: dup            
        //   357: ifnull          343
        //   360: checkcast       Ljava/lang/Throwable;
        //   363: athrow         
        //   364: aconst_null    
        //   365: athrow         
        //    StackMapTable: 00 38 43 07 00 6A 04 FF 00 0B 00 00 00 01 07 00 6A FF 00 03 00 04 07 00 03 01 01 01 00 00 4B 07 00 03 FF 00 01 00 04 07 00 03 01 01 01 00 02 07 00 03 01 5D 07 00 03 FF 00 0C 00 04 07 00 03 01 01 01 00 03 07 00 03 01 01 FF 00 01 00 04 07 00 03 01 01 01 00 04 07 00 03 01 01 01 FF 00 1C 00 04 07 00 03 01 01 01 00 03 07 00 03 01 01 FF 00 03 00 00 00 01 07 00 6A FF 00 00 00 04 07 00 03 01 01 01 00 04 07 00 03 01 01 01 45 07 00 6A 00 03 04 41 01 18 47 07 00 6A FF 00 00 00 04 07 00 03 01 01 01 00 02 07 00 24 07 00 03 45 07 00 6A 00 02 50 07 00 03 FF 00 01 00 04 07 00 03 01 01 01 00 02 07 00 03 01 5D 07 00 03 42 07 00 5C 40 07 00 03 45 07 00 6A 40 07 00 83 42 07 00 66 40 07 00 83 47 07 00 6A 40 01 FF 00 0F 00 04 07 00 03 01 01 01 00 02 07 00 03 07 00 03 FF 00 01 00 04 07 00 03 01 01 01 00 03 07 00 03 07 00 03 01 FF 00 1D 00 04 07 00 03 01 01 01 00 02 07 00 03 07 00 03 42 07 00 6A FF 00 00 00 04 07 00 03 01 01 01 00 02 07 00 03 07 00 03 45 07 00 6A FF 00 00 00 04 07 00 03 01 01 01 00 02 07 00 03 01 46 07 00 03 FF 00 00 00 04 07 00 03 01 01 01 00 02 07 00 03 01 FF 00 02 00 00 00 01 07 00 6A FF 00 00 00 04 07 00 03 01 01 01 00 02 07 00 03 01 45 07 00 6A 00 40 07 00 03 FF 00 01 00 04 07 00 03 01 01 01 00 03 07 00 03 01 01 41 07 00 03 FF 00 01 00 04 07 00 03 01 01 01 00 02 07 00 03 07 00 03 41 07 00 6A 43 05 44 07 00 6A 47 05 47 07 00 6A
        //    Exceptions:
        //  Try           Handler
        //  Start  End    Start  End    Type                                      
        //  -----  -----  -----  -----  ------------------------------------------
        //  8      20     348    356    Ljava/lang/RuntimeException;
        //  348    356    348    356    Any
        //  364    366    3      8      Any
        //  117    123    123    124    Any
        //  117    123    123    124    Any
        //  117    123    3      8      Any
        //  117    123    123    124    Any
        //  117    123    3      8      Ljava/lang/AssertionError;
        //  168    175    175    176    Any
        //  168    175    168    169    Any
        //  168    175    3      8      Any
        //  168    175    3      8      Any
        //  169    175    168    169    Ljava/lang/IllegalStateException;
        //  231    238    238    239    Any
        //  232    238    238    239    Any
        //  231    238    231    232    Ljava/lang/IndexOutOfBoundsException;
        //  231    238    231    232    Ljava/lang/IllegalStateException;
        //  231    238    231    232    Ljava/lang/ArrayIndexOutOfBoundsException;
        //  242    251    251    252    Any
        //  243    251    242    243    Ljava/lang/ArithmeticException;
        //  242    251    3      8      Any
        //  243    251    3      8      Ljava/lang/NumberFormatException;
        //  243    251    251    252    Any
        //  303    310    310    311    Any
        //  304    310    303    304    Any
        //  304    310    303    304    Any
        //  304    310    3      8      Any
        //  303    310    303    304    Any
        //  323    329    329    330    Any
        //  323    329    329    330    Any
        //  323    329    3      8      Any
        //  323    329    329    330    Ljava/lang/IndexOutOfBoundsException;
        //  323    329    3      8      Ljava/lang/ArrayIndexOutOfBoundsException;
        // 
        // The error that occurred was:
        // 
        // java.lang.IndexOutOfBoundsException: Index -1 out of bounds for length 0
        //     at java.base/jdk.internal.util.Preconditions.outOfBounds(Preconditions.java:64)
        //     at java.base/jdk.internal.util.Preconditions.outOfBoundsCheckIndex(Preconditions.java:70)
        //     at java.base/jdk.internal.util.Preconditions.checkIndex(Preconditions.java:248)
        //     at java.base/java.util.Objects.checkIndex(Objects.java:372)
        //     at java.base/java.util.ArrayList.remove(ArrayList.java:535)
        //     at com.strobel.assembler.ir.StackMappingVisitor.pop(StackMappingVisitor.java:267)
        //     at com.strobel.assembler.ir.StackMappingVisitor$InstructionAnalyzer.execute(StackMappingVisitor.java:577)
        //     at com.strobel.assembler.ir.StackMappingVisitor$InstructionAnalyzer.visit(StackMappingVisitor.java:398)
        //     at com.strobel.decompiler.ast.AstBuilder.performStackAnalysis(AstBuilder.java:2030)
        //     at com.strobel.decompiler.ast.AstBuilder.build(AstBuilder.java:108)
        //     at com.strobel.decompiler.languages.java.ast.AstMethodBodyBuilder.createMethodBody(AstMethodBodyBuilder.java:211)
        //     at com.strobel.decompiler.languages.java.ast.AstMethodBodyBuilder.createMethodBody(AstMethodBodyBuilder.java:99)
        //     at com.strobel.decompiler.languages.java.ast.AstBuilder.createMethodBody(AstBuilder.java:782)
        //     at com.strobel.decompiler.languages.java.ast.AstBuilder.createMethod(AstBuilder.java:675)
        //     at com.strobel.decompiler.languages.java.ast.AstBuilder.addTypeMembers(AstBuilder.java:552)
        //     at com.strobel.decompiler.languages.java.ast.AstBuilder.createTypeCore(AstBuilder.java:519)
        //     at com.strobel.decompiler.languages.java.ast.AstBuilder.createTypeNoCache(AstBuilder.java:161)
        //     at com.strobel.decompiler.languages.java.ast.AstBuilder.createType(AstBuilder.java:150)
        //     at com.strobel.decompiler.languages.java.ast.AstBuilder.addType(AstBuilder.java:125)
        //     at com.strobel.decompiler.languages.java.JavaLanguage.buildAst(JavaLanguage.java:71)
        //     at com.strobel.decompiler.languages.java.JavaLanguage.decompileType(JavaLanguage.java:59)
        //     at com.strobel.decompiler.DecompilerDriver.decompileType(DecompilerDriver.java:330)
        //     at com.strobel.decompiler.DecompilerDriver.decompileJar(DecompilerDriver.java:251)
        //     at com.strobel.decompiler.DecompilerDriver.main(DecompilerDriver.java:126)
        // 
        throw new IllegalStateException("An error occurred while decompiling this method.");
    }
    
    public boolean c() {
        return fbS.eE(this, 255261138);
    }
}
