// 
// Decompiled by Procyon v0.5.36
// 

package dev.nuker.pyro;

import dev.nuker.pyro.f3Q$dev.nuker.pyro.f3P;
import java.util.ArrayList;

public class f3Q extends f3T
{
    public Object[] c;
    public ArrayList<f3P> c;
    
    @Override
    public void c() {
        // 
        // This method could not be decompiled.
        // 
        // Original Bytecode:
        // 
        //     3: dup            
        //     4: ifnull          701
        //     7: athrow         
        //     8: aconst_null    
        //     9: getstatic       dev/nuker/pyro/fc.1:I
        //    12: ifgt            693
        //    15: pop            
        //    16: aconst_null    
        //    17: goto            685
        //    20: nop            
        //    21: nop            
        //    22: nop            
        //    23: athrow         
        //    24: aload_0        
        //    25: goto            29
        //    28: athrow         
        //    29: invokevirtual   dev/nuker/pyro/f3Q.4:()Ljava/util/List;
        //    32: goto            36
        //    35: athrow         
        //    36: goto            40
        //    39: athrow         
        //    40: invokeinterface java/util/List.clear:()V
        //    45: goto            49
        //    48: athrow         
        //    49: aload_0        
        //    50: getstatic       dev/nuker/pyro/fc.c:I
        //    53: ifge            61
        //    56: ldc             -1067216300
        //    58: goto            63
        //    61: ldc             1171302545
        //    63: ldc             -1849427656
        //    65: ixor           
        //    66: lookupswitch {
        //          1369467756: 662
        //          2039469434: 61
        //          default: 92
        //        }
        //    92: getfield        dev/nuker/pyro/f3Q.c:Ldev/nuker/pyro/f0n;
        //    95: checkcast       Ldev/nuker/pyro/f0f;
        //    98: astore_1       
        //    99: aload_1        
        //   100: goto            104
        //   103: athrow         
        //   104: invokevirtual   dev/nuker/pyro/f0f.3:()Ljava/lang/Object;
        //   107: goto            111
        //   110: athrow         
        //   111: goto            115
        //   114: athrow         
        //   115: invokevirtual   java/lang/Object.getClass:()Ljava/lang/Class;
        //   118: goto            122
        //   121: athrow         
        //   122: goto            126
        //   125: athrow         
        //   126: invokevirtual   java/lang/Class.getEnumConstants:()[Ljava/lang/Object;
        //   129: goto            133
        //   132: athrow         
        //   133: ifnull          657
        //   136: aload_0        
        //   137: aload_1        
        //   138: goto            142
        //   141: athrow         
        //   142: invokevirtual   dev/nuker/pyro/f0f.3:()Ljava/lang/Object;
        //   145: goto            149
        //   148: athrow         
        //   149: getstatic       dev/nuker/pyro/fc.c:I
        //   152: ifge            160
        //   155: ldc             54544723
        //   157: goto            162
        //   160: ldc             504453361
        //   162: ldc             1613613684
        //   164: ixor           
        //   165: lookupswitch {
        //          1558658607: 160
        //          1668121383: 664
        //          default: 192
        //        }
        //   192: goto            196
        //   195: athrow         
        //   196: invokevirtual   java/lang/Object.getClass:()Ljava/lang/Class;
        //   199: goto            203
        //   202: athrow         
        //   203: goto            207
        //   206: athrow         
        //   207: invokevirtual   java/lang/Class.getEnumConstants:()[Ljava/lang/Object;
        //   210: goto            214
        //   213: athrow         
        //   214: putfield        dev/nuker/pyro/f3Q.c:[Ljava/lang/Object;
        //   217: aload_0        
        //   218: getfield        dev/nuker/pyro/f3Q.c:[Ljava/lang/Object;
        //   221: astore_2       
        //   222: aload_2        
        //   223: arraylength    
        //   224: istore_3       
        //   225: iconst_0       
        //   226: istore          4
        //   228: iload           4
        //   230: iload_3        
        //   231: if_icmpge       657
        //   234: aload_2        
        //   235: iload           4
        //   237: aaload         
        //   238: astore          5
        //   240: aload_0        
        //   241: getfield        dev/nuker/pyro/f3Q.c:Ljava/util/List;
        //   244: new             Ldev/nuker/pyro/f3P;
        //   247: dup            
        //   248: aload_0        
        //   249: aload_0        
        //   250: aload           5
        //   252: aload_0        
        //   253: goto            257
        //   256: athrow         
        //   257: invokevirtual   dev/nuker/pyro/f3Q.1:()F
        //   260: goto            264
        //   263: athrow         
        //   264: aload_0        
        //   265: goto            269
        //   268: athrow         
        //   269: invokevirtual   dev/nuker/pyro/f3Q.3:()F
        //   272: goto            276
        //   275: athrow         
        //   276: getstatic       dev/nuker/pyro/fc.1:I
        //   279: ifeq            287
        //   282: ldc             -815165258
        //   284: goto            289
        //   287: ldc             1196858559
        //   289: ldc             1645477612
        //   291: ixor           
        //   292: lookupswitch {
        //          -1384485286: 666
        //          -839340910: 287
        //          default: 320
        //        }
        //   320: goto            324
        //   323: athrow         
        //   324: invokespecial   dev/nuker/pyro/f3P.<init>:(Ldev/nuker/pyro/f3Q;Ldev/nuker/pyro/f3Q;Ljava/lang/Object;FF)V
        //   327: goto            331
        //   330: athrow         
        //   331: dup            
        //   332: getstatic       dev/nuker/pyro/fc.0:I
        //   335: ifeq            343
        //   338: ldc             -1719226153
        //   340: goto            345
        //   343: ldc             562408637
        //   345: ldc             2083485487
        //   347: ixor           
        //   348: lookupswitch {
        //          -441858056: 672
        //          -215516689: 343
        //          default: 376
        //        }
        //   376: astore          6
        //   378: getstatic       dev/nuker/pyro/fc.c:I
        //   381: ifge            389
        //   384: ldc             1327339765
        //   386: goto            391
        //   389: ldc             2065911628
        //   391: ldc             1010535119
        //   393: ixor           
        //   394: lookupswitch {
        //          693731106: 389
        //          1931874874: 668
        //          default: 420
        //        }
        //   420: goto            424
        //   423: athrow         
        //   424: invokeinterface java/util/List.add:(Ljava/lang/Object;)Z
        //   429: goto            433
        //   432: athrow         
        //   433: pop            
        //   434: aload_0        
        //   435: getstatic       dev/nuker/pyro/fc.c:I
        //   438: ifge            446
        //   441: ldc             752263130
        //   443: goto            448
        //   446: ldc             -761736469
        //   448: ldc             -522749966
        //   450: ixor           
        //   451: lookupswitch {
        //          -872290264: 670
        //          1690511911: 446
        //          default: 476
        //        }
        //   476: getfield        dev/nuker/pyro/f3Q.c:Ljava/util/ArrayList;
        //   479: aload           6
        //   481: getstatic       dev/nuker/pyro/fc.0:I
        //   484: ifeq            492
        //   487: ldc             1892504633
        //   489: goto            494
        //   492: ldc             -781010845
        //   494: ldc             1820715749
        //   496: ixor           
        //   497: lookupswitch {
        //          -1066712713: 492
        //          474529500: 660
        //          default: 524
        //        }
        //   524: goto            528
        //   527: athrow         
        //   528: invokevirtual   java/util/ArrayList.add:(Ljava/lang/Object;)Z
        //   531: goto            535
        //   534: athrow         
        //   535: pop            
        //   536: aload_1        
        //   537: getstatic       dev/nuker/pyro/fc.0:I
        //   540: ifeq            548
        //   543: ldc             618776709
        //   545: goto            550
        //   548: ldc             1554475369
        //   550: ldc             1439258256
        //   552: ixor           
        //   553: lookupswitch {
        //          -1997826654: 548
        //          1898487317: 674
        //          default: 580
        //        }
        //   580: goto            584
        //   583: athrow         
        //   584: invokevirtual   dev/nuker/pyro/f0f.3:()Ljava/lang/Object;
        //   587: goto            591
        //   590: athrow         
        //   591: aload           5
        //   593: if_acmpne       651
        //   596: aload           6
        //   598: iconst_1       
        //   599: getstatic       dev/nuker/pyro/fc.c:I
        //   602: ifge            610
        //   605: ldc             1688613309
        //   607: goto            612
        //   610: ldc             1192678627
        //   612: ldc             -1463126048
        //   614: ixor           
        //   615: lookupswitch {
        //          -865319331: 610
        //          -270753021: 640
        //          default: 658
        //        }
        //   640: goto            644
        //   643: athrow         
        //   644: invokevirtual   dev/nuker/pyro/f3P.1:(Z)V
        //   647: goto            651
        //   650: athrow         
        //   651: iinc            4, 1
        //   654: goto            228
        //   657: return         
        //   658: aconst_null    
        //   659: athrow         
        //   660: aconst_null    
        //   661: athrow         
        //   662: aconst_null    
        //   663: athrow         
        //   664: aconst_null    
        //   665: athrow         
        //   666: aconst_null    
        //   667: athrow         
        //   668: aconst_null    
        //   669: athrow         
        //   670: aconst_null    
        //   671: athrow         
        //   672: aconst_null    
        //   673: athrow         
        //   674: aconst_null    
        //   675: athrow         
        //   676: pop            
        //   677: goto            24
        //   680: pop            
        //   681: aconst_null    
        //   682: goto            676
        //   685: dup            
        //   686: ifnull          676
        //   689: checkcast       Ljava/lang/Throwable;
        //   692: athrow         
        //   693: dup            
        //   694: ifnull          680
        //   697: checkcast       Ljava/lang/Throwable;
        //   700: athrow         
        //   701: aconst_null    
        //   702: athrow         
        //    StackMapTable: 00 6B 43 07 00 2E 04 FF 00 0B 00 00 00 01 07 00 2E FC 00 03 07 00 03 43 07 00 2E 40 07 00 03 45 07 00 2E 40 07 00 34 FF 00 02 00 00 00 01 07 00 2E FF 00 00 00 01 07 00 03 00 01 07 00 34 47 07 00 2E 00 4B 07 00 03 FF 00 01 00 01 07 00 03 00 02 07 00 03 01 5C 07 00 03 FF 00 0A 00 00 00 01 07 00 2E FF 00 00 00 02 07 00 03 07 00 41 00 01 07 00 41 45 07 00 2E 40 07 00 47 42 07 00 1A 40 07 00 47 45 07 00 2E 40 07 00 4D 42 07 00 2E 40 07 00 4D 45 07 00 2E 40 07 00 89 47 07 00 10 FF 00 00 00 02 07 00 03 07 00 41 00 02 07 00 03 07 00 41 45 07 00 2E FF 00 00 00 02 07 00 03 07 00 41 00 02 07 00 03 07 00 47 FF 00 0A 00 02 07 00 03 07 00 41 00 02 07 00 03 07 00 47 FF 00 01 00 02 07 00 03 07 00 41 00 03 07 00 03 07 00 47 01 FF 00 1D 00 02 07 00 03 07 00 41 00 02 07 00 03 07 00 47 42 07 00 2E FF 00 00 00 02 07 00 03 07 00 41 00 02 07 00 03 07 00 47 45 07 00 2E FF 00 00 00 02 07 00 03 07 00 41 00 02 07 00 03 07 00 4D 42 07 00 2E FF 00 00 00 02 07 00 03 07 00 41 00 02 07 00 03 07 00 4D 45 07 00 2E FF 00 00 00 02 07 00 03 07 00 41 00 02 07 00 03 07 00 89 FE 00 0D 07 00 89 01 01 FF 00 1B 00 06 07 00 03 07 00 41 07 00 89 01 01 07 00 47 00 01 07 00 22 FF 00 00 00 06 07 00 03 07 00 41 07 00 89 01 01 07 00 47 00 07 07 00 34 08 00 F4 08 00 F4 07 00 03 07 00 03 07 00 47 07 00 03 45 07 00 2E FF 00 00 00 06 07 00 03 07 00 41 07 00 89 01 01 07 00 47 00 07 07 00 34 08 00 F4 08 00 F4 07 00 03 07 00 03 07 00 47 02 FF 00 03 00 00 00 01 07 00 2E FF 00 00 00 06 07 00 03 07 00 41 07 00 89 01 01 07 00 47 00 08 07 00 34 08 00 F4 08 00 F4 07 00 03 07 00 03 07 00 47 02 07 00 03 45 07 00 2E FF 00 00 00 06 07 00 03 07 00 41 07 00 89 01 01 07 00 47 00 08 07 00 34 08 00 F4 08 00 F4 07 00 03 07 00 03 07 00 47 02 02 FF 00 0A 00 06 07 00 03 07 00 41 07 00 89 01 01 07 00 47 00 08 07 00 34 08 00 F4 08 00 F4 07 00 03 07 00 03 07 00 47 02 02 FF 00 01 00 06 07 00 03 07 00 41 07 00 89 01 01 07 00 47 00 09 07 00 34 08 00 F4 08 00 F4 07 00 03 07 00 03 07 00 47 02 02 01 FF 00 1E 00 06 07 00 03 07 00 41 07 00 89 01 01 07 00 47 00 08 07 00 34 08 00 F4 08 00 F4 07 00 03 07 00 03 07 00 47 02 02 42 07 00 2E FF 00 00 00 06 07 00 03 07 00 41 07 00 89 01 01 07 00 47 00 08 07 00 34 08 00 F4 08 00 F4 07 00 03 07 00 03 07 00 47 02 02 45 07 00 2E FF 00 00 00 06 07 00 03 07 00 41 07 00 89 01 01 07 00 47 00 02 07 00 34 07 00 5B FF 00 0B 00 06 07 00 03 07 00 41 07 00 89 01 01 07 00 47 00 03 07 00 34 07 00 5B 07 00 5B FF 00 01 00 06 07 00 03 07 00 41 07 00 89 01 01 07 00 47 00 04 07 00 34 07 00 5B 07 00 5B 01 FF 00 1E 00 06 07 00 03 07 00 41 07 00 89 01 01 07 00 47 00 03 07 00 34 07 00 5B 07 00 5B FF 00 0C 00 07 07 00 03 07 00 41 07 00 89 01 01 07 00 47 07 00 5B 00 02 07 00 34 07 00 5B FF 00 01 00 07 07 00 03 07 00 41 07 00 89 01 01 07 00 47 07 00 5B 00 03 07 00 34 07 00 5B 01 FF 00 1C 00 07 07 00 03 07 00 41 07 00 89 01 01 07 00 47 07 00 5B 00 02 07 00 34 07 00 5B 42 07 00 2E FF 00 00 00 07 07 00 03 07 00 41 07 00 89 01 01 07 00 47 07 00 5B 00 02 07 00 34 07 00 5B 47 07 00 2E 40 01 4C 07 00 03 FF 00 01 00 07 07 00 03 07 00 41 07 00 89 01 01 07 00 47 07 00 5B 00 02 07 00 03 01 5B 07 00 03 FF 00 0F 00 07 07 00 03 07 00 41 07 00 89 01 01 07 00 47 07 00 5B 00 02 07 00 7E 07 00 5B FF 00 01 00 07 07 00 03 07 00 41 07 00 89 01 01 07 00 47 07 00 5B 00 03 07 00 7E 07 00 5B 01 FF 00 1D 00 07 07 00 03 07 00 41 07 00 89 01 01 07 00 47 07 00 5B 00 02 07 00 7E 07 00 5B 42 07 00 2E FF 00 00 00 07 07 00 03 07 00 41 07 00 89 01 01 07 00 47 07 00 5B 00 02 07 00 7E 07 00 5B 45 07 00 2E 40 01 4C 07 00 41 FF 00 01 00 07 07 00 03 07 00 41 07 00 89 01 01 07 00 47 07 00 5B 00 02 07 00 41 01 5D 07 00 41 42 07 00 1C 40 07 00 41 45 07 00 2E 40 07 00 47 FF 00 12 00 07 07 00 03 07 00 41 07 00 89 01 01 07 00 47 07 00 5B 00 02 07 00 5B 01 FF 00 01 00 07 07 00 03 07 00 41 07 00 89 01 01 07 00 47 07 00 5B 00 03 07 00 5B 01 01 FF 00 1B 00 07 07 00 03 07 00 41 07 00 89 01 01 07 00 47 07 00 5B 00 02 07 00 5B 01 42 07 00 2E FF 00 00 00 07 07 00 03 07 00 41 07 00 89 01 01 07 00 47 07 00 5B 00 02 07 00 5B 01 45 07 00 2E 00 FF 00 05 00 02 07 00 03 07 00 41 00 00 FF 00 00 00 07 07 00 03 07 00 41 07 00 89 01 01 07 00 47 07 00 5B 00 02 07 00 5B 01 FF 00 01 00 07 07 00 03 07 00 41 07 00 89 01 01 07 00 47 07 00 5B 00 02 07 00 7E 07 00 5B FF 00 01 00 01 07 00 03 00 01 07 00 03 FF 00 01 00 02 07 00 03 07 00 41 00 02 07 00 03 07 00 47 FF 00 01 00 06 07 00 03 07 00 41 07 00 89 01 01 07 00 47 00 08 07 00 34 08 00 F4 08 00 F4 07 00 03 07 00 03 07 00 47 02 02 FF 00 01 00 07 07 00 03 07 00 41 07 00 89 01 01 07 00 47 07 00 5B 00 02 07 00 34 07 00 5B 41 07 00 03 FF 00 01 00 06 07 00 03 07 00 41 07 00 89 01 01 07 00 47 00 03 07 00 34 07 00 5B 07 00 5B FF 00 01 00 07 07 00 03 07 00 41 07 00 89 01 01 07 00 47 07 00 5B 00 01 07 00 41 FF 00 01 00 01 07 00 03 00 01 07 00 2E 43 05 44 07 00 2E 47 05 47 07 00 2E
        //    Exceptions:
        //  Try           Handler
        //  Start  End    Start  End    Type                                       
        //  -----  -----  -----  -----  -------------------------------------------
        //  8      20     685    693    Any
        //  685    693    685    693    Ljava/lang/IllegalStateException;
        //  701    703    3      8      Ljava/lang/StringIndexOutOfBoundsException;
        //  28     35     35     36     Any
        //  29     35     3      8      Any
        //  28     35     28     29     Any
        //  29     35     28     29     Any
        //  29     35     35     36     Ljava/util/NoSuchElementException;
        //  40     48     48     49     Any
        //  40     48     48     49     Any
        //  40     48     3      8      Any
        //  40     48     48     49     Any
        //  40     48     3      8      Any
        //  104    110    110    111    Any
        //  104    110    110    111    Ljava/lang/ClassCastException;
        //  104    110    110    111    Ljava/lang/UnsupportedOperationException;
        //  104    110    3      8      Ljava/lang/NumberFormatException;
        //  104    110    3      8      Ljava/lang/ClassCastException;
        //  114    121    121    122    Any
        //  114    121    121    122    Ljava/lang/IllegalArgumentException;
        //  114    121    114    115    Ljava/util/ConcurrentModificationException;
        //  115    121    3      8      Ljava/lang/IndexOutOfBoundsException;
        //  115    121    3      8      Any
        //  125    132    132    133    Any
        //  126    132    125    126    Ljava/lang/EnumConstantNotPresentException;
        //  126    132    3      8      Ljava/util/ConcurrentModificationException;
        //  126    132    125    126    Any
        //  125    132    125    126    Any
        //  141    148    148    149    Any
        //  142    148    148    149    Ljava/lang/AssertionError;
        //  141    148    3      8      Ljava/lang/IllegalArgumentException;
        //  142    148    148    149    Any
        //  141    148    141    142    Ljava/util/NoSuchElementException;
        //  195    202    202    203    Any
        //  196    202    3      8      Any
        //  195    202    195    196    Any
        //  196    202    195    196    Any
        //  196    202    202    203    Any
        //  206    213    213    214    Any
        //  206    213    206    207    Ljava/lang/StringIndexOutOfBoundsException;
        //  206    213    206    207    Any
        //  207    213    206    207    Ljava/lang/NumberFormatException;
        //  207    213    206    207    Ljava/lang/IllegalStateException;
        //  256    263    263    264    Any
        //  257    263    263    264    Any
        //  256    263    3      8      Any
        //  256    263    256    257    Ljava/lang/RuntimeException;
        //  256    263    3      8      Any
        //  269    275    275    276    Any
        //  269    275    275    276    Any
        //  269    275    3      8      Any
        //  269    275    275    276    Ljava/lang/NegativeArraySizeException;
        //  269    275    275    276    Ljava/lang/StringIndexOutOfBoundsException;
        //  323    330    330    331    Any
        //  323    330    3      8      Ljava/lang/NullPointerException;
        //  323    330    3      8      Ljava/lang/IndexOutOfBoundsException;
        //  324    330    330    331    Any
        //  323    330    323    324    Any
        //  423    432    432    433    Any
        //  424    432    3      8      Any
        //  424    432    423    424    Any
        //  423    432    423    424    Ljava/lang/IndexOutOfBoundsException;
        //  423    432    3      8      Any
        //  527    534    534    535    Any
        //  527    534    527    528    Ljava/lang/UnsupportedOperationException;
        //  527    534    527    528    Any
        //  527    534    534    535    Ljava/lang/EnumConstantNotPresentException;
        //  528    534    527    528    Ljava/lang/AssertionError;
        //  583    590    590    591    Any
        //  583    590    3      8      Any
        //  583    590    583    584    Ljava/lang/StringIndexOutOfBoundsException;
        //  583    590    583    584    Ljava/lang/IndexOutOfBoundsException;
        //  584    590    590    591    Ljava/lang/ClassCastException;
        //  643    650    650    651    Any
        //  643    650    3      8      Ljava/lang/UnsupportedOperationException;
        //  644    650    643    644    Ljava/lang/ClassCastException;
        //  644    650    643    644    Any
        //  643    650    643    644    Ljava/lang/NegativeArraySizeException;
        // 
        // The error that occurred was:
        // 
        // java.lang.IndexOutOfBoundsException: Index -1 out of bounds for length 0
        //     at java.base/jdk.internal.util.Preconditions.outOfBounds(Preconditions.java:64)
        //     at java.base/jdk.internal.util.Preconditions.outOfBoundsCheckIndex(Preconditions.java:70)
        //     at java.base/jdk.internal.util.Preconditions.checkIndex(Preconditions.java:248)
        //     at java.base/java.util.Objects.checkIndex(Objects.java:372)
        //     at java.base/java.util.ArrayList.remove(ArrayList.java:535)
        //     at com.strobel.assembler.ir.StackMappingVisitor.pop(StackMappingVisitor.java:267)
        //     at com.strobel.assembler.ir.StackMappingVisitor$InstructionAnalyzer.execute(StackMappingVisitor.java:776)
        //     at com.strobel.assembler.ir.StackMappingVisitor$InstructionAnalyzer.visit(StackMappingVisitor.java:398)
        //     at com.strobel.decompiler.ast.AstBuilder.performStackAnalysis(AstBuilder.java:2030)
        //     at com.strobel.decompiler.ast.AstBuilder.build(AstBuilder.java:108)
        //     at com.strobel.decompiler.languages.java.ast.AstMethodBodyBuilder.createMethodBody(AstMethodBodyBuilder.java:211)
        //     at com.strobel.decompiler.languages.java.ast.AstMethodBodyBuilder.createMethodBody(AstMethodBodyBuilder.java:99)
        //     at com.strobel.decompiler.languages.java.ast.AstBuilder.createMethodBody(AstBuilder.java:782)
        //     at com.strobel.decompiler.languages.java.ast.AstBuilder.createMethod(AstBuilder.java:675)
        //     at com.strobel.decompiler.languages.java.ast.AstBuilder.addTypeMembers(AstBuilder.java:552)
        //     at com.strobel.decompiler.languages.java.ast.AstBuilder.createTypeCore(AstBuilder.java:519)
        //     at com.strobel.decompiler.languages.java.ast.AstBuilder.createTypeNoCache(AstBuilder.java:161)
        //     at com.strobel.decompiler.languages.java.ast.AstBuilder.createType(AstBuilder.java:150)
        //     at com.strobel.decompiler.languages.java.ast.AstBuilder.addType(AstBuilder.java:125)
        //     at com.strobel.decompiler.languages.java.JavaLanguage.buildAst(JavaLanguage.java:71)
        //     at com.strobel.decompiler.languages.java.JavaLanguage.decompileType(JavaLanguage.java:59)
        //     at com.strobel.decompiler.DecompilerDriver.decompileType(DecompilerDriver.java:330)
        //     at com.strobel.decompiler.DecompilerDriver.decompileJar(DecompilerDriver.java:251)
        //     at com.strobel.decompiler.DecompilerDriver.main(DecompilerDriver.java:126)
        // 
        throw new IllegalStateException("An error occurred while decompiling this method.");
    }
    
    static {
        throw t;
    }
    
    public void c(final dev.nuker.pyro.f3P p0) {
        // 
        // This method could not be decompiled.
        // 
        // Original Bytecode:
        // 
        //     3: dup            
        //     4: ifnull          323
        //     7: athrow         
        //     8: aconst_null    
        //     9: getstatic       dev/nuker/pyro/fc.1:I
        //    12: ifgt            315
        //    15: pop            
        //    16: aconst_null    
        //    17: goto            307
        //    20: nop            
        //    21: nop            
        //    22: nop            
        //    23: athrow         
        //    24: aload_0        
        //    25: getfield        dev/nuker/pyro/f3Q.c:Ldev/nuker/pyro/f0n;
        //    28: aload_1        
        //    29: getstatic       dev/nuker/pyro/fc.c:I
        //    32: ifge            40
        //    35: ldc             928697598
        //    37: goto            42
        //    40: ldc             1750048352
        //    42: ldc             -1449588643
        //    44: ixor           
        //    45: lookupswitch {
        //          -1631337309: 292
        //          763048207: 40
        //          default: 72
        //        }
        //    72: goto            76
        //    75: athrow         
        //    76: invokevirtual   dev/nuker/pyro/f3P.0:()Ljava/lang/Object;
        //    79: goto            83
        //    82: athrow         
        //    83: goto            87
        //    86: athrow         
        //    87: invokevirtual   dev/nuker/pyro/f0n.c:(Ljava/lang/Object;)V
        //    90: goto            94
        //    93: athrow         
        //    94: getstatic       dev/nuker/pyro/fc.c:I
        //    97: ifge            105
        //   100: ldc             -1239742044
        //   102: goto            107
        //   105: ldc             -1684502229
        //   107: ldc             -77814365
        //   109: ixor           
        //   110: lookupswitch {
        //          1167350649: 105
        //          1296542727: 294
        //          default: 136
        //        }
        //   136: aload_0        
        //   137: getfield        dev/nuker/pyro/f3Q.c:Ljava/util/ArrayList;
        //   140: goto            144
        //   143: athrow         
        //   144: invokevirtual   java/util/ArrayList.iterator:()Ljava/util/Iterator;
        //   147: goto            151
        //   150: athrow         
        //   151: getstatic       dev/nuker/pyro/fc.0:I
        //   154: ifeq            162
        //   157: ldc             190992294
        //   159: goto            164
        //   162: ldc             -1434008883
        //   164: ldc             1322160021
        //   166: ixor           
        //   167: lookupswitch {
        //          -465023656: 192
        //          1168949299: 162
        //          default: 296
        //        }
        //   192: astore_2       
        //   193: aload_2        
        //   194: goto            198
        //   197: athrow         
        //   198: invokeinterface java/util/Iterator.hasNext:()Z
        //   203: goto            207
        //   206: athrow         
        //   207: ifeq            215
        //   210: ldc             -999301833
        //   212: goto            217
        //   215: ldc             -999301836
        //   217: ldc             -1912064150
        //   219: ixor           
        //   220: tableswitch {
        //          -1798318918: 244
        //          -1798318917: 278
        //          default: 210
        //        }
        //   244: aload_2        
        //   245: goto            249
        //   248: athrow         
        //   249: invokeinterface java/util/Iterator.next:()Ljava/lang/Object;
        //   254: goto            258
        //   257: athrow         
        //   258: checkcast       Ldev/nuker/pyro/f3P;
        //   261: astore_3       
        //   262: aload_3        
        //   263: iconst_0       
        //   264: goto            268
        //   267: athrow         
        //   268: invokevirtual   dev/nuker/pyro/f3P.1:(Z)V
        //   271: goto            275
        //   274: athrow         
        //   275: goto            193
        //   278: aload_1        
        //   279: iconst_1       
        //   280: goto            284
        //   283: athrow         
        //   284: invokevirtual   dev/nuker/pyro/f3P.1:(Z)V
        //   287: goto            291
        //   290: athrow         
        //   291: return         
        //   292: aconst_null    
        //   293: athrow         
        //   294: aconst_null    
        //   295: athrow         
        //   296: aconst_null    
        //   297: athrow         
        //   298: pop            
        //   299: goto            24
        //   302: pop            
        //   303: aconst_null    
        //   304: goto            298
        //   307: dup            
        //   308: ifnull          298
        //   311: checkcast       Ljava/lang/Throwable;
        //   314: athrow         
        //   315: dup            
        //   316: ifnull          302
        //   319: checkcast       Ljava/lang/Throwable;
        //   322: athrow         
        //   323: aconst_null    
        //   324: athrow         
        //    StackMapTable: 00 37 43 07 00 2E 04 FF 00 0B 00 00 00 01 07 00 2E FD 00 03 07 00 03 07 00 5B FF 00 0F 00 02 07 00 03 07 00 5B 00 02 07 00 97 07 00 5B FF 00 01 00 02 07 00 03 07 00 5B 00 03 07 00 97 07 00 5B 01 FF 00 1D 00 02 07 00 03 07 00 5B 00 02 07 00 97 07 00 5B 42 07 00 22 FF 00 00 00 02 07 00 03 07 00 5B 00 02 07 00 97 07 00 5B 45 07 00 2E FF 00 00 00 02 07 00 03 07 00 5B 00 02 07 00 97 07 00 47 42 07 00 2E FF 00 00 00 02 07 00 03 07 00 5B 00 02 07 00 97 07 00 47 45 07 00 2E 00 0A 41 01 1C 46 07 00 2E 40 07 00 7E 45 07 00 2E 40 07 00 A6 4A 07 00 A6 FF 00 01 00 02 07 00 03 07 00 5B 00 02 07 00 A6 01 5B 07 00 A6 FC 00 00 07 00 A6 FF 00 03 00 00 00 01 07 00 2E FF 00 00 00 03 07 00 03 07 00 5B 07 00 A6 00 01 07 00 A6 47 07 00 2E 40 01 02 04 41 01 1A 43 07 00 2E 40 07 00 A6 47 07 00 2E 40 07 00 47 FF 00 08 00 04 07 00 03 07 00 5B 07 00 A6 07 00 5B 00 01 07 00 2E FF 00 00 00 04 07 00 03 07 00 5B 07 00 A6 07 00 5B 00 02 07 00 5B 01 45 07 00 2E 00 FA 00 02 44 07 00 1E FF 00 00 00 03 07 00 03 07 00 5B 07 00 A6 00 02 07 00 5B 01 45 07 00 2E 00 FF 00 00 00 02 07 00 03 07 00 5B 00 02 07 00 97 07 00 5B 01 41 07 00 A6 41 07 00 2E 43 05 44 07 00 2E 47 05 47 07 00 2E
        //    Exceptions:
        //  Try           Handler
        //  Start  End    Start  End    Type                                       
        //  -----  -----  -----  -----  -------------------------------------------
        //  8      20     307    315    Any
        //  307    315    307    315    Ljava/lang/ArrayIndexOutOfBoundsException;
        //  323    325    3      8      Any
        //  75     82     82     83     Any
        //  75     82     75     76     Ljava/lang/StringIndexOutOfBoundsException;
        //  76     82     75     76     Ljava/lang/EnumConstantNotPresentException;
        //  75     82     82     83     Any
        //  76     82     82     83     Ljava/lang/AssertionError;
        //  86     93     93     94     Any
        //  87     93     86     87     Any
        //  87     93     86     87     Ljava/lang/EnumConstantNotPresentException;
        //  86     93     3      8      Ljava/lang/ArithmeticException;
        //  87     93     3      8      Ljava/lang/NullPointerException;
        //  143    150    150    151    Any
        //  144    150    143    144    Any
        //  143    150    143    144    Any
        //  143    150    143    144    Ljava/lang/NullPointerException;
        //  143    150    143    144    Any
        //  198    206    206    207    Any
        //  198    206    3      8      Any
        //  198    206    3      8      Any
        //  198    206    3      8      Any
        //  198    206    3      8      Any
        //  248    257    257    258    Any
        //  249    257    248    249    Any
        //  248    257    3      8      Any
        //  249    257    257    258    Ljava/lang/NegativeArraySizeException;
        //  248    257    3      8      Any
        //  267    274    274    275    Any
        //  268    274    274    275    Any
        //  267    274    267    268    Ljava/lang/RuntimeException;
        //  267    274    3      8      Ljava/util/NoSuchElementException;
        //  267    274    267    268    Any
        //  283    290    290    291    Any
        //  284    290    283    284    Ljava/lang/EnumConstantNotPresentException;
        //  283    290    290    291    Ljava/lang/StringIndexOutOfBoundsException;
        //  284    290    290    291    Ljava/util/NoSuchElementException;
        //  283    290    3      8      Ljava/util/ConcurrentModificationException;
        // 
        // The error that occurred was:
        // 
        // java.lang.IndexOutOfBoundsException: Index -1 out of bounds for length 0
        //     at java.base/jdk.internal.util.Preconditions.outOfBounds(Preconditions.java:64)
        //     at java.base/jdk.internal.util.Preconditions.outOfBoundsCheckIndex(Preconditions.java:70)
        //     at java.base/jdk.internal.util.Preconditions.checkIndex(Preconditions.java:248)
        //     at java.base/java.util.Objects.checkIndex(Objects.java:372)
        //     at java.base/java.util.ArrayList.remove(ArrayList.java:535)
        //     at com.strobel.assembler.ir.StackMappingVisitor.pop(StackMappingVisitor.java:267)
        //     at com.strobel.assembler.ir.StackMappingVisitor$InstructionAnalyzer.execute(StackMappingVisitor.java:577)
        //     at com.strobel.assembler.ir.StackMappingVisitor$InstructionAnalyzer.visit(StackMappingVisitor.java:398)
        //     at com.strobel.decompiler.ast.AstBuilder.performStackAnalysis(AstBuilder.java:2030)
        //     at com.strobel.decompiler.ast.AstBuilder.build(AstBuilder.java:108)
        //     at com.strobel.decompiler.languages.java.ast.AstMethodBodyBuilder.createMethodBody(AstMethodBodyBuilder.java:211)
        //     at com.strobel.decompiler.languages.java.ast.AstMethodBodyBuilder.createMethodBody(AstMethodBodyBuilder.java:99)
        //     at com.strobel.decompiler.languages.java.ast.AstBuilder.createMethodBody(AstBuilder.java:782)
        //     at com.strobel.decompiler.languages.java.ast.AstBuilder.createMethod(AstBuilder.java:675)
        //     at com.strobel.decompiler.languages.java.ast.AstBuilder.addTypeMembers(AstBuilder.java:552)
        //     at com.strobel.decompiler.languages.java.ast.AstBuilder.createTypeCore(AstBuilder.java:519)
        //     at com.strobel.decompiler.languages.java.ast.AstBuilder.createTypeNoCache(AstBuilder.java:161)
        //     at com.strobel.decompiler.languages.java.ast.AstBuilder.createType(AstBuilder.java:150)
        //     at com.strobel.decompiler.languages.java.ast.AstBuilder.addType(AstBuilder.java:125)
        //     at com.strobel.decompiler.languages.java.JavaLanguage.buildAst(JavaLanguage.java:71)
        //     at com.strobel.decompiler.languages.java.JavaLanguage.decompileType(JavaLanguage.java:59)
        //     at com.strobel.decompiler.DecompilerDriver.decompileType(DecompilerDriver.java:330)
        //     at com.strobel.decompiler.DecompilerDriver.decompileJar(DecompilerDriver.java:251)
        //     at com.strobel.decompiler.DecompilerDriver.main(DecompilerDriver.java:126)
        // 
        throw new IllegalStateException("An error occurred while decompiling this method.");
    }
    
    public f3Q(final f0n f0n, final float n, final float n2) {
        super(f0n, n, n2);
        this.c = new ArrayList<f3P>();
        this.c();
    }
    
    @Override
    public void c(final int p0, final int p1, final int p2) {
        // 
        // This method could not be decompiled.
        // 
        // Original Bytecode:
        // 
        //     3: dup            
        //     4: ifnull          729
        //     7: athrow         
        //     8: aconst_null    
        //     9: getstatic       dev/nuker/pyro/fc.1:I
        //    12: ifgt            721
        //    15: pop            
        //    16: aconst_null    
        //    17: goto            713
        //    20: nop            
        //    21: nop            
        //    22: nop            
        //    23: athrow         
        //    24: getstatic       dev/nuker/pyro/fc.c:I
        //    27: ifge            35
        //    30: ldc             1248058968
        //    32: goto            37
        //    35: ldc             -567289457
        //    37: ldc             1823382657
        //    39: ixor           
        //    40: lookupswitch {
        //          -1300151026: 68
        //          650986201: 35
        //          default: 690
        //        }
        //    68: aload_0        
        //    69: iload_1        
        //    70: iload_2        
        //    71: getstatic       dev/nuker/pyro/fc.c:I
        //    74: ifge            82
        //    77: ldc             688975810
        //    79: goto            84
        //    82: ldc             -25482406
        //    84: ldc             -687283413
        //    86: ixor           
        //    87: lookupswitch {
        //          -31978263: 82
        //          695453809: 112
        //          default: 698
        //        }
        //   112: iload_3        
        //   113: goto            117
        //   116: athrow         
        //   117: invokespecial   dev/nuker/pyro/f3T.c:(III)V
        //   120: goto            124
        //   123: athrow         
        //   124: iload_3        
        //   125: ifne            500
        //   128: aload_0        
        //   129: getstatic       dev/nuker/pyro/fc.1:I
        //   132: ifeq            140
        //   135: ldc             1995588490
        //   137: goto            142
        //   140: ldc             -1857113887
        //   142: ldc             1306328891
        //   144: ixor           
        //   145: lookupswitch {
        //          992918705: 684
        //          1672965738: 140
        //          default: 172
        //        }
        //   172: getfield        dev/nuker/pyro/f3Q.c:Ldev/nuker/pyro/f0n;
        //   175: checkcast       Ldev/nuker/pyro/f0f;
        //   178: astore          4
        //   180: iconst_m1      
        //   181: istore          5
        //   183: iconst_0       
        //   184: istore          6
        //   186: iload           6
        //   188: aload_0        
        //   189: getstatic       dev/nuker/pyro/fc.1:I
        //   192: ifeq            200
        //   195: ldc             -601206620
        //   197: goto            202
        //   200: ldc             1984017989
        //   202: ldc             -281212391
        //   204: ixor           
        //   205: lookupswitch {
        //          -1719878564: 232
        //          857168573: 200
        //          default: 686
        //        }
        //   232: getfield        dev/nuker/pyro/f3Q.c:[Ljava/lang/Object;
        //   235: arraylength    
        //   236: iconst_1       
        //   237: isub           
        //   238: if_icmpge       363
        //   241: getstatic       dev/nuker/pyro/fc.c:I
        //   244: ifge            252
        //   247: ldc             1922060368
        //   249: goto            254
        //   252: ldc             1984738817
        //   254: ldc             -57309317
        //   256: ixor           
        //   257: lookupswitch {
        //          -1912219861: 692
        //          177422634: 252
        //          default: 284
        //        }
        //   284: aload_0        
        //   285: getstatic       dev/nuker/pyro/fc.1:I
        //   288: ifeq            296
        //   291: ldc             -389651346
        //   293: goto            298
        //   296: ldc             1974937666
        //   298: ldc             1974797219
        //   300: ixor           
        //   301: lookupswitch {
        //          -1653381171: 694
        //          -1201975786: 296
        //          default: 328
        //        }
        //   328: getfield        dev/nuker/pyro/f3Q.c:[Ljava/lang/Object;
        //   331: iload           6
        //   333: aaload         
        //   334: aload           4
        //   336: goto            340
        //   339: athrow         
        //   340: invokevirtual   dev/nuker/pyro/f0f.3:()Ljava/lang/Object;
        //   343: goto            347
        //   346: athrow         
        //   347: if_acmpne       357
        //   350: iload           6
        //   352: istore          5
        //   354: goto            363
        //   357: iinc            6, 1
        //   360: goto            186
        //   363: iload           5
        //   365: getstatic       dev/nuker/pyro/fc.c:I
        //   368: ifge            376
        //   371: ldc             41743353
        //   373: goto            378
        //   376: ldc             -482038680
        //   378: ldc             -31203386
        //   380: ixor           
        //   381: lookupswitch {
        //          -60871617: 376
        //          493319086: 408
        //          default: 700
        //        }
        //   408: aload_0        
        //   409: getfield        dev/nuker/pyro/f3Q.c:[Ljava/lang/Object;
        //   412: arraylength    
        //   413: iconst_1       
        //   414: isub           
        //   415: if_icmplt       462
        //   418: iconst_m1      
        //   419: getstatic       dev/nuker/pyro/fc.1:I
        //   422: ifeq            430
        //   425: ldc             -891309657
        //   427: goto            432
        //   430: ldc             525467456
        //   432: ldc             1267177126
        //   434: ixor           
        //   435: lookupswitch {
        //          -2124929279: 702
        //          1324958329: 430
        //          default: 460
        //        }
        //   460: istore          5
        //   462: aload           4
        //   464: aload_0        
        //   465: getfield        dev/nuker/pyro/f3Q.c:[Ljava/lang/Object;
        //   468: iinc            5, 1
        //   471: iload           5
        //   473: aaload         
        //   474: goto            478
        //   477: athrow         
        //   478: invokevirtual   dev/nuker/pyro/f0f.c:(Ljava/lang/Object;)V
        //   481: goto            485
        //   484: athrow         
        //   485: aload_0        
        //   486: goto            490
        //   489: athrow         
        //   490: invokevirtual   dev/nuker/pyro/f3Q.c:()V
        //   493: goto            497
        //   496: athrow         
        //   497: goto            683
        //   500: iload_3        
        //   501: iconst_1       
        //   502: if_icmpne       683
        //   505: getstatic       dev/nuker/pyro/fc.c:I
        //   508: ifge            516
        //   511: ldc             -655941564
        //   513: goto            518
        //   516: ldc             290218189
        //   518: ldc             -50400759
        //   520: ixor           
        //   521: lookupswitch {
        //          -307064124: 548
        //          605672013: 516
        //          default: 688
        //        }
        //   548: aload_0        
        //   549: goto            553
        //   552: athrow         
        //   553: invokevirtual   dev/nuker/pyro/f3Q.4:()Ljava/util/List;
        //   556: goto            560
        //   559: athrow         
        //   560: goto            564
        //   563: athrow         
        //   564: invokeinterface java/util/List.isEmpty:()Z
        //   569: goto            573
        //   572: athrow         
        //   573: ifne            581
        //   576: ldc             1902960957
        //   578: goto            583
        //   581: ldc             1902960956
        //   583: ldc             1693956393
        //   585: ixor           
        //   586: tableswitch {
        //          725004328: 608
        //          725004329: 683
        //          default: 576
        //        }
        //   608: aload_0        
        //   609: aload_0        
        //   610: goto            614
        //   613: athrow         
        //   614: invokevirtual   dev/nuker/pyro/f3Q.0:()Z
        //   617: goto            621
        //   620: athrow         
        //   621: ifne            628
        //   624: iconst_1       
        //   625: goto            629
        //   628: iconst_0       
        //   629: getstatic       dev/nuker/pyro/fc.c:I
        //   632: ifge            640
        //   635: ldc             1739142835
        //   637: goto            642
        //   640: ldc             695910449
        //   642: ldc             -1863379844
        //   644: ixor           
        //   645: lookupswitch {
        //          -1181363123: 672
        //          -146398513: 640
        //          default: 696
        //        }
        //   672: goto            676
        //   675: athrow         
        //   676: invokevirtual   dev/nuker/pyro/f3Q.c:(Z)V
        //   679: goto            683
        //   682: athrow         
        //   683: return         
        //   684: aconst_null    
        //   685: athrow         
        //   686: aconst_null    
        //   687: athrow         
        //   688: aconst_null    
        //   689: athrow         
        //   690: aconst_null    
        //   691: athrow         
        //   692: aconst_null    
        //   693: athrow         
        //   694: aconst_null    
        //   695: athrow         
        //   696: aconst_null    
        //   697: athrow         
        //   698: aconst_null    
        //   699: athrow         
        //   700: aconst_null    
        //   701: athrow         
        //   702: aconst_null    
        //   703: athrow         
        //   704: pop            
        //   705: goto            24
        //   708: pop            
        //   709: aconst_null    
        //   710: goto            704
        //   713: dup            
        //   714: ifnull          704
        //   717: checkcast       Ljava/lang/Throwable;
        //   720: athrow         
        //   721: dup            
        //   722: ifnull          708
        //   725: checkcast       Ljava/lang/Throwable;
        //   728: athrow         
        //   729: aconst_null    
        //   730: athrow         
        //    StackMapTable: 00 5C 43 07 00 2E 04 FF 00 0B 00 00 00 01 07 00 2E FF 00 03 00 04 07 00 03 01 01 01 00 00 0A 41 01 1E FF 00 0D 00 04 07 00 03 01 01 01 00 03 07 00 03 01 01 FF 00 01 00 04 07 00 03 01 01 01 00 04 07 00 03 01 01 01 FF 00 1B 00 04 07 00 03 01 01 01 00 03 07 00 03 01 01 43 07 00 26 FF 00 00 00 04 07 00 03 01 01 01 00 04 07 00 03 01 01 01 45 07 00 2E 00 4F 07 00 03 FF 00 01 00 04 07 00 03 01 01 01 00 02 07 00 03 01 5D 07 00 03 FE 00 0D 07 00 41 01 01 FF 00 0D 00 07 07 00 03 01 01 01 07 00 41 01 01 00 02 01 07 00 03 FF 00 01 00 07 07 00 03 01 01 01 07 00 41 01 01 00 03 01 07 00 03 01 FF 00 1D 00 07 07 00 03 01 01 01 07 00 41 01 01 00 02 01 07 00 03 13 41 01 1D 4B 07 00 03 FF 00 01 00 07 07 00 03 01 01 01 07 00 41 01 01 00 02 07 00 03 01 5D 07 00 03 4A 07 00 0C FF 00 00 00 07 07 00 03 01 01 01 07 00 41 01 01 00 02 07 00 47 07 00 41 45 07 00 2E FF 00 00 00 07 07 00 03 01 01 01 07 00 41 01 01 00 02 07 00 47 07 00 47 09 05 4C 01 FF 00 01 00 07 07 00 03 01 01 01 07 00 41 01 01 00 02 01 01 5D 01 55 01 FF 00 01 00 07 07 00 03 01 01 01 07 00 41 01 01 00 02 01 01 5B 01 01 4E 07 00 2E FF 00 00 00 07 07 00 03 01 01 01 07 00 41 01 01 00 02 07 00 41 07 00 47 45 07 00 2E 00 FF 00 03 00 00 00 01 07 00 2E FF 00 00 00 07 07 00 03 01 01 01 07 00 41 01 01 00 01 07 00 03 45 07 00 2E 00 F8 00 02 0F 41 01 1D 43 07 00 2E 40 07 00 03 45 07 00 2E 40 07 00 34 42 07 00 2E 40 07 00 34 47 07 00 2E 40 01 02 04 41 01 18 44 07 00 2E FF 00 00 00 04 07 00 03 01 01 01 00 02 07 00 03 07 00 03 45 07 00 2E FF 00 00 00 04 07 00 03 01 01 01 00 02 07 00 03 01 46 07 00 03 FF 00 00 00 04 07 00 03 01 01 01 00 02 07 00 03 01 FF 00 0A 00 04 07 00 03 01 01 01 00 02 07 00 03 01 FF 00 01 00 04 07 00 03 01 01 01 00 03 07 00 03 01 01 FF 00 1D 00 04 07 00 03 01 01 01 00 02 07 00 03 01 FF 00 02 00 00 00 01 07 00 2E FF 00 00 00 04 07 00 03 01 01 01 00 02 07 00 03 01 45 07 00 2E 00 40 07 00 03 FF 00 01 00 07 07 00 03 01 01 01 07 00 41 01 01 00 02 01 07 00 03 F8 00 01 01 FE 00 01 07 00 41 01 01 41 07 00 03 FF 00 01 00 04 07 00 03 01 01 01 00 02 07 00 03 01 FF 00 01 00 04 07 00 03 01 01 01 00 03 07 00 03 01 01 FF 00 01 00 07 07 00 03 01 01 01 07 00 41 01 01 00 01 01 41 01 FF 00 01 00 04 07 00 03 01 01 01 00 01 07 00 8E 43 05 44 07 00 8E 47 05 47 07 00 2E
        //    Exceptions:
        //  Try           Handler
        //  Start  End    Start  End    Type                                       
        //  -----  -----  -----  -----  -------------------------------------------
        //  8      20     713    721    Ljava/lang/ArrayIndexOutOfBoundsException;
        //  713    721    713    721    Ljava/lang/ArrayIndexOutOfBoundsException;
        //  729    731    3      8      Any
        //  116    123    123    124    Any
        //  116    123    3      8      Any
        //  117    123    3      8      Ljava/lang/EnumConstantNotPresentException;
        //  117    123    123    124    Any
        //  116    123    116    117    Ljava/lang/NullPointerException;
        //  339    346    346    347    Any
        //  339    346    346    347    Any
        //  340    346    3      8      Any
        //  339    346    339    340    Ljava/lang/IllegalStateException;
        //  340    346    346    347    Ljava/lang/StringIndexOutOfBoundsException;
        //  477    484    484    485    Any
        //  478    484    3      8      Any
        //  478    484    477    478    Any
        //  477    484    484    485    Any
        //  477    484    484    485    Any
        //  490    496    496    497    Any
        //  490    496    496    497    Any
        //  490    496    496    497    Any
        //  490    496    3      8      Any
        //  490    496    496    497    Any
        //  552    559    559    560    Any
        //  553    559    552    553    Any
        //  552    559    552    553    Any
        //  553    559    552    553    Any
        //  552    559    3      8      Any
        //  563    572    572    573    Any
        //  563    572    563    564    Any
        //  564    572    572    573    Ljava/util/NoSuchElementException;
        //  564    572    563    564    Ljava/lang/UnsupportedOperationException;
        //  564    572    572    573    Ljava/lang/IllegalStateException;
        //  613    620    620    621    Any
        //  614    620    3      8      Any
        //  613    620    620    621    Ljava/lang/ArrayIndexOutOfBoundsException;
        //  614    620    3      8      Any
        //  614    620    613    614    Any
        //  676    682    682    683    Any
        //  676    682    3      8      Ljava/lang/IllegalStateException;
        //  676    682    682    683    Any
        //  676    682    3      8      Ljava/lang/NumberFormatException;
        //  676    682    682    683    Ljava/lang/StringIndexOutOfBoundsException;
        // 
        // The error that occurred was:
        // 
        // java.lang.IndexOutOfBoundsException: Index -1 out of bounds for length 0
        //     at java.base/jdk.internal.util.Preconditions.outOfBounds(Preconditions.java:64)
        //     at java.base/jdk.internal.util.Preconditions.outOfBoundsCheckIndex(Preconditions.java:70)
        //     at java.base/jdk.internal.util.Preconditions.checkIndex(Preconditions.java:248)
        //     at java.base/java.util.Objects.checkIndex(Objects.java:372)
        //     at java.base/java.util.ArrayList.remove(ArrayList.java:535)
        //     at com.strobel.assembler.ir.StackMappingVisitor.pop(StackMappingVisitor.java:267)
        //     at com.strobel.assembler.ir.StackMappingVisitor$InstructionAnalyzer.execute(StackMappingVisitor.java:577)
        //     at com.strobel.assembler.ir.StackMappingVisitor$InstructionAnalyzer.visit(StackMappingVisitor.java:398)
        //     at com.strobel.decompiler.ast.AstBuilder.performStackAnalysis(AstBuilder.java:2030)
        //     at com.strobel.decompiler.ast.AstBuilder.build(AstBuilder.java:108)
        //     at com.strobel.decompiler.languages.java.ast.AstMethodBodyBuilder.createMethodBody(AstMethodBodyBuilder.java:211)
        //     at com.strobel.decompiler.languages.java.ast.AstMethodBodyBuilder.createMethodBody(AstMethodBodyBuilder.java:99)
        //     at com.strobel.decompiler.languages.java.ast.AstBuilder.createMethodBody(AstBuilder.java:782)
        //     at com.strobel.decompiler.languages.java.ast.AstBuilder.createMethod(AstBuilder.java:675)
        //     at com.strobel.decompiler.languages.java.ast.AstBuilder.addTypeMembers(AstBuilder.java:552)
        //     at com.strobel.decompiler.languages.java.ast.AstBuilder.createTypeCore(AstBuilder.java:519)
        //     at com.strobel.decompiler.languages.java.ast.AstBuilder.createTypeNoCache(AstBuilder.java:161)
        //     at com.strobel.decompiler.languages.java.ast.AstBuilder.createType(AstBuilder.java:150)
        //     at com.strobel.decompiler.languages.java.ast.AstBuilder.addType(AstBuilder.java:125)
        //     at com.strobel.decompiler.languages.java.JavaLanguage.buildAst(JavaLanguage.java:71)
        //     at com.strobel.decompiler.languages.java.JavaLanguage.decompileType(JavaLanguage.java:59)
        //     at com.strobel.decompiler.DecompilerDriver.decompileType(DecompilerDriver.java:330)
        //     at com.strobel.decompiler.DecompilerDriver.decompileJar(DecompilerDriver.java:251)
        //     at com.strobel.decompiler.DecompilerDriver.main(DecompilerDriver.java:126)
        // 
        throw new IllegalStateException("An error occurred while decompiling this method.");
    }
    
    @Override
    public boolean c(final float n, final float n2, final float n3) {
        return fbS.e(this, 1287254080, n, n2, n3);
    }
    
    @Override
    public String 7() {
        // 
        // This method could not be decompiled.
        // 
        // Original Bytecode:
        // 
        //     3: dup            
        //     4: ifnull          186
        //     7: athrow         
        //     8: aconst_null    
        //     9: getstatic       dev/nuker/pyro/fc.1:I
        //    12: ifgt            178
        //    15: pop            
        //    16: aconst_null    
        //    17: goto            170
        //    20: nop            
        //    21: nop            
        //    22: nop            
        //    23: athrow         
        //    24: aload_0        
        //    25: getfield        dev/nuker/pyro/f3Q.c:Ldev/nuker/pyro/f0n;
        //    28: checkcast       Ldev/nuker/pyro/f0f;
        //    31: astore_1       
        //    32: new             Ljava/lang/StringBuilder;
        //    35: dup            
        //    36: goto            40
        //    39: athrow         
        //    40: invokespecial   java/lang/StringBuilder.<init>:()V
        //    43: goto            47
        //    46: athrow         
        //    47: aload_1        
        //    48: goto            52
        //    51: athrow         
        //    52: invokevirtual   dev/nuker/pyro/f0f.c:()Ljava/lang/String;
        //    55: goto            59
        //    58: athrow         
        //    59: goto            63
        //    62: athrow         
        //    63: invokevirtual   java/lang/StringBuilder.append:(Ljava/lang/String;)Ljava/lang/StringBuilder;
        //    66: goto            70
        //    69: athrow         
        //    70: ldc             " "
        //    72: goto            76
        //    75: athrow         
        //    76: invokevirtual   java/lang/StringBuilder.append:(Ljava/lang/String;)Ljava/lang/StringBuilder;
        //    79: goto            83
        //    82: athrow         
        //    83: aload_1        
        //    84: goto            88
        //    87: athrow         
        //    88: invokevirtual   dev/nuker/pyro/f0f.3:()Ljava/lang/Object;
        //    91: goto            95
        //    94: athrow         
        //    95: getstatic       dev/nuker/pyro/fc.0:I
        //    98: ifeq            106
        //   101: ldc             283469884
        //   103: goto            108
        //   106: ldc             -460151663
        //   108: ldc             -740423739
        //   110: ixor           
        //   111: lookupswitch {
        //          -1019514887: 159
        //          -669849649: 106
        //          default: 136
        //        }
        //   136: goto            140
        //   139: athrow         
        //   140: invokevirtual   java/lang/StringBuilder.append:(Ljava/lang/Object;)Ljava/lang/StringBuilder;
        //   143: goto            147
        //   146: athrow         
        //   147: goto            151
        //   150: athrow         
        //   151: invokevirtual   java/lang/StringBuilder.toString:()Ljava/lang/String;
        //   154: goto            158
        //   157: athrow         
        //   158: areturn        
        //   159: aconst_null    
        //   160: athrow         
        //   161: pop            
        //   162: goto            24
        //   165: pop            
        //   166: aconst_null    
        //   167: goto            161
        //   170: dup            
        //   171: ifnull          161
        //   174: checkcast       Ljava/lang/Throwable;
        //   177: athrow         
        //   178: dup            
        //   179: ifnull          165
        //   182: checkcast       Ljava/lang/Throwable;
        //   185: athrow         
        //   186: aconst_null    
        //   187: athrow         
        //    StackMapTable: 00 29 FF 00 03 00 02 07 00 03 07 00 41 00 01 07 00 2E FA 00 04 FF 00 0B 00 00 00 01 07 00 2E FC 00 03 07 00 03 FF 00 0E 00 02 07 00 03 07 00 41 00 01 07 00 2E FF 00 00 00 02 07 00 03 07 00 41 00 02 08 00 20 08 00 20 45 07 00 2E 40 07 00 EF 43 07 00 2E FF 00 00 00 02 07 00 03 07 00 41 00 02 07 00 EF 07 00 41 45 07 00 2E FF 00 00 00 02 07 00 03 07 00 41 00 02 07 00 EF 07 01 03 42 07 00 2E FF 00 00 00 02 07 00 03 07 00 41 00 02 07 00 EF 07 01 03 45 07 00 2E 40 07 00 EF FF 00 04 00 00 00 01 07 00 2E FF 00 00 00 02 07 00 03 07 00 41 00 02 07 00 EF 07 01 03 45 07 00 2E 40 07 00 EF FF 00 03 00 00 00 01 07 00 2E FF 00 00 00 02 07 00 03 07 00 41 00 02 07 00 EF 07 00 41 45 07 00 2E FF 00 00 00 02 07 00 03 07 00 41 00 02 07 00 EF 07 00 47 FF 00 0A 00 02 07 00 03 07 00 41 00 02 07 00 EF 07 00 47 FF 00 01 00 02 07 00 03 07 00 41 00 03 07 00 EF 07 00 47 01 FF 00 1B 00 02 07 00 03 07 00 41 00 02 07 00 EF 07 00 47 42 07 00 2E FF 00 00 00 02 07 00 03 07 00 41 00 02 07 00 EF 07 00 47 45 07 00 2E 40 07 00 EF 42 07 00 90 40 07 00 EF 45 07 00 2E 40 07 01 03 FF 00 00 00 02 07 00 03 07 00 41 00 02 07 00 EF 07 00 47 FF 00 01 00 01 07 00 03 00 01 07 00 2E 43 05 44 07 00 2E 47 05 FF 00 07 00 02 07 00 03 07 00 41 00 01 07 00 2E
        //    Exceptions:
        //  Try           Handler
        //  Start  End    Start  End    Type                              
        //  -----  -----  -----  -----  ----------------------------------
        //  8      20     170    178    Any
        //  170    178    170    178    Any
        //  186    188    3      8      Ljava/lang/NullPointerException;
        //  39     46     46     47     Any
        //  39     46     39     40     Ljava/lang/IllegalStateException;
        //  40     46     46     47     Any
        //  40     46     39     40     Any
        //  39     46     39     40     Any
        //  51     58     58     59     Any
        //  52     58     3      8      Any
        //  51     58     3      8      Any
        //  52     58     51     52     Any
        //  51     58     3      8      Any
        //  62     69     69     70     Any
        //  62     69     3      8      Ljava/lang/RuntimeException;
        //  63     69     69     70     Any
        //  62     69     62     63     Any
        //  63     69     62     63     Any
        //  76     82     82     83     Any
        //  76     82     82     83     Any
        //  76     82     82     83     Any
        //  76     82     82     83     Any
        //  76     82     3      8      Any
        //  88     94     94     95     Any
        //  88     94     3      8      Any
        //  88     94     94     95     Ljava/lang/ArithmeticException;
        //  88     94     3      8      Ljava/lang/RuntimeException;
        //  88     94     94     95     Ljava/lang/ClassCastException;
        //  139    146    146    147    Any
        //  140    146    3      8      Ljava/lang/NullPointerException;
        //  139    146    139    140    Any
        //  140    146    146    147    Any
        //  139    146    146    147    Any
        //  150    157    157    158    Any
        //  151    157    157    158    Any
        //  151    157    157    158    Any
        //  151    157    150    151    Ljava/lang/ArithmeticException;
        //  150    157    157    158    Ljava/util/NoSuchElementException;
        // 
        // The error that occurred was:
        // 
        // java.lang.IndexOutOfBoundsException: Index -1 out of bounds for length 0
        //     at java.base/jdk.internal.util.Preconditions.outOfBounds(Preconditions.java:64)
        //     at java.base/jdk.internal.util.Preconditions.outOfBoundsCheckIndex(Preconditions.java:70)
        //     at java.base/jdk.internal.util.Preconditions.checkIndex(Preconditions.java:248)
        //     at java.base/java.util.Objects.checkIndex(Objects.java:372)
        //     at java.base/java.util.ArrayList.remove(ArrayList.java:535)
        //     at com.strobel.assembler.ir.StackMappingVisitor.pop(StackMappingVisitor.java:267)
        //     at com.strobel.assembler.ir.StackMappingVisitor$InstructionAnalyzer.execute(StackMappingVisitor.java:738)
        //     at com.strobel.assembler.ir.StackMappingVisitor$InstructionAnalyzer.visit(StackMappingVisitor.java:398)
        //     at com.strobel.decompiler.ast.AstBuilder.performStackAnalysis(AstBuilder.java:2030)
        //     at com.strobel.decompiler.ast.AstBuilder.build(AstBuilder.java:108)
        //     at com.strobel.decompiler.languages.java.ast.AstMethodBodyBuilder.createMethodBody(AstMethodBodyBuilder.java:211)
        //     at com.strobel.decompiler.languages.java.ast.AstMethodBodyBuilder.createMethodBody(AstMethodBodyBuilder.java:99)
        //     at com.strobel.decompiler.languages.java.ast.AstBuilder.createMethodBody(AstBuilder.java:782)
        //     at com.strobel.decompiler.languages.java.ast.AstBuilder.createMethod(AstBuilder.java:675)
        //     at com.strobel.decompiler.languages.java.ast.AstBuilder.addTypeMembers(AstBuilder.java:552)
        //     at com.strobel.decompiler.languages.java.ast.AstBuilder.createTypeCore(AstBuilder.java:519)
        //     at com.strobel.decompiler.languages.java.ast.AstBuilder.createTypeNoCache(AstBuilder.java:161)
        //     at com.strobel.decompiler.languages.java.ast.AstBuilder.createType(AstBuilder.java:150)
        //     at com.strobel.decompiler.languages.java.ast.AstBuilder.addType(AstBuilder.java:125)
        //     at com.strobel.decompiler.languages.java.JavaLanguage.buildAst(JavaLanguage.java:71)
        //     at com.strobel.decompiler.languages.java.JavaLanguage.decompileType(JavaLanguage.java:59)
        //     at com.strobel.decompiler.DecompilerDriver.decompileType(DecompilerDriver.java:330)
        //     at com.strobel.decompiler.DecompilerDriver.decompileJar(DecompilerDriver.java:251)
        //     at com.strobel.decompiler.DecompilerDriver.main(DecompilerDriver.java:126)
        // 
        throw new IllegalStateException("An error occurred while decompiling this method.");
    }
}
