// 
// Decompiled by Procyon v0.5.36
// 

package dev.nuker.pyro;

import net.minecraft.client.gui.ScaledResolution;
import net.minecraft.client.Minecraft;
import net.minecraft.client.gui.GuiScreen;

public class f3W extends GuiScreen
{
    public GuiScreen c;
    public f3X c;
    public String c;
    public f4c c;
    
    public f3W(final String c, final GuiScreen c2, final f3X c3) {
        while (true) {
            int n = 0;
            Label_0013: {
                if (fc.0 != 0) {
                    n = 1312711882;
                    break Label_0013;
                }
                n = 1050795327;
            }
            switch (n ^ 0x46E2823A) {
                case 1421675280: {
                    continue;
                }
                default: {
                    this.c = c;
                    this.c = c2;
                    this.c = c3;
                    final ScaledResolution scaledResolution = new ScaledResolution(Minecraft.func_71410_x());
                    while (true) {
                        int n2 = 0;
                        Label_0090: {
                            if (fc.1 != 0) {
                                n2 = -623977606;
                                break Label_0090;
                            }
                            n2 = 1473559704;
                        }
                        switch (n2 ^ 0xD5C6BE30) {
                            case 252208458: {
                                continue;
                            }
                            case -2112748888: {
                                final float n3 = (float)(scaledResolution.func_78326_a() / 2);
                                final float n4 = (float)(scaledResolution.func_78328_b() / 2 + 40);
                                while (true) {
                                    int n5 = 0;
                                    Label_0152: {
                                        if (fc.1 != 0) {
                                            n5 = 1741952962;
                                            break Label_0152;
                                        }
                                        n5 = 2027128031;
                                    }
                                    switch (n5 ^ 0x8C814E38) {
                                        case -675622048: {
                                            continue;
                                        }
                                        default: {
                                            final float n6 = n4;
                                            while (true) {
                                                int n7 = 0;
                                                Label_0195: {
                                                    if (fc.0 != 0) {
                                                        n7 = -1200141812;
                                                        break Label_0195;
                                                    }
                                                    n7 = 1761457468;
                                                }
                                                switch (n7 ^ 0x1869E11F) {
                                                    case -1608602861: {
                                                        continue;
                                                    }
                                                    case 1888769059: {
                                                        final f4c c4 = new f4c(c, n3, n6);
                                                        while (true) {
                                                            int n8 = 0;
                                                            Label_0250: {
                                                                if (fc.c < 0) {
                                                                    n8 = -873383005;
                                                                    break Label_0250;
                                                                }
                                                                n8 = -1397833531;
                                                            }
                                                            switch (n8 ^ 0xC760BCA5) {
                                                                case 244253261: {
                                                                    continue;
                                                                }
                                                                default: {
                                                                    this.c = c4;
                                                                    final f0n c5 = this.c.c().c();
                                                                    Label_0741: {
                                                                        if (c5 instanceof f0d) {
                                                                            final f0d f0d = (f0d)c5;
                                                                            while (true) {
                                                                                int n9 = 0;
                                                                                Label_0323: {
                                                                                    if (fc.0 != 0) {
                                                                                        n9 = 1521566742;
                                                                                        break Label_0323;
                                                                                    }
                                                                                    n9 = -709541787;
                                                                                }
                                                                                switch (n9 ^ 0x5A948305) {
                                                                                    case -1991267964: {
                                                                                        continue;
                                                                                    }
                                                                                    default: {
                                                                                        while (true) {
                                                                                            int n10 = 0;
                                                                                            Label_0366: {
                                                                                                if (fc.1 != 0) {
                                                                                                    n10 = 1675967641;
                                                                                                    break Label_0366;
                                                                                                }
                                                                                                n10 = -417768170;
                                                                                            }
                                                                                            switch (n10 ^ 0xE4C8F10C) {
                                                                                                case -2027041387: {
                                                                                                    continue;
                                                                                                }
                                                                                                case 64072730: {
                                                                                                    final f4c c6 = this.c;
                                                                                                    while (true) {
                                                                                                        int n11 = 0;
                                                                                                        Label_0412: {
                                                                                                            if (fc.c < 0) {
                                                                                                                n11 = -1220889450;
                                                                                                                break Label_0412;
                                                                                                            }
                                                                                                            n11 = 2121476993;
                                                                                                        }
                                                                                                        switch (n11 ^ 0x663074B8) {
                                                                                                            case -1272142234: {
                                                                                                                continue;
                                                                                                            }
                                                                                                            default: {
                                                                                                                final f3Z c7 = c6.c();
                                                                                                                while (true) {
                                                                                                                    int n12 = 0;
                                                                                                                    Label_0456: {
                                                                                                                        if (fc.c < 0) {
                                                                                                                            n12 = -2031226880;
                                                                                                                            break Label_0456;
                                                                                                                        }
                                                                                                                        n12 = -804048418;
                                                                                                                    }
                                                                                                                    switch (n12 ^ 0x9339F169) {
                                                                                                                        case 1608346801: {
                                                                                                                            continue;
                                                                                                                        }
                                                                                                                        default: {
                                                                                                                            final f0d f0d2 = f0d;
                                                                                                                            while (true) {
                                                                                                                                int n13 = 0;
                                                                                                                                Label_0499: {
                                                                                                                                    if (fc.c < 0) {
                                                                                                                                        n13 = 925290200;
                                                                                                                                        break Label_0499;
                                                                                                                                    }
                                                                                                                                    n13 = 334960667;
                                                                                                                                }
                                                                                                                                switch (n13 ^ 0x4652102A) {
                                                                                                                                    case -1326110775: {
                                                                                                                                        continue;
                                                                                                                                    }
                                                                                                                                    default: {
                                                                                                                                        final Object 3 = f0d2.3();
                                                                                                                                        while (true) {
                                                                                                                                            int n14 = 0;
                                                                                                                                            Label_0544: {
                                                                                                                                                if (fc.1 != 0) {
                                                                                                                                                    n14 = 1357348634;
                                                                                                                                                    break Label_0544;
                                                                                                                                                }
                                                                                                                                                n14 = -1146671230;
                                                                                                                                            }
                                                                                                                                            switch (n14 ^ 0x5394CA3D) {
                                                                                                                                                case -1076869476: {
                                                                                                                                                    continue;
                                                                                                                                                }
                                                                                                                                                default: {
                                                                                                                                                    c7.0(String.valueOf(3));
                                                                                                                                                    break Label_0741;
                                                                                                                                                }
                                                                                                                                                case 57914663: {
                                                                                                                                                    throw null;
                                                                                                                                                }
                                                                                                                                            }
                                                                                                                                            break;
                                                                                                                                        }
                                                                                                                                        break;
                                                                                                                                    }
                                                                                                                                    case 1903484658: {
                                                                                                                                        throw null;
                                                                                                                                    }
                                                                                                                                }
                                                                                                                                break;
                                                                                                                            }
                                                                                                                            break;
                                                                                                                        }
                                                                                                                        case 366215529: {
                                                                                                                            throw null;
                                                                                                                        }
                                                                                                                    }
                                                                                                                    break;
                                                                                                                }
                                                                                                                break;
                                                                                                            }
                                                                                                            case -787824594: {
                                                                                                                throw null;
                                                                                                            }
                                                                                                        }
                                                                                                        break;
                                                                                                    }
                                                                                                    break;
                                                                                                }
                                                                                                default: {
                                                                                                    throw null;
                                                                                                }
                                                                                            }
                                                                                            break;
                                                                                        }
                                                                                        break;
                                                                                    }
                                                                                    case 2475795: {
                                                                                        throw null;
                                                                                    }
                                                                                }
                                                                                break;
                                                                            }
                                                                        }
                                                                        else {
                                                                            while (true) {
                                                                                int n15 = 0;
                                                                                Label_0594: {
                                                                                    if (fc.1 != 0) {
                                                                                        n15 = -608023218;
                                                                                        break Label_0594;
                                                                                    }
                                                                                    n15 = 1595034411;
                                                                                }
                                                                                switch (n15 ^ 0xF099230C) {
                                                                                    case 996699030: {
                                                                                        continue;
                                                                                    }
                                                                                    default: {
                                                                                        if (!(c5 instanceof f0g)) {
                                                                                            break;
                                                                                        }
                                                                                        final f0g f0g = (f0g)c5;
                                                                                        while (true) {
                                                                                            int n16 = 0;
                                                                                            Label_0652: {
                                                                                                if (fc.c < 0) {
                                                                                                    n16 = -1630219344;
                                                                                                    break Label_0652;
                                                                                                }
                                                                                                n16 = -1433052322;
                                                                                            }
                                                                                            switch (n16 ^ 0x1263EA46) {
                                                                                                case -67648218: {
                                                                                                    continue;
                                                                                                }
                                                                                                default: {
                                                                                                    while (true) {
                                                                                                        int n17 = 0;
                                                                                                        Label_0694: {
                                                                                                            if (fc.c < 0) {
                                                                                                                n17 = -146064244;
                                                                                                                break Label_0694;
                                                                                                            }
                                                                                                            n17 = 590455264;
                                                                                                        }
                                                                                                        switch (n17 ^ 0x9E45A291) {
                                                                                                            case 554694366: {
                                                                                                                continue;
                                                                                                            }
                                                                                                            default: {
                                                                                                                this.c.c().0(String.valueOf(f0g.3()));
                                                                                                                break Label_0741;
                                                                                                            }
                                                                                                            case 1762565661: {
                                                                                                                throw null;
                                                                                                            }
                                                                                                        }
                                                                                                        break;
                                                                                                    }
                                                                                                    break;
                                                                                                }
                                                                                                case -1934149130: {
                                                                                                    throw null;
                                                                                                }
                                                                                            }
                                                                                            break;
                                                                                        }
                                                                                        break;
                                                                                    }
                                                                                    case 727412290: {
                                                                                        throw null;
                                                                                    }
                                                                                }
                                                                                break;
                                                                            }
                                                                        }
                                                                    }
                                                                    return;
                                                                }
                                                                case 210863878: {
                                                                    throw null;
                                                                }
                                                            }
                                                            break;
                                                        }
                                                        break;
                                                    }
                                                    default: {
                                                        throw null;
                                                    }
                                                }
                                                break;
                                            }
                                            break;
                                        }
                                        case -346727942: {
                                            throw null;
                                        }
                                    }
                                    break;
                                }
                                break;
                            }
                            default: {
                                throw null;
                            }
                        }
                        break;
                    }
                    break;
                }
                case 148694768: {
                    throw null;
                }
            }
            break;
        }
    }
    
    public void func_73864_a(final int p0, final int p1, final int p2) {
        // 
        // This method could not be decompiled.
        // 
        // Original Bytecode:
        // 
        //     3: dup            
        //     4: ifnull          68
        //     7: athrow         
        //     8: aconst_null    
        //     9: getstatic       dev/nuker/pyro/fc.0:I
        //    12: ifgt            60
        //    15: pop            
        //    16: aconst_null    
        //    17: goto            52
        //    20: nop            
        //    21: nop            
        //    22: nop            
        //    23: athrow         
        //    24: aload_0        
        //    25: getfield        dev/nuker/pyro/f3W.c:Ldev/nuker/pyro/f4c;
        //    28: iload_1        
        //    29: iload_2        
        //    30: iload_3        
        //    31: goto            35
        //    34: athrow         
        //    35: invokevirtual   dev/nuker/pyro/f4c.c:(III)V
        //    38: goto            42
        //    41: athrow         
        //    42: return         
        //    43: pop            
        //    44: goto            24
        //    47: pop            
        //    48: aconst_null    
        //    49: goto            43
        //    52: dup            
        //    53: ifnull          43
        //    56: checkcast       Ljava/lang/Throwable;
        //    59: athrow         
        //    60: dup            
        //    61: ifnull          47
        //    64: checkcast       Ljava/lang/Throwable;
        //    67: athrow         
        //    68: aconst_null    
        //    69: athrow         
        //    StackMapTable: 00 0D 43 07 00 92 04 FF 00 0B 00 00 00 01 07 00 94 FF 00 03 00 04 07 00 03 01 01 01 00 00 49 07 00 92 FF 00 00 00 04 07 00 03 01 01 01 00 04 07 00 3E 01 01 01 45 07 00 94 00 40 07 00 94 43 05 44 07 00 94 47 05 47 07 00 92
        //    Exceptions:
        //  Try           Handler
        //  Start  End    Start  End    Type                                       
        //  -----  -----  -----  -----  -------------------------------------------
        //  8      20     52     60     Ljava/lang/IndexOutOfBoundsException;
        //  52     60     52     60     Any
        //  68     70     3      8      Ljava/lang/UnsupportedOperationException;
        //  34     41     41     42     Any
        //  35     41     34     35     Ljava/lang/EnumConstantNotPresentException;
        //  35     41     3      8      Ljava/lang/RuntimeException;
        //  35     41     41     42     Any
        //  34     41     34     35     Ljava/lang/RuntimeException;
        // 
        // The error that occurred was:
        // 
        // java.lang.IndexOutOfBoundsException: Index 36 out of bounds for length 36
        //     at java.base/jdk.internal.util.Preconditions.outOfBounds(Preconditions.java:64)
        //     at java.base/jdk.internal.util.Preconditions.outOfBoundsCheckIndex(Preconditions.java:70)
        //     at java.base/jdk.internal.util.Preconditions.checkIndex(Preconditions.java:248)
        //     at java.base/java.util.Objects.checkIndex(Objects.java:372)
        //     at java.base/java.util.ArrayList.get(ArrayList.java:458)
        //     at com.strobel.decompiler.ast.AstBuilder.convertToAst(AstBuilder.java:3321)
        //     at com.strobel.decompiler.ast.AstBuilder.convertToAst(AstBuilder.java:3569)
        //     at com.strobel.decompiler.ast.AstBuilder.convertToAst(AstBuilder.java:3435)
        //     at com.strobel.decompiler.ast.AstBuilder.convertToAst(AstBuilder.java:3435)
        //     at com.strobel.decompiler.ast.AstBuilder.build(AstBuilder.java:113)
        //     at com.strobel.decompiler.languages.java.ast.AstMethodBodyBuilder.createMethodBody(AstMethodBodyBuilder.java:211)
        //     at com.strobel.decompiler.languages.java.ast.AstMethodBodyBuilder.createMethodBody(AstMethodBodyBuilder.java:99)
        //     at com.strobel.decompiler.languages.java.ast.AstBuilder.createMethodBody(AstBuilder.java:782)
        //     at com.strobel.decompiler.languages.java.ast.AstBuilder.createMethod(AstBuilder.java:675)
        //     at com.strobel.decompiler.languages.java.ast.AstBuilder.addTypeMembers(AstBuilder.java:552)
        //     at com.strobel.decompiler.languages.java.ast.AstBuilder.createTypeCore(AstBuilder.java:519)
        //     at com.strobel.decompiler.languages.java.ast.AstBuilder.createTypeNoCache(AstBuilder.java:161)
        //     at com.strobel.decompiler.languages.java.ast.AstBuilder.createType(AstBuilder.java:150)
        //     at com.strobel.decompiler.languages.java.ast.AstBuilder.addType(AstBuilder.java:125)
        //     at com.strobel.decompiler.languages.java.JavaLanguage.buildAst(JavaLanguage.java:71)
        //     at com.strobel.decompiler.languages.java.JavaLanguage.decompileType(JavaLanguage.java:59)
        //     at com.strobel.decompiler.DecompilerDriver.decompileType(DecompilerDriver.java:330)
        //     at com.strobel.decompiler.DecompilerDriver.decompileJar(DecompilerDriver.java:251)
        //     at com.strobel.decompiler.DecompilerDriver.main(DecompilerDriver.java:126)
        // 
        throw new IllegalStateException("An error occurred while decompiling this method.");
    }
    
    public void func_146286_b(final int n, final int n2, final int n3) {
        fbS.b3(this, 1791887801, n, n2, n3);
    }
    
    static {
        throw t;
    }
    
    public void func_73869_a(final char c, final int n) {
        fbS.5n(this, 836829302, c, n);
    }
    
    public void c(final boolean b) {
        fbS.4g(this, 651544699, b);
    }
    
    public void func_73863_a(final int p0, final int p1, final float p2) {
        // 
        // This method could not be decompiled.
        // 
        // Original Bytecode:
        // 
        //     3: dup            
        //     4: ifnull          183
        //     7: athrow         
        //     8: aconst_null    
        //     9: getstatic       dev/nuker/pyro/fc.c:I
        //    12: iflt            175
        //    15: pop            
        //    16: aconst_null    
        //    17: goto            167
        //    20: nop            
        //    21: nop            
        //    22: nop            
        //    23: athrow         
        //    24: aload_0        
        //    25: getfield        dev/nuker/pyro/f3W.c:Lnet/minecraft/client/gui/GuiScreen;
        //    28: sipush          -1337
        //    31: sipush          -1337
        //    34: fload_3        
        //    35: goto            39
        //    38: athrow         
        //    39: invokevirtual   net/minecraft/client/gui/GuiScreen.func_73863_a:(IIF)V
        //    42: goto            46
        //    45: athrow         
        //    46: getstatic       dev/nuker/pyro/fc.1:I
        //    49: ifeq            57
        //    52: ldc             307153434
        //    54: goto            59
        //    57: ldc             -1257775433
        //    59: ldc             -634939667
        //    61: ixor           
        //    62: lookupswitch {
        //          -932619017: 154
        //          -138467860: 57
        //          default: 88
        //        }
        //    88: aload_0        
        //    89: getfield        dev/nuker/pyro/f3W.c:Ldev/nuker/pyro/f4c;
        //    92: getstatic       dev/nuker/pyro/fc.c:I
        //    95: ifge            103
        //    98: ldc             -1418020460
        //   100: goto            105
        //   103: ldc             851717293
        //   105: ldc             193088913
        //   107: ixor           
        //   108: lookupswitch {
        //          -1594297339: 103
        //          960913724: 136
        //          default: 156
        //        }
        //   136: iload_1        
        //   137: i2f            
        //   138: iload_2        
        //   139: i2f            
        //   140: fload_3        
        //   141: goto            145
        //   144: athrow         
        //   145: invokevirtual   dev/nuker/pyro/f4c.c:(FFF)Z
        //   148: goto            152
        //   151: athrow         
        //   152: pop            
        //   153: return         
        //   154: aconst_null    
        //   155: athrow         
        //   156: aconst_null    
        //   157: athrow         
        //   158: pop            
        //   159: goto            24
        //   162: pop            
        //   163: aconst_null    
        //   164: goto            158
        //   167: dup            
        //   168: ifnull          158
        //   171: checkcast       Ljava/lang/Throwable;
        //   174: athrow         
        //   175: dup            
        //   176: ifnull          162
        //   179: checkcast       Ljava/lang/Throwable;
        //   182: athrow         
        //   183: aconst_null    
        //   184: athrow         
        //    StackMapTable: 00 19 43 07 00 94 04 FF 00 0B 00 00 00 01 07 00 94 FF 00 03 00 04 07 00 03 01 01 02 00 00 4D 07 00 92 FF 00 00 00 04 07 00 03 01 01 02 00 04 07 00 05 01 01 02 45 07 00 94 00 0A 41 01 1C 4E 07 00 3E FF 00 01 00 04 07 00 03 01 01 02 00 02 07 00 3E 01 5E 07 00 3E 47 07 00 94 FF 00 00 00 04 07 00 03 01 01 02 00 04 07 00 3E 02 02 02 45 07 00 94 40 01 01 41 07 00 3E 41 07 00 92 43 05 44 07 00 92 47 05 47 07 00 94
        //    Exceptions:
        //  Try           Handler
        //  Start  End    Start  End    Type                                       
        //  -----  -----  -----  -----  -------------------------------------------
        //  8      20     167    175    Ljava/lang/ArrayIndexOutOfBoundsException;
        //  167    175    167    175    Ljava/lang/IllegalStateException;
        //  183    185    3      8      Ljava/lang/NumberFormatException;
        //  38     45     45     46     Any
        //  39     45     38     39     Ljava/util/ConcurrentModificationException;
        //  39     45     3      8      Any
        //  39     45     45     46     Ljava/lang/ArithmeticException;
        //  38     45     38     39     Ljava/lang/EnumConstantNotPresentException;
        //  144    151    151    152    Any
        //  145    151    144    145    Any
        //  144    151    151    152    Any
        //  144    151    3      8      Any
        //  145    151    144    145    Any
        // 
        // The error that occurred was:
        // 
        // java.lang.IndexOutOfBoundsException: Index -1 out of bounds for length 0
        //     at java.base/jdk.internal.util.Preconditions.outOfBounds(Preconditions.java:64)
        //     at java.base/jdk.internal.util.Preconditions.outOfBoundsCheckIndex(Preconditions.java:70)
        //     at java.base/jdk.internal.util.Preconditions.checkIndex(Preconditions.java:248)
        //     at java.base/java.util.Objects.checkIndex(Objects.java:372)
        //     at java.base/java.util.ArrayList.remove(ArrayList.java:535)
        //     at com.strobel.assembler.ir.StackMappingVisitor.pop(StackMappingVisitor.java:267)
        //     at com.strobel.assembler.ir.StackMappingVisitor$InstructionAnalyzer.execute(StackMappingVisitor.java:543)
        //     at com.strobel.assembler.ir.StackMappingVisitor$InstructionAnalyzer.visit(StackMappingVisitor.java:398)
        //     at com.strobel.decompiler.ast.AstBuilder.performStackAnalysis(AstBuilder.java:2030)
        //     at com.strobel.decompiler.ast.AstBuilder.build(AstBuilder.java:108)
        //     at com.strobel.decompiler.languages.java.ast.AstMethodBodyBuilder.createMethodBody(AstMethodBodyBuilder.java:211)
        //     at com.strobel.decompiler.languages.java.ast.AstMethodBodyBuilder.createMethodBody(AstMethodBodyBuilder.java:99)
        //     at com.strobel.decompiler.languages.java.ast.AstBuilder.createMethodBody(AstBuilder.java:782)
        //     at com.strobel.decompiler.languages.java.ast.AstBuilder.createMethod(AstBuilder.java:675)
        //     at com.strobel.decompiler.languages.java.ast.AstBuilder.addTypeMembers(AstBuilder.java:552)
        //     at com.strobel.decompiler.languages.java.ast.AstBuilder.createTypeCore(AstBuilder.java:519)
        //     at com.strobel.decompiler.languages.java.ast.AstBuilder.createTypeNoCache(AstBuilder.java:161)
        //     at com.strobel.decompiler.languages.java.ast.AstBuilder.createType(AstBuilder.java:150)
        //     at com.strobel.decompiler.languages.java.ast.AstBuilder.addType(AstBuilder.java:125)
        //     at com.strobel.decompiler.languages.java.JavaLanguage.buildAst(JavaLanguage.java:71)
        //     at com.strobel.decompiler.languages.java.JavaLanguage.decompileType(JavaLanguage.java:59)
        //     at com.strobel.decompiler.DecompilerDriver.decompileType(DecompilerDriver.java:330)
        //     at com.strobel.decompiler.DecompilerDriver.decompileJar(DecompilerDriver.java:251)
        //     at com.strobel.decompiler.DecompilerDriver.main(DecompilerDriver.java:126)
        // 
        throw new IllegalStateException("An error occurred while decompiling this method.");
    }
}
