// 
// Decompiled by Procyon v0.5.36
// 

package dev.nuker.pyro;

public class f3Y extends f3A
{
    public f3Y(final String s, final float n, final float n2, final float n3, final float n4) {
        super(s, n, n2, n3, n4);
    }
    
    static {
        throw t;
    }
    
    @Override
    public boolean c(final float p0, final float p1, final float p2) {
        // 
        // This method could not be decompiled.
        // 
        // Original Bytecode:
        // 
        //     3: dup            
        //     4: ifnull          691
        //     7: athrow         
        //     8: aconst_null    
        //     9: getstatic       dev/nuker/pyro/fc.1:I
        //    12: ifgt            683
        //    15: pop            
        //    16: aconst_null    
        //    17: goto            675
        //    20: nop            
        //    21: nop            
        //    22: nop            
        //    23: athrow         
        //    24: aload_0        
        //    25: goto            29
        //    28: athrow         
        //    29: invokevirtual   dev/nuker/pyro/f3Y.5:()F
        //    32: goto            36
        //    35: athrow         
        //    36: aload_0        
        //    37: getstatic       dev/nuker/pyro/fc.c:I
        //    40: ifge            48
        //    43: ldc             1340444425
        //    45: goto            50
        //    48: ldc             -24870402
        //    50: ldc             -1271690326
        //    52: ixor           
        //    53: lookupswitch {
        //          -69860189: 654
        //          2139470875: 48
        //          default: 80
        //        }
        //    80: goto            84
        //    83: athrow         
        //    84: invokevirtual   dev/nuker/pyro/f3Y.2:()F
        //    87: goto            91
        //    90: athrow         
        //    91: aload_0        
        //    92: goto            96
        //    95: athrow         
        //    96: invokevirtual   dev/nuker/pyro/f3Y.5:()F
        //    99: goto            103
        //   102: athrow         
        //   103: aload_0        
        //   104: goto            108
        //   107: athrow         
        //   108: invokevirtual   dev/nuker/pyro/f3Y.1:()F
        //   111: goto            115
        //   114: athrow         
        //   115: fadd           
        //   116: aload_0        
        //   117: goto            121
        //   120: athrow         
        //   121: invokevirtual   dev/nuker/pyro/f3Y.2:()F
        //   124: goto            128
        //   127: athrow         
        //   128: aload_0        
        //   129: goto            133
        //   132: athrow         
        //   133: invokevirtual   dev/nuker/pyro/f3Y.3:()F
        //   136: goto            140
        //   139: athrow         
        //   140: fadd           
        //   141: aload_0        
        //   142: getstatic       dev/nuker/pyro/fc.1:I
        //   145: ifeq            153
        //   148: ldc             -1555961991
        //   150: goto            155
        //   153: ldc             -426034489
        //   155: ldc             -284178715
        //   157: ixor           
        //   158: lookupswitch {
        //          160758818: 184
        //          1280188828: 153
        //          default: 650
        //        }
        //   184: goto            188
        //   187: athrow         
        //   188: invokevirtual   dev/nuker/pyro/f3Y.9:()Z
        //   191: goto            195
        //   194: athrow         
        //   195: ifeq            203
        //   198: ldc             321665661
        //   200: goto            205
        //   203: ldc             321665662
        //   205: ldc             -303476008
        //   207: ixor           
        //   208: tableswitch {
        //          -41234102: 232
        //          -41234101: 237
        //          default: 198
        //        }
        //   232: ldc             -65521
        //   234: goto            295
        //   237: getstatic       dev/nuker/pyro/f0y.c:Ldev/nuker/pyro/f0y;
        //   240: getstatic       dev/nuker/pyro/fc.0:I
        //   243: ifeq            251
        //   246: ldc             679440989
        //   248: goto            253
        //   251: ldc             -9556310
        //   253: ldc             78387974
        //   255: ixor           
        //   256: lookupswitch {
        //          -71158356: 284
        //          752052571: 251
        //          default: 652
        //        }
        //   284: goto            288
        //   287: athrow         
        //   288: invokevirtual   dev/nuker/pyro/f0y.6:()I
        //   291: goto            295
        //   294: athrow         
        //   295: goto            299
        //   298: athrow         
        //   299: invokestatic    dev/nuker/pyro/fbs.c:(FFFFI)V
        //   302: goto            306
        //   305: athrow         
        //   306: getstatic       dev/nuker/pyro/fy.c:Ldev/nuker/pyro/fy;
        //   309: getstatic       dev/nuker/pyro/fc.1:I
        //   312: ifeq            320
        //   315: ldc             -1202079396
        //   317: goto            322
        //   320: ldc             -1406994868
        //   322: ldc             -1009834569
        //   324: ixor           
        //   325: lookupswitch {
        //          1877857275: 352
        //          2073468139: 320
        //          default: 658
        //        }
        //   352: getfield        dev/nuker/pyro/fy.0:Ldev/nuker/pyro/util/font/GameFontRenderer;
        //   355: getstatic       dev/nuker/pyro/fc.1:I
        //   358: ifeq            366
        //   361: ldc             2078322398
        //   363: goto            368
        //   366: ldc             -1820551474
        //   368: ldc             -1520778190
        //   370: ixor           
        //   371: lookupswitch {
        //          -558208276: 366
        //          908481276: 396
        //          default: 648
        //        }
        //   396: aload_0        
        //   397: getstatic       dev/nuker/pyro/fc.c:I
        //   400: ifge            408
        //   403: ldc             -586229216
        //   405: goto            410
        //   408: ldc             2061278343
        //   410: ldc             1502509973
        //   412: ixor           
        //   413: lookupswitch {
        //          -2071944779: 662
        //          2072714161: 408
        //          default: 440
        //        }
        //   440: goto            444
        //   443: athrow         
        //   444: invokevirtual   dev/nuker/pyro/f3Y.7:()Ljava/lang/String;
        //   447: goto            451
        //   450: athrow         
        //   451: aload_0        
        //   452: goto            456
        //   455: athrow         
        //   456: invokevirtual   dev/nuker/pyro/f3Y.5:()F
        //   459: goto            463
        //   462: athrow         
        //   463: getstatic       dev/nuker/pyro/fc.c:I
        //   466: ifge            474
        //   469: ldc             -1099585433
        //   471: goto            476
        //   474: ldc             -178753353
        //   476: ldc             1882977967
        //   478: ixor           
        //   479: lookupswitch {
        //          -2057075176: 504
        //          -833724728: 474
        //          default: 660
        //        }
        //   504: aload_0        
        //   505: getstatic       dev/nuker/pyro/fc.c:I
        //   508: ifge            516
        //   511: ldc             -1778720921
        //   513: goto            518
        //   516: ldc             1316759275
        //   518: ldc             -1976042071
        //   520: ixor           
        //   521: lookupswitch {
        //          -1001661630: 548
        //          533537486: 516
        //          default: 656
        //        }
        //   548: goto            552
        //   551: athrow         
        //   552: invokevirtual   dev/nuker/pyro/f3Y.1:()F
        //   555: goto            559
        //   558: athrow         
        //   559: fconst_2       
        //   560: fdiv           
        //   561: fadd           
        //   562: aload_0        
        //   563: goto            567
        //   566: athrow         
        //   567: invokevirtual   dev/nuker/pyro/f3Y.2:()F
        //   570: goto            574
        //   573: athrow         
        //   574: ldc             5.0
        //   576: fadd           
        //   577: iconst_m1      
        //   578: iconst_1       
        //   579: goto            583
        //   582: athrow         
        //   583: invokevirtual   dev/nuker/pyro/util/font/GameFontRenderer.drawCenteredString:(Ljava/lang/String;FFIZ)V
        //   586: goto            590
        //   589: athrow         
        //   590: aload_0        
        //   591: fload_1        
        //   592: fload_2        
        //   593: fload_3        
        //   594: getstatic       dev/nuker/pyro/fc.1:I
        //   597: ifeq            605
        //   600: ldc             -1075743118
        //   602: goto            607
        //   605: ldc             582506447
        //   607: ldc             999946797
        //   609: ixor           
        //   610: lookupswitch {
        //          -2072474529: 605
        //          421637602: 636
        //          default: 664
        //        }
        //   636: goto            640
        //   639: athrow         
        //   640: invokespecial   dev/nuker/pyro/f3A.c:(FFF)Z
        //   643: goto            647
        //   646: athrow         
        //   647: ireturn        
        //   648: aconst_null    
        //   649: athrow         
        //   650: aconst_null    
        //   651: athrow         
        //   652: aconst_null    
        //   653: athrow         
        //   654: aconst_null    
        //   655: athrow         
        //   656: aconst_null    
        //   657: athrow         
        //   658: aconst_null    
        //   659: athrow         
        //   660: aconst_null    
        //   661: athrow         
        //   662: aconst_null    
        //   663: athrow         
        //   664: aconst_null    
        //   665: athrow         
        //   666: pop            
        //   667: goto            24
        //   670: pop            
        //   671: aconst_null    
        //   672: goto            666
        //   675: dup            
        //   676: ifnull          666
        //   679: checkcast       Ljava/lang/Throwable;
        //   682: athrow         
        //   683: dup            
        //   684: ifnull          670
        //   687: checkcast       Ljava/lang/Throwable;
        //   690: athrow         
        //   691: aconst_null    
        //   692: athrow         
        //    StackMapTable: 00 6E 43 07 00 31 04 FF 00 0B 00 00 00 01 07 00 31 FF 00 03 00 04 07 00 03 02 02 02 00 00 FF 00 03 00 00 00 01 07 00 31 FF 00 00 00 04 07 00 03 02 02 02 00 01 07 00 03 45 07 00 31 40 02 FF 00 0B 00 04 07 00 03 02 02 02 00 02 02 07 00 03 FF 00 01 00 04 07 00 03 02 02 02 00 03 02 07 00 03 01 FF 00 1D 00 04 07 00 03 02 02 02 00 02 02 07 00 03 42 07 00 31 FF 00 00 00 04 07 00 03 02 02 02 00 02 02 07 00 03 45 07 00 31 FF 00 00 00 04 07 00 03 02 02 02 00 02 02 02 43 07 00 31 FF 00 00 00 04 07 00 03 02 02 02 00 03 02 02 07 00 03 45 07 00 31 FF 00 00 00 04 07 00 03 02 02 02 00 03 02 02 02 43 07 00 31 FF 00 00 00 04 07 00 03 02 02 02 00 04 02 02 02 07 00 03 45 07 00 31 FF 00 00 00 04 07 00 03 02 02 02 00 04 02 02 02 02 44 07 00 31 FF 00 00 00 04 07 00 03 02 02 02 00 04 02 02 02 07 00 03 45 07 00 31 FF 00 00 00 04 07 00 03 02 02 02 00 04 02 02 02 02 43 07 00 31 FF 00 00 00 04 07 00 03 02 02 02 00 05 02 02 02 02 07 00 03 45 07 00 31 FF 00 00 00 04 07 00 03 02 02 02 00 05 02 02 02 02 02 FF 00 0C 00 04 07 00 03 02 02 02 00 05 02 02 02 02 07 00 03 FF 00 01 00 04 07 00 03 02 02 02 00 06 02 02 02 02 07 00 03 01 FF 00 1C 00 04 07 00 03 02 02 02 00 05 02 02 02 02 07 00 03 42 07 00 31 FF 00 00 00 04 07 00 03 02 02 02 00 05 02 02 02 02 07 00 03 45 07 00 31 FF 00 00 00 04 07 00 03 02 02 02 00 05 02 02 02 02 01 FF 00 02 00 04 07 00 03 02 02 02 00 04 02 02 02 02 FF 00 04 00 04 07 00 03 02 02 02 00 04 02 02 02 02 FF 00 01 00 04 07 00 03 02 02 02 00 05 02 02 02 02 01 FF 00 1A 00 04 07 00 03 02 02 02 00 04 02 02 02 02 FF 00 04 00 04 07 00 03 02 02 02 00 04 02 02 02 02 FF 00 0D 00 04 07 00 03 02 02 02 00 05 02 02 02 02 07 00 4F FF 00 01 00 04 07 00 03 02 02 02 00 06 02 02 02 02 07 00 4F 01 FF 00 1E 00 04 07 00 03 02 02 02 00 05 02 02 02 02 07 00 4F 42 07 00 1B FF 00 00 00 04 07 00 03 02 02 02 00 05 02 02 02 02 07 00 4F 45 07 00 31 FF 00 00 00 04 07 00 03 02 02 02 00 05 02 02 02 02 01 FF 00 02 00 00 00 01 07 00 31 FF 00 00 00 04 07 00 03 02 02 02 00 05 02 02 02 02 01 45 07 00 31 00 4D 07 00 63 FF 00 01 00 04 07 00 03 02 02 02 00 02 07 00 63 01 5D 07 00 63 4D 07 00 7F FF 00 01 00 04 07 00 03 02 02 02 00 02 07 00 7F 01 5B 07 00 7F FF 00 0B 00 04 07 00 03 02 02 02 00 02 07 00 7F 07 00 03 FF 00 01 00 04 07 00 03 02 02 02 00 03 07 00 7F 07 00 03 01 FF 00 1D 00 04 07 00 03 02 02 02 00 02 07 00 7F 07 00 03 42 07 00 1D FF 00 00 00 04 07 00 03 02 02 02 00 02 07 00 7F 07 00 03 45 07 00 31 FF 00 00 00 04 07 00 03 02 02 02 00 02 07 00 7F 07 00 8A FF 00 03 00 00 00 01 07 00 31 FF 00 00 00 04 07 00 03 02 02 02 00 03 07 00 7F 07 00 8A 07 00 03 45 07 00 31 FF 00 00 00 04 07 00 03 02 02 02 00 03 07 00 7F 07 00 8A 02 FF 00 0A 00 04 07 00 03 02 02 02 00 03 07 00 7F 07 00 8A 02 FF 00 01 00 04 07 00 03 02 02 02 00 04 07 00 7F 07 00 8A 02 01 FF 00 1B 00 04 07 00 03 02 02 02 00 03 07 00 7F 07 00 8A 02 FF 00 0B 00 04 07 00 03 02 02 02 00 04 07 00 7F 07 00 8A 02 07 00 03 FF 00 01 00 04 07 00 03 02 02 02 00 05 07 00 7F 07 00 8A 02 07 00 03 01 FF 00 1D 00 04 07 00 03 02 02 02 00 04 07 00 7F 07 00 8A 02 07 00 03 42 07 00 31 FF 00 00 00 04 07 00 03 02 02 02 00 04 07 00 7F 07 00 8A 02 07 00 03 45 07 00 31 FF 00 00 00 04 07 00 03 02 02 02 00 04 07 00 7F 07 00 8A 02 02 46 07 00 31 FF 00 00 00 04 07 00 03 02 02 02 00 04 07 00 7F 07 00 8A 02 07 00 03 45 07 00 31 FF 00 00 00 04 07 00 03 02 02 02 00 04 07 00 7F 07 00 8A 02 02 47 07 00 31 FF 00 00 00 04 07 00 03 02 02 02 00 06 07 00 7F 07 00 8A 02 02 01 01 45 07 00 31 00 FF 00 0E 00 04 07 00 03 02 02 02 00 04 07 00 03 02 02 02 FF 00 01 00 04 07 00 03 02 02 02 00 05 07 00 03 02 02 02 01 FF 00 1C 00 04 07 00 03 02 02 02 00 04 07 00 03 02 02 02 42 07 00 31 FF 00 00 00 04 07 00 03 02 02 02 00 04 07 00 03 02 02 02 45 07 00 31 40 01 40 07 00 7F FF 00 01 00 04 07 00 03 02 02 02 00 05 02 02 02 02 07 00 03 FF 00 01 00 04 07 00 03 02 02 02 00 05 02 02 02 02 07 00 4F FF 00 01 00 04 07 00 03 02 02 02 00 02 02 07 00 03 FF 00 01 00 04 07 00 03 02 02 02 00 04 07 00 7F 07 00 8A 02 07 00 03 41 07 00 63 FF 00 01 00 04 07 00 03 02 02 02 00 03 07 00 7F 07 00 8A 02 FF 00 01 00 04 07 00 03 02 02 02 00 02 07 00 7F 07 00 03 FF 00 01 00 04 07 00 03 02 02 02 00 04 07 00 03 02 02 02 41 07 00 31 43 05 44 07 00 31 47 05 47 07 00 31
        //    Exceptions:
        //  Try           Handler
        //  Start  End    Start  End    Type                                       
        //  -----  -----  -----  -----  -------------------------------------------
        //  8      20     675    683    Any
        //  675    683    675    683    Ljava/lang/NegativeArraySizeException;
        //  691    693    3      8      Any
        //  29     35     35     36     Any
        //  29     35     3      8      Ljava/lang/ArithmeticException;
        //  29     35     3      8      Any
        //  29     35     3      8      Any
        //  29     35     35     36     Ljava/lang/NullPointerException;
        //  83     90     90     91     Any
        //  83     90     3      8      Ljava/lang/NumberFormatException;
        //  83     90     83     84     Any
        //  83     90     83     84     Any
        //  84     90     90     91     Ljava/lang/ClassCastException;
        //  95     102    102    103    Any
        //  95     102    95     96     Any
        //  96     102    3      8      Any
        //  95     102    102    103    Any
        //  96     102    102    103    Ljava/lang/NumberFormatException;
        //  107    114    114    115    Any
        //  107    114    114    115    Ljava/lang/IndexOutOfBoundsException;
        //  107    114    107    108    Any
        //  107    114    107    108    Ljava/lang/RuntimeException;
        //  108    114    107    108    Any
        //  120    127    127    128    Any
        //  121    127    120    121    Any
        //  121    127    120    121    Ljava/lang/EnumConstantNotPresentException;
        //  121    127    3      8      Any
        //  121    127    127    128    Ljava/lang/IndexOutOfBoundsException;
        //  132    139    139    140    Any
        //  133    139    139    140    Ljava/lang/EnumConstantNotPresentException;
        //  132    139    132    133    Any
        //  133    139    3      8      Any
        //  133    139    3      8      Any
        //  187    194    194    195    Any
        //  188    194    194    195    Any
        //  187    194    194    195    Any
        //  187    194    3      8      Any
        //  187    194    187    188    Any
        //  287    294    294    295    Any
        //  287    294    287    288    Ljava/lang/NullPointerException;
        //  288    294    287    288    Ljava/lang/StringIndexOutOfBoundsException;
        //  288    294    287    288    Ljava/lang/ArrayIndexOutOfBoundsException;
        //  288    294    3      8      Ljava/util/NoSuchElementException;
        //  299    305    305    306    Any
        //  299    305    3      8      Any
        //  299    305    3      8      Ljava/util/NoSuchElementException;
        //  299    305    3      8      Ljava/lang/RuntimeException;
        //  299    305    305    306    Any
        //  443    450    450    451    Any
        //  443    450    443    444    Ljava/lang/EnumConstantNotPresentException;
        //  444    450    450    451    Ljava/lang/RuntimeException;
        //  444    450    3      8      Any
        //  444    450    3      8      Ljava/lang/NegativeArraySizeException;
        //  456    462    462    463    Any
        //  456    462    462    463    Ljava/lang/ClassCastException;
        //  456    462    3      8      Ljava/lang/UnsupportedOperationException;
        //  456    462    462    463    Any
        //  456    462    462    463    Any
        //  551    558    558    559    Any
        //  551    558    558    559    Ljava/lang/NegativeArraySizeException;
        //  552    558    558    559    Ljava/lang/ArithmeticException;
        //  552    558    551    552    Ljava/util/NoSuchElementException;
        //  552    558    551    552    Ljava/lang/AssertionError;
        //  566    573    573    574    Any
        //  567    573    566    567    Any
        //  567    573    3      8      Ljava/lang/StringIndexOutOfBoundsException;
        //  566    573    566    567    Any
        //  567    573    3      8      Any
        //  582    589    589    590    Any
        //  582    589    582    583    Any
        //  583    589    3      8      Ljava/util/ConcurrentModificationException;
        //  583    589    582    583    Ljava/lang/RuntimeException;
        //  583    589    589    590    Any
        //  639    646    646    647    Any
        //  640    646    3      8      Any
        //  640    646    646    647    Ljava/lang/EnumConstantNotPresentException;
        //  640    646    639    640    Any
        //  640    646    3      8      Any
        // 
        // The error that occurred was:
        // 
        // java.lang.IndexOutOfBoundsException: Index -1 out of bounds for length 0
        //     at java.base/jdk.internal.util.Preconditions.outOfBounds(Preconditions.java:64)
        //     at java.base/jdk.internal.util.Preconditions.outOfBoundsCheckIndex(Preconditions.java:70)
        //     at java.base/jdk.internal.util.Preconditions.checkIndex(Preconditions.java:248)
        //     at java.base/java.util.Objects.checkIndex(Objects.java:372)
        //     at java.base/java.util.ArrayList.remove(ArrayList.java:535)
        //     at com.strobel.assembler.ir.StackMappingVisitor.pop(StackMappingVisitor.java:267)
        //     at com.strobel.assembler.ir.StackMappingVisitor$InstructionAnalyzer.execute(StackMappingVisitor.java:618)
        //     at com.strobel.assembler.ir.StackMappingVisitor$InstructionAnalyzer.visit(StackMappingVisitor.java:398)
        //     at com.strobel.decompiler.ast.AstBuilder.performStackAnalysis(AstBuilder.java:2030)
        //     at com.strobel.decompiler.ast.AstBuilder.build(AstBuilder.java:108)
        //     at com.strobel.decompiler.languages.java.ast.AstMethodBodyBuilder.createMethodBody(AstMethodBodyBuilder.java:211)
        //     at com.strobel.decompiler.languages.java.ast.AstMethodBodyBuilder.createMethodBody(AstMethodBodyBuilder.java:99)
        //     at com.strobel.decompiler.languages.java.ast.AstBuilder.createMethodBody(AstBuilder.java:782)
        //     at com.strobel.decompiler.languages.java.ast.AstBuilder.createMethod(AstBuilder.java:675)
        //     at com.strobel.decompiler.languages.java.ast.AstBuilder.addTypeMembers(AstBuilder.java:552)
        //     at com.strobel.decompiler.languages.java.ast.AstBuilder.createTypeCore(AstBuilder.java:519)
        //     at com.strobel.decompiler.languages.java.ast.AstBuilder.createTypeNoCache(AstBuilder.java:161)
        //     at com.strobel.decompiler.languages.java.ast.AstBuilder.createType(AstBuilder.java:150)
        //     at com.strobel.decompiler.languages.java.ast.AstBuilder.addType(AstBuilder.java:125)
        //     at com.strobel.decompiler.languages.java.JavaLanguage.buildAst(JavaLanguage.java:71)
        //     at com.strobel.decompiler.languages.java.JavaLanguage.decompileType(JavaLanguage.java:59)
        //     at com.strobel.decompiler.DecompilerDriver.decompileType(DecompilerDriver.java:330)
        //     at com.strobel.decompiler.DecompilerDriver.decompileJar(DecompilerDriver.java:251)
        //     at com.strobel.decompiler.DecompilerDriver.main(DecompilerDriver.java:126)
        // 
        throw new IllegalStateException("An error occurred while decompiling this method.");
    }
}
