// 
// Decompiled by Procyon v0.5.36
// 

package dev.nuker.pyro;

import org.jetbrains.annotations.NotNull;

public class f4Q extends fH
{
    @NotNull
    public f0a c;
    
    static {
        throw t;
    }
    
    @NotNull
    public f0a c() {
        return fbS.t(this, 152823405);
    }
    
    public f4Q() {
        // 
        // This method could not be decompiled.
        // 
        // Original Bytecode:
        // 
        //     3: ifeq            11
        //     6: ldc             2045535476
        //     8: goto            13
        //    11: ldc             1124402322
        //    13: ldc             1234829457
        //    15: ixor           
        //    16: lookupswitch {
        //          194495031: 11
        //          813065317: 230
        //          default: 44
        //        }
        //    44: aload_0        
        //    45: ldc             "\u238e\u149d\u8a8a\ub3d0\uc9c6\ued86\ub230\ue6a0"
        //    47: invokestatic    invokestatic   !!! ERROR
        //    50: ldc             "\u23ae\u149d\u8a8a\ub3d0\uc9e6\ued86\ub230\ue6a0"
        //    52: invokestatic    invokestatic   !!! ERROR
        //    55: ldc             "\u23ae\u1487\u8a8a\ub3dc\uc9c9\ued99\ub230\ue6a0\ud928\ue9a3\ua746\u1e0c\ue185\uc5a2\u813d\u891d\u57b2\u7773\ubd7d\uc009\u2b72\uc22f\u6a6d\u2d16\ud7da\u35e4\u7d6b\u89d5\u8008\u8c80\u84c6\ufb2a\u70a4\u9a1a\u1bcd\uf105\u4975\u881c\uca83\uff30\ub6bb\u41f6\ub99f\ub308\u4c61\u8a9f\u7c7b\uce40\u7d4b\uead7\ue6a4"
        //    57: invokestatic    invokestatic   !!! ERROR
        //    60: invokespecial   dev/nuker/pyro/fH.<init>:(Ljava/lang/String;Ljava/lang/String;Ljava/lang/String;)V
        //    63: aload_0        
        //    64: aload_0        
        //    65: new             Ldev/nuker/pyro/f0a;
        //    68: dup            
        //    69: ldc             "\u2388\u1484\u8a9b\ub3d7"
        //    71: invokestatic    invokestatic   !!! ERROR
        //    74: ldc             "\u23a8\u1484\u8a9b\ub3d7"
        //    76: invokestatic    invokestatic   !!! ERROR
        //    79: ldc             "\u23bb\u1481\u8a97\ub3dc\uc9d7\uedc9\ub230\ue6bc\ud928\ue9a5\ua74c\u1e41\ue198\uc5b1\u8135\u8952\u57a6\u7779\ubd29\uc018\u2b3d\uc234\u6a70\u2d16\ud7c1\u35e2\u7d2e\u899d\u8036\u8ca7\u84ea\ufb1c\u70e1\u9a17\u1b8c\uf11c\u4975\u8811\uca8e\uff25\ub6b6\u41e7\ub9c7\ub300\u4c5f\u8a93\u7c67\uce53\u7d5e\ueac9\ue6b2\u16c0\uee6c"
        //    81: getstatic       dev/nuker/pyro/fc.c:I
        //    84: ifge            92
        //    87: ldc             -1219015717
        //    89: goto            94
        //    92: ldc             1823507452
        //    94: ldc             -1734424789
        //    96: ixor           
        //    97: lookupswitch {
        //          -198294313: 124
        //          801737968: 92
        //          default: 232
        //        }
        //   124: invokestatic    invokestatic   !!! ERROR
        //   127: iconst_1       
        //   128: getstatic       dev/nuker/pyro/fc.1:I
        //   131: ifeq            139
        //   134: ldc             1776660461
        //   136: goto            141
        //   139: ldc             -757781383
        //   141: ldc             -501340937
        //   143: ixor           
        //   144: lookupswitch {
        //          -1946449126: 139
        //          818612366: 172
        //          default: 236
        //        }
        //   172: invokespecial   dev/nuker/pyro/f0a.<init>:(Ljava/lang/String;Ljava/lang/String;Ljava/lang/String;Z)V
        //   175: checkcast       Ldev/nuker/pyro/f0n;
        //   178: getstatic       dev/nuker/pyro/fc.c:I
        //   181: ifge            189
        //   184: ldc             -189126697
        //   186: goto            191
        //   189: ldc             -1686535955
        //   191: ldc             -1118876086
        //   193: ixor           
        //   194: lookupswitch {
        //          641126055: 220
        //          1240820125: 189
        //          default: 234
        //        }
        //   220: invokevirtual   dev/nuker/pyro/f4Q.c:(Ldev/nuker/pyro/f0n;)Ldev/nuker/pyro/f0n;
        //   223: checkcast       Ldev/nuker/pyro/f0a;
        //   226: putfield        dev/nuker/pyro/f4Q.c:Ldev/nuker/pyro/f0a;
        //   229: return         
        //   230: aconst_null    
        //   231: athrow         
        //   232: aconst_null    
        //   233: athrow         
        //   234: aconst_null    
        //   235: athrow         
        //   236: aconst_null    
        //   237: athrow         
        //    StackMapTable: 00 10 0B 41 01 1E FF 00 2F 00 01 07 00 03 00 07 07 00 03 07 00 03 08 00 41 08 00 41 07 00 4D 07 00 4D 07 00 4D FF 00 01 00 01 07 00 03 00 08 07 00 03 07 00 03 08 00 41 08 00 41 07 00 4D 07 00 4D 07 00 4D 01 FF 00 1D 00 01 07 00 03 00 07 07 00 03 07 00 03 08 00 41 08 00 41 07 00 4D 07 00 4D 07 00 4D FF 00 0E 00 01 07 00 03 00 08 07 00 03 07 00 03 08 00 41 08 00 41 07 00 4D 07 00 4D 07 00 4D 01 FF 00 01 00 01 07 00 03 00 09 07 00 03 07 00 03 08 00 41 08 00 41 07 00 4D 07 00 4D 07 00 4D 01 01 FF 00 1E 00 01 07 00 03 00 08 07 00 03 07 00 03 08 00 41 08 00 41 07 00 4D 07 00 4D 07 00 4D 01 FF 00 10 00 01 07 00 03 00 03 07 00 03 07 00 03 07 00 43 FF 00 01 00 01 07 00 03 00 04 07 00 03 07 00 03 07 00 43 01 FF 00 1C 00 01 07 00 03 00 03 07 00 03 07 00 03 07 00 43 FF 00 09 00 01 06 00 00 FF 00 01 00 01 07 00 03 00 07 07 00 03 07 00 03 08 00 41 08 00 41 07 00 4D 07 00 4D 07 00 4D FF 00 01 00 01 07 00 03 00 03 07 00 03 07 00 03 07 00 43 FF 00 01 00 01 07 00 03 00 08 07 00 03 07 00 03 08 00 41 08 00 41 07 00 4D 07 00 4D 07 00 4D 01
        // 
        // The error that occurred was:
        // 
        // java.lang.IllegalStateException: Invalid BootstrapMethods attribute entry: 21 additional arguments required for method a.a, but only 0 specified.
        //     at com.strobel.assembler.ir.Error.invalidBootstrapMethodEntry(Error.java:244)
        //     at com.strobel.assembler.ir.MetadataReader.readAttributeCore(MetadataReader.java:280)
        //     at com.strobel.assembler.metadata.ClassFileReader.readAttributeCore(ClassFileReader.java:261)
        //     at com.strobel.assembler.ir.MetadataReader.inflateAttributes(MetadataReader.java:439)
        //     at com.strobel.assembler.metadata.ClassFileReader.visitAttributes(ClassFileReader.java:1134)
        //     at com.strobel.assembler.metadata.ClassFileReader.readClass(ClassFileReader.java:439)
        //     at com.strobel.assembler.metadata.ClassFileReader.readClass(ClassFileReader.java:377)
        //     at com.strobel.assembler.metadata.MetadataSystem.resolveType(MetadataSystem.java:129)
        //     at com.strobel.decompiler.NoRetryMetadataSystem.resolveType(DecompilerDriver.java:476)
        //     at com.strobel.assembler.metadata.MetadataSystem.resolveCore(MetadataSystem.java:81)
        //     at com.strobel.assembler.metadata.MetadataResolver.resolve(MetadataResolver.java:104)
        //     at com.strobel.assembler.metadata.CoreMetadataFactory$UnresolvedType.resolve(CoreMetadataFactory.java:616)
        //     at com.strobel.assembler.metadata.MetadataResolver.resolve(MetadataResolver.java:128)
        //     at com.strobel.assembler.metadata.CoreMetadataFactory$UnresolvedType.resolve(CoreMetadataFactory.java:626)
        //     at com.strobel.assembler.metadata.MethodReference.resolve(MethodReference.java:177)
        //     at com.strobel.decompiler.ast.TypeAnalysis.inferCall(TypeAnalysis.java:2438)
        //     at com.strobel.decompiler.ast.TypeAnalysis.doInferTypeForExpression(TypeAnalysis.java:1029)
        //     at com.strobel.decompiler.ast.TypeAnalysis.inferTypeForExpression(TypeAnalysis.java:803)
        //     at com.strobel.decompiler.ast.TypeAnalysis.inferCall(TypeAnalysis.java:2695)
        //     at com.strobel.decompiler.ast.TypeAnalysis.doInferTypeForExpression(TypeAnalysis.java:1029)
        //     at com.strobel.decompiler.ast.TypeAnalysis.inferTypeForExpression(TypeAnalysis.java:803)
        //     at com.strobel.decompiler.ast.TypeAnalysis.runInference(TypeAnalysis.java:672)
        //     at com.strobel.decompiler.ast.TypeAnalysis.runInference(TypeAnalysis.java:655)
        //     at com.strobel.decompiler.ast.TypeAnalysis.runInference(TypeAnalysis.java:365)
        //     at com.strobel.decompiler.ast.TypeAnalysis.run(TypeAnalysis.java:96)
        //     at com.strobel.decompiler.ast.AstOptimizer.optimize(AstOptimizer.java:109)
        //     at com.strobel.decompiler.ast.AstOptimizer.optimize(AstOptimizer.java:42)
        //     at com.strobel.decompiler.languages.java.ast.AstMethodBodyBuilder.createMethodBody(AstMethodBodyBuilder.java:214)
        //     at com.strobel.decompiler.languages.java.ast.AstMethodBodyBuilder.createMethodBody(AstMethodBodyBuilder.java:99)
        //     at com.strobel.decompiler.languages.java.ast.AstBuilder.createMethodBody(AstBuilder.java:782)
        //     at com.strobel.decompiler.languages.java.ast.AstBuilder.createConstructor(AstBuilder.java:713)
        //     at com.strobel.decompiler.languages.java.ast.AstBuilder.addTypeMembers(AstBuilder.java:549)
        //     at com.strobel.decompiler.languages.java.ast.AstBuilder.createTypeCore(AstBuilder.java:519)
        //     at com.strobel.decompiler.languages.java.ast.AstBuilder.createTypeNoCache(AstBuilder.java:161)
        //     at com.strobel.decompiler.languages.java.ast.AstBuilder.createType(AstBuilder.java:150)
        //     at com.strobel.decompiler.languages.java.ast.AstBuilder.addType(AstBuilder.java:125)
        //     at com.strobel.decompiler.languages.java.JavaLanguage.buildAst(JavaLanguage.java:71)
        //     at com.strobel.decompiler.languages.java.JavaLanguage.decompileType(JavaLanguage.java:59)
        //     at com.strobel.decompiler.DecompilerDriver.decompileType(DecompilerDriver.java:330)
        //     at com.strobel.decompiler.DecompilerDriver.decompileJar(DecompilerDriver.java:251)
        //     at com.strobel.decompiler.DecompilerDriver.main(DecompilerDriver.java:126)
        // 
        throw new IllegalStateException("An error occurred while decompiling this method.");
    }
    
    @f06
    public void c(@NotNull final f34 p0) {
        // 
        // This method could not be decompiled.
        // 
        // Original Bytecode:
        // 
        //     3: dup            
        //     4: ifnull          1166
        //     7: athrow         
        //     8: aconst_null    
        //     9: getstatic       dev/nuker/pyro/fc.1:I
        //    12: ifgt            1158
        //    15: pop            
        //    16: aconst_null    
        //    17: goto            1150
        //    20: nop            
        //    21: nop            
        //    22: nop            
        //    23: athrow         
        //    24: aload_1        
        //    25: pop            
        //    26: aload_1        
        //    27: goto            31
        //    30: athrow         
        //    31: invokevirtual   dev/nuker/pyro/f34.c:()Ldev/nuker/pyro/f2T;
        //    34: goto            38
        //    37: athrow         
        //    38: getstatic       dev/nuker/pyro/f2T.c:Ldev/nuker/pyro/f2T;
        //    41: if_acmpne       1110
        //    44: aload_0        
        //    45: getfield        dev/nuker/pyro/f4Q.c:Ldev/nuker/pyro/f0a;
        //    48: getstatic       dev/nuker/pyro/fc.c:I
        //    51: ifge            59
        //    54: ldc             -201601679
        //    56: goto            61
        //    59: ldc             7452396
        //    61: ldc             796759739
        //    63: ixor           
        //    64: lookupswitch {
        //          -2046850812: 59
        //          -595174454: 1139
        //          default: 92
        //        }
        //    92: goto            96
        //    95: athrow         
        //    96: invokevirtual   dev/nuker/pyro/f0a.3:()Ljava/lang/Object;
        //    99: goto            103
        //   102: athrow         
        //   103: checkcast       Ljava/lang/Boolean;
        //   106: goto            110
        //   109: athrow         
        //   110: invokevirtual   java/lang/Boolean.booleanValue:()Z
        //   113: goto            117
        //   116: athrow         
        //   117: ifeq            1110
        //   120: aload_1        
        //   121: getstatic       dev/nuker/pyro/fc.c:I
        //   124: ifge            132
        //   127: ldc             -1688693541
        //   129: goto            134
        //   132: ldc             1388020054
        //   134: ldc             1464874695
        //   136: ixor           
        //   137: lookupswitch {
        //          -871849444: 132
        //          99334033: 164
        //          default: 1123
        //        }
        //   164: goto            168
        //   167: athrow         
        //   168: invokevirtual   dev/nuker/pyro/f34.c:()Lnet/minecraft/network/Packet;
        //   171: goto            175
        //   174: athrow         
        //   175: instanceof      Lnet/minecraft/network/play/server/SPacketSpawnPlayer;
        //   178: ifeq            1110
        //   181: aload_1        
        //   182: getstatic       dev/nuker/pyro/fc.1:I
        //   185: ifeq            193
        //   188: ldc             -1777427244
        //   190: goto            195
        //   193: ldc             1386183994
        //   195: ldc             -1659691527
        //   197: ixor           
        //   198: lookupswitch {
        //          -812883773: 224
        //          186482989: 193
        //          default: 1131
        //        }
        //   224: goto            228
        //   227: athrow         
        //   228: invokevirtual   dev/nuker/pyro/f34.c:()Lnet/minecraft/network/Packet;
        //   231: goto            235
        //   234: athrow         
        //   235: dup            
        //   236: ifnonnull       268
        //   239: new             Lkotlin/TypeCastException;
        //   242: dup            
        //   243: ldc             "\u2381\u1486\u8a92\ub1c4\ucfb3\ued8a\ub225\ue6bd\udb77\uef8f\ua75d\u1e0c\ue195\uc7b3\u8747\u8911\u57a5\u7765\ubf38\uc67c\u2b69\uc234\u6a3e\u2f49\ud1ed\u35e4\u7d66\u89d3\u8215\u8aab\u84c3\ufb72\u70b5\u981e\u1da5\uf10d\u493c\u881c\uc892\uf903\ub6f9\u41fe\ub98e\ub157\u4a40\u8a99\u7c7b\uce57\u7f59\uece6\ue6f9\u16d6\uee20\u358b\u408d\ue19c\u0a05\u86a9\u1b8a\u0962\u777e\u728c\uc780\ub9e5\u9cfe\u6a7f\ue2f4\ud051\ua739\u23ef\u8997\u4f92\u8b32\u1618\ua5e7\u70ae\u55a3\u1c04\u63ed\u17ba\u8817\u0521\uf8bc\u2451\u1f29\ub982\u7ce1\u4be5\u185e"
        //   245: goto            249
        //   248: athrow         
        //   249: invokestatic    invokestatic   !!! ERROR
        //   252: goto            256
        //   255: athrow         
        //   256: goto            260
        //   259: athrow         
        //   260: invokespecial   kotlin/TypeCastException.<init>:(Ljava/lang/String;)V
        //   263: goto            267
        //   266: athrow         
        //   267: athrow         
        //   268: checkcast       Lnet/minecraft/network/play/server/SPacketSpawnPlayer;
        //   271: astore_2       
        //   272: aload_2        
        //   273: goto            277
        //   276: athrow         
        //   277: invokevirtual   net/minecraft/network/play/server/SPacketSpawnPlayer.func_186898_d:()D
        //   280: goto            284
        //   283: athrow         
        //   284: ldc2_w          32.0
        //   287: ddiv           
        //   288: getstatic       dev/nuker/pyro/fc.1:I
        //   291: ifeq            299
        //   294: ldc             776685058
        //   296: goto            301
        //   299: ldc             -1340107492
        //   301: ldc             1370169246
        //   303: ixor           
        //   304: lookupswitch {
        //          -508261758: 332
        //          2145409436: 299
        //          default: 1117
        //        }
        //   332: dstore_3       
        //   333: aload_2        
        //   334: goto            338
        //   337: athrow         
        //   338: invokevirtual   net/minecraft/network/play/server/SPacketSpawnPlayer.func_186897_e:()D
        //   341: goto            345
        //   344: athrow         
        //   345: ldc2_w          32.0
        //   348: ddiv           
        //   349: getstatic       dev/nuker/pyro/fc.0:I
        //   352: ifeq            360
        //   355: ldc             -1809523746
        //   357: goto            362
        //   360: ldc             1310768550
        //   362: ldc             1890938676
        //   364: ixor           
        //   365: lookupswitch {
        //          -460213014: 1121
        //          696726080: 360
        //          default: 392
        //        }
        //   392: dstore          5
        //   394: aload_2        
        //   395: goto            399
        //   398: athrow         
        //   399: invokevirtual   net/minecraft/network/play/server/SPacketSpawnPlayer.func_186899_f:()D
        //   402: goto            406
        //   405: athrow         
        //   406: ldc2_w          32.0
        //   409: ddiv           
        //   410: dstore          7
        //   412: aload_0        
        //   413: getfield        dev/nuker/pyro/f4Q.c:Lnet/minecraft/client/Minecraft;
        //   416: getfield        net/minecraft/client/Minecraft.field_71439_g:Lnet/minecraft/client/entity/EntityPlayerSP;
        //   419: getfield        net/minecraft/client/entity/EntityPlayerSP.field_70165_t:D
        //   422: dload_3        
        //   423: dsub           
        //   424: dstore          9
        //   426: aload_0        
        //   427: getfield        dev/nuker/pyro/f4Q.c:Lnet/minecraft/client/Minecraft;
        //   430: getfield        net/minecraft/client/Minecraft.field_71439_g:Lnet/minecraft/client/entity/EntityPlayerSP;
        //   433: getfield        net/minecraft/client/entity/EntityPlayerSP.field_70163_u:D
        //   436: dload           5
        //   438: dsub           
        //   439: getstatic       dev/nuker/pyro/fc.0:I
        //   442: ifeq            450
        //   445: ldc             -1412147565
        //   447: goto            452
        //   450: ldc             -1618136287
        //   452: ldc             -212154253
        //   454: ixor           
        //   455: lookupswitch {
        //          1485741792: 450
        //          1826093906: 480
        //          default: 1111
        //        }
        //   480: dstore          11
        //   482: getstatic       dev/nuker/pyro/fc.1:I
        //   485: ifeq            493
        //   488: ldc             358025408
        //   490: goto            495
        //   493: ldc             1658454474
        //   495: ldc             302262213
        //   497: ixor           
        //   498: lookupswitch {
        //          -255206597: 493
        //          122892037: 1119
        //          default: 524
        //        }
        //   524: aload_0        
        //   525: getfield        dev/nuker/pyro/f4Q.c:Lnet/minecraft/client/Minecraft;
        //   528: getfield        net/minecraft/client/Minecraft.field_71439_g:Lnet/minecraft/client/entity/EntityPlayerSP;
        //   531: getfield        net/minecraft/client/entity/EntityPlayerSP.field_70161_v:D
        //   534: dload           7
        //   536: dsub           
        //   537: dstore          13
        //   539: dload           9
        //   541: getstatic       dev/nuker/pyro/fc.0:I
        //   544: ifeq            552
        //   547: ldc             258721254
        //   549: goto            554
        //   552: ldc             -1070865744
        //   554: ldc             1190188738
        //   556: ixor           
        //   557: lookupswitch {
        //          -1255208556: 552
        //          1234899748: 1133
        //          default: 584
        //        }
        //   584: dload           9
        //   586: dmul           
        //   587: dload           11
        //   589: dload           11
        //   591: dmul           
        //   592: dadd           
        //   593: dload           13
        //   595: dload           13
        //   597: dmul           
        //   598: dadd           
        //   599: dstore          17
        //   601: iconst_0       
        //   602: istore          19
        //   604: dload           17
        //   606: goto            610
        //   609: athrow         
        //   610: invokestatic    java/lang/Math.sqrt:(D)D
        //   613: goto            617
        //   616: athrow         
        //   617: dstore          15
        //   619: dload           15
        //   621: bipush          17
        //   623: i2d            
        //   624: dcmpg          
        //   625: ifgt            633
        //   628: ldc             -1746037725
        //   630: goto            635
        //   633: ldc             -1746037728
        //   635: ldc             1357953902
        //   637: ixor           
        //   638: tableswitch {
        //          -1908777318: 660
        //          -1908777317: 1110
        //          default: 628
        //        }
        //   660: dload_3        
        //   661: aload_0        
        //   662: getfield        dev/nuker/pyro/f4Q.c:Lnet/minecraft/client/Minecraft;
        //   665: getfield        net/minecraft/client/Minecraft.field_71439_g:Lnet/minecraft/client/entity/EntityPlayerSP;
        //   668: getfield        net/minecraft/client/entity/EntityPlayerSP.field_70165_t:D
        //   671: dcmpg          
        //   672: ifeq            680
        //   675: ldc             -811157063
        //   677: goto            682
        //   680: ldc             -811157064
        //   682: ldc             -881910261
        //   684: ixor           
        //   685: tableswitch {
        //          160649060: 708
        //          160649061: 1110
        //          default: 675
        //        }
        //   708: getstatic       dev/nuker/pyro/fc.c:I
        //   711: ifge            719
        //   714: ldc             -557704852
        //   716: goto            721
        //   719: ldc             -896611465
        //   721: ldc             2024742352
        //   723: ixor           
        //   724: lookupswitch {
        //          -1502804804: 719
        //          -1306405209: 752
        //          default: 1125
        //        }
        //   752: dload           5
        //   754: getstatic       dev/nuker/pyro/fc.1:I
        //   757: ifeq            765
        //   760: ldc             -187548288
        //   762: goto            767
        //   765: ldc             1047998403
        //   767: ldc             -1740481701
        //   769: ixor           
        //   770: lookupswitch {
        //          -1506446184: 796
        //          1821402843: 765
        //          default: 1137
        //        }
        //   796: aload_0        
        //   797: getfield        dev/nuker/pyro/f4Q.c:Lnet/minecraft/client/Minecraft;
        //   800: getfield        net/minecraft/client/Minecraft.field_71439_g:Lnet/minecraft/client/entity/EntityPlayerSP;
        //   803: getstatic       dev/nuker/pyro/fc.1:I
        //   806: ifeq            814
        //   809: ldc             46759237
        //   811: goto            816
        //   814: ldc             1682120764
        //   816: ldc             884785578
        //   818: ixor           
        //   819: lookupswitch {
        //          913685743: 814
        //          1358946710: 844
        //          default: 1135
        //        }
        //   844: getfield        net/minecraft/client/entity/EntityPlayerSP.field_70163_u:D
        //   847: dcmpg          
        //   848: ifeq            856
        //   851: ldc             1068294123
        //   853: goto            858
        //   856: ldc             1068294122
        //   858: ldc             1827475159
        //   860: ixor           
        //   861: tableswitch {
        //          -1501322632: 884
        //          -1501322631: 1110
        //          default: 851
        //        }
        //   884: getstatic       dev/nuker/pyro/fc.1:I
        //   887: ifeq            895
        //   890: ldc             878630873
        //   892: goto            897
        //   895: ldc             516926489
        //   897: ldc             -1737714162
        //   899: ixor           
        //   900: lookupswitch {
        //          -1405992489: 1115
        //          1900772390: 895
        //          default: 928
        //        }
        //   928: dload           7
        //   930: getstatic       dev/nuker/pyro/fc.0:I
        //   933: ifeq            941
        //   936: ldc             518628275
        //   938: goto            943
        //   941: ldc             -451170436
        //   943: ldc             412815994
        //   945: ixor           
        //   946: lookupswitch {
        //          108179913: 1113
        //          1121902727: 941
        //          default: 972
        //        }
        //   972: aload_0        
        //   973: getfield        dev/nuker/pyro/f4Q.c:Lnet/minecraft/client/Minecraft;
        //   976: getstatic       dev/nuker/pyro/fc.c:I
        //   979: ifge            987
        //   982: ldc             1933431257
        //   984: goto            989
        //   987: ldc             105505233
        //   989: ldc             -334908603
        //   991: ixor           
        //   992: lookupswitch {
        //          -1623956836: 987
        //          -364883308: 1020
        //          default: 1129
        //        }
        //  1020: getfield        net/minecraft/client/Minecraft.field_71439_g:Lnet/minecraft/client/entity/EntityPlayerSP;
        //  1023: getfield        net/minecraft/client/entity/EntityPlayerSP.field_70161_v:D
        //  1026: dcmpg          
        //  1027: ifeq            1110
        //  1030: getstatic       dev/nuker/pyro/Pyro.INSTANCE:Ldev/nuker/pyro/Pyro;
        //  1033: ldc             "\u23bd\u1496\u8a93\ub1c7\ucfe5\ued8c\ub220\ue6f3\udb78\uefc0\ua74b\u1e43\ue183\uc7f8\u8747\u8929\u5783\u7741\ubf09\uc612\u2b40"
        //  1035: getstatic       dev/nuker/pyro/fc.0:I
        //  1038: ifeq            1046
        //  1041: ldc             -1593239494
        //  1043: goto            1048
        //  1046: ldc             -1082067218
        //  1048: ldc             -466245203
        //  1050: ixor           
        //  1051: lookupswitch {
        //          1161605527: 1046
        //          1538613059: 1076
        //          default: 1127
        //        }
        //  1076: goto            1080
        //  1079: athrow         
        //  1080: invokestatic    invokestatic   !!! ERROR
        //  1083: goto            1087
        //  1086: athrow         
        //  1087: goto            1091
        //  1090: athrow         
        //  1091: invokevirtual   dev/nuker/pyro/Pyro.sendMessage:(Ljava/lang/String;)V
        //  1094: goto            1098
        //  1097: athrow         
        //  1098: aload_1        
        //  1099: goto            1103
        //  1102: athrow         
        //  1103: invokevirtual   dev/nuker/pyro/f34.c:()V
        //  1106: goto            1110
        //  1109: athrow         
        //  1110: return         
        //  1111: aconst_null    
        //  1112: athrow         
        //  1113: aconst_null    
        //  1114: athrow         
        //  1115: aconst_null    
        //  1116: athrow         
        //  1117: aconst_null    
        //  1118: athrow         
        //  1119: aconst_null    
        //  1120: athrow         
        //  1121: aconst_null    
        //  1122: athrow         
        //  1123: aconst_null    
        //  1124: athrow         
        //  1125: aconst_null    
        //  1126: athrow         
        //  1127: aconst_null    
        //  1128: athrow         
        //  1129: aconst_null    
        //  1130: athrow         
        //  1131: aconst_null    
        //  1132: athrow         
        //  1133: aconst_null    
        //  1134: athrow         
        //  1135: aconst_null    
        //  1136: athrow         
        //  1137: aconst_null    
        //  1138: athrow         
        //  1139: aconst_null    
        //  1140: athrow         
        //  1141: pop            
        //  1142: goto            24
        //  1145: pop            
        //  1146: aconst_null    
        //  1147: goto            1141
        //  1150: dup            
        //  1151: ifnull          1141
        //  1154: checkcast       Ljava/lang/Throwable;
        //  1157: athrow         
        //  1158: dup            
        //  1159: ifnull          1145
        //  1162: checkcast       Ljava/lang/Throwable;
        //  1165: athrow         
        //  1166: aconst_null    
        //  1167: athrow         
        //    StackMapTable: 00 8A 43 07 00 6F 04 FF 00 0B 00 00 00 01 07 00 6F FD 00 03 07 00 03 07 00 71 45 07 00 53 40 07 00 71 45 07 00 6F 40 07 00 76 54 07 00 2D FF 00 01 00 02 07 00 03 07 00 71 00 02 07 00 2D 01 5E 07 00 2D 42 07 00 5B 40 07 00 2D 45 07 00 6F 40 07 00 FB 45 07 00 53 40 07 00 82 45 07 00 6F 40 01 4E 07 00 71 FF 00 01 00 02 07 00 03 07 00 71 00 02 07 00 71 01 5D 07 00 71 42 07 00 61 40 07 00 71 45 07 00 6F 40 07 00 FD 51 07 00 71 FF 00 01 00 02 07 00 03 07 00 71 00 02 07 00 71 01 5C 07 00 71 42 07 00 6F 40 07 00 71 45 07 00 6F 40 07 00 FD 4C 07 00 6F FF 00 00 00 02 07 00 03 07 00 71 00 04 07 00 FD 08 00 EF 08 00 EF 07 00 4D 45 07 00 6F FF 00 00 00 02 07 00 03 07 00 71 00 04 07 00 FD 08 00 EF 08 00 EF 07 00 4D 42 07 00 65 FF 00 00 00 02 07 00 03 07 00 71 00 04 07 00 FD 08 00 EF 08 00 EF 07 00 4D 45 07 00 6F FF 00 00 00 02 07 00 03 07 00 71 00 02 07 00 FD 07 00 93 40 07 00 FD FF 00 07 00 03 07 00 03 07 00 71 07 00 8E 00 01 07 00 6F 40 07 00 8E 45 07 00 6F 40 03 4E 03 FF 00 01 00 03 07 00 03 07 00 71 07 00 8E 00 02 03 01 5E 03 FF 00 04 00 00 00 01 07 00 6F FF 00 00 00 04 07 00 03 07 00 71 07 00 8E 03 00 01 07 00 8E 45 07 00 6F 40 03 4E 03 FF 00 01 00 04 07 00 03 07 00 71 07 00 8E 03 00 02 03 01 5D 03 FF 00 05 00 00 00 01 07 00 6F FF 00 00 00 05 07 00 03 07 00 71 07 00 8E 03 03 00 01 07 00 8E 45 07 00 6F 40 03 FF 00 2B 00 07 07 00 03 07 00 71 07 00 8E 03 03 03 03 00 01 03 FF 00 01 00 07 07 00 03 07 00 71 07 00 8E 03 03 03 03 00 02 03 01 5B 03 FC 00 0C 03 41 01 1C FF 00 1B 00 09 07 00 03 07 00 71 07 00 8E 03 03 03 03 03 03 00 01 03 FF 00 01 00 09 07 00 03 07 00 71 07 00 8E 03 03 03 03 03 03 00 02 03 01 5D 03 FF 00 18 00 0D 07 00 03 07 00 71 07 00 8E 03 03 03 03 03 03 00 00 03 01 00 01 07 00 6F 40 03 45 07 00 6F 40 03 FF 00 0A 00 0C 07 00 03 07 00 71 07 00 8E 03 03 03 03 03 03 03 03 01 00 00 04 41 01 18 0E 04 41 01 19 0A 41 01 1E 4C 03 FF 00 01 00 0C 07 00 03 07 00 71 07 00 8E 03 03 03 03 03 03 03 03 01 00 02 03 01 5C 03 FF 00 11 00 0C 07 00 03 07 00 71 07 00 8E 03 03 03 03 03 03 03 03 01 00 02 03 07 00 B5 FF 00 01 00 0C 07 00 03 07 00 71 07 00 8E 03 03 03 03 03 03 03 03 01 00 03 03 07 00 B5 01 FF 00 1B 00 0C 07 00 03 07 00 71 07 00 8E 03 03 03 03 03 03 03 03 01 00 02 03 07 00 B5 06 04 41 01 19 0A 41 01 1E 4C 03 FF 00 01 00 0C 07 00 03 07 00 71 07 00 8E 03 03 03 03 03 03 03 03 01 00 02 03 01 5C 03 FF 00 0E 00 0C 07 00 03 07 00 71 07 00 8E 03 03 03 03 03 03 03 03 01 00 02 03 07 00 AF FF 00 01 00 0C 07 00 03 07 00 71 07 00 8E 03 03 03 03 03 03 03 03 01 00 03 03 07 00 AF 01 FF 00 1E 00 0C 07 00 03 07 00 71 07 00 8E 03 03 03 03 03 03 03 03 01 00 02 03 07 00 AF FF 00 19 00 0C 07 00 03 07 00 71 07 00 8E 03 03 03 03 03 03 03 03 01 00 02 07 00 EB 07 00 4D FF 00 01 00 0C 07 00 03 07 00 71 07 00 8E 03 03 03 03 03 03 03 03 01 00 03 07 00 EB 07 00 4D 01 FF 00 1B 00 0C 07 00 03 07 00 71 07 00 8E 03 03 03 03 03 03 03 03 01 00 02 07 00 EB 07 00 4D 42 07 00 6F FF 00 00 00 0C 07 00 03 07 00 71 07 00 8E 03 03 03 03 03 03 03 03 01 00 02 07 00 EB 07 00 4D 45 07 00 6F FF 00 00 00 0C 07 00 03 07 00 71 07 00 8E 03 03 03 03 03 03 03 03 01 00 02 07 00 EB 07 00 4D FF 00 02 00 00 00 01 07 00 6F FF 00 00 00 0C 07 00 03 07 00 71 07 00 8E 03 03 03 03 03 03 03 03 01 00 02 07 00 EB 07 00 4D 45 07 00 6F 00 43 07 00 67 40 07 00 71 45 07 00 6F FF 00 00 00 02 07 00 03 07 00 71 00 00 FF 00 00 00 07 07 00 03 07 00 71 07 00 8E 03 03 03 03 00 01 03 FF 00 01 00 0C 07 00 03 07 00 71 07 00 8E 03 03 03 03 03 03 03 03 01 00 01 03 01 FF 00 01 00 03 07 00 03 07 00 71 07 00 8E 00 01 03 FF 00 01 00 08 07 00 03 07 00 71 07 00 8E 03 03 03 03 03 00 00 FF 00 01 00 04 07 00 03 07 00 71 07 00 8E 03 00 01 03 FF 00 01 00 02 07 00 03 07 00 71 00 01 07 00 71 FF 00 01 00 0C 07 00 03 07 00 71 07 00 8E 03 03 03 03 03 03 03 03 01 00 00 FF 00 01 00 0C 07 00 03 07 00 71 07 00 8E 03 03 03 03 03 03 03 03 01 00 02 07 00 EB 07 00 4D FF 00 01 00 0C 07 00 03 07 00 71 07 00 8E 03 03 03 03 03 03 03 03 01 00 02 03 07 00 AF FF 00 01 00 02 07 00 03 07 00 71 00 01 07 00 71 FF 00 01 00 09 07 00 03 07 00 71 07 00 8E 03 03 03 03 03 03 00 01 03 FF 00 01 00 0C 07 00 03 07 00 71 07 00 8E 03 03 03 03 03 03 03 03 01 00 02 03 07 00 B5 41 03 FF 00 01 00 02 07 00 03 07 00 71 00 01 07 00 2D 41 07 00 6F 43 05 44 07 00 6F 47 05 47 07 00 6F
        //    Exceptions:
        //  Try           Handler
        //  Start  End    Start  End    Type                                       
        //  -----  -----  -----  -----  -------------------------------------------
        //  8      20     1150   1158   Any
        //  1150   1158   1150   1158   Any
        //  1166   1168   3      8      Ljava/lang/RuntimeException;
        //  30     37     37     38     Any
        //  31     37     3      8      Any
        //  31     37     30     31     Ljava/lang/NullPointerException;
        //  30     37     3      8      Ljava/lang/NegativeArraySizeException;
        //  31     37     37     38     Ljava/lang/ClassCastException;
        //  95     102    102    103    Any
        //  96     102    3      8      Ljava/lang/UnsupportedOperationException;
        //  96     102    95     96     Ljava/lang/IllegalStateException;
        //  95     102    102    103    Ljava/lang/IllegalStateException;
        //  95     102    102    103    Ljava/lang/NegativeArraySizeException;
        //  109    116    116    117    Any
        //  109    116    3      8      Ljava/lang/AssertionError;
        //  109    116    3      8      Ljava/lang/ArrayIndexOutOfBoundsException;
        //  109    116    116    117    Any
        //  110    116    109    110    Ljava/lang/NullPointerException;
        //  167    174    174    175    Any
        //  167    174    167    168    Ljava/lang/StringIndexOutOfBoundsException;
        //  167    174    3      8      Ljava/lang/RuntimeException;
        //  167    174    3      8      Any
        //  168    174    174    175    Any
        //  227    234    234    235    Any
        //  228    234    227    228    Any
        //  228    234    3      8      Ljava/lang/UnsupportedOperationException;
        //  228    234    227    228    Any
        //  227    234    227    228    Any
        //  248    255    255    256    Any
        //  249    255    3      8      Ljava/lang/UnsupportedOperationException;
        //  249    255    248    249    Ljava/lang/StringIndexOutOfBoundsException;
        //  249    255    248    249    Any
        //  248    255    3      8      Ljava/lang/AssertionError;
        //  259    266    266    267    Any
        //  260    266    3      8      Ljava/util/NoSuchElementException;
        //  259    266    3      8      Any
        //  259    266    3      8      Ljava/lang/NegativeArraySizeException;
        //  260    266    259    260    Ljava/lang/NumberFormatException;
        //  276    283    283    284    Any
        //  277    283    3      8      Any
        //  276    283    276    277    Ljava/lang/ArithmeticException;
        //  277    283    276    277    Any
        //  276    283    3      8      Any
        //  338    344    344    345    Any
        //  338    344    3      8      Ljava/lang/UnsupportedOperationException;
        //  338    344    3      8      Ljava/lang/AssertionError;
        //  338    344    344    345    Ljava/lang/IndexOutOfBoundsException;
        //  338    344    344    345    Any
        //  399    405    405    406    Any
        //  399    405    405    406    Ljava/lang/IllegalStateException;
        //  399    405    405    406    Ljava/lang/NumberFormatException;
        //  399    405    405    406    Any
        //  399    405    3      8      Ljava/lang/StringIndexOutOfBoundsException;
        //  609    616    616    617    Any
        //  609    616    3      8      Ljava/lang/IllegalStateException;
        //  609    616    3      8      Any
        //  609    616    3      8      Any
        //  610    616    609    610    Any
        //  1079   1086   1086   1087   Any
        //  1080   1086   1086   1087   Ljava/lang/IllegalArgumentException;
        //  1080   1086   1079   1080   Any
        //  1079   1086   3      8      Ljava/lang/AssertionError;
        //  1079   1086   1086   1087   Ljava/lang/StringIndexOutOfBoundsException;
        //  1091   1097   1097   1098   Any
        //  1091   1097   3      8      Any
        //  1091   1097   3      8      Any
        //  1091   1097   3      8      Ljava/lang/EnumConstantNotPresentException;
        //  1091   1097   1097   1098   Any
        //  1102   1109   1109   1110   Any
        //  1102   1109   3      8      Any
        //  1103   1109   1109   1110   Ljava/lang/NumberFormatException;
        //  1103   1109   1102   1103   Ljava/lang/ArithmeticException;
        //  1103   1109   1109   1110   Ljava/lang/ClassCastException;
        // 
        // The error that occurred was:
        // 
        // java.lang.IndexOutOfBoundsException: Index -1 out of bounds for length 0
        //     at java.base/jdk.internal.util.Preconditions.outOfBounds(Preconditions.java:64)
        //     at java.base/jdk.internal.util.Preconditions.outOfBoundsCheckIndex(Preconditions.java:70)
        //     at java.base/jdk.internal.util.Preconditions.checkIndex(Preconditions.java:248)
        //     at java.base/java.util.Objects.checkIndex(Objects.java:372)
        //     at java.base/java.util.ArrayList.remove(ArrayList.java:535)
        //     at com.strobel.assembler.ir.StackMappingVisitor.pop(StackMappingVisitor.java:267)
        //     at com.strobel.assembler.ir.StackMappingVisitor$InstructionAnalyzer.execute(StackMappingVisitor.java:667)
        //     at com.strobel.assembler.ir.StackMappingVisitor$InstructionAnalyzer.visit(StackMappingVisitor.java:398)
        //     at com.strobel.decompiler.ast.AstBuilder.performStackAnalysis(AstBuilder.java:2030)
        //     at com.strobel.decompiler.ast.AstBuilder.build(AstBuilder.java:108)
        //     at com.strobel.decompiler.languages.java.ast.AstMethodBodyBuilder.createMethodBody(AstMethodBodyBuilder.java:211)
        //     at com.strobel.decompiler.languages.java.ast.AstMethodBodyBuilder.createMethodBody(AstMethodBodyBuilder.java:99)
        //     at com.strobel.decompiler.languages.java.ast.AstBuilder.createMethodBody(AstBuilder.java:782)
        //     at com.strobel.decompiler.languages.java.ast.AstBuilder.createMethod(AstBuilder.java:675)
        //     at com.strobel.decompiler.languages.java.ast.AstBuilder.addTypeMembers(AstBuilder.java:552)
        //     at com.strobel.decompiler.languages.java.ast.AstBuilder.createTypeCore(AstBuilder.java:519)
        //     at com.strobel.decompiler.languages.java.ast.AstBuilder.createTypeNoCache(AstBuilder.java:161)
        //     at com.strobel.decompiler.languages.java.ast.AstBuilder.createType(AstBuilder.java:150)
        //     at com.strobel.decompiler.languages.java.ast.AstBuilder.addType(AstBuilder.java:125)
        //     at com.strobel.decompiler.languages.java.JavaLanguage.buildAst(JavaLanguage.java:71)
        //     at com.strobel.decompiler.languages.java.JavaLanguage.decompileType(JavaLanguage.java:59)
        //     at com.strobel.decompiler.DecompilerDriver.decompileType(DecompilerDriver.java:330)
        //     at com.strobel.decompiler.DecompilerDriver.decompileJar(DecompilerDriver.java:251)
        //     at com.strobel.decompiler.DecompilerDriver.main(DecompilerDriver.java:126)
        // 
        throw new IllegalStateException("An error occurred while decompiling this method.");
    }
}
