// 
// Decompiled by Procyon v0.5.36
// 

package dev.nuker.pyro;

import net.minecraft.entity.Entity;
import dev.nuker.pyro.security.inject.LauncherEventHide;

public class f5i extends fH
{
    public f0f<f5h> c;
    
    @f06
    @LauncherEventHide
    public void c(final f37 p0) {
        // 
        // This method could not be decompiled.
        // 
        // Original Bytecode:
        // 
        //     3: dup            
        //     4: ifnull          2932
        //     7: athrow         
        //     8: aconst_null    
        //     9: getstatic       dev/nuker/pyro/fc.1:I
        //    12: ifgt            2924
        //    15: pop            
        //    16: aconst_null    
        //    17: goto            2916
        //    20: nop            
        //    21: nop            
        //    22: nop            
        //    23: athrow         
        //    24: aload_1        
        //    25: getstatic       dev/nuker/pyro/fc.c:I
        //    28: ifge            36
        //    31: ldc             -982643997
        //    33: goto            38
        //    36: ldc             -1261687192
        //    38: ldc             1155087582
        //    40: ixor           
        //    41: lookupswitch {
        //          -2118699459: 36
        //          -267054410: 68
        //          default: 2861
        //        }
        //    68: goto            72
        //    71: athrow         
        //    72: invokevirtual   dev/nuker/pyro/f37.c:()Ldev/nuker/pyro/f2T;
        //    75: goto            79
        //    78: athrow         
        //    79: getstatic       dev/nuker/pyro/f2T.0:Ldev/nuker/pyro/f2T;
        //    82: if_acmpne       187
        //    85: aload_0        
        //    86: getfield        dev/nuker/pyro/f5i.c:Lnet/minecraft/client/Minecraft;
        //    89: getfield        net/minecraft/client/Minecraft.field_71439_g:Lnet/minecraft/client/entity/EntityPlayerSP;
        //    92: getfield        net/minecraft/client/entity/EntityPlayerSP.field_70143_R:F
        //    95: ldc             1337.0
        //    97: fcmpl          
        //    98: ifne            106
        //   101: ldc             1598716858
        //   103: goto            108
        //   106: ldc             1598716861
        //   108: ldc             74651313
        //   110: ixor           
        //   111: tableswitch {
        //          -1233987050: 132
        //          -1233987049: 186
        //          default: 101
        //        }
        //   132: aload_0        
        //   133: getstatic       dev/nuker/pyro/fc.0:I
        //   136: ifeq            144
        //   139: ldc             -1752198345
        //   141: goto            146
        //   144: ldc             832227980
        //   146: ldc             -1088154747
        //   148: ixor           
        //   149: lookupswitch {
        //          -1209055606: 144
        //          682328242: 2877
        //          default: 176
        //        }
        //   176: getfield        dev/nuker/pyro/f5i.c:Lnet/minecraft/client/Minecraft;
        //   179: getfield        net/minecraft/client/Minecraft.field_71439_g:Lnet/minecraft/client/entity/EntityPlayerSP;
        //   182: fconst_0       
        //   183: putfield        net/minecraft/client/entity/EntityPlayerSP.field_70143_R:F
        //   186: return         
        //   187: aload_0        
        //   188: getfield        dev/nuker/pyro/f5i.c:Lnet/minecraft/client/Minecraft;
        //   191: getfield        net/minecraft/client/Minecraft.field_71439_g:Lnet/minecraft/client/entity/EntityPlayerSP;
        //   194: getfield        net/minecraft/client/entity/EntityPlayerSP.field_70143_R:F
        //   197: fconst_0       
        //   198: fcmpl          
        //   199: ifgt            207
        //   202: ldc             -938429814
        //   204: goto            209
        //   207: ldc             -938429813
        //   209: ldc             1595125010
        //   211: ixor           
        //   212: tableswitch {
        //          772161328: 236
        //          772161329: 254
        //          default: 202
        //        }
        //   236: aload_1        
        //   237: goto            241
        //   240: athrow         
        //   241: invokevirtual   dev/nuker/pyro/f37.c:()Lnet/minecraft/entity/Entity;
        //   244: goto            248
        //   247: athrow         
        //   248: instanceof      Lnet/minecraft/entity/EntityLivingBase;
        //   251: ifne            255
        //   254: return         
        //   255: getstatic       dev/nuker/pyro/fc.c:I
        //   258: ifge            266
        //   261: ldc             1332577068
        //   263: goto            268
        //   266: ldc             -1978860045
        //   268: ldc             1727972333
        //   270: ixor           
        //   271: lookupswitch {
        //          -1608428277: 266
        //          697516225: 2819
        //          default: 296
        //        }
        //   296: getstatic       dev/nuker/pyro/f4N.c:Ldev/nuker/pyro/f7Y;
        //   299: getfield        dev/nuker/pyro/f7Y.c:Ldev/nuker/pyro/fw;
        //   302: goto            306
        //   305: athrow         
        //   306: invokevirtual   dev/nuker/pyro/fw.0:()Ljava/lang/Object;
        //   309: goto            313
        //   312: athrow         
        //   313: checkcast       Ljava/lang/Boolean;
        //   316: goto            320
        //   319: athrow         
        //   320: invokevirtual   java/lang/Boolean.booleanValue:()Z
        //   323: goto            327
        //   326: athrow         
        //   327: ifeq            345
        //   330: goto            334
        //   333: athrow         
        //   334: invokestatic    dev/nuker/pyro/fbl.7:()Z
        //   337: goto            341
        //   340: athrow         
        //   341: ifeq            345
        //   344: return         
        //   345: getstatic       dev/nuker/pyro/f5g.c:[I
        //   348: getstatic       dev/nuker/pyro/fc.c:I
        //   351: ifge            359
        //   354: ldc             1630590351
        //   356: goto            361
        //   359: ldc             -444172775
        //   361: ldc             582829896
        //   363: ixor           
        //   364: lookupswitch {
        //          -952422063: 392
        //          1133351623: 359
        //          default: 2869
        //        }
        //   392: aload_0        
        //   393: getstatic       dev/nuker/pyro/fc.c:I
        //   396: ifge            404
        //   399: ldc             534298503
        //   401: goto            406
        //   404: ldc             1132388430
        //   406: ldc             -636453820
        //   408: ixor           
        //   409: lookupswitch {
        //          -1720804342: 436
        //          -976698429: 404
        //          default: 2835
        //        }
        //   436: getfield        dev/nuker/pyro/f5i.c:Ldev/nuker/pyro/f0f;
        //   439: goto            443
        //   442: athrow         
        //   443: invokevirtual   dev/nuker/pyro/f0f.3:()Ljava/lang/Object;
        //   446: goto            450
        //   449: athrow         
        //   450: checkcast       Ldev/nuker/pyro/f5h;
        //   453: goto            457
        //   456: athrow         
        //   457: invokevirtual   dev/nuker/pyro/f5h.ordinal:()I
        //   460: goto            464
        //   463: athrow         
        //   464: iaload         
        //   465: tableswitch {
        //                2: 496
        //                3: 1253
        //                4: 2578
        //                5: 2644
        //          default: 2759
        //        }
        //   496: aload_0        
        //   497: getstatic       dev/nuker/pyro/fc.0:I
        //   500: ifeq            508
        //   503: ldc             2038035451
        //   505: goto            510
        //   508: ldc             433065978
        //   510: ldc             -2140423695
        //   512: ixor           
        //   513: lookupswitch {
        //          -1715751413: 540
        //          -116241910: 508
        //          default: 2865
        //        }
        //   540: getfield        dev/nuker/pyro/f5i.c:Lnet/minecraft/client/Minecraft;
        //   543: getstatic       dev/nuker/pyro/fc.1:I
        //   546: ifeq            554
        //   549: ldc             -1541678454
        //   551: goto            556
        //   554: ldc             -177581307
        //   556: ldc             -1149451971
        //   558: ixor           
        //   559: lookupswitch {
        //          526850999: 554
        //          1310102072: 584
        //          default: 2885
        //        }
        //   584: getfield        net/minecraft/client/Minecraft.field_71439_g:Lnet/minecraft/client/entity/EntityPlayerSP;
        //   587: getfield        net/minecraft/client/entity/EntityPlayerSP.field_71174_a:Lnet/minecraft/client/network/NetHandlerPlayClient;
        //   590: new             Lnet/minecraft/network/play/client/CPacketPlayer$Position;
        //   593: dup            
        //   594: aload_0        
        //   595: getfield        dev/nuker/pyro/f5i.c:Lnet/minecraft/client/Minecraft;
        //   598: getfield        net/minecraft/client/Minecraft.field_71439_g:Lnet/minecraft/client/entity/EntityPlayerSP;
        //   601: getfield        net/minecraft/client/entity/EntityPlayerSP.field_70165_t:D
        //   604: aload_0        
        //   605: getfield        dev/nuker/pyro/f5i.c:Lnet/minecraft/client/Minecraft;
        //   608: getfield        net/minecraft/client/Minecraft.field_71439_g:Lnet/minecraft/client/entity/EntityPlayerSP;
        //   611: getfield        net/minecraft/client/entity/EntityPlayerSP.field_70163_u:D
        //   614: ldc2_w          0.11
        //   617: dadd           
        //   618: aload_0        
        //   619: getstatic       dev/nuker/pyro/fc.1:I
        //   622: ifeq            630
        //   625: ldc             -1904398352
        //   627: goto            632
        //   630: ldc             248222916
        //   632: ldc             857050810
        //   634: ixor           
        //   635: lookupswitch {
        //          -1117216438: 630
        //          1037965950: 660
        //          default: 2859
        //        }
        //   660: getfield        dev/nuker/pyro/f5i.c:Lnet/minecraft/client/Minecraft;
        //   663: getfield        net/minecraft/client/Minecraft.field_71439_g:Lnet/minecraft/client/entity/EntityPlayerSP;
        //   666: getfield        net/minecraft/client/entity/EntityPlayerSP.field_70161_v:D
        //   669: iconst_0       
        //   670: getstatic       dev/nuker/pyro/fc.c:I
        //   673: ifge            681
        //   676: ldc             123132101
        //   678: goto            683
        //   681: ldc             1529955254
        //   683: ldc             -393043905
        //   685: ixor           
        //   686: lookupswitch {
        //          -1281105015: 712
        //          -272336646: 681
        //          default: 2817
        //        }
        //   712: goto            716
        //   715: athrow         
        //   716: invokespecial   net/minecraft/network/play/client/CPacketPlayer$Position.<init>:(DDDZ)V
        //   719: goto            723
        //   722: athrow         
        //   723: goto            727
        //   726: athrow         
        //   727: invokevirtual   net/minecraft/client/network/NetHandlerPlayClient.func_147297_a:(Lnet/minecraft/network/Packet;)V
        //   730: goto            734
        //   733: athrow         
        //   734: aload_0        
        //   735: getstatic       dev/nuker/pyro/fc.0:I
        //   738: ifeq            746
        //   741: ldc             -1874375815
        //   743: goto            748
        //   746: ldc             1196508380
        //   748: ldc             140054457
        //   750: ixor           
        //   751: lookupswitch {
        //          -1742846784: 746
        //          1325943653: 776
        //          default: 2839
        //        }
        //   776: getfield        dev/nuker/pyro/f5i.c:Lnet/minecraft/client/Minecraft;
        //   779: getstatic       dev/nuker/pyro/fc.c:I
        //   782: ifge            790
        //   785: ldc             -1569151764
        //   787: goto            792
        //   790: ldc             782137302
        //   792: ldc             -1525651450
        //   794: ixor           
        //   795: lookupswitch {
        //          -1953620016: 820
        //          124308714: 790
        //          default: 2879
        //        }
        //   820: getfield        net/minecraft/client/Minecraft.field_71439_g:Lnet/minecraft/client/entity/EntityPlayerSP;
        //   823: getfield        net/minecraft/client/entity/EntityPlayerSP.field_71174_a:Lnet/minecraft/client/network/NetHandlerPlayClient;
        //   826: new             Lnet/minecraft/network/play/client/CPacketPlayer$Position;
        //   829: dup            
        //   830: aload_0        
        //   831: getfield        dev/nuker/pyro/f5i.c:Lnet/minecraft/client/Minecraft;
        //   834: getfield        net/minecraft/client/Minecraft.field_71439_g:Lnet/minecraft/client/entity/EntityPlayerSP;
        //   837: getstatic       dev/nuker/pyro/fc.1:I
        //   840: ifeq            848
        //   843: ldc             1181053374
        //   845: goto            850
        //   848: ldc             -1204371181
        //   850: ldc             -2039526375
        //   852: ixor           
        //   853: lookupswitch {
        //          -1073070681: 2895
        //          -854905278: 848
        //          default: 880
        //        }
        //   880: getfield        net/minecraft/client/entity/EntityPlayerSP.field_70165_t:D
        //   883: aload_0        
        //   884: getfield        dev/nuker/pyro/f5i.c:Lnet/minecraft/client/Minecraft;
        //   887: getfield        net/minecraft/client/Minecraft.field_71439_g:Lnet/minecraft/client/entity/EntityPlayerSP;
        //   890: getfield        net/minecraft/client/entity/EntityPlayerSP.field_70163_u:D
        //   893: ldc2_w          0.1100013579
        //   896: dadd           
        //   897: getstatic       dev/nuker/pyro/fc.0:I
        //   900: ifeq            908
        //   903: ldc             659220544
        //   905: goto            910
        //   908: ldc             -1051338503
        //   910: ldc             -65119331
        //   912: ixor           
        //   913: lookupswitch {
        //          -615205923: 2897
        //          1301973165: 908
        //          default: 940
        //        }
        //   940: aload_0        
        //   941: getfield        dev/nuker/pyro/f5i.c:Lnet/minecraft/client/Minecraft;
        //   944: getfield        net/minecraft/client/Minecraft.field_71439_g:Lnet/minecraft/client/entity/EntityPlayerSP;
        //   947: getstatic       dev/nuker/pyro/fc.c:I
        //   950: ifge            958
        //   953: ldc             2084324804
        //   955: goto            960
        //   958: ldc             -1438694398
        //   960: ldc             -1388927201
        //   962: ixor           
        //   963: lookupswitch {
        //          -787815717: 958
        //          118088477: 988
        //          default: 2829
        //        }
        //   988: getfield        net/minecraft/client/entity/EntityPlayerSP.field_70161_v:D
        //   991: iconst_0       
        //   992: goto            996
        //   995: athrow         
        //   996: invokespecial   net/minecraft/network/play/client/CPacketPlayer$Position.<init>:(DDDZ)V
        //   999: goto            1003
        //  1002: athrow         
        //  1003: getstatic       dev/nuker/pyro/fc.0:I
        //  1006: ifeq            1014
        //  1009: ldc             -1728508844
        //  1011: goto            1016
        //  1014: ldc             1415650138
        //  1016: ldc             1766768586
        //  1018: ixor           
        //  1019: lookupswitch {
        //          -1852410839: 1014
        //          -239619170: 2863
        //          default: 1044
        //        }
        //  1044: goto            1048
        //  1047: athrow         
        //  1048: invokevirtual   net/minecraft/client/network/NetHandlerPlayClient.func_147297_a:(Lnet/minecraft/network/Packet;)V
        //  1051: goto            1055
        //  1054: athrow         
        //  1055: getstatic       dev/nuker/pyro/fc.c:I
        //  1058: ifge            1066
        //  1061: ldc             793166784
        //  1063: goto            1068
        //  1066: ldc             1631036350
        //  1068: ldc             486558200
        //  1070: ixor           
        //  1071: lookupswitch {
        //          -429814263: 1066
        //          843483704: 2899
        //          default: 1096
        //        }
        //  1096: aload_0        
        //  1097: getfield        dev/nuker/pyro/f5i.c:Lnet/minecraft/client/Minecraft;
        //  1100: getfield        net/minecraft/client/Minecraft.field_71439_g:Lnet/minecraft/client/entity/EntityPlayerSP;
        //  1103: getfield        net/minecraft/client/entity/EntityPlayerSP.field_71174_a:Lnet/minecraft/client/network/NetHandlerPlayClient;
        //  1106: new             Lnet/minecraft/network/play/client/CPacketPlayer$Position;
        //  1109: dup            
        //  1110: aload_0        
        //  1111: getfield        dev/nuker/pyro/f5i.c:Lnet/minecraft/client/Minecraft;
        //  1114: getstatic       dev/nuker/pyro/fc.0:I
        //  1117: ifeq            1125
        //  1120: ldc             -1205263
        //  1122: goto            1127
        //  1125: ldc             86773372
        //  1127: ldc             1059938390
        //  1129: ixor           
        //  1130: lookupswitch {
        //          -1061094489: 2855
        //          1830799352: 1125
        //          default: 1156
        //        }
        //  1156: getfield        net/minecraft/client/Minecraft.field_71439_g:Lnet/minecraft/client/entity/EntityPlayerSP;
        //  1159: getstatic       dev/nuker/pyro/fc.0:I
        //  1162: ifeq            1170
        //  1165: ldc             -445098221
        //  1167: goto            1172
        //  1170: ldc             -1867343348
        //  1172: ldc             786808808
        //  1174: ixor           
        //  1175: lookupswitch {
        //          -878843653: 2905
        //          224139327: 1170
        //          default: 1200
        //        }
        //  1200: getfield        net/minecraft/client/entity/EntityPlayerSP.field_70165_t:D
        //  1203: aload_0        
        //  1204: getfield        dev/nuker/pyro/f5i.c:Lnet/minecraft/client/Minecraft;
        //  1207: getfield        net/minecraft/client/Minecraft.field_71439_g:Lnet/minecraft/client/entity/EntityPlayerSP;
        //  1210: getfield        net/minecraft/client/entity/EntityPlayerSP.field_70163_u:D
        //  1213: ldc2_w          1.3579E-6
        //  1216: dadd           
        //  1217: aload_0        
        //  1218: getfield        dev/nuker/pyro/f5i.c:Lnet/minecraft/client/Minecraft;
        //  1221: getfield        net/minecraft/client/Minecraft.field_71439_g:Lnet/minecraft/client/entity/EntityPlayerSP;
        //  1224: getfield        net/minecraft/client/entity/EntityPlayerSP.field_70161_v:D
        //  1227: iconst_0       
        //  1228: goto            1232
        //  1231: athrow         
        //  1232: invokespecial   net/minecraft/network/play/client/CPacketPlayer$Position.<init>:(DDDZ)V
        //  1235: goto            1239
        //  1238: athrow         
        //  1239: goto            1243
        //  1242: athrow         
        //  1243: invokevirtual   net/minecraft/client/network/NetHandlerPlayClient.func_147297_a:(Lnet/minecraft/network/Packet;)V
        //  1246: goto            1250
        //  1249: athrow         
        //  1250: goto            2759
        //  1253: aload_0        
        //  1254: getfield        dev/nuker/pyro/f5i.c:Lnet/minecraft/client/Minecraft;
        //  1257: getstatic       dev/nuker/pyro/fc.1:I
        //  1260: ifeq            1268
        //  1263: ldc             -1640885552
        //  1265: goto            1270
        //  1268: ldc             -287752913
        //  1270: ldc             775578856
        //  1272: ixor           
        //  1273: lookupswitch {
        //          -2104582537: 1268
        //          -1341622728: 2883
        //          default: 1300
        //        }
        //  1300: getfield        net/minecraft/client/Minecraft.field_71439_g:Lnet/minecraft/client/entity/EntityPlayerSP;
        //  1303: getfield        net/minecraft/client/entity/EntityPlayerSP.field_71174_a:Lnet/minecraft/client/network/NetHandlerPlayClient;
        //  1306: new             Lnet/minecraft/network/play/client/CPacketPlayer$Position;
        //  1309: dup            
        //  1310: aload_0        
        //  1311: getfield        dev/nuker/pyro/f5i.c:Lnet/minecraft/client/Minecraft;
        //  1314: getfield        net/minecraft/client/Minecraft.field_71439_g:Lnet/minecraft/client/entity/EntityPlayerSP;
        //  1317: getfield        net/minecraft/client/entity/EntityPlayerSP.field_70165_t:D
        //  1320: aload_0        
        //  1321: getstatic       dev/nuker/pyro/fc.1:I
        //  1324: ifeq            1332
        //  1327: ldc             -54535744
        //  1329: goto            1334
        //  1332: ldc             1397104101
        //  1334: ldc             749869384
        //  1336: ixor           
        //  1337: lookupswitch {
        //          -1730105690: 1332
        //          -804405112: 2873
        //          default: 1364
        //        }
        //  1364: getfield        dev/nuker/pyro/f5i.c:Lnet/minecraft/client/Minecraft;
        //  1367: getfield        net/minecraft/client/Minecraft.field_71439_g:Lnet/minecraft/client/entity/EntityPlayerSP;
        //  1370: getfield        net/minecraft/client/entity/EntityPlayerSP.field_70163_u:D
        //  1373: ldc2_w          0.05000000074505806
        //  1376: dadd           
        //  1377: getstatic       dev/nuker/pyro/fc.0:I
        //  1380: ifeq            1388
        //  1383: ldc             -822422123
        //  1385: goto            1390
        //  1388: ldc             1965227984
        //  1390: ldc             -1618249757
        //  1392: ixor           
        //  1393: lookupswitch {
        //          -357988301: 1420
        //          1366401654: 1388
        //          default: 2857
        //        }
        //  1420: aload_0        
        //  1421: getfield        dev/nuker/pyro/f5i.c:Lnet/minecraft/client/Minecraft;
        //  1424: getfield        net/minecraft/client/Minecraft.field_71439_g:Lnet/minecraft/client/entity/EntityPlayerSP;
        //  1427: getfield        net/minecraft/client/entity/EntityPlayerSP.field_70161_v:D
        //  1430: iconst_0       
        //  1431: getstatic       dev/nuker/pyro/fc.0:I
        //  1434: ifeq            1442
        //  1437: ldc             1907753018
        //  1439: goto            1444
        //  1442: ldc             785007526
        //  1444: ldc             -393171267
        //  1446: ixor           
        //  1447: lookupswitch {
        //          -1725518201: 1442
        //          -967119589: 1472
        //          default: 2867
        //        }
        //  1472: goto            1476
        //  1475: athrow         
        //  1476: invokespecial   net/minecraft/network/play/client/CPacketPlayer$Position.<init>:(DDDZ)V
        //  1479: goto            1483
        //  1482: athrow         
        //  1483: goto            1487
        //  1486: athrow         
        //  1487: invokevirtual   net/minecraft/client/network/NetHandlerPlayClient.func_147297_a:(Lnet/minecraft/network/Packet;)V
        //  1490: goto            1494
        //  1493: athrow         
        //  1494: aload_0        
        //  1495: getstatic       dev/nuker/pyro/fc.0:I
        //  1498: ifeq            1506
        //  1501: ldc             -1732230676
        //  1503: goto            1508
        //  1506: ldc             1602482645
        //  1508: ldc             1861532777
        //  1510: ixor           
        //  1511: lookupswitch {
        //          -164299387: 1506
        //          829902268: 1536
        //          default: 2853
        //        }
        //  1536: getfield        dev/nuker/pyro/f5i.c:Lnet/minecraft/client/Minecraft;
        //  1539: getfield        net/minecraft/client/Minecraft.field_71439_g:Lnet/minecraft/client/entity/EntityPlayerSP;
        //  1542: getstatic       dev/nuker/pyro/fc.c:I
        //  1545: ifge            1553
        //  1548: ldc             867042139
        //  1550: goto            1555
        //  1553: ldc             -736778403
        //  1555: ldc             1934700821
        //  1557: ixor           
        //  1558: lookupswitch {
        //          -1488677304: 1584
        //          1090466382: 1553
        //          default: 2841
        //        }
        //  1584: getfield        net/minecraft/client/entity/EntityPlayerSP.field_71174_a:Lnet/minecraft/client/network/NetHandlerPlayClient;
        //  1587: new             Lnet/minecraft/network/play/client/CPacketPlayer$Position;
        //  1590: dup            
        //  1591: aload_0        
        //  1592: getfield        dev/nuker/pyro/f5i.c:Lnet/minecraft/client/Minecraft;
        //  1595: getstatic       dev/nuker/pyro/fc.0:I
        //  1598: ifeq            1606
        //  1601: ldc             1679433199
        //  1603: goto            1608
        //  1606: ldc             1411521442
        //  1608: ldc             1599164640
        //  1610: ixor           
        //  1611: lookupswitch {
        //          994790671: 2891
        //          1577529981: 1606
        //          default: 1636
        //        }
        //  1636: getfield        net/minecraft/client/Minecraft.field_71439_g:Lnet/minecraft/client/entity/EntityPlayerSP;
        //  1639: getstatic       dev/nuker/pyro/fc.0:I
        //  1642: ifeq            1650
        //  1645: ldc             -279444195
        //  1647: goto            1652
        //  1650: ldc             -1476357818
        //  1652: ldc             -772764875
        //  1654: ixor           
        //  1655: lookupswitch {
        //          1051233832: 1650
        //          2045778547: 1680
        //          default: 2831
        //        }
        //  1680: getfield        net/minecraft/client/entity/EntityPlayerSP.field_70165_t:D
        //  1683: aload_0        
        //  1684: getfield        dev/nuker/pyro/f5i.c:Lnet/minecraft/client/Minecraft;
        //  1687: getfield        net/minecraft/client/Minecraft.field_71439_g:Lnet/minecraft/client/entity/EntityPlayerSP;
        //  1690: getfield        net/minecraft/client/entity/EntityPlayerSP.field_70163_u:D
        //  1693: aload_0        
        //  1694: getstatic       dev/nuker/pyro/fc.c:I
        //  1697: ifge            1705
        //  1700: ldc             -558632437
        //  1702: goto            1707
        //  1705: ldc             -418001560
        //  1707: ldc             -2050718998
        //  1709: ixor           
        //  1710: lookupswitch {
        //          -954616848: 1705
        //          1534554337: 2887
        //          default: 1736
        //        }
        //  1736: getfield        dev/nuker/pyro/f5i.c:Lnet/minecraft/client/Minecraft;
        //  1739: getfield        net/minecraft/client/Minecraft.field_71439_g:Lnet/minecraft/client/entity/EntityPlayerSP;
        //  1742: getstatic       dev/nuker/pyro/fc.1:I
        //  1745: ifeq            1753
        //  1748: ldc             -559421864
        //  1750: goto            1755
        //  1753: ldc             -1516783387
        //  1755: ldc             488128345
        //  1757: ixor           
        //  1758: lookupswitch {
        //          -1010837247: 2843
        //          2072984760: 1753
        //          default: 1784
        //        }
        //  1784: getfield        net/minecraft/client/entity/EntityPlayerSP.field_70161_v:D
        //  1787: iconst_0       
        //  1788: getstatic       dev/nuker/pyro/fc.c:I
        //  1791: ifge            1800
        //  1794: ldc_w           1088414656
        //  1797: goto            1803
        //  1800: ldc_w           -208843729
        //  1803: ldc_w           -987479493
        //  1806: ixor           
        //  1807: lookupswitch {
        //          -2047106565: 2845
        //          1999068334: 1800
        //          default: 1832
        //        }
        //  1832: goto            1836
        //  1835: athrow         
        //  1836: invokespecial   net/minecraft/network/play/client/CPacketPlayer$Position.<init>:(DDDZ)V
        //  1839: goto            1843
        //  1842: athrow         
        //  1843: goto            1847
        //  1846: athrow         
        //  1847: invokevirtual   net/minecraft/client/network/NetHandlerPlayClient.func_147297_a:(Lnet/minecraft/network/Packet;)V
        //  1850: goto            1854
        //  1853: athrow         
        //  1854: aload_0        
        //  1855: getstatic       dev/nuker/pyro/fc.c:I
        //  1858: ifge            1867
        //  1861: ldc_w           -1502417183
        //  1864: goto            1870
        //  1867: ldc_w           1985242565
        //  1870: ldc_w           56458807
        //  1873: ixor           
        //  1874: lookupswitch {
        //          -1523609386: 2903
        //          -1224695914: 1867
        //          default: 1900
        //        }
        //  1900: getfield        dev/nuker/pyro/f5i.c:Lnet/minecraft/client/Minecraft;
        //  1903: getstatic       dev/nuker/pyro/fc.0:I
        //  1906: ifeq            1915
        //  1909: ldc_w           1796171455
        //  1912: goto            1918
        //  1915: ldc_w           -490216191
        //  1918: ldc_w           -921442841
        //  1921: ixor           
        //  1922: lookupswitch {
        //          -1575189672: 1915
        //          735314150: 1948
        //          default: 2901
        //        }
        //  1948: getfield        net/minecraft/client/Minecraft.field_71439_g:Lnet/minecraft/client/entity/EntityPlayerSP;
        //  1951: getfield        net/minecraft/client/entity/EntityPlayerSP.field_71174_a:Lnet/minecraft/client/network/NetHandlerPlayClient;
        //  1954: new             Lnet/minecraft/network/play/client/CPacketPlayer$Position;
        //  1957: dup            
        //  1958: aload_0        
        //  1959: getstatic       dev/nuker/pyro/fc.c:I
        //  1962: ifge            1971
        //  1965: ldc_w           1570404715
        //  1968: goto            1974
        //  1971: ldc_w           840949170
        //  1974: ldc_w           -1297266122
        //  1977: ixor           
        //  1978: lookupswitch {
        //          -281595043: 2847
        //          38480098: 1971
        //          default: 2004
        //        }
        //  2004: getfield        dev/nuker/pyro/f5i.c:Lnet/minecraft/client/Minecraft;
        //  2007: getfield        net/minecraft/client/Minecraft.field_71439_g:Lnet/minecraft/client/entity/EntityPlayerSP;
        //  2010: getfield        net/minecraft/client/entity/EntityPlayerSP.field_70165_t:D
        //  2013: aload_0        
        //  2014: getfield        dev/nuker/pyro/f5i.c:Lnet/minecraft/client/Minecraft;
        //  2017: getfield        net/minecraft/client/Minecraft.field_71439_g:Lnet/minecraft/client/entity/EntityPlayerSP;
        //  2020: getfield        net/minecraft/client/entity/EntityPlayerSP.field_70163_u:D
        //  2023: ldc2_w          0.012511000037193298
        //  2026: dadd           
        //  2027: getstatic       dev/nuker/pyro/fc.1:I
        //  2030: ifeq            2039
        //  2033: ldc_w           1793804801
        //  2036: goto            2042
        //  2039: ldc_w           -601405767
        //  2042: ldc_w           1670105083
        //  2045: ixor           
        //  2046: lookupswitch {
        //          -1079213758: 2072
        //          157322746: 2039
        //          default: 2823
        //        }
        //  2072: aload_0        
        //  2073: getfield        dev/nuker/pyro/f5i.c:Lnet/minecraft/client/Minecraft;
        //  2076: getstatic       dev/nuker/pyro/fc.1:I
        //  2079: ifeq            2088
        //  2082: ldc_w           630155894
        //  2085: goto            2091
        //  2088: ldc_w           -1395308300
        //  2091: ldc_w           -1687645352
        //  2094: ixor           
        //  2095: lookupswitch {
        //          -1092093650: 2088
        //          935189420: 2120
        //          default: 2893
        //        }
        //  2120: getfield        net/minecraft/client/Minecraft.field_71439_g:Lnet/minecraft/client/entity/EntityPlayerSP;
        //  2123: getfield        net/minecraft/client/entity/EntityPlayerSP.field_70161_v:D
        //  2126: iconst_0       
        //  2127: goto            2131
        //  2130: athrow         
        //  2131: invokespecial   net/minecraft/network/play/client/CPacketPlayer$Position.<init>:(DDDZ)V
        //  2134: goto            2138
        //  2137: athrow         
        //  2138: goto            2142
        //  2141: athrow         
        //  2142: invokevirtual   net/minecraft/client/network/NetHandlerPlayClient.func_147297_a:(Lnet/minecraft/network/Packet;)V
        //  2145: goto            2149
        //  2148: athrow         
        //  2149: aload_0        
        //  2150: getfield        dev/nuker/pyro/f5i.c:Lnet/minecraft/client/Minecraft;
        //  2153: getfield        net/minecraft/client/Minecraft.field_71439_g:Lnet/minecraft/client/entity/EntityPlayerSP;
        //  2156: getstatic       dev/nuker/pyro/fc.1:I
        //  2159: ifeq            2168
        //  2162: ldc_w           686138580
        //  2165: goto            2171
        //  2168: ldc_w           -1406962437
        //  2171: ldc_w           -500456718
        //  2174: ixor           
        //  2175: lookupswitch {
        //          -892467674: 2168
        //          1309201929: 2200
        //          default: 2827
        //        }
        //  2200: getfield        net/minecraft/client/entity/EntityPlayerSP.field_71174_a:Lnet/minecraft/client/network/NetHandlerPlayClient;
        //  2203: new             Lnet/minecraft/network/play/client/CPacketPlayer$Position;
        //  2206: dup            
        //  2207: getstatic       dev/nuker/pyro/fc.1:I
        //  2210: ifeq            2219
        //  2213: ldc_w           92823865
        //  2216: goto            2222
        //  2219: ldc_w           198677080
        //  2222: ldc_w           -1299466429
        //  2225: ixor           
        //  2226: lookupswitch {
        //          -1224485254: 2219
        //          -1185143525: 2252
        //          default: 2871
        //        }
        //  2252: aload_0        
        //  2253: getfield        dev/nuker/pyro/f5i.c:Lnet/minecraft/client/Minecraft;
        //  2256: getfield        net/minecraft/client/Minecraft.field_71439_g:Lnet/minecraft/client/entity/EntityPlayerSP;
        //  2259: getstatic       dev/nuker/pyro/fc.1:I
        //  2262: ifeq            2271
        //  2265: ldc_w           181559320
        //  2268: goto            2274
        //  2271: ldc_w           -736629141
        //  2274: ldc_w           343750909
        //  2277: ixor           
        //  2278: lookupswitch {
        //          -1066740074: 2304
        //          514808037: 2271
        //          default: 2889
        //        }
        //  2304: getfield        net/minecraft/client/entity/EntityPlayerSP.field_70165_t:D
        //  2307: aload_0        
        //  2308: getfield        dev/nuker/pyro/f5i.c:Lnet/minecraft/client/Minecraft;
        //  2311: getstatic       dev/nuker/pyro/fc.1:I
        //  2314: ifeq            2323
        //  2317: ldc_w           -1719582118
        //  2320: goto            2326
        //  2323: ldc_w           1678752010
        //  2326: ldc_w           1077656187
        //  2329: ixor           
        //  2330: lookupswitch {
        //          -1001950217: 2323
        //          -642058207: 2881
        //          default: 2356
        //        }
        //  2356: getfield        net/minecraft/client/Minecraft.field_71439_g:Lnet/minecraft/client/entity/EntityPlayerSP;
        //  2359: getfield        net/minecraft/client/entity/EntityPlayerSP.field_70163_u:D
        //  2362: getstatic       dev/nuker/pyro/fc.c:I
        //  2365: ifge            2374
        //  2368: ldc_w           -2060156841
        //  2371: goto            2377
        //  2374: ldc_w           -884692202
        //  2377: ldc_w           732000071
        //  2380: ixor           
        //  2381: lookupswitch {
        //          -1365905648: 2374
        //          -521812911: 2408
        //          default: 2837
        //        }
        //  2408: aload_0        
        //  2409: getfield        dev/nuker/pyro/f5i.c:Lnet/minecraft/client/Minecraft;
        //  2412: getstatic       dev/nuker/pyro/fc.1:I
        //  2415: ifeq            2424
        //  2418: ldc_w           -875819156
        //  2421: goto            2427
        //  2424: ldc_w           -2093662108
        //  2427: ldc_w           775222128
        //  2430: ixor           
        //  2431: lookupswitch {
        //          -1392397548: 2456
        //          -436667364: 2424
        //          default: 2821
        //        }
        //  2456: getfield        net/minecraft/client/Minecraft.field_71439_g:Lnet/minecraft/client/entity/EntityPlayerSP;
        //  2459: getfield        net/minecraft/client/entity/EntityPlayerSP.field_70161_v:D
        //  2462: iconst_0       
        //  2463: getstatic       dev/nuker/pyro/fc.1:I
        //  2466: ifeq            2475
        //  2469: ldc_w           -1832103437
        //  2472: goto            2478
        //  2475: ldc_w           450532289
        //  2478: ldc_w           1847073803
        //  2481: ixor           
        //  2482: lookupswitch {
        //          -53195272: 2475
        //          1958907850: 2508
        //          default: 2825
        //        }
        //  2508: goto            2512
        //  2511: athrow         
        //  2512: invokespecial   net/minecraft/network/play/client/CPacketPlayer$Position.<init>:(DDDZ)V
        //  2515: goto            2519
        //  2518: athrow         
        //  2519: getstatic       dev/nuker/pyro/fc.0:I
        //  2522: ifeq            2531
        //  2525: ldc_w           -1937793119
        //  2528: goto            2534
        //  2531: ldc_w           687922151
        //  2534: ldc_w           -1716453039
        //  2537: ixor           
        //  2538: lookupswitch {
        //          -1330521418: 2564
        //          365862640: 2531
        //          default: 2833
        //        }
        //  2564: goto            2568
        //  2567: athrow         
        //  2568: invokevirtual   net/minecraft/client/network/NetHandlerPlayClient.func_147297_a:(Lnet/minecraft/network/Packet;)V
        //  2571: goto            2575
        //  2574: athrow         
        //  2575: goto            2759
        //  2578: aload_0        
        //  2579: getfield        dev/nuker/pyro/f5i.c:Lnet/minecraft/client/Minecraft;
        //  2582: getfield        net/minecraft/client/Minecraft.field_71439_g:Lnet/minecraft/client/entity/EntityPlayerSP;
        //  2585: getfield        net/minecraft/client/entity/EntityPlayerSP.field_70122_E:Z
        //  2588: ifeq            2597
        //  2591: ldc_w           184690750
        //  2594: goto            2600
        //  2597: ldc_w           184690745
        //  2600: ldc_w           -900689699
        //  2603: ixor           
        //  2604: tableswitch {
        //          -2103086650: 2628
        //          -2103086649: 2759
        //          default: 2591
        //        }
        //  2628: aload_0        
        //  2629: getfield        dev/nuker/pyro/f5i.c:Lnet/minecraft/client/Minecraft;
        //  2632: getfield        net/minecraft/client/Minecraft.field_71439_g:Lnet/minecraft/client/entity/EntityPlayerSP;
        //  2635: ldc2_w          0.405
        //  2638: putfield        net/minecraft/client/entity/EntityPlayerSP.field_70181_x:D
        //  2641: goto            2759
        //  2644: aload_0        
        //  2645: getfield        dev/nuker/pyro/f5i.c:Lnet/minecraft/client/Minecraft;
        //  2648: getstatic       dev/nuker/pyro/fc.0:I
        //  2651: ifeq            2660
        //  2654: ldc_w           -1064297484
        //  2657: goto            2663
        //  2660: ldc_w           158101308
        //  2663: ldc_w           -1128324297
        //  2666: ixor           
        //  2667: lookupswitch {
        //          2051543702: 2660
        //          2083469507: 2851
        //          default: 2692
        //        }
        //  2692: getfield        net/minecraft/client/Minecraft.field_71439_g:Lnet/minecraft/client/entity/EntityPlayerSP;
        //  2695: getstatic       dev/nuker/pyro/fc.0:I
        //  2698: ifeq            2707
        //  2701: ldc_w           -772361649
        //  2704: goto            2710
        //  2707: ldc_w           199099395
        //  2710: ldc_w           881829743
        //  2713: ixor           
        //  2714: lookupswitch {
        //          -445049568: 2707
        //          1062314860: 2740
        //          default: 2875
        //        }
        //  2740: getfield        net/minecraft/client/entity/EntityPlayerSP.field_70122_E:Z
        //  2743: ifeq            2759
        //  2746: aload_0        
        //  2747: getfield        dev/nuker/pyro/f5i.c:Lnet/minecraft/client/Minecraft;
        //  2750: getfield        net/minecraft/client/Minecraft.field_71439_g:Lnet/minecraft/client/entity/EntityPlayerSP;
        //  2753: ldc2_w          0.11111111
        //  2756: putfield        net/minecraft/client/entity/EntityPlayerSP.field_70181_x:D
        //  2759: getstatic       dev/nuker/pyro/fc.1:I
        //  2762: ifeq            2771
        //  2765: ldc_w           387939593
        //  2768: goto            2774
        //  2771: ldc_w           1145793948
        //  2774: ldc_w           483570607
        //  2777: ixor           
        //  2778: lookupswitch {
        //          198037158: 2771
        //          1486478899: 2804
        //          default: 2849
        //        }
        //  2804: aload_0        
        //  2805: getfield        dev/nuker/pyro/f5i.c:Lnet/minecraft/client/Minecraft;
        //  2808: getfield        net/minecraft/client/Minecraft.field_71439_g:Lnet/minecraft/client/entity/EntityPlayerSP;
        //  2811: ldc             1337.0
        //  2813: putfield        net/minecraft/client/entity/EntityPlayerSP.field_70143_R:F
        //  2816: return         
        //  2817: aconst_null    
        //  2818: athrow         
        //  2819: aconst_null    
        //  2820: athrow         
        //  2821: aconst_null    
        //  2822: athrow         
        //  2823: aconst_null    
        //  2824: athrow         
        //  2825: aconst_null    
        //  2826: athrow         
        //  2827: aconst_null    
        //  2828: athrow         
        //  2829: aconst_null    
        //  2830: athrow         
        //  2831: aconst_null    
        //  2832: athrow         
        //  2833: aconst_null    
        //  2834: athrow         
        //  2835: aconst_null    
        //  2836: athrow         
        //  2837: aconst_null    
        //  2838: athrow         
        //  2839: aconst_null    
        //  2840: athrow         
        //  2841: aconst_null    
        //  2842: athrow         
        //  2843: aconst_null    
        //  2844: athrow         
        //  2845: aconst_null    
        //  2846: athrow         
        //  2847: aconst_null    
        //  2848: athrow         
        //  2849: aconst_null    
        //  2850: athrow         
        //  2851: aconst_null    
        //  2852: athrow         
        //  2853: aconst_null    
        //  2854: athrow         
        //  2855: aconst_null    
        //  2856: athrow         
        //  2857: aconst_null    
        //  2858: athrow         
        //  2859: aconst_null    
        //  2860: athrow         
        //  2861: aconst_null    
        //  2862: athrow         
        //  2863: aconst_null    
        //  2864: athrow         
        //  2865: aconst_null    
        //  2866: athrow         
        //  2867: aconst_null    
        //  2868: athrow         
        //  2869: aconst_null    
        //  2870: athrow         
        //  2871: aconst_null    
        //  2872: athrow         
        //  2873: aconst_null    
        //  2874: athrow         
        //  2875: aconst_null    
        //  2876: athrow         
        //  2877: aconst_null    
        //  2878: athrow         
        //  2879: aconst_null    
        //  2880: athrow         
        //  2881: aconst_null    
        //  2882: athrow         
        //  2883: aconst_null    
        //  2884: athrow         
        //  2885: aconst_null    
        //  2886: athrow         
        //  2887: aconst_null    
        //  2888: athrow         
        //  2889: aconst_null    
        //  2890: athrow         
        //  2891: aconst_null    
        //  2892: athrow         
        //  2893: aconst_null    
        //  2894: athrow         
        //  2895: aconst_null    
        //  2896: athrow         
        //  2897: aconst_null    
        //  2898: athrow         
        //  2899: aconst_null    
        //  2900: athrow         
        //  2901: aconst_null    
        //  2902: athrow         
        //  2903: aconst_null    
        //  2904: athrow         
        //  2905: aconst_null    
        //  2906: athrow         
        //  2907: pop            
        //  2908: goto            24
        //  2911: pop            
        //  2912: aconst_null    
        //  2913: goto            2907
        //  2916: dup            
        //  2917: ifnull          2907
        //  2920: checkcast       Ljava/lang/Throwable;
        //  2923: athrow         
        //  2924: dup            
        //  2925: ifnull          2911
        //  2928: checkcast       Ljava/lang/Throwable;
        //  2931: athrow         
        //  2932: aconst_null    
        //  2933: athrow         
        //    StackMapTable: 01 27 43 07 00 33 04 FF 00 0B 00 00 00 01 07 00 33 FD 00 03 07 00 03 07 00 3A 4B 07 00 3A FF 00 01 00 02 07 00 03 07 00 3A 00 02 07 00 3A 01 5D 07 00 3A FF 00 02 00 00 00 01 07 00 33 FF 00 00 00 02 07 00 03 07 00 3A 00 01 07 00 3A 45 07 00 33 40 07 00 3F 15 04 41 01 17 4B 07 00 03 FF 00 01 00 02 07 00 03 07 00 3A 00 02 07 00 03 01 5D 07 00 03 09 00 0E 04 41 01 1A 43 07 00 33 40 07 00 3A 45 07 00 33 40 07 01 44 05 00 0A 41 01 1B 48 07 00 33 40 07 00 72 45 07 00 33 40 07 01 46 45 07 00 13 40 07 00 77 45 07 00 33 40 01 45 07 00 13 00 45 07 00 33 40 01 03 4D 07 01 47 FF 00 01 00 02 07 00 03 07 00 3A 00 02 07 01 47 01 5E 07 01 47 FF 00 0B 00 02 07 00 03 07 00 3A 00 02 07 01 47 07 00 03 FF 00 01 00 02 07 00 03 07 00 3A 00 03 07 01 47 07 00 03 01 FF 00 1D 00 02 07 00 03 07 00 3A 00 02 07 01 47 07 00 03 45 07 00 33 FF 00 00 00 02 07 00 03 07 00 3A 00 02 07 01 47 07 00 8F 45 07 00 33 FF 00 00 00 02 07 00 03 07 00 3A 00 02 07 01 47 07 01 46 45 07 00 33 FF 00 00 00 02 07 00 03 07 00 3A 00 02 07 01 47 07 00 94 45 07 00 33 FF 00 00 00 02 07 00 03 07 00 3A 00 02 07 01 47 01 1F 4B 07 00 03 FF 00 01 00 02 07 00 03 07 00 3A 00 02 07 00 03 01 5D 07 00 03 4D 07 00 48 FF 00 01 00 02 07 00 03 07 00 3A 00 02 07 00 48 01 5B 07 00 48 FF 00 2D 00 02 07 00 03 07 00 3A 00 06 07 00 BC 08 02 4E 08 02 4E 03 03 07 00 03 FF 00 01 00 02 07 00 03 07 00 3A 00 07 07 00 BC 08 02 4E 08 02 4E 03 03 07 00 03 01 FF 00 1B 00 02 07 00 03 07 00 3A 00 06 07 00 BC 08 02 4E 08 02 4E 03 03 07 00 03 FF 00 14 00 02 07 00 03 07 00 3A 00 07 07 00 BC 08 02 4E 08 02 4E 03 03 03 01 FF 00 01 00 02 07 00 03 07 00 3A 00 08 07 00 BC 08 02 4E 08 02 4E 03 03 03 01 01 FF 00 1C 00 02 07 00 03 07 00 3A 00 07 07 00 BC 08 02 4E 08 02 4E 03 03 03 01 42 07 00 1F FF 00 00 00 02 07 00 03 07 00 3A 00 07 07 00 BC 08 02 4E 08 02 4E 03 03 03 01 45 07 00 33 FF 00 00 00 02 07 00 03 07 00 3A 00 02 07 00 BC 07 00 A4 42 07 00 13 FF 00 00 00 02 07 00 03 07 00 3A 00 02 07 00 BC 07 00 A4 45 07 00 33 00 4B 07 00 03 FF 00 01 00 02 07 00 03 07 00 3A 00 02 07 00 03 01 5B 07 00 03 4D 07 00 48 FF 00 01 00 02 07 00 03 07 00 3A 00 02 07 00 48 01 5B 07 00 48 FF 00 1B 00 02 07 00 03 07 00 3A 00 04 07 00 BC 08 03 3A 08 03 3A 07 00 4E FF 00 01 00 02 07 00 03 07 00 3A 00 05 07 00 BC 08 03 3A 08 03 3A 07 00 4E 01 FF 00 1D 00 02 07 00 03 07 00 3A 00 04 07 00 BC 08 03 3A 08 03 3A 07 00 4E FF 00 1B 00 02 07 00 03 07 00 3A 00 05 07 00 BC 08 03 3A 08 03 3A 03 03 FF 00 01 00 02 07 00 03 07 00 3A 00 06 07 00 BC 08 03 3A 08 03 3A 03 03 01 FF 00 1D 00 02 07 00 03 07 00 3A 00 05 07 00 BC 08 03 3A 08 03 3A 03 03 FF 00 11 00 02 07 00 03 07 00 3A 00 06 07 00 BC 08 03 3A 08 03 3A 03 03 07 00 4E FF 00 01 00 02 07 00 03 07 00 3A 00 07 07 00 BC 08 03 3A 08 03 3A 03 03 07 00 4E 01 FF 00 1B 00 02 07 00 03 07 00 3A 00 06 07 00 BC 08 03 3A 08 03 3A 03 03 07 00 4E 46 07 00 33 FF 00 00 00 02 07 00 03 07 00 3A 00 07 07 00 BC 08 03 3A 08 03 3A 03 03 03 01 45 07 00 33 FF 00 00 00 02 07 00 03 07 00 3A 00 02 07 00 BC 07 00 A4 FF 00 0A 00 02 07 00 03 07 00 3A 00 02 07 00 BC 07 00 A4 FF 00 01 00 02 07 00 03 07 00 3A 00 03 07 00 BC 07 00 A4 01 FF 00 1B 00 02 07 00 03 07 00 3A 00 02 07 00 BC 07 00 A4 FF 00 02 00 00 00 01 07 00 33 FF 00 00 00 02 07 00 03 07 00 3A 00 02 07 00 BC 07 00 A4 45 07 00 33 00 0A 41 01 1B FF 00 1C 00 02 07 00 03 07 00 3A 00 04 07 00 BC 08 04 52 08 04 52 07 00 48 FF 00 01 00 02 07 00 03 07 00 3A 00 05 07 00 BC 08 04 52 08 04 52 07 00 48 01 FF 00 1C 00 02 07 00 03 07 00 3A 00 04 07 00 BC 08 04 52 08 04 52 07 00 48 FF 00 0D 00 02 07 00 03 07 00 3A 00 04 07 00 BC 08 04 52 08 04 52 07 00 4E FF 00 01 00 02 07 00 03 07 00 3A 00 05 07 00 BC 08 04 52 08 04 52 07 00 4E 01 FF 00 1B 00 02 07 00 03 07 00 3A 00 04 07 00 BC 08 04 52 08 04 52 07 00 4E 5E 07 00 33 FF 00 00 00 02 07 00 03 07 00 3A 00 07 07 00 BC 08 04 52 08 04 52 03 03 03 01 45 07 00 33 FF 00 00 00 02 07 00 03 07 00 3A 00 02 07 00 BC 07 00 A4 42 07 00 33 FF 00 00 00 02 07 00 03 07 00 3A 00 02 07 00 BC 07 00 A4 45 07 00 33 00 02 4E 07 00 48 FF 00 01 00 02 07 00 03 07 00 3A 00 02 07 00 48 01 5D 07 00 48 FF 00 1F 00 02 07 00 03 07 00 3A 00 05 07 00 BC 08 05 1A 08 05 1A 03 07 00 03 FF 00 01 00 02 07 00 03 07 00 3A 00 06 07 00 BC 08 05 1A 08 05 1A 03 07 00 03 01 FF 00 1D 00 02 07 00 03 07 00 3A 00 05 07 00 BC 08 05 1A 08 05 1A 03 07 00 03 FF 00 17 00 02 07 00 03 07 00 3A 00 05 07 00 BC 08 05 1A 08 05 1A 03 03 FF 00 01 00 02 07 00 03 07 00 3A 00 06 07 00 BC 08 05 1A 08 05 1A 03 03 01 FF 00 1D 00 02 07 00 03 07 00 3A 00 05 07 00 BC 08 05 1A 08 05 1A 03 03 FF 00 15 00 02 07 00 03 07 00 3A 00 07 07 00 BC 08 05 1A 08 05 1A 03 03 03 01 FF 00 01 00 02 07 00 03 07 00 3A 00 08 07 00 BC 08 05 1A 08 05 1A 03 03 03 01 01 FF 00 1B 00 02 07 00 03 07 00 3A 00 07 07 00 BC 08 05 1A 08 05 1A 03 03 03 01 FF 00 02 00 00 00 01 07 00 33 FF 00 00 00 02 07 00 03 07 00 3A 00 07 07 00 BC 08 05 1A 08 05 1A 03 03 03 01 45 07 00 33 FF 00 00 00 02 07 00 03 07 00 3A 00 02 07 00 BC 07 00 A4 42 07 00 33 FF 00 00 00 02 07 00 03 07 00 3A 00 02 07 00 BC 07 00 A4 45 07 00 33 00 4B 07 00 03 FF 00 01 00 02 07 00 03 07 00 3A 00 02 07 00 03 01 5B 07 00 03 50 07 00 4E FF 00 01 00 02 07 00 03 07 00 3A 00 02 07 00 4E 01 5C 07 00 4E FF 00 15 00 02 07 00 03 07 00 3A 00 04 07 00 BC 08 06 33 08 06 33 07 00 48 FF 00 01 00 02 07 00 03 07 00 3A 00 05 07 00 BC 08 06 33 08 06 33 07 00 48 01 FF 00 1B 00 02 07 00 03 07 00 3A 00 04 07 00 BC 08 06 33 08 06 33 07 00 48 FF 00 0D 00 02 07 00 03 07 00 3A 00 04 07 00 BC 08 06 33 08 06 33 07 00 4E FF 00 01 00 02 07 00 03 07 00 3A 00 05 07 00 BC 08 06 33 08 06 33 07 00 4E 01 FF 00 1B 00 02 07 00 03 07 00 3A 00 04 07 00 BC 08 06 33 08 06 33 07 00 4E FF 00 18 00 02 07 00 03 07 00 3A 00 06 07 00 BC 08 06 33 08 06 33 03 03 07 00 03 FF 00 01 00 02 07 00 03 07 00 3A 00 07 07 00 BC 08 06 33 08 06 33 03 03 07 00 03 01 FF 00 1C 00 02 07 00 03 07 00 3A 00 06 07 00 BC 08 06 33 08 06 33 03 03 07 00 03 FF 00 10 00 02 07 00 03 07 00 3A 00 06 07 00 BC 08 06 33 08 06 33 03 03 07 00 4E FF 00 01 00 02 07 00 03 07 00 3A 00 07 07 00 BC 08 06 33 08 06 33 03 03 07 00 4E 01 FF 00 1C 00 02 07 00 03 07 00 3A 00 06 07 00 BC 08 06 33 08 06 33 03 03 07 00 4E FF 00 0F 00 02 07 00 03 07 00 3A 00 07 07 00 BC 08 06 33 08 06 33 03 03 03 01 FF 00 02 00 02 07 00 03 07 00 3A 00 08 07 00 BC 08 06 33 08 06 33 03 03 03 01 01 FF 00 1C 00 02 07 00 03 07 00 3A 00 07 07 00 BC 08 06 33 08 06 33 03 03 03 01 42 07 00 33 FF 00 00 00 02 07 00 03 07 00 3A 00 07 07 00 BC 08 06 33 08 06 33 03 03 03 01 45 07 00 33 FF 00 00 00 02 07 00 03 07 00 3A 00 02 07 00 BC 07 00 A4 42 07 00 33 FF 00 00 00 02 07 00 03 07 00 3A 00 02 07 00 BC 07 00 A4 45 07 00 33 00 4C 07 00 03 FF 00 02 00 02 07 00 03 07 00 3A 00 02 07 00 03 01 5D 07 00 03 4E 07 00 48 FF 00 02 00 02 07 00 03 07 00 3A 00 02 07 00 48 01 5D 07 00 48 FF 00 16 00 02 07 00 03 07 00 3A 00 04 07 00 BC 08 07 A2 08 07 A2 07 00 03 FF 00 02 00 02 07 00 03 07 00 3A 00 05 07 00 BC 08 07 A2 08 07 A2 07 00 03 01 FF 00 1D 00 02 07 00 03 07 00 3A 00 04 07 00 BC 08 07 A2 08 07 A2 07 00 03 FF 00 22 00 02 07 00 03 07 00 3A 00 05 07 00 BC 08 07 A2 08 07 A2 03 03 FF 00 02 00 02 07 00 03 07 00 3A 00 06 07 00 BC 08 07 A2 08 07 A2 03 03 01 FF 00 1D 00 02 07 00 03 07 00 3A 00 05 07 00 BC 08 07 A2 08 07 A2 03 03 FF 00 0F 00 02 07 00 03 07 00 3A 00 06 07 00 BC 08 07 A2 08 07 A2 03 03 07 00 48 FF 00 02 00 02 07 00 03 07 00 3A 00 07 07 00 BC 08 07 A2 08 07 A2 03 03 07 00 48 01 FF 00 1C 00 02 07 00 03 07 00 3A 00 06 07 00 BC 08 07 A2 08 07 A2 03 03 07 00 48 49 07 00 13 FF 00 00 00 02 07 00 03 07 00 3A 00 07 07 00 BC 08 07 A2 08 07 A2 03 03 03 01 45 07 00 33 FF 00 00 00 02 07 00 03 07 00 3A 00 02 07 00 BC 07 00 A4 42 07 00 33 FF 00 00 00 02 07 00 03 07 00 3A 00 02 07 00 BC 07 00 A4 45 07 00 33 00 52 07 00 4E FF 00 02 00 02 07 00 03 07 00 3A 00 02 07 00 4E 01 5C 07 00 4E FF 00 12 00 02 07 00 03 07 00 3A 00 03 07 00 BC 08 08 9B 08 08 9B FF 00 02 00 02 07 00 03 07 00 3A 00 04 07 00 BC 08 08 9B 08 08 9B 01 FF 00 1D 00 02 07 00 03 07 00 3A 00 03 07 00 BC 08 08 9B 08 08 9B FF 00 12 00 02 07 00 03 07 00 3A 00 04 07 00 BC 08 08 9B 08 08 9B 07 00 4E FF 00 02 00 02 07 00 03 07 00 3A 00 05 07 00 BC 08 08 9B 08 08 9B 07 00 4E 01 FF 00 1D 00 02 07 00 03 07 00 3A 00 04 07 00 BC 08 08 9B 08 08 9B 07 00 4E FF 00 12 00 02 07 00 03 07 00 3A 00 05 07 00 BC 08 08 9B 08 08 9B 03 07 00 48 FF 00 02 00 02 07 00 03 07 00 3A 00 06 07 00 BC 08 08 9B 08 08 9B 03 07 00 48 01 FF 00 1D 00 02 07 00 03 07 00 3A 00 05 07 00 BC 08 08 9B 08 08 9B 03 07 00 48 FF 00 11 00 02 07 00 03 07 00 3A 00 05 07 00 BC 08 08 9B 08 08 9B 03 03 FF 00 02 00 02 07 00 03 07 00 3A 00 06 07 00 BC 08 08 9B 08 08 9B 03 03 01 FF 00 1E 00 02 07 00 03 07 00 3A 00 05 07 00 BC 08 08 9B 08 08 9B 03 03 FF 00 0F 00 02 07 00 03 07 00 3A 00 06 07 00 BC 08 08 9B 08 08 9B 03 03 07 00 48 FF 00 02 00 02 07 00 03 07 00 3A 00 07 07 00 BC 08 08 9B 08 08 9B 03 03 07 00 48 01 FF 00 1C 00 02 07 00 03 07 00 3A 00 06 07 00 BC 08 08 9B 08 08 9B 03 03 07 00 48 FF 00 12 00 02 07 00 03 07 00 3A 00 07 07 00 BC 08 08 9B 08 08 9B 03 03 03 01 FF 00 02 00 02 07 00 03 07 00 3A 00 08 07 00 BC 08 08 9B 08 08 9B 03 03 03 01 01 FF 00 1D 00 02 07 00 03 07 00 3A 00 07 07 00 BC 08 08 9B 08 08 9B 03 03 03 01 42 07 00 13 FF 00 00 00 02 07 00 03 07 00 3A 00 07 07 00 BC 08 08 9B 08 08 9B 03 03 03 01 45 07 00 33 FF 00 00 00 02 07 00 03 07 00 3A 00 02 07 00 BC 07 00 A4 FF 00 0B 00 02 07 00 03 07 00 3A 00 02 07 00 BC 07 00 A4 FF 00 02 00 02 07 00 03 07 00 3A 00 03 07 00 BC 07 00 A4 01 FF 00 1D 00 02 07 00 03 07 00 3A 00 02 07 00 BC 07 00 A4 42 07 00 33 FF 00 00 00 02 07 00 03 07 00 3A 00 02 07 00 BC 07 00 A4 45 07 00 33 00 02 0C 05 42 01 1B 0F 4F 07 00 48 FF 00 02 00 02 07 00 03 07 00 3A 00 02 07 00 48 01 5C 07 00 48 4E 07 00 4E FF 00 02 00 02 07 00 03 07 00 3A 00 02 07 00 4E 01 5D 07 00 4E 12 0B 42 01 1D FF 00 0C 00 02 07 00 03 07 00 3A 00 07 07 00 BC 08 02 4E 08 02 4E 03 03 03 01 01 FF 00 01 00 02 07 00 03 07 00 3A 00 06 07 00 BC 08 08 9B 08 08 9B 03 03 07 00 48 FF 00 01 00 02 07 00 03 07 00 3A 00 05 07 00 BC 08 07 A2 08 07 A2 03 03 FF 00 01 00 02 07 00 03 07 00 3A 00 07 07 00 BC 08 08 9B 08 08 9B 03 03 03 01 41 07 00 4E FF 00 01 00 02 07 00 03 07 00 3A 00 06 07 00 BC 08 03 3A 08 03 3A 03 03 07 00 4E FF 00 01 00 02 07 00 03 07 00 3A 00 04 07 00 BC 08 06 33 08 06 33 07 00 4E FF 00 01 00 02 07 00 03 07 00 3A 00 02 07 00 BC 07 00 A4 FF 00 01 00 02 07 00 03 07 00 3A 00 02 07 01 47 07 00 03 FF 00 01 00 02 07 00 03 07 00 3A 00 05 07 00 BC 08 08 9B 08 08 9B 03 03 41 07 00 03 41 07 00 4E FF 00 01 00 02 07 00 03 07 00 3A 00 06 07 00 BC 08 06 33 08 06 33 03 03 07 00 4E FF 00 01 00 02 07 00 03 07 00 3A 00 07 07 00 BC 08 06 33 08 06 33 03 03 03 01 FF 00 01 00 02 07 00 03 07 00 3A 00 04 07 00 BC 08 07 A2 08 07 A2 07 00 03 01 41 07 00 48 41 07 00 03 FF 00 01 00 02 07 00 03 07 00 3A 00 04 07 00 BC 08 04 52 08 04 52 07 00 48 FF 00 01 00 02 07 00 03 07 00 3A 00 05 07 00 BC 08 05 1A 08 05 1A 03 03 FF 00 01 00 02 07 00 03 07 00 3A 00 06 07 00 BC 08 02 4E 08 02 4E 03 03 07 00 03 41 07 00 3A FF 00 01 00 02 07 00 03 07 00 3A 00 02 07 00 BC 07 00 A4 41 07 00 03 FF 00 01 00 02 07 00 03 07 00 3A 00 07 07 00 BC 08 05 1A 08 05 1A 03 03 03 01 41 07 01 47 FF 00 01 00 02 07 00 03 07 00 3A 00 03 07 00 BC 08 08 9B 08 08 9B FF 00 01 00 02 07 00 03 07 00 3A 00 05 07 00 BC 08 05 1A 08 05 1A 03 07 00 03 41 07 00 4E 41 07 00 03 41 07 00 48 FF 00 01 00 02 07 00 03 07 00 3A 00 05 07 00 BC 08 08 9B 08 08 9B 03 07 00 48 41 07 00 48 41 07 00 48 FF 00 01 00 02 07 00 03 07 00 3A 00 06 07 00 BC 08 06 33 08 06 33 03 03 07 00 03 FF 00 01 00 02 07 00 03 07 00 3A 00 04 07 00 BC 08 08 9B 08 08 9B 07 00 4E FF 00 01 00 02 07 00 03 07 00 3A 00 04 07 00 BC 08 06 33 08 06 33 07 00 48 FF 00 01 00 02 07 00 03 07 00 3A 00 06 07 00 BC 08 07 A2 08 07 A2 03 03 07 00 48 FF 00 01 00 02 07 00 03 07 00 3A 00 04 07 00 BC 08 03 3A 08 03 3A 07 00 4E FF 00 01 00 02 07 00 03 07 00 3A 00 05 07 00 BC 08 03 3A 08 03 3A 03 03 01 41 07 00 48 41 07 00 03 FF 00 01 00 02 07 00 03 07 00 3A 00 04 07 00 BC 08 04 52 08 04 52 07 00 4E 41 07 00 33 43 05 44 07 00 33 47 05 47 07 00 33
        //    Exceptions:
        //  Try           Handler
        //  Start  End    Start  End    Type                                       
        //  -----  -----  -----  -----  -------------------------------------------
        //  8      20     2916   2924   Any
        //  2916   2924   2916   2924   Any
        //  2932   2934   3      8      Ljava/lang/NegativeArraySizeException;
        //  72     78     78     79     Any
        //  72     78     3      8      Any
        //  72     78     3      8      Ljava/lang/ArithmeticException;
        //  72     78     78     79     Any
        //  72     78     78     79     Any
        //  240    247    247    248    Any
        //  240    247    247    248    Any
        //  241    247    240    241    Any
        //  241    247    3      8      Ljava/lang/NegativeArraySizeException;
        //  240    247    247    248    Any
        //  305    312    312    313    Any
        //  306    312    3      8      Any
        //  306    312    312    313    Ljava/lang/StringIndexOutOfBoundsException;
        //  305    312    305    306    Any
        //  306    312    305    306    Any
        //  319    326    326    327    Any
        //  320    326    319    320    Ljava/lang/RuntimeException;
        //  319    326    326    327    Ljava/lang/IllegalArgumentException;
        //  320    326    326    327    Ljava/lang/EnumConstantNotPresentException;
        //  319    326    326    327    Any
        //  333    340    340    341    Any
        //  334    340    333    334    Ljava/lang/UnsupportedOperationException;
        //  334    340    333    334    Ljava/util/NoSuchElementException;
        //  333    340    333    334    Ljava/lang/StringIndexOutOfBoundsException;
        //  333    340    333    334    Ljava/lang/StringIndexOutOfBoundsException;
        //  442    449    449    450    Any
        //  442    449    3      8      Any
        //  443    449    442    443    Any
        //  442    449    3      8      Ljava/lang/IndexOutOfBoundsException;
        //  443    449    449    450    Ljava/util/NoSuchElementException;
        //  456    463    463    464    Any
        //  457    463    3      8      Any
        //  456    463    3      8      Any
        //  457    463    456    457    Any
        //  457    463    463    464    Ljava/lang/UnsupportedOperationException;
        //  715    722    722    723    Any
        //  715    722    3      8      Any
        //  716    722    715    716    Ljava/lang/AssertionError;
        //  716    722    722    723    Ljava/lang/IllegalStateException;
        //  716    722    722    723    Ljava/util/ConcurrentModificationException;
        //  726    733    733    734    Any
        //  727    733    726    727    Ljava/lang/EnumConstantNotPresentException;
        //  726    733    726    727    Ljava/lang/NumberFormatException;
        //  727    733    733    734    Any
        //  726    733    733    734    Ljava/util/ConcurrentModificationException;
        //  995    1002   1002   1003   Any
        //  996    1002   995    996    Ljava/lang/ArrayIndexOutOfBoundsException;
        //  995    1002   3      8      Any
        //  995    1002   995    996    Any
        //  996    1002   3      8      Any
        //  1048   1054   1054   1055   Any
        //  1048   1054   1054   1055   Ljava/lang/ArrayIndexOutOfBoundsException;
        //  1048   1054   3      8      Ljava/lang/IllegalStateException;
        //  1048   1054   3      8      Ljava/lang/NegativeArraySizeException;
        //  1048   1054   3      8      Any
        //  1231   1238   1238   1239   Any
        //  1231   1238   3      8      Any
        //  1231   1238   1238   1239   Ljava/util/NoSuchElementException;
        //  1232   1238   1231   1232   Any
        //  1231   1238   3      8      Ljava/lang/EnumConstantNotPresentException;
        //  1242   1249   1249   1250   Any
        //  1242   1249   1242   1243   Any
        //  1243   1249   1249   1250   Ljava/lang/RuntimeException;
        //  1242   1249   1249   1250   Ljava/util/ConcurrentModificationException;
        //  1242   1249   3      8      Any
        //  1476   1482   1482   1483   Any
        //  1476   1482   3      8      Any
        //  1476   1482   3      8      Any
        //  1476   1482   1482   1483   Ljava/lang/NumberFormatException;
        //  1476   1482   3      8      Ljava/lang/UnsupportedOperationException;
        //  1486   1493   1493   1494   Any
        //  1487   1493   1486   1487   Ljava/lang/IllegalStateException;
        //  1486   1493   1486   1487   Ljava/lang/NumberFormatException;
        //  1486   1493   1486   1487   Any
        //  1487   1493   1486   1487   Any
        //  1835   1842   1842   1843   Any
        //  1836   1842   1842   1843   Ljava/lang/IndexOutOfBoundsException;
        //  1835   1842   1842   1843   Any
        //  1836   1842   1835   1836   Any
        //  1835   1842   3      8      Ljava/util/ConcurrentModificationException;
        //  1846   1853   1853   1854   Any
        //  1846   1853   1846   1847   Ljava/lang/UnsupportedOperationException;
        //  1847   1853   3      8      Any
        //  1847   1853   1846   1847   Ljava/lang/NegativeArraySizeException;
        //  1846   1853   1846   1847   Any
        //  2130   2137   2137   2138   Any
        //  2131   2137   2130   2131   Ljava/lang/IndexOutOfBoundsException;
        //  2131   2137   3      8      Any
        //  2130   2137   2130   2131   Ljava/lang/NumberFormatException;
        //  2130   2137   2137   2138   Ljava/lang/EnumConstantNotPresentException;
        //  2141   2148   2148   2149   Any
        //  2141   2148   2141   2142   Ljava/lang/AssertionError;
        //  2141   2148   2141   2142   Ljava/lang/StringIndexOutOfBoundsException;
        //  2142   2148   2148   2149   Ljava/lang/ArithmeticException;
        //  2142   2148   2141   2142   Any
        //  2511   2518   2518   2519   Any
        //  2512   2518   2511   2512   Ljava/lang/StringIndexOutOfBoundsException;
        //  2512   2518   2518   2519   Ljava/lang/NullPointerException;
        //  2512   2518   2511   2512   Ljava/lang/IllegalStateException;
        //  2512   2518   2518   2519   Any
        //  2567   2574   2574   2575   Any
        //  2568   2574   3      8      Ljava/lang/ClassCastException;
        //  2568   2574   3      8      Ljava/util/ConcurrentModificationException;
        //  2568   2574   2574   2575   Ljava/lang/RuntimeException;
        //  2567   2574   2567   2568   Any
        // 
        // The error that occurred was:
        // 
        // java.lang.IndexOutOfBoundsException: Index -1 out of bounds for length 0
        //     at java.base/jdk.internal.util.Preconditions.outOfBounds(Preconditions.java:64)
        //     at java.base/jdk.internal.util.Preconditions.outOfBoundsCheckIndex(Preconditions.java:70)
        //     at java.base/jdk.internal.util.Preconditions.checkIndex(Preconditions.java:248)
        //     at java.base/java.util.Objects.checkIndex(Objects.java:372)
        //     at java.base/java.util.ArrayList.remove(ArrayList.java:535)
        //     at com.strobel.assembler.ir.StackMappingVisitor.pop(StackMappingVisitor.java:267)
        //     at com.strobel.assembler.ir.StackMappingVisitor$InstructionAnalyzer.execute(StackMappingVisitor.java:595)
        //     at com.strobel.assembler.ir.StackMappingVisitor$InstructionAnalyzer.visit(StackMappingVisitor.java:398)
        //     at com.strobel.decompiler.ast.AstBuilder.performStackAnalysis(AstBuilder.java:2030)
        //     at com.strobel.decompiler.ast.AstBuilder.build(AstBuilder.java:108)
        //     at com.strobel.decompiler.languages.java.ast.AstMethodBodyBuilder.createMethodBody(AstMethodBodyBuilder.java:211)
        //     at com.strobel.decompiler.languages.java.ast.AstMethodBodyBuilder.createMethodBody(AstMethodBodyBuilder.java:99)
        //     at com.strobel.decompiler.languages.java.ast.AstBuilder.createMethodBody(AstBuilder.java:782)
        //     at com.strobel.decompiler.languages.java.ast.AstBuilder.createMethod(AstBuilder.java:675)
        //     at com.strobel.decompiler.languages.java.ast.AstBuilder.addTypeMembers(AstBuilder.java:552)
        //     at com.strobel.decompiler.languages.java.ast.AstBuilder.createTypeCore(AstBuilder.java:519)
        //     at com.strobel.decompiler.languages.java.ast.AstBuilder.createTypeNoCache(AstBuilder.java:161)
        //     at com.strobel.decompiler.languages.java.ast.AstBuilder.createType(AstBuilder.java:150)
        //     at com.strobel.decompiler.languages.java.ast.AstBuilder.addType(AstBuilder.java:125)
        //     at com.strobel.decompiler.languages.java.JavaLanguage.buildAst(JavaLanguage.java:71)
        //     at com.strobel.decompiler.languages.java.JavaLanguage.decompileType(JavaLanguage.java:59)
        //     at com.strobel.decompiler.DecompilerDriver.decompileType(DecompilerDriver.java:330)
        //     at com.strobel.decompiler.DecompilerDriver.decompileJar(DecompilerDriver.java:251)
        //     at com.strobel.decompiler.DecompilerDriver.main(DecompilerDriver.java:126)
        // 
        throw new IllegalStateException("An error occurred while decompiling this method.");
    }
    
    @f06
    @LauncherEventHide
    public void c(final f3h f3h) {
        fbS.hF(this, 1068393565, f3h);
    }
    
    public void c(final Entity entity) {
        fbS.hc(this, 1297204826, entity);
    }
    
    static {
        throw t;
    }
    
    public f5i() {
        // 
        // This method could not be decompiled.
        // 
        // Original Bytecode:
        // 
        //     3: ifeq            12
        //     6: ldc_w           1181044423
        //     9: goto            15
        //    12: ldc_w           761502875
        //    15: ldc_w           419917287
        //    18: ixor           
        //    19: lookupswitch {
        //          879030652: 44
        //          1600267040: 12
        //          default: 199
        //        }
        //    44: aload_0        
        //    45: ldc_w           "\u23d5\u1481\u8ace\ub3cd\uc9b4\uedd3\ub225\ue6e6\ud97b"
        //    48: invokestatic    invokestatic   !!! ERROR
        //    51: ldc_w           "\u23f5\u1481\u8ace\ub3cd\uc9b4\uedd3\ub225\ue6e6\ud97b"
        //    54: invokestatic    invokestatic   !!! ERROR
        //    57: ldc_w           "\u23f2\u1496\u8ac6\ub3d5\uc9fd\uedd1\ub264\ue6e9\ud97a\ue9c7\ua704\u1e45\ue1cd\uc5a6\u8145\u890b\u57ac\u7726\ubd29\uc032\u2b2b\uc235\u6a67\u2d53\ud7ba\u35b6\u7d39\u899d\u8051\u8ce8\u8482\ufb26\u70f9\u9a15\u1bf0"
        //    60: invokestatic    invokestatic   !!! ERROR
        //    63: getstatic       dev/nuker/pyro/fc.0:I
        //    66: ifeq            75
        //    69: ldc_w           -660854956
        //    72: goto            78
        //    75: ldc_w           1034456788
        //    78: ldc_w           1690341564
        //    81: ixor           
        //    82: lookupswitch {
        //          -1134774296: 75
        //          1499995752: 108
        //          default: 201
        //        }
        //   108: invokespecial   dev/nuker/pyro/fH.<init>:(Ljava/lang/String;Ljava/lang/String;Ljava/lang/String;)V
        //   111: aload_0        
        //   112: new             Ldev/nuker/pyro/f0f;
        //   115: dup            
        //   116: ldc_w           "\u23db\u149c\u8ac3\ub3dc"
        //   119: invokestatic    invokestatic   !!! ERROR
        //   122: ldc_w           "\u23fb\u149c\u8ac3\ub3dc"
        //   125: invokestatic    invokestatic   !!! ERROR
        //   128: ldc_w           "\u23e2\u149b\u8ac2\ub399\uc9b0\ueddf\ub220\ue6ef\ud928\ue9c1\ua716\u1e0c\ue1cd\uc5b5\u8140\u895f\u57ad\u772c\ubd3c\uc07e\u2b37\uc27b\u6a33\u2d59\ud7ec\u35b7\u7d24"
        //   131: invokestatic    invokestatic   !!! ERROR
        //   134: getstatic       dev/nuker/pyro/f5h.c:Ldev/nuker/pyro/f5h;
        //   137: invokespecial   dev/nuker/pyro/f0f.<init>:(Ljava/lang/String;Ljava/lang/String;Ljava/lang/String;Ljava/lang/Enum;)V
        //   140: putfield        dev/nuker/pyro/f5i.c:Ldev/nuker/pyro/f0f;
        //   143: aload_0        
        //   144: aload_0        
        //   145: getfield        dev/nuker/pyro/f5i.c:Ldev/nuker/pyro/f0f;
        //   148: getstatic       dev/nuker/pyro/fc.0:I
        //   151: ifeq            160
        //   154: ldc_w           -1174543925
        //   157: goto            163
        //   160: ldc_w           -742816683
        //   163: ldc_w           -1501788714
        //   166: ixor           
        //   167: lookupswitch {
        //          181370072: 160
        //          528573469: 197
        //          default: 192
        //        }
        //   192: invokevirtual   dev/nuker/pyro/f5i.c:(Ldev/nuker/pyro/f0n;)Ldev/nuker/pyro/f0n;
        //   195: pop            
        //   196: return         
        //   197: aconst_null    
        //   198: athrow         
        //   199: aconst_null    
        //   200: athrow         
        //   201: aconst_null    
        //   202: athrow         
        //    StackMapTable: 00 0C 0C 42 01 1C FF 00 1E 00 01 06 00 04 06 07 01 80 07 01 80 07 01 80 FF 00 02 00 01 06 00 05 06 07 01 80 07 01 80 07 01 80 01 FF 00 1D 00 01 06 00 04 06 07 01 80 07 01 80 07 01 80 FF 00 33 00 01 07 00 03 00 02 07 00 03 07 00 8F FF 00 02 00 01 07 00 03 00 03 07 00 03 07 00 8F 01 FF 00 1C 00 01 07 00 03 00 02 07 00 03 07 00 8F FF 00 04 00 01 07 00 03 00 02 07 00 03 07 00 8F FF 00 01 00 01 06 00 00 FF 00 01 00 01 06 00 04 06 07 01 80 07 01 80 07 01 80
        // 
        // The error that occurred was:
        // 
        // java.lang.IllegalStateException: Invalid BootstrapMethods attribute entry: 21 additional arguments required for method a.a, but only 0 specified.
        //     at com.strobel.assembler.ir.Error.invalidBootstrapMethodEntry(Error.java:244)
        //     at com.strobel.assembler.ir.MetadataReader.readAttributeCore(MetadataReader.java:280)
        //     at com.strobel.assembler.metadata.ClassFileReader.readAttributeCore(ClassFileReader.java:261)
        //     at com.strobel.assembler.ir.MetadataReader.inflateAttributes(MetadataReader.java:439)
        //     at com.strobel.assembler.metadata.ClassFileReader.visitAttributes(ClassFileReader.java:1134)
        //     at com.strobel.assembler.metadata.ClassFileReader.readClass(ClassFileReader.java:439)
        //     at com.strobel.assembler.metadata.ClassFileReader.readClass(ClassFileReader.java:377)
        //     at com.strobel.assembler.metadata.MetadataSystem.resolveType(MetadataSystem.java:129)
        //     at com.strobel.decompiler.NoRetryMetadataSystem.resolveType(DecompilerDriver.java:476)
        //     at com.strobel.assembler.metadata.MetadataSystem.resolveCore(MetadataSystem.java:81)
        //     at com.strobel.assembler.metadata.MetadataResolver.resolve(MetadataResolver.java:104)
        //     at com.strobel.assembler.metadata.CoreMetadataFactory$UnresolvedType.resolve(CoreMetadataFactory.java:616)
        //     at com.strobel.assembler.metadata.MetadataResolver.resolve(MetadataResolver.java:128)
        //     at com.strobel.assembler.metadata.CoreMetadataFactory$UnresolvedType.resolve(CoreMetadataFactory.java:626)
        //     at com.strobel.assembler.metadata.MethodReference.resolve(MethodReference.java:177)
        //     at com.strobel.decompiler.ast.TypeAnalysis.inferCall(TypeAnalysis.java:2438)
        //     at com.strobel.decompiler.ast.TypeAnalysis.doInferTypeForExpression(TypeAnalysis.java:1029)
        //     at com.strobel.decompiler.ast.TypeAnalysis.inferTypeForExpression(TypeAnalysis.java:803)
        //     at com.strobel.decompiler.ast.TypeAnalysis.inferTypeForExpression(TypeAnalysis.java:770)
        //     at com.strobel.decompiler.ast.TypeAnalysis.doInferTypeForExpression(TypeAnalysis.java:881)
        //     at com.strobel.decompiler.ast.TypeAnalysis.inferTypeForExpression(TypeAnalysis.java:803)
        //     at com.strobel.decompiler.ast.TypeAnalysis.runInference(TypeAnalysis.java:672)
        //     at com.strobel.decompiler.ast.TypeAnalysis.runInference(TypeAnalysis.java:655)
        //     at com.strobel.decompiler.ast.TypeAnalysis.runInference(TypeAnalysis.java:365)
        //     at com.strobel.decompiler.ast.TypeAnalysis.run(TypeAnalysis.java:96)
        //     at com.strobel.decompiler.ast.AstOptimizer.optimize(AstOptimizer.java:109)
        //     at com.strobel.decompiler.ast.AstOptimizer.optimize(AstOptimizer.java:42)
        //     at com.strobel.decompiler.languages.java.ast.AstMethodBodyBuilder.createMethodBody(AstMethodBodyBuilder.java:214)
        //     at com.strobel.decompiler.languages.java.ast.AstMethodBodyBuilder.createMethodBody(AstMethodBodyBuilder.java:99)
        //     at com.strobel.decompiler.languages.java.ast.AstBuilder.createMethodBody(AstBuilder.java:782)
        //     at com.strobel.decompiler.languages.java.ast.AstBuilder.createConstructor(AstBuilder.java:713)
        //     at com.strobel.decompiler.languages.java.ast.AstBuilder.addTypeMembers(AstBuilder.java:549)
        //     at com.strobel.decompiler.languages.java.ast.AstBuilder.createTypeCore(AstBuilder.java:519)
        //     at com.strobel.decompiler.languages.java.ast.AstBuilder.createTypeNoCache(AstBuilder.java:161)
        //     at com.strobel.decompiler.languages.java.ast.AstBuilder.createType(AstBuilder.java:150)
        //     at com.strobel.decompiler.languages.java.ast.AstBuilder.addType(AstBuilder.java:125)
        //     at com.strobel.decompiler.languages.java.JavaLanguage.buildAst(JavaLanguage.java:71)
        //     at com.strobel.decompiler.languages.java.JavaLanguage.decompileType(JavaLanguage.java:59)
        //     at com.strobel.decompiler.DecompilerDriver.decompileType(DecompilerDriver.java:330)
        //     at com.strobel.decompiler.DecompilerDriver.decompileJar(DecompilerDriver.java:251)
        //     at com.strobel.decompiler.DecompilerDriver.main(DecompilerDriver.java:126)
        // 
        throw new IllegalStateException("An error occurred while decompiling this method.");
    }
}
