// 
// Decompiled by Procyon v0.5.36
// 

package dev.nuker.pyro;

public class f5l extends fH
{
    public f0f<f5k> c;
    public f0g c;
    public boolean[] c;
    
    public String c(final int n) {
        return fbS.fL(this, 231996266, n);
    }
    
    static {
        throw t;
    }
    
    public f5l() {
        // 
        // This method could not be decompiled.
        // 
        // Original Bytecode:
        // 
        //     1: ldc             "\u23d1\u1486\u8ad6\ub3d8\uc9b8\uedda\ub228\ue6e0\ud97c\ue9d0\ua712\u1e40\ue1c8\uc5b5\u815a"
        //     3: getstatic       dev/nuker/pyro/fc.0:I
        //     6: ifeq            14
        //     9: ldc             -762797788
        //    11: goto            16
        //    14: ldc             316092109
        //    16: ldc             -927767436
        //    18: ixor           
        //    19: lookupswitch {
        //          307204587: 14
        //          440124752: 371
        //          default: 44
        //        }
        //    44: invokestatic    invokestatic   !!! ERROR
        //    47: ldc             "\u23f1\u1486\u8ad6\ub3d8\uc9b8\uedda\ub228\ue6e0\ud97c\ue9d0\ua732\u1e40\ue1c8\uc5b5\u815a"
        //    49: invokestatic    invokestatic   !!! ERROR
        //    52: ldc             "\u23fb\u149c\u8ad0\ub3d0\uc9bc\uedda\ub221\ue6fa\ud928\ue9d0\ua71c\u1e59\ue18d\uc5ae\u8148\u8908\u57bd\u7723\ubd28\uc067\u2b67\uc23a\u6a36\u2d5b\ud7a4\u35a2\u7d6b\u898e\u8002\u8cae\u8499\ufb3d\u70ec\u9a58"
        //    54: invokestatic    invokestatic   !!! ERROR
        //    57: getstatic       dev/nuker/pyro/fc.c:I
        //    60: ifge            68
        //    63: ldc             -116566831
        //    65: goto            70
        //    68: ldc             -1070515204
        //    70: ldc             28897323
        //    72: ixor           
        //    73: lookupswitch {
        //          -1047933993: 100
        //          -122313478: 68
        //          default: 373
        //        }
        //   100: invokespecial   dev/nuker/pyro/fH.<init>:(Ljava/lang/String;Ljava/lang/String;Ljava/lang/String;)V
        //   103: aload_0        
        //   104: new             Ldev/nuker/pyro/f0f;
        //   107: dup            
        //   108: ldc             "\u23d1\u149a\u8ad7\ub3c9\uc9b6\uedd2\ub23d"
        //   110: invokestatic    invokestatic   !!! ERROR
        //   113: ldc             "\u23f1\u149a\u8ad7\ub3c9\uc9b6\uedd2\ub23d"
        //   115: invokestatic    invokestatic   !!! ERROR
        //   118: aconst_null    
        //   119: getstatic       dev/nuker/pyro/f5k.0:Ldev/nuker/pyro/f5k;
        //   122: getstatic       dev/nuker/pyro/fc.1:I
        //   125: ifeq            133
        //   128: ldc             -1907316845
        //   130: goto            135
        //   133: ldc             306113393
        //   135: ldc             -306083376
        //   137: ixor           
        //   138: lookupswitch {
        //          589266742: 133
        //          1670458947: 379
        //          default: 164
        //        }
        //   164: invokespecial   dev/nuker/pyro/f0f.<init>:(Ljava/lang/String;Ljava/lang/String;Ljava/lang/String;Ljava/lang/Enum;)V
        //   167: putfield        dev/nuker/pyro/f5l.c:Ldev/nuker/pyro/f0f;
        //   170: aload_0        
        //   171: new             Ldev/nuker/pyro/f0g;
        //   174: dup            
        //   175: ldc             "\u23d1\u1486\u8ad6\ub3d8\uc9b8\uedda\ub228\ue6e0\ud97c\ue9d0"
        //   177: getstatic       dev/nuker/pyro/fc.c:I
        //   180: ifge            188
        //   183: ldc             188165290
        //   185: goto            190
        //   188: ldc             2087143367
        //   190: ldc             -238883800
        //   192: ixor           
        //   193: lookupswitch {
        //          -1918522385: 220
        //          -84557694: 188
        //          default: 369
        //        }
        //   220: invokestatic    invokestatic   !!! ERROR
        //   223: ldc             "\u23f1\u1486\u8ad6\ub3d8\uc9b8\uedda\ub228\ue6e0\ud97c\ue9d0"
        //   225: getstatic       dev/nuker/pyro/fc.1:I
        //   228: ifeq            236
        //   231: ldc             1855453851
        //   233: goto            238
        //   236: ldc             -252555319
        //   238: ldc             -1624329574
        //   240: ixor           
        //   241: lookupswitch {
        //          -239515647: 236
        //          1876753747: 268
        //          default: 377
        //        }
        //   268: invokestatic    invokestatic   !!! ERROR
        //   271: aconst_null    
        //   272: bipush          40
        //   274: iconst_0       
        //   275: bipush          100
        //   277: invokespecial   dev/nuker/pyro/f0g.<init>:(Ljava/lang/String;Ljava/lang/String;Ljava/lang/String;III)V
        //   280: putfield        dev/nuker/pyro/f5l.c:Ldev/nuker/pyro/f0g;
        //   283: aload_0        
        //   284: iconst_4       
        //   285: newarray        Z
        //   287: dup            
        //   288: iconst_0       
        //   289: iconst_0       
        //   290: bastore        
        //   291: dup            
        //   292: iconst_1       
        //   293: iconst_0       
        //   294: bastore        
        //   295: dup            
        //   296: iconst_2       
        //   297: iconst_0       
        //   298: bastore        
        //   299: dup            
        //   300: iconst_3       
        //   301: iconst_0       
        //   302: bastore        
        //   303: putfield        dev/nuker/pyro/f5l.c:[Z
        //   306: aload_0        
        //   307: aload_0        
        //   308: getstatic       dev/nuker/pyro/fc.c:I
        //   311: ifge            319
        //   314: ldc             -371647822
        //   316: goto            321
        //   319: ldc             2093455695
        //   321: ldc             -1253553226
        //   323: ixor           
        //   324: lookupswitch {
        //          -913321223: 352
        //          1553027332: 319
        //          default: 375
        //        }
        //   352: getfield        dev/nuker/pyro/f5l.c:Ldev/nuker/pyro/f0f;
        //   355: invokevirtual   dev/nuker/pyro/f5l.c:(Ldev/nuker/pyro/f0n;)Ldev/nuker/pyro/f0n;
        //   358: pop            
        //   359: aload_0        
        //   360: aload_0        
        //   361: getfield        dev/nuker/pyro/f5l.c:Ldev/nuker/pyro/f0g;
        //   364: invokevirtual   dev/nuker/pyro/f5l.c:(Ldev/nuker/pyro/f0n;)Ldev/nuker/pyro/f0n;
        //   367: pop            
        //   368: return         
        //   369: aconst_null    
        //   370: athrow         
        //   371: aconst_null    
        //   372: athrow         
        //   373: aconst_null    
        //   374: athrow         
        //   375: aconst_null    
        //   376: athrow         
        //   377: aconst_null    
        //   378: athrow         
        //   379: aconst_null    
        //   380: athrow         
        //    StackMapTable: 00 18 FF 00 0E 00 01 06 00 02 06 07 00 63 FF 00 01 00 01 06 00 03 06 07 00 63 01 FF 00 1B 00 01 06 00 02 06 07 00 63 FF 00 17 00 01 06 00 04 06 07 00 63 07 00 63 07 00 63 FF 00 01 00 01 06 00 05 06 07 00 63 07 00 63 07 00 63 01 FF 00 1D 00 01 06 00 04 06 07 00 63 07 00 63 07 00 63 FF 00 20 00 01 07 00 03 00 07 07 00 03 08 00 68 08 00 68 07 00 63 07 00 63 05 07 00 3A FF 00 01 00 01 07 00 03 00 08 07 00 03 08 00 68 08 00 68 07 00 63 07 00 63 05 07 00 3A 01 FF 00 1C 00 01 07 00 03 00 07 07 00 03 08 00 68 08 00 68 07 00 63 07 00 63 05 07 00 3A FF 00 17 00 01 07 00 03 00 04 07 00 03 08 00 AB 08 00 AB 07 00 63 FF 00 01 00 01 07 00 03 00 05 07 00 03 08 00 AB 08 00 AB 07 00 63 01 FF 00 1D 00 01 07 00 03 00 04 07 00 03 08 00 AB 08 00 AB 07 00 63 FF 00 0F 00 01 07 00 03 00 05 07 00 03 08 00 AB 08 00 AB 07 00 63 07 00 63 FF 00 01 00 01 07 00 03 00 06 07 00 03 08 00 AB 08 00 AB 07 00 63 07 00 63 01 FF 00 1D 00 01 07 00 03 00 05 07 00 03 08 00 AB 08 00 AB 07 00 63 07 00 63 FF 00 32 00 01 07 00 03 00 02 07 00 03 07 00 03 FF 00 01 00 01 07 00 03 00 03 07 00 03 07 00 03 01 FF 00 1E 00 01 07 00 03 00 02 07 00 03 07 00 03 FF 00 10 00 01 07 00 03 00 04 07 00 03 08 00 AB 08 00 AB 07 00 63 FF 00 01 00 01 06 00 02 06 07 00 63 FF 00 01 00 01 06 00 04 06 07 00 63 07 00 63 07 00 63 FF 00 01 00 01 07 00 03 00 02 07 00 03 07 00 03 FF 00 01 00 01 07 00 03 00 05 07 00 03 08 00 AB 08 00 AB 07 00 63 07 00 63 FF 00 01 00 01 07 00 03 00 07 07 00 03 08 00 68 08 00 68 07 00 63 07 00 63 05 07 00 3A
        // 
        // The error that occurred was:
        // 
        // java.lang.IllegalStateException: Invalid BootstrapMethods attribute entry: 21 additional arguments required for method a.a, but only 0 specified.
        //     at com.strobel.assembler.ir.Error.invalidBootstrapMethodEntry(Error.java:244)
        //     at com.strobel.assembler.ir.MetadataReader.readAttributeCore(MetadataReader.java:280)
        //     at com.strobel.assembler.metadata.ClassFileReader.readAttributeCore(ClassFileReader.java:261)
        //     at com.strobel.assembler.ir.MetadataReader.inflateAttributes(MetadataReader.java:439)
        //     at com.strobel.assembler.metadata.ClassFileReader.visitAttributes(ClassFileReader.java:1134)
        //     at com.strobel.assembler.metadata.ClassFileReader.readClass(ClassFileReader.java:439)
        //     at com.strobel.assembler.metadata.ClassFileReader.readClass(ClassFileReader.java:377)
        //     at com.strobel.assembler.metadata.MetadataSystem.resolveType(MetadataSystem.java:129)
        //     at com.strobel.decompiler.NoRetryMetadataSystem.resolveType(DecompilerDriver.java:476)
        //     at com.strobel.assembler.metadata.MetadataSystem.resolveCore(MetadataSystem.java:81)
        //     at com.strobel.assembler.metadata.MetadataResolver.resolve(MetadataResolver.java:104)
        //     at com.strobel.assembler.metadata.CoreMetadataFactory$UnresolvedType.resolve(CoreMetadataFactory.java:616)
        //     at com.strobel.assembler.metadata.MetadataResolver.resolve(MetadataResolver.java:128)
        //     at com.strobel.assembler.metadata.CoreMetadataFactory$UnresolvedType.resolve(CoreMetadataFactory.java:626)
        //     at com.strobel.assembler.metadata.MethodReference.resolve(MethodReference.java:177)
        //     at com.strobel.decompiler.ast.TypeAnalysis.inferCall(TypeAnalysis.java:2438)
        //     at com.strobel.decompiler.ast.TypeAnalysis.doInferTypeForExpression(TypeAnalysis.java:1029)
        //     at com.strobel.decompiler.ast.TypeAnalysis.inferTypeForExpression(TypeAnalysis.java:803)
        //     at com.strobel.decompiler.ast.TypeAnalysis.inferTypeForExpression(TypeAnalysis.java:770)
        //     at com.strobel.decompiler.ast.TypeAnalysis.doInferTypeForExpression(TypeAnalysis.java:881)
        //     at com.strobel.decompiler.ast.TypeAnalysis.inferTypeForExpression(TypeAnalysis.java:803)
        //     at com.strobel.decompiler.ast.TypeAnalysis.runInference(TypeAnalysis.java:672)
        //     at com.strobel.decompiler.ast.TypeAnalysis.runInference(TypeAnalysis.java:655)
        //     at com.strobel.decompiler.ast.TypeAnalysis.runInference(TypeAnalysis.java:365)
        //     at com.strobel.decompiler.ast.TypeAnalysis.run(TypeAnalysis.java:96)
        //     at com.strobel.decompiler.ast.AstOptimizer.optimize(AstOptimizer.java:109)
        //     at com.strobel.decompiler.ast.AstOptimizer.optimize(AstOptimizer.java:42)
        //     at com.strobel.decompiler.languages.java.ast.AstMethodBodyBuilder.createMethodBody(AstMethodBodyBuilder.java:214)
        //     at com.strobel.decompiler.languages.java.ast.AstMethodBodyBuilder.createMethodBody(AstMethodBodyBuilder.java:99)
        //     at com.strobel.decompiler.languages.java.ast.AstBuilder.createMethodBody(AstBuilder.java:782)
        //     at com.strobel.decompiler.languages.java.ast.AstBuilder.createConstructor(AstBuilder.java:713)
        //     at com.strobel.decompiler.languages.java.ast.AstBuilder.addTypeMembers(AstBuilder.java:549)
        //     at com.strobel.decompiler.languages.java.ast.AstBuilder.createTypeCore(AstBuilder.java:519)
        //     at com.strobel.decompiler.languages.java.ast.AstBuilder.createTypeNoCache(AstBuilder.java:161)
        //     at com.strobel.decompiler.languages.java.ast.AstBuilder.createType(AstBuilder.java:150)
        //     at com.strobel.decompiler.languages.java.ast.AstBuilder.addType(AstBuilder.java:125)
        //     at com.strobel.decompiler.languages.java.JavaLanguage.buildAst(JavaLanguage.java:71)
        //     at com.strobel.decompiler.languages.java.JavaLanguage.decompileType(JavaLanguage.java:59)
        //     at com.strobel.decompiler.DecompilerDriver.decompileType(DecompilerDriver.java:330)
        //     at com.strobel.decompiler.DecompilerDriver.decompileJar(DecompilerDriver.java:251)
        //     at com.strobel.decompiler.DecompilerDriver.main(DecompilerDriver.java:126)
        // 
        throw new IllegalStateException("An error occurred while decompiling this method.");
    }
    
    @f06
    public void c(final f3h p0) {
        // 
        // This method could not be decompiled.
        // 
        // Original Bytecode:
        // 
        //     3: dup            
        //     4: ifnull          1374
        //     7: athrow         
        //     8: aconst_null    
        //     9: getstatic       dev/nuker/pyro/fc.1:I
        //    12: ifgt            1366
        //    15: pop            
        //    16: aconst_null    
        //    17: goto            1358
        //    20: nop            
        //    21: nop            
        //    22: nop            
        //    23: athrow         
        //    24: iconst_0       
        //    25: getstatic       dev/nuker/pyro/fc.1:I
        //    28: ifeq            36
        //    31: ldc             -1841589412
        //    33: goto            38
        //    36: ldc             2117501867
        //    38: ldc             253060453
        //    40: ixor           
        //    41: lookupswitch {
        //          -1657866695: 36
        //          1898178254: 68
        //          default: 1341
        //        }
        //    68: istore_2       
        //    69: getstatic       dev/nuker/pyro/fc.0:I
        //    72: ifeq            80
        //    75: ldc             30514375
        //    77: goto            82
        //    80: ldc             1692932616
        //    82: ldc             -1930129624
        //    84: ixor           
        //    85: lookupswitch {
        //          -1926949905: 1335
        //          97568082: 80
        //          default: 112
        //        }
        //   112: iload_2        
        //   113: iconst_3       
        //   114: if_icmpge       1314
        //   117: getstatic       dev/nuker/pyro/fc.c:I
        //   120: ifge            128
        //   123: ldc             -44274455
        //   125: goto            130
        //   128: ldc             1960488254
        //   130: ldc             1884753848
        //   132: ixor           
        //   133: lookupswitch {
        //          -1974055013: 128
        //          -1928633519: 1333
        //          default: 160
        //        }
        //   160: iload_2        
        //   161: getstatic       dev/nuker/pyro/fc.0:I
        //   164: ifeq            172
        //   167: ldc             1160151590
        //   169: goto            174
        //   172: ldc             487410850
        //   174: ldc             -1212155359
        //   176: ixor           
        //   177: lookupswitch {
        //          -1312277664: 172
        //          -224823289: 1343
        //          default: 204
        //        }
        //   204: goto            208
        //   207: athrow         
        //   208: invokestatic    dev/nuker/pyro/fbv.c:(I)F
        //   211: goto            215
        //   214: athrow         
        //   215: fstore_3       
        //   216: fload_3        
        //   217: aload_0        
        //   218: getfield        dev/nuker/pyro/f5l.c:Ldev/nuker/pyro/f0g;
        //   221: getstatic       dev/nuker/pyro/fc.0:I
        //   224: ifeq            232
        //   227: ldc             1247464309
        //   229: goto            234
        //   232: ldc             1076339028
        //   234: ldc             -1832707043
        //   236: ixor           
        //   237: lookupswitch {
        //          -756761271: 264
        //          -661006488: 232
        //          default: 1345
        //        }
        //   264: goto            268
        //   267: athrow         
        //   268: invokevirtual   dev/nuker/pyro/f0g.3:()Ljava/lang/Object;
        //   271: goto            275
        //   274: athrow         
        //   275: checkcast       Ljava/lang/Integer;
        //   278: goto            282
        //   281: athrow         
        //   282: invokevirtual   java/lang/Integer.intValue:()I
        //   285: goto            289
        //   288: athrow         
        //   289: i2f            
        //   290: fcmpg          
        //   291: ifgt            299
        //   294: ldc             -1004043602
        //   296: goto            301
        //   299: ldc             -1004043601
        //   301: ldc             328809720
        //   303: ixor           
        //   304: tableswitch {
        //          -1350730580: 328
        //          -1350730579: 1301
        //          default: 294
        //        }
        //   328: aload_0        
        //   329: getfield        dev/nuker/pyro/f5l.c:[Z
        //   332: getstatic       dev/nuker/pyro/fc.1:I
        //   335: ifeq            343
        //   338: ldc             -1208474622
        //   340: goto            345
        //   343: ldc             835904508
        //   345: ldc             1374058394
        //   347: ixor           
        //   348: lookupswitch {
        //          -1779005426: 343
        //          -434220136: 1327
        //          default: 376
        //        }
        //   376: iload_2        
        //   377: baload         
        //   378: ifne            1308
        //   381: getstatic       dev/nuker/pyro/fc.0:I
        //   384: ifeq            392
        //   387: ldc             512078598
        //   389: goto            394
        //   392: ldc             -1443713727
        //   394: ldc             -2025090593
        //   396: ixor           
        //   397: lookupswitch {
        //          -1714543911: 1329
        //          -509949980: 392
        //          default: 424
        //        }
        //   424: aload_0        
        //   425: iload_2        
        //   426: goto            430
        //   429: athrow         
        //   430: invokespecial   dev/nuker/pyro/f5l.c:(I)Ljava/lang/String;
        //   433: goto            437
        //   436: athrow         
        //   437: getstatic       dev/nuker/pyro/fc.c:I
        //   440: ifge            448
        //   443: ldc             -195401283
        //   445: goto            450
        //   448: ldc             756940394
        //   450: ldc             -29678119
        //   452: ixor           
        //   453: lookupswitch {
        //          -752428109: 480
        //          174148708: 448
        //          default: 1347
        //        }
        //   480: astore          4
        //   482: new             Ljava/lang/StringBuilder;
        //   485: dup            
        //   486: goto            490
        //   489: athrow         
        //   490: invokespecial   java/lang/StringBuilder.<init>:()V
        //   493: goto            497
        //   496: athrow         
        //   497: ldc             "\u23ec\u149c\u8ad1\ub1da\ucfe9"
        //   499: getstatic       dev/nuker/pyro/fc.c:I
        //   502: ifge            510
        //   505: ldc             -2101132526
        //   507: goto            512
        //   510: ldc             -288103560
        //   512: ldc             391227456
        //   514: ixor           
        //   515: lookupswitch {
        //          -1785533614: 1323
        //          -1747626308: 510
        //          default: 540
        //        }
        //   540: goto            544
        //   543: athrow         
        //   544: invokestatic    invokestatic   !!! ERROR
        //   547: goto            551
        //   550: athrow         
        //   551: goto            555
        //   554: athrow         
        //   555: invokevirtual   java/lang/StringBuilder.append:(Ljava/lang/String;)Ljava/lang/StringBuilder;
        //   558: goto            562
        //   561: athrow         
        //   562: aload           4
        //   564: goto            568
        //   567: athrow         
        //   568: invokevirtual   java/lang/StringBuilder.append:(Ljava/lang/String;)Ljava/lang/StringBuilder;
        //   571: goto            575
        //   574: athrow         
        //   575: ldc             "\u2395\u1491\u8ac1\ub1c4\ucfa6\uedc4\ub264"
        //   577: goto            581
        //   580: athrow         
        //   581: invokestatic    invokestatic   !!! ERROR
        //   584: goto            588
        //   587: athrow         
        //   588: goto            592
        //   591: athrow         
        //   592: invokevirtual   java/lang/StringBuilder.append:(Ljava/lang/String;)Ljava/lang/StringBuilder;
        //   595: goto            599
        //   598: athrow         
        //   599: getstatic       dev/nuker/pyro/fc.1:I
        //   602: ifeq            610
        //   605: ldc             -2110003456
        //   607: goto            612
        //   610: ldc             1403844003
        //   612: ldc             -1532550419
        //   614: ixor           
        //   615: lookupswitch {
        //          647808493: 1325
        //          665824022: 610
        //          default: 640
        //        }
        //   640: aload_0        
        //   641: getfield        dev/nuker/pyro/f5l.c:Ldev/nuker/pyro/f0g;
        //   644: goto            648
        //   647: athrow         
        //   648: invokevirtual   dev/nuker/pyro/f0g.3:()Ljava/lang/Object;
        //   651: goto            655
        //   654: athrow         
        //   655: getstatic       dev/nuker/pyro/fc.1:I
        //   658: ifeq            666
        //   661: ldc             1058975258
        //   663: goto            668
        //   666: ldc             -2070590581
        //   668: ldc             1390074815
        //   670: ixor           
        //   671: lookupswitch {
        //          -699428812: 696
        //          1841591717: 666
        //          default: 1315
        //        }
        //   696: goto            700
        //   699: athrow         
        //   700: invokevirtual   java/lang/StringBuilder.append:(Ljava/lang/Object;)Ljava/lang/StringBuilder;
        //   703: goto            707
        //   706: athrow         
        //   707: ldc             "%"
        //   709: goto            713
        //   712: athrow         
        //   713: invokevirtual   java/lang/StringBuilder.append:(Ljava/lang/String;)Ljava/lang/StringBuilder;
        //   716: goto            720
        //   719: athrow         
        //   720: goto            724
        //   723: athrow         
        //   724: invokevirtual   java/lang/StringBuilder.toString:()Ljava/lang/String;
        //   727: goto            731
        //   730: athrow         
        //   731: astore          5
        //   733: getstatic       dev/nuker/pyro/f5j.c:[I
        //   736: aload_0        
        //   737: getstatic       dev/nuker/pyro/fc.0:I
        //   740: ifeq            748
        //   743: ldc             -704904724
        //   745: goto            750
        //   748: ldc             -1288704134
        //   750: ldc             -1497042681
        //   752: ixor           
        //   753: lookupswitch {
        //          -636695401: 748
        //          1933111531: 1321
        //          default: 780
        //        }
        //   780: getfield        dev/nuker/pyro/f5l.c:Ldev/nuker/pyro/f0f;
        //   783: goto            787
        //   786: athrow         
        //   787: invokevirtual   dev/nuker/pyro/f0f.3:()Ljava/lang/Object;
        //   790: goto            794
        //   793: athrow         
        //   794: checkcast       Ldev/nuker/pyro/f5k;
        //   797: goto            801
        //   800: athrow         
        //   801: invokevirtual   dev/nuker/pyro/f5k.ordinal:()I
        //   804: goto            808
        //   807: athrow         
        //   808: iaload         
        //   809: tableswitch {
        //                2: 836
        //                3: 1083
        //                4: 1170
        //          default: 1247
        //        }
        //   836: goto            840
        //   839: athrow         
        //   840: invokestatic    dev/nuker/pyro/f41.c:()Ldev/nuker/pyro/f41;
        //   843: goto            847
        //   846: athrow         
        //   847: ldc             "\u23f4\u149f\u8ac1\ub1da\ucfbd\ued92"
        //   849: getstatic       dev/nuker/pyro/fc.0:I
        //   852: ifeq            860
        //   855: ldc             -1325813789
        //   857: goto            862
        //   860: ldc             201166509
        //   862: ldc             -1063996109
        //   864: ixor           
        //   865: lookupswitch {
        //          -882295906: 892
        //          1886198480: 860
        //          default: 1339
        //        }
        //   892: goto            896
        //   895: athrow         
        //   896: invokestatic    invokestatic   !!! ERROR
        //   899: goto            903
        //   902: athrow         
        //   903: getstatic       dev/nuker/pyro/fc.c:I
        //   906: ifge            914
        //   909: ldc             1445821293
        //   911: goto            916
        //   914: ldc             1676152511
        //   916: ldc             1333891746
        //   918: ixor           
        //   919: lookupswitch {
        //          430762447: 914
        //          745118749: 944
        //          default: 1337
        //        }
        //   944: aload           5
        //   946: ldc             -1234904
        //   948: getstatic       dev/nuker/pyro/fc.1:I
        //   951: ifeq            959
        //   954: ldc             -1376427892
        //   956: goto            961
        //   959: ldc             -980976570
        //   961: ldc             -806810191
        //   963: ixor           
        //   964: lookupswitch {
        //          175010295: 992
        //          1646030141: 959
        //          default: 1319
        //        }
        //   992: goto            996
        //   995: athrow         
        //   996: invokevirtual   dev/nuker/pyro/f41.c:(Ljava/lang/String;Ljava/lang/String;I)V
        //   999: goto            1003
        //  1002: athrow         
        //  1003: getstatic       dev/nuker/pyro/Pyro.INSTANCE:Ldev/nuker/pyro/Pyro;
        //  1006: new             Ljava/lang/StringBuilder;
        //  1009: dup            
        //  1010: goto            1014
        //  1013: athrow         
        //  1014: invokespecial   java/lang/StringBuilder.<init>:()V
        //  1017: goto            1021
        //  1020: athrow         
        //  1021: ldc             "\u23f4\u149f\u8ac1\ub1da\ucfbd\ued92\ub264"
        //  1023: goto            1027
        //  1026: athrow         
        //  1027: invokestatic    invokestatic   !!! ERROR
        //  1030: goto            1034
        //  1033: athrow         
        //  1034: goto            1038
        //  1037: athrow         
        //  1038: invokevirtual   java/lang/StringBuilder.append:(Ljava/lang/String;)Ljava/lang/StringBuilder;
        //  1041: goto            1045
        //  1044: athrow         
        //  1045: aload           5
        //  1047: goto            1051
        //  1050: athrow         
        //  1051: invokevirtual   java/lang/StringBuilder.append:(Ljava/lang/String;)Ljava/lang/StringBuilder;
        //  1054: goto            1058
        //  1057: athrow         
        //  1058: goto            1062
        //  1061: athrow         
        //  1062: invokevirtual   java/lang/StringBuilder.toString:()Ljava/lang/String;
        //  1065: goto            1069
        //  1068: athrow         
        //  1069: goto            1073
        //  1072: athrow         
        //  1073: invokevirtual   dev/nuker/pyro/Pyro.sendMessage:(Ljava/lang/String;)V
        //  1076: goto            1080
        //  1079: athrow         
        //  1080: goto            1247
        //  1083: getstatic       dev/nuker/pyro/fc.0:I
        //  1086: ifeq            1094
        //  1089: ldc             -21211734
        //  1091: goto            1096
        //  1094: ldc             -1163529048
        //  1096: ldc_w           1170071627
        //  1099: ixor           
        //  1100: lookupswitch {
        //          -1157515807: 1094
        //          -15199005: 1128
        //          default: 1317
        //        }
        //  1128: goto            1132
        //  1131: athrow         
        //  1132: invokestatic    dev/nuker/pyro/f41.c:()Ldev/nuker/pyro/f41;
        //  1135: goto            1139
        //  1138: athrow         
        //  1139: ldc             "\u23f4\u149f\u8ac1\ub1da\ucfbd\ued92"
        //  1141: goto            1145
        //  1144: athrow         
        //  1145: invokestatic    invokestatic   !!! ERROR
        //  1148: goto            1152
        //  1151: athrow         
        //  1152: aload           5
        //  1154: ldc             -1234904
        //  1156: goto            1160
        //  1159: athrow         
        //  1160: invokevirtual   dev/nuker/pyro/f41.c:(Ljava/lang/String;Ljava/lang/String;I)V
        //  1163: goto            1167
        //  1166: athrow         
        //  1167: goto            1247
        //  1170: getstatic       dev/nuker/pyro/Pyro.INSTANCE:Ldev/nuker/pyro/Pyro;
        //  1173: new             Ljava/lang/StringBuilder;
        //  1176: dup            
        //  1177: goto            1181
        //  1180: athrow         
        //  1181: invokespecial   java/lang/StringBuilder.<init>:()V
        //  1184: goto            1188
        //  1187: athrow         
        //  1188: ldc             "\u23f4\u149f\u8ac1\ub1da\ucfbd\ued92\ub264"
        //  1190: goto            1194
        //  1193: athrow         
        //  1194: invokestatic    invokestatic   !!! ERROR
        //  1197: goto            1201
        //  1200: athrow         
        //  1201: goto            1205
        //  1204: athrow         
        //  1205: invokevirtual   java/lang/StringBuilder.append:(Ljava/lang/String;)Ljava/lang/StringBuilder;
        //  1208: goto            1212
        //  1211: athrow         
        //  1212: aload           5
        //  1214: goto            1218
        //  1217: athrow         
        //  1218: invokevirtual   java/lang/StringBuilder.append:(Ljava/lang/String;)Ljava/lang/StringBuilder;
        //  1221: goto            1225
        //  1224: athrow         
        //  1225: goto            1229
        //  1228: athrow         
        //  1229: invokevirtual   java/lang/StringBuilder.toString:()Ljava/lang/String;
        //  1232: goto            1236
        //  1235: athrow         
        //  1236: goto            1240
        //  1239: athrow         
        //  1240: invokevirtual   dev/nuker/pyro/Pyro.sendMessage:(Ljava/lang/String;)V
        //  1243: goto            1247
        //  1246: athrow         
        //  1247: aload_0        
        //  1248: getstatic       dev/nuker/pyro/fc.1:I
        //  1251: ifeq            1260
        //  1254: ldc_w           1195565702
        //  1257: goto            1263
        //  1260: ldc_w           -1266342850
        //  1263: ldc_w           22616611
        //  1266: ixor           
        //  1267: lookupswitch {
        //          -1243857379: 1292
        //          1176238245: 1260
        //          default: 1331
        //        }
        //  1292: getfield        dev/nuker/pyro/f5l.c:[Z
        //  1295: iload_2        
        //  1296: iconst_1       
        //  1297: bastore        
        //  1298: goto            1308
        //  1301: aload_0        
        //  1302: getfield        dev/nuker/pyro/f5l.c:[Z
        //  1305: iload_2        
        //  1306: iconst_0       
        //  1307: bastore        
        //  1308: iinc            2, 1
        //  1311: goto            69
        //  1314: return         
        //  1315: aconst_null    
        //  1316: athrow         
        //  1317: aconst_null    
        //  1318: athrow         
        //  1319: aconst_null    
        //  1320: athrow         
        //  1321: aconst_null    
        //  1322: athrow         
        //  1323: aconst_null    
        //  1324: athrow         
        //  1325: aconst_null    
        //  1326: athrow         
        //  1327: aconst_null    
        //  1328: athrow         
        //  1329: aconst_null    
        //  1330: athrow         
        //  1331: aconst_null    
        //  1332: athrow         
        //  1333: aconst_null    
        //  1334: athrow         
        //  1335: aconst_null    
        //  1336: athrow         
        //  1337: aconst_null    
        //  1338: athrow         
        //  1339: aconst_null    
        //  1340: athrow         
        //  1341: aconst_null    
        //  1342: athrow         
        //  1343: aconst_null    
        //  1344: athrow         
        //  1345: aconst_null    
        //  1346: athrow         
        //  1347: aconst_null    
        //  1348: athrow         
        //  1349: pop            
        //  1350: goto            24
        //  1353: pop            
        //  1354: aconst_null    
        //  1355: goto            1349
        //  1358: dup            
        //  1359: ifnull          1349
        //  1362: checkcast       Ljava/lang/Throwable;
        //  1365: athrow         
        //  1366: dup            
        //  1367: ifnull          1353
        //  1370: checkcast       Ljava/lang/Throwable;
        //  1373: athrow         
        //  1374: aconst_null    
        //  1375: athrow         
        //    StackMapTable: 00 E0 FF 00 03 00 04 07 00 03 07 01 05 01 02 00 01 07 00 87 F9 00 04 FF 00 0B 00 00 00 01 07 00 87 FD 00 03 07 00 03 07 01 05 4B 01 FF 00 01 00 02 07 00 03 07 01 05 00 02 01 01 5D 01 FC 00 00 01 0A 41 01 1D 0F 41 01 1D 4B 01 FF 00 01 00 03 07 00 03 07 01 05 01 00 02 01 01 5D 01 42 07 00 87 40 01 45 07 00 87 40 02 FF 00 10 00 04 07 00 03 07 01 05 01 02 00 02 02 07 00 4A FF 00 01 00 04 07 00 03 07 01 05 01 02 00 03 02 07 00 4A 01 FF 00 1D 00 04 07 00 03 07 01 05 01 02 00 02 02 07 00 4A 42 07 00 87 FF 00 00 00 04 07 00 03 07 01 05 01 02 00 02 02 07 00 4A 45 07 00 87 FF 00 00 00 04 07 00 03 07 01 05 01 02 00 02 02 07 01 07 45 07 00 87 FF 00 00 00 04 07 00 03 07 01 05 01 02 00 02 02 07 00 A1 45 07 00 87 FF 00 00 00 04 07 00 03 07 01 05 01 02 00 02 02 01 04 04 41 01 1A 4E 07 01 08 FF 00 01 00 04 07 00 03 07 01 05 01 02 00 02 07 01 08 01 5E 07 01 08 0F 41 01 1D 44 07 00 87 FF 00 00 00 04 07 00 03 07 01 05 01 02 00 02 07 00 03 01 45 07 00 87 40 07 00 63 4A 07 00 63 FF 00 01 00 04 07 00 03 07 01 05 01 02 00 02 07 00 63 01 5D 07 00 63 FF 00 08 00 05 07 00 03 07 01 05 01 02 07 00 63 00 01 07 00 75 FF 00 00 00 05 07 00 03 07 01 05 01 02 07 00 63 00 02 08 01 E2 08 01 E2 45 07 00 87 40 07 00 B5 FF 00 0C 00 05 07 00 03 07 01 05 01 02 07 00 63 00 02 07 00 B5 07 00 63 FF 00 01 00 05 07 00 03 07 01 05 01 02 07 00 63 00 03 07 00 B5 07 00 63 01 FF 00 1B 00 05 07 00 03 07 01 05 01 02 07 00 63 00 02 07 00 B5 07 00 63 42 07 00 87 FF 00 00 00 05 07 00 03 07 01 05 01 02 07 00 63 00 02 07 00 B5 07 00 63 45 07 00 87 FF 00 00 00 05 07 00 03 07 01 05 01 02 07 00 63 00 02 07 00 B5 07 00 63 42 07 00 87 FF 00 00 00 05 07 00 03 07 01 05 01 02 07 00 63 00 02 07 00 B5 07 00 63 45 07 00 87 40 07 00 B5 44 07 00 6F FF 00 00 00 05 07 00 03 07 01 05 01 02 07 00 63 00 02 07 00 B5 07 00 63 45 07 00 87 40 07 00 B5 44 07 00 87 FF 00 00 00 05 07 00 03 07 01 05 01 02 07 00 63 00 02 07 00 B5 07 00 63 45 07 00 87 FF 00 00 00 05 07 00 03 07 01 05 01 02 07 00 63 00 02 07 00 B5 07 00 63 42 07 00 87 FF 00 00 00 05 07 00 03 07 01 05 01 02 07 00 63 00 02 07 00 B5 07 00 63 45 07 00 87 40 07 00 B5 4A 07 00 B5 FF 00 01 00 05 07 00 03 07 01 05 01 02 07 00 63 00 02 07 00 B5 01 5B 07 00 B5 FF 00 06 00 00 00 01 07 00 87 FF 00 00 00 05 07 00 03 07 01 05 01 02 07 00 63 00 02 07 00 B5 07 00 4A 45 07 00 87 FF 00 00 00 05 07 00 03 07 01 05 01 02 07 00 63 00 02 07 00 B5 07 01 07 FF 00 0A 00 05 07 00 03 07 01 05 01 02 07 00 63 00 02 07 00 B5 07 01 07 FF 00 01 00 05 07 00 03 07 01 05 01 02 07 00 63 00 03 07 00 B5 07 01 07 01 FF 00 1B 00 05 07 00 03 07 01 05 01 02 07 00 63 00 02 07 00 B5 07 01 07 42 07 00 87 FF 00 00 00 05 07 00 03 07 01 05 01 02 07 00 63 00 02 07 00 B5 07 01 07 45 07 00 87 40 07 00 B5 44 07 00 87 FF 00 00 00 05 07 00 03 07 01 05 01 02 07 00 63 00 02 07 00 B5 07 00 63 45 07 00 87 40 07 00 B5 42 07 00 87 40 07 00 B5 45 07 00 87 40 07 00 63 FF 00 10 00 06 07 00 03 07 01 05 01 02 07 00 63 07 00 63 00 02 07 01 09 07 00 03 FF 00 01 00 06 07 00 03 07 01 05 01 02 07 00 63 07 00 63 00 03 07 01 09 07 00 03 01 FF 00 1D 00 06 07 00 03 07 01 05 01 02 07 00 63 07 00 63 00 02 07 01 09 07 00 03 45 07 00 87 FF 00 00 00 06 07 00 03 07 01 05 01 02 07 00 63 07 00 63 00 02 07 01 09 07 00 34 45 07 00 87 FF 00 00 00 06 07 00 03 07 01 05 01 02 07 00 63 07 00 63 00 02 07 01 09 07 01 07 45 07 00 75 FF 00 00 00 06 07 00 03 07 01 05 01 02 07 00 63 07 00 63 00 02 07 01 09 07 00 3A 45 07 00 87 FF 00 00 00 06 07 00 03 07 01 05 01 02 07 00 63 07 00 63 00 02 07 01 09 01 1B 42 07 00 87 00 45 07 00 87 40 07 00 DF FF 00 0C 00 06 07 00 03 07 01 05 01 02 07 00 63 07 00 63 00 02 07 00 DF 07 00 63 FF 00 01 00 06 07 00 03 07 01 05 01 02 07 00 63 07 00 63 00 03 07 00 DF 07 00 63 01 FF 00 1D 00 06 07 00 03 07 01 05 01 02 07 00 63 07 00 63 00 02 07 00 DF 07 00 63 42 07 00 71 FF 00 00 00 06 07 00 03 07 01 05 01 02 07 00 63 07 00 63 00 02 07 00 DF 07 00 63 45 07 00 87 FF 00 00 00 06 07 00 03 07 01 05 01 02 07 00 63 07 00 63 00 02 07 00 DF 07 00 63 FF 00 0A 00 06 07 00 03 07 01 05 01 02 07 00 63 07 00 63 00 02 07 00 DF 07 00 63 FF 00 01 00 06 07 00 03 07 01 05 01 02 07 00 63 07 00 63 00 03 07 00 DF 07 00 63 01 FF 00 1B 00 06 07 00 03 07 01 05 01 02 07 00 63 07 00 63 00 02 07 00 DF 07 00 63 FF 00 0E 00 06 07 00 03 07 01 05 01 02 07 00 63 07 00 63 00 04 07 00 DF 07 00 63 07 00 63 01 FF 00 01 00 06 07 00 03 07 01 05 01 02 07 00 63 07 00 63 00 05 07 00 DF 07 00 63 07 00 63 01 01 FF 00 1E 00 06 07 00 03 07 01 05 01 02 07 00 63 07 00 63 00 04 07 00 DF 07 00 63 07 00 63 01 42 07 00 87 FF 00 00 00 06 07 00 03 07 01 05 01 02 07 00 63 07 00 63 00 04 07 00 DF 07 00 63 07 00 63 01 45 07 00 87 00 49 07 00 87 FF 00 00 00 06 07 00 03 07 01 05 01 02 07 00 63 07 00 63 00 03 07 00 F3 08 03 EE 08 03 EE 45 07 00 87 FF 00 00 00 06 07 00 03 07 01 05 01 02 07 00 63 07 00 63 00 02 07 00 F3 07 00 B5 44 07 00 6B FF 00 00 00 06 07 00 03 07 01 05 01 02 07 00 63 07 00 63 00 03 07 00 F3 07 00 B5 07 00 63 45 07 00 87 FF 00 00 00 06 07 00 03 07 01 05 01 02 07 00 63 07 00 63 00 03 07 00 F3 07 00 B5 07 00 63 42 07 00 71 FF 00 00 00 06 07 00 03 07 01 05 01 02 07 00 63 07 00 63 00 03 07 00 F3 07 00 B5 07 00 63 45 07 00 87 FF 00 00 00 06 07 00 03 07 01 05 01 02 07 00 63 07 00 63 00 02 07 00 F3 07 00 B5 FF 00 04 00 00 00 01 07 00 87 FF 00 00 00 06 07 00 03 07 01 05 01 02 07 00 63 07 00 63 00 03 07 00 F3 07 00 B5 07 00 63 45 07 00 87 FF 00 00 00 06 07 00 03 07 01 05 01 02 07 00 63 07 00 63 00 02 07 00 F3 07 00 B5 42 07 00 87 FF 00 00 00 06 07 00 03 07 01 05 01 02 07 00 63 07 00 63 00 02 07 00 F3 07 00 B5 45 07 00 87 FF 00 00 00 06 07 00 03 07 01 05 01 02 07 00 63 07 00 63 00 02 07 00 F3 07 00 63 42 07 00 79 FF 00 00 00 06 07 00 03 07 01 05 01 02 07 00 63 07 00 63 00 02 07 00 F3 07 00 63 45 07 00 87 00 02 0A 41 01 1F 42 07 00 87 00 45 07 00 87 40 07 00 DF 44 07 00 87 FF 00 00 00 06 07 00 03 07 01 05 01 02 07 00 63 07 00 63 00 02 07 00 DF 07 00 63 45 07 00 87 FF 00 00 00 06 07 00 03 07 01 05 01 02 07 00 63 07 00 63 00 02 07 00 DF 07 00 63 46 07 00 87 FF 00 00 00 06 07 00 03 07 01 05 01 02 07 00 63 07 00 63 00 04 07 00 DF 07 00 63 07 00 63 01 45 07 00 87 00 02 FF 00 09 00 00 00 01 07 00 87 FF 00 00 00 06 07 00 03 07 01 05 01 02 07 00 63 07 00 63 00 03 07 00 F3 08 04 95 08 04 95 45 07 00 87 FF 00 00 00 06 07 00 03 07 01 05 01 02 07 00 63 07 00 63 00 02 07 00 F3 07 00 B5 44 07 00 87 FF 00 00 00 06 07 00 03 07 01 05 01 02 07 00 63 07 00 63 00 03 07 00 F3 07 00 B5 07 00 63 45 07 00 87 FF 00 00 00 06 07 00 03 07 01 05 01 02 07 00 63 07 00 63 00 03 07 00 F3 07 00 B5 07 00 63 42 07 00 87 FF 00 00 00 06 07 00 03 07 01 05 01 02 07 00 63 07 00 63 00 03 07 00 F3 07 00 B5 07 00 63 45 07 00 87 FF 00 00 00 06 07 00 03 07 01 05 01 02 07 00 63 07 00 63 00 02 07 00 F3 07 00 B5 44 07 00 87 FF 00 00 00 06 07 00 03 07 01 05 01 02 07 00 63 07 00 63 00 03 07 00 F3 07 00 B5 07 00 63 45 07 00 87 FF 00 00 00 06 07 00 03 07 01 05 01 02 07 00 63 07 00 63 00 02 07 00 F3 07 00 B5 42 07 00 87 FF 00 00 00 06 07 00 03 07 01 05 01 02 07 00 63 07 00 63 00 02 07 00 F3 07 00 B5 45 07 00 87 FF 00 00 00 06 07 00 03 07 01 05 01 02 07 00 63 07 00 63 00 02 07 00 F3 07 00 63 FF 00 02 00 00 00 01 07 00 87 FF 00 00 00 06 07 00 03 07 01 05 01 02 07 00 63 07 00 63 00 02 07 00 F3 07 00 63 45 07 00 87 00 4C 07 00 03 FF 00 02 00 06 07 00 03 07 01 05 01 02 07 00 63 07 00 63 00 02 07 00 03 01 5C 07 00 03 F9 00 08 06 FA 00 05 FF 00 00 00 05 07 00 03 07 01 05 01 02 07 00 63 00 02 07 00 B5 07 01 07 FC 00 01 07 00 63 FF 00 01 00 06 07 00 03 07 01 05 01 02 07 00 63 07 00 63 00 04 07 00 DF 07 00 63 07 00 63 01 FF 00 01 00 06 07 00 03 07 01 05 01 02 07 00 63 07 00 63 00 02 07 01 09 07 00 03 FF 00 01 00 05 07 00 03 07 01 05 01 02 07 00 63 00 02 07 00 B5 07 00 63 41 07 00 B5 FF 00 01 00 04 07 00 03 07 01 05 01 02 00 01 07 01 08 01 FF 00 01 00 06 07 00 03 07 01 05 01 02 07 00 63 07 00 63 00 01 07 00 03 F8 00 01 01 FF 00 01 00 06 07 00 03 07 01 05 01 02 07 00 63 07 00 63 00 02 07 00 DF 07 00 63 FF 00 01 00 06 07 00 03 07 01 05 01 02 07 00 63 07 00 63 00 02 07 00 DF 07 00 63 FF 00 01 00 02 07 00 03 07 01 05 00 01 01 FF 00 01 00 03 07 00 03 07 01 05 01 00 01 01 FF 00 01 00 04 07 00 03 07 01 05 01 02 00 02 02 07 00 4A 41 07 00 63 FF 00 01 00 02 07 00 03 07 01 05 00 01 07 00 75 43 05 44 07 00 75 47 05 FF 00 07 00 04 07 00 03 07 01 05 01 02 00 01 07 00 87
        //    Exceptions:
        //  Try           Handler
        //  Start  End    Start  End    Type                                       
        //  -----  -----  -----  -----  -------------------------------------------
        //  8      20     1358   1366   Ljava/lang/IndexOutOfBoundsException;
        //  1358   1366   1358   1366   Ljava/lang/NumberFormatException;
        //  1374   1376   3      8      Ljava/lang/UnsupportedOperationException;
        //  207    214    214    215    Any
        //  207    214    207    208    Ljava/lang/NullPointerException;
        //  207    214    207    208    Ljava/lang/UnsupportedOperationException;
        //  208    214    207    208    Ljava/lang/StringIndexOutOfBoundsException;
        //  207    214    207    208    Any
        //  267    274    274    275    Any
        //  267    274    3      8      Any
        //  268    274    274    275    Any
        //  268    274    3      8      Ljava/lang/EnumConstantNotPresentException;
        //  268    274    267    268    Any
        //  281    288    288    289    Any
        //  281    288    288    289    Any
        //  282    288    288    289    Ljava/lang/IllegalStateException;
        //  282    288    281    282    Any
        //  282    288    288    289    Ljava/lang/UnsupportedOperationException;
        //  429    436    436    437    Any
        //  430    436    429    430    Any
        //  429    436    436    437    Ljava/lang/UnsupportedOperationException;
        //  429    436    3      8      Any
        //  429    436    429    430    Ljava/lang/NullPointerException;
        //  489    496    496    497    Any
        //  489    496    489    490    Ljava/lang/UnsupportedOperationException;
        //  489    496    496    497    Ljava/lang/IndexOutOfBoundsException;
        //  489    496    496    497    Any
        //  489    496    489    490    Ljava/lang/RuntimeException;
        //  543    550    550    551    Any
        //  543    550    3      8      Ljava/lang/ArithmeticException;
        //  544    550    543    544    Any
        //  543    550    543    544    Ljava/lang/StringIndexOutOfBoundsException;
        //  543    550    3      8      Ljava/lang/EnumConstantNotPresentException;
        //  554    561    561    562    Any
        //  554    561    554    555    Any
        //  555    561    561    562    Ljava/lang/NumberFormatException;
        //  555    561    554    555    Any
        //  554    561    3      8      Any
        //  567    574    574    575    Any
        //  568    574    567    568    Ljava/lang/StringIndexOutOfBoundsException;
        //  568    574    574    575    Any
        //  567    574    3      8      Ljava/lang/EnumConstantNotPresentException;
        //  568    574    574    575    Any
        //  580    587    587    588    Any
        //  581    587    3      8      Any
        //  580    587    580    581    Ljava/lang/AssertionError;
        //  580    587    580    581    Ljava/lang/StringIndexOutOfBoundsException;
        //  581    587    3      8      Any
        //  591    598    598    599    Any
        //  591    598    591    592    Any
        //  592    598    591    592    Ljava/lang/ArrayIndexOutOfBoundsException;
        //  591    598    591    592    Any
        //  591    598    598    599    Any
        //  648    654    654    655    Any
        //  648    654    3      8      Any
        //  648    654    3      8      Ljava/lang/NegativeArraySizeException;
        //  648    654    654    655    Any
        //  648    654    654    655    Any
        //  699    706    706    707    Any
        //  700    706    706    707    Ljava/lang/EnumConstantNotPresentException;
        //  699    706    699    700    Any
        //  699    706    706    707    Ljava/util/NoSuchElementException;
        //  699    706    699    700    Any
        //  712    719    719    720    Any
        //  713    719    3      8      Ljava/lang/IllegalArgumentException;
        //  712    719    719    720    Ljava/lang/IllegalStateException;
        //  712    719    712    713    Any
        //  712    719    3      8      Ljava/lang/NullPointerException;
        //  723    730    730    731    Any
        //  723    730    723    724    Any
        //  723    730    730    731    Any
        //  724    730    730    731    Ljava/lang/RuntimeException;
        //  723    730    723    724    Any
        //  786    793    793    794    Any
        //  787    793    786    787    Ljava/lang/ClassCastException;
        //  786    793    793    794    Any
        //  786    793    786    787    Any
        //  787    793    786    787    Ljava/lang/NumberFormatException;
        //  800    807    807    808    Any
        //  801    807    800    801    Ljava/lang/StringIndexOutOfBoundsException;
        //  800    807    807    808    Ljava/lang/ArithmeticException;
        //  800    807    800    801    Ljava/lang/UnsupportedOperationException;
        //  801    807    3      8      Ljava/lang/StringIndexOutOfBoundsException;
        //  839    846    846    847    Any
        //  840    846    846    847    Any
        //  840    846    839    840    Ljava/lang/AssertionError;
        //  839    846    839    840    Ljava/lang/EnumConstantNotPresentException;
        //  839    846    846    847    Ljava/util/NoSuchElementException;
        //  895    902    902    903    Any
        //  895    902    3      8      Ljava/lang/ArithmeticException;
        //  896    902    902    903    Ljava/lang/ArithmeticException;
        //  896    902    902    903    Any
        //  896    902    895    896    Ljava/lang/EnumConstantNotPresentException;
        //  995    1002   1002   1003   Any
        //  995    1002   995    996    Ljava/lang/ArithmeticException;
        //  996    1002   3      8      Ljava/lang/IllegalArgumentException;
        //  995    1002   995    996    Any
        //  995    1002   3      8      Ljava/util/ConcurrentModificationException;
        //  1013   1020   1020   1021   Any
        //  1013   1020   1020   1021   Ljava/lang/IllegalStateException;
        //  1013   1020   1013   1014   Any
        //  1014   1020   1020   1021   Ljava/lang/ArithmeticException;
        //  1014   1020   3      8      Ljava/lang/EnumConstantNotPresentException;
        //  1026   1033   1033   1034   Any
        //  1026   1033   3      8      Any
        //  1027   1033   1026   1027   Ljava/lang/UnsupportedOperationException;
        //  1027   1033   3      8      Ljava/lang/IllegalStateException;
        //  1027   1033   1033   1034   Any
        //  1037   1044   1044   1045   Any
        //  1038   1044   1044   1045   Ljava/lang/AssertionError;
        //  1037   1044   1037   1038   Ljava/lang/EnumConstantNotPresentException;
        //  1038   1044   3      8      Ljava/lang/NullPointerException;
        //  1038   1044   3      8      Ljava/util/ConcurrentModificationException;
        //  1051   1057   1057   1058   Any
        //  1051   1057   3      8      Any
        //  1051   1057   3      8      Ljava/lang/IllegalArgumentException;
        //  1051   1057   1057   1058   Any
        //  1051   1057   1057   1058   Any
        //  1061   1068   1068   1069   Any
        //  1061   1068   1061   1062   Ljava/lang/IndexOutOfBoundsException;
        //  1062   1068   1068   1069   Any
        //  1061   1068   1061   1062   Any
        //  1061   1068   3      8      Ljava/lang/IllegalArgumentException;
        //  1072   1079   1079   1080   Any
        //  1072   1079   1072   1073   Ljava/lang/AssertionError;
        //  1072   1079   1079   1080   Ljava/lang/ArrayIndexOutOfBoundsException;
        //  1072   1079   1079   1080   Any
        //  1072   1079   3      8      Ljava/lang/RuntimeException;
        //  1131   1138   1138   1139   Any
        //  1132   1138   3      8      Any
        //  1131   1138   1131   1132   Ljava/lang/ArrayIndexOutOfBoundsException;
        //  1131   1138   1131   1132   Any
        //  1132   1138   1138   1139   Ljava/lang/ClassCastException;
        //  1144   1151   1151   1152   Any
        //  1144   1151   3      8      Ljava/lang/NullPointerException;
        //  1145   1151   1144   1145   Any
        //  1145   1151   1144   1145   Ljava/lang/IllegalArgumentException;
        //  1144   1151   1151   1152   Any
        //  1159   1166   1166   1167   Any
        //  1159   1166   1159   1160   Any
        //  1159   1166   3      8      Any
        //  1160   1166   3      8      Any
        //  1160   1166   1166   1167   Any
        //  1181   1187   1187   1188   Any
        //  1181   1187   1187   1188   Any
        //  1181   1187   1187   1188   Ljava/lang/IllegalArgumentException;
        //  1181   1187   3      8      Ljava/lang/NegativeArraySizeException;
        //  1181   1187   3      8      Ljava/lang/ArithmeticException;
        //  1193   1200   1200   1201   Any
        //  1193   1200   1193   1194   Any
        //  1194   1200   1200   1201   Ljava/lang/AssertionError;
        //  1193   1200   3      8      Any
        //  1194   1200   3      8      Any
        //  1204   1211   1211   1212   Any
        //  1204   1211   1204   1205   Any
        //  1205   1211   1211   1212   Any
        //  1204   1211   3      8      Any
        //  1205   1211   1204   1205   Ljava/util/NoSuchElementException;
        //  1217   1224   1224   1225   Any
        //  1218   1224   1224   1225   Any
        //  1217   1224   3      8      Ljava/lang/ArithmeticException;
        //  1218   1224   1217   1218   Any
        //  1217   1224   3      8      Any
        //  1228   1235   1235   1236   Any
        //  1229   1235   1228   1229   Ljava/lang/ClassCastException;
        //  1228   1235   1228   1229   Ljava/lang/IndexOutOfBoundsException;
        //  1228   1235   1228   1229   Any
        //  1228   1235   1235   1236   Any
        //  1240   1246   1246   1247   Any
        //  1240   1246   1246   1247   Any
        //  1240   1246   3      8      Any
        //  1240   1246   1246   1247   Any
        //  1240   1246   1246   1247   Ljava/lang/NumberFormatException;
        // 
        // The error that occurred was:
        // 
        // java.lang.IndexOutOfBoundsException: Index -1 out of bounds for length 0
        //     at java.base/jdk.internal.util.Preconditions.outOfBounds(Preconditions.java:64)
        //     at java.base/jdk.internal.util.Preconditions.outOfBoundsCheckIndex(Preconditions.java:70)
        //     at java.base/jdk.internal.util.Preconditions.checkIndex(Preconditions.java:248)
        //     at java.base/java.util.Objects.checkIndex(Objects.java:372)
        //     at java.base/java.util.ArrayList.remove(ArrayList.java:535)
        //     at com.strobel.assembler.ir.StackMappingVisitor.pop(StackMappingVisitor.java:267)
        //     at com.strobel.assembler.ir.StackMappingVisitor$InstructionAnalyzer.execute(StackMappingVisitor.java:595)
        //     at com.strobel.assembler.ir.StackMappingVisitor$InstructionAnalyzer.visit(StackMappingVisitor.java:398)
        //     at com.strobel.decompiler.ast.AstBuilder.performStackAnalysis(AstBuilder.java:2030)
        //     at com.strobel.decompiler.ast.AstBuilder.build(AstBuilder.java:108)
        //     at com.strobel.decompiler.languages.java.ast.AstMethodBodyBuilder.createMethodBody(AstMethodBodyBuilder.java:211)
        //     at com.strobel.decompiler.languages.java.ast.AstMethodBodyBuilder.createMethodBody(AstMethodBodyBuilder.java:99)
        //     at com.strobel.decompiler.languages.java.ast.AstBuilder.createMethodBody(AstBuilder.java:782)
        //     at com.strobel.decompiler.languages.java.ast.AstBuilder.createMethod(AstBuilder.java:675)
        //     at com.strobel.decompiler.languages.java.ast.AstBuilder.addTypeMembers(AstBuilder.java:552)
        //     at com.strobel.decompiler.languages.java.ast.AstBuilder.createTypeCore(AstBuilder.java:519)
        //     at com.strobel.decompiler.languages.java.ast.AstBuilder.createTypeNoCache(AstBuilder.java:161)
        //     at com.strobel.decompiler.languages.java.ast.AstBuilder.createType(AstBuilder.java:150)
        //     at com.strobel.decompiler.languages.java.ast.AstBuilder.addType(AstBuilder.java:125)
        //     at com.strobel.decompiler.languages.java.JavaLanguage.buildAst(JavaLanguage.java:71)
        //     at com.strobel.decompiler.languages.java.JavaLanguage.decompileType(JavaLanguage.java:59)
        //     at com.strobel.decompiler.DecompilerDriver.decompileType(DecompilerDriver.java:330)
        //     at com.strobel.decompiler.DecompilerDriver.decompileJar(DecompilerDriver.java:251)
        //     at com.strobel.decompiler.DecompilerDriver.main(DecompilerDriver.java:126)
        // 
        throw new IllegalStateException("An error occurred while decompiling this method.");
    }
}
