// 
// Decompiled by Procyon v0.5.36
// 

package dev.nuker.pyro;

import dev.nuker.pyro.security.inject.LauncherEventHide;
import org.jetbrains.annotations.NotNull;

public class f5m extends fH
{
    @NotNull
    public f0h c;
    
    static {
        throw t;
    }
    
    public f5m() {
        // 
        // This method could not be decompiled.
        // 
        // Original Bytecode:
        // 
        //     1: ldc             "\u23cc\u1492\u8acf\ub3d5"
        //     3: getstatic       dev/nuker/pyro/fc.c:I
        //     6: ifge            14
        //     9: ldc             -1573520101
        //    11: goto            16
        //    14: ldc             -1376279942
        //    16: ldc             -1731368065
        //    18: ixor           
        //    19: lookupswitch {
        //          989369956: 360
        //          995784074: 14
        //          default: 44
        //        }
        //    44: invokestatic    invokestatic   !!! ERROR
        //    47: ldc             "\u23ec\u1492\u8acf\ub3d5"
        //    49: getstatic       dev/nuker/pyro/fc.c:I
        //    52: ifge            60
        //    55: ldc             1094381754
        //    57: goto            62
        //    60: ldc             -1284305890
        //    62: ldc             -359267805
        //    64: ixor           
        //    65: lookupswitch {
        //          -1414729063: 356
        //          767905097: 60
        //          default: 92
        //        }
        //    92: invokestatic    invokestatic   !!! ERROR
        //    95: ldc             "\u23e3\u149e\u8ace\ub399\uc9bf\uedcd\ub228\ue6e2\ud964\ue9c6\ua705\u1e45\ue1c3\uc5a9\u8143\u8950\u57a3\u772c\ubd3a\uc071\u2b76\uc275\u6a6d\u2d18\ud7e6\u35e1"
        //    97: getstatic       dev/nuker/pyro/fc.1:I
        //   100: ifeq            108
        //   103: ldc             -1729057661
        //   105: goto            110
        //   108: ldc             -1759509400
        //   110: ldc             76890892
        //   112: ixor           
        //   113: lookupswitch {
        //          -1816836252: 140
        //          -1671041137: 108
        //          default: 364
        //        }
        //   140: invokestatic    invokestatic   !!! ERROR
        //   143: getstatic       dev/nuker/pyro/fc.c:I
        //   146: ifge            154
        //   149: ldc             -1035586826
        //   151: goto            156
        //   154: ldc             1306925773
        //   156: ldc             106631204
        //   158: ixor           
        //   159: lookupswitch {
        //          -1004723502: 352
        //          1124131181: 154
        //          default: 184
        //        }
        //   184: invokespecial   dev/nuker/pyro/fH.<init>:(Ljava/lang/String;Ljava/lang/String;Ljava/lang/String;)V
        //   187: getstatic       dev/nuker/pyro/fc.1:I
        //   190: ifeq            198
        //   193: ldc             1671799391
        //   195: goto            200
        //   198: ldc             -1657295998
        //   200: ldc             284533375
        //   202: ixor           
        //   203: lookupswitch {
        //          -1543960470: 198
        //          1934622752: 354
        //          default: 228
        //        }
        //   228: aload_0        
        //   229: aload_0        
        //   230: new             Ldev/nuker/pyro/f0h;
        //   233: dup            
        //   234: ldc             "\u23c1\u1496\u8ada"
        //   236: invokestatic    invokestatic   !!! ERROR
        //   239: ldc             "\u23e1\u1496\u8ada"
        //   241: getstatic       dev/nuker/pyro/fc.c:I
        //   244: ifge            252
        //   247: ldc             -1860843007
        //   249: goto            254
        //   252: ldc             -414168191
        //   254: ldc             -1103759172
        //   256: ixor           
        //   257: lookupswitch {
        //          780431186: 252
        //          790639293: 362
        //          default: 284
        //        }
        //   284: invokestatic    invokestatic   !!! ERROR
        //   287: ldc             "\u23eb\u1490\u8ad7\ub3d0\uc9af\uedc9\ub264\ue6f9\ud960\ue9c3\ua700\u1e49\ue18a\uc5af\u8142\u895b\u57a0\u7722\ubd33\uc071\u2b78\uc22f\u6a2b\u2d5f\ud7bb\u35ef\u7d20\u8985\u8008"
        //   289: getstatic       dev/nuker/pyro/fc.0:I
        //   292: ifeq            300
        //   295: ldc             -527848163
        //   297: goto            302
        //   300: ldc             -1119564116
        //   302: ldc             507303483
        //   304: ixor           
        //   305: lookupswitch {
        //          -1552410473: 332
        //          -21660890: 300
        //          default: 358
        //        }
        //   332: invokestatic    invokestatic   !!! ERROR
        //   335: iconst_m1      
        //   336: invokespecial   dev/nuker/pyro/f0h.<init>:(Ljava/lang/String;Ljava/lang/String;Ljava/lang/String;I)V
        //   339: checkcast       Ldev/nuker/pyro/f0n;
        //   342: invokevirtual   dev/nuker/pyro/f5m.c:(Ldev/nuker/pyro/f0n;)Ldev/nuker/pyro/f0n;
        //   345: checkcast       Ldev/nuker/pyro/f0h;
        //   348: putfield        dev/nuker/pyro/f5m.c:Ldev/nuker/pyro/f0h;
        //   351: return         
        //   352: aconst_null    
        //   353: athrow         
        //   354: aconst_null    
        //   355: athrow         
        //   356: aconst_null    
        //   357: athrow         
        //   358: aconst_null    
        //   359: athrow         
        //   360: aconst_null    
        //   361: athrow         
        //   362: aconst_null    
        //   363: athrow         
        //   364: aconst_null    
        //   365: athrow         
        //    StackMapTable: 00 1C FF 00 0E 00 01 06 00 02 06 07 00 4E FF 00 01 00 01 06 00 03 06 07 00 4E 01 FF 00 1B 00 01 06 00 02 06 07 00 4E FF 00 0F 00 01 06 00 03 06 07 00 4E 07 00 4E FF 00 01 00 01 06 00 04 06 07 00 4E 07 00 4E 01 FF 00 1D 00 01 06 00 03 06 07 00 4E 07 00 4E FF 00 0F 00 01 06 00 04 06 07 00 4E 07 00 4E 07 00 4E FF 00 01 00 01 06 00 05 06 07 00 4E 07 00 4E 07 00 4E 01 FF 00 1D 00 01 06 00 04 06 07 00 4E 07 00 4E 07 00 4E FF 00 0D 00 01 06 00 04 06 07 00 4E 07 00 4E 07 00 4E FF 00 01 00 01 06 00 05 06 07 00 4E 07 00 4E 07 00 4E 01 FF 00 1B 00 01 06 00 04 06 07 00 4E 07 00 4E 07 00 4E FF 00 0D 00 01 07 00 03 00 00 41 01 1B FF 00 17 00 01 07 00 03 00 06 07 00 03 07 00 03 08 00 E6 08 00 E6 07 00 4E 07 00 4E FF 00 01 00 01 07 00 03 00 07 07 00 03 07 00 03 08 00 E6 08 00 E6 07 00 4E 07 00 4E 01 FF 00 1D 00 01 07 00 03 00 06 07 00 03 07 00 03 08 00 E6 08 00 E6 07 00 4E 07 00 4E FF 00 0F 00 01 07 00 03 00 07 07 00 03 07 00 03 08 00 E6 08 00 E6 07 00 4E 07 00 4E 07 00 4E FF 00 01 00 01 07 00 03 00 08 07 00 03 07 00 03 08 00 E6 08 00 E6 07 00 4E 07 00 4E 07 00 4E 01 FF 00 1D 00 01 07 00 03 00 07 07 00 03 07 00 03 08 00 E6 08 00 E6 07 00 4E 07 00 4E 07 00 4E FF 00 13 00 01 06 00 04 06 07 00 4E 07 00 4E 07 00 4E FF 00 01 00 01 07 00 03 00 00 FF 00 01 00 01 06 00 03 06 07 00 4E 07 00 4E FF 00 01 00 01 07 00 03 00 07 07 00 03 07 00 03 08 00 E6 08 00 E6 07 00 4E 07 00 4E 07 00 4E FF 00 01 00 01 06 00 02 06 07 00 4E FF 00 01 00 01 07 00 03 00 06 07 00 03 07 00 03 08 00 E6 08 00 E6 07 00 4E 07 00 4E FF 00 01 00 01 06 00 04 06 07 00 4E 07 00 4E 07 00 4E
        // 
        // The error that occurred was:
        // 
        // java.lang.IllegalStateException: Invalid BootstrapMethods attribute entry: 21 additional arguments required for method a.a, but only 0 specified.
        //     at com.strobel.assembler.ir.Error.invalidBootstrapMethodEntry(Error.java:244)
        //     at com.strobel.assembler.ir.MetadataReader.readAttributeCore(MetadataReader.java:280)
        //     at com.strobel.assembler.metadata.ClassFileReader.readAttributeCore(ClassFileReader.java:261)
        //     at com.strobel.assembler.ir.MetadataReader.inflateAttributes(MetadataReader.java:439)
        //     at com.strobel.assembler.metadata.ClassFileReader.visitAttributes(ClassFileReader.java:1134)
        //     at com.strobel.assembler.metadata.ClassFileReader.readClass(ClassFileReader.java:439)
        //     at com.strobel.assembler.metadata.ClassFileReader.readClass(ClassFileReader.java:377)
        //     at com.strobel.assembler.metadata.MetadataSystem.resolveType(MetadataSystem.java:129)
        //     at com.strobel.decompiler.NoRetryMetadataSystem.resolveType(DecompilerDriver.java:476)
        //     at com.strobel.assembler.metadata.MetadataSystem.resolveCore(MetadataSystem.java:81)
        //     at com.strobel.assembler.metadata.MetadataResolver.resolve(MetadataResolver.java:104)
        //     at com.strobel.assembler.metadata.CoreMetadataFactory$UnresolvedType.resolve(CoreMetadataFactory.java:616)
        //     at com.strobel.assembler.metadata.MetadataResolver.resolve(MetadataResolver.java:128)
        //     at com.strobel.assembler.metadata.CoreMetadataFactory$UnresolvedType.resolve(CoreMetadataFactory.java:626)
        //     at com.strobel.assembler.metadata.MethodReference.resolve(MethodReference.java:177)
        //     at com.strobel.decompiler.ast.TypeAnalysis.inferCall(TypeAnalysis.java:2438)
        //     at com.strobel.decompiler.ast.TypeAnalysis.doInferTypeForExpression(TypeAnalysis.java:1029)
        //     at com.strobel.decompiler.ast.TypeAnalysis.inferTypeForExpression(TypeAnalysis.java:803)
        //     at com.strobel.decompiler.ast.TypeAnalysis.inferTypeForExpression(TypeAnalysis.java:770)
        //     at com.strobel.decompiler.ast.TypeAnalysis.doInferTypeForExpression(TypeAnalysis.java:881)
        //     at com.strobel.decompiler.ast.TypeAnalysis.inferTypeForExpression(TypeAnalysis.java:803)
        //     at com.strobel.decompiler.ast.TypeAnalysis.runInference(TypeAnalysis.java:672)
        //     at com.strobel.decompiler.ast.TypeAnalysis.runInference(TypeAnalysis.java:655)
        //     at com.strobel.decompiler.ast.TypeAnalysis.runInference(TypeAnalysis.java:365)
        //     at com.strobel.decompiler.ast.TypeAnalysis.run(TypeAnalysis.java:96)
        //     at com.strobel.decompiler.ast.AstOptimizer.optimize(AstOptimizer.java:109)
        //     at com.strobel.decompiler.ast.AstOptimizer.optimize(AstOptimizer.java:42)
        //     at com.strobel.decompiler.languages.java.ast.AstMethodBodyBuilder.createMethodBody(AstMethodBodyBuilder.java:214)
        //     at com.strobel.decompiler.languages.java.ast.AstMethodBodyBuilder.createMethodBody(AstMethodBodyBuilder.java:99)
        //     at com.strobel.decompiler.languages.java.ast.AstBuilder.createMethodBody(AstBuilder.java:782)
        //     at com.strobel.decompiler.languages.java.ast.AstBuilder.createConstructor(AstBuilder.java:713)
        //     at com.strobel.decompiler.languages.java.ast.AstBuilder.addTypeMembers(AstBuilder.java:549)
        //     at com.strobel.decompiler.languages.java.ast.AstBuilder.createTypeCore(AstBuilder.java:519)
        //     at com.strobel.decompiler.languages.java.ast.AstBuilder.createTypeNoCache(AstBuilder.java:161)
        //     at com.strobel.decompiler.languages.java.ast.AstBuilder.createType(AstBuilder.java:150)
        //     at com.strobel.decompiler.languages.java.ast.AstBuilder.addType(AstBuilder.java:125)
        //     at com.strobel.decompiler.languages.java.JavaLanguage.buildAst(JavaLanguage.java:71)
        //     at com.strobel.decompiler.languages.java.JavaLanguage.decompileType(JavaLanguage.java:59)
        //     at com.strobel.decompiler.DecompilerDriver.decompileType(DecompilerDriver.java:330)
        //     at com.strobel.decompiler.DecompilerDriver.decompileJar(DecompilerDriver.java:251)
        //     at com.strobel.decompiler.DecompilerDriver.main(DecompilerDriver.java:126)
        // 
        throw new IllegalStateException("An error occurred while decompiling this method.");
    }
    
    @f06(1)
    @LauncherEventHide
    public void c(@NotNull final f3e p0) {
        // 
        // This method could not be decompiled.
        // 
        // Original Bytecode:
        // 
        //     3: dup            
        //     4: ifnull          1477
        //     7: athrow         
        //     8: aconst_null    
        //     9: getstatic       dev/nuker/pyro/fc.0:I
        //    12: ifgt            1469
        //    15: pop            
        //    16: aconst_null    
        //    17: goto            1461
        //    20: nop            
        //    21: nop            
        //    22: nop            
        //    23: athrow         
        //    24: getstatic       dev/nuker/pyro/fc.c:I
        //    27: ifge            35
        //    30: ldc             2021347288
        //    32: goto            37
        //    35: ldc             -1000166026
        //    37: ldc             -1171725396
        //    39: ixor           
        //    40: lookupswitch {
        //          -1034703756: 35
        //          2118799066: 68
        //          default: 1414
        //        }
        //    68: aload_1        
        //    69: pop            
        //    70: getstatic       dev/nuker/pyro/fc.c:I
        //    73: ifge            81
        //    76: ldc             -1723481318
        //    78: goto            83
        //    81: ldc             -332796823
        //    83: ldc             755090436
        //    85: ixor           
        //    86: lookupswitch {
        //          -1583689381: 81
        //          -1270610146: 1418
        //          default: 112
        //        }
        //   112: aload_0        
        //   113: getfield        dev/nuker/pyro/f5m.c:Ldev/nuker/pyro/f0h;
        //   116: goto            120
        //   119: athrow         
        //   120: invokevirtual   dev/nuker/pyro/f0h.c:()Z
        //   123: goto            127
        //   126: athrow         
        //   127: ifeq            1407
        //   130: aload_0        
        //   131: getfield        dev/nuker/pyro/f5m.c:Lnet/minecraft/client/Minecraft;
        //   134: getstatic       dev/nuker/pyro/fc.0:I
        //   137: ifeq            145
        //   140: ldc             948786192
        //   142: goto            147
        //   145: ldc             372713593
        //   147: ldc             2021018200
        //   149: ixor           
        //   150: lookupswitch {
        //          1090199112: 145
        //          1849778721: 176
        //          default: 1416
        //        }
        //   176: getfield        net/minecraft/client/Minecraft.field_71439_g:Lnet/minecraft/client/entity/EntityPlayerSP;
        //   179: dconst_0       
        //   180: putfield        net/minecraft/client/entity/EntityPlayerSP.field_70159_w:D
        //   183: aload_0        
        //   184: getfield        dev/nuker/pyro/f5m.c:Lnet/minecraft/client/Minecraft;
        //   187: getfield        net/minecraft/client/Minecraft.field_71439_g:Lnet/minecraft/client/entity/EntityPlayerSP;
        //   190: dconst_0       
        //   191: putfield        net/minecraft/client/entity/EntityPlayerSP.field_70179_y:D
        //   194: getstatic       dev/nuker/pyro/fc.1:I
        //   197: ifeq            205
        //   200: ldc             -30241228
        //   202: goto            207
        //   205: ldc             1220150885
        //   207: ldc             -1022652793
        //   209: ixor           
        //   210: lookupswitch {
        //          1027145907: 1438
        //          1150170249: 205
        //          default: 236
        //        }
        //   236: aload_0        
        //   237: getfield        dev/nuker/pyro/f5m.c:Lnet/minecraft/client/Minecraft;
        //   240: getfield        net/minecraft/client/Minecraft.field_71439_g:Lnet/minecraft/client/entity/EntityPlayerSP;
        //   243: getstatic       dev/nuker/pyro/fc.1:I
        //   246: ifeq            254
        //   249: ldc             1147846198
        //   251: goto            256
        //   254: ldc             -513133207
        //   256: ldc             -1246824939
        //   258: ixor           
        //   259: lookupswitch {
        //          -238794717: 254
        //          1422181244: 284
        //          default: 1440
        //        }
        //   284: getfield        net/minecraft/client/entity/EntityPlayerSP.field_71158_b:Lnet/minecraft/util/MovementInput;
        //   287: fconst_0       
        //   288: putfield        net/minecraft/util/MovementInput.field_192832_b:F
        //   291: aload_0        
        //   292: getstatic       dev/nuker/pyro/fc.c:I
        //   295: ifge            303
        //   298: ldc             -809492913
        //   300: goto            305
        //   303: ldc             -1187759522
        //   305: ldc             -1470236414
        //   307: ixor           
        //   308: lookupswitch {
        //          1097846118: 303
        //          1738401613: 1412
        //          default: 336
        //        }
        //   336: getfield        dev/nuker/pyro/f5m.c:Lnet/minecraft/client/Minecraft;
        //   339: getfield        net/minecraft/client/Minecraft.field_71439_g:Lnet/minecraft/client/entity/EntityPlayerSP;
        //   342: getstatic       dev/nuker/pyro/fc.0:I
        //   345: ifeq            353
        //   348: ldc             -635931846
        //   350: goto            355
        //   353: ldc             -876438970
        //   355: ldc             -650121751
        //   357: ixor           
        //   358: lookupswitch {
        //          52928211: 353
        //          318601135: 384
        //          default: 1424
        //        }
        //   384: getfield        net/minecraft/client/entity/EntityPlayerSP.field_71158_b:Lnet/minecraft/util/MovementInput;
        //   387: fconst_0       
        //   388: getstatic       dev/nuker/pyro/fc.0:I
        //   391: ifeq            399
        //   394: ldc             -1129115390
        //   396: goto            401
        //   399: ldc             1847291671
        //   401: ldc             -1651404545
        //   403: ixor           
        //   404: lookupswitch {
        //          -1223074637: 399
        //          555909629: 1426
        //          default: 432
        //        }
        //   432: putfield        net/minecraft/util/MovementInput.field_78902_a:F
        //   435: aload_0        
        //   436: getfield        dev/nuker/pyro/f5m.c:Lnet/minecraft/client/Minecraft;
        //   439: getstatic       dev/nuker/pyro/fc.0:I
        //   442: ifeq            450
        //   445: ldc             324134022
        //   447: goto            452
        //   450: ldc             903291265
        //   452: ldc             -1857447490
        //   454: ixor           
        //   455: lookupswitch {
        //          -2112324296: 1408
        //          -409915148: 450
        //          default: 480
        //        }
        //   480: getfield        net/minecraft/client/Minecraft.field_71439_g:Lnet/minecraft/client/entity/EntityPlayerSP;
        //   483: getfield        net/minecraft/client/entity/EntityPlayerSP.field_70181_x:D
        //   486: ldc2_w          -0.1
        //   489: dcmpl          
        //   490: ifle            506
        //   493: aload_0        
        //   494: getfield        dev/nuker/pyro/f5m.c:Lnet/minecraft/client/Minecraft;
        //   497: getfield        net/minecraft/client/Minecraft.field_71439_g:Lnet/minecraft/client/entity/EntityPlayerSP;
        //   500: ldc2_w          -0.1
        //   503: putfield        net/minecraft/client/entity/EntityPlayerSP.field_70181_x:D
        //   506: new             Lnet/minecraft/util/math/BlockPos;
        //   509: dup            
        //   510: aload_0        
        //   511: getfield        dev/nuker/pyro/f5m.c:Lnet/minecraft/client/Minecraft;
        //   514: getfield        net/minecraft/client/Minecraft.field_71439_g:Lnet/minecraft/client/entity/EntityPlayerSP;
        //   517: dup            
        //   518: pop            
        //   519: goto            523
        //   522: athrow         
        //   523: invokevirtual   net/minecraft/client/entity/EntityPlayerSP.func_174791_d:()Lnet/minecraft/util/math/Vec3d;
        //   526: goto            530
        //   529: athrow         
        //   530: goto            534
        //   533: athrow         
        //   534: invokespecial   net/minecraft/util/math/BlockPos.<init>:(Lnet/minecraft/util/math/Vec3d;)V
        //   537: goto            541
        //   540: athrow         
        //   541: getstatic       dev/nuker/pyro/fc.1:I
        //   544: ifeq            552
        //   547: ldc             1615641198
        //   549: goto            554
        //   552: ldc             1642780108
        //   554: ldc             468058297
        //   556: ixor           
        //   557: lookupswitch {
        //          2047661429: 584
        //          2074786519: 552
        //          default: 1446
        //        }
        //   584: astore_2       
        //   585: aload_0        
        //   586: getfield        dev/nuker/pyro/f5m.c:Lnet/minecraft/client/Minecraft;
        //   589: getfield        net/minecraft/client/Minecraft.field_71439_g:Lnet/minecraft/client/entity/EntityPlayerSP;
        //   592: dup            
        //   593: pop            
        //   594: goto            598
        //   597: athrow         
        //   598: invokevirtual   net/minecraft/client/entity/EntityPlayerSP.func_174813_aQ:()Lnet/minecraft/util/math/AxisAlignedBB;
        //   601: goto            605
        //   604: athrow         
        //   605: getfield        net/minecraft/util/math/AxisAlignedBB.field_72340_a:D
        //   608: aload_2        
        //   609: goto            613
        //   612: athrow         
        //   613: invokevirtual   net/minecraft/util/math/BlockPos.func_177958_n:()I
        //   616: goto            620
        //   619: athrow         
        //   620: i2d            
        //   621: dcmpg          
        //   622: ifle            994
        //   625: aload_0        
        //   626: getfield        dev/nuker/pyro/f5m.c:Lnet/minecraft/client/Minecraft;
        //   629: getfield        net/minecraft/client/Minecraft.field_71439_g:Lnet/minecraft/client/entity/EntityPlayerSP;
        //   632: dup            
        //   633: pop            
        //   634: goto            638
        //   637: athrow         
        //   638: invokevirtual   net/minecraft/client/entity/EntityPlayerSP.func_174813_aQ:()Lnet/minecraft/util/math/AxisAlignedBB;
        //   641: goto            645
        //   644: athrow         
        //   645: getstatic       dev/nuker/pyro/fc.0:I
        //   648: ifeq            656
        //   651: ldc             1589807130
        //   653: goto            658
        //   656: ldc             -1205796930
        //   658: ldc             -358698621
        //   660: ixor           
        //   661: lookupswitch {
        //          -1269024359: 656
        //          1388203581: 688
        //          default: 1444
        //        }
        //   688: getfield        net/minecraft/util/math/AxisAlignedBB.field_72339_c:D
        //   691: aload_2        
        //   692: goto            696
        //   695: athrow         
        //   696: invokevirtual   net/minecraft/util/math/BlockPos.func_177952_p:()I
        //   699: goto            703
        //   702: athrow         
        //   703: i2d            
        //   704: dcmpg          
        //   705: ifle            713
        //   708: ldc             222986407
        //   710: goto            715
        //   713: ldc             222986406
        //   715: ldc             -1406659865
        //   717: ixor           
        //   718: tableswitch {
        //          1120216192: 740
        //          1120216193: 994
        //          default: 708
        //        }
        //   740: aload_0        
        //   741: getfield        dev/nuker/pyro/f5m.c:Lnet/minecraft/client/Minecraft;
        //   744: getstatic       dev/nuker/pyro/fc.0:I
        //   747: ifeq            755
        //   750: ldc             602175329
        //   752: goto            757
        //   755: ldc             -307584441
        //   757: ldc             938762582
        //   759: ixor           
        //   760: lookupswitch {
        //          -631323887: 788
        //          336598583: 755
        //          default: 1442
        //        }
        //   788: getfield        net/minecraft/client/Minecraft.field_71439_g:Lnet/minecraft/client/entity/EntityPlayerSP;
        //   791: dup            
        //   792: pop            
        //   793: getstatic       dev/nuker/pyro/fc.c:I
        //   796: ifge            804
        //   799: ldc             -1943051183
        //   801: goto            806
        //   804: ldc             1548212730
        //   806: ldc             -2048576028
        //   808: ixor           
        //   809: lookupswitch {
        //          -643634146: 836
        //          164254133: 804
        //          default: 1448
        //        }
        //   836: goto            840
        //   839: athrow         
        //   840: invokevirtual   net/minecraft/client/entity/EntityPlayerSP.func_174813_aQ:()Lnet/minecraft/util/math/AxisAlignedBB;
        //   843: goto            847
        //   846: athrow         
        //   847: getfield        net/minecraft/util/math/AxisAlignedBB.field_72336_d:D
        //   850: getstatic       dev/nuker/pyro/fc.1:I
        //   853: ifeq            861
        //   856: ldc             -215234155
        //   858: goto            863
        //   861: ldc             1746388489
        //   863: ldc             -970461978
        //   865: ixor           
        //   866: lookupswitch {
        //          321431841: 861
        //          889988467: 1422
        //          default: 892
        //        }
        //   892: aload_2        
        //   893: goto            897
        //   896: athrow         
        //   897: invokevirtual   net/minecraft/util/math/BlockPos.func_177958_n:()I
        //   900: goto            904
        //   903: athrow         
        //   904: iconst_1       
        //   905: iadd           
        //   906: i2d            
        //   907: dcmpl          
        //   908: ifge            994
        //   911: getstatic       dev/nuker/pyro/fc.c:I
        //   914: ifge            922
        //   917: ldc             1663008723
        //   919: goto            924
        //   922: ldc             -874036693
        //   924: ldc             1978387876
        //   926: ixor           
        //   927: lookupswitch {
        //          -1106473073: 952
        //          385135223: 922
        //          default: 1430
        //        }
        //   952: aload_0        
        //   953: getfield        dev/nuker/pyro/f5m.c:Lnet/minecraft/client/Minecraft;
        //   956: getfield        net/minecraft/client/Minecraft.field_71439_g:Lnet/minecraft/client/entity/EntityPlayerSP;
        //   959: dup            
        //   960: pop            
        //   961: goto            965
        //   964: athrow         
        //   965: invokevirtual   net/minecraft/client/entity/EntityPlayerSP.func_174813_aQ:()Lnet/minecraft/util/math/AxisAlignedBB;
        //   968: goto            972
        //   971: athrow         
        //   972: getfield        net/minecraft/util/math/AxisAlignedBB.field_72334_f:D
        //   975: aload_2        
        //   976: goto            980
        //   979: athrow         
        //   980: invokevirtual   net/minecraft/util/math/BlockPos.func_177952_p:()I
        //   983: goto            987
        //   986: athrow         
        //   987: iconst_1       
        //   988: iadd           
        //   989: i2d            
        //   990: dcmpl          
        //   991: iflt            1395
        //   994: getstatic       dev/nuker/pyro/fc.1:I
        //   997: ifeq            1005
        //  1000: ldc             573965421
        //  1002: goto            1007
        //  1005: ldc             1618696915
        //  1007: ldc             -699509253
        //  1009: ixor           
        //  1010: lookupswitch {
        //          -1238036696: 1036
        //          -193441386: 1005
        //          default: 1410
        //        }
        //  1036: aload_2        
        //  1037: goto            1041
        //  1040: athrow         
        //  1041: invokevirtual   net/minecraft/util/math/BlockPos.func_177958_n:()I
        //  1044: goto            1048
        //  1047: athrow         
        //  1048: i2d            
        //  1049: ldc2_w          0.5
        //  1052: dadd           
        //  1053: aload_0        
        //  1054: getfield        dev/nuker/pyro/f5m.c:Lnet/minecraft/client/Minecraft;
        //  1057: getfield        net/minecraft/client/Minecraft.field_71439_g:Lnet/minecraft/client/entity/EntityPlayerSP;
        //  1060: getfield        net/minecraft/client/entity/EntityPlayerSP.field_70165_t:D
        //  1063: dsub           
        //  1064: getstatic       dev/nuker/pyro/fc.1:I
        //  1067: ifeq            1075
        //  1070: ldc             -1962135560
        //  1072: goto            1077
        //  1075: ldc             1305849666
        //  1077: ldc             1610057181
        //  1079: ixor           
        //  1080: lookupswitch {
        //          -721704411: 1075
        //          304229023: 1108
        //          default: 1420
        //        }
        //  1108: dstore_3       
        //  1109: getstatic       dev/nuker/pyro/fc.c:I
        //  1112: ifge            1120
        //  1115: ldc             1047259281
        //  1117: goto            1122
        //  1120: ldc             573189984
        //  1122: ldc             51280103
        //  1124: ixor           
        //  1125: lookupswitch {
        //          -1026944700: 1120
        //          1030066294: 1450
        //          default: 1152
        //        }
        //  1152: aload_2        
        //  1153: goto            1157
        //  1156: athrow         
        //  1157: invokevirtual   net/minecraft/util/math/BlockPos.func_177952_p:()I
        //  1160: goto            1164
        //  1163: athrow         
        //  1164: i2d            
        //  1165: ldc2_w          0.5
        //  1168: dadd           
        //  1169: aload_0        
        //  1170: getstatic       dev/nuker/pyro/fc.0:I
        //  1173: ifeq            1181
        //  1176: ldc             -1988037024
        //  1178: goto            1183
        //  1181: ldc             -565592944
        //  1183: ldc             1950296234
        //  1185: ixor           
        //  1186: lookupswitch {
        //          -853463192: 1181
        //          -37757238: 1428
        //          default: 1212
        //        }
        //  1212: getfield        dev/nuker/pyro/f5m.c:Lnet/minecraft/client/Minecraft;
        //  1215: getfield        net/minecraft/client/Minecraft.field_71439_g:Lnet/minecraft/client/entity/EntityPlayerSP;
        //  1218: getfield        net/minecraft/client/entity/EntityPlayerSP.field_70161_v:D
        //  1221: dsub           
        //  1222: dstore          5
        //  1224: aload_1        
        //  1225: dload_3        
        //  1226: iconst_2       
        //  1227: i2d            
        //  1228: ddiv           
        //  1229: goto            1233
        //  1232: athrow         
        //  1233: invokevirtual   dev/nuker/pyro/f3e.1:(D)V
        //  1236: goto            1240
        //  1239: athrow         
        //  1240: getstatic       dev/nuker/pyro/fc.0:I
        //  1243: ifeq            1252
        //  1246: ldc_w           149181250
        //  1249: goto            1255
        //  1252: ldc_w           -1590608145
        //  1255: ldc_w           463936067
        //  1258: ixor           
        //  1259: lookupswitch {
        //          -1164565332: 1284
        //          323176705: 1252
        //          default: 1432
        //        }
        //  1284: aload_1        
        //  1285: getstatic       dev/nuker/pyro/fc.0:I
        //  1288: ifeq            1297
        //  1291: ldc_w           1891410416
        //  1294: goto            1300
        //  1297: ldc_w           272368596
        //  1300: ldc_w           -123239269
        //  1303: ixor           
        //  1304: lookupswitch {
        //          -2011486869: 1434
        //          1504981516: 1297
        //          default: 1332
        //        }
        //  1332: dload           5
        //  1334: iconst_2       
        //  1335: i2d            
        //  1336: ddiv           
        //  1337: getstatic       dev/nuker/pyro/fc.0:I
        //  1340: ifeq            1349
        //  1343: ldc_w           -1681531903
        //  1346: goto            1352
        //  1349: ldc_w           1581599043
        //  1352: ldc_w           458453236
        //  1355: ixor           
        //  1356: lookupswitch {
        //          -2137608971: 1349
        //          1159084471: 1384
        //          default: 1436
        //        }
        //  1384: goto            1388
        //  1387: athrow         
        //  1388: invokevirtual   dev/nuker/pyro/f3e.0:(D)V
        //  1391: goto            1395
        //  1394: athrow         
        //  1395: aload_1        
        //  1396: goto            1400
        //  1399: athrow         
        //  1400: invokevirtual   dev/nuker/pyro/f3e.c:()V
        //  1403: goto            1407
        //  1406: athrow         
        //  1407: return         
        //  1408: aconst_null    
        //  1409: athrow         
        //  1410: aconst_null    
        //  1411: athrow         
        //  1412: aconst_null    
        //  1413: athrow         
        //  1414: aconst_null    
        //  1415: athrow         
        //  1416: aconst_null    
        //  1417: athrow         
        //  1418: aconst_null    
        //  1419: athrow         
        //  1420: aconst_null    
        //  1421: athrow         
        //  1422: aconst_null    
        //  1423: athrow         
        //  1424: aconst_null    
        //  1425: athrow         
        //  1426: aconst_null    
        //  1427: athrow         
        //  1428: aconst_null    
        //  1429: athrow         
        //  1430: aconst_null    
        //  1431: athrow         
        //  1432: aconst_null    
        //  1433: athrow         
        //  1434: aconst_null    
        //  1435: athrow         
        //  1436: aconst_null    
        //  1437: athrow         
        //  1438: aconst_null    
        //  1439: athrow         
        //  1440: aconst_null    
        //  1441: athrow         
        //  1442: aconst_null    
        //  1443: athrow         
        //  1444: aconst_null    
        //  1445: athrow         
        //  1446: aconst_null    
        //  1447: athrow         
        //  1448: aconst_null    
        //  1449: athrow         
        //  1450: aconst_null    
        //  1451: athrow         
        //  1452: pop            
        //  1453: goto            24
        //  1456: pop            
        //  1457: aconst_null    
        //  1458: goto            1452
        //  1461: dup            
        //  1462: ifnull          1452
        //  1465: checkcast       Ljava/lang/Throwable;
        //  1468: athrow         
        //  1469: dup            
        //  1470: ifnull          1456
        //  1473: checkcast       Ljava/lang/Throwable;
        //  1476: athrow         
        //  1477: aconst_null    
        //  1478: athrow         
        //    StackMapTable: 00 A7 43 07 00 71 04 FF 00 0B 00 00 00 01 07 00 71 FD 00 03 07 00 03 07 01 00 0A 41 01 1E 0C 41 01 1C 46 07 00 71 40 07 00 34 45 07 00 71 40 01 51 07 00 82 FF 00 01 00 02 07 00 03 07 01 00 00 02 07 00 82 01 5C 07 00 82 1C 41 01 1C 51 07 00 88 FF 00 01 00 02 07 00 03 07 01 00 00 02 07 00 88 01 5B 07 00 88 52 07 00 03 FF 00 01 00 02 07 00 03 07 01 00 00 02 07 00 03 01 5E 07 00 03 50 07 00 88 FF 00 01 00 02 07 00 03 07 01 00 00 02 07 00 88 01 5C 07 00 88 FF 00 0E 00 02 07 00 03 07 01 00 00 02 07 00 9B 02 FF 00 01 00 02 07 00 03 07 01 00 00 03 07 00 9B 02 01 FF 00 1E 00 02 07 00 03 07 01 00 00 02 07 00 9B 02 51 07 00 82 FF 00 01 00 02 07 00 03 07 01 00 00 02 07 00 82 01 5B 07 00 82 19 4F 07 00 5B FF 00 00 00 02 07 00 03 07 01 00 00 03 08 01 FA 08 01 FA 07 00 88 45 07 00 71 FF 00 00 00 02 07 00 03 07 01 00 00 03 08 01 FA 08 01 FA 07 01 12 FF 00 02 00 00 00 01 07 00 71 FF 00 00 00 02 07 00 03 07 01 00 00 03 08 01 FA 08 01 FA 07 01 12 45 07 00 71 40 07 00 B5 4A 07 00 B5 FF 00 01 00 02 07 00 03 07 01 00 00 02 07 00 B5 01 5D 07 00 B5 FF 00 0C 00 03 07 00 03 07 01 00 07 00 B5 00 01 07 00 71 40 07 00 88 45 07 00 71 40 07 00 C5 FF 00 06 00 00 00 01 07 00 71 FF 00 00 00 03 07 00 03 07 01 00 07 00 B5 00 02 03 07 00 B5 45 07 00 71 FF 00 00 00 03 07 00 03 07 01 00 07 00 B5 00 02 03 01 FF 00 10 00 00 00 01 07 00 71 FF 00 00 00 03 07 00 03 07 01 00 07 00 B5 00 01 07 00 88 45 07 00 71 40 07 00 C5 4A 07 00 C5 FF 00 01 00 03 07 00 03 07 01 00 07 00 B5 00 02 07 00 C5 01 5D 07 00 C5 FF 00 06 00 00 00 01 07 00 71 FF 00 00 00 03 07 00 03 07 01 00 07 00 B5 00 02 03 07 00 B5 45 07 00 71 FF 00 00 00 03 07 00 03 07 01 00 07 00 B5 00 02 03 01 04 04 41 01 18 4E 07 00 82 FF 00 01 00 03 07 00 03 07 01 00 07 00 B5 00 02 07 00 82 01 5E 07 00 82 4F 07 00 88 FF 00 01 00 03 07 00 03 07 01 00 07 00 B5 00 02 07 00 88 01 5D 07 00 88 42 07 00 71 40 07 00 88 45 07 00 71 40 07 00 C5 4D 03 FF 00 01 00 03 07 00 03 07 01 00 07 00 B5 00 02 03 01 5C 03 43 07 00 71 FF 00 00 00 03 07 00 03 07 01 00 07 00 B5 00 02 03 07 00 B5 45 07 00 71 FF 00 00 00 03 07 00 03 07 01 00 07 00 B5 00 02 03 01 11 41 01 1B 4B 07 00 71 40 07 00 88 45 07 00 71 40 07 00 C5 FF 00 06 00 00 00 01 07 00 71 FF 00 00 00 03 07 00 03 07 01 00 07 00 B5 00 02 03 07 00 B5 45 07 00 71 FF 00 00 00 03 07 00 03 07 01 00 07 00 B5 00 02 03 01 06 0A 41 01 1C 43 07 00 71 40 07 00 B5 45 07 00 71 40 01 5A 03 FF 00 01 00 03 07 00 03 07 01 00 07 00 B5 00 02 03 01 5E 03 FC 00 0B 03 41 01 1D 43 07 00 55 40 07 00 B5 45 07 00 71 40 01 FF 00 10 00 04 07 00 03 07 01 00 07 00 B5 03 00 02 03 07 00 03 FF 00 01 00 04 07 00 03 07 01 00 07 00 B5 03 00 03 03 07 00 03 01 FF 00 1C 00 04 07 00 03 07 01 00 07 00 B5 03 00 02 03 07 00 03 FF 00 13 00 05 07 00 03 07 01 00 07 00 B5 03 03 00 01 07 00 71 FF 00 00 00 05 07 00 03 07 01 00 07 00 B5 03 03 00 02 07 01 00 03 45 07 00 71 00 0B 42 01 1C 4C 07 01 00 FF 00 02 00 05 07 00 03 07 01 00 07 00 B5 03 03 00 02 07 01 00 01 5F 07 01 00 FF 00 10 00 05 07 00 03 07 01 00 07 00 B5 03 03 00 02 07 01 00 03 FF 00 02 00 05 07 00 03 07 01 00 07 00 B5 03 03 00 03 07 01 00 03 01 FF 00 1F 00 05 07 00 03 07 01 00 07 00 B5 03 03 00 02 07 01 00 03 42 07 00 71 FF 00 00 00 05 07 00 03 07 01 00 07 00 B5 03 03 00 02 07 01 00 03 45 07 00 71 F9 00 00 43 07 00 5F 40 07 01 00 45 07 00 71 FA 00 00 40 07 00 82 FC 00 01 07 00 B5 FF 00 01 00 02 07 00 03 07 01 00 00 01 07 00 03 01 41 07 00 82 01 FF 00 01 00 03 07 00 03 07 01 00 07 00 B5 00 01 03 41 03 FF 00 01 00 02 07 00 03 07 01 00 00 01 07 00 88 FF 00 01 00 02 07 00 03 07 01 00 00 02 07 00 9B 02 FF 00 01 00 04 07 00 03 07 01 00 07 00 B5 03 00 02 03 07 00 03 FA 00 01 FD 00 01 03 03 41 07 01 00 FF 00 01 00 05 07 00 03 07 01 00 07 00 B5 03 03 00 02 07 01 00 03 F8 00 01 41 07 00 88 FF 00 01 00 03 07 00 03 07 01 00 07 00 B5 00 01 07 00 82 41 07 00 C5 FF 00 01 00 02 07 00 03 07 01 00 00 01 07 00 B5 FF 00 01 00 03 07 00 03 07 01 00 07 00 B5 00 01 07 00 88 FC 00 01 03 FF 00 01 00 02 07 00 03 07 01 00 00 01 07 00 71 43 05 44 07 00 71 47 05 47 07 00 71
        //    Exceptions:
        //  Try           Handler
        //  Start  End    Start  End    Type                                       
        //  -----  -----  -----  -----  -------------------------------------------
        //  8      20     1461   1469   Any
        //  1461   1469   1461   1469   Ljava/lang/AssertionError;
        //  1477   1479   3      8      Any
        //  119    126    126    127    Any
        //  120    126    119    120    Any
        //  119    126    126    127    Ljava/lang/ArrayIndexOutOfBoundsException;
        //  119    126    3      8      Ljava/lang/NullPointerException;
        //  120    126    3      8      Any
        //  522    529    529    530    Any
        //  522    529    529    530    Any
        //  522    529    522    523    Ljava/lang/ArithmeticException;
        //  522    529    529    530    Any
        //  523    529    522    523    Ljava/lang/ArithmeticException;
        //  534    540    540    541    Any
        //  534    540    540    541    Any
        //  534    540    540    541    Any
        //  534    540    3      8      Ljava/lang/AssertionError;
        //  534    540    3      8      Ljava/lang/NegativeArraySizeException;
        //  597    604    604    605    Any
        //  598    604    597    598    Any
        //  598    604    597    598    Any
        //  598    604    597    598    Ljava/lang/RuntimeException;
        //  597    604    3      8      Any
        //  613    619    619    620    Any
        //  613    619    619    620    Ljava/lang/NullPointerException;
        //  613    619    3      8      Ljava/util/ConcurrentModificationException;
        //  613    619    3      8      Ljava/lang/AssertionError;
        //  613    619    619    620    Ljava/lang/IndexOutOfBoundsException;
        //  638    644    644    645    Any
        //  638    644    644    645    Ljava/lang/IllegalArgumentException;
        //  638    644    3      8      Ljava/lang/ArrayIndexOutOfBoundsException;
        //  638    644    3      8      Any
        //  638    644    3      8      Any
        //  696    702    702    703    Any
        //  696    702    3      8      Any
        //  696    702    3      8      Ljava/util/NoSuchElementException;
        //  696    702    3      8      Any
        //  696    702    702    703    Ljava/lang/ArrayIndexOutOfBoundsException;
        //  839    846    846    847    Any
        //  840    846    3      8      Any
        //  839    846    839    840    Any
        //  840    846    846    847    Ljava/lang/RuntimeException;
        //  840    846    839    840    Ljava/util/ConcurrentModificationException;
        //  896    903    903    904    Any
        //  897    903    896    897    Any
        //  897    903    896    897    Ljava/lang/IndexOutOfBoundsException;
        //  897    903    896    897    Any
        //  896    903    903    904    Any
        //  964    971    971    972    Any
        //  964    971    964    965    Ljava/lang/IllegalStateException;
        //  964    971    964    965    Any
        //  965    971    3      8      Any
        //  964    971    3      8      Any
        //  980    986    986    987    Any
        //  980    986    3      8      Any
        //  980    986    986    987    Ljava/lang/NullPointerException;
        //  980    986    986    987    Ljava/lang/AssertionError;
        //  980    986    986    987    Ljava/lang/IndexOutOfBoundsException;
        //  1040   1047   1047   1048   Any
        //  1041   1047   1040   1041   Any
        //  1041   1047   3      8      Any
        //  1041   1047   1040   1041   Any
        //  1040   1047   3      8      Ljava/lang/ArithmeticException;
        //  1156   1163   1163   1164   Any
        //  1157   1163   1163   1164   Any
        //  1156   1163   1163   1164   Ljava/util/ConcurrentModificationException;
        //  1157   1163   1156   1157   Ljava/lang/AssertionError;
        //  1157   1163   1163   1164   Any
        //  1232   1239   1239   1240   Any
        //  1232   1239   3      8      Any
        //  1232   1239   3      8      Ljava/lang/NumberFormatException;
        //  1233   1239   1232   1233   Any
        //  1232   1239   1239   1240   Any
        //  1387   1394   1394   1395   Any
        //  1388   1394   3      8      Any
        //  1388   1394   1387   1388   Any
        //  1388   1394   1394   1395   Ljava/lang/StringIndexOutOfBoundsException;
        //  1387   1394   1394   1395   Any
        //  1399   1406   1406   1407   Any
        //  1399   1406   1399   1400   Ljava/util/ConcurrentModificationException;
        //  1400   1406   1399   1400   Ljava/lang/UnsupportedOperationException;
        //  1399   1406   1406   1407   Any
        //  1400   1406   1406   1407   Ljava/lang/IndexOutOfBoundsException;
        // 
        // The error that occurred was:
        // 
        // java.lang.IndexOutOfBoundsException: Index -1 out of bounds for length 0
        //     at java.base/jdk.internal.util.Preconditions.outOfBounds(Preconditions.java:64)
        //     at java.base/jdk.internal.util.Preconditions.outOfBoundsCheckIndex(Preconditions.java:70)
        //     at java.base/jdk.internal.util.Preconditions.checkIndex(Preconditions.java:248)
        //     at java.base/java.util.Objects.checkIndex(Objects.java:372)
        //     at java.base/java.util.ArrayList.remove(ArrayList.java:535)
        //     at com.strobel.assembler.ir.StackMappingVisitor.pop(StackMappingVisitor.java:267)
        //     at com.strobel.assembler.ir.StackMappingVisitor$InstructionAnalyzer.execute(StackMappingVisitor.java:595)
        //     at com.strobel.assembler.ir.StackMappingVisitor$InstructionAnalyzer.visit(StackMappingVisitor.java:398)
        //     at com.strobel.decompiler.ast.AstBuilder.performStackAnalysis(AstBuilder.java:2030)
        //     at com.strobel.decompiler.ast.AstBuilder.build(AstBuilder.java:108)
        //     at com.strobel.decompiler.languages.java.ast.AstMethodBodyBuilder.createMethodBody(AstMethodBodyBuilder.java:211)
        //     at com.strobel.decompiler.languages.java.ast.AstMethodBodyBuilder.createMethodBody(AstMethodBodyBuilder.java:99)
        //     at com.strobel.decompiler.languages.java.ast.AstBuilder.createMethodBody(AstBuilder.java:782)
        //     at com.strobel.decompiler.languages.java.ast.AstBuilder.createMethod(AstBuilder.java:675)
        //     at com.strobel.decompiler.languages.java.ast.AstBuilder.addTypeMembers(AstBuilder.java:552)
        //     at com.strobel.decompiler.languages.java.ast.AstBuilder.createTypeCore(AstBuilder.java:519)
        //     at com.strobel.decompiler.languages.java.ast.AstBuilder.createTypeNoCache(AstBuilder.java:161)
        //     at com.strobel.decompiler.languages.java.ast.AstBuilder.createType(AstBuilder.java:150)
        //     at com.strobel.decompiler.languages.java.ast.AstBuilder.addType(AstBuilder.java:125)
        //     at com.strobel.decompiler.languages.java.JavaLanguage.buildAst(JavaLanguage.java:71)
        //     at com.strobel.decompiler.languages.java.JavaLanguage.decompileType(JavaLanguage.java:59)
        //     at com.strobel.decompiler.DecompilerDriver.decompileType(DecompilerDriver.java:330)
        //     at com.strobel.decompiler.DecompilerDriver.decompileJar(DecompilerDriver.java:251)
        //     at com.strobel.decompiler.DecompilerDriver.main(DecompilerDriver.java:126)
        // 
        throw new IllegalStateException("An error occurred while decompiling this method.");
    }
    
    @NotNull
    public f0h c() {
        return fbS.97(this, 45105395);
    }
}
