// 
// Decompiled by Procyon v0.5.36
// 

package dev.nuker.pyro;

import org.jetbrains.annotations.NotNull;
import kotlin.jvm.JvmField;

public class f66 extends fH
{
    @JvmField
    @NotNull
    public f0a c;
    @JvmField
    @NotNull
    public f0a 0;
    
    public f66() {
        // 
        // This method could not be decompiled.
        // 
        // Original Bytecode:
        // 
        //     1: ldc             "\u23e3\u149d\u8aef\ub3d0\uc99e\uede0\ub22d\ue6c5\ud96b\ue9dd\ua72a\u1e42\ue1f7\uc5a4\u8141"
        //     3: invokestatic    invokestatic   !!! ERROR
        //     6: ldc             "\u23c3\u149d\u8aef\ub3d0\uc985\ueded\ub237\ue6d5\ud967\ue9dc\ua72a\u1e49\ue1f1\uc5b3"
        //     8: invokestatic    invokestatic   !!! ERROR
        //    11: ldc             "\u23c5\u149a\u8aed\ub3dc\uc9b2\ueda4\ub225\ue696\ud96b\ue9dd\ua72a\u1e4a\ue1fb\uc5b5\u8158\u897e\u57b0\u771a\ubd32\uc060\u2b50\uc228\u6a18\u2d44\ud7b5\u3582\u7d25\u89f8\u8013\u8cf0\u84a4\ufb3d\u70d6\u9a13\u1ba7\uf17c\u4973\u8862\ucac6\uff41\ub6d3\u41e0\ub9e1\ub347\u4c19\u8af9\u7c6c\uce30\u7d5a"
        //    13: getstatic       dev/nuker/pyro/fc.1:I
        //    16: ifeq            24
        //    19: ldc             1736045565
        //    21: goto            26
        //    24: ldc             -233858832
        //    26: ldc             -1784430845
        //    28: ixor           
        //    29: lookupswitch {
        //          -220574466: 524
        //          -66562235: 24
        //          default: 56
        //        }
        //    56: invokestatic    invokestatic   !!! ERROR
        //    59: iconst_1       
        //    60: invokespecial   dev/nuker/pyro/fH.<init>:(Ljava/lang/String;Ljava/lang/String;Ljava/lang/String;Z)V
        //    63: aload_0        
        //    64: getstatic       dev/nuker/pyro/fc.0:I
        //    67: ifeq            75
        //    70: ldc             -1349276295
        //    72: goto            77
        //    75: ldc             214880774
        //    77: ldc             -1221479416
        //    79: ixor           
        //    80: lookupswitch {
        //          -1854624497: 75
        //          413276529: 532
        //          default: 108
        //        }
        //   108: aload_0        
        //   109: new             Ldev/nuker/pyro/f0a;
        //   112: dup            
        //   113: ldc             "\u23e6\u149a\u8ae8\ub3da\uc9ae\uedea\ub22a\ue6d3\ud96b\ue9c6"
        //   115: getstatic       dev/nuker/pyro/fc.1:I
        //   118: ifeq            126
        //   121: ldc             -985641462
        //   123: goto            128
        //   126: ldc             566416239
        //   128: ldc             -491770915
        //   130: ixor           
        //   131: lookupswitch {
        //          -963607061: 126
        //          670066135: 530
        //          default: 156
        //        }
        //   156: invokestatic    invokestatic   !!! ERROR
        //   159: ldc             "\u23c0\u149f\u8af4\ub3da\uc9aa\ueda4\ub200\ue6df\ud97b\ue9d1\ua72b\u1e42\ue1fc\uc5a2\u8156\u896b"
        //   161: invokestatic    invokestatic   !!! ERROR
        //   164: ldc             "\u23c3\u1497\u8aff\ub399\uc9a0\ueda4\ub227\ue6d9\ud966\ue9d4\ua72d\u1e5e\ue1ff\uc5a6\u8141\u8976\u57ab\u771d\ubd7d\uc07e\u2b1f\uc22b\u6a0e\u2d46\ud7f0\u3581\u7d24\u89aa\u8051\u8ce1\u84aa\ufb37\u7084\u9a12\u1bee\uf176\u497f\u8878\uca88\uff4b\ub6df\u41f0\ub9f6\ub308\u4c15\u8ae2\u7c7d\uce27\u7d41\ueaae"
        //   166: getstatic       dev/nuker/pyro/fc.c:I
        //   169: ifge            177
        //   172: ldc             -1821877122
        //   174: goto            179
        //   177: ldc             -753836304
        //   179: ldc             1892768487
        //   181: ixor           
        //   182: lookupswitch {
        //          -1547697129: 208
        //          -474413415: 177
        //          default: 542
        //        }
        //   208: invokestatic    invokestatic   !!! ERROR
        //   211: iconst_1       
        //   212: getstatic       dev/nuker/pyro/fc.1:I
        //   215: ifeq            223
        //   218: ldc             2099379935
        //   220: goto            225
        //   223: ldc             -1062216123
        //   225: ldc             620141992
        //   227: ixor           
        //   228: lookupswitch {
        //          -529968061: 223
        //          1507287927: 540
        //          default: 256
        //        }
        //   256: invokespecial   dev/nuker/pyro/f0a.<init>:(Ljava/lang/String;Ljava/lang/String;Ljava/lang/String;Z)V
        //   259: checkcast       Ldev/nuker/pyro/f0n;
        //   262: invokevirtual   dev/nuker/pyro/f66.c:(Ldev/nuker/pyro/f0n;)Ldev/nuker/pyro/f0n;
        //   265: checkcast       Ldev/nuker/pyro/f0a;
        //   268: putfield        dev/nuker/pyro/f66.c:Ldev/nuker/pyro/f0a;
        //   271: aload_0        
        //   272: getstatic       dev/nuker/pyro/fc.0:I
        //   275: ifeq            283
        //   278: ldc             774593003
        //   280: goto            285
        //   283: ldc             106930397
        //   285: ldc             -1988171576
        //   287: ixor           
        //   288: lookupswitch {
        //          -1487556317: 538
        //          -20574508: 283
        //          default: 316
        //        }
        //   316: aload_0        
        //   317: new             Ldev/nuker/pyro/f0a;
        //   320: dup            
        //   321: ldc             "\u23e1\u149f\u8af4\ub3ca\uc9a4\ueddb\ub233\ue6df\ud966\ue9d6\ua72b\u1e5b"
        //   323: invokestatic    invokestatic   !!! ERROR
        //   326: ldc             "\u23c0\u149f\u8af4\ub3da\uc9aa\ueda4\ub213\ue6df\ud966\ue9d6\ua72b\u1e5b\ue1b2\uc584\u8159\u8970\u57b7\u7716"
        //   328: invokestatic    invokestatic   !!! ERROR
        //   331: ldc             "\u23c3\u1497\u8aff\ub399\uc9a0\ueda4\ub227\ue6d9\ud966\ue9d4\ua72d\u1e5e\ue1ff\uc5a6\u8141\u8976\u57ab\u771d\ubd7d\uc07e\u2b1f\uc22b\u6a0e\u2d46\ud7f0\u3581\u7d24\u89aa\u8051\u8ce1\u84aa\ufb37\u7084\u9a51\u1bdf\uf122\u493c\u8875\uca93\uff51\ub6ce\u41fc\ub9ec"
        //   333: getstatic       dev/nuker/pyro/fc.c:I
        //   336: ifge            344
        //   339: ldc             -285775097
        //   341: goto            346
        //   344: ldc             1401608640
        //   346: ldc             1476293385
        //   348: ixor           
        //   349: lookupswitch {
        //          -1190586354: 344
        //          74754761: 376
        //          default: 526
        //        }
        //   376: invokestatic    invokestatic   !!! ERROR
        //   379: iconst_1       
        //   380: getstatic       dev/nuker/pyro/fc.1:I
        //   383: ifeq            391
        //   386: ldc             1445351393
        //   388: goto            393
        //   391: ldc             -1483194835
        //   393: ldc             63428375
        //   395: ixor           
        //   396: lookupswitch {
        //          -1537218246: 424
        //          1440848118: 391
        //          default: 536
        //        }
        //   424: invokespecial   dev/nuker/pyro/f0a.<init>:(Ljava/lang/String;Ljava/lang/String;Ljava/lang/String;Z)V
        //   427: checkcast       Ldev/nuker/pyro/f0n;
        //   430: getstatic       dev/nuker/pyro/fc.c:I
        //   433: ifge            441
        //   436: ldc             20707367
        //   438: goto            443
        //   441: ldc             833707711
        //   443: ldc             -1090548679
        //   445: ixor           
        //   446: lookupswitch {
        //          -1890659706: 472
        //          -1077644258: 441
        //          default: 534
        //        }
        //   472: invokevirtual   dev/nuker/pyro/f66.c:(Ldev/nuker/pyro/f0n;)Ldev/nuker/pyro/f0n;
        //   475: checkcast       Ldev/nuker/pyro/f0a;
        //   478: getstatic       dev/nuker/pyro/fc.0:I
        //   481: ifeq            489
        //   484: ldc             -707683797
        //   486: goto            491
        //   489: ldc             1811162308
        //   491: ldc             -675568186
        //   493: ixor           
        //   494: lookupswitch {
        //          -1135640318: 520
        //          40517613: 489
        //          default: 528
        //        }
        //   520: putfield        dev/nuker/pyro/f66.0:Ldev/nuker/pyro/f0a;
        //   523: return         
        //   524: aconst_null    
        //   525: athrow         
        //   526: aconst_null    
        //   527: athrow         
        //   528: aconst_null    
        //   529: athrow         
        //   530: aconst_null    
        //   531: athrow         
        //   532: aconst_null    
        //   533: athrow         
        //   534: aconst_null    
        //   535: athrow         
        //   536: aconst_null    
        //   537: athrow         
        //   538: aconst_null    
        //   539: athrow         
        //   540: aconst_null    
        //   541: athrow         
        //   542: aconst_null    
        //   543: athrow         
        //    StackMapTable: 00 28 FF 00 18 00 01 06 00 04 06 07 00 5C 07 00 5C 07 00 5C FF 00 01 00 01 06 00 05 06 07 00 5C 07 00 5C 07 00 5C 01 FF 00 1D 00 01 06 00 04 06 07 00 5C 07 00 5C 07 00 5C FF 00 12 00 01 07 00 03 00 01 07 00 03 FF 00 01 00 01 07 00 03 00 02 07 00 03 01 5E 07 00 03 FF 00 11 00 01 07 00 03 00 05 07 00 03 07 00 03 08 00 6D 08 00 6D 07 00 5C FF 00 01 00 01 07 00 03 00 06 07 00 03 07 00 03 08 00 6D 08 00 6D 07 00 5C 01 FF 00 1B 00 01 07 00 03 00 05 07 00 03 07 00 03 08 00 6D 08 00 6D 07 00 5C FF 00 14 00 01 07 00 03 00 07 07 00 03 07 00 03 08 00 6D 08 00 6D 07 00 5C 07 00 5C 07 00 5C FF 00 01 00 01 07 00 03 00 08 07 00 03 07 00 03 08 00 6D 08 00 6D 07 00 5C 07 00 5C 07 00 5C 01 FF 00 1C 00 01 07 00 03 00 07 07 00 03 07 00 03 08 00 6D 08 00 6D 07 00 5C 07 00 5C 07 00 5C FF 00 0E 00 01 07 00 03 00 08 07 00 03 07 00 03 08 00 6D 08 00 6D 07 00 5C 07 00 5C 07 00 5C 01 FF 00 01 00 01 07 00 03 00 09 07 00 03 07 00 03 08 00 6D 08 00 6D 07 00 5C 07 00 5C 07 00 5C 01 01 FF 00 1E 00 01 07 00 03 00 08 07 00 03 07 00 03 08 00 6D 08 00 6D 07 00 5C 07 00 5C 07 00 5C 01 5A 07 00 03 FF 00 01 00 01 07 00 03 00 02 07 00 03 01 5E 07 00 03 FF 00 1B 00 01 07 00 03 00 07 07 00 03 07 00 03 08 01 3D 08 01 3D 07 00 5C 07 00 5C 07 00 5C FF 00 01 00 01 07 00 03 00 08 07 00 03 07 00 03 08 01 3D 08 01 3D 07 00 5C 07 00 5C 07 00 5C 01 FF 00 1D 00 01 07 00 03 00 07 07 00 03 07 00 03 08 01 3D 08 01 3D 07 00 5C 07 00 5C 07 00 5C FF 00 0E 00 01 07 00 03 00 08 07 00 03 07 00 03 08 01 3D 08 01 3D 07 00 5C 07 00 5C 07 00 5C 01 FF 00 01 00 01 07 00 03 00 09 07 00 03 07 00 03 08 01 3D 08 01 3D 07 00 5C 07 00 5C 07 00 5C 01 01 FF 00 1E 00 01 07 00 03 00 08 07 00 03 07 00 03 08 01 3D 08 01 3D 07 00 5C 07 00 5C 07 00 5C 01 FF 00 10 00 01 07 00 03 00 03 07 00 03 07 00 03 07 00 3E FF 00 01 00 01 07 00 03 00 04 07 00 03 07 00 03 07 00 3E 01 FF 00 1C 00 01 07 00 03 00 03 07 00 03 07 00 03 07 00 3E FF 00 10 00 01 07 00 03 00 02 07 00 03 07 00 2A FF 00 01 00 01 07 00 03 00 03 07 00 03 07 00 2A 01 FF 00 1C 00 01 07 00 03 00 02 07 00 03 07 00 2A FF 00 03 00 01 06 00 04 06 07 00 5C 07 00 5C 07 00 5C FF 00 01 00 01 07 00 03 00 07 07 00 03 07 00 03 08 01 3D 08 01 3D 07 00 5C 07 00 5C 07 00 5C FF 00 01 00 01 07 00 03 00 02 07 00 03 07 00 2A FF 00 01 00 01 07 00 03 00 05 07 00 03 07 00 03 08 00 6D 08 00 6D 07 00 5C 41 07 00 03 FF 00 01 00 01 07 00 03 00 03 07 00 03 07 00 03 07 00 3E FF 00 01 00 01 07 00 03 00 08 07 00 03 07 00 03 08 01 3D 08 01 3D 07 00 5C 07 00 5C 07 00 5C 01 41 07 00 03 FF 00 01 00 01 07 00 03 00 08 07 00 03 07 00 03 08 00 6D 08 00 6D 07 00 5C 07 00 5C 07 00 5C 01 FF 00 01 00 01 07 00 03 00 07 07 00 03 07 00 03 08 00 6D 08 00 6D 07 00 5C 07 00 5C 07 00 5C
        // 
        // The error that occurred was:
        // 
        // java.lang.IllegalStateException: Invalid BootstrapMethods attribute entry: 21 additional arguments required for method a.a, but only 0 specified.
        //     at com.strobel.assembler.ir.Error.invalidBootstrapMethodEntry(Error.java:244)
        //     at com.strobel.assembler.ir.MetadataReader.readAttributeCore(MetadataReader.java:280)
        //     at com.strobel.assembler.metadata.ClassFileReader.readAttributeCore(ClassFileReader.java:261)
        //     at com.strobel.assembler.ir.MetadataReader.inflateAttributes(MetadataReader.java:439)
        //     at com.strobel.assembler.metadata.ClassFileReader.visitAttributes(ClassFileReader.java:1134)
        //     at com.strobel.assembler.metadata.ClassFileReader.readClass(ClassFileReader.java:439)
        //     at com.strobel.assembler.metadata.ClassFileReader.readClass(ClassFileReader.java:377)
        //     at com.strobel.assembler.metadata.MetadataSystem.resolveType(MetadataSystem.java:129)
        //     at com.strobel.decompiler.NoRetryMetadataSystem.resolveType(DecompilerDriver.java:476)
        //     at com.strobel.assembler.metadata.MetadataSystem.resolveCore(MetadataSystem.java:81)
        //     at com.strobel.assembler.metadata.MetadataResolver.resolve(MetadataResolver.java:104)
        //     at com.strobel.assembler.metadata.CoreMetadataFactory$UnresolvedType.resolve(CoreMetadataFactory.java:616)
        //     at com.strobel.assembler.metadata.MetadataResolver.resolve(MetadataResolver.java:128)
        //     at com.strobel.assembler.metadata.CoreMetadataFactory$UnresolvedType.resolve(CoreMetadataFactory.java:626)
        //     at com.strobel.assembler.metadata.MethodReference.resolve(MethodReference.java:177)
        //     at com.strobel.decompiler.ast.TypeAnalysis.inferCall(TypeAnalysis.java:2438)
        //     at com.strobel.decompiler.ast.TypeAnalysis.doInferTypeForExpression(TypeAnalysis.java:1029)
        //     at com.strobel.decompiler.ast.TypeAnalysis.inferTypeForExpression(TypeAnalysis.java:803)
        //     at com.strobel.decompiler.ast.TypeAnalysis.inferTypeForExpression(TypeAnalysis.java:770)
        //     at com.strobel.decompiler.ast.TypeAnalysis.doInferTypeForExpression(TypeAnalysis.java:881)
        //     at com.strobel.decompiler.ast.TypeAnalysis.inferTypeForExpression(TypeAnalysis.java:803)
        //     at com.strobel.decompiler.ast.TypeAnalysis.runInference(TypeAnalysis.java:672)
        //     at com.strobel.decompiler.ast.TypeAnalysis.runInference(TypeAnalysis.java:655)
        //     at com.strobel.decompiler.ast.TypeAnalysis.runInference(TypeAnalysis.java:365)
        //     at com.strobel.decompiler.ast.TypeAnalysis.run(TypeAnalysis.java:96)
        //     at com.strobel.decompiler.ast.AstOptimizer.optimize(AstOptimizer.java:109)
        //     at com.strobel.decompiler.ast.AstOptimizer.optimize(AstOptimizer.java:42)
        //     at com.strobel.decompiler.languages.java.ast.AstMethodBodyBuilder.createMethodBody(AstMethodBodyBuilder.java:214)
        //     at com.strobel.decompiler.languages.java.ast.AstMethodBodyBuilder.createMethodBody(AstMethodBodyBuilder.java:99)
        //     at com.strobel.decompiler.languages.java.ast.AstBuilder.createMethodBody(AstBuilder.java:782)
        //     at com.strobel.decompiler.languages.java.ast.AstBuilder.createConstructor(AstBuilder.java:713)
        //     at com.strobel.decompiler.languages.java.ast.AstBuilder.addTypeMembers(AstBuilder.java:549)
        //     at com.strobel.decompiler.languages.java.ast.AstBuilder.createTypeCore(AstBuilder.java:519)
        //     at com.strobel.decompiler.languages.java.ast.AstBuilder.createTypeNoCache(AstBuilder.java:161)
        //     at com.strobel.decompiler.languages.java.ast.AstBuilder.createType(AstBuilder.java:150)
        //     at com.strobel.decompiler.languages.java.ast.AstBuilder.addType(AstBuilder.java:125)
        //     at com.strobel.decompiler.languages.java.JavaLanguage.buildAst(JavaLanguage.java:71)
        //     at com.strobel.decompiler.languages.java.JavaLanguage.decompileType(JavaLanguage.java:59)
        //     at com.strobel.decompiler.DecompilerDriver.decompileType(DecompilerDriver.java:330)
        //     at com.strobel.decompiler.DecompilerDriver.decompileJar(DecompilerDriver.java:251)
        //     at com.strobel.decompiler.DecompilerDriver.main(DecompilerDriver.java:126)
        // 
        throw new IllegalStateException("An error occurred while decompiling this method.");
    }
    
    static {
        throw t;
    }
}
