// 
// Decompiled by Procyon v0.5.36
// 

package dev.nuker.pyro;

import org.jetbrains.annotations.Nullable;
import kotlin.jvm.JvmField;
import net.minecraft.client.multiplayer.ServerData;
import org.jetbrains.annotations.NotNull;

public class f6g extends fH
{
    @NotNull
    public f0d c;
    @NotNull
    public f0a c;
    @JvmField
    @Nullable
    public static ServerData c;
    public static f6f c;
    
    public void c(@NotNull final f0d f0d) {
        fbS.gv(this, 1747347616, f0d);
    }
    
    public f6g() {
        // 
        // This method could not be decompiled.
        // 
        // Original Bytecode:
        // 
        //     1: ldc             "\u2232\u1486\u8b3e\ub3d6\uc9af\uec27\ub221\ue704\ud967\ue9ed\ua6fb\u1e49\ue020\uc5b3"
        //     3: getstatic       dev/nuker/pyro/fc.0:I
        //     6: ifeq            14
        //     9: ldc             -1961865349
        //    11: goto            16
        //    14: ldc             -770387725
        //    16: ldc             1018265724
        //    18: ixor           
        //    19: lookupswitch {
        //          -1910411254: 14
        //          -1214132473: 404
        //          default: 44
        //        }
        //    44: invokestatic    invokestatic   !!! ERROR
        //    47: ldc             "\u2212\u1486\u8b3e\ub3d6\uc9a2\uec30\ub227\ue708\ud966\ue9ed\ua6f0\u1e4f\ue037"
        //    49: getstatic       dev/nuker/pyro/fc.1:I
        //    52: ifeq            60
        //    55: ldc             247062612
        //    57: goto            62
        //    60: ldc             -2107909347
        //    62: ldc             -1077355280
        //    64: ixor           
        //    65: lookupswitch {
        //          -1317978972: 60
        //          1033045997: 92
        //          default: 406
        //        }
        //    92: invokestatic    invokestatic   !!! ERROR
        //    95: ldc             "\u2212\u1486\u8b3e\ub3d6\uc99d\uec34\ub230\ue70e\ud96b\ue9e2\ua6f9\u1e40\ue03a\uc5e7\u8176\u88ab\u57a7\u76cd\ubd33\uc051\u2ac4\uc238\u6bde\u2d45\ud7c1\u3442\u7d24\u8829\u8010\u8c84\u8560\ufb37\u7107\u9a00\u1bd3\uf0a6\u493c\u89b1\uca8e\uff71\ub705\u41b3\ub82a\ub347\u4c33\u8b66\u7c6e\ucfe7\u7d5a\uead1\ue70f\u16d1\uef82\u378d\u46f6\ue021\u0a19\u8713\u19d6\u0f05\u76cb\u7289\uc663"
        //    97: getstatic       dev/nuker/pyro/fc.c:I
        //   100: ifge            108
        //   103: ldc             -215131273
        //   105: goto            110
        //   108: ldc             -500981521
        //   110: ldc             784013961
        //   112: ixor           
        //   113: lookupswitch {
        //          -577355266: 396
        //          1734361231: 108
        //          default: 140
        //        }
        //   140: invokestatic    invokestatic   !!! ERROR
        //   143: getstatic       dev/nuker/pyro/fc.0:I
        //   146: ifeq            154
        //   149: ldc             1641331135
        //   151: goto            156
        //   154: ldc             -1154090778
        //   156: ldc             1870059384
        //   158: ixor           
        //   159: lookupswitch {
        //          -733794402: 184
        //          245526215: 154
        //          default: 400
        //        }
        //   184: invokespecial   dev/nuker/pyro/fH.<init>:(Ljava/lang/String;Ljava/lang/String;Ljava/lang/String;)V
        //   187: aload_0        
        //   188: aload_0        
        //   189: new             Ldev/nuker/pyro/f0d;
        //   192: dup            
        //   193: ldc             "\u2237\u1496\u8b26\ub3d8\uc989\uec2c"
        //   195: invokestatic    invokestatic   !!! ERROR
        //   198: ldc             "\u2217\u1496\u8b26\ub3d8\uc989"
        //   200: invokestatic    invokestatic   !!! ERROR
        //   203: ldc             "\u2217\u1496\u8b26\ub3d8\uc989\uec75\ub22d\ue709\ud928\ue9f0\ua6f0\u1e4f\ue02c\uc5a9\u8160\u88bd"
        //   205: invokestatic    invokestatic   !!! ERROR
        //   208: ldc2_w          5.0
        //   211: dconst_0       
        //   212: ldc2_w          20.0
        //   215: dconst_0       
        //   216: bipush          64
        //   218: aconst_null    
        //   219: invokespecial   dev/nuker/pyro/f0d.<init>:(Ljava/lang/String;Ljava/lang/String;Ljava/lang/String;DDDDILkotlin/jvm/internal/DefaultConstructorMarker;)V
        //   222: checkcast       Ldev/nuker/pyro/f0n;
        //   225: invokevirtual   dev/nuker/pyro/f6g.c:(Ldev/nuker/pyro/f0n;)Ldev/nuker/pyro/f0n;
        //   228: checkcast       Ldev/nuker/pyro/f0d;
        //   231: putfield        dev/nuker/pyro/f6g.c:Ldev/nuker/pyro/f0d;
        //   234: aload_0        
        //   235: aload_0        
        //   236: new             Ldev/nuker/pyro/f0a;
        //   239: dup            
        //   240: ldc             "\u2220\u149b\u8b25\ub3ce"
        //   242: invokestatic    invokestatic   !!! ERROR
        //   245: ldc             "\u2200\u149b\u8b25\ub3ce\uc9d0\uec17\ub231\ue713\ud97c\ue9ec\ua6fb\u1e5f"
        //   247: getstatic       dev/nuker/pyro/fc.0:I
        //   250: ifeq            258
        //   253: ldc             -1467669111
        //   255: goto            260
        //   258: ldc             -33899088
        //   260: ldc             -1849525350
        //   262: ixor           
        //   263: lookupswitch {
        //          960978451: 258
        //          1815660074: 288
        //          default: 408
        //        }
        //   288: invokestatic    invokestatic   !!! ERROR
        //   291: ldc             "\u2200\u149b\u8b25\ub3ce\uc9d0\uec27\ub221\ue704\ud967\ue9ed\ua6fb\u1e49\ue020\uc5b3\u8124\u88ac\u57b1\u76d6\ubd29\uc050\u2acf\uc228\u6b8a\u2d59\ud78f\u3416\u7d3f\u8861\u8014\u8c84\u8577\ufb3b\u7106\u9a15\u1bd9\uf0ba\u4972\u89a3\uca85\uff60\ub74b\u41e0\ub830\ub35a\u4c23\u8b23\u7c67"
        //   293: invokestatic    invokestatic   !!! ERROR
        //   296: iconst_1       
        //   297: invokespecial   dev/nuker/pyro/f0a.<init>:(Ljava/lang/String;Ljava/lang/String;Ljava/lang/String;Z)V
        //   300: checkcast       Ldev/nuker/pyro/f0n;
        //   303: getstatic       dev/nuker/pyro/fc.0:I
        //   306: ifeq            314
        //   309: ldc             -326337051
        //   311: goto            316
        //   314: ldc             611390030
        //   316: ldc             -1253627378
        //   318: ixor           
        //   319: lookupswitch {
        //          1354033451: 314
        //          1506498539: 398
        //          default: 344
        //        }
        //   344: invokevirtual   dev/nuker/pyro/f6g.c:(Ldev/nuker/pyro/f0n;)Ldev/nuker/pyro/f0n;
        //   347: checkcast       Ldev/nuker/pyro/f0a;
        //   350: getstatic       dev/nuker/pyro/fc.1:I
        //   353: ifeq            361
        //   356: ldc             1569671364
        //   358: goto            363
        //   361: ldc             -344274790
        //   363: ldc             -1760587724
        //   365: ixor           
        //   366: lookupswitch {
        //          -897525520: 361
        //          2088065198: 392
        //          default: 402
        //        }
        //   392: putfield        dev/nuker/pyro/f6g.c:Ldev/nuker/pyro/f0a;
        //   395: return         
        //   396: aconst_null    
        //   397: athrow         
        //   398: aconst_null    
        //   399: athrow         
        //   400: aconst_null    
        //   401: athrow         
        //   402: aconst_null    
        //   403: athrow         
        //   404: aconst_null    
        //   405: athrow         
        //   406: aconst_null    
        //   407: athrow         
        //   408: aconst_null    
        //   409: athrow         
        //    StackMapTable: 00 1C FF 00 0E 00 01 06 00 02 06 07 00 6A FF 00 01 00 01 06 00 03 06 07 00 6A 01 FF 00 1B 00 01 06 00 02 06 07 00 6A FF 00 0F 00 01 06 00 03 06 07 00 6A 07 00 6A FF 00 01 00 01 06 00 04 06 07 00 6A 07 00 6A 01 FF 00 1D 00 01 06 00 03 06 07 00 6A 07 00 6A FF 00 0F 00 01 06 00 04 06 07 00 6A 07 00 6A 07 00 6A FF 00 01 00 01 06 00 05 06 07 00 6A 07 00 6A 07 00 6A 01 FF 00 1D 00 01 06 00 04 06 07 00 6A 07 00 6A 07 00 6A FF 00 0D 00 01 06 00 04 06 07 00 6A 07 00 6A 07 00 6A FF 00 01 00 01 06 00 05 06 07 00 6A 07 00 6A 07 00 6A 01 FF 00 1B 00 01 06 00 04 06 07 00 6A 07 00 6A 07 00 6A FF 00 49 00 01 07 00 03 00 06 07 00 03 07 00 03 08 00 EC 08 00 EC 07 00 6A 07 00 6A FF 00 01 00 01 07 00 03 00 07 07 00 03 07 00 03 08 00 EC 08 00 EC 07 00 6A 07 00 6A 01 FF 00 1B 00 01 07 00 03 00 06 07 00 03 07 00 03 08 00 EC 08 00 EC 07 00 6A 07 00 6A FF 00 19 00 01 07 00 03 00 03 07 00 03 07 00 03 07 00 4D FF 00 01 00 01 07 00 03 00 04 07 00 03 07 00 03 07 00 4D 01 FF 00 1B 00 01 07 00 03 00 03 07 00 03 07 00 03 07 00 4D FF 00 10 00 01 07 00 03 00 02 07 00 03 07 00 54 FF 00 01 00 01 07 00 03 00 03 07 00 03 07 00 54 01 FF 00 1C 00 01 07 00 03 00 02 07 00 03 07 00 54 FF 00 03 00 01 06 00 04 06 07 00 6A 07 00 6A 07 00 6A FF 00 01 00 01 07 00 03 00 03 07 00 03 07 00 03 07 00 4D FF 00 01 00 01 06 00 04 06 07 00 6A 07 00 6A 07 00 6A FF 00 01 00 01 07 00 03 00 02 07 00 03 07 00 54 FF 00 01 00 01 06 00 02 06 07 00 6A FF 00 01 00 01 06 00 03 06 07 00 6A 07 00 6A FF 00 01 00 01 07 00 03 00 06 07 00 03 07 00 03 08 00 EC 08 00 EC 07 00 6A 07 00 6A
        // 
        // The error that occurred was:
        // 
        // java.lang.IllegalStateException: Invalid BootstrapMethods attribute entry: 21 additional arguments required for method a.a, but only 0 specified.
        //     at com.strobel.assembler.ir.Error.invalidBootstrapMethodEntry(Error.java:244)
        //     at com.strobel.assembler.ir.MetadataReader.readAttributeCore(MetadataReader.java:280)
        //     at com.strobel.assembler.metadata.ClassFileReader.readAttributeCore(ClassFileReader.java:261)
        //     at com.strobel.assembler.ir.MetadataReader.inflateAttributes(MetadataReader.java:439)
        //     at com.strobel.assembler.metadata.ClassFileReader.visitAttributes(ClassFileReader.java:1134)
        //     at com.strobel.assembler.metadata.ClassFileReader.readClass(ClassFileReader.java:439)
        //     at com.strobel.assembler.metadata.ClassFileReader.readClass(ClassFileReader.java:377)
        //     at com.strobel.assembler.metadata.MetadataSystem.resolveType(MetadataSystem.java:129)
        //     at com.strobel.decompiler.NoRetryMetadataSystem.resolveType(DecompilerDriver.java:476)
        //     at com.strobel.assembler.metadata.MetadataSystem.resolveCore(MetadataSystem.java:81)
        //     at com.strobel.assembler.metadata.MetadataResolver.resolve(MetadataResolver.java:104)
        //     at com.strobel.assembler.metadata.CoreMetadataFactory$UnresolvedType.resolve(CoreMetadataFactory.java:616)
        //     at com.strobel.assembler.metadata.MetadataResolver.resolve(MetadataResolver.java:128)
        //     at com.strobel.assembler.metadata.CoreMetadataFactory$UnresolvedType.resolve(CoreMetadataFactory.java:626)
        //     at com.strobel.assembler.metadata.MethodReference.resolve(MethodReference.java:177)
        //     at com.strobel.decompiler.ast.TypeAnalysis.inferCall(TypeAnalysis.java:2438)
        //     at com.strobel.decompiler.ast.TypeAnalysis.doInferTypeForExpression(TypeAnalysis.java:1029)
        //     at com.strobel.decompiler.ast.TypeAnalysis.inferTypeForExpression(TypeAnalysis.java:803)
        //     at com.strobel.decompiler.ast.TypeAnalysis.inferTypeForExpression(TypeAnalysis.java:770)
        //     at com.strobel.decompiler.ast.TypeAnalysis.doInferTypeForExpression(TypeAnalysis.java:881)
        //     at com.strobel.decompiler.ast.TypeAnalysis.inferTypeForExpression(TypeAnalysis.java:803)
        //     at com.strobel.decompiler.ast.TypeAnalysis.runInference(TypeAnalysis.java:672)
        //     at com.strobel.decompiler.ast.TypeAnalysis.runInference(TypeAnalysis.java:655)
        //     at com.strobel.decompiler.ast.TypeAnalysis.runInference(TypeAnalysis.java:365)
        //     at com.strobel.decompiler.ast.TypeAnalysis.run(TypeAnalysis.java:96)
        //     at com.strobel.decompiler.ast.AstOptimizer.optimize(AstOptimizer.java:109)
        //     at com.strobel.decompiler.ast.AstOptimizer.optimize(AstOptimizer.java:42)
        //     at com.strobel.decompiler.languages.java.ast.AstMethodBodyBuilder.createMethodBody(AstMethodBodyBuilder.java:214)
        //     at com.strobel.decompiler.languages.java.ast.AstMethodBodyBuilder.createMethodBody(AstMethodBodyBuilder.java:99)
        //     at com.strobel.decompiler.languages.java.ast.AstBuilder.createMethodBody(AstBuilder.java:782)
        //     at com.strobel.decompiler.languages.java.ast.AstBuilder.createConstructor(AstBuilder.java:713)
        //     at com.strobel.decompiler.languages.java.ast.AstBuilder.addTypeMembers(AstBuilder.java:549)
        //     at com.strobel.decompiler.languages.java.ast.AstBuilder.createTypeCore(AstBuilder.java:519)
        //     at com.strobel.decompiler.languages.java.ast.AstBuilder.createTypeNoCache(AstBuilder.java:161)
        //     at com.strobel.decompiler.languages.java.ast.AstBuilder.createType(AstBuilder.java:150)
        //     at com.strobel.decompiler.languages.java.ast.AstBuilder.addType(AstBuilder.java:125)
        //     at com.strobel.decompiler.languages.java.JavaLanguage.buildAst(JavaLanguage.java:71)
        //     at com.strobel.decompiler.languages.java.JavaLanguage.decompileType(JavaLanguage.java:59)
        //     at com.strobel.decompiler.DecompilerDriver.decompileType(DecompilerDriver.java:330)
        //     at com.strobel.decompiler.DecompilerDriver.decompileJar(DecompilerDriver.java:251)
        //     at com.strobel.decompiler.DecompilerDriver.main(DecompilerDriver.java:126)
        // 
        throw new IllegalStateException("An error occurred while decompiling this method.");
    }
    
    public void c(@NotNull final f0a f0a) {
        fbS.6N(this, 517452500, f0a);
    }
    
    @NotNull
    public f0a 0() {
        return fbS.0G(this, 359093295);
    }
    
    @NotNull
    public f0d c() {
        return fbS.gj(this, 1156108263);
    }
    
    static {
        final f6f c = new f6f(null);
        while (true) {
            int n = 0;
            Label_0021: {
                if (fc.0 != 0) {
                    n = -248262015;
                    break Label_0021;
                }
                n = -2067416240;
            }
            switch (n ^ 0x167E5B32) {
                case -1197538885: {
                    continue;
                }
                default: {
                    f6g.c = c;
                }
                case -414348877: {
                    throw null;
                }
            }
            break;
        }
    }
}
