// 
// Decompiled by Procyon v0.5.36
// 

package dev.nuker.pyro;

import com.mojang.realmsclient.gui.ChatFormatting;

public class f6l extends fH
{
    public f0a c;
    public f0f<f6k> c;
    public f0f<f6k> 0;
    public f0f<f6k> 1;
    public static boolean c;
    
    public ChatFormatting c(final f0f p0) {
        // 
        // This method could not be decompiled.
        // 
        // Original Bytecode:
        // 
        //     3: nop            
        //     4: nop            
        //     5: nop            
        //     6: athrow         
        //     7: athrow         
        //     8: aconst_null    
        //     9: getstatic       dev/nuker/pyro/fc.c:I
        //    12: iflt            553
        //    15: pop            
        //    16: aconst_null    
        //    17: goto            545
        //    20: nop            
        //    21: nop            
        //    22: nop            
        //    23: athrow         
        //    24: getstatic       dev/nuker/pyro/f6j.c:[I
        //    27: aload_1        
        //    28: getstatic       dev/nuker/pyro/fc.0:I
        //    31: ifeq            39
        //    34: ldc             -680342030
        //    36: goto            41
        //    39: ldc             -1494751216
        //    41: ldc             55489764
        //    43: ixor           
        //    44: lookupswitch {
        //          -1515627276: 72
        //          -734234346: 39
        //          default: 530
        //        }
        //    72: goto            76
        //    75: athrow         
        //    76: invokevirtual   dev/nuker/pyro/f0f.3:()Ljava/lang/Object;
        //    79: goto            83
        //    82: athrow         
        //    83: checkcast       Ldev/nuker/pyro/f6k;
        //    86: goto            90
        //    89: athrow         
        //    90: invokevirtual   dev/nuker/pyro/f6k.ordinal:()I
        //    93: goto            97
        //    96: athrow         
        //    97: iaload         
        //    98: tableswitch {
        //                2: 160
        //                3: 208
        //                4: 256
        //                5: 304
        //                6: 308
        //                7: 312
        //                8: 316
        //                9: 364
        //               10: 368
        //               11: 416
        //               12: 420
        //               13: 468
        //          default: 516
        //        }
        //   160: getstatic       dev/nuker/pyro/fc.1:I
        //   163: ifeq            171
        //   166: ldc             331657837
        //   168: goto            173
        //   171: ldc             1240400826
        //   173: ldc             13372377
        //   175: ixor           
        //   176: lookupswitch {
        //          319338932: 526
        //          1260151032: 171
        //          default: 204
        //        }
        //   204: getstatic       com/mojang/realmsclient/gui/ChatFormatting.WHITE:Lcom/mojang/realmsclient/gui/ChatFormatting;
        //   207: areturn        
        //   208: getstatic       dev/nuker/pyro/fc.0:I
        //   211: ifeq            219
        //   214: ldc             -1971352900
        //   216: goto            221
        //   219: ldc             -1174058049
        //   221: ldc             -1101274587
        //   223: ixor           
        //   224: lookupswitch {
        //          874801305: 522
        //          944314547: 219
        //          default: 252
        //        }
        //   252: getstatic       com/mojang/realmsclient/gui/ChatFormatting.GRAY:Lcom/mojang/realmsclient/gui/ChatFormatting;
        //   255: areturn        
        //   256: getstatic       dev/nuker/pyro/fc.c:I
        //   259: ifge            267
        //   262: ldc             1121469863
        //   264: goto            269
        //   267: ldc             -474727145
        //   269: ldc             1725307226
        //   271: ixor           
        //   272: lookupswitch {
        //          -2057165747: 300
        //          604921085: 267
        //          default: 532
        //        }
        //   300: getstatic       com/mojang/realmsclient/gui/ChatFormatting.DARK_GRAY:Lcom/mojang/realmsclient/gui/ChatFormatting;
        //   303: areturn        
        //   304: getstatic       com/mojang/realmsclient/gui/ChatFormatting.RED:Lcom/mojang/realmsclient/gui/ChatFormatting;
        //   307: areturn        
        //   308: getstatic       com/mojang/realmsclient/gui/ChatFormatting.DARK_RED:Lcom/mojang/realmsclient/gui/ChatFormatting;
        //   311: areturn        
        //   312: getstatic       com/mojang/realmsclient/gui/ChatFormatting.GREEN:Lcom/mojang/realmsclient/gui/ChatFormatting;
        //   315: areturn        
        //   316: getstatic       dev/nuker/pyro/fc.1:I
        //   319: ifeq            327
        //   322: ldc             -633740041
        //   324: goto            329
        //   327: ldc             180227079
        //   329: ldc             2088281617
        //   331: ixor           
        //   332: lookupswitch {
        //          -1505672474: 520
        //          713286179: 327
        //          default: 360
        //        }
        //   360: getstatic       com/mojang/realmsclient/gui/ChatFormatting.DARK_GREEN:Lcom/mojang/realmsclient/gui/ChatFormatting;
        //   363: areturn        
        //   364: getstatic       com/mojang/realmsclient/gui/ChatFormatting.BLUE:Lcom/mojang/realmsclient/gui/ChatFormatting;
        //   367: areturn        
        //   368: getstatic       dev/nuker/pyro/fc.c:I
        //   371: ifge            379
        //   374: ldc             -128986867
        //   376: goto            381
        //   379: ldc             1009876915
        //   381: ldc             -1164985051
        //   383: ixor           
        //   384: lookupswitch {
        //          -2034318698: 412
        //          1119906856: 379
        //          default: 534
        //        }
        //   412: getstatic       com/mojang/realmsclient/gui/ChatFormatting.DARK_BLUE:Lcom/mojang/realmsclient/gui/ChatFormatting;
        //   415: areturn        
        //   416: getstatic       com/mojang/realmsclient/gui/ChatFormatting.AQUA:Lcom/mojang/realmsclient/gui/ChatFormatting;
        //   419: areturn        
        //   420: getstatic       dev/nuker/pyro/fc.1:I
        //   423: ifeq            431
        //   426: ldc             991305779
        //   428: goto            433
        //   431: ldc             44004702
        //   433: ldc             481833762
        //   435: ixor           
        //   436: lookupswitch {
        //          -835453019: 431
        //          665719569: 528
        //          default: 464
        //        }
        //   464: getstatic       com/mojang/realmsclient/gui/ChatFormatting.YELLOW:Lcom/mojang/realmsclient/gui/ChatFormatting;
        //   467: areturn        
        //   468: getstatic       dev/nuker/pyro/fc.c:I
        //   471: ifge            479
        //   474: ldc             1891614901
        //   476: goto            481
        //   479: ldc             1161080176
        //   481: ldc             -1600596522
        //   483: ixor           
        //   484: lookupswitch {
        //          -1154194220: 479
        //          -802744989: 524
        //          default: 512
        //        }
        //   512: getstatic       com/mojang/realmsclient/gui/ChatFormatting.GOLD:Lcom/mojang/realmsclient/gui/ChatFormatting;
        //   515: areturn        
        //   516: getstatic       com/mojang/realmsclient/gui/ChatFormatting.RESET:Lcom/mojang/realmsclient/gui/ChatFormatting;
        //   519: areturn        
        //   520: aconst_null    
        //   521: athrow         
        //   522: aconst_null    
        //   523: athrow         
        //   524: aconst_null    
        //   525: athrow         
        //   526: aconst_null    
        //   527: athrow         
        //   528: aconst_null    
        //   529: athrow         
        //   530: aconst_null    
        //   531: athrow         
        //   532: aconst_null    
        //   533: athrow         
        //   534: aconst_null    
        //   535: athrow         
        //   536: pop            
        //   537: goto            24
        //   540: pop            
        //   541: aconst_null    
        //   542: goto            536
        //   545: dup            
        //   546: ifnull          536
        //   549: checkcast       Ljava/lang/Throwable;
        //   552: athrow         
        //   553: dup            
        //   554: ifnull          540
        //   557: checkcast       Ljava/lang/Throwable;
        //   560: athrow         
        //   561: nop            
        //   562: athrow         
        //    StackMapTable: 00 3F FF 00 03 00 00 00 01 07 00 1E 43 07 00 1E FD 00 00 07 00 03 07 00 2A FF 00 0B 00 00 00 01 07 00 1E FD 00 03 07 00 03 07 00 2A FF 00 0E 00 02 07 00 03 07 00 2A 00 02 07 00 76 07 00 2A FF 00 01 00 02 07 00 03 07 00 2A 00 03 07 00 76 07 00 2A 01 FF 00 1E 00 02 07 00 03 07 00 2A 00 02 07 00 76 07 00 2A 42 07 00 1E FF 00 00 00 02 07 00 03 07 00 2A 00 02 07 00 76 07 00 2A 45 07 00 1E FF 00 00 00 02 07 00 03 07 00 2A 00 02 07 00 76 07 00 78 45 07 00 1E FF 00 00 00 02 07 00 03 07 00 2A 00 02 07 00 76 07 00 30 45 07 00 1E FF 00 00 00 02 07 00 03 07 00 2A 00 02 07 00 76 01 3E 0A 41 01 1E 03 0A 41 01 1E 03 0A 41 01 1E 03 03 03 03 0A 41 01 1E 03 03 0A 41 01 1E 03 03 0A 41 01 1E 03 0A 41 01 1E 03 03 01 01 01 01 FF 00 01 00 02 07 00 03 07 00 2A 00 02 07 00 76 07 00 2A 01 01 41 07 00 7A 43 05 44 07 00 7A 47 05 FF 00 07 00 00 00 01 07 00 1E
        //    Exceptions:
        //  Try           Handler
        //  Start  End    Start  End    Type                                       
        //  -----  -----  -----  -----  -------------------------------------------
        //  8      20     545    553    Ljava/util/ConcurrentModificationException;
        //  545    553    545    553    Ljava/lang/EnumConstantNotPresentException;
        //  75     82     82     83     Any
        //  76     82     75     76     Any
        //  76     82     75     76     Any
        //  76     82     82     83     Ljava/lang/StringIndexOutOfBoundsException;
        //  75     82     75     76     Any
        //  89     96     96     97     Any
        //  90     96     89     90     Any
        //  89     96     89     90     Ljava/util/ConcurrentModificationException;
        //  90     96     89     90     Ljava/lang/IndexOutOfBoundsException;
        //  89     96     89     90     Ljava/lang/IllegalArgumentException;
        // 
        // The error that occurred was:
        // 
        // java.lang.IndexOutOfBoundsException: Index 141 out of bounds for length 141
        //     at java.base/jdk.internal.util.Preconditions.outOfBounds(Preconditions.java:64)
        //     at java.base/jdk.internal.util.Preconditions.outOfBoundsCheckIndex(Preconditions.java:70)
        //     at java.base/jdk.internal.util.Preconditions.checkIndex(Preconditions.java:248)
        //     at java.base/java.util.Objects.checkIndex(Objects.java:372)
        //     at java.base/java.util.ArrayList.get(ArrayList.java:458)
        //     at com.strobel.decompiler.ast.AstBuilder.convertToAst(AstBuilder.java:3321)
        //     at com.strobel.decompiler.ast.AstBuilder.convertToAst(AstBuilder.java:3569)
        //     at com.strobel.decompiler.ast.AstBuilder.convertToAst(AstBuilder.java:3435)
        //     at com.strobel.decompiler.ast.AstBuilder.build(AstBuilder.java:113)
        //     at com.strobel.decompiler.languages.java.ast.AstMethodBodyBuilder.createMethodBody(AstMethodBodyBuilder.java:211)
        //     at com.strobel.decompiler.languages.java.ast.AstMethodBodyBuilder.createMethodBody(AstMethodBodyBuilder.java:99)
        //     at com.strobel.decompiler.languages.java.ast.AstBuilder.createMethodBody(AstBuilder.java:782)
        //     at com.strobel.decompiler.languages.java.ast.AstBuilder.createMethod(AstBuilder.java:675)
        //     at com.strobel.decompiler.languages.java.ast.AstBuilder.addTypeMembers(AstBuilder.java:552)
        //     at com.strobel.decompiler.languages.java.ast.AstBuilder.createTypeCore(AstBuilder.java:519)
        //     at com.strobel.decompiler.languages.java.ast.AstBuilder.createTypeNoCache(AstBuilder.java:161)
        //     at com.strobel.decompiler.languages.java.ast.AstBuilder.createType(AstBuilder.java:150)
        //     at com.strobel.decompiler.languages.java.ast.AstBuilder.addType(AstBuilder.java:125)
        //     at com.strobel.decompiler.languages.java.JavaLanguage.buildAst(JavaLanguage.java:71)
        //     at com.strobel.decompiler.languages.java.JavaLanguage.decompileType(JavaLanguage.java:59)
        //     at com.strobel.decompiler.DecompilerDriver.decompileType(DecompilerDriver.java:330)
        //     at com.strobel.decompiler.DecompilerDriver.decompileJar(DecompilerDriver.java:251)
        //     at com.strobel.decompiler.DecompilerDriver.main(DecompilerDriver.java:126)
        // 
        throw new IllegalStateException("An error occurred while decompiling this method.");
    }
    
    @f06
    public void c(final f34 p0) {
        // 
        // This method could not be decompiled.
        // 
        // Original Bytecode:
        // 
        //     3: dup            
        //     4: ifnull          2811
        //     7: athrow         
        //     8: aconst_null    
        //     9: getstatic       dev/nuker/pyro/fc.1:I
        //    12: ifgt            2803
        //    15: pop            
        //    16: aconst_null    
        //    17: goto            2795
        //    20: nop            
        //    21: nop            
        //    22: nop            
        //    23: athrow         
        //    24: aload_1        
        //    25: goto            29
        //    28: athrow         
        //    29: invokevirtual   dev/nuker/pyro/f34.c:()Ldev/nuker/pyro/f2T;
        //    32: goto            36
        //    35: athrow         
        //    36: getstatic       dev/nuker/pyro/f2T.c:Ldev/nuker/pyro/f2T;
        //    39: if_acmpeq       43
        //    42: return         
        //    43: aload_1        
        //    44: goto            48
        //    47: athrow         
        //    48: invokevirtual   dev/nuker/pyro/f34.c:()Lnet/minecraft/network/Packet;
        //    51: goto            55
        //    54: athrow         
        //    55: instanceof      Lnet/minecraft/network/play/server/SPacketChat;
        //    58: ifeq            2715
        //    61: aload_1        
        //    62: goto            66
        //    65: athrow         
        //    66: invokevirtual   dev/nuker/pyro/f34.c:()Lnet/minecraft/network/Packet;
        //    69: goto            73
        //    72: athrow         
        //    73: checkcast       Lnet/minecraft/network/play/server/SPacketChat;
        //    76: getstatic       dev/nuker/pyro/fc.c:I
        //    79: ifge            87
        //    82: ldc             -987897450
        //    84: goto            89
        //    87: ldc             2140254577
        //    89: ldc             -772026832
        //    91: ixor           
        //    92: lookupswitch {
        //          -1368752319: 120
        //          350629798: 87
        //          default: 2768
        //        }
        //   120: astore_2       
        //   121: getstatic       dev/nuker/pyro/fc.1:I
        //   124: ifeq            132
        //   127: ldc             1565905949
        //   129: goto            134
        //   132: ldc             1894292697
        //   134: ldc             283961460
        //   136: ixor           
        //   137: lookupswitch {
        //          1241765115: 132
        //          1303985257: 2734
        //          default: 164
        //        }
        //   164: aload_2        
        //   165: getstatic       dev/nuker/pyro/fc.1:I
        //   168: ifeq            176
        //   171: ldc             -1425822927
        //   173: goto            178
        //   176: ldc             -1078649091
        //   178: ldc             1920346600
        //   180: ixor           
        //   181: lookupswitch {
        //          -646610215: 2718
        //          865192298: 176
        //          default: 208
        //        }
        //   208: goto            212
        //   211: athrow         
        //   212: invokevirtual   net/minecraft/network/play/server/SPacketChat.func_148915_c:()Lnet/minecraft/util/text/ITextComponent;
        //   215: goto            219
        //   218: athrow         
        //   219: instanceof      Lnet/minecraft/util/text/TextComponentString;
        //   222: ifeq            329
        //   225: getstatic       dev/nuker/pyro/fc.c:I
        //   228: ifge            236
        //   231: ldc             -1743488036
        //   233: goto            238
        //   236: ldc             -266542674
        //   238: ldc             1828535574
        //   240: ixor           
        //   241: lookupswitch {
        //          -1662919496: 268
        //          -186038582: 236
        //          default: 2762
        //        }
        //   268: aload_2        
        //   269: getstatic       dev/nuker/pyro/fc.0:I
        //   272: ifeq            280
        //   275: ldc             227574883
        //   277: goto            282
        //   280: ldc             -304640845
        //   282: ldc             1905316097
        //   284: ixor           
        //   285: lookupswitch {
        //          975827693: 280
        //          2080396642: 2728
        //          default: 312
        //        }
        //   312: goto            316
        //   315: athrow         
        //   316: invokevirtual   net/minecraft/network/play/server/SPacketChat.func_192590_c:()Lnet/minecraft/util/text/ChatType;
        //   319: goto            323
        //   322: athrow         
        //   323: getstatic       net/minecraft/util/text/ChatType.GAME_INFO:Lnet/minecraft/util/text/ChatType;
        //   326: if_acmpne       330
        //   329: return         
        //   330: aload_0        
        //   331: getfield        dev/nuker/pyro/f6l.c:Ldev/nuker/pyro/f0a;
        //   334: getstatic       dev/nuker/pyro/fc.c:I
        //   337: ifge            345
        //   340: ldc             -1605645003
        //   342: goto            347
        //   345: ldc             -347586386
        //   347: ldc             -87120203
        //   349: ixor           
        //   350: lookupswitch {
        //          -1488102236: 345
        //          1518693248: 2782
        //          default: 376
        //        }
        //   376: goto            380
        //   379: athrow         
        //   380: invokevirtual   dev/nuker/pyro/f0a.3:()Ljava/lang/Object;
        //   383: goto            387
        //   386: athrow         
        //   387: checkcast       Ljava/lang/Boolean;
        //   390: goto            394
        //   393: athrow         
        //   394: invokevirtual   java/lang/Boolean.booleanValue:()Z
        //   397: goto            401
        //   400: athrow         
        //   401: ifeq            410
        //   404: getstatic       dev/nuker/pyro/Pyro.prefix:Lnet/minecraft/util/text/ITextComponent;
        //   407: goto            427
        //   410: new             Lnet/minecraft/util/text/TextComponentString;
        //   413: dup            
        //   414: ldc             ""
        //   416: goto            420
        //   419: athrow         
        //   420: invokespecial   net/minecraft/util/text/TextComponentString.<init>:(Ljava/lang/String;)V
        //   423: goto            427
        //   426: athrow         
        //   427: astore_3       
        //   428: getstatic       dev/nuker/pyro/fc.1:I
        //   431: ifeq            439
        //   434: ldc             1794924288
        //   436: goto            441
        //   439: ldc             -580877724
        //   441: ldc             -208527342
        //   443: ixor           
        //   444: lookupswitch {
        //          -1720811758: 439
        //          787653238: 472
        //          default: 2740
        //        }
        //   472: aload_2        
        //   473: goto            477
        //   476: athrow         
        //   477: invokevirtual   net/minecraft/network/play/server/SPacketChat.func_148915_c:()Lnet/minecraft/util/text/ITextComponent;
        //   480: goto            484
        //   483: athrow         
        //   484: goto            488
        //   487: athrow         
        //   488: invokeinterface net/minecraft/util/text/ITextComponent.func_150254_d:()Ljava/lang/String;
        //   493: goto            497
        //   496: athrow         
        //   497: astore          4
        //   499: aload           4
        //   501: getstatic       dev/nuker/pyro/fc.0:I
        //   504: ifeq            512
        //   507: ldc             614238710
        //   509: goto            514
        //   512: ldc             -1651263027
        //   514: ldc             822662094
        //   516: ixor           
        //   517: lookupswitch {
        //          -927092614: 512
        //          362043960: 2784
        //          default: 544
        //        }
        //   544: goto            548
        //   547: athrow         
        //   548: invokevirtual   java/lang/String.toLowerCase:()Ljava/lang/String;
        //   551: goto            555
        //   554: athrow         
        //   555: ldc             "\u2220\u149c"
        //   557: getstatic       dev/nuker/pyro/fc.0:I
        //   560: ifeq            568
        //   563: ldc             1808009172
        //   565: goto            570
        //   568: ldc             2103197582
        //   570: ldc             -963130839
        //   572: ixor           
        //   573: lookupswitch {
        //          -1387016707: 2732
        //          952691441: 568
        //          default: 600
        //        }
        //   600: goto            604
        //   603: athrow         
        //   604: invokestatic    invokestatic   !!! ERROR
        //   607: goto            611
        //   610: athrow         
        //   611: goto            615
        //   614: athrow         
        //   615: invokevirtual   java/lang/String.contains:(Ljava/lang/CharSequence;)Z
        //   618: goto            622
        //   621: athrow         
        //   622: ifeq            630
        //   625: ldc             990521891
        //   627: goto            632
        //   630: ldc             990521890
        //   632: ldc             667833917
        //   634: ixor           
        //   635: tableswitch {
        //          965277756: 656
        //          965277757: 846
        //          default: 625
        //        }
        //   656: aload           4
        //   658: goto            662
        //   661: athrow         
        //   662: invokevirtual   java/lang/String.toLowerCase:()Ljava/lang/String;
        //   665: goto            669
        //   668: athrow         
        //   669: ldc             "\u2223\u149b\u8b2c\ub1db\ucf9a\uec37\ub236"
        //   671: goto            675
        //   674: athrow         
        //   675: invokestatic    invokestatic   !!! ERROR
        //   678: goto            682
        //   681: athrow         
        //   682: getstatic       dev/nuker/pyro/fc.0:I
        //   685: ifeq            693
        //   688: ldc             -706380692
        //   690: goto            695
        //   693: ldc             -1717635959
        //   695: ldc             2021878866
        //   697: ixor           
        //   698: lookupswitch {
        //          -1385820098: 2776
        //          761937189: 693
        //          default: 724
        //        }
        //   724: goto            728
        //   727: athrow         
        //   728: invokevirtual   java/lang/String.contains:(Ljava/lang/CharSequence;)Z
        //   731: goto            735
        //   734: athrow         
        //   735: ifeq            744
        //   738: ldc_w           -537927329
        //   741: goto            747
        //   744: ldc_w           -537927330
        //   747: ldc_w           1106092811
        //   750: ixor           
        //   751: tableswitch {
        //          1006929064: 772
        //          1006929065: 846
        //          default: 738
        //        }
        //   772: aload           4
        //   774: goto            778
        //   777: athrow         
        //   778: invokevirtual   java/lang/String.toLowerCase:()Ljava/lang/String;
        //   781: goto            785
        //   784: athrow         
        //   785: ldc_w           ":"
        //   788: getstatic       dev/nuker/pyro/fc.0:I
        //   791: ifeq            800
        //   794: ldc_w           401855180
        //   797: goto            803
        //   800: ldc_w           -1621991204
        //   803: ldc_w           701988621
        //   806: ixor           
        //   807: lookupswitch {
        //          -991637613: 800
        //          1042591169: 2780
        //          default: 832
        //        }
        //   832: goto            836
        //   835: athrow         
        //   836: invokevirtual   java/lang/String.contains:(Ljava/lang/CharSequence;)Z
        //   839: goto            843
        //   842: athrow         
        //   843: ifne            2136
        //   846: aload_0        
        //   847: getfield        dev/nuker/pyro/f6l.c:Ldev/nuker/pyro/f0f;
        //   850: ifnull          2136
        //   853: getstatic       dev/nuker/pyro/fc.c:I
        //   856: ifge            865
        //   859: ldc_w           1172444522
        //   862: goto            868
        //   865: ldc_w           -1843302003
        //   868: ldc_w           1025450639
        //   871: ixor           
        //   872: lookupswitch {
        //          1239314688: 865
        //          2029860837: 2724
        //          default: 900
        //        }
        //   900: aload_0        
        //   901: getfield        dev/nuker/pyro/f6l.0:Ldev/nuker/pyro/f0f;
        //   904: ifnull          913
        //   907: ldc_w           -1059379981
        //   910: goto            916
        //   913: ldc_w           -1059379982
        //   916: ldc_w           1488322657
        //   919: ixor           
        //   920: tableswitch {
        //          819611940: 944
        //          819611941: 2136
        //          default: 907
        //        }
        //   944: aload           4
        //   946: new             Ljava/lang/StringBuilder;
        //   949: dup            
        //   950: goto            954
        //   953: athrow         
        //   954: invokespecial   java/lang/StringBuilder.<init>:()V
        //   957: goto            961
        //   960: athrow         
        //   961: ldc_w           "\u227c\u14cc\u8b2c\ub181"
        //   964: goto            968
        //   967: athrow         
        //   968: invokestatic    invokestatic   !!! ERROR
        //   971: goto            975
        //   974: athrow         
        //   975: getstatic       dev/nuker/pyro/fc.1:I
        //   978: ifeq            987
        //   981: ldc_w           -1402754322
        //   984: goto            990
        //   987: ldc_w           -1532099990
        //   990: ldc_w           -256837035
        //   993: ixor           
        //   994: lookupswitch {
        //          -1261610815: 987
        //          1557352635: 2764
        //          default: 1020
        //        }
        //  1020: goto            1024
        //  1023: athrow         
        //  1024: invokevirtual   java/lang/StringBuilder.append:(Ljava/lang/String;)Ljava/lang/StringBuilder;
        //  1027: goto            1031
        //  1030: athrow         
        //  1031: aload_0        
        //  1032: getfield        dev/nuker/pyro/f6l.c:Lnet/minecraft/client/Minecraft;
        //  1035: getfield        net/minecraft/client/Minecraft.field_71439_g:Lnet/minecraft/client/entity/EntityPlayerSP;
        //  1038: goto            1042
        //  1041: athrow         
        //  1042: invokevirtual   net/minecraft/client/entity/EntityPlayerSP.func_70005_c_:()Ljava/lang/String;
        //  1045: goto            1049
        //  1048: athrow         
        //  1049: goto            1053
        //  1052: athrow         
        //  1053: invokevirtual   java/lang/StringBuilder.append:(Ljava/lang/String;)Ljava/lang/StringBuilder;
        //  1056: goto            1060
        //  1059: athrow         
        //  1060: getstatic       dev/nuker/pyro/fc.0:I
        //  1063: ifeq            1072
        //  1066: ldc_w           1908815800
        //  1069: goto            1075
        //  1072: ldc_w           -867969518
        //  1075: ldc_w           1744716374
        //  1078: ixor           
        //  1079: lookupswitch {
        //          -565419918: 1072
        //          372798958: 2720
        //          default: 1104
        //        }
        //  1104: goto            1108
        //  1107: athrow         
        //  1108: invokevirtual   java/lang/StringBuilder.toString:()Ljava/lang/String;
        //  1111: goto            1115
        //  1114: athrow         
        //  1115: new             Ljava/lang/StringBuilder;
        //  1118: dup            
        //  1119: goto            1123
        //  1122: athrow         
        //  1123: invokespecial   java/lang/StringBuilder.<init>:()V
        //  1126: goto            1130
        //  1129: athrow         
        //  1130: aload_0        
        //  1131: aload_0        
        //  1132: getstatic       dev/nuker/pyro/fc.1:I
        //  1135: ifeq            1144
        //  1138: ldc_w           -2139598618
        //  1141: goto            1147
        //  1144: ldc_w           -12059410
        //  1147: ldc_w           -669131056
        //  1150: ixor           
        //  1151: lookupswitch {
        //          -144066828: 1144
        //          1483050550: 2756
        //          default: 1176
        //        }
        //  1176: getfield        dev/nuker/pyro/f6l.c:Ldev/nuker/pyro/f0f;
        //  1179: getstatic       dev/nuker/pyro/fc.c:I
        //  1182: ifge            1191
        //  1185: ldc_w           37034201
        //  1188: goto            1194
        //  1191: ldc_w           -1980775504
        //  1194: ldc_w           -558109810
        //  1197: ixor           
        //  1198: lookupswitch {
        //          -594611369: 1191
        //          1465133118: 1224
        //          default: 2772
        //        }
        //  1224: goto            1228
        //  1227: athrow         
        //  1228: invokespecial   dev/nuker/pyro/f6l.c:(Ldev/nuker/pyro/f0f;)Lcom/mojang/realmsclient/gui/ChatFormatting;
        //  1231: goto            1235
        //  1234: athrow         
        //  1235: goto            1239
        //  1238: athrow         
        //  1239: invokevirtual   java/lang/StringBuilder.append:(Ljava/lang/Object;)Ljava/lang/StringBuilder;
        //  1242: goto            1246
        //  1245: athrow         
        //  1246: aload_0        
        //  1247: getstatic       dev/nuker/pyro/fc.c:I
        //  1250: ifge            1259
        //  1253: ldc_w           -182382390
        //  1256: goto            1262
        //  1259: ldc_w           521222141
        //  1262: ldc_w           538550426
        //  1265: ixor           
        //  1266: lookupswitch {
        //          -717705136: 1259
        //          1057527655: 1292
        //          default: 2736
        //        }
        //  1292: getfield        dev/nuker/pyro/f6l.c:Lnet/minecraft/client/Minecraft;
        //  1295: getfield        net/minecraft/client/Minecraft.field_71439_g:Lnet/minecraft/client/entity/EntityPlayerSP;
        //  1298: getstatic       dev/nuker/pyro/fc.c:I
        //  1301: ifge            1310
        //  1304: ldc_w           -754161280
        //  1307: goto            1313
        //  1310: ldc_w           221146256
        //  1313: ldc_w           -660340882
        //  1316: ixor           
        //  1317: lookupswitch {
        //          -712141826: 1344
        //          196056814: 1310
        //          default: 2750
        //        }
        //  1344: goto            1348
        //  1347: athrow         
        //  1348: invokevirtual   net/minecraft/client/entity/EntityPlayerSP.func_70005_c_:()Ljava/lang/String;
        //  1351: goto            1355
        //  1354: athrow         
        //  1355: getstatic       dev/nuker/pyro/fc.c:I
        //  1358: ifge            1367
        //  1361: ldc_w           -562280766
        //  1364: goto            1370
        //  1367: ldc_w           1594276193
        //  1370: ldc_w           -544017842
        //  1373: ixor           
        //  1374: lookupswitch {
        //          -2137765073: 1400
        //          32421004: 1367
        //          default: 2722
        //        }
        //  1400: goto            1404
        //  1403: athrow         
        //  1404: invokevirtual   java/lang/StringBuilder.append:(Ljava/lang/String;)Ljava/lang/StringBuilder;
        //  1407: goto            1411
        //  1410: athrow         
        //  1411: getstatic       com/mojang/realmsclient/gui/ChatFormatting.RESET:Lcom/mojang/realmsclient/gui/ChatFormatting;
        //  1414: goto            1418
        //  1417: athrow         
        //  1418: invokevirtual   java/lang/StringBuilder.append:(Ljava/lang/Object;)Ljava/lang/StringBuilder;
        //  1421: goto            1425
        //  1424: athrow         
        //  1425: goto            1429
        //  1428: athrow         
        //  1429: invokevirtual   java/lang/StringBuilder.toString:()Ljava/lang/String;
        //  1432: goto            1436
        //  1435: athrow         
        //  1436: getstatic       dev/nuker/pyro/fc.0:I
        //  1439: ifeq            1448
        //  1442: ldc_w           1439392774
        //  1445: goto            1451
        //  1448: ldc_w           -1144701740
        //  1451: ldc_w           -598542285
        //  1454: ixor           
        //  1455: lookupswitch {
        //          -1986421707: 2716
        //          1720837053: 1448
        //          default: 1480
        //        }
        //  1480: goto            1484
        //  1483: athrow         
        //  1484: invokevirtual   java/lang/String.replaceAll:(Ljava/lang/String;Ljava/lang/String;)Ljava/lang/String;
        //  1487: goto            1491
        //  1490: athrow         
        //  1491: astore          4
        //  1493: aload           4
        //  1495: ldc_w           "<"
        //  1498: goto            1502
        //  1501: athrow         
        //  1502: invokevirtual   java/lang/String.contains:(Ljava/lang/CharSequence;)Z
        //  1505: goto            1509
        //  1508: athrow         
        //  1509: ifeq            2136
        //  1512: getstatic       dev/nuker/pyro/fc.0:I
        //  1515: ifeq            1524
        //  1518: ldc_w           -437711577
        //  1521: goto            1527
        //  1524: ldc_w           1757362786
        //  1527: ldc_w           -873616131
        //  1530: ixor           
        //  1531: lookupswitch {
        //          772055514: 2726
        //          845992193: 1524
        //          default: 1556
        //        }
        //  1556: aload           4
        //  1558: ldc_w           ">"
        //  1561: goto            1565
        //  1564: athrow         
        //  1565: invokevirtual   java/lang/String.contains:(Ljava/lang/CharSequence;)Z
        //  1568: goto            1572
        //  1571: athrow         
        //  1572: ifeq            1581
        //  1575: ldc_w           -1427334258
        //  1578: goto            1584
        //  1581: ldc_w           -1427334223
        //  1584: ldc_w           2012228625
        //  1587: ixor           
        //  1588: tableswitch {
        //          -1170641090: 1612
        //          -1170641089: 2136
        //          default: 1575
        //        }
        //  1612: aload           4
        //  1614: ldc_w           "<"
        //  1617: new             Ljava/lang/StringBuilder;
        //  1620: dup            
        //  1621: goto            1625
        //  1624: athrow         
        //  1625: invokespecial   java/lang/StringBuilder.<init>:()V
        //  1628: goto            1632
        //  1631: athrow         
        //  1632: aload_0        
        //  1633: aload_0        
        //  1634: getstatic       dev/nuker/pyro/fc.1:I
        //  1637: ifeq            1646
        //  1640: ldc_w           -1722729999
        //  1643: goto            1649
        //  1646: ldc_w           1410063621
        //  1649: ldc_w           -1774252709
        //  1652: ixor           
        //  1653: lookupswitch {
        //          -1036726178: 1680
        //          258880682: 1646
        //          default: 2770
        //        }
        //  1680: getfield        dev/nuker/pyro/f6l.1:Ldev/nuker/pyro/f0f;
        //  1683: getstatic       dev/nuker/pyro/fc.0:I
        //  1686: ifeq            1695
        //  1689: ldc_w           -1234256839
        //  1692: goto            1698
        //  1695: ldc_w           271066315
        //  1698: ldc_w           -2095714680
        //  1701: ixor           
        //  1702: lookupswitch {
        //          -1824667069: 1728
        //          897274545: 1695
        //          default: 2766
        //        }
        //  1728: goto            1732
        //  1731: athrow         
        //  1732: invokespecial   dev/nuker/pyro/f6l.c:(Ldev/nuker/pyro/f0f;)Lcom/mojang/realmsclient/gui/ChatFormatting;
        //  1735: goto            1739
        //  1738: athrow         
        //  1739: goto            1743
        //  1742: athrow         
        //  1743: invokevirtual   java/lang/StringBuilder.append:(Ljava/lang/Object;)Ljava/lang/StringBuilder;
        //  1746: goto            1750
        //  1749: athrow         
        //  1750: ldc_w           "["
        //  1753: goto            1757
        //  1756: athrow         
        //  1757: invokevirtual   java/lang/StringBuilder.append:(Ljava/lang/String;)Ljava/lang/StringBuilder;
        //  1760: goto            1764
        //  1763: athrow         
        //  1764: aload_0        
        //  1765: aload_0        
        //  1766: getfield        dev/nuker/pyro/f6l.0:Ldev/nuker/pyro/f0f;
        //  1769: goto            1773
        //  1772: athrow         
        //  1773: invokespecial   dev/nuker/pyro/f6l.c:(Ldev/nuker/pyro/f0f;)Lcom/mojang/realmsclient/gui/ChatFormatting;
        //  1776: goto            1780
        //  1779: athrow         
        //  1780: goto            1784
        //  1783: athrow         
        //  1784: invokevirtual   java/lang/StringBuilder.append:(Ljava/lang/Object;)Ljava/lang/StringBuilder;
        //  1787: goto            1791
        //  1790: athrow         
        //  1791: getstatic       dev/nuker/pyro/fc.1:I
        //  1794: ifeq            1803
        //  1797: ldc_w           1677297286
        //  1800: goto            1806
        //  1803: ldc_w           -1999879735
        //  1806: ldc_w           -1755240346
        //  1809: ixor           
        //  1810: lookupswitch {
        //          -191320352: 1803
        //          531458479: 1836
        //          default: 2746
        //        }
        //  1836: goto            1840
        //  1839: athrow         
        //  1840: invokevirtual   java/lang/StringBuilder.toString:()Ljava/lang/String;
        //  1843: goto            1847
        //  1846: athrow         
        //  1847: goto            1851
        //  1850: athrow         
        //  1851: invokevirtual   java/lang/String.replaceFirst:(Ljava/lang/String;Ljava/lang/String;)Ljava/lang/String;
        //  1854: goto            1858
        //  1857: athrow         
        //  1858: ldc_w           ">"
        //  1861: new             Ljava/lang/StringBuilder;
        //  1864: dup            
        //  1865: goto            1869
        //  1868: athrow         
        //  1869: invokespecial   java/lang/StringBuilder.<init>:()V
        //  1872: goto            1876
        //  1875: athrow         
        //  1876: getstatic       dev/nuker/pyro/fc.0:I
        //  1879: ifeq            1888
        //  1882: ldc_w           -298981404
        //  1885: goto            1891
        //  1888: ldc_w           -1658313136
        //  1891: ldc_w           -348330206
        //  1894: ixor           
        //  1895: lookupswitch {
        //          85000390: 1888
        //          1981071730: 1920
        //          default: 2730
        //        }
        //  1920: aload_0        
        //  1921: aload_0        
        //  1922: getstatic       dev/nuker/pyro/fc.c:I
        //  1925: ifge            1934
        //  1928: ldc_w           -1949207090
        //  1931: goto            1937
        //  1934: ldc_w           1577815047
        //  1937: ldc_w           662661788
        //  1940: ixor           
        //  1941: lookupswitch {
        //          -1397874862: 1934
        //          2037704347: 1968
        //          default: 2752
        //        }
        //  1968: getfield        dev/nuker/pyro/f6l.1:Ldev/nuker/pyro/f0f;
        //  1971: goto            1975
        //  1974: athrow         
        //  1975: invokespecial   dev/nuker/pyro/f6l.c:(Ldev/nuker/pyro/f0f;)Lcom/mojang/realmsclient/gui/ChatFormatting;
        //  1978: goto            1982
        //  1981: athrow         
        //  1982: getstatic       dev/nuker/pyro/fc.0:I
        //  1985: ifeq            1994
        //  1988: ldc_w           455212715
        //  1991: goto            1997
        //  1994: ldc_w           -1805997894
        //  1997: ldc_w           1803415857
        //  2000: ixor           
        //  2001: lookupswitch {
        //          -840403986: 1994
        //          1885081498: 2744
        //          default: 2028
        //        }
        //  2028: goto            2032
        //  2031: athrow         
        //  2032: invokevirtual   java/lang/StringBuilder.append:(Ljava/lang/Object;)Ljava/lang/StringBuilder;
        //  2035: goto            2039
        //  2038: athrow         
        //  2039: ldc_w           "]"
        //  2042: goto            2046
        //  2045: athrow         
        //  2046: invokevirtual   java/lang/StringBuilder.append:(Ljava/lang/String;)Ljava/lang/StringBuilder;
        //  2049: goto            2053
        //  2052: athrow         
        //  2053: getstatic       com/mojang/realmsclient/gui/ChatFormatting.RESET:Lcom/mojang/realmsclient/gui/ChatFormatting;
        //  2056: goto            2060
        //  2059: athrow         
        //  2060: invokevirtual   java/lang/StringBuilder.append:(Ljava/lang/Object;)Ljava/lang/StringBuilder;
        //  2063: goto            2067
        //  2066: athrow         
        //  2067: getstatic       dev/nuker/pyro/fc.1:I
        //  2070: ifeq            2079
        //  2073: ldc_w           -1324616586
        //  2076: goto            2082
        //  2079: ldc_w           2019882866
        //  2082: ldc_w           1656389147
        //  2085: ixor           
        //  2086: lookupswitch {
        //          -743339411: 2079
        //          450791785: 2112
        //          default: 2748
        //        }
        //  2112: goto            2116
        //  2115: athrow         
        //  2116: invokevirtual   java/lang/StringBuilder.toString:()Ljava/lang/String;
        //  2119: goto            2123
        //  2122: athrow         
        //  2123: goto            2127
        //  2126: athrow         
        //  2127: invokevirtual   java/lang/String.replaceFirst:(Ljava/lang/String;Ljava/lang/String;)Ljava/lang/String;
        //  2130: goto            2134
        //  2133: athrow         
        //  2134: astore          4
        //  2136: aload_1        
        //  2137: getstatic       dev/nuker/pyro/fc.0:I
        //  2140: ifeq            2149
        //  2143: ldc_w           -401182406
        //  2146: goto            2152
        //  2149: ldc_w           -1487115937
        //  2152: ldc_w           663515347
        //  2155: ixor           
        //  2156: lookupswitch {
        //          -811990551: 2738
        //          -498136931: 2149
        //          default: 2184
        //        }
        //  2184: goto            2188
        //  2187: athrow         
        //  2188: invokevirtual   dev/nuker/pyro/f34.c:()V
        //  2191: goto            2195
        //  2194: athrow         
        //  2195: getstatic       dev/nuker/pyro/fc.1:I
        //  2198: ifeq            2207
        //  2201: ldc_w           1922811174
        //  2204: goto            2210
        //  2207: ldc_w           -1328324241
        //  2210: ldc_w           -718135733
        //  2213: ixor           
        //  2214: lookupswitch {
        //          -1482040467: 2207
        //          1709276964: 2240
        //          default: 2760
        //        }
        //  2240: goto            2244
        //  2243: athrow         
        //  2244: invokestatic    net/minecraft/client/Minecraft.func_71410_x:()Lnet/minecraft/client/Minecraft;
        //  2247: goto            2251
        //  2250: athrow         
        //  2251: getfield        net/minecraft/client/Minecraft.field_71456_v:Lnet/minecraft/client/gui/GuiIngame;
        //  2254: ifnonnull       2348
        //  2257: getstatic       dev/nuker/pyro/fc.1:I
        //  2260: ifeq            2269
        //  2263: ldc_w           275413573
        //  2266: goto            2272
        //  2269: ldc_w           1011270790
        //  2272: ldc_w           133010785
        //  2275: ixor           
        //  2276: lookupswitch {
        //          -863008238: 2269
        //          394784548: 2758
        //          default: 2304
        //        }
        //  2304: aload_0        
        //  2305: getfield        dev/nuker/pyro/f6l.c:Lnet/minecraft/client/Minecraft;
        //  2308: getfield        net/minecraft/client/Minecraft.field_71439_g:Lnet/minecraft/client/entity/EntityPlayerSP;
        //  2311: ifnonnull       2320
        //  2314: ldc_w           1651407688
        //  2317: goto            2323
        //  2320: ldc_w           1651407691
        //  2323: ldc_w           655155897
        //  2326: ixor           
        //  2327: tableswitch {
        //          -1966787614: 2348
        //          -1966787613: 2715
        //          default: 2314
        //        }
        //  2348: getstatic       dev/nuker/pyro/f6l.c:Z
        //  2351: ifne            2433
        //  2354: getstatic       dev/nuker/pyro/fc.0:I
        //  2357: ifeq            2366
        //  2360: ldc_w           -1566347156
        //  2363: goto            2369
        //  2366: ldc_w           1039338737
        //  2369: ldc_w           630873281
        //  2372: ixor           
        //  2373: lookupswitch {
        //          -2026296147: 2754
        //          1609876935: 2366
        //          default: 2400
        //        }
        //  2400: goto            2404
        //  2403: athrow         
        //  2404: invokestatic    net/minecraft/client/Minecraft.func_71410_x:()Lnet/minecraft/client/Minecraft;
        //  2407: goto            2411
        //  2410: athrow         
        //  2411: getfield        net/minecraft/client/Minecraft.field_71456_v:Lnet/minecraft/client/gui/GuiIngame;
        //  2414: ifnonnull       2433
        //  2417: new             Ljava/lang/AssertionError;
        //  2420: dup            
        //  2421: goto            2425
        //  2424: athrow         
        //  2425: invokespecial   java/lang/AssertionError.<init>:()V
        //  2428: goto            2432
        //  2431: athrow         
        //  2432: athrow         
        //  2433: goto            2437
        //  2436: athrow         
        //  2437: invokestatic    net/minecraft/client/Minecraft.func_71410_x:()Lnet/minecraft/client/Minecraft;
        //  2440: goto            2444
        //  2443: athrow         
        //  2444: getfield        net/minecraft/client/Minecraft.field_71456_v:Lnet/minecraft/client/gui/GuiIngame;
        //  2447: goto            2451
        //  2450: athrow         
        //  2451: invokevirtual   net/minecraft/client/gui/GuiIngame.func_146158_b:()Lnet/minecraft/client/gui/GuiNewChat;
        //  2454: goto            2458
        //  2457: athrow         
        //  2458: new             Lnet/minecraft/util/text/TextComponentString;
        //  2461: dup            
        //  2462: ldc             ""
        //  2464: goto            2468
        //  2467: athrow         
        //  2468: invokespecial   net/minecraft/util/text/TextComponentString.<init>:(Ljava/lang/String;)V
        //  2471: goto            2475
        //  2474: athrow         
        //  2475: aload_3        
        //  2476: goto            2480
        //  2479: athrow         
        //  2480: invokevirtual   net/minecraft/util/text/TextComponentString.func_150257_a:(Lnet/minecraft/util/text/ITextComponent;)Lnet/minecraft/util/text/ITextComponent;
        //  2483: goto            2487
        //  2486: athrow         
        //  2487: new             Lnet/minecraft/util/text/TextComponentString;
        //  2490: dup            
        //  2491: new             Ljava/lang/StringBuilder;
        //  2494: dup            
        //  2495: goto            2499
        //  2498: athrow         
        //  2499: invokespecial   java/lang/StringBuilder.<init>:()V
        //  2502: goto            2506
        //  2505: athrow         
        //  2506: getstatic       dev/nuker/pyro/fc.0:I
        //  2509: ifeq            2518
        //  2512: ldc_w           -1212778815
        //  2515: goto            2521
        //  2518: ldc_w           365700650
        //  2521: ldc_w           2101477496
        //  2524: ixor           
        //  2525: lookupswitch {
        //          -889948487: 2778
        //          1404193565: 2518
        //          default: 2552
        //        }
        //  2552: aload           4
        //  2554: goto            2558
        //  2557: athrow         
        //  2558: invokevirtual   java/lang/StringBuilder.append:(Ljava/lang/String;)Ljava/lang/StringBuilder;
        //  2561: goto            2565
        //  2564: athrow         
        //  2565: getstatic       com/mojang/realmsclient/gui/ChatFormatting.RESET:Lcom/mojang/realmsclient/gui/ChatFormatting;
        //  2568: getstatic       dev/nuker/pyro/fc.c:I
        //  2571: ifge            2580
        //  2574: ldc_w           -296646167
        //  2577: goto            2583
        //  2580: ldc_w           -1082792547
        //  2583: ldc_w           -562252159
        //  2586: ixor           
        //  2587: lookupswitch {
        //          -57843439: 2580
        //          808271720: 2742
        //          default: 2612
        //        }
        //  2612: goto            2616
        //  2615: athrow         
        //  2616: invokevirtual   java/lang/StringBuilder.append:(Ljava/lang/Object;)Ljava/lang/StringBuilder;
        //  2619: goto            2623
        //  2622: athrow         
        //  2623: goto            2627
        //  2626: athrow         
        //  2627: invokevirtual   java/lang/StringBuilder.toString:()Ljava/lang/String;
        //  2630: goto            2634
        //  2633: athrow         
        //  2634: getstatic       dev/nuker/pyro/fc.0:I
        //  2637: ifeq            2646
        //  2640: ldc_w           667475079
        //  2643: goto            2649
        //  2646: ldc_w           1398855919
        //  2649: ldc_w           1004551844
        //  2652: ixor           
        //  2653: lookupswitch {
        //          472441379: 2774
        //          859050709: 2646
        //          default: 2680
        //        }
        //  2680: goto            2684
        //  2683: athrow         
        //  2684: invokespecial   net/minecraft/util/text/TextComponentString.<init>:(Ljava/lang/String;)V
        //  2687: goto            2691
        //  2690: athrow         
        //  2691: goto            2695
        //  2694: athrow         
        //  2695: invokeinterface net/minecraft/util/text/ITextComponent.func_150257_a:(Lnet/minecraft/util/text/ITextComponent;)Lnet/minecraft/util/text/ITextComponent;
        //  2700: goto            2704
        //  2703: athrow         
        //  2704: goto            2708
        //  2707: athrow         
        //  2708: invokevirtual   net/minecraft/client/gui/GuiNewChat.func_146227_a:(Lnet/minecraft/util/text/ITextComponent;)V
        //  2711: goto            2715
        //  2714: athrow         
        //  2715: return         
        //  2716: aconst_null    
        //  2717: athrow         
        //  2718: aconst_null    
        //  2719: athrow         
        //  2720: aconst_null    
        //  2721: athrow         
        //  2722: aconst_null    
        //  2723: athrow         
        //  2724: aconst_null    
        //  2725: athrow         
        //  2726: aconst_null    
        //  2727: athrow         
        //  2728: aconst_null    
        //  2729: athrow         
        //  2730: aconst_null    
        //  2731: athrow         
        //  2732: aconst_null    
        //  2733: athrow         
        //  2734: aconst_null    
        //  2735: athrow         
        //  2736: aconst_null    
        //  2737: athrow         
        //  2738: aconst_null    
        //  2739: athrow         
        //  2740: aconst_null    
        //  2741: athrow         
        //  2742: aconst_null    
        //  2743: athrow         
        //  2744: aconst_null    
        //  2745: athrow         
        //  2746: aconst_null    
        //  2747: athrow         
        //  2748: aconst_null    
        //  2749: athrow         
        //  2750: aconst_null    
        //  2751: athrow         
        //  2752: aconst_null    
        //  2753: athrow         
        //  2754: aconst_null    
        //  2755: athrow         
        //  2756: aconst_null    
        //  2757: athrow         
        //  2758: aconst_null    
        //  2759: athrow         
        //  2760: aconst_null    
        //  2761: athrow         
        //  2762: aconst_null    
        //  2763: athrow         
        //  2764: aconst_null    
        //  2765: athrow         
        //  2766: aconst_null    
        //  2767: athrow         
        //  2768: aconst_null    
        //  2769: athrow         
        //  2770: aconst_null    
        //  2771: athrow         
        //  2772: aconst_null    
        //  2773: athrow         
        //  2774: aconst_null    
        //  2775: athrow         
        //  2776: aconst_null    
        //  2777: athrow         
        //  2778: aconst_null    
        //  2779: athrow         
        //  2780: aconst_null    
        //  2781: athrow         
        //  2782: aconst_null    
        //  2783: athrow         
        //  2784: aconst_null    
        //  2785: athrow         
        //  2786: pop            
        //  2787: goto            24
        //  2790: pop            
        //  2791: aconst_null    
        //  2792: goto            2786
        //  2795: dup            
        //  2796: ifnull          2786
        //  2799: checkcast       Ljava/lang/Throwable;
        //  2802: athrow         
        //  2803: dup            
        //  2804: ifnull          2790
        //  2807: checkcast       Ljava/lang/Throwable;
        //  2810: athrow         
        //  2811: aconst_null    
        //  2812: athrow         
        //    StackMapTable: 01 B0 43 07 00 1E 04 FF 00 0B 00 00 00 01 07 00 1E FD 00 03 07 00 03 07 00 92 FF 00 03 00 00 00 01 07 00 1E FF 00 00 00 02 07 00 03 07 00 92 00 01 07 00 92 45 07 00 1E 40 07 00 97 06 43 07 00 1E 40 07 00 92 45 07 00 1E 40 07 01 AE 49 07 00 1E 40 07 00 92 45 07 00 1E 40 07 01 AE 4D 07 00 9F FF 00 01 00 02 07 00 03 07 00 92 00 02 07 00 9F 01 5E 07 00 9F FC 00 0B 07 00 9F 41 01 1D 4B 07 00 9F FF 00 01 00 03 07 00 03 07 00 92 07 00 9F 00 02 07 00 9F 01 5D 07 00 9F 42 07 00 1E 40 07 00 9F 45 07 00 1E 40 07 00 DD 10 41 01 1D 4B 07 00 9F FF 00 01 00 03 07 00 03 07 00 92 07 00 9F 00 02 07 00 9F 01 5D 07 00 9F 42 07 00 1E 40 07 00 9F 45 07 00 1E 40 07 00 BA 05 00 4E 07 00 C5 FF 00 01 00 03 07 00 03 07 00 92 07 00 9F 00 02 07 00 C5 01 5C 07 00 C5 42 07 00 1E 40 07 00 C5 45 07 00 1E 40 07 00 78 45 07 00 86 40 07 00 C8 45 07 00 1E 40 01 08 48 07 00 1E FF 00 00 00 03 07 00 03 07 00 92 07 00 9F 00 03 08 01 9A 08 01 9A 07 00 E6 45 07 00 1E 40 07 00 DD FC 00 0B 07 00 DD 41 01 1E 43 07 00 82 40 07 00 9F 45 07 00 1E 40 07 00 DD 42 07 00 7A 40 07 00 DD 47 07 00 1E 40 07 00 E6 FF 00 0E 00 05 07 00 03 07 00 92 07 00 9F 07 00 DD 07 00 E6 00 01 07 00 E6 FF 00 01 00 05 07 00 03 07 00 92 07 00 9F 07 00 DD 07 00 E6 00 02 07 00 E6 01 5D 07 00 E6 42 07 00 1E 40 07 00 E6 45 07 00 1E 40 07 00 E6 FF 00 0C 00 05 07 00 03 07 00 92 07 00 9F 07 00 DD 07 00 E6 00 02 07 00 E6 07 00 E6 FF 00 01 00 05 07 00 03 07 00 92 07 00 9F 07 00 DD 07 00 E6 00 03 07 00 E6 07 00 E6 01 FF 00 1D 00 05 07 00 03 07 00 92 07 00 9F 07 00 DD 07 00 E6 00 02 07 00 E6 07 00 E6 42 07 00 7A FF 00 00 00 05 07 00 03 07 00 92 07 00 9F 07 00 DD 07 00 E6 00 02 07 00 E6 07 00 E6 45 07 00 1E FF 00 00 00 05 07 00 03 07 00 92 07 00 9F 07 00 DD 07 00 E6 00 02 07 00 E6 07 00 E6 42 07 00 90 FF 00 00 00 05 07 00 03 07 00 92 07 00 9F 07 00 DD 07 00 E6 00 02 07 00 E6 07 00 E6 45 07 00 1E 40 01 02 04 41 01 17 44 07 00 1E 40 07 00 E6 45 07 00 1E 40 07 00 E6 44 07 00 1E FF 00 00 00 05 07 00 03 07 00 92 07 00 9F 07 00 DD 07 00 E6 00 02 07 00 E6 07 00 E6 45 07 00 1E FF 00 00 00 05 07 00 03 07 00 92 07 00 9F 07 00 DD 07 00 E6 00 02 07 00 E6 07 00 E6 FF 00 0A 00 05 07 00 03 07 00 92 07 00 9F 07 00 DD 07 00 E6 00 02 07 00 E6 07 00 E6 FF 00 01 00 05 07 00 03 07 00 92 07 00 9F 07 00 DD 07 00 E6 00 03 07 00 E6 07 00 E6 01 FF 00 1C 00 05 07 00 03 07 00 92 07 00 9F 07 00 DD 07 00 E6 00 02 07 00 E6 07 00 E6 42 07 00 1E FF 00 00 00 05 07 00 03 07 00 92 07 00 9F 07 00 DD 07 00 E6 00 02 07 00 E6 07 00 E6 45 07 00 1E 40 01 02 05 42 01 18 44 07 00 7A 40 07 00 E6 45 07 00 1E 40 07 00 E6 FF 00 0E 00 05 07 00 03 07 00 92 07 00 9F 07 00 DD 07 00 E6 00 02 07 00 E6 07 00 E6 FF 00 02 00 05 07 00 03 07 00 92 07 00 9F 07 00 DD 07 00 E6 00 03 07 00 E6 07 00 E6 01 FF 00 1C 00 05 07 00 03 07 00 92 07 00 9F 07 00 DD 07 00 E6 00 02 07 00 E6 07 00 E6 42 07 00 1E FF 00 00 00 05 07 00 03 07 00 92 07 00 9F 07 00 DD 07 00 E6 00 02 07 00 E6 07 00 E6 45 07 00 1E 40 01 02 12 42 01 1F 06 05 42 01 1B 48 07 00 88 FF 00 00 00 05 07 00 03 07 00 92 07 00 9F 07 00 DD 07 00 E6 00 03 07 00 E6 08 03 B2 08 03 B2 45 07 00 1E FF 00 00 00 05 07 00 03 07 00 92 07 00 9F 07 00 DD 07 00 E6 00 02 07 00 E6 07 01 13 45 07 00 1E FF 00 00 00 05 07 00 03 07 00 92 07 00 9F 07 00 DD 07 00 E6 00 03 07 00 E6 07 01 13 07 00 E6 45 07 00 1E FF 00 00 00 05 07 00 03 07 00 92 07 00 9F 07 00 DD 07 00 E6 00 03 07 00 E6 07 01 13 07 00 E6 FF 00 0B 00 05 07 00 03 07 00 92 07 00 9F 07 00 DD 07 00 E6 00 03 07 00 E6 07 01 13 07 00 E6 FF 00 02 00 05 07 00 03 07 00 92 07 00 9F 07 00 DD 07 00 E6 00 04 07 00 E6 07 01 13 07 00 E6 01 FF 00 1D 00 05 07 00 03 07 00 92 07 00 9F 07 00 DD 07 00 E6 00 03 07 00 E6 07 01 13 07 00 E6 42 07 00 11 FF 00 00 00 05 07 00 03 07 00 92 07 00 9F 07 00 DD 07 00 E6 00 03 07 00 E6 07 01 13 07 00 E6 45 07 00 1E FF 00 00 00 05 07 00 03 07 00 92 07 00 9F 07 00 DD 07 00 E6 00 02 07 00 E6 07 01 13 FF 00 09 00 00 00 01 07 00 1E FF 00 00 00 05 07 00 03 07 00 92 07 00 9F 07 00 DD 07 00 E6 00 03 07 00 E6 07 01 13 07 01 2A 45 07 00 1E FF 00 00 00 05 07 00 03 07 00 92 07 00 9F 07 00 DD 07 00 E6 00 03 07 00 E6 07 01 13 07 00 E6 42 07 00 1E FF 00 00 00 05 07 00 03 07 00 92 07 00 9F 07 00 DD 07 00 E6 00 03 07 00 E6 07 01 13 07 00 E6 45 07 00 1E FF 00 00 00 05 07 00 03 07 00 92 07 00 9F 07 00 DD 07 00 E6 00 02 07 00 E6 07 01 13 FF 00 0B 00 05 07 00 03 07 00 92 07 00 9F 07 00 DD 07 00 E6 00 02 07 00 E6 07 01 13 FF 00 02 00 05 07 00 03 07 00 92 07 00 9F 07 00 DD 07 00 E6 00 03 07 00 E6 07 01 13 01 FF 00 1C 00 05 07 00 03 07 00 92 07 00 9F 07 00 DD 07 00 E6 00 02 07 00 E6 07 01 13 42 07 00 1E FF 00 00 00 05 07 00 03 07 00 92 07 00 9F 07 00 DD 07 00 E6 00 02 07 00 E6 07 01 13 45 07 00 1E FF 00 00 00 05 07 00 03 07 00 92 07 00 9F 07 00 DD 07 00 E6 00 02 07 00 E6 07 00 E6 46 07 00 1E FF 00 00 00 05 07 00 03 07 00 92 07 00 9F 07 00 DD 07 00 E6 00 04 07 00 E6 07 00 E6 08 04 5B 08 04 5B 45 07 00 1E FF 00 00 00 05 07 00 03 07 00 92 07 00 9F 07 00 DD 07 00 E6 00 03 07 00 E6 07 00 E6 07 01 13 FF 00 0D 00 05 07 00 03 07 00 92 07 00 9F 07 00 DD 07 00 E6 00 05 07 00 E6 07 00 E6 07 01 13 07 00 03 07 00 03 FF 00 02 00 05 07 00 03 07 00 92 07 00 9F 07 00 DD 07 00 E6 00 06 07 00 E6 07 00 E6 07 01 13 07 00 03 07 00 03 01 FF 00 1C 00 05 07 00 03 07 00 92 07 00 9F 07 00 DD 07 00 E6 00 05 07 00 E6 07 00 E6 07 01 13 07 00 03 07 00 03 FF 00 0E 00 05 07 00 03 07 00 92 07 00 9F 07 00 DD 07 00 E6 00 05 07 00 E6 07 00 E6 07 01 13 07 00 03 07 00 2A FF 00 02 00 05 07 00 03 07 00 92 07 00 9F 07 00 DD 07 00 E6 00 06 07 00 E6 07 00 E6 07 01 13 07 00 03 07 00 2A 01 FF 00 1D 00 05 07 00 03 07 00 92 07 00 9F 07 00 DD 07 00 E6 00 05 07 00 E6 07 00 E6 07 01 13 07 00 03 07 00 2A 42 07 00 1E FF 00 00 00 05 07 00 03 07 00 92 07 00 9F 07 00 DD 07 00 E6 00 05 07 00 E6 07 00 E6 07 01 13 07 00 03 07 00 2A 45 07 00 1E FF 00 00 00 05 07 00 03 07 00 92 07 00 9F 07 00 DD 07 00 E6 00 04 07 00 E6 07 00 E6 07 01 13 07 00 3B 42 07 00 1E FF 00 00 00 05 07 00 03 07 00 92 07 00 9F 07 00 DD 07 00 E6 00 04 07 00 E6 07 00 E6 07 01 13 07 00 3B 45 07 00 1E FF 00 00 00 05 07 00 03 07 00 92 07 00 9F 07 00 DD 07 00 E6 00 03 07 00 E6 07 00 E6 07 01 13 FF 00 0C 00 05 07 00 03 07 00 92 07 00 9F 07 00 DD 07 00 E6 00 04 07 00 E6 07 00 E6 07 01 13 07 00 03 FF 00 02 00 05 07 00 03 07 00 92 07 00 9F 07 00 DD 07 00 E6 00 05 07 00 E6 07 00 E6 07 01 13 07 00 03 01 FF 00 1D 00 05 07 00 03 07 00 92 07 00 9F 07 00 DD 07 00 E6 00 04 07 00 E6 07 00 E6 07 01 13 07 00 03 FF 00 11 00 05 07 00 03 07 00 92 07 00 9F 07 00 DD 07 00 E6 00 04 07 00 E6 07 00 E6 07 01 13 07 01 2A FF 00 02 00 05 07 00 03 07 00 92 07 00 9F 07 00 DD 07 00 E6 00 05 07 00 E6 07 00 E6 07 01 13 07 01 2A 01 FF 00 1E 00 05 07 00 03 07 00 92 07 00 9F 07 00 DD 07 00 E6 00 04 07 00 E6 07 00 E6 07 01 13 07 01 2A FF 00 02 00 00 00 01 07 00 1E FF 00 00 00 05 07 00 03 07 00 92 07 00 9F 07 00 DD 07 00 E6 00 04 07 00 E6 07 00 E6 07 01 13 07 01 2A 45 07 00 1E FF 00 00 00 05 07 00 03 07 00 92 07 00 9F 07 00 DD 07 00 E6 00 04 07 00 E6 07 00 E6 07 01 13 07 00 E6 FF 00 0B 00 05 07 00 03 07 00 92 07 00 9F 07 00 DD 07 00 E6 00 04 07 00 E6 07 00 E6 07 01 13 07 00 E6 FF 00 02 00 05 07 00 03 07 00 92 07 00 9F 07 00 DD 07 00 E6 00 05 07 00 E6 07 00 E6 07 01 13 07 00 E6 01 FF 00 1D 00 05 07 00 03 07 00 92 07 00 9F 07 00 DD 07 00 E6 00 04 07 00 E6 07 00 E6 07 01 13 07 00 E6 42 07 00 80 FF 00 00 00 05 07 00 03 07 00 92 07 00 9F 07 00 DD 07 00 E6 00 04 07 00 E6 07 00 E6 07 01 13 07 00 E6 45 07 00 1E FF 00 00 00 05 07 00 03 07 00 92 07 00 9F 07 00 DD 07 00 E6 00 03 07 00 E6 07 00 E6 07 01 13 45 07 00 1E FF 00 00 00 05 07 00 03 07 00 92 07 00 9F 07 00 DD 07 00 E6 00 04 07 00 E6 07 00 E6 07 01 13 07 00 3B 45 07 00 1E FF 00 00 00 05 07 00 03 07 00 92 07 00 9F 07 00 DD 07 00 E6 00 03 07 00 E6 07 00 E6 07 01 13 42 07 00 1E FF 00 00 00 05 07 00 03 07 00 92 07 00 9F 07 00 DD 07 00 E6 00 03 07 00 E6 07 00 E6 07 01 13 45 07 00 1E FF 00 00 00 05 07 00 03 07 00 92 07 00 9F 07 00 DD 07 00 E6 00 03 07 00 E6 07 00 E6 07 00 E6 FF 00 0B 00 05 07 00 03 07 00 92 07 00 9F 07 00 DD 07 00 E6 00 03 07 00 E6 07 00 E6 07 00 E6 FF 00 02 00 05 07 00 03 07 00 92 07 00 9F 07 00 DD 07 00 E6 00 04 07 00 E6 07 00 E6 07 00 E6 01 FF 00 1C 00 05 07 00 03 07 00 92 07 00 9F 07 00 DD 07 00 E6 00 03 07 00 E6 07 00 E6 07 00 E6 42 07 00 1E FF 00 00 00 05 07 00 03 07 00 92 07 00 9F 07 00 DD 07 00 E6 00 03 07 00 E6 07 00 E6 07 00 E6 45 07 00 1E 40 07 00 E6 49 07 00 1E FF 00 00 00 05 07 00 03 07 00 92 07 00 9F 07 00 DD 07 00 E6 00 02 07 00 E6 07 00 E6 45 07 00 1E 40 01 0E 42 01 1C 47 07 00 90 FF 00 00 00 05 07 00 03 07 00 92 07 00 9F 07 00 DD 07 00 E6 00 02 07 00 E6 07 00 E6 45 07 00 1E 40 01 02 05 42 01 1B 4B 07 00 1E FF 00 00 00 05 07 00 03 07 00 92 07 00 9F 07 00 DD 07 00 E6 00 04 07 00 E6 07 00 E6 08 06 51 08 06 51 45 07 00 1E FF 00 00 00 05 07 00 03 07 00 92 07 00 9F 07 00 DD 07 00 E6 00 03 07 00 E6 07 00 E6 07 01 13 FF 00 0D 00 05 07 00 03 07 00 92 07 00 9F 07 00 DD 07 00 E6 00 05 07 00 E6 07 00 E6 07 01 13 07 00 03 07 00 03 FF 00 02 00 05 07 00 03 07 00 92 07 00 9F 07 00 DD 07 00 E6 00 06 07 00 E6 07 00 E6 07 01 13 07 00 03 07 00 03 01 FF 00 1E 00 05 07 00 03 07 00 92 07 00 9F 07 00 DD 07 00 E6 00 05 07 00 E6 07 00 E6 07 01 13 07 00 03 07 00 03 FF 00 0E 00 05 07 00 03 07 00 92 07 00 9F 07 00 DD 07 00 E6 00 05 07 00 E6 07 00 E6 07 01 13 07 00 03 07 00 2A FF 00 02 00 05 07 00 03 07 00 92 07 00 9F 07 00 DD 07 00 E6 00 06 07 00 E6 07 00 E6 07 01 13 07 00 03 07 00 2A 01 FF 00 1D 00 05 07 00 03 07 00 92 07 00 9F 07 00 DD 07 00 E6 00 05 07 00 E6 07 00 E6 07 01 13 07 00 03 07 00 2A 42 07 00 1E FF 00 00 00 05 07 00 03 07 00 92 07 00 9F 07 00 DD 07 00 E6 00 05 07 00 E6 07 00 E6 07 01 13 07 00 03 07 00 2A 45 07 00 1E FF 00 00 00 05 07 00 03 07 00 92 07 00 9F 07 00 DD 07 00 E6 00 04 07 00 E6 07 00 E6 07 01 13 07 00 3B 42 07 00 1E FF 00 00 00 05 07 00 03 07 00 92 07 00 9F 07 00 DD 07 00 E6 00 04 07 00 E6 07 00 E6 07 01 13 07 00 3B 45 07 00 1E FF 00 00 00 05 07 00 03 07 00 92 07 00 9F 07 00 DD 07 00 E6 00 03 07 00 E6 07 00 E6 07 01 13 FF 00 05 00 00 00 01 07 00 1E FF 00 00 00 05 07 00 03 07 00 92 07 00 9F 07 00 DD 07 00 E6 00 04 07 00 E6 07 00 E6 07 01 13 07 00 E6 45 07 00 1E FF 00 00 00 05 07 00 03 07 00 92 07 00 9F 07 00 DD 07 00 E6 00 03 07 00 E6 07 00 E6 07 01 13 47 07 00 13 FF 00 00 00 05 07 00 03 07 00 92 07 00 9F 07 00 DD 07 00 E6 00 05 07 00 E6 07 00 E6 07 01 13 07 00 03 07 00 2A 45 07 00 1E FF 00 00 00 05 07 00 03 07 00 92 07 00 9F 07 00 DD 07 00 E6 00 04 07 00 E6 07 00 E6 07 01 13 07 00 3B 42 07 00 1E FF 00 00 00 05 07 00 03 07 00 92 07 00 9F 07 00 DD 07 00 E6 00 04 07 00 E6 07 00 E6 07 01 13 07 00 3B 45 07 00 1E FF 00 00 00 05 07 00 03 07 00 92 07 00 9F 07 00 DD 07 00 E6 00 03 07 00 E6 07 00 E6 07 01 13 FF 00 0B 00 05 07 00 03 07 00 92 07 00 9F 07 00 DD 07 00 E6 00 03 07 00 E6 07 00 E6 07 01 13 FF 00 02 00 05 07 00 03 07 00 92 07 00 9F 07 00 DD 07 00 E6 00 04 07 00 E6 07 00 E6 07 01 13 01 FF 00 1D 00 05 07 00 03 07 00 92 07 00 9F 07 00 DD 07 00 E6 00 03 07 00 E6 07 00 E6 07 01 13 42 07 00 7A FF 00 00 00 05 07 00 03 07 00 92 07 00 9F 07 00 DD 07 00 E6 00 03 07 00 E6 07 00 E6 07 01 13 45 07 00 1E FF 00 00 00 05 07 00 03 07 00 92 07 00 9F 07 00 DD 07 00 E6 00 03 07 00 E6 07 00 E6 07 00 E6 FF 00 02 00 00 00 01 07 00 1E FF 00 00 00 05 07 00 03 07 00 92 07 00 9F 07 00 DD 07 00 E6 00 03 07 00 E6 07 00 E6 07 00 E6 45 07 00 1E 40 07 00 E6 49 07 00 1E FF 00 00 00 05 07 00 03 07 00 92 07 00 9F 07 00 DD 07 00 E6 00 04 07 00 E6 07 00 E6 08 07 45 08 07 45 45 07 00 1E FF 00 00 00 05 07 00 03 07 00 92 07 00 9F 07 00 DD 07 00 E6 00 03 07 00 E6 07 00 E6 07 01 13 FF 00 0B 00 05 07 00 03 07 00 92 07 00 9F 07 00 DD 07 00 E6 00 03 07 00 E6 07 00 E6 07 01 13 FF 00 02 00 05 07 00 03 07 00 92 07 00 9F 07 00 DD 07 00 E6 00 04 07 00 E6 07 00 E6 07 01 13 01 FF 00 1C 00 05 07 00 03 07 00 92 07 00 9F 07 00 DD 07 00 E6 00 03 07 00 E6 07 00 E6 07 01 13 FF 00 0D 00 05 07 00 03 07 00 92 07 00 9F 07 00 DD 07 00 E6 00 05 07 00 E6 07 00 E6 07 01 13 07 00 03 07 00 03 FF 00 02 00 05 07 00 03 07 00 92 07 00 9F 07 00 DD 07 00 E6 00 06 07 00 E6 07 00 E6 07 01 13 07 00 03 07 00 03 01 FF 00 1E 00 05 07 00 03 07 00 92 07 00 9F 07 00 DD 07 00 E6 00 05 07 00 E6 07 00 E6 07 01 13 07 00 03 07 00 03 45 07 00 1E FF 00 00 00 05 07 00 03 07 00 92 07 00 9F 07 00 DD 07 00 E6 00 05 07 00 E6 07 00 E6 07 01 13 07 00 03 07 00 2A 45 07 00 1E FF 00 00 00 05 07 00 03 07 00 92 07 00 9F 07 00 DD 07 00 E6 00 04 07 00 E6 07 00 E6 07 01 13 07 00 3B FF 00 0B 00 05 07 00 03 07 00 92 07 00 9F 07 00 DD 07 00 E6 00 04 07 00 E6 07 00 E6 07 01 13 07 00 3B FF 00 02 00 05 07 00 03 07 00 92 07 00 9F 07 00 DD 07 00 E6 00 05 07 00 E6 07 00 E6 07 01 13 07 00 3B 01 FF 00 1E 00 05 07 00 03 07 00 92 07 00 9F 07 00 DD 07 00 E6 00 04 07 00 E6 07 00 E6 07 01 13 07 00 3B FF 00 02 00 00 00 01 07 00 1E FF 00 00 00 05 07 00 03 07 00 92 07 00 9F 07 00 DD 07 00 E6 00 04 07 00 E6 07 00 E6 07 01 13 07 00 3B 45 07 00 1E FF 00 00 00 05 07 00 03 07 00 92 07 00 9F 07 00 DD 07 00 E6 00 03 07 00 E6 07 00 E6 07 01 13 FF 00 05 00 00 00 01 07 00 1E FF 00 00 00 05 07 00 03 07 00 92 07 00 9F 07 00 DD 07 00 E6 00 04 07 00 E6 07 00 E6 07 01 13 07 00 E6 45 07 00 1E FF 00 00 00 05 07 00 03 07 00 92 07 00 9F 07 00 DD 07 00 E6 00 03 07 00 E6 07 00 E6 07 01 13 45 07 00 88 FF 00 00 00 05 07 00 03 07 00 92 07 00 9F 07 00 DD 07 00 E6 00 04 07 00 E6 07 00 E6 07 01 13 07 00 3B 45 07 00 1E FF 00 00 00 05 07 00 03 07 00 92 07 00 9F 07 00 DD 07 00 E6 00 03 07 00 E6 07 00 E6 07 01 13 FF 00 0B 00 05 07 00 03 07 00 92 07 00 9F 07 00 DD 07 00 E6 00 03 07 00 E6 07 00 E6 07 01 13 FF 00 02 00 05 07 00 03 07 00 92 07 00 9F 07 00 DD 07 00 E6 00 04 07 00 E6 07 00 E6 07 01 13 01 FF 00 1D 00 05 07 00 03 07 00 92 07 00 9F 07 00 DD 07 00 E6 00 03 07 00 E6 07 00 E6 07 01 13 FF 00 02 00 00 00 01 07 00 1E FF 00 00 00 05 07 00 03 07 00 92 07 00 9F 07 00 DD 07 00 E6 00 03 07 00 E6 07 00 E6 07 01 13 45 07 00 1E FF 00 00 00 05 07 00 03 07 00 92 07 00 9F 07 00 DD 07 00 E6 00 03 07 00 E6 07 00 E6 07 00 E6 42 07 00 7A FF 00 00 00 05 07 00 03 07 00 92 07 00 9F 07 00 DD 07 00 E6 00 03 07 00 E6 07 00 E6 07 00 E6 45 07 00 1E 40 07 00 E6 01 4C 07 00 92 FF 00 02 00 05 07 00 03 07 00 92 07 00 9F 07 00 DD 07 00 E6 00 02 07 00 92 01 5F 07 00 92 42 07 00 1E 40 07 00 92 45 07 00 1E 00 0B 42 01 1D 42 07 00 1E 00 45 07 00 1E 40 07 01 24 11 42 01 1F 09 05 42 01 18 11 42 01 1E 42 07 00 7A 00 45 07 00 1E 40 07 01 24 4C 07 00 1E FF 00 00 00 05 07 00 03 07 00 92 07 00 9F 07 00 DD 07 00 E6 00 02 08 09 71 08 09 71 45 07 00 1E 40 07 00 7E 00 42 07 00 1E 00 45 07 00 1E 40 07 01 24 45 07 00 8E 40 07 01 94 45 07 00 1E 40 07 01 A8 48 07 00 11 FF 00 00 00 05 07 00 03 07 00 92 07 00 9F 07 00 DD 07 00 E6 00 04 07 01 A8 08 09 9A 08 09 9A 07 00 E6 45 07 00 1E FF 00 00 00 05 07 00 03 07 00 92 07 00 9F 07 00 DD 07 00 E6 00 02 07 01 A8 07 00 AE FF 00 03 00 00 00 01 07 00 1E FF 00 00 00 05 07 00 03 07 00 92 07 00 9F 07 00 DD 07 00 E6 00 03 07 01 A8 07 00 AE 07 00 DD 45 07 00 1E FF 00 00 00 05 07 00 03 07 00 92 07 00 9F 07 00 DD 07 00 E6 00 02 07 01 A8 07 00 DD 4A 07 00 1E FF 00 00 00 05 07 00 03 07 00 92 07 00 9F 07 00 DD 07 00 E6 00 06 07 01 A8 07 00 DD 08 09 B7 08 09 B7 08 09 BB 08 09 BB 45 07 00 1E FF 00 00 00 05 07 00 03 07 00 92 07 00 9F 07 00 DD 07 00 E6 00 05 07 01 A8 07 00 DD 08 09 B7 08 09 B7 07 01 13 FF 00 0B 00 05 07 00 03 07 00 92 07 00 9F 07 00 DD 07 00 E6 00 05 07 01 A8 07 00 DD 08 09 B7 08 09 B7 07 01 13 FF 00 02 00 05 07 00 03 07 00 92 07 00 9F 07 00 DD 07 00 E6 00 06 07 01 A8 07 00 DD 08 09 B7 08 09 B7 07 01 13 01 FF 00 1E 00 05 07 00 03 07 00 92 07 00 9F 07 00 DD 07 00 E6 00 05 07 01 A8 07 00 DD 08 09 B7 08 09 B7 07 01 13 44 07 00 1E FF 00 00 00 05 07 00 03 07 00 92 07 00 9F 07 00 DD 07 00 E6 00 06 07 01 A8 07 00 DD 08 09 B7 08 09 B7 07 01 13 07 00 E6 45 07 00 1E FF 00 00 00 05 07 00 03 07 00 92 07 00 9F 07 00 DD 07 00 E6 00 05 07 01 A8 07 00 DD 08 09 B7 08 09 B7 07 01 13 FF 00 0E 00 05 07 00 03 07 00 92 07 00 9F 07 00 DD 07 00 E6 00 06 07 01 A8 07 00 DD 08 09 B7 08 09 B7 07 01 13 07 00 3B FF 00 02 00 05 07 00 03 07 00 92 07 00 9F 07 00 DD 07 00 E6 00 07 07 01 A8 07 00 DD 08 09 B7 08 09 B7 07 01 13 07 00 3B 01 FF 00 1C 00 05 07 00 03 07 00 92 07 00 9F 07 00 DD 07 00 E6 00 06 07 01 A8 07 00 DD 08 09 B7 08 09 B7 07 01 13 07 00 3B 42 07 00 80 FF 00 00 00 05 07 00 03 07 00 92 07 00 9F 07 00 DD 07 00 E6 00 06 07 01 A8 07 00 DD 08 09 B7 08 09 B7 07 01 13 07 00 3B 45 07 00 1E FF 00 00 00 05 07 00 03 07 00 92 07 00 9F 07 00 DD 07 00 E6 00 05 07 01 A8 07 00 DD 08 09 B7 08 09 B7 07 01 13 42 07 00 8A FF 00 00 00 05 07 00 03 07 00 92 07 00 9F 07 00 DD 07 00 E6 00 05 07 01 A8 07 00 DD 08 09 B7 08 09 B7 07 01 13 45 07 00 1E FF 00 00 00 05 07 00 03 07 00 92 07 00 9F 07 00 DD 07 00 E6 00 05 07 01 A8 07 00 DD 08 09 B7 08 09 B7 07 00 E6 FF 00 0B 00 05 07 00 03 07 00 92 07 00 9F 07 00 DD 07 00 E6 00 05 07 01 A8 07 00 DD 08 09 B7 08 09 B7 07 00 E6 FF 00 02 00 05 07 00 03 07 00 92 07 00 9F 07 00 DD 07 00 E6 00 06 07 01 A8 07 00 DD 08 09 B7 08 09 B7 07 00 E6 01 FF 00 1E 00 05 07 00 03 07 00 92 07 00 9F 07 00 DD 07 00 E6 00 05 07 01 A8 07 00 DD 08 09 B7 08 09 B7 07 00 E6 42 07 00 1E FF 00 00 00 05 07 00 03 07 00 92 07 00 9F 07 00 DD 07 00 E6 00 05 07 01 A8 07 00 DD 08 09 B7 08 09 B7 07 00 E6 45 07 00 1E FF 00 00 00 05 07 00 03 07 00 92 07 00 9F 07 00 DD 07 00 E6 00 03 07 01 A8 07 00 DD 07 00 AE 42 07 00 8A FF 00 00 00 05 07 00 03 07 00 92 07 00 9F 07 00 DD 07 00 E6 00 03 07 01 A8 07 00 DD 07 00 AE 47 07 00 1E FF 00 00 00 05 07 00 03 07 00 92 07 00 9F 07 00 DD 07 00 E6 00 02 07 01 A8 07 00 DD 42 07 00 1E FF 00 00 00 05 07 00 03 07 00 92 07 00 9F 07 00 DD 07 00 E6 00 02 07 01 A8 07 00 DD 45 07 00 1E F8 00 00 FF 00 00 00 05 07 00 03 07 00 92 07 00 9F 07 00 DD 07 00 E6 00 03 07 00 E6 07 00 E6 07 00 E6 FF 00 01 00 03 07 00 03 07 00 92 07 00 9F 00 01 07 00 9F FF 00 01 00 05 07 00 03 07 00 92 07 00 9F 07 00 DD 07 00 E6 00 02 07 00 E6 07 01 13 FF 00 01 00 05 07 00 03 07 00 92 07 00 9F 07 00 DD 07 00 E6 00 04 07 00 E6 07 00 E6 07 01 13 07 00 E6 01 01 FF 00 01 00 03 07 00 03 07 00 92 07 00 9F 00 01 07 00 9F FF 00 01 00 05 07 00 03 07 00 92 07 00 9F 07 00 DD 07 00 E6 00 03 07 00 E6 07 00 E6 07 01 13 FF 00 01 00 05 07 00 03 07 00 92 07 00 9F 07 00 DD 07 00 E6 00 02 07 00 E6 07 00 E6 F9 00 01 FF 00 01 00 05 07 00 03 07 00 92 07 00 9F 07 00 DD 07 00 E6 00 04 07 00 E6 07 00 E6 07 01 13 07 00 03 41 07 00 92 FA 00 01 FF 00 01 00 05 07 00 03 07 00 92 07 00 9F 07 00 DD 07 00 E6 00 06 07 01 A8 07 00 DD 08 09 B7 08 09 B7 07 01 13 07 00 3B FF 00 01 00 05 07 00 03 07 00 92 07 00 9F 07 00 DD 07 00 E6 00 04 07 00 E6 07 00 E6 07 01 13 07 00 3B FF 00 01 00 05 07 00 03 07 00 92 07 00 9F 07 00 DD 07 00 E6 00 03 07 00 E6 07 00 E6 07 01 13 FF 00 01 00 05 07 00 03 07 00 92 07 00 9F 07 00 DD 07 00 E6 00 03 07 00 E6 07 00 E6 07 01 13 FF 00 01 00 05 07 00 03 07 00 92 07 00 9F 07 00 DD 07 00 E6 00 04 07 00 E6 07 00 E6 07 01 13 07 01 2A FF 00 01 00 05 07 00 03 07 00 92 07 00 9F 07 00 DD 07 00 E6 00 05 07 00 E6 07 00 E6 07 01 13 07 00 03 07 00 03 01 FF 00 01 00 05 07 00 03 07 00 92 07 00 9F 07 00 DD 07 00 E6 00 05 07 00 E6 07 00 E6 07 01 13 07 00 03 07 00 03 01 01 F9 00 01 FF 00 01 00 05 07 00 03 07 00 92 07 00 9F 07 00 DD 07 00 E6 00 03 07 00 E6 07 01 13 07 00 E6 FF 00 01 00 05 07 00 03 07 00 92 07 00 9F 07 00 DD 07 00 E6 00 05 07 00 E6 07 00 E6 07 01 13 07 00 03 07 00 2A FF 00 01 00 02 07 00 03 07 00 92 00 01 07 00 9F FF 00 01 00 05 07 00 03 07 00 92 07 00 9F 07 00 DD 07 00 E6 00 05 07 00 E6 07 00 E6 07 01 13 07 00 03 07 00 03 FF 00 01 00 05 07 00 03 07 00 92 07 00 9F 07 00 DD 07 00 E6 00 05 07 00 E6 07 00 E6 07 01 13 07 00 03 07 00 2A FF 00 01 00 05 07 00 03 07 00 92 07 00 9F 07 00 DD 07 00 E6 00 05 07 01 A8 07 00 DD 08 09 B7 08 09 B7 07 00 E6 FF 00 01 00 05 07 00 03 07 00 92 07 00 9F 07 00 DD 07 00 E6 00 02 07 00 E6 07 00 E6 FF 00 01 00 05 07 00 03 07 00 92 07 00 9F 07 00 DD 07 00 E6 00 05 07 01 A8 07 00 DD 08 09 B7 08 09 B7 07 01 13 FF 00 01 00 05 07 00 03 07 00 92 07 00 9F 07 00 DD 07 00 E6 00 02 07 00 E6 07 00 E6 FF 00 01 00 03 07 00 03 07 00 92 07 00 9F 00 01 07 00 C5 FF 00 01 00 05 07 00 03 07 00 92 07 00 9F 07 00 DD 07 00 E6 00 01 07 00 E6 FF 00 01 00 02 07 00 03 07 00 92 00 01 07 00 1E 43 05 44 07 00 1E 47 05 47 07 00 1E
        //    Exceptions:
        //  Try           Handler
        //  Start  End    Start  End    Type                                       
        //  -----  -----  -----  -----  -------------------------------------------
        //  8      20     2795   2803   Ljava/lang/AssertionError;
        //  2795   2803   2795   2803   Ljava/lang/IllegalArgumentException;
        //  2811   2813   3      8      Any
        //  29     35     35     36     Any
        //  29     35     35     36     Any
        //  29     35     35     36     Ljava/util/NoSuchElementException;
        //  29     35     3      8      Ljava/util/NoSuchElementException;
        //  29     35     35     36     Ljava/lang/NullPointerException;
        //  47     54     54     55     Any
        //  47     54     47     48     Any
        //  47     54     54     55     Ljava/lang/IllegalStateException;
        //  48     54     47     48     Ljava/lang/IllegalArgumentException;
        //  48     54     47     48     Ljava/lang/StringIndexOutOfBoundsException;
        //  65     72     72     73     Any
        //  66     72     65     66     Any
        //  66     72     72     73     Ljava/lang/StringIndexOutOfBoundsException;
        //  66     72     65     66     Ljava/util/ConcurrentModificationException;
        //  66     72     72     73     Ljava/lang/AssertionError;
        //  211    218    218    219    Any
        //  211    218    3      8      Ljava/lang/AssertionError;
        //  212    218    211    212    Any
        //  212    218    211    212    Any
        //  211    218    211    212    Any
        //  315    322    322    323    Any
        //  316    322    322    323    Ljava/lang/IndexOutOfBoundsException;
        //  315    322    3      8      Any
        //  316    322    322    323    Ljava/lang/StringIndexOutOfBoundsException;
        //  315    322    315    316    Any
        //  379    386    386    387    Any
        //  380    386    379    380    Any
        //  380    386    386    387    Any
        //  380    386    379    380    Ljava/lang/AssertionError;
        //  380    386    3      8      Ljava/lang/NumberFormatException;
        //  393    400    400    401    Any
        //  393    400    400    401    Any
        //  393    400    400    401    Ljava/lang/RuntimeException;
        //  394    400    400    401    Ljava/lang/ClassCastException;
        //  394    400    393    394    Ljava/lang/NumberFormatException;
        //  419    426    426    427    Any
        //  420    426    419    420    Ljava/lang/AssertionError;
        //  420    426    426    427    Any
        //  419    426    419    420    Ljava/lang/RuntimeException;
        //  419    426    426    427    Any
        //  476    483    483    484    Any
        //  477    483    3      8      Ljava/lang/NegativeArraySizeException;
        //  477    483    483    484    Ljava/lang/IllegalArgumentException;
        //  477    483    476    477    Ljava/lang/NullPointerException;
        //  477    483    483    484    Ljava/lang/ArithmeticException;
        //  487    496    496    497    Any
        //  488    496    496    497    Ljava/lang/IllegalStateException;
        //  488    496    487    488    Ljava/lang/NegativeArraySizeException;
        //  487    496    3      8      Ljava/util/ConcurrentModificationException;
        //  487    496    487    488    Ljava/lang/IllegalStateException;
        //  547    554    554    555    Any
        //  548    554    3      8      Ljava/lang/ArithmeticException;
        //  547    554    554    555    Ljava/lang/ArrayIndexOutOfBoundsException;
        //  548    554    547    548    Any
        //  548    554    554    555    Any
        //  603    610    610    611    Any
        //  604    610    603    604    Ljava/lang/IllegalArgumentException;
        //  603    610    3      8      Ljava/lang/AssertionError;
        //  603    610    603    604    Ljava/lang/StringIndexOutOfBoundsException;
        //  603    610    603    604    Ljava/lang/EnumConstantNotPresentException;
        //  614    621    621    622    Any
        //  615    621    621    622    Ljava/lang/AssertionError;
        //  615    621    614    615    Ljava/lang/UnsupportedOperationException;
        //  615    621    621    622    Ljava/lang/EnumConstantNotPresentException;
        //  614    621    3      8      Any
        //  661    668    668    669    Any
        //  662    668    661    662    Ljava/lang/AssertionError;
        //  661    668    661    662    Any
        //  662    668    661    662    Any
        //  661    668    3      8      Ljava/util/NoSuchElementException;
        //  674    681    681    682    Any
        //  674    681    674    675    Any
        //  674    681    681    682    Ljava/lang/StringIndexOutOfBoundsException;
        //  674    681    681    682    Any
        //  675    681    674    675    Any
        //  727    734    734    735    Any
        //  727    734    3      8      Ljava/lang/IllegalStateException;
        //  728    734    734    735    Ljava/lang/ArithmeticException;
        //  727    734    727    728    Ljava/util/NoSuchElementException;
        //  728    734    727    728    Any
        //  777    784    784    785    Any
        //  777    784    784    785    Ljava/lang/IllegalStateException;
        //  778    784    777    778    Ljava/lang/NumberFormatException;
        //  777    784    784    785    Ljava/lang/IllegalStateException;
        //  778    784    777    778    Ljava/lang/RuntimeException;
        //  835    842    842    843    Any
        //  835    842    835    836    Any
        //  835    842    835    836    Ljava/lang/AssertionError;
        //  836    842    842    843    Any
        //  835    842    835    836    Ljava/lang/NumberFormatException;
        //  953    960    960    961    Any
        //  954    960    953    954    Ljava/lang/ClassCastException;
        //  954    960    960    961    Ljava/lang/ArithmeticException;
        //  953    960    3      8      Ljava/lang/AssertionError;
        //  953    960    3      8      Any
        //  967    974    974    975    Any
        //  968    974    967    968    Ljava/util/ConcurrentModificationException;
        //  967    974    967    968    Any
        //  967    974    974    975    Any
        //  968    974    974    975    Any
        //  1023   1030   1030   1031   Any
        //  1024   1030   3      8      Ljava/lang/ArrayIndexOutOfBoundsException;
        //  1024   1030   1030   1031   Any
        //  1023   1030   1030   1031   Any
        //  1024   1030   1023   1024   Ljava/lang/EnumConstantNotPresentException;
        //  1042   1048   1048   1049   Any
        //  1042   1048   3      8      Ljava/lang/IllegalStateException;
        //  1042   1048   3      8      Any
        //  1042   1048   3      8      Ljava/util/NoSuchElementException;
        //  1042   1048   1048   1049   Any
        //  1052   1059   1059   1060   Any
        //  1052   1059   1052   1053   Any
        //  1052   1059   1052   1053   Ljava/lang/ArithmeticException;
        //  1053   1059   1059   1060   Ljava/lang/EnumConstantNotPresentException;
        //  1052   1059   1059   1060   Ljava/lang/NegativeArraySizeException;
        //  1107   1114   1114   1115   Any
        //  1108   1114   1107   1108   Any
        //  1108   1114   3      8      Any
        //  1107   1114   1107   1108   Any
        //  1107   1114   1114   1115   Ljava/lang/NullPointerException;
        //  1122   1129   1129   1130   Any
        //  1122   1129   1122   1123   Any
        //  1123   1129   1122   1123   Ljava/lang/ArithmeticException;
        //  1123   1129   1129   1130   Any
        //  1122   1129   3      8      Any
        //  1227   1234   1234   1235   Any
        //  1228   1234   1234   1235   Ljava/lang/EnumConstantNotPresentException;
        //  1228   1234   1227   1228   Any
        //  1227   1234   3      8      Ljava/lang/ArithmeticException;
        //  1228   1234   1227   1228   Any
        //  1238   1245   1245   1246   Any
        //  1239   1245   3      8      Any
        //  1238   1245   1238   1239   Any
        //  1239   1245   1245   1246   Ljava/lang/AssertionError;
        //  1239   1245   1238   1239   Ljava/lang/UnsupportedOperationException;
        //  1348   1354   1354   1355   Any
        //  1348   1354   3      8      Ljava/lang/ArrayIndexOutOfBoundsException;
        //  1348   1354   1354   1355   Any
        //  1348   1354   1354   1355   Ljava/lang/IllegalArgumentException;
        //  1348   1354   3      8      Ljava/lang/IllegalStateException;
        //  1403   1410   1410   1411   Any
        //  1404   1410   1403   1404   Ljava/util/NoSuchElementException;
        //  1403   1410   3      8      Ljava/lang/ClassCastException;
        //  1403   1410   1410   1411   Ljava/lang/RuntimeException;
        //  1403   1410   1410   1411   Ljava/lang/NegativeArraySizeException;
        //  1417   1424   1424   1425   Any
        //  1417   1424   1424   1425   Any
        //  1417   1424   3      8      Any
        //  1418   1424   1417   1418   Any
        //  1418   1424   1417   1418   Any
        //  1428   1435   1435   1436   Any
        //  1429   1435   1428   1429   Any
        //  1429   1435   1428   1429   Ljava/lang/ArithmeticException;
        //  1429   1435   1435   1436   Any
        //  1428   1435   3      8      Ljava/lang/StringIndexOutOfBoundsException;
        //  1483   1490   1490   1491   Any
        //  1484   1490   3      8      Ljava/lang/EnumConstantNotPresentException;
        //  1483   1490   1483   1484   Ljava/lang/IllegalStateException;
        //  1484   1490   1483   1484   Any
        //  1483   1490   1483   1484   Ljava/lang/ArrayIndexOutOfBoundsException;
        //  1501   1508   1508   1509   Any
        //  1502   1508   1501   1502   Ljava/lang/RuntimeException;
        //  1501   1508   1501   1502   Any
        //  1501   1508   1501   1502   Any
        //  1502   1508   1501   1502   Any
        //  1564   1571   1571   1572   Any
        //  1565   1571   1564   1565   Ljava/lang/UnsupportedOperationException;
        //  1564   1571   3      8      Any
        //  1564   1571   1571   1572   Ljava/lang/UnsupportedOperationException;
        //  1565   1571   3      8      Any
        //  1624   1631   1631   1632   Any
        //  1624   1631   1624   1625   Any
        //  1624   1631   1624   1625   Any
        //  1624   1631   1624   1625   Any
        //  1624   1631   1631   1632   Any
        //  1731   1738   1738   1739   Any
        //  1732   1738   3      8      Any
        //  1732   1738   1731   1732   Any
        //  1731   1738   1731   1732   Any
        //  1732   1738   3      8      Any
        //  1742   1749   1749   1750   Any
        //  1743   1749   1749   1750   Ljava/lang/StringIndexOutOfBoundsException;
        //  1742   1749   3      8      Ljava/lang/RuntimeException;
        //  1742   1749   1742   1743   Ljava/lang/RuntimeException;
        //  1743   1749   1742   1743   Any
        //  1757   1763   1763   1764   Any
        //  1757   1763   1763   1764   Ljava/lang/NullPointerException;
        //  1757   1763   3      8      Any
        //  1757   1763   3      8      Ljava/lang/ClassCastException;
        //  1757   1763   3      8      Any
        //  1772   1779   1779   1780   Any
        //  1773   1779   1779   1780   Any
        //  1772   1779   1772   1773   Ljava/lang/StringIndexOutOfBoundsException;
        //  1773   1779   1779   1780   Ljava/util/NoSuchElementException;
        //  1772   1779   3      8      Ljava/lang/ArithmeticException;
        //  1783   1790   1790   1791   Any
        //  1784   1790   1783   1784   Any
        //  1784   1790   1790   1791   Any
        //  1784   1790   3      8      Ljava/lang/NegativeArraySizeException;
        //  1784   1790   1790   1791   Ljava/util/NoSuchElementException;
        //  1839   1846   1846   1847   Any
        //  1839   1846   1839   1840   Ljava/lang/RuntimeException;
        //  1839   1846   1839   1840   Ljava/lang/ArrayIndexOutOfBoundsException;
        //  1840   1846   3      8      Any
        //  1840   1846   3      8      Ljava/lang/RuntimeException;
        //  1851   1857   1857   1858   Any
        //  1851   1857   1857   1858   Any
        //  1851   1857   1857   1858   Ljava/lang/ClassCastException;
        //  1851   1857   1857   1858   Ljava/lang/ArithmeticException;
        //  1851   1857   3      8      Any
        //  1868   1875   1875   1876   Any
        //  1868   1875   1868   1869   Any
        //  1868   1875   1868   1869   Any
        //  1869   1875   1868   1869   Ljava/lang/AssertionError;
        //  1869   1875   1868   1869   Ljava/lang/RuntimeException;
        //  1974   1981   1981   1982   Any
        //  1974   1981   3      8      Ljava/lang/ArrayIndexOutOfBoundsException;
        //  1975   1981   1974   1975   Any
        //  1974   1981   1981   1982   Ljava/lang/IllegalArgumentException;
        //  1974   1981   3      8      Any
        //  2032   2038   2038   2039   Any
        //  2032   2038   2038   2039   Ljava/lang/IllegalArgumentException;
        //  2032   2038   3      8      Any
        //  2032   2038   2038   2039   Ljava/lang/UnsupportedOperationException;
        //  2032   2038   3      8      Any
        //  2046   2052   2052   2053   Any
        //  2046   2052   3      8      Any
        //  2046   2052   2052   2053   Ljava/lang/ArrayIndexOutOfBoundsException;
        //  2046   2052   2052   2053   Any
        //  2046   2052   2052   2053   Ljava/util/ConcurrentModificationException;
        //  2059   2066   2066   2067   Any
        //  2059   2066   3      8      Ljava/lang/IllegalArgumentException;
        //  2059   2066   3      8      Ljava/lang/IllegalStateException;
        //  2059   2066   2059   2060   Ljava/lang/ClassCastException;
        //  2060   2066   2066   2067   Ljava/lang/UnsupportedOperationException;
        //  2116   2122   2122   2123   Any
        //  2116   2122   3      8      Ljava/lang/IllegalStateException;
        //  2116   2122   3      8      Any
        //  2116   2122   2122   2123   Any
        //  2116   2122   3      8      Ljava/lang/NegativeArraySizeException;
        //  2126   2133   2133   2134   Any
        //  2126   2133   3      8      Ljava/lang/ArrayIndexOutOfBoundsException;
        //  2126   2133   2126   2127   Ljava/lang/ArithmeticException;
        //  2127   2133   2133   2134   Ljava/lang/NegativeArraySizeException;
        //  2126   2133   2126   2127   Ljava/lang/RuntimeException;
        //  2187   2194   2194   2195   Any
        //  2187   2194   2187   2188   Any
        //  2187   2194   2187   2188   Ljava/lang/StringIndexOutOfBoundsException;
        //  2187   2194   2194   2195   Any
        //  2187   2194   3      8      Ljava/lang/NullPointerException;
        //  2243   2250   2250   2251   Any
        //  2243   2250   2243   2244   Any
        //  2243   2250   3      8      Any
        //  2243   2250   3      8      Ljava/lang/AssertionError;
        //  2243   2250   2250   2251   Any
        //  2403   2410   2410   2411   Any
        //  2403   2410   2403   2404   Ljava/lang/ArrayIndexOutOfBoundsException;
        //  2404   2410   2410   2411   Any
        //  2404   2410   2410   2411   Any
        //  2404   2410   2403   2404   Ljava/lang/NumberFormatException;
        //  2424   2431   2431   2432   Any
        //  2424   2431   2424   2425   Ljava/lang/IllegalStateException;
        //  2425   2431   3      8      Ljava/lang/NullPointerException;
        //  2424   2431   2424   2425   Any
        //  2424   2431   3      8      Ljava/lang/ClassCastException;
        //  2436   2443   2443   2444   Any
        //  2437   2443   2443   2444   Ljava/lang/IllegalStateException;
        //  2437   2443   3      8      Ljava/lang/StringIndexOutOfBoundsException;
        //  2436   2443   2436   2437   Any
        //  2437   2443   2436   2437   Ljava/lang/EnumConstantNotPresentException;
        //  2450   2457   2457   2458   Any
        //  2451   2457   3      8      Ljava/lang/ArrayIndexOutOfBoundsException;
        //  2450   2457   3      8      Ljava/util/NoSuchElementException;
        //  2450   2457   2457   2458   Ljava/lang/NumberFormatException;
        //  2450   2457   2450   2451   Ljava/lang/ArrayIndexOutOfBoundsException;
        //  2467   2474   2474   2475   Any
        //  2468   2474   2474   2475   Ljava/lang/EnumConstantNotPresentException;
        //  2468   2474   2467   2468   Ljava/lang/EnumConstantNotPresentException;
        //  2468   2474   3      8      Any
        //  2468   2474   2474   2475   Any
        //  2480   2486   2486   2487   Any
        //  2480   2486   3      8      Any
        //  2480   2486   3      8      Ljava/lang/ArithmeticException;
        //  2480   2486   2486   2487   Any
        //  2480   2486   3      8      Any
        //  2498   2505   2505   2506   Any
        //  2498   2505   2505   2506   Any
        //  2498   2505   2498   2499   Any
        //  2498   2505   3      8      Any
        //  2499   2505   2505   2506   Ljava/lang/IllegalStateException;
        //  2557   2564   2564   2565   Any
        //  2558   2564   2557   2558   Any
        //  2558   2564   3      8      Any
        //  2558   2564   2564   2565   Any
        //  2557   2564   2564   2565   Any
        //  2615   2622   2622   2623   Any
        //  2615   2622   2622   2623   Any
        //  2616   2622   3      8      Ljava/util/ConcurrentModificationException;
        //  2616   2622   2615   2616   Ljava/util/NoSuchElementException;
        //  2615   2622   2622   2623   Any
        //  2626   2633   2633   2634   Any
        //  2626   2633   2626   2627   Ljava/lang/NegativeArraySizeException;
        //  2627   2633   2633   2634   Any
        //  2627   2633   2633   2634   Any
        //  2626   2633   2633   2634   Ljava/util/NoSuchElementException;
        //  2683   2690   2690   2691   Any
        //  2684   2690   2683   2684   Ljava/lang/NegativeArraySizeException;
        //  2683   2690   2683   2684   Any
        //  2684   2690   2690   2691   Any
        //  2683   2690   2683   2684   Ljava/lang/NumberFormatException;
        //  2694   2703   2703   2704   Any
        //  2694   2703   2703   2704   Ljava/lang/ArrayIndexOutOfBoundsException;
        //  2694   2703   3      8      Any
        //  2694   2703   2694   2695   Ljava/lang/NegativeArraySizeException;
        //  2694   2703   2703   2704   Ljava/lang/EnumConstantNotPresentException;
        //  2707   2714   2714   2715   Any
        //  2708   2714   2714   2715   Ljava/lang/NullPointerException;
        //  2707   2714   2707   2708   Any
        //  2707   2714   3      8      Ljava/lang/StringIndexOutOfBoundsException;
        //  2708   2714   2714   2715   Ljava/lang/AssertionError;
        // 
        // The error that occurred was:
        // 
        // java.lang.IndexOutOfBoundsException: Index -1 out of bounds for length 0
        //     at java.base/jdk.internal.util.Preconditions.outOfBounds(Preconditions.java:64)
        //     at java.base/jdk.internal.util.Preconditions.outOfBoundsCheckIndex(Preconditions.java:70)
        //     at java.base/jdk.internal.util.Preconditions.checkIndex(Preconditions.java:248)
        //     at java.base/java.util.Objects.checkIndex(Objects.java:372)
        //     at java.base/java.util.ArrayList.remove(ArrayList.java:535)
        //     at com.strobel.assembler.ir.StackMappingVisitor.pop(StackMappingVisitor.java:267)
        //     at com.strobel.assembler.ir.StackMappingVisitor$InstructionAnalyzer.execute(StackMappingVisitor.java:667)
        //     at com.strobel.assembler.ir.StackMappingVisitor$InstructionAnalyzer.visit(StackMappingVisitor.java:398)
        //     at com.strobel.decompiler.ast.AstBuilder.performStackAnalysis(AstBuilder.java:2030)
        //     at com.strobel.decompiler.ast.AstBuilder.build(AstBuilder.java:108)
        //     at com.strobel.decompiler.languages.java.ast.AstMethodBodyBuilder.createMethodBody(AstMethodBodyBuilder.java:211)
        //     at com.strobel.decompiler.languages.java.ast.AstMethodBodyBuilder.createMethodBody(AstMethodBodyBuilder.java:99)
        //     at com.strobel.decompiler.languages.java.ast.AstBuilder.createMethodBody(AstBuilder.java:782)
        //     at com.strobel.decompiler.languages.java.ast.AstBuilder.createMethod(AstBuilder.java:675)
        //     at com.strobel.decompiler.languages.java.ast.AstBuilder.addTypeMembers(AstBuilder.java:552)
        //     at com.strobel.decompiler.languages.java.ast.AstBuilder.createTypeCore(AstBuilder.java:519)
        //     at com.strobel.decompiler.languages.java.ast.AstBuilder.createTypeNoCache(AstBuilder.java:161)
        //     at com.strobel.decompiler.languages.java.ast.AstBuilder.createType(AstBuilder.java:150)
        //     at com.strobel.decompiler.languages.java.ast.AstBuilder.addType(AstBuilder.java:125)
        //     at com.strobel.decompiler.languages.java.JavaLanguage.buildAst(JavaLanguage.java:71)
        //     at com.strobel.decompiler.languages.java.JavaLanguage.decompileType(JavaLanguage.java:59)
        //     at com.strobel.decompiler.DecompilerDriver.decompileType(DecompilerDriver.java:330)
        //     at com.strobel.decompiler.DecompilerDriver.decompileJar(DecompilerDriver.java:251)
        //     at com.strobel.decompiler.DecompilerDriver.main(DecompilerDriver.java:126)
        // 
        throw new IllegalStateException("An error occurred while decompiling this method.");
    }
    
    public f6l() {
        // 
        // This method could not be decompiled.
        // 
        // Original Bytecode:
        // 
        //     1: ldc_w           "\u2236\u1496\u8b31\ub3cd\uc99e\uec20\ub227\ue700\ud969\ue9fc"
        //     4: invokestatic    invokestatic   !!! ERROR
        //     7: ldc_w           "\u2216\u1496\u8b31\ub3cd\uc99e\uec20\ub207\ue700\ud969\ue9fc"
        //    10: invokestatic    invokestatic   !!! ERROR
        //    13: ldc_w           "\u2219\u1492\u8b2e\ub3dc\uc988\uec72\ub227\ue700\ud969\ue9fc\ua6b2\u1e41\ue023\uc5b5\u816a\u88e9\u57a7\u76d8\ubd2e\uc040\u2ac9\uc236\u6bcc\u2d4c\ud78b\u3453\u7d27\u8863\u805f"
        //    16: invokestatic    invokestatic   !!! ERROR
        //    19: iconst_1       
        //    20: invokespecial   dev/nuker/pyro/fH.<init>:(Ljava/lang/String;Ljava/lang/String;Ljava/lang/String;Z)V
        //    23: aload_0        
        //    24: new             Ldev/nuker/pyro/f0a;
        //    27: dup            
        //    28: ldc_w           "\u2224\u1481\u8b20\ub3df\uc992\uec2a"
        //    31: invokestatic    invokestatic   !!! ERROR
        //    34: ldc_w           "\u2204\u1481\u8b20\ub3df\uc992\uec2a"
        //    37: invokestatic    invokestatic   !!! ERROR
        //    40: aconst_null    
        //    41: iconst_1       
        //    42: invokespecial   dev/nuker/pyro/f0a.<init>:(Ljava/lang/String;Ljava/lang/String;Ljava/lang/String;Z)V
        //    45: putfield        dev/nuker/pyro/f6l.c:Ldev/nuker/pyro/f0a;
        //    48: getstatic       dev/nuker/pyro/fc.0:I
        //    51: ifeq            60
        //    54: ldc_w           1152217339
        //    57: goto            63
        //    60: ldc_w           894685188
        //    63: ldc_w           -8266887
        //    66: ixor           
        //    67: lookupswitch {
        //          -1154700414: 585
        //          -747602919: 60
        //          default: 92
        //        }
        //    92: aload_0        
        //    93: new             Ldev/nuker/pyro/f0f;
        //    96: dup            
        //    97: ldc_w           "\u2227\u1496\u8b29\ub3df"
        //   100: invokestatic    invokestatic   !!! ERROR
        //   103: ldc_w           "\u2207\u1496\u8b29\ub3df"
        //   106: invokestatic    invokestatic   !!! ERROR
        //   109: aconst_null    
        //   110: getstatic       dev/nuker/pyro/f6k.2:Ldev/nuker/pyro/f6k;
        //   113: getstatic       dev/nuker/pyro/fc.0:I
        //   116: ifeq            125
        //   119: ldc_w           1276626048
        //   122: goto            128
        //   125: ldc_w           -1575827590
        //   128: ldc_w           573973820
        //   131: ixor           
        //   132: lookupswitch {
        //          -2145066426: 160
        //          1847714236: 125
        //          default: 573
        //        }
        //   160: invokespecial   dev/nuker/pyro/f0f.<init>:(Ljava/lang/String;Ljava/lang/String;Ljava/lang/String;Ljava/lang/Enum;)V
        //   163: putfield        dev/nuker/pyro/f6l.c:Ldev/nuker/pyro/f0f;
        //   166: aload_0        
        //   167: new             Ldev/nuker/pyro/f0f;
        //   170: dup            
        //   171: ldc_w           "\u2224\u149f\u8b24\ub3c0\uc99e\uec20\ub237"
        //   174: invokestatic    invokestatic   !!! ERROR
        //   177: ldc_w           "\u2204\u149f\u8b24\ub3c0\uc99e\uec20\ub237"
        //   180: getstatic       dev/nuker/pyro/fc.0:I
        //   183: ifeq            192
        //   186: ldc_w           597574915
        //   189: goto            195
        //   192: ldc_w           504670372
        //   195: ldc_w           -1249582309
        //   198: ixor           
        //   199: lookupswitch {
        //          -1776638440: 192
        //          -1416606785: 224
        //          default: 577
        //        }
        //   224: invokestatic    invokestatic   !!! ERROR
        //   227: aconst_null    
        //   228: getstatic       dev/nuker/pyro/f6k.0:Ldev/nuker/pyro/f6k;
        //   231: invokespecial   dev/nuker/pyro/f0f.<init>:(Ljava/lang/String;Ljava/lang/String;Ljava/lang/String;Ljava/lang/Enum;)V
        //   234: putfield        dev/nuker/pyro/f6l.0:Ldev/nuker/pyro/f0f;
        //   237: aload_0        
        //   238: new             Ldev/nuker/pyro/f0f;
        //   241: dup            
        //   242: ldc_w           "\u2236\u1481\u8b24\ub3da\uc990\uec37\ub230\ue71b"
        //   245: invokestatic    invokestatic   !!! ERROR
        //   248: ldc_w           "\u2216\u1481\u8b24\ub3da\uc990\uec37\ub230\ue71b"
        //   251: invokestatic    invokestatic   !!! ERROR
        //   254: aconst_null    
        //   255: getstatic       dev/nuker/pyro/f6k.1:Ldev/nuker/pyro/f6k;
        //   258: getstatic       dev/nuker/pyro/fc.0:I
        //   261: ifeq            270
        //   264: ldc_w           -260246536
        //   267: goto            273
        //   270: ldc_w           -1989107083
        //   273: ldc_w           1653661719
        //   276: ixor           
        //   277: lookupswitch {
        //          -1830022161: 575
        //          -578101461: 270
        //          default: 304
        //        }
        //   304: invokespecial   dev/nuker/pyro/f0f.<init>:(Ljava/lang/String;Ljava/lang/String;Ljava/lang/String;Ljava/lang/Enum;)V
        //   307: putfield        dev/nuker/pyro/f6l.1:Ldev/nuker/pyro/f0f;
        //   310: getstatic       dev/nuker/pyro/fc.0:I
        //   313: ifeq            322
        //   316: ldc_w           1769394400
        //   319: goto            325
        //   322: ldc_w           -603328335
        //   325: ldc_w           1567635335
        //   328: ixor           
        //   329: lookupswitch {
        //          872867687: 579
        //          1492530584: 322
        //          default: 356
        //        }
        //   356: aload_0        
        //   357: getstatic       dev/nuker/pyro/fc.1:I
        //   360: ifeq            369
        //   363: ldc_w           1001308788
        //   366: goto            372
        //   369: ldc_w           -900840105
        //   372: ldc_w           -1849130284
        //   375: ixor           
        //   376: lookupswitch {
        //          -1436139360: 369
        //          1535559555: 404
        //          default: 589
        //        }
        //   404: aload_0        
        //   405: getfield        dev/nuker/pyro/f6l.c:Ldev/nuker/pyro/f0a;
        //   408: invokevirtual   dev/nuker/pyro/f6l.c:(Ldev/nuker/pyro/f0n;)Ldev/nuker/pyro/f0n;
        //   411: pop            
        //   412: aload_0        
        //   413: aload_0        
        //   414: getfield        dev/nuker/pyro/f6l.c:Ldev/nuker/pyro/f0f;
        //   417: invokevirtual   dev/nuker/pyro/f6l.c:(Ldev/nuker/pyro/f0n;)Ldev/nuker/pyro/f0n;
        //   420: pop            
        //   421: aload_0        
        //   422: aload_0        
        //   423: getstatic       dev/nuker/pyro/fc.1:I
        //   426: ifeq            435
        //   429: ldc_w           -1101055829
        //   432: goto            438
        //   435: ldc_w           -1403828305
        //   438: ldc_w           250292366
        //   441: ixor           
        //   442: lookupswitch {
        //          -1579264107: 435
        //          -1330376667: 581
        //          default: 468
        //        }
        //   468: getfield        dev/nuker/pyro/f6l.0:Ldev/nuker/pyro/f0f;
        //   471: invokevirtual   dev/nuker/pyro/f6l.c:(Ldev/nuker/pyro/f0n;)Ldev/nuker/pyro/f0n;
        //   474: pop            
        //   475: aload_0        
        //   476: getstatic       dev/nuker/pyro/fc.1:I
        //   479: ifeq            488
        //   482: ldc_w           -1857074442
        //   485: goto            491
        //   488: ldc_w           620143611
        //   491: ldc_w           -1080568771
        //   494: ixor           
        //   495: lookupswitch {
        //          785948363: 587
        //          1916290493: 488
        //          default: 520
        //        }
        //   520: aload_0        
        //   521: getfield        dev/nuker/pyro/f6l.1:Ldev/nuker/pyro/f0f;
        //   524: getstatic       dev/nuker/pyro/fc.1:I
        //   527: ifeq            536
        //   530: ldc_w           73938103
        //   533: goto            539
        //   536: ldc_w           2117226437
        //   539: ldc_w           -1038776776
        //   542: ixor           
        //   543: lookupswitch {
        //          -964840817: 583
        //          34537173: 536
        //          default: 568
        //        }
        //   568: invokevirtual   dev/nuker/pyro/f6l.c:(Ldev/nuker/pyro/f0n;)Ldev/nuker/pyro/f0n;
        //   571: pop            
        //   572: return         
        //   573: aconst_null    
        //   574: athrow         
        //   575: aconst_null    
        //   576: athrow         
        //   577: aconst_null    
        //   578: athrow         
        //   579: aconst_null    
        //   580: athrow         
        //   581: aconst_null    
        //   582: athrow         
        //   583: aconst_null    
        //   584: athrow         
        //   585: aconst_null    
        //   586: athrow         
        //   587: aconst_null    
        //   588: athrow         
        //   589: aconst_null    
        //   590: athrow         
        //    StackMapTable: 00 24 FF 00 3C 00 01 07 00 03 00 00 42 01 1C FF 00 20 00 01 07 00 03 00 07 07 00 03 08 00 5D 08 00 5D 07 00 E6 07 00 E6 05 07 00 30 FF 00 02 00 01 07 00 03 00 08 07 00 03 08 00 5D 08 00 5D 07 00 E6 07 00 E6 05 07 00 30 01 FF 00 1F 00 01 07 00 03 00 07 07 00 03 08 00 5D 08 00 5D 07 00 E6 07 00 E6 05 07 00 30 FF 00 1F 00 01 07 00 03 00 05 07 00 03 08 00 A7 08 00 A7 07 00 E6 07 00 E6 FF 00 02 00 01 07 00 03 00 06 07 00 03 08 00 A7 08 00 A7 07 00 E6 07 00 E6 01 FF 00 1C 00 01 07 00 03 00 05 07 00 03 08 00 A7 08 00 A7 07 00 E6 07 00 E6 FF 00 2D 00 01 07 00 03 00 07 07 00 03 08 00 EE 08 00 EE 07 00 E6 07 00 E6 05 07 00 30 FF 00 02 00 01 07 00 03 00 08 07 00 03 08 00 EE 08 00 EE 07 00 E6 07 00 E6 05 07 00 30 01 FF 00 1E 00 01 07 00 03 00 07 07 00 03 08 00 EE 08 00 EE 07 00 E6 07 00 E6 05 07 00 30 11 42 01 1E 4C 07 00 03 FF 00 02 00 01 07 00 03 00 02 07 00 03 01 5F 07 00 03 FF 00 1E 00 01 07 00 03 00 02 07 00 03 07 00 03 FF 00 02 00 01 07 00 03 00 03 07 00 03 07 00 03 01 FF 00 1D 00 01 07 00 03 00 02 07 00 03 07 00 03 53 07 00 03 FF 00 02 00 01 07 00 03 00 02 07 00 03 01 5C 07 00 03 FF 00 0F 00 01 07 00 03 00 02 07 00 03 07 00 2A FF 00 02 00 01 07 00 03 00 03 07 00 03 07 00 2A 01 FF 00 1C 00 01 07 00 03 00 02 07 00 03 07 00 2A FF 00 04 00 01 07 00 03 00 07 07 00 03 08 00 5D 08 00 5D 07 00 E6 07 00 E6 05 07 00 30 FF 00 01 00 01 07 00 03 00 07 07 00 03 08 00 EE 08 00 EE 07 00 E6 07 00 E6 05 07 00 30 FF 00 01 00 01 07 00 03 00 05 07 00 03 08 00 A7 08 00 A7 07 00 E6 07 00 E6 01 FF 00 01 00 01 07 00 03 00 02 07 00 03 07 00 03 FF 00 01 00 01 07 00 03 00 02 07 00 03 07 00 2A 01 41 07 00 03 41 07 00 03
        // 
        // The error that occurred was:
        // 
        // java.lang.IllegalStateException: Invalid BootstrapMethods attribute entry: 21 additional arguments required for method a.a, but only 0 specified.
        //     at com.strobel.assembler.ir.Error.invalidBootstrapMethodEntry(Error.java:244)
        //     at com.strobel.assembler.ir.MetadataReader.readAttributeCore(MetadataReader.java:280)
        //     at com.strobel.assembler.metadata.ClassFileReader.readAttributeCore(ClassFileReader.java:261)
        //     at com.strobel.assembler.ir.MetadataReader.inflateAttributes(MetadataReader.java:439)
        //     at com.strobel.assembler.metadata.ClassFileReader.visitAttributes(ClassFileReader.java:1134)
        //     at com.strobel.assembler.metadata.ClassFileReader.readClass(ClassFileReader.java:439)
        //     at com.strobel.assembler.metadata.ClassFileReader.readClass(ClassFileReader.java:377)
        //     at com.strobel.assembler.metadata.MetadataSystem.resolveType(MetadataSystem.java:129)
        //     at com.strobel.decompiler.NoRetryMetadataSystem.resolveType(DecompilerDriver.java:476)
        //     at com.strobel.assembler.metadata.MetadataSystem.resolveCore(MetadataSystem.java:81)
        //     at com.strobel.assembler.metadata.MetadataResolver.resolve(MetadataResolver.java:104)
        //     at com.strobel.assembler.metadata.CoreMetadataFactory$UnresolvedType.resolve(CoreMetadataFactory.java:616)
        //     at com.strobel.assembler.metadata.MetadataResolver.resolve(MetadataResolver.java:128)
        //     at com.strobel.assembler.metadata.CoreMetadataFactory$UnresolvedType.resolve(CoreMetadataFactory.java:626)
        //     at com.strobel.assembler.metadata.MethodReference.resolve(MethodReference.java:177)
        //     at com.strobel.decompiler.ast.TypeAnalysis.inferCall(TypeAnalysis.java:2438)
        //     at com.strobel.decompiler.ast.TypeAnalysis.doInferTypeForExpression(TypeAnalysis.java:1029)
        //     at com.strobel.decompiler.ast.TypeAnalysis.inferTypeForExpression(TypeAnalysis.java:803)
        //     at com.strobel.decompiler.ast.TypeAnalysis.inferCall(TypeAnalysis.java:2695)
        //     at com.strobel.decompiler.ast.TypeAnalysis.doInferTypeForExpression(TypeAnalysis.java:1029)
        //     at com.strobel.decompiler.ast.TypeAnalysis.inferTypeForExpression(TypeAnalysis.java:803)
        //     at com.strobel.decompiler.ast.TypeAnalysis.runInference(TypeAnalysis.java:672)
        //     at com.strobel.decompiler.ast.TypeAnalysis.runInference(TypeAnalysis.java:655)
        //     at com.strobel.decompiler.ast.TypeAnalysis.runInference(TypeAnalysis.java:365)
        //     at com.strobel.decompiler.ast.TypeAnalysis.run(TypeAnalysis.java:96)
        //     at com.strobel.decompiler.ast.AstOptimizer.optimize(AstOptimizer.java:109)
        //     at com.strobel.decompiler.ast.AstOptimizer.optimize(AstOptimizer.java:42)
        //     at com.strobel.decompiler.languages.java.ast.AstMethodBodyBuilder.createMethodBody(AstMethodBodyBuilder.java:214)
        //     at com.strobel.decompiler.languages.java.ast.AstMethodBodyBuilder.createMethodBody(AstMethodBodyBuilder.java:99)
        //     at com.strobel.decompiler.languages.java.ast.AstBuilder.createMethodBody(AstBuilder.java:782)
        //     at com.strobel.decompiler.languages.java.ast.AstBuilder.createConstructor(AstBuilder.java:713)
        //     at com.strobel.decompiler.languages.java.ast.AstBuilder.addTypeMembers(AstBuilder.java:549)
        //     at com.strobel.decompiler.languages.java.ast.AstBuilder.createTypeCore(AstBuilder.java:519)
        //     at com.strobel.decompiler.languages.java.ast.AstBuilder.createTypeNoCache(AstBuilder.java:161)
        //     at com.strobel.decompiler.languages.java.ast.AstBuilder.createType(AstBuilder.java:150)
        //     at com.strobel.decompiler.languages.java.ast.AstBuilder.addType(AstBuilder.java:125)
        //     at com.strobel.decompiler.languages.java.JavaLanguage.buildAst(JavaLanguage.java:71)
        //     at com.strobel.decompiler.languages.java.JavaLanguage.decompileType(JavaLanguage.java:59)
        //     at com.strobel.decompiler.DecompilerDriver.decompileType(DecompilerDriver.java:330)
        //     at com.strobel.decompiler.DecompilerDriver.decompileJar(DecompilerDriver.java:251)
        //     at com.strobel.decompiler.DecompilerDriver.main(DecompilerDriver.java:126)
        // 
        throw new IllegalStateException("An error occurred while decompiling this method.");
    }
    
    static {
        final boolean c = !f6l.class.desiredAssertionStatus();
        while (true) {
            int n = 0;
            Label_0028: {
                if (fc.c < 0) {
                    n = -1340728950;
                    break Label_0028;
                }
                n = -1856707512;
            }
            switch (n ^ 0xDEEFE495) {
                case 444529464: {
                    continue;
                }
                default: {
                    f6l.c = c;
                }
                case 1861877023: {
                    throw null;
                }
            }
            break;
        }
    }
}
