// 
// Decompiled by Procyon v0.5.36
// 

package dev.nuker.pyro;

import dev.nuker.pyro.security.inject.LauncherEventHide;

public class f6m extends fH
{
    public f0a c;
    public f0a 0;
    public f0a 1;
    public f0a 2;
    public f0a 3;
    public f0a 4;
    public f0a 5;
    public f0a 6;
    
    @f06
    @LauncherEventHide
    public void c(final f2W p0) {
        // 
        // This method could not be decompiled.
        // 
        // Original Bytecode:
        // 
        //     3: dup            
        //     4: ifnull          2395
        //     7: athrow         
        //     8: aconst_null    
        //     9: getstatic       dev/nuker/pyro/fc.1:I
        //    12: ifgt            2387
        //    15: pop            
        //    16: aconst_null    
        //    17: goto            2379
        //    20: nop            
        //    21: nop            
        //    22: nop            
        //    23: athrow         
        //    24: aload_0        
        //    25: getfield        dev/nuker/pyro/f6m.c:Lnet/minecraft/client/Minecraft;
        //    28: getstatic       dev/nuker/pyro/fc.1:I
        //    31: ifeq            39
        //    34: ldc             -1150743982
        //    36: goto            41
        //    39: ldc             -160189958
        //    41: ldc             77117280
        //    43: ixor           
        //    44: lookupswitch {
        //          -1074676430: 39
        //          -219478374: 72
        //          default: 2360
        //        }
        //    72: getfield        net/minecraft/client/Minecraft.field_71439_g:Lnet/minecraft/client/entity/EntityPlayerSP;
        //    75: ifnull          170
        //    78: aload_0        
        //    79: getstatic       dev/nuker/pyro/fc.c:I
        //    82: ifge            90
        //    85: ldc             345273432
        //    87: goto            92
        //    90: ldc             1272100842
        //    92: ldc             -294231337
        //    94: ixor           
        //    95: lookupswitch {
        //          -438558528: 90
        //          -85846385: 2322
        //          default: 120
        //        }
        //   120: getfield        dev/nuker/pyro/f6m.c:Lnet/minecraft/client/Minecraft;
        //   123: getstatic       dev/nuker/pyro/fc.c:I
        //   126: ifge            134
        //   129: ldc             -170870825
        //   131: goto            136
        //   134: ldc             -1186084174
        //   136: ldc             -409743451
        //   138: ixor           
        //   139: lookupswitch {
        //          -837485233: 134
        //          306411634: 2358
        //          default: 164
        //        }
        //   164: getfield        net/minecraft/client/Minecraft.field_71456_v:Lnet/minecraft/client/gui/GuiIngame;
        //   167: ifnonnull       171
        //   170: return         
        //   171: aload_0        
        //   172: getfield        dev/nuker/pyro/f6m.c:Ldev/nuker/pyro/f0a;
        //   175: goto            179
        //   178: athrow         
        //   179: invokevirtual   dev/nuker/pyro/f0a.3:()Ljava/lang/Object;
        //   182: goto            186
        //   185: athrow         
        //   186: checkcast       Ljava/lang/Boolean;
        //   189: goto            193
        //   192: athrow         
        //   193: invokevirtual   java/lang/Boolean.booleanValue:()Z
        //   196: goto            200
        //   199: athrow         
        //   200: ifne            208
        //   203: ldc             -1295942625
        //   205: goto            210
        //   208: ldc             -1295942640
        //   210: ldc             70489624
        //   212: ixor           
        //   213: tableswitch {
        //          1843778574: 236
        //          1843778575: 365
        //          default: 203
        //        }
        //   236: aload_1        
        //   237: getstatic       dev/nuker/pyro/fc.0:I
        //   240: ifeq            248
        //   243: ldc             276745858
        //   245: goto            250
        //   248: ldc             1498495011
        //   250: ldc             -523632836
        //   252: ixor           
        //   253: lookupswitch {
        //          -256429634: 2330
        //          958686363: 248
        //          default: 280
        //        }
        //   280: goto            284
        //   283: athrow         
        //   284: invokevirtual   dev/nuker/pyro/f2W.c:()Ldev/nuker/pyro/fH;
        //   287: goto            291
        //   290: athrow         
        //   291: getfield        dev/nuker/pyro/fH.c:Ldev/nuker/pyro/fw;
        //   294: getstatic       dev/nuker/pyro/fc.0:I
        //   297: ifeq            305
        //   300: ldc             964618057
        //   302: goto            307
        //   305: ldc             604585007
        //   307: ldc             -638824415
        //   309: ixor           
        //   310: lookupswitch {
        //          -577336638: 305
        //          -527255704: 2332
        //          default: 336
        //        }
        //   336: goto            340
        //   339: athrow         
        //   340: invokevirtual   dev/nuker/pyro/fw.0:()Ljava/lang/Object;
        //   343: goto            347
        //   346: athrow         
        //   347: checkcast       Ljava/lang/Boolean;
        //   350: goto            354
        //   353: athrow         
        //   354: invokevirtual   java/lang/Boolean.booleanValue:()Z
        //   357: goto            361
        //   360: athrow         
        //   361: ifeq            365
        //   364: return         
        //   365: aload_0        
        //   366: getstatic       dev/nuker/pyro/fc.1:I
        //   369: ifeq            377
        //   372: ldc             -912663253
        //   374: goto            379
        //   377: ldc             1086884975
        //   379: ldc             1284769871
        //   381: ixor           
        //   382: lookupswitch {
        //          -2062690972: 2368
        //          -196776071: 377
        //          default: 408
        //        }
        //   408: getfield        dev/nuker/pyro/f6m.0:Ldev/nuker/pyro/f0a;
        //   411: goto            415
        //   414: athrow         
        //   415: invokevirtual   dev/nuker/pyro/f0a.3:()Ljava/lang/Object;
        //   418: goto            422
        //   421: athrow         
        //   422: checkcast       Ljava/lang/Boolean;
        //   425: goto            429
        //   428: athrow         
        //   429: invokevirtual   java/lang/Boolean.booleanValue:()Z
        //   432: goto            436
        //   435: athrow         
        //   436: ifne            527
        //   439: aload_1        
        //   440: goto            444
        //   443: athrow         
        //   444: invokevirtual   dev/nuker/pyro/f2W.c:()Ldev/nuker/pyro/fH;
        //   447: goto            451
        //   450: athrow         
        //   451: getfield        dev/nuker/pyro/fH.c:Ldev/nuker/pyro/fw;
        //   454: goto            458
        //   457: athrow         
        //   458: invokevirtual   dev/nuker/pyro/fw.0:()Ljava/lang/Object;
        //   461: goto            465
        //   464: athrow         
        //   465: checkcast       Ljava/lang/Boolean;
        //   468: getstatic       dev/nuker/pyro/fc.1:I
        //   471: ifeq            479
        //   474: ldc             1663622642
        //   476: goto            481
        //   479: ldc             -1289673270
        //   481: ldc             1381192290
        //   483: ixor           
        //   484: lookupswitch {
        //          830181264: 2338
        //          1053282513: 479
        //          default: 512
        //        }
        //   512: goto            516
        //   515: athrow         
        //   516: invokevirtual   java/lang/Boolean.booleanValue:()Z
        //   519: goto            523
        //   522: athrow         
        //   523: ifne            527
        //   526: return         
        //   527: aload_1        
        //   528: goto            532
        //   531: athrow         
        //   532: invokevirtual   dev/nuker/pyro/f2W.c:()Ldev/nuker/pyro/fH;
        //   535: goto            539
        //   538: athrow         
        //   539: goto            543
        //   542: athrow         
        //   543: invokevirtual   dev/nuker/pyro/fH.5:()Ljava/lang/String;
        //   546: goto            550
        //   549: athrow         
        //   550: ldc             "\u2216\u149c\u8b29\ub1ca\ucf88\uec27"
        //   552: getstatic       dev/nuker/pyro/fc.1:I
        //   555: ifeq            563
        //   558: ldc             -1845423796
        //   560: goto            565
        //   563: ldc             -1512278864
        //   565: ldc             1274638769
        //   567: ixor           
        //   568: lookupswitch {
        //          -638033667: 563
        //          -299563775: 596
        //          default: 2310
        //        }
        //   596: goto            600
        //   599: athrow         
        //   600: invokestatic    invokestatic   !!! ERROR
        //   603: goto            607
        //   606: athrow         
        //   607: goto            611
        //   610: athrow         
        //   611: invokevirtual   java/lang/String.equals:(Ljava/lang/Object;)Z
        //   614: goto            618
        //   617: athrow         
        //   618: ifeq            685
        //   621: aload_0        
        //   622: getfield        dev/nuker/pyro/f6m.1:Ldev/nuker/pyro/f0a;
        //   625: goto            629
        //   628: athrow         
        //   629: invokevirtual   dev/nuker/pyro/f0a.3:()Ljava/lang/Object;
        //   632: goto            636
        //   635: athrow         
        //   636: checkcast       Ljava/lang/Boolean;
        //   639: goto            643
        //   642: athrow         
        //   643: invokevirtual   java/lang/Boolean.booleanValue:()Z
        //   646: goto            650
        //   649: athrow         
        //   650: ifne            658
        //   653: ldc             1678994930
        //   655: goto            660
        //   658: ldc             1678994931
        //   660: ldc             -1210774520
        //   662: ixor           
        //   663: tableswitch {
        //          -1483947020: 684
        //          -1483947019: 685
        //          default: 653
        //        }
        //   684: return         
        //   685: aload_1        
        //   686: goto            690
        //   689: athrow         
        //   690: invokevirtual   dev/nuker/pyro/f2W.c:()Ldev/nuker/pyro/fH;
        //   693: goto            697
        //   696: athrow         
        //   697: goto            701
        //   700: athrow         
        //   701: invokevirtual   dev/nuker/pyro/fH.5:()Ljava/lang/String;
        //   704: goto            708
        //   707: athrow         
        //   708: ldc             "\u2210\u148b\u8b34\ub1c4\ucf86\uec3a\ub230"
        //   710: getstatic       dev/nuker/pyro/fc.c:I
        //   713: ifge            721
        //   716: ldc             -306625537
        //   718: goto            723
        //   721: ldc             2142069087
        //   723: ldc             1146153663
        //   725: ixor           
        //   726: lookupswitch {
        //          -1444304576: 2352
        //          -1230661210: 721
        //          default: 752
        //        }
        //   752: goto            756
        //   755: athrow         
        //   756: invokestatic    invokestatic   !!! ERROR
        //   759: goto            763
        //   762: athrow         
        //   763: getstatic       dev/nuker/pyro/fc.1:I
        //   766: ifeq            774
        //   769: ldc             1349769304
        //   771: goto            776
        //   774: ldc             497893865
        //   776: ldc             327715021
        //   778: ixor           
        //   779: lookupswitch {
        //          1140543637: 2316
        //          1290622716: 774
        //          default: 804
        //        }
        //   804: goto            808
        //   807: athrow         
        //   808: invokevirtual   java/lang/String.equals:(Ljava/lang/Object;)Z
        //   811: goto            815
        //   814: athrow         
        //   815: ifeq            935
        //   818: aload_0        
        //   819: getfield        dev/nuker/pyro/f6m.2:Ldev/nuker/pyro/f0a;
        //   822: getstatic       dev/nuker/pyro/fc.1:I
        //   825: ifeq            833
        //   828: ldc             414025337
        //   830: goto            835
        //   833: ldc             -538384428
        //   835: ldc             -2009618700
        //   837: ixor           
        //   838: lookupswitch {
        //          -1868947315: 2334
        //          189531452: 833
        //          default: 864
        //        }
        //   864: goto            868
        //   867: athrow         
        //   868: invokevirtual   dev/nuker/pyro/f0a.3:()Ljava/lang/Object;
        //   871: goto            875
        //   874: athrow         
        //   875: checkcast       Ljava/lang/Boolean;
        //   878: getstatic       dev/nuker/pyro/fc.c:I
        //   881: ifge            889
        //   884: ldc             1935539017
        //   886: goto            891
        //   889: ldc             509841130
        //   891: ldc             -941082480
        //   893: ixor           
        //   894: lookupswitch {
        //          -1263156263: 889
        //          -645155206: 920
        //          default: 2336
        //        }
        //   920: goto            924
        //   923: athrow         
        //   924: invokevirtual   java/lang/Boolean.booleanValue:()Z
        //   927: goto            931
        //   930: athrow         
        //   931: ifne            935
        //   934: return         
        //   935: aload_1        
        //   936: goto            940
        //   939: athrow         
        //   940: invokevirtual   dev/nuker/pyro/f2W.c:()Ldev/nuker/pyro/fH;
        //   943: goto            947
        //   946: athrow         
        //   947: getstatic       dev/nuker/pyro/fc.c:I
        //   950: ifge            958
        //   953: ldc             792684573
        //   955: goto            960
        //   958: ldc             -924911941
        //   960: ldc             -1350416791
        //   962: ixor           
        //   963: lookupswitch {
        //          -2135085452: 2348
        //          -310203358: 958
        //          default: 988
        //        }
        //   988: goto            992
        //   991: athrow         
        //   992: invokevirtual   dev/nuker/pyro/fH.5:()Ljava/lang/String;
        //   995: goto            999
        //   998: athrow         
        //   999: ldc             "\u2218\u149c\u8b32\ub1cd\ucf84\uec36\ub22a\ue71d"
        //  1001: goto            1005
        //  1004: athrow         
        //  1005: invokestatic    invokestatic   !!! ERROR
        //  1008: goto            1012
        //  1011: athrow         
        //  1012: goto            1016
        //  1015: athrow         
        //  1016: invokevirtual   java/lang/String.equals:(Ljava/lang/Object;)Z
        //  1019: goto            1023
        //  1022: athrow         
        //  1023: ifeq            1059
        //  1026: aload_0        
        //  1027: getfield        dev/nuker/pyro/f6m.3:Ldev/nuker/pyro/f0a;
        //  1030: goto            1034
        //  1033: athrow         
        //  1034: invokevirtual   dev/nuker/pyro/f0a.3:()Ljava/lang/Object;
        //  1037: goto            1041
        //  1040: athrow         
        //  1041: checkcast       Ljava/lang/Boolean;
        //  1044: goto            1048
        //  1047: athrow         
        //  1048: invokevirtual   java/lang/Boolean.booleanValue:()Z
        //  1051: goto            1055
        //  1054: athrow         
        //  1055: ifne            1059
        //  1058: return         
        //  1059: getstatic       dev/nuker/pyro/fc.1:I
        //  1062: ifeq            1070
        //  1065: ldc             262747608
        //  1067: goto            1072
        //  1070: ldc             -555145735
        //  1072: ldc             -1991529383
        //  1074: ixor           
        //  1075: lookupswitch {
        //          -2031969919: 2354
        //          -1933401539: 1070
        //          default: 1100
        //        }
        //  1100: aload_1        
        //  1101: getstatic       dev/nuker/pyro/fc.1:I
        //  1104: ifeq            1112
        //  1107: ldc             -452291833
        //  1109: goto            1114
        //  1112: ldc             1882439972
        //  1114: ldc             -372761795
        //  1116: ixor           
        //  1117: lookupswitch {
        //          -1711547879: 1144
        //          214075450: 1112
        //          default: 2312
        //        }
        //  1144: goto            1148
        //  1147: athrow         
        //  1148: invokevirtual   dev/nuker/pyro/f2W.c:()Ldev/nuker/pyro/fH;
        //  1151: goto            1155
        //  1154: athrow         
        //  1155: goto            1159
        //  1158: athrow         
        //  1159: invokevirtual   dev/nuker/pyro/fH.5:()Ljava/lang/String;
        //  1162: goto            1166
        //  1165: athrow         
        //  1166: ldc             "\u2218\u149a\u8b37\ub1cb"
        //  1168: goto            1172
        //  1171: athrow         
        //  1172: invokestatic    invokestatic   !!! ERROR
        //  1175: goto            1179
        //  1178: athrow         
        //  1179: getstatic       dev/nuker/pyro/fc.c:I
        //  1182: ifge            1190
        //  1185: ldc             1089514208
        //  1187: goto            1192
        //  1190: ldc             967844878
        //  1192: ldc             -1298517883
        //  1194: ixor           
        //  1195: lookupswitch {
        //          -1586281812: 1190
        //          -227894683: 2324
        //          default: 1220
        //        }
        //  1220: goto            1224
        //  1223: athrow         
        //  1224: invokevirtual   java/lang/String.equals:(Ljava/lang/Object;)Z
        //  1227: goto            1231
        //  1230: athrow         
        //  1231: ifeq            1311
        //  1234: aload_0        
        //  1235: getfield        dev/nuker/pyro/f6m.4:Ldev/nuker/pyro/f0a;
        //  1238: goto            1242
        //  1241: athrow         
        //  1242: invokevirtual   dev/nuker/pyro/f0a.3:()Ljava/lang/Object;
        //  1245: goto            1249
        //  1248: athrow         
        //  1249: checkcast       Ljava/lang/Boolean;
        //  1252: getstatic       dev/nuker/pyro/fc.1:I
        //  1255: ifeq            1263
        //  1258: ldc             -109789732
        //  1260: goto            1265
        //  1263: ldc             1320143686
        //  1265: ldc             9738426
        //  1267: ixor           
        //  1268: lookupswitch {
        //          -102750874: 1263
        //          1312510972: 1296
        //          default: 2320
        //        }
        //  1296: goto            1300
        //  1299: athrow         
        //  1300: invokevirtual   java/lang/Boolean.booleanValue:()Z
        //  1303: goto            1307
        //  1306: athrow         
        //  1307: ifne            1311
        //  1310: return         
        //  1311: aload_1        
        //  1312: goto            1316
        //  1315: athrow         
        //  1316: invokevirtual   dev/nuker/pyro/f2W.c:()Ldev/nuker/pyro/fH;
        //  1319: goto            1323
        //  1322: athrow         
        //  1323: goto            1327
        //  1326: athrow         
        //  1327: invokevirtual   dev/nuker/pyro/fH.5:()Ljava/lang/String;
        //  1330: goto            1334
        //  1333: athrow         
        //  1334: ldc             "\u2207\u1496\u8b2a\ub1cc\ucf8c\uec21"
        //  1336: goto            1340
        //  1339: athrow         
        //  1340: invokestatic    invokestatic   !!! ERROR
        //  1343: goto            1347
        //  1346: athrow         
        //  1347: getstatic       dev/nuker/pyro/fc.1:I
        //  1350: ifeq            1358
        //  1353: ldc             -1852154850
        //  1355: goto            1360
        //  1358: ldc             -257080669
        //  1360: ldc             -840606029
        //  1362: ixor           
        //  1363: lookupswitch {
        //          1028135952: 1388
        //          1551827629: 1358
        //          default: 2362
        //        }
        //  1388: goto            1392
        //  1391: athrow         
        //  1392: invokevirtual   java/lang/String.equals:(Ljava/lang/Object;)Z
        //  1395: goto            1399
        //  1398: athrow         
        //  1399: ifeq            1477
        //  1402: aload_0        
        //  1403: getfield        dev/nuker/pyro/f6m.5:Ldev/nuker/pyro/f0a;
        //  1406: getstatic       dev/nuker/pyro/fc.1:I
        //  1409: ifeq            1417
        //  1412: ldc             -12854143
        //  1414: goto            1419
        //  1417: ldc             -1222493822
        //  1419: ldc             577572241
        //  1421: ixor           
        //  1422: lookupswitch {
        //          -1789971437: 1448
        //          -581512944: 1417
        //          default: 2356
        //        }
        //  1448: goto            1452
        //  1451: athrow         
        //  1452: invokevirtual   dev/nuker/pyro/f0a.3:()Ljava/lang/Object;
        //  1455: goto            1459
        //  1458: athrow         
        //  1459: checkcast       Ljava/lang/Boolean;
        //  1462: goto            1466
        //  1465: athrow         
        //  1466: invokevirtual   java/lang/Boolean.booleanValue:()Z
        //  1469: goto            1473
        //  1472: athrow         
        //  1473: ifne            1477
        //  1476: return         
        //  1477: aload_1        
        //  1478: goto            1482
        //  1481: athrow         
        //  1482: invokevirtual   dev/nuker/pyro/f2W.c:()Ldev/nuker/pyro/fH;
        //  1485: goto            1489
        //  1488: athrow         
        //  1489: getstatic       dev/nuker/pyro/fc.0:I
        //  1492: ifeq            1500
        //  1495: ldc             -2134297015
        //  1497: goto            1502
        //  1500: ldc             -381288332
        //  1502: ldc             -1044163676
        //  1504: ixor           
        //  1505: lookupswitch {
        //          679826384: 1532
        //          1091200493: 1500
        //          default: 2326
        //        }
        //  1532: goto            1536
        //  1535: athrow         
        //  1536: invokevirtual   dev/nuker/pyro/fH.5:()Ljava/lang/String;
        //  1539: goto            1543
        //  1542: athrow         
        //  1543: ldc             "\u2202\u149c\u8b36\ub1c4\ucf8d"
        //  1545: getstatic       dev/nuker/pyro/fc.c:I
        //  1548: ifge            1556
        //  1551: ldc             1240277219
        //  1553: goto            1558
        //  1556: ldc             -1171038496
        //  1558: ldc             -1758111792
        //  1560: ixor           
        //  1561: lookupswitch {
        //          -556239053: 1556
        //          755370288: 1588
        //          default: 2364
        //        }
        //  1588: goto            1592
        //  1591: athrow         
        //  1592: invokestatic    invokestatic   !!! ERROR
        //  1595: goto            1599
        //  1598: athrow         
        //  1599: getstatic       dev/nuker/pyro/fc.0:I
        //  1602: ifeq            1610
        //  1605: ldc             79173772
        //  1607: goto            1612
        //  1610: ldc             1844232455
        //  1612: ldc             2112339294
        //  1614: ixor           
        //  1615: lookupswitch {
        //          813465909: 1610
        //          2036311506: 2340
        //          default: 1640
        //        }
        //  1640: goto            1644
        //  1643: athrow         
        //  1644: invokevirtual   java/lang/String.equals:(Ljava/lang/Object;)Z
        //  1647: goto            1651
        //  1650: athrow         
        //  1651: ifeq            1729
        //  1654: getstatic       dev/nuker/pyro/fc.1:I
        //  1657: ifeq            1665
        //  1660: ldc             -1372700828
        //  1662: goto            1667
        //  1665: ldc             2019270551
        //  1667: ldc             1331995744
        //  1669: ixor           
        //  1670: lookupswitch {
        //          -974491751: 1665
        //          -515204348: 2318
        //          default: 1696
        //        }
        //  1696: aload_0        
        //  1697: getfield        dev/nuker/pyro/f6m.6:Ldev/nuker/pyro/f0a;
        //  1700: goto            1704
        //  1703: athrow         
        //  1704: invokevirtual   dev/nuker/pyro/f0a.3:()Ljava/lang/Object;
        //  1707: goto            1711
        //  1710: athrow         
        //  1711: checkcast       Ljava/lang/Boolean;
        //  1714: goto            1718
        //  1717: athrow         
        //  1718: invokevirtual   java/lang/Boolean.booleanValue:()Z
        //  1721: goto            1725
        //  1724: athrow         
        //  1725: ifne            1729
        //  1728: return         
        //  1729: aload_1        
        //  1730: goto            1734
        //  1733: athrow         
        //  1734: invokevirtual   dev/nuker/pyro/f2W.c:()Ldev/nuker/pyro/fH;
        //  1737: goto            1741
        //  1740: athrow         
        //  1741: getstatic       dev/nuker/pyro/fc.1:I
        //  1744: ifeq            1752
        //  1747: ldc             -1093200286
        //  1749: goto            1754
        //  1752: ldc             -292064450
        //  1754: ldc             -224638075
        //  1756: ixor           
        //  1757: lookupswitch {
        //          470497467: 1784
        //          1280007655: 1752
        //          default: 2344
        //        }
        //  1784: getfield        dev/nuker/pyro/fH.c:Ldev/nuker/pyro/fw;
        //  1787: goto            1791
        //  1790: athrow         
        //  1791: invokevirtual   dev/nuker/pyro/fw.0:()Ljava/lang/Object;
        //  1794: goto            1798
        //  1797: athrow         
        //  1798: checkcast       Ljava/lang/Boolean;
        //  1801: goto            1805
        //  1804: athrow         
        //  1805: invokevirtual   java/lang/Boolean.booleanValue:()Z
        //  1808: goto            1812
        //  1811: athrow         
        //  1812: ifeq            2056
        //  1815: getstatic       dev/nuker/pyro/Pyro.INSTANCE:Ldev/nuker/pyro/Pyro;
        //  1818: new             Ljava/lang/StringBuilder;
        //  1821: dup            
        //  1822: getstatic       dev/nuker/pyro/fc.1:I
        //  1825: ifeq            1833
        //  1828: ldc             888151926
        //  1830: goto            1835
        //  1833: ldc             -1350226556
        //  1835: ldc             -2147241020
        //  1837: ixor           
        //  1838: lookupswitch {
        //          -1259098958: 1833
        //          797351488: 1864
        //          default: 2314
        //        }
        //  1864: goto            1868
        //  1867: athrow         
        //  1868: invokespecial   java/lang/StringBuilder.<init>:()V
        //  1871: goto            1875
        //  1874: athrow         
        //  1875: getstatic       com/mojang/realmsclient/gui/ChatFormatting.GREEN:Lcom/mojang/realmsclient/gui/ChatFormatting;
        //  1878: goto            1882
        //  1881: athrow         
        //  1882: invokevirtual   java/lang/StringBuilder.append:(Ljava/lang/Object;)Ljava/lang/StringBuilder;
        //  1885: goto            1889
        //  1888: athrow         
        //  1889: aload_1        
        //  1890: getstatic       dev/nuker/pyro/fc.1:I
        //  1893: ifeq            1901
        //  1896: ldc             279574239
        //  1898: goto            1903
        //  1901: ldc             -1943002470
        //  1903: ldc             1976144688
        //  1905: ixor           
        //  1906: lookupswitch {
        //          381199440: 1901
        //          1700816367: 2346
        //          default: 1932
        //        }
        //  1932: goto            1936
        //  1935: athrow         
        //  1936: invokevirtual   dev/nuker/pyro/f2W.c:()Ldev/nuker/pyro/fH;
        //  1939: goto            1943
        //  1942: athrow         
        //  1943: goto            1947
        //  1946: athrow         
        //  1947: invokevirtual   dev/nuker/pyro/fH.9:()Ljava/lang/String;
        //  1950: goto            1954
        //  1953: athrow         
        //  1954: getstatic       dev/nuker/pyro/fc.0:I
        //  1957: ifeq            1965
        //  1960: ldc             786516957
        //  1962: goto            1967
        //  1965: ldc             1994565341
        //  1967: ldc             -1825121243
        //  1969: ixor           
        //  1970: lookupswitch {
        //          -1109944328: 1965
        //          -439059720: 1996
        //          default: 2350
        //        }
        //  1996: goto            2000
        //  1999: athrow         
        //  2000: invokevirtual   java/lang/StringBuilder.append:(Ljava/lang/String;)Ljava/lang/StringBuilder;
        //  2003: goto            2007
        //  2006: athrow         
        //  2007: ldc             "\u2275\u149b\u8b25\ub1db\ucfc9\uec31\ub221\ue70c\udb77\uefba\ua6f6\u1e42\ue02c\uc7b4\u8771\u88ad\u57a0\u7682"
        //  2009: goto            2013
        //  2012: athrow         
        //  2013: invokestatic    invokestatic   !!! ERROR
        //  2016: goto            2020
        //  2019: athrow         
        //  2020: goto            2024
        //  2023: athrow         
        //  2024: invokevirtual   java/lang/StringBuilder.append:(Ljava/lang/String;)Ljava/lang/StringBuilder;
        //  2027: goto            2031
        //  2030: athrow         
        //  2031: goto            2035
        //  2034: athrow         
        //  2035: invokevirtual   java/lang/StringBuilder.toString:()Ljava/lang/String;
        //  2038: goto            2042
        //  2041: athrow         
        //  2042: goto            2046
        //  2045: athrow         
        //  2046: invokevirtual   dev/nuker/pyro/Pyro.sendMessage:(Ljava/lang/String;)V
        //  2049: goto            2053
        //  2052: athrow         
        //  2053: goto            2309
        //  2056: getstatic       dev/nuker/pyro/Pyro.INSTANCE:Ldev/nuker/pyro/Pyro;
        //  2059: new             Ljava/lang/StringBuilder;
        //  2062: dup            
        //  2063: goto            2067
        //  2066: athrow         
        //  2067: invokespecial   java/lang/StringBuilder.<init>:()V
        //  2070: goto            2074
        //  2073: athrow         
        //  2074: getstatic       dev/nuker/pyro/fc.c:I
        //  2077: ifge            2086
        //  2080: ldc_w           1162147131
        //  2083: goto            2089
        //  2086: ldc_w           -2031191303
        //  2089: ldc_w           -625418119
        //  2092: ixor           
        //  2093: lookupswitch {
        //          -1610869438: 2342
        //          977606825: 2086
        //          default: 2120
        //        }
        //  2120: getstatic       com/mojang/realmsclient/gui/ChatFormatting.RED:Lcom/mojang/realmsclient/gui/ChatFormatting;
        //  2123: goto            2127
        //  2126: athrow         
        //  2127: invokevirtual   java/lang/StringBuilder.append:(Ljava/lang/Object;)Ljava/lang/StringBuilder;
        //  2130: goto            2134
        //  2133: athrow         
        //  2134: aload_1        
        //  2135: goto            2139
        //  2138: athrow         
        //  2139: invokevirtual   dev/nuker/pyro/f2W.c:()Ldev/nuker/pyro/fH;
        //  2142: goto            2146
        //  2145: athrow         
        //  2146: goto            2150
        //  2149: athrow         
        //  2150: invokevirtual   dev/nuker/pyro/fH.9:()Ljava/lang/String;
        //  2153: goto            2157
        //  2156: athrow         
        //  2157: getstatic       dev/nuker/pyro/fc.0:I
        //  2160: ifeq            2169
        //  2163: ldc_w           -881087473
        //  2166: goto            2172
        //  2169: ldc_w           2106457920
        //  2172: ldc_w           1736087900
        //  2175: ixor           
        //  2176: lookupswitch {
        //          -1409206957: 2169
        //          452421148: 2204
        //          default: 2328
        //        }
        //  2204: goto            2208
        //  2207: athrow         
        //  2208: invokevirtual   java/lang/StringBuilder.append:(Ljava/lang/String;)Ljava/lang/StringBuilder;
        //  2211: goto            2215
        //  2214: athrow         
        //  2215: ldc_w           "\u2275\u149b\u8b25\ub1db\ucfc9\uec31\ub221\ue70c\udb77\uefba\ua6f7\u1e45\ue03e\uc7b7\u877f\u88a4\u57a1\u76c8\ubf62"
        //  2218: goto            2222
        //  2221: athrow         
        //  2222: invokestatic    invokestatic   !!! ERROR
        //  2225: goto            2229
        //  2228: athrow         
        //  2229: getstatic       dev/nuker/pyro/fc.c:I
        //  2232: ifge            2241
        //  2235: ldc_w           2124045145
        //  2238: goto            2244
        //  2241: ldc_w           1810338334
        //  2244: ldc_w           -1381996537
        //  2247: ixor           
        //  2248: lookupswitch {
        //          -968361447: 2276
        //          -751160482: 2241
        //          default: 2366
        //        }
        //  2276: goto            2280
        //  2279: athrow         
        //  2280: invokevirtual   java/lang/StringBuilder.append:(Ljava/lang/String;)Ljava/lang/StringBuilder;
        //  2283: goto            2287
        //  2286: athrow         
        //  2287: goto            2291
        //  2290: athrow         
        //  2291: invokevirtual   java/lang/StringBuilder.toString:()Ljava/lang/String;
        //  2294: goto            2298
        //  2297: athrow         
        //  2298: goto            2302
        //  2301: athrow         
        //  2302: invokevirtual   dev/nuker/pyro/Pyro.sendMessage:(Ljava/lang/String;)V
        //  2305: goto            2309
        //  2308: athrow         
        //  2309: return         
        //  2310: aconst_null    
        //  2311: athrow         
        //  2312: aconst_null    
        //  2313: athrow         
        //  2314: aconst_null    
        //  2315: athrow         
        //  2316: aconst_null    
        //  2317: athrow         
        //  2318: aconst_null    
        //  2319: athrow         
        //  2320: aconst_null    
        //  2321: athrow         
        //  2322: aconst_null    
        //  2323: athrow         
        //  2324: aconst_null    
        //  2325: athrow         
        //  2326: aconst_null    
        //  2327: athrow         
        //  2328: aconst_null    
        //  2329: athrow         
        //  2330: aconst_null    
        //  2331: athrow         
        //  2332: aconst_null    
        //  2333: athrow         
        //  2334: aconst_null    
        //  2335: athrow         
        //  2336: aconst_null    
        //  2337: athrow         
        //  2338: aconst_null    
        //  2339: athrow         
        //  2340: aconst_null    
        //  2341: athrow         
        //  2342: aconst_null    
        //  2343: athrow         
        //  2344: aconst_null    
        //  2345: athrow         
        //  2346: aconst_null    
        //  2347: athrow         
        //  2348: aconst_null    
        //  2349: athrow         
        //  2350: aconst_null    
        //  2351: athrow         
        //  2352: aconst_null    
        //  2353: athrow         
        //  2354: aconst_null    
        //  2355: athrow         
        //  2356: aconst_null    
        //  2357: athrow         
        //  2358: aconst_null    
        //  2359: athrow         
        //  2360: aconst_null    
        //  2361: athrow         
        //  2362: aconst_null    
        //  2363: athrow         
        //  2364: aconst_null    
        //  2365: athrow         
        //  2366: aconst_null    
        //  2367: athrow         
        //  2368: aconst_null    
        //  2369: athrow         
        //  2370: pop            
        //  2371: goto            24
        //  2374: pop            
        //  2375: aconst_null    
        //  2376: goto            2370
        //  2379: dup            
        //  2380: ifnull          2370
        //  2383: checkcast       Ljava/lang/Throwable;
        //  2386: athrow         
        //  2387: dup            
        //  2388: ifnull          2374
        //  2391: checkcast       Ljava/lang/Throwable;
        //  2394: athrow         
        //  2395: aconst_null    
        //  2396: athrow         
        //    StackMapTable: 01 A0 43 07 00 38 04 FF 00 0B 00 00 00 01 07 00 38 FD 00 03 07 00 03 07 00 67 4E 07 00 40 FF 00 01 00 02 07 00 03 07 00 67 00 02 07 00 40 01 5E 07 00 40 51 07 00 03 FF 00 01 00 02 07 00 03 07 00 67 00 02 07 00 03 01 5B 07 00 03 4D 07 00 40 FF 00 01 00 02 07 00 03 07 00 67 00 02 07 00 40 01 5B 07 00 40 05 00 46 07 00 1B 40 07 00 54 45 07 00 38 40 07 01 16 45 07 00 13 40 07 00 59 45 07 00 38 40 01 02 04 41 01 19 4B 07 00 67 FF 00 01 00 02 07 00 03 07 00 67 00 02 07 00 67 01 5D 07 00 67 42 07 00 1F 40 07 00 67 45 07 00 38 40 07 00 05 4D 07 00 72 FF 00 01 00 02 07 00 03 07 00 67 00 02 07 00 72 01 5C 07 00 72 42 07 00 38 40 07 00 72 45 07 00 38 40 07 01 16 45 07 00 38 40 07 00 59 45 07 00 38 40 01 03 4B 07 00 03 FF 00 01 00 02 07 00 03 07 00 67 00 02 07 00 03 01 5C 07 00 03 45 07 00 15 40 07 00 54 45 07 00 38 40 07 01 16 FF 00 05 00 00 00 01 07 00 38 FF 00 00 00 02 07 00 03 07 00 67 00 01 07 00 59 45 07 00 38 40 01 46 07 00 38 40 07 00 67 45 07 00 38 40 07 00 05 45 07 00 38 40 07 00 72 45 07 00 38 40 07 01 16 4D 07 00 59 FF 00 01 00 02 07 00 03 07 00 67 00 02 07 00 59 01 5E 07 00 59 42 07 00 38 40 07 00 59 45 07 00 38 40 01 03 FF 00 03 00 00 00 01 07 00 38 FF 00 00 00 02 07 00 03 07 00 67 00 01 07 00 67 45 07 00 38 40 07 00 05 42 07 00 2B 40 07 00 05 45 07 00 38 40 07 00 8B FF 00 0C 00 02 07 00 03 07 00 67 00 02 07 00 8B 07 00 8B FF 00 01 00 02 07 00 03 07 00 67 00 03 07 00 8B 07 00 8B 01 FF 00 1E 00 02 07 00 03 07 00 67 00 02 07 00 8B 07 00 8B 42 07 00 38 FF 00 00 00 02 07 00 03 07 00 67 00 02 07 00 8B 07 00 8B 45 07 00 38 FF 00 00 00 02 07 00 03 07 00 67 00 02 07 00 8B 07 00 8B FF 00 02 00 00 00 01 07 00 38 FF 00 00 00 02 07 00 03 07 00 67 00 02 07 00 8B 07 00 8B 45 07 00 38 40 01 49 07 00 38 40 07 00 54 45 07 00 38 40 07 01 16 45 07 00 1D 40 07 00 59 45 07 00 38 40 01 02 04 41 01 17 00 43 07 00 38 40 07 00 67 45 07 00 38 40 07 00 05 42 07 00 38 40 07 00 05 45 07 00 38 40 07 00 8B FF 00 0C 00 02 07 00 03 07 00 67 00 02 07 00 8B 07 00 8B FF 00 01 00 02 07 00 03 07 00 67 00 03 07 00 8B 07 00 8B 01 FF 00 1C 00 02 07 00 03 07 00 67 00 02 07 00 8B 07 00 8B 42 07 00 38 FF 00 00 00 02 07 00 03 07 00 67 00 02 07 00 8B 07 00 8B 45 07 00 38 FF 00 00 00 02 07 00 03 07 00 67 00 02 07 00 8B 07 00 8B FF 00 0A 00 02 07 00 03 07 00 67 00 02 07 00 8B 07 00 8B FF 00 01 00 02 07 00 03 07 00 67 00 03 07 00 8B 07 00 8B 01 FF 00 1B 00 02 07 00 03 07 00 67 00 02 07 00 8B 07 00 8B 42 07 00 38 FF 00 00 00 02 07 00 03 07 00 67 00 02 07 00 8B 07 00 8B 45 07 00 38 40 01 51 07 00 54 FF 00 01 00 02 07 00 03 07 00 67 00 02 07 00 54 01 5C 07 00 54 FF 00 02 00 00 00 01 07 00 38 FF 00 00 00 02 07 00 03 07 00 67 00 01 07 00 54 45 07 00 38 40 07 01 16 4D 07 00 59 FF 00 01 00 02 07 00 03 07 00 67 00 02 07 00 59 01 5C 07 00 59 FF 00 02 00 00 00 01 07 00 38 FF 00 00 00 02 07 00 03 07 00 67 00 01 07 00 59 45 07 00 38 40 01 03 FF 00 03 00 00 00 01 07 00 38 FF 00 00 00 02 07 00 03 07 00 67 00 01 07 00 67 45 07 00 38 40 07 00 05 4A 07 00 05 FF 00 01 00 02 07 00 03 07 00 67 00 02 07 00 05 01 5B 07 00 05 42 07 00 23 40 07 00 05 45 07 00 38 40 07 00 8B 44 07 00 17 FF 00 00 00 02 07 00 03 07 00 67 00 02 07 00 8B 07 00 8B 45 07 00 38 FF 00 00 00 02 07 00 03 07 00 67 00 02 07 00 8B 07 00 8B 42 07 00 38 FF 00 00 00 02 07 00 03 07 00 67 00 02 07 00 8B 07 00 8B 45 07 00 38 40 01 49 07 00 38 40 07 00 54 45 07 00 38 40 07 01 16 45 07 00 27 40 07 00 59 45 07 00 38 40 01 03 0A 41 01 1B 4B 07 00 67 FF 00 01 00 02 07 00 03 07 00 67 00 02 07 00 67 01 5D 07 00 67 FF 00 02 00 00 00 01 07 00 38 FF 00 00 00 02 07 00 03 07 00 67 00 01 07 00 67 45 07 00 38 40 07 00 05 42 07 00 38 40 07 00 05 45 07 00 38 40 07 00 8B FF 00 04 00 00 00 01 07 00 38 FF 00 00 00 02 07 00 03 07 00 67 00 02 07 00 8B 07 00 8B 45 07 00 38 FF 00 00 00 02 07 00 03 07 00 67 00 02 07 00 8B 07 00 8B FF 00 0A 00 02 07 00 03 07 00 67 00 02 07 00 8B 07 00 8B FF 00 01 00 02 07 00 03 07 00 67 00 03 07 00 8B 07 00 8B 01 FF 00 1B 00 02 07 00 03 07 00 67 00 02 07 00 8B 07 00 8B 42 07 00 31 FF 00 00 00 02 07 00 03 07 00 67 00 02 07 00 8B 07 00 8B 45 07 00 38 40 01 49 07 00 38 40 07 00 54 45 07 00 38 40 07 01 16 4D 07 00 59 FF 00 01 00 02 07 00 03 07 00 67 00 02 07 00 59 01 5E 07 00 59 42 07 00 38 40 07 00 59 45 07 00 38 40 01 03 43 07 00 38 40 07 00 67 45 07 00 38 40 07 00 05 42 07 00 25 40 07 00 05 45 07 00 38 40 07 00 8B 44 07 00 15 FF 00 00 00 02 07 00 03 07 00 67 00 02 07 00 8B 07 00 8B 45 07 00 38 FF 00 00 00 02 07 00 03 07 00 67 00 02 07 00 8B 07 00 8B FF 00 0A 00 02 07 00 03 07 00 67 00 02 07 00 8B 07 00 8B FF 00 01 00 02 07 00 03 07 00 67 00 03 07 00 8B 07 00 8B 01 FF 00 1B 00 02 07 00 03 07 00 67 00 02 07 00 8B 07 00 8B 42 07 00 38 FF 00 00 00 02 07 00 03 07 00 67 00 02 07 00 8B 07 00 8B 45 07 00 38 40 01 51 07 00 54 FF 00 01 00 02 07 00 03 07 00 67 00 02 07 00 54 01 5C 07 00 54 42 07 00 2B 40 07 00 54 45 07 00 38 40 07 01 16 45 07 00 1B 40 07 00 59 45 07 00 38 40 01 03 43 07 00 38 40 07 00 67 45 07 00 38 40 07 00 05 4A 07 00 05 FF 00 01 00 02 07 00 03 07 00 67 00 02 07 00 05 01 5D 07 00 05 42 07 00 38 40 07 00 05 45 07 00 38 40 07 00 8B FF 00 0C 00 02 07 00 03 07 00 67 00 02 07 00 8B 07 00 8B FF 00 01 00 02 07 00 03 07 00 67 00 03 07 00 8B 07 00 8B 01 FF 00 1D 00 02 07 00 03 07 00 67 00 02 07 00 8B 07 00 8B 42 07 00 1D FF 00 00 00 02 07 00 03 07 00 67 00 02 07 00 8B 07 00 8B 45 07 00 38 FF 00 00 00 02 07 00 03 07 00 67 00 02 07 00 8B 07 00 8B FF 00 0A 00 02 07 00 03 07 00 67 00 02 07 00 8B 07 00 8B FF 00 01 00 02 07 00 03 07 00 67 00 03 07 00 8B 07 00 8B 01 FF 00 1B 00 02 07 00 03 07 00 67 00 02 07 00 8B 07 00 8B 42 07 00 38 FF 00 00 00 02 07 00 03 07 00 67 00 02 07 00 8B 07 00 8B 45 07 00 38 40 01 0D 41 01 1C 46 07 00 31 40 07 00 54 45 07 00 38 40 07 01 16 FF 00 05 00 00 00 01 07 00 38 FF 00 00 00 02 07 00 03 07 00 67 00 01 07 00 59 45 07 00 38 40 01 03 43 07 00 15 40 07 00 67 45 07 00 38 40 07 00 05 4A 07 00 05 FF 00 01 00 02 07 00 03 07 00 67 00 02 07 00 05 01 5D 07 00 05 45 07 00 38 40 07 00 72 45 07 00 38 40 07 01 16 45 07 00 29 40 07 00 59 45 07 00 38 40 01 FF 00 14 00 02 07 00 03 07 00 67 00 03 07 00 DA 08 07 1A 08 07 1A FF 00 01 00 02 07 00 03 07 00 67 00 04 07 00 DA 08 07 1A 08 07 1A 01 FF 00 1C 00 02 07 00 03 07 00 67 00 03 07 00 DA 08 07 1A 08 07 1A 42 07 00 38 FF 00 00 00 02 07 00 03 07 00 67 00 03 07 00 DA 08 07 1A 08 07 1A 45 07 00 38 FF 00 00 00 02 07 00 03 07 00 67 00 02 07 00 DA 07 00 E0 45 07 00 38 FF 00 00 00 02 07 00 03 07 00 67 00 03 07 00 DA 07 00 E0 07 00 E9 45 07 00 38 FF 00 00 00 02 07 00 03 07 00 67 00 02 07 00 DA 07 00 E0 FF 00 0B 00 02 07 00 03 07 00 67 00 03 07 00 DA 07 00 E0 07 00 67 FF 00 01 00 02 07 00 03 07 00 67 00 04 07 00 DA 07 00 E0 07 00 67 01 FF 00 1C 00 02 07 00 03 07 00 67 00 03 07 00 DA 07 00 E0 07 00 67 42 07 00 38 FF 00 00 00 02 07 00 03 07 00 67 00 03 07 00 DA 07 00 E0 07 00 67 45 07 00 38 FF 00 00 00 02 07 00 03 07 00 67 00 03 07 00 DA 07 00 E0 07 00 05 FF 00 02 00 00 00 01 07 00 38 FF 00 00 00 02 07 00 03 07 00 67 00 03 07 00 DA 07 00 E0 07 00 05 45 07 00 38 FF 00 00 00 02 07 00 03 07 00 67 00 03 07 00 DA 07 00 E0 07 00 8B FF 00 0A 00 02 07 00 03 07 00 67 00 03 07 00 DA 07 00 E0 07 00 8B FF 00 01 00 02 07 00 03 07 00 67 00 04 07 00 DA 07 00 E0 07 00 8B 01 FF 00 1C 00 02 07 00 03 07 00 67 00 03 07 00 DA 07 00 E0 07 00 8B FF 00 02 00 00 00 01 07 00 38 FF 00 00 00 02 07 00 03 07 00 67 00 03 07 00 DA 07 00 E0 07 00 8B 45 07 00 38 FF 00 00 00 02 07 00 03 07 00 67 00 02 07 00 DA 07 00 E0 44 07 00 38 FF 00 00 00 02 07 00 03 07 00 67 00 03 07 00 DA 07 00 E0 07 00 8B 45 07 00 38 FF 00 00 00 02 07 00 03 07 00 67 00 03 07 00 DA 07 00 E0 07 00 8B FF 00 02 00 00 00 01 07 00 38 FF 00 00 00 02 07 00 03 07 00 67 00 03 07 00 DA 07 00 E0 07 00 8B 45 07 00 38 FF 00 00 00 02 07 00 03 07 00 67 00 02 07 00 DA 07 00 E0 42 07 00 38 FF 00 00 00 02 07 00 03 07 00 67 00 02 07 00 DA 07 00 E0 45 07 00 38 FF 00 00 00 02 07 00 03 07 00 67 00 02 07 00 DA 07 00 8B 42 07 00 2F FF 00 00 00 02 07 00 03 07 00 67 00 02 07 00 DA 07 00 8B 45 07 00 38 00 02 49 07 00 38 FF 00 00 00 02 07 00 03 07 00 67 00 03 07 00 DA 08 08 0B 08 08 0B 45 07 00 38 FF 00 00 00 02 07 00 03 07 00 67 00 02 07 00 DA 07 00 E0 FF 00 0B 00 02 07 00 03 07 00 67 00 02 07 00 DA 07 00 E0 FF 00 02 00 02 07 00 03 07 00 67 00 03 07 00 DA 07 00 E0 01 FF 00 1E 00 02 07 00 03 07 00 67 00 02 07 00 DA 07 00 E0 FF 00 05 00 00 00 01 07 00 38 FF 00 00 00 02 07 00 03 07 00 67 00 03 07 00 DA 07 00 E0 07 00 E9 45 07 00 38 FF 00 00 00 02 07 00 03 07 00 67 00 02 07 00 DA 07 00 E0 43 07 00 1B FF 00 00 00 02 07 00 03 07 00 67 00 03 07 00 DA 07 00 E0 07 00 67 45 07 00 38 FF 00 00 00 02 07 00 03 07 00 67 00 03 07 00 DA 07 00 E0 07 00 05 42 07 00 38 FF 00 00 00 02 07 00 03 07 00 67 00 03 07 00 DA 07 00 E0 07 00 05 45 07 00 38 FF 00 00 00 02 07 00 03 07 00 67 00 03 07 00 DA 07 00 E0 07 00 8B FF 00 0B 00 02 07 00 03 07 00 67 00 03 07 00 DA 07 00 E0 07 00 8B FF 00 02 00 02 07 00 03 07 00 67 00 04 07 00 DA 07 00 E0 07 00 8B 01 FF 00 1F 00 02 07 00 03 07 00 67 00 03 07 00 DA 07 00 E0 07 00 8B 42 07 00 38 FF 00 00 00 02 07 00 03 07 00 67 00 03 07 00 DA 07 00 E0 07 00 8B 45 07 00 38 FF 00 00 00 02 07 00 03 07 00 67 00 02 07 00 DA 07 00 E0 45 07 00 38 FF 00 00 00 02 07 00 03 07 00 67 00 03 07 00 DA 07 00 E0 07 00 8B 45 07 00 38 FF 00 00 00 02 07 00 03 07 00 67 00 03 07 00 DA 07 00 E0 07 00 8B FF 00 0B 00 02 07 00 03 07 00 67 00 03 07 00 DA 07 00 E0 07 00 8B FF 00 02 00 02 07 00 03 07 00 67 00 04 07 00 DA 07 00 E0 07 00 8B 01 FF 00 1F 00 02 07 00 03 07 00 67 00 03 07 00 DA 07 00 E0 07 00 8B 42 07 00 38 FF 00 00 00 02 07 00 03 07 00 67 00 03 07 00 DA 07 00 E0 07 00 8B 45 07 00 38 FF 00 00 00 02 07 00 03 07 00 67 00 02 07 00 DA 07 00 E0 42 07 00 15 FF 00 00 00 02 07 00 03 07 00 67 00 02 07 00 DA 07 00 E0 45 07 00 38 FF 00 00 00 02 07 00 03 07 00 67 00 02 07 00 DA 07 00 8B 42 07 00 38 FF 00 00 00 02 07 00 03 07 00 67 00 02 07 00 DA 07 00 8B 45 07 00 38 00 FF 00 00 00 02 07 00 03 07 00 67 00 02 07 00 8B 07 00 8B 41 07 00 67 FF 00 01 00 02 07 00 03 07 00 67 00 03 07 00 DA 08 07 1A 08 07 1A FF 00 01 00 02 07 00 03 07 00 67 00 02 07 00 8B 07 00 8B 01 41 07 00 59 41 07 00 03 FF 00 01 00 02 07 00 03 07 00 67 00 02 07 00 8B 07 00 8B 41 07 00 05 FF 00 01 00 02 07 00 03 07 00 67 00 03 07 00 DA 07 00 E0 07 00 8B 41 07 00 67 41 07 00 72 41 07 00 54 41 07 00 59 41 07 00 59 FF 00 01 00 02 07 00 03 07 00 67 00 02 07 00 8B 07 00 8B FF 00 01 00 02 07 00 03 07 00 67 00 02 07 00 DA 07 00 E0 41 07 00 05 FF 00 01 00 02 07 00 03 07 00 67 00 03 07 00 DA 07 00 E0 07 00 67 41 07 00 05 FF 00 01 00 02 07 00 03 07 00 67 00 03 07 00 DA 07 00 E0 07 00 8B FF 00 01 00 02 07 00 03 07 00 67 00 02 07 00 8B 07 00 8B 01 41 07 00 54 41 07 00 40 41 07 00 40 FF 00 01 00 02 07 00 03 07 00 67 00 02 07 00 8B 07 00 8B FF 00 01 00 02 07 00 03 07 00 67 00 02 07 00 8B 07 00 8B FF 00 01 00 02 07 00 03 07 00 67 00 03 07 00 DA 07 00 E0 07 00 8B 41 07 00 03 41 07 00 38 43 05 44 07 00 38 47 05 47 07 00 38
        //    Exceptions:
        //  Try           Handler
        //  Start  End    Start  End    Type                                       
        //  -----  -----  -----  -----  -------------------------------------------
        //  8      20     2379   2387   Any
        //  2379   2387   2379   2387   Ljava/lang/NegativeArraySizeException;
        //  2395   2397   3      8      Ljava/lang/RuntimeException;
        //  178    185    185    186    Any
        //  179    185    3      8      Ljava/lang/AssertionError;
        //  178    185    3      8      Any
        //  178    185    185    186    Ljava/lang/IndexOutOfBoundsException;
        //  178    185    178    179    Ljava/lang/EnumConstantNotPresentException;
        //  192    199    199    200    Any
        //  193    199    3      8      Any
        //  193    199    199    200    Any
        //  192    199    192    193    Ljava/lang/NegativeArraySizeException;
        //  192    199    199    200    Ljava/lang/IllegalStateException;
        //  283    290    290    291    Any
        //  283    290    3      8      Any
        //  283    290    3      8      Any
        //  283    290    3      8      Any
        //  283    290    283    284    Ljava/lang/ArrayIndexOutOfBoundsException;
        //  339    346    346    347    Any
        //  340    346    346    347    Any
        //  339    346    339    340    Any
        //  339    346    339    340    Any
        //  339    346    346    347    Ljava/lang/ArithmeticException;
        //  353    360    360    361    Any
        //  353    360    3      8      Ljava/lang/RuntimeException;
        //  353    360    3      8      Ljava/lang/AssertionError;
        //  354    360    353    354    Any
        //  353    360    353    354    Any
        //  414    421    421    422    Any
        //  414    421    3      8      Ljava/lang/AssertionError;
        //  414    421    414    415    Ljava/lang/NullPointerException;
        //  415    421    3      8      Ljava/lang/IndexOutOfBoundsException;
        //  415    421    414    415    Ljava/lang/ArithmeticException;
        //  429    435    435    436    Any
        //  429    435    3      8      Ljava/lang/AssertionError;
        //  429    435    3      8      Any
        //  429    435    3      8      Ljava/lang/NullPointerException;
        //  429    435    435    436    Any
        //  443    450    450    451    Any
        //  444    450    3      8      Ljava/lang/RuntimeException;
        //  443    450    443    444    Ljava/lang/IndexOutOfBoundsException;
        //  444    450    450    451    Ljava/lang/IllegalArgumentException;
        //  444    450    443    444    Any
        //  457    464    464    465    Any
        //  458    464    457    458    Ljava/lang/StringIndexOutOfBoundsException;
        //  458    464    457    458    Any
        //  458    464    3      8      Ljava/lang/IllegalArgumentException;
        //  457    464    3      8      Ljava/lang/EnumConstantNotPresentException;
        //  515    522    522    523    Any
        //  515    522    3      8      Any
        //  515    522    515    516    Any
        //  516    522    3      8      Any
        //  516    522    515    516    Any
        //  532    538    538    539    Any
        //  532    538    3      8      Any
        //  532    538    538    539    Ljava/util/NoSuchElementException;
        //  532    538    538    539    Ljava/lang/UnsupportedOperationException;
        //  532    538    538    539    Ljava/lang/ArithmeticException;
        //  542    549    549    550    Any
        //  542    549    3      8      Ljava/lang/UnsupportedOperationException;
        //  543    549    3      8      Ljava/lang/EnumConstantNotPresentException;
        //  543    549    542    543    Ljava/lang/UnsupportedOperationException;
        //  543    549    3      8      Any
        //  599    606    606    607    Any
        //  599    606    3      8      Any
        //  600    606    599    600    Any
        //  599    606    3      8      Any
        //  599    606    599    600    Ljava/lang/IndexOutOfBoundsException;
        //  611    617    617    618    Any
        //  611    617    3      8      Ljava/lang/UnsupportedOperationException;
        //  611    617    3      8      Ljava/lang/NumberFormatException;
        //  611    617    3      8      Ljava/util/ConcurrentModificationException;
        //  611    617    617    618    Ljava/lang/IndexOutOfBoundsException;
        //  628    635    635    636    Any
        //  628    635    628    629    Any
        //  628    635    635    636    Any
        //  628    635    635    636    Any
        //  629    635    3      8      Any
        //  642    649    649    650    Any
        //  642    649    642    643    Ljava/lang/IllegalStateException;
        //  642    649    649    650    Ljava/lang/NegativeArraySizeException;
        //  642    649    3      8      Any
        //  642    649    649    650    Ljava/lang/RuntimeException;
        //  689    696    696    697    Any
        //  689    696    689    690    Any
        //  689    696    689    690    Ljava/lang/IndexOutOfBoundsException;
        //  689    696    689    690    Any
        //  690    696    3      8      Any
        //  700    707    707    708    Any
        //  701    707    707    708    Ljava/lang/IllegalStateException;
        //  700    707    707    708    Ljava/util/NoSuchElementException;
        //  701    707    700    701    Any
        //  700    707    707    708    Any
        //  755    762    762    763    Any
        //  756    762    755    756    Ljava/lang/ArrayIndexOutOfBoundsException;
        //  755    762    3      8      Any
        //  756    762    755    756    Any
        //  756    762    3      8      Ljava/lang/ArrayIndexOutOfBoundsException;
        //  807    814    814    815    Any
        //  808    814    807    808    Any
        //  807    814    3      8      Ljava/lang/IllegalStateException;
        //  808    814    807    808    Any
        //  808    814    807    808    Ljava/lang/StringIndexOutOfBoundsException;
        //  868    874    874    875    Any
        //  868    874    874    875    Any
        //  868    874    874    875    Ljava/lang/IllegalStateException;
        //  868    874    3      8      Ljava/lang/NullPointerException;
        //  868    874    874    875    Any
        //  924    930    930    931    Any
        //  924    930    930    931    Any
        //  924    930    930    931    Ljava/lang/NullPointerException;
        //  924    930    3      8      Any
        //  924    930    930    931    Any
        //  940    946    946    947    Any
        //  940    946    3      8      Ljava/lang/IllegalStateException;
        //  940    946    3      8      Ljava/lang/AssertionError;
        //  940    946    946    947    Any
        //  940    946    3      8      Any
        //  991    998    998    999    Any
        //  991    998    991    992    Ljava/lang/NullPointerException;
        //  992    998    998    999    Ljava/lang/IndexOutOfBoundsException;
        //  991    998    998    999    Any
        //  991    998    3      8      Any
        //  1004   1011   1011   1012   Any
        //  1004   1011   1004   1005   Ljava/lang/AssertionError;
        //  1005   1011   1011   1012   Any
        //  1004   1011   3      8      Ljava/lang/ArithmeticException;
        //  1005   1011   3      8      Ljava/lang/ArithmeticException;
        //  1015   1022   1022   1023   Any
        //  1015   1022   3      8      Ljava/lang/ClassCastException;
        //  1015   1022   1015   1016   Any
        //  1016   1022   1015   1016   Any
        //  1016   1022   1022   1023   Any
        //  1033   1040   1040   1041   Any
        //  1033   1040   1033   1034   Any
        //  1033   1040   1040   1041   Ljava/util/NoSuchElementException;
        //  1034   1040   1040   1041   Any
        //  1034   1040   3      8      Ljava/lang/IllegalStateException;
        //  1047   1054   1054   1055   Any
        //  1048   1054   1047   1048   Ljava/lang/StringIndexOutOfBoundsException;
        //  1047   1054   1054   1055   Ljava/util/NoSuchElementException;
        //  1048   1054   3      8      Ljava/lang/NullPointerException;
        //  1048   1054   1054   1055   Ljava/lang/EnumConstantNotPresentException;
        //  1148   1154   1154   1155   Any
        //  1148   1154   3      8      Ljava/lang/NumberFormatException;
        //  1148   1154   3      8      Ljava/util/NoSuchElementException;
        //  1148   1154   3      8      Ljava/lang/NumberFormatException;
        //  1148   1154   1154   1155   Any
        //  1158   1165   1165   1166   Any
        //  1159   1165   1158   1159   Any
        //  1159   1165   1165   1166   Ljava/lang/ClassCastException;
        //  1158   1165   1165   1166   Any
        //  1158   1165   1165   1166   Ljava/lang/ArithmeticException;
        //  1172   1178   1178   1179   Any
        //  1172   1178   1178   1179   Any
        //  1172   1178   1178   1179   Ljava/lang/ClassCastException;
        //  1172   1178   1178   1179   Ljava/lang/RuntimeException;
        //  1172   1178   3      8      Ljava/lang/ArrayIndexOutOfBoundsException;
        //  1223   1230   1230   1231   Any
        //  1223   1230   1230   1231   Ljava/util/ConcurrentModificationException;
        //  1224   1230   3      8      Any
        //  1223   1230   1223   1224   Ljava/lang/ClassCastException;
        //  1224   1230   3      8      Ljava/lang/StringIndexOutOfBoundsException;
        //  1241   1248   1248   1249   Any
        //  1242   1248   1241   1242   Any
        //  1242   1248   1241   1242   Any
        //  1242   1248   1241   1242   Any
        //  1242   1248   1241   1242   Ljava/lang/IndexOutOfBoundsException;
        //  1299   1306   1306   1307   Any
        //  1299   1306   1306   1307   Any
        //  1299   1306   1299   1300   Ljava/lang/StringIndexOutOfBoundsException;
        //  1299   1306   1299   1300   Any
        //  1299   1306   1299   1300   Any
        //  1315   1322   1322   1323   Any
        //  1315   1322   1315   1316   Ljava/lang/ClassCastException;
        //  1316   1322   3      8      Ljava/lang/EnumConstantNotPresentException;
        //  1315   1322   1315   1316   Any
        //  1316   1322   1322   1323   Any
        //  1326   1333   1333   1334   Any
        //  1327   1333   3      8      Any
        //  1326   1333   3      8      Any
        //  1327   1333   3      8      Ljava/util/ConcurrentModificationException;
        //  1326   1333   1326   1327   Ljava/lang/IllegalArgumentException;
        //  1339   1346   1346   1347   Any
        //  1339   1346   1339   1340   Ljava/lang/NumberFormatException;
        //  1339   1346   3      8      Ljava/lang/NumberFormatException;
        //  1339   1346   1346   1347   Ljava/lang/StringIndexOutOfBoundsException;
        //  1339   1346   1339   1340   Ljava/lang/RuntimeException;
        //  1391   1398   1398   1399   Any
        //  1391   1398   1391   1392   Any
        //  1392   1398   3      8      Ljava/lang/NullPointerException;
        //  1392   1398   1398   1399   Any
        //  1392   1398   1398   1399   Any
        //  1451   1458   1458   1459   Any
        //  1451   1458   3      8      Ljava/lang/NullPointerException;
        //  1452   1458   3      8      Any
        //  1451   1458   1458   1459   Any
        //  1451   1458   1451   1452   Ljava/lang/UnsupportedOperationException;
        //  1465   1472   1472   1473   Any
        //  1466   1472   1472   1473   Any
        //  1465   1472   1465   1466   Ljava/lang/EnumConstantNotPresentException;
        //  1465   1472   3      8      Any
        //  1466   1472   3      8      Any
        //  1481   1488   1488   1489   Any
        //  1481   1488   1481   1482   Any
        //  1481   1488   1488   1489   Any
        //  1482   1488   1488   1489   Any
        //  1482   1488   1488   1489   Ljava/lang/UnsupportedOperationException;
        //  1535   1542   1542   1543   Any
        //  1536   1542   1535   1536   Any
        //  1536   1542   3      8      Any
        //  1536   1542   1535   1536   Any
        //  1536   1542   1542   1543   Any
        //  1591   1598   1598   1599   Any
        //  1591   1598   1598   1599   Any
        //  1592   1598   1591   1592   Ljava/lang/IllegalStateException;
        //  1591   1598   1591   1592   Ljava/lang/IllegalStateException;
        //  1591   1598   1598   1599   Ljava/lang/UnsupportedOperationException;
        //  1643   1650   1650   1651   Any
        //  1643   1650   1643   1644   Ljava/lang/NullPointerException;
        //  1643   1650   1650   1651   Any
        //  1644   1650   3      8      Ljava/lang/EnumConstantNotPresentException;
        //  1643   1650   1643   1644   Ljava/lang/AssertionError;
        //  1703   1710   1710   1711   Any
        //  1704   1710   1710   1711   Any
        //  1704   1710   1703   1704   Ljava/lang/ClassCastException;
        //  1704   1710   1710   1711   Ljava/util/NoSuchElementException;
        //  1704   1710   1710   1711   Ljava/lang/NumberFormatException;
        //  1718   1724   1724   1725   Any
        //  1718   1724   1724   1725   Any
        //  1718   1724   3      8      Ljava/lang/RuntimeException;
        //  1718   1724   3      8      Ljava/lang/UnsupportedOperationException;
        //  1718   1724   1724   1725   Ljava/lang/StringIndexOutOfBoundsException;
        //  1733   1740   1740   1741   Any
        //  1733   1740   1733   1734   Ljava/util/ConcurrentModificationException;
        //  1734   1740   1733   1734   Ljava/lang/StringIndexOutOfBoundsException;
        //  1733   1740   1733   1734   Ljava/util/ConcurrentModificationException;
        //  1733   1740   3      8      Any
        //  1790   1797   1797   1798   Any
        //  1791   1797   1797   1798   Ljava/lang/IndexOutOfBoundsException;
        //  1791   1797   3      8      Ljava/lang/NegativeArraySizeException;
        //  1791   1797   1790   1791   Any
        //  1791   1797   3      8      Any
        //  1804   1811   1811   1812   Any
        //  1804   1811   1804   1805   Ljava/util/NoSuchElementException;
        //  1805   1811   3      8      Ljava/util/ConcurrentModificationException;
        //  1804   1811   1811   1812   Ljava/lang/IllegalArgumentException;
        //  1804   1811   3      8      Ljava/lang/ArrayIndexOutOfBoundsException;
        //  1867   1874   1874   1875   Any
        //  1867   1874   1867   1868   Ljava/lang/NullPointerException;
        //  1868   1874   1867   1868   Any
        //  1867   1874   1867   1868   Any
        //  1868   1874   1867   1868   Any
        //  1881   1888   1888   1889   Any
        //  1881   1888   3      8      Ljava/lang/AssertionError;
        //  1881   1888   1888   1889   Ljava/util/NoSuchElementException;
        //  1882   1888   1881   1882   Ljava/lang/StringIndexOutOfBoundsException;
        //  1882   1888   1881   1882   Any
        //  1935   1942   1942   1943   Any
        //  1935   1942   1935   1936   Any
        //  1935   1942   3      8      Ljava/lang/NegativeArraySizeException;
        //  1935   1942   3      8      Ljava/lang/NullPointerException;
        //  1935   1942   3      8      Ljava/lang/NullPointerException;
        //  1947   1953   1953   1954   Any
        //  1947   1953   3      8      Ljava/util/ConcurrentModificationException;
        //  1947   1953   1953   1954   Any
        //  1947   1953   1953   1954   Ljava/lang/NullPointerException;
        //  1947   1953   3      8      Ljava/util/NoSuchElementException;
        //  2000   2006   2006   2007   Any
        //  2000   2006   3      8      Ljava/util/ConcurrentModificationException;
        //  2000   2006   2006   2007   Any
        //  2000   2006   3      8      Any
        //  2000   2006   3      8      Ljava/lang/ArithmeticException;
        //  2012   2019   2019   2020   Any
        //  2012   2019   2012   2013   Ljava/lang/ClassCastException;
        //  2012   2019   2012   2013   Any
        //  2012   2019   3      8      Ljava/util/NoSuchElementException;
        //  2013   2019   2012   2013   Any
        //  2024   2030   2030   2031   Any
        //  2024   2030   2030   2031   Any
        //  2024   2030   2030   2031   Any
        //  2024   2030   3      8      Ljava/lang/ArrayIndexOutOfBoundsException;
        //  2024   2030   3      8      Ljava/lang/IllegalArgumentException;
        //  2034   2041   2041   2042   Any
        //  2035   2041   3      8      Ljava/lang/ArrayIndexOutOfBoundsException;
        //  2034   2041   2034   2035   Any
        //  2034   2041   3      8      Ljava/lang/EnumConstantNotPresentException;
        //  2035   2041   2034   2035   Any
        //  2045   2052   2052   2053   Any
        //  2046   2052   2052   2053   Ljava/lang/EnumConstantNotPresentException;
        //  2045   2052   2052   2053   Any
        //  2045   2052   2052   2053   Any
        //  2046   2052   2045   2046   Ljava/util/ConcurrentModificationException;
        //  2066   2073   2073   2074   Any
        //  2067   2073   2073   2074   Ljava/lang/ArrayIndexOutOfBoundsException;
        //  2066   2073   2073   2074   Ljava/lang/NumberFormatException;
        //  2066   2073   2066   2067   Any
        //  2066   2073   2073   2074   Ljava/lang/EnumConstantNotPresentException;
        //  2127   2133   2133   2134   Any
        //  2127   2133   3      8      Ljava/lang/NumberFormatException;
        //  2127   2133   3      8      Ljava/lang/RuntimeException;
        //  2127   2133   3      8      Ljava/lang/ClassCastException;
        //  2127   2133   3      8      Any
        //  2138   2145   2145   2146   Any
        //  2138   2145   3      8      Ljava/lang/IllegalArgumentException;
        //  2139   2145   2145   2146   Ljava/lang/ClassCastException;
        //  2139   2145   2138   2139   Ljava/lang/EnumConstantNotPresentException;
        //  2138   2145   2145   2146   Ljava/lang/IllegalArgumentException;
        //  2149   2156   2156   2157   Any
        //  2149   2156   3      8      Ljava/lang/NullPointerException;
        //  2150   2156   3      8      Ljava/lang/NegativeArraySizeException;
        //  2149   2156   2149   2150   Any
        //  2149   2156   3      8      Ljava/lang/NumberFormatException;
        //  2207   2214   2214   2215   Any
        //  2208   2214   2207   2208   Any
        //  2208   2214   3      8      Any
        //  2207   2214   2214   2215   Ljava/util/ConcurrentModificationException;
        //  2207   2214   2214   2215   Ljava/lang/ArrayIndexOutOfBoundsException;
        //  2221   2228   2228   2229   Any
        //  2221   2228   2221   2222   Ljava/lang/ArithmeticException;
        //  2222   2228   2221   2222   Ljava/lang/IndexOutOfBoundsException;
        //  2221   2228   2228   2229   Any
        //  2222   2228   2221   2222   Any
        //  2279   2286   2286   2287   Any
        //  2279   2286   2286   2287   Any
        //  2279   2286   2279   2280   Any
        //  2280   2286   3      8      Ljava/lang/NegativeArraySizeException;
        //  2279   2286   2286   2287   Any
        //  2290   2297   2297   2298   Any
        //  2291   2297   2290   2291   Ljava/lang/NegativeArraySizeException;
        //  2290   2297   3      8      Any
        //  2291   2297   2297   2298   Ljava/lang/AssertionError;
        //  2290   2297   2290   2291   Ljava/lang/IllegalArgumentException;
        //  2301   2308   2308   2309   Any
        //  2302   2308   2301   2302   Any
        //  2301   2308   2308   2309   Ljava/lang/EnumConstantNotPresentException;
        //  2301   2308   2308   2309   Any
        //  2301   2308   2301   2302   Ljava/lang/IllegalStateException;
        // 
        // The error that occurred was:
        // 
        // java.lang.IndexOutOfBoundsException: Index -1 out of bounds for length 0
        //     at java.base/jdk.internal.util.Preconditions.outOfBounds(Preconditions.java:64)
        //     at java.base/jdk.internal.util.Preconditions.outOfBoundsCheckIndex(Preconditions.java:70)
        //     at java.base/jdk.internal.util.Preconditions.checkIndex(Preconditions.java:248)
        //     at java.base/java.util.Objects.checkIndex(Objects.java:372)
        //     at java.base/java.util.ArrayList.remove(ArrayList.java:535)
        //     at com.strobel.assembler.ir.StackMappingVisitor.pop(StackMappingVisitor.java:267)
        //     at com.strobel.assembler.ir.StackMappingVisitor$InstructionAnalyzer.execute(StackMappingVisitor.java:577)
        //     at com.strobel.assembler.ir.StackMappingVisitor$InstructionAnalyzer.visit(StackMappingVisitor.java:398)
        //     at com.strobel.decompiler.ast.AstBuilder.performStackAnalysis(AstBuilder.java:2030)
        //     at com.strobel.decompiler.ast.AstBuilder.build(AstBuilder.java:108)
        //     at com.strobel.decompiler.languages.java.ast.AstMethodBodyBuilder.createMethodBody(AstMethodBodyBuilder.java:211)
        //     at com.strobel.decompiler.languages.java.ast.AstMethodBodyBuilder.createMethodBody(AstMethodBodyBuilder.java:99)
        //     at com.strobel.decompiler.languages.java.ast.AstBuilder.createMethodBody(AstBuilder.java:782)
        //     at com.strobel.decompiler.languages.java.ast.AstBuilder.createMethod(AstBuilder.java:675)
        //     at com.strobel.decompiler.languages.java.ast.AstBuilder.addTypeMembers(AstBuilder.java:552)
        //     at com.strobel.decompiler.languages.java.ast.AstBuilder.createTypeCore(AstBuilder.java:519)
        //     at com.strobel.decompiler.languages.java.ast.AstBuilder.createTypeNoCache(AstBuilder.java:161)
        //     at com.strobel.decompiler.languages.java.ast.AstBuilder.createType(AstBuilder.java:150)
        //     at com.strobel.decompiler.languages.java.ast.AstBuilder.addType(AstBuilder.java:125)
        //     at com.strobel.decompiler.languages.java.JavaLanguage.buildAst(JavaLanguage.java:71)
        //     at com.strobel.decompiler.languages.java.JavaLanguage.decompileType(JavaLanguage.java:59)
        //     at com.strobel.decompiler.DecompilerDriver.decompileType(DecompilerDriver.java:330)
        //     at com.strobel.decompiler.DecompilerDriver.decompileJar(DecompilerDriver.java:251)
        //     at com.strobel.decompiler.DecompilerDriver.main(DecompilerDriver.java:126)
        // 
        throw new IllegalStateException("An error occurred while decompiling this method.");
    }
    
    public f6m() {
        // 
        // This method could not be decompiled.
        // 
        // Original Bytecode:
        // 
        //     1: ldc_w           "\u2236\u149b\u8b25\ub3cd\uc994\uec3c\ub230\ue700\ud96e\ue9e0\ua6f6\u1e5e"
        //     4: invokestatic    invokestatic   !!! ERROR
        //     7: ldc_w           "\u2216\u149b\u8b25\ub3cd\uc9b4\uec3c\ub230\ue700\ud96e\ue9e0\ua6f6\u1e5e"
        //    10: getstatic       dev/nuker/pyro/fc.c:I
        //    13: ifge            22
        //    16: ldc_w           395451642
        //    19: goto            25
        //    22: ldc_w           -1280590645
        //    25: ldc_w           -1614853264
        //    28: ixor           
        //    29: lookupswitch {
        //          -2010294390: 1220
        //          -5215815: 22
        //          default: 56
        //        }
        //    56: invokestatic    invokestatic   !!! ERROR
        //    59: ldc_w           "\u221b\u149c\u8b30\ub3d0\uc99c\uec3a\ub221\ue71a\ud928\ue9f0\ua6fc\u1e59\ue06d\uc5ae\u8160\u88e8\u57a7\u76c4\ubd3c\uc041\u2a87\uc22c\u6bcc\u2d53\ud785\u3410\u7d2a\u8827\u801c\u8cc1\u8571\ufb27\u7117\u9a13\u1b9c\uf0bb\u496f\u89e8\uca83\uff70\ub70c\u41f1\ub831\ub34d\u4c28\u8b6f\u7c6d\ucfe5\u7d5d\uea9a\ue70f\u16d4\uef9a\u378a\u46b3\ue02d\u0a12\u8708\u19d0\u0f15\u76cc\u7284\uc62d\ubbbd\u9ac4\u6bcf\ue2e8\ud1bd\ua53a\u259c\u8862\u4fb5\u8af8\u1401\ua39e\u715f\u55a0\u1da3\u61c3\u11d7\u89a9\u0524\uf90d\u2674"
        //    62: getstatic       dev/nuker/pyro/fc.1:I
        //    65: ifeq            74
        //    68: ldc_w           783984805
        //    71: goto            77
        //    74: ldc_w           618770856
        //    77: ldc_w           1740585780
        //    80: ixor           
        //    81: lookupswitch {
        //          1130269340: 108
        //          1225102225: 74
        //          default: 1240
        //        }
        //   108: invokestatic    invokestatic   !!! ERROR
        //   111: iconst_1       
        //   112: getstatic       dev/nuker/pyro/fc.c:I
        //   115: ifge            124
        //   118: ldc_w           -42620388
        //   121: goto            127
        //   124: ldc_w           -1119278697
        //   127: ldc_w           1226483676
        //   130: ixor           
        //   131: lookupswitch {
        //          -1267790400: 1228
        //          2129032403: 124
        //          default: 156
        //        }
        //   156: invokespecial   dev/nuker/pyro/fH.<init>:(Ljava/lang/String;Ljava/lang/String;Ljava/lang/String;Z)V
        //   159: aload_0        
        //   160: new             Ldev/nuker/pyro/f0a;
        //   163: dup            
        //   164: ldc_w           "\u2226\u149b\u8b2b\ub3ce\uc9bf\uec3d\ub225\ue70b\ud964\ue9ec\ua6f7"
        //   167: invokestatic    invokestatic   !!! ERROR
        //   170: ldc_w           "\u2206\u149b\u8b2b\ub3ce\uc9bf\uec3d\ub225\ue70b\ud964\ue9ec\ua6f7"
        //   173: getstatic       dev/nuker/pyro/fc.1:I
        //   176: ifeq            185
        //   179: ldc_w           471011315
        //   182: goto            188
        //   185: ldc_w           1150365693
        //   188: ldc_w           -730344042
        //   191: ixor           
        //   192: lookupswitch {
        //          -1863910805: 220
        //          -932914587: 185
        //          default: 1252
        //        }
        //   220: invokestatic    invokestatic   !!! ERROR
        //   223: aconst_null    
        //   224: iconst_1       
        //   225: invokespecial   dev/nuker/pyro/f0a.<init>:(Ljava/lang/String;Ljava/lang/String;Ljava/lang/String;Z)V
        //   228: getstatic       dev/nuker/pyro/fc.1:I
        //   231: ifeq            240
        //   234: ldc_w           1968107442
        //   237: goto            243
        //   240: ldc_w           1192425406
        //   243: ldc_w           -1115895694
        //   246: ixor           
        //   247: lookupswitch {
        //          -936237120: 1230
        //          185144133: 240
        //          default: 272
        //        }
        //   272: putfield        dev/nuker/pyro/f6m.c:Ldev/nuker/pyro/f0a;
        //   275: aload_0        
        //   276: new             Ldev/nuker/pyro/f0a;
        //   279: dup            
        //   280: ldc_w           "\u2226\u149b\u8b2b\ub3ce\uc9be\uec3a\ub237\ue708\ud96a\ue9e5\ua6f6\u1e48"
        //   283: getstatic       dev/nuker/pyro/fc.1:I
        //   286: ifeq            295
        //   289: ldc_w           118376018
        //   292: goto            298
        //   295: ldc_w           239295638
        //   298: ldc_w           1750354115
        //   301: ixor           
        //   302: lookupswitch {
        //          -1417336875: 295
        //          1868172945: 1236
        //          default: 328
        //        }
        //   328: invokestatic    invokestatic   !!! ERROR
        //   331: ldc_w           "\u2206\u149b\u8b2b\ub3ce\uc9be\uec3a\ub237\ue708\ud96a\ue9e5\ua6f6\u1e48"
        //   334: getstatic       dev/nuker/pyro/fc.0:I
        //   337: ifeq            346
        //   340: ldc_w           -589350854
        //   343: goto            349
        //   346: ldc_w           -1747858579
        //   349: ldc_w           2016802107
        //   352: ixor           
        //   353: lookupswitch {
        //          -1528115967: 1218
        //          519332390: 346
        //          default: 380
        //        }
        //   380: invokestatic    invokestatic   !!! ERROR
        //   383: aconst_null    
        //   384: iconst_1       
        //   385: invokespecial   dev/nuker/pyro/f0a.<init>:(Ljava/lang/String;Ljava/lang/String;Ljava/lang/String;Z)V
        //   388: putfield        dev/nuker/pyro/f6m.0:Ldev/nuker/pyro/f0a;
        //   391: aload_0        
        //   392: new             Ldev/nuker/pyro/f0a;
        //   395: dup            
        //   396: ldc_w           "\u2236\u149c\u8b29\ub3db\uc99b\uec27"
        //   399: invokestatic    invokestatic   !!! ERROR
        //   402: ldc_w           "\u2216\u149c\u8b29\ub3db\uc99b\uec27"
        //   405: invokestatic    invokestatic   !!! ERROR
        //   408: aconst_null    
        //   409: iconst_1       
        //   410: invokespecial   dev/nuker/pyro/f0a.<init>:(Ljava/lang/String;Ljava/lang/String;Ljava/lang/String;Z)V
        //   413: putfield        dev/nuker/pyro/f6m.1:Ldev/nuker/pyro/f0a;
        //   416: aload_0        
        //   417: new             Ldev/nuker/pyro/f0a;
        //   420: dup            
        //   421: ldc_w           "\u2230\u148b\u8b34\ub3d5\uc995\uec3a\ub230"
        //   424: invokestatic    invokestatic   !!! ERROR
        //   427: ldc_w           "\u2210\u148b\u8b34\ub3d5\uc995\uec3a\ub230"
        //   430: getstatic       dev/nuker/pyro/fc.1:I
        //   433: ifeq            442
        //   436: ldc_w           -770371921
        //   439: goto            445
        //   442: ldc_w           -1487652577
        //   445: ldc_w           -199945313
        //   448: ixor           
        //   449: lookupswitch {
        //          -2041519803: 442
        //          637541680: 1242
        //          default: 476
        //        }
        //   476: invokestatic    invokestatic   !!! ERROR
        //   479: aconst_null    
        //   480: iconst_1       
        //   481: invokespecial   dev/nuker/pyro/f0a.<init>:(Ljava/lang/String;Ljava/lang/String;Ljava/lang/String;Z)V
        //   484: putfield        dev/nuker/pyro/f6m.2:Ldev/nuker/pyro/f0a;
        //   487: aload_0        
        //   488: new             Ldev/nuker/pyro/f0a;
        //   491: dup            
        //   492: ldc_w           "\u2238\u149c\u8b32\ub3dc\uc997\uec36\ub22a\ue71d"
        //   495: getstatic       dev/nuker/pyro/fc.c:I
        //   498: ifge            507
        //   501: ldc_w           1926874204
        //   504: goto            510
        //   507: ldc_w           8101910
        //   510: ldc_w           -479496929
        //   513: ixor           
        //   514: lookupswitch {
        //          -1850560189: 507
        //          -485436151: 540
        //          default: 1214
        //        }
        //   540: invokestatic    invokestatic   !!! ERROR
        //   543: ldc_w           "\u2218\u149c\u8b32\ub3dc\uc997\uec36\ub22a\ue71d"
        //   546: invokestatic    invokestatic   !!! ERROR
        //   549: aconst_null    
        //   550: iconst_1       
        //   551: invokespecial   dev/nuker/pyro/f0a.<init>:(Ljava/lang/String;Ljava/lang/String;Ljava/lang/String;Z)V
        //   554: putfield        dev/nuker/pyro/f6m.3:Ldev/nuker/pyro/f0a;
        //   557: aload_0        
        //   558: new             Ldev/nuker/pyro/f0a;
        //   561: dup            
        //   562: ldc_w           "\u2238\u149a\u8b37\ub3da"
        //   565: invokestatic    invokestatic   !!! ERROR
        //   568: ldc_w           "\u2218\u149a\u8b37\ub3da"
        //   571: invokestatic    invokestatic   !!! ERROR
        //   574: aconst_null    
        //   575: iconst_1       
        //   576: invokespecial   dev/nuker/pyro/f0a.<init>:(Ljava/lang/String;Ljava/lang/String;Ljava/lang/String;Z)V
        //   579: putfield        dev/nuker/pyro/f6m.4:Ldev/nuker/pyro/f0a;
        //   582: aload_0        
        //   583: new             Ldev/nuker/pyro/f0a;
        //   586: dup            
        //   587: ldc_w           "\u2227\u1496\u8b2a\ub3dd\uc99f\uec21"
        //   590: getstatic       dev/nuker/pyro/fc.0:I
        //   593: ifeq            602
        //   596: ldc_w           1901268918
        //   599: goto            605
        //   602: ldc_w           -989202955
        //   605: ldc_w           -1701215136
        //   608: ixor           
        //   609: lookupswitch {
        //          -1841322520: 602
        //          -339047466: 1238
        //          default: 636
        //        }
        //   636: invokestatic    invokestatic   !!! ERROR
        //   639: ldc_w           "\u2207\u1496\u8b2a\ub3dd\uc99f\uec21"
        //   642: invokestatic    invokestatic   !!! ERROR
        //   645: aconst_null    
        //   646: iconst_1       
        //   647: invokespecial   dev/nuker/pyro/f0a.<init>:(Ljava/lang/String;Ljava/lang/String;Ljava/lang/String;Z)V
        //   650: getstatic       dev/nuker/pyro/fc.1:I
        //   653: ifeq            662
        //   656: ldc_w           562874709
        //   659: goto            665
        //   662: ldc_w           1975868022
        //   665: ldc_w           -823071369
        //   668: ixor           
        //   669: lookupswitch {
        //          -1154107647: 696
        //          -277076958: 662
        //          default: 1250
        //        }
        //   696: putfield        dev/nuker/pyro/f6m.5:Ldev/nuker/pyro/f0a;
        //   699: aload_0        
        //   700: new             Ldev/nuker/pyro/f0a;
        //   703: dup            
        //   704: ldc_w           "\u2222\u149c\u8b36\ub3d5\uc99e"
        //   707: invokestatic    invokestatic   !!! ERROR
        //   710: ldc_w           "\u2202\u149c\u8b36\ub3d5\uc99e"
        //   713: getstatic       dev/nuker/pyro/fc.0:I
        //   716: ifeq            725
        //   719: ldc_w           -523960489
        //   722: goto            728
        //   725: ldc_w           -1965824610
        //   728: ldc_w           -29620205
        //   731: ixor           
        //   732: lookupswitch {
        //          519632708: 725
        //          1961880973: 760
        //          default: 1248
        //        }
        //   760: invokestatic    invokestatic   !!! ERROR
        //   763: aconst_null    
        //   764: iconst_1       
        //   765: invokespecial   dev/nuker/pyro/f0a.<init>:(Ljava/lang/String;Ljava/lang/String;Ljava/lang/String;Z)V
        //   768: putfield        dev/nuker/pyro/f6m.6:Ldev/nuker/pyro/f0a;
        //   771: aload_0        
        //   772: aload_0        
        //   773: getfield        dev/nuker/pyro/f6m.c:Ldev/nuker/pyro/f0a;
        //   776: invokevirtual   dev/nuker/pyro/f6m.c:(Ldev/nuker/pyro/f0n;)Ldev/nuker/pyro/f0n;
        //   779: pop            
        //   780: getstatic       dev/nuker/pyro/fc.c:I
        //   783: ifge            792
        //   786: ldc_w           312912110
        //   789: goto            795
        //   792: ldc_w           1707185383
        //   795: ldc_w           1269637068
        //   798: ixor           
        //   799: lookupswitch {
        //          778865451: 824
        //          1493940002: 792
        //          default: 1226
        //        }
        //   824: aload_0        
        //   825: getstatic       dev/nuker/pyro/fc.c:I
        //   828: ifge            837
        //   831: ldc_w           -2104184453
        //   834: goto            840
        //   837: ldc_w           402405786
        //   840: ldc_w           -461198251
        //   843: ixor           
        //   844: lookupswitch {
        //          -1080935305: 837
        //          1712725294: 1222
        //          default: 872
        //        }
        //   872: aload_0        
        //   873: getstatic       dev/nuker/pyro/fc.1:I
        //   876: ifeq            885
        //   879: ldc_w           -737249428
        //   882: goto            888
        //   885: ldc_w           233758420
        //   888: ldc_w           32310232
        //   891: ixor           
        //   892: lookupswitch {
        //          -706513740: 885
        //          201579788: 920
        //          default: 1244
        //        }
        //   920: getfield        dev/nuker/pyro/f6m.0:Ldev/nuker/pyro/f0a;
        //   923: invokevirtual   dev/nuker/pyro/f6m.c:(Ldev/nuker/pyro/f0n;)Ldev/nuker/pyro/f0n;
        //   926: pop            
        //   927: getstatic       dev/nuker/pyro/fc.0:I
        //   930: ifeq            939
        //   933: ldc_w           -1049864209
        //   936: goto            942
        //   939: ldc_w           -2045534634
        //   942: ldc_w           -1225455250
        //   945: ixor           
        //   946: lookupswitch {
        //          -938046006: 939
        //          2006539905: 1232
        //          default: 972
        //        }
        //   972: aload_0        
        //   973: getstatic       dev/nuker/pyro/fc.0:I
        //   976: ifeq            985
        //   979: ldc_w           -1510139631
        //   982: goto            988
        //   985: ldc_w           250133890
        //   988: ldc_w           -640637216
        //   991: ixor           
        //   992: lookupswitch {
        //          -684188830: 1020
        //          2083373041: 985
        //          default: 1224
        //        }
        //  1020: aload_0        
        //  1021: getstatic       dev/nuker/pyro/fc.1:I
        //  1024: ifeq            1033
        //  1027: ldc_w           -1776470600
        //  1030: goto            1036
        //  1033: ldc_w           -1157775006
        //  1036: ldc_w           745492444
        //  1039: ixor           
        //  1040: lookupswitch {
        //          -1166902684: 1234
        //          -311567770: 1033
        //          default: 1068
        //        }
        //  1068: getfield        dev/nuker/pyro/f6m.1:Ldev/nuker/pyro/f0a;
        //  1071: invokevirtual   dev/nuker/pyro/f6m.c:(Ldev/nuker/pyro/f0n;)Ldev/nuker/pyro/f0n;
        //  1074: pop            
        //  1075: aload_0        
        //  1076: aload_0        
        //  1077: getfield        dev/nuker/pyro/f6m.2:Ldev/nuker/pyro/f0a;
        //  1080: invokevirtual   dev/nuker/pyro/f6m.c:(Ldev/nuker/pyro/f0n;)Ldev/nuker/pyro/f0n;
        //  1083: pop            
        //  1084: aload_0        
        //  1085: aload_0        
        //  1086: getstatic       dev/nuker/pyro/fc.0:I
        //  1089: ifeq            1098
        //  1092: ldc_w           -1160921845
        //  1095: goto            1101
        //  1098: ldc_w           1535664502
        //  1101: ldc_w           1947797631
        //  1104: ixor           
        //  1105: lookupswitch {
        //          -824920716: 1098
        //          798058761: 1132
        //          default: 1246
        //        }
        //  1132: getfield        dev/nuker/pyro/f6m.3:Ldev/nuker/pyro/f0a;
        //  1135: invokevirtual   dev/nuker/pyro/f6m.c:(Ldev/nuker/pyro/f0n;)Ldev/nuker/pyro/f0n;
        //  1138: pop            
        //  1139: aload_0        
        //  1140: aload_0        
        //  1141: getfield        dev/nuker/pyro/f6m.4:Ldev/nuker/pyro/f0a;
        //  1144: invokevirtual   dev/nuker/pyro/f6m.c:(Ldev/nuker/pyro/f0n;)Ldev/nuker/pyro/f0n;
        //  1147: pop            
        //  1148: aload_0        
        //  1149: aload_0        
        //  1150: getfield        dev/nuker/pyro/f6m.5:Ldev/nuker/pyro/f0a;
        //  1153: invokevirtual   dev/nuker/pyro/f6m.c:(Ldev/nuker/pyro/f0n;)Ldev/nuker/pyro/f0n;
        //  1156: pop            
        //  1157: getstatic       dev/nuker/pyro/fc.1:I
        //  1160: ifeq            1169
        //  1163: ldc_w           1691519059
        //  1166: goto            1172
        //  1169: ldc_w           -361827048
        //  1172: ldc_w           2141353976
        //  1175: ixor           
        //  1176: lookupswitch {
        //          -953897495: 1169
        //          460390315: 1216
        //          default: 1204
        //        }
        //  1204: aload_0        
        //  1205: aload_0        
        //  1206: getfield        dev/nuker/pyro/f6m.6:Ldev/nuker/pyro/f0a;
        //  1209: invokevirtual   dev/nuker/pyro/f6m.c:(Ldev/nuker/pyro/f0n;)Ldev/nuker/pyro/f0n;
        //  1212: pop            
        //  1213: return         
        //  1214: aconst_null    
        //  1215: athrow         
        //  1216: aconst_null    
        //  1217: athrow         
        //  1218: aconst_null    
        //  1219: athrow         
        //  1220: aconst_null    
        //  1221: athrow         
        //  1222: aconst_null    
        //  1223: athrow         
        //  1224: aconst_null    
        //  1225: athrow         
        //  1226: aconst_null    
        //  1227: athrow         
        //  1228: aconst_null    
        //  1229: athrow         
        //  1230: aconst_null    
        //  1231: athrow         
        //  1232: aconst_null    
        //  1233: athrow         
        //  1234: aconst_null    
        //  1235: athrow         
        //  1236: aconst_null    
        //  1237: athrow         
        //  1238: aconst_null    
        //  1239: athrow         
        //  1240: aconst_null    
        //  1241: athrow         
        //  1242: aconst_null    
        //  1243: athrow         
        //  1244: aconst_null    
        //  1245: athrow         
        //  1246: aconst_null    
        //  1247: athrow         
        //  1248: aconst_null    
        //  1249: athrow         
        //  1250: aconst_null    
        //  1251: athrow         
        //  1252: aconst_null    
        //  1253: athrow         
        //    StackMapTable: 00 50 FF 00 16 00 01 06 00 03 06 07 00 8B 07 00 8B FF 00 02 00 01 06 00 04 06 07 00 8B 07 00 8B 01 FF 00 1E 00 01 06 00 03 06 07 00 8B 07 00 8B FF 00 11 00 01 06 00 04 06 07 00 8B 07 00 8B 07 00 8B FF 00 02 00 01 06 00 05 06 07 00 8B 07 00 8B 07 00 8B 01 FF 00 1E 00 01 06 00 04 06 07 00 8B 07 00 8B 07 00 8B FF 00 0F 00 01 06 00 05 06 07 00 8B 07 00 8B 07 00 8B 01 FF 00 02 00 01 06 00 06 06 07 00 8B 07 00 8B 07 00 8B 01 01 FF 00 1C 00 01 06 00 05 06 07 00 8B 07 00 8B 07 00 8B 01 FF 00 1C 00 01 07 00 03 00 05 07 00 03 08 00 A0 08 00 A0 07 00 8B 07 00 8B FF 00 02 00 01 07 00 03 00 06 07 00 03 08 00 A0 08 00 A0 07 00 8B 07 00 8B 01 FF 00 1F 00 01 07 00 03 00 05 07 00 03 08 00 A0 08 00 A0 07 00 8B 07 00 8B FF 00 13 00 01 07 00 03 00 02 07 00 03 07 00 54 FF 00 02 00 01 07 00 03 00 03 07 00 03 07 00 54 01 FF 00 1C 00 01 07 00 03 00 02 07 00 03 07 00 54 FF 00 16 00 01 07 00 03 00 04 07 00 03 08 01 14 08 01 14 07 00 8B FF 00 02 00 01 07 00 03 00 05 07 00 03 08 01 14 08 01 14 07 00 8B 01 FF 00 1D 00 01 07 00 03 00 04 07 00 03 08 01 14 08 01 14 07 00 8B FF 00 11 00 01 07 00 03 00 05 07 00 03 08 01 14 08 01 14 07 00 8B 07 00 8B FF 00 02 00 01 07 00 03 00 06 07 00 03 08 01 14 08 01 14 07 00 8B 07 00 8B 01 FF 00 1E 00 01 07 00 03 00 05 07 00 03 08 01 14 08 01 14 07 00 8B 07 00 8B FF 00 3D 00 01 07 00 03 00 05 07 00 03 08 01 A1 08 01 A1 07 00 8B 07 00 8B FF 00 02 00 01 07 00 03 00 06 07 00 03 08 01 A1 08 01 A1 07 00 8B 07 00 8B 01 FF 00 1E 00 01 07 00 03 00 05 07 00 03 08 01 A1 08 01 A1 07 00 8B 07 00 8B FF 00 1E 00 01 07 00 03 00 04 07 00 03 08 01 E8 08 01 E8 07 00 8B FF 00 02 00 01 07 00 03 00 05 07 00 03 08 01 E8 08 01 E8 07 00 8B 01 FF 00 1D 00 01 07 00 03 00 04 07 00 03 08 01 E8 08 01 E8 07 00 8B FF 00 3D 00 01 07 00 03 00 04 07 00 03 08 02 47 08 02 47 07 00 8B FF 00 02 00 01 07 00 03 00 05 07 00 03 08 02 47 08 02 47 07 00 8B 01 FF 00 1E 00 01 07 00 03 00 04 07 00 03 08 02 47 08 02 47 07 00 8B FF 00 19 00 01 07 00 03 00 02 07 00 03 07 00 54 FF 00 02 00 01 07 00 03 00 03 07 00 03 07 00 54 01 FF 00 1E 00 01 07 00 03 00 02 07 00 03 07 00 54 FF 00 1C 00 01 07 00 03 00 05 07 00 03 08 02 BC 08 02 BC 07 00 8B 07 00 8B FF 00 02 00 01 07 00 03 00 06 07 00 03 08 02 BC 08 02 BC 07 00 8B 07 00 8B 01 FF 00 1F 00 01 07 00 03 00 05 07 00 03 08 02 BC 08 02 BC 07 00 8B 07 00 8B 1F 42 01 1C 4C 07 00 03 FF 00 02 00 01 07 00 03 00 02 07 00 03 01 5F 07 00 03 FF 00 0C 00 01 07 00 03 00 02 07 00 03 07 00 03 FF 00 02 00 01 07 00 03 00 03 07 00 03 07 00 03 01 FF 00 1F 00 01 07 00 03 00 02 07 00 03 07 00 03 12 42 01 1D 4C 07 00 03 FF 00 02 00 01 07 00 03 00 02 07 00 03 01 5F 07 00 03 FF 00 0C 00 01 07 00 03 00 02 07 00 03 07 00 03 FF 00 02 00 01 07 00 03 00 03 07 00 03 07 00 03 01 FF 00 1F 00 01 07 00 03 00 02 07 00 03 07 00 03 FF 00 1D 00 01 07 00 03 00 02 07 00 03 07 00 03 FF 00 02 00 01 07 00 03 00 03 07 00 03 07 00 03 01 FF 00 1E 00 01 07 00 03 00 02 07 00 03 07 00 03 24 42 01 1F FF 00 09 00 01 07 00 03 00 04 07 00 03 08 01 E8 08 01 E8 07 00 8B 01 FF 00 01 00 01 07 00 03 00 05 07 00 03 08 01 14 08 01 14 07 00 8B 07 00 8B FF 00 01 00 01 06 00 03 06 07 00 8B 07 00 8B FF 00 01 00 01 07 00 03 00 01 07 00 03 41 07 00 03 01 FF 00 01 00 01 06 00 05 06 07 00 8B 07 00 8B 07 00 8B 01 FF 00 01 00 01 07 00 03 00 02 07 00 03 07 00 54 01 FF 00 01 00 01 07 00 03 00 02 07 00 03 07 00 03 FF 00 01 00 01 07 00 03 00 04 07 00 03 08 01 14 08 01 14 07 00 8B FF 00 01 00 01 07 00 03 00 04 07 00 03 08 02 47 08 02 47 07 00 8B FF 00 01 00 01 06 00 04 06 07 00 8B 07 00 8B 07 00 8B FF 00 01 00 01 07 00 03 00 05 07 00 03 08 01 A1 08 01 A1 07 00 8B 07 00 8B FF 00 01 00 01 07 00 03 00 02 07 00 03 07 00 03 FF 00 01 00 01 07 00 03 00 02 07 00 03 07 00 03 FF 00 01 00 01 07 00 03 00 05 07 00 03 08 02 BC 08 02 BC 07 00 8B 07 00 8B FF 00 01 00 01 07 00 03 00 02 07 00 03 07 00 54 FF 00 01 00 01 07 00 03 00 05 07 00 03 08 00 A0 08 00 A0 07 00 8B 07 00 8B
        // 
        // The error that occurred was:
        // 
        // java.lang.IllegalStateException: Invalid BootstrapMethods attribute entry: 21 additional arguments required for method a.a, but only 0 specified.
        //     at com.strobel.assembler.ir.Error.invalidBootstrapMethodEntry(Error.java:244)
        //     at com.strobel.assembler.ir.MetadataReader.readAttributeCore(MetadataReader.java:280)
        //     at com.strobel.assembler.metadata.ClassFileReader.readAttributeCore(ClassFileReader.java:261)
        //     at com.strobel.assembler.ir.MetadataReader.inflateAttributes(MetadataReader.java:439)
        //     at com.strobel.assembler.metadata.ClassFileReader.visitAttributes(ClassFileReader.java:1134)
        //     at com.strobel.assembler.metadata.ClassFileReader.readClass(ClassFileReader.java:439)
        //     at com.strobel.assembler.metadata.ClassFileReader.readClass(ClassFileReader.java:377)
        //     at com.strobel.assembler.metadata.MetadataSystem.resolveType(MetadataSystem.java:129)
        //     at com.strobel.decompiler.NoRetryMetadataSystem.resolveType(DecompilerDriver.java:476)
        //     at com.strobel.assembler.metadata.MetadataSystem.resolveCore(MetadataSystem.java:81)
        //     at com.strobel.assembler.metadata.MetadataResolver.resolve(MetadataResolver.java:104)
        //     at com.strobel.assembler.metadata.CoreMetadataFactory$UnresolvedType.resolve(CoreMetadataFactory.java:616)
        //     at com.strobel.assembler.metadata.MetadataResolver.resolve(MetadataResolver.java:128)
        //     at com.strobel.assembler.metadata.CoreMetadataFactory$UnresolvedType.resolve(CoreMetadataFactory.java:626)
        //     at com.strobel.assembler.metadata.MethodReference.resolve(MethodReference.java:177)
        //     at com.strobel.decompiler.ast.TypeAnalysis.inferCall(TypeAnalysis.java:2438)
        //     at com.strobel.decompiler.ast.TypeAnalysis.doInferTypeForExpression(TypeAnalysis.java:1029)
        //     at com.strobel.decompiler.ast.TypeAnalysis.inferTypeForExpression(TypeAnalysis.java:803)
        //     at com.strobel.decompiler.ast.TypeAnalysis.inferTypeForExpression(TypeAnalysis.java:770)
        //     at com.strobel.decompiler.ast.TypeAnalysis.doInferTypeForExpression(TypeAnalysis.java:881)
        //     at com.strobel.decompiler.ast.TypeAnalysis.inferTypeForExpression(TypeAnalysis.java:803)
        //     at com.strobel.decompiler.ast.TypeAnalysis.runInference(TypeAnalysis.java:672)
        //     at com.strobel.decompiler.ast.TypeAnalysis.runInference(TypeAnalysis.java:655)
        //     at com.strobel.decompiler.ast.TypeAnalysis.runInference(TypeAnalysis.java:365)
        //     at com.strobel.decompiler.ast.TypeAnalysis.run(TypeAnalysis.java:96)
        //     at com.strobel.decompiler.ast.AstOptimizer.optimize(AstOptimizer.java:109)
        //     at com.strobel.decompiler.ast.AstOptimizer.optimize(AstOptimizer.java:42)
        //     at com.strobel.decompiler.languages.java.ast.AstMethodBodyBuilder.createMethodBody(AstMethodBodyBuilder.java:214)
        //     at com.strobel.decompiler.languages.java.ast.AstMethodBodyBuilder.createMethodBody(AstMethodBodyBuilder.java:99)
        //     at com.strobel.decompiler.languages.java.ast.AstBuilder.createMethodBody(AstBuilder.java:782)
        //     at com.strobel.decompiler.languages.java.ast.AstBuilder.createConstructor(AstBuilder.java:713)
        //     at com.strobel.decompiler.languages.java.ast.AstBuilder.addTypeMembers(AstBuilder.java:549)
        //     at com.strobel.decompiler.languages.java.ast.AstBuilder.createTypeCore(AstBuilder.java:519)
        //     at com.strobel.decompiler.languages.java.ast.AstBuilder.createTypeNoCache(AstBuilder.java:161)
        //     at com.strobel.decompiler.languages.java.ast.AstBuilder.createType(AstBuilder.java:150)
        //     at com.strobel.decompiler.languages.java.ast.AstBuilder.addType(AstBuilder.java:125)
        //     at com.strobel.decompiler.languages.java.JavaLanguage.buildAst(JavaLanguage.java:71)
        //     at com.strobel.decompiler.languages.java.JavaLanguage.decompileType(JavaLanguage.java:59)
        //     at com.strobel.decompiler.DecompilerDriver.decompileType(DecompilerDriver.java:330)
        //     at com.strobel.decompiler.DecompilerDriver.decompileJar(DecompilerDriver.java:251)
        //     at com.strobel.decompiler.DecompilerDriver.main(DecompilerDriver.java:126)
        // 
        throw new IllegalStateException("An error occurred while decompiling this method.");
    }
    
    static {
        throw t;
    }
}
