// 
// Decompiled by Procyon v0.5.36
// 

package dev.nuker.pyro;

import org.jetbrains.annotations.NotNull;

public class f8X extends f8W
{
    @Override
    public void c(@NotNull final f3i p0) {
        // 
        // This method could not be decompiled.
        // 
        // Original Bytecode:
        // 
        //     3: dup            
        //     4: ifnull          531
        //     7: athrow         
        //     8: aconst_null    
        //     9: getstatic       dev/nuker/pyro/fc.1:I
        //    12: ifgt            523
        //    15: pop            
        //    16: aconst_null    
        //    17: goto            515
        //    20: nop            
        //    21: nop            
        //    22: nop            
        //    23: athrow         
        //    24: aload_1        
        //    25: pop            
        //    26: getstatic       dev/nuker/pyro/fc.1:I
        //    29: ifeq            37
        //    32: ldc             -1534019126
        //    34: goto            39
        //    37: ldc             2111817260
        //    39: ldc             -2100097597
        //    41: ixor           
        //    42: lookupswitch {
        //          641971209: 498
        //          1633474706: 37
        //          default: 68
        //        }
        //    68: aload_1        
        //    69: goto            73
        //    72: athrow         
        //    73: invokevirtual   dev/nuker/pyro/f3i.c:()Ldev/nuker/pyro/f2T;
        //    76: goto            80
        //    79: athrow         
        //    80: getstatic       dev/nuker/pyro/f2T.c:Ldev/nuker/pyro/f2T;
        //    83: if_acmpne       491
        //    86: goto            90
        //    89: athrow         
        //    90: invokestatic    dev/nuker/pyro/fbl.7:()Z
        //    93: goto            97
        //    96: athrow         
        //    97: ifeq            105
        //   100: ldc             1300415733
        //   102: goto            107
        //   105: ldc             1300415734
        //   107: ldc             471772152
        //   109: ixor           
        //   110: tableswitch {
        //          -1556554214: 132
        //          -1556554213: 491
        //          default: 100
        //        }
        //   132: getstatic       dev/nuker/pyro/f8W.c:Lnet/minecraft/client/Minecraft;
        //   135: getfield        net/minecraft/client/Minecraft.field_71439_g:Lnet/minecraft/client/entity/EntityPlayerSP;
        //   138: dup            
        //   139: pop            
        //   140: getstatic       dev/nuker/pyro/fc.0:I
        //   143: ifeq            151
        //   146: ldc             519838365
        //   148: goto            153
        //   151: ldc             -1709800509
        //   153: ldc             1999341364
        //   155: ixor           
        //   156: lookupswitch {
        //          -314768137: 184
        //          1775738281: 151
        //          default: 494
        //        }
        //   184: goto            188
        //   187: athrow         
        //   188: invokevirtual   net/minecraft/client/entity/EntityPlayerSP.func_70093_af:()Z
        //   191: goto            195
        //   194: athrow         
        //   195: ifne            491
        //   198: getstatic       dev/nuker/pyro/fc.c:I
        //   201: ifge            209
        //   204: ldc             -1939464785
        //   206: goto            211
        //   209: ldc             901283660
        //   211: ldc             -836523704
        //   213: ixor           
        //   214: lookupswitch {
        //          -8382117: 209
        //          1111864551: 492
        //          default: 240
        //        }
        //   240: getstatic       dev/nuker/pyro/f8W.c:Lnet/minecraft/client/Minecraft;
        //   243: getstatic       dev/nuker/pyro/fc.0:I
        //   246: ifeq            254
        //   249: ldc             791168957
        //   251: goto            256
        //   254: ldc             -1450309733
        //   256: ldc             -197498543
        //   258: ixor           
        //   259: lookupswitch {
        //          -1366058182: 254
        //          -619565332: 504
        //          default: 284
        //        }
        //   284: getfield        net/minecraft/client/Minecraft.field_71439_g:Lnet/minecraft/client/entity/EntityPlayerSP;
        //   287: fconst_0       
        //   288: putfield        net/minecraft/client/entity/EntityPlayerSP.field_70726_aT:F
        //   291: getstatic       dev/nuker/pyro/f8W.c:Lnet/minecraft/client/Minecraft;
        //   294: getfield        net/minecraft/client/Minecraft.field_71439_g:Lnet/minecraft/client/entity/EntityPlayerSP;
        //   297: getfield        net/minecraft/client/entity/EntityPlayerSP.field_70122_E:Z
        //   300: ifeq            479
        //   303: getstatic       dev/nuker/pyro/f8W.c:Lnet/minecraft/client/Minecraft;
        //   306: getstatic       dev/nuker/pyro/fc.1:I
        //   309: ifeq            317
        //   312: ldc             -141184609
        //   314: goto            319
        //   317: ldc             2090931951
        //   319: ldc             -1676790111
        //   321: ixor           
        //   322: lookupswitch {
        //          -2091867096: 317
        //          1805354814: 500
        //          default: 348
        //        }
        //   348: getfield        net/minecraft/client/Minecraft.field_71439_g:Lnet/minecraft/client/entity/EntityPlayerSP;
        //   351: ldc2_w          0.3425
        //   354: putfield        net/minecraft/client/entity/EntityPlayerSP.field_70181_x:D
        //   357: getstatic       dev/nuker/pyro/fc.c:I
        //   360: ifge            368
        //   363: ldc             755521973
        //   365: goto            370
        //   368: ldc             1072926751
        //   370: ldc             -130804586
        //   372: ixor           
        //   373: lookupswitch {
        //          -717468381: 502
        //          1374853094: 368
        //          default: 400
        //        }
        //   400: getstatic       dev/nuker/pyro/f8W.c:Lnet/minecraft/client/Minecraft;
        //   403: getfield        net/minecraft/client/Minecraft.field_71439_g:Lnet/minecraft/client/entity/EntityPlayerSP;
        //   406: dup            
        //   407: getfield        net/minecraft/client/entity/EntityPlayerSP.field_70159_w:D
        //   410: ldc2_w          1.5893
        //   413: dmul           
        //   414: getstatic       dev/nuker/pyro/fc.0:I
        //   417: ifeq            425
        //   420: ldc             -269262208
        //   422: goto            427
        //   425: ldc             -1825268055
        //   427: ldc             -1344168869
        //   429: ixor           
        //   430: lookupswitch {
        //          1020592882: 456
        //          1074986715: 425
        //          default: 496
        //        }
        //   456: putfield        net/minecraft/client/entity/EntityPlayerSP.field_70159_w:D
        //   459: getstatic       dev/nuker/pyro/f8W.c:Lnet/minecraft/client/Minecraft;
        //   462: getfield        net/minecraft/client/Minecraft.field_71439_g:Lnet/minecraft/client/entity/EntityPlayerSP;
        //   465: dup            
        //   466: getfield        net/minecraft/client/entity/EntityPlayerSP.field_70179_y:D
        //   469: ldc2_w          1.5893
        //   472: dmul           
        //   473: putfield        net/minecraft/client/entity/EntityPlayerSP.field_70179_y:D
        //   476: goto            491
        //   479: getstatic       dev/nuker/pyro/f8W.c:Lnet/minecraft/client/Minecraft;
        //   482: getfield        net/minecraft/client/Minecraft.field_71439_g:Lnet/minecraft/client/entity/EntityPlayerSP;
        //   485: ldc2_w          -0.19
        //   488: putfield        net/minecraft/client/entity/EntityPlayerSP.field_70181_x:D
        //   491: return         
        //   492: aconst_null    
        //   493: athrow         
        //   494: aconst_null    
        //   495: athrow         
        //   496: aconst_null    
        //   497: athrow         
        //   498: aconst_null    
        //   499: athrow         
        //   500: aconst_null    
        //   501: athrow         
        //   502: aconst_null    
        //   503: athrow         
        //   504: aconst_null    
        //   505: athrow         
        //   506: pop            
        //   507: goto            24
        //   510: pop            
        //   511: aconst_null    
        //   512: goto            506
        //   515: dup            
        //   516: ifnull          506
        //   519: checkcast       Ljava/lang/Throwable;
        //   522: athrow         
        //   523: dup            
        //   524: ifnull          510
        //   527: checkcast       Ljava/lang/Throwable;
        //   530: athrow         
        //   531: aconst_null    
        //   532: athrow         
        //    StackMapTable: 00 37 43 07 00 20 04 FF 00 0B 00 00 00 01 07 00 20 FD 00 03 07 00 03 07 00 25 0C 41 01 1C 43 07 00 20 40 07 00 25 45 07 00 20 40 07 00 2A 48 07 00 12 00 45 07 00 20 40 01 02 04 41 01 18 52 07 00 47 FF 00 01 00 02 07 00 03 07 00 25 00 02 07 00 47 01 5E 07 00 47 42 07 00 18 40 07 00 47 45 07 00 20 40 01 0D 41 01 1C 4D 07 00 3B FF 00 01 00 02 07 00 03 07 00 25 00 02 07 00 3B 01 5B 07 00 3B 60 07 00 3B FF 00 01 00 02 07 00 03 07 00 25 00 02 07 00 3B 01 5C 07 00 3B 13 41 01 1D FF 00 18 00 02 07 00 03 07 00 25 00 02 07 00 47 03 FF 00 01 00 02 07 00 03 07 00 25 00 03 07 00 47 03 01 FF 00 1C 00 02 07 00 03 07 00 25 00 02 07 00 47 03 16 0B 00 41 07 00 47 FF 00 01 00 02 07 00 03 07 00 25 00 02 07 00 47 03 01 41 07 00 3B 01 41 07 00 3B 41 07 00 20 43 05 44 07 00 20 47 05 47 07 00 20
        //    Exceptions:
        //  Try           Handler
        //  Start  End    Start  End    Type                                       
        //  -----  -----  -----  -----  -------------------------------------------
        //  8      20     515    523    Any
        //  515    523    515    523    Any
        //  531    533    3      8      Ljava/lang/NullPointerException;
        //  72     79     79     80     Any
        //  72     79     3      8      Any
        //  72     79     72     73     Ljava/lang/IllegalArgumentException;
        //  73     79     72     73     Ljava/lang/AssertionError;
        //  73     79     3      8      Any
        //  89     96     96     97     Any
        //  90     96     96     97     Ljava/util/ConcurrentModificationException;
        //  89     96     89     90     Ljava/lang/StringIndexOutOfBoundsException;
        //  90     96     96     97     Ljava/lang/UnsupportedOperationException;
        //  90     96     96     97     Ljava/lang/IllegalStateException;
        //  187    194    194    195    Any
        //  187    194    3      8      Any
        //  187    194    187    188    Ljava/lang/RuntimeException;
        //  187    194    194    195    Ljava/lang/UnsupportedOperationException;
        //  187    194    3      8      Any
        // 
        // The error that occurred was:
        // 
        // java.lang.IndexOutOfBoundsException: Index -1 out of bounds for length 0
        //     at java.base/jdk.internal.util.Preconditions.outOfBounds(Preconditions.java:64)
        //     at java.base/jdk.internal.util.Preconditions.outOfBoundsCheckIndex(Preconditions.java:70)
        //     at java.base/jdk.internal.util.Preconditions.checkIndex(Preconditions.java:248)
        //     at java.base/java.util.Objects.checkIndex(Objects.java:372)
        //     at java.base/java.util.ArrayList.remove(ArrayList.java:535)
        //     at com.strobel.assembler.ir.StackMappingVisitor.pop(StackMappingVisitor.java:267)
        //     at com.strobel.assembler.ir.StackMappingVisitor$InstructionAnalyzer.execute(StackMappingVisitor.java:543)
        //     at com.strobel.assembler.ir.StackMappingVisitor$InstructionAnalyzer.visit(StackMappingVisitor.java:398)
        //     at com.strobel.decompiler.ast.AstBuilder.performStackAnalysis(AstBuilder.java:2030)
        //     at com.strobel.decompiler.ast.AstBuilder.build(AstBuilder.java:108)
        //     at com.strobel.decompiler.languages.java.ast.AstMethodBodyBuilder.createMethodBody(AstMethodBodyBuilder.java:211)
        //     at com.strobel.decompiler.languages.java.ast.AstMethodBodyBuilder.createMethodBody(AstMethodBodyBuilder.java:99)
        //     at com.strobel.decompiler.languages.java.ast.AstBuilder.createMethodBody(AstBuilder.java:782)
        //     at com.strobel.decompiler.languages.java.ast.AstBuilder.createMethod(AstBuilder.java:675)
        //     at com.strobel.decompiler.languages.java.ast.AstBuilder.addTypeMembers(AstBuilder.java:552)
        //     at com.strobel.decompiler.languages.java.ast.AstBuilder.createTypeCore(AstBuilder.java:519)
        //     at com.strobel.decompiler.languages.java.ast.AstBuilder.createTypeNoCache(AstBuilder.java:161)
        //     at com.strobel.decompiler.languages.java.ast.AstBuilder.createType(AstBuilder.java:150)
        //     at com.strobel.decompiler.languages.java.ast.AstBuilder.addType(AstBuilder.java:125)
        //     at com.strobel.decompiler.languages.java.JavaLanguage.buildAst(JavaLanguage.java:71)
        //     at com.strobel.decompiler.languages.java.JavaLanguage.decompileType(JavaLanguage.java:59)
        //     at com.strobel.decompiler.DecompilerDriver.decompileType(DecompilerDriver.java:330)
        //     at com.strobel.decompiler.DecompilerDriver.decompileJar(DecompilerDriver.java:251)
        //     at com.strobel.decompiler.DecompilerDriver.main(DecompilerDriver.java:126)
        // 
        throw new IllegalStateException("An error occurred while decompiling this method.");
    }
    
    @Override
    public void 0() {
        fbS.e3(this, 203042765);
    }
    
    @Override
    public void c(@NotNull final f3e f3e) {
        fbS.5H(this, 438468705, f3e);
    }
    
    static {
        throw t;
    }
    
    @Override
    public void c() {
        fbS.da(this, 1918674742);
    }
}
