// 
// Decompiled by Procyon v0.5.36
// 

package dev.nuker.pyro;

import net.minecraft.client.renderer.DestroyBlockProgress;
import org.jetbrains.annotations.Nullable;
import net.minecraft.util.math.Vec3d;

public class f9e extends fH
{
    public f0b c;
    public f0b 0;
    public f0a c;
    public f0a 0;
    public f0a 1;
    public f0k c;
    
    public f9e() {
        // 
        // This method could not be decompiled.
        // 
        // Original Bytecode:
        // 
        //     1: ldc             "\u225c\u1481\u8b4a\ub3d8\uc93e\uec70\ub22d\ue765\ud960\ue94a\ua691\u1e4b\ue04e\uc5b3"
        //     3: getstatic       dev/nuker/pyro/fc.c:I
        //     6: ifge            14
        //     9: ldc             -82417887
        //    11: goto            16
        //    14: ldc             1953461304
        //    16: ldc             404244614
        //    18: ixor           
        //    19: lookupswitch {
        //          -485609561: 822
        //          427872159: 14
        //          default: 44
        //        }
        //    44: invokestatic    invokestatic   !!! ERROR
        //    47: ldc             "\u227c\u1481\u8b4a\ub3d8\uc93e\uec70\ub22d\ue765\ud960\ue94a\ua691\u1e4b\ue04e\uc5b3"
        //    49: invokestatic    invokestatic   !!! ERROR
        //    52: ldc             "\u226c\u1496\u8b41\ub3dd\uc930\uec4a\ub237\ue722\ud96d\ue95e\ua68c\u1e5e\ue047\uc5e7\u81d5\u88cb\u57ad\u76a9\ubd3a\uc0e9\u2aec\uc234\u6ba1\u2d16\ud726\u3437\u7d24\u880f\u801a\u8c72\u855e\ufb26\u7178\u9a17\u1b67\uf099\u4979\u89cd\uca83\uffdc\ub76f\u41f6\ub845\ub308\u4c82\u8b59\u7c6c\ucfc7\u7d43\uea3d\ue768\u16d1\ueffa\u3789"
        //    54: invokestatic    invokestatic   !!! ERROR
        //    57: iconst_1       
        //    58: invokespecial   dev/nuker/pyro/fH.<init>:(Ljava/lang/String;Ljava/lang/String;Ljava/lang/String;Z)V
        //    61: aload_0        
        //    62: new             Ldev/nuker/pyro/f0b;
        //    65: dup            
        //    66: ldc             "\u225d\u149c\u8b43\ub3d6\uc927"
        //    68: invokestatic    invokestatic   !!! ERROR
        //    71: ldc             "\u227b\u149d\u8b4a\ub3d4\uc92c\uec7b\ub22b\ue76e\ud967\ue954"
        //    73: invokestatic    invokestatic   !!! ERROR
        //    76: aconst_null    
        //    77: new             Ldev/nuker/pyro/fS;
        //    80: dup            
        //    81: ldc             0.1
        //    83: fconst_1       
        //    84: ldc             0.5
        //    86: ldc             0.5
        //    88: invokespecial   dev/nuker/pyro/fS.<init>:(FFFF)V
        //    91: getstatic       dev/nuker/pyro/fc.1:I
        //    94: ifeq            102
        //    97: ldc             913013132
        //    99: goto            104
        //   102: ldc             1805579186
        //   104: ldc             -329850753
        //   106: ixor           
        //   107: lookupswitch {
        //          -2016930867: 132
        //          -633497101: 102
        //          default: 820
        //        }
        //   132: invokespecial   dev/nuker/pyro/f0b.<init>:(Ljava/lang/String;Ljava/lang/String;Ljava/lang/String;Ldev/nuker/pyro/fS;)V
        //   135: putfield        dev/nuker/pyro/f9e.c:Ldev/nuker/pyro/f0b;
        //   138: aload_0        
        //   139: new             Ldev/nuker/pyro/f0b;
        //   142: dup            
        //   143: ldc             "\u227c\u1492\u8b5d\ub3fa\uc93a\uec54\ub22b\ue770"
        //   145: invokestatic    invokestatic   !!! ERROR
        //   148: ldc             "\u227c\u1492\u8b5d\ub3fa\uc93a\uec54\ub22b\ue770"
        //   150: getstatic       dev/nuker/pyro/fc.0:I
        //   153: ifeq            161
        //   156: ldc             1849380309
        //   158: goto            163
        //   161: ldc             17534562
        //   163: ldc             984797424
        //   165: ixor           
        //   166: lookupswitch {
        //          1002004114: 192
        //          1418304805: 161
        //          default: 806
        //        }
        //   192: invokestatic    invokestatic   !!! ERROR
        //   195: aconst_null    
        //   196: new             Ldev/nuker/pyro/fS;
        //   199: dup            
        //   200: fconst_0       
        //   201: fconst_1       
        //   202: ldc             0.5
        //   204: fconst_1       
        //   205: invokespecial   dev/nuker/pyro/fS.<init>:(FFFF)V
        //   208: invokespecial   dev/nuker/pyro/f0b.<init>:(Ljava/lang/String;Ljava/lang/String;Ljava/lang/String;Ldev/nuker/pyro/fS;)V
        //   211: putfield        dev/nuker/pyro/f9e.0:Ldev/nuker/pyro/f0b;
        //   214: getstatic       dev/nuker/pyro/fc.0:I
        //   217: ifeq            225
        //   220: ldc             -1122790414
        //   222: goto            227
        //   225: ldc             -191268511
        //   227: ldc             -1146708182
        //   229: ixor           
        //   230: lookupswitch {
        //          112528600: 225
        //          1329587787: 256
        //          default: 826
        //        }
        //   256: aload_0        
        //   257: new             Ldev/nuker/pyro/f0a;
        //   260: dup            
        //   261: ldc             "\u224c\u1496\u8b41\ub3dd\uc930\uec4a\ub214\ue761\ud97c"
        //   263: invokestatic    invokestatic   !!! ERROR
        //   266: ldc             "\u226e\u1490\u8b5b"
        //   268: getstatic       dev/nuker/pyro/fc.0:I
        //   271: ifeq            279
        //   274: ldc             46659608
        //   276: goto            281
        //   279: ldc             -1983015154
        //   281: ldc             702251107
        //   283: ixor           
        //   284: lookupswitch {
        //          723286139: 824
        //          1939535999: 279
        //          default: 312
        //        }
        //   312: invokestatic    invokestatic   !!! ERROR
        //   315: ldc             "\u226c\u1496\u8b41\ub3dd\uc930\uec4a\ub237\ue722\ud97c\ue94e\ua69d\u1e0c\ue056\uc5a2\u81d3\u88c0\u57a1\u76a9\ubd29\uc0fb\u2aab\uc23e\u6bef\u2d59\ud722\u347b\u7d2f\u880d\u801c\u8c60\u8519\ufb37\u7130\u9a14\u1b61\uf0d6\u4977\u89c6\uca88\uff91\ub769\u41fd\ub816\ub35c\u4c8b\u8b4e\u7c29\ucf85\u7d42\uea3b\ue765\u16d3"
        //   317: invokestatic    invokestatic   !!! ERROR
        //   320: iconst_1       
        //   321: invokespecial   dev/nuker/pyro/f0a.<init>:(Ljava/lang/String;Ljava/lang/String;Ljava/lang/String;Z)V
        //   324: putfield        dev/nuker/pyro/f9e.c:Ldev/nuker/pyro/f0a;
        //   327: aload_0        
        //   328: new             Ldev/nuker/pyro/f0a;
        //   331: dup            
        //   332: ldc             "\u224c\u1496\u8b41\ub3dd\uc930\uec4a\ub206\ue770\ud96d\ue947\ua693\u1e49\ue054\uc589\u81c0\u88ce\u57a1"
        //   334: getstatic       dev/nuker/pyro/fc.0:I
        //   337: ifeq            345
        //   340: ldc             -377591320
        //   342: goto            347
        //   345: ldc             -247742896
        //   347: ldc             -984764201
        //   349: ixor           
        //   350: lookupswitch {
        //          741595455: 345
        //          880152199: 376
        //          default: 814
        //        }
        //   376: invokestatic    invokestatic   !!! ERROR
        //   379: ldc             "\u227c\u1481\u8b4a\ub3d8\uc93e\uec5d\ub236"
        //   381: invokestatic    invokestatic   !!! ERROR
        //   384: ldc             "\u226c\u1496\u8b41\ub3dd\uc930\uec4a\ub237\ue722\ud97c\ue94e\ua69d\u1e0c\ue044\uc5b5\u81c4\u88c2\u57af\u76a2\ubd2f\uc0ba\u2aa2\uc23a\u6ba2\u2d53"
        //   386: invokestatic    invokestatic   !!! ERROR
        //   389: iconst_1       
        //   390: invokespecial   dev/nuker/pyro/f0a.<init>:(Ljava/lang/String;Ljava/lang/String;Ljava/lang/String;Z)V
        //   393: getstatic       dev/nuker/pyro/fc.1:I
        //   396: ifeq            404
        //   399: ldc             -28816519
        //   401: goto            406
        //   404: ldc             1494597719
        //   406: ldc             -1525379652
        //   408: ixor           
        //   409: lookupswitch {
        //          -1410046411: 404
        //          1532806853: 812
        //          default: 436
        //        }
        //   436: putfield        dev/nuker/pyro/f9e.0:Ldev/nuker/pyro/f0a;
        //   439: aload_0        
        //   440: new             Ldev/nuker/pyro/f0a;
        //   443: dup            
        //   444: ldc             "\u224c\u1496\u8b41\ub3dd\uc930\uec4a\ub206\ue763\ud97a"
        //   446: invokestatic    invokestatic   !!! ERROR
        //   449: ldc             "\u227c\u1492\u8b5d"
        //   451: invokestatic    invokestatic   !!! ERROR
        //   454: ldc             "\u226c\u1496\u8b41\ub3dd\uc930\uec4a\ub237\ue722\ud97c\ue94e\ua69d\u1e0c\ue044\uc5b5\u81c4\u88c2\u57af\u76e7\ubd2d\uc0ff\u2abe\uc238\u6baa\u2d58\ud730\u343a\u7d2c\u8809\u8051\u8c63\u851f\ufb20"
        //   456: invokestatic    invokestatic   !!! ERROR
        //   459: iconst_1       
        //   460: invokespecial   dev/nuker/pyro/f0a.<init>:(Ljava/lang/String;Ljava/lang/String;Ljava/lang/String;Z)V
        //   463: putfield        dev/nuker/pyro/f9e.1:Ldev/nuker/pyro/f0a;
        //   466: aload_0        
        //   467: new             Ldev/nuker/pyro/f0k;
        //   470: dup            
        //   471: new             Ldev/nuker/pyro/f0e;
        //   474: dup            
        //   475: ldc             "\u224c\u1496\u8b41\ub3dd\uc930\uec4a"
        //   477: invokestatic    invokestatic   !!! ERROR
        //   480: ldc             "\u226c\u1496\u8b41\ub3dd\uc930\uec4a"
        //   482: invokestatic    invokestatic   !!! ERROR
        //   485: ldc             "\u227b\u1497\u8b46\ub3cd\uc975\uec4c\ub22c\ue767\ud928\ue954\ua69d\u1e42\ue042\uc5a2\u81d3\u8883\u57b7\u76a2\ubd29\uc0ee\u2aa5\uc235\u6ba8\u2d45"
        //   487: invokestatic    invokestatic   !!! ERROR
        //   490: invokespecial   dev/nuker/pyro/f0e.<init>:(Ljava/lang/String;Ljava/lang/String;Ljava/lang/String;)V
        //   493: iconst_3       
        //   494: anewarray       Ldev/nuker/pyro/f0n;
        //   497: dup            
        //   498: iconst_0       
        //   499: aload_0        
        //   500: getfield        dev/nuker/pyro/f9e.c:Ldev/nuker/pyro/f0a;
        //   503: aastore        
        //   504: dup            
        //   505: iconst_1       
        //   506: aload_0        
        //   507: getstatic       dev/nuker/pyro/fc.0:I
        //   510: ifeq            518
        //   513: ldc             -1318378039
        //   515: goto            520
        //   518: ldc             1640364916
        //   520: ldc             209857461
        //   522: ixor           
        //   523: lookupswitch {
        //          -1108799876: 816
        //          -1074733198: 518
        //          default: 548
        //        }
        //   548: getfield        dev/nuker/pyro/f9e.0:Ldev/nuker/pyro/f0a;
        //   551: aastore        
        //   552: dup            
        //   553: iconst_2       
        //   554: getstatic       dev/nuker/pyro/fc.1:I
        //   557: ifeq            565
        //   560: ldc             -1674321729
        //   562: goto            567
        //   565: ldc             -1450749498
        //   567: ldc             -228988802
        //   569: ixor           
        //   570: lookupswitch {
        //          1541323192: 596
        //          1852442817: 565
        //          default: 830
        //        }
        //   596: aload_0        
        //   597: getstatic       dev/nuker/pyro/fc.0:I
        //   600: ifeq            608
        //   603: ldc             -1826395124
        //   605: goto            610
        //   608: ldc             -315188209
        //   610: ldc             -2145698188
        //   612: ixor           
        //   613: lookupswitch {
        //          -456991345: 608
        //          322458232: 810
        //          default: 640
        //        }
        //   640: getfield        dev/nuker/pyro/f9e.1:Ldev/nuker/pyro/f0a;
        //   643: aastore        
        //   644: invokespecial   dev/nuker/pyro/f0k.<init>:(Ldev/nuker/pyro/f0n;[Ldev/nuker/pyro/f0n;)V
        //   647: getstatic       dev/nuker/pyro/fc.1:I
        //   650: ifeq            658
        //   653: ldc             202728846
        //   655: goto            660
        //   658: ldc             841698089
        //   660: ldc             -1954255981
        //   662: ixor           
        //   663: lookupswitch {
        //          -2020536803: 818
        //          397370485: 658
        //          default: 688
        //        }
        //   688: putfield        dev/nuker/pyro/f9e.c:Ldev/nuker/pyro/f0k;
        //   691: aload_0        
        //   692: getstatic       dev/nuker/pyro/fc.0:I
        //   695: ifeq            703
        //   698: ldc             -1751677352
        //   700: goto            705
        //   703: ldc             -970256399
        //   705: ldc             1208556860
        //   707: ixor           
        //   708: lookupswitch {
        //          -543253660: 828
        //          1518370832: 703
        //          default: 736
        //        }
        //   736: aload_0        
        //   737: getfield        dev/nuker/pyro/f9e.c:Ldev/nuker/pyro/f0k;
        //   740: invokevirtual   dev/nuker/pyro/f9e.c:(Ldev/nuker/pyro/f0n;)Ldev/nuker/pyro/f0n;
        //   743: pop            
        //   744: aload_0        
        //   745: getstatic       dev/nuker/pyro/fc.c:I
        //   748: ifge            756
        //   751: ldc             1164755274
        //   753: goto            758
        //   756: ldc             1912336575
        //   758: ldc             -1623462429
        //   760: ixor           
        //   761: lookupswitch {
        //          -631821143: 756
        //          -289399460: 788
        //          default: 808
        //        }
        //   788: aload_0        
        //   789: getfield        dev/nuker/pyro/f9e.c:Ldev/nuker/pyro/f0b;
        //   792: invokevirtual   dev/nuker/pyro/f9e.c:(Ldev/nuker/pyro/f0n;)Ldev/nuker/pyro/f0n;
        //   795: pop            
        //   796: aload_0        
        //   797: aload_0        
        //   798: getfield        dev/nuker/pyro/f9e.0:Ldev/nuker/pyro/f0b;
        //   801: invokevirtual   dev/nuker/pyro/f9e.c:(Ldev/nuker/pyro/f0n;)Ldev/nuker/pyro/f0n;
        //   804: pop            
        //   805: return         
        //   806: aconst_null    
        //   807: athrow         
        //   808: aconst_null    
        //   809: athrow         
        //   810: aconst_null    
        //   811: athrow         
        //   812: aconst_null    
        //   813: athrow         
        //   814: aconst_null    
        //   815: athrow         
        //   816: aconst_null    
        //   817: athrow         
        //   818: aconst_null    
        //   819: athrow         
        //   820: aconst_null    
        //   821: athrow         
        //   822: aconst_null    
        //   823: athrow         
        //   824: aconst_null    
        //   825: athrow         
        //   826: aconst_null    
        //   827: athrow         
        //   828: aconst_null    
        //   829: athrow         
        //   830: aconst_null    
        //   831: athrow         
        //    StackMapTable: 00 34 FF 00 0E 00 01 06 00 02 06 07 00 95 FF 00 01 00 01 06 00 03 06 07 00 95 01 FF 00 1B 00 01 06 00 02 06 07 00 95 FF 00 39 00 01 07 00 03 00 07 07 00 03 08 00 3E 08 00 3E 07 00 95 07 00 95 05 07 00 2B FF 00 01 00 01 07 00 03 00 08 07 00 03 08 00 3E 08 00 3E 07 00 95 07 00 95 05 07 00 2B 01 FF 00 1B 00 01 07 00 03 00 07 07 00 03 08 00 3E 08 00 3E 07 00 95 07 00 95 05 07 00 2B FF 00 1C 00 01 07 00 03 00 05 07 00 03 08 00 8B 08 00 8B 07 00 95 07 00 95 FF 00 01 00 01 07 00 03 00 06 07 00 03 08 00 8B 08 00 8B 07 00 95 07 00 95 01 FF 00 1C 00 01 07 00 03 00 05 07 00 03 08 00 8B 08 00 8B 07 00 95 07 00 95 20 41 01 1C FF 00 16 00 01 07 00 03 00 05 07 00 03 08 01 01 08 01 01 07 00 95 07 00 95 FF 00 01 00 01 07 00 03 00 06 07 00 03 08 01 01 08 01 01 07 00 95 07 00 95 01 FF 00 1E 00 01 07 00 03 00 05 07 00 03 08 01 01 08 01 01 07 00 95 07 00 95 FF 00 20 00 01 07 00 03 00 04 07 00 03 08 01 48 08 01 48 07 00 95 FF 00 01 00 01 07 00 03 00 05 07 00 03 08 01 48 08 01 48 07 00 95 01 FF 00 1C 00 01 07 00 03 00 04 07 00 03 08 01 48 08 01 48 07 00 95 FF 00 1B 00 01 07 00 03 00 02 07 00 03 07 00 48 FF 00 01 00 01 07 00 03 00 03 07 00 03 07 00 48 01 FF 00 1D 00 01 07 00 03 00 02 07 00 03 07 00 48 FF 00 51 00 01 07 00 03 00 08 07 00 03 08 01 D3 08 01 D3 07 00 6E 07 00 97 07 00 97 01 07 00 03 FF 00 01 00 01 07 00 03 00 09 07 00 03 08 01 D3 08 01 D3 07 00 6E 07 00 97 07 00 97 01 07 00 03 01 FF 00 1B 00 01 07 00 03 00 08 07 00 03 08 01 D3 08 01 D3 07 00 6E 07 00 97 07 00 97 01 07 00 03 FF 00 10 00 01 07 00 03 00 07 07 00 03 08 01 D3 08 01 D3 07 00 6E 07 00 97 07 00 97 01 FF 00 01 00 01 07 00 03 00 08 07 00 03 08 01 D3 08 01 D3 07 00 6E 07 00 97 07 00 97 01 01 FF 00 1C 00 01 07 00 03 00 07 07 00 03 08 01 D3 08 01 D3 07 00 6E 07 00 97 07 00 97 01 FF 00 0B 00 01 07 00 03 00 08 07 00 03 08 01 D3 08 01 D3 07 00 6E 07 00 97 07 00 97 01 07 00 03 FF 00 01 00 01 07 00 03 00 09 07 00 03 08 01 D3 08 01 D3 07 00 6E 07 00 97 07 00 97 01 07 00 03 01 FF 00 1D 00 01 07 00 03 00 08 07 00 03 08 01 D3 08 01 D3 07 00 6E 07 00 97 07 00 97 01 07 00 03 FF 00 11 00 01 07 00 03 00 02 07 00 03 07 00 6C FF 00 01 00 01 07 00 03 00 03 07 00 03 07 00 6C 01 FF 00 1B 00 01 07 00 03 00 02 07 00 03 07 00 6C 4E 07 00 03 FF 00 01 00 01 07 00 03 00 02 07 00 03 01 5E 07 00 03 53 07 00 03 FF 00 01 00 01 07 00 03 00 02 07 00 03 01 5D 07 00 03 FF 00 11 00 01 07 00 03 00 05 07 00 03 08 00 8B 08 00 8B 07 00 95 07 00 95 41 07 00 03 FF 00 01 00 01 07 00 03 00 08 07 00 03 08 01 D3 08 01 D3 07 00 6E 07 00 97 07 00 97 01 07 00 03 FF 00 01 00 01 07 00 03 00 02 07 00 03 07 00 48 FF 00 01 00 01 07 00 03 00 04 07 00 03 08 01 48 08 01 48 07 00 95 FF 00 01 00 01 07 00 03 00 08 07 00 03 08 01 D3 08 01 D3 07 00 6E 07 00 97 07 00 97 01 07 00 03 FF 00 01 00 01 07 00 03 00 02 07 00 03 07 00 6C FF 00 01 00 01 07 00 03 00 07 07 00 03 08 00 3E 08 00 3E 07 00 95 07 00 95 05 07 00 2B FF 00 01 00 01 06 00 02 06 07 00 95 FF 00 01 00 01 07 00 03 00 05 07 00 03 08 01 01 08 01 01 07 00 95 07 00 95 01 41 07 00 03 FF 00 01 00 01 07 00 03 00 07 07 00 03 08 01 D3 08 01 D3 07 00 6E 07 00 97 07 00 97 01
        // 
        // The error that occurred was:
        // 
        // java.lang.IllegalStateException: Invalid BootstrapMethods attribute entry: 21 additional arguments required for method a.a, but only 0 specified.
        //     at com.strobel.assembler.ir.Error.invalidBootstrapMethodEntry(Error.java:244)
        //     at com.strobel.assembler.ir.MetadataReader.readAttributeCore(MetadataReader.java:280)
        //     at com.strobel.assembler.metadata.ClassFileReader.readAttributeCore(ClassFileReader.java:261)
        //     at com.strobel.assembler.ir.MetadataReader.inflateAttributes(MetadataReader.java:439)
        //     at com.strobel.assembler.metadata.ClassFileReader.visitAttributes(ClassFileReader.java:1134)
        //     at com.strobel.assembler.metadata.ClassFileReader.readClass(ClassFileReader.java:439)
        //     at com.strobel.assembler.metadata.ClassFileReader.readClass(ClassFileReader.java:377)
        //     at com.strobel.assembler.metadata.MetadataSystem.resolveType(MetadataSystem.java:129)
        //     at com.strobel.decompiler.NoRetryMetadataSystem.resolveType(DecompilerDriver.java:476)
        //     at com.strobel.assembler.metadata.MetadataSystem.resolveCore(MetadataSystem.java:81)
        //     at com.strobel.assembler.metadata.MetadataResolver.resolve(MetadataResolver.java:104)
        //     at com.strobel.assembler.metadata.CoreMetadataFactory$UnresolvedType.resolve(CoreMetadataFactory.java:616)
        //     at com.strobel.assembler.metadata.MetadataResolver.resolve(MetadataResolver.java:128)
        //     at com.strobel.assembler.metadata.CoreMetadataFactory$UnresolvedType.resolve(CoreMetadataFactory.java:626)
        //     at com.strobel.assembler.metadata.MethodReference.resolve(MethodReference.java:177)
        //     at com.strobel.decompiler.ast.TypeAnalysis.inferCall(TypeAnalysis.java:2438)
        //     at com.strobel.decompiler.ast.TypeAnalysis.doInferTypeForExpression(TypeAnalysis.java:1029)
        //     at com.strobel.decompiler.ast.TypeAnalysis.inferTypeForExpression(TypeAnalysis.java:803)
        //     at com.strobel.decompiler.ast.TypeAnalysis.inferCall(TypeAnalysis.java:2695)
        //     at com.strobel.decompiler.ast.TypeAnalysis.doInferTypeForExpression(TypeAnalysis.java:1029)
        //     at com.strobel.decompiler.ast.TypeAnalysis.inferTypeForExpression(TypeAnalysis.java:803)
        //     at com.strobel.decompiler.ast.TypeAnalysis.runInference(TypeAnalysis.java:672)
        //     at com.strobel.decompiler.ast.TypeAnalysis.runInference(TypeAnalysis.java:655)
        //     at com.strobel.decompiler.ast.TypeAnalysis.runInference(TypeAnalysis.java:365)
        //     at com.strobel.decompiler.ast.TypeAnalysis.run(TypeAnalysis.java:96)
        //     at com.strobel.decompiler.ast.AstOptimizer.optimize(AstOptimizer.java:109)
        //     at com.strobel.decompiler.ast.AstOptimizer.optimize(AstOptimizer.java:42)
        //     at com.strobel.decompiler.languages.java.ast.AstMethodBodyBuilder.createMethodBody(AstMethodBodyBuilder.java:214)
        //     at com.strobel.decompiler.languages.java.ast.AstMethodBodyBuilder.createMethodBody(AstMethodBodyBuilder.java:99)
        //     at com.strobel.decompiler.languages.java.ast.AstBuilder.createMethodBody(AstBuilder.java:782)
        //     at com.strobel.decompiler.languages.java.ast.AstBuilder.createConstructor(AstBuilder.java:713)
        //     at com.strobel.decompiler.languages.java.ast.AstBuilder.addTypeMembers(AstBuilder.java:549)
        //     at com.strobel.decompiler.languages.java.ast.AstBuilder.createTypeCore(AstBuilder.java:519)
        //     at com.strobel.decompiler.languages.java.ast.AstBuilder.createTypeNoCache(AstBuilder.java:161)
        //     at com.strobel.decompiler.languages.java.ast.AstBuilder.createType(AstBuilder.java:150)
        //     at com.strobel.decompiler.languages.java.ast.AstBuilder.addType(AstBuilder.java:125)
        //     at com.strobel.decompiler.languages.java.JavaLanguage.buildAst(JavaLanguage.java:71)
        //     at com.strobel.decompiler.languages.java.JavaLanguage.decompileType(JavaLanguage.java:59)
        //     at com.strobel.decompiler.DecompilerDriver.decompileType(DecompilerDriver.java:330)
        //     at com.strobel.decompiler.DecompilerDriver.decompileJar(DecompilerDriver.java:251)
        //     at com.strobel.decompiler.DecompilerDriver.main(DecompilerDriver.java:126)
        // 
        throw new IllegalStateException("An error occurred while decompiling this method.");
    }
    
    @Override
    public void c(@Nullable final Vec3d p0, final float p1) {
        // 
        // This method could not be decompiled.
        // 
        // Original Bytecode:
        // 
        //     3: dup            
        //     4: ifnull          196
        //     7: athrow         
        //     8: aconst_null    
        //     9: getstatic       dev/nuker/pyro/fc.0:I
        //    12: ifgt            188
        //    15: pop            
        //    16: aconst_null    
        //    17: goto            180
        //    20: nop            
        //    21: nop            
        //    22: nop            
        //    23: athrow         
        //    24: aload_0        
        //    25: aload_1        
        //    26: fload_2        
        //    27: goto            31
        //    30: athrow         
        //    31: invokespecial   dev/nuker/pyro/fH.c:(Lnet/minecraft/util/math/Vec3d;F)V
        //    34: goto            38
        //    37: athrow         
        //    38: getstatic       dev/nuker/pyro/fc.1:I
        //    41: ifeq            49
        //    44: ldc             -419249660
        //    46: goto            51
        //    49: ldc             927897263
        //    51: ldc             1648274654
        //    53: ixor           
        //    54: lookupswitch {
        //          -2059637030: 49
        //          1433418353: 80
        //          default: 167
        //        }
        //    80: aload_0        
        //    81: getfield        dev/nuker/pyro/f9e.c:Lnet/minecraft/client/Minecraft;
        //    84: getfield        net/minecraft/client/Minecraft.field_71438_f:Lnet/minecraft/client/renderer/RenderGlobal;
        //    87: checkcast       Ldev/nuker/pyro/mixin/RenderGlobalAccessor;
        //    90: getstatic       dev/nuker/pyro/fc.0:I
        //    93: ifeq            101
        //    96: ldc             2005378211
        //    98: goto            103
        //   101: ldc             1158709595
        //   103: ldc             -2050060978
        //   105: ixor           
        //   106: lookupswitch {
        //          -1059189739: 132
        //          -230086163: 101
        //          default: 169
        //        }
        //   132: astore_3       
        //   133: aload_3        
        //   134: goto            138
        //   137: athrow         
        //   138: invokeinterface dev/nuker/pyro/mixin/RenderGlobalAccessor.getDamagedBlocks:()Ljava/util/Map;
        //   143: goto            147
        //   146: athrow         
        //   147: aload_0        
        //   148: invokedynamic   BootstrapMethod #0, accept:(Ldev/nuker/pyro/f9e;)Ljava/util/function/BiConsumer;
        //   153: goto            157
        //   156: athrow         
        //   157: invokeinterface java/util/Map.forEach:(Ljava/util/function/BiConsumer;)V
        //   162: goto            166
        //   165: athrow         
        //   166: return         
        //   167: aconst_null    
        //   168: athrow         
        //   169: aconst_null    
        //   170: athrow         
        //   171: pop            
        //   172: goto            24
        //   175: pop            
        //   176: aconst_null    
        //   177: goto            171
        //   180: dup            
        //   181: ifnull          171
        //   184: checkcast       Ljava/lang/Throwable;
        //   187: athrow         
        //   188: dup            
        //   189: ifnull          175
        //   192: checkcast       Ljava/lang/Throwable;
        //   195: athrow         
        //   196: aconst_null    
        //   197: athrow         
        //    RuntimeInvisibleTypeAnnotations: 00 01 16 00 00 00 99 00 00
        //    StackMapTable: 00 1D FF 00 03 00 04 07 00 03 07 00 D6 02 07 00 B5 00 01 07 00 A5 FA 00 04 FF 00 0B 00 00 00 01 07 00 A5 FE 00 03 07 00 03 07 00 D6 02 45 07 00 A5 FF 00 00 00 03 07 00 03 07 00 D6 02 00 03 07 00 03 07 00 D6 02 45 07 00 A5 00 0A 41 01 1C 54 07 00 B5 FF 00 01 00 03 07 00 03 07 00 D6 02 00 02 07 00 B5 01 5C 07 00 B5 FF 00 04 00 04 07 00 03 07 00 D6 02 07 00 B5 00 01 07 00 A5 40 07 00 B5 47 07 00 A5 40 07 00 D0 48 07 00 A5 FF 00 00 00 04 07 00 03 07 00 D6 02 07 00 B5 00 02 07 00 D0 07 00 D8 47 07 00 A5 00 FA 00 00 41 07 00 B5 41 07 00 A5 43 05 44 07 00 A5 47 05 FF 00 07 00 04 07 00 03 07 00 D6 02 07 00 B5 00 01 07 00 A5
        //    Exceptions:
        //  Try           Handler
        //  Start  End    Start  End    Type                                       
        //  -----  -----  -----  -----  -------------------------------------------
        //  8      20     180    188    Ljava/util/ConcurrentModificationException;
        //  180    188    180    188    Any
        //  196    198    3      8      Ljava/lang/NumberFormatException;
        //  30     37     37     38     Any
        //  30     37     30     31     Any
        //  31     37     37     38     Any
        //  30     37     30     31     Ljava/lang/NegativeArraySizeException;
        //  31     37     37     38     Ljava/lang/NullPointerException;
        //  137    146    146    147    Any
        //  138    146    137    138    Any
        //  137    146    137    138    Ljava/util/ConcurrentModificationException;
        //  138    146    146    147    Any
        //  137    146    3      8      Any
        //  156    165    165    166    Any
        //  157    165    156    157    Any
        //  157    165    156    157    Ljava/lang/NumberFormatException;
        //  156    165    3      8      Any
        //  157    165    156    157    Ljava/lang/ArithmeticException;
        // 
        // The error that occurred was:
        // 
        // java.lang.IndexOutOfBoundsException: Index 72 out of bounds for length 72
        //     at java.base/jdk.internal.util.Preconditions.outOfBounds(Preconditions.java:64)
        //     at java.base/jdk.internal.util.Preconditions.outOfBoundsCheckIndex(Preconditions.java:70)
        //     at java.base/jdk.internal.util.Preconditions.checkIndex(Preconditions.java:248)
        //     at java.base/java.util.Objects.checkIndex(Objects.java:372)
        //     at java.base/java.util.ArrayList.get(ArrayList.java:458)
        //     at com.strobel.decompiler.ast.AstBuilder.convertToAst(AstBuilder.java:3321)
        //     at com.strobel.decompiler.ast.AstBuilder.convertToAst(AstBuilder.java:3569)
        //     at com.strobel.decompiler.ast.AstBuilder.convertToAst(AstBuilder.java:3435)
        //     at com.strobel.decompiler.ast.AstBuilder.build(AstBuilder.java:113)
        //     at com.strobel.decompiler.languages.java.ast.AstMethodBodyBuilder.createMethodBody(AstMethodBodyBuilder.java:211)
        //     at com.strobel.decompiler.languages.java.ast.AstMethodBodyBuilder.createMethodBody(AstMethodBodyBuilder.java:99)
        //     at com.strobel.decompiler.languages.java.ast.AstBuilder.createMethodBody(AstBuilder.java:782)
        //     at com.strobel.decompiler.languages.java.ast.AstBuilder.createMethod(AstBuilder.java:675)
        //     at com.strobel.decompiler.languages.java.ast.AstBuilder.addTypeMembers(AstBuilder.java:552)
        //     at com.strobel.decompiler.languages.java.ast.AstBuilder.createTypeCore(AstBuilder.java:519)
        //     at com.strobel.decompiler.languages.java.ast.AstBuilder.createTypeNoCache(AstBuilder.java:161)
        //     at com.strobel.decompiler.languages.java.ast.AstBuilder.createType(AstBuilder.java:150)
        //     at com.strobel.decompiler.languages.java.ast.AstBuilder.addType(AstBuilder.java:125)
        //     at com.strobel.decompiler.languages.java.JavaLanguage.buildAst(JavaLanguage.java:71)
        //     at com.strobel.decompiler.languages.java.JavaLanguage.decompileType(JavaLanguage.java:59)
        //     at com.strobel.decompiler.DecompilerDriver.decompileType(DecompilerDriver.java:330)
        //     at com.strobel.decompiler.DecompilerDriver.decompileJar(DecompilerDriver.java:251)
        //     at com.strobel.decompiler.DecompilerDriver.main(DecompilerDriver.java:126)
        // 
        throw new IllegalStateException("An error occurred while decompiling this method.");
    }
    
    static {
        throw t;
    }
    
    public void c(final Integer p0, final DestroyBlockProgress p1) {
        // 
        // This method could not be decompiled.
        // 
        // Original Bytecode:
        // 
        //     3: dup            
        //     4: ifnull          4349
        //     7: athrow         
        //     8: aconst_null    
        //     9: getstatic       dev/nuker/pyro/fc.0:I
        //    12: ifgt            4341
        //    15: pop            
        //    16: aconst_null    
        //    17: goto            4333
        //    20: nop            
        //    21: nop            
        //    22: nop            
        //    23: athrow         
        //    24: aload_1        
        //    25: goto            29
        //    28: athrow         
        //    29: invokevirtual   java/lang/Integer.intValue:()I
        //    32: goto            36
        //    35: athrow         
        //    36: aload_0        
        //    37: getfield        dev/nuker/pyro/f9e.c:Lnet/minecraft/client/Minecraft;
        //    40: getfield        net/minecraft/client/Minecraft.field_71439_g:Lnet/minecraft/client/entity/EntityPlayerSP;
        //    43: goto            47
        //    46: athrow         
        //    47: invokevirtual   net/minecraft/client/entity/EntityPlayerSP.func_145782_y:()I
        //    50: goto            54
        //    53: athrow         
        //    54: if_icmpeq       4219
        //    57: getstatic       dev/nuker/pyro/fbr.c:Ldev/nuker/pyro/fbr;
        //    60: bipush          7
        //    62: goto            66
        //    65: athrow         
        //    66: invokevirtual   dev/nuker/pyro/fbr.c:(I)V
        //    69: goto            73
        //    72: athrow         
        //    73: getstatic       dev/nuker/pyro/fbr.c:Ldev/nuker/pyro/fbr;
        //    76: aload_2        
        //    77: getstatic       dev/nuker/pyro/fc.0:I
        //    80: ifeq            89
        //    83: ldc_w           -1815089034
        //    86: goto            92
        //    89: ldc_w           746610985
        //    92: ldc_w           -1943105999
        //    95: ixor           
        //    96: lookupswitch {
        //          -672283758: 89
        //          534871623: 4242
        //          default: 124
        //        }
        //   124: goto            128
        //   127: athrow         
        //   128: invokevirtual   net/minecraft/client/renderer/DestroyBlockProgress.func_180246_b:()Lnet/minecraft/util/math/BlockPos;
        //   131: goto            135
        //   134: athrow         
        //   135: getstatic       dev/nuker/pyro/fc.0:I
        //   138: ifeq            147
        //   141: ldc_w           1726600128
        //   144: goto            150
        //   147: ldc_w           -1742142740
        //   150: ldc_w           -1951346430
        //   153: ixor           
        //   154: lookupswitch {
        //          -1297606537: 147
        //          -312933694: 4256
        //          default: 180
        //        }
        //   180: aload_0        
        //   181: getfield        dev/nuker/pyro/f9e.c:Ldev/nuker/pyro/f0b;
        //   184: goto            188
        //   187: athrow         
        //   188: invokevirtual   dev/nuker/pyro/f0b.3:()Ljava/lang/Object;
        //   191: goto            195
        //   194: athrow         
        //   195: checkcast       Ldev/nuker/pyro/fS;
        //   198: getstatic       dev/nuker/pyro/fc.0:I
        //   201: ifeq            210
        //   204: ldc_w           -404988645
        //   207: goto            213
        //   210: ldc_w           1162880065
        //   213: ldc_w           -886252831
        //   216: ixor           
        //   217: lookupswitch {
        //          -611745863: 210
        //          753960954: 4294
        //          default: 244
        //        }
        //   244: goto            248
        //   247: athrow         
        //   248: invokevirtual   dev/nuker/pyro/fS.5:()I
        //   251: goto            255
        //   254: athrow         
        //   255: bipush          63
        //   257: goto            261
        //   260: athrow         
        //   261: invokevirtual   dev/nuker/pyro/fbr.0:(Lnet/minecraft/util/math/BlockPos;II)V
        //   264: goto            268
        //   267: athrow         
        //   268: getstatic       dev/nuker/pyro/fbr.c:Ldev/nuker/pyro/fbr;
        //   271: goto            275
        //   274: athrow         
        //   275: invokevirtual   dev/nuker/pyro/fbr.2:()V
        //   278: goto            282
        //   281: athrow         
        //   282: goto            286
        //   285: athrow         
        //   286: invokestatic    net/minecraft/client/renderer/GlStateManager.func_179094_E:()V
        //   289: goto            293
        //   292: athrow         
        //   293: aload_0        
        //   294: getfield        dev/nuker/pyro/f9e.c:Lnet/minecraft/client/Minecraft;
        //   297: goto            301
        //   300: athrow         
        //   301: invokevirtual   net/minecraft/client/Minecraft.func_175606_aa:()Lnet/minecraft/entity/Entity;
        //   304: goto            308
        //   307: athrow         
        //   308: instanceof      Lnet/minecraft/entity/player/EntityPlayer;
        //   311: ifeq            320
        //   314: ldc_w           -610189648
        //   317: goto            323
        //   320: ldc_w           -610189641
        //   323: ldc_w           -722048037
        //   326: ixor           
        //   327: tableswitch {
        //          514763478: 348
        //          514763479: 413
        //          default: 314
        //        }
        //   348: getstatic       dev/nuker/pyro/fc.1:I
        //   351: ifeq            360
        //   354: ldc_w           255605382
        //   357: goto            363
        //   360: ldc_w           294635483
        //   363: ldc_w           -196283449
        //   366: ixor           
        //   367: lookupswitch {
        //          -440191972: 392
        //          -76494527: 360
        //          default: 4250
        //        }
        //   392: aload_0        
        //   393: getfield        dev/nuker/pyro/f9e.c:Lnet/minecraft/client/Minecraft;
        //   396: goto            400
        //   399: athrow         
        //   400: invokevirtual   net/minecraft/client/Minecraft.func_175606_aa:()Lnet/minecraft/entity/Entity;
        //   403: goto            407
        //   406: athrow         
        //   407: checkcast       Lnet/minecraft/entity/player/EntityPlayer;
        //   410: goto            466
        //   413: aload_0        
        //   414: getstatic       dev/nuker/pyro/fc.1:I
        //   417: ifeq            426
        //   420: ldc_w           -1658354350
        //   423: goto            429
        //   426: ldc_w           1983070089
        //   429: ldc_w           -1203691607
        //   432: ixor           
        //   433: lookupswitch {
        //          241773658: 426
        //          627481339: 4264
        //          default: 460
        //        }
        //   460: getfield        dev/nuker/pyro/f9e.c:Lnet/minecraft/client/Minecraft;
        //   463: getfield        net/minecraft/client/Minecraft.field_71439_g:Lnet/minecraft/client/entity/EntityPlayerSP;
        //   466: astore_3       
        //   467: aload_2        
        //   468: goto            472
        //   471: athrow         
        //   472: invokevirtual   net/minecraft/client/renderer/DestroyBlockProgress.func_180246_b:()Lnet/minecraft/util/math/BlockPos;
        //   475: goto            479
        //   478: athrow         
        //   479: goto            483
        //   482: athrow         
        //   483: invokevirtual   net/minecraft/util/math/BlockPos.func_177958_n:()I
        //   486: goto            490
        //   489: athrow         
        //   490: i2f            
        //   491: ldc             0.5
        //   493: fadd           
        //   494: aload_2        
        //   495: goto            499
        //   498: athrow         
        //   499: invokevirtual   net/minecraft/client/renderer/DestroyBlockProgress.func_180246_b:()Lnet/minecraft/util/math/BlockPos;
        //   502: goto            506
        //   505: athrow         
        //   506: getstatic       dev/nuker/pyro/fc.1:I
        //   509: ifeq            518
        //   512: ldc_w           487623916
        //   515: goto            521
        //   518: ldc_w           -1323128791
        //   521: ldc_w           -1628476895
        //   524: ixor           
        //   525: lookupswitch {
        //          -2080381235: 4220
        //          -915462838: 518
        //          default: 552
        //        }
        //   552: goto            556
        //   555: athrow         
        //   556: invokevirtual   net/minecraft/util/math/BlockPos.func_177956_o:()I
        //   559: goto            563
        //   562: athrow         
        //   563: i2f            
        //   564: ldc             0.5
        //   566: fadd           
        //   567: aload_2        
        //   568: goto            572
        //   571: athrow         
        //   572: invokevirtual   net/minecraft/client/renderer/DestroyBlockProgress.func_180246_b:()Lnet/minecraft/util/math/BlockPos;
        //   575: goto            579
        //   578: athrow         
        //   579: getstatic       dev/nuker/pyro/fc.1:I
        //   582: ifeq            591
        //   585: ldc_w           461557204
        //   588: goto            594
        //   591: ldc_w           1808484236
        //   594: ldc_w           -479980359
        //   597: ixor           
        //   598: lookupswitch {
        //          -119088787: 4224
        //          -19660921: 591
        //          default: 624
        //        }
        //   624: goto            628
        //   627: athrow         
        //   628: invokevirtual   net/minecraft/util/math/BlockPos.func_177952_p:()I
        //   631: goto            635
        //   634: athrow         
        //   635: i2f            
        //   636: ldc             0.5
        //   638: fadd           
        //   639: aload_3        
        //   640: fconst_1       
        //   641: getstatic       dev/nuker/pyro/fc.0:I
        //   644: ifeq            653
        //   647: ldc_w           -1887476195
        //   650: goto            656
        //   653: ldc_w           1825449693
        //   656: ldc_w           -676291516
        //   659: ixor           
        //   660: lookupswitch {
        //          -1695845593: 653
        //          1490025049: 4308
        //          default: 688
        //        }
        //   688: goto            692
        //   691: athrow         
        //   692: invokestatic    dev/nuker/pyro/fbs.c:(FFFLnet/minecraft/entity/Entity;F)V
        //   695: goto            699
        //   698: athrow         
        //   699: aload_2        
        //   700: goto            704
        //   703: athrow         
        //   704: invokevirtual   net/minecraft/client/renderer/DestroyBlockProgress.func_73106_e:()I
        //   707: goto            711
        //   710: athrow         
        //   711: i2f            
        //   712: ldc_w           10.0
        //   715: fmul           
        //   716: fstore          4
        //   718: goto            722
        //   721: athrow         
        //   722: invokestatic    net/minecraft/client/renderer/GlStateManager.func_179097_i:()V
        //   725: goto            729
        //   728: athrow         
        //   729: aload_0        
        //   730: getfield        dev/nuker/pyro/f9e.c:Ldev/nuker/pyro/f0a;
        //   733: goto            737
        //   736: athrow         
        //   737: invokevirtual   dev/nuker/pyro/f0a.3:()Ljava/lang/Object;
        //   740: goto            744
        //   743: athrow         
        //   744: checkcast       Ljava/lang/Boolean;
        //   747: goto            751
        //   750: athrow         
        //   751: invokevirtual   java/lang/Boolean.booleanValue:()Z
        //   754: goto            758
        //   757: athrow         
        //   758: ifeq            767
        //   761: ldc_w           1422003587
        //   764: goto            770
        //   767: ldc_w           1422003612
        //   770: ldc_w           -1320674964
        //   773: ixor           
        //   774: tableswitch {
        //          -887871010: 796
        //          -887871009: 1104
        //          default: 761
        //        }
        //   796: new             Ljava/lang/StringBuilder;
        //   799: dup            
        //   800: goto            804
        //   803: athrow         
        //   804: invokespecial   java/lang/StringBuilder.<init>:()V
        //   807: goto            811
        //   810: athrow         
        //   811: ldc_w           "\u221b\u14dd\u8b1e\ub1ce"
        //   814: goto            818
        //   817: athrow         
        //   818: invokestatic    invokestatic   !!! ERROR
        //   821: goto            825
        //   824: athrow         
        //   825: iconst_1       
        //   826: anewarray       Ljava/lang/Object;
        //   829: dup            
        //   830: iconst_0       
        //   831: fload           4
        //   833: goto            837
        //   836: athrow         
        //   837: invokestatic    java/lang/Float.valueOf:(F)Ljava/lang/Float;
        //   840: goto            844
        //   843: athrow         
        //   844: aastore        
        //   845: goto            849
        //   848: athrow         
        //   849: invokestatic    java/lang/String.format:(Ljava/lang/String;[Ljava/lang/Object;)Ljava/lang/String;
        //   852: goto            856
        //   855: athrow         
        //   856: goto            860
        //   859: athrow         
        //   860: invokevirtual   java/lang/StringBuilder.append:(Ljava/lang/String;)Ljava/lang/StringBuilder;
        //   863: goto            867
        //   866: athrow         
        //   867: ldc_w           "%"
        //   870: getstatic       dev/nuker/pyro/fc.1:I
        //   873: ifeq            882
        //   876: ldc_w           -27571083
        //   879: goto            885
        //   882: ldc_w           1093538383
        //   885: ldc_w           267230422
        //   888: ixor           
        //   889: lookupswitch {
        //          -239677277: 4226
        //          127906046: 882
        //          default: 916
        //        }
        //   916: goto            920
        //   919: athrow         
        //   920: invokevirtual   java/lang/StringBuilder.append:(Ljava/lang/String;)Ljava/lang/StringBuilder;
        //   923: goto            927
        //   926: athrow         
        //   927: goto            931
        //   930: athrow         
        //   931: invokevirtual   java/lang/StringBuilder.toString:()Ljava/lang/String;
        //   934: goto            938
        //   937: athrow         
        //   938: astore          5
        //   940: goto            944
        //   943: athrow         
        //   944: invokestatic    net/minecraft/client/renderer/GlStateManager.func_179094_E:()V
        //   947: goto            951
        //   950: athrow         
        //   951: getstatic       dev/nuker/pyro/fc.c:I
        //   954: ifge            963
        //   957: ldc_w           734680108
        //   960: goto            966
        //   963: ldc_w           -426082342
        //   966: ldc_w           380937157
        //   969: ixor           
        //   970: lookupswitch {
        //          166776371: 963
        //          1031731177: 4286
        //          default: 996
        //        }
        //   996: aload           5
        //   998: goto            1002
        //  1001: athrow         
        //  1002: invokestatic    dev/nuker/pyro/fbs.c:(Ljava/lang/String;)F
        //  1005: goto            1009
        //  1008: athrow         
        //  1009: fstore          6
        //  1011: getstatic       dev/nuker/pyro/fc.c:I
        //  1014: ifge            1023
        //  1017: ldc_w           1588772793
        //  1020: goto            1026
        //  1023: ldc_w           -450054095
        //  1026: ldc_w           -721227644
        //  1029: ixor           
        //  1030: lookupswitch {
        //          -1951379651: 1023
        //          808339637: 1056
        //          default: 4230
        //        }
        //  1056: fload           6
        //  1058: f2d            
        //  1059: ldc2_w          2.0
        //  1062: ddiv           
        //  1063: dneg           
        //  1064: dconst_0       
        //  1065: dconst_0       
        //  1066: goto            1070
        //  1069: athrow         
        //  1070: invokestatic    net/minecraft/client/renderer/GlStateManager.func_179137_b:(DDD)V
        //  1073: goto            1077
        //  1076: athrow         
        //  1077: aload           5
        //  1079: fconst_0       
        //  1080: fconst_0       
        //  1081: iconst_m1      
        //  1082: goto            1086
        //  1085: athrow         
        //  1086: invokestatic    dev/nuker/pyro/fbs.1:(Ljava/lang/String;FFI)V
        //  1089: goto            1093
        //  1092: athrow         
        //  1093: goto            1097
        //  1096: athrow         
        //  1097: invokestatic    net/minecraft/client/renderer/GlStateManager.func_179121_F:()V
        //  1100: goto            1104
        //  1103: athrow         
        //  1104: aload_0        
        //  1105: getfield        dev/nuker/pyro/f9e.0:Ldev/nuker/pyro/f0a;
        //  1108: goto            1112
        //  1111: athrow         
        //  1112: invokevirtual   dev/nuker/pyro/f0a.3:()Ljava/lang/Object;
        //  1115: goto            1119
        //  1118: athrow         
        //  1119: checkcast       Ljava/lang/Boolean;
        //  1122: goto            1126
        //  1125: athrow         
        //  1126: invokevirtual   java/lang/Boolean.booleanValue:()Z
        //  1129: goto            1133
        //  1132: athrow         
        //  1133: ifeq            1363
        //  1136: aload_0        
        //  1137: getfield        dev/nuker/pyro/f9e.c:Lnet/minecraft/client/Minecraft;
        //  1140: getfield        net/minecraft/client/Minecraft.field_71441_e:Lnet/minecraft/client/multiplayer/WorldClient;
        //  1143: aload_1        
        //  1144: goto            1148
        //  1147: athrow         
        //  1148: invokevirtual   java/lang/Integer.intValue:()I
        //  1151: goto            1155
        //  1154: athrow         
        //  1155: goto            1159
        //  1158: athrow         
        //  1159: invokevirtual   net/minecraft/client/multiplayer/WorldClient.func_73045_a:(I)Lnet/minecraft/entity/Entity;
        //  1162: goto            1166
        //  1165: athrow         
        //  1166: astore          5
        //  1168: aload           5
        //  1170: ifnull          1363
        //  1173: getstatic       dev/nuker/pyro/fc.c:I
        //  1176: ifge            1185
        //  1179: ldc_w           703782273
        //  1182: goto            1188
        //  1185: ldc_w           -492082406
        //  1188: ldc_w           -1578903615
        //  1191: ixor           
        //  1192: lookupswitch {
        //          -2012149184: 4270
        //          -415818541: 1185
        //          default: 1220
        //        }
        //  1220: goto            1224
        //  1223: athrow         
        //  1224: invokestatic    net/minecraft/client/renderer/GlStateManager.func_179094_E:()V
        //  1227: goto            1231
        //  1230: athrow         
        //  1231: aload           5
        //  1233: goto            1237
        //  1236: athrow         
        //  1237: invokevirtual   net/minecraft/entity/Entity.func_70005_c_:()Ljava/lang/String;
        //  1240: goto            1244
        //  1243: athrow         
        //  1244: goto            1248
        //  1247: athrow         
        //  1248: invokestatic    dev/nuker/pyro/fbs.c:(Ljava/lang/String;)F
        //  1251: goto            1255
        //  1254: athrow         
        //  1255: fstore          6
        //  1257: fload           6
        //  1259: f2d            
        //  1260: ldc2_w          2.0
        //  1263: ddiv           
        //  1264: dneg           
        //  1265: goto            1269
        //  1268: athrow         
        //  1269: invokestatic    dev/nuker/pyro/fbs.c:()F
        //  1272: goto            1276
        //  1275: athrow         
        //  1276: f2d            
        //  1277: dconst_0       
        //  1278: goto            1282
        //  1281: athrow         
        //  1282: invokestatic    net/minecraft/client/renderer/GlStateManager.func_179137_b:(DDD)V
        //  1285: goto            1289
        //  1288: athrow         
        //  1289: aload           5
        //  1291: goto            1295
        //  1294: athrow         
        //  1295: invokevirtual   net/minecraft/entity/Entity.func_70005_c_:()Ljava/lang/String;
        //  1298: goto            1302
        //  1301: athrow         
        //  1302: fconst_0       
        //  1303: fconst_0       
        //  1304: getstatic       dev/nuker/pyro/FriendManager.Companion:Ldev/nuker/pyro/FriendManager$Companion;
        //  1307: aload           5
        //  1309: goto            1313
        //  1312: athrow         
        //  1313: invokevirtual   net/minecraft/entity/Entity.func_70005_c_:()Ljava/lang/String;
        //  1316: goto            1320
        //  1319: athrow         
        //  1320: goto            1324
        //  1323: athrow         
        //  1324: invokevirtual   dev/nuker/pyro/FriendManager$Companion.isFriend:(Ljava/lang/String;)Z
        //  1327: goto            1331
        //  1330: athrow         
        //  1331: ifeq            1340
        //  1334: ldc_w           65527
        //  1337: goto            1341
        //  1340: iconst_m1      
        //  1341: goto            1345
        //  1344: athrow         
        //  1345: invokestatic    dev/nuker/pyro/fbs.1:(Ljava/lang/String;FFI)V
        //  1348: goto            1352
        //  1351: athrow         
        //  1352: goto            1356
        //  1355: athrow         
        //  1356: invokestatic    net/minecraft/client/renderer/GlStateManager.func_179121_F:()V
        //  1359: goto            1363
        //  1362: athrow         
        //  1363: aload_0        
        //  1364: getfield        dev/nuker/pyro/f9e.1:Ldev/nuker/pyro/f0a;
        //  1367: goto            1371
        //  1370: athrow         
        //  1371: invokevirtual   dev/nuker/pyro/f0a.3:()Ljava/lang/Object;
        //  1374: goto            1378
        //  1377: athrow         
        //  1378: checkcast       Ljava/lang/Boolean;
        //  1381: goto            1385
        //  1384: athrow         
        //  1385: invokevirtual   java/lang/Boolean.booleanValue:()Z
        //  1388: goto            1392
        //  1391: athrow         
        //  1392: ifeq            4208
        //  1395: goto            1399
        //  1398: athrow         
        //  1399: invokestatic    net/minecraft/client/renderer/GlStateManager.func_179094_E:()V
        //  1402: goto            1406
        //  1405: athrow         
        //  1406: ldc_w           "\u2249\u149b\u8b4a\ub1cd\ucf28\uec5b\ub22c\ue763\udb70\uef45"
        //  1409: getstatic       dev/nuker/pyro/fc.0:I
        //  1412: ifeq            1421
        //  1415: ldc_w           -777472757
        //  1418: goto            1424
        //  1421: ldc_w           -303313721
        //  1424: ldc_w           1576608890
        //  1427: ixor           
        //  1428: lookupswitch {
        //          -1940811407: 1421
        //          -1340938051: 1456
        //          default: 4320
        //        }
        //  1456: goto            1460
        //  1459: athrow         
        //  1460: invokestatic    invokestatic   !!! ERROR
        //  1463: goto            1467
        //  1466: athrow         
        //  1467: goto            1471
        //  1470: athrow         
        //  1471: invokestatic    dev/nuker/pyro/fbs.c:(Ljava/lang/String;)F
        //  1474: goto            1478
        //  1477: athrow         
        //  1478: fstore          5
        //  1480: fload           5
        //  1482: f2d            
        //  1483: ldc2_w          2.0
        //  1486: ddiv           
        //  1487: dneg           
        //  1488: getstatic       dev/nuker/pyro/fc.c:I
        //  1491: ifge            1500
        //  1494: ldc_w           2014498046
        //  1497: goto            1503
        //  1500: ldc_w           839583519
        //  1503: ldc_w           365229807
        //  1506: ixor           
        //  1507: lookupswitch {
        //          -968926381: 1500
        //          1842756113: 4322
        //          default: 1532
        //        }
        //  1532: goto            1536
        //  1535: athrow         
        //  1536: invokestatic    dev/nuker/pyro/fbs.c:()F
        //  1539: goto            1543
        //  1542: athrow         
        //  1543: fneg           
        //  1544: ldc_w           5.0
        //  1547: fsub           
        //  1548: f2d            
        //  1549: dconst_0       
        //  1550: goto            1554
        //  1553: athrow         
        //  1554: invokestatic    net/minecraft/client/renderer/GlStateManager.func_179137_b:(DDD)V
        //  1557: goto            1561
        //  1560: athrow         
        //  1561: fconst_0       
        //  1562: fconst_0       
        //  1563: getstatic       dev/nuker/pyro/fc.0:I
        //  1566: ifeq            1575
        //  1569: ldc_w           388967510
        //  1572: goto            1578
        //  1575: ldc_w           -416207320
        //  1578: ldc_w           1536778270
        //  1581: ixor           
        //  1582: lookupswitch {
        //          -1129820618: 1608
        //          1287015496: 1575
        //          default: 4272
        //        }
        //  1608: fload           5
        //  1610: getstatic       dev/nuker/pyro/fc.0:I
        //  1613: ifeq            1622
        //  1616: ldc_w           711823249
        //  1619: goto            1625
        //  1622: ldc_w           -245873252
        //  1625: ldc_w           1155389570
        //  1628: ixor           
        //  1629: lookupswitch {
        //          -1249534690: 1656
        //          1857050387: 1622
        //          default: 4252
        //        }
        //  1656: goto            1660
        //  1659: athrow         
        //  1660: invokestatic    dev/nuker/pyro/fbs.4:()F
        //  1663: goto            1667
        //  1666: athrow         
        //  1667: ldc_w           -1879048192
        //  1670: getstatic       dev/nuker/pyro/fc.1:I
        //  1673: ifeq            1682
        //  1676: ldc_w           -440021757
        //  1679: goto            1685
        //  1682: ldc_w           -408574189
        //  1685: ldc_w           -1907221874
        //  1688: ixor           
        //  1689: lookupswitch {
        //          1777843613: 1716
        //          1805113229: 1682
        //          default: 4312
        //        }
        //  1716: goto            1720
        //  1719: athrow         
        //  1720: invokestatic    dev/nuker/pyro/fbs.c:(FFFFI)V
        //  1723: goto            1727
        //  1726: athrow         
        //  1727: goto            1731
        //  1730: athrow         
        //  1731: invokestatic    net/minecraft/client/renderer/Tessellator.func_178181_a:()Lnet/minecraft/client/renderer/Tessellator;
        //  1734: goto            1738
        //  1737: athrow         
        //  1738: astore          6
        //  1740: aload           6
        //  1742: goto            1746
        //  1745: athrow         
        //  1746: invokevirtual   net/minecraft/client/renderer/Tessellator.func_178180_c:()Lnet/minecraft/client/renderer/BufferBuilder;
        //  1749: goto            1753
        //  1752: athrow         
        //  1753: astore          7
        //  1755: sipush          7425
        //  1758: goto            1762
        //  1761: athrow         
        //  1762: invokestatic    net/minecraft/client/renderer/GlStateManager.func_179103_j:(I)V
        //  1765: goto            1769
        //  1768: athrow         
        //  1769: goto            1773
        //  1772: athrow         
        //  1773: invokestatic    net/minecraft/client/renderer/GlStateManager.func_179147_l:()V
        //  1776: goto            1780
        //  1779: athrow         
        //  1780: goto            1784
        //  1783: athrow         
        //  1784: invokestatic    net/minecraft/client/renderer/GlStateManager.func_179090_x:()V
        //  1787: goto            1791
        //  1790: athrow         
        //  1791: getstatic       dev/nuker/pyro/fc.0:I
        //  1794: ifeq            1803
        //  1797: ldc_w           -1515654216
        //  1800: goto            1806
        //  1803: ldc_w           1060318460
        //  1806: ldc_w           -1546430714
        //  1809: ixor           
        //  1810: lookupswitch {
        //          -1663009798: 1836
        //          108766398: 1803
        //          default: 4228
        //        }
        //  1836: getstatic       net/minecraft/client/renderer/GlStateManager$SourceFactor.SRC_ALPHA:Lnet/minecraft/client/renderer/GlStateManager$SourceFactor;
        //  1839: getstatic       net/minecraft/client/renderer/GlStateManager$DestFactor.ONE_MINUS_SRC_ALPHA:Lnet/minecraft/client/renderer/GlStateManager$DestFactor;
        //  1842: getstatic       dev/nuker/pyro/fc.0:I
        //  1845: ifeq            1854
        //  1848: ldc_w           877459288
        //  1851: goto            1857
        //  1854: ldc_w           -126060857
        //  1857: ldc_w           -1176647922
        //  1860: ixor           
        //  1861: lookupswitch {
        //          -1919864746: 1854
        //          1101115849: 1888
        //          default: 4232
        //        }
        //  1888: getstatic       net/minecraft/client/renderer/GlStateManager$SourceFactor.ONE:Lnet/minecraft/client/renderer/GlStateManager$SourceFactor;
        //  1891: getstatic       net/minecraft/client/renderer/GlStateManager$DestFactor.ZERO:Lnet/minecraft/client/renderer/GlStateManager$DestFactor;
        //  1894: getstatic       dev/nuker/pyro/fc.1:I
        //  1897: ifeq            1906
        //  1900: ldc_w           1283183620
        //  1903: goto            1909
        //  1906: ldc_w           739328877
        //  1909: ldc_w           -449413837
        //  1912: ixor           
        //  1913: lookupswitch {
        //          -1454528201: 1906
        //          -920175010: 1940
        //          default: 4238
        //        }
        //  1940: goto            1944
        //  1943: athrow         
        //  1944: invokestatic    net/minecraft/client/renderer/GlStateManager.func_187428_a:(Lnet/minecraft/client/renderer/GlStateManager$SourceFactor;Lnet/minecraft/client/renderer/GlStateManager$DestFactor;Lnet/minecraft/client/renderer/GlStateManager$SourceFactor;Lnet/minecraft/client/renderer/GlStateManager$DestFactor;)V
        //  1947: goto            1951
        //  1950: athrow         
        //  1951: fconst_1       
        //  1952: fconst_1       
        //  1953: fconst_1       
        //  1954: fconst_1       
        //  1955: goto            1959
        //  1958: athrow         
        //  1959: invokestatic    net/minecraft/client/renderer/GlStateManager.func_179131_c:(FFFF)V
        //  1962: goto            1966
        //  1965: athrow         
        //  1966: aload           7
        //  1968: bipush          7
        //  1970: getstatic       dev/nuker/pyro/fc.c:I
        //  1973: ifge            1982
        //  1976: ldc_w           -1304119957
        //  1979: goto            1985
        //  1982: ldc_w           -1773322130
        //  1985: ldc_w           591123386
        //  1988: ixor           
        //  1989: lookupswitch {
        //          -1853921583: 4298
        //          495121219: 1982
        //          default: 2016
        //        }
        //  2016: getstatic       net/minecraft/client/renderer/vertex/DefaultVertexFormats.field_181706_f:Lnet/minecraft/client/renderer/vertex/VertexFormat;
        //  2019: goto            2023
        //  2022: athrow         
        //  2023: invokevirtual   net/minecraft/client/renderer/BufferBuilder.func_181668_a:(ILnet/minecraft/client/renderer/vertex/VertexFormat;)V
        //  2026: goto            2030
        //  2029: athrow         
        //  2030: fload           5
        //  2032: f2i            
        //  2033: i2f            
        //  2034: fload           4
        //  2036: ldc_w           100.0
        //  2039: fdiv           
        //  2040: fmul           
        //  2041: fstore          5
        //  2043: goto            2047
        //  2046: athrow         
        //  2047: invokestatic    dev/nuker/pyro/fbs.4:()F
        //  2050: goto            2054
        //  2053: athrow         
        //  2054: f2i            
        //  2055: istore          8
        //  2057: getstatic       dev/nuker/pyro/fc.0:I
        //  2060: ifeq            2069
        //  2063: ldc_w           -302363873
        //  2066: goto            2072
        //  2069: ldc_w           -1988970261
        //  2072: ldc_w           -1268786042
        //  2075: ixor           
        //  2076: lookupswitch {
        //          1026385005: 2104
        //          1504024473: 2069
        //          default: 4276
        //        }
        //  2104: aload_0        
        //  2105: getfield        dev/nuker/pyro/f9e.0:Ldev/nuker/pyro/f0b;
        //  2108: getstatic       dev/nuker/pyro/fc.1:I
        //  2111: ifeq            2120
        //  2114: ldc_w           300113348
        //  2117: goto            2123
        //  2120: ldc_w           2095602032
        //  2123: ldc_w           -1447621803
        //  2126: ixor           
        //  2127: lookupswitch {
        //          -1202432367: 4296
        //          395243174: 2120
        //          default: 2152
        //        }
        //  2152: goto            2156
        //  2155: athrow         
        //  2156: invokevirtual   dev/nuker/pyro/f0b.3:()Ljava/lang/Object;
        //  2159: goto            2163
        //  2162: athrow         
        //  2163: checkcast       Ldev/nuker/pyro/fS;
        //  2166: goto            2170
        //  2169: athrow         
        //  2170: invokevirtual   dev/nuker/pyro/fS.8:()F
        //  2173: goto            2177
        //  2176: athrow         
        //  2177: fstore          9
        //  2179: aload_0        
        //  2180: getfield        dev/nuker/pyro/f9e.0:Ldev/nuker/pyro/f0b;
        //  2183: goto            2187
        //  2186: athrow         
        //  2187: invokevirtual   dev/nuker/pyro/f0b.3:()Ljava/lang/Object;
        //  2190: goto            2194
        //  2193: athrow         
        //  2194: checkcast       Ldev/nuker/pyro/fS;
        //  2197: goto            2201
        //  2200: athrow         
        //  2201: invokevirtual   dev/nuker/pyro/fS.2:()F
        //  2204: goto            2208
        //  2207: athrow         
        //  2208: getstatic       dev/nuker/pyro/fc.1:I
        //  2211: ifeq            2220
        //  2214: ldc_w           -827438151
        //  2217: goto            2223
        //  2220: ldc_w           635608633
        //  2223: ldc_w           -148433967
        //  2226: ixor           
        //  2227: lookupswitch {
        //          -344330147: 2220
        //          965302376: 4248
        //          default: 2252
        //        }
        //  2252: fstore          10
        //  2254: aload_0        
        //  2255: getfield        dev/nuker/pyro/f9e.0:Ldev/nuker/pyro/f0b;
        //  2258: getstatic       dev/nuker/pyro/fc.c:I
        //  2261: ifge            2270
        //  2264: ldc_w           -622902008
        //  2267: goto            2273
        //  2270: ldc_w           -1814952920
        //  2273: ldc_w           2041473114
        //  2276: ixor           
        //  2277: lookupswitch {
        //          -1552863918: 2270
        //          -360944526: 2304
        //          default: 4254
        //        }
        //  2304: goto            2308
        //  2307: athrow         
        //  2308: invokevirtual   dev/nuker/pyro/f0b.3:()Ljava/lang/Object;
        //  2311: goto            2315
        //  2314: athrow         
        //  2315: checkcast       Ldev/nuker/pyro/fS;
        //  2318: goto            2322
        //  2321: athrow         
        //  2322: invokevirtual   dev/nuker/pyro/fS.b:()F
        //  2325: goto            2329
        //  2328: athrow         
        //  2329: getstatic       dev/nuker/pyro/fc.0:I
        //  2332: ifeq            2341
        //  2335: ldc_w           1470199142
        //  2338: goto            2344
        //  2341: ldc_w           786496425
        //  2344: ldc_w           1790411134
        //  2347: ixor           
        //  2348: lookupswitch {
        //          1024914456: 2341
        //          1146583767: 2376
        //          default: 4274
        //        }
        //  2376: fstore          11
        //  2378: aload_0        
        //  2379: getfield        dev/nuker/pyro/f9e.0:Ldev/nuker/pyro/f0b;
        //  2382: goto            2386
        //  2385: athrow         
        //  2386: invokevirtual   dev/nuker/pyro/f0b.3:()Ljava/lang/Object;
        //  2389: goto            2393
        //  2392: athrow         
        //  2393: checkcast       Ldev/nuker/pyro/fS;
        //  2396: goto            2400
        //  2399: athrow         
        //  2400: invokevirtual   dev/nuker/pyro/fS.9:()F
        //  2403: goto            2407
        //  2406: athrow         
        //  2407: fstore          12
        //  2409: iconst_1       
        //  2410: getstatic       dev/nuker/pyro/fc.c:I
        //  2413: ifge            2422
        //  2416: ldc_w           -210975860
        //  2419: goto            2425
        //  2422: ldc_w           798910105
        //  2425: ldc_w           -1864924254
        //  2428: ixor           
        //  2429: lookupswitch {
        //          -679612781: 2422
        //          1673216046: 4244
        //          default: 2456
        //        }
        //  2456: istore          13
        //  2458: iconst_0       
        //  2459: istore          14
        //  2461: goto            2465
        //  2464: athrow         
        //  2465: invokestatic    dev/nuker/pyro/fbs.4:()F
        //  2468: goto            2472
        //  2471: athrow         
        //  2472: f2i            
        //  2473: iload           8
        //  2475: isub           
        //  2476: istore          15
        //  2478: fconst_0       
        //  2479: getstatic       dev/nuker/pyro/fc.c:I
        //  2482: ifge            2491
        //  2485: ldc_w           -1652803809
        //  2488: goto            2494
        //  2491: ldc_w           -841627219
        //  2494: ldc_w           1569109169
        //  2497: ixor           
        //  2498: lookupswitch {
        //          -1873576676: 2524
        //          -1057324114: 2491
        //          default: 4310
        //        }
        //  2524: fstore          16
        //  2526: iload           14
        //  2528: istore          17
        //  2530: iload           14
        //  2532: i2f            
        //  2533: fload           5
        //  2535: fadd           
        //  2536: f2i            
        //  2537: getstatic       dev/nuker/pyro/fc.c:I
        //  2540: ifge            2549
        //  2543: ldc_w           -1503943179
        //  2546: goto            2552
        //  2549: ldc_w           395250451
        //  2552: ldc_w           1073849128
        //  2555: ixor           
        //  2556: lookupswitch {
        //          -430307619: 4288
        //          2112038844: 2549
        //          default: 2584
        //        }
        //  2584: istore          18
        //  2586: iload           17
        //  2588: iload           18
        //  2590: if_icmpge       2599
        //  2593: ldc_w           1421771383
        //  2596: goto            2602
        //  2599: ldc_w           1421771382
        //  2602: ldc_w           -2146304601
        //  2605: ixor           
        //  2606: tableswitch {
        //          -1453391968: 2628
        //          -1453391967: 4056
        //          default: 2593
        //        }
        //  2628: iload           17
        //  2630: iload           14
        //  2632: isub           
        //  2633: i2f            
        //  2634: getstatic       dev/nuker/pyro/fc.c:I
        //  2637: ifge            2646
        //  2640: ldc_w           -1608199536
        //  2643: goto            2649
        //  2646: ldc_w           410358083
        //  2649: ldc_w           -1230657376
        //  2652: ixor           
        //  2653: lookupswitch {
        //          -1362085405: 2680
        //          377584176: 2646
        //          default: 4236
        //        }
        //  2680: fload           5
        //  2682: fdiv           
        //  2683: fstore          19
        //  2685: iconst_4       
        //  2686: newarray        F
        //  2688: dup            
        //  2689: iconst_0       
        //  2690: iload           13
        //  2692: ifne            2701
        //  2695: ldc_w           -226501005
        //  2698: goto            2704
        //  2701: ldc_w           -226501012
        //  2704: ldc_w           -952960100
        //  2707: ixor           
        //  2708: tableswitch {
        //          1788496862: 2732
        //          1788496863: 2737
        //          default: 2695
        //        }
        //  2732: fload           16
        //  2734: goto            2786
        //  2737: getstatic       dev/nuker/pyro/fc.c:I
        //  2740: ifge            2749
        //  2743: ldc_w           -877856393
        //  2746: goto            2752
        //  2749: ldc_w           1134700009
        //  2752: ldc_w           -1191167816
        //  2755: ixor           
        //  2756: lookupswitch {
        //          -1501911989: 2749
        //          1923924431: 4300
        //          default: 2784
        //        }
        //  2784: fload           9
        //  2786: fastore        
        //  2787: dup            
        //  2788: iconst_1       
        //  2789: iload           13
        //  2791: iconst_1       
        //  2792: if_icmpne       2800
        //  2795: fload           16
        //  2797: goto            2802
        //  2800: fload           10
        //  2802: fastore        
        //  2803: dup            
        //  2804: iconst_2       
        //  2805: iload           13
        //  2807: iconst_2       
        //  2808: if_icmpne       2816
        //  2811: fload           16
        //  2813: goto            2862
        //  2816: getstatic       dev/nuker/pyro/fc.c:I
        //  2819: ifge            2828
        //  2822: ldc_w           -430714039
        //  2825: goto            2831
        //  2828: ldc_w           -917688807
        //  2831: ldc_w           -1639239715
        //  2834: ixor           
        //  2835: lookupswitch {
        //          1039394830: 2828
        //          2014903444: 4318
        //          default: 2860
        //        }
        //  2860: fload           11
        //  2862: fastore        
        //  2863: dup            
        //  2864: iconst_3       
        //  2865: iload           13
        //  2867: iconst_3       
        //  2868: if_icmpne       2877
        //  2871: ldc_w           1144727959
        //  2874: goto            2880
        //  2877: ldc_w           1144727958
        //  2880: ldc_w           1487151435
        //  2883: ixor           
        //  2884: tableswitch {
        //          960369080: 2908
        //          960369081: 2913
        //          default: 2871
        //        }
        //  2908: fload           16
        //  2910: goto            2915
        //  2913: fload           12
        //  2915: fastore        
        //  2916: getstatic       dev/nuker/pyro/fc.0:I
        //  2919: ifeq            2928
        //  2922: ldc_w           -256028530
        //  2925: goto            2931
        //  2928: ldc_w           -1597941437
        //  2931: ldc_w           -152718852
        //  2934: ixor           
        //  2935: lookupswitch {
        //          106488178: 2928
        //          1445259455: 2960
        //          default: 4314
        //        }
        //  2960: astore          20
        //  2962: iconst_4       
        //  2963: newarray        F
        //  2965: dup            
        //  2966: iconst_0       
        //  2967: iload           13
        //  2969: ifne            2977
        //  2972: fload           19
        //  2974: goto            2979
        //  2977: fload           9
        //  2979: fastore        
        //  2980: dup            
        //  2981: iconst_1       
        //  2982: iload           13
        //  2984: iconst_1       
        //  2985: if_icmpne       2993
        //  2988: fload           19
        //  2990: goto            3042
        //  2993: getstatic       dev/nuker/pyro/fc.1:I
        //  2996: ifeq            3005
        //  2999: ldc_w           1411977601
        //  3002: goto            3008
        //  3005: ldc_w           1965486935
        //  3008: ldc_w           2054676787
        //  3011: ixor           
        //  3012: lookupswitch {
        //          256971364: 3040
        //          777973938: 3005
        //          default: 4292
        //        }
        //  3040: fload           10
        //  3042: fastore        
        //  3043: dup            
        //  3044: iconst_2       
        //  3045: iload           13
        //  3047: iconst_2       
        //  3048: if_icmpne       3101
        //  3051: getstatic       dev/nuker/pyro/fc.0:I
        //  3054: ifeq            3063
        //  3057: ldc_w           -1633566657
        //  3060: goto            3066
        //  3063: ldc_w           -843661130
        //  3066: ldc_w           -1147984661
        //  3069: ixor           
        //  3070: lookupswitch {
        //          624092372: 3063
        //          1982194781: 3096
        //          default: 4302
        //        }
        //  3096: fload           19
        //  3098: goto            3103
        //  3101: fload           11
        //  3103: fastore        
        //  3104: dup            
        //  3105: iconst_3       
        //  3106: iload           13
        //  3108: iconst_3       
        //  3109: if_icmpne       3117
        //  3112: fload           19
        //  3114: goto            3119
        //  3117: fload           12
        //  3119: fastore        
        //  3120: astore          21
        //  3122: getstatic       dev/nuker/pyro/fc.0:I
        //  3125: ifeq            3134
        //  3128: ldc_w           1536725455
        //  3131: goto            3137
        //  3134: ldc_w           1953759695
        //  3137: ldc_w           -1785272654
        //  3140: ixor           
        //  3141: lookupswitch {
        //          -837912707: 3134
        //          -505223299: 3168
        //          default: 4280
        //        }
        //  3168: aload           7
        //  3170: getstatic       dev/nuker/pyro/fc.0:I
        //  3173: ifeq            3182
        //  3176: ldc_w           -1270143939
        //  3179: goto            3185
        //  3182: ldc_w           1858156568
        //  3185: ldc_w           1782408439
        //  3188: ixor           
        //  3189: lookupswitch {
        //          -562675510: 3182
        //          83647727: 3216
        //          default: 4268
        //        }
        //  3216: iload           17
        //  3218: i2d            
        //  3219: iload           15
        //  3221: iload           8
        //  3223: iadd           
        //  3224: i2d            
        //  3225: dconst_0       
        //  3226: goto            3230
        //  3229: athrow         
        //  3230: invokevirtual   net/minecraft/client/renderer/BufferBuilder.func_181662_b:(DDD)Lnet/minecraft/client/renderer/BufferBuilder;
        //  3233: goto            3237
        //  3236: athrow         
        //  3237: getstatic       dev/nuker/pyro/fc.0:I
        //  3240: ifeq            3249
        //  3243: ldc_w           325239452
        //  3246: goto            3252
        //  3249: ldc_w           754042477
        //  3252: ldc_w           -1359291597
        //  3255: ixor           
        //  3256: lookupswitch {
        //          -1114105425: 4222
        //          -523238232: 3249
        //          default: 3284
        //        }
        //  3284: aload           20
        //  3286: iconst_0       
        //  3287: faload         
        //  3288: getstatic       dev/nuker/pyro/fc.0:I
        //  3291: ifeq            3300
        //  3294: ldc_w           224775585
        //  3297: goto            3303
        //  3300: ldc_w           -2054189125
        //  3303: ldc_w           -287701324
        //  3306: ixor           
        //  3307: lookupswitch {
        //          -473969899: 4234
        //          2137136967: 3300
        //          default: 3332
        //        }
        //  3332: aload           20
        //  3334: iconst_1       
        //  3335: faload         
        //  3336: aload           20
        //  3338: iconst_2       
        //  3339: faload         
        //  3340: aload           20
        //  3342: iconst_3       
        //  3343: faload         
        //  3344: goto            3348
        //  3347: athrow         
        //  3348: invokevirtual   net/minecraft/client/renderer/BufferBuilder.func_181666_a:(FFFF)Lnet/minecraft/client/renderer/BufferBuilder;
        //  3351: goto            3355
        //  3354: athrow         
        //  3355: getstatic       dev/nuker/pyro/fc.0:I
        //  3358: ifeq            3367
        //  3361: ldc_w           -1728189689
        //  3364: goto            3370
        //  3367: ldc_w           808239461
        //  3370: ldc_w           -772132328
        //  3373: ixor           
        //  3374: lookupswitch {
        //          -649295111: 3367
        //          1225251103: 4284
        //          default: 3400
        //        }
        //  3400: goto            3404
        //  3403: athrow         
        //  3404: invokevirtual   net/minecraft/client/renderer/BufferBuilder.func_181675_d:()V
        //  3407: goto            3411
        //  3410: athrow         
        //  3411: aload           7
        //  3413: getstatic       dev/nuker/pyro/fc.0:I
        //  3416: ifeq            3425
        //  3419: ldc_w           -1699416837
        //  3422: goto            3428
        //  3425: ldc_w           1799847592
        //  3428: ldc_w           832973451
        //  3431: ixor           
        //  3432: lookupswitch {
        //          -1424826768: 4304
        //          582740692: 3425
        //          default: 3460
        //        }
        //  3460: iload           17
        //  3462: i2d            
        //  3463: dconst_1       
        //  3464: dadd           
        //  3465: getstatic       dev/nuker/pyro/fc.c:I
        //  3468: ifge            3477
        //  3471: ldc_w           -1852881829
        //  3474: goto            3480
        //  3477: ldc_w           -1352165600
        //  3480: ldc_w           1890501527
        //  3483: ixor           
        //  3484: lookupswitch {
        //          -540453705: 3512
        //          -517896244: 3477
        //          default: 4278
        //        }
        //  3512: iload           15
        //  3514: iload           8
        //  3516: iadd           
        //  3517: i2d            
        //  3518: dconst_0       
        //  3519: goto            3523
        //  3522: athrow         
        //  3523: invokevirtual   net/minecraft/client/renderer/BufferBuilder.func_181662_b:(DDD)Lnet/minecraft/client/renderer/BufferBuilder;
        //  3526: goto            3530
        //  3529: athrow         
        //  3530: aload           21
        //  3532: iconst_0       
        //  3533: faload         
        //  3534: aload           21
        //  3536: iconst_1       
        //  3537: faload         
        //  3538: aload           21
        //  3540: iconst_2       
        //  3541: faload         
        //  3542: aload           21
        //  3544: iconst_3       
        //  3545: faload         
        //  3546: getstatic       dev/nuker/pyro/fc.1:I
        //  3549: ifeq            3558
        //  3552: ldc_w           -818299215
        //  3555: goto            3561
        //  3558: ldc_w           -2114628272
        //  3561: ldc_w           -1875097029
        //  3564: ixor           
        //  3565: lookupswitch {
        //          884332584: 3558
        //          1594225802: 4290
        //          default: 3592
        //        }
        //  3592: goto            3596
        //  3595: athrow         
        //  3596: invokevirtual   net/minecraft/client/renderer/BufferBuilder.func_181666_a:(FFFF)Lnet/minecraft/client/renderer/BufferBuilder;
        //  3599: goto            3603
        //  3602: athrow         
        //  3603: goto            3607
        //  3606: athrow         
        //  3607: invokevirtual   net/minecraft/client/renderer/BufferBuilder.func_181675_d:()V
        //  3610: goto            3614
        //  3613: athrow         
        //  3614: getstatic       dev/nuker/pyro/fc.c:I
        //  3617: ifge            3626
        //  3620: ldc_w           -1965898427
        //  3623: goto            3629
        //  3626: ldc_w           1996554977
        //  3629: ldc_w           1057300305
        //  3632: ixor           
        //  3633: lookupswitch {
        //          -1244145132: 4258
        //          -1156409924: 3626
        //          default: 3660
        //        }
        //  3660: aload           7
        //  3662: iload           17
        //  3664: i2d            
        //  3665: dconst_1       
        //  3666: dadd           
        //  3667: iload           15
        //  3669: i2d            
        //  3670: dconst_0       
        //  3671: goto            3675
        //  3674: athrow         
        //  3675: invokevirtual   net/minecraft/client/renderer/BufferBuilder.func_181662_b:(DDD)Lnet/minecraft/client/renderer/BufferBuilder;
        //  3678: goto            3682
        //  3681: athrow         
        //  3682: aload           21
        //  3684: iconst_0       
        //  3685: faload         
        //  3686: aload           21
        //  3688: iconst_1       
        //  3689: faload         
        //  3690: getstatic       dev/nuker/pyro/fc.c:I
        //  3693: ifge            3702
        //  3696: ldc_w           -2022616986
        //  3699: goto            3705
        //  3702: ldc_w           80030026
        //  3705: ldc_w           1003165308
        //  3708: ixor           
        //  3709: lookupswitch {
        //          -1128643046: 4306
        //          422610262: 3702
        //          default: 3736
        //        }
        //  3736: aload           21
        //  3738: iconst_2       
        //  3739: faload         
        //  3740: aload           21
        //  3742: iconst_3       
        //  3743: faload         
        //  3744: getstatic       dev/nuker/pyro/fc.c:I
        //  3747: ifge            3756
        //  3750: ldc_w           347368183
        //  3753: goto            3759
        //  3756: ldc_w           -847356615
        //  3759: ldc_w           -1614291782
        //  3762: ixor           
        //  3763: lookupswitch {
        //          -1955350963: 4282
        //          -1859096054: 3756
        //          default: 3788
        //        }
        //  3788: goto            3792
        //  3791: athrow         
        //  3792: invokevirtual   net/minecraft/client/renderer/BufferBuilder.func_181666_a:(FFFF)Lnet/minecraft/client/renderer/BufferBuilder;
        //  3795: goto            3799
        //  3798: athrow         
        //  3799: goto            3803
        //  3802: athrow         
        //  3803: invokevirtual   net/minecraft/client/renderer/BufferBuilder.func_181675_d:()V
        //  3806: goto            3810
        //  3809: athrow         
        //  3810: aload           7
        //  3812: getstatic       dev/nuker/pyro/fc.0:I
        //  3815: ifeq            3824
        //  3818: ldc_w           1229305377
        //  3821: goto            3827
        //  3824: ldc_w           2044355400
        //  3827: ldc_w           782353491
        //  3830: ixor           
        //  3831: lookupswitch {
        //          1467721499: 3856
        //          1743024754: 3824
        //          default: 4316
        //        }
        //  3856: iload           17
        //  3858: i2d            
        //  3859: getstatic       dev/nuker/pyro/fc.1:I
        //  3862: ifeq            3871
        //  3865: ldc_w           491523671
        //  3868: goto            3874
        //  3871: ldc_w           -2061063874
        //  3874: ldc_w           272141791
        //  3877: ixor           
        //  3878: lookupswitch {
        //          -1793186591: 3904
        //          225739656: 3871
        //          default: 4266
        //        }
        //  3904: iload           15
        //  3906: i2d            
        //  3907: dconst_0       
        //  3908: goto            3912
        //  3911: athrow         
        //  3912: invokevirtual   net/minecraft/client/renderer/BufferBuilder.func_181662_b:(DDD)Lnet/minecraft/client/renderer/BufferBuilder;
        //  3915: goto            3919
        //  3918: athrow         
        //  3919: aload           20
        //  3921: iconst_0       
        //  3922: faload         
        //  3923: getstatic       dev/nuker/pyro/fc.0:I
        //  3926: ifeq            3935
        //  3929: ldc_w           1509601186
        //  3932: goto            3938
        //  3935: ldc_w           1917371
        //  3938: ldc_w           -999307763
        //  3941: ixor           
        //  3942: lookupswitch {
        //          -1651152465: 4260
        //          1275887959: 3935
        //          default: 3968
        //        }
        //  3968: aload           20
        //  3970: iconst_1       
        //  3971: faload         
        //  3972: getstatic       dev/nuker/pyro/fc.1:I
        //  3975: ifeq            3984
        //  3978: ldc_w           750231509
        //  3981: goto            3987
        //  3984: ldc_w           439122434
        //  3987: ldc_w           1421032237
        //  3990: ixor           
        //  3991: lookupswitch {
        //          815066133: 3984
        //          2013570296: 4262
        //          default: 4016
        //        }
        //  4016: aload           20
        //  4018: iconst_2       
        //  4019: faload         
        //  4020: aload           20
        //  4022: iconst_3       
        //  4023: faload         
        //  4024: goto            4028
        //  4027: athrow         
        //  4028: invokevirtual   net/minecraft/client/renderer/BufferBuilder.func_181666_a:(FFFF)Lnet/minecraft/client/renderer/BufferBuilder;
        //  4031: goto            4035
        //  4034: athrow         
        //  4035: goto            4039
        //  4038: athrow         
        //  4039: invokevirtual   net/minecraft/client/renderer/BufferBuilder.func_181675_d:()V
        //  4042: goto            4046
        //  4045: athrow         
        //  4046: fload           19
        //  4048: fstore          16
        //  4050: iinc            17, 1
        //  4053: goto            2586
        //  4056: aload           6
        //  4058: getstatic       dev/nuker/pyro/fc.c:I
        //  4061: ifge            4070
        //  4064: ldc_w           -1989266098
        //  4067: goto            4073
        //  4070: ldc_w           2063798388
        //  4073: ldc_w           1941392225
        //  4076: ixor           
        //  4077: lookupswitch {
        //          -86409681: 4070
        //          146037525: 4104
        //          default: 4240
        //        }
        //  4104: goto            4108
        //  4107: athrow         
        //  4108: invokevirtual   net/minecraft/client/renderer/Tessellator.func_78381_a:()V
        //  4111: goto            4115
        //  4114: athrow         
        //  4115: goto            4119
        //  4118: athrow         
        //  4119: invokestatic    net/minecraft/client/renderer/GlStateManager.func_179098_w:()V
        //  4122: goto            4126
        //  4125: athrow         
        //  4126: getstatic       dev/nuker/pyro/fc.1:I
        //  4129: ifeq            4138
        //  4132: ldc_w           -892293964
        //  4135: goto            4141
        //  4138: ldc_w           230262951
        //  4141: ldc_w           1822116635
        //  4144: ixor           
        //  4145: lookupswitch {
        //          -1504974929: 4138
        //          1629668284: 4172
        //          default: 4246
        //        }
        //  4172: goto            4176
        //  4175: athrow         
        //  4176: invokestatic    net/minecraft/client/renderer/GlStateManager.func_179084_k:()V
        //  4179: goto            4183
        //  4182: athrow         
        //  4183: sipush          7424
        //  4186: goto            4190
        //  4189: athrow         
        //  4190: invokestatic    net/minecraft/client/renderer/GlStateManager.func_179103_j:(I)V
        //  4193: goto            4197
        //  4196: athrow         
        //  4197: goto            4201
        //  4200: athrow         
        //  4201: invokestatic    net/minecraft/client/renderer/GlStateManager.func_179121_F:()V
        //  4204: goto            4208
        //  4207: athrow         
        //  4208: goto            4212
        //  4211: athrow         
        //  4212: invokestatic    net/minecraft/client/renderer/GlStateManager.func_179121_F:()V
        //  4215: goto            4219
        //  4218: athrow         
        //  4219: return         
        //  4220: aconst_null    
        //  4221: athrow         
        //  4222: aconst_null    
        //  4223: athrow         
        //  4224: aconst_null    
        //  4225: athrow         
        //  4226: aconst_null    
        //  4227: athrow         
        //  4228: aconst_null    
        //  4229: athrow         
        //  4230: aconst_null    
        //  4231: athrow         
        //  4232: aconst_null    
        //  4233: athrow         
        //  4234: aconst_null    
        //  4235: athrow         
        //  4236: aconst_null    
        //  4237: athrow         
        //  4238: aconst_null    
        //  4239: athrow         
        //  4240: aconst_null    
        //  4241: athrow         
        //  4242: aconst_null    
        //  4243: athrow         
        //  4244: aconst_null    
        //  4245: athrow         
        //  4246: aconst_null    
        //  4247: athrow         
        //  4248: aconst_null    
        //  4249: athrow         
        //  4250: aconst_null    
        //  4251: athrow         
        //  4252: aconst_null    
        //  4253: athrow         
        //  4254: aconst_null    
        //  4255: athrow         
        //  4256: aconst_null    
        //  4257: athrow         
        //  4258: aconst_null    
        //  4259: athrow         
        //  4260: aconst_null    
        //  4261: athrow         
        //  4262: aconst_null    
        //  4263: athrow         
        //  4264: aconst_null    
        //  4265: athrow         
        //  4266: aconst_null    
        //  4267: athrow         
        //  4268: aconst_null    
        //  4269: athrow         
        //  4270: aconst_null    
        //  4271: athrow         
        //  4272: aconst_null    
        //  4273: athrow         
        //  4274: aconst_null    
        //  4275: athrow         
        //  4276: aconst_null    
        //  4277: athrow         
        //  4278: aconst_null    
        //  4279: athrow         
        //  4280: aconst_null    
        //  4281: athrow         
        //  4282: aconst_null    
        //  4283: athrow         
        //  4284: aconst_null    
        //  4285: athrow         
        //  4286: aconst_null    
        //  4287: athrow         
        //  4288: aconst_null    
        //  4289: athrow         
        //  4290: aconst_null    
        //  4291: athrow         
        //  4292: aconst_null    
        //  4293: athrow         
        //  4294: aconst_null    
        //  4295: athrow         
        //  4296: aconst_null    
        //  4297: athrow         
        //  4298: aconst_null    
        //  4299: athrow         
        //  4300: aconst_null    
        //  4301: athrow         
        //  4302: aconst_null    
        //  4303: athrow         
        //  4304: aconst_null    
        //  4305: athrow         
        //  4306: aconst_null    
        //  4307: athrow         
        //  4308: aconst_null    
        //  4309: athrow         
        //  4310: aconst_null    
        //  4311: athrow         
        //  4312: aconst_null    
        //  4313: athrow         
        //  4314: aconst_null    
        //  4315: athrow         
        //  4316: aconst_null    
        //  4317: athrow         
        //  4318: aconst_null    
        //  4319: athrow         
        //  4320: aconst_null    
        //  4321: athrow         
        //  4322: aconst_null    
        //  4323: athrow         
        //  4324: pop            
        //  4325: goto            24
        //  4328: pop            
        //  4329: aconst_null    
        //  4330: goto            4324
        //  4333: dup            
        //  4334: ifnull          4324
        //  4337: checkcast       Ljava/lang/Throwable;
        //  4340: athrow         
        //  4341: dup            
        //  4342: ifnull          4328
        //  4345: checkcast       Ljava/lang/Throwable;
        //  4348: athrow         
        //  4349: aconst_null    
        //  4350: athrow         
        //    StackMapTable: 02 77 43 07 00 A5 04 FF 00 0B 00 00 00 01 07 00 A5 FE 00 03 07 00 03 07 00 F2 07 01 0C 43 07 00 A5 40 07 00 F2 45 07 00 A5 40 01 49 07 00 A5 FF 00 00 00 03 07 00 03 07 00 F2 07 01 0C 00 02 01 07 00 FC 45 07 00 A5 FF 00 00 00 03 07 00 03 07 00 F2 07 01 0C 00 02 01 01 4A 07 00 A5 FF 00 00 00 03 07 00 03 07 00 F2 07 01 0C 00 02 07 01 01 01 45 07 00 A5 00 FF 00 0F 00 03 07 00 03 07 00 F2 07 01 0C 00 02 07 01 01 07 01 0C FF 00 02 00 03 07 00 03 07 00 F2 07 01 0C 00 03 07 01 01 07 01 0C 01 FF 00 1F 00 03 07 00 03 07 00 F2 07 01 0C 00 02 07 01 01 07 01 0C 42 07 00 DE FF 00 00 00 03 07 00 03 07 00 F2 07 01 0C 00 02 07 01 01 07 01 0C 45 07 00 A5 FF 00 00 00 03 07 00 03 07 00 F2 07 01 0C 00 02 07 01 01 07 01 39 FF 00 0B 00 03 07 00 03 07 00 F2 07 01 0C 00 02 07 01 01 07 01 39 FF 00 02 00 03 07 00 03 07 00 F2 07 01 0C 00 03 07 01 01 07 01 39 01 FF 00 1D 00 03 07 00 03 07 00 F2 07 01 0C 00 02 07 01 01 07 01 39 46 07 00 A5 FF 00 00 00 03 07 00 03 07 00 F2 07 01 0C 00 03 07 01 01 07 01 39 07 00 25 45 07 00 A5 FF 00 00 00 03 07 00 03 07 00 F2 07 01 0C 00 03 07 01 01 07 01 39 07 01 69 FF 00 0E 00 03 07 00 03 07 00 F2 07 01 0C 00 03 07 01 01 07 01 39 07 00 2B FF 00 02 00 03 07 00 03 07 00 F2 07 01 0C 00 04 07 01 01 07 01 39 07 00 2B 01 FF 00 1E 00 03 07 00 03 07 00 F2 07 01 0C 00 03 07 01 01 07 01 39 07 00 2B FF 00 02 00 00 00 01 07 00 A5 FF 00 00 00 03 07 00 03 07 00 F2 07 01 0C 00 03 07 01 01 07 01 39 07 00 2B 45 07 00 A5 FF 00 00 00 03 07 00 03 07 00 F2 07 01 0C 00 03 07 01 01 07 01 39 01 FF 00 04 00 00 00 01 07 00 A5 FF 00 00 00 03 07 00 03 07 00 F2 07 01 0C 00 04 07 01 01 07 01 39 01 01 45 07 00 A5 00 FF 00 05 00 00 00 01 07 00 A5 FF 00 00 00 03 07 00 03 07 00 F2 07 01 0C 00 01 07 01 01 45 07 00 A5 00 42 07 00 A1 00 45 07 00 A5 00 46 07 00 A5 40 07 00 AF 45 07 00 A5 40 07 01 A4 05 05 42 01 18 0B 42 01 1C 46 07 00 A5 40 07 00 AF 45 07 00 A5 40 07 01 A4 05 4C 07 00 03 FF 00 02 00 03 07 00 03 07 00 F2 07 01 0C 00 02 07 00 03 01 5E 07 00 03 45 07 01 2E FF 00 04 00 04 07 00 03 07 00 F2 07 01 0C 07 01 2E 00 01 07 00 A5 40 07 01 0C 45 07 00 A5 40 07 01 39 42 07 00 F0 40 07 01 39 45 07 00 A5 40 01 47 07 00 EE FF 00 00 00 04 07 00 03 07 00 F2 07 01 0C 07 01 2E 00 02 02 07 01 0C 45 07 00 A5 FF 00 00 00 04 07 00 03 07 00 F2 07 01 0C 07 01 2E 00 02 02 07 01 39 FF 00 0B 00 04 07 00 03 07 00 F2 07 01 0C 07 01 2E 00 02 02 07 01 39 FF 00 02 00 04 07 00 03 07 00 F2 07 01 0C 07 01 2E 00 03 02 07 01 39 01 FF 00 1E 00 04 07 00 03 07 00 F2 07 01 0C 07 01 2E 00 02 02 07 01 39 42 07 00 A5 FF 00 00 00 04 07 00 03 07 00 F2 07 01 0C 07 01 2E 00 02 02 07 01 39 45 07 00 A5 FF 00 00 00 04 07 00 03 07 00 F2 07 01 0C 07 01 2E 00 02 02 01 47 07 00 A5 FF 00 00 00 04 07 00 03 07 00 F2 07 01 0C 07 01 2E 00 03 02 02 07 01 0C 45 07 00 A5 FF 00 00 00 04 07 00 03 07 00 F2 07 01 0C 07 01 2E 00 03 02 02 07 01 39 FF 00 0B 00 04 07 00 03 07 00 F2 07 01 0C 07 01 2E 00 03 02 02 07 01 39 FF 00 02 00 04 07 00 03 07 00 F2 07 01 0C 07 01 2E 00 04 02 02 07 01 39 01 FF 00 1D 00 04 07 00 03 07 00 F2 07 01 0C 07 01 2E 00 03 02 02 07 01 39 42 07 00 E6 FF 00 00 00 04 07 00 03 07 00 F2 07 01 0C 07 01 2E 00 03 02 02 07 01 39 45 07 00 A5 FF 00 00 00 04 07 00 03 07 00 F2 07 01 0C 07 01 2E 00 03 02 02 01 FF 00 11 00 04 07 00 03 07 00 F2 07 01 0C 07 01 2E 00 05 02 02 02 07 01 2E 02 FF 00 02 00 04 07 00 03 07 00 F2 07 01 0C 07 01 2E 00 06 02 02 02 07 01 2E 02 01 FF 00 1F 00 04 07 00 03 07 00 F2 07 01 0C 07 01 2E 00 05 02 02 02 07 01 2E 02 42 07 00 A5 FF 00 00 00 04 07 00 03 07 00 F2 07 01 0C 07 01 2E 00 05 02 02 02 07 01 2E 02 45 07 00 A5 00 43 07 00 EC 40 07 01 0C 45 07 00 A5 40 01 FF 00 09 00 05 07 00 03 07 00 F2 07 01 0C 07 01 2E 02 00 01 07 00 A5 00 45 07 00 A5 00 46 07 00 A5 40 07 00 48 45 07 00 A5 40 07 01 69 45 07 00 A5 40 07 01 5A 45 07 00 A5 40 01 02 05 42 01 19 46 07 00 A5 FF 00 00 00 05 07 00 03 07 00 F2 07 01 0C 07 01 2E 02 00 02 08 03 1C 08 03 1C 45 07 00 A5 40 07 01 63 45 07 00 9F FF 00 00 00 05 07 00 03 07 00 F2 07 01 0C 07 01 2E 02 00 02 07 01 63 07 00 95 45 07 00 A5 FF 00 00 00 05 07 00 03 07 00 F2 07 01 0C 07 01 2E 02 00 02 07 01 63 07 00 95 4A 07 00 A5 FF 00 00 00 05 07 00 03 07 00 F2 07 01 0C 07 01 2E 02 00 06 07 01 63 07 00 95 07 02 9C 07 02 9C 01 02 45 07 00 A5 FF 00 00 00 05 07 00 03 07 00 F2 07 01 0C 07 01 2E 02 00 06 07 01 63 07 00 95 07 02 9C 07 02 9C 01 07 01 6B 43 07 00 A5 FF 00 00 00 05 07 00 03 07 00 F2 07 01 0C 07 01 2E 02 00 03 07 01 63 07 00 95 07 02 9C 45 07 00 A5 FF 00 00 00 05 07 00 03 07 00 F2 07 01 0C 07 01 2E 02 00 02 07 01 63 07 00 95 42 07 00 EC FF 00 00 00 05 07 00 03 07 00 F2 07 01 0C 07 01 2E 02 00 02 07 01 63 07 00 95 45 07 00 A5 40 07 01 63 FF 00 0E 00 05 07 00 03 07 00 F2 07 01 0C 07 01 2E 02 00 02 07 01 63 07 00 95 FF 00 02 00 05 07 00 03 07 00 F2 07 01 0C 07 01 2E 02 00 03 07 01 63 07 00 95 01 FF 00 1E 00 05 07 00 03 07 00 F2 07 01 0C 07 01 2E 02 00 02 07 01 63 07 00 95 42 07 00 A5 FF 00 00 00 05 07 00 03 07 00 F2 07 01 0C 07 01 2E 02 00 02 07 01 63 07 00 95 45 07 00 A5 40 07 01 63 42 07 00 A5 40 07 01 63 45 07 00 A5 40 07 00 95 FF 00 04 00 06 07 00 03 07 00 F2 07 01 0C 07 01 2E 02 07 00 95 00 01 07 00 A5 00 45 07 00 A5 00 0B 42 01 1D 44 07 00 A5 40 07 00 95 45 07 00 A5 40 02 FC 00 0D 02 42 01 1D 4C 07 00 A5 FF 00 00 00 07 07 00 03 07 00 F2 07 01 0C 07 01 2E 02 07 00 95 02 00 03 03 03 03 45 07 00 A5 00 47 07 00 A5 FF 00 00 00 07 07 00 03 07 00 F2 07 01 0C 07 01 2E 02 07 00 95 02 00 04 07 00 95 02 02 01 45 07 00 A5 00 42 07 00 A5 00 45 07 00 A5 F9 00 00 46 07 00 DC 40 07 00 48 45 07 00 A5 40 07 01 69 45 07 00 A5 40 07 01 5A 45 07 00 A5 40 01 FF 00 0D 00 00 00 01 07 00 A5 FF 00 00 00 05 07 00 03 07 00 F2 07 01 0C 07 01 2E 02 00 02 07 01 9B 07 00 F2 45 07 00 A5 FF 00 00 00 05 07 00 03 07 00 F2 07 01 0C 07 01 2E 02 00 02 07 01 9B 01 42 07 00 A5 FF 00 00 00 05 07 00 03 07 00 F2 07 01 0C 07 01 2E 02 00 02 07 01 9B 01 45 07 00 A5 40 07 01 A4 FC 00 12 07 01 A4 42 01 1F 42 07 00 A5 00 45 07 00 A5 00 44 07 00 F0 40 07 01 A4 45 07 00 A5 40 07 00 95 42 07 00 E4 40 07 00 95 45 07 00 A5 40 02 FF 00 0C 00 00 00 01 07 00 A5 FF 00 00 00 07 07 00 03 07 00 F2 07 01 0C 07 01 2E 02 07 01 A4 02 00 01 03 45 07 00 A5 FF 00 00 00 07 07 00 03 07 00 F2 07 01 0C 07 01 2E 02 07 01 A4 02 00 02 03 02 44 07 00 A5 FF 00 00 00 07 07 00 03 07 00 F2 07 01 0C 07 01 2E 02 07 01 A4 02 00 03 03 03 03 45 07 00 A5 00 44 07 00 F0 40 07 01 A4 45 07 00 A5 40 07 00 95 FF 00 09 00 00 00 01 07 00 A5 FF 00 00 00 07 07 00 03 07 00 F2 07 01 0C 07 01 2E 02 07 01 A4 02 00 05 07 00 95 02 02 07 01 B2 07 01 A4 45 07 00 A5 FF 00 00 00 07 07 00 03 07 00 F2 07 01 0C 07 01 2E 02 07 01 A4 02 00 05 07 00 95 02 02 07 01 B2 07 00 95 42 07 00 A5 FF 00 00 00 07 07 00 03 07 00 F2 07 01 0C 07 01 2E 02 07 01 A4 02 00 05 07 00 95 02 02 07 01 B2 07 00 95 45 07 00 A5 FF 00 00 00 07 07 00 03 07 00 F2 07 01 0C 07 01 2E 02 07 01 A4 02 00 04 07 00 95 02 02 01 FF 00 08 00 07 07 00 03 07 00 F2 07 01 0C 07 01 2E 02 07 01 A4 02 00 03 07 00 95 02 02 FF 00 00 00 07 07 00 03 07 00 F2 07 01 0C 07 01 2E 02 07 01 A4 02 00 04 07 00 95 02 02 01 FF 00 02 00 00 00 01 07 00 A5 FF 00 00 00 07 07 00 03 07 00 F2 07 01 0C 07 01 2E 02 07 01 A4 02 00 04 07 00 95 02 02 01 45 07 00 A5 00 42 07 00 A5 00 45 07 00 A5 F9 00 00 46 07 00 A1 40 07 00 48 45 07 00 A5 40 07 01 69 FF 00 05 00 00 00 01 07 00 A5 FF 00 00 00 05 07 00 03 07 00 F2 07 01 0C 07 01 2E 02 00 01 07 01 5A 45 07 00 A5 40 01 45 07 00 A5 00 45 07 00 A5 00 4E 07 00 95 FF 00 02 00 05 07 00 03 07 00 F2 07 01 0C 07 01 2E 02 00 02 07 00 95 01 5F 07 00 95 FF 00 02 00 00 00 01 07 00 A5 FF 00 00 00 05 07 00 03 07 00 F2 07 01 0C 07 01 2E 02 00 01 07 00 95 45 07 00 A5 40 07 00 95 42 07 00 A5 40 07 00 95 45 07 00 A5 40 02 FF 00 15 00 06 07 00 03 07 00 F2 07 01 0C 07 01 2E 02 02 00 01 03 FF 00 02 00 06 07 00 03 07 00 F2 07 01 0C 07 01 2E 02 02 00 02 03 01 5C 03 42 07 00 A5 40 03 45 07 00 A5 FF 00 00 00 06 07 00 03 07 00 F2 07 01 0C 07 01 2E 02 02 00 02 03 02 49 07 00 A5 FF 00 00 00 06 07 00 03 07 00 F2 07 01 0C 07 01 2E 02 02 00 03 03 03 03 45 07 00 A5 00 FF 00 0D 00 06 07 00 03 07 00 F2 07 01 0C 07 01 2E 02 02 00 02 02 02 FF 00 02 00 06 07 00 03 07 00 F2 07 01 0C 07 01 2E 02 02 00 03 02 02 01 FF 00 1D 00 06 07 00 03 07 00 F2 07 01 0C 07 01 2E 02 02 00 02 02 02 FF 00 0D 00 06 07 00 03 07 00 F2 07 01 0C 07 01 2E 02 02 00 03 02 02 02 FF 00 02 00 06 07 00 03 07 00 F2 07 01 0C 07 01 2E 02 02 00 04 02 02 02 01 FF 00 1E 00 06 07 00 03 07 00 F2 07 01 0C 07 01 2E 02 02 00 03 02 02 02 FF 00 02 00 00 00 01 07 00 A5 FF 00 00 00 06 07 00 03 07 00 F2 07 01 0C 07 01 2E 02 02 00 03 02 02 02 45 07 00 A5 FF 00 00 00 06 07 00 03 07 00 F2 07 01 0C 07 01 2E 02 02 00 04 02 02 02 02 FF 00 0E 00 06 07 00 03 07 00 F2 07 01 0C 07 01 2E 02 02 00 05 02 02 02 02 01 FF 00 02 00 06 07 00 03 07 00 F2 07 01 0C 07 01 2E 02 02 00 06 02 02 02 02 01 01 FF 00 1E 00 06 07 00 03 07 00 F2 07 01 0C 07 01 2E 02 02 00 05 02 02 02 02 01 42 07 00 F0 FF 00 00 00 06 07 00 03 07 00 F2 07 01 0C 07 01 2E 02 02 00 05 02 02 02 02 01 45 07 00 A5 00 42 07 00 A5 00 45 07 00 A5 40 07 01 D2 FF 00 06 00 07 07 00 03 07 00 F2 07 01 0C 07 01 2E 02 02 07 01 D2 00 01 07 00 A5 40 07 01 D2 45 07 00 A5 40 07 02 10 FF 00 07 00 08 07 00 03 07 00 F2 07 01 0C 07 01 2E 02 02 07 01 D2 07 02 10 00 01 07 00 A5 40 01 45 07 00 A5 00 42 07 00 A5 00 45 07 00 A5 00 FF 00 02 00 00 00 01 07 00 A5 FF 00 00 00 08 07 00 03 07 00 F2 07 01 0C 07 01 2E 02 02 07 01 D2 07 02 10 00 00 45 07 00 A5 00 0B 42 01 1D FF 00 11 00 08 07 00 03 07 00 F2 07 01 0C 07 01 2E 02 02 07 01 D2 07 02 10 00 02 07 01 E8 07 01 EE FF 00 02 00 08 07 00 03 07 00 F2 07 01 0C 07 01 2E 02 02 07 01 D2 07 02 10 00 03 07 01 E8 07 01 EE 01 FF 00 1E 00 08 07 00 03 07 00 F2 07 01 0C 07 01 2E 02 02 07 01 D2 07 02 10 00 02 07 01 E8 07 01 EE FF 00 11 00 08 07 00 03 07 00 F2 07 01 0C 07 01 2E 02 02 07 01 D2 07 02 10 00 04 07 01 E8 07 01 EE 07 01 E8 07 01 EE FF 00 02 00 08 07 00 03 07 00 F2 07 01 0C 07 01 2E 02 02 07 01 D2 07 02 10 00 05 07 01 E8 07 01 EE 07 01 E8 07 01 EE 01 FF 00 1E 00 08 07 00 03 07 00 F2 07 01 0C 07 01 2E 02 02 07 01 D2 07 02 10 00 04 07 01 E8 07 01 EE 07 01 E8 07 01 EE 42 07 00 E4 FF 00 00 00 08 07 00 03 07 00 F2 07 01 0C 07 01 2E 02 02 07 01 D2 07 02 10 00 04 07 01 E8 07 01 EE 07 01 E8 07 01 EE 45 07 00 A5 00 FF 00 06 00 00 00 01 07 00 A5 FF 00 00 00 08 07 00 03 07 00 F2 07 01 0C 07 01 2E 02 02 07 01 D2 07 02 10 00 04 02 02 02 02 45 07 00 A5 00 FF 00 0F 00 08 07 00 03 07 00 F2 07 01 0C 07 01 2E 02 02 07 01 D2 07 02 10 00 02 07 02 10 01 FF 00 02 00 08 07 00 03 07 00 F2 07 01 0C 07 01 2E 02 02 07 01 D2 07 02 10 00 03 07 02 10 01 01 FF 00 1E 00 08 07 00 03 07 00 F2 07 01 0C 07 01 2E 02 02 07 01 D2 07 02 10 00 02 07 02 10 01 45 07 00 A5 FF 00 00 00 08 07 00 03 07 00 F2 07 01 0C 07 01 2E 02 02 07 01 D2 07 02 10 00 03 07 02 10 01 07 02 9E 45 07 00 A5 00 4F 07 00 A5 00 45 07 00 A5 40 02 FC 00 0E 01 42 01 1F 4F 07 00 25 FF 00 02 00 09 07 00 03 07 00 F2 07 01 0C 07 01 2E 02 02 07 01 D2 07 02 10 01 00 02 07 00 25 01 5C 07 00 25 FF 00 02 00 00 00 01 07 00 A5 FF 00 00 00 09 07 00 03 07 00 F2 07 01 0C 07 01 2E 02 02 07 01 D2 07 02 10 01 00 01 07 00 25 45 07 00 A5 40 07 01 69 45 07 00 A5 40 07 00 2B 45 07 00 A5 40 02 FF 00 08 00 0A 07 00 03 07 00 F2 07 01 0C 07 01 2E 02 02 07 01 D2 07 02 10 01 02 00 01 07 00 A5 40 07 00 25 45 07 00 A5 40 07 01 69 45 07 00 F0 40 07 00 2B 45 07 00 A5 40 02 4B 02 FF 00 02 00 0A 07 00 03 07 00 F2 07 01 0C 07 01 2E 02 02 07 01 D2 07 02 10 01 02 00 02 02 01 5C 02 FF 00 11 00 0B 07 00 03 07 00 F2 07 01 0C 07 01 2E 02 02 07 01 D2 07 02 10 01 02 02 00 01 07 00 25 FF 00 02 00 0B 07 00 03 07 00 F2 07 01 0C 07 01 2E 02 02 07 01 D2 07 02 10 01 02 02 00 02 07 00 25 01 5E 07 00 25 FF 00 02 00 00 00 01 07 00 A5 FF 00 00 00 0B 07 00 03 07 00 F2 07 01 0C 07 01 2E 02 02 07 01 D2 07 02 10 01 02 02 00 01 07 00 25 45 07 00 A5 40 07 01 69 45 07 00 EC 40 07 00 2B 45 07 00 A5 40 02 4B 02 FF 00 02 00 0B 07 00 03 07 00 F2 07 01 0C 07 01 2E 02 02 07 01 D2 07 02 10 01 02 02 00 02 02 01 5F 02 FF 00 08 00 0C 07 00 03 07 00 F2 07 01 0C 07 01 2E 02 02 07 01 D2 07 02 10 01 02 02 02 00 01 07 00 EC 40 07 00 25 45 07 00 A5 40 07 01 69 45 07 00 EC 40 07 00 2B 45 07 00 A5 40 02 FF 00 0E 00 0D 07 00 03 07 00 F2 07 01 0C 07 01 2E 02 02 07 01 D2 07 02 10 01 02 02 02 02 00 01 01 FF 00 02 00 0D 07 00 03 07 00 F2 07 01 0C 07 01 2E 02 02 07 01 D2 07 02 10 01 02 02 02 02 00 02 01 01 5E 01 FF 00 07 00 0F 07 00 03 07 00 F2 07 01 0C 07 01 2E 02 02 07 01 D2 07 02 10 01 02 02 02 02 01 01 00 01 07 00 A5 00 45 07 00 A5 40 02 FF 00 12 00 10 07 00 03 07 00 F2 07 01 0C 07 01 2E 02 02 07 01 D2 07 02 10 01 02 02 02 02 01 01 01 00 01 02 FF 00 02 00 10 07 00 03 07 00 F2 07 01 0C 07 01 2E 02 02 07 01 D2 07 02 10 01 02 02 02 02 01 01 01 00 02 02 01 5D 02 FF 00 18 00 12 07 00 03 07 00 F2 07 01 0C 07 01 2E 02 02 07 01 D2 07 02 10 01 02 02 02 02 01 01 01 02 01 00 01 01 FF 00 02 00 12 07 00 03 07 00 F2 07 01 0C 07 01 2E 02 02 07 01 D2 07 02 10 01 02 02 02 02 01 01 01 02 01 00 02 01 01 5F 01 FC 00 01 01 06 05 42 01 19 51 02 FF 00 02 00 13 07 00 03 07 00 F2 07 01 0C 07 01 2E 02 02 07 01 D2 07 02 10 01 02 02 02 02 01 01 01 02 01 01 00 02 02 01 5E 02 FF 00 0E 00 14 07 00 03 07 00 F2 07 01 0C 07 01 2E 02 02 07 01 D2 07 02 10 01 02 02 02 02 01 01 01 02 01 01 02 00 03 07 02 A0 07 02 A0 01 FF 00 05 00 14 07 00 03 07 00 F2 07 01 0C 07 01 2E 02 02 07 01 D2 07 02 10 01 02 02 02 02 01 01 01 02 01 01 02 00 03 07 02 A0 07 02 A0 01 FF 00 02 00 14 07 00 03 07 00 F2 07 01 0C 07 01 2E 02 02 07 01 D2 07 02 10 01 02 02 02 02 01 01 01 02 01 01 02 00 04 07 02 A0 07 02 A0 01 01 FF 00 1B 00 14 07 00 03 07 00 F2 07 01 0C 07 01 2E 02 02 07 01 D2 07 02 10 01 02 02 02 02 01 01 01 02 01 01 02 00 03 07 02 A0 07 02 A0 01 FF 00 04 00 14 07 00 03 07 00 F2 07 01 0C 07 01 2E 02 02 07 01 D2 07 02 10 01 02 02 02 02 01 01 01 02 01 01 02 00 03 07 02 A0 07 02 A0 01 FF 00 0B 00 14 07 00 03 07 00 F2 07 01 0C 07 01 2E 02 02 07 01 D2 07 02 10 01 02 02 02 02 01 01 01 02 01 01 02 00 03 07 02 A0 07 02 A0 01 FF 00 02 00 14 07 00 03 07 00 F2 07 01 0C 07 01 2E 02 02 07 01 D2 07 02 10 01 02 02 02 02 01 01 01 02 01 01 02 00 04 07 02 A0 07 02 A0 01 01 FF 00 1F 00 14 07 00 03 07 00 F2 07 01 0C 07 01 2E 02 02 07 01 D2 07 02 10 01 02 02 02 02 01 01 01 02 01 01 02 00 03 07 02 A0 07 02 A0 01 FF 00 01 00 14 07 00 03 07 00 F2 07 01 0C 07 01 2E 02 02 07 01 D2 07 02 10 01 02 02 02 02 01 01 01 02 01 01 02 00 04 07 02 A0 07 02 A0 01 02 FF 00 0D 00 14 07 00 03 07 00 F2 07 01 0C 07 01 2E 02 02 07 01 D2 07 02 10 01 02 02 02 02 01 01 01 02 01 01 02 00 03 07 02 A0 07 02 A0 01 FF 00 01 00 14 07 00 03 07 00 F2 07 01 0C 07 01 2E 02 02 07 01 D2 07 02 10 01 02 02 02 02 01 01 01 02 01 01 02 00 04 07 02 A0 07 02 A0 01 02 FF 00 0D 00 14 07 00 03 07 00 F2 07 01 0C 07 01 2E 02 02 07 01 D2 07 02 10 01 02 02 02 02 01 01 01 02 01 01 02 00 03 07 02 A0 07 02 A0 01 FF 00 0B 00 14 07 00 03 07 00 F2 07 01 0C 07 01 2E 02 02 07 01 D2 07 02 10 01 02 02 02 02 01 01 01 02 01 01 02 00 03 07 02 A0 07 02 A0 01 FF 00 02 00 14 07 00 03 07 00 F2 07 01 0C 07 01 2E 02 02 07 01 D2 07 02 10 01 02 02 02 02 01 01 01 02 01 01 02 00 04 07 02 A0 07 02 A0 01 01 FF 00 1C 00 14 07 00 03 07 00 F2 07 01 0C 07 01 2E 02 02 07 01 D2 07 02 10 01 02 02 02 02 01 01 01 02 01 01 02 00 03 07 02 A0 07 02 A0 01 FF 00 01 00 14 07 00 03 07 00 F2 07 01 0C 07 01 2E 02 02 07 01 D2 07 02 10 01 02 02 02 02 01 01 01 02 01 01 02 00 04 07 02 A0 07 02 A0 01 02 FF 00 08 00 14 07 00 03 07 00 F2 07 01 0C 07 01 2E 02 02 07 01 D2 07 02 10 01 02 02 02 02 01 01 01 02 01 01 02 00 03 07 02 A0 07 02 A0 01 FF 00 05 00 14 07 00 03 07 00 F2 07 01 0C 07 01 2E 02 02 07 01 D2 07 02 10 01 02 02 02 02 01 01 01 02 01 01 02 00 03 07 02 A0 07 02 A0 01 FF 00 02 00 14 07 00 03 07 00 F2 07 01 0C 07 01 2E 02 02 07 01 D2 07 02 10 01 02 02 02 02 01 01 01 02 01 01 02 00 04 07 02 A0 07 02 A0 01 01 FF 00 1B 00 14 07 00 03 07 00 F2 07 01 0C 07 01 2E 02 02 07 01 D2 07 02 10 01 02 02 02 02 01 01 01 02 01 01 02 00 03 07 02 A0 07 02 A0 01 FF 00 04 00 14 07 00 03 07 00 F2 07 01 0C 07 01 2E 02 02 07 01 D2 07 02 10 01 02 02 02 02 01 01 01 02 01 01 02 00 03 07 02 A0 07 02 A0 01 FF 00 01 00 14 07 00 03 07 00 F2 07 01 0C 07 01 2E 02 02 07 01 D2 07 02 10 01 02 02 02 02 01 01 01 02 01 01 02 00 04 07 02 A0 07 02 A0 01 02 4C 07 02 A0 FF 00 02 00 14 07 00 03 07 00 F2 07 01 0C 07 01 2E 02 02 07 01 D2 07 02 10 01 02 02 02 02 01 01 01 02 01 01 02 00 02 07 02 A0 01 5C 07 02 A0 FF 00 10 00 15 07 00 03 07 00 F2 07 01 0C 07 01 2E 02 02 07 01 D2 07 02 10 01 02 02 02 02 01 01 01 02 01 01 02 07 02 A0 00 03 07 02 A0 07 02 A0 01 FF 00 01 00 15 07 00 03 07 00 F2 07 01 0C 07 01 2E 02 02 07 01 D2 07 02 10 01 02 02 02 02 01 01 01 02 01 01 02 07 02 A0 00 04 07 02 A0 07 02 A0 01 02 FF 00 0D 00 15 07 00 03 07 00 F2 07 01 0C 07 01 2E 02 02 07 01 D2 07 02 10 01 02 02 02 02 01 01 01 02 01 01 02 07 02 A0 00 03 07 02 A0 07 02 A0 01 FF 00 0B 00 15 07 00 03 07 00 F2 07 01 0C 07 01 2E 02 02 07 01 D2 07 02 10 01 02 02 02 02 01 01 01 02 01 01 02 07 02 A0 00 03 07 02 A0 07 02 A0 01 FF 00 02 00 15 07 00 03 07 00 F2 07 01 0C 07 01 2E 02 02 07 01 D2 07 02 10 01 02 02 02 02 01 01 01 02 01 01 02 07 02 A0 00 04 07 02 A0 07 02 A0 01 01 FF 00 1F 00 15 07 00 03 07 00 F2 07 01 0C 07 01 2E 02 02 07 01 D2 07 02 10 01 02 02 02 02 01 01 01 02 01 01 02 07 02 A0 00 03 07 02 A0 07 02 A0 01 FF 00 01 00 15 07 00 03 07 00 F2 07 01 0C 07 01 2E 02 02 07 01 D2 07 02 10 01 02 02 02 02 01 01 01 02 01 01 02 07 02 A0 00 04 07 02 A0 07 02 A0 01 02 FF 00 14 00 15 07 00 03 07 00 F2 07 01 0C 07 01 2E 02 02 07 01 D2 07 02 10 01 02 02 02 02 01 01 01 02 01 01 02 07 02 A0 00 03 07 02 A0 07 02 A0 01 FF 00 02 00 15 07 00 03 07 00 F2 07 01 0C 07 01 2E 02 02 07 01 D2 07 02 10 01 02 02 02 02 01 01 01 02 01 01 02 07 02 A0 00 04 07 02 A0 07 02 A0 01 01 FF 00 1D 00 15 07 00 03 07 00 F2 07 01 0C 07 01 2E 02 02 07 01 D2 07 02 10 01 02 02 02 02 01 01 01 02 01 01 02 07 02 A0 00 03 07 02 A0 07 02 A0 01 FF 00 04 00 15 07 00 03 07 00 F2 07 01 0C 07 01 2E 02 02 07 01 D2 07 02 10 01 02 02 02 02 01 01 01 02 01 01 02 07 02 A0 00 03 07 02 A0 07 02 A0 01 FF 00 01 00 15 07 00 03 07 00 F2 07 01 0C 07 01 2E 02 02 07 01 D2 07 02 10 01 02 02 02 02 01 01 01 02 01 01 02 07 02 A0 00 04 07 02 A0 07 02 A0 01 02 FF 00 0D 00 15 07 00 03 07 00 F2 07 01 0C 07 01 2E 02 02 07 01 D2 07 02 10 01 02 02 02 02 01 01 01 02 01 01 02 07 02 A0 00 03 07 02 A0 07 02 A0 01 FF 00 01 00 15 07 00 03 07 00 F2 07 01 0C 07 01 2E 02 02 07 01 D2 07 02 10 01 02 02 02 02 01 01 01 02 01 01 02 07 02 A0 00 04 07 02 A0 07 02 A0 01 02 FC 00 0E 07 02 A0 42 01 1E 4D 07 02 10 FF 00 02 00 16 07 00 03 07 00 F2 07 01 0C 07 01 2E 02 02 07 01 D2 07 02 10 01 02 02 02 02 01 01 01 02 01 01 02 07 02 A0 07 02 A0 00 02 07 02 10 01 5E 07 02 10 FF 00 0C 00 00 00 01 07 00 A5 FF 00 00 00 16 07 00 03 07 00 F2 07 01 0C 07 01 2E 02 02 07 01 D2 07 02 10 01 02 02 02 02 01 01 01 02 01 01 02 07 02 A0 07 02 A0 00 04 07 02 10 03 03 03 45 07 00 A5 40 07 02 10 4B 07 02 10 FF 00 02 00 16 07 00 03 07 00 F2 07 01 0C 07 01 2E 02 02 07 01 D2 07 02 10 01 02 02 02 02 01 01 01 02 01 01 02 07 02 A0 07 02 A0 00 02 07 02 10 01 5F 07 02 10 FF 00 0F 00 16 07 00 03 07 00 F2 07 01 0C 07 01 2E 02 02 07 01 D2 07 02 10 01 02 02 02 02 01 01 01 02 01 01 02 07 02 A0 07 02 A0 00 02 07 02 10 02 FF 00 02 00 16 07 00 03 07 00 F2 07 01 0C 07 01 2E 02 02 07 01 D2 07 02 10 01 02 02 02 02 01 01 01 02 01 01 02 07 02 A0 07 02 A0 00 03 07 02 10 02 01 FF 00 1C 00 16 07 00 03 07 00 F2 07 01 0C 07 01 2E 02 02 07 01 D2 07 02 10 01 02 02 02 02 01 01 01 02 01 01 02 07 02 A0 07 02 A0 00 02 07 02 10 02 4E 07 00 EC FF 00 00 00 16 07 00 03 07 00 F2 07 01 0C 07 01 2E 02 02 07 01 D2 07 02 10 01 02 02 02 02 01 01 01 02 01 01 02 07 02 A0 07 02 A0 00 05 07 02 10 02 02 02 02 45 07 00 A5 40 07 02 10 4B 07 02 10 FF 00 02 00 16 07 00 03 07 00 F2 07 01 0C 07 01 2E 02 02 07 01 D2 07 02 10 01 02 02 02 02 01 01 01 02 01 01 02 07 02 A0 07 02 A0 00 02 07 02 10 01 5D 07 02 10 42 07 00 A5 40 07 02 10 45 07 00 A5 00 4D 07 02 10 FF 00 02 00 16 07 00 03 07 00 F2 07 01 0C 07 01 2E 02 02 07 01 D2 07 02 10 01 02 02 02 02 01 01 01 02 01 01 02 07 02 A0 07 02 A0 00 02 07 02 10 01 5F 07 02 10 FF 00 10 00 16 07 00 03 07 00 F2 07 01 0C 07 01 2E 02 02 07 01 D2 07 02 10 01 02 02 02 02 01 01 01 02 01 01 02 07 02 A0 07 02 A0 00 02 07 02 10 03 FF 00 02 00 16 07 00 03 07 00 F2 07 01 0C 07 01 2E 02 02 07 01 D2 07 02 10 01 02 02 02 02 01 01 01 02 01 01 02 07 02 A0 07 02 A0 00 03 07 02 10 03 01 FF 00 1F 00 16 07 00 03 07 00 F2 07 01 0C 07 01 2E 02 02 07 01 D2 07 02 10 01 02 02 02 02 01 01 01 02 01 01 02 07 02 A0 07 02 A0 00 02 07 02 10 03 49 07 00 E0 FF 00 00 00 16 07 00 03 07 00 F2 07 01 0C 07 01 2E 02 02 07 01 D2 07 02 10 01 02 02 02 02 01 01 01 02 01 01 02 07 02 A0 07 02 A0 00 04 07 02 10 03 03 03 45 07 00 A5 40 07 02 10 FF 00 1B 00 16 07 00 03 07 00 F2 07 01 0C 07 01 2E 02 02 07 01 D2 07 02 10 01 02 02 02 02 01 01 01 02 01 01 02 07 02 A0 07 02 A0 00 05 07 02 10 02 02 02 02 FF 00 02 00 16 07 00 03 07 00 F2 07 01 0C 07 01 2E 02 02 07 01 D2 07 02 10 01 02 02 02 02 01 01 01 02 01 01 02 07 02 A0 07 02 A0 00 06 07 02 10 02 02 02 02 01 FF 00 1E 00 16 07 00 03 07 00 F2 07 01 0C 07 01 2E 02 02 07 01 D2 07 02 10 01 02 02 02 02 01 01 01 02 01 01 02 07 02 A0 07 02 A0 00 05 07 02 10 02 02 02 02 42 07 00 9B FF 00 00 00 16 07 00 03 07 00 F2 07 01 0C 07 01 2E 02 02 07 01 D2 07 02 10 01 02 02 02 02 01 01 01 02 01 01 02 07 02 A0 07 02 A0 00 05 07 02 10 02 02 02 02 45 07 00 A5 40 07 02 10 42 07 00 A5 40 07 02 10 45 07 00 A5 00 0B 42 01 1E 4D 07 00 A5 FF 00 00 00 16 07 00 03 07 00 F2 07 01 0C 07 01 2E 02 02 07 01 D2 07 02 10 01 02 02 02 02 01 01 01 02 01 01 02 07 02 A0 07 02 A0 00 04 07 02 10 03 03 03 45 07 00 A5 40 07 02 10 FF 00 13 00 16 07 00 03 07 00 F2 07 01 0C 07 01 2E 02 02 07 01 D2 07 02 10 01 02 02 02 02 01 01 01 02 01 01 02 07 02 A0 07 02 A0 00 03 07 02 10 02 02 FF 00 02 00 16 07 00 03 07 00 F2 07 01 0C 07 01 2E 02 02 07 01 D2 07 02 10 01 02 02 02 02 01 01 01 02 01 01 02 07 02 A0 07 02 A0 00 04 07 02 10 02 02 01 FF 00 1E 00 16 07 00 03 07 00 F2 07 01 0C 07 01 2E 02 02 07 01 D2 07 02 10 01 02 02 02 02 01 01 01 02 01 01 02 07 02 A0 07 02 A0 00 03 07 02 10 02 02 FF 00 13 00 16 07 00 03 07 00 F2 07 01 0C 07 01 2E 02 02 07 01 D2 07 02 10 01 02 02 02 02 01 01 01 02 01 01 02 07 02 A0 07 02 A0 00 05 07 02 10 02 02 02 02 FF 00 02 00 16 07 00 03 07 00 F2 07 01 0C 07 01 2E 02 02 07 01 D2 07 02 10 01 02 02 02 02 01 01 01 02 01 01 02 07 02 A0 07 02 A0 00 06 07 02 10 02 02 02 02 01 FF 00 1C 00 16 07 00 03 07 00 F2 07 01 0C 07 01 2E 02 02 07 01 D2 07 02 10 01 02 02 02 02 01 01 01 02 01 01 02 07 02 A0 07 02 A0 00 05 07 02 10 02 02 02 02 42 07 00 EC FF 00 00 00 16 07 00 03 07 00 F2 07 01 0C 07 01 2E 02 02 07 01 D2 07 02 10 01 02 02 02 02 01 01 01 02 01 01 02 07 02 A0 07 02 A0 00 05 07 02 10 02 02 02 02 45 07 00 A5 40 07 02 10 42 07 00 A5 40 07 02 10 45 07 00 A5 00 4D 07 02 10 FF 00 02 00 16 07 00 03 07 00 F2 07 01 0C 07 01 2E 02 02 07 01 D2 07 02 10 01 02 02 02 02 01 01 01 02 01 01 02 07 02 A0 07 02 A0 00 02 07 02 10 01 5C 07 02 10 FF 00 0E 00 16 07 00 03 07 00 F2 07 01 0C 07 01 2E 02 02 07 01 D2 07 02 10 01 02 02 02 02 01 01 01 02 01 01 02 07 02 A0 07 02 A0 00 02 07 02 10 03 FF 00 02 00 16 07 00 03 07 00 F2 07 01 0C 07 01 2E 02 02 07 01 D2 07 02 10 01 02 02 02 02 01 01 01 02 01 01 02 07 02 A0 07 02 A0 00 03 07 02 10 03 01 FF 00 1D 00 16 07 00 03 07 00 F2 07 01 0C 07 01 2E 02 02 07 01 D2 07 02 10 01 02 02 02 02 01 01 01 02 01 01 02 07 02 A0 07 02 A0 00 02 07 02 10 03 46 07 00 A5 FF 00 00 00 16 07 00 03 07 00 F2 07 01 0C 07 01 2E 02 02 07 01 D2 07 02 10 01 02 02 02 02 01 01 01 02 01 01 02 07 02 A0 07 02 A0 00 04 07 02 10 03 03 03 45 07 00 A5 40 07 02 10 FF 00 0F 00 16 07 00 03 07 00 F2 07 01 0C 07 01 2E 02 02 07 01 D2 07 02 10 01 02 02 02 02 01 01 01 02 01 01 02 07 02 A0 07 02 A0 00 02 07 02 10 02 FF 00 02 00 16 07 00 03 07 00 F2 07 01 0C 07 01 2E 02 02 07 01 D2 07 02 10 01 02 02 02 02 01 01 01 02 01 01 02 07 02 A0 07 02 A0 00 03 07 02 10 02 01 FF 00 1D 00 16 07 00 03 07 00 F2 07 01 0C 07 01 2E 02 02 07 01 D2 07 02 10 01 02 02 02 02 01 01 01 02 01 01 02 07 02 A0 07 02 A0 00 02 07 02 10 02 FF 00 0F 00 16 07 00 03 07 00 F2 07 01 0C 07 01 2E 02 02 07 01 D2 07 02 10 01 02 02 02 02 01 01 01 02 01 01 02 07 02 A0 07 02 A0 00 03 07 02 10 02 02 FF 00 02 00 16 07 00 03 07 00 F2 07 01 0C 07 01 2E 02 02 07 01 D2 07 02 10 01 02 02 02 02 01 01 01 02 01 01 02 07 02 A0 07 02 A0 00 04 07 02 10 02 02 01 FF 00 1C 00 16 07 00 03 07 00 F2 07 01 0C 07 01 2E 02 02 07 01 D2 07 02 10 01 02 02 02 02 01 01 01 02 01 01 02 07 02 A0 07 02 A0 00 03 07 02 10 02 02 4A 07 00 E2 FF 00 00 00 16 07 00 03 07 00 F2 07 01 0C 07 01 2E 02 02 07 01 D2 07 02 10 01 02 02 02 02 01 01 01 02 01 01 02 07 02 A0 07 02 A0 00 05 07 02 10 02 02 02 02 45 07 00 A5 40 07 02 10 42 07 00 A5 40 07 02 10 45 07 00 A5 00 F8 00 09 4D 07 01 D2 FF 00 02 00 13 07 00 03 07 00 F2 07 01 0C 07 01 2E 02 02 07 01 D2 07 02 10 01 02 02 02 02 01 01 01 02 01 01 00 02 07 01 D2 01 5E 07 01 D2 42 07 00 9B 40 07 01 D2 45 07 00 A5 00 42 07 00 A5 00 45 07 00 A5 00 0B 42 01 1E 42 07 00 A5 00 45 07 00 A5 00 45 07 00 A5 40 01 45 07 00 A5 00 42 07 00 A1 00 45 07 00 A5 FF 00 00 00 05 07 00 03 07 00 F2 07 01 0C 07 01 2E 02 00 00 FF 00 02 00 00 00 01 07 00 A5 FF 00 00 00 05 07 00 03 07 00 F2 07 01 0C 07 01 2E 02 00 00 45 07 00 A5 F9 00 00 FF 00 00 00 04 07 00 03 07 00 F2 07 01 0C 07 01 2E 00 02 02 07 01 39 FF 00 01 00 16 07 00 03 07 00 F2 07 01 0C 07 01 2E 02 02 07 01 D2 07 02 10 01 02 02 02 02 01 01 01 02 01 01 02 07 02 A0 07 02 A0 00 01 07 02 10 FF 00 01 00 04 07 00 03 07 00 F2 07 01 0C 07 01 2E 00 03 02 02 07 01 39 FF 00 01 00 05 07 00 03 07 00 F2 07 01 0C 07 01 2E 02 00 02 07 01 63 07 00 95 FE 00 01 02 07 01 D2 07 02 10 FF 00 01 00 07 07 00 03 07 00 F2 07 01 0C 07 01 2E 02 07 00 95 02 00 00 FF 00 01 00 08 07 00 03 07 00 F2 07 01 0C 07 01 2E 02 02 07 01 D2 07 02 10 00 02 07 01 E8 07 01 EE FF 00 01 00 16 07 00 03 07 00 F2 07 01 0C 07 01 2E 02 02 07 01 D2 07 02 10 01 02 02 02 02 01 01 01 02 01 01 02 07 02 A0 07 02 A0 00 02 07 02 10 02 FF 00 01 00 13 07 00 03 07 00 F2 07 01 0C 07 01 2E 02 02 07 01 D2 07 02 10 01 02 02 02 02 01 01 01 02 01 01 00 01 02 FF 00 01 00 08 07 00 03 07 00 F2 07 01 0C 07 01 2E 02 02 07 01 D2 07 02 10 00 04 07 01 E8 07 01 EE 07 01 E8 07 01 EE FF 00 01 00 13 07 00 03 07 00 F2 07 01 0C 07 01 2E 02 02 07 01 D2 07 02 10 01 02 02 02 02 01 01 01 02 01 01 00 01 07 01 D2 FF 00 01 00 03 07 00 03 07 00 F2 07 01 0C 00 02 07 01 01 07 01 0C FF 00 01 00 0D 07 00 03 07 00 F2 07 01 0C 07 01 2E 02 02 07 01 D2 07 02 10 01 02 02 02 02 00 01 01 FF 00 01 00 13 07 00 03 07 00 F2 07 01 0C 07 01 2E 02 02 07 01 D2 07 02 10 01 02 02 02 02 01 01 01 02 01 01 00 00 FF 00 01 00 0A 07 00 03 07 00 F2 07 01 0C 07 01 2E 02 02 07 01 D2 07 02 10 01 02 00 01 02 FF 00 01 00 03 07 00 03 07 00 F2 07 01 0C 00 00 FF 00 01 00 06 07 00 03 07 00 F2 07 01 0C 07 01 2E 02 02 00 03 02 02 02 FF 00 01 00 0B 07 00 03 07 00 F2 07 01 0C 07 01 2E 02 02 07 01 D2 07 02 10 01 02 02 00 01 07 00 25 FF 00 01 00 03 07 00 03 07 00 F2 07 01 0C 00 02 07 01 01 07 01 39 FF 00 01 00 16 07 00 03 07 00 F2 07 01 0C 07 01 2E 02 02 07 01 D2 07 02 10 01 02 02 02 02 01 01 01 02 01 01 02 07 02 A0 07 02 A0 00 00 FF 00 01 00 16 07 00 03 07 00 F2 07 01 0C 07 01 2E 02 02 07 01 D2 07 02 10 01 02 02 02 02 01 01 01 02 01 01 02 07 02 A0 07 02 A0 00 02 07 02 10 02 FF 00 01 00 16 07 00 03 07 00 F2 07 01 0C 07 01 2E 02 02 07 01 D2 07 02 10 01 02 02 02 02 01 01 01 02 01 01 02 07 02 A0 07 02 A0 00 03 07 02 10 02 02 FF 00 01 00 03 07 00 03 07 00 F2 07 01 0C 00 01 07 00 03 FF 00 01 00 16 07 00 03 07 00 F2 07 01 0C 07 01 2E 02 02 07 01 D2 07 02 10 01 02 02 02 02 01 01 01 02 01 01 02 07 02 A0 07 02 A0 00 02 07 02 10 03 41 07 02 10 FF 00 01 00 06 07 00 03 07 00 F2 07 01 0C 07 01 2E 02 07 01 A4 00 00 FF 00 01 00 06 07 00 03 07 00 F2 07 01 0C 07 01 2E 02 02 00 02 02 02 FF 00 01 00 0B 07 00 03 07 00 F2 07 01 0C 07 01 2E 02 02 07 01 D2 07 02 10 01 02 02 00 01 02 F9 00 01 FF 00 01 00 16 07 00 03 07 00 F2 07 01 0C 07 01 2E 02 02 07 01 D2 07 02 10 01 02 02 02 02 01 01 01 02 01 01 02 07 02 A0 07 02 A0 00 02 07 02 10 03 01 FF 00 01 00 16 07 00 03 07 00 F2 07 01 0C 07 01 2E 02 02 07 01 D2 07 02 10 01 02 02 02 02 01 01 01 02 01 01 02 07 02 A0 07 02 A0 00 05 07 02 10 02 02 02 02 41 07 02 10 FF 00 01 00 06 07 00 03 07 00 F2 07 01 0C 07 01 2E 02 07 00 95 00 00 FF 00 01 00 12 07 00 03 07 00 F2 07 01 0C 07 01 2E 02 02 07 01 D2 07 02 10 01 02 02 02 02 01 01 01 02 01 00 01 01 FF 00 01 00 16 07 00 03 07 00 F2 07 01 0C 07 01 2E 02 02 07 01 D2 07 02 10 01 02 02 02 02 01 01 01 02 01 01 02 07 02 A0 07 02 A0 00 05 07 02 10 02 02 02 02 FF 00 01 00 15 07 00 03 07 00 F2 07 01 0C 07 01 2E 02 02 07 01 D2 07 02 10 01 02 02 02 02 01 01 01 02 01 01 02 07 02 A0 00 03 07 02 A0 07 02 A0 01 FF 00 01 00 03 07 00 03 07 00 F2 07 01 0C 00 03 07 01 01 07 01 39 07 00 2B FF 00 01 00 09 07 00 03 07 00 F2 07 01 0C 07 01 2E 02 02 07 01 D2 07 02 10 01 00 01 07 00 25 FF 00 01 00 08 07 00 03 07 00 F2 07 01 0C 07 01 2E 02 02 07 01 D2 07 02 10 00 02 07 02 10 01 FF 00 01 00 14 07 00 03 07 00 F2 07 01 0C 07 01 2E 02 02 07 01 D2 07 02 10 01 02 02 02 02 01 01 01 02 01 01 02 00 03 07 02 A0 07 02 A0 01 FF 00 01 00 15 07 00 03 07 00 F2 07 01 0C 07 01 2E 02 02 07 01 D2 07 02 10 01 02 02 02 02 01 01 01 02 01 01 02 07 02 A0 00 03 07 02 A0 07 02 A0 01 FF 00 01 00 16 07 00 03 07 00 F2 07 01 0C 07 01 2E 02 02 07 01 D2 07 02 10 01 02 02 02 02 01 01 01 02 01 01 02 07 02 A0 07 02 A0 00 01 07 02 10 FF 00 01 00 16 07 00 03 07 00 F2 07 01 0C 07 01 2E 02 02 07 01 D2 07 02 10 01 02 02 02 02 01 01 01 02 01 01 02 07 02 A0 07 02 A0 00 03 07 02 10 02 02 FF 00 01 00 04 07 00 03 07 00 F2 07 01 0C 07 01 2E 00 05 02 02 02 07 01 2E 02 FF 00 01 00 10 07 00 03 07 00 F2 07 01 0C 07 01 2E 02 02 07 01 D2 07 02 10 01 02 02 02 02 01 01 01 00 01 02 FF 00 01 00 06 07 00 03 07 00 F2 07 01 0C 07 01 2E 02 02 00 05 02 02 02 02 01 FF 00 01 00 14 07 00 03 07 00 F2 07 01 0C 07 01 2E 02 02 07 01 D2 07 02 10 01 02 02 02 02 01 01 01 02 01 01 02 00 01 07 02 A0 FF 00 01 00 16 07 00 03 07 00 F2 07 01 0C 07 01 2E 02 02 07 01 D2 07 02 10 01 02 02 02 02 01 01 01 02 01 01 02 07 02 A0 07 02 A0 00 01 07 02 10 FF 00 01 00 14 07 00 03 07 00 F2 07 01 0C 07 01 2E 02 02 07 01 D2 07 02 10 01 02 02 02 02 01 01 01 02 01 01 02 00 03 07 02 A0 07 02 A0 01 FF 00 01 00 05 07 00 03 07 00 F2 07 01 0C 07 01 2E 02 00 01 07 00 95 FF 00 01 00 06 07 00 03 07 00 F2 07 01 0C 07 01 2E 02 02 00 01 03 FF 00 01 00 03 07 00 03 07 00 F2 07 01 0C 00 01 07 00 A5 43 05 44 07 00 A5 47 05 47 07 00 A5
        //    Exceptions:
        //  Try           Handler
        //  Start  End    Start  End    Type                                       
        //  -----  -----  -----  -----  -------------------------------------------
        //  8      20     4333   4341   Ljava/lang/ClassCastException;
        //  4333   4341   4333   4341   Any
        //  4349   4351   3      8      Any
        //  28     35     35     36     Any
        //  28     35     3      8      Any
        //  29     35     28     29     Ljava/lang/NumberFormatException;
        //  28     35     3      8      Any
        //  28     35     28     29     Any
        //  46     53     53     54     Any
        //  46     53     46     47     Any
        //  47     53     46     47     Any
        //  46     53     3      8      Ljava/lang/NegativeArraySizeException;
        //  46     53     3      8      Any
        //  65     72     72     73     Any
        //  66     72     3      8      Any
        //  65     72     65     66     Any
        //  66     72     65     66     Any
        //  66     72     3      8      Any
        //  127    134    134    135    Any
        //  128    134    127    128    Ljava/lang/ArrayIndexOutOfBoundsException;
        //  127    134    3      8      Ljava/lang/ClassCastException;
        //  128    134    134    135    Ljava/lang/AssertionError;
        //  128    134    3      8      Any
        //  187    194    194    195    Any
        //  187    194    187    188    Any
        //  187    194    187    188    Any
        //  188    194    187    188    Ljava/lang/UnsupportedOperationException;
        //  187    194    194    195    Ljava/lang/EnumConstantNotPresentException;
        //  248    254    254    255    Any
        //  248    254    3      8      Ljava/lang/NumberFormatException;
        //  248    254    3      8      Any
        //  248    254    254    255    Ljava/lang/IllegalStateException;
        //  248    254    3      8      Any
        //  261    267    267    268    Any
        //  261    267    3      8      Ljava/lang/AssertionError;
        //  261    267    3      8      Ljava/lang/StringIndexOutOfBoundsException;
        //  261    267    3      8      Any
        //  261    267    3      8      Ljava/lang/EnumConstantNotPresentException;
        //  275    281    281    282    Any
        //  275    281    281    282    Any
        //  275    281    3      8      Any
        //  275    281    3      8      Ljava/lang/UnsupportedOperationException;
        //  275    281    281    282    Ljava/lang/AssertionError;
        //  285    292    292    293    Any
        //  286    292    285    286    Ljava/lang/NullPointerException;
        //  285    292    292    293    Any
        //  285    292    292    293    Any
        //  286    292    292    293    Ljava/lang/IllegalArgumentException;
        //  300    307    307    308    Any
        //  300    307    300    301    Ljava/lang/ClassCastException;
        //  300    307    307    308    Ljava/util/NoSuchElementException;
        //  301    307    300    301    Any
        //  300    307    307    308    Ljava/lang/StringIndexOutOfBoundsException;
        //  399    406    406    407    Any
        //  400    406    3      8      Ljava/lang/UnsupportedOperationException;
        //  400    406    406    407    Ljava/lang/IndexOutOfBoundsException;
        //  400    406    399    400    Any
        //  400    406    406    407    Ljava/lang/IndexOutOfBoundsException;
        //  471    478    478    479    Any
        //  472    478    471    472    Any
        //  471    478    471    472    Ljava/lang/NullPointerException;
        //  471    478    3      8      Any
        //  472    478    478    479    Ljava/lang/ClassCastException;
        //  482    489    489    490    Any
        //  482    489    3      8      Ljava/lang/NullPointerException;
        //  482    489    489    490    Any
        //  483    489    482    483    Ljava/lang/ClassCastException;
        //  482    489    482    483    Ljava/lang/EnumConstantNotPresentException;
        //  498    505    505    506    Any
        //  499    505    498    499    Ljava/lang/IndexOutOfBoundsException;
        //  498    505    3      8      Any
        //  498    505    3      8      Ljava/lang/NegativeArraySizeException;
        //  498    505    3      8      Any
        //  555    562    562    563    Any
        //  556    562    555    556    Ljava/lang/AssertionError;
        //  556    562    3      8      Any
        //  556    562    555    556    Any
        //  556    562    562    563    Any
        //  571    578    578    579    Any
        //  571    578    571    572    Ljava/lang/NullPointerException;
        //  571    578    578    579    Ljava/lang/NegativeArraySizeException;
        //  571    578    571    572    Any
        //  571    578    3      8      Any
        //  627    634    634    635    Any
        //  627    634    634    635    Any
        //  627    634    627    628    Ljava/lang/IllegalStateException;
        //  628    634    634    635    Ljava/lang/RuntimeException;
        //  628    634    3      8      Any
        //  691    698    698    699    Any
        //  691    698    691    692    Any
        //  692    698    3      8      Ljava/lang/RuntimeException;
        //  692    698    3      8      Any
        //  691    698    691    692    Ljava/lang/IndexOutOfBoundsException;
        //  703    710    710    711    Any
        //  704    710    710    711    Any
        //  703    710    710    711    Any
        //  704    710    703    704    Ljava/util/NoSuchElementException;
        //  704    710    710    711    Any
        //  721    728    728    729    Any
        //  722    728    721    722    Any
        //  722    728    728    729    Ljava/lang/NumberFormatException;
        //  722    728    3      8      Ljava/lang/EnumConstantNotPresentException;
        //  721    728    721    722    Any
        //  736    743    743    744    Any
        //  737    743    736    737    Any
        //  737    743    736    737    Any
        //  736    743    3      8      Any
        //  736    743    736    737    Any
        //  750    757    757    758    Any
        //  751    757    750    751    Any
        //  750    757    750    751    Ljava/lang/NullPointerException;
        //  750    757    3      8      Any
        //  750    757    3      8      Any
        //  803    810    810    811    Any
        //  803    810    803    804    Any
        //  803    810    3      8      Ljava/lang/NumberFormatException;
        //  804    810    803    804    Ljava/lang/ArrayIndexOutOfBoundsException;
        //  804    810    803    804    Ljava/lang/IllegalArgumentException;
        //  817    824    824    825    Any
        //  817    824    824    825    Ljava/lang/IndexOutOfBoundsException;
        //  817    824    824    825    Any
        //  817    824    824    825    Ljava/lang/ArithmeticException;
        //  817    824    817    818    Ljava/lang/NegativeArraySizeException;
        //  836    843    843    844    Any
        //  837    843    836    837    Any
        //  837    843    836    837    Any
        //  837    843    843    844    Any
        //  836    843    843    844    Any
        //  848    855    855    856    Any
        //  848    855    855    856    Any
        //  849    855    855    856    Any
        //  848    855    848    849    Any
        //  848    855    855    856    Any
        //  859    866    866    867    Any
        //  859    866    866    867    Any
        //  860    866    3      8      Ljava/lang/AssertionError;
        //  860    866    3      8      Any
        //  860    866    859    860    Ljava/util/NoSuchElementException;
        //  919    926    926    927    Any
        //  920    926    926    927    Ljava/lang/IndexOutOfBoundsException;
        //  919    926    3      8      Ljava/lang/StringIndexOutOfBoundsException;
        //  920    926    919    920    Any
        //  920    926    3      8      Ljava/lang/UnsupportedOperationException;
        //  930    937    937    938    Any
        //  930    937    3      8      Any
        //  930    937    930    931    Any
        //  931    937    930    931    Any
        //  931    937    930    931    Ljava/lang/NumberFormatException;
        //  943    950    950    951    Any
        //  943    950    943    944    Any
        //  944    950    943    944    Any
        //  944    950    943    944    Ljava/lang/ArithmeticException;
        //  944    950    3      8      Any
        //  1001   1008   1008   1009   Any
        //  1002   1008   1008   1009   Any
        //  1001   1008   1001   1002   Ljava/lang/IndexOutOfBoundsException;
        //  1001   1008   3      8      Any
        //  1001   1008   1001   1002   Any
        //  1069   1076   1076   1077   Any
        //  1070   1076   1076   1077   Ljava/lang/UnsupportedOperationException;
        //  1070   1076   1069   1070   Any
        //  1069   1076   3      8      Any
        //  1069   1076   1076   1077   Any
        //  1085   1092   1092   1093   Any
        //  1085   1092   1092   1093   Ljava/util/NoSuchElementException;
        //  1086   1092   1085   1086   Any
        //  1085   1092   1092   1093   Any
        //  1085   1092   1092   1093   Any
        //  1096   1103   1103   1104   Any
        //  1097   1103   3      8      Ljava/util/NoSuchElementException;
        //  1096   1103   3      8      Ljava/lang/UnsupportedOperationException;
        //  1096   1103   1096   1097   Any
        //  1097   1103   1096   1097   Any
        //  1111   1118   1118   1119   Any
        //  1111   1118   1118   1119   Any
        //  1111   1118   1118   1119   Ljava/lang/IndexOutOfBoundsException;
        //  1111   1118   1111   1112   Ljava/lang/ClassCastException;
        //  1111   1118   3      8      Ljava/util/ConcurrentModificationException;
        //  1125   1132   1132   1133   Any
        //  1126   1132   1132   1133   Ljava/lang/NegativeArraySizeException;
        //  1126   1132   1132   1133   Any
        //  1126   1132   1125   1126   Any
        //  1125   1132   1125   1126   Any
        //  1148   1154   1154   1155   Any
        //  1148   1154   1154   1155   Any
        //  1148   1154   3      8      Ljava/lang/UnsupportedOperationException;
        //  1148   1154   1154   1155   Any
        //  1148   1154   3      8      Ljava/lang/StringIndexOutOfBoundsException;
        //  1158   1165   1165   1166   Any
        //  1158   1165   1158   1159   Ljava/util/NoSuchElementException;
        //  1158   1165   1158   1159   Any
        //  1158   1165   1158   1159   Ljava/lang/RuntimeException;
        //  1158   1165   1165   1166   Any
        //  1223   1230   1230   1231   Any
        //  1223   1230   1223   1224   Ljava/lang/ClassCastException;
        //  1223   1230   1230   1231   Any
        //  1224   1230   1223   1224   Ljava/lang/AssertionError;
        //  1224   1230   3      8      Ljava/lang/IllegalStateException;
        //  1236   1243   1243   1244   Any
        //  1237   1243   1236   1237   Ljava/lang/NegativeArraySizeException;
        //  1236   1243   3      8      Any
        //  1236   1243   1236   1237   Ljava/lang/StringIndexOutOfBoundsException;
        //  1236   1243   1243   1244   Any
        //  1247   1254   1254   1255   Any
        //  1248   1254   3      8      Any
        //  1248   1254   1254   1255   Ljava/lang/NegativeArraySizeException;
        //  1248   1254   3      8      Any
        //  1248   1254   1247   1248   Ljava/lang/EnumConstantNotPresentException;
        //  1269   1275   1275   1276   Any
        //  1269   1275   1275   1276   Any
        //  1269   1275   3      8      Any
        //  1269   1275   3      8      Ljava/lang/RuntimeException;
        //  1269   1275   3      8      Any
        //  1281   1288   1288   1289   Any
        //  1282   1288   1288   1289   Ljava/lang/ArrayIndexOutOfBoundsException;
        //  1282   1288   1281   1282   Any
        //  1282   1288   1281   1282   Any
        //  1281   1288   1288   1289   Ljava/lang/ArithmeticException;
        //  1294   1301   1301   1302   Any
        //  1295   1301   3      8      Any
        //  1295   1301   3      8      Ljava/lang/EnumConstantNotPresentException;
        //  1294   1301   1294   1295   Ljava/lang/NullPointerException;
        //  1294   1301   1294   1295   Ljava/lang/RuntimeException;
        //  1313   1319   1319   1320   Any
        //  1313   1319   1319   1320   Any
        //  1313   1319   1319   1320   Any
        //  1313   1319   1319   1320   Ljava/lang/IllegalStateException;
        //  1313   1319   3      8      Any
        //  1323   1330   1330   1331   Any
        //  1323   1330   1323   1324   Ljava/lang/NullPointerException;
        //  1324   1330   1323   1324   Any
        //  1324   1330   1323   1324   Any
        //  1323   1330   3      8      Ljava/lang/AssertionError;
        //  1345   1351   1351   1352   Any
        //  1345   1351   3      8      Any
        //  1345   1351   3      8      Any
        //  1345   1351   1351   1352   Any
        //  1345   1351   1351   1352   Any
        //  1355   1362   1362   1363   Any
        //  1356   1362   1355   1356   Any
        //  1355   1362   1362   1363   Any
        //  1355   1362   3      8      Any
        //  1355   1362   3      8      Ljava/lang/UnsupportedOperationException;
        //  1370   1377   1377   1378   Any
        //  1370   1377   1370   1371   Ljava/lang/NullPointerException;
        //  1371   1377   1377   1378   Any
        //  1370   1377   3      8      Any
        //  1370   1377   3      8      Ljava/lang/UnsupportedOperationException;
        //  1385   1391   1391   1392   Any
        //  1385   1391   1391   1392   Ljava/lang/IndexOutOfBoundsException;
        //  1385   1391   3      8      Ljava/lang/NegativeArraySizeException;
        //  1385   1391   3      8      Ljava/lang/ArithmeticException;
        //  1385   1391   1391   1392   Ljava/lang/IllegalArgumentException;
        //  1398   1405   1405   1406   Any
        //  1398   1405   1398   1399   Any
        //  1398   1405   1405   1406   Ljava/lang/RuntimeException;
        //  1398   1405   1405   1406   Ljava/lang/ClassCastException;
        //  1399   1405   3      8      Any
        //  1460   1466   1466   1467   Any
        //  1460   1466   1466   1467   Ljava/lang/StringIndexOutOfBoundsException;
        //  1460   1466   3      8      Ljava/lang/EnumConstantNotPresentException;
        //  1460   1466   3      8      Ljava/lang/AssertionError;
        //  1460   1466   1466   1467   Any
        //  1470   1477   1477   1478   Any
        //  1470   1477   1470   1471   Any
        //  1471   1477   1477   1478   Any
        //  1470   1477   1477   1478   Any
        //  1470   1477   1477   1478   Any
        //  1535   1542   1542   1543   Any
        //  1536   1542   3      8      Any
        //  1536   1542   3      8      Any
        //  1535   1542   3      8      Any
        //  1536   1542   1535   1536   Any
        //  1553   1560   1560   1561   Any
        //  1553   1560   1553   1554   Ljava/lang/ClassCastException;
        //  1554   1560   1560   1561   Any
        //  1554   1560   1553   1554   Any
        //  1553   1560   3      8      Ljava/lang/NumberFormatException;
        //  1660   1666   1666   1667   Any
        //  1660   1666   1666   1667   Any
        //  1660   1666   3      8      Any
        //  1660   1666   3      8      Ljava/lang/UnsupportedOperationException;
        //  1660   1666   3      8      Any
        //  1719   1726   1726   1727   Any
        //  1720   1726   3      8      Ljava/lang/NumberFormatException;
        //  1720   1726   1719   1720   Ljava/lang/StringIndexOutOfBoundsException;
        //  1720   1726   1719   1720   Ljava/lang/EnumConstantNotPresentException;
        //  1719   1726   3      8      Ljava/lang/ArrayIndexOutOfBoundsException;
        //  1730   1737   1737   1738   Any
        //  1730   1737   3      8      Ljava/lang/ClassCastException;
        //  1731   1737   3      8      Ljava/lang/NumberFormatException;
        //  1731   1737   1730   1731   Any
        //  1730   1737   3      8      Ljava/lang/IllegalArgumentException;
        //  1745   1752   1752   1753   Any
        //  1745   1752   1752   1753   Ljava/util/ConcurrentModificationException;
        //  1746   1752   1752   1753   Any
        //  1745   1752   1745   1746   Any
        //  1745   1752   1752   1753   Any
        //  1761   1768   1768   1769   Any
        //  1761   1768   1761   1762   Any
        //  1761   1768   1761   1762   Any
        //  1761   1768   1768   1769   Ljava/lang/ArithmeticException;
        //  1762   1768   1768   1769   Ljava/util/NoSuchElementException;
        //  1772   1779   1779   1780   Any
        //  1772   1779   3      8      Ljava/lang/IndexOutOfBoundsException;
        //  1773   1779   1772   1773   Any
        //  1772   1779   3      8      Ljava/lang/IllegalArgumentException;
        //  1773   1779   1772   1773   Ljava/lang/ArithmeticException;
        //  1784   1790   1790   1791   Any
        //  1784   1790   1790   1791   Ljava/lang/ArithmeticException;
        //  1784   1790   3      8      Any
        //  1784   1790   3      8      Ljava/lang/EnumConstantNotPresentException;
        //  1784   1790   3      8      Ljava/lang/IllegalArgumentException;
        //  1943   1950   1950   1951   Any
        //  1943   1950   1950   1951   Any
        //  1944   1950   1943   1944   Ljava/lang/EnumConstantNotPresentException;
        //  1944   1950   1950   1951   Any
        //  1943   1950   3      8      Any
        //  1959   1965   1965   1966   Any
        //  1959   1965   1965   1966   Ljava/lang/ArrayIndexOutOfBoundsException;
        //  1959   1965   1965   1966   Ljava/lang/NegativeArraySizeException;
        //  1959   1965   1965   1966   Ljava/lang/EnumConstantNotPresentException;
        //  1959   1965   1965   1966   Any
        //  2022   2029   2029   2030   Any
        //  2023   2029   3      8      Ljava/util/NoSuchElementException;
        //  2023   2029   2022   2023   Ljava/lang/StringIndexOutOfBoundsException;
        //  2022   2029   3      8      Ljava/lang/NullPointerException;
        //  2022   2029   2022   2023   Any
        //  2046   2053   2053   2054   Any
        //  2046   2053   3      8      Ljava/lang/NegativeArraySizeException;
        //  2047   2053   2053   2054   Any
        //  2046   2053   2046   2047   Any
        //  2046   2053   3      8      Any
        //  2156   2162   2162   2163   Any
        //  2156   2162   2162   2163   Any
        //  2156   2162   3      8      Ljava/lang/IllegalArgumentException;
        //  2156   2162   3      8      Ljava/lang/IllegalStateException;
        //  2156   2162   2162   2163   Any
        //  2169   2176   2176   2177   Any
        //  2169   2176   3      8      Ljava/lang/NegativeArraySizeException;
        //  2170   2176   2176   2177   Ljava/lang/IllegalArgumentException;
        //  2169   2176   2176   2177   Ljava/lang/StringIndexOutOfBoundsException;
        //  2170   2176   2169   2170   Any
        //  2186   2193   2193   2194   Any
        //  2187   2193   3      8      Ljava/util/ConcurrentModificationException;
        //  2187   2193   2186   2187   Any
        //  2187   2193   2193   2194   Any
        //  2186   2193   3      8      Any
        //  2200   2207   2207   2208   Any
        //  2201   2207   3      8      Any
        //  2200   2207   2200   2201   Ljava/lang/ArithmeticException;
        //  2200   2207   2207   2208   Ljava/lang/IndexOutOfBoundsException;
        //  2201   2207   2200   2201   Ljava/lang/RuntimeException;
        //  2308   2314   2314   2315   Any
        //  2308   2314   3      8      Any
        //  2308   2314   2314   2315   Any
        //  2308   2314   3      8      Ljava/lang/NumberFormatException;
        //  2308   2314   3      8      Any
        //  2321   2328   2328   2329   Any
        //  2321   2328   3      8      Any
        //  2321   2328   2321   2322   Ljava/util/NoSuchElementException;
        //  2322   2328   2321   2322   Ljava/util/NoSuchElementException;
        //  2321   2328   2328   2329   Ljava/lang/RuntimeException;
        //  2385   2392   2392   2393   Any
        //  2386   2392   2385   2386   Ljava/util/NoSuchElementException;
        //  2385   2392   3      8      Any
        //  2386   2392   3      8      Any
        //  2385   2392   2392   2393   Any
        //  2399   2406   2406   2407   Any
        //  2400   2406   3      8      Any
        //  2400   2406   3      8      Any
        //  2399   2406   2399   2400   Ljava/util/NoSuchElementException;
        //  2399   2406   2406   2407   Any
        //  2464   2471   2471   2472   Any
        //  2464   2471   3      8      Ljava/lang/IllegalArgumentException;
        //  2465   2471   2471   2472   Any
        //  2464   2471   3      8      Ljava/lang/NegativeArraySizeException;
        //  2465   2471   2464   2465   Any
        //  3230   3236   3236   3237   Any
        //  3230   3236   3236   3237   Ljava/util/ConcurrentModificationException;
        //  3230   3236   3      8      Ljava/lang/NegativeArraySizeException;
        //  3230   3236   3236   3237   Ljava/util/ConcurrentModificationException;
        //  3230   3236   3236   3237   Ljava/lang/RuntimeException;
        //  3347   3354   3354   3355   Any
        //  3348   3354   3      8      Ljava/lang/StringIndexOutOfBoundsException;
        //  3347   3354   3      8      Any
        //  3348   3354   3347   3348   Ljava/util/NoSuchElementException;
        //  3347   3354   3354   3355   Ljava/lang/IllegalArgumentException;
        //  3403   3410   3410   3411   Any
        //  3403   3410   3403   3404   Any
        //  3404   3410   3403   3404   Any
        //  3404   3410   3      8      Ljava/lang/IndexOutOfBoundsException;
        //  3403   3410   3410   3411   Ljava/lang/ArithmeticException;
        //  3522   3529   3529   3530   Any
        //  3522   3529   3522   3523   Ljava/lang/AssertionError;
        //  3523   3529   3      8      Any
        //  3523   3529   3      8      Ljava/lang/RuntimeException;
        //  3523   3529   3529   3530   Any
        //  3595   3602   3602   3603   Any
        //  3595   3602   3602   3603   Ljava/lang/NegativeArraySizeException;
        //  3596   3602   3602   3603   Ljava/lang/NumberFormatException;
        //  3596   3602   3      8      Any
        //  3595   3602   3595   3596   Ljava/util/ConcurrentModificationException;
        //  3606   3613   3613   3614   Any
        //  3607   3613   3606   3607   Ljava/lang/AssertionError;
        //  3606   3613   3      8      Ljava/lang/UnsupportedOperationException;
        //  3606   3613   3606   3607   Ljava/lang/IllegalStateException;
        //  3607   3613   3606   3607   Ljava/lang/StringIndexOutOfBoundsException;
        //  3674   3681   3681   3682   Any
        //  3674   3681   3681   3682   Any
        //  3674   3681   3674   3675   Any
        //  3675   3681   3      8      Any
        //  3675   3681   3      8      Any
        //  3791   3798   3798   3799   Any
        //  3791   3798   3791   3792   Ljava/util/NoSuchElementException;
        //  3792   3798   3798   3799   Any
        //  3792   3798   3798   3799   Any
        //  3792   3798   3      8      Any
        //  3802   3809   3809   3810   Any
        //  3803   3809   3      8      Ljava/util/NoSuchElementException;
        //  3803   3809   3      8      Any
        //  3802   3809   3802   3803   Any
        //  3802   3809   3809   3810   Ljava/lang/ClassCastException;
        //  3911   3918   3918   3919   Any
        //  3912   3918   3      8      Any
        //  3911   3918   3911   3912   Any
        //  3912   3918   3      8      Ljava/util/NoSuchElementException;
        //  3912   3918   3      8      Ljava/lang/NullPointerException;
        //  4027   4034   4034   4035   Any
        //  4028   4034   4027   4028   Ljava/lang/UnsupportedOperationException;
        //  4028   4034   4034   4035   Ljava/lang/RuntimeException;
        //  4027   4034   4034   4035   Any
        //  4027   4034   3      8      Any
        //  4038   4045   4045   4046   Any
        //  4038   4045   4045   4046   Ljava/lang/NumberFormatException;
        //  4038   4045   4045   4046   Any
        //  4039   4045   4045   4046   Any
        //  4038   4045   4038   4039   Any
        //  4107   4114   4114   4115   Any
        //  4108   4114   4107   4108   Ljava/util/ConcurrentModificationException;
        //  4107   4114   4114   4115   Any
        //  4108   4114   3      8      Any
        //  4107   4114   4114   4115   Any
        //  4118   4125   4125   4126   Any
        //  4118   4125   3      8      Ljava/lang/IllegalArgumentException;
        //  4119   4125   3      8      Ljava/util/ConcurrentModificationException;
        //  4119   4125   4125   4126   Any
        //  4118   4125   4118   4119   Any
        //  4175   4182   4182   4183   Any
        //  4175   4182   4175   4176   Ljava/lang/IndexOutOfBoundsException;
        //  4175   4182   4175   4176   Any
        //  4176   4182   4182   4183   Ljava/lang/NumberFormatException;
        //  4176   4182   3      8      Any
        //  4189   4196   4196   4197   Any
        //  4190   4196   3      8      Any
        //  4190   4196   4196   4197   Ljava/lang/NullPointerException;
        //  4189   4196   4189   4190   Any
        //  4189   4196   4196   4197   Any
        //  4200   4207   4207   4208   Any
        //  4201   4207   4200   4201   Ljava/lang/NullPointerException;
        //  4200   4207   4207   4208   Ljava/lang/IllegalArgumentException;
        //  4200   4207   3      8      Any
        //  4201   4207   4207   4208   Any
        //  4212   4218   4218   4219   Any
        //  4212   4218   3      8      Any
        //  4212   4218   3      8      Any
        //  4212   4218   4218   4219   Ljava/lang/StringIndexOutOfBoundsException;
        //  4212   4218   4218   4219   Any
        // 
        // The error that occurred was:
        // 
        // java.lang.IndexOutOfBoundsException: Index -1 out of bounds for length 0
        //     at java.base/jdk.internal.util.Preconditions.outOfBounds(Preconditions.java:64)
        //     at java.base/jdk.internal.util.Preconditions.outOfBoundsCheckIndex(Preconditions.java:70)
        //     at java.base/jdk.internal.util.Preconditions.checkIndex(Preconditions.java:248)
        //     at java.base/java.util.Objects.checkIndex(Objects.java:372)
        //     at java.base/java.util.ArrayList.remove(ArrayList.java:535)
        //     at com.strobel.assembler.ir.StackMappingVisitor.pop(StackMappingVisitor.java:267)
        //     at com.strobel.assembler.ir.StackMappingVisitor$InstructionAnalyzer.execute(StackMappingVisitor.java:738)
        //     at com.strobel.assembler.ir.StackMappingVisitor$InstructionAnalyzer.visit(StackMappingVisitor.java:398)
        //     at com.strobel.decompiler.ast.AstBuilder.performStackAnalysis(AstBuilder.java:2030)
        //     at com.strobel.decompiler.ast.AstBuilder.build(AstBuilder.java:108)
        //     at com.strobel.decompiler.languages.java.ast.AstMethodBodyBuilder.createMethodBody(AstMethodBodyBuilder.java:211)
        //     at com.strobel.decompiler.languages.java.ast.AstMethodBodyBuilder.createMethodBody(AstMethodBodyBuilder.java:99)
        //     at com.strobel.decompiler.languages.java.ast.AstBuilder.createMethodBody(AstBuilder.java:782)
        //     at com.strobel.decompiler.languages.java.ast.AstBuilder.createMethod(AstBuilder.java:675)
        //     at com.strobel.decompiler.languages.java.ast.AstBuilder.addTypeMembers(AstBuilder.java:552)
        //     at com.strobel.decompiler.languages.java.ast.AstBuilder.createTypeCore(AstBuilder.java:519)
        //     at com.strobel.decompiler.languages.java.ast.AstBuilder.createTypeNoCache(AstBuilder.java:161)
        //     at com.strobel.decompiler.languages.java.ast.AstBuilder.createType(AstBuilder.java:150)
        //     at com.strobel.decompiler.languages.java.ast.AstBuilder.addType(AstBuilder.java:125)
        //     at com.strobel.decompiler.languages.java.JavaLanguage.buildAst(JavaLanguage.java:71)
        //     at com.strobel.decompiler.languages.java.JavaLanguage.decompileType(JavaLanguage.java:59)
        //     at com.strobel.decompiler.DecompilerDriver.decompileType(DecompilerDriver.java:330)
        //     at com.strobel.decompiler.DecompilerDriver.decompileJar(DecompilerDriver.java:251)
        //     at com.strobel.decompiler.DecompilerDriver.main(DecompilerDriver.java:126)
        // 
        throw new IllegalStateException("An error occurred while decompiling this method.");
    }
}
