// 
// Decompiled by Procyon v0.5.36
// 

package dev.nuker.pyro;

import net.minecraft.util.EnumHandSide;
import org.jetbrains.annotations.NotNull;

public class f9Q extends fH
{
    public double c;
    public double 0;
    public double 1;
    @NotNull
    public f0d c;
    @NotNull
    public f0d 0;
    @NotNull
    public f0d 1;
    @NotNull
    public f0d 2;
    @NotNull
    public f0d 3;
    @NotNull
    public f0d 4;
    @NotNull
    public f0d 5;
    @NotNull
    public f0d 6;
    @NotNull
    public f0d 7;
    @NotNull
    public f0d 8;
    @NotNull
    public f0d 9;
    @NotNull
    public f0d a;
    @NotNull
    public f0d b;
    @NotNull
    public f0d d;
    @NotNull
    public f0d e;
    @NotNull
    public f0d f;
    @NotNull
    public f0d g;
    @NotNull
    public f0d h;
    
    @NotNull
    public f0d 2() {
        return fbS.g2(this, 536015690);
    }
    
    @NotNull
    public f0d 0() {
        return fbS.fM(this, 158037368);
    }
    
    public double 8() {
        return fbS.a1(this, 1020230372);
    }
    
    public double d() {
        return fbS.9P(this, 1792138303);
    }
    
    public f9Q() {
        // 
        // This method could not be decompiled.
        // 
        // Original Bytecode:
        // 
        //     1: ldc2_w          3.0
        //     4: putfield        dev/nuker/pyro/f9Q.c:D
        //     7: aload_0        
        //     8: ldc2_w          3.0
        //    11: getstatic       dev/nuker/pyro/fc.0:I
        //    14: ifeq            22
        //    17: ldc             1576189644
        //    19: goto            24
        //    22: ldc             -996671764
        //    24: ldc             528932462
        //    26: ixor           
        //    27: lookupswitch {
        //          -619634558: 52
        //          1114923170: 22
        //          default: 3389
        //        }
        //    52: putfield        dev/nuker/pyro/f9Q.0:D
        //    55: aload_0        
        //    56: ldc2_w          360.0
        //    59: getstatic       dev/nuker/pyro/fc.1:I
        //    62: ifeq            70
        //    65: ldc             -1505685690
        //    67: goto            72
        //    70: ldc             -1964719152
        //    72: ldc             819781873
        //    74: ixor           
        //    75: lookupswitch {
        //          -1768034377: 3361
        //          859168262: 70
        //          default: 100
        //        }
        //   100: putfield        dev/nuker/pyro/f9Q.1:D
        //   103: aload_0        
        //   104: ldc             "\u2263\u1487\u8b66\ub3d4\uc96f\uec65\ub221\ue759\ud945\ue925\ua6a8\u1e49\ue066"
        //   106: getstatic       dev/nuker/pyro/fc.1:I
        //   109: ifeq            117
        //   112: ldc             -1979621
        //   114: goto            119
        //   117: ldc             1944129885
        //   119: ldc             896945034
        //   121: ixor           
        //   122: lookupswitch {
        //          -896040815: 3421
        //          1712746977: 117
        //          default: 148
        //        }
        //   148: invokestatic    invokestatic   !!! ERROR
        //   151: ldc             "\u2243\u1487\u8b66\ub3d4\uc96f\uec65\ub221\ue759\ud945\ue925\ua6a8\u1e49\ue066"
        //   153: invokestatic    invokestatic   !!! ERROR
        //   156: ldc             "\u2249\u149b\u8b62\ub3d7\uc95e\uec69\ub237\ue70e\ud97c\ue922\ua6a9\u1e0c\ue07c\uc5ae\u81a8\u88e0\u57e4\u7686\ubd32\uc092\u2a9d\uc237\u6bc3\u2d59\ud74e\u344f\u7d23\u8821\u801f\u8c09\u856a\ufb3b\u7148\u9a13\u1b12\uf0fe"
        //   158: getstatic       dev/nuker/pyro/fc.1:I
        //   161: ifeq            169
        //   164: ldc             -1706898678
        //   166: goto            171
        //   169: ldc             1763551330
        //   171: ldc             1275976514
        //   173: ixor           
        //   174: lookupswitch {
        //          -699461560: 169
        //          621835040: 200
        //          default: 3427
        //        }
        //   200: invokestatic    invokestatic   !!! ERROR
        //   203: invokespecial   dev/nuker/pyro/fH.<init>:(Ljava/lang/String;Ljava/lang/String;Ljava/lang/String;)V
        //   206: aload_0        
        //   207: ldc2_w          3.0
        //   210: putfield        dev/nuker/pyro/f9Q.c:D
        //   213: aload_0        
        //   214: ldc2_w          3.0
        //   217: getstatic       dev/nuker/pyro/fc.c:I
        //   220: ifge            228
        //   223: ldc             -952046254
        //   225: goto            230
        //   228: ldc             975464979
        //   230: ldc             -1686032619
        //   232: ixor           
        //   233: lookupswitch {
        //          393934108: 228
        //          1556202055: 3411
        //          default: 260
        //        }
        //   260: putfield        dev/nuker/pyro/f9Q.0:D
        //   263: aload_0        
        //   264: ldc2_w          360.0
        //   267: putfield        dev/nuker/pyro/f9Q.1:D
        //   270: aload_0        
        //   271: new             Ldev/nuker/pyro/f0d;
        //   274: dup            
        //   275: ldc             "x"
        //   277: ldc             "X"
        //   279: aconst_null    
        //   280: dconst_0       
        //   281: aload_0        
        //   282: getfield        dev/nuker/pyro/f9Q.c:D
        //   285: dneg           
        //   286: aload_0        
        //   287: getstatic       dev/nuker/pyro/fc.0:I
        //   290: ifeq            298
        //   293: ldc             -317538823
        //   295: goto            300
        //   298: ldc             1990237485
        //   300: ldc             -249145836
        //   302: ixor           
        //   303: lookupswitch {
        //          -2021209287: 328
        //          473230317: 298
        //          default: 3363
        //        }
        //   328: getfield        dev/nuker/pyro/f9Q.c:D
        //   331: dconst_0       
        //   332: bipush          64
        //   334: aconst_null    
        //   335: invokespecial   dev/nuker/pyro/f0d.<init>:(Ljava/lang/String;Ljava/lang/String;Ljava/lang/String;DDDDILkotlin/jvm/internal/DefaultConstructorMarker;)V
        //   338: putfield        dev/nuker/pyro/f9Q.c:Ldev/nuker/pyro/f0d;
        //   341: aload_0        
        //   342: new             Ldev/nuker/pyro/f0d;
        //   345: dup            
        //   346: ldc             "y"
        //   348: ldc             "Y"
        //   350: aconst_null    
        //   351: dconst_0       
        //   352: getstatic       dev/nuker/pyro/fc.c:I
        //   355: ifge            363
        //   358: ldc             -1081336204
        //   360: goto            365
        //   363: ldc             1978996448
        //   365: ldc             1418545644
        //   367: ixor           
        //   368: lookupswitch {
        //          -974115787: 363
        //          -352233576: 3435
        //          default: 396
        //        }
        //   396: aload_0        
        //   397: getfield        dev/nuker/pyro/f9Q.c:D
        //   400: dneg           
        //   401: aload_0        
        //   402: getstatic       dev/nuker/pyro/fc.0:I
        //   405: ifeq            413
        //   408: ldc             -418394181
        //   410: goto            415
        //   413: ldc             -178122704
        //   415: ldc             -1617359838
        //   417: ixor           
        //   418: lookupswitch {
        //          372169805: 413
        //          2023146393: 3391
        //          default: 444
        //        }
        //   444: getfield        dev/nuker/pyro/f9Q.c:D
        //   447: dconst_0       
        //   448: bipush          64
        //   450: aconst_null    
        //   451: invokespecial   dev/nuker/pyro/f0d.<init>:(Ljava/lang/String;Ljava/lang/String;Ljava/lang/String;DDDDILkotlin/jvm/internal/DefaultConstructorMarker;)V
        //   454: putfield        dev/nuker/pyro/f9Q.0:Ldev/nuker/pyro/f0d;
        //   457: aload_0        
        //   458: new             Ldev/nuker/pyro/f0d;
        //   461: dup            
        //   462: ldc             "z"
        //   464: ldc             "Z"
        //   466: aconst_null    
        //   467: dconst_0       
        //   468: getstatic       dev/nuker/pyro/fc.1:I
        //   471: ifeq            479
        //   474: ldc             1211618938
        //   476: goto            481
        //   479: ldc             373670986
        //   481: ldc             1606211162
        //   483: ixor           
        //   484: lookupswitch {
        //          394985504: 479
        //          1241059856: 512
        //          default: 3355
        //        }
        //   512: aload_0        
        //   513: getstatic       dev/nuker/pyro/fc.0:I
        //   516: ifeq            524
        //   519: ldc             -330013086
        //   521: goto            526
        //   524: ldc             -1661368314
        //   526: ldc             1773321735
        //   528: ixor           
        //   529: lookupswitch {
        //          -2048468891: 524
        //          -179620351: 556
        //          default: 3367
        //        }
        //   556: getfield        dev/nuker/pyro/f9Q.c:D
        //   559: dneg           
        //   560: aload_0        
        //   561: getstatic       dev/nuker/pyro/fc.0:I
        //   564: ifeq            572
        //   567: ldc             365571273
        //   569: goto            574
        //   572: ldc             1960599900
        //   574: ldc             1655575631
        //   576: ixor           
        //   577: lookupswitch {
        //          376599827: 604
        //          2003056774: 572
        //          default: 3433
        //        }
        //   604: getfield        dev/nuker/pyro/f9Q.c:D
        //   607: dconst_0       
        //   608: bipush          64
        //   610: aconst_null    
        //   611: getstatic       dev/nuker/pyro/fc.c:I
        //   614: ifge            622
        //   617: ldc             -1662501053
        //   619: goto            624
        //   622: ldc             -174260227
        //   624: ldc             936046878
        //   626: ixor           
        //   627: lookupswitch {
        //          -1575615819: 622
        //          -1423782307: 3429
        //          default: 652
        //        }
        //   652: invokespecial   dev/nuker/pyro/f0d.<init>:(Ljava/lang/String;Ljava/lang/String;Ljava/lang/String;DDDDILkotlin/jvm/internal/DefaultConstructorMarker;)V
        //   655: putfield        dev/nuker/pyro/f9Q.1:Ldev/nuker/pyro/f0d;
        //   658: aload_0        
        //   659: new             Ldev/nuker/pyro/f0d;
        //   662: dup            
        //   663: ldc             "x"
        //   665: ldc             "X"
        //   667: aconst_null    
        //   668: dconst_1       
        //   669: dconst_0       
        //   670: aload_0        
        //   671: getfield        dev/nuker/pyro/f9Q.0:D
        //   674: dconst_0       
        //   675: bipush          64
        //   677: aconst_null    
        //   678: invokespecial   dev/nuker/pyro/f0d.<init>:(Ljava/lang/String;Ljava/lang/String;Ljava/lang/String;DDDDILkotlin/jvm/internal/DefaultConstructorMarker;)V
        //   681: getstatic       dev/nuker/pyro/fc.0:I
        //   684: ifeq            692
        //   687: ldc             -2147408469
        //   689: goto            694
        //   692: ldc             -305490687
        //   694: ldc             -1095736636
        //   696: ixor           
        //   697: lookupswitch {
        //          852644705: 692
        //          1051805551: 3347
        //          default: 724
        //        }
        //   724: putfield        dev/nuker/pyro/f9Q.2:Ldev/nuker/pyro/f0d;
        //   727: aload_0        
        //   728: new             Ldev/nuker/pyro/f0d;
        //   731: dup            
        //   732: ldc             "y"
        //   734: ldc             "Y"
        //   736: aconst_null    
        //   737: dconst_1       
        //   738: dconst_0       
        //   739: aload_0        
        //   740: getfield        dev/nuker/pyro/f9Q.0:D
        //   743: dconst_0       
        //   744: bipush          64
        //   746: aconst_null    
        //   747: invokespecial   dev/nuker/pyro/f0d.<init>:(Ljava/lang/String;Ljava/lang/String;Ljava/lang/String;DDDDILkotlin/jvm/internal/DefaultConstructorMarker;)V
        //   750: putfield        dev/nuker/pyro/f9Q.3:Ldev/nuker/pyro/f0d;
        //   753: aload_0        
        //   754: new             Ldev/nuker/pyro/f0d;
        //   757: dup            
        //   758: ldc             "z"
        //   760: ldc             "Z"
        //   762: aconst_null    
        //   763: dconst_1       
        //   764: dconst_0       
        //   765: aload_0        
        //   766: getstatic       dev/nuker/pyro/fc.c:I
        //   769: ifge            777
        //   772: ldc             -1740589763
        //   774: goto            779
        //   777: ldc             1964211865
        //   779: ldc             -852052983
        //   781: ixor           
        //   782: lookupswitch {
        //          -1205482864: 808
        //          1433796916: 777
        //          default: 3349
        //        }
        //   808: getfield        dev/nuker/pyro/f9Q.0:D
        //   811: dconst_0       
        //   812: bipush          64
        //   814: aconst_null    
        //   815: getstatic       dev/nuker/pyro/fc.0:I
        //   818: ifeq            826
        //   821: ldc             -415066491
        //   823: goto            828
        //   826: ldc             -1133781179
        //   828: ldc             712647166
        //   830: ixor           
        //   831: lookupswitch {
        //          -1777205573: 856
        //          -851921029: 826
        //          default: 3451
        //        }
        //   856: invokespecial   dev/nuker/pyro/f0d.<init>:(Ljava/lang/String;Ljava/lang/String;Ljava/lang/String;DDDDILkotlin/jvm/internal/DefaultConstructorMarker;)V
        //   859: putfield        dev/nuker/pyro/f9Q.4:Ldev/nuker/pyro/f0d;
        //   862: getstatic       dev/nuker/pyro/fc.1:I
        //   865: ifeq            873
        //   868: ldc             -988717818
        //   870: goto            875
        //   873: ldc             -1057138188
        //   875: ldc             -1213590862
        //   877: ixor           
        //   878: lookupswitch {
        //          1924878260: 873
        //          2002209606: 904
        //          default: 3395
        //        }
        //   904: aload_0        
        //   905: new             Ldev/nuker/pyro/f0d;
        //   908: dup            
        //   909: ldc             "x"
        //   911: ldc             "X"
        //   913: aconst_null    
        //   914: dconst_0       
        //   915: dconst_0       
        //   916: aload_0        
        //   917: getfield        dev/nuker/pyro/f9Q.1:D
        //   920: dconst_0       
        //   921: bipush          64
        //   923: aconst_null    
        //   924: invokespecial   dev/nuker/pyro/f0d.<init>:(Ljava/lang/String;Ljava/lang/String;Ljava/lang/String;DDDDILkotlin/jvm/internal/DefaultConstructorMarker;)V
        //   927: putfield        dev/nuker/pyro/f9Q.5:Ldev/nuker/pyro/f0d;
        //   930: getstatic       dev/nuker/pyro/fc.0:I
        //   933: ifeq            941
        //   936: ldc             -46781907
        //   938: goto            943
        //   941: ldc             1867802414
        //   943: ldc             -1028150149
        //   945: ixor           
        //   946: lookupswitch {
        //          -1377580203: 972
        //          1065453142: 941
        //          default: 3359
        //        }
        //   972: aload_0        
        //   973: new             Ldev/nuker/pyro/f0d;
        //   976: dup            
        //   977: ldc             "y"
        //   979: ldc             "Y"
        //   981: aconst_null    
        //   982: dconst_0       
        //   983: dconst_0       
        //   984: aload_0        
        //   985: getfield        dev/nuker/pyro/f9Q.1:D
        //   988: dconst_0       
        //   989: bipush          64
        //   991: aconst_null    
        //   992: invokespecial   dev/nuker/pyro/f0d.<init>:(Ljava/lang/String;Ljava/lang/String;Ljava/lang/String;DDDDILkotlin/jvm/internal/DefaultConstructorMarker;)V
        //   995: putfield        dev/nuker/pyro/f9Q.6:Ldev/nuker/pyro/f0d;
        //   998: aload_0        
        //   999: new             Ldev/nuker/pyro/f0d;
        //  1002: dup            
        //  1003: ldc             "z"
        //  1005: ldc             "Z"
        //  1007: aconst_null    
        //  1008: dconst_0       
        //  1009: dconst_0       
        //  1010: aload_0        
        //  1011: getfield        dev/nuker/pyro/f9Q.1:D
        //  1014: dconst_0       
        //  1015: bipush          64
        //  1017: aconst_null    
        //  1018: invokespecial   dev/nuker/pyro/f0d.<init>:(Ljava/lang/String;Ljava/lang/String;Ljava/lang/String;DDDDILkotlin/jvm/internal/DefaultConstructorMarker;)V
        //  1021: putfield        dev/nuker/pyro/f9Q.7:Ldev/nuker/pyro/f0d;
        //  1024: getstatic       dev/nuker/pyro/fc.0:I
        //  1027: ifeq            1035
        //  1030: ldc             156239395
        //  1032: goto            1037
        //  1035: ldc             1053398655
        //  1037: ldc             1357392430
        //  1039: ixor           
        //  1040: lookupswitch {
        //          1505242125: 1035
        //          1847704657: 1068
        //          default: 3375
        //        }
        //  1068: aload_0        
        //  1069: new             Ldev/nuker/pyro/f0d;
        //  1072: dup            
        //  1073: ldc             "x"
        //  1075: ldc             "X"
        //  1077: aconst_null    
        //  1078: dconst_0       
        //  1079: getstatic       dev/nuker/pyro/fc.c:I
        //  1082: ifge            1090
        //  1085: ldc             -701701459
        //  1087: goto            1092
        //  1090: ldc             1100456380
        //  1092: ldc             1887848068
        //  1094: ixor           
        //  1095: lookupswitch {
        //          -1498766295: 3441
        //          -156680043: 1090
        //          default: 1120
        //        }
        //  1120: aload_0        
        //  1121: getfield        dev/nuker/pyro/f9Q.c:D
        //  1124: dneg           
        //  1125: aload_0        
        //  1126: getfield        dev/nuker/pyro/f9Q.c:D
        //  1129: dconst_0       
        //  1130: bipush          64
        //  1132: aconst_null    
        //  1133: invokespecial   dev/nuker/pyro/f0d.<init>:(Ljava/lang/String;Ljava/lang/String;Ljava/lang/String;DDDDILkotlin/jvm/internal/DefaultConstructorMarker;)V
        //  1136: getstatic       dev/nuker/pyro/fc.c:I
        //  1139: ifge            1147
        //  1142: ldc             360981704
        //  1144: goto            1149
        //  1147: ldc             -1271687464
        //  1149: ldc             1593500316
        //  1151: ixor           
        //  1152: lookupswitch {
        //          -1839432316: 1147
        //          1266599508: 3393
        //          default: 1180
        //        }
        //  1180: putfield        dev/nuker/pyro/f9Q.8:Ldev/nuker/pyro/f0d;
        //  1183: aload_0        
        //  1184: new             Ldev/nuker/pyro/f0d;
        //  1187: dup            
        //  1188: ldc             "y"
        //  1190: ldc             "Y"
        //  1192: aconst_null    
        //  1193: dconst_0       
        //  1194: aload_0        
        //  1195: getfield        dev/nuker/pyro/f9Q.c:D
        //  1198: dneg           
        //  1199: aload_0        
        //  1200: getstatic       dev/nuker/pyro/fc.0:I
        //  1203: ifeq            1211
        //  1206: ldc             -246470227
        //  1208: goto            1213
        //  1211: ldc             -1816356590
        //  1213: ldc             2012133870
        //  1215: ixor           
        //  1216: lookupswitch {
        //          -2036232125: 1211
        //          -464379652: 1244
        //          default: 3401
        //        }
        //  1244: getfield        dev/nuker/pyro/f9Q.c:D
        //  1247: dconst_0       
        //  1248: bipush          64
        //  1250: aconst_null    
        //  1251: invokespecial   dev/nuker/pyro/f0d.<init>:(Ljava/lang/String;Ljava/lang/String;Ljava/lang/String;DDDDILkotlin/jvm/internal/DefaultConstructorMarker;)V
        //  1254: getstatic       dev/nuker/pyro/fc.1:I
        //  1257: ifeq            1265
        //  1260: ldc             -31120522
        //  1262: goto            1267
        //  1265: ldc             -281617970
        //  1267: ldc             -894602788
        //  1269: ixor           
        //  1270: lookupswitch {
        //          321293291: 1265
        //          881349290: 3423
        //          default: 1296
        //        }
        //  1296: putfield        dev/nuker/pyro/f9Q.9:Ldev/nuker/pyro/f0d;
        //  1299: aload_0        
        //  1300: new             Ldev/nuker/pyro/f0d;
        //  1303: dup            
        //  1304: ldc             "z"
        //  1306: ldc             "Z"
        //  1308: aconst_null    
        //  1309: dconst_0       
        //  1310: aload_0        
        //  1311: getfield        dev/nuker/pyro/f9Q.c:D
        //  1314: dneg           
        //  1315: getstatic       dev/nuker/pyro/fc.0:I
        //  1318: ifeq            1326
        //  1321: ldc             1710698745
        //  1323: goto            1328
        //  1326: ldc             -519591695
        //  1328: ldc             -1346849644
        //  1330: ixor           
        //  1331: lookupswitch {
        //          -900758419: 3365
        //          538869773: 1326
        //          default: 1356
        //        }
        //  1356: aload_0        
        //  1357: getstatic       dev/nuker/pyro/fc.c:I
        //  1360: ifge            1368
        //  1363: ldc             517647879
        //  1365: goto            1370
        //  1368: ldc             -1786466597
        //  1370: ldc             179936554
        //  1372: ixor           
        //  1373: lookupswitch {
        //          -1444085010: 1368
        //          342045485: 3447
        //          default: 1400
        //        }
        //  1400: getfield        dev/nuker/pyro/f9Q.c:D
        //  1403: dconst_0       
        //  1404: bipush          64
        //  1406: aconst_null    
        //  1407: getstatic       dev/nuker/pyro/fc.1:I
        //  1410: ifeq            1418
        //  1413: ldc             1349110611
        //  1415: goto            1420
        //  1418: ldc             1367904546
        //  1420: ldc             1313172051
        //  1422: ixor           
        //  1423: lookupswitch {
        //          506241280: 1418
        //          533592945: 1448
        //          default: 3413
        //        }
        //  1448: invokespecial   dev/nuker/pyro/f0d.<init>:(Ljava/lang/String;Ljava/lang/String;Ljava/lang/String;DDDDILkotlin/jvm/internal/DefaultConstructorMarker;)V
        //  1451: putfield        dev/nuker/pyro/f9Q.a:Ldev/nuker/pyro/f0d;
        //  1454: getstatic       dev/nuker/pyro/fc.1:I
        //  1457: ifeq            1465
        //  1460: ldc             -275855326
        //  1462: goto            1467
        //  1465: ldc             -94975303
        //  1467: ldc             1689567682
        //  1469: ixor           
        //  1470: lookupswitch {
        //          -1959130656: 1465
        //          -1629353093: 1496
        //          default: 3383
        //        }
        //  1496: aload_0        
        //  1497: new             Ldev/nuker/pyro/f0d;
        //  1500: dup            
        //  1501: ldc             "x"
        //  1503: ldc             "X"
        //  1505: aconst_null    
        //  1506: dconst_1       
        //  1507: dconst_0       
        //  1508: aload_0        
        //  1509: getfield        dev/nuker/pyro/f9Q.0:D
        //  1512: dconst_0       
        //  1513: bipush          64
        //  1515: aconst_null    
        //  1516: invokespecial   dev/nuker/pyro/f0d.<init>:(Ljava/lang/String;Ljava/lang/String;Ljava/lang/String;DDDDILkotlin/jvm/internal/DefaultConstructorMarker;)V
        //  1519: getstatic       dev/nuker/pyro/fc.0:I
        //  1522: ifeq            1530
        //  1525: ldc             -1865587301
        //  1527: goto            1532
        //  1530: ldc             609738480
        //  1532: ldc             -1146551966
        //  1534: ixor           
        //  1535: lookupswitch {
        //          -1646201982: 1530
        //          727999737: 3415
        //          default: 1560
        //        }
        //  1560: putfield        dev/nuker/pyro/f9Q.b:Ldev/nuker/pyro/f0d;
        //  1563: getstatic       dev/nuker/pyro/fc.1:I
        //  1566: ifeq            1574
        //  1569: ldc             987218839
        //  1571: goto            1576
        //  1574: ldc             -526152896
        //  1576: ldc             372090529
        //  1578: ixor           
        //  1579: lookupswitch {
        //          -158454303: 1604
        //          754607414: 1574
        //          default: 3381
        //        }
        //  1604: aload_0        
        //  1605: new             Ldev/nuker/pyro/f0d;
        //  1608: dup            
        //  1609: ldc             "y"
        //  1611: ldc             "Y"
        //  1613: aconst_null    
        //  1614: dconst_1       
        //  1615: dconst_0       
        //  1616: aload_0        
        //  1617: getfield        dev/nuker/pyro/f9Q.0:D
        //  1620: dconst_0       
        //  1621: bipush          64
        //  1623: aconst_null    
        //  1624: invokespecial   dev/nuker/pyro/f0d.<init>:(Ljava/lang/String;Ljava/lang/String;Ljava/lang/String;DDDDILkotlin/jvm/internal/DefaultConstructorMarker;)V
        //  1627: putfield        dev/nuker/pyro/f9Q.d:Ldev/nuker/pyro/f0d;
        //  1630: getstatic       dev/nuker/pyro/fc.c:I
        //  1633: ifge            1641
        //  1636: ldc             1342755110
        //  1638: goto            1643
        //  1641: ldc             2125156538
        //  1643: ldc             874936948
        //  1645: ixor           
        //  1646: lookupswitch {
        //          1250765518: 1672
        //          1680780114: 1641
        //          default: 3385
        //        }
        //  1672: aload_0        
        //  1673: new             Ldev/nuker/pyro/f0d;
        //  1676: dup            
        //  1677: ldc             "z"
        //  1679: ldc             "Z"
        //  1681: aconst_null    
        //  1682: dconst_1       
        //  1683: dconst_0       
        //  1684: aload_0        
        //  1685: getfield        dev/nuker/pyro/f9Q.0:D
        //  1688: dconst_0       
        //  1689: bipush          64
        //  1691: aconst_null    
        //  1692: invokespecial   dev/nuker/pyro/f0d.<init>:(Ljava/lang/String;Ljava/lang/String;Ljava/lang/String;DDDDILkotlin/jvm/internal/DefaultConstructorMarker;)V
        //  1695: putfield        dev/nuker/pyro/f9Q.e:Ldev/nuker/pyro/f0d;
        //  1698: aload_0        
        //  1699: new             Ldev/nuker/pyro/f0d;
        //  1702: dup            
        //  1703: ldc             "x"
        //  1705: ldc             "X"
        //  1707: aconst_null    
        //  1708: dconst_0       
        //  1709: dconst_0       
        //  1710: aload_0        
        //  1711: getstatic       dev/nuker/pyro/fc.1:I
        //  1714: ifeq            1722
        //  1717: ldc             1364170242
        //  1719: goto            1724
        //  1722: ldc             -787654851
        //  1724: ldc             2068825564
        //  1726: ixor           
        //  1727: lookupswitch {
        //          704664542: 3403
        //          1599100510: 1722
        //          default: 1752
        //        }
        //  1752: getfield        dev/nuker/pyro/f9Q.1:D
        //  1755: dconst_0       
        //  1756: bipush          64
        //  1758: aconst_null    
        //  1759: invokespecial   dev/nuker/pyro/f0d.<init>:(Ljava/lang/String;Ljava/lang/String;Ljava/lang/String;DDDDILkotlin/jvm/internal/DefaultConstructorMarker;)V
        //  1762: putfield        dev/nuker/pyro/f9Q.f:Ldev/nuker/pyro/f0d;
        //  1765: getstatic       dev/nuker/pyro/fc.1:I
        //  1768: ifeq            1776
        //  1771: ldc             1994892658
        //  1773: goto            1778
        //  1776: ldc             427646327
        //  1778: ldc             -340107513
        //  1780: ixor           
        //  1781: lookupswitch {
        //          -1654785419: 3353
        //          -217897087: 1776
        //          default: 1808
        //        }
        //  1808: aload_0        
        //  1809: new             Ldev/nuker/pyro/f0d;
        //  1812: dup            
        //  1813: ldc             "y"
        //  1815: ldc             "Y"
        //  1817: aconst_null    
        //  1818: dconst_0       
        //  1819: dconst_0       
        //  1820: aload_0        
        //  1821: getfield        dev/nuker/pyro/f9Q.1:D
        //  1824: dconst_0       
        //  1825: bipush          64
        //  1827: aconst_null    
        //  1828: invokespecial   dev/nuker/pyro/f0d.<init>:(Ljava/lang/String;Ljava/lang/String;Ljava/lang/String;DDDDILkotlin/jvm/internal/DefaultConstructorMarker;)V
        //  1831: getstatic       dev/nuker/pyro/fc.c:I
        //  1834: ifge            1842
        //  1837: ldc             1957468706
        //  1839: goto            1844
        //  1842: ldc             1713675348
        //  1844: ldc             -1795471004
        //  1846: ixor           
        //  1847: lookupswitch {
        //          -531115194: 1842
        //          -220211920: 1872
        //          default: 3379
        //        }
        //  1872: putfield        dev/nuker/pyro/f9Q.g:Ldev/nuker/pyro/f0d;
        //  1875: aload_0        
        //  1876: new             Ldev/nuker/pyro/f0d;
        //  1879: dup            
        //  1880: ldc             "z"
        //  1882: ldc             "Z"
        //  1884: aconst_null    
        //  1885: dconst_0       
        //  1886: dconst_0       
        //  1887: getstatic       dev/nuker/pyro/fc.1:I
        //  1890: ifeq            1898
        //  1893: ldc             -456243784
        //  1895: goto            1900
        //  1898: ldc             945903629
        //  1900: ldc             -122537598
        //  1902: ixor           
        //  1903: lookupswitch {
        //          477920314: 3369
        //          1608485822: 1898
        //          default: 1928
        //        }
        //  1928: aload_0        
        //  1929: getstatic       dev/nuker/pyro/fc.1:I
        //  1932: ifeq            1940
        //  1935: ldc             -1984754467
        //  1937: goto            1942
        //  1940: ldc             523156209
        //  1942: ldc             -1516612762
        //  1944: ixor           
        //  1945: lookupswitch {
        //          -1162548841: 1972
        //          740908987: 1940
        //          default: 3437
        //        }
        //  1972: getfield        dev/nuker/pyro/f9Q.1:D
        //  1975: dconst_0       
        //  1976: bipush          64
        //  1978: aconst_null    
        //  1979: invokespecial   dev/nuker/pyro/f0d.<init>:(Ljava/lang/String;Ljava/lang/String;Ljava/lang/String;DDDDILkotlin/jvm/internal/DefaultConstructorMarker;)V
        //  1982: putfield        dev/nuker/pyro/f9Q.h:Ldev/nuker/pyro/f0d;
        //  1985: getstatic       dev/nuker/pyro/fc.c:I
        //  1988: ifge            1996
        //  1991: ldc             -459879668
        //  1993: goto            1998
        //  1996: ldc             2036476098
        //  1998: ldc             311603469
        //  2000: ixor           
        //  2001: lookupswitch {
        //          -167478783: 3409
        //          231245081: 1996
        //          default: 2028
        //        }
        //  2028: aload_0        
        //  2029: new             Ldev/nuker/pyro/f0k;
        //  2032: dup            
        //  2033: new             Ldev/nuker/pyro/f0e;
        //  2036: dup            
        //  2037: ldc             "\u2267\u1492\u8b6a\ub3d7\uc951\uec6d\ub22a\ue74a"
        //  2039: getstatic       dev/nuker/pyro/fc.0:I
        //  2042: ifeq            2050
        //  2045: ldc             1045416931
        //  2047: goto            2052
        //  2050: ldc             2107201640
        //  2052: ldc             -806934527
        //  2054: ixor           
        //  2055: lookupswitch {
        //          -1283014858: 2050
        //          -240589854: 3371
        //          default: 2080
        //        }
        //  2080: invokestatic    invokestatic   !!! ERROR
        //  2083: ldc             "\u2247\u1492\u8b6a\ub3d7\uc951\uec6d\ub22a\ue74a"
        //  2085: invokestatic    invokestatic   !!! ERROR
        //  2088: aconst_null    
        //  2089: getstatic       dev/nuker/pyro/fc.c:I
        //  2092: ifge            2100
        //  2095: ldc             308211138
        //  2097: goto            2102
        //  2100: ldc             -1238628150
        //  2102: ldc             -2024249034
        //  2104: ixor           
        //  2105: lookupswitch {
        //          -1794734860: 3407
        //          1280987393: 2100
        //          default: 2132
        //        }
        //  2132: invokespecial   dev/nuker/pyro/f0e.<init>:(Ljava/lang/String;Ljava/lang/String;Ljava/lang/String;)V
        //  2135: checkcast       Ldev/nuker/pyro/f0n;
        //  2138: iconst_3       
        //  2139: anewarray       Ldev/nuker/pyro/f0n;
        //  2142: dup            
        //  2143: iconst_0       
        //  2144: new             Ldev/nuker/pyro/f0k;
        //  2147: dup            
        //  2148: new             Ldev/nuker/pyro/f0e;
        //  2151: dup            
        //  2152: ldc_w           "\u227e\u1481\u8b62\ub3d7\uc94a\uec60\ub225\ue75a\ud96d"
        //  2155: invokestatic    invokestatic   !!! ERROR
        //  2158: ldc_w           "\u225e\u1481\u8b62\ub3d7\uc94a\uec60\ub225\ue75a\ud961\ue925\ua6a2"
        //  2161: getstatic       dev/nuker/pyro/fc.1:I
        //  2164: ifeq            2173
        //  2167: ldc_w           976336363
        //  2170: goto            2176
        //  2173: ldc_w           1103556964
        //  2176: ldc_w           1494183464
        //  2179: ixor           
        //  2180: lookupswitch {
        //          415866700: 2208
        //          1665063875: 2173
        //          default: 3397
        //        }
        //  2208: invokestatic    invokestatic   !!! ERROR
        //  2211: aconst_null    
        //  2212: invokespecial   dev/nuker/pyro/f0e.<init>:(Ljava/lang/String;Ljava/lang/String;Ljava/lang/String;)V
        //  2215: checkcast       Ldev/nuker/pyro/f0n;
        //  2218: iconst_3       
        //  2219: anewarray       Ldev/nuker/pyro/f0n;
        //  2222: dup            
        //  2223: iconst_0       
        //  2224: aload_0        
        //  2225: getfield        dev/nuker/pyro/f9Q.c:Ldev/nuker/pyro/f0d;
        //  2228: checkcast       Ldev/nuker/pyro/f0n;
        //  2231: aastore        
        //  2232: dup            
        //  2233: iconst_1       
        //  2234: aload_0        
        //  2235: getfield        dev/nuker/pyro/f9Q.0:Ldev/nuker/pyro/f0d;
        //  2238: checkcast       Ldev/nuker/pyro/f0n;
        //  2241: aastore        
        //  2242: dup            
        //  2243: iconst_2       
        //  2244: aload_0        
        //  2245: getstatic       dev/nuker/pyro/fc.c:I
        //  2248: ifge            2257
        //  2251: ldc_w           -413153287
        //  2254: goto            2260
        //  2257: ldc_w           -599556995
        //  2260: ldc_w           982066340
        //  2263: ixor           
        //  2264: lookupswitch {
        //          -1054183785: 2257
        //          -573119651: 3449
        //          default: 2292
        //        }
        //  2292: getfield        dev/nuker/pyro/f9Q.1:Ldev/nuker/pyro/f0d;
        //  2295: checkcast       Ldev/nuker/pyro/f0n;
        //  2298: aastore        
        //  2299: invokespecial   dev/nuker/pyro/f0k.<init>:(Ldev/nuker/pyro/f0n;[Ldev/nuker/pyro/f0n;)V
        //  2302: checkcast       Ldev/nuker/pyro/f0n;
        //  2305: aastore        
        //  2306: dup            
        //  2307: iconst_1       
        //  2308: new             Ldev/nuker/pyro/f0k;
        //  2311: dup            
        //  2312: new             Ldev/nuker/pyro/f0e;
        //  2315: dup            
        //  2316: ldc_w           "\u2279\u1490\u8b62\ub3d5\uc95c"
        //  2319: invokestatic    invokestatic   !!! ERROR
        //  2322: ldc_w           "\u2259\u1490\u8b62\ub3d5\uc95c"
        //  2325: invokestatic    invokestatic   !!! ERROR
        //  2328: aconst_null    
        //  2329: invokespecial   dev/nuker/pyro/f0e.<init>:(Ljava/lang/String;Ljava/lang/String;Ljava/lang/String;)V
        //  2332: checkcast       Ldev/nuker/pyro/f0n;
        //  2335: iconst_3       
        //  2336: anewarray       Ldev/nuker/pyro/f0n;
        //  2339: dup            
        //  2340: iconst_0       
        //  2341: getstatic       dev/nuker/pyro/fc.1:I
        //  2344: ifeq            2353
        //  2347: ldc_w           -945440140
        //  2350: goto            2356
        //  2353: ldc_w           -29603566
        //  2356: ldc_w           -1033523356
        //  2359: ixor           
        //  2360: lookupswitch {
        //          96474384: 2353
        //          1012524662: 2388
        //          default: 3425
        //        }
        //  2388: aload_0        
        //  2389: getfield        dev/nuker/pyro/f9Q.2:Ldev/nuker/pyro/f0d;
        //  2392: checkcast       Ldev/nuker/pyro/f0n;
        //  2395: aastore        
        //  2396: dup            
        //  2397: iconst_1       
        //  2398: aload_0        
        //  2399: getstatic       dev/nuker/pyro/fc.0:I
        //  2402: ifeq            2411
        //  2405: ldc_w           -27028273
        //  2408: goto            2414
        //  2411: ldc_w           -614728314
        //  2414: ldc_w           223641211
        //  2417: ixor           
        //  2418: lookupswitch {
        //          -214439244: 3377
        //          1558857553: 2411
        //          default: 2444
        //        }
        //  2444: getfield        dev/nuker/pyro/f9Q.3:Ldev/nuker/pyro/f0d;
        //  2447: checkcast       Ldev/nuker/pyro/f0n;
        //  2450: aastore        
        //  2451: dup            
        //  2452: iconst_2       
        //  2453: aload_0        
        //  2454: getfield        dev/nuker/pyro/f9Q.4:Ldev/nuker/pyro/f0d;
        //  2457: checkcast       Ldev/nuker/pyro/f0n;
        //  2460: aastore        
        //  2461: invokespecial   dev/nuker/pyro/f0k.<init>:(Ldev/nuker/pyro/f0n;[Ldev/nuker/pyro/f0n;)V
        //  2464: checkcast       Ldev/nuker/pyro/f0n;
        //  2467: aastore        
        //  2468: dup            
        //  2469: iconst_2       
        //  2470: new             Ldev/nuker/pyro/f0k;
        //  2473: dup            
        //  2474: new             Ldev/nuker/pyro/f0e;
        //  2477: dup            
        //  2478: ldc_w           "\u2278\u149c\u8b77\ub3d8\uc94d\uec65\ub22b\ue740"
        //  2481: invokestatic    invokestatic   !!! ERROR
        //  2484: ldc_w           "\u2258\u149c\u8b77\ub3d8\uc94d\uec65\ub22b\ue740"
        //  2487: invokestatic    invokestatic   !!! ERROR
        //  2490: aconst_null    
        //  2491: invokespecial   dev/nuker/pyro/f0e.<init>:(Ljava/lang/String;Ljava/lang/String;Ljava/lang/String;)V
        //  2494: checkcast       Ldev/nuker/pyro/f0n;
        //  2497: iconst_3       
        //  2498: anewarray       Ldev/nuker/pyro/f0n;
        //  2501: dup            
        //  2502: iconst_0       
        //  2503: getstatic       dev/nuker/pyro/fc.c:I
        //  2506: ifge            2515
        //  2509: ldc_w           76894277
        //  2512: goto            2518
        //  2515: ldc_w           1771243950
        //  2518: ldc_w           1192070490
        //  2521: ixor           
        //  2522: lookupswitch {
        //          419928126: 2515
        //          1134091551: 3439
        //          default: 2548
        //        }
        //  2548: aload_0        
        //  2549: getfield        dev/nuker/pyro/f9Q.5:Ldev/nuker/pyro/f0d;
        //  2552: checkcast       Ldev/nuker/pyro/f0n;
        //  2555: aastore        
        //  2556: dup            
        //  2557: iconst_1       
        //  2558: aload_0        
        //  2559: getfield        dev/nuker/pyro/f9Q.6:Ldev/nuker/pyro/f0d;
        //  2562: checkcast       Ldev/nuker/pyro/f0n;
        //  2565: aastore        
        //  2566: dup            
        //  2567: iconst_2       
        //  2568: getstatic       dev/nuker/pyro/fc.c:I
        //  2571: ifge            2580
        //  2574: ldc_w           93282204
        //  2577: goto            2583
        //  2580: ldc_w           46065051
        //  2583: ldc_w           -1632620237
        //  2586: ixor           
        //  2587: lookupswitch {
        //          -1690341713: 3431
        //          -723364382: 2580
        //          default: 2612
        //        }
        //  2612: aload_0        
        //  2613: getstatic       dev/nuker/pyro/fc.1:I
        //  2616: ifeq            2625
        //  2619: ldc_w           -314327755
        //  2622: goto            2628
        //  2625: ldc_w           2083108003
        //  2628: ldc_w           -2087120917
        //  2631: ixor           
        //  2632: lookupswitch {
        //          -2070893334: 2625
        //          1859826398: 3387
        //          default: 2660
        //        }
        //  2660: getfield        dev/nuker/pyro/f9Q.7:Ldev/nuker/pyro/f0d;
        //  2663: checkcast       Ldev/nuker/pyro/f0n;
        //  2666: aastore        
        //  2667: invokespecial   dev/nuker/pyro/f0k.<init>:(Ldev/nuker/pyro/f0n;[Ldev/nuker/pyro/f0n;)V
        //  2670: checkcast       Ldev/nuker/pyro/f0n;
        //  2673: aastore        
        //  2674: invokespecial   dev/nuker/pyro/f0k.<init>:(Ldev/nuker/pyro/f0n;[Ldev/nuker/pyro/f0n;)V
        //  2677: checkcast       Ldev/nuker/pyro/f0n;
        //  2680: invokevirtual   dev/nuker/pyro/f9Q.c:(Ldev/nuker/pyro/f0n;)Ldev/nuker/pyro/f0n;
        //  2683: pop            
        //  2684: aload_0        
        //  2685: new             Ldev/nuker/pyro/f0k;
        //  2688: dup            
        //  2689: new             Ldev/nuker/pyro/f0e;
        //  2692: dup            
        //  2693: ldc_w           "\u2265\u1495\u8b65\ub3d1\uc958\uec62\ub220"
        //  2696: getstatic       dev/nuker/pyro/fc.1:I
        //  2699: ifeq            2708
        //  2702: ldc_w           163723373
        //  2705: goto            2711
        //  2708: ldc_w           926312786
        //  2711: ldc_w           1741655461
        //  2714: ixor           
        //  2715: lookupswitch {
        //          1358554359: 2740
        //          1846392264: 2708
        //          default: 3445
        //        }
        //  2740: invokestatic    invokestatic   !!! ERROR
        //  2743: ldc_w           "\u2245\u1495\u8b65\ub3d1\uc958\uec62\ub220"
        //  2746: invokestatic    invokestatic   !!! ERROR
        //  2749: aconst_null    
        //  2750: invokespecial   dev/nuker/pyro/f0e.<init>:(Ljava/lang/String;Ljava/lang/String;Ljava/lang/String;)V
        //  2753: checkcast       Ldev/nuker/pyro/f0n;
        //  2756: iconst_3       
        //  2757: anewarray       Ldev/nuker/pyro/f0n;
        //  2760: dup            
        //  2761: iconst_0       
        //  2762: new             Ldev/nuker/pyro/f0k;
        //  2765: dup            
        //  2766: new             Ldev/nuker/pyro/f0e;
        //  2769: dup            
        //  2770: ldc_w           "\u227e\u1481\u8b62\ub3d7\uc94a\uec60\ub225\ue75a\ud96d"
        //  2773: getstatic       dev/nuker/pyro/fc.1:I
        //  2776: ifeq            2785
        //  2779: ldc_w           -193533601
        //  2782: goto            2788
        //  2785: ldc_w           -150543588
        //  2788: ldc_w           -1285288887
        //  2791: ixor           
        //  2792: lookupswitch {
        //          1147334485: 2820
        //          1192420630: 2785
        //          default: 3357
        //        }
        //  2820: invokestatic    invokestatic   !!! ERROR
        //  2823: ldc_w           "\u225e\u1481\u8b62\ub3d7\uc94a\uec60\ub225\ue75a\ud961\ue925\ua6a2"
        //  2826: invokestatic    invokestatic   !!! ERROR
        //  2829: aconst_null    
        //  2830: getstatic       dev/nuker/pyro/fc.1:I
        //  2833: ifeq            2842
        //  2836: ldc_w           -1484606167
        //  2839: goto            2845
        //  2842: ldc_w           274481092
        //  2845: ldc_w           -473649933
        //  2848: ixor           
        //  2849: lookupswitch {
        //          -208104649: 2876
        //          1145444826: 2842
        //          default: 3417
        //        }
        //  2876: invokespecial   dev/nuker/pyro/f0e.<init>:(Ljava/lang/String;Ljava/lang/String;Ljava/lang/String;)V
        //  2879: checkcast       Ldev/nuker/pyro/f0n;
        //  2882: iconst_3       
        //  2883: anewarray       Ldev/nuker/pyro/f0n;
        //  2886: dup            
        //  2887: iconst_0       
        //  2888: aload_0        
        //  2889: getfield        dev/nuker/pyro/f9Q.8:Ldev/nuker/pyro/f0d;
        //  2892: checkcast       Ldev/nuker/pyro/f0n;
        //  2895: aastore        
        //  2896: dup            
        //  2897: iconst_1       
        //  2898: aload_0        
        //  2899: getfield        dev/nuker/pyro/f9Q.9:Ldev/nuker/pyro/f0d;
        //  2902: checkcast       Ldev/nuker/pyro/f0n;
        //  2905: aastore        
        //  2906: dup            
        //  2907: iconst_2       
        //  2908: aload_0        
        //  2909: getfield        dev/nuker/pyro/f9Q.a:Ldev/nuker/pyro/f0d;
        //  2912: checkcast       Ldev/nuker/pyro/f0n;
        //  2915: aastore        
        //  2916: invokespecial   dev/nuker/pyro/f0k.<init>:(Ldev/nuker/pyro/f0n;[Ldev/nuker/pyro/f0n;)V
        //  2919: checkcast       Ldev/nuker/pyro/f0n;
        //  2922: aastore        
        //  2923: dup            
        //  2924: iconst_1       
        //  2925: new             Ldev/nuker/pyro/f0k;
        //  2928: dup            
        //  2929: new             Ldev/nuker/pyro/f0e;
        //  2932: dup            
        //  2933: ldc_w           "\u2279\u1490\u8b62\ub3d5\uc95c"
        //  2936: invokestatic    invokestatic   !!! ERROR
        //  2939: ldc_w           "\u2259\u1490\u8b62\ub3d5\uc95c"
        //  2942: invokestatic    invokestatic   !!! ERROR
        //  2945: aconst_null    
        //  2946: invokespecial   dev/nuker/pyro/f0e.<init>:(Ljava/lang/String;Ljava/lang/String;Ljava/lang/String;)V
        //  2949: checkcast       Ldev/nuker/pyro/f0n;
        //  2952: iconst_3       
        //  2953: anewarray       Ldev/nuker/pyro/f0n;
        //  2956: dup            
        //  2957: iconst_0       
        //  2958: aload_0        
        //  2959: getfield        dev/nuker/pyro/f9Q.b:Ldev/nuker/pyro/f0d;
        //  2962: checkcast       Ldev/nuker/pyro/f0n;
        //  2965: aastore        
        //  2966: dup            
        //  2967: iconst_1       
        //  2968: getstatic       dev/nuker/pyro/fc.c:I
        //  2971: ifge            2980
        //  2974: ldc_w           -349260557
        //  2977: goto            2983
        //  2980: ldc_w           986475420
        //  2983: ldc_w           2072566031
        //  2986: ixor           
        //  2987: lookupswitch {
        //          -1868141060: 2980
        //          1095021203: 3012
        //          default: 3419
        //        }
        //  3012: aload_0        
        //  3013: getstatic       dev/nuker/pyro/fc.0:I
        //  3016: ifeq            3025
        //  3019: ldc_w           327623274
        //  3022: goto            3028
        //  3025: ldc_w           1199012393
        //  3028: ldc_w           -376788368
        //  3031: ixor           
        //  3032: lookupswitch {
        //          -1359097767: 3060
        //          -99776486: 3025
        //          default: 3443
        //        }
        //  3060: getfield        dev/nuker/pyro/f9Q.d:Ldev/nuker/pyro/f0d;
        //  3063: checkcast       Ldev/nuker/pyro/f0n;
        //  3066: aastore        
        //  3067: dup            
        //  3068: iconst_2       
        //  3069: aload_0        
        //  3070: getstatic       dev/nuker/pyro/fc.c:I
        //  3073: ifge            3082
        //  3076: ldc_w           2104152089
        //  3079: goto            3085
        //  3082: ldc_w           1133840921
        //  3085: ldc_w           -1443662896
        //  3088: ixor           
        //  3089: lookupswitch {
        //          -728128567: 3373
        //          825934222: 3082
        //          default: 3116
        //        }
        //  3116: getfield        dev/nuker/pyro/f9Q.e:Ldev/nuker/pyro/f0d;
        //  3119: checkcast       Ldev/nuker/pyro/f0n;
        //  3122: aastore        
        //  3123: getstatic       dev/nuker/pyro/fc.0:I
        //  3126: ifeq            3135
        //  3129: ldc_w           -1867141998
        //  3132: goto            3138
        //  3135: ldc_w           -1453439605
        //  3138: ldc_w           208706793
        //  3141: ixor           
        //  3142: lookupswitch {
        //          -1810573919: 3135
        //          -1664798597: 3351
        //          default: 3168
        //        }
        //  3168: invokespecial   dev/nuker/pyro/f0k.<init>:(Ldev/nuker/pyro/f0n;[Ldev/nuker/pyro/f0n;)V
        //  3171: checkcast       Ldev/nuker/pyro/f0n;
        //  3174: aastore        
        //  3175: dup            
        //  3176: iconst_2       
        //  3177: new             Ldev/nuker/pyro/f0k;
        //  3180: dup            
        //  3181: new             Ldev/nuker/pyro/f0e;
        //  3184: dup            
        //  3185: ldc_w           "\u2278\u149c\u8b77\ub3d8\uc94d\uec65\ub22b\ue740"
        //  3188: invokestatic    invokestatic   !!! ERROR
        //  3191: ldc_w           "\u2258\u149c\u8b77\ub3d8\uc94d\uec65\ub22b\ue740"
        //  3194: invokestatic    invokestatic   !!! ERROR
        //  3197: aconst_null    
        //  3198: invokespecial   dev/nuker/pyro/f0e.<init>:(Ljava/lang/String;Ljava/lang/String;Ljava/lang/String;)V
        //  3201: checkcast       Ldev/nuker/pyro/f0n;
        //  3204: iconst_3       
        //  3205: anewarray       Ldev/nuker/pyro/f0n;
        //  3208: dup            
        //  3209: iconst_0       
        //  3210: aload_0        
        //  3211: getfield        dev/nuker/pyro/f9Q.f:Ldev/nuker/pyro/f0d;
        //  3214: checkcast       Ldev/nuker/pyro/f0n;
        //  3217: aastore        
        //  3218: dup            
        //  3219: iconst_1       
        //  3220: aload_0        
        //  3221: getstatic       dev/nuker/pyro/fc.c:I
        //  3224: ifge            3233
        //  3227: ldc_w           989192899
        //  3230: goto            3236
        //  3233: ldc_w           -1265126970
        //  3236: ldc_w           -1532311672
        //  3239: ixor           
        //  3240: lookupswitch {
        //          -1637931701: 3399
        //          -395687242: 3233
        //          default: 3268
        //        }
        //  3268: getfield        dev/nuker/pyro/f9Q.g:Ldev/nuker/pyro/f0d;
        //  3271: checkcast       Ldev/nuker/pyro/f0n;
        //  3274: aastore        
        //  3275: dup            
        //  3276: iconst_2       
        //  3277: aload_0        
        //  3278: getfield        dev/nuker/pyro/f9Q.h:Ldev/nuker/pyro/f0d;
        //  3281: checkcast       Ldev/nuker/pyro/f0n;
        //  3284: aastore        
        //  3285: invokespecial   dev/nuker/pyro/f0k.<init>:(Ldev/nuker/pyro/f0n;[Ldev/nuker/pyro/f0n;)V
        //  3288: checkcast       Ldev/nuker/pyro/f0n;
        //  3291: aastore        
        //  3292: getstatic       dev/nuker/pyro/fc.1:I
        //  3295: ifeq            3304
        //  3298: ldc_w           1854760025
        //  3301: goto            3307
        //  3304: ldc_w           -1879845498
        //  3307: ldc_w           -1683916908
        //  3310: ixor           
        //  3311: lookupswitch {
        //          -181660723: 3405
        //          1543303590: 3304
        //          default: 3336
        //        }
        //  3336: invokespecial   dev/nuker/pyro/f0k.<init>:(Ldev/nuker/pyro/f0n;[Ldev/nuker/pyro/f0n;)V
        //  3339: checkcast       Ldev/nuker/pyro/f0n;
        //  3342: invokevirtual   dev/nuker/pyro/f9Q.c:(Ldev/nuker/pyro/f0n;)Ldev/nuker/pyro/f0n;
        //  3345: pop            
        //  3346: return         
        //  3347: aconst_null    
        //  3348: athrow         
        //  3349: aconst_null    
        //  3350: athrow         
        //  3351: aconst_null    
        //  3352: athrow         
        //  3353: aconst_null    
        //  3354: athrow         
        //  3355: aconst_null    
        //  3356: athrow         
        //  3357: aconst_null    
        //  3358: athrow         
        //  3359: aconst_null    
        //  3360: athrow         
        //  3361: aconst_null    
        //  3362: athrow         
        //  3363: aconst_null    
        //  3364: athrow         
        //  3365: aconst_null    
        //  3366: athrow         
        //  3367: aconst_null    
        //  3368: athrow         
        //  3369: aconst_null    
        //  3370: athrow         
        //  3371: aconst_null    
        //  3372: athrow         
        //  3373: aconst_null    
        //  3374: athrow         
        //  3375: aconst_null    
        //  3376: athrow         
        //  3377: aconst_null    
        //  3378: athrow         
        //  3379: aconst_null    
        //  3380: athrow         
        //  3381: aconst_null    
        //  3382: athrow         
        //  3383: aconst_null    
        //  3384: athrow         
        //  3385: aconst_null    
        //  3386: athrow         
        //  3387: aconst_null    
        //  3388: athrow         
        //  3389: aconst_null    
        //  3390: athrow         
        //  3391: aconst_null    
        //  3392: athrow         
        //  3393: aconst_null    
        //  3394: athrow         
        //  3395: aconst_null    
        //  3396: athrow         
        //  3397: aconst_null    
        //  3398: athrow         
        //  3399: aconst_null    
        //  3400: athrow         
        //  3401: aconst_null    
        //  3402: athrow         
        //  3403: aconst_null    
        //  3404: athrow         
        //  3405: aconst_null    
        //  3406: athrow         
        //  3407: aconst_null    
        //  3408: athrow         
        //  3409: aconst_null    
        //  3410: athrow         
        //  3411: aconst_null    
        //  3412: athrow         
        //  3413: aconst_null    
        //  3414: athrow         
        //  3415: aconst_null    
        //  3416: athrow         
        //  3417: aconst_null    
        //  3418: athrow         
        //  3419: aconst_null    
        //  3420: athrow         
        //  3421: aconst_null    
        //  3422: athrow         
        //  3423: aconst_null    
        //  3424: athrow         
        //  3425: aconst_null    
        //  3426: athrow         
        //  3427: aconst_null    
        //  3428: athrow         
        //  3429: aconst_null    
        //  3430: athrow         
        //  3431: aconst_null    
        //  3432: athrow         
        //  3433: aconst_null    
        //  3434: athrow         
        //  3435: aconst_null    
        //  3436: athrow         
        //  3437: aconst_null    
        //  3438: athrow         
        //  3439: aconst_null    
        //  3440: athrow         
        //  3441: aconst_null    
        //  3442: athrow         
        //  3443: aconst_null    
        //  3444: athrow         
        //  3445: aconst_null    
        //  3446: athrow         
        //  3447: aconst_null    
        //  3448: athrow         
        //  3449: aconst_null    
        //  3450: athrow         
        //  3451: aconst_null    
        //  3452: athrow         
        //    StackMapTable: 00 D4 FF 00 16 00 01 06 00 02 06 03 FF 00 01 00 01 06 00 03 06 03 01 FF 00 1B 00 01 06 00 02 06 03 FF 00 11 00 01 06 00 02 06 03 FF 00 01 00 01 06 00 03 06 03 01 FF 00 1B 00 01 06 00 02 06 03 FF 00 10 00 01 06 00 02 06 07 01 4A FF 00 01 00 01 06 00 03 06 07 01 4A 01 FF 00 1C 00 01 06 00 02 06 07 01 4A FF 00 14 00 01 06 00 04 06 07 01 4A 07 01 4A 07 01 4A FF 00 01 00 01 06 00 05 06 07 01 4A 07 01 4A 07 01 4A 01 FF 00 1C 00 01 06 00 04 06 07 01 4A 07 01 4A 07 01 4A FF 00 1B 00 01 07 00 03 00 02 07 00 03 03 FF 00 01 00 01 07 00 03 00 03 07 00 03 03 01 FF 00 1D 00 01 07 00 03 00 02 07 00 03 03 FF 00 25 00 01 07 00 03 00 09 07 00 03 08 01 0F 08 01 0F 07 01 4A 07 01 4A 05 03 03 07 00 03 FF 00 01 00 01 07 00 03 00 0A 07 00 03 08 01 0F 08 01 0F 07 01 4A 07 01 4A 05 03 03 07 00 03 01 FF 00 1B 00 01 07 00 03 00 09 07 00 03 08 01 0F 08 01 0F 07 01 4A 07 01 4A 05 03 03 07 00 03 FF 00 22 00 01 07 00 03 00 07 07 00 03 08 01 56 08 01 56 07 01 4A 07 01 4A 05 03 FF 00 01 00 01 07 00 03 00 08 07 00 03 08 01 56 08 01 56 07 01 4A 07 01 4A 05 03 01 FF 00 1E 00 01 07 00 03 00 07 07 00 03 08 01 56 08 01 56 07 01 4A 07 01 4A 05 03 FF 00 10 00 01 07 00 03 00 09 07 00 03 08 01 56 08 01 56 07 01 4A 07 01 4A 05 03 03 07 00 03 FF 00 01 00 01 07 00 03 00 0A 07 00 03 08 01 56 08 01 56 07 01 4A 07 01 4A 05 03 03 07 00 03 01 FF 00 1C 00 01 07 00 03 00 09 07 00 03 08 01 56 08 01 56 07 01 4A 07 01 4A 05 03 03 07 00 03 FF 00 22 00 01 07 00 03 00 07 07 00 03 08 01 CA 08 01 CA 07 01 4A 07 01 4A 05 03 FF 00 01 00 01 07 00 03 00 08 07 00 03 08 01 CA 08 01 CA 07 01 4A 07 01 4A 05 03 01 FF 00 1E 00 01 07 00 03 00 07 07 00 03 08 01 CA 08 01 CA 07 01 4A 07 01 4A 05 03 FF 00 0B 00 01 07 00 03 00 08 07 00 03 08 01 CA 08 01 CA 07 01 4A 07 01 4A 05 03 07 00 03 FF 00 01 00 01 07 00 03 00 09 07 00 03 08 01 CA 08 01 CA 07 01 4A 07 01 4A 05 03 07 00 03 01 FF 00 1D 00 01 07 00 03 00 08 07 00 03 08 01 CA 08 01 CA 07 01 4A 07 01 4A 05 03 07 00 03 FF 00 0F 00 01 07 00 03 00 09 07 00 03 08 01 CA 08 01 CA 07 01 4A 07 01 4A 05 03 03 07 00 03 FF 00 01 00 01 07 00 03 00 0A 07 00 03 08 01 CA 08 01 CA 07 01 4A 07 01 4A 05 03 03 07 00 03 01 FF 00 1D 00 01 07 00 03 00 09 07 00 03 08 01 CA 08 01 CA 07 01 4A 07 01 4A 05 03 03 07 00 03 FF 00 11 00 01 07 00 03 00 0C 07 00 03 08 01 CA 08 01 CA 07 01 4A 07 01 4A 05 03 03 03 03 01 05 FF 00 01 00 01 07 00 03 00 0D 07 00 03 08 01 CA 08 01 CA 07 01 4A 07 01 4A 05 03 03 03 03 01 05 01 FF 00 1B 00 01 07 00 03 00 0C 07 00 03 08 01 CA 08 01 CA 07 01 4A 07 01 4A 05 03 03 03 03 01 05 FF 00 27 00 01 07 00 03 00 02 07 00 03 07 00 64 FF 00 01 00 01 07 00 03 00 03 07 00 03 07 00 64 01 FF 00 1D 00 01 07 00 03 00 02 07 00 03 07 00 64 FF 00 34 00 01 07 00 03 00 09 07 00 03 08 02 F2 08 02 F2 07 01 4A 07 01 4A 05 03 03 07 00 03 FF 00 01 00 01 07 00 03 00 0A 07 00 03 08 02 F2 08 02 F2 07 01 4A 07 01 4A 05 03 03 07 00 03 01 FF 00 1C 00 01 07 00 03 00 09 07 00 03 08 02 F2 08 02 F2 07 01 4A 07 01 4A 05 03 03 07 00 03 FF 00 11 00 01 07 00 03 00 0C 07 00 03 08 02 F2 08 02 F2 07 01 4A 07 01 4A 05 03 03 03 03 01 05 FF 00 01 00 01 07 00 03 00 0D 07 00 03 08 02 F2 08 02 F2 07 01 4A 07 01 4A 05 03 03 03 03 01 05 01 FF 00 1B 00 01 07 00 03 00 0C 07 00 03 08 02 F2 08 02 F2 07 01 4A 07 01 4A 05 03 03 03 03 01 05 10 41 01 1C 24 41 01 1C 3E 41 01 1E FF 00 15 00 01 07 00 03 00 07 07 00 03 08 04 2D 08 04 2D 07 01 4A 07 01 4A 05 03 FF 00 01 00 01 07 00 03 00 08 07 00 03 08 04 2D 08 04 2D 07 01 4A 07 01 4A 05 03 01 FF 00 1B 00 01 07 00 03 00 07 07 00 03 08 04 2D 08 04 2D 07 01 4A 07 01 4A 05 03 FF 00 1A 00 01 07 00 03 00 02 07 00 03 07 00 64 FF 00 01 00 01 07 00 03 00 03 07 00 03 07 00 64 01 FF 00 1E 00 01 07 00 03 00 02 07 00 03 07 00 64 FF 00 1E 00 01 07 00 03 00 09 07 00 03 08 04 A0 08 04 A0 07 01 4A 07 01 4A 05 03 03 07 00 03 FF 00 01 00 01 07 00 03 00 0A 07 00 03 08 04 A0 08 04 A0 07 01 4A 07 01 4A 05 03 03 07 00 03 01 FF 00 1E 00 01 07 00 03 00 09 07 00 03 08 04 A0 08 04 A0 07 01 4A 07 01 4A 05 03 03 07 00 03 FF 00 14 00 01 07 00 03 00 02 07 00 03 07 00 64 FF 00 01 00 01 07 00 03 00 03 07 00 03 07 00 64 01 FF 00 1C 00 01 07 00 03 00 02 07 00 03 07 00 64 FF 00 1D 00 01 07 00 03 00 08 07 00 03 08 05 14 08 05 14 07 01 4A 07 01 4A 05 03 03 FF 00 01 00 01 07 00 03 00 09 07 00 03 08 05 14 08 05 14 07 01 4A 07 01 4A 05 03 03 01 FF 00 1B 00 01 07 00 03 00 08 07 00 03 08 05 14 08 05 14 07 01 4A 07 01 4A 05 03 03 FF 00 0B 00 01 07 00 03 00 09 07 00 03 08 05 14 08 05 14 07 01 4A 07 01 4A 05 03 03 07 00 03 FF 00 01 00 01 07 00 03 00 0A 07 00 03 08 05 14 08 05 14 07 01 4A 07 01 4A 05 03 03 07 00 03 01 FF 00 1D 00 01 07 00 03 00 09 07 00 03 08 05 14 08 05 14 07 01 4A 07 01 4A 05 03 03 07 00 03 FF 00 11 00 01 07 00 03 00 0C 07 00 03 08 05 14 08 05 14 07 01 4A 07 01 4A 05 03 03 03 03 01 05 FF 00 01 00 01 07 00 03 00 0D 07 00 03 08 05 14 08 05 14 07 01 4A 07 01 4A 05 03 03 03 03 01 05 01 FF 00 1B 00 01 07 00 03 00 0C 07 00 03 08 05 14 08 05 14 07 01 4A 07 01 4A 05 03 03 03 03 01 05 10 41 01 1C FF 00 21 00 01 07 00 03 00 02 07 00 03 07 00 64 FF 00 01 00 01 07 00 03 00 03 07 00 03 07 00 64 01 FF 00 1B 00 01 07 00 03 00 02 07 00 03 07 00 64 0D 41 01 1B 24 41 01 1C FF 00 31 00 01 07 00 03 00 09 07 00 03 08 06 A3 08 06 A3 07 01 4A 07 01 4A 05 03 03 07 00 03 FF 00 01 00 01 07 00 03 00 0A 07 00 03 08 06 A3 08 06 A3 07 01 4A 07 01 4A 05 03 03 07 00 03 01 FF 00 1B 00 01 07 00 03 00 09 07 00 03 08 06 A3 08 06 A3 07 01 4A 07 01 4A 05 03 03 07 00 03 17 41 01 1D FF 00 21 00 01 07 00 03 00 02 07 00 03 07 00 64 FF 00 01 00 01 07 00 03 00 03 07 00 03 07 00 64 01 FF 00 1B 00 01 07 00 03 00 02 07 00 03 07 00 64 FF 00 19 00 01 07 00 03 00 08 07 00 03 08 07 54 08 07 54 07 01 4A 07 01 4A 05 03 03 FF 00 01 00 01 07 00 03 00 09 07 00 03 08 07 54 08 07 54 07 01 4A 07 01 4A 05 03 03 01 FF 00 1B 00 01 07 00 03 00 08 07 00 03 08 07 54 08 07 54 07 01 4A 07 01 4A 05 03 03 FF 00 0B 00 01 07 00 03 00 09 07 00 03 08 07 54 08 07 54 07 01 4A 07 01 4A 05 03 03 07 00 03 FF 00 01 00 01 07 00 03 00 0A 07 00 03 08 07 54 08 07 54 07 01 4A 07 01 4A 05 03 03 07 00 03 01 FF 00 1D 00 01 07 00 03 00 09 07 00 03 08 07 54 08 07 54 07 01 4A 07 01 4A 05 03 03 07 00 03 17 41 01 1D FF 00 15 00 01 07 00 03 00 06 07 00 03 08 07 ED 08 07 ED 08 07 F1 08 07 F1 07 01 4A FF 00 01 00 01 07 00 03 00 07 07 00 03 08 07 ED 08 07 ED 08 07 F1 08 07 F1 07 01 4A 01 FF 00 1B 00 01 07 00 03 00 06 07 00 03 08 07 ED 08 07 ED 08 07 F1 08 07 F1 07 01 4A FF 00 13 00 01 07 00 03 00 08 07 00 03 08 07 ED 08 07 ED 08 07 F1 08 07 F1 07 01 4A 07 01 4A 05 FF 00 01 00 01 07 00 03 00 09 07 00 03 08 07 ED 08 07 ED 08 07 F1 08 07 F1 07 01 4A 07 01 4A 05 01 FF 00 1D 00 01 07 00 03 00 08 07 00 03 08 07 ED 08 07 ED 08 07 F1 08 07 F1 07 01 4A 07 01 4A 05 FF 00 28 00 01 07 00 03 00 0D 07 00 03 08 07 ED 08 07 ED 07 01 02 07 01 4C 07 01 4C 01 08 08 60 08 08 60 08 08 64 08 08 64 07 01 4A 07 01 4A FF 00 02 00 01 07 00 03 00 0E 07 00 03 08 07 ED 08 07 ED 07 01 02 07 01 4C 07 01 4C 01 08 08 60 08 08 60 08 08 64 08 08 64 07 01 4A 07 01 4A 01 FF 00 1F 00 01 07 00 03 00 0D 07 00 03 08 07 ED 08 07 ED 07 01 02 07 01 4C 07 01 4C 01 08 08 60 08 08 60 08 08 64 08 08 64 07 01 4A 07 01 4A FF 00 30 00 01 07 00 03 00 0E 07 00 03 08 07 ED 08 07 ED 07 01 02 07 01 4C 07 01 4C 01 08 08 60 08 08 60 07 01 02 07 01 4C 07 01 4C 01 07 00 03 FF 00 02 00 01 07 00 03 00 0F 07 00 03 08 07 ED 08 07 ED 07 01 02 07 01 4C 07 01 4C 01 08 08 60 08 08 60 07 01 02 07 01 4C 07 01 4C 01 07 00 03 01 FF 00 1F 00 01 07 00 03 00 0E 07 00 03 08 07 ED 08 07 ED 07 01 02 07 01 4C 07 01 4C 01 08 08 60 08 08 60 07 01 02 07 01 4C 07 01 4C 01 07 00 03 FF 00 3C 00 01 07 00 03 00 0D 07 00 03 08 07 ED 08 07 ED 07 01 02 07 01 4C 07 01 4C 01 08 09 04 08 09 04 07 01 02 07 01 4C 07 01 4C 01 FF 00 02 00 01 07 00 03 00 0E 07 00 03 08 07 ED 08 07 ED 07 01 02 07 01 4C 07 01 4C 01 08 09 04 08 09 04 07 01 02 07 01 4C 07 01 4C 01 01 FF 00 1F 00 01 07 00 03 00 0D 07 00 03 08 07 ED 08 07 ED 07 01 02 07 01 4C 07 01 4C 01 08 09 04 08 09 04 07 01 02 07 01 4C 07 01 4C 01 FF 00 16 00 01 07 00 03 00 0E 07 00 03 08 07 ED 08 07 ED 07 01 02 07 01 4C 07 01 4C 01 08 09 04 08 09 04 07 01 02 07 01 4C 07 01 4C 01 07 00 03 FF 00 02 00 01 07 00 03 00 0F 07 00 03 08 07 ED 08 07 ED 07 01 02 07 01 4C 07 01 4C 01 08 09 04 08 09 04 07 01 02 07 01 4C 07 01 4C 01 07 00 03 01 FF 00 1D 00 01 07 00 03 00 0E 07 00 03 08 07 ED 08 07 ED 07 01 02 07 01 4C 07 01 4C 01 08 09 04 08 09 04 07 01 02 07 01 4C 07 01 4C 01 07 00 03 FF 00 46 00 01 07 00 03 00 0D 07 00 03 08 07 ED 08 07 ED 07 01 02 07 01 4C 07 01 4C 01 08 09 A6 08 09 A6 07 01 02 07 01 4C 07 01 4C 01 FF 00 02 00 01 07 00 03 00 0E 07 00 03 08 07 ED 08 07 ED 07 01 02 07 01 4C 07 01 4C 01 08 09 A6 08 09 A6 07 01 02 07 01 4C 07 01 4C 01 01 FF 00 1D 00 01 07 00 03 00 0D 07 00 03 08 07 ED 08 07 ED 07 01 02 07 01 4C 07 01 4C 01 08 09 A6 08 09 A6 07 01 02 07 01 4C 07 01 4C 01 FF 00 1F 00 01 07 00 03 00 0D 07 00 03 08 07 ED 08 07 ED 07 01 02 07 01 4C 07 01 4C 01 08 09 A6 08 09 A6 07 01 02 07 01 4C 07 01 4C 01 FF 00 02 00 01 07 00 03 00 0E 07 00 03 08 07 ED 08 07 ED 07 01 02 07 01 4C 07 01 4C 01 08 09 A6 08 09 A6 07 01 02 07 01 4C 07 01 4C 01 01 FF 00 1C 00 01 07 00 03 00 0D 07 00 03 08 07 ED 08 07 ED 07 01 02 07 01 4C 07 01 4C 01 08 09 A6 08 09 A6 07 01 02 07 01 4C 07 01 4C 01 FF 00 0C 00 01 07 00 03 00 0E 07 00 03 08 07 ED 08 07 ED 07 01 02 07 01 4C 07 01 4C 01 08 09 A6 08 09 A6 07 01 02 07 01 4C 07 01 4C 01 07 00 03 FF 00 02 00 01 07 00 03 00 0F 07 00 03 08 07 ED 08 07 ED 07 01 02 07 01 4C 07 01 4C 01 08 09 A6 08 09 A6 07 01 02 07 01 4C 07 01 4C 01 07 00 03 01 FF 00 1F 00 01 07 00 03 00 0E 07 00 03 08 07 ED 08 07 ED 07 01 02 07 01 4C 07 01 4C 01 08 09 A6 08 09 A6 07 01 02 07 01 4C 07 01 4C 01 07 00 03 FF 00 2F 00 01 07 00 03 00 06 07 00 03 08 0A 7D 08 0A 7D 08 0A 81 08 0A 81 07 01 4A FF 00 02 00 01 07 00 03 00 07 07 00 03 08 0A 7D 08 0A 7D 08 0A 81 08 0A 81 07 01 4A 01 FF 00 1C 00 01 07 00 03 00 06 07 00 03 08 0A 7D 08 0A 7D 08 0A 81 08 0A 81 07 01 4A FF 00 2C 00 01 07 00 03 00 0C 07 00 03 08 0A 7D 08 0A 7D 07 01 02 07 01 4C 07 01 4C 01 08 0A CA 08 0A CA 08 0A CE 08 0A CE 07 01 4A FF 00 02 00 01 07 00 03 00 0D 07 00 03 08 0A 7D 08 0A 7D 07 01 02 07 01 4C 07 01 4C 01 08 0A CA 08 0A CA 08 0A CE 08 0A CE 07 01 4A 01 FF 00 1F 00 01 07 00 03 00 0C 07 00 03 08 0A 7D 08 0A 7D 07 01 02 07 01 4C 07 01 4C 01 08 0A CA 08 0A CA 08 0A CE 08 0A CE 07 01 4A FF 00 15 00 01 07 00 03 00 0E 07 00 03 08 0A 7D 08 0A 7D 07 01 02 07 01 4C 07 01 4C 01 08 0A CA 08 0A CA 08 0A CE 08 0A CE 07 01 4A 07 01 4A 05 FF 00 02 00 01 07 00 03 00 0F 07 00 03 08 0A 7D 08 0A 7D 07 01 02 07 01 4C 07 01 4C 01 08 0A CA 08 0A CA 08 0A CE 08 0A CE 07 01 4A 07 01 4A 05 01 FF 00 1E 00 01 07 00 03 00 0E 07 00 03 08 0A 7D 08 0A 7D 07 01 02 07 01 4C 07 01 4C 01 08 0A CA 08 0A CA 08 0A CE 08 0A CE 07 01 4A 07 01 4A 05 FF 00 67 00 01 07 00 03 00 0D 07 00 03 08 0A 7D 08 0A 7D 07 01 02 07 01 4C 07 01 4C 01 08 0B 6D 08 0B 6D 07 01 02 07 01 4C 07 01 4C 01 FF 00 02 00 01 07 00 03 00 0E 07 00 03 08 0A 7D 08 0A 7D 07 01 02 07 01 4C 07 01 4C 01 08 0B 6D 08 0B 6D 07 01 02 07 01 4C 07 01 4C 01 01 FF 00 1C 00 01 07 00 03 00 0D 07 00 03 08 0A 7D 08 0A 7D 07 01 02 07 01 4C 07 01 4C 01 08 0B 6D 08 0B 6D 07 01 02 07 01 4C 07 01 4C 01 FF 00 0C 00 01 07 00 03 00 0E 07 00 03 08 0A 7D 08 0A 7D 07 01 02 07 01 4C 07 01 4C 01 08 0B 6D 08 0B 6D 07 01 02 07 01 4C 07 01 4C 01 07 00 03 FF 00 02 00 01 07 00 03 00 0F 07 00 03 08 0A 7D 08 0A 7D 07 01 02 07 01 4C 07 01 4C 01 08 0B 6D 08 0B 6D 07 01 02 07 01 4C 07 01 4C 01 07 00 03 01 FF 00 1F 00 01 07 00 03 00 0E 07 00 03 08 0A 7D 08 0A 7D 07 01 02 07 01 4C 07 01 4C 01 08 0B 6D 08 0B 6D 07 01 02 07 01 4C 07 01 4C 01 07 00 03 FF 00 15 00 01 07 00 03 00 0E 07 00 03 08 0A 7D 08 0A 7D 07 01 02 07 01 4C 07 01 4C 01 08 0B 6D 08 0B 6D 07 01 02 07 01 4C 07 01 4C 01 07 00 03 FF 00 02 00 01 07 00 03 00 0F 07 00 03 08 0A 7D 08 0A 7D 07 01 02 07 01 4C 07 01 4C 01 08 0B 6D 08 0B 6D 07 01 02 07 01 4C 07 01 4C 01 07 00 03 01 FF 00 1E 00 01 07 00 03 00 0E 07 00 03 08 0A 7D 08 0A 7D 07 01 02 07 01 4C 07 01 4C 01 08 0B 6D 08 0B 6D 07 01 02 07 01 4C 07 01 4C 01 07 00 03 FF 00 12 00 01 07 00 03 00 0B 07 00 03 08 0A 7D 08 0A 7D 07 01 02 07 01 4C 07 01 4C 01 08 0B 6D 08 0B 6D 07 01 02 07 01 4C FF 00 02 00 01 07 00 03 00 0C 07 00 03 08 0A 7D 08 0A 7D 07 01 02 07 01 4C 07 01 4C 01 08 0B 6D 08 0B 6D 07 01 02 07 01 4C 01 FF 00 1D 00 01 07 00 03 00 0B 07 00 03 08 0A 7D 08 0A 7D 07 01 02 07 01 4C 07 01 4C 01 08 0B 6D 08 0B 6D 07 01 02 07 01 4C FF 00 40 00 01 07 00 03 00 0E 07 00 03 08 0A 7D 08 0A 7D 07 01 02 07 01 4C 07 01 4C 01 08 0C 69 08 0C 69 07 01 02 07 01 4C 07 01 4C 01 07 00 03 FF 00 02 00 01 07 00 03 00 0F 07 00 03 08 0A 7D 08 0A 7D 07 01 02 07 01 4C 07 01 4C 01 08 0C 69 08 0C 69 07 01 02 07 01 4C 07 01 4C 01 07 00 03 01 FF 00 1F 00 01 07 00 03 00 0E 07 00 03 08 0A 7D 08 0A 7D 07 01 02 07 01 4C 07 01 4C 01 08 0C 69 08 0C 69 07 01 02 07 01 4C 07 01 4C 01 07 00 03 FF 00 23 00 01 07 00 03 00 05 07 00 03 08 0A 7D 08 0A 7D 07 01 02 07 01 4C FF 00 02 00 01 07 00 03 00 06 07 00 03 08 0A 7D 08 0A 7D 07 01 02 07 01 4C 01 FF 00 1C 00 01 07 00 03 00 05 07 00 03 08 0A 7D 08 0A 7D 07 01 02 07 01 4C FF 00 0A 00 01 07 00 03 00 02 07 00 03 07 00 64 FF 00 01 00 01 07 00 03 00 09 07 00 03 08 02 F2 08 02 F2 07 01 4A 07 01 4A 05 03 03 07 00 03 FF 00 01 00 01 07 00 03 00 0B 07 00 03 08 0A 7D 08 0A 7D 07 01 02 07 01 4C 07 01 4C 01 08 0B 6D 08 0B 6D 07 01 02 07 01 4C 01 FF 00 01 00 01 07 00 03 00 07 07 00 03 08 01 CA 08 01 CA 07 01 4A 07 01 4A 05 03 FF 00 01 00 01 07 00 03 00 0C 07 00 03 08 0A 7D 08 0A 7D 07 01 02 07 01 4C 07 01 4C 01 08 0A CA 08 0A CA 08 0A CE 08 0A CE 07 01 4A 01 FF 00 01 00 01 06 00 02 06 03 FF 00 01 00 01 07 00 03 00 09 07 00 03 08 01 0F 08 01 0F 07 01 4A 07 01 4A 05 03 03 07 00 03 FF 00 01 00 01 07 00 03 00 08 07 00 03 08 05 14 08 05 14 07 01 4A 07 01 4A 05 03 03 FF 00 01 00 01 07 00 03 00 08 07 00 03 08 01 CA 08 01 CA 07 01 4A 07 01 4A 05 03 07 00 03 FF 00 01 00 01 07 00 03 00 08 07 00 03 08 07 54 08 07 54 07 01 4A 07 01 4A 05 03 03 FF 00 01 00 01 07 00 03 00 06 07 00 03 08 07 ED 08 07 ED 08 07 F1 08 07 F1 07 01 4A FF 00 01 00 01 07 00 03 00 0E 07 00 03 08 0A 7D 08 0A 7D 07 01 02 07 01 4C 07 01 4C 01 08 0B 6D 08 0B 6D 07 01 02 07 01 4C 07 01 4C 01 07 00 03 01 FF 00 01 00 01 07 00 03 00 0E 07 00 03 08 07 ED 08 07 ED 07 01 02 07 01 4C 07 01 4C 01 08 09 04 08 09 04 07 01 02 07 01 4C 07 01 4C 01 07 00 03 FF 00 01 00 01 07 00 03 00 02 07 00 03 07 00 64 01 01 01 FF 00 01 00 01 07 00 03 00 0E 07 00 03 08 07 ED 08 07 ED 07 01 02 07 01 4C 07 01 4C 01 08 09 A6 08 09 A6 07 01 02 07 01 4C 07 01 4C 01 07 00 03 FF 00 01 00 01 06 00 02 06 03 FF 00 01 00 01 07 00 03 00 09 07 00 03 08 01 56 08 01 56 07 01 4A 07 01 4A 05 03 03 07 00 03 FF 00 01 00 01 07 00 03 00 02 07 00 03 07 00 64 01 FF 00 01 00 01 07 00 03 00 0D 07 00 03 08 07 ED 08 07 ED 07 01 02 07 01 4C 07 01 4C 01 08 08 60 08 08 60 08 08 64 08 08 64 07 01 4A 07 01 4A FF 00 01 00 01 07 00 03 00 0E 07 00 03 08 0A 7D 08 0A 7D 07 01 02 07 01 4C 07 01 4C 01 08 0C 69 08 0C 69 07 01 02 07 01 4C 07 01 4C 01 07 00 03 FF 00 01 00 01 07 00 03 00 09 07 00 03 08 04 A0 08 04 A0 07 01 4A 07 01 4A 05 03 03 07 00 03 FF 00 01 00 01 07 00 03 00 09 07 00 03 08 06 A3 08 06 A3 07 01 4A 07 01 4A 05 03 03 07 00 03 FF 00 01 00 01 07 00 03 00 05 07 00 03 08 0A 7D 08 0A 7D 07 01 02 07 01 4C FF 00 01 00 01 07 00 03 00 08 07 00 03 08 07 ED 08 07 ED 08 07 F1 08 07 F1 07 01 4A 07 01 4A 05 01 FF 00 01 00 01 07 00 03 00 02 07 00 03 03 FF 00 01 00 01 07 00 03 00 0C 07 00 03 08 05 14 08 05 14 07 01 4A 07 01 4A 05 03 03 03 03 01 05 FF 00 01 00 01 07 00 03 00 02 07 00 03 07 00 64 FF 00 01 00 01 07 00 03 00 0E 07 00 03 08 0A 7D 08 0A 7D 07 01 02 07 01 4C 07 01 4C 01 08 0A CA 08 0A CA 08 0A CE 08 0A CE 07 01 4A 07 01 4A 05 FF 00 01 00 01 07 00 03 00 0D 07 00 03 08 0A 7D 08 0A 7D 07 01 02 07 01 4C 07 01 4C 01 08 0B 6D 08 0B 6D 07 01 02 07 01 4C 07 01 4C 01 FF 00 01 00 01 06 00 02 06 07 01 4A FF 00 01 00 01 07 00 03 00 02 07 00 03 07 00 64 FF 00 01 00 01 07 00 03 00 0D 07 00 03 08 07 ED 08 07 ED 07 01 02 07 01 4C 07 01 4C 01 08 09 04 08 09 04 07 01 02 07 01 4C 07 01 4C 01 FF 00 01 00 01 06 00 04 06 07 01 4A 07 01 4A 07 01 4A FF 00 01 00 01 07 00 03 00 0C 07 00 03 08 01 CA 08 01 CA 07 01 4A 07 01 4A 05 03 03 03 03 01 05 FF 00 01 00 01 07 00 03 00 0D 07 00 03 08 07 ED 08 07 ED 07 01 02 07 01 4C 07 01 4C 01 08 09 A6 08 09 A6 07 01 02 07 01 4C 07 01 4C 01 FF 00 01 00 01 07 00 03 00 09 07 00 03 08 01 CA 08 01 CA 07 01 4A 07 01 4A 05 03 03 07 00 03 FF 00 01 00 01 07 00 03 00 07 07 00 03 08 01 56 08 01 56 07 01 4A 07 01 4A 05 03 FF 00 01 00 01 07 00 03 00 09 07 00 03 08 07 54 08 07 54 07 01 4A 07 01 4A 05 03 03 07 00 03 FF 00 01 00 01 07 00 03 00 0D 07 00 03 08 07 ED 08 07 ED 07 01 02 07 01 4C 07 01 4C 01 08 09 A6 08 09 A6 07 01 02 07 01 4C 07 01 4C 01 FF 00 01 00 01 07 00 03 00 07 07 00 03 08 04 2D 08 04 2D 07 01 4A 07 01 4A 05 03 FF 00 01 00 01 07 00 03 00 0E 07 00 03 08 0A 7D 08 0A 7D 07 01 02 07 01 4C 07 01 4C 01 08 0B 6D 08 0B 6D 07 01 02 07 01 4C 07 01 4C 01 07 00 03 FF 00 01 00 01 07 00 03 00 06 07 00 03 08 0A 7D 08 0A 7D 08 0A 81 08 0A 81 07 01 4A FF 00 01 00 01 07 00 03 00 09 07 00 03 08 05 14 08 05 14 07 01 4A 07 01 4A 05 03 03 07 00 03 FF 00 01 00 01 07 00 03 00 0E 07 00 03 08 07 ED 08 07 ED 07 01 02 07 01 4C 07 01 4C 01 08 08 60 08 08 60 07 01 02 07 01 4C 07 01 4C 01 07 00 03 FF 00 01 00 01 07 00 03 00 0C 07 00 03 08 02 F2 08 02 F2 07 01 4A 07 01 4A 05 03 03 03 03 01 05
        // 
        // The error that occurred was:
        // 
        // java.lang.IllegalStateException: Invalid BootstrapMethods attribute entry: 21 additional arguments required for method a.a, but only 0 specified.
        //     at com.strobel.assembler.ir.Error.invalidBootstrapMethodEntry(Error.java:244)
        //     at com.strobel.assembler.ir.MetadataReader.readAttributeCore(MetadataReader.java:280)
        //     at com.strobel.assembler.metadata.ClassFileReader.readAttributeCore(ClassFileReader.java:261)
        //     at com.strobel.assembler.ir.MetadataReader.inflateAttributes(MetadataReader.java:439)
        //     at com.strobel.assembler.metadata.ClassFileReader.visitAttributes(ClassFileReader.java:1134)
        //     at com.strobel.assembler.metadata.ClassFileReader.readClass(ClassFileReader.java:439)
        //     at com.strobel.assembler.metadata.ClassFileReader.readClass(ClassFileReader.java:377)
        //     at com.strobel.assembler.metadata.MetadataSystem.resolveType(MetadataSystem.java:129)
        //     at com.strobel.decompiler.NoRetryMetadataSystem.resolveType(DecompilerDriver.java:476)
        //     at com.strobel.assembler.metadata.MetadataSystem.resolveCore(MetadataSystem.java:81)
        //     at com.strobel.assembler.metadata.MetadataResolver.resolve(MetadataResolver.java:104)
        //     at com.strobel.assembler.metadata.CoreMetadataFactory$UnresolvedType.resolve(CoreMetadataFactory.java:616)
        //     at com.strobel.assembler.metadata.MetadataResolver.resolve(MetadataResolver.java:128)
        //     at com.strobel.assembler.metadata.CoreMetadataFactory$UnresolvedType.resolve(CoreMetadataFactory.java:626)
        //     at com.strobel.assembler.metadata.MethodReference.resolve(MethodReference.java:177)
        //     at com.strobel.decompiler.ast.TypeAnalysis.inferCall(TypeAnalysis.java:2438)
        //     at com.strobel.decompiler.ast.TypeAnalysis.doInferTypeForExpression(TypeAnalysis.java:1029)
        //     at com.strobel.decompiler.ast.TypeAnalysis.inferTypeForExpression(TypeAnalysis.java:803)
        //     at com.strobel.decompiler.ast.TypeAnalysis.inferTypeForExpression(TypeAnalysis.java:770)
        //     at com.strobel.decompiler.ast.TypeAnalysis.doInferTypeForExpression(TypeAnalysis.java:881)
        //     at com.strobel.decompiler.ast.TypeAnalysis.inferTypeForExpression(TypeAnalysis.java:803)
        //     at com.strobel.decompiler.ast.TypeAnalysis.runInference(TypeAnalysis.java:672)
        //     at com.strobel.decompiler.ast.TypeAnalysis.runInference(TypeAnalysis.java:655)
        //     at com.strobel.decompiler.ast.TypeAnalysis.runInference(TypeAnalysis.java:365)
        //     at com.strobel.decompiler.ast.TypeAnalysis.run(TypeAnalysis.java:96)
        //     at com.strobel.decompiler.ast.AstOptimizer.optimize(AstOptimizer.java:109)
        //     at com.strobel.decompiler.ast.AstOptimizer.optimize(AstOptimizer.java:42)
        //     at com.strobel.decompiler.languages.java.ast.AstMethodBodyBuilder.createMethodBody(AstMethodBodyBuilder.java:214)
        //     at com.strobel.decompiler.languages.java.ast.AstMethodBodyBuilder.createMethodBody(AstMethodBodyBuilder.java:99)
        //     at com.strobel.decompiler.languages.java.ast.AstBuilder.createMethodBody(AstBuilder.java:782)
        //     at com.strobel.decompiler.languages.java.ast.AstBuilder.createConstructor(AstBuilder.java:713)
        //     at com.strobel.decompiler.languages.java.ast.AstBuilder.addTypeMembers(AstBuilder.java:549)
        //     at com.strobel.decompiler.languages.java.ast.AstBuilder.createTypeCore(AstBuilder.java:519)
        //     at com.strobel.decompiler.languages.java.ast.AstBuilder.createTypeNoCache(AstBuilder.java:161)
        //     at com.strobel.decompiler.languages.java.ast.AstBuilder.createType(AstBuilder.java:150)
        //     at com.strobel.decompiler.languages.java.ast.AstBuilder.addType(AstBuilder.java:125)
        //     at com.strobel.decompiler.languages.java.JavaLanguage.buildAst(JavaLanguage.java:71)
        //     at com.strobel.decompiler.languages.java.JavaLanguage.decompileType(JavaLanguage.java:59)
        //     at com.strobel.decompiler.DecompilerDriver.decompileType(DecompilerDriver.java:330)
        //     at com.strobel.decompiler.DecompilerDriver.decompileJar(DecompilerDriver.java:251)
        //     at com.strobel.decompiler.DecompilerDriver.main(DecompilerDriver.java:126)
        // 
        throw new IllegalStateException("An error occurred while decompiling this method.");
    }
    
    @NotNull
    public f0d h() {
        return fbS.gi(this, 606912234);
    }
    
    @NotNull
    public f0d i() {
        return fbS.gp(this, 186917239);
    }
    
    @NotNull
    public f0d 9() {
        return fbS.g1(this, 696665630);
    }
    
    @NotNull
    public f0d c() {
        return fbS.ga(this, 17605530);
    }
    
    @NotNull
    public f0d e() {
        return fbS.gn(this, 497534102);
    }
    
    @NotNull
    public f0d j() {
        return fbS.gp(this, 186917224);
    }
    
    @NotNull
    public f0d b() {
        return fbS.g3(this, 227758774);
    }
    
    @NotNull
    public f0d g() {
        return fbS.fS(this, 697717845);
    }
    
    @NotNull
    public f0d 5() {
        return fbS.fW(this, 1198714604);
    }
    
    public void c(@NotNull final EnumHandSide p0) {
        // 
        // This method could not be decompiled.
        // 
        // Original Bytecode:
        // 
        //     3: dup            
        //     4: ifnull          1719
        //     7: athrow         
        //     8: aconst_null    
        //     9: getstatic       dev/nuker/pyro/fc.1:I
        //    12: ifgt            1711
        //    15: pop            
        //    16: aconst_null    
        //    17: goto            1703
        //    20: nop            
        //    21: nop            
        //    22: nop            
        //    23: athrow         
        //    24: aload_1        
        //    25: pop            
        //    26: aload_1        
        //    27: getstatic       net/minecraft/util/EnumHandSide.RIGHT:Lnet/minecraft/util/EnumHandSide;
        //    30: if_acmpne       865
        //    33: getstatic       dev/nuker/pyro/fc.1:I
        //    36: ifeq            45
        //    39: ldc_w           1670437976
        //    42: goto            48
        //    45: ldc_w           -261290633
        //    48: ldc_w           313438557
        //    51: ixor           
        //    52: lookupswitch {
        //          -2139068738: 45
        //          1899916549: 1658
        //          default: 80
        //        }
        //    80: aload_0        
        //    81: getfield        dev/nuker/pyro/f9Q.c:Ldev/nuker/pyro/f0d;
        //    84: goto            88
        //    87: athrow         
        //    88: invokevirtual   dev/nuker/pyro/f0d.3:()Ljava/lang/Object;
        //    91: goto            95
        //    94: athrow         
        //    95: checkcast       Ljava/lang/Number;
        //    98: goto            102
        //   101: athrow         
        //   102: invokevirtual   java/lang/Number.doubleValue:()D
        //   105: goto            109
        //   108: athrow         
        //   109: aload_0        
        //   110: getfield        dev/nuker/pyro/f9Q.0:Ldev/nuker/pyro/f0d;
        //   113: goto            117
        //   116: athrow         
        //   117: invokevirtual   dev/nuker/pyro/f0d.3:()Ljava/lang/Object;
        //   120: goto            124
        //   123: athrow         
        //   124: checkcast       Ljava/lang/Number;
        //   127: goto            131
        //   130: athrow         
        //   131: invokevirtual   java/lang/Number.doubleValue:()D
        //   134: goto            138
        //   137: athrow         
        //   138: aload_0        
        //   139: getstatic       dev/nuker/pyro/fc.1:I
        //   142: ifeq            151
        //   145: ldc_w           233904991
        //   148: goto            154
        //   151: ldc_w           1849131791
        //   154: ldc_w           -706994623
        //   157: ixor           
        //   158: lookupswitch {
        //          -1142186674: 184
        //          -668138210: 151
        //          default: 1692
        //        }
        //   184: getfield        dev/nuker/pyro/f9Q.1:Ldev/nuker/pyro/f0d;
        //   187: getstatic       dev/nuker/pyro/fc.1:I
        //   190: ifeq            199
        //   193: ldc_w           -1417282507
        //   196: goto            202
        //   199: ldc_w           -1522090144
        //   202: ldc_w           1996278780
        //   205: ixor           
        //   206: lookupswitch {
        //          -780914635: 199
        //          -579258423: 1676
        //          default: 232
        //        }
        //   232: goto            236
        //   235: athrow         
        //   236: invokevirtual   dev/nuker/pyro/f0d.3:()Ljava/lang/Object;
        //   239: goto            243
        //   242: athrow         
        //   243: checkcast       Ljava/lang/Number;
        //   246: goto            250
        //   249: athrow         
        //   250: invokevirtual   java/lang/Number.doubleValue:()D
        //   253: goto            257
        //   256: athrow         
        //   257: goto            261
        //   260: athrow         
        //   261: invokestatic    net/minecraft/client/renderer/GlStateManager.func_179137_b:(DDD)V
        //   264: goto            268
        //   267: athrow         
        //   268: getstatic       dev/nuker/pyro/fc.0:I
        //   271: ifeq            280
        //   274: ldc_w           60896451
        //   277: goto            283
        //   280: ldc_w           1415339377
        //   283: ldc_w           728929211
        //   286: ixor           
        //   287: lookupswitch {
        //          684959608: 1684
        //          1689136162: 280
        //          default: 312
        //        }
        //   312: aload_0        
        //   313: getfield        dev/nuker/pyro/f9Q.2:Ldev/nuker/pyro/f0d;
        //   316: goto            320
        //   319: athrow         
        //   320: invokevirtual   dev/nuker/pyro/f0d.3:()Ljava/lang/Object;
        //   323: goto            327
        //   326: athrow         
        //   327: checkcast       Ljava/lang/Number;
        //   330: goto            334
        //   333: athrow         
        //   334: invokevirtual   java/lang/Number.doubleValue:()D
        //   337: goto            341
        //   340: athrow         
        //   341: aload_0        
        //   342: getfield        dev/nuker/pyro/f9Q.2:Ldev/nuker/pyro/f0d;
        //   345: getstatic       dev/nuker/pyro/fc.0:I
        //   348: ifeq            357
        //   351: ldc_w           -1789174487
        //   354: goto            360
        //   357: ldc_w           313885656
        //   360: ldc_w           388383091
        //   363: ixor           
        //   364: lookupswitch {
        //          -2105729958: 357
        //          93569707: 392
        //          default: 1678
        //        }
        //   392: goto            396
        //   395: athrow         
        //   396: invokevirtual   dev/nuker/pyro/f0d.3:()Ljava/lang/Object;
        //   399: goto            403
        //   402: athrow         
        //   403: checkcast       Ljava/lang/Number;
        //   406: getstatic       dev/nuker/pyro/fc.c:I
        //   409: ifge            418
        //   412: ldc_w           -929052862
        //   415: goto            421
        //   418: ldc_w           1177442186
        //   421: ldc_w           2055136066
        //   424: ixor           
        //   425: lookupswitch {
        //          -1477240395: 418
        //          -1293868032: 1662
        //          default: 452
        //        }
        //   452: goto            456
        //   455: athrow         
        //   456: invokevirtual   java/lang/Number.doubleValue:()D
        //   459: goto            463
        //   462: athrow         
        //   463: aload_0        
        //   464: getfield        dev/nuker/pyro/f9Q.4:Ldev/nuker/pyro/f0d;
        //   467: getstatic       dev/nuker/pyro/fc.0:I
        //   470: ifeq            479
        //   473: ldc_w           1144020856
        //   476: goto            482
        //   479: ldc_w           1190124230
        //   482: ldc_w           1656435068
        //   485: ixor           
        //   486: lookupswitch {
        //          609545146: 512
        //          646671876: 479
        //          default: 1670
        //        }
        //   512: goto            516
        //   515: athrow         
        //   516: invokevirtual   dev/nuker/pyro/f0d.3:()Ljava/lang/Object;
        //   519: goto            523
        //   522: athrow         
        //   523: checkcast       Ljava/lang/Number;
        //   526: getstatic       dev/nuker/pyro/fc.c:I
        //   529: ifge            538
        //   532: ldc_w           1054060609
        //   535: goto            541
        //   538: ldc_w           -1796261583
        //   541: ldc_w           134521593
        //   544: ixor           
        //   545: lookupswitch {
        //          920064696: 1682
        //          1858205714: 538
        //          default: 572
        //        }
        //   572: goto            576
        //   575: athrow         
        //   576: invokevirtual   java/lang/Number.doubleValue:()D
        //   579: goto            583
        //   582: athrow         
        //   583: getstatic       dev/nuker/pyro/fc.1:I
        //   586: ifeq            595
        //   589: ldc_w           -170054506
        //   592: goto            598
        //   595: ldc_w           876012147
        //   598: ldc_w           -1005174665
        //   601: ixor           
        //   602: lookupswitch {
        //          -266296828: 628
        //          835415265: 595
        //          default: 1680
        //        }
        //   628: goto            632
        //   631: athrow         
        //   632: invokestatic    net/minecraft/client/renderer/GlStateManager.func_179139_a:(DDD)V
        //   635: goto            639
        //   638: athrow         
        //   639: getstatic       dev/nuker/pyro/fc.0:I
        //   642: ifeq            651
        //   645: ldc_w           -983002287
        //   648: goto            654
        //   651: ldc_w           1792837880
        //   654: ldc_w           -1434711158
        //   657: ixor           
        //   658: lookupswitch {
        //          1405811818: 651
        //          1863620827: 1654
        //          default: 684
        //        }
        //   684: aload_0        
        //   685: getfield        dev/nuker/pyro/f9Q.5:Ldev/nuker/pyro/f0d;
        //   688: goto            692
        //   691: athrow         
        //   692: invokevirtual   dev/nuker/pyro/f0d.3:()Ljava/lang/Object;
        //   695: goto            699
        //   698: athrow         
        //   699: checkcast       Ljava/lang/Number;
        //   702: goto            706
        //   705: athrow         
        //   706: invokevirtual   java/lang/Number.doubleValue:()D
        //   709: goto            713
        //   712: athrow         
        //   713: d2f            
        //   714: fconst_1       
        //   715: fconst_0       
        //   716: fconst_0       
        //   717: goto            721
        //   720: athrow         
        //   721: invokestatic    net/minecraft/client/renderer/GlStateManager.func_179114_b:(FFFF)V
        //   724: goto            728
        //   727: athrow         
        //   728: aload_0        
        //   729: getfield        dev/nuker/pyro/f9Q.6:Ldev/nuker/pyro/f0d;
        //   732: goto            736
        //   735: athrow         
        //   736: invokevirtual   dev/nuker/pyro/f0d.3:()Ljava/lang/Object;
        //   739: goto            743
        //   742: athrow         
        //   743: checkcast       Ljava/lang/Number;
        //   746: getstatic       dev/nuker/pyro/fc.1:I
        //   749: ifeq            758
        //   752: ldc_w           1023440414
        //   755: goto            761
        //   758: ldc_w           293798686
        //   761: ldc_w           -1181554245
        //   764: ixor           
        //   765: lookupswitch {
        //          -2070765659: 1664
        //          -1431482988: 758
        //          default: 792
        //        }
        //   792: goto            796
        //   795: athrow         
        //   796: invokevirtual   java/lang/Number.doubleValue:()D
        //   799: goto            803
        //   802: athrow         
        //   803: d2f            
        //   804: fconst_0       
        //   805: fconst_1       
        //   806: fconst_0       
        //   807: goto            811
        //   810: athrow         
        //   811: invokestatic    net/minecraft/client/renderer/GlStateManager.func_179114_b:(FFFF)V
        //   814: goto            818
        //   817: athrow         
        //   818: aload_0        
        //   819: getfield        dev/nuker/pyro/f9Q.7:Ldev/nuker/pyro/f0d;
        //   822: goto            826
        //   825: athrow         
        //   826: invokevirtual   dev/nuker/pyro/f0d.3:()Ljava/lang/Object;
        //   829: goto            833
        //   832: athrow         
        //   833: checkcast       Ljava/lang/Number;
        //   836: goto            840
        //   839: athrow         
        //   840: invokevirtual   java/lang/Number.doubleValue:()D
        //   843: goto            847
        //   846: athrow         
        //   847: d2f            
        //   848: fconst_0       
        //   849: fconst_0       
        //   850: fconst_1       
        //   851: goto            855
        //   854: athrow         
        //   855: invokestatic    net/minecraft/client/renderer/GlStateManager.func_179114_b:(FFFF)V
        //   858: goto            862
        //   861: athrow         
        //   862: goto            1651
        //   865: aload_0        
        //   866: getfield        dev/nuker/pyro/f9Q.8:Ldev/nuker/pyro/f0d;
        //   869: goto            873
        //   872: athrow         
        //   873: invokevirtual   dev/nuker/pyro/f0d.3:()Ljava/lang/Object;
        //   876: goto            880
        //   879: athrow         
        //   880: checkcast       Ljava/lang/Number;
        //   883: goto            887
        //   886: athrow         
        //   887: invokevirtual   java/lang/Number.doubleValue:()D
        //   890: goto            894
        //   893: athrow         
        //   894: aload_0        
        //   895: getstatic       dev/nuker/pyro/fc.c:I
        //   898: ifge            907
        //   901: ldc_w           758363152
        //   904: goto            910
        //   907: ldc_w           -656291200
        //   910: ldc_w           -1898650794
        //   913: ixor           
        //   914: lookupswitch {
        //          -1545119930: 907
        //          1446324694: 940
        //          default: 1686
        //        }
        //   940: getfield        dev/nuker/pyro/f9Q.9:Ldev/nuker/pyro/f0d;
        //   943: getstatic       dev/nuker/pyro/fc.c:I
        //   946: ifge            955
        //   949: ldc_w           -1590169423
        //   952: goto            958
        //   955: ldc_w           35964599
        //   958: ldc_w           200070027
        //   961: ixor           
        //   962: lookupswitch {
        //          -1428479174: 1666
        //          17403864: 955
        //          default: 988
        //        }
        //   988: goto            992
        //   991: athrow         
        //   992: invokevirtual   dev/nuker/pyro/f0d.3:()Ljava/lang/Object;
        //   995: goto            999
        //   998: athrow         
        //   999: checkcast       Ljava/lang/Number;
        //  1002: getstatic       dev/nuker/pyro/fc.0:I
        //  1005: ifeq            1014
        //  1008: ldc_w           -422329451
        //  1011: goto            1017
        //  1014: ldc_w           728036605
        //  1017: ldc_w           -1641480106
        //  1020: ixor           
        //  1021: lookupswitch {
        //          1382970532: 1014
        //          2029700035: 1668
        //          default: 1048
        //        }
        //  1048: goto            1052
        //  1051: athrow         
        //  1052: invokevirtual   java/lang/Number.doubleValue:()D
        //  1055: goto            1059
        //  1058: athrow         
        //  1059: aload_0        
        //  1060: getfield        dev/nuker/pyro/f9Q.a:Ldev/nuker/pyro/f0d;
        //  1063: goto            1067
        //  1066: athrow         
        //  1067: invokevirtual   dev/nuker/pyro/f0d.3:()Ljava/lang/Object;
        //  1070: goto            1074
        //  1073: athrow         
        //  1074: checkcast       Ljava/lang/Number;
        //  1077: getstatic       dev/nuker/pyro/fc.0:I
        //  1080: ifeq            1089
        //  1083: ldc_w           2105055903
        //  1086: goto            1092
        //  1089: ldc_w           472399545
        //  1092: ldc_w           -1921832111
        //  1095: ixor           
        //  1096: lookupswitch {
        //          -1856301592: 1124
        //          -267669042: 1089
        //          default: 1652
        //        }
        //  1124: goto            1128
        //  1127: athrow         
        //  1128: invokevirtual   java/lang/Number.doubleValue:()D
        //  1131: goto            1135
        //  1134: athrow         
        //  1135: goto            1139
        //  1138: athrow         
        //  1139: invokestatic    net/minecraft/client/renderer/GlStateManager.func_179137_b:(DDD)V
        //  1142: goto            1146
        //  1145: athrow         
        //  1146: aload_0        
        //  1147: getstatic       dev/nuker/pyro/fc.0:I
        //  1150: ifeq            1159
        //  1153: ldc_w           2094134642
        //  1156: goto            1162
        //  1159: ldc_w           513054543
        //  1162: ldc_w           831738267
        //  1165: ixor           
        //  1166: lookupswitch {
        //          -371263369: 1159
        //          1296213225: 1674
        //          default: 1192
        //        }
        //  1192: getfield        dev/nuker/pyro/f9Q.b:Ldev/nuker/pyro/f0d;
        //  1195: getstatic       dev/nuker/pyro/fc.c:I
        //  1198: ifge            1207
        //  1201: ldc_w           -1952210262
        //  1204: goto            1210
        //  1207: ldc_w           305668071
        //  1210: ldc_w           -47220742
        //  1213: ixor           
        //  1214: lookupswitch {
        //          -283678691: 1240
        //          1988941136: 1207
        //          default: 1656
        //        }
        //  1240: goto            1244
        //  1243: athrow         
        //  1244: invokevirtual   dev/nuker/pyro/f0d.3:()Ljava/lang/Object;
        //  1247: goto            1251
        //  1250: athrow         
        //  1251: checkcast       Ljava/lang/Number;
        //  1254: goto            1258
        //  1257: athrow         
        //  1258: invokevirtual   java/lang/Number.doubleValue:()D
        //  1261: goto            1265
        //  1264: athrow         
        //  1265: aload_0        
        //  1266: getstatic       dev/nuker/pyro/fc.c:I
        //  1269: ifge            1278
        //  1272: ldc_w           -114073252
        //  1275: goto            1281
        //  1278: ldc_w           -686034087
        //  1281: ldc_w           -826491638
        //  1284: ixor           
        //  1285: lookupswitch {
        //          430394963: 1312
        //          932174934: 1278
        //          default: 1688
        //        }
        //  1312: getfield        dev/nuker/pyro/f9Q.b:Ldev/nuker/pyro/f0d;
        //  1315: goto            1319
        //  1318: athrow         
        //  1319: invokevirtual   dev/nuker/pyro/f0d.3:()Ljava/lang/Object;
        //  1322: goto            1326
        //  1325: athrow         
        //  1326: checkcast       Ljava/lang/Number;
        //  1329: goto            1333
        //  1332: athrow         
        //  1333: invokevirtual   java/lang/Number.doubleValue:()D
        //  1336: goto            1340
        //  1339: athrow         
        //  1340: aload_0        
        //  1341: getfield        dev/nuker/pyro/f9Q.e:Ldev/nuker/pyro/f0d;
        //  1344: goto            1348
        //  1347: athrow         
        //  1348: invokevirtual   dev/nuker/pyro/f0d.3:()Ljava/lang/Object;
        //  1351: goto            1355
        //  1354: athrow         
        //  1355: checkcast       Ljava/lang/Number;
        //  1358: goto            1362
        //  1361: athrow         
        //  1362: invokevirtual   java/lang/Number.doubleValue:()D
        //  1365: goto            1369
        //  1368: athrow         
        //  1369: goto            1373
        //  1372: athrow         
        //  1373: invokestatic    net/minecraft/client/renderer/GlStateManager.func_179139_a:(DDD)V
        //  1376: goto            1380
        //  1379: athrow         
        //  1380: aload_0        
        //  1381: getfield        dev/nuker/pyro/f9Q.f:Ldev/nuker/pyro/f0d;
        //  1384: goto            1388
        //  1387: athrow         
        //  1388: invokevirtual   dev/nuker/pyro/f0d.3:()Ljava/lang/Object;
        //  1391: goto            1395
        //  1394: athrow         
        //  1395: checkcast       Ljava/lang/Number;
        //  1398: goto            1402
        //  1401: athrow         
        //  1402: invokevirtual   java/lang/Number.doubleValue:()D
        //  1405: goto            1409
        //  1408: athrow         
        //  1409: d2f            
        //  1410: fconst_1       
        //  1411: fconst_0       
        //  1412: fconst_0       
        //  1413: goto            1417
        //  1416: athrow         
        //  1417: invokestatic    net/minecraft/client/renderer/GlStateManager.func_179114_b:(FFFF)V
        //  1420: goto            1424
        //  1423: athrow         
        //  1424: aload_0        
        //  1425: getfield        dev/nuker/pyro/f9Q.g:Ldev/nuker/pyro/f0d;
        //  1428: goto            1432
        //  1431: athrow         
        //  1432: invokevirtual   dev/nuker/pyro/f0d.3:()Ljava/lang/Object;
        //  1435: goto            1439
        //  1438: athrow         
        //  1439: checkcast       Ljava/lang/Number;
        //  1442: goto            1446
        //  1445: athrow         
        //  1446: invokevirtual   java/lang/Number.doubleValue:()D
        //  1449: goto            1453
        //  1452: athrow         
        //  1453: d2f            
        //  1454: fconst_0       
        //  1455: fconst_1       
        //  1456: fconst_0       
        //  1457: getstatic       dev/nuker/pyro/fc.0:I
        //  1460: ifeq            1469
        //  1463: ldc_w           -1773783094
        //  1466: goto            1472
        //  1469: ldc_w           -1443066257
        //  1472: ldc_w           1569644420
        //  1475: ixor           
        //  1476: lookupswitch {
        //          -876025778: 1660
        //          -219215112: 1469
        //          default: 1504
        //        }
        //  1504: goto            1508
        //  1507: athrow         
        //  1508: invokestatic    net/minecraft/client/renderer/GlStateManager.func_179114_b:(FFFF)V
        //  1511: goto            1515
        //  1514: athrow         
        //  1515: aload_0        
        //  1516: getfield        dev/nuker/pyro/f9Q.h:Ldev/nuker/pyro/f0d;
        //  1519: getstatic       dev/nuker/pyro/fc.0:I
        //  1522: ifeq            1531
        //  1525: ldc_w           -177820692
        //  1528: goto            1534
        //  1531: ldc_w           -1013423271
        //  1534: ldc_w           -1976574427
        //  1537: ixor           
        //  1538: lookupswitch {
        //          1236778364: 1564
        //          2135520713: 1531
        //          default: 1690
        //        }
        //  1564: goto            1568
        //  1567: athrow         
        //  1568: invokevirtual   dev/nuker/pyro/f0d.3:()Ljava/lang/Object;
        //  1571: goto            1575
        //  1574: athrow         
        //  1575: checkcast       Ljava/lang/Number;
        //  1578: goto            1582
        //  1581: athrow         
        //  1582: invokevirtual   java/lang/Number.doubleValue:()D
        //  1585: goto            1589
        //  1588: athrow         
        //  1589: d2f            
        //  1590: fconst_0       
        //  1591: fconst_0       
        //  1592: fconst_1       
        //  1593: getstatic       dev/nuker/pyro/fc.1:I
        //  1596: ifeq            1605
        //  1599: ldc_w           -1292494411
        //  1602: goto            1608
        //  1605: ldc_w           -1645563928
        //  1608: ldc_w           1841696689
        //  1611: ixor           
        //  1612: lookupswitch {
        //          -550496764: 1605
        //          -265510823: 1640
        //          default: 1672
        //        }
        //  1640: goto            1644
        //  1643: athrow         
        //  1644: invokestatic    net/minecraft/client/renderer/GlStateManager.func_179114_b:(FFFF)V
        //  1647: goto            1651
        //  1650: athrow         
        //  1651: return         
        //  1652: aconst_null    
        //  1653: athrow         
        //  1654: aconst_null    
        //  1655: athrow         
        //  1656: aconst_null    
        //  1657: athrow         
        //  1658: aconst_null    
        //  1659: athrow         
        //  1660: aconst_null    
        //  1661: athrow         
        //  1662: aconst_null    
        //  1663: athrow         
        //  1664: aconst_null    
        //  1665: athrow         
        //  1666: aconst_null    
        //  1667: athrow         
        //  1668: aconst_null    
        //  1669: athrow         
        //  1670: aconst_null    
        //  1671: athrow         
        //  1672: aconst_null    
        //  1673: athrow         
        //  1674: aconst_null    
        //  1675: athrow         
        //  1676: aconst_null    
        //  1677: athrow         
        //  1678: aconst_null    
        //  1679: athrow         
        //  1680: aconst_null    
        //  1681: athrow         
        //  1682: aconst_null    
        //  1683: athrow         
        //  1684: aconst_null    
        //  1685: athrow         
        //  1686: aconst_null    
        //  1687: athrow         
        //  1688: aconst_null    
        //  1689: athrow         
        //  1690: aconst_null    
        //  1691: athrow         
        //  1692: aconst_null    
        //  1693: athrow         
        //  1694: pop            
        //  1695: goto            24
        //  1698: pop            
        //  1699: aconst_null    
        //  1700: goto            1694
        //  1703: dup            
        //  1704: ifnull          1694
        //  1707: checkcast       Ljava/lang/Throwable;
        //  1710: athrow         
        //  1711: dup            
        //  1712: ifnull          1698
        //  1715: checkcast       Ljava/lang/Throwable;
        //  1718: athrow         
        //  1719: aconst_null    
        //  1720: athrow         
        //    StackMapTable: 01 16 43 07 01 92 04 FF 00 0B 00 00 00 01 07 01 92 FD 00 03 07 00 03 07 01 94 14 42 01 1F 46 07 01 76 40 07 00 64 45 07 01 92 40 07 01 EE 45 07 01 92 40 07 01 A0 45 07 01 92 40 03 46 07 01 92 FF 00 00 00 02 07 00 03 07 01 94 00 02 03 07 00 64 45 07 01 92 FF 00 00 00 02 07 00 03 07 01 94 00 02 03 07 01 EE 45 07 01 92 FF 00 00 00 02 07 00 03 07 01 94 00 02 03 07 01 A0 45 07 01 92 FF 00 00 00 02 07 00 03 07 01 94 00 02 03 03 FF 00 0C 00 02 07 00 03 07 01 94 00 03 03 03 07 00 03 FF 00 02 00 02 07 00 03 07 01 94 00 04 03 03 07 00 03 01 FF 00 1D 00 02 07 00 03 07 01 94 00 03 03 03 07 00 03 FF 00 0E 00 02 07 00 03 07 01 94 00 03 03 03 07 00 64 FF 00 02 00 02 07 00 03 07 01 94 00 04 03 03 07 00 64 01 FF 00 1D 00 02 07 00 03 07 01 94 00 03 03 03 07 00 64 42 07 01 92 FF 00 00 00 02 07 00 03 07 01 94 00 03 03 03 07 00 64 45 07 01 92 FF 00 00 00 02 07 00 03 07 01 94 00 03 03 03 07 01 EE 45 07 01 7E FF 00 00 00 02 07 00 03 07 01 94 00 03 03 03 07 01 A0 45 07 01 92 FF 00 00 00 02 07 00 03 07 01 94 00 03 03 03 03 FF 00 02 00 00 00 01 07 01 92 FF 00 00 00 02 07 00 03 07 01 94 00 03 03 03 03 45 07 01 92 00 0B 42 01 1C FF 00 06 00 00 00 01 07 01 92 FF 00 00 00 02 07 00 03 07 01 94 00 01 07 00 64 45 07 01 92 40 07 01 EE 45 07 01 86 40 07 01 A0 45 07 01 92 40 03 FF 00 0F 00 02 07 00 03 07 01 94 00 02 03 07 00 64 FF 00 02 00 02 07 00 03 07 01 94 00 03 03 07 00 64 01 FF 00 1F 00 02 07 00 03 07 01 94 00 02 03 07 00 64 42 07 01 92 FF 00 00 00 02 07 00 03 07 01 94 00 02 03 07 00 64 45 07 01 92 FF 00 00 00 02 07 00 03 07 01 94 00 02 03 07 01 EE FF 00 0E 00 02 07 00 03 07 01 94 00 02 03 07 01 A0 FF 00 02 00 02 07 00 03 07 01 94 00 03 03 07 01 A0 01 FF 00 1E 00 02 07 00 03 07 01 94 00 02 03 07 01 A0 FF 00 02 00 00 00 01 07 01 92 FF 00 00 00 02 07 00 03 07 01 94 00 02 03 07 01 A0 45 07 01 92 FF 00 00 00 02 07 00 03 07 01 94 00 02 03 03 FF 00 0F 00 02 07 00 03 07 01 94 00 03 03 03 07 00 64 FF 00 02 00 02 07 00 03 07 01 94 00 04 03 03 07 00 64 01 FF 00 1D 00 02 07 00 03 07 01 94 00 03 03 03 07 00 64 42 07 01 92 FF 00 00 00 02 07 00 03 07 01 94 00 03 03 03 07 00 64 45 07 01 92 FF 00 00 00 02 07 00 03 07 01 94 00 03 03 03 07 01 EE FF 00 0E 00 02 07 00 03 07 01 94 00 03 03 03 07 01 A0 FF 00 02 00 02 07 00 03 07 01 94 00 04 03 03 07 01 A0 01 FF 00 1E 00 02 07 00 03 07 01 94 00 03 03 03 07 01 A0 42 07 01 78 FF 00 00 00 02 07 00 03 07 01 94 00 03 03 03 07 01 A0 45 07 01 92 FF 00 00 00 02 07 00 03 07 01 94 00 03 03 03 03 FF 00 0B 00 02 07 00 03 07 01 94 00 03 03 03 03 FF 00 02 00 02 07 00 03 07 01 94 00 04 03 03 03 01 FF 00 1D 00 02 07 00 03 07 01 94 00 03 03 03 03 42 07 01 92 FF 00 00 00 02 07 00 03 07 01 94 00 03 03 03 03 45 07 01 92 00 0B 42 01 1D FF 00 06 00 00 00 01 07 01 92 FF 00 00 00 02 07 00 03 07 01 94 00 01 07 00 64 45 07 01 92 40 07 01 EE 45 07 01 92 40 07 01 A0 45 07 01 92 40 03 46 07 01 92 FF 00 00 00 02 07 00 03 07 01 94 00 04 02 02 02 02 45 07 01 92 00 46 07 01 92 40 07 00 64 45 07 01 92 40 07 01 EE 4E 07 01 A0 FF 00 02 00 02 07 00 03 07 01 94 00 02 07 01 A0 01 5E 07 01 A0 42 07 01 92 40 07 01 A0 45 07 01 92 40 03 FF 00 06 00 00 00 01 07 01 92 FF 00 00 00 02 07 00 03 07 01 94 00 04 02 02 02 02 45 07 01 92 00 46 07 01 92 40 07 00 64 45 07 01 92 40 07 01 EE 45 07 01 92 40 07 01 A0 45 07 01 92 40 03 FF 00 06 00 00 00 01 07 01 92 FF 00 00 00 02 07 00 03 07 01 94 00 04 02 02 02 02 45 07 01 92 00 02 46 07 01 82 40 07 00 64 45 07 01 92 40 07 01 EE FF 00 05 00 00 00 01 07 01 92 FF 00 00 00 02 07 00 03 07 01 94 00 01 07 01 A0 45 07 01 92 40 03 FF 00 0C 00 02 07 00 03 07 01 94 00 02 03 07 00 03 FF 00 02 00 02 07 00 03 07 01 94 00 03 03 07 00 03 01 FF 00 1D 00 02 07 00 03 07 01 94 00 02 03 07 00 03 FF 00 0E 00 02 07 00 03 07 01 94 00 02 03 07 00 64 FF 00 02 00 02 07 00 03 07 01 94 00 03 03 07 00 64 01 FF 00 1D 00 02 07 00 03 07 01 94 00 02 03 07 00 64 42 07 01 92 FF 00 00 00 02 07 00 03 07 01 94 00 02 03 07 00 64 45 07 01 92 FF 00 00 00 02 07 00 03 07 01 94 00 02 03 07 01 EE FF 00 0E 00 02 07 00 03 07 01 94 00 02 03 07 01 A0 FF 00 02 00 02 07 00 03 07 01 94 00 03 03 07 01 A0 01 FF 00 1E 00 02 07 00 03 07 01 94 00 02 03 07 01 A0 42 07 01 92 FF 00 00 00 02 07 00 03 07 01 94 00 02 03 07 01 A0 45 07 01 92 FF 00 00 00 02 07 00 03 07 01 94 00 02 03 03 46 07 01 74 FF 00 00 00 02 07 00 03 07 01 94 00 03 03 03 07 00 64 45 07 01 92 FF 00 00 00 02 07 00 03 07 01 94 00 03 03 03 07 01 EE FF 00 0E 00 02 07 00 03 07 01 94 00 03 03 03 07 01 A0 FF 00 02 00 02 07 00 03 07 01 94 00 04 03 03 07 01 A0 01 FF 00 1F 00 02 07 00 03 07 01 94 00 03 03 03 07 01 A0 42 07 01 78 FF 00 00 00 02 07 00 03 07 01 94 00 03 03 03 07 01 A0 45 07 01 92 FF 00 00 00 02 07 00 03 07 01 94 00 03 03 03 03 42 07 01 8E FF 00 00 00 02 07 00 03 07 01 94 00 03 03 03 03 45 07 01 92 00 4C 07 00 03 FF 00 02 00 02 07 00 03 07 01 94 00 02 07 00 03 01 5D 07 00 03 4E 07 00 64 FF 00 02 00 02 07 00 03 07 01 94 00 02 07 00 64 01 5D 07 00 64 42 07 01 92 40 07 00 64 45 07 01 92 40 07 01 EE 45 07 01 92 40 07 01 A0 45 07 01 92 40 03 FF 00 0C 00 02 07 00 03 07 01 94 00 02 03 07 00 03 FF 00 02 00 02 07 00 03 07 01 94 00 03 03 07 00 03 01 FF 00 1E 00 02 07 00 03 07 01 94 00 02 03 07 00 03 45 07 01 92 FF 00 00 00 02 07 00 03 07 01 94 00 02 03 07 00 64 45 07 01 92 FF 00 00 00 02 07 00 03 07 01 94 00 02 03 07 01 EE 45 07 01 92 FF 00 00 00 02 07 00 03 07 01 94 00 02 03 07 01 A0 45 07 01 92 FF 00 00 00 02 07 00 03 07 01 94 00 02 03 03 46 07 01 92 FF 00 00 00 02 07 00 03 07 01 94 00 03 03 03 07 00 64 45 07 01 92 FF 00 00 00 02 07 00 03 07 01 94 00 03 03 03 07 01 EE 45 07 01 86 FF 00 00 00 02 07 00 03 07 01 94 00 03 03 03 07 01 A0 45 07 01 92 FF 00 00 00 02 07 00 03 07 01 94 00 03 03 03 03 42 07 01 92 FF 00 00 00 02 07 00 03 07 01 94 00 03 03 03 03 45 07 01 92 00 46 07 01 92 40 07 00 64 45 07 01 92 40 07 01 EE 45 07 01 92 40 07 01 A0 45 07 01 92 40 03 46 07 01 72 FF 00 00 00 02 07 00 03 07 01 94 00 04 02 02 02 02 45 07 01 92 00 46 07 01 92 40 07 00 64 45 07 01 92 40 07 01 EE 45 07 01 92 40 07 01 A0 45 07 01 92 40 03 FF 00 0F 00 02 07 00 03 07 01 94 00 04 02 02 02 02 FF 00 02 00 02 07 00 03 07 01 94 00 05 02 02 02 02 01 FF 00 1F 00 02 07 00 03 07 01 94 00 04 02 02 02 02 42 07 01 78 FF 00 00 00 02 07 00 03 07 01 94 00 04 02 02 02 02 45 07 01 92 00 4F 07 00 64 FF 00 02 00 02 07 00 03 07 01 94 00 02 07 00 64 01 5D 07 00 64 42 07 01 92 40 07 00 64 45 07 01 92 40 07 01 EE FF 00 05 00 00 00 01 07 01 92 FF 00 00 00 02 07 00 03 07 01 94 00 01 07 01 A0 45 07 01 92 40 03 FF 00 0F 00 02 07 00 03 07 01 94 00 04 02 02 02 02 FF 00 02 00 02 07 00 03 07 01 94 00 05 02 02 02 02 01 FF 00 1F 00 02 07 00 03 07 01 94 00 04 02 02 02 02 42 07 01 78 FF 00 00 00 02 07 00 03 07 01 94 00 04 02 02 02 02 45 07 01 92 00 FF 00 00 00 02 07 00 03 07 01 94 00 03 03 03 07 01 A0 01 41 07 00 64 01 FF 00 01 00 02 07 00 03 07 01 94 00 04 02 02 02 02 FF 00 01 00 02 07 00 03 07 01 94 00 02 03 07 01 A0 41 07 01 A0 FF 00 01 00 02 07 00 03 07 01 94 00 02 03 07 00 64 FF 00 01 00 02 07 00 03 07 01 94 00 02 03 07 01 A0 FF 00 01 00 02 07 00 03 07 01 94 00 03 03 03 07 00 64 FF 00 01 00 02 07 00 03 07 01 94 00 04 02 02 02 02 41 07 00 03 FF 00 01 00 02 07 00 03 07 01 94 00 03 03 03 07 00 64 FF 00 01 00 02 07 00 03 07 01 94 00 02 03 07 00 64 FF 00 01 00 02 07 00 03 07 01 94 00 03 03 03 03 FF 00 01 00 02 07 00 03 07 01 94 00 03 03 03 07 01 A0 01 FF 00 01 00 02 07 00 03 07 01 94 00 02 03 07 00 03 FF 00 01 00 02 07 00 03 07 01 94 00 02 03 07 00 03 41 07 00 64 FF 00 01 00 02 07 00 03 07 01 94 00 03 03 03 07 00 03 41 07 01 92 43 05 44 07 01 92 47 05 47 07 01 92
        //    Exceptions:
        //  Try           Handler
        //  Start  End    Start  End    Type                                       
        //  -----  -----  -----  -----  -------------------------------------------
        //  8      20     1703   1711   Ljava/util/ConcurrentModificationException;
        //  1703   1711   1703   1711   Any
        //  1719   1721   3      8      Ljava/lang/EnumConstantNotPresentException;
        //  87     94     94     95     Any
        //  87     94     94     95     Any
        //  87     94     94     95     Any
        //  87     94     94     95     Any
        //  87     94     87     88     Ljava/lang/NullPointerException;
        //  101    108    108    109    Any
        //  101    108    108    109    Ljava/lang/RuntimeException;
        //  101    108    101    102    Any
        //  101    108    3      8      Any
        //  101    108    108    109    Ljava/lang/IllegalArgumentException;
        //  116    123    123    124    Any
        //  117    123    116    117    Ljava/lang/RuntimeException;
        //  116    123    116    117    Ljava/lang/NullPointerException;
        //  117    123    3      8      Any
        //  117    123    116    117    Any
        //  130    137    137    138    Any
        //  130    137    130    131    Ljava/lang/IllegalArgumentException;
        //  130    137    3      8      Ljava/lang/IndexOutOfBoundsException;
        //  131    137    3      8      Ljava/lang/NumberFormatException;
        //  131    137    130    131    Any
        //  235    242    242    243    Any
        //  235    242    242    243    Ljava/util/ConcurrentModificationException;
        //  235    242    3      8      Ljava/lang/ClassCastException;
        //  236    242    235    236    Ljava/lang/NumberFormatException;
        //  236    242    235    236    Any
        //  249    256    256    257    Any
        //  250    256    256    257    Ljava/lang/NegativeArraySizeException;
        //  250    256    3      8      Any
        //  250    256    3      8      Any
        //  249    256    249    250    Ljava/lang/NumberFormatException;
        //  261    267    267    268    Any
        //  261    267    3      8      Any
        //  261    267    267    268    Ljava/lang/NullPointerException;
        //  261    267    267    268    Any
        //  261    267    267    268    Any
        //  320    326    326    327    Any
        //  320    326    3      8      Any
        //  320    326    3      8      Ljava/util/NoSuchElementException;
        //  320    326    326    327    Any
        //  320    326    326    327    Ljava/util/NoSuchElementException;
        //  333    340    340    341    Any
        //  333    340    333    334    Ljava/lang/IllegalStateException;
        //  334    340    3      8      Any
        //  334    340    3      8      Any
        //  334    340    3      8      Ljava/util/ConcurrentModificationException;
        //  395    402    402    403    Any
        //  396    402    3      8      Any
        //  395    402    395    396    Any
        //  395    402    395    396    Any
        //  395    402    402    403    Any
        //  456    462    462    463    Any
        //  456    462    3      8      Ljava/lang/NumberFormatException;
        //  456    462    3      8      Ljava/lang/AssertionError;
        //  456    462    3      8      Ljava/lang/ClassCastException;
        //  456    462    462    463    Ljava/lang/IndexOutOfBoundsException;
        //  515    522    522    523    Any
        //  515    522    515    516    Any
        //  515    522    515    516    Any
        //  516    522    3      8      Ljava/lang/NegativeArraySizeException;
        //  515    522    515    516    Ljava/lang/NegativeArraySizeException;
        //  575    582    582    583    Any
        //  575    582    575    576    Ljava/lang/ArithmeticException;
        //  575    582    582    583    Any
        //  576    582    575    576    Ljava/lang/StringIndexOutOfBoundsException;
        //  576    582    582    583    Ljava/lang/ArrayIndexOutOfBoundsException;
        //  631    638    638    639    Any
        //  631    638    631    632    Ljava/lang/NegativeArraySizeException;
        //  631    638    3      8      Ljava/lang/NumberFormatException;
        //  631    638    631    632    Any
        //  631    638    631    632    Ljava/lang/UnsupportedOperationException;
        //  692    698    698    699    Any
        //  692    698    3      8      Any
        //  692    698    698    699    Any
        //  692    698    698    699    Any
        //  692    698    698    699    Ljava/lang/NegativeArraySizeException;
        //  705    712    712    713    Any
        //  706    712    705    706    Ljava/lang/ClassCastException;
        //  706    712    3      8      Ljava/lang/AssertionError;
        //  705    712    705    706    Ljava/lang/AssertionError;
        //  705    712    705    706    Ljava/lang/UnsupportedOperationException;
        //  720    727    727    728    Any
        //  720    727    727    728    Ljava/lang/IllegalStateException;
        //  721    727    720    721    Any
        //  721    727    3      8      Ljava/lang/RuntimeException;
        //  721    727    720    721    Ljava/lang/IllegalStateException;
        //  735    742    742    743    Any
        //  736    742    3      8      Any
        //  735    742    3      8      Any
        //  735    742    735    736    Any
        //  736    742    742    743    Any
        //  795    802    802    803    Any
        //  796    802    3      8      Ljava/lang/UnsupportedOperationException;
        //  795    802    802    803    Any
        //  795    802    795    796    Any
        //  795    802    3      8      Ljava/lang/IllegalStateException;
        //  811    817    817    818    Any
        //  811    817    3      8      Ljava/lang/IllegalArgumentException;
        //  811    817    3      8      Any
        //  811    817    817    818    Any
        //  811    817    3      8      Any
        //  825    832    832    833    Any
        //  825    832    832    833    Ljava/lang/NegativeArraySizeException;
        //  825    832    825    826    Any
        //  825    832    3      8      Any
        //  826    832    825    826    Ljava/lang/AssertionError;
        //  839    846    846    847    Any
        //  840    846    839    840    Any
        //  840    846    846    847    Ljava/lang/RuntimeException;
        //  839    846    3      8      Ljava/util/NoSuchElementException;
        //  840    846    846    847    Any
        //  855    861    861    862    Any
        //  855    861    861    862    Ljava/lang/RuntimeException;
        //  855    861    861    862    Any
        //  855    861    861    862    Any
        //  855    861    3      8      Any
        //  872    879    879    880    Any
        //  872    879    3      8      Any
        //  872    879    879    880    Any
        //  872    879    879    880    Ljava/lang/ArithmeticException;
        //  873    879    872    873    Ljava/lang/NegativeArraySizeException;
        //  887    893    893    894    Any
        //  887    893    893    894    Ljava/lang/IllegalStateException;
        //  887    893    893    894    Any
        //  887    893    3      8      Any
        //  887    893    893    894    Ljava/lang/StringIndexOutOfBoundsException;
        //  991    998    998    999    Any
        //  991    998    3      8      Ljava/lang/RuntimeException;
        //  992    998    3      8      Any
        //  991    998    998    999    Any
        //  991    998    991    992    Any
        //  1051   1058   1058   1059   Any
        //  1051   1058   1051   1052   Any
        //  1052   1058   3      8      Any
        //  1052   1058   1058   1059   Ljava/lang/ArithmeticException;
        //  1052   1058   3      8      Any
        //  1066   1073   1073   1074   Any
        //  1067   1073   3      8      Any
        //  1067   1073   1066   1067   Ljava/lang/EnumConstantNotPresentException;
        //  1066   1073   1073   1074   Any
        //  1066   1073   3      8      Ljava/lang/ArithmeticException;
        //  1127   1134   1134   1135   Any
        //  1127   1134   1127   1128   Ljava/lang/EnumConstantNotPresentException;
        //  1128   1134   3      8      Any
        //  1128   1134   3      8      Any
        //  1127   1134   1127   1128   Ljava/lang/RuntimeException;
        //  1138   1145   1145   1146   Any
        //  1139   1145   3      8      Any
        //  1138   1145   3      8      Any
        //  1139   1145   1145   1146   Any
        //  1138   1145   1138   1139   Ljava/lang/ArrayIndexOutOfBoundsException;
        //  1243   1250   1250   1251   Any
        //  1244   1250   1243   1244   Any
        //  1243   1250   1250   1251   Ljava/lang/EnumConstantNotPresentException;
        //  1243   1250   1250   1251   Ljava/lang/NegativeArraySizeException;
        //  1243   1250   1250   1251   Any
        //  1257   1264   1264   1265   Any
        //  1258   1264   3      8      Ljava/lang/AssertionError;
        //  1258   1264   1264   1265   Ljava/lang/AssertionError;
        //  1257   1264   1257   1258   Ljava/lang/ClassCastException;
        //  1258   1264   1257   1258   Any
        //  1318   1325   1325   1326   Any
        //  1319   1325   1318   1319   Any
        //  1319   1325   1318   1319   Any
        //  1318   1325   1318   1319   Ljava/lang/ClassCastException;
        //  1318   1325   1318   1319   Ljava/util/ConcurrentModificationException;
        //  1332   1339   1339   1340   Any
        //  1332   1339   3      8      Any
        //  1332   1339   3      8      Any
        //  1333   1339   1332   1333   Ljava/lang/ArithmeticException;
        //  1332   1339   1332   1333   Any
        //  1347   1354   1354   1355   Any
        //  1347   1354   1347   1348   Any
        //  1347   1354   3      8      Any
        //  1347   1354   1354   1355   Ljava/lang/UnsupportedOperationException;
        //  1348   1354   1347   1348   Ljava/util/NoSuchElementException;
        //  1361   1368   1368   1369   Any
        //  1361   1368   1368   1369   Any
        //  1362   1368   1361   1362   Ljava/lang/IllegalStateException;
        //  1361   1368   1361   1362   Ljava/lang/IllegalStateException;
        //  1362   1368   3      8      Any
        //  1372   1379   1379   1380   Any
        //  1373   1379   1372   1373   Any
        //  1372   1379   1379   1380   Any
        //  1373   1379   3      8      Ljava/lang/EnumConstantNotPresentException;
        //  1372   1379   1372   1373   Ljava/lang/EnumConstantNotPresentException;
        //  1387   1394   1394   1395   Any
        //  1387   1394   1394   1395   Any
        //  1388   1394   1387   1388   Any
        //  1388   1394   1387   1388   Ljava/lang/ClassCastException;
        //  1387   1394   3      8      Any
        //  1401   1408   1408   1409   Any
        //  1401   1408   1408   1409   Ljava/lang/ClassCastException;
        //  1402   1408   3      8      Any
        //  1402   1408   1408   1409   Any
        //  1402   1408   1401   1402   Any
        //  1416   1423   1423   1424   Any
        //  1416   1423   1423   1424   Ljava/lang/ArrayIndexOutOfBoundsException;
        //  1416   1423   3      8      Ljava/lang/ArithmeticException;
        //  1417   1423   1423   1424   Ljava/lang/IllegalArgumentException;
        //  1417   1423   1416   1417   Ljava/util/ConcurrentModificationException;
        //  1431   1438   1438   1439   Any
        //  1432   1438   1438   1439   Ljava/util/NoSuchElementException;
        //  1431   1438   1431   1432   Ljava/lang/IndexOutOfBoundsException;
        //  1432   1438   1431   1432   Any
        //  1431   1438   3      8      Ljava/lang/NullPointerException;
        //  1445   1452   1452   1453   Any
        //  1445   1452   1445   1446   Ljava/lang/StringIndexOutOfBoundsException;
        //  1445   1452   1445   1446   Any
        //  1446   1452   1445   1446   Ljava/lang/ArrayIndexOutOfBoundsException;
        //  1445   1452   3      8      Ljava/lang/NegativeArraySizeException;
        //  1507   1514   1514   1515   Any
        //  1507   1514   1514   1515   Any
        //  1508   1514   1507   1508   Ljava/lang/RuntimeException;
        //  1507   1514   3      8      Any
        //  1508   1514   3      8      Any
        //  1567   1574   1574   1575   Any
        //  1568   1574   1574   1575   Any
        //  1568   1574   1567   1568   Any
        //  1567   1574   1567   1568   Any
        //  1568   1574   3      8      Ljava/lang/IndexOutOfBoundsException;
        //  1582   1588   1588   1589   Any
        //  1582   1588   3      8      Any
        //  1582   1588   1588   1589   Any
        //  1582   1588   3      8      Any
        //  1582   1588   1588   1589   Ljava/lang/NumberFormatException;
        //  1643   1650   1650   1651   Any
        //  1644   1650   1643   1644   Ljava/lang/StringIndexOutOfBoundsException;
        //  1644   1650   1650   1651   Ljava/lang/IndexOutOfBoundsException;
        //  1643   1650   1643   1644   Ljava/lang/IllegalArgumentException;
        //  1644   1650   1650   1651   Any
        // 
        // The error that occurred was:
        // 
        // java.lang.IndexOutOfBoundsException: Index -1 out of bounds for length 0
        //     at java.base/jdk.internal.util.Preconditions.outOfBounds(Preconditions.java:64)
        //     at java.base/jdk.internal.util.Preconditions.outOfBoundsCheckIndex(Preconditions.java:70)
        //     at java.base/jdk.internal.util.Preconditions.checkIndex(Preconditions.java:248)
        //     at java.base/java.util.Objects.checkIndex(Objects.java:372)
        //     at java.base/java.util.ArrayList.remove(ArrayList.java:535)
        //     at com.strobel.assembler.ir.StackMappingVisitor.pop(StackMappingVisitor.java:267)
        //     at com.strobel.assembler.ir.StackMappingVisitor$InstructionAnalyzer.execute(StackMappingVisitor.java:595)
        //     at com.strobel.assembler.ir.StackMappingVisitor$InstructionAnalyzer.visit(StackMappingVisitor.java:398)
        //     at com.strobel.decompiler.ast.AstBuilder.performStackAnalysis(AstBuilder.java:2030)
        //     at com.strobel.decompiler.ast.AstBuilder.build(AstBuilder.java:108)
        //     at com.strobel.decompiler.languages.java.ast.AstMethodBodyBuilder.createMethodBody(AstMethodBodyBuilder.java:211)
        //     at com.strobel.decompiler.languages.java.ast.AstMethodBodyBuilder.createMethodBody(AstMethodBodyBuilder.java:99)
        //     at com.strobel.decompiler.languages.java.ast.AstBuilder.createMethodBody(AstBuilder.java:782)
        //     at com.strobel.decompiler.languages.java.ast.AstBuilder.createMethod(AstBuilder.java:675)
        //     at com.strobel.decompiler.languages.java.ast.AstBuilder.addTypeMembers(AstBuilder.java:552)
        //     at com.strobel.decompiler.languages.java.ast.AstBuilder.createTypeCore(AstBuilder.java:519)
        //     at com.strobel.decompiler.languages.java.ast.AstBuilder.createTypeNoCache(AstBuilder.java:161)
        //     at com.strobel.decompiler.languages.java.ast.AstBuilder.createType(AstBuilder.java:150)
        //     at com.strobel.decompiler.languages.java.ast.AstBuilder.addType(AstBuilder.java:125)
        //     at com.strobel.decompiler.languages.java.JavaLanguage.buildAst(JavaLanguage.java:71)
        //     at com.strobel.decompiler.languages.java.JavaLanguage.decompileType(JavaLanguage.java:59)
        //     at com.strobel.decompiler.DecompilerDriver.decompileType(DecompilerDriver.java:330)
        //     at com.strobel.decompiler.DecompilerDriver.decompileJar(DecompilerDriver.java:251)
        //     at com.strobel.decompiler.DecompilerDriver.main(DecompilerDriver.java:126)
        // 
        throw new IllegalStateException("An error occurred while decompiling this method.");
    }
    
    @NotNull
    public f0d a() {
        return fbS.g6(this, 1582134526);
    }
    
    @NotNull
    public f0d 4() {
        return fbS.fT(this, 209564060);
    }
    
    @NotNull
    public f0d k() {
        return fbS.gb(this, 67154394);
    }
    
    @NotNull
    public f0d f() {
        return fbS.g8(this, 1576183835);
    }
    
    @NotNull
    public f0d 6() {
        return fbS.gq(this, 1708741159);
    }
    
    public double 7() {
        return fbS.9T(this, 1464687016);
    }
    
    @NotNull
    public f0d 3() {
        return fbS.g7(this, 1082124943);
    }
    
    static {
        throw t;
    }
    
    @NotNull
    public f0d 1() {
        return fbS.fQ(this, 898867180);
    }
}
