// 
// Decompiled by Procyon v0.5.36
// 

package dev.nuker.pyro;

import net.minecraft.util.math.Vec3d;
import org.jetbrains.annotations.NotNull;

public class fa5 extends fH
{
    @NotNull
    public f0b c;
    @NotNull
    public f0b 0;
    @NotNull
    public f0b 1;
    
    @NotNull
    public Vec3d 0() {
        // 
        // This method could not be decompiled.
        // 
        // Original Bytecode:
        // 
        //     3: dup            
        //     4: ifnull          1003
        //     7: athrow         
        //     8: aconst_null    
        //     9: getstatic       dev/nuker/pyro/fc.c:I
        //    12: iflt            995
        //    15: pop            
        //    16: aconst_null    
        //    17: goto            987
        //    20: nop            
        //    21: nop            
        //    22: nop            
        //    23: athrow         
        //    24: aload_0        
        //    25: getfield        dev/nuker/pyro/fa5.c:Lnet/minecraft/client/Minecraft;
        //    28: getfield        net/minecraft/client/Minecraft.field_71439_g:Lnet/minecraft/client/entity/EntityPlayerSP;
        //    31: getfield        net/minecraft/client/entity/EntityPlayerSP.field_71093_bK:I
        //    34: tableswitch {
        //               -2: 60
        //               -1: 292
        //                0: 568
        //          default: 718
        //        }
        //    60: new             Lnet/minecraft/util/math/Vec3d;
        //    63: dup            
        //    64: aload_0        
        //    65: getfield        dev/nuker/pyro/fa5.0:Ldev/nuker/pyro/f0b;
        //    68: goto            72
        //    71: athrow         
        //    72: invokevirtual   dev/nuker/pyro/f0b.3:()Ljava/lang/Object;
        //    75: goto            79
        //    78: athrow         
        //    79: checkcast       Ldev/nuker/pyro/fS;
        //    82: goto            86
        //    85: athrow         
        //    86: invokevirtual   dev/nuker/pyro/fS.8:()F
        //    89: goto            93
        //    92: athrow         
        //    93: f2d            
        //    94: getstatic       dev/nuker/pyro/fc.c:I
        //    97: ifge            105
        //   100: ldc             80009112
        //   102: goto            107
        //   105: ldc             373654666
        //   107: ldc             1205698833
        //   109: ixor           
        //   110: lookupswitch {
        //          1125734025: 105
        //          1368917403: 136
        //          default: 970
        //        }
        //   136: aload_0        
        //   137: getfield        dev/nuker/pyro/fa5.0:Ldev/nuker/pyro/f0b;
        //   140: goto            144
        //   143: athrow         
        //   144: invokevirtual   dev/nuker/pyro/f0b.3:()Ljava/lang/Object;
        //   147: goto            151
        //   150: athrow         
        //   151: checkcast       Ldev/nuker/pyro/fS;
        //   154: goto            158
        //   157: athrow         
        //   158: invokevirtual   dev/nuker/pyro/fS.2:()F
        //   161: goto            165
        //   164: athrow         
        //   165: f2d            
        //   166: getstatic       dev/nuker/pyro/fc.0:I
        //   169: ifeq            177
        //   172: ldc             -281076540
        //   174: goto            179
        //   177: ldc             -736660791
        //   179: ldc             1715204845
        //   181: ixor           
        //   182: lookupswitch {
        //          -1996165591: 976
        //          -1241849671: 177
        //          default: 208
        //        }
        //   208: aload_0        
        //   209: getfield        dev/nuker/pyro/fa5.0:Ldev/nuker/pyro/f0b;
        //   212: goto            216
        //   215: athrow         
        //   216: invokevirtual   dev/nuker/pyro/f0b.3:()Ljava/lang/Object;
        //   219: goto            223
        //   222: athrow         
        //   223: checkcast       Ldev/nuker/pyro/fS;
        //   226: goto            230
        //   229: athrow         
        //   230: invokevirtual   dev/nuker/pyro/fS.b:()F
        //   233: goto            237
        //   236: athrow         
        //   237: f2d            
        //   238: getstatic       dev/nuker/pyro/fc.1:I
        //   241: ifeq            249
        //   244: ldc             -64027266
        //   246: goto            251
        //   249: ldc             -293584622
        //   251: ldc             -1048693263
        //   253: ixor           
        //   254: lookupswitch {
        //          -1390617269: 249
        //          1028731023: 964
        //          default: 280
        //        }
        //   280: goto            284
        //   283: athrow         
        //   284: invokespecial   net/minecraft/util/math/Vec3d.<init>:(DDD)V
        //   287: goto            291
        //   290: athrow         
        //   291: areturn        
        //   292: new             Lnet/minecraft/util/math/Vec3d;
        //   295: dup            
        //   296: getstatic       dev/nuker/pyro/fc.0:I
        //   299: ifeq            307
        //   302: ldc             -1058183820
        //   304: goto            309
        //   307: ldc             -713887951
        //   309: ldc             -1040956921
        //   311: ixor           
        //   312: lookupswitch {
        //          -282098417: 307
        //          18425715: 972
        //          default: 340
        //        }
        //   340: aload_0        
        //   341: getfield        dev/nuker/pyro/fa5.c:Ldev/nuker/pyro/f0b;
        //   344: goto            348
        //   347: athrow         
        //   348: invokevirtual   dev/nuker/pyro/f0b.3:()Ljava/lang/Object;
        //   351: goto            355
        //   354: athrow         
        //   355: checkcast       Ldev/nuker/pyro/fS;
        //   358: goto            362
        //   361: athrow         
        //   362: invokevirtual   dev/nuker/pyro/fS.8:()F
        //   365: goto            369
        //   368: athrow         
        //   369: f2d            
        //   370: getstatic       dev/nuker/pyro/fc.1:I
        //   373: ifeq            381
        //   376: ldc             -644815332
        //   378: goto            383
        //   381: ldc             -398772180
        //   383: ldc             -2049466412
        //   385: ixor           
        //   386: lookupswitch {
        //          1548188104: 381
        //          1844226040: 412
        //          default: 958
        //        }
        //   412: aload_0        
        //   413: getfield        dev/nuker/pyro/fa5.c:Ldev/nuker/pyro/f0b;
        //   416: goto            420
        //   419: athrow         
        //   420: invokevirtual   dev/nuker/pyro/f0b.3:()Ljava/lang/Object;
        //   423: goto            427
        //   426: athrow         
        //   427: checkcast       Ldev/nuker/pyro/fS;
        //   430: goto            434
        //   433: athrow         
        //   434: invokevirtual   dev/nuker/pyro/fS.2:()F
        //   437: goto            441
        //   440: athrow         
        //   441: f2d            
        //   442: aload_0        
        //   443: getfield        dev/nuker/pyro/fa5.c:Ldev/nuker/pyro/f0b;
        //   446: getstatic       dev/nuker/pyro/fc.c:I
        //   449: ifge            457
        //   452: ldc             2140361372
        //   454: goto            459
        //   457: ldc             1599258100
        //   459: ldc             -18142045
        //   461: ixor           
        //   462: lookupswitch {
        //          -2122809793: 974
        //          -1539863639: 457
        //          default: 488
        //        }
        //   488: goto            492
        //   491: athrow         
        //   492: invokevirtual   dev/nuker/pyro/f0b.3:()Ljava/lang/Object;
        //   495: goto            499
        //   498: athrow         
        //   499: checkcast       Ldev/nuker/pyro/fS;
        //   502: goto            506
        //   505: athrow         
        //   506: invokevirtual   dev/nuker/pyro/fS.b:()F
        //   509: goto            513
        //   512: athrow         
        //   513: f2d            
        //   514: getstatic       dev/nuker/pyro/fc.c:I
        //   517: ifge            525
        //   520: ldc             -1644792534
        //   522: goto            527
        //   525: ldc             -1608591462
        //   527: ldc             -1033978636
        //   529: ixor           
        //   530: lookupswitch {
        //          530779662: 525
        //          1604897246: 960
        //          default: 556
        //        }
        //   556: goto            560
        //   559: athrow         
        //   560: invokespecial   net/minecraft/util/math/Vec3d.<init>:(DDD)V
        //   563: goto            567
        //   566: athrow         
        //   567: areturn        
        //   568: new             Lnet/minecraft/util/math/Vec3d;
        //   571: dup            
        //   572: aload_0        
        //   573: getfield        dev/nuker/pyro/fa5.1:Ldev/nuker/pyro/f0b;
        //   576: goto            580
        //   579: athrow         
        //   580: invokevirtual   dev/nuker/pyro/f0b.3:()Ljava/lang/Object;
        //   583: goto            587
        //   586: athrow         
        //   587: checkcast       Ldev/nuker/pyro/fS;
        //   590: goto            594
        //   593: athrow         
        //   594: invokevirtual   dev/nuker/pyro/fS.8:()F
        //   597: goto            601
        //   600: athrow         
        //   601: f2d            
        //   602: aload_0        
        //   603: getfield        dev/nuker/pyro/fa5.1:Ldev/nuker/pyro/f0b;
        //   606: goto            610
        //   609: athrow         
        //   610: invokevirtual   dev/nuker/pyro/f0b.3:()Ljava/lang/Object;
        //   613: goto            617
        //   616: athrow         
        //   617: checkcast       Ldev/nuker/pyro/fS;
        //   620: getstatic       dev/nuker/pyro/fc.c:I
        //   623: ifge            631
        //   626: ldc             1325508615
        //   628: goto            633
        //   631: ldc             2120265065
        //   633: ldc             588633009
        //   635: ixor           
        //   636: lookupswitch {
        //          1567981272: 664
        //          1813281718: 631
        //          default: 968
        //        }
        //   664: goto            668
        //   667: athrow         
        //   668: invokevirtual   dev/nuker/pyro/fS.2:()F
        //   671: goto            675
        //   674: athrow         
        //   675: f2d            
        //   676: aload_0        
        //   677: getfield        dev/nuker/pyro/fa5.1:Ldev/nuker/pyro/f0b;
        //   680: goto            684
        //   683: athrow         
        //   684: invokevirtual   dev/nuker/pyro/f0b.3:()Ljava/lang/Object;
        //   687: goto            691
        //   690: athrow         
        //   691: checkcast       Ldev/nuker/pyro/fS;
        //   694: goto            698
        //   697: athrow         
        //   698: invokevirtual   dev/nuker/pyro/fS.b:()F
        //   701: goto            705
        //   704: athrow         
        //   705: f2d            
        //   706: goto            710
        //   709: athrow         
        //   710: invokespecial   net/minecraft/util/math/Vec3d.<init>:(DDD)V
        //   713: goto            717
        //   716: athrow         
        //   717: areturn        
        //   718: new             Lnet/minecraft/util/math/Vec3d;
        //   721: dup            
        //   722: aload_0        
        //   723: getfield        dev/nuker/pyro/fa5.c:Ldev/nuker/pyro/f0b;
        //   726: goto            730
        //   729: athrow         
        //   730: invokevirtual   dev/nuker/pyro/f0b.3:()Ljava/lang/Object;
        //   733: goto            737
        //   736: athrow         
        //   737: checkcast       Ldev/nuker/pyro/fS;
        //   740: goto            744
        //   743: athrow         
        //   744: invokevirtual   dev/nuker/pyro/fS.8:()F
        //   747: goto            751
        //   750: athrow         
        //   751: f2d            
        //   752: aload_0        
        //   753: getfield        dev/nuker/pyro/fa5.c:Ldev/nuker/pyro/f0b;
        //   756: getstatic       dev/nuker/pyro/fc.0:I
        //   759: ifeq            767
        //   762: ldc             1892906456
        //   764: goto            769
        //   767: ldc             -781166097
        //   769: ldc             1948019530
        //   771: ixor           
        //   772: lookupswitch {
        //          80682642: 962
        //          1568732853: 767
        //          default: 800
        //        }
        //   800: goto            804
        //   803: athrow         
        //   804: invokevirtual   dev/nuker/pyro/f0b.3:()Ljava/lang/Object;
        //   807: goto            811
        //   810: athrow         
        //   811: checkcast       Ldev/nuker/pyro/fS;
        //   814: goto            818
        //   817: athrow         
        //   818: invokevirtual   dev/nuker/pyro/fS.2:()F
        //   821: goto            825
        //   824: athrow         
        //   825: f2d            
        //   826: aload_0        
        //   827: getfield        dev/nuker/pyro/fa5.c:Ldev/nuker/pyro/f0b;
        //   830: goto            834
        //   833: athrow         
        //   834: invokevirtual   dev/nuker/pyro/f0b.3:()Ljava/lang/Object;
        //   837: goto            841
        //   840: athrow         
        //   841: checkcast       Ldev/nuker/pyro/fS;
        //   844: getstatic       dev/nuker/pyro/fc.c:I
        //   847: ifge            855
        //   850: ldc             1642335904
        //   852: goto            857
        //   855: ldc             1431551140
        //   857: ldc             -1729212892
        //   859: ixor           
        //   860: lookupswitch {
        //          -843189632: 888
        //          -116768636: 855
        //          default: 966
        //        }
        //   888: goto            892
        //   891: athrow         
        //   892: invokevirtual   dev/nuker/pyro/fS.b:()F
        //   895: goto            899
        //   898: athrow         
        //   899: f2d            
        //   900: getstatic       dev/nuker/pyro/fc.c:I
        //   903: ifge            911
        //   906: ldc             -1764360088
        //   908: goto            913
        //   911: ldc             -839712719
        //   913: ldc             -1288485965
        //   915: ixor           
        //   916: lookupswitch {
        //          -331298834: 911
        //          635782107: 956
        //          default: 944
        //        }
        //   944: goto            948
        //   947: athrow         
        //   948: invokespecial   net/minecraft/util/math/Vec3d.<init>:(DDD)V
        //   951: goto            955
        //   954: athrow         
        //   955: areturn        
        //   956: aconst_null    
        //   957: athrow         
        //   958: aconst_null    
        //   959: athrow         
        //   960: aconst_null    
        //   961: athrow         
        //   962: aconst_null    
        //   963: athrow         
        //   964: aconst_null    
        //   965: athrow         
        //   966: aconst_null    
        //   967: athrow         
        //   968: aconst_null    
        //   969: athrow         
        //   970: aconst_null    
        //   971: athrow         
        //   972: aconst_null    
        //   973: athrow         
        //   974: aconst_null    
        //   975: athrow         
        //   976: aconst_null    
        //   977: athrow         
        //   978: pop            
        //   979: goto            24
        //   982: pop            
        //   983: aconst_null    
        //   984: goto            978
        //   987: dup            
        //   988: ifnull          978
        //   991: checkcast       Ljava/lang/Throwable;
        //   994: athrow         
        //   995: dup            
        //   996: ifnull          982
        //   999: checkcast       Ljava/lang/Throwable;
        //  1002: athrow         
        //  1003: aconst_null    
        //  1004: athrow         
        //    StackMapTable: 00 A9 43 07 00 32 04 FF 00 0B 00 00 00 01 07 00 32 FC 00 03 07 00 03 23 FF 00 0A 00 00 00 01 07 00 32 FF 00 00 00 01 07 00 03 00 03 08 00 3C 08 00 3C 07 00 46 45 07 00 32 FF 00 00 00 01 07 00 03 00 03 08 00 3C 08 00 3C 07 00 85 45 07 00 32 FF 00 00 00 01 07 00 03 00 03 08 00 3C 08 00 3C 07 00 4C 45 07 00 32 FF 00 00 00 01 07 00 03 00 03 08 00 3C 08 00 3C 02 FF 00 0B 00 01 07 00 03 00 03 08 00 3C 08 00 3C 03 FF 00 01 00 01 07 00 03 00 04 08 00 3C 08 00 3C 03 01 FF 00 1C 00 01 07 00 03 00 03 08 00 3C 08 00 3C 03 46 07 00 32 FF 00 00 00 01 07 00 03 00 04 08 00 3C 08 00 3C 03 07 00 46 45 07 00 32 FF 00 00 00 01 07 00 03 00 04 08 00 3C 08 00 3C 03 07 00 85 45 07 00 32 FF 00 00 00 01 07 00 03 00 04 08 00 3C 08 00 3C 03 07 00 4C 45 07 00 32 FF 00 00 00 01 07 00 03 00 04 08 00 3C 08 00 3C 03 02 FF 00 0B 00 01 07 00 03 00 04 08 00 3C 08 00 3C 03 03 FF 00 01 00 01 07 00 03 00 05 08 00 3C 08 00 3C 03 03 01 FF 00 1C 00 01 07 00 03 00 04 08 00 3C 08 00 3C 03 03 FF 00 06 00 00 00 01 07 00 32 FF 00 00 00 01 07 00 03 00 05 08 00 3C 08 00 3C 03 03 07 00 46 45 07 00 32 FF 00 00 00 01 07 00 03 00 05 08 00 3C 08 00 3C 03 03 07 00 85 FF 00 05 00 00 00 01 07 00 32 FF 00 00 00 01 07 00 03 00 05 08 00 3C 08 00 3C 03 03 07 00 4C 45 07 00 32 FF 00 00 00 01 07 00 03 00 05 08 00 3C 08 00 3C 03 03 02 FF 00 0B 00 01 07 00 03 00 05 08 00 3C 08 00 3C 03 03 03 FF 00 01 00 01 07 00 03 00 06 08 00 3C 08 00 3C 03 03 03 01 FF 00 1C 00 01 07 00 03 00 05 08 00 3C 08 00 3C 03 03 03 42 07 00 32 FF 00 00 00 01 07 00 03 00 05 08 00 3C 08 00 3C 03 03 03 45 07 00 32 40 07 00 42 00 FF 00 0E 00 01 07 00 03 00 02 08 01 24 08 01 24 FF 00 01 00 01 07 00 03 00 03 08 01 24 08 01 24 01 FF 00 1E 00 01 07 00 03 00 02 08 01 24 08 01 24 46 07 00 21 FF 00 00 00 01 07 00 03 00 03 08 01 24 08 01 24 07 00 46 45 07 00 32 FF 00 00 00 01 07 00 03 00 03 08 01 24 08 01 24 07 00 85 45 07 00 21 FF 00 00 00 01 07 00 03 00 03 08 01 24 08 01 24 07 00 4C 45 07 00 32 FF 00 00 00 01 07 00 03 00 03 08 01 24 08 01 24 02 FF 00 0B 00 01 07 00 03 00 03 08 01 24 08 01 24 03 FF 00 01 00 01 07 00 03 00 04 08 01 24 08 01 24 03 01 FF 00 1C 00 01 07 00 03 00 03 08 01 24 08 01 24 03 46 07 00 32 FF 00 00 00 01 07 00 03 00 04 08 01 24 08 01 24 03 07 00 46 45 07 00 32 FF 00 00 00 01 07 00 03 00 04 08 01 24 08 01 24 03 07 00 85 FF 00 05 00 00 00 01 07 00 32 FF 00 00 00 01 07 00 03 00 04 08 01 24 08 01 24 03 07 00 4C 45 07 00 32 FF 00 00 00 01 07 00 03 00 04 08 01 24 08 01 24 03 02 FF 00 0F 00 01 07 00 03 00 05 08 01 24 08 01 24 03 03 07 00 46 FF 00 01 00 01 07 00 03 00 06 08 01 24 08 01 24 03 03 07 00 46 01 FF 00 1C 00 01 07 00 03 00 05 08 01 24 08 01 24 03 03 07 00 46 42 07 00 21 FF 00 00 00 01 07 00 03 00 05 08 01 24 08 01 24 03 03 07 00 46 45 07 00 32 FF 00 00 00 01 07 00 03 00 05 08 01 24 08 01 24 03 03 07 00 85 45 07 00 23 FF 00 00 00 01 07 00 03 00 05 08 01 24 08 01 24 03 03 07 00 4C 45 07 00 32 FF 00 00 00 01 07 00 03 00 05 08 01 24 08 01 24 03 03 02 FF 00 0B 00 01 07 00 03 00 05 08 01 24 08 01 24 03 03 03 FF 00 01 00 01 07 00 03 00 06 08 01 24 08 01 24 03 03 03 01 FF 00 1C 00 01 07 00 03 00 05 08 01 24 08 01 24 03 03 03 42 07 00 11 FF 00 00 00 01 07 00 03 00 05 08 01 24 08 01 24 03 03 03 45 07 00 32 40 07 00 42 00 FF 00 0A 00 00 00 01 07 00 32 FF 00 00 00 01 07 00 03 00 03 08 02 38 08 02 38 07 00 46 45 07 00 32 FF 00 00 00 01 07 00 03 00 03 08 02 38 08 02 38 07 00 85 45 07 00 32 FF 00 00 00 01 07 00 03 00 03 08 02 38 08 02 38 07 00 4C 45 07 00 32 FF 00 00 00 01 07 00 03 00 03 08 02 38 08 02 38 02 47 07 00 32 FF 00 00 00 01 07 00 03 00 04 08 02 38 08 02 38 03 07 00 46 45 07 00 32 FF 00 00 00 01 07 00 03 00 04 08 02 38 08 02 38 03 07 00 85 FF 00 0D 00 01 07 00 03 00 04 08 02 38 08 02 38 03 07 00 4C FF 00 01 00 01 07 00 03 00 05 08 02 38 08 02 38 03 07 00 4C 01 FF 00 1E 00 01 07 00 03 00 04 08 02 38 08 02 38 03 07 00 4C FF 00 02 00 00 00 01 07 00 32 FF 00 00 00 01 07 00 03 00 04 08 02 38 08 02 38 03 07 00 4C 45 07 00 32 FF 00 00 00 01 07 00 03 00 04 08 02 38 08 02 38 03 02 47 07 00 32 FF 00 00 00 01 07 00 03 00 05 08 02 38 08 02 38 03 03 07 00 46 45 07 00 32 FF 00 00 00 01 07 00 03 00 05 08 02 38 08 02 38 03 03 07 00 85 45 07 00 25 FF 00 00 00 01 07 00 03 00 05 08 02 38 08 02 38 03 03 07 00 4C 45 07 00 32 FF 00 00 00 01 07 00 03 00 05 08 02 38 08 02 38 03 03 02 43 07 00 17 FF 00 00 00 01 07 00 03 00 05 08 02 38 08 02 38 03 03 03 45 07 00 32 40 07 00 42 00 FF 00 0A 00 00 00 01 07 00 32 FF 00 00 00 01 07 00 03 00 03 08 02 CE 08 02 CE 07 00 46 45 07 00 32 FF 00 00 00 01 07 00 03 00 03 08 02 CE 08 02 CE 07 00 85 45 07 00 11 FF 00 00 00 01 07 00 03 00 03 08 02 CE 08 02 CE 07 00 4C 45 07 00 32 FF 00 00 00 01 07 00 03 00 03 08 02 CE 08 02 CE 02 FF 00 0F 00 01 07 00 03 00 04 08 02 CE 08 02 CE 03 07 00 46 FF 00 01 00 01 07 00 03 00 05 08 02 CE 08 02 CE 03 07 00 46 01 FF 00 1E 00 01 07 00 03 00 04 08 02 CE 08 02 CE 03 07 00 46 42 07 00 32 FF 00 00 00 01 07 00 03 00 04 08 02 CE 08 02 CE 03 07 00 46 45 07 00 32 FF 00 00 00 01 07 00 03 00 04 08 02 CE 08 02 CE 03 07 00 85 45 07 00 32 FF 00 00 00 01 07 00 03 00 04 08 02 CE 08 02 CE 03 07 00 4C 45 07 00 32 FF 00 00 00 01 07 00 03 00 04 08 02 CE 08 02 CE 03 02 47 07 00 0F FF 00 00 00 01 07 00 03 00 05 08 02 CE 08 02 CE 03 03 07 00 46 45 07 00 32 FF 00 00 00 01 07 00 03 00 05 08 02 CE 08 02 CE 03 03 07 00 85 FF 00 0D 00 01 07 00 03 00 05 08 02 CE 08 02 CE 03 03 07 00 4C FF 00 01 00 01 07 00 03 00 06 08 02 CE 08 02 CE 03 03 07 00 4C 01 FF 00 1E 00 01 07 00 03 00 05 08 02 CE 08 02 CE 03 03 07 00 4C 42 07 00 32 FF 00 00 00 01 07 00 03 00 05 08 02 CE 08 02 CE 03 03 07 00 4C 45 07 00 32 FF 00 00 00 01 07 00 03 00 05 08 02 CE 08 02 CE 03 03 02 FF 00 0B 00 01 07 00 03 00 05 08 02 CE 08 02 CE 03 03 03 FF 00 01 00 01 07 00 03 00 06 08 02 CE 08 02 CE 03 03 03 01 FF 00 1E 00 01 07 00 03 00 05 08 02 CE 08 02 CE 03 03 03 42 07 00 13 FF 00 00 00 01 07 00 03 00 05 08 02 CE 08 02 CE 03 03 03 45 07 00 32 40 07 00 42 FF 00 00 00 01 07 00 03 00 05 08 02 CE 08 02 CE 03 03 03 FF 00 01 00 01 07 00 03 00 03 08 01 24 08 01 24 03 FF 00 01 00 01 07 00 03 00 05 08 01 24 08 01 24 03 03 03 FF 00 01 00 01 07 00 03 00 04 08 02 CE 08 02 CE 03 07 00 46 FF 00 01 00 01 07 00 03 00 05 08 00 3C 08 00 3C 03 03 03 FF 00 01 00 01 07 00 03 00 05 08 02 CE 08 02 CE 03 03 07 00 4C FF 00 01 00 01 07 00 03 00 04 08 02 38 08 02 38 03 07 00 4C FF 00 01 00 01 07 00 03 00 03 08 00 3C 08 00 3C 03 FF 00 01 00 01 07 00 03 00 02 08 01 24 08 01 24 FF 00 01 00 01 07 00 03 00 05 08 01 24 08 01 24 03 03 07 00 46 FF 00 01 00 01 07 00 03 00 04 08 00 3C 08 00 3C 03 03 41 07 00 32 43 05 44 07 00 32 47 05 47 07 00 32
        //    Exceptions:
        //  Try           Handler
        //  Start  End    Start  End    Type                                       
        //  -----  -----  -----  -----  -------------------------------------------
        //  8      20     987    995    Ljava/lang/ArrayIndexOutOfBoundsException;
        //  987    995    987    995    Any
        //  1003   1005   3      8      Ljava/lang/ArithmeticException;
        //  72     78     78     79     Any
        //  72     78     3      8      Any
        //  72     78     78     79     Any
        //  72     78     3      8      Any
        //  72     78     3      8      Ljava/lang/NegativeArraySizeException;
        //  85     92     92     93     Any
        //  85     92     3      8      Ljava/lang/StringIndexOutOfBoundsException;
        //  85     92     85     86     Any
        //  86     92     92     93     Any
        //  86     92     3      8      Ljava/lang/NegativeArraySizeException;
        //  143    150    150    151    Any
        //  144    150    150    151    Ljava/lang/EnumConstantNotPresentException;
        //  144    150    143    144    Ljava/lang/IndexOutOfBoundsException;
        //  144    150    143    144    Any
        //  143    150    150    151    Ljava/lang/EnumConstantNotPresentException;
        //  157    164    164    165    Any
        //  158    164    164    165    Ljava/lang/ArithmeticException;
        //  158    164    157    158    Ljava/lang/NumberFormatException;
        //  158    164    157    158    Any
        //  158    164    164    165    Ljava/lang/IndexOutOfBoundsException;
        //  216    222    222    223    Any
        //  216    222    222    223    Any
        //  216    222    3      8      Ljava/lang/ClassCastException;
        //  216    222    3      8      Ljava/lang/IllegalArgumentException;
        //  216    222    222    223    Ljava/lang/IllegalArgumentException;
        //  230    236    236    237    Any
        //  230    236    3      8      Ljava/lang/IllegalArgumentException;
        //  230    236    3      8      Ljava/lang/IllegalArgumentException;
        //  230    236    3      8      Ljava/lang/NullPointerException;
        //  230    236    236    237    Any
        //  283    290    290    291    Any
        //  283    290    283    284    Any
        //  284    290    3      8      Ljava/lang/IndexOutOfBoundsException;
        //  284    290    283    284    Any
        //  284    290    290    291    Ljava/lang/NumberFormatException;
        //  347    354    354    355    Any
        //  348    354    354    355    Any
        //  347    354    347    348    Ljava/lang/RuntimeException;
        //  347    354    3      8      Ljava/lang/UnsupportedOperationException;
        //  348    354    3      8      Any
        //  361    368    368    369    Any
        //  362    368    361    362    Ljava/lang/ArithmeticException;
        //  362    368    361    362    Ljava/lang/IllegalArgumentException;
        //  362    368    368    369    Any
        //  362    368    368    369    Any
        //  419    426    426    427    Any
        //  419    426    3      8      Any
        //  420    426    419    420    Ljava/lang/NullPointerException;
        //  420    426    419    420    Any
        //  420    426    426    427    Any
        //  434    440    440    441    Any
        //  434    440    3      8      Any
        //  434    440    3      8      Any
        //  434    440    3      8      Any
        //  434    440    3      8      Ljava/lang/ArrayIndexOutOfBoundsException;
        //  491    498    498    499    Any
        //  491    498    491    492    Ljava/lang/RuntimeException;
        //  492    498    498    499    Ljava/lang/IndexOutOfBoundsException;
        //  491    498    498    499    Any
        //  491    498    491    492    Ljava/util/NoSuchElementException;
        //  505    512    512    513    Any
        //  505    512    512    513    Any
        //  505    512    512    513    Ljava/lang/RuntimeException;
        //  505    512    3      8      Ljava/lang/EnumConstantNotPresentException;
        //  506    512    505    506    Ljava/lang/UnsupportedOperationException;
        //  559    566    566    567    Any
        //  560    566    566    567    Ljava/lang/IllegalArgumentException;
        //  559    566    559    560    Ljava/lang/NegativeArraySizeException;
        //  559    566    566    567    Ljava/lang/UnsupportedOperationException;
        //  559    566    566    567    Ljava/lang/EnumConstantNotPresentException;
        //  580    586    586    587    Any
        //  580    586    3      8      Any
        //  580    586    3      8      Ljava/lang/AssertionError;
        //  580    586    3      8      Ljava/lang/NegativeArraySizeException;
        //  580    586    3      8      Ljava/lang/NumberFormatException;
        //  593    600    600    601    Any
        //  594    600    593    594    Ljava/lang/ArrayIndexOutOfBoundsException;
        //  594    600    600    601    Any
        //  594    600    3      8      Any
        //  593    600    593    594    Any
        //  609    616    616    617    Any
        //  609    616    609    610    Any
        //  609    616    3      8      Ljava/lang/IllegalArgumentException;
        //  609    616    616    617    Ljava/lang/ArrayIndexOutOfBoundsException;
        //  610    616    616    617    Ljava/lang/EnumConstantNotPresentException;
        //  668    674    674    675    Any
        //  668    674    674    675    Ljava/lang/NegativeArraySizeException;
        //  668    674    674    675    Any
        //  668    674    3      8      Ljava/lang/EnumConstantNotPresentException;
        //  668    674    3      8      Ljava/lang/StringIndexOutOfBoundsException;
        //  683    690    690    691    Any
        //  683    690    3      8      Ljava/util/NoSuchElementException;
        //  684    690    690    691    Any
        //  684    690    683    684    Ljava/lang/RuntimeException;
        //  683    690    683    684    Any
        //  697    704    704    705    Any
        //  698    704    3      8      Any
        //  697    704    704    705    Ljava/lang/NullPointerException;
        //  697    704    704    705    Any
        //  698    704    697    698    Ljava/util/NoSuchElementException;
        //  709    716    716    717    Any
        //  710    716    716    717    Any
        //  710    716    709    710    Ljava/lang/IndexOutOfBoundsException;
        //  709    716    3      8      Any
        //  709    716    3      8      Ljava/lang/RuntimeException;
        //  730    736    736    737    Any
        //  730    736    3      8      Ljava/lang/StringIndexOutOfBoundsException;
        //  730    736    3      8      Any
        //  730    736    736    737    Any
        //  730    736    736    737    Ljava/util/ConcurrentModificationException;
        //  743    750    750    751    Any
        //  743    750    743    744    Ljava/lang/NegativeArraySizeException;
        //  743    750    3      8      Ljava/lang/IllegalStateException;
        //  743    750    3      8      Ljava/lang/IndexOutOfBoundsException;
        //  743    750    750    751    Any
        //  803    810    810    811    Any
        //  804    810    803    804    Ljava/lang/ArrayIndexOutOfBoundsException;
        //  804    810    3      8      Ljava/lang/IndexOutOfBoundsException;
        //  804    810    803    804    Any
        //  804    810    810    811    Any
        //  817    824    824    825    Any
        //  817    824    817    818    Any
        //  818    824    3      8      Ljava/lang/StringIndexOutOfBoundsException;
        //  818    824    824    825    Any
        //  817    824    817    818    Ljava/lang/NegativeArraySizeException;
        //  833    840    840    841    Any
        //  834    840    833    834    Ljava/lang/ArithmeticException;
        //  833    840    840    841    Any
        //  834    840    3      8      Ljava/lang/NumberFormatException;
        //  833    840    3      8      Any
        //  891    898    898    899    Any
        //  891    898    3      8      Ljava/lang/NegativeArraySizeException;
        //  891    898    891    892    Any
        //  891    898    3      8      Ljava/lang/UnsupportedOperationException;
        //  892    898    3      8      Any
        //  947    954    954    955    Any
        //  947    954    954    955    Any
        //  947    954    947    948    Ljava/lang/StringIndexOutOfBoundsException;
        //  948    954    954    955    Any
        //  948    954    954    955    Any
        // 
        // The error that occurred was:
        // 
        // java.lang.IndexOutOfBoundsException: Index -1 out of bounds for length 0
        //     at java.base/jdk.internal.util.Preconditions.outOfBounds(Preconditions.java:64)
        //     at java.base/jdk.internal.util.Preconditions.outOfBoundsCheckIndex(Preconditions.java:70)
        //     at java.base/jdk.internal.util.Preconditions.checkIndex(Preconditions.java:248)
        //     at java.base/java.util.Objects.checkIndex(Objects.java:372)
        //     at java.base/java.util.ArrayList.remove(ArrayList.java:535)
        //     at com.strobel.assembler.ir.StackMappingVisitor.pop(StackMappingVisitor.java:267)
        //     at com.strobel.assembler.ir.StackMappingVisitor$InstructionAnalyzer.execute(StackMappingVisitor.java:595)
        //     at com.strobel.assembler.ir.StackMappingVisitor$InstructionAnalyzer.visit(StackMappingVisitor.java:398)
        //     at com.strobel.decompiler.ast.AstBuilder.performStackAnalysis(AstBuilder.java:2030)
        //     at com.strobel.decompiler.ast.AstBuilder.build(AstBuilder.java:108)
        //     at com.strobel.decompiler.languages.java.ast.AstMethodBodyBuilder.createMethodBody(AstMethodBodyBuilder.java:211)
        //     at com.strobel.decompiler.languages.java.ast.AstMethodBodyBuilder.createMethodBody(AstMethodBodyBuilder.java:99)
        //     at com.strobel.decompiler.languages.java.ast.AstBuilder.createMethodBody(AstBuilder.java:782)
        //     at com.strobel.decompiler.languages.java.ast.AstBuilder.createMethod(AstBuilder.java:675)
        //     at com.strobel.decompiler.languages.java.ast.AstBuilder.addTypeMembers(AstBuilder.java:552)
        //     at com.strobel.decompiler.languages.java.ast.AstBuilder.createTypeCore(AstBuilder.java:519)
        //     at com.strobel.decompiler.languages.java.ast.AstBuilder.createTypeNoCache(AstBuilder.java:161)
        //     at com.strobel.decompiler.languages.java.ast.AstBuilder.createType(AstBuilder.java:150)
        //     at com.strobel.decompiler.languages.java.ast.AstBuilder.addType(AstBuilder.java:125)
        //     at com.strobel.decompiler.languages.java.JavaLanguage.buildAst(JavaLanguage.java:71)
        //     at com.strobel.decompiler.languages.java.JavaLanguage.decompileType(JavaLanguage.java:59)
        //     at com.strobel.decompiler.DecompilerDriver.decompileType(DecompilerDriver.java:330)
        //     at com.strobel.decompiler.DecompilerDriver.decompileJar(DecompilerDriver.java:251)
        //     at com.strobel.decompiler.DecompilerDriver.main(DecompilerDriver.java:126)
        // 
        throw new IllegalStateException("An error occurred while decompiling this method.");
    }
    
    public void c(@NotNull final f0b f0b) {
        fbS.7Y(this, 2050652902, f0b);
    }
    
    @NotNull
    public f0b c() {
        return fbS.1y(this, 2012073397);
    }
    
    public float 1() {
        return fbS.aw(this, 79423588);
    }
    
    public fa5() {
        // 
        // This method could not be decompiled.
        // 
        // Original Bytecode:
        // 
        //     1: ldc             "\u2925\u1498\u803e\ub3da\uc692\ue73c\ub22b\uec18"
        //     3: getstatic       dev/nuker/pyro/fc.c:I
        //     6: ifge            14
        //     9: ldc             361681509
        //    11: goto            16
        //    14: ldc             631566583
        //    16: ldc             -1870846304
        //    18: ixor           
        //    19: lookupswitch {
        //          -2047609659: 14
        //          -1244015017: 44
        //          default: 540
        //        }
        //    44: invokestatic    invokestatic   !!! ERROR
        //    47: ldc             "\u2905\u1498\u803e\ub3fa\uc692\ue73c\ub22b\uec18"
        //    49: getstatic       dev/nuker/pyro/fc.0:I
        //    52: ifeq            60
        //    55: ldc             -610130952
        //    57: goto            62
        //    60: ldc             -1769915630
        //    62: ldc             795816824
        //    64: ixor           
        //    65: lookupswitch {
        //          -1175582614: 92
        //          -187887488: 60
        //          default: 548
        //        }
        //    92: invokestatic    invokestatic   !!! ERROR
        //    95: aconst_null    
        //    96: invokespecial   dev/nuker/pyro/fH.<init>:(Ljava/lang/String;Ljava/lang/String;Ljava/lang/String;)V
        //    99: aload_0        
        //   100: aload_0        
        //   101: new             Ldev/nuker/pyro/f0b;
        //   104: dup            
        //   105: ldc             "\u2939\u1485\u8022\ub3cb\uc68a\ue73f\ub236\uec06\ud96c"
        //   107: getstatic       dev/nuker/pyro/fc.1:I
        //   110: ifeq            118
        //   113: ldc             1250185341
        //   115: goto            120
        //   118: ldc             -1112152046
        //   120: ldc             837594810
        //   122: ixor           
        //   123: lookupswitch {
        //          -1940306264: 148
        //          2070478535: 118
        //          default: 542
        //        }
        //   148: invokestatic    invokestatic   !!! ERROR
        //   151: ldc             "\u2919\u1485\u8022\ub3cb\uc68a\ue73f\ub236\uec06\ud96c"
        //   153: invokestatic    invokestatic   !!! ERROR
        //   156: aconst_null    
        //   157: new             Ldev/nuker/pyro/fS;
        //   160: dup            
        //   161: ldc             0.5416667
        //   163: fconst_1       
        //   164: ldc             0.9
        //   166: ldc             0.5
        //   168: getstatic       dev/nuker/pyro/fc.0:I
        //   171: ifeq            179
        //   174: ldc             -1156617420
        //   176: goto            181
        //   179: ldc             1844897607
        //   181: ldc             -472289953
        //   183: ixor           
        //   184: lookupswitch {
        //          53133804: 179
        //          1490421355: 536
        //          default: 212
        //        }
        //   212: invokespecial   dev/nuker/pyro/fS.<init>:(FFFF)V
        //   215: getstatic       dev/nuker/pyro/fc.1:I
        //   218: ifeq            226
        //   221: ldc             816955700
        //   223: goto            228
        //   226: ldc             -1256291918
        //   228: ldc             -596533518
        //   230: ixor           
        //   231: lookupswitch {
        //          -322936890: 226
        //          1768890176: 256
        //          default: 546
        //        }
        //   256: invokespecial   dev/nuker/pyro/f0b.<init>:(Ljava/lang/String;Ljava/lang/String;Ljava/lang/String;Ldev/nuker/pyro/fS;)V
        //   259: checkcast       Ldev/nuker/pyro/f0n;
        //   262: invokevirtual   dev/nuker/pyro/fa5.c:(Ldev/nuker/pyro/f0n;)Ldev/nuker/pyro/f0n;
        //   265: checkcast       Ldev/nuker/pyro/f0b;
        //   268: putfield        dev/nuker/pyro/fa5.c:Ldev/nuker/pyro/f0b;
        //   271: getstatic       dev/nuker/pyro/fc.c:I
        //   274: ifge            282
        //   277: ldc             -1951002996
        //   279: goto            284
        //   282: ldc             -3365298
        //   284: ldc             -1110940180
        //   286: ixor           
        //   287: lookupswitch {
        //          914254688: 282
        //          1107608482: 312
        //          default: 534
        //        }
        //   312: aload_0        
        //   313: aload_0        
        //   314: new             Ldev/nuker/pyro/f0b;
        //   317: dup            
        //   318: ldc             "\u2938\u1496\u8033\ub3d1\uc698\ue722"
        //   320: invokestatic    invokestatic   !!! ERROR
        //   323: ldc             "\u2918\u1496\u8033\ub3d1\uc698\ue722"
        //   325: invokestatic    invokestatic   !!! ERROR
        //   328: aconst_null    
        //   329: new             Ldev/nuker/pyro/fS;
        //   332: dup            
        //   333: fconst_0       
        //   334: ldc             0.81
        //   336: ldc             0.31
        //   338: ldc             0.5
        //   340: getstatic       dev/nuker/pyro/fc.1:I
        //   343: ifeq            351
        //   346: ldc             763412633
        //   348: goto            353
        //   351: ldc             -1717355440
        //   353: ldc             1059109439
        //   355: ixor           
        //   356: lookupswitch {
        //          -1501329809: 384
        //          312507046: 351
        //          default: 532
        //        }
        //   384: invokespecial   dev/nuker/pyro/fS.<init>:(FFFF)V
        //   387: invokespecial   dev/nuker/pyro/f0b.<init>:(Ljava/lang/String;Ljava/lang/String;Ljava/lang/String;Ldev/nuker/pyro/fS;)V
        //   390: checkcast       Ldev/nuker/pyro/f0n;
        //   393: invokevirtual   dev/nuker/pyro/fa5.c:(Ldev/nuker/pyro/f0n;)Ldev/nuker/pyro/f0n;
        //   396: checkcast       Ldev/nuker/pyro/f0b;
        //   399: putfield        dev/nuker/pyro/fa5.0:Ldev/nuker/pyro/f0b;
        //   402: getstatic       dev/nuker/pyro/fc.0:I
        //   405: ifeq            413
        //   408: ldc             -2071085058
        //   410: goto            415
        //   413: ldc             897486141
        //   415: ldc             -54429590
        //   417: ixor           
        //   418: lookupswitch {
        //          -910166697: 444
        //          2018297748: 413
        //          default: 544
        //        }
        //   444: aload_0        
        //   445: getstatic       dev/nuker/pyro/fc.0:I
        //   448: ifeq            456
        //   451: ldc             420960134
        //   453: goto            458
        //   456: ldc             921816364
        //   458: ldc             -787078025
        //   460: ixor           
        //   461: lookupswitch {
        //          -939428879: 538
        //          462817331: 456
        //          default: 488
        //        }
        //   488: aload_0        
        //   489: new             Ldev/nuker/pyro/f0b;
        //   492: dup            
        //   493: ldc             "\u2933\u149d\u8023"
        //   495: invokestatic    invokestatic   !!! ERROR
        //   498: ldc             "\u2913\u149d\u8023"
        //   500: invokestatic    invokestatic   !!! ERROR
        //   503: aconst_null    
        //   504: new             Ldev/nuker/pyro/fS;
        //   507: dup            
        //   508: fconst_0       
        //   509: fconst_0       
        //   510: fconst_0       
        //   511: ldc             0.5
        //   513: invokespecial   dev/nuker/pyro/fS.<init>:(FFFF)V
        //   516: invokespecial   dev/nuker/pyro/f0b.<init>:(Ljava/lang/String;Ljava/lang/String;Ljava/lang/String;Ldev/nuker/pyro/fS;)V
        //   519: checkcast       Ldev/nuker/pyro/f0n;
        //   522: invokevirtual   dev/nuker/pyro/fa5.c:(Ldev/nuker/pyro/f0n;)Ldev/nuker/pyro/f0n;
        //   525: checkcast       Ldev/nuker/pyro/f0b;
        //   528: putfield        dev/nuker/pyro/fa5.1:Ldev/nuker/pyro/f0b;
        //   531: return         
        //   532: aconst_null    
        //   533: athrow         
        //   534: aconst_null    
        //   535: athrow         
        //   536: aconst_null    
        //   537: athrow         
        //   538: aconst_null    
        //   539: athrow         
        //   540: aconst_null    
        //   541: athrow         
        //   542: aconst_null    
        //   543: athrow         
        //   544: aconst_null    
        //   545: athrow         
        //   546: aconst_null    
        //   547: athrow         
        //   548: aconst_null    
        //   549: athrow         
        //    StackMapTable: 00 24 FF 00 0E 00 01 06 00 02 06 07 00 DE FF 00 01 00 01 06 00 03 06 07 00 DE 01 FF 00 1B 00 01 06 00 02 06 07 00 DE FF 00 0F 00 01 06 00 03 06 07 00 DE 07 00 DE FF 00 01 00 01 06 00 04 06 07 00 DE 07 00 DE 01 FF 00 1D 00 01 06 00 03 06 07 00 DE 07 00 DE FF 00 19 00 01 07 00 03 00 05 07 00 03 07 00 03 08 00 65 08 00 65 07 00 DE FF 00 01 00 01 07 00 03 00 06 07 00 03 07 00 03 08 00 65 08 00 65 07 00 DE 01 FF 00 1B 00 01 07 00 03 00 05 07 00 03 07 00 03 08 00 65 08 00 65 07 00 DE FF 00 1E 00 01 07 00 03 00 0D 07 00 03 07 00 03 08 00 65 08 00 65 07 00 DE 07 00 DE 05 08 00 9D 08 00 9D 02 02 02 02 FF 00 01 00 01 07 00 03 00 0E 07 00 03 07 00 03 08 00 65 08 00 65 07 00 DE 07 00 DE 05 08 00 9D 08 00 9D 02 02 02 02 01 FF 00 1E 00 01 07 00 03 00 0D 07 00 03 07 00 03 08 00 65 08 00 65 07 00 DE 07 00 DE 05 08 00 9D 08 00 9D 02 02 02 02 FF 00 0D 00 01 07 00 03 00 08 07 00 03 07 00 03 08 00 65 08 00 65 07 00 DE 07 00 DE 05 07 00 4C FF 00 01 00 01 07 00 03 00 09 07 00 03 07 00 03 08 00 65 08 00 65 07 00 DE 07 00 DE 05 07 00 4C 01 FF 00 1B 00 01 07 00 03 00 08 07 00 03 07 00 03 08 00 65 08 00 65 07 00 DE 07 00 DE 05 07 00 4C 19 41 01 1B FF 00 26 00 01 07 00 03 00 0D 07 00 03 07 00 03 08 01 3A 08 01 3A 07 00 DE 07 00 DE 05 08 01 49 08 01 49 02 02 02 02 FF 00 01 00 01 07 00 03 00 0E 07 00 03 07 00 03 08 01 3A 08 01 3A 07 00 DE 07 00 DE 05 08 01 49 08 01 49 02 02 02 02 01 FF 00 1E 00 01 07 00 03 00 0D 07 00 03 07 00 03 08 01 3A 08 01 3A 07 00 DE 07 00 DE 05 08 01 49 08 01 49 02 02 02 02 1C 41 01 1C 4B 07 00 03 FF 00 01 00 01 07 00 03 00 02 07 00 03 01 5D 07 00 03 FF 00 2B 00 01 07 00 03 00 0D 07 00 03 07 00 03 08 01 3A 08 01 3A 07 00 DE 07 00 DE 05 08 01 49 08 01 49 02 02 02 02 01 FF 00 01 00 01 07 00 03 00 0D 07 00 03 07 00 03 08 00 65 08 00 65 07 00 DE 07 00 DE 05 08 00 9D 08 00 9D 02 02 02 02 41 07 00 03 FF 00 01 00 01 06 00 02 06 07 00 DE FF 00 01 00 01 07 00 03 00 05 07 00 03 07 00 03 08 00 65 08 00 65 07 00 DE 01 FF 00 01 00 01 07 00 03 00 08 07 00 03 07 00 03 08 00 65 08 00 65 07 00 DE 07 00 DE 05 07 00 4C FF 00 01 00 01 06 00 03 06 07 00 DE 07 00 DE
        // 
        // The error that occurred was:
        // 
        // java.lang.IllegalStateException: Invalid BootstrapMethods attribute entry: 21 additional arguments required for method a.a, but only 0 specified.
        //     at com.strobel.assembler.ir.Error.invalidBootstrapMethodEntry(Error.java:244)
        //     at com.strobel.assembler.ir.MetadataReader.readAttributeCore(MetadataReader.java:280)
        //     at com.strobel.assembler.metadata.ClassFileReader.readAttributeCore(ClassFileReader.java:261)
        //     at com.strobel.assembler.ir.MetadataReader.inflateAttributes(MetadataReader.java:439)
        //     at com.strobel.assembler.metadata.ClassFileReader.visitAttributes(ClassFileReader.java:1134)
        //     at com.strobel.assembler.metadata.ClassFileReader.readClass(ClassFileReader.java:439)
        //     at com.strobel.assembler.metadata.ClassFileReader.readClass(ClassFileReader.java:377)
        //     at com.strobel.assembler.metadata.MetadataSystem.resolveType(MetadataSystem.java:129)
        //     at com.strobel.decompiler.NoRetryMetadataSystem.resolveType(DecompilerDriver.java:476)
        //     at com.strobel.assembler.metadata.MetadataSystem.resolveCore(MetadataSystem.java:81)
        //     at com.strobel.assembler.metadata.MetadataResolver.resolve(MetadataResolver.java:104)
        //     at com.strobel.assembler.metadata.CoreMetadataFactory$UnresolvedType.resolve(CoreMetadataFactory.java:616)
        //     at com.strobel.assembler.metadata.MetadataResolver.resolve(MetadataResolver.java:128)
        //     at com.strobel.assembler.metadata.CoreMetadataFactory$UnresolvedType.resolve(CoreMetadataFactory.java:626)
        //     at com.strobel.assembler.metadata.MethodReference.resolve(MethodReference.java:177)
        //     at com.strobel.decompiler.ast.TypeAnalysis.inferCall(TypeAnalysis.java:2438)
        //     at com.strobel.decompiler.ast.TypeAnalysis.doInferTypeForExpression(TypeAnalysis.java:1029)
        //     at com.strobel.decompiler.ast.TypeAnalysis.inferTypeForExpression(TypeAnalysis.java:803)
        //     at com.strobel.decompiler.ast.TypeAnalysis.inferTypeForExpression(TypeAnalysis.java:770)
        //     at com.strobel.decompiler.ast.TypeAnalysis.doInferTypeForExpression(TypeAnalysis.java:881)
        //     at com.strobel.decompiler.ast.TypeAnalysis.inferTypeForExpression(TypeAnalysis.java:803)
        //     at com.strobel.decompiler.ast.TypeAnalysis.runInference(TypeAnalysis.java:672)
        //     at com.strobel.decompiler.ast.TypeAnalysis.runInference(TypeAnalysis.java:655)
        //     at com.strobel.decompiler.ast.TypeAnalysis.runInference(TypeAnalysis.java:365)
        //     at com.strobel.decompiler.ast.TypeAnalysis.run(TypeAnalysis.java:96)
        //     at com.strobel.decompiler.ast.AstOptimizer.optimize(AstOptimizer.java:109)
        //     at com.strobel.decompiler.ast.AstOptimizer.optimize(AstOptimizer.java:42)
        //     at com.strobel.decompiler.languages.java.ast.AstMethodBodyBuilder.createMethodBody(AstMethodBodyBuilder.java:214)
        //     at com.strobel.decompiler.languages.java.ast.AstMethodBodyBuilder.createMethodBody(AstMethodBodyBuilder.java:99)
        //     at com.strobel.decompiler.languages.java.ast.AstBuilder.createMethodBody(AstBuilder.java:782)
        //     at com.strobel.decompiler.languages.java.ast.AstBuilder.createConstructor(AstBuilder.java:713)
        //     at com.strobel.decompiler.languages.java.ast.AstBuilder.addTypeMembers(AstBuilder.java:549)
        //     at com.strobel.decompiler.languages.java.ast.AstBuilder.createTypeCore(AstBuilder.java:519)
        //     at com.strobel.decompiler.languages.java.ast.AstBuilder.createTypeNoCache(AstBuilder.java:161)
        //     at com.strobel.decompiler.languages.java.ast.AstBuilder.createType(AstBuilder.java:150)
        //     at com.strobel.decompiler.languages.java.ast.AstBuilder.addType(AstBuilder.java:125)
        //     at com.strobel.decompiler.languages.java.JavaLanguage.buildAst(JavaLanguage.java:71)
        //     at com.strobel.decompiler.languages.java.JavaLanguage.decompileType(JavaLanguage.java:59)
        //     at com.strobel.decompiler.DecompilerDriver.decompileType(DecompilerDriver.java:330)
        //     at com.strobel.decompiler.DecompilerDriver.decompileJar(DecompilerDriver.java:251)
        //     at com.strobel.decompiler.DecompilerDriver.main(DecompilerDriver.java:126)
        // 
        throw new IllegalStateException("An error occurred while decompiling this method.");
    }
    
    static {
        throw t;
    }
    
    @NotNull
    public f0b 3() {
        return fbS.1F(this, 1179780083);
    }
    
    public void 0(@NotNull final f0b f0b) {
        fbS.7X(this, 739167932, f0b);
    }
    
    @NotNull
    public f0b 4() {
        return fbS.1z(this, 1927244550);
    }
    
    public void 1(@NotNull final f0b f0b) {
        fbS.7Z(this, 944869642, f0b);
    }
    
    @NotNull
    public float[] 2() {
        return fbS.k(this, 2034803336);
    }
}
