// 
// Decompiled by Procyon v0.5.36
// 

package dev.nuker.pyro;

import org.jetbrains.annotations.Nullable;
import java.io.File;
import org.jetbrains.annotations.NotNull;
import dev.nuker.pyro.hacks.stashfinder.StashFinderConfig;

public class faC
{
    @NotNull
    public StashFinderConfig 2() {
        return fbS.3E(this, 448931671);
    }
    
    @Nullable
    public File 1() {
        return fbS.2r(this, 1999017694);
    }
    
    @NotNull
    public faG 0() {
        return fbS.8X(this, 118935800);
    }
    
    public void c(@NotNull final faG faG) {
        fbS.6S(this, 203781866, faG);
    }
    
    public void c(@Nullable final File file) {
        fbS.8I(this, 1487231405, file);
    }
    
    @NotNull
    public File c(@NotNull final String p0) {
        // 
        // This method could not be decompiled.
        // 
        // Original Bytecode:
        // 
        //     3: dup            
        //     4: ifnull          337
        //     7: athrow         
        //     8: aconst_null    
        //     9: getstatic       dev/nuker/pyro/fc.0:I
        //    12: ifgt            329
        //    15: pop            
        //    16: aconst_null    
        //    17: goto            321
        //    20: nop            
        //    21: nop            
        //    22: nop            
        //    23: athrow         
        //    24: aload_1        
        //    25: pop            
        //    26: iconst_0       
        //    27: istore_2       
        //    28: new             Ljava/io/File;
        //    31: dup            
        //    32: new             Ljava/lang/StringBuilder;
        //    35: dup            
        //    36: goto            40
        //    39: athrow         
        //    40: invokespecial   java/lang/StringBuilder.<init>:()V
        //    43: goto            47
        //    46: athrow         
        //    47: aload_1        
        //    48: getstatic       dev/nuker/pyro/fc.0:I
        //    51: ifeq            59
        //    54: ldc             -661372328
        //    56: goto            61
        //    59: ldc             1594899499
        //    61: ldc             1895248304
        //    63: ixor           
        //    64: lookupswitch {
        //          -1469877272: 310
        //          1976973804: 59
        //          default: 92
        //        }
        //    92: goto            96
        //    95: athrow         
        //    96: invokevirtual   java/lang/StringBuilder.append:(Ljava/lang/String;)Ljava/lang/StringBuilder;
        //    99: goto            103
        //   102: athrow         
        //   103: iload_2        
        //   104: goto            108
        //   107: athrow         
        //   108: invokevirtual   java/lang/StringBuilder.append:(I)Ljava/lang/StringBuilder;
        //   111: goto            115
        //   114: athrow         
        //   115: goto            119
        //   118: athrow         
        //   119: invokevirtual   java/lang/StringBuilder.toString:()Ljava/lang/String;
        //   122: goto            126
        //   125: athrow         
        //   126: getstatic       dev/nuker/pyro/fc.0:I
        //   129: ifeq            137
        //   132: ldc             -1220904339
        //   134: goto            139
        //   137: ldc             593181907
        //   139: ldc             -1251483673
        //   141: ixor           
        //   142: lookupswitch {
        //          -1295193932: 137
        //          39691658: 306
        //          default: 168
        //        }
        //   168: goto            172
        //   171: athrow         
        //   172: invokespecial   java/io/File.<init>:(Ljava/lang/String;)V
        //   175: goto            179
        //   178: athrow         
        //   179: goto            183
        //   182: athrow         
        //   183: invokevirtual   java/io/File.exists:()Z
        //   186: goto            190
        //   189: athrow         
        //   190: ifeq            199
        //   193: iinc            2, 1
        //   196: goto            28
        //   199: new             Ljava/io/File;
        //   202: dup            
        //   203: new             Ljava/lang/StringBuilder;
        //   206: dup            
        //   207: getstatic       dev/nuker/pyro/fc.0:I
        //   210: ifeq            218
        //   213: ldc             -2060304332
        //   215: goto            220
        //   218: ldc             -1037650013
        //   220: ldc             -141196065
        //   222: ixor           
        //   223: lookupswitch {
        //          -617250339: 218
        //          1923597547: 308
        //          default: 248
        //        }
        //   248: goto            252
        //   251: athrow         
        //   252: invokespecial   java/lang/StringBuilder.<init>:()V
        //   255: goto            259
        //   258: athrow         
        //   259: aload_1        
        //   260: goto            264
        //   263: athrow         
        //   264: invokevirtual   java/lang/StringBuilder.append:(Ljava/lang/String;)Ljava/lang/StringBuilder;
        //   267: goto            271
        //   270: athrow         
        //   271: iload_2        
        //   272: goto            276
        //   275: athrow         
        //   276: invokevirtual   java/lang/StringBuilder.append:(I)Ljava/lang/StringBuilder;
        //   279: goto            283
        //   282: athrow         
        //   283: goto            287
        //   286: athrow         
        //   287: invokevirtual   java/lang/StringBuilder.toString:()Ljava/lang/String;
        //   290: goto            294
        //   293: athrow         
        //   294: goto            298
        //   297: athrow         
        //   298: invokespecial   java/io/File.<init>:(Ljava/lang/String;)V
        //   301: goto            305
        //   304: athrow         
        //   305: areturn        
        //   306: aconst_null    
        //   307: athrow         
        //   308: aconst_null    
        //   309: athrow         
        //   310: aconst_null    
        //   311: athrow         
        //   312: pop            
        //   313: goto            24
        //   316: pop            
        //   317: aconst_null    
        //   318: goto            312
        //   321: dup            
        //   322: ifnull          312
        //   325: checkcast       Ljava/lang/Throwable;
        //   328: athrow         
        //   329: dup            
        //   330: ifnull          316
        //   333: checkcast       Ljava/lang/Throwable;
        //   336: athrow         
        //   337: aconst_null    
        //   338: athrow         
        //    StackMapTable: 00 43 FF 00 03 00 03 07 00 03 07 00 72 01 00 01 07 00 4D FA 00 04 FF 00 0B 00 00 00 01 07 00 4D FD 00 03 07 00 03 07 00 72 FC 00 03 01 4A 07 00 4D FF 00 00 00 03 07 00 03 07 00 72 01 00 04 08 00 1C 08 00 1C 08 00 20 08 00 20 45 07 00 4D FF 00 00 00 03 07 00 03 07 00 72 01 00 03 08 00 1C 08 00 1C 07 00 51 FF 00 0B 00 03 07 00 03 07 00 72 01 00 04 08 00 1C 08 00 1C 07 00 51 07 00 72 FF 00 01 00 03 07 00 03 07 00 72 01 00 05 08 00 1C 08 00 1C 07 00 51 07 00 72 01 FF 00 1E 00 03 07 00 03 07 00 72 01 00 04 08 00 1C 08 00 1C 07 00 51 07 00 72 42 07 00 30 FF 00 00 00 03 07 00 03 07 00 72 01 00 04 08 00 1C 08 00 1C 07 00 51 07 00 72 45 07 00 4D FF 00 00 00 03 07 00 03 07 00 72 01 00 03 08 00 1C 08 00 1C 07 00 51 43 07 00 4D FF 00 00 00 03 07 00 03 07 00 72 01 00 04 08 00 1C 08 00 1C 07 00 51 01 45 07 00 4D FF 00 00 00 03 07 00 03 07 00 72 01 00 03 08 00 1C 08 00 1C 07 00 51 42 07 00 32 FF 00 00 00 03 07 00 03 07 00 72 01 00 03 08 00 1C 08 00 1C 07 00 51 45 07 00 4D FF 00 00 00 03 07 00 03 07 00 72 01 00 03 08 00 1C 08 00 1C 07 00 72 FF 00 0A 00 03 07 00 03 07 00 72 01 00 03 08 00 1C 08 00 1C 07 00 72 FF 00 01 00 03 07 00 03 07 00 72 01 00 04 08 00 1C 08 00 1C 07 00 72 01 FF 00 1C 00 03 07 00 03 07 00 72 01 00 03 08 00 1C 08 00 1C 07 00 72 42 07 00 3A FF 00 00 00 03 07 00 03 07 00 72 01 00 03 08 00 1C 08 00 1C 07 00 72 45 07 00 4D 40 07 00 4F 42 07 00 4D 40 07 00 4F 45 07 00 4D 40 01 08 FF 00 12 00 03 07 00 03 07 00 72 01 00 04 08 00 C7 08 00 C7 08 00 CB 08 00 CB FF 00 01 00 03 07 00 03 07 00 72 01 00 05 08 00 C7 08 00 C7 08 00 CB 08 00 CB 01 FF 00 1B 00 03 07 00 03 07 00 72 01 00 04 08 00 C7 08 00 C7 08 00 CB 08 00 CB 42 07 00 4D FF 00 00 00 03 07 00 03 07 00 72 01 00 04 08 00 C7 08 00 C7 08 00 CB 08 00 CB 45 07 00 4D FF 00 00 00 03 07 00 03 07 00 72 01 00 03 08 00 C7 08 00 C7 07 00 51 43 07 00 4D FF 00 00 00 03 07 00 03 07 00 72 01 00 04 08 00 C7 08 00 C7 07 00 51 07 00 72 45 07 00 4D FF 00 00 00 03 07 00 03 07 00 72 01 00 03 08 00 C7 08 00 C7 07 00 51 FF 00 03 00 00 00 01 07 00 4D FF 00 00 00 03 07 00 03 07 00 72 01 00 04 08 00 C7 08 00 C7 07 00 51 01 45 07 00 4D FF 00 00 00 03 07 00 03 07 00 72 01 00 03 08 00 C7 08 00 C7 07 00 51 42 07 00 4D FF 00 00 00 03 07 00 03 07 00 72 01 00 03 08 00 C7 08 00 C7 07 00 51 45 07 00 4D FF 00 00 00 03 07 00 03 07 00 72 01 00 03 08 00 C7 08 00 C7 07 00 72 42 07 00 36 FF 00 00 00 03 07 00 03 07 00 72 01 00 03 08 00 C7 08 00 C7 07 00 72 45 07 00 4D 40 07 00 4F FF 00 00 00 03 07 00 03 07 00 72 01 00 03 08 00 1C 08 00 1C 07 00 72 FF 00 01 00 03 07 00 03 07 00 72 01 00 04 08 00 C7 08 00 C7 08 00 CB 08 00 CB FF 00 01 00 03 07 00 03 07 00 72 01 00 04 08 00 1C 08 00 1C 07 00 51 07 00 72 FF 00 01 00 02 07 00 03 07 00 72 00 01 07 00 4D 43 05 44 07 00 4D 47 05 FF 00 07 00 03 07 00 03 07 00 72 01 00 01 07 00 4D
        //    Exceptions:
        //  Try           Handler
        //  Start  End    Start  End    Type                                       
        //  -----  -----  -----  -----  -------------------------------------------
        //  8      20     321    329    Any
        //  321    329    321    329    Any
        //  337    339    3      8      Any
        //  39     46     46     47     Any
        //  40     46     39     40     Any
        //  39     46     46     47     Any
        //  40     46     3      8      Ljava/lang/NumberFormatException;
        //  39     46     3      8      Any
        //  95     102    102    103    Any
        //  95     102    3      8      Ljava/lang/NumberFormatException;
        //  96     102    95     96     Ljava/lang/NullPointerException;
        //  95     102    3      8      Any
        //  95     102    102    103    Any
        //  107    114    114    115    Any
        //  108    114    107    108    Any
        //  107    114    3      8      Any
        //  108    114    107    108    Any
        //  107    114    107    108    Any
        //  118    125    125    126    Any
        //  119    125    118    119    Ljava/util/NoSuchElementException;
        //  118    125    3      8      Ljava/lang/StringIndexOutOfBoundsException;
        //  118    125    3      8      Ljava/lang/NullPointerException;
        //  119    125    125    126    Ljava/lang/RuntimeException;
        //  171    178    178    179    Any
        //  171    178    3      8      Any
        //  172    178    3      8      Any
        //  172    178    178    179    Ljava/lang/IllegalArgumentException;
        //  171    178    171    172    Ljava/util/ConcurrentModificationException;
        //  182    189    189    190    Any
        //  183    189    3      8      Ljava/util/NoSuchElementException;
        //  183    189    182    183    Any
        //  183    189    189    190    Any
        //  183    189    3      8      Any
        //  251    258    258    259    Any
        //  252    258    251    252    Ljava/lang/EnumConstantNotPresentException;
        //  251    258    3      8      Any
        //  251    258    258    259    Ljava/lang/NegativeArraySizeException;
        //  251    258    251    252    Any
        //  263    270    270    271    Any
        //  263    270    263    264    Any
        //  263    270    263    264    Any
        //  263    270    270    271    Ljava/lang/EnumConstantNotPresentException;
        //  263    270    3      8      Ljava/util/ConcurrentModificationException;
        //  276    282    282    283    Any
        //  276    282    3      8      Any
        //  276    282    3      8      Ljava/lang/NullPointerException;
        //  276    282    3      8      Any
        //  276    282    282    283    Ljava/lang/RuntimeException;
        //  286    293    293    294    Any
        //  287    293    286    287    Ljava/lang/UnsupportedOperationException;
        //  286    293    286    287    Any
        //  286    293    3      8      Any
        //  286    293    3      8      Any
        //  297    304    304    305    Any
        //  298    304    297    298    Ljava/lang/RuntimeException;
        //  297    304    3      8      Ljava/lang/ClassCastException;
        //  298    304    3      8      Ljava/lang/IllegalStateException;
        //  298    304    3      8      Ljava/lang/ArrayIndexOutOfBoundsException;
        // 
        // The error that occurred was:
        // 
        // java.lang.IndexOutOfBoundsException: Index -1 out of bounds for length 0
        //     at java.base/jdk.internal.util.Preconditions.outOfBounds(Preconditions.java:64)
        //     at java.base/jdk.internal.util.Preconditions.outOfBoundsCheckIndex(Preconditions.java:70)
        //     at java.base/jdk.internal.util.Preconditions.checkIndex(Preconditions.java:248)
        //     at java.base/java.util.Objects.checkIndex(Objects.java:372)
        //     at java.base/java.util.ArrayList.remove(ArrayList.java:535)
        //     at com.strobel.assembler.ir.StackMappingVisitor.pop(StackMappingVisitor.java:267)
        //     at com.strobel.assembler.ir.StackMappingVisitor$InstructionAnalyzer.execute(StackMappingVisitor.java:776)
        //     at com.strobel.assembler.ir.StackMappingVisitor$InstructionAnalyzer.visit(StackMappingVisitor.java:398)
        //     at com.strobel.decompiler.ast.AstBuilder.performStackAnalysis(AstBuilder.java:2030)
        //     at com.strobel.decompiler.ast.AstBuilder.build(AstBuilder.java:108)
        //     at com.strobel.decompiler.languages.java.ast.AstMethodBodyBuilder.createMethodBody(AstMethodBodyBuilder.java:211)
        //     at com.strobel.decompiler.languages.java.ast.AstMethodBodyBuilder.createMethodBody(AstMethodBodyBuilder.java:99)
        //     at com.strobel.decompiler.languages.java.ast.AstBuilder.createMethodBody(AstBuilder.java:782)
        //     at com.strobel.decompiler.languages.java.ast.AstBuilder.createMethod(AstBuilder.java:675)
        //     at com.strobel.decompiler.languages.java.ast.AstBuilder.addTypeMembers(AstBuilder.java:552)
        //     at com.strobel.decompiler.languages.java.ast.AstBuilder.createTypeCore(AstBuilder.java:519)
        //     at com.strobel.decompiler.languages.java.ast.AstBuilder.createTypeNoCache(AstBuilder.java:161)
        //     at com.strobel.decompiler.languages.java.ast.AstBuilder.createType(AstBuilder.java:150)
        //     at com.strobel.decompiler.languages.java.ast.AstBuilder.addType(AstBuilder.java:125)
        //     at com.strobel.decompiler.languages.java.JavaLanguage.buildAst(JavaLanguage.java:71)
        //     at com.strobel.decompiler.languages.java.JavaLanguage.decompileType(JavaLanguage.java:59)
        //     at com.strobel.decompiler.DecompilerDriver.decompileType(DecompilerDriver.java:330)
        //     at com.strobel.decompiler.DecompilerDriver.decompileJar(DecompilerDriver.java:251)
        //     at com.strobel.decompiler.DecompilerDriver.main(DecompilerDriver.java:126)
        // 
        throw new IllegalStateException("An error occurred while decompiling this method.");
    }
    
    public faC() {
        while (true) {
            int n = 0;
            Label_0014: {
                if (fc.c < 0) {
                    n = 780739337;
                    break Label_0014;
                }
                n = 1205434447;
            }
            switch (n ^ 0x8955084E) {
                case 1640529357: {
                    continue;
                }
                default: {}
                case -1478743225: {
                    throw null;
                }
            }
            break;
        }
    }
    
    public void c(@NotNull final StashFinderConfig stashFinderConfig) {
        fbS.ff(this, 1593552134, stashFinderConfig);
    }
    
    static {
        throw t;
    }
    
    public void c() {
        // 
        // This method could not be decompiled.
        // 
        // Original Bytecode:
        // 
        //     3: dup            
        //     4: ifnull          3177
        //     7: athrow         
        //     8: aconst_null    
        //     9: getstatic       dev/nuker/pyro/fc.c:I
        //    12: iflt            3169
        //    15: pop            
        //    16: aconst_null    
        //    17: goto            3161
        //    20: nop            
        //    21: nop            
        //    22: nop            
        //    23: athrow         
        //    24: getstatic       dev/nuker/pyro/f4N.c:Ldev/nuker/pyro/faH;
        //    27: getfield        dev/nuker/pyro/faH.c:Ldev/nuker/pyro/fw;
        //    30: getstatic       dev/nuker/pyro/fc.1:I
        //    33: ifeq            41
        //    36: ldc             -2039002314
        //    38: goto            43
        //    41: ldc             1620419573
        //    43: ldc             1786273184
        //    45: ixor           
        //    46: lookupswitch {
        //          -1512196383: 41
        //          -334555498: 3118
        //          default: 72
        //        }
        //    72: goto            76
        //    75: athrow         
        //    76: invokevirtual   dev/nuker/pyro/fw.0:()Ljava/lang/Object;
        //    79: goto            83
        //    82: athrow         
        //    83: dup            
        //    84: pop            
        //    85: checkcast       Ljava/lang/Boolean;
        //    88: goto            92
        //    91: athrow         
        //    92: invokevirtual   java/lang/Boolean.booleanValue:()Z
        //    95: goto            99
        //    98: athrow         
        //    99: ifeq            3077
        //   102: nop            
        //   103: aload_0        
        //   104: checkcast       Ldev/nuker/pyro/faC;
        //   107: goto            111
        //   110: athrow         
        //   111: invokevirtual   dev/nuker/pyro/faC.1:()Ljava/io/File;
        //   114: goto            118
        //   117: athrow         
        //   118: dup            
        //   119: ifnonnull       127
        //   122: ldc             564357252
        //   124: goto            129
        //   127: ldc             564357307
        //   129: ldc             -1541798309
        //   131: ixor           
        //   132: tableswitch {
        //          192077246: 156
        //          192077247: 167
        //          default: 122
        //        }
        //   156: goto            160
        //   159: athrow         
        //   160: invokestatic    kotlin/jvm/internal/Intrinsics.throwNpe:()V
        //   163: goto            167
        //   166: athrow         
        //   167: goto            171
        //   170: athrow         
        //   171: invokevirtual   java/io/File.exists:()Z
        //   174: goto            178
        //   177: athrow         
        //   178: ifne            299
        //   181: aload_0        
        //   182: checkcast       Ldev/nuker/pyro/faC;
        //   185: goto            189
        //   188: athrow         
        //   189: invokevirtual   dev/nuker/pyro/faC.1:()Ljava/io/File;
        //   192: goto            196
        //   195: athrow         
        //   196: dup            
        //   197: ifnonnull       205
        //   200: ldc             21875346
        //   202: goto            207
        //   205: ldc             21875373
        //   207: ldc             823515341
        //   209: ixor           
        //   210: tableswitch {
        //          1622156478: 232
        //          1622156479: 287
        //          default: 200
        //        }
        //   232: getstatic       dev/nuker/pyro/fc.1:I
        //   235: ifeq            243
        //   238: ldc             -1859195132
        //   240: goto            245
        //   243: ldc             -1455299
        //   245: ldc             1914222189
        //   247: ixor           
        //   248: lookupswitch {
        //          -1913553584: 276
        //          -482977431: 243
        //          default: 3078
        //        }
        //   276: goto            280
        //   279: athrow         
        //   280: invokestatic    kotlin/jvm/internal/Intrinsics.throwNpe:()V
        //   283: goto            287
        //   286: athrow         
        //   287: goto            291
        //   290: athrow         
        //   291: invokevirtual   java/io/File.mkdirs:()Z
        //   294: goto            298
        //   297: athrow         
        //   298: pop            
        //   299: new             Ljava/io/File;
        //   302: dup            
        //   303: getstatic       dev/nuker/pyro/fc.0:I
        //   306: ifeq            314
        //   309: ldc             1394276855
        //   311: goto            316
        //   314: ldc             -1302648783
        //   316: ldc             -474611541
        //   318: ixor           
        //   319: lookupswitch {
        //          -1330841252: 314
        //          1374496922: 344
        //          default: 3146
        //        }
        //   344: aload_0        
        //   345: checkcast       Ldev/nuker/pyro/faC;
        //   348: goto            352
        //   351: athrow         
        //   352: invokevirtual   dev/nuker/pyro/faC.1:()Ljava/io/File;
        //   355: goto            359
        //   358: athrow         
        //   359: ldc             "\u2933\u1487\u8038\ub1db\uc496\ue723\ub237\uec5a\udb6d\ue4f5\uadf2"
        //   361: goto            365
        //   364: athrow         
        //   365: invokestatic    invokestatic   !!! ERROR
        //   368: goto            372
        //   371: athrow         
        //   372: goto            376
        //   375: athrow         
        //   376: invokespecial   java/io/File.<init>:(Ljava/io/File;Ljava/lang/String;)V
        //   379: goto            383
        //   382: athrow         
        //   383: goto            387
        //   386: athrow         
        //   387: invokevirtual   java/io/File.delete:()Z
        //   390: goto            394
        //   393: athrow         
        //   394: pop            
        //   395: new             Ljava/io/OutputStreamWriter;
        //   398: dup            
        //   399: new             Ljava/io/FileOutputStream;
        //   402: dup            
        //   403: new             Ljava/io/File;
        //   406: dup            
        //   407: aload_0        
        //   408: checkcast       Ldev/nuker/pyro/faC;
        //   411: goto            415
        //   414: athrow         
        //   415: invokevirtual   dev/nuker/pyro/faC.1:()Ljava/io/File;
        //   418: goto            422
        //   421: athrow         
        //   422: ldc             "\u2933\u1487\u8038\ub1db\uc496\ue723\ub237\uec5a\udb6d\ue4f5\uadf2"
        //   424: goto            428
        //   427: athrow         
        //   428: invokestatic    invokestatic   !!! ERROR
        //   431: goto            435
        //   434: athrow         
        //   435: goto            439
        //   438: athrow         
        //   439: invokespecial   java/io/File.<init>:(Ljava/io/File;Ljava/lang/String;)V
        //   442: goto            446
        //   445: athrow         
        //   446: iconst_0       
        //   447: goto            451
        //   450: athrow         
        //   451: invokespecial   java/io/FileOutputStream.<init>:(Ljava/io/File;Z)V
        //   454: goto            458
        //   457: athrow         
        //   458: checkcast       Ljava/io/OutputStream;
        //   461: getstatic       dev/nuker/pyro/fc.0:I
        //   464: ifeq            472
        //   467: ldc             447795057
        //   469: goto            474
        //   472: ldc             2025222878
        //   474: ldc             -1103115537
        //   476: ixor           
        //   477: lookupswitch {
        //          -1534130786: 472
        //          -964052943: 504
        //          default: 3094
        //        }
        //   504: getstatic       com/google/common/base/Charsets.UTF_8:Ljava/nio/charset/Charset;
        //   507: goto            511
        //   510: athrow         
        //   511: invokespecial   java/io/OutputStreamWriter.<init>:(Ljava/io/OutputStream;Ljava/nio/charset/Charset;)V
        //   514: goto            518
        //   517: athrow         
        //   518: getstatic       dev/nuker/pyro/fc.0:I
        //   521: ifeq            529
        //   524: ldc             -349172962
        //   526: goto            531
        //   529: ldc             825406137
        //   531: ldc             -2052454790
        //   533: ixor           
        //   534: lookupswitch {
        //          1091381436: 529
        //          1855589732: 3126
        //          default: 560
        //        }
        //   560: astore_1       
        //   561: aload_0        
        //   562: checkcast       Ldev/nuker/pyro/faC;
        //   565: goto            569
        //   568: athrow         
        //   569: invokevirtual   dev/nuker/pyro/faC.0:()Ldev/nuker/pyro/faG;
        //   572: goto            576
        //   575: athrow         
        //   576: goto            580
        //   579: athrow         
        //   580: invokestatic    dev/nuker/pyro/faG.0:(Ldev/nuker/pyro/faG;)Ljava/lang/Thread;
        //   583: goto            587
        //   586: athrow         
        //   587: dup            
        //   588: ifnonnull       602
        //   591: goto            595
        //   594: athrow         
        //   595: invokestatic    kotlin/jvm/internal/Intrinsics.throwNpe:()V
        //   598: goto            602
        //   601: athrow         
        //   602: getstatic       dev/nuker/pyro/fc.1:I
        //   605: ifeq            613
        //   608: ldc             1362955787
        //   610: goto            615
        //   613: ldc             204308208
        //   615: ldc             -291438957
        //   617: ixor           
        //   618: lookupswitch {
        //          -1080168296: 613
        //          -494043037: 644
        //          default: 3098
        //        }
        //   644: astore_2       
        //   645: iconst_0       
        //   646: istore_3       
        //   647: iconst_0       
        //   648: istore          4
        //   650: aload_2        
        //   651: monitorenter   
        //   652: nop            
        //   653: iconst_0       
        //   654: istore          5
        //   656: getstatic       dev/nuker/pyro/faG.c:Ldev/nuker/pyro/faC;
        //   659: goto            663
        //   662: athrow         
        //   663: invokevirtual   dev/nuker/pyro/faC.0:()Ldev/nuker/pyro/faG;
        //   666: goto            670
        //   669: athrow         
        //   670: goto            674
        //   673: athrow         
        //   674: invokevirtual   dev/nuker/pyro/faG.3:()Ljava/util/List;
        //   677: goto            681
        //   680: athrow         
        //   681: goto            685
        //   684: athrow         
        //   685: invokeinterface java/util/List.iterator:()Ljava/util/Iterator;
        //   690: goto            694
        //   693: athrow         
        //   694: astore          6
        //   696: aload           6
        //   698: goto            702
        //   701: athrow         
        //   702: invokeinterface java/util/Iterator.hasNext:()Z
        //   707: goto            711
        //   710: athrow         
        //   711: ifeq            719
        //   714: ldc             -1820534366
        //   716: goto            721
        //   719: ldc             -1820534363
        //   721: ldc             -178336023
        //   723: ixor           
        //   724: tableswitch {
        //          -867946858: 748
        //          -867946857: 2330
        //          default: 714
        //        }
        //   748: getstatic       dev/nuker/pyro/fc.0:I
        //   751: ifeq            759
        //   754: ldc             -135960740
        //   756: goto            761
        //   759: ldc             -533502868
        //   761: ldc             -834195974
        //   763: ixor           
        //   764: lookupswitch {
        //          -88386416: 759
        //          966937254: 3080
        //          default: 792
        //        }
        //   792: aload           6
        //   794: goto            798
        //   797: athrow         
        //   798: invokeinterface java/util/Iterator.next:()Ljava/lang/Object;
        //   803: goto            807
        //   806: athrow         
        //   807: checkcast       Ldev/nuker/pyro/faB;
        //   810: astore          7
        //   812: aload           7
        //   814: goto            818
        //   817: athrow         
        //   818: invokevirtual   dev/nuker/pyro/faB.0:()Ldev/nuker/pyro/hacks/stashfinder/StashFinderConfig$StashDefinition;
        //   821: goto            825
        //   824: athrow         
        //   825: dup            
        //   826: ifnull          832
        //   829: goto            836
        //   832: pop            
        //   833: goto            2327
        //   836: astore          8
        //   838: getstatic       dev/nuker/pyro/fa.c:Ldev/nuker/pyro/f9;
        //   841: aload           7
        //   843: aload           8
        //   845: goto            849
        //   848: athrow         
        //   849: invokevirtual   dev/nuker/pyro/faB.c:(Ldev/nuker/pyro/hacks/stashfinder/StashFinderConfig$StashDefinition;)Ljava/lang/String;
        //   852: goto            856
        //   855: athrow         
        //   856: getstatic       dev/nuker/pyro/fc.1:I
        //   859: ifeq            868
        //   862: ldc_w           -1698549764
        //   865: goto            871
        //   868: ldc_w           -895944234
        //   871: ldc_w           632422921
        //   874: ixor           
        //   875: lookupswitch {
        //          -1083167243: 3144
        //          708775832: 868
        //          default: 900
        //        }
        //   900: goto            904
        //   903: athrow         
        //   904: invokevirtual   dev/nuker/pyro/f9.c:(Ljava/lang/String;)Ldev/nuker/pyro/fa;
        //   907: goto            911
        //   910: athrow         
        //   911: getstatic       dev/nuker/pyro/fc.c:I
        //   914: ifge            923
        //   917: ldc_w           -248931618
        //   920: goto            926
        //   923: ldc_w           -2099670492
        //   926: ldc_w           -457442869
        //   929: ixor           
        //   930: lookupswitch {
        //          -649409473: 923
        //          361915157: 3104
        //          default: 956
        //        }
        //   956: astore          9
        //   958: getstatic       dev/nuker/pyro/fc.c:I
        //   961: ifge            970
        //   964: ldc_w           -357169232
        //   967: goto            973
        //   970: ldc_w           281165784
        //   973: ldc_w           308509438
        //   976: ixor           
        //   977: lookupswitch {
        //          -1702589766: 970
        //          -120226482: 3112
        //          default: 1004
        //        }
        //  1004: aload           8
        //  1006: getstatic       dev/nuker/pyro/fc.c:I
        //  1009: ifge            1018
        //  1012: ldc_w           -25193512
        //  1015: goto            1021
        //  1018: ldc_w           624660027
        //  1021: ldc_w           608009249
        //  1024: ixor           
        //  1025: lookupswitch {
        //          -1807059377: 1018
        //          -633147399: 3084
        //          default: 1052
        //        }
        //  1052: goto            1056
        //  1055: athrow         
        //  1056: invokevirtual   dev/nuker/pyro/hacks/stashfinder/StashFinderConfig$StashDefinition.getSaveLargeLog:()Z
        //  1059: goto            1063
        //  1062: athrow         
        //  1063: ifeq            2195
        //  1066: getstatic       dev/nuker/pyro/faG.c:Ldev/nuker/pyro/faC;
        //  1069: goto            1073
        //  1072: athrow         
        //  1073: invokevirtual   dev/nuker/pyro/faC.0:()Ldev/nuker/pyro/faG;
        //  1076: goto            1080
        //  1079: athrow         
        //  1080: getstatic       dev/nuker/pyro/fc.1:I
        //  1083: ifeq            1092
        //  1086: ldc_w           1159948377
        //  1089: goto            1095
        //  1092: ldc_w           1412585102
        //  1095: ldc_w           1483875701
        //  1098: ixor           
        //  1099: lookupswitch {
        //          -1915352941: 1092
        //          491867436: 3130
        //          default: 1124
        //        }
        //  1124: goto            1128
        //  1127: athrow         
        //  1128: invokevirtual   dev/nuker/pyro/faG.4:()Ljava/util/List;
        //  1131: goto            1135
        //  1134: athrow         
        //  1135: aload           7
        //  1137: goto            1141
        //  1140: athrow         
        //  1141: invokeinterface java/util/List.contains:(Ljava/lang/Object;)Z
        //  1146: goto            1150
        //  1149: athrow         
        //  1150: ifeq            2255
        //  1153: new             Ljava/io/File;
        //  1156: dup            
        //  1157: getstatic       dev/nuker/pyro/faG.c:Ldev/nuker/pyro/faC;
        //  1160: goto            1164
        //  1163: athrow         
        //  1164: invokevirtual   dev/nuker/pyro/faC.1:()Ljava/io/File;
        //  1167: goto            1171
        //  1170: athrow         
        //  1171: aload           7
        //  1173: getstatic       dev/nuker/pyro/fc.c:I
        //  1176: ifge            1185
        //  1179: ldc_w           1592334140
        //  1182: goto            1188
        //  1185: ldc_w           -401184849
        //  1188: ldc_w           269723432
        //  1191: ixor           
        //  1192: lookupswitch {
        //          813624789: 1185
        //          1325051924: 3114
        //          default: 1220
        //        }
        //  1220: aload           8
        //  1222: goto            1226
        //  1225: athrow         
        //  1226: invokevirtual   dev/nuker/pyro/faB.0:(Ldev/nuker/pyro/hacks/stashfinder/StashFinderConfig$StashDefinition;)Ljava/lang/String;
        //  1229: goto            1233
        //  1232: athrow         
        //  1233: goto            1237
        //  1236: athrow         
        //  1237: invokespecial   java/io/File.<init>:(Ljava/io/File;Ljava/lang/String;)V
        //  1240: goto            1244
        //  1243: athrow         
        //  1244: astore          10
        //  1246: aload           10
        //  1248: goto            1252
        //  1251: athrow         
        //  1252: invokevirtual   java/io/File.exists:()Z
        //  1255: goto            1259
        //  1258: athrow         
        //  1259: ifne            1320
        //  1262: aload           10
        //  1264: getstatic       dev/nuker/pyro/fc.c:I
        //  1267: ifge            1276
        //  1270: ldc_w           -2101625947
        //  1273: goto            1279
        //  1276: ldc_w           179630022
        //  1279: ldc_w           -688360677
        //  1282: ixor           
        //  1283: lookupswitch {
        //          -598958883: 1308
        //          1413728446: 1276
        //          default: 3106
        //        }
        //  1308: goto            1312
        //  1311: athrow         
        //  1312: invokevirtual   java/io/File.mkdirs:()Z
        //  1315: goto            1319
        //  1318: athrow         
        //  1319: pop            
        //  1320: new             Ljava/io/OutputStreamWriter;
        //  1323: dup            
        //  1324: new             Ljava/io/FileOutputStream;
        //  1327: dup            
        //  1328: new             Ljava/io/File;
        //  1331: dup            
        //  1332: aload           10
        //  1334: ldc_w           "\u292c\u149c\u803e\ub186\uc48a\ue73e\ub230"
        //  1337: goto            1341
        //  1340: athrow         
        //  1341: invokestatic    invokestatic   !!! ERROR
        //  1344: goto            1348
        //  1347: athrow         
        //  1348: getstatic       dev/nuker/pyro/fc.0:I
        //  1351: ifeq            1360
        //  1354: ldc_w           -8855480
        //  1357: goto            1363
        //  1360: ldc_w           -847073847
        //  1363: ldc_w           -821035040
        //  1366: ixor           
        //  1367: lookupswitch {
        //          813113256: 3134
        //          1606451890: 1360
        //          default: 1392
        //        }
        //  1392: goto            1396
        //  1395: athrow         
        //  1396: invokespecial   java/io/File.<init>:(Ljava/io/File;Ljava/lang/String;)V
        //  1399: goto            1403
        //  1402: athrow         
        //  1403: goto            1407
        //  1406: athrow         
        //  1407: invokespecial   java/io/FileOutputStream.<init>:(Ljava/io/File;)V
        //  1410: goto            1414
        //  1413: athrow         
        //  1414: checkcast       Ljava/io/OutputStream;
        //  1417: getstatic       com/google/common/base/Charsets.UTF_8:Ljava/nio/charset/Charset;
        //  1420: goto            1424
        //  1423: athrow         
        //  1424: invokespecial   java/io/OutputStreamWriter.<init>:(Ljava/io/OutputStream;Ljava/nio/charset/Charset;)V
        //  1427: goto            1431
        //  1430: athrow         
        //  1431: astore          11
        //  1433: getstatic       dev/nuker/pyro/fc.0:I
        //  1436: ifeq            1445
        //  1439: ldc_w           1559222919
        //  1442: goto            1448
        //  1445: ldc_w           -1199914461
        //  1448: ldc_w           21860954
        //  1451: ixor           
        //  1452: lookupswitch {
        //          -1187557255: 1480
        //          1570916573: 1445
        //          default: 3136
        //        }
        //  1480: aload           11
        //  1482: aload           7
        //  1484: aload           8
        //  1486: aconst_null    
        //  1487: goto            1491
        //  1490: athrow         
        //  1491: invokevirtual   dev/nuker/pyro/faB.c:(Ldev/nuker/pyro/hacks/stashfinder/StashFinderConfig$StashDefinition;Ljava/lang/String;)Ldev/nuker/pyro/fa;
        //  1494: goto            1498
        //  1497: athrow         
        //  1498: goto            1502
        //  1501: athrow         
        //  1502: invokevirtual   dev/nuker/pyro/fa.toString:()Ljava/lang/String;
        //  1505: goto            1509
        //  1508: athrow         
        //  1509: getstatic       dev/nuker/pyro/fc.0:I
        //  1512: ifeq            1521
        //  1515: ldc_w           1126240268
        //  1518: goto            1524
        //  1521: ldc_w           -1103531051
        //  1524: ldc_w           1516499050
        //  1527: ixor           
        //  1528: lookupswitch {
        //          -1140247344: 1521
        //          423813222: 3124
        //          default: 1556
        //        }
        //  1556: goto            1560
        //  1559: athrow         
        //  1560: invokevirtual   java/io/OutputStreamWriter.write:(Ljava/lang/String;)V
        //  1563: goto            1567
        //  1566: athrow         
        //  1567: getstatic       dev/nuker/pyro/fc.1:I
        //  1570: ifeq            1579
        //  1573: ldc_w           -1004747536
        //  1576: goto            1582
        //  1579: ldc_w           1311987998
        //  1582: ldc_w           1761402636
        //  1585: ixor           
        //  1586: lookupswitch {
        //          -1404352228: 1579
        //          -1394598916: 3138
        //          default: 1612
        //        }
        //  1612: aload           11
        //  1614: goto            1618
        //  1617: athrow         
        //  1618: invokevirtual   java/io/OutputStreamWriter.close:()V
        //  1621: goto            1625
        //  1624: athrow         
        //  1625: aload           9
        //  1627: new             Ljava/lang/StringBuilder;
        //  1630: dup            
        //  1631: goto            1635
        //  1634: athrow         
        //  1635: invokespecial   java/lang/StringBuilder.<init>:()V
        //  1638: goto            1642
        //  1641: athrow         
        //  1642: ldc_w           "\u290c\u149c\u803e\ub188\uc48d\ue727\ub232\uec11\udb7d\ue4ad\uadf2\u1e43\ueb70"
        //  1645: goto            1649
        //  1648: athrow         
        //  1649: invokestatic    invokestatic   !!! ERROR
        //  1652: goto            1656
        //  1655: athrow         
        //  1656: goto            1660
        //  1659: athrow         
        //  1660: invokevirtual   java/lang/StringBuilder.append:(Ljava/lang/String;)Ljava/lang/StringBuilder;
        //  1663: goto            1667
        //  1666: athrow         
        //  1667: new             Ljava/io/File;
        //  1670: dup            
        //  1671: aload           10
        //  1673: ldc_w           "\u292c\u149c\u803e\ub186\uc48a\ue73e\ub230"
        //  1676: goto            1680
        //  1679: athrow         
        //  1680: invokestatic    invokestatic   !!! ERROR
        //  1683: goto            1687
        //  1686: athrow         
        //  1687: getstatic       dev/nuker/pyro/fc.0:I
        //  1690: ifeq            1699
        //  1693: ldc_w           2033602155
        //  1696: goto            1702
        //  1699: ldc_w           -228216380
        //  1702: ldc_w           -878136860
        //  1705: ixor           
        //  1706: lookupswitch {
        //          -1298202737: 1699
        //          969736224: 1732
        //          default: 3082
        //        }
        //  1732: goto            1736
        //  1735: athrow         
        //  1736: invokespecial   java/io/File.<init>:(Ljava/io/File;Ljava/lang/String;)V
        //  1739: goto            1743
        //  1742: athrow         
        //  1743: goto            1747
        //  1746: athrow         
        //  1747: invokevirtual   java/io/File.getAbsolutePath:()Ljava/lang/String;
        //  1750: goto            1754
        //  1753: athrow         
        //  1754: getstatic       dev/nuker/pyro/fc.c:I
        //  1757: ifge            1766
        //  1760: ldc_w           1948924960
        //  1763: goto            1769
        //  1766: ldc_w           -1547878937
        //  1769: ldc_w           714090722
        //  1772: ixor           
        //  1773: lookupswitch {
        //          -1993534203: 1800
        //          1589253314: 1766
        //          default: 3090
        //        }
        //  1800: goto            1804
        //  1803: athrow         
        //  1804: invokevirtual   java/lang/StringBuilder.append:(Ljava/lang/String;)Ljava/lang/StringBuilder;
        //  1807: goto            1811
        //  1810: athrow         
        //  1811: goto            1815
        //  1814: athrow         
        //  1815: invokevirtual   java/lang/StringBuilder.toString:()Ljava/lang/String;
        //  1818: goto            1822
        //  1821: athrow         
        //  1822: getstatic       dev/nuker/pyro/fc.c:I
        //  1825: ifge            1834
        //  1828: ldc_w           691034435
        //  1831: goto            1837
        //  1834: ldc_w           1784311622
        //  1837: ldc_w           -234245723
        //  1840: ixor           
        //  1841: lookupswitch {
        //          -616961818: 3142
        //          1905962942: 1834
        //          default: 1868
        //        }
        //  1868: goto            1872
        //  1871: athrow         
        //  1872: invokevirtual   dev/nuker/pyro/fa.c:(Ljava/lang/String;)V
        //  1875: goto            1879
        //  1878: athrow         
        //  1879: aload           8
        //  1881: goto            1885
        //  1884: athrow         
        //  1885: invokevirtual   dev/nuker/pyro/hacks/stashfinder/StashFinderConfig$StashDefinition.getDownloadChunks:()Z
        //  1888: goto            1892
        //  1891: athrow         
        //  1892: ifeq            2255
        //  1895: aload           9
        //  1897: new             Ljava/lang/StringBuilder;
        //  1900: dup            
        //  1901: goto            1905
        //  1904: athrow         
        //  1905: invokespecial   java/lang/StringBuilder.<init>:()V
        //  1908: goto            1912
        //  1911: athrow         
        //  1912: ldc_w           "\u2917\u149c\u802b\ub1c4\uc49a\ue766\ub220\uec1b\udb6e\ue4e3\uadea\u1e43\ueb31\uc7b2\u8c2a\u83bc\u57b0\u7d91"
        //  1915: getstatic       dev/nuker/pyro/fc.c:I
        //  1918: ifge            1927
        //  1921: ldc_w           -1465776171
        //  1924: goto            1930
        //  1927: ldc_w           1754036850
        //  1930: ldc_w           -627652144
        //  1933: ixor           
        //  1934: lookupswitch {
        //          -1352945420: 1927
        //          1916063237: 3148
        //          default: 1960
        //        }
        //  1960: goto            1964
        //  1963: athrow         
        //  1964: invokestatic    invokestatic   !!! ERROR
        //  1967: goto            1971
        //  1970: athrow         
        //  1971: goto            1975
        //  1974: athrow         
        //  1975: invokevirtual   java/lang/StringBuilder.append:(Ljava/lang/String;)Ljava/lang/StringBuilder;
        //  1978: goto            1982
        //  1981: athrow         
        //  1982: new             Ljava/io/File;
        //  1985: dup            
        //  1986: getstatic       dev/nuker/pyro/fc.1:I
        //  1989: ifeq            1998
        //  1992: ldc_w           -300016897
        //  1995: goto            2001
        //  1998: ldc_w           258077937
        //  2001: ldc_w           1607655087
        //  2004: ixor           
        //  2005: lookupswitch {
        //          -1311980464: 1998
        //          1353919070: 2032
        //          default: 3086
        //        }
        //  2032: aload           10
        //  2034: ldc_w           "\u2924\u149c\u802e\ub1c6\uc492\ue729\ub225\uec10\udb37\ue4f7\uadef\u1e5c"
        //  2037: goto            2041
        //  2040: athrow         
        //  2041: invokestatic    invokestatic   !!! ERROR
        //  2044: goto            2048
        //  2047: athrow         
        //  2048: getstatic       dev/nuker/pyro/fc.1:I
        //  2051: ifeq            2060
        //  2054: ldc_w           261202615
        //  2057: goto            2063
        //  2060: ldc_w           913987856
        //  2063: ldc_w           1608914181
        //  2066: ixor           
        //  2067: lookupswitch {
        //          126008223: 2060
        //          1350023090: 3116
        //          default: 2092
        //        }
        //  2092: goto            2096
        //  2095: athrow         
        //  2096: invokespecial   java/io/File.<init>:(Ljava/io/File;Ljava/lang/String;)V
        //  2099: goto            2103
        //  2102: athrow         
        //  2103: getstatic       dev/nuker/pyro/fc.1:I
        //  2106: ifeq            2115
        //  2109: ldc_w           106729094
        //  2112: goto            2118
        //  2115: ldc_w           -1299883436
        //  2118: ldc_w           2034124069
        //  2121: ixor           
        //  2122: lookupswitch {
        //          -876929167: 2148
        //          2137181091: 2115
        //          default: 3092
        //        }
        //  2148: goto            2152
        //  2151: athrow         
        //  2152: invokevirtual   java/io/File.getAbsolutePath:()Ljava/lang/String;
        //  2155: goto            2159
        //  2158: athrow         
        //  2159: goto            2163
        //  2162: athrow         
        //  2163: invokevirtual   java/lang/StringBuilder.append:(Ljava/lang/String;)Ljava/lang/StringBuilder;
        //  2166: goto            2170
        //  2169: athrow         
        //  2170: goto            2174
        //  2173: athrow         
        //  2174: invokevirtual   java/lang/StringBuilder.toString:()Ljava/lang/String;
        //  2177: goto            2181
        //  2180: athrow         
        //  2181: goto            2185
        //  2184: athrow         
        //  2185: invokevirtual   dev/nuker/pyro/fa.c:(Ljava/lang/String;)V
        //  2188: goto            2192
        //  2191: athrow         
        //  2192: goto            2255
        //  2195: getstatic       dev/nuker/pyro/fc.1:I
        //  2198: ifeq            2207
        //  2201: ldc_w           1832366766
        //  2204: goto            2210
        //  2207: ldc_w           -1609169970
        //  2210: ldc_w           -1940425145
        //  2213: ixor           
        //  2214: lookupswitch {
        //          -513751831: 3122
        //          1589117998: 2207
        //          default: 2240
        //        }
        //  2240: aload           7
        //  2242: aload           9
        //  2244: goto            2248
        //  2247: athrow         
        //  2248: invokevirtual   dev/nuker/pyro/faB.c:(Ldev/nuker/pyro/fa;)V
        //  2251: goto            2255
        //  2254: athrow         
        //  2255: aload_1        
        //  2256: aload           9
        //  2258: goto            2262
        //  2261: athrow         
        //  2262: invokevirtual   dev/nuker/pyro/fa.toString:()Ljava/lang/String;
        //  2265: goto            2269
        //  2268: athrow         
        //  2269: getstatic       dev/nuker/pyro/fc.0:I
        //  2272: ifeq            2281
        //  2275: ldc_w           -2125345532
        //  2278: goto            2284
        //  2281: ldc_w           1371688540
        //  2284: ldc_w           749961832
        //  2287: ixor           
        //  2288: lookupswitch {
        //          -1377677460: 2281
        //          2104609844: 2316
        //          default: 3108
        //        }
        //  2316: goto            2320
        //  2319: athrow         
        //  2320: invokevirtual   java/io/OutputStreamWriter.write:(Ljava/lang/String;)V
        //  2323: goto            2327
        //  2326: athrow         
        //  2327: goto            696
        //  2330: getstatic       dev/nuker/pyro/faG.c:Ldev/nuker/pyro/faC;
        //  2333: getstatic       dev/nuker/pyro/fc.c:I
        //  2336: ifge            2345
        //  2339: ldc_w           1412209845
        //  2342: goto            2348
        //  2345: ldc_w           733730174
        //  2348: ldc_w           962567483
        //  2351: ixor           
        //  2352: lookupswitch {
        //          -18457380: 2345
        //          1836253582: 3096
        //          default: 2380
        //        }
        //  2380: goto            2384
        //  2383: athrow         
        //  2384: invokevirtual   dev/nuker/pyro/faC.0:()Ldev/nuker/pyro/faG;
        //  2387: goto            2391
        //  2390: athrow         
        //  2391: goto            2395
        //  2394: athrow         
        //  2395: invokevirtual   dev/nuker/pyro/faG.4:()Ljava/util/List;
        //  2398: goto            2402
        //  2401: athrow         
        //  2402: goto            2406
        //  2405: athrow         
        //  2406: invokeinterface java/util/List.clear:()V
        //  2411: goto            2415
        //  2414: athrow         
        //  2415: getstatic       dev/nuker/pyro/fc.0:I
        //  2418: ifeq            2427
        //  2421: ldc_w           923255934
        //  2424: goto            2430
        //  2427: ldc_w           -538495618
        //  2430: ldc_w           -1010427570
        //  2433: ixor           
        //  2434: lookupswitch {
        //          -1636113586: 2427
        //          -188621520: 3120
        //          default: 2460
        //        }
        //  2460: getstatic       dev/nuker/pyro/fa.c:Ldev/nuker/pyro/f9;
        //  2463: ldc_w           "\u290c\u149c\u803e\ub1cf\uc49b\ue722\ub264\uec36\udb75\ue4e2\uade5\u1e47\ueb23"
        //  2466: getstatic       dev/nuker/pyro/fc.c:I
        //  2469: ifge            2478
        //  2472: ldc_w           -61912803
        //  2475: goto            2481
        //  2478: ldc_w           -1826267467
        //  2481: ldc_w           1796439241
        //  2484: ixor           
        //  2485: lookupswitch {
        //          -1755564588: 2478
        //          -130669956: 2512
        //          default: 3150
        //        }
        //  2512: goto            2516
        //  2515: athrow         
        //  2516: invokestatic    invokestatic   !!! ERROR
        //  2519: goto            2523
        //  2522: athrow         
        //  2523: goto            2527
        //  2526: athrow         
        //  2527: invokevirtual   dev/nuker/pyro/f9.c:(Ljava/lang/String;)Ldev/nuker/pyro/fa;
        //  2530: goto            2534
        //  2533: athrow         
        //  2534: astore          7
        //  2536: getstatic       dev/nuker/pyro/fc.1:I
        //  2539: ifeq            2548
        //  2542: ldc_w           1137700371
        //  2545: goto            2551
        //  2548: ldc_w           1633699744
        //  2551: ldc_w           -937002011
        //  2554: ixor           
        //  2555: lookupswitch {
        //          -1947625994: 3132
        //          1631888672: 2548
        //          default: 2580
        //        }
        //  2580: getstatic       dev/nuker/pyro/faG.c:Ldev/nuker/pyro/faC;
        //  2583: goto            2587
        //  2586: athrow         
        //  2587: invokevirtual   dev/nuker/pyro/faC.0:()Ldev/nuker/pyro/faG;
        //  2590: goto            2594
        //  2593: athrow         
        //  2594: goto            2598
        //  2597: athrow         
        //  2598: invokevirtual   dev/nuker/pyro/faG.0:()Ljava/util/List;
        //  2601: goto            2605
        //  2604: athrow         
        //  2605: goto            2609
        //  2608: athrow         
        //  2609: invokeinterface java/util/List.iterator:()Ljava/util/Iterator;
        //  2614: goto            2618
        //  2617: athrow         
        //  2618: getstatic       dev/nuker/pyro/fc.c:I
        //  2621: ifge            2630
        //  2624: ldc_w           1890724630
        //  2627: goto            2633
        //  2630: ldc_w           -1688497076
        //  2633: ldc_w           38817810
        //  2636: ixor           
        //  2637: lookupswitch {
        //          542799358: 2630
        //          1927445252: 3110
        //          default: 2664
        //        }
        //  2664: astore          8
        //  2666: aload           8
        //  2668: getstatic       dev/nuker/pyro/fc.c:I
        //  2671: ifge            2680
        //  2674: ldc_w           1989227810
        //  2677: goto            2683
        //  2680: ldc_w           -680026295
        //  2683: ldc_w           1494559892
        //  2686: ixor           
        //  2687: lookupswitch {
        //          627333386: 2680
        //          797186486: 3128
        //          default: 2712
        //        }
        //  2712: goto            2716
        //  2715: athrow         
        //  2716: invokeinterface java/util/Iterator.hasNext:()Z
        //  2721: goto            2725
        //  2724: athrow         
        //  2725: ifeq            2734
        //  2728: ldc_w           1571224932
        //  2731: goto            2737
        //  2734: ldc_w           1571224933
        //  2737: ldc_w           1749482126
        //  2740: ixor           
        //  2741: tableswitch {
        //          1807749076: 2764
        //          1807749077: 2857
        //          default: 2728
        //        }
        //  2764: aload           8
        //  2766: goto            2770
        //  2769: athrow         
        //  2770: invokeinterface java/util/Iterator.next:()Ljava/lang/Object;
        //  2775: goto            2779
        //  2778: athrow         
        //  2779: checkcast       Ldev/nuker/pyro/fax;
        //  2782: astore          6
        //  2784: aload           7
        //  2786: aload           6
        //  2788: getstatic       dev/nuker/pyro/fc.0:I
        //  2791: ifeq            2800
        //  2794: ldc_w           -1740631793
        //  2797: goto            2803
        //  2800: ldc_w           621450346
        //  2803: ldc_w           1008402881
        //  2806: ixor           
        //  2807: lookupswitch {
        //          -1537535794: 3102
        //          1926602944: 2800
        //          default: 2832
        //        }
        //  2832: goto            2836
        //  2835: athrow         
        //  2836: invokevirtual   dev/nuker/pyro/fax.5:()Ldev/nuker/pyro/fa;
        //  2839: goto            2843
        //  2842: athrow         
        //  2843: goto            2847
        //  2846: athrow         
        //  2847: invokevirtual   dev/nuker/pyro/fa.c:(Ldev/nuker/pyro/fa;)V
        //  2850: goto            2854
        //  2853: athrow         
        //  2854: goto            2666
        //  2857: aload_1        
        //  2858: ldc_w           "\n"
        //  2861: goto            2865
        //  2864: athrow         
        //  2865: invokevirtual   java/io/OutputStreamWriter.write:(Ljava/lang/String;)V
        //  2868: goto            2872
        //  2871: athrow         
        //  2872: getstatic       dev/nuker/pyro/fc.0:I
        //  2875: ifeq            2884
        //  2878: ldc_w           1238050762
        //  2881: goto            2887
        //  2884: ldc_w           -932244040
        //  2887: ldc_w           1155045395
        //  2890: ixor           
        //  2891: lookupswitch {
        //          219398105: 3140
        //          1873347500: 2884
        //          default: 2916
        //        }
        //  2916: aload_1        
        //  2917: aload           7
        //  2919: getstatic       dev/nuker/pyro/fc.0:I
        //  2922: ifeq            2931
        //  2925: ldc_w           -237584227
        //  2928: goto            2934
        //  2931: ldc_w           -248887744
        //  2934: ldc_w           1633813214
        //  2937: ixor           
        //  2938: lookupswitch {
        //          -1867201981: 3100
        //          1965496004: 2931
        //          default: 2964
        //        }
        //  2964: goto            2968
        //  2967: athrow         
        //  2968: invokevirtual   dev/nuker/pyro/fa.toString:()Ljava/lang/String;
        //  2971: goto            2975
        //  2974: athrow         
        //  2975: goto            2979
        //  2978: athrow         
        //  2979: invokevirtual   java/io/OutputStreamWriter.write:(Ljava/lang/String;)V
        //  2982: goto            2986
        //  2985: athrow         
        //  2986: aload_1        
        //  2987: goto            2991
        //  2990: athrow         
        //  2991: invokevirtual   java/io/OutputStreamWriter.close:()V
        //  2994: goto            2998
        //  2997: athrow         
        //  2998: nop            
        //  2999: getstatic       kotlin/Unit.INSTANCE:Lkotlin/Unit;
        //  3002: astore          4
        //  3004: aload_2        
        //  3005: monitorexit    
        //  3006: goto            3016
        //  3009: astore          4
        //  3011: aload_2        
        //  3012: monitorexit    
        //  3013: aload           4
        //  3015: athrow         
        //  3016: goto            3077
        //  3019: getstatic       dev/nuker/pyro/fc.0:I
        //  3022: ifeq            3031
        //  3025: ldc_w           -1170046068
        //  3028: goto            3034
        //  3031: ldc_w           -257777693
        //  3034: ldc_w           1110974960
        //  3037: ixor           
        //  3038: lookupswitch {
        //          -1298481645: 3064
        //          -126180740: 3031
        //          default: 3088
        //        }
        //  3064: astore_1       
        //  3065: aload_1        
        //  3066: goto            3070
        //  3069: athrow         
        //  3070: invokevirtual   java/io/IOException.printStackTrace:()V
        //  3073: goto            3077
        //  3076: athrow         
        //  3077: return         
        //  3078: aconst_null    
        //  3079: athrow         
        //  3080: aconst_null    
        //  3081: athrow         
        //  3082: aconst_null    
        //  3083: athrow         
        //  3084: aconst_null    
        //  3085: athrow         
        //  3086: aconst_null    
        //  3087: athrow         
        //  3088: aconst_null    
        //  3089: athrow         
        //  3090: aconst_null    
        //  3091: athrow         
        //  3092: aconst_null    
        //  3093: athrow         
        //  3094: aconst_null    
        //  3095: athrow         
        //  3096: aconst_null    
        //  3097: athrow         
        //  3098: aconst_null    
        //  3099: athrow         
        //  3100: aconst_null    
        //  3101: athrow         
        //  3102: aconst_null    
        //  3103: athrow         
        //  3104: aconst_null    
        //  3105: athrow         
        //  3106: aconst_null    
        //  3107: athrow         
        //  3108: aconst_null    
        //  3109: athrow         
        //  3110: aconst_null    
        //  3111: athrow         
        //  3112: aconst_null    
        //  3113: athrow         
        //  3114: aconst_null    
        //  3115: athrow         
        //  3116: aconst_null    
        //  3117: athrow         
        //  3118: aconst_null    
        //  3119: athrow         
        //  3120: aconst_null    
        //  3121: athrow         
        //  3122: aconst_null    
        //  3123: athrow         
        //  3124: aconst_null    
        //  3125: athrow         
        //  3126: aconst_null    
        //  3127: athrow         
        //  3128: aconst_null    
        //  3129: athrow         
        //  3130: aconst_null    
        //  3131: athrow         
        //  3132: aconst_null    
        //  3133: athrow         
        //  3134: aconst_null    
        //  3135: athrow         
        //  3136: aconst_null    
        //  3137: athrow         
        //  3138: aconst_null    
        //  3139: athrow         
        //  3140: aconst_null    
        //  3141: athrow         
        //  3142: aconst_null    
        //  3143: athrow         
        //  3144: aconst_null    
        //  3145: athrow         
        //  3146: aconst_null    
        //  3147: athrow         
        //  3148: aconst_null    
        //  3149: athrow         
        //  3150: aconst_null    
        //  3151: athrow         
        //  3152: pop            
        //  3153: goto            24
        //  3156: pop            
        //  3157: aconst_null    
        //  3158: goto            3152
        //  3161: dup            
        //  3162: ifnull          3152
        //  3165: checkcast       Ljava/lang/Throwable;
        //  3168: athrow         
        //  3169: dup            
        //  3170: ifnull          3156
        //  3173: checkcast       Ljava/lang/Throwable;
        //  3176: athrow         
        //  3177: aconst_null    
        //  3178: athrow         
        //    StackMapTable: 02 09 43 07 00 4D 04 FF 00 0B 00 00 00 01 07 00 4D FC 00 03 07 00 03 50 07 00 99 FF 00 01 00 01 07 00 03 00 02 07 00 99 01 5C 07 00 99 42 07 00 38 40 07 00 99 45 07 00 4D 40 07 00 05 47 07 00 4D 40 07 00 9E 45 07 00 4D 40 01 4A 07 00 34 40 07 00 03 45 07 00 4D 40 07 00 4F 43 07 00 4F 44 07 00 4F FF 00 01 00 01 07 00 03 00 02 07 00 4F 01 5A 07 00 4F 42 07 00 4D 40 07 00 4F 45 07 00 4D 40 07 00 4F 42 07 00 84 40 07 00 4F 45 07 00 4D 40 01 49 07 00 4D 40 07 00 03 45 07 00 4D 40 07 00 4F 43 07 00 4F 44 07 00 4F FF 00 01 00 01 07 00 03 00 02 07 00 4F 01 58 07 00 4F 4A 07 00 4F FF 00 01 00 01 07 00 03 00 02 07 00 4F 01 5E 07 00 4F 42 07 00 4D 40 07 00 4F 45 07 00 4D 40 07 00 4F 42 07 00 4D 40 07 00 4F 45 07 00 4D 40 01 00 FF 00 0E 00 01 07 00 03 00 02 08 01 2B 08 01 2B FF 00 01 00 01 07 00 03 00 03 08 01 2B 08 01 2B 01 FF 00 1B 00 01 07 00 03 00 02 08 01 2B 08 01 2B 46 07 00 4D FF 00 00 00 01 07 00 03 00 03 08 01 2B 08 01 2B 07 00 03 45 07 00 4D FF 00 00 00 01 07 00 03 00 03 08 01 2B 08 01 2B 07 00 4F 44 07 00 4D FF 00 00 00 01 07 00 03 00 04 08 01 2B 08 01 2B 07 00 4F 07 00 72 45 07 00 4D FF 00 00 00 01 07 00 03 00 04 08 01 2B 08 01 2B 07 00 4F 07 00 72 FF 00 02 00 00 00 01 07 00 4D FF 00 00 00 01 07 00 03 00 04 08 01 2B 08 01 2B 07 00 4F 07 00 72 45 07 00 4D 40 07 00 4F 42 07 00 4D 40 07 00 4F 45 07 00 4D 40 01 53 07 00 4D FF 00 00 00 01 07 00 03 00 07 08 01 8B 08 01 8B 08 01 8F 08 01 8F 08 01 93 08 01 93 07 00 03 45 07 00 4D FF 00 00 00 01 07 00 03 00 07 08 01 8B 08 01 8B 08 01 8F 08 01 8F 08 01 93 08 01 93 07 00 4F FF 00 04 00 00 00 01 07 00 4D FF 00 00 00 01 07 00 03 00 08 08 01 8B 08 01 8B 08 01 8F 08 01 8F 08 01 93 08 01 93 07 00 4F 07 00 72 45 07 00 4D FF 00 00 00 01 07 00 03 00 08 08 01 8B 08 01 8B 08 01 8F 08 01 8F 08 01 93 08 01 93 07 00 4F 07 00 72 42 07 00 30 FF 00 00 00 01 07 00 03 00 08 08 01 8B 08 01 8B 08 01 8F 08 01 8F 08 01 93 08 01 93 07 00 4F 07 00 72 45 07 00 4D FF 00 00 00 01 07 00 03 00 05 08 01 8B 08 01 8B 08 01 8F 08 01 8F 07 00 4F 43 07 00 36 FF 00 00 00 01 07 00 03 00 06 08 01 8B 08 01 8B 08 01 8F 08 01 8F 07 00 4F 01 45 07 00 4D FF 00 00 00 01 07 00 03 00 03 08 01 8B 08 01 8B 07 00 C8 FF 00 0D 00 01 07 00 03 00 03 08 01 8B 08 01 8B 07 00 CD FF 00 01 00 01 07 00 03 00 04 08 01 8B 08 01 8B 07 00 CD 01 FF 00 1D 00 01 07 00 03 00 03 08 01 8B 08 01 8B 07 00 CD 45 07 00 4D FF 00 00 00 01 07 00 03 00 04 08 01 8B 08 01 8B 07 00 CD 07 01 B8 45 07 00 4D 40 07 00 C6 4A 07 00 C6 FF 00 01 00 01 07 00 03 00 02 07 00 C6 01 5C 07 00 C6 FF 00 07 00 02 07 00 03 07 00 C6 00 01 07 00 3C 40 07 00 03 45 07 00 4D 40 07 00 E0 42 07 00 4D 40 07 00 E0 45 07 00 4D 40 07 01 BA 46 07 00 4D 40 07 01 BA 45 07 00 4D 40 07 01 BA 4A 07 01 BA FF 00 01 00 02 07 00 03 07 00 C6 00 02 07 01 BA 01 5C 07 01 BA FF 00 11 00 06 07 00 03 07 00 C6 07 01 BA 01 01 01 00 01 07 00 4D 40 07 00 03 45 07 00 4D 40 07 00 E0 42 07 00 44 40 07 00 E0 45 07 00 4D 40 07 00 EF 42 07 00 4D 40 07 00 EF 47 07 00 4D 40 07 00 F5 FC 00 01 07 00 F5 FF 00 04 00 00 00 01 07 00 4D FF 00 00 00 07 07 00 03 07 00 C6 07 01 BA 01 01 01 07 00 F5 00 01 07 00 F5 47 07 00 4D 40 01 02 04 41 01 1A 0A 41 01 1E FF 00 04 00 00 00 01 07 00 4D FF 00 00 00 07 07 00 03 07 00 C6 07 01 BA 01 01 01 07 00 F5 00 01 07 00 F5 47 07 00 4D 40 07 00 05 FF 00 09 00 08 07 00 03 07 00 C6 07 01 BA 01 01 01 07 00 F5 07 01 03 00 01 07 00 4D 40 07 01 03 45 07 00 4D 40 07 01 21 46 07 01 21 43 07 01 21 FF 00 0B 00 09 07 00 03 07 00 C6 07 01 BA 01 01 01 07 00 F5 07 01 03 07 01 21 00 01 07 00 4D FF 00 00 00 09 07 00 03 07 00 C6 07 01 BA 01 01 01 07 00 F5 07 01 03 07 01 21 00 03 07 01 13 07 01 03 07 01 21 45 07 00 4D FF 00 00 00 09 07 00 03 07 00 C6 07 01 BA 01 01 01 07 00 F5 07 01 03 07 01 21 00 02 07 01 13 07 00 72 FF 00 0B 00 09 07 00 03 07 00 C6 07 01 BA 01 01 01 07 00 F5 07 01 03 07 01 21 00 02 07 01 13 07 00 72 FF 00 02 00 09 07 00 03 07 00 C6 07 01 BA 01 01 01 07 00 F5 07 01 03 07 01 21 00 03 07 01 13 07 00 72 01 FF 00 1C 00 09 07 00 03 07 00 C6 07 01 BA 01 01 01 07 00 F5 07 01 03 07 01 21 00 02 07 01 13 07 00 72 42 07 00 4D FF 00 00 00 09 07 00 03 07 00 C6 07 01 BA 01 01 01 07 00 F5 07 01 03 07 01 21 00 02 07 01 13 07 00 72 45 07 00 4D 40 07 01 08 4B 07 01 08 FF 00 02 00 09 07 00 03 07 00 C6 07 01 BA 01 01 01 07 00 F5 07 01 03 07 01 21 00 02 07 01 08 01 5D 07 01 08 FC 00 0D 07 01 08 42 01 1E 4D 07 01 21 FF 00 02 00 0A 07 00 03 07 00 C6 07 01 BA 01 01 01 07 00 F5 07 01 03 07 01 21 07 01 08 00 02 07 01 21 01 5E 07 01 21 42 07 00 4D 40 07 01 21 45 07 00 4D 40 01 48 07 00 36 40 07 00 03 45 07 00 4D 40 07 00 E0 4B 07 00 E0 FF 00 02 00 0A 07 00 03 07 00 C6 07 01 BA 01 01 01 07 00 F5 07 01 03 07 01 21 07 01 08 00 02 07 00 E0 01 5C 07 00 E0 42 07 00 4D 40 07 00 E0 45 07 00 4D 40 07 00 EF 44 07 00 34 FF 00 00 00 0A 07 00 03 07 00 C6 07 01 BA 01 01 01 07 00 F5 07 01 03 07 01 21 07 01 08 00 02 07 00 EF 07 01 03 47 07 00 4D 40 01 4C 07 00 46 FF 00 00 00 0A 07 00 03 07 00 C6 07 01 BA 01 01 01 07 00 F5 07 01 03 07 01 21 07 01 08 00 03 08 04 81 08 04 81 07 00 03 45 07 00 4D FF 00 00 00 0A 07 00 03 07 00 C6 07 01 BA 01 01 01 07 00 F5 07 01 03 07 01 21 07 01 08 00 03 08 04 81 08 04 81 07 00 4F FF 00 0D 00 0A 07 00 03 07 00 C6 07 01 BA 01 01 01 07 00 F5 07 01 03 07 01 21 07 01 08 00 04 08 04 81 08 04 81 07 00 4F 07 01 03 FF 00 02 00 0A 07 00 03 07 00 C6 07 01 BA 01 01 01 07 00 F5 07 01 03 07 01 21 07 01 08 00 05 08 04 81 08 04 81 07 00 4F 07 01 03 01 FF 00 1F 00 0A 07 00 03 07 00 C6 07 01 BA 01 01 01 07 00 F5 07 01 03 07 01 21 07 01 08 00 04 08 04 81 08 04 81 07 00 4F 07 01 03 FF 00 04 00 00 00 01 07 00 4D FF 00 00 00 0A 07 00 03 07 00 C6 07 01 BA 01 01 01 07 00 F5 07 01 03 07 01 21 07 01 08 00 05 08 04 81 08 04 81 07 00 4F 07 01 03 07 01 21 45 07 00 4D FF 00 00 00 0A 07 00 03 07 00 C6 07 01 BA 01 01 01 07 00 F5 07 01 03 07 01 21 07 01 08 00 04 08 04 81 08 04 81 07 00 4F 07 00 72 42 07 00 44 FF 00 00 00 0A 07 00 03 07 00 C6 07 01 BA 01 01 01 07 00 F5 07 01 03 07 01 21 07 01 08 00 04 08 04 81 08 04 81 07 00 4F 07 00 72 45 07 00 4D 40 07 00 4F FF 00 06 00 0B 07 00 03 07 00 C6 07 01 BA 01 01 01 07 00 F5 07 01 03 07 01 21 07 01 08 07 00 4F 00 01 07 00 4D 40 07 00 4F 45 07 00 4D 40 01 50 07 00 4F FF 00 02 00 0B 07 00 03 07 00 C6 07 01 BA 01 01 01 07 00 F5 07 01 03 07 01 21 07 01 08 07 00 4F 00 02 07 00 4F 01 5C 07 00 4F 42 07 00 36 40 07 00 4F 45 07 00 4D 40 01 00 FF 00 13 00 00 00 01 07 00 4D FF 00 00 00 0B 07 00 03 07 00 C6 07 01 BA 01 01 01 07 00 F5 07 01 03 07 01 21 07 01 08 07 00 4F 00 08 08 05 28 08 05 28 08 05 2C 08 05 2C 08 05 30 08 05 30 07 00 4F 07 00 72 45 07 00 4D FF 00 00 00 0B 07 00 03 07 00 C6 07 01 BA 01 01 01 07 00 F5 07 01 03 07 01 21 07 01 08 07 00 4F 00 08 08 05 28 08 05 28 08 05 2C 08 05 2C 08 05 30 08 05 30 07 00 4F 07 00 72 FF 00 0B 00 0B 07 00 03 07 00 C6 07 01 BA 01 01 01 07 00 F5 07 01 03 07 01 21 07 01 08 07 00 4F 00 08 08 05 28 08 05 28 08 05 2C 08 05 2C 08 05 30 08 05 30 07 00 4F 07 00 72 FF 00 02 00 0B 07 00 03 07 00 C6 07 01 BA 01 01 01 07 00 F5 07 01 03 07 01 21 07 01 08 07 00 4F 00 09 08 05 28 08 05 28 08 05 2C 08 05 2C 08 05 30 08 05 30 07 00 4F 07 00 72 01 FF 00 1C 00 0B 07 00 03 07 00 C6 07 01 BA 01 01 01 07 00 F5 07 01 03 07 01 21 07 01 08 07 00 4F 00 08 08 05 28 08 05 28 08 05 2C 08 05 2C 08 05 30 08 05 30 07 00 4F 07 00 72 FF 00 02 00 00 00 01 07 00 4D FF 00 00 00 0B 07 00 03 07 00 C6 07 01 BA 01 01 01 07 00 F5 07 01 03 07 01 21 07 01 08 07 00 4F 00 08 08 05 28 08 05 28 08 05 2C 08 05 2C 08 05 30 08 05 30 07 00 4F 07 00 72 45 07 00 4D FF 00 00 00 0B 07 00 03 07 00 C6 07 01 BA 01 01 01 07 00 F5 07 01 03 07 01 21 07 01 08 07 00 4F 00 05 08 05 28 08 05 28 08 05 2C 08 05 2C 07 00 4F 42 07 00 88 FF 00 00 00 0B 07 00 03 07 00 C6 07 01 BA 01 01 01 07 00 F5 07 01 03 07 01 21 07 01 08 07 00 4F 00 05 08 05 28 08 05 28 08 05 2C 08 05 2C 07 00 4F 45 07 00 4D FF 00 00 00 0B 07 00 03 07 00 C6 07 01 BA 01 01 01 07 00 F5 07 01 03 07 01 21 07 01 08 07 00 4F 00 03 08 05 28 08 05 28 07 00 C8 48 07 00 4D FF 00 00 00 0B 07 00 03 07 00 C6 07 01 BA 01 01 01 07 00 F5 07 01 03 07 01 21 07 01 08 07 00 4F 00 04 08 05 28 08 05 28 07 00 CD 07 01 B8 45 07 00 4D 40 07 00 C6 FC 00 0D 07 00 C6 42 01 1F 49 07 00 84 FF 00 00 00 0C 07 00 03 07 00 C6 07 01 BA 01 01 01 07 00 F5 07 01 03 07 01 21 07 01 08 07 00 4F 07 00 C6 00 04 07 00 C6 07 01 03 07 01 21 05 45 07 00 4D FF 00 00 00 0C 07 00 03 07 00 C6 07 01 BA 01 01 01 07 00 F5 07 01 03 07 01 21 07 01 08 07 00 4F 07 00 C6 00 02 07 00 C6 07 01 08 42 07 00 3E FF 00 00 00 0C 07 00 03 07 00 C6 07 01 BA 01 01 01 07 00 F5 07 01 03 07 01 21 07 01 08 07 00 4F 07 00 C6 00 02 07 00 C6 07 01 08 45 07 00 4D FF 00 00 00 0C 07 00 03 07 00 C6 07 01 BA 01 01 01 07 00 F5 07 01 03 07 01 21 07 01 08 07 00 4F 07 00 C6 00 02 07 00 C6 07 00 72 FF 00 0B 00 0C 07 00 03 07 00 C6 07 01 BA 01 01 01 07 00 F5 07 01 03 07 01 21 07 01 08 07 00 4F 07 00 C6 00 02 07 00 C6 07 00 72 FF 00 02 00 0C 07 00 03 07 00 C6 07 01 BA 01 01 01 07 00 F5 07 01 03 07 01 21 07 01 08 07 00 4F 07 00 C6 00 03 07 00 C6 07 00 72 01 FF 00 1F 00 0C 07 00 03 07 00 C6 07 01 BA 01 01 01 07 00 F5 07 01 03 07 01 21 07 01 08 07 00 4F 07 00 C6 00 02 07 00 C6 07 00 72 FF 00 02 00 00 00 01 07 00 4D FF 00 00 00 0C 07 00 03 07 00 C6 07 01 BA 01 01 01 07 00 F5 07 01 03 07 01 21 07 01 08 07 00 4F 07 00 C6 00 02 07 00 C6 07 00 72 45 07 00 4D 00 0B 42 01 1D 44 07 00 42 40 07 00 C6 45 07 00 4D 00 48 07 00 46 FF 00 00 00 0C 07 00 03 07 00 C6 07 01 BA 01 01 01 07 00 F5 07 01 03 07 01 21 07 01 08 07 00 4F 07 00 C6 00 03 07 01 08 08 06 5B 08 06 5B 45 07 00 4D FF 00 00 00 0C 07 00 03 07 00 C6 07 01 BA 01 01 01 07 00 F5 07 01 03 07 01 21 07 01 08 07 00 4F 07 00 C6 00 02 07 01 08 07 00 51 45 07 00 3C FF 00 00 00 0C 07 00 03 07 00 C6 07 01 BA 01 01 01 07 00 F5 07 01 03 07 01 21 07 01 08 07 00 4F 07 00 C6 00 03 07 01 08 07 00 51 07 00 72 45 07 00 4D FF 00 00 00 0C 07 00 03 07 00 C6 07 01 BA 01 01 01 07 00 F5 07 01 03 07 01 21 07 01 08 07 00 4F 07 00 C6 00 03 07 01 08 07 00 51 07 00 72 42 07 00 4D FF 00 00 00 0C 07 00 03 07 00 C6 07 01 BA 01 01 01 07 00 F5 07 01 03 07 01 21 07 01 08 07 00 4F 07 00 C6 00 03 07 01 08 07 00 51 07 00 72 45 07 00 4D FF 00 00 00 0C 07 00 03 07 00 C6 07 01 BA 01 01 01 07 00 F5 07 01 03 07 01 21 07 01 08 07 00 4F 07 00 C6 00 02 07 01 08 07 00 51 FF 00 0B 00 00 00 01 07 00 4D FF 00 00 00 0C 07 00 03 07 00 C6 07 01 BA 01 01 01 07 00 F5 07 01 03 07 01 21 07 01 08 07 00 4F 07 00 C6 00 06 07 01 08 07 00 51 08 06 83 08 06 83 07 00 4F 07 00 72 45 07 00 4D FF 00 00 00 0C 07 00 03 07 00 C6 07 01 BA 01 01 01 07 00 F5 07 01 03 07 01 21 07 01 08 07 00 4F 07 00 C6 00 06 07 01 08 07 00 51 08 06 83 08 06 83 07 00 4F 07 00 72 FF 00 0B 00 0C 07 00 03 07 00 C6 07 01 BA 01 01 01 07 00 F5 07 01 03 07 01 21 07 01 08 07 00 4F 07 00 C6 00 06 07 01 08 07 00 51 08 06 83 08 06 83 07 00 4F 07 00 72 FF 00 02 00 0C 07 00 03 07 00 C6 07 01 BA 01 01 01 07 00 F5 07 01 03 07 01 21 07 01 08 07 00 4F 07 00 C6 00 07 07 01 08 07 00 51 08 06 83 08 06 83 07 00 4F 07 00 72 01 FF 00 1D 00 0C 07 00 03 07 00 C6 07 01 BA 01 01 01 07 00 F5 07 01 03 07 01 21 07 01 08 07 00 4F 07 00 C6 00 06 07 01 08 07 00 51 08 06 83 08 06 83 07 00 4F 07 00 72 42 07 00 4D FF 00 00 00 0C 07 00 03 07 00 C6 07 01 BA 01 01 01 07 00 F5 07 01 03 07 01 21 07 01 08 07 00 4F 07 00 C6 00 06 07 01 08 07 00 51 08 06 83 08 06 83 07 00 4F 07 00 72 45 07 00 4D FF 00 00 00 0C 07 00 03 07 00 C6 07 01 BA 01 01 01 07 00 F5 07 01 03 07 01 21 07 01 08 07 00 4F 07 00 C6 00 03 07 01 08 07 00 51 07 00 4F FF 00 02 00 00 00 01 07 00 4D FF 00 00 00 0C 07 00 03 07 00 C6 07 01 BA 01 01 01 07 00 F5 07 01 03 07 01 21 07 01 08 07 00 4F 07 00 C6 00 03 07 01 08 07 00 51 07 00 4F 45 07 00 4D FF 00 00 00 0C 07 00 03 07 00 C6 07 01 BA 01 01 01 07 00 F5 07 01 03 07 01 21 07 01 08 07 00 4F 07 00 C6 00 03 07 01 08 07 00 51 07 00 72 FF 00 0B 00 0C 07 00 03 07 00 C6 07 01 BA 01 01 01 07 00 F5 07 01 03 07 01 21 07 01 08 07 00 4F 07 00 C6 00 03 07 01 08 07 00 51 07 00 72 FF 00 02 00 0C 07 00 03 07 00 C6 07 01 BA 01 01 01 07 00 F5 07 01 03 07 01 21 07 01 08 07 00 4F 07 00 C6 00 04 07 01 08 07 00 51 07 00 72 01 FF 00 1E 00 0C 07 00 03 07 00 C6 07 01 BA 01 01 01 07 00 F5 07 01 03 07 01 21 07 01 08 07 00 4F 07 00 C6 00 03 07 01 08 07 00 51 07 00 72 42 07 00 4D FF 00 00 00 0C 07 00 03 07 00 C6 07 01 BA 01 01 01 07 00 F5 07 01 03 07 01 21 07 01 08 07 00 4F 07 00 C6 00 03 07 01 08 07 00 51 07 00 72 45 07 00 4D FF 00 00 00 0C 07 00 03 07 00 C6 07 01 BA 01 01 01 07 00 F5 07 01 03 07 01 21 07 01 08 07 00 4F 07 00 C6 00 02 07 01 08 07 00 51 42 07 00 4D FF 00 00 00 0C 07 00 03 07 00 C6 07 01 BA 01 01 01 07 00 F5 07 01 03 07 01 21 07 01 08 07 00 4F 07 00 C6 00 02 07 01 08 07 00 51 45 07 00 4D FF 00 00 00 0C 07 00 03 07 00 C6 07 01 BA 01 01 01 07 00 F5 07 01 03 07 01 21 07 01 08 07 00 4F 07 00 C6 00 02 07 01 08 07 00 72 FF 00 0B 00 0C 07 00 03 07 00 C6 07 01 BA 01 01 01 07 00 F5 07 01 03 07 01 21 07 01 08 07 00 4F 07 00 C6 00 02 07 01 08 07 00 72 FF 00 02 00 0C 07 00 03 07 00 C6 07 01 BA 01 01 01 07 00 F5 07 01 03 07 01 21 07 01 08 07 00 4F 07 00 C6 00 03 07 01 08 07 00 72 01 FF 00 1E 00 0C 07 00 03 07 00 C6 07 01 BA 01 01 01 07 00 F5 07 01 03 07 01 21 07 01 08 07 00 4F 07 00 C6 00 02 07 01 08 07 00 72 42 07 00 34 FF 00 00 00 0C 07 00 03 07 00 C6 07 01 BA 01 01 01 07 00 F5 07 01 03 07 01 21 07 01 08 07 00 4F 07 00 C6 00 02 07 01 08 07 00 72 45 07 00 4D 00 44 07 00 40 40 07 01 21 45 07 00 4D 40 01 4B 07 00 4D FF 00 00 00 0C 07 00 03 07 00 C6 07 01 BA 01 01 01 07 00 F5 07 01 03 07 01 21 07 01 08 07 00 4F 07 00 C6 00 03 07 01 08 08 07 69 08 07 69 45 07 00 4D FF 00 00 00 0C 07 00 03 07 00 C6 07 01 BA 01 01 01 07 00 F5 07 01 03 07 01 21 07 01 08 07 00 4F 07 00 C6 00 02 07 01 08 07 00 51 FF 00 0E 00 0C 07 00 03 07 00 C6 07 01 BA 01 01 01 07 00 F5 07 01 03 07 01 21 07 01 08 07 00 4F 07 00 C6 00 03 07 01 08 07 00 51 07 00 72 FF 00 02 00 0C 07 00 03 07 00 C6 07 01 BA 01 01 01 07 00 F5 07 01 03 07 01 21 07 01 08 07 00 4F 07 00 C6 00 04 07 01 08 07 00 51 07 00 72 01 FF 00 1D 00 0C 07 00 03 07 00 C6 07 01 BA 01 01 01 07 00 F5 07 01 03 07 01 21 07 01 08 07 00 4F 07 00 C6 00 03 07 01 08 07 00 51 07 00 72 42 07 00 4D FF 00 00 00 0C 07 00 03 07 00 C6 07 01 BA 01 01 01 07 00 F5 07 01 03 07 01 21 07 01 08 07 00 4F 07 00 C6 00 03 07 01 08 07 00 51 07 00 72 45 07 00 4D FF 00 00 00 0C 07 00 03 07 00 C6 07 01 BA 01 01 01 07 00 F5 07 01 03 07 01 21 07 01 08 07 00 4F 07 00 C6 00 03 07 01 08 07 00 51 07 00 72 42 07 00 4D FF 00 00 00 0C 07 00 03 07 00 C6 07 01 BA 01 01 01 07 00 F5 07 01 03 07 01 21 07 01 08 07 00 4F 07 00 C6 00 03 07 01 08 07 00 51 07 00 72 45 07 00 4D FF 00 00 00 0C 07 00 03 07 00 C6 07 01 BA 01 01 01 07 00 F5 07 01 03 07 01 21 07 01 08 07 00 4F 07 00 C6 00 02 07 01 08 07 00 51 FF 00 0F 00 0C 07 00 03 07 00 C6 07 01 BA 01 01 01 07 00 F5 07 01 03 07 01 21 07 01 08 07 00 4F 07 00 C6 00 04 07 01 08 07 00 51 08 07 BE 08 07 BE FF 00 02 00 0C 07 00 03 07 00 C6 07 01 BA 01 01 01 07 00 F5 07 01 03 07 01 21 07 01 08 07 00 4F 07 00 C6 00 05 07 01 08 07 00 51 08 07 BE 08 07 BE 01 FF 00 1E 00 0C 07 00 03 07 00 C6 07 01 BA 01 01 01 07 00 F5 07 01 03 07 01 21 07 01 08 07 00 4F 07 00 C6 00 04 07 01 08 07 00 51 08 07 BE 08 07 BE 47 07 00 3C FF 00 00 00 0C 07 00 03 07 00 C6 07 01 BA 01 01 01 07 00 F5 07 01 03 07 01 21 07 01 08 07 00 4F 07 00 C6 00 06 07 01 08 07 00 51 08 07 BE 08 07 BE 07 00 4F 07 00 72 45 07 00 4D FF 00 00 00 0C 07 00 03 07 00 C6 07 01 BA 01 01 01 07 00 F5 07 01 03 07 01 21 07 01 08 07 00 4F 07 00 C6 00 06 07 01 08 07 00 51 08 07 BE 08 07 BE 07 00 4F 07 00 72 FF 00 0B 00 0C 07 00 03 07 00 C6 07 01 BA 01 01 01 07 00 F5 07 01 03 07 01 21 07 01 08 07 00 4F 07 00 C6 00 06 07 01 08 07 00 51 08 07 BE 08 07 BE 07 00 4F 07 00 72 FF 00 02 00 0C 07 00 03 07 00 C6 07 01 BA 01 01 01 07 00 F5 07 01 03 07 01 21 07 01 08 07 00 4F 07 00 C6 00 07 07 01 08 07 00 51 08 07 BE 08 07 BE 07 00 4F 07 00 72 01 FF 00 1C 00 0C 07 00 03 07 00 C6 07 01 BA 01 01 01 07 00 F5 07 01 03 07 01 21 07 01 08 07 00 4F 07 00 C6 00 06 07 01 08 07 00 51 08 07 BE 08 07 BE 07 00 4F 07 00 72 42 07 00 2E FF 00 00 00 0C 07 00 03 07 00 C6 07 01 BA 01 01 01 07 00 F5 07 01 03 07 01 21 07 01 08 07 00 4F 07 00 C6 00 06 07 01 08 07 00 51 08 07 BE 08 07 BE 07 00 4F 07 00 72 45 07 00 4D FF 00 00 00 0C 07 00 03 07 00 C6 07 01 BA 01 01 01 07 00 F5 07 01 03 07 01 21 07 01 08 07 00 4F 07 00 C6 00 03 07 01 08 07 00 51 07 00 4F FF 00 0B 00 0C 07 00 03 07 00 C6 07 01 BA 01 01 01 07 00 F5 07 01 03 07 01 21 07 01 08 07 00 4F 07 00 C6 00 03 07 01 08 07 00 51 07 00 4F FF 00 02 00 0C 07 00 03 07 00 C6 07 01 BA 01 01 01 07 00 F5 07 01 03 07 01 21 07 01 08 07 00 4F 07 00 C6 00 04 07 01 08 07 00 51 07 00 4F 01 FF 00 1D 00 0C 07 00 03 07 00 C6 07 01 BA 01 01 01 07 00 F5 07 01 03 07 01 21 07 01 08 07 00 4F 07 00 C6 00 03 07 01 08 07 00 51 07 00 4F FF 00 02 00 00 00 01 07 00 4D FF 00 00 00 0C 07 00 03 07 00 C6 07 01 BA 01 01 01 07 00 F5 07 01 03 07 01 21 07 01 08 07 00 4F 07 00 C6 00 03 07 01 08 07 00 51 07 00 4F 45 07 00 4D FF 00 00 00 0C 07 00 03 07 00 C6 07 01 BA 01 01 01 07 00 F5 07 01 03 07 01 21 07 01 08 07 00 4F 07 00 C6 00 03 07 01 08 07 00 51 07 00 72 42 07 00 4D FF 00 00 00 0C 07 00 03 07 00 C6 07 01 BA 01 01 01 07 00 F5 07 01 03 07 01 21 07 01 08 07 00 4F 07 00 C6 00 03 07 01 08 07 00 51 07 00 72 45 07 00 4D FF 00 00 00 0C 07 00 03 07 00 C6 07 01 BA 01 01 01 07 00 F5 07 01 03 07 01 21 07 01 08 07 00 4F 07 00 C6 00 02 07 01 08 07 00 51 42 07 00 4D FF 00 00 00 0C 07 00 03 07 00 C6 07 01 BA 01 01 01 07 00 F5 07 01 03 07 01 21 07 01 08 07 00 4F 07 00 C6 00 02 07 01 08 07 00 51 45 07 00 4D FF 00 00 00 0C 07 00 03 07 00 C6 07 01 BA 01 01 01 07 00 F5 07 01 03 07 01 21 07 01 08 07 00 4F 07 00 C6 00 02 07 01 08 07 00 72 FF 00 02 00 00 00 01 07 00 4D FF 00 00 00 0C 07 00 03 07 00 C6 07 01 BA 01 01 01 07 00 F5 07 01 03 07 01 21 07 01 08 07 00 4F 07 00 C6 00 02 07 01 08 07 00 72 45 07 00 4D 00 F9 00 02 0B 42 01 1D 46 07 00 4D FF 00 00 00 0A 07 00 03 07 00 C6 07 01 BA 01 01 01 07 00 F5 07 01 03 07 01 21 07 01 08 00 02 07 01 03 07 01 08 45 07 00 4D 00 45 07 00 4D FF 00 00 00 0A 07 00 03 07 00 C6 07 01 BA 01 01 01 07 00 F5 07 01 03 07 01 21 07 01 08 00 02 07 00 C6 07 01 08 45 07 00 4D FF 00 00 00 0A 07 00 03 07 00 C6 07 01 BA 01 01 01 07 00 F5 07 01 03 07 01 21 07 01 08 00 02 07 00 C6 07 00 72 FF 00 0B 00 0A 07 00 03 07 00 C6 07 01 BA 01 01 01 07 00 F5 07 01 03 07 01 21 07 01 08 00 02 07 00 C6 07 00 72 FF 00 02 00 0A 07 00 03 07 00 C6 07 01 BA 01 01 01 07 00 F5 07 01 03 07 01 21 07 01 08 00 03 07 00 C6 07 00 72 01 FF 00 1F 00 0A 07 00 03 07 00 C6 07 01 BA 01 01 01 07 00 F5 07 01 03 07 01 21 07 01 08 00 02 07 00 C6 07 00 72 42 07 00 4D FF 00 00 00 0A 07 00 03 07 00 C6 07 01 BA 01 01 01 07 00 F5 07 01 03 07 01 21 07 01 08 00 02 07 00 C6 07 00 72 45 07 00 4D F9 00 00 FA 00 02 4E 07 00 03 FF 00 02 00 07 07 00 03 07 00 C6 07 01 BA 01 01 01 07 00 F5 00 02 07 00 03 01 5F 07 00 03 42 07 00 4D 40 07 00 03 45 07 00 4D 40 07 00 E0 42 07 00 4D 40 07 00 E0 45 07 00 4D 40 07 00 EF 42 07 00 36 40 07 00 EF 47 07 00 4D 00 0B 42 01 1D FF 00 11 00 07 07 00 03 07 00 C6 07 01 BA 01 01 01 07 00 F5 00 02 07 01 13 07 00 72 FF 00 02 00 07 07 00 03 07 00 C6 07 01 BA 01 01 01 07 00 F5 00 03 07 01 13 07 00 72 01 FF 00 1E 00 07 07 00 03 07 00 C6 07 01 BA 01 01 01 07 00 F5 00 02 07 01 13 07 00 72 FF 00 02 00 00 00 01 07 00 4D FF 00 00 00 07 07 00 03 07 00 C6 07 01 BA 01 01 01 07 00 F5 00 02 07 01 13 07 00 72 45 07 00 4D FF 00 00 00 07 07 00 03 07 00 C6 07 01 BA 01 01 01 07 00 F5 00 02 07 01 13 07 00 72 42 07 00 46 FF 00 00 00 07 07 00 03 07 00 C6 07 01 BA 01 01 01 07 00 F5 00 02 07 01 13 07 00 72 45 07 00 4D 40 07 01 08 FC 00 0D 07 01 08 42 01 1C 45 07 00 4D 40 07 00 03 45 07 00 4D 40 07 00 E0 42 07 00 4D 40 07 00 E0 45 07 00 4D 40 07 00 EF 42 07 00 88 40 07 00 EF 47 07 00 4D 40 07 00 F5 4B 07 00 F5 FF 00 02 00 08 07 00 03 07 00 C6 07 01 BA 01 01 01 07 00 F5 07 01 08 00 02 07 00 F5 01 5E 07 00 F5 FF 00 01 00 09 07 00 03 07 00 C6 07 01 BA 01 01 01 07 00 05 07 01 08 07 00 F5 00 00 4D 07 00 F5 FF 00 02 00 09 07 00 03 07 00 C6 07 01 BA 01 01 01 07 00 05 07 01 08 07 00 F5 00 02 07 00 F5 01 5C 07 00 F5 FF 00 02 00 00 00 01 07 00 4D FF 00 00 00 09 07 00 03 07 00 C6 07 01 BA 01 01 01 07 00 05 07 01 08 07 00 F5 00 01 07 00 F5 47 07 00 4D 40 01 02 05 42 01 1A 44 07 00 44 40 07 00 F5 47 07 00 4D 40 07 00 05 FF 00 14 00 09 07 00 03 07 00 C6 07 01 BA 01 01 01 07 01 9A 07 01 08 07 00 F5 00 02 07 01 08 07 01 9A FF 00 02 00 09 07 00 03 07 00 C6 07 01 BA 01 01 01 07 01 9A 07 01 08 07 00 F5 00 03 07 01 08 07 01 9A 01 FF 00 1C 00 09 07 00 03 07 00 C6 07 01 BA 01 01 01 07 01 9A 07 01 08 07 00 F5 00 02 07 01 08 07 01 9A 42 07 00 32 FF 00 00 00 09 07 00 03 07 00 C6 07 01 BA 01 01 01 07 01 9A 07 01 08 07 00 F5 00 02 07 01 08 07 01 9A 45 07 00 4D FF 00 00 00 09 07 00 03 07 00 C6 07 01 BA 01 01 01 07 01 9A 07 01 08 07 00 F5 00 02 07 01 08 07 01 08 42 07 00 4D FF 00 00 00 09 07 00 03 07 00 C6 07 01 BA 01 01 01 07 01 9A 07 01 08 07 00 F5 00 02 07 01 08 07 01 08 45 07 00 4D 00 FF 00 02 00 09 07 00 03 07 00 C6 07 01 BA 01 01 01 07 00 05 07 01 08 07 00 F5 00 00 46 07 00 4D FF 00 00 00 09 07 00 03 07 00 C6 07 01 BA 01 01 01 07 00 05 07 01 08 07 00 F5 00 02 07 00 C6 07 00 72 45 07 00 4D 00 0B 42 01 1C FF 00 0E 00 09 07 00 03 07 00 C6 07 01 BA 01 01 01 07 00 05 07 01 08 07 00 F5 00 02 07 00 C6 07 01 08 FF 00 02 00 09 07 00 03 07 00 C6 07 01 BA 01 01 01 07 00 05 07 01 08 07 00 F5 00 03 07 00 C6 07 01 08 01 FF 00 1D 00 09 07 00 03 07 00 C6 07 01 BA 01 01 01 07 00 05 07 01 08 07 00 F5 00 02 07 00 C6 07 01 08 42 07 00 30 FF 00 00 00 09 07 00 03 07 00 C6 07 01 BA 01 01 01 07 00 05 07 01 08 07 00 F5 00 02 07 00 C6 07 01 08 45 07 00 4D FF 00 00 00 09 07 00 03 07 00 C6 07 01 BA 01 01 01 07 00 05 07 01 08 07 00 F5 00 02 07 00 C6 07 00 72 42 07 00 4D FF 00 00 00 09 07 00 03 07 00 C6 07 01 BA 01 01 01 07 00 05 07 01 08 07 00 F5 00 02 07 00 C6 07 00 72 45 07 00 4D 00 43 07 00 36 40 07 00 C6 45 07 00 4D 00 FF 00 0A 00 04 07 00 03 07 00 C6 07 01 BA 01 00 01 07 00 4D FF 00 06 00 09 07 00 03 07 00 C6 07 01 BA 01 07 01 AC 01 07 00 05 07 01 08 07 00 F5 00 00 FF 00 02 00 01 07 00 03 00 01 07 00 82 4B 07 00 82 FF 00 02 00 01 07 00 03 00 02 07 00 82 01 5D 07 00 82 FF 00 04 00 02 07 00 03 07 00 82 00 01 07 00 46 40 07 00 82 45 07 00 4D FA 00 00 40 07 00 4F FF 00 01 00 07 07 00 03 07 00 C6 07 01 BA 01 01 01 07 00 F5 00 00 FF 00 01 00 0C 07 00 03 07 00 C6 07 01 BA 01 01 01 07 00 F5 07 01 03 07 01 21 07 01 08 07 00 4F 07 00 C6 00 06 07 01 08 07 00 51 08 06 83 08 06 83 07 00 4F 07 00 72 FF 00 01 00 0A 07 00 03 07 00 C6 07 01 BA 01 01 01 07 00 F5 07 01 03 07 01 21 07 01 08 00 01 07 01 21 FF 00 01 00 0C 07 00 03 07 00 C6 07 01 BA 01 01 01 07 00 F5 07 01 03 07 01 21 07 01 08 07 00 4F 07 00 C6 00 04 07 01 08 07 00 51 08 07 BE 08 07 BE FF 00 01 00 01 07 00 03 00 01 07 00 82 FF 00 01 00 0C 07 00 03 07 00 C6 07 01 BA 01 01 01 07 00 F5 07 01 03 07 01 21 07 01 08 07 00 4F 07 00 C6 00 03 07 01 08 07 00 51 07 00 72 FF 00 01 00 0C 07 00 03 07 00 C6 07 01 BA 01 01 01 07 00 F5 07 01 03 07 01 21 07 01 08 07 00 4F 07 00 C6 00 03 07 01 08 07 00 51 07 00 4F FF 00 01 00 01 07 00 03 00 03 08 01 8B 08 01 8B 07 00 CD FF 00 01 00 07 07 00 03 07 00 C6 07 01 BA 01 01 01 07 00 F5 00 01 07 00 03 FF 00 01 00 02 07 00 03 07 00 C6 00 01 07 01 BA FF 00 01 00 09 07 00 03 07 00 C6 07 01 BA 01 01 01 07 00 05 07 01 08 07 00 F5 00 02 07 00 C6 07 01 08 FF 00 01 00 09 07 00 03 07 00 C6 07 01 BA 01 01 01 07 01 9A 07 01 08 07 00 F5 00 02 07 01 08 07 01 9A FF 00 01 00 09 07 00 03 07 00 C6 07 01 BA 01 01 01 07 00 F5 07 01 03 07 01 21 00 01 07 01 08 FF 00 01 00 0B 07 00 03 07 00 C6 07 01 BA 01 01 01 07 00 F5 07 01 03 07 01 21 07 01 08 07 00 4F 00 01 07 00 4F FF 00 01 00 0A 07 00 03 07 00 C6 07 01 BA 01 01 01 07 00 F5 07 01 03 07 01 21 07 01 08 00 02 07 00 C6 07 00 72 FF 00 01 00 08 07 00 03 07 00 C6 07 01 BA 01 01 01 07 00 F5 07 01 08 00 01 07 00 F5 FF 00 01 00 0A 07 00 03 07 00 C6 07 01 BA 01 01 01 07 00 F5 07 01 03 07 01 21 07 01 08 00 00 FF 00 01 00 0A 07 00 03 07 00 C6 07 01 BA 01 01 01 07 00 F5 07 01 03 07 01 21 07 01 08 00 04 08 04 81 08 04 81 07 00 4F 07 01 03 FF 00 01 00 0C 07 00 03 07 00 C6 07 01 BA 01 01 01 07 00 F5 07 01 03 07 01 21 07 01 08 07 00 4F 07 00 C6 00 06 07 01 08 07 00 51 08 07 BE 08 07 BE 07 00 4F 07 00 72 FF 00 01 00 01 07 00 03 00 01 07 00 99 FF 00 01 00 07 07 00 03 07 00 C6 07 01 BA 01 01 01 07 00 F5 00 00 FE 00 01 07 01 03 07 01 21 07 01 08 FF 00 01 00 0C 07 00 03 07 00 C6 07 01 BA 01 01 01 07 00 F5 07 01 03 07 01 21 07 01 08 07 00 4F 07 00 C6 00 02 07 00 C6 07 00 72 FF 00 01 00 01 07 00 03 00 01 07 00 C6 FF 00 01 00 09 07 00 03 07 00 C6 07 01 BA 01 01 01 07 00 05 07 01 08 07 00 F5 00 01 07 00 F5 FF 00 01 00 0A 07 00 03 07 00 C6 07 01 BA 01 01 01 07 00 F5 07 01 03 07 01 21 07 01 08 00 01 07 00 E0 FF 00 01 00 08 07 00 03 07 00 C6 07 01 BA 01 01 01 07 00 F5 07 01 08 00 00 FF 00 01 00 0B 07 00 03 07 00 C6 07 01 BA 01 01 01 07 00 F5 07 01 03 07 01 21 07 01 08 07 00 4F 00 08 08 05 28 08 05 28 08 05 2C 08 05 2C 08 05 30 08 05 30 07 00 4F 07 00 72 FC 00 01 07 00 C6 01 FF 00 01 00 09 07 00 03 07 00 C6 07 01 BA 01 01 01 07 00 05 07 01 08 07 00 F5 00 00 FF 00 01 00 0C 07 00 03 07 00 C6 07 01 BA 01 01 01 07 00 F5 07 01 03 07 01 21 07 01 08 07 00 4F 07 00 C6 00 02 07 01 08 07 00 72 FF 00 01 00 09 07 00 03 07 00 C6 07 01 BA 01 01 01 07 00 F5 07 01 03 07 01 21 00 02 07 01 13 07 00 72 FF 00 01 00 01 07 00 03 00 02 08 01 2B 08 01 2B FF 00 01 00 0C 07 00 03 07 00 C6 07 01 BA 01 01 01 07 00 F5 07 01 03 07 01 21 07 01 08 07 00 4F 07 00 C6 00 03 07 01 08 07 00 51 07 00 72 FF 00 01 00 07 07 00 03 07 00 C6 07 01 BA 01 01 01 07 00 F5 00 02 07 01 13 07 00 72 FF 00 01 00 01 07 00 03 00 01 07 00 4D 43 05 44 07 00 4D 47 05 47 07 00 4D
        //    Exceptions:
        //  Try           Handler
        //  Start  End    Start  End    Type                                       
        //  -----  -----  -----  -----  -------------------------------------------
        //  652    701    3009   3016   Any
        //  702    797    3009   3016   Any
        //  798    1225   3009   3016   Any
        //  1226   1340   3009   3016   Any
        //  1341   1395   3009   3016   Any
        //  1396   1559   3009   3016   Any
        //  1560   1679   3009   3016   Any
        //  1680   1746   3009   3016   Any
        //  1747   2151   3009   3016   Any
        //  2152   2184   3009   3016   Any
        //  2185   2515   3009   3016   Any
        //  2516   2715   3009   3016   Any
        //  2716   3004   3009   3016   Any
        //  3009   3011   3009   3016   Any
        //  102    375    3019   3077   Ljava/io/IOException;
        //  376    427    3019   3077   Ljava/io/IOException;
        //  428    701    3019   3077   Ljava/io/IOException;
        //  702    797    3019   3077   Ljava/io/IOException;
        //  798    1225   3019   3077   Ljava/io/IOException;
        //  1226   1340   3019   3077   Ljava/io/IOException;
        //  1341   1395   3019   3077   Ljava/io/IOException;
        //  1396   1559   3019   3077   Ljava/io/IOException;
        //  1560   1679   3019   3077   Ljava/io/IOException;
        //  1680   1746   3019   3077   Ljava/io/IOException;
        //  1747   2151   3019   3077   Ljava/io/IOException;
        //  2152   2184   3019   3077   Ljava/io/IOException;
        //  2185   2515   3019   3077   Ljava/io/IOException;
        //  2516   2715   3019   3077   Ljava/io/IOException;
        //  2716   3016   3019   3077   Ljava/io/IOException;
        //  8      20     3161   3169   Any
        //  3161   3169   3161   3169   Any
        //  3177   3179   3      8      Ljava/lang/EnumConstantNotPresentException;
        //  75     82     82     83     Any
        //  75     82     75     76     Ljava/lang/IllegalArgumentException;
        //  76     82     82     83     Any
        //  75     82     82     83     Any
        //  76     82     82     83     Ljava/lang/NegativeArraySizeException;
        //  91     98     98     99     Any
        //  92     98     91     92     Ljava/lang/ArithmeticException;
        //  92     98     98     99     Ljava/lang/NullPointerException;
        //  92     98     3      8      Ljava/lang/IllegalArgumentException;
        //  91     98     91     92     Any
        //  110    117    117    118    Any
        //  111    117    117    118    Ljava/lang/ClassCastException;
        //  110    117    3      8      Ljava/util/ConcurrentModificationException;
        //  110    117    117    118    Ljava/lang/EnumConstantNotPresentException;
        //  110    117    110    111    Ljava/lang/StringIndexOutOfBoundsException;
        //  159    166    166    167    Any
        //  159    166    3      8      Ljava/lang/AssertionError;
        //  159    166    159    160    Any
        //  160    166    166    167    Any
        //  159    166    159    160    Ljava/util/ConcurrentModificationException;
        //  170    177    177    178    Any
        //  171    177    177    178    Ljava/lang/IllegalStateException;
        //  171    177    170    171    Ljava/lang/ArithmeticException;
        //  171    177    177    178    Ljava/lang/ArrayIndexOutOfBoundsException;
        //  170    177    177    178    Ljava/lang/ArithmeticException;
        //  188    195    195    196    Any
        //  188    195    188    189    Ljava/lang/ArithmeticException;
        //  188    195    3      8      Any
        //  188    195    188    189    Any
        //  188    195    188    189    Ljava/lang/UnsupportedOperationException;
        //  279    286    286    287    Any
        //  279    286    3      8      Ljava/lang/NumberFormatException;
        //  280    286    279    280    Any
        //  279    286    3      8      Any
        //  279    286    286    287    Ljava/lang/EnumConstantNotPresentException;
        //  290    297    297    298    Any
        //  291    297    297    298    Ljava/lang/IndexOutOfBoundsException;
        //  290    297    3      8      Ljava/lang/IndexOutOfBoundsException;
        //  290    297    290    291    Ljava/lang/IllegalArgumentException;
        //  291    297    290    291    Any
        //  351    358    358    359    Any
        //  351    358    358    359    Ljava/lang/EnumConstantNotPresentException;
        //  352    358    351    352    Any
        //  352    358    351    352    Any
        //  351    358    3      8      Any
        //  364    371    371    372    Any
        //  365    371    371    372    Ljava/lang/NegativeArraySizeException;
        //  364    371    364    365    Any
        //  365    371    364    365    Any
        //  364    371    3      8      Ljava/lang/AssertionError;
        //  376    382    382    383    Any
        //  376    382    382    383    Any
        //  376    382    3      8      Ljava/lang/UnsupportedOperationException;
        //  376    382    3      8      Ljava/lang/IllegalArgumentException;
        //  376    382    382    383    Ljava/lang/ArithmeticException;
        //  386    393    393    394    Any
        //  387    393    393    394    Any
        //  386    393    386    387    Ljava/lang/ArrayIndexOutOfBoundsException;
        //  387    393    386    387    Any
        //  387    393    386    387    Any
        //  414    421    421    422    Any
        //  414    421    421    422    Ljava/lang/NumberFormatException;
        //  414    421    414    415    Ljava/lang/StringIndexOutOfBoundsException;
        //  414    421    414    415    Ljava/lang/NegativeArraySizeException;
        //  415    421    414    415    Ljava/lang/AssertionError;
        //  428    434    434    435    Any
        //  428    434    3      8      Any
        //  428    434    434    435    Ljava/lang/StringIndexOutOfBoundsException;
        //  428    434    434    435    Ljava/util/ConcurrentModificationException;
        //  428    434    3      8      Ljava/lang/StringIndexOutOfBoundsException;
        //  438    445    445    446    Any
        //  439    445    438    439    Ljava/lang/NullPointerException;
        //  438    445    445    446    Any
        //  439    445    3      8      Any
        //  438    445    3      8      Ljava/lang/ClassCastException;
        //  450    457    457    458    Any
        //  450    457    450    451    Ljava/lang/NegativeArraySizeException;
        //  451    457    450    451    Ljava/lang/ArithmeticException;
        //  451    457    457    458    Any
        //  450    457    457    458    Ljava/lang/ArithmeticException;
        //  510    517    517    518    Any
        //  511    517    517    518    Ljava/lang/NullPointerException;
        //  511    517    510    511    Any
        //  510    517    3      8      Ljava/lang/ArithmeticException;
        //  510    517    510    511    Ljava/lang/StringIndexOutOfBoundsException;
        //  568    575    575    576    Any
        //  569    575    568    569    Ljava/lang/EnumConstantNotPresentException;
        //  569    575    3      8      Ljava/lang/RuntimeException;
        //  569    575    575    576    Any
        //  569    575    3      8      Any
        //  579    586    586    587    Any
        //  580    586    579    580    Any
        //  580    586    579    580    Any
        //  580    586    586    587    Any
        //  580    586    586    587    Any
        //  594    601    601    602    Any
        //  595    601    3      8      Any
        //  594    601    594    595    Ljava/lang/NegativeArraySizeException;
        //  595    601    3      8      Ljava/lang/IllegalArgumentException;
        //  595    601    594    595    Any
        //  662    669    669    670    Any
        //  662    669    662    663    Any
        //  662    669    669    670    Ljava/lang/RuntimeException;
        //  663    669    3      8      Ljava/lang/ClassCastException;
        //  662    669    662    663    Ljava/lang/NegativeArraySizeException;
        //  673    680    680    681    Any
        //  674    680    673    674    Ljava/lang/IllegalStateException;
        //  674    680    3      8      Ljava/lang/StringIndexOutOfBoundsException;
        //  674    680    3      8      Ljava/lang/ClassCastException;
        //  674    680    673    674    Ljava/lang/IllegalStateException;
        //  684    693    693    694    Any
        //  684    693    684    685    Any
        //  685    693    3      8      Ljava/lang/ArrayIndexOutOfBoundsException;
        //  684    693    3      8      Ljava/lang/RuntimeException;
        //  685    693    684    685    Any
        //  702    710    710    711    Any
        //  702    710    710    711    Ljava/lang/StringIndexOutOfBoundsException;
        //  702    710    3      8      Ljava/lang/NumberFormatException;
        //  702    710    710    711    Any
        //  702    710    3      8      Ljava/lang/ClassCastException;
        //  798    806    806    807    Any
        //  798    806    806    807    Any
        //  798    806    3      8      Ljava/lang/ArrayIndexOutOfBoundsException;
        //  798    806    806    807    Ljava/lang/ArithmeticException;
        //  798    806    806    807    Any
        //  817    824    824    825    Any
        //  818    824    824    825    Any
        //  817    824    3      8      Ljava/lang/NullPointerException;
        //  817    824    817    818    Any
        //  817    824    824    825    Ljava/lang/ArrayIndexOutOfBoundsException;
        //  848    855    855    856    Any
        //  849    855    855    856    Ljava/lang/StringIndexOutOfBoundsException;
        //  848    855    855    856    Any
        //  849    855    848    849    Any
        //  849    855    855    856    Any
        //  903    910    910    911    Any
        //  904    910    903    904    Any
        //  904    910    903    904    Ljava/util/ConcurrentModificationException;
        //  904    910    910    911    Any
        //  903    910    903    904    Ljava/lang/NullPointerException;
        //  1055   1062   1062   1063   Any
        //  1055   1062   1055   1056   Any
        //  1055   1062   3      8      Any
        //  1055   1062   1062   1063   Ljava/lang/ArrayIndexOutOfBoundsException;
        //  1056   1062   1055   1056   Ljava/lang/ArithmeticException;
        //  1072   1079   1079   1080   Any
        //  1073   1079   1079   1080   Any
        //  1073   1079   1072   1073   Ljava/lang/ArithmeticException;
        //  1072   1079   3      8      Any
        //  1073   1079   1072   1073   Ljava/lang/EnumConstantNotPresentException;
        //  1127   1134   1134   1135   Any
        //  1127   1134   1134   1135   Ljava/lang/IllegalStateException;
        //  1127   1134   1127   1128   Any
        //  1128   1134   1127   1128   Ljava/lang/IndexOutOfBoundsException;
        //  1127   1134   1134   1135   Any
        //  1140   1149   1149   1150   Any
        //  1140   1149   3      8      Any
        //  1141   1149   1149   1150   Any
        //  1141   1149   1140   1141   Ljava/lang/StringIndexOutOfBoundsException;
        //  1141   1149   1149   1150   Ljava/lang/RuntimeException;
        //  1163   1170   1170   1171   Any
        //  1164   1170   3      8      Ljava/lang/AssertionError;
        //  1164   1170   3      8      Ljava/util/NoSuchElementException;
        //  1163   1170   1163   1164   Ljava/lang/ArrayIndexOutOfBoundsException;
        //  1163   1170   3      8      Any
        //  1226   1232   1232   1233   Any
        //  1226   1232   3      8      Ljava/lang/IllegalArgumentException;
        //  1226   1232   1232   1233   Ljava/util/ConcurrentModificationException;
        //  1226   1232   1232   1233   Any
        //  1226   1232   3      8      Ljava/lang/EnumConstantNotPresentException;
        //  1236   1243   1243   1244   Any
        //  1237   1243   3      8      Ljava/lang/RuntimeException;
        //  1236   1243   1236   1237   Ljava/lang/IllegalStateException;
        //  1237   1243   3      8      Any
        //  1236   1243   3      8      Any
        //  1251   1258   1258   1259   Any
        //  1251   1258   1251   1252   Any
        //  1251   1258   1251   1252   Ljava/lang/ClassCastException;
        //  1252   1258   3      8      Ljava/lang/NumberFormatException;
        //  1251   1258   1251   1252   Any
        //  1311   1318   1318   1319   Any
        //  1311   1318   1311   1312   Ljava/lang/RuntimeException;
        //  1312   1318   3      8      Any
        //  1312   1318   1318   1319   Ljava/lang/NullPointerException;
        //  1312   1318   3      8      Ljava/lang/NegativeArraySizeException;
        //  1341   1347   1347   1348   Any
        //  1341   1347   1347   1348   Any
        //  1341   1347   1347   1348   Ljava/lang/IndexOutOfBoundsException;
        //  1341   1347   1347   1348   Any
        //  1341   1347   3      8      Ljava/lang/ArrayIndexOutOfBoundsException;
        //  1396   1402   1402   1403   Any
        //  1396   1402   3      8      Ljava/lang/ClassCastException;
        //  1396   1402   1402   1403   Ljava/util/ConcurrentModificationException;
        //  1396   1402   3      8      Any
        //  1396   1402   3      8      Any
        //  1406   1413   1413   1414   Any
        //  1407   1413   3      8      Any
        //  1406   1413   1413   1414   Ljava/util/NoSuchElementException;
        //  1406   1413   1413   1414   Ljava/lang/RuntimeException;
        //  1407   1413   1406   1407   Ljava/lang/IndexOutOfBoundsException;
        //  1423   1430   1430   1431   Any
        //  1424   1430   1423   1424   Any
        //  1423   1430   1423   1424   Ljava/util/NoSuchElementException;
        //  1423   1430   1430   1431   Ljava/lang/RuntimeException;
        //  1423   1430   1430   1431   Ljava/lang/EnumConstantNotPresentException;
        //  1490   1497   1497   1498   Any
        //  1490   1497   3      8      Ljava/lang/StringIndexOutOfBoundsException;
        //  1491   1497   1497   1498   Any
        //  1491   1497   3      8      Any
        //  1490   1497   1490   1491   Ljava/lang/ArithmeticException;
        //  1501   1508   1508   1509   Any
        //  1501   1508   1508   1509   Any
        //  1501   1508   1501   1502   Ljava/lang/NegativeArraySizeException;
        //  1501   1508   1508   1509   Any
        //  1501   1508   3      8      Any
        //  1560   1566   1566   1567   Any
        //  1560   1566   3      8      Ljava/lang/ArrayIndexOutOfBoundsException;
        //  1560   1566   3      8      Ljava/lang/IndexOutOfBoundsException;
        //  1560   1566   1566   1567   Any
        //  1560   1566   3      8      Any
        //  1617   1624   1624   1625   Any
        //  1618   1624   1617   1618   Ljava/lang/ClassCastException;
        //  1618   1624   3      8      Ljava/lang/AssertionError;
        //  1617   1624   1624   1625   Any
        //  1618   1624   3      8      Ljava/lang/IndexOutOfBoundsException;
        //  1634   1641   1641   1642   Any
        //  1634   1641   1641   1642   Ljava/lang/EnumConstantNotPresentException;
        //  1635   1641   1634   1635   Ljava/lang/ArrayIndexOutOfBoundsException;
        //  1635   1641   3      8      Any
        //  1635   1641   1641   1642   Any
        //  1648   1655   1655   1656   Any
        //  1648   1655   1648   1649   Ljava/lang/EnumConstantNotPresentException;
        //  1648   1655   1655   1656   Ljava/lang/EnumConstantNotPresentException;
        //  1649   1655   3      8      Any
        //  1648   1655   1655   1656   Ljava/util/NoSuchElementException;
        //  1659   1666   1666   1667   Any
        //  1660   1666   1666   1667   Any
        //  1660   1666   3      8      Ljava/util/NoSuchElementException;
        //  1660   1666   1659   1660   Any
        //  1660   1666   3      8      Any
        //  1680   1686   1686   1687   Any
        //  1680   1686   1686   1687   Ljava/lang/IllegalArgumentException;
        //  1680   1686   3      8      Ljava/lang/NumberFormatException;
        //  1680   1686   1686   1687   Any
        //  1680   1686   3      8      Any
        //  1735   1742   1742   1743   Any
        //  1735   1742   1735   1736   Any
        //  1736   1742   3      8      Any
        //  1735   1742   3      8      Any
        //  1736   1742   1742   1743   Any
        //  1747   1753   1753   1754   Any
        //  1747   1753   1753   1754   Ljava/lang/IndexOutOfBoundsException;
        //  1747   1753   3      8      Any
        //  1747   1753   3      8      Any
        //  1747   1753   1753   1754   Ljava/lang/IllegalArgumentException;
        //  1803   1810   1810   1811   Any
        //  1804   1810   3      8      Any
        //  1804   1810   1810   1811   Any
        //  1803   1810   1810   1811   Ljava/lang/ClassCastException;
        //  1803   1810   1803   1804   Any
        //  1814   1821   1821   1822   Any
        //  1815   1821   1814   1815   Ljava/lang/ArrayIndexOutOfBoundsException;
        //  1814   1821   1814   1815   Any
        //  1815   1821   1821   1822   Any
        //  1815   1821   1821   1822   Any
        //  1871   1878   1878   1879   Any
        //  1872   1878   3      8      Any
        //  1872   1878   3      8      Ljava/lang/IllegalArgumentException;
        //  1871   1878   3      8      Any
        //  1872   1878   1871   1872   Ljava/lang/StringIndexOutOfBoundsException;
        //  1884   1891   1891   1892   Any
        //  1885   1891   1891   1892   Ljava/lang/NumberFormatException;
        //  1885   1891   1884   1885   Ljava/lang/UnsupportedOperationException;
        //  1885   1891   3      8      Any
        //  1884   1891   3      8      Ljava/lang/IndexOutOfBoundsException;
        //  1904   1911   1911   1912   Any
        //  1904   1911   3      8      Ljava/lang/AssertionError;
        //  1905   1911   1904   1905   Any
        //  1904   1911   1904   1905   Any
        //  1904   1911   1904   1905   Ljava/lang/IndexOutOfBoundsException;
        //  1963   1970   1970   1971   Any
        //  1963   1970   1963   1964   Any
        //  1964   1970   1970   1971   Any
        //  1964   1970   1963   1964   Ljava/util/NoSuchElementException;
        //  1963   1970   1963   1964   Ljava/lang/AssertionError;
        //  1974   1981   1981   1982   Any
        //  1975   1981   3      8      Any
        //  1975   1981   1981   1982   Ljava/lang/RuntimeException;
        //  1974   1981   1974   1975   Any
        //  1975   1981   1981   1982   Ljava/lang/ArrayIndexOutOfBoundsException;
        //  2040   2047   2047   2048   Any
        //  2041   2047   2047   2048   Any
        //  2041   2047   2040   2041   Ljava/lang/EnumConstantNotPresentException;
        //  2041   2047   2047   2048   Ljava/lang/RuntimeException;
        //  2041   2047   3      8      Any
        //  2095   2102   2102   2103   Any
        //  2095   2102   2095   2096   Ljava/lang/NumberFormatException;
        //  2096   2102   2102   2103   Ljava/lang/EnumConstantNotPresentException;
        //  2096   2102   3      8      Ljava/lang/ArithmeticException;
        //  2096   2102   2102   2103   Any
        //  2152   2158   2158   2159   Any
        //  2152   2158   3      8      Any
        //  2152   2158   2158   2159   Any
        //  2152   2158   3      8      Ljava/lang/ClassCastException;
        //  2152   2158   3      8      Ljava/lang/ArithmeticException;
        //  2162   2169   2169   2170   Any
        //  2162   2169   3      8      Any
        //  2162   2169   2162   2163   Ljava/lang/UnsupportedOperationException;
        //  2163   2169   3      8      Ljava/lang/AssertionError;
        //  2163   2169   2162   2163   Any
        //  2173   2180   2180   2181   Any
        //  2173   2180   2173   2174   Ljava/lang/UnsupportedOperationException;
        //  2174   2180   2180   2181   Ljava/lang/IllegalArgumentException;
        //  2173   2180   2173   2174   Any
        //  2173   2180   2180   2181   Ljava/lang/IndexOutOfBoundsException;
        //  2185   2191   2191   2192   Any
        //  2185   2191   2191   2192   Ljava/lang/IllegalArgumentException;
        //  2185   2191   2191   2192   Ljava/lang/RuntimeException;
        //  2185   2191   2191   2192   Ljava/lang/IllegalArgumentException;
        //  2185   2191   2191   2192   Any
        //  2247   2254   2254   2255   Any
        //  2248   2254   3      8      Ljava/lang/StringIndexOutOfBoundsException;
        //  2248   2254   2254   2255   Ljava/lang/UnsupportedOperationException;
        //  2247   2254   3      8      Ljava/lang/ClassCastException;
        //  2248   2254   2247   2248   Any
        //  2261   2268   2268   2269   Any
        //  2261   2268   2261   2262   Ljava/lang/RuntimeException;
        //  2262   2268   2268   2269   Ljava/lang/IndexOutOfBoundsException;
        //  2261   2268   2261   2262   Any
        //  2261   2268   3      8      Any
        //  2319   2326   2326   2327   Any
        //  2319   2326   2319   2320   Any
        //  2320   2326   2319   2320   Ljava/lang/ArithmeticException;
        //  2320   2326   3      8      Any
        //  2319   2326   2326   2327   Ljava/lang/RuntimeException;
        //  2383   2390   2390   2391   Any
        //  2383   2390   2383   2384   Any
        //  2383   2390   3      8      Any
        //  2383   2390   2383   2384   Ljava/lang/ClassCastException;
        //  2384   2390   2390   2391   Ljava/lang/IndexOutOfBoundsException;
        //  2394   2401   2401   2402   Any
        //  2394   2401   2394   2395   Any
        //  2395   2401   3      8      Ljava/lang/NumberFormatException;
        //  2394   2401   2394   2395   Ljava/lang/NumberFormatException;
        //  2395   2401   2401   2402   Any
        //  2405   2414   2414   2415   Any
        //  2405   2414   2405   2406   Ljava/lang/ArithmeticException;
        //  2406   2414   2405   2406   Ljava/lang/IllegalArgumentException;
        //  2406   2414   3      8      Any
        //  2406   2414   3      8      Ljava/lang/IllegalArgumentException;
        //  2516   2522   2522   2523   Any
        //  2516   2522   3      8      Any
        //  2516   2522   3      8      Any
        //  2516   2522   3      8      Ljava/lang/RuntimeException;
        //  2516   2522   3      8      Any
        //  2526   2533   2533   2534   Any
        //  2527   2533   3      8      Any
        //  2527   2533   2526   2527   Ljava/lang/ArrayIndexOutOfBoundsException;
        //  2527   2533   3      8      Any
        //  2526   2533   2533   2534   Any
        //  2586   2593   2593   2594   Any
        //  2587   2593   2586   2587   Ljava/lang/NullPointerException;
        //  2586   2593   2586   2587   Any
        //  2586   2593   2586   2587   Any
        //  2587   2593   3      8      Ljava/lang/EnumConstantNotPresentException;
        //  2597   2604   2604   2605   Any
        //  2597   2604   3      8      Ljava/lang/UnsupportedOperationException;
        //  2597   2604   2597   2598   Any
        //  2598   2604   3      8      Any
        //  2597   2604   2604   2605   Ljava/lang/EnumConstantNotPresentException;
        //  2608   2617   2617   2618   Any
        //  2609   2617   2617   2618   Any
        //  2608   2617   2608   2609   Ljava/lang/IndexOutOfBoundsException;
        //  2609   2617   3      8      Ljava/lang/StringIndexOutOfBoundsException;
        //  2608   2617   2608   2609   Ljava/lang/StringIndexOutOfBoundsException;
        //  2716   2724   2724   2725   Any
        //  2716   2724   2724   2725   Any
        //  2716   2724   3      8      Any
        //  2716   2724   2724   2725   Any
        //  2716   2724   3      8      Any
        //  2769   2778   2778   2779   Any
        //  2769   2778   3      8      Any
        //  2769   2778   3      8      Ljava/lang/StringIndexOutOfBoundsException;
        //  2769   2778   3      8      Ljava/lang/IllegalArgumentException;
        //  2770   2778   2769   2770   Ljava/lang/IllegalStateException;
        //  2835   2842   2842   2843   Any
        //  2836   2842   2842   2843   Ljava/lang/NegativeArraySizeException;
        //  2836   2842   3      8      Ljava/lang/UnsupportedOperationException;
        //  2835   2842   2842   2843   Ljava/lang/StringIndexOutOfBoundsException;
        //  2836   2842   2835   2836   Ljava/util/NoSuchElementException;
        //  2846   2853   2853   2854   Any
        //  2847   2853   2853   2854   Any
        //  2847   2853   2846   2847   Ljava/lang/UnsupportedOperationException;
        //  2847   2853   2846   2847   Any
        //  2847   2853   3      8      Any
        //  2864   2871   2871   2872   Any
        //  2864   2871   2864   2865   Ljava/lang/ClassCastException;
        //  2865   2871   2864   2865   Ljava/lang/AssertionError;
        //  2864   2871   3      8      Ljava/lang/NullPointerException;
        //  2865   2871   2864   2865   Any
        //  2967   2974   2974   2975   Any
        //  2967   2974   3      8      Any
        //  2967   2974   2967   2968   Ljava/lang/NullPointerException;
        //  2968   2974   3      8      Ljava/lang/StringIndexOutOfBoundsException;
        //  2967   2974   2974   2975   Ljava/lang/ArrayIndexOutOfBoundsException;
        //  2978   2985   2985   2986   Any
        //  2979   2985   2978   2979   Any
        //  2979   2985   2985   2986   Ljava/lang/NullPointerException;
        //  2978   2985   3      8      Ljava/lang/ArrayIndexOutOfBoundsException;
        //  2978   2985   3      8      Any
        //  2990   2997   2997   2998   Any
        //  2990   2997   2997   2998   Ljava/lang/NumberFormatException;
        //  2990   2997   3      8      Any
        //  2991   2997   2990   2991   Ljava/lang/NullPointerException;
        //  2991   2997   2990   2991   Ljava/util/ConcurrentModificationException;
        //  3069   3076   3076   3077   Any
        //  3070   3076   3076   3077   Any
        //  3070   3076   3069   3070   Ljava/lang/ArrayIndexOutOfBoundsException;
        //  3070   3076   3      8      Any
        //  3069   3076   3      8      Ljava/lang/ArrayIndexOutOfBoundsException;
        // 
        // The error that occurred was:
        // 
        // java.lang.IndexOutOfBoundsException: Index -1 out of bounds for length 0
        //     at java.base/jdk.internal.util.Preconditions.outOfBounds(Preconditions.java:64)
        //     at java.base/jdk.internal.util.Preconditions.outOfBoundsCheckIndex(Preconditions.java:70)
        //     at java.base/jdk.internal.util.Preconditions.checkIndex(Preconditions.java:248)
        //     at java.base/java.util.Objects.checkIndex(Objects.java:372)
        //     at java.base/java.util.ArrayList.remove(ArrayList.java:535)
        //     at com.strobel.assembler.ir.StackMappingVisitor.pop(StackMappingVisitor.java:267)
        //     at com.strobel.assembler.ir.StackMappingVisitor$InstructionAnalyzer.execute(StackMappingVisitor.java:577)
        //     at com.strobel.assembler.ir.StackMappingVisitor$InstructionAnalyzer.visit(StackMappingVisitor.java:398)
        //     at com.strobel.decompiler.ast.AstBuilder.performStackAnalysis(AstBuilder.java:2030)
        //     at com.strobel.decompiler.ast.AstBuilder.build(AstBuilder.java:108)
        //     at com.strobel.decompiler.languages.java.ast.AstMethodBodyBuilder.createMethodBody(AstMethodBodyBuilder.java:211)
        //     at com.strobel.decompiler.languages.java.ast.AstMethodBodyBuilder.createMethodBody(AstMethodBodyBuilder.java:99)
        //     at com.strobel.decompiler.languages.java.ast.AstBuilder.createMethodBody(AstBuilder.java:782)
        //     at com.strobel.decompiler.languages.java.ast.AstBuilder.createMethod(AstBuilder.java:675)
        //     at com.strobel.decompiler.languages.java.ast.AstBuilder.addTypeMembers(AstBuilder.java:552)
        //     at com.strobel.decompiler.languages.java.ast.AstBuilder.createTypeCore(AstBuilder.java:519)
        //     at com.strobel.decompiler.languages.java.ast.AstBuilder.createTypeNoCache(AstBuilder.java:161)
        //     at com.strobel.decompiler.languages.java.ast.AstBuilder.createType(AstBuilder.java:150)
        //     at com.strobel.decompiler.languages.java.ast.AstBuilder.addType(AstBuilder.java:125)
        //     at com.strobel.decompiler.languages.java.JavaLanguage.buildAst(JavaLanguage.java:71)
        //     at com.strobel.decompiler.languages.java.JavaLanguage.decompileType(JavaLanguage.java:59)
        //     at com.strobel.decompiler.DecompilerDriver.decompileType(DecompilerDriver.java:330)
        //     at com.strobel.decompiler.DecompilerDriver.decompileJar(DecompilerDriver.java:251)
        //     at com.strobel.decompiler.DecompilerDriver.main(DecompilerDriver.java:126)
        // 
        throw new IllegalStateException("An error occurred while decompiling this method.");
    }
    
    public faC(final DefaultConstructorMarker defaultConstructorMarker) {
        this();
    }
}
