// 
// Decompiled by Procyon v0.5.36
// 

package dev.nuker.pyro;

import org.jetbrains.annotations.NotNull;

public class fay implements faw
{
    public fay() {
        while (true) {
            int n = 0;
            Label_0013: {
                if (fc.c < 0) {
                    n = 351572975;
                    break Label_0013;
                }
                n = -1887413406;
            }
            switch (n ^ 0x3B79BFC3) {
                case -270169116: {
                    continue;
                }
                default: {}
                case 797781036: {
                    throw null;
                }
            }
            break;
        }
    }
    
    static {
        throw t;
    }
    
    @Override
    public boolean c(@NotNull final fax p0, @NotNull final fa p1) {
        // 
        // This method could not be decompiled.
        // 
        // Original Bytecode:
        // 
        //     3: dup            
        //     4: ifnull          781
        //     7: athrow         
        //     8: aconst_null    
        //     9: getstatic       dev/nuker/pyro/fc.c:I
        //    12: iflt            773
        //    15: pop            
        //    16: aconst_null    
        //    17: goto            765
        //    20: nop            
        //    21: nop            
        //    22: nop            
        //    23: athrow         
        //    24: getstatic       dev/nuker/pyro/fc.c:I
        //    27: ifge            35
        //    30: ldc             1932563730
        //    32: goto            37
        //    35: ldc             -1349640031
        //    37: ldc             -1901613018
        //    39: ixor           
        //    40: lookupswitch {
        //          -40426188: 754
        //          2131427469: 35
        //          default: 68
        //        }
        //    68: aload_1        
        //    69: pop            
        //    70: getstatic       dev/nuker/pyro/fc.0:I
        //    73: ifeq            81
        //    76: ldc             -99712532
        //    78: goto            83
        //    81: ldc             -1768434032
        //    83: ldc             742967117
        //    85: ixor           
        //    86: lookupswitch {
        //          -700037471: 750
        //          1733697090: 81
        //          default: 112
        //        }
        //   112: aload_2        
        //   113: pop            
        //   114: aload_1        
        //   115: getstatic       dev/nuker/pyro/fc.c:I
        //   118: ifge            126
        //   121: ldc             -584367268
        //   123: goto            128
        //   126: ldc             -1938356426
        //   128: ldc             540914200
        //   130: ixor           
        //   131: lookupswitch {
        //          -1404390098: 156
        //          -48828092: 126
        //          default: 746
        //        }
        //   156: goto            160
        //   159: athrow         
        //   160: invokevirtual   dev/nuker/pyro/fax.3:()Lnet/minecraft/block/state/IBlockState;
        //   163: goto            167
        //   166: athrow         
        //   167: goto            171
        //   170: athrow         
        //   171: invokeinterface net/minecraft/block/state/IBlockState.func_177230_c:()Lnet/minecraft/block/Block;
        //   176: goto            180
        //   179: athrow         
        //   180: instanceof      Lnet/minecraft/block/BlockSign;
        //   183: ifne            248
        //   186: aload_1        
        //   187: goto            191
        //   190: athrow         
        //   191: invokevirtual   dev/nuker/pyro/fax.3:()Lnet/minecraft/block/state/IBlockState;
        //   194: goto            198
        //   197: athrow         
        //   198: goto            202
        //   201: athrow         
        //   202: invokeinterface net/minecraft/block/state/IBlockState.func_177230_c:()Lnet/minecraft/block/Block;
        //   207: goto            211
        //   210: athrow         
        //   211: instanceof      Lnet/minecraft/block/BlockWallSign;
        //   214: ifeq            222
        //   217: ldc             -2023856355
        //   219: goto            224
        //   222: ldc             -2023856358
        //   224: ldc             1118148638
        //   226: ixor           
        //   227: tableswitch {
        //          -1946681850: 248
        //          -1946681849: 738
        //          default: 217
        //        }
        //   248: getstatic       dev/nuker/pyro/fc.0:I
        //   251: ifeq            259
        //   254: ldc             1229195417
        //   256: goto            261
        //   259: ldc             1241463723
        //   261: ldc             191129505
        //   263: ixor           
        //   264: lookupswitch {
        //          434193259: 259
        //          1109421880: 740
        //          default: 292
        //        }
        //   292: aload_1        
        //   293: goto            297
        //   296: athrow         
        //   297: invokevirtual   dev/nuker/pyro/fax.1:()Lnet/minecraft/tileentity/TileEntity;
        //   300: goto            304
        //   303: athrow         
        //   304: ifnull          738
        //   307: aload_1        
        //   308: getstatic       dev/nuker/pyro/fc.c:I
        //   311: ifge            319
        //   314: ldc             527313025
        //   316: goto            321
        //   319: ldc             1649438632
        //   321: ldc             2121912617
        //   323: ixor           
        //   324: lookupswitch {
        //          472497793: 352
        //          1628961192: 319
        //          default: 752
        //        }
        //   352: goto            356
        //   355: athrow         
        //   356: invokevirtual   dev/nuker/pyro/fax.1:()Lnet/minecraft/tileentity/TileEntity;
        //   359: goto            363
        //   362: athrow         
        //   363: dup            
        //   364: ifnonnull       440
        //   367: new             Lkotlin/TypeCastException;
        //   370: dup            
        //   371: ldc             "\u2964\u1486\u806f\ub1c4\uc408\ue76f\ub225\uec40\udb77\ue434\uadb8\u1e0c\ueb68\uc7b3\u8cfc\u83f4\u57a5\u7d98\ubf38\ucdc7\u218c\uc234\u60c3\u2f49\uda56\u3f01\u7d66\u832e\u8215\u8110\u8e26\ufb72\u7a48\u981e\u161e\ufbe8\u493c\u82e1\uc892\uf2b8\ubc1c\u41fe\ub373\ub157\u41fb\u807c\u7c7b\uc4aa\u7f59\ue75d\uec1c\u16cc\ue4d1\u3593\u4b24\ueb73\u0a19\u8c4b\u1bcd\u02dd\u7d8e\u72c3\ucd50\ub9a2\u975a\u609a\ue2c3\udab4\ua728\u284f\u8328\u4fb8\u81cc\u1610\uae58\u7a4e"
        //   373: goto            377
        //   376: athrow         
        //   377: invokestatic    invokestatic   !!! ERROR
        //   380: goto            384
        //   383: athrow         
        //   384: getstatic       dev/nuker/pyro/fc.1:I
        //   387: ifeq            395
        //   390: ldc             290793101
        //   392: goto            397
        //   395: ldc             93570094
        //   397: ldc             -809856748
        //   399: ixor           
        //   400: lookupswitch {
        //          -903260870: 428
        //          -554715239: 395
        //          default: 744
        //        }
        //   428: goto            432
        //   431: athrow         
        //   432: invokespecial   kotlin/TypeCastException.<init>:(Ljava/lang/String;)V
        //   435: goto            439
        //   438: athrow         
        //   439: athrow         
        //   440: checkcast       Lnet/minecraft/tileentity/TileEntitySign;
        //   443: astore_3       
        //   444: aload_2        
        //   445: new             Ljava/lang/StringBuilder;
        //   448: dup            
        //   449: goto            453
        //   452: athrow         
        //   453: invokespecial   java/lang/StringBuilder.<init>:()V
        //   456: goto            460
        //   459: athrow         
        //   460: aload_3        
        //   461: getfield        net/minecraft/tileentity/TileEntitySign.field_145915_a:[Lnet/minecraft/util/text/ITextComponent;
        //   464: iconst_0       
        //   465: aaload         
        //   466: dup            
        //   467: pop            
        //   468: getstatic       dev/nuker/pyro/fc.c:I
        //   471: ifge            479
        //   474: ldc             1059894448
        //   476: goto            481
        //   479: ldc             -355848804
        //   481: ldc             -124141821
        //   483: ixor           
        //   484: lookupswitch {
        //          -944436301: 479
        //          307466911: 512
        //          default: 742
        //        }
        //   512: goto            516
        //   515: athrow         
        //   516: invokeinterface net/minecraft/util/text/ITextComponent.func_150260_c:()Ljava/lang/String;
        //   521: goto            525
        //   524: athrow         
        //   525: goto            529
        //   528: athrow         
        //   529: invokevirtual   java/lang/StringBuilder.append:(Ljava/lang/String;)Ljava/lang/StringBuilder;
        //   532: goto            536
        //   535: athrow         
        //   536: ldc             "\n"
        //   538: goto            542
        //   541: athrow         
        //   542: invokevirtual   java/lang/StringBuilder.append:(Ljava/lang/String;)Ljava/lang/StringBuilder;
        //   545: goto            549
        //   548: athrow         
        //   549: getstatic       dev/nuker/pyro/fc.c:I
        //   552: ifge            560
        //   555: ldc             -1121137968
        //   557: goto            562
        //   560: ldc             291405926
        //   562: ldc             1982916492
        //   564: ixor           
        //   565: lookupswitch {
        //          -887345828: 748
        //          572006190: 560
        //          default: 592
        //        }
        //   592: aload_3        
        //   593: getfield        net/minecraft/tileentity/TileEntitySign.field_145915_a:[Lnet/minecraft/util/text/ITextComponent;
        //   596: iconst_1       
        //   597: aaload         
        //   598: dup            
        //   599: pop            
        //   600: goto            604
        //   603: athrow         
        //   604: invokeinterface net/minecraft/util/text/ITextComponent.func_150260_c:()Ljava/lang/String;
        //   609: goto            613
        //   612: athrow         
        //   613: goto            617
        //   616: athrow         
        //   617: invokevirtual   java/lang/StringBuilder.append:(Ljava/lang/String;)Ljava/lang/StringBuilder;
        //   620: goto            624
        //   623: athrow         
        //   624: ldc             "\n"
        //   626: goto            630
        //   629: athrow         
        //   630: invokevirtual   java/lang/StringBuilder.append:(Ljava/lang/String;)Ljava/lang/StringBuilder;
        //   633: goto            637
        //   636: athrow         
        //   637: aload_3        
        //   638: getfield        net/minecraft/tileentity/TileEntitySign.field_145915_a:[Lnet/minecraft/util/text/ITextComponent;
        //   641: iconst_2       
        //   642: aaload         
        //   643: dup            
        //   644: pop            
        //   645: goto            649
        //   648: athrow         
        //   649: invokeinterface net/minecraft/util/text/ITextComponent.func_150260_c:()Ljava/lang/String;
        //   654: goto            658
        //   657: athrow         
        //   658: goto            662
        //   661: athrow         
        //   662: invokevirtual   java/lang/StringBuilder.append:(Ljava/lang/String;)Ljava/lang/StringBuilder;
        //   665: goto            669
        //   668: athrow         
        //   669: ldc             "\n"
        //   671: goto            675
        //   674: athrow         
        //   675: invokevirtual   java/lang/StringBuilder.append:(Ljava/lang/String;)Ljava/lang/StringBuilder;
        //   678: goto            682
        //   681: athrow         
        //   682: aload_3        
        //   683: getfield        net/minecraft/tileentity/TileEntitySign.field_145915_a:[Lnet/minecraft/util/text/ITextComponent;
        //   686: iconst_3       
        //   687: aaload         
        //   688: dup            
        //   689: pop            
        //   690: goto            694
        //   693: athrow         
        //   694: invokeinterface net/minecraft/util/text/ITextComponent.func_150260_c:()Ljava/lang/String;
        //   699: goto            703
        //   702: athrow         
        //   703: goto            707
        //   706: athrow         
        //   707: invokevirtual   java/lang/StringBuilder.append:(Ljava/lang/String;)Ljava/lang/StringBuilder;
        //   710: goto            714
        //   713: athrow         
        //   714: goto            718
        //   717: athrow         
        //   718: invokevirtual   java/lang/StringBuilder.toString:()Ljava/lang/String;
        //   721: goto            725
        //   724: athrow         
        //   725: goto            729
        //   728: athrow         
        //   729: invokevirtual   dev/nuker/pyro/fa.c:(Ljava/lang/String;)V
        //   732: goto            736
        //   735: athrow         
        //   736: iconst_1       
        //   737: ireturn        
        //   738: iconst_0       
        //   739: ireturn        
        //   740: aconst_null    
        //   741: athrow         
        //   742: aconst_null    
        //   743: athrow         
        //   744: aconst_null    
        //   745: athrow         
        //   746: aconst_null    
        //   747: athrow         
        //   748: aconst_null    
        //   749: athrow         
        //   750: aconst_null    
        //   751: athrow         
        //   752: aconst_null    
        //   753: athrow         
        //   754: aconst_null    
        //   755: athrow         
        //   756: pop            
        //   757: goto            24
        //   760: pop            
        //   761: aconst_null    
        //   762: goto            756
        //   765: dup            
        //   766: ifnull          756
        //   769: checkcast       Ljava/lang/Throwable;
        //   772: athrow         
        //   773: dup            
        //   774: ifnull          760
        //   777: checkcast       Ljava/lang/Throwable;
        //   780: athrow         
        //   781: aconst_null    
        //   782: athrow         
        //    StackMapTable: 00 87 43 07 00 3C 04 FF 00 0B 00 00 00 01 07 00 3C FE 00 03 07 00 03 07 00 4A 07 00 96 0A 41 01 1E 0C 41 01 1C 4D 07 00 4A FF 00 01 00 03 07 00 03 07 00 4A 07 00 96 00 02 07 00 4A 01 5B 07 00 4A FF 00 02 00 00 00 01 07 00 3C FF 00 00 00 03 07 00 03 07 00 4A 07 00 96 00 01 07 00 4A 45 07 00 3C 40 07 00 50 42 07 00 3C 40 07 00 50 47 07 00 3C 40 07 00 9A 49 07 00 24 40 07 00 4A 45 07 00 3C 40 07 00 50 42 07 00 3C 40 07 00 50 47 07 00 3C 40 07 00 9A 05 04 41 01 17 0A 41 01 1E 43 07 00 3C 40 07 00 4A 45 07 00 3C 40 07 00 9C 4E 07 00 4A FF 00 01 00 03 07 00 03 07 00 4A 07 00 96 00 02 07 00 4A 01 5E 07 00 4A 42 07 00 2E 40 07 00 4A 45 07 00 3C 40 07 00 9C 4C 07 00 22 FF 00 00 00 03 07 00 03 07 00 4A 07 00 96 00 04 07 00 9C 08 01 6F 08 01 6F 07 00 9E 45 07 00 3C FF 00 00 00 03 07 00 03 07 00 4A 07 00 96 00 04 07 00 9C 08 01 6F 08 01 6F 07 00 9E FF 00 0A 00 03 07 00 03 07 00 4A 07 00 96 00 04 07 00 9C 08 01 6F 08 01 6F 07 00 9E FF 00 01 00 03 07 00 03 07 00 4A 07 00 96 00 05 07 00 9C 08 01 6F 08 01 6F 07 00 9E 01 FF 00 1E 00 03 07 00 03 07 00 4A 07 00 96 00 04 07 00 9C 08 01 6F 08 01 6F 07 00 9E 42 07 00 3C FF 00 00 00 03 07 00 03 07 00 4A 07 00 96 00 04 07 00 9C 08 01 6F 08 01 6F 07 00 9E 45 07 00 3C FF 00 00 00 03 07 00 03 07 00 4A 07 00 96 00 02 07 00 9C 07 00 67 40 07 00 9C FF 00 0B 00 04 07 00 03 07 00 4A 07 00 96 07 00 78 00 01 07 00 32 FF 00 00 00 04 07 00 03 07 00 4A 07 00 96 07 00 78 00 03 07 00 96 08 01 BD 08 01 BD 45 07 00 3C FF 00 00 00 04 07 00 03 07 00 4A 07 00 96 07 00 78 00 02 07 00 96 07 00 7A FF 00 12 00 04 07 00 03 07 00 4A 07 00 96 07 00 78 00 03 07 00 96 07 00 7A 07 00 84 FF 00 01 00 04 07 00 03 07 00 4A 07 00 96 07 00 78 00 04 07 00 96 07 00 7A 07 00 84 01 FF 00 1E 00 04 07 00 03 07 00 4A 07 00 96 07 00 78 00 03 07 00 96 07 00 7A 07 00 84 42 07 00 1E FF 00 00 00 04 07 00 03 07 00 4A 07 00 96 07 00 78 00 03 07 00 96 07 00 7A 07 00 84 47 07 00 3C FF 00 00 00 04 07 00 03 07 00 4A 07 00 96 07 00 78 00 03 07 00 96 07 00 7A 07 00 9E FF 00 02 00 00 00 01 07 00 3C FF 00 00 00 04 07 00 03 07 00 4A 07 00 96 07 00 78 00 03 07 00 96 07 00 7A 07 00 9E 45 07 00 3C FF 00 00 00 04 07 00 03 07 00 4A 07 00 96 07 00 78 00 02 07 00 96 07 00 7A 44 07 00 3C FF 00 00 00 04 07 00 03 07 00 4A 07 00 96 07 00 78 00 03 07 00 96 07 00 7A 07 00 9E 45 07 00 3C FF 00 00 00 04 07 00 03 07 00 4A 07 00 96 07 00 78 00 02 07 00 96 07 00 7A FF 00 0A 00 04 07 00 03 07 00 4A 07 00 96 07 00 78 00 02 07 00 96 07 00 7A FF 00 01 00 04 07 00 03 07 00 4A 07 00 96 07 00 78 00 03 07 00 96 07 00 7A 01 FF 00 1D 00 04 07 00 03 07 00 4A 07 00 96 07 00 78 00 02 07 00 96 07 00 7A FF 00 0A 00 00 00 01 07 00 3C FF 00 00 00 04 07 00 03 07 00 4A 07 00 96 07 00 78 00 03 07 00 96 07 00 7A 07 00 84 47 07 00 3C FF 00 00 00 04 07 00 03 07 00 4A 07 00 96 07 00 78 00 03 07 00 96 07 00 7A 07 00 9E 42 07 00 3C FF 00 00 00 04 07 00 03 07 00 4A 07 00 96 07 00 78 00 03 07 00 96 07 00 7A 07 00 9E 45 07 00 3C FF 00 00 00 04 07 00 03 07 00 4A 07 00 96 07 00 78 00 02 07 00 96 07 00 7A 44 07 00 2E FF 00 00 00 04 07 00 03 07 00 4A 07 00 96 07 00 78 00 03 07 00 96 07 00 7A 07 00 9E 45 07 00 3C FF 00 00 00 04 07 00 03 07 00 4A 07 00 96 07 00 78 00 02 07 00 96 07 00 7A 4A 07 00 28 FF 00 00 00 04 07 00 03 07 00 4A 07 00 96 07 00 78 00 03 07 00 96 07 00 7A 07 00 84 47 07 00 3C FF 00 00 00 04 07 00 03 07 00 4A 07 00 96 07 00 78 00 03 07 00 96 07 00 7A 07 00 9E 42 07 00 28 FF 00 00 00 04 07 00 03 07 00 4A 07 00 96 07 00 78 00 03 07 00 96 07 00 7A 07 00 9E 45 07 00 3C FF 00 00 00 04 07 00 03 07 00 4A 07 00 96 07 00 78 00 02 07 00 96 07 00 7A 44 07 00 3C FF 00 00 00 04 07 00 03 07 00 4A 07 00 96 07 00 78 00 03 07 00 96 07 00 7A 07 00 9E 45 07 00 3C FF 00 00 00 04 07 00 03 07 00 4A 07 00 96 07 00 78 00 02 07 00 96 07 00 7A 4A 07 00 3C FF 00 00 00 04 07 00 03 07 00 4A 07 00 96 07 00 78 00 03 07 00 96 07 00 7A 07 00 84 47 07 00 3C FF 00 00 00 04 07 00 03 07 00 4A 07 00 96 07 00 78 00 03 07 00 96 07 00 7A 07 00 9E 42 07 00 3C FF 00 00 00 04 07 00 03 07 00 4A 07 00 96 07 00 78 00 03 07 00 96 07 00 7A 07 00 9E 45 07 00 3C FF 00 00 00 04 07 00 03 07 00 4A 07 00 96 07 00 78 00 02 07 00 96 07 00 7A 42 07 00 3C FF 00 00 00 04 07 00 03 07 00 4A 07 00 96 07 00 78 00 02 07 00 96 07 00 7A 45 07 00 3C FF 00 00 00 04 07 00 03 07 00 4A 07 00 96 07 00 78 00 02 07 00 96 07 00 9E 42 07 00 3C FF 00 00 00 04 07 00 03 07 00 4A 07 00 96 07 00 78 00 02 07 00 96 07 00 9E 45 07 00 3C 00 FA 00 01 01 FF 00 01 00 04 07 00 03 07 00 4A 07 00 96 07 00 78 00 03 07 00 96 07 00 7A 07 00 84 FF 00 01 00 03 07 00 03 07 00 4A 07 00 96 00 04 07 00 9C 08 01 6F 08 01 6F 07 00 9E 41 07 00 4A FF 00 01 00 04 07 00 03 07 00 4A 07 00 96 07 00 78 00 02 07 00 96 07 00 7A FA 00 01 41 07 00 4A 01 41 07 00 3C 43 05 44 07 00 3C 47 05 47 07 00 3C
        //    Exceptions:
        //  Try           Handler
        //  Start  End    Start  End    Type                                       
        //  -----  -----  -----  -----  -------------------------------------------
        //  8      20     765    773    Any
        //  765    773    765    773    Any
        //  781    783    3      8      Ljava/lang/ClassCastException;
        //  160    166    166    167    Any
        //  160    166    166    167    Ljava/lang/NegativeArraySizeException;
        //  160    166    166    167    Ljava/lang/ClassCastException;
        //  160    166    166    167    Ljava/lang/EnumConstantNotPresentException;
        //  160    166    166    167    Any
        //  170    179    179    180    Any
        //  171    179    3      8      Ljava/lang/ArithmeticException;
        //  170    179    179    180    Ljava/lang/NegativeArraySizeException;
        //  170    179    179    180    Any
        //  170    179    170    171    Any
        //  190    197    197    198    Any
        //  190    197    190    191    Ljava/lang/NumberFormatException;
        //  190    197    197    198    Ljava/lang/NumberFormatException;
        //  190    197    197    198    Ljava/lang/ArrayIndexOutOfBoundsException;
        //  190    197    3      8      Ljava/lang/ClassCastException;
        //  201    210    210    211    Any
        //  201    210    210    211    Ljava/lang/RuntimeException;
        //  201    210    201    202    Any
        //  201    210    3      8      Any
        //  201    210    210    211    Ljava/lang/StringIndexOutOfBoundsException;
        //  296    303    303    304    Any
        //  296    303    296    297    Any
        //  296    303    3      8      Ljava/lang/IllegalStateException;
        //  297    303    3      8      Any
        //  297    303    303    304    Ljava/lang/IllegalStateException;
        //  355    362    362    363    Any
        //  355    362    362    363    Ljava/lang/ArithmeticException;
        //  356    362    3      8      Ljava/lang/IllegalStateException;
        //  356    362    362    363    Ljava/lang/StringIndexOutOfBoundsException;
        //  355    362    355    356    Ljava/lang/UnsupportedOperationException;
        //  376    383    383    384    Any
        //  377    383    376    377    Ljava/lang/ArithmeticException;
        //  376    383    3      8      Ljava/lang/RuntimeException;
        //  376    383    3      8      Any
        //  377    383    383    384    Ljava/lang/IllegalArgumentException;
        //  431    438    438    439    Any
        //  431    438    431    432    Any
        //  431    438    431    432    Any
        //  431    438    431    432    Ljava/lang/NegativeArraySizeException;
        //  431    438    438    439    Any
        //  452    459    459    460    Any
        //  452    459    3      8      Ljava/lang/ArrayIndexOutOfBoundsException;
        //  453    459    459    460    Ljava/lang/EnumConstantNotPresentException;
        //  453    459    459    460    Any
        //  452    459    452    453    Ljava/lang/IndexOutOfBoundsException;
        //  515    524    524    525    Any
        //  515    524    524    525    Any
        //  516    524    515    516    Ljava/lang/NegativeArraySizeException;
        //  516    524    3      8      Ljava/util/NoSuchElementException;
        //  516    524    524    525    Ljava/lang/AssertionError;
        //  529    535    535    536    Any
        //  529    535    535    536    Any
        //  529    535    535    536    Any
        //  529    535    3      8      Any
        //  529    535    3      8      Any
        //  541    548    548    549    Any
        //  542    548    541    542    Any
        //  541    548    541    542    Any
        //  541    548    3      8      Any
        //  541    548    3      8      Any
        //  604    612    612    613    Any
        //  604    612    612    613    Any
        //  604    612    3      8      Any
        //  604    612    612    613    Ljava/lang/IllegalStateException;
        //  604    612    612    613    Ljava/lang/AssertionError;
        //  616    623    623    624    Any
        //  617    623    3      8      Ljava/util/ConcurrentModificationException;
        //  617    623    616    617    Ljava/lang/IndexOutOfBoundsException;
        //  616    623    616    617    Any
        //  617    623    623    624    Any
        //  629    636    636    637    Any
        //  629    636    3      8      Ljava/lang/NegativeArraySizeException;
        //  629    636    636    637    Any
        //  629    636    3      8      Ljava/lang/NullPointerException;
        //  629    636    629    630    Ljava/lang/UnsupportedOperationException;
        //  648    657    657    658    Any
        //  649    657    3      8      Ljava/lang/ClassCastException;
        //  648    657    657    658    Ljava/lang/IllegalArgumentException;
        //  649    657    648    649    Ljava/lang/RuntimeException;
        //  649    657    3      8      Ljava/lang/UnsupportedOperationException;
        //  661    668    668    669    Any
        //  661    668    668    669    Ljava/lang/IllegalStateException;
        //  661    668    661    662    Ljava/lang/NumberFormatException;
        //  661    668    668    669    Any
        //  661    668    661    662    Ljava/util/NoSuchElementException;
        //  674    681    681    682    Any
        //  674    681    681    682    Ljava/lang/IllegalArgumentException;
        //  674    681    674    675    Any
        //  675    681    3      8      Any
        //  675    681    681    682    Any
        //  693    702    702    703    Any
        //  694    702    693    694    Ljava/lang/AssertionError;
        //  693    702    693    694    Any
        //  693    702    702    703    Ljava/lang/ArrayIndexOutOfBoundsException;
        //  694    702    702    703    Any
        //  706    713    713    714    Any
        //  707    713    3      8      Any
        //  706    713    706    707    Any
        //  706    713    706    707    Any
        //  707    713    713    714    Any
        //  717    724    724    725    Any
        //  718    724    724    725    Any
        //  717    724    724    725    Ljava/lang/IllegalArgumentException;
        //  717    724    724    725    Ljava/lang/RuntimeException;
        //  717    724    717    718    Any
        //  728    735    735    736    Any
        //  728    735    728    729    Ljava/lang/ArithmeticException;
        //  729    735    728    729    Any
        //  729    735    3      8      Ljava/lang/NullPointerException;
        //  729    735    735    736    Ljava/lang/IllegalStateException;
        // 
        // The error that occurred was:
        // 
        // java.lang.IndexOutOfBoundsException: Index -1 out of bounds for length 0
        //     at java.base/jdk.internal.util.Preconditions.outOfBounds(Preconditions.java:64)
        //     at java.base/jdk.internal.util.Preconditions.outOfBoundsCheckIndex(Preconditions.java:70)
        //     at java.base/jdk.internal.util.Preconditions.checkIndex(Preconditions.java:248)
        //     at java.base/java.util.Objects.checkIndex(Objects.java:372)
        //     at java.base/java.util.ArrayList.remove(ArrayList.java:535)
        //     at com.strobel.assembler.ir.StackMappingVisitor.pop(StackMappingVisitor.java:267)
        //     at com.strobel.assembler.ir.StackMappingVisitor$InstructionAnalyzer.execute(StackMappingVisitor.java:776)
        //     at com.strobel.assembler.ir.StackMappingVisitor$InstructionAnalyzer.visit(StackMappingVisitor.java:398)
        //     at com.strobel.decompiler.ast.AstBuilder.performStackAnalysis(AstBuilder.java:2030)
        //     at com.strobel.decompiler.ast.AstBuilder.build(AstBuilder.java:108)
        //     at com.strobel.decompiler.languages.java.ast.AstMethodBodyBuilder.createMethodBody(AstMethodBodyBuilder.java:211)
        //     at com.strobel.decompiler.languages.java.ast.AstMethodBodyBuilder.createMethodBody(AstMethodBodyBuilder.java:99)
        //     at com.strobel.decompiler.languages.java.ast.AstBuilder.createMethodBody(AstBuilder.java:782)
        //     at com.strobel.decompiler.languages.java.ast.AstBuilder.createMethod(AstBuilder.java:675)
        //     at com.strobel.decompiler.languages.java.ast.AstBuilder.addTypeMembers(AstBuilder.java:552)
        //     at com.strobel.decompiler.languages.java.ast.AstBuilder.createTypeCore(AstBuilder.java:519)
        //     at com.strobel.decompiler.languages.java.ast.AstBuilder.createTypeNoCache(AstBuilder.java:161)
        //     at com.strobel.decompiler.languages.java.ast.AstBuilder.createType(AstBuilder.java:150)
        //     at com.strobel.decompiler.languages.java.ast.AstBuilder.addType(AstBuilder.java:125)
        //     at com.strobel.decompiler.languages.java.JavaLanguage.buildAst(JavaLanguage.java:71)
        //     at com.strobel.decompiler.languages.java.JavaLanguage.decompileType(JavaLanguage.java:59)
        //     at com.strobel.decompiler.DecompilerDriver.decompileType(DecompilerDriver.java:330)
        //     at com.strobel.decompiler.DecompilerDriver.decompileJar(DecompilerDriver.java:251)
        //     at com.strobel.decompiler.DecompilerDriver.main(DecompilerDriver.java:126)
        // 
        throw new IllegalStateException("An error occurred while decompiling this method.");
    }
}
