// 
// Decompiled by Procyon v0.5.36
// 

package dev.nuker.pyro;

import dev.nuker.pyro.security.inject.LauncherEventHide;

public class fb0 extends fH
{
    public f0f<fbc> c;
    public f0d c;
    public f0d 0;
    
    public fb0() {
        // 
        // This method could not be decompiled.
        // 
        // Original Bytecode:
        // 
        //     3: ifeq            11
        //     6: ldc             -1318983384
        //     8: goto            13
        //    11: ldc             488451511
        //    13: ldc             858931402
        //    15: ixor           
        //    16: lookupswitch {
        //          -2108446238: 11
        //          774860157: 44
        //          default: 694
        //        }
        //    44: aload_0        
        //    45: ldc             "\u290f\u1483\u8008\ub3dc\uc677\ue717\ub22d\uec2e\ud96d"
        //    47: invokestatic    invokestatic   !!! ERROR
        //    50: ldc             "\u292f\u1483\u8008\ub3dc\uc677\ue717\ub22d\uec2e\ud96d"
        //    52: getstatic       dev/nuker/pyro/fc.0:I
        //    55: ifeq            63
        //    58: ldc             -2091244009
        //    60: goto            65
        //    63: ldc             -1011450610
        //    65: ldc             1093241920
        //    67: ixor           
        //    68: lookupswitch {
        //          -2103447218: 96
        //          -1032607145: 63
        //          default: 690
        //        }
        //    96: invokestatic    invokestatic   !!! ERROR
        //    99: ldc             "\u293d\u149f\u8001\ub3d6\uc664\ue709\ub264\uec39\ud967\ue615\uad9a\u1e58\ueb0b\uc5e7\u8e8a\u8388\u57aa\u7de0\ubd7d\ucfbe\u21e2\uc234\u60ee\u2d5d\ud871\u3f39\u7d2d\u834f\u8002\u8333\u8e59\ufb20"
        //   101: invokestatic    invokestatic   !!! ERROR
        //   104: getstatic       dev/nuker/pyro/fc.c:I
        //   107: ifge            115
        //   110: ldc             -690772740
        //   112: goto            117
        //   115: ldc             299517656
        //   117: ldc             56701152
        //   119: ixor           
        //   120: lookupswitch {
        //          -709716964: 680
        //          623582681: 115
        //          default: 148
        //        }
        //   148: invokespecial   dev/nuker/pyro/fH.<init>:(Ljava/lang/String;Ljava/lang/String;Ljava/lang/String;)V
        //   151: aload_0        
        //   152: new             Ldev/nuker/pyro/f0f;
        //   155: dup            
        //   156: ldc             "\u2911\u149c\u8009\ub3dc"
        //   158: invokestatic    invokestatic   !!! ERROR
        //   161: ldc             "\u2931\u149c\u8009\ub3dc"
        //   163: invokestatic    invokestatic   !!! ERROR
        //   166: aconst_null    
        //   167: getstatic       dev/nuker/pyro/fc.1:I
        //   170: ifeq            178
        //   173: ldc             -1450391934
        //   175: goto            180
        //   178: ldc             -825439280
        //   180: ldc             -1807358390
        //   182: ixor           
        //   183: lookupswitch {
        //          989415765: 178
        //          1036591304: 692
        //          default: 208
        //        }
        //   208: getstatic       dev/nuker/pyro/fbc.c:Ldev/nuker/pyro/fbc;
        //   211: invokespecial   dev/nuker/pyro/f0f.<init>:(Ljava/lang/String;Ljava/lang/String;Ljava/lang/String;Ljava/lang/Enum;)V
        //   214: getstatic       dev/nuker/pyro/fc.1:I
        //   217: ifeq            225
        //   220: ldc             496017901
        //   222: goto            227
        //   225: ldc             578760189
        //   227: ldc             -1023188279
        //   229: ixor           
        //   230: lookupswitch {
        //          -560741596: 225
        //          -511946956: 256
        //          default: 682
        //        }
        //   256: putfield        dev/nuker/pyro/fb0.c:Ldev/nuker/pyro/f0f;
        //   259: getstatic       dev/nuker/pyro/fc.c:I
        //   262: ifge            270
        //   265: ldc             880913648
        //   267: goto            272
        //   270: ldc             -93186355
        //   272: ldc             1956168215
        //   274: ixor           
        //   275: lookupswitch {
        //          -1836401795: 270
        //          1075408615: 700
        //          default: 300
        //        }
        //   300: aload_0        
        //   301: new             Ldev/nuker/pyro/f0d;
        //   304: dup            
        //   305: ldc             "\u290f\u1487\u800c\ub3cb\uc667\ue73e\ub225\uec2d\ud969\ue607\uaddf"
        //   307: invokestatic    invokestatic   !!! ERROR
        //   310: ldc             "\u292f\u1487\u800c\ub3cb\uc667\ue75a\ub200\uec21\ud965\ue601\uaddd\u1e49"
        //   312: invokestatic    invokestatic   !!! ERROR
        //   315: aconst_null    
        //   316: dconst_0       
        //   317: dconst_0       
        //   318: dconst_1       
        //   319: invokespecial   dev/nuker/pyro/f0d.<init>:(Ljava/lang/String;Ljava/lang/String;Ljava/lang/String;DDD)V
        //   322: getstatic       dev/nuker/pyro/fc.c:I
        //   325: ifge            333
        //   328: ldc             -416959336
        //   330: goto            335
        //   333: ldc             -917490364
        //   335: ldc             -1992078847
        //   337: ixor           
        //   338: lookupswitch {
        //          1075019589: 364
        //          1852243609: 333
        //          default: 686
        //        }
        //   364: putfield        dev/nuker/pyro/fb0.c:Ldev/nuker/pyro/f0d;
        //   367: aload_0        
        //   368: new             Ldev/nuker/pyro/f0d;
        //   371: dup            
        //   372: ldc             "\u2919\u149d\u8009\ub3dd\uc672\ue717\ub225\uec27\ud96d"
        //   374: getstatic       dev/nuker/pyro/fc.0:I
        //   377: ifeq            385
        //   380: ldc             -1307438410
        //   382: goto            387
        //   385: ldc             -1531460638
        //   387: ldc             -532929677
        //   389: ixor           
        //   390: lookupswitch {
        //          1150017681: 416
        //          1378759109: 385
        //          default: 676
        //        }
        //   416: invokestatic    invokestatic   !!! ERROR
        //   419: ldc             "\u2939\u149d\u8009\ub399\uc657\ue71b\ub229\uec21\ud96f\ue605"
        //   421: invokestatic    invokestatic   !!! ERROR
        //   424: aconst_null    
        //   425: ldc2_w          0.699999988079071
        //   428: dconst_0       
        //   429: dconst_1       
        //   430: getstatic       dev/nuker/pyro/fc.1:I
        //   433: ifeq            441
        //   436: ldc             -241865608
        //   438: goto            443
        //   441: ldc             1706125126
        //   443: ldc             656040495
        //   445: ixor           
        //   446: lookupswitch {
        //          -695267753: 698
        //          670541314: 441
        //          default: 472
        //        }
        //   472: invokespecial   dev/nuker/pyro/f0d.<init>:(Ljava/lang/String;Ljava/lang/String;Ljava/lang/String;DDD)V
        //   475: getstatic       dev/nuker/pyro/fc.1:I
        //   478: ifeq            486
        //   481: ldc             2023151872
        //   483: goto            488
        //   486: ldc             -556107605
        //   488: ldc             -622213518
        //   490: ixor           
        //   491: lookupswitch {
        //          -1568727182: 684
        //          1152997480: 486
        //          default: 516
        //        }
        //   516: putfield        dev/nuker/pyro/fb0.0:Ldev/nuker/pyro/f0d;
        //   519: aload_0        
        //   520: aload_0        
        //   521: getfield        dev/nuker/pyro/fb0.c:Ldev/nuker/pyro/f0f;
        //   524: invokevirtual   dev/nuker/pyro/fb0.c:(Ldev/nuker/pyro/f0n;)Ldev/nuker/pyro/f0n;
        //   527: pop            
        //   528: aload_0        
        //   529: aload_0        
        //   530: getfield        dev/nuker/pyro/fb0.c:Ldev/nuker/pyro/f0d;
        //   533: getstatic       dev/nuker/pyro/fc.c:I
        //   536: ifge            544
        //   539: ldc             -1948887211
        //   541: goto            546
        //   544: ldc             -1978480007
        //   546: ldc             -1495626187
        //   548: ixor           
        //   549: lookupswitch {
        //          751322188: 576
        //          755816800: 544
        //          default: 696
        //        }
        //   576: invokevirtual   dev/nuker/pyro/fb0.c:(Ldev/nuker/pyro/f0n;)Ldev/nuker/pyro/f0n;
        //   579: pop            
        //   580: getstatic       dev/nuker/pyro/fc.c:I
        //   583: ifge            591
        //   586: ldc             1441440332
        //   588: goto            593
        //   591: ldc             1084224063
        //   593: ldc             737912301
        //   595: ixor           
        //   596: lookupswitch {
        //          1801738194: 624
        //          2115045281: 591
        //          default: 688
        //        }
        //   624: aload_0        
        //   625: aload_0        
        //   626: getstatic       dev/nuker/pyro/fc.1:I
        //   629: ifeq            637
        //   632: ldc             -1491986537
        //   634: goto            639
        //   637: ldc             970727774
        //   639: ldc             -275583644
        //   641: ixor           
        //   642: lookupswitch {
        //          -699478982: 668
        //          1216412403: 637
        //          default: 678
        //        }
        //   668: getfield        dev/nuker/pyro/fb0.0:Ldev/nuker/pyro/f0d;
        //   671: invokevirtual   dev/nuker/pyro/fb0.c:(Ldev/nuker/pyro/f0n;)Ldev/nuker/pyro/f0n;
        //   674: pop            
        //   675: return         
        //   676: aconst_null    
        //   677: athrow         
        //   678: aconst_null    
        //   679: athrow         
        //   680: aconst_null    
        //   681: athrow         
        //   682: aconst_null    
        //   683: athrow         
        //   684: aconst_null    
        //   685: athrow         
        //   686: aconst_null    
        //   687: athrow         
        //   688: aconst_null    
        //   689: athrow         
        //   690: aconst_null    
        //   691: athrow         
        //   692: aconst_null    
        //   693: athrow         
        //   694: aconst_null    
        //   695: athrow         
        //   696: aconst_null    
        //   697: athrow         
        //   698: aconst_null    
        //   699: athrow         
        //   700: aconst_null    
        //   701: athrow         
        //    StackMapTable: 00 34 0B 41 01 1E FF 00 12 00 01 06 00 03 06 07 00 73 07 00 73 FF 00 01 00 01 06 00 04 06 07 00 73 07 00 73 01 FF 00 1E 00 01 06 00 03 06 07 00 73 07 00 73 FF 00 12 00 01 06 00 04 06 07 00 73 07 00 73 07 00 73 FF 00 01 00 01 06 00 05 06 07 00 73 07 00 73 07 00 73 01 FF 00 1E 00 01 06 00 04 06 07 00 73 07 00 73 07 00 73 FF 00 1D 00 01 07 00 03 00 06 07 00 03 08 00 98 08 00 98 07 00 73 07 00 73 05 FF 00 01 00 01 07 00 03 00 07 07 00 03 08 00 98 08 00 98 07 00 73 07 00 73 05 01 FF 00 1B 00 01 07 00 03 00 06 07 00 03 08 00 98 08 00 98 07 00 73 07 00 73 05 FF 00 10 00 01 07 00 03 00 02 07 00 03 07 00 2C FF 00 01 00 01 07 00 03 00 03 07 00 03 07 00 2C 01 FF 00 1C 00 01 07 00 03 00 02 07 00 03 07 00 2C 0D 41 01 1B FF 00 20 00 01 07 00 03 00 02 07 00 03 07 00 48 FF 00 01 00 01 07 00 03 00 03 07 00 03 07 00 48 01 FF 00 1C 00 01 07 00 03 00 02 07 00 03 07 00 48 FF 00 14 00 01 07 00 03 00 04 07 00 03 08 01 70 08 01 70 07 00 73 FF 00 01 00 01 07 00 03 00 05 07 00 03 08 01 70 08 01 70 07 00 73 01 FF 00 1C 00 01 07 00 03 00 04 07 00 03 08 01 70 08 01 70 07 00 73 FF 00 18 00 01 07 00 03 00 09 07 00 03 08 01 70 08 01 70 07 00 73 07 00 73 05 03 03 03 FF 00 01 00 01 07 00 03 00 0A 07 00 03 08 01 70 08 01 70 07 00 73 07 00 73 05 03 03 03 01 FF 00 1C 00 01 07 00 03 00 09 07 00 03 08 01 70 08 01 70 07 00 73 07 00 73 05 03 03 03 FF 00 0D 00 01 07 00 03 00 02 07 00 03 07 00 48 FF 00 01 00 01 07 00 03 00 03 07 00 03 07 00 48 01 FF 00 1B 00 01 07 00 03 00 02 07 00 03 07 00 48 FF 00 1B 00 01 07 00 03 00 02 07 00 03 07 00 48 FF 00 01 00 01 07 00 03 00 03 07 00 03 07 00 48 01 FF 00 1D 00 01 07 00 03 00 02 07 00 03 07 00 48 0E 41 01 1E FF 00 0C 00 01 07 00 03 00 02 07 00 03 07 00 03 FF 00 01 00 01 07 00 03 00 03 07 00 03 07 00 03 01 FF 00 1C 00 01 07 00 03 00 02 07 00 03 07 00 03 FF 00 07 00 01 07 00 03 00 04 07 00 03 08 01 70 08 01 70 07 00 73 FF 00 01 00 01 07 00 03 00 02 07 00 03 07 00 03 FF 00 01 00 01 06 00 04 06 07 00 73 07 00 73 07 00 73 FF 00 01 00 01 07 00 03 00 02 07 00 03 07 00 2C FF 00 01 00 01 07 00 03 00 02 07 00 03 07 00 48 FF 00 01 00 01 07 00 03 00 02 07 00 03 07 00 48 01 FF 00 01 00 01 06 00 03 06 07 00 73 07 00 73 FF 00 01 00 01 07 00 03 00 06 07 00 03 08 00 98 08 00 98 07 00 73 07 00 73 05 FF 00 01 00 01 06 00 00 FF 00 01 00 01 07 00 03 00 02 07 00 03 07 00 48 FF 00 01 00 01 07 00 03 00 09 07 00 03 08 01 70 08 01 70 07 00 73 07 00 73 05 03 03 03 01
        // 
        // The error that occurred was:
        // 
        // java.lang.IllegalStateException: Invalid BootstrapMethods attribute entry: 21 additional arguments required for method a.a, but only 0 specified.
        //     at com.strobel.assembler.ir.Error.invalidBootstrapMethodEntry(Error.java:244)
        //     at com.strobel.assembler.ir.MetadataReader.readAttributeCore(MetadataReader.java:280)
        //     at com.strobel.assembler.metadata.ClassFileReader.readAttributeCore(ClassFileReader.java:261)
        //     at com.strobel.assembler.ir.MetadataReader.inflateAttributes(MetadataReader.java:439)
        //     at com.strobel.assembler.metadata.ClassFileReader.visitAttributes(ClassFileReader.java:1134)
        //     at com.strobel.assembler.metadata.ClassFileReader.readClass(ClassFileReader.java:439)
        //     at com.strobel.assembler.metadata.ClassFileReader.readClass(ClassFileReader.java:377)
        //     at com.strobel.assembler.metadata.MetadataSystem.resolveType(MetadataSystem.java:129)
        //     at com.strobel.decompiler.NoRetryMetadataSystem.resolveType(DecompilerDriver.java:476)
        //     at com.strobel.assembler.metadata.MetadataSystem.resolveCore(MetadataSystem.java:81)
        //     at com.strobel.assembler.metadata.MetadataResolver.resolve(MetadataResolver.java:104)
        //     at com.strobel.assembler.metadata.CoreMetadataFactory$UnresolvedType.resolve(CoreMetadataFactory.java:616)
        //     at com.strobel.assembler.metadata.MetadataResolver.resolve(MetadataResolver.java:128)
        //     at com.strobel.assembler.metadata.CoreMetadataFactory$UnresolvedType.resolve(CoreMetadataFactory.java:626)
        //     at com.strobel.assembler.metadata.MethodReference.resolve(MethodReference.java:177)
        //     at com.strobel.decompiler.ast.TypeAnalysis.inferCall(TypeAnalysis.java:2438)
        //     at com.strobel.decompiler.ast.TypeAnalysis.doInferTypeForExpression(TypeAnalysis.java:1029)
        //     at com.strobel.decompiler.ast.TypeAnalysis.inferTypeForExpression(TypeAnalysis.java:803)
        //     at com.strobel.decompiler.ast.TypeAnalysis.inferTypeForExpression(TypeAnalysis.java:770)
        //     at com.strobel.decompiler.ast.TypeAnalysis.doInferTypeForExpression(TypeAnalysis.java:881)
        //     at com.strobel.decompiler.ast.TypeAnalysis.inferTypeForExpression(TypeAnalysis.java:803)
        //     at com.strobel.decompiler.ast.TypeAnalysis.runInference(TypeAnalysis.java:672)
        //     at com.strobel.decompiler.ast.TypeAnalysis.runInference(TypeAnalysis.java:655)
        //     at com.strobel.decompiler.ast.TypeAnalysis.runInference(TypeAnalysis.java:365)
        //     at com.strobel.decompiler.ast.TypeAnalysis.run(TypeAnalysis.java:96)
        //     at com.strobel.decompiler.ast.AstOptimizer.optimize(AstOptimizer.java:109)
        //     at com.strobel.decompiler.ast.AstOptimizer.optimize(AstOptimizer.java:42)
        //     at com.strobel.decompiler.languages.java.ast.AstMethodBodyBuilder.createMethodBody(AstMethodBodyBuilder.java:214)
        //     at com.strobel.decompiler.languages.java.ast.AstMethodBodyBuilder.createMethodBody(AstMethodBodyBuilder.java:99)
        //     at com.strobel.decompiler.languages.java.ast.AstBuilder.createMethodBody(AstBuilder.java:782)
        //     at com.strobel.decompiler.languages.java.ast.AstBuilder.createConstructor(AstBuilder.java:713)
        //     at com.strobel.decompiler.languages.java.ast.AstBuilder.addTypeMembers(AstBuilder.java:549)
        //     at com.strobel.decompiler.languages.java.ast.AstBuilder.createTypeCore(AstBuilder.java:519)
        //     at com.strobel.decompiler.languages.java.ast.AstBuilder.createTypeNoCache(AstBuilder.java:161)
        //     at com.strobel.decompiler.languages.java.ast.AstBuilder.createType(AstBuilder.java:150)
        //     at com.strobel.decompiler.languages.java.ast.AstBuilder.addType(AstBuilder.java:125)
        //     at com.strobel.decompiler.languages.java.JavaLanguage.buildAst(JavaLanguage.java:71)
        //     at com.strobel.decompiler.languages.java.JavaLanguage.decompileType(JavaLanguage.java:59)
        //     at com.strobel.decompiler.DecompilerDriver.decompileType(DecompilerDriver.java:330)
        //     at com.strobel.decompiler.DecompilerDriver.decompileJar(DecompilerDriver.java:251)
        //     at com.strobel.decompiler.DecompilerDriver.main(DecompilerDriver.java:126)
        // 
        throw new IllegalStateException("An error occurred while decompiling this method.");
    }
    
    static {
        throw t;
    }
    
    @f06
    @LauncherEventHide
    public void c(final f3h f3h) {
        fbS.hF(this, 1068393566, f3h);
    }
    
    @f06
    @LauncherEventHide
    public void c(final f39 p0) {
        // 
        // This method could not be decompiled.
        // 
        // Original Bytecode:
        // 
        //     3: dup            
        //     4: ifnull          738
        //     7: athrow         
        //     8: aconst_null    
        //     9: getstatic       dev/nuker/pyro/fc.1:I
        //    12: ifgt            730
        //    15: pop            
        //    16: aconst_null    
        //    17: goto            722
        //    20: nop            
        //    21: nop            
        //    22: nop            
        //    23: athrow         
        //    24: aload_1        
        //    25: goto            29
        //    28: athrow         
        //    29: invokevirtual   dev/nuker/pyro/f39.c:()Ldev/nuker/pyro/f2T;
        //    32: goto            36
        //    35: athrow         
        //    36: getstatic       dev/nuker/pyro/fc.0:I
        //    39: ifeq            47
        //    42: ldc             -1505998291
        //    44: goto            49
        //    47: ldc             502972310
        //    49: ldc             -1440248841
        //    51: ixor           
        //    52: lookupswitch {
        //          -198434789: 47
        //          203145690: 711
        //          default: 80
        //        }
        //    80: getstatic       dev/nuker/pyro/f2T.c:Ldev/nuker/pyro/f2T;
        //    83: if_acmpne       690
        //    86: aload_0        
        //    87: getstatic       dev/nuker/pyro/fc.c:I
        //    90: ifge            98
        //    93: ldc             -568639856
        //    95: goto            100
        //    98: ldc             -348242393
        //   100: ldc             646037384
        //   102: ixor           
        //   103: lookupswitch {
        //          -843087441: 128
        //          -124092136: 98
        //          default: 695
        //        }
        //   128: getfield        dev/nuker/pyro/fb0.c:Ldev/nuker/pyro/f0f;
        //   131: goto            135
        //   134: athrow         
        //   135: invokevirtual   dev/nuker/pyro/f0f.3:()Ljava/lang/Object;
        //   138: goto            142
        //   141: athrow         
        //   142: getstatic       dev/nuker/pyro/fc.c:I
        //   145: ifge            153
        //   148: ldc             535466988
        //   150: goto            155
        //   153: ldc             -1240403264
        //   155: ldc             2068447128
        //   157: ixor           
        //   158: lookupswitch {
        //          1688431732: 691
        //          1903337674: 153
        //          default: 184
        //        }
        //   184: getstatic       dev/nuker/pyro/fbc.0:Ldev/nuker/pyro/fbc;
        //   187: if_acmpne       690
        //   190: aload_1        
        //   191: goto            195
        //   194: athrow         
        //   195: invokevirtual   dev/nuker/pyro/f39.c:()V
        //   198: goto            202
        //   201: athrow         
        //   202: aload_0        
        //   203: getstatic       dev/nuker/pyro/fc.c:I
        //   206: ifge            214
        //   209: ldc             681756790
        //   211: goto            216
        //   214: ldc             862464927
        //   216: ldc             1875111479
        //   218: ixor           
        //   219: lookupswitch {
        //          1197549121: 214
        //          1554761128: 244
        //          default: 693
        //        }
        //   244: getfield        dev/nuker/pyro/fb0.c:Lnet/minecraft/client/Minecraft;
        //   247: getfield        net/minecraft/client/Minecraft.field_71439_g:Lnet/minecraft/client/entity/EntityPlayerSP;
        //   250: getstatic       net/minecraft/util/EnumHand.MAIN_HAND:Lnet/minecraft/util/EnumHand;
        //   253: goto            257
        //   256: athrow         
        //   257: invokevirtual   net/minecraft/client/entity/EntityPlayerSP.func_184609_a:(Lnet/minecraft/util/EnumHand;)V
        //   260: goto            264
        //   263: athrow         
        //   264: aload_0        
        //   265: getfield        dev/nuker/pyro/fb0.c:Lnet/minecraft/client/Minecraft;
        //   268: getfield        net/minecraft/client/Minecraft.field_71439_g:Lnet/minecraft/client/entity/EntityPlayerSP;
        //   271: getstatic       dev/nuker/pyro/fc.1:I
        //   274: ifeq            282
        //   277: ldc             -1913467541
        //   279: goto            284
        //   282: ldc             -1071138188
        //   284: ldc             -94778602
        //   286: ixor           
        //   287: lookupswitch {
        //          -1973812504: 282
        //          2007697021: 709
        //          default: 312
        //        }
        //   312: getfield        net/minecraft/client/entity/EntityPlayerSP.field_71174_a:Lnet/minecraft/client/network/NetHandlerPlayClient;
        //   315: new             Lnet/minecraft/network/play/client/CPacketPlayerDigging;
        //   318: dup            
        //   319: getstatic       net/minecraft/network/play/client/CPacketPlayerDigging$Action.START_DESTROY_BLOCK:Lnet/minecraft/network/play/client/CPacketPlayerDigging$Action;
        //   322: aload_1        
        //   323: getstatic       dev/nuker/pyro/fc.1:I
        //   326: ifeq            334
        //   329: ldc             -1612558263
        //   331: goto            336
        //   334: ldc             -1026900690
        //   336: ldc             848669146
        //   338: ixor           
        //   339: lookupswitch {
        //          -1384646253: 334
        //          -262204172: 364
        //          default: 701
        //        }
        //   364: goto            368
        //   367: athrow         
        //   368: invokevirtual   dev/nuker/pyro/f39.0:()Lnet/minecraft/util/math/BlockPos;
        //   371: goto            375
        //   374: athrow         
        //   375: getstatic       dev/nuker/pyro/fc.c:I
        //   378: ifge            386
        //   381: ldc             -104611605
        //   383: goto            388
        //   386: ldc             963948685
        //   388: ldc             1786344410
        //   390: ixor           
        //   391: lookupswitch {
        //          -1816480975: 705
        //          -381910764: 386
        //          default: 416
        //        }
        //   416: aload_1        
        //   417: goto            421
        //   420: athrow         
        //   421: invokevirtual   dev/nuker/pyro/f39.c:()Lnet/minecraft/util/EnumFacing;
        //   424: goto            428
        //   427: athrow         
        //   428: goto            432
        //   431: athrow         
        //   432: invokespecial   net/minecraft/network/play/client/CPacketPlayerDigging.<init>:(Lnet/minecraft/network/play/client/CPacketPlayerDigging$Action;Lnet/minecraft/util/math/BlockPos;Lnet/minecraft/util/EnumFacing;)V
        //   435: goto            439
        //   438: athrow         
        //   439: getstatic       dev/nuker/pyro/fc.1:I
        //   442: ifeq            450
        //   445: ldc             -1680756684
        //   447: goto            452
        //   450: ldc             -1273614629
        //   452: ldc             -1835078672
        //   454: ixor           
        //   455: lookupswitch {
        //          156195780: 450
        //          646497579: 480
        //          default: 707
        //        }
        //   480: goto            484
        //   483: athrow         
        //   484: invokevirtual   net/minecraft/client/network/NetHandlerPlayClient.func_147297_a:(Lnet/minecraft/network/Packet;)V
        //   487: goto            491
        //   490: athrow         
        //   491: aload_0        
        //   492: getstatic       dev/nuker/pyro/fc.1:I
        //   495: ifeq            503
        //   498: ldc             -1088855651
        //   500: goto            505
        //   503: ldc             1738972638
        //   505: ldc             -1883975404
        //   507: ixor           
        //   508: lookupswitch {
        //          816689289: 703
        //          1158811650: 503
        //          default: 536
        //        }
        //   536: getfield        dev/nuker/pyro/fb0.c:Lnet/minecraft/client/Minecraft;
        //   539: getfield        net/minecraft/client/Minecraft.field_71439_g:Lnet/minecraft/client/entity/EntityPlayerSP;
        //   542: getstatic       dev/nuker/pyro/fc.c:I
        //   545: ifge            554
        //   548: ldc_w           -854237131
        //   551: goto            557
        //   554: ldc_w           698391545
        //   557: ldc_w           -838216191
        //   560: ixor           
        //   561: lookupswitch {
        //          -408334856: 588
        //          52213300: 554
        //          default: 699
        //        }
        //   588: getfield        net/minecraft/client/entity/EntityPlayerSP.field_71174_a:Lnet/minecraft/client/network/NetHandlerPlayClient;
        //   591: new             Lnet/minecraft/network/play/client/CPacketPlayerDigging;
        //   594: dup            
        //   595: getstatic       net/minecraft/network/play/client/CPacketPlayerDigging$Action.STOP_DESTROY_BLOCK:Lnet/minecraft/network/play/client/CPacketPlayerDigging$Action;
        //   598: aload_1        
        //   599: goto            603
        //   602: athrow         
        //   603: invokevirtual   dev/nuker/pyro/f39.0:()Lnet/minecraft/util/math/BlockPos;
        //   606: goto            610
        //   609: athrow         
        //   610: aload_1        
        //   611: goto            615
        //   614: athrow         
        //   615: invokevirtual   dev/nuker/pyro/f39.c:()Lnet/minecraft/util/EnumFacing;
        //   618: goto            622
        //   621: athrow         
        //   622: getstatic       dev/nuker/pyro/fc.1:I
        //   625: ifeq            634
        //   628: ldc_w           558546086
        //   631: goto            637
        //   634: ldc_w           959405532
        //   637: ldc_w           704831071
        //   640: ixor           
        //   641: lookupswitch {
        //          189293305: 697
        //          1798217677: 634
        //          default: 668
        //        }
        //   668: goto            672
        //   671: athrow         
        //   672: invokespecial   net/minecraft/network/play/client/CPacketPlayerDigging.<init>:(Lnet/minecraft/network/play/client/CPacketPlayerDigging$Action;Lnet/minecraft/util/math/BlockPos;Lnet/minecraft/util/EnumFacing;)V
        //   675: goto            679
        //   678: athrow         
        //   679: goto            683
        //   682: athrow         
        //   683: invokevirtual   net/minecraft/client/network/NetHandlerPlayClient.func_147297_a:(Lnet/minecraft/network/Packet;)V
        //   686: goto            690
        //   689: athrow         
        //   690: return         
        //   691: aconst_null    
        //   692: athrow         
        //   693: aconst_null    
        //   694: athrow         
        //   695: aconst_null    
        //   696: athrow         
        //   697: aconst_null    
        //   698: athrow         
        //   699: aconst_null    
        //   700: athrow         
        //   701: aconst_null    
        //   702: athrow         
        //   703: aconst_null    
        //   704: athrow         
        //   705: aconst_null    
        //   706: athrow         
        //   707: aconst_null    
        //   708: athrow         
        //   709: aconst_null    
        //   710: athrow         
        //   711: aconst_null    
        //   712: athrow         
        //   713: pop            
        //   714: goto            24
        //   717: pop            
        //   718: aconst_null    
        //   719: goto            713
        //   722: dup            
        //   723: ifnull          713
        //   726: checkcast       Ljava/lang/Throwable;
        //   729: athrow         
        //   730: dup            
        //   731: ifnull          717
        //   734: checkcast       Ljava/lang/Throwable;
        //   737: athrow         
        //   738: aconst_null    
        //   739: athrow         
        //    StackMapTable: 00 65 43 07 00 A2 04 FF 00 0B 00 00 00 01 07 00 A2 FD 00 03 07 00 03 07 00 A4 43 07 00 A2 40 07 00 A4 45 07 00 A2 40 07 00 AC 4A 07 00 AC FF 00 01 00 02 07 00 03 07 00 A4 00 02 07 00 AC 01 5E 07 00 AC 51 07 00 03 FF 00 01 00 02 07 00 03 07 00 A4 00 02 07 00 03 01 5B 07 00 03 45 07 00 88 40 07 00 2C 45 07 00 A2 40 07 01 0A 4A 07 01 0A FF 00 01 00 02 07 00 03 07 00 A4 00 02 07 01 0A 01 5C 07 01 0A 49 07 00 84 40 07 00 A4 45 07 00 A2 00 4B 07 00 03 FF 00 01 00 02 07 00 03 07 00 A4 00 02 07 00 03 01 5B 07 00 03 4B 07 00 A2 FF 00 00 00 02 07 00 03 07 00 A4 00 02 07 00 D1 07 00 CB 45 07 00 A2 00 51 07 00 D1 FF 00 01 00 02 07 00 03 07 00 A4 00 02 07 00 D1 01 5B 07 00 D1 FF 00 15 00 02 07 00 03 07 00 A4 00 05 07 00 F8 08 01 3B 08 01 3B 07 00 E0 07 00 A4 FF 00 01 00 02 07 00 03 07 00 A4 00 06 07 00 F8 08 01 3B 08 01 3B 07 00 E0 07 00 A4 01 FF 00 1B 00 02 07 00 03 07 00 A4 00 05 07 00 F8 08 01 3B 08 01 3B 07 00 E0 07 00 A4 42 07 00 A2 FF 00 00 00 02 07 00 03 07 00 A4 00 05 07 00 F8 08 01 3B 08 01 3B 07 00 E0 07 00 A4 45 07 00 A2 FF 00 00 00 02 07 00 03 07 00 A4 00 05 07 00 F8 08 01 3B 08 01 3B 07 00 E0 07 01 0C FF 00 0A 00 02 07 00 03 07 00 A4 00 05 07 00 F8 08 01 3B 08 01 3B 07 00 E0 07 01 0C FF 00 01 00 02 07 00 03 07 00 A4 00 06 07 00 F8 08 01 3B 08 01 3B 07 00 E0 07 01 0C 01 FF 00 1B 00 02 07 00 03 07 00 A4 00 05 07 00 F8 08 01 3B 08 01 3B 07 00 E0 07 01 0C 43 07 00 A2 FF 00 00 00 02 07 00 03 07 00 A4 00 06 07 00 F8 08 01 3B 08 01 3B 07 00 E0 07 01 0C 07 00 A4 45 07 00 A2 FF 00 00 00 02 07 00 03 07 00 A4 00 06 07 00 F8 08 01 3B 08 01 3B 07 00 E0 07 01 0C 07 01 0E 42 07 00 8E FF 00 00 00 02 07 00 03 07 00 A4 00 06 07 00 F8 08 01 3B 08 01 3B 07 00 E0 07 01 0C 07 01 0E 45 07 00 A2 FF 00 00 00 02 07 00 03 07 00 A4 00 02 07 00 F8 07 00 DE FF 00 0A 00 02 07 00 03 07 00 A4 00 02 07 00 F8 07 00 DE FF 00 01 00 02 07 00 03 07 00 A4 00 03 07 00 F8 07 00 DE 01 FF 00 1B 00 02 07 00 03 07 00 A4 00 02 07 00 F8 07 00 DE 42 07 00 98 FF 00 00 00 02 07 00 03 07 00 A4 00 02 07 00 F8 07 00 DE 45 07 00 A2 00 4B 07 00 03 FF 00 01 00 02 07 00 03 07 00 A4 00 02 07 00 03 01 5E 07 00 03 51 07 00 D1 FF 00 02 00 02 07 00 03 07 00 A4 00 02 07 00 D1 01 5E 07 00 D1 FF 00 0D 00 00 00 01 07 00 A2 FF 00 00 00 02 07 00 03 07 00 A4 00 05 07 00 F8 08 02 4F 08 02 4F 07 00 E0 07 00 A4 45 07 00 A2 FF 00 00 00 02 07 00 03 07 00 A4 00 05 07 00 F8 08 02 4F 08 02 4F 07 00 E0 07 01 0C 43 07 00 8C FF 00 00 00 02 07 00 03 07 00 A4 00 06 07 00 F8 08 02 4F 08 02 4F 07 00 E0 07 01 0C 07 00 A4 45 07 00 A2 FF 00 00 00 02 07 00 03 07 00 A4 00 06 07 00 F8 08 02 4F 08 02 4F 07 00 E0 07 01 0C 07 01 0E FF 00 0B 00 02 07 00 03 07 00 A4 00 06 07 00 F8 08 02 4F 08 02 4F 07 00 E0 07 01 0C 07 01 0E FF 00 02 00 02 07 00 03 07 00 A4 00 07 07 00 F8 08 02 4F 08 02 4F 07 00 E0 07 01 0C 07 01 0E 01 FF 00 1E 00 02 07 00 03 07 00 A4 00 06 07 00 F8 08 02 4F 08 02 4F 07 00 E0 07 01 0C 07 01 0E 42 07 00 A2 FF 00 00 00 02 07 00 03 07 00 A4 00 06 07 00 F8 08 02 4F 08 02 4F 07 00 E0 07 01 0C 07 01 0E 45 07 00 A2 FF 00 00 00 02 07 00 03 07 00 A4 00 02 07 00 F8 07 00 DE 42 07 00 A2 FF 00 00 00 02 07 00 03 07 00 A4 00 02 07 00 F8 07 00 DE 45 07 00 A2 00 40 07 01 0A 41 07 00 03 41 07 00 03 FF 00 01 00 02 07 00 03 07 00 A4 00 06 07 00 F8 08 02 4F 08 02 4F 07 00 E0 07 01 0C 07 01 0E 41 07 00 D1 FF 00 01 00 02 07 00 03 07 00 A4 00 05 07 00 F8 08 01 3B 08 01 3B 07 00 E0 07 00 A4 41 07 00 03 FF 00 01 00 02 07 00 03 07 00 A4 00 05 07 00 F8 08 01 3B 08 01 3B 07 00 E0 07 01 0C FF 00 01 00 02 07 00 03 07 00 A4 00 02 07 00 F8 07 00 DE 41 07 00 D1 41 07 00 AC 41 07 00 A2 43 05 44 07 00 A2 47 05 47 07 00 A2
        //    Exceptions:
        //  Try           Handler
        //  Start  End    Start  End    Type                                       
        //  -----  -----  -----  -----  -------------------------------------------
        //  8      20     722    730    Any
        //  722    730    722    730    Ljava/lang/ClassCastException;
        //  738    740    3      8      Ljava/util/NoSuchElementException;
        //  28     35     35     36     Any
        //  28     35     35     36     Any
        //  28     35     28     29     Any
        //  29     35     3      8      Any
        //  28     35     35     36     Any
        //  134    141    141    142    Any
        //  135    141    3      8      Ljava/util/ConcurrentModificationException;
        //  135    141    134    135    Ljava/lang/StringIndexOutOfBoundsException;
        //  135    141    3      8      Ljava/lang/NegativeArraySizeException;
        //  134    141    3      8      Any
        //  194    201    201    202    Any
        //  195    201    3      8      Ljava/lang/ClassCastException;
        //  194    201    194    195    Ljava/util/NoSuchElementException;
        //  195    201    201    202    Ljava/lang/RuntimeException;
        //  195    201    3      8      Ljava/lang/IllegalStateException;
        //  256    263    263    264    Any
        //  257    263    3      8      Any
        //  257    263    256    257    Any
        //  256    263    256    257    Any
        //  257    263    256    257    Any
        //  367    374    374    375    Any
        //  367    374    367    368    Ljava/lang/AssertionError;
        //  367    374    374    375    Ljava/lang/ClassCastException;
        //  367    374    367    368    Any
        //  367    374    374    375    Ljava/lang/StringIndexOutOfBoundsException;
        //  420    427    427    428    Any
        //  421    427    427    428    Any
        //  420    427    427    428    Ljava/lang/NullPointerException;
        //  421    427    3      8      Any
        //  421    427    420    421    Any
        //  431    438    438    439    Any
        //  432    438    3      8      Ljava/lang/UnsupportedOperationException;
        //  432    438    431    432    Ljava/lang/IllegalStateException;
        //  432    438    3      8      Ljava/lang/ArithmeticException;
        //  431    438    3      8      Ljava/lang/ArithmeticException;
        //  483    490    490    491    Any
        //  483    490    3      8      Any
        //  484    490    3      8      Ljava/lang/StringIndexOutOfBoundsException;
        //  483    490    483    484    Ljava/lang/IllegalArgumentException;
        //  483    490    490    491    Any
        //  603    609    609    610    Any
        //  603    609    3      8      Ljava/util/ConcurrentModificationException;
        //  603    609    3      8      Any
        //  603    609    609    610    Ljava/lang/IndexOutOfBoundsException;
        //  603    609    609    610    Any
        //  614    621    621    622    Any
        //  615    621    614    615    Ljava/lang/NumberFormatException;
        //  614    621    621    622    Ljava/lang/IllegalArgumentException;
        //  615    621    621    622    Ljava/lang/ArrayIndexOutOfBoundsException;
        //  615    621    614    615    Ljava/lang/ArrayIndexOutOfBoundsException;
        //  671    678    678    679    Any
        //  671    678    3      8      Ljava/lang/RuntimeException;
        //  671    678    671    672    Any
        //  671    678    671    672    Ljava/lang/EnumConstantNotPresentException;
        //  671    678    3      8      Ljava/util/ConcurrentModificationException;
        //  682    689    689    690    Any
        //  682    689    3      8      Ljava/lang/NegativeArraySizeException;
        //  682    689    682    683    Ljava/lang/ClassCastException;
        //  682    689    682    683    Any
        //  682    689    689    690    Any
        // 
        // The error that occurred was:
        // 
        // java.lang.IndexOutOfBoundsException: Index -1 out of bounds for length 0
        //     at java.base/jdk.internal.util.Preconditions.outOfBounds(Preconditions.java:64)
        //     at java.base/jdk.internal.util.Preconditions.outOfBoundsCheckIndex(Preconditions.java:70)
        //     at java.base/jdk.internal.util.Preconditions.checkIndex(Preconditions.java:248)
        //     at java.base/java.util.Objects.checkIndex(Objects.java:372)
        //     at java.base/java.util.ArrayList.remove(ArrayList.java:535)
        //     at com.strobel.assembler.ir.StackMappingVisitor.pop(StackMappingVisitor.java:267)
        //     at com.strobel.assembler.ir.StackMappingVisitor$InstructionAnalyzer.execute(StackMappingVisitor.java:667)
        //     at com.strobel.assembler.ir.StackMappingVisitor$InstructionAnalyzer.visit(StackMappingVisitor.java:398)
        //     at com.strobel.decompiler.ast.AstBuilder.performStackAnalysis(AstBuilder.java:2030)
        //     at com.strobel.decompiler.ast.AstBuilder.build(AstBuilder.java:108)
        //     at com.strobel.decompiler.languages.java.ast.AstMethodBodyBuilder.createMethodBody(AstMethodBodyBuilder.java:211)
        //     at com.strobel.decompiler.languages.java.ast.AstMethodBodyBuilder.createMethodBody(AstMethodBodyBuilder.java:99)
        //     at com.strobel.decompiler.languages.java.ast.AstBuilder.createMethodBody(AstBuilder.java:782)
        //     at com.strobel.decompiler.languages.java.ast.AstBuilder.createMethod(AstBuilder.java:675)
        //     at com.strobel.decompiler.languages.java.ast.AstBuilder.addTypeMembers(AstBuilder.java:552)
        //     at com.strobel.decompiler.languages.java.ast.AstBuilder.createTypeCore(AstBuilder.java:519)
        //     at com.strobel.decompiler.languages.java.ast.AstBuilder.createTypeNoCache(AstBuilder.java:161)
        //     at com.strobel.decompiler.languages.java.ast.AstBuilder.createType(AstBuilder.java:150)
        //     at com.strobel.decompiler.languages.java.ast.AstBuilder.addType(AstBuilder.java:125)
        //     at com.strobel.decompiler.languages.java.JavaLanguage.buildAst(JavaLanguage.java:71)
        //     at com.strobel.decompiler.languages.java.JavaLanguage.decompileType(JavaLanguage.java:59)
        //     at com.strobel.decompiler.DecompilerDriver.decompileType(DecompilerDriver.java:330)
        //     at com.strobel.decompiler.DecompilerDriver.decompileJar(DecompilerDriver.java:251)
        //     at com.strobel.decompiler.DecompilerDriver.main(DecompilerDriver.java:126)
        // 
        throw new IllegalStateException("An error occurred while decompiling this method.");
    }
}
