// 
// Decompiled by Procyon v0.5.36
// 

package dev.nuker.pyro;

import java.awt.image.BufferedImage;
import java.util.Map;
import java.util.HashMap;
import java.awt.Font;
import java.util.ArrayList;
import net.minecraftforge.fml.relauncher.Side;
import net.minecraftforge.fml.relauncher.SideOnly;

@SideOnly(Side.CLIENT)
public class fbE
{
    public static boolean c;
    public static ArrayList<fbE> c;
    public static int c;
    public static int 0;
    public static int 1;
    public Font c;
    public int 2;
    public int 3;
    public int 4;
    public fbD[] c;
    public HashMap<String, fbF> c;
    public int 5;
    public int 6;
    public int 7;
    
    public static boolean c(final long n, final Map.Entry entry) {
        return fbS.84(null, 966807986, n, entry);
    }
    
    public fbE(final Font c, final int 2, final int 3) {
        while (true) {
            int n = 0;
            Label_0013: {
                if (fc.0 != 0) {
                    n = 621821812;
                    break Label_0013;
                }
                n = 520979614;
            }
            switch (n ^ 0xEEED4D5E) {
                case -872582614: {
                    continue;
                }
                case -236926528: {
                    this.4 = -1;
                    while (true) {
                        int n2 = 0;
                        Label_0066: {
                            if (fc.1 != 0) {
                                n2 = 1615345795;
                                break Label_0066;
                            }
                            n2 = -2018452078;
                        }
                        switch (n2 ^ 0xA397101D) {
                            case -1008785250: {
                                continue;
                            }
                            case 606588303: {
                                final fbD[] c2 = null;
                                while (true) {
                                    int n3 = 0;
                                    Label_0111: {
                                        if (fc.0 != 0) {
                                            n3 = -1328053118;
                                            break Label_0111;
                                        }
                                        n3 = -410935196;
                                    }
                                    switch (n3 ^ 0x1F5ABC45) {
                                        case -1349699385: {
                                            continue;
                                        }
                                        case -119858143: {
                                            this.c = c2;
                                            while (true) {
                                                int n4 = 0;
                                                Label_0156: {
                                                    if (fc.0 != 0) {
                                                        n4 = 736850567;
                                                        break Label_0156;
                                                    }
                                                    n4 = -1984655599;
                                                }
                                                switch (n4 ^ 0x744559B4) {
                                                    case -1328168529: {
                                                        continue;
                                                    }
                                                    default: {
                                                        while (true) {
                                                            int n5 = 0;
                                                            Label_0202: {
                                                                if (fc.0 != 0) {
                                                                    n5 = -2094147153;
                                                                    break Label_0202;
                                                                }
                                                                n5 = 432262174;
                                                            }
                                                            switch (n5 ^ 0x9C21B617) {
                                                                case 520908728: {
                                                                    continue;
                                                                }
                                                                case -2048755191: {
                                                                    this.c = new HashMap<String, fbF>();
                                                                    this.5 = 0;
                                                                    while (true) {
                                                                        int n6 = 0;
                                                                        Label_0256: {
                                                                            if (fc.c < 0) {
                                                                                n6 = -407120788;
                                                                                break Label_0256;
                                                                            }
                                                                            n6 = 440793443;
                                                                        }
                                                                        switch (n6 ^ 0x11E814E4) {
                                                                            case -162283384: {
                                                                                continue;
                                                                            }
                                                                            case 195947911: {
                                                                                final int 4 = 0;
                                                                                while (true) {
                                                                                    int n7 = 0;
                                                                                    Label_0299: {
                                                                                        if (fc.1 != 0) {
                                                                                            n7 = -1018466868;
                                                                                            break Label_0299;
                                                                                        }
                                                                                        n7 = 1884551673;
                                                                                    }
                                                                                    switch (n7 ^ 0x32CBDD38) {
                                                                                        case -243224332: {
                                                                                            continue;
                                                                                        }
                                                                                        case 1117267137: {
                                                                                            this.6 = 4;
                                                                                            this.7 = 0;
                                                                                            while (true) {
                                                                                                int n8 = 0;
                                                                                                Label_0349: {
                                                                                                    if (fc.c < 0) {
                                                                                                        n8 = -56030478;
                                                                                                        break Label_0349;
                                                                                                    }
                                                                                                    n8 = 134671062;
                                                                                                }
                                                                                                switch (n8 ^ 0xA9D9A6FA) {
                                                                                                    case 158626970: {
                                                                                                        continue;
                                                                                                    }
                                                                                                    default: {
                                                                                                        while (true) {
                                                                                                            int n9 = 0;
                                                                                                            Label_0394: {
                                                                                                                if (fc.1 != 0) {
                                                                                                                    n9 = 1305364764;
                                                                                                                    break Label_0394;
                                                                                                                }
                                                                                                                n9 = 1028441397;
                                                                                                            }
                                                                                                            switch (n9 ^ 0x8780B0E1) {
                                                                                                                case -1956363271: {
                                                                                                                    continue;
                                                                                                                }
                                                                                                                default: {
                                                                                                                    while (true) {
                                                                                                                        int n10 = 0;
                                                                                                                        Label_0438: {
                                                                                                                            if (fc.c < 0) {
                                                                                                                                n10 = -2121705810;
                                                                                                                                break Label_0438;
                                                                                                                            }
                                                                                                                            n10 = 178970676;
                                                                                                                        }
                                                                                                                        switch (n10 ^ 0xBF44B285) {
                                                                                                                            case 1053680683: {
                                                                                                                                continue;
                                                                                                                            }
                                                                                                                            case -1242672463: {
                                                                                                                                this.c = c;
                                                                                                                                this.2 = 2;
                                                                                                                                while (true) {
                                                                                                                                    int n11 = 0;
                                                                                                                                    Label_0489: {
                                                                                                                                        if (fc.c < 0) {
                                                                                                                                            n11 = -980144630;
                                                                                                                                            break Label_0489;
                                                                                                                                        }
                                                                                                                                        n11 = 1138985469;
                                                                                                                                    }
                                                                                                                                    switch (n11 ^ 0xB4673F6) {
                                                                                                                                        case -98665422: {
                                                                                                                                            continue;
                                                                                                                                        }
                                                                                                                                        default: {
                                                                                                                                            while (true) {
                                                                                                                                                int n12 = 0;
                                                                                                                                                Label_0535: {
                                                                                                                                                    if (fc.0 != 0) {
                                                                                                                                                        n12 = -1859166147;
                                                                                                                                                        break Label_0535;
                                                                                                                                                    }
                                                                                                                                                    n12 = 709693747;
                                                                                                                                                }
                                                                                                                                                switch (n12 ^ 0x6D8D946) {
                                                                                                                                                    case -441746747: {
                                                                                                                                                        continue;
                                                                                                                                                    }
                                                                                                                                                    default: {
                                                                                                                                                        this.3 = 3;
                                                                                                                                                        while (true) {
                                                                                                                                                            int n13 = 0;
                                                                                                                                                            Label_0581: {
                                                                                                                                                                if (fc.0 != 0) {
                                                                                                                                                                    n13 = -124438351;
                                                                                                                                                                    break Label_0581;
                                                                                                                                                                }
                                                                                                                                                                n13 = -551714087;
                                                                                                                                                            }
                                                                                                                                                            switch (n13 ^ 0x8E7736CE) {
                                                                                                                                                                case 1136682335: {
                                                                                                                                                                    continue;
                                                                                                                                                                }
                                                                                                                                                                default: {
                                                                                                                                                                    final fbD[] c3 = new fbD[3];
                                                                                                                                                                    while (true) {
                                                                                                                                                                        int n14 = 0;
                                                                                                                                                                        Label_0629: {
                                                                                                                                                                            if (fc.1 != 0) {
                                                                                                                                                                                n14 = 659653472;
                                                                                                                                                                                break Label_0629;
                                                                                                                                                                            }
                                                                                                                                                                            n14 = 108283112;
                                                                                                                                                                        }
                                                                                                                                                                        switch (n14 ^ 0x550EAC91) {
                                                                                                                                                                            case 1918840817: {
                                                                                                                                                                                continue;
                                                                                                                                                                            }
                                                                                                                                                                            case 1400563833: {
                                                                                                                                                                                this.c = c3;
                                                                                                                                                                                this.c(2, 3);
                                                                                                                                                                                while (true) {
                                                                                                                                                                                    int n15 = 0;
                                                                                                                                                                                    Label_0682: {
                                                                                                                                                                                        if (fc.0 != 0) {
                                                                                                                                                                                            n15 = 299770061;
                                                                                                                                                                                            break Label_0682;
                                                                                                                                                                                        }
                                                                                                                                                                                        n15 = 664230527;
                                                                                                                                                                                    }
                                                                                                                                                                                    switch (n15 ^ 0x9DEF948) {
                                                                                                                                                                                        case 342652822: {
                                                                                                                                                                                            continue;
                                                                                                                                                                                        }
                                                                                                                                                                                        default: {
                                                                                                                                                                                            fbE.c.add(this);
                                                                                                                                                                                            return;
                                                                                                                                                                                        }
                                                                                                                                                                                        case 402708869: {
                                                                                                                                                                                            throw null;
                                                                                                                                                                                        }
                                                                                                                                                                                    }
                                                                                                                                                                                    break;
                                                                                                                                                                                }
                                                                                                                                                                                break;
                                                                                                                                                                            }
                                                                                                                                                                            default: {
                                                                                                                                                                                throw null;
                                                                                                                                                                            }
                                                                                                                                                                        }
                                                                                                                                                                        break;
                                                                                                                                                                    }
                                                                                                                                                                    break;
                                                                                                                                                                }
                                                                                                                                                                case 1994526335: {
                                                                                                                                                                    throw null;
                                                                                                                                                                }
                                                                                                                                                            }
                                                                                                                                                            break;
                                                                                                                                                        }
                                                                                                                                                        break;
                                                                                                                                                    }
                                                                                                                                                    case -1745372805: {
                                                                                                                                                        throw null;
                                                                                                                                                    }
                                                                                                                                                }
                                                                                                                                                break;
                                                                                                                                            }
                                                                                                                                            break;
                                                                                                                                        }
                                                                                                                                        case -825074180: {
                                                                                                                                            throw null;
                                                                                                                                        }
                                                                                                                                    }
                                                                                                                                    break;
                                                                                                                                }
                                                                                                                                break;
                                                                                                                            }
                                                                                                                            default: {
                                                                                                                                throw null;
                                                                                                                            }
                                                                                                                        }
                                                                                                                        break;
                                                                                                                    }
                                                                                                                    break;
                                                                                                                }
                                                                                                                case -900793859: {
                                                                                                                    throw null;
                                                                                                                }
                                                                                                            }
                                                                                                            break;
                                                                                                        }
                                                                                                        break;
                                                                                                    }
                                                                                                    case 1433447432: {
                                                                                                        throw null;
                                                                                                    }
                                                                                                }
                                                                                                break;
                                                                                            }
                                                                                            break;
                                                                                        }
                                                                                        default: {
                                                                                            throw null;
                                                                                        }
                                                                                    }
                                                                                    break;
                                                                                }
                                                                                break;
                                                                            }
                                                                            default: {
                                                                                throw null;
                                                                            }
                                                                        }
                                                                        break;
                                                                    }
                                                                    break;
                                                                }
                                                                default: {
                                                                    throw null;
                                                                }
                                                            }
                                                            break;
                                                        }
                                                        break;
                                                    }
                                                    case 1605249843: {
                                                        throw null;
                                                    }
                                                }
                                                break;
                                            }
                                            break;
                                        }
                                        default: {
                                            throw null;
                                        }
                                    }
                                    break;
                                }
                                break;
                            }
                            default: {
                                throw null;
                            }
                        }
                        break;
                    }
                    break;
                }
                default: {
                    throw null;
                }
            }
            break;
        }
    }
    
    public void c(final Map.Entry entry) {
        fbS.eU(this, 1706884146, entry);
    }
    
    public void c(final int p0, final int p1) {
        // 
        // This method could not be decompiled.
        // 
        // Original Bytecode:
        // 
        //     3: dup            
        //     4: ifnull          1906
        //     7: athrow         
        //     8: aconst_null    
        //     9: getstatic       dev/nuker/pyro/fc.1:I
        //    12: ifgt            1898
        //    15: pop            
        //    16: aconst_null    
        //    17: goto            1890
        //    20: nop            
        //    21: nop            
        //    22: nop            
        //    23: athrow         
        //    24: iload_2        
        //    25: anewarray       Ljava/awt/image/BufferedImage;
        //    28: astore_3       
        //    29: iconst_0       
        //    30: istore          4
        //    32: iconst_0       
        //    33: istore          5
        //    35: iconst_0       
        //    36: istore          6
        //    38: iload_1        
        //    39: istore          7
        //    41: iload           7
        //    43: iload_2        
        //    44: if_icmpge       959
        //    47: aload_0        
        //    48: iload           7
        //    50: i2c            
        //    51: goto            55
        //    54: athrow         
        //    55: invokespecial   dev/nuker/pyro/fbE.c:(C)Ljava/awt/image/BufferedImage;
        //    58: goto            62
        //    61: athrow         
        //    62: astore          8
        //    64: new             Ldev/nuker/pyro/fbD;
        //    67: dup            
        //    68: iload           5
        //    70: iload           6
        //    72: aload           8
        //    74: goto            78
        //    77: athrow         
        //    78: invokevirtual   java/awt/image/BufferedImage.getWidth:()I
        //    81: goto            85
        //    84: athrow         
        //    85: aload           8
        //    87: getstatic       dev/nuker/pyro/fc.0:I
        //    90: ifeq            98
        //    93: ldc             805307224
        //    95: goto            100
        //    98: ldc             2127758767
        //   100: ldc             131843725
        //   102: ixor           
        //   103: lookupswitch {
        //          -940713733: 98
        //          937149909: 1877
        //          default: 128
        //        }
        //   128: goto            132
        //   131: athrow         
        //   132: invokevirtual   java/awt/image/BufferedImage.getHeight:()I
        //   135: goto            139
        //   138: athrow         
        //   139: goto            143
        //   142: athrow         
        //   143: invokespecial   dev/nuker/pyro/fbD.<init>:(IIII)V
        //   146: goto            150
        //   149: athrow         
        //   150: astore          9
        //   152: getstatic       dev/nuker/pyro/fc.0:I
        //   155: ifeq            163
        //   158: ldc             478317470
        //   160: goto            165
        //   163: ldc             1805921201
        //   165: ldc             -796579822
        //   167: ixor           
        //   168: lookupswitch {
        //          -871914612: 1833
        //          -78270022: 163
        //          default: 196
        //        }
        //   196: aload           9
        //   198: getstatic       dev/nuker/pyro/fc.0:I
        //   201: ifeq            209
        //   204: ldc             -87785791
        //   206: goto            211
        //   209: ldc             -291011744
        //   211: ldc             1064754818
        //   213: ixor           
        //   214: lookupswitch {
        //          -978149309: 1851
        //          2131178328: 209
        //          default: 240
        //        }
        //   240: goto            244
        //   243: athrow         
        //   244: invokestatic    dev/nuker/pyro/fbD.c:(Ldev/nuker/pyro/fbD;)I
        //   247: goto            251
        //   250: athrow         
        //   251: aload_0        
        //   252: getfield        dev/nuker/pyro/fbE.4:I
        //   255: if_icmple       317
        //   258: getstatic       dev/nuker/pyro/fc.0:I
        //   261: ifeq            269
        //   264: ldc             1860009322
        //   266: goto            271
        //   269: ldc             420691103
        //   271: ldc             -1991768216
        //   273: ixor           
        //   274: lookupswitch {
        //          -1873069065: 300
        //          -409634302: 269
        //          default: 1855
        //        }
        //   300: aload_0        
        //   301: aload           9
        //   303: goto            307
        //   306: athrow         
        //   307: invokestatic    dev/nuker/pyro/fbD.c:(Ldev/nuker/pyro/fbD;)I
        //   310: goto            314
        //   313: athrow         
        //   314: putfield        dev/nuker/pyro/fbE.4:I
        //   317: aload           9
        //   319: goto            323
        //   322: athrow         
        //   323: invokestatic    dev/nuker/pyro/fbD.c:(Ldev/nuker/pyro/fbD;)I
        //   326: goto            330
        //   329: athrow         
        //   330: iload           4
        //   332: if_icmple       434
        //   335: aload           9
        //   337: getstatic       dev/nuker/pyro/fc.0:I
        //   340: ifeq            348
        //   343: ldc             -148072554
        //   345: goto            350
        //   348: ldc             846517573
        //   350: ldc             2083512295
        //   352: ixor           
        //   353: lookupswitch {
        //          -1962719119: 1859
        //          1536567881: 348
        //          default: 380
        //        }
        //   380: goto            384
        //   383: athrow         
        //   384: invokestatic    dev/nuker/pyro/fbD.c:(Ldev/nuker/pyro/fbD;)I
        //   387: goto            391
        //   390: athrow         
        //   391: getstatic       dev/nuker/pyro/fc.c:I
        //   394: ifge            402
        //   397: ldc             -1204054390
        //   399: goto            404
        //   402: ldc             1239833074
        //   404: ldc             113288351
        //   406: ixor           
        //   407: lookupswitch {
        //          -1090833899: 402
        //          1327955309: 432
        //          default: 1835
        //        }
        //   432: istore          4
        //   434: getstatic       dev/nuker/pyro/fc.0:I
        //   437: ifeq            445
        //   440: ldc             1778302507
        //   442: goto            447
        //   445: ldc             -396108620
        //   447: ldc             856645071
        //   449: ixor           
        //   450: lookupswitch {
        //          -613645957: 476
        //          1525801956: 445
        //          default: 1829
        //        }
        //   476: aload_0        
        //   477: getstatic       dev/nuker/pyro/fc.0:I
        //   480: ifeq            488
        //   483: ldc             172704681
        //   485: goto            490
        //   488: ldc             1135601265
        //   490: ldc             -1064804761
        //   492: ixor           
        //   493: lookupswitch {
        //          -2094548970: 520
        //          -893182514: 488
        //          default: 1839
        //        }
        //   520: getfield        dev/nuker/pyro/fbE.c:[Ldev/nuker/pyro/fbD;
        //   523: arraylength    
        //   524: iload           7
        //   526: if_icmpgt       534
        //   529: ldc             498898991
        //   531: goto            536
        //   534: ldc             498898990
        //   536: ldc             877198973
        //   538: ixor           
        //   539: tableswitch {
        //          1407765668: 560
        //          1407765669: 563
        //          default: 529
        //        }
        //   560: goto            953
        //   563: aload_0        
        //   564: getfield        dev/nuker/pyro/fbE.c:[Ldev/nuker/pyro/fbD;
        //   567: iload           7
        //   569: getstatic       dev/nuker/pyro/fc.1:I
        //   572: ifeq            580
        //   575: ldc             445184048
        //   577: goto            582
        //   580: ldc             1990354969
        //   582: ldc             -1380289165
        //   584: ixor           
        //   585: lookupswitch {
        //          -1221423805: 1873
        //          548052191: 580
        //          default: 612
        //        }
        //   612: aload           9
        //   614: aastore        
        //   615: getstatic       dev/nuker/pyro/fc.0:I
        //   618: ifeq            626
        //   621: ldc             -10829429
        //   623: goto            628
        //   626: ldc             1240194308
        //   628: ldc             602981914
        //   630: ixor           
        //   631: lookupswitch {
        //          -592836719: 626
        //          1780161310: 656
        //          default: 1843
        //        }
        //   656: aload_3        
        //   657: iload           7
        //   659: aload           8
        //   661: aastore        
        //   662: iload           5
        //   664: getstatic       dev/nuker/pyro/fc.c:I
        //   667: ifge            675
        //   670: ldc             395230177
        //   672: goto            677
        //   675: ldc             625930403
        //   677: ldc             -937603987
        //   679: ixor           
        //   680: lookupswitch {
        //          -543950964: 1863
        //          808510843: 675
        //          default: 708
        //        }
        //   708: aload           9
        //   710: goto            714
        //   713: athrow         
        //   714: invokestatic    dev/nuker/pyro/fbD.2:(Ldev/nuker/pyro/fbD;)I
        //   717: goto            721
        //   720: athrow         
        //   721: iadd           
        //   722: istore          5
        //   724: iload           5
        //   726: sipush          2048
        //   729: if_icmple       737
        //   732: ldc             -1283490694
        //   734: goto            739
        //   737: ldc             -1283490695
        //   739: ldc             -522793857
        //   741: ixor           
        //   742: tableswitch {
        //          -1487708150: 764
        //          -1487708149: 953
        //          default: 732
        //        }
        //   764: iload           5
        //   766: aload_0        
        //   767: getfield        dev/nuker/pyro/fbE.6:I
        //   770: if_icmple       778
        //   773: ldc             -198396264
        //   775: goto            780
        //   778: ldc             -198396263
        //   780: ldc             -1775308006
        //   782: ixor           
        //   783: tableswitch {
        //          -1006335228: 804
        //          -1006335227: 897
        //          default: 773
        //        }
        //   804: getstatic       dev/nuker/pyro/fc.c:I
        //   807: ifge            815
        //   810: ldc             -1676939675
        //   812: goto            817
        //   815: ldc             265841840
        //   817: ldc             -1673584927
        //   819: ixor           
        //   820: lookupswitch {
        //          -1748129443: 815
        //          3469444: 1861
        //          default: 848
        //        }
        //   848: aload_0        
        //   849: getstatic       dev/nuker/pyro/fc.1:I
        //   852: ifeq            860
        //   855: ldc             -1538039073
        //   857: goto            862
        //   860: ldc             503412802
        //   862: ldc             1941668146
        //   864: ixor           
        //   865: lookupswitch {
        //          -672603155: 860
        //          1840970096: 892
        //          default: 1869
        //        }
        //   892: iload           5
        //   894: putfield        dev/nuker/pyro/fbE.6:I
        //   897: iconst_0       
        //   898: istore          5
        //   900: iload           6
        //   902: iload           4
        //   904: iadd           
        //   905: getstatic       dev/nuker/pyro/fc.1:I
        //   908: ifeq            916
        //   911: ldc             -84618471
        //   913: goto            918
        //   916: ldc             -1201813133
        //   918: ldc             675053296
        //   920: ixor           
        //   921: lookupswitch {
        //          -1915324219: 916
        //          -758600215: 1837
        //          default: 948
        //        }
        //   948: istore          6
        //   950: iconst_0       
        //   951: istore          4
        //   953: iinc            7, 1
        //   956: goto            41
        //   959: aload_0        
        //   960: iload           6
        //   962: iload           4
        //   964: iadd           
        //   965: putfield        dev/nuker/pyro/fbE.7:I
        //   968: new             Ljava/awt/image/BufferedImage;
        //   971: dup            
        //   972: aload_0        
        //   973: getfield        dev/nuker/pyro/fbE.6:I
        //   976: aload_0        
        //   977: getstatic       dev/nuker/pyro/fc.0:I
        //   980: ifeq            988
        //   983: ldc             -405704595
        //   985: goto            990
        //   988: ldc             682769676
        //   990: ldc             -462915108
        //   992: ixor           
        //   993: lookupswitch {
        //          -858110768: 1020
        //          62458289: 988
        //          default: 1865
        //        }
        //  1020: getfield        dev/nuker/pyro/fbE.7:I
        //  1023: iconst_2       
        //  1024: goto            1028
        //  1027: athrow         
        //  1028: invokespecial   java/awt/image/BufferedImage.<init>:(III)V
        //  1031: goto            1035
        //  1034: athrow         
        //  1035: astore          7
        //  1037: aload           7
        //  1039: goto            1043
        //  1042: athrow         
        //  1043: invokevirtual   java/awt/image/BufferedImage.getGraphics:()Ljava/awt/Graphics;
        //  1046: goto            1050
        //  1049: athrow         
        //  1050: checkcast       Ljava/awt/Graphics2D;
        //  1053: getstatic       dev/nuker/pyro/fc.1:I
        //  1056: ifeq            1064
        //  1059: ldc             2146206229
        //  1061: goto            1066
        //  1064: ldc             -1943976857
        //  1066: ldc             2092090414
        //  1068: ixor           
        //  1069: lookupswitch {
        //          -1968498290: 1064
        //          56510011: 1857
        //          default: 1096
        //        }
        //  1096: astore          8
        //  1098: aload           8
        //  1100: getstatic       dev/nuker/pyro/fc.0:I
        //  1103: ifeq            1112
        //  1106: ldc_w           2135912308
        //  1109: goto            1115
        //  1112: ldc_w           880891360
        //  1115: ldc_w           -334661369
        //  1118: ixor           
        //  1119: lookupswitch {
        //          -1824385421: 1112
        //          -661902105: 1144
        //          default: 1871
        //        }
        //  1144: aload_0        
        //  1145: getfield        dev/nuker/pyro/fbE.c:Ljava/awt/Font;
        //  1148: getstatic       dev/nuker/pyro/fc.1:I
        //  1151: ifeq            1160
        //  1154: ldc_w           -1341098881
        //  1157: goto            1163
        //  1160: ldc_w           1115545604
        //  1163: ldc_w           910279012
        //  1166: ixor           
        //  1167: lookupswitch {
        //          -2041465573: 1849
        //          198116599: 1160
        //          default: 1192
        //        }
        //  1192: goto            1196
        //  1195: athrow         
        //  1196: invokevirtual   java/awt/Graphics2D.setFont:(Ljava/awt/Font;)V
        //  1199: goto            1203
        //  1202: athrow         
        //  1203: aload           8
        //  1205: new             Ljava/awt/Color;
        //  1208: dup            
        //  1209: sipush          255
        //  1212: sipush          255
        //  1215: sipush          255
        //  1218: iconst_0       
        //  1219: getstatic       dev/nuker/pyro/fc.1:I
        //  1222: ifeq            1231
        //  1225: ldc_w           839202539
        //  1228: goto            1234
        //  1231: ldc_w           648563821
        //  1234: ldc_w           1903006533
        //  1237: ixor           
        //  1238: lookupswitch {
        //          1130931630: 1231
        //          1472585512: 1264
        //          default: 1867
        //        }
        //  1264: goto            1268
        //  1267: athrow         
        //  1268: invokespecial   java/awt/Color.<init>:(IIII)V
        //  1271: goto            1275
        //  1274: athrow         
        //  1275: goto            1279
        //  1278: athrow         
        //  1279: invokevirtual   java/awt/Graphics2D.setColor:(Ljava/awt/Color;)V
        //  1282: goto            1286
        //  1285: athrow         
        //  1286: aload           8
        //  1288: iconst_0       
        //  1289: iconst_0       
        //  1290: getstatic       dev/nuker/pyro/fc.0:I
        //  1293: ifeq            1302
        //  1296: ldc_w           -1464089110
        //  1299: goto            1305
        //  1302: ldc_w           1744526702
        //  1305: ldc_w           -2100702081
        //  1308: ixor           
        //  1309: lookupswitch {
        //          -900137070: 1302
        //          712118677: 1847
        //          default: 1336
        //        }
        //  1336: aload_0        
        //  1337: getfield        dev/nuker/pyro/fbE.6:I
        //  1340: aload_0        
        //  1341: getfield        dev/nuker/pyro/fbE.7:I
        //  1344: goto            1348
        //  1347: athrow         
        //  1348: invokevirtual   java/awt/Graphics2D.fillRect:(IIII)V
        //  1351: goto            1355
        //  1354: athrow         
        //  1355: aload           8
        //  1357: getstatic       java/awt/Color.WHITE:Ljava/awt/Color;
        //  1360: goto            1364
        //  1363: athrow         
        //  1364: invokevirtual   java/awt/Graphics2D.setColor:(Ljava/awt/Color;)V
        //  1367: goto            1371
        //  1370: athrow         
        //  1371: iload_1        
        //  1372: istore          9
        //  1374: getstatic       dev/nuker/pyro/fc.1:I
        //  1377: ifeq            1386
        //  1380: ldc_w           2106341810
        //  1383: goto            1389
        //  1386: ldc_w           644227154
        //  1389: ldc_w           1427527456
        //  1392: ixor           
        //  1393: lookupswitch {
        //          681209490: 1831
        //          996329366: 1386
        //          default: 1420
        //        }
        //  1420: iload           9
        //  1422: iload_2        
        //  1423: if_icmpge       1798
        //  1426: aload_3        
        //  1427: getstatic       dev/nuker/pyro/fc.c:I
        //  1430: ifge            1439
        //  1433: ldc_w           -1185598327
        //  1436: goto            1442
        //  1439: ldc_w           1303260254
        //  1442: ldc_w           -1328759315
        //  1445: ixor           
        //  1446: lookupswitch {
        //          -43871821: 1472
        //          161057124: 1439
        //          default: 1875
        //        }
        //  1472: iload           9
        //  1474: aaload         
        //  1475: ifnull          1484
        //  1478: ldc_w           -17488896
        //  1481: goto            1487
        //  1484: ldc_w           -17488893
        //  1487: ldc_w           885503697
        //  1490: ixor           
        //  1491: tableswitch {
        //          -1805310558: 1512
        //          -1805310557: 1792
        //          default: 1478
        //        }
        //  1512: aload_0        
        //  1513: getfield        dev/nuker/pyro/fbE.c:[Ldev/nuker/pyro/fbD;
        //  1516: iload           9
        //  1518: aaload         
        //  1519: ifnull          1528
        //  1522: ldc_w           598410388
        //  1525: goto            1531
        //  1528: ldc_w           598410389
        //  1531: ldc_w           -1946115408
        //  1534: ixor           
        //  1535: tableswitch {
        //          1599556680: 1556
        //          1599556681: 1792
        //          default: 1522
        //        }
        //  1556: aload           8
        //  1558: aload_3        
        //  1559: iload           9
        //  1561: aaload         
        //  1562: getstatic       dev/nuker/pyro/fc.c:I
        //  1565: ifge            1574
        //  1568: ldc_w           -1756107724
        //  1571: goto            1577
        //  1574: ldc_w           1907771111
        //  1577: ldc_w           -778965848
        //  1580: ixor           
        //  1581: lookupswitch {
        //          -930206998: 1574
        //          1187119260: 1845
        //          default: 1608
        //        }
        //  1608: aload_0        
        //  1609: getfield        dev/nuker/pyro/fbE.c:[Ldev/nuker/pyro/fbD;
        //  1612: getstatic       dev/nuker/pyro/fc.0:I
        //  1615: ifeq            1624
        //  1618: ldc_w           -1309176522
        //  1621: goto            1627
        //  1624: ldc_w           -1419617735
        //  1627: ldc_w           546089613
        //  1630: ixor           
        //  1631: lookupswitch {
        //          -1947275084: 1656
        //          -1854199877: 1624
        //          default: 1853
        //        }
        //  1656: iload           9
        //  1658: aaload         
        //  1659: goto            1663
        //  1662: athrow         
        //  1663: invokestatic    dev/nuker/pyro/fbD.0:(Ldev/nuker/pyro/fbD;)I
        //  1666: goto            1670
        //  1669: athrow         
        //  1670: aload_0        
        //  1671: getstatic       dev/nuker/pyro/fc.c:I
        //  1674: ifge            1683
        //  1677: ldc_w           207760720
        //  1680: goto            1686
        //  1683: ldc_w           239036848
        //  1686: ldc_w           1454327709
        //  1689: ixor           
        //  1690: lookupswitch {
        //          1485844013: 1716
        //          1523411661: 1683
        //          default: 1879
        //        }
        //  1716: getfield        dev/nuker/pyro/fbE.c:[Ldev/nuker/pyro/fbD;
        //  1719: iload           9
        //  1721: aaload         
        //  1722: getstatic       dev/nuker/pyro/fc.0:I
        //  1725: ifeq            1734
        //  1728: ldc_w           -1698062235
        //  1731: goto            1737
        //  1734: ldc_w           -149658918
        //  1737: ldc_w           -541175450
        //  1740: ixor           
        //  1741: lookupswitch {
        //          682243004: 1768
        //          1165488387: 1734
        //          default: 1841
        //        }
        //  1768: goto            1772
        //  1771: athrow         
        //  1772: invokestatic    dev/nuker/pyro/fbD.1:(Ldev/nuker/pyro/fbD;)I
        //  1775: goto            1779
        //  1778: athrow         
        //  1779: aconst_null    
        //  1780: goto            1784
        //  1783: athrow         
        //  1784: invokevirtual   java/awt/Graphics2D.drawImage:(Ljava/awt/Image;IILjava/awt/image/ImageObserver;)Z
        //  1787: goto            1791
        //  1790: athrow         
        //  1791: pop            
        //  1792: iinc            9, 1
        //  1795: goto            1374
        //  1798: aload_0        
        //  1799: goto            1803
        //  1802: athrow         
        //  1803: invokestatic    net/minecraft/client/renderer/texture/TextureUtil.func_110996_a:()I
        //  1806: goto            1810
        //  1809: athrow         
        //  1810: aload           7
        //  1812: iconst_1       
        //  1813: iconst_1       
        //  1814: goto            1818
        //  1817: athrow         
        //  1818: invokestatic    net/minecraft/client/renderer/texture/TextureUtil.func_110989_a:(ILjava/awt/image/BufferedImage;ZZ)I
        //  1821: goto            1825
        //  1824: athrow         
        //  1825: putfield        dev/nuker/pyro/fbE.5:I
        //  1828: return         
        //  1829: aconst_null    
        //  1830: athrow         
        //  1831: aconst_null    
        //  1832: athrow         
        //  1833: aconst_null    
        //  1834: athrow         
        //  1835: aconst_null    
        //  1836: athrow         
        //  1837: aconst_null    
        //  1838: athrow         
        //  1839: aconst_null    
        //  1840: athrow         
        //  1841: aconst_null    
        //  1842: athrow         
        //  1843: aconst_null    
        //  1844: athrow         
        //  1845: aconst_null    
        //  1846: athrow         
        //  1847: aconst_null    
        //  1848: athrow         
        //  1849: aconst_null    
        //  1850: athrow         
        //  1851: aconst_null    
        //  1852: athrow         
        //  1853: aconst_null    
        //  1854: athrow         
        //  1855: aconst_null    
        //  1856: athrow         
        //  1857: aconst_null    
        //  1858: athrow         
        //  1859: aconst_null    
        //  1860: athrow         
        //  1861: aconst_null    
        //  1862: athrow         
        //  1863: aconst_null    
        //  1864: athrow         
        //  1865: aconst_null    
        //  1866: athrow         
        //  1867: aconst_null    
        //  1868: athrow         
        //  1869: aconst_null    
        //  1870: athrow         
        //  1871: aconst_null    
        //  1872: athrow         
        //  1873: aconst_null    
        //  1874: athrow         
        //  1875: aconst_null    
        //  1876: athrow         
        //  1877: aconst_null    
        //  1878: athrow         
        //  1879: aconst_null    
        //  1880: athrow         
        //  1881: pop            
        //  1882: goto            24
        //  1885: pop            
        //  1886: aconst_null    
        //  1887: goto            1881
        //  1890: dup            
        //  1891: ifnull          1881
        //  1894: checkcast       Ljava/lang/Throwable;
        //  1897: athrow         
        //  1898: dup            
        //  1899: ifnull          1885
        //  1902: checkcast       Ljava/lang/Throwable;
        //  1905: athrow         
        //  1906: aconst_null    
        //  1907: athrow         
        //    StackMapTable: 00 E3 FF 00 03 00 07 07 00 03 01 01 07 01 48 01 01 01 00 01 07 00 A9 FF 00 04 00 03 07 00 03 01 01 00 00 FF 00 0B 00 00 00 01 07 00 A9 FE 00 03 07 00 03 01 01 FF 00 10 00 08 07 00 03 01 01 07 01 48 01 01 01 01 00 00 4C 07 00 8B FF 00 00 00 08 07 00 03 01 01 07 01 48 01 01 01 01 00 02 07 00 03 01 45 07 00 A9 40 07 00 AB FF 00 0E 00 09 07 00 03 01 01 07 01 48 01 01 01 01 07 00 AB 00 01 07 00 A9 FF 00 00 00 09 07 00 03 01 01 07 01 48 01 01 01 01 07 00 AB 00 05 08 00 40 08 00 40 01 01 07 00 AB 45 07 00 A9 FF 00 00 00 09 07 00 03 01 01 07 01 48 01 01 01 01 07 00 AB 00 05 08 00 40 08 00 40 01 01 01 FF 00 0C 00 09 07 00 03 01 01 07 01 48 01 01 01 01 07 00 AB 00 06 08 00 40 08 00 40 01 01 01 07 00 AB FF 00 01 00 09 07 00 03 01 01 07 01 48 01 01 01 01 07 00 AB 00 07 08 00 40 08 00 40 01 01 01 07 00 AB 01 FF 00 1B 00 09 07 00 03 01 01 07 01 48 01 01 01 01 07 00 AB 00 06 08 00 40 08 00 40 01 01 01 07 00 AB FF 00 02 00 00 00 01 07 00 A9 FF 00 00 00 09 07 00 03 01 01 07 01 48 01 01 01 01 07 00 AB 00 06 08 00 40 08 00 40 01 01 01 07 00 AB 45 07 00 A9 FF 00 00 00 09 07 00 03 01 01 07 01 48 01 01 01 01 07 00 AB 00 06 08 00 40 08 00 40 01 01 01 01 FF 00 02 00 00 00 01 07 00 A9 FF 00 00 00 09 07 00 03 01 01 07 01 48 01 01 01 01 07 00 AB 00 06 08 00 40 08 00 40 01 01 01 01 45 07 00 A9 40 07 00 6D FC 00 0C 07 00 6D 41 01 1E 4C 07 00 6D FF 00 01 00 0A 07 00 03 01 01 07 01 48 01 01 01 01 07 00 AB 07 00 6D 00 02 07 00 6D 01 5C 07 00 6D 42 07 00 A9 40 07 00 6D 45 07 00 A9 40 01 11 41 01 1C 45 07 00 A9 FF 00 00 00 0A 07 00 03 01 01 07 01 48 01 01 01 01 07 00 AB 07 00 6D 00 02 07 00 03 07 00 6D 45 07 00 A9 FF 00 00 00 0A 07 00 03 01 01 07 01 48 01 01 01 01 07 00 AB 07 00 6D 00 02 07 00 03 01 02 44 07 00 A9 40 07 00 6D 45 07 00 A9 40 01 51 07 00 6D FF 00 01 00 0A 07 00 03 01 01 07 01 48 01 01 01 01 07 00 AB 07 00 6D 00 02 07 00 6D 01 5D 07 00 6D 42 07 00 A9 40 07 00 6D 45 07 00 A9 40 01 4A 01 FF 00 01 00 0A 07 00 03 01 01 07 01 48 01 01 01 01 07 00 AB 07 00 6D 00 02 01 01 5B 01 01 0A 41 01 1C 4B 07 00 03 FF 00 01 00 0A 07 00 03 01 01 07 01 48 01 01 01 01 07 00 AB 07 00 6D 00 02 07 00 03 01 5D 07 00 03 08 04 41 01 17 02 FF 00 10 00 0A 07 00 03 01 01 07 01 48 01 01 01 01 07 00 AB 07 00 6D 00 02 07 00 81 01 FF 00 01 00 0A 07 00 03 01 01 07 01 48 01 01 01 01 07 00 AB 07 00 6D 00 03 07 00 81 01 01 FF 00 1D 00 0A 07 00 03 01 01 07 01 48 01 01 01 01 07 00 AB 07 00 6D 00 02 07 00 81 01 0D 41 01 1B 52 01 FF 00 01 00 0A 07 00 03 01 01 07 01 48 01 01 01 01 07 00 AB 07 00 6D 00 02 01 01 5E 01 44 07 00 A9 FF 00 00 00 0A 07 00 03 01 01 07 01 48 01 01 01 01 07 00 AB 07 00 6D 00 02 01 07 00 6D 45 07 00 A9 FF 00 00 00 0A 07 00 03 01 01 07 01 48 01 01 01 01 07 00 AB 07 00 6D 00 02 01 01 0A 04 41 01 18 08 04 41 01 17 0A 41 01 1E 4B 07 00 03 FF 00 01 00 0A 07 00 03 01 01 07 01 48 01 01 01 01 07 00 AB 07 00 6D 00 02 07 00 03 01 5D 07 00 03 04 52 01 FF 00 01 00 0A 07 00 03 01 01 07 01 48 01 01 01 01 07 00 AB 07 00 6D 00 02 01 01 5D 01 04 F9 00 05 FF 00 1C 00 08 07 00 03 01 01 07 01 48 01 01 01 01 00 04 08 03 C8 08 03 C8 01 07 00 03 FF 00 01 00 08 07 00 03 01 01 07 01 48 01 01 01 01 00 05 08 03 C8 08 03 C8 01 07 00 03 01 FF 00 1D 00 08 07 00 03 01 01 07 01 48 01 01 01 01 00 04 08 03 C8 08 03 C8 01 07 00 03 46 07 00 A9 FF 00 00 00 08 07 00 03 01 01 07 01 48 01 01 01 01 00 05 08 03 C8 08 03 C8 01 01 01 45 07 00 A9 40 07 00 AB FF 00 06 00 08 07 00 03 01 01 07 01 48 01 01 01 07 00 AB 00 01 07 00 A9 40 07 00 AB 45 07 00 A9 40 07 01 4A 4D 07 00 FC FF 00 01 00 08 07 00 03 01 01 07 01 48 01 01 01 07 00 AB 00 02 07 00 FC 01 5D 07 00 FC FF 00 0F 00 09 07 00 03 01 01 07 01 48 01 01 01 07 00 AB 07 00 FC 00 01 07 00 FC FF 00 02 00 09 07 00 03 01 01 07 01 48 01 01 01 07 00 AB 07 00 FC 00 02 07 00 FC 01 5C 07 00 FC FF 00 0F 00 09 07 00 03 01 01 07 01 48 01 01 01 07 00 AB 07 00 FC 00 02 07 00 FC 07 00 80 FF 00 02 00 09 07 00 03 01 01 07 01 48 01 01 01 07 00 AB 07 00 FC 00 03 07 00 FC 07 00 80 01 FF 00 1C 00 09 07 00 03 01 01 07 01 48 01 01 01 07 00 AB 07 00 FC 00 02 07 00 FC 07 00 80 42 07 00 A9 FF 00 00 00 09 07 00 03 01 01 07 01 48 01 01 01 07 00 AB 07 00 FC 00 02 07 00 FC 07 00 80 45 07 00 A9 00 FF 00 1B 00 09 07 00 03 01 01 07 01 48 01 01 01 07 00 AB 07 00 FC 00 07 07 00 FC 08 04 B5 08 04 B5 01 01 01 01 FF 00 02 00 09 07 00 03 01 01 07 01 48 01 01 01 07 00 AB 07 00 FC 00 08 07 00 FC 08 04 B5 08 04 B5 01 01 01 01 01 FF 00 1D 00 09 07 00 03 01 01 07 01 48 01 01 01 07 00 AB 07 00 FC 00 07 07 00 FC 08 04 B5 08 04 B5 01 01 01 01 42 07 00 8F FF 00 00 00 09 07 00 03 01 01 07 01 48 01 01 01 07 00 AB 07 00 FC 00 07 07 00 FC 08 04 B5 08 04 B5 01 01 01 01 45 07 00 A9 FF 00 00 00 09 07 00 03 01 01 07 01 48 01 01 01 07 00 AB 07 00 FC 00 02 07 00 FC 07 01 0B 42 07 00 A9 FF 00 00 00 09 07 00 03 01 01 07 01 48 01 01 01 07 00 AB 07 00 FC 00 02 07 00 FC 07 01 0B 45 07 00 A9 00 FF 00 0F 00 09 07 00 03 01 01 07 01 48 01 01 01 07 00 AB 07 00 FC 00 03 07 00 FC 01 01 FF 00 02 00 09 07 00 03 01 01 07 01 48 01 01 01 07 00 AB 07 00 FC 00 04 07 00 FC 01 01 01 FF 00 1E 00 09 07 00 03 01 01 07 01 48 01 01 01 07 00 AB 07 00 FC 00 03 07 00 FC 01 01 4A 07 00 A9 FF 00 00 00 09 07 00 03 01 01 07 01 48 01 01 01 07 00 AB 07 00 FC 00 05 07 00 FC 01 01 01 01 45 07 00 A9 00 FF 00 07 00 00 00 01 07 00 A9 FF 00 00 00 09 07 00 03 01 01 07 01 48 01 01 01 07 00 AB 07 00 FC 00 02 07 00 FC 07 01 0B 45 07 00 A9 00 FC 00 02 01 0B 42 01 1E 52 07 01 48 FF 00 02 00 0A 07 00 03 01 01 07 01 48 01 01 01 07 00 AB 07 00 FC 01 00 02 07 01 48 01 5D 07 01 48 05 05 42 01 18 09 05 42 01 18 FF 00 11 00 0A 07 00 03 01 01 07 01 48 01 01 01 07 00 AB 07 00 FC 01 00 02 07 00 FC 07 00 AB FF 00 02 00 0A 07 00 03 01 01 07 01 48 01 01 01 07 00 AB 07 00 FC 01 00 03 07 00 FC 07 00 AB 01 FF 00 1E 00 0A 07 00 03 01 01 07 01 48 01 01 01 07 00 AB 07 00 FC 01 00 02 07 00 FC 07 00 AB FF 00 0F 00 0A 07 00 03 01 01 07 01 48 01 01 01 07 00 AB 07 00 FC 01 00 03 07 00 FC 07 00 AB 07 00 81 FF 00 02 00 0A 07 00 03 01 01 07 01 48 01 01 01 07 00 AB 07 00 FC 01 00 04 07 00 FC 07 00 AB 07 00 81 01 FF 00 1C 00 0A 07 00 03 01 01 07 01 48 01 01 01 07 00 AB 07 00 FC 01 00 03 07 00 FC 07 00 AB 07 00 81 45 07 00 8F FF 00 00 00 0A 07 00 03 01 01 07 01 48 01 01 01 07 00 AB 07 00 FC 01 00 03 07 00 FC 07 00 AB 07 00 6D 45 07 00 A9 FF 00 00 00 0A 07 00 03 01 01 07 01 48 01 01 01 07 00 AB 07 00 FC 01 00 03 07 00 FC 07 00 AB 01 FF 00 0C 00 0A 07 00 03 01 01 07 01 48 01 01 01 07 00 AB 07 00 FC 01 00 04 07 00 FC 07 00 AB 01 07 00 03 FF 00 02 00 0A 07 00 03 01 01 07 01 48 01 01 01 07 00 AB 07 00 FC 01 00 05 07 00 FC 07 00 AB 01 07 00 03 01 FF 00 1D 00 0A 07 00 03 01 01 07 01 48 01 01 01 07 00 AB 07 00 FC 01 00 04 07 00 FC 07 00 AB 01 07 00 03 FF 00 11 00 0A 07 00 03 01 01 07 01 48 01 01 01 07 00 AB 07 00 FC 01 00 04 07 00 FC 07 00 AB 01 07 00 6D FF 00 02 00 0A 07 00 03 01 01 07 01 48 01 01 01 07 00 AB 07 00 FC 01 00 05 07 00 FC 07 00 AB 01 07 00 6D 01 FF 00 1E 00 0A 07 00 03 01 01 07 01 48 01 01 01 07 00 AB 07 00 FC 01 00 04 07 00 FC 07 00 AB 01 07 00 6D FF 00 02 00 00 00 01 07 00 A9 FF 00 00 00 0A 07 00 03 01 01 07 01 48 01 01 01 07 00 AB 07 00 FC 01 00 04 07 00 FC 07 00 AB 01 07 00 6D 45 07 00 A9 FF 00 00 00 0A 07 00 03 01 01 07 01 48 01 01 01 07 00 AB 07 00 FC 01 00 04 07 00 FC 07 00 AB 01 01 43 07 00 A9 FF 00 00 00 0A 07 00 03 01 01 07 01 48 01 01 01 07 00 AB 07 00 FC 01 00 05 07 00 FC 07 00 AB 01 01 05 45 07 00 A9 40 01 00 05 FF 00 03 00 00 00 01 07 00 A9 FF 00 00 00 0A 07 00 03 01 01 07 01 48 01 01 01 07 00 AB 07 00 FC 01 00 01 07 00 03 45 07 00 A9 FF 00 00 00 0A 07 00 03 01 01 07 01 48 01 01 01 07 00 AB 07 00 FC 01 00 02 07 00 03 01 FF 00 06 00 00 00 01 07 00 A9 FF 00 00 00 0A 07 00 03 01 01 07 01 48 01 01 01 07 00 AB 07 00 FC 01 00 05 07 00 03 01 07 00 AB 01 01 45 07 00 A9 FF 00 00 00 0A 07 00 03 01 01 07 01 48 01 01 01 07 00 AB 07 00 FC 01 00 02 07 00 03 01 FF 00 03 00 0A 07 00 03 01 01 07 01 48 01 01 01 01 07 00 AB 07 00 6D 00 00 FF 00 01 00 0A 07 00 03 01 01 07 01 48 01 01 01 07 00 AB 07 00 FC 01 00 00 FF 00 01 00 0A 07 00 03 01 01 07 01 48 01 01 01 01 07 00 AB 07 00 6D 00 00 41 01 41 01 41 07 00 03 FF 00 01 00 0A 07 00 03 01 01 07 01 48 01 01 01 07 00 AB 07 00 FC 01 00 04 07 00 FC 07 00 AB 01 07 00 6D FF 00 01 00 0A 07 00 03 01 01 07 01 48 01 01 01 01 07 00 AB 07 00 6D 00 00 FF 00 01 00 0A 07 00 03 01 01 07 01 48 01 01 01 07 00 AB 07 00 FC 01 00 02 07 00 FC 07 00 AB FF 00 01 00 09 07 00 03 01 01 07 01 48 01 01 01 07 00 AB 07 00 FC 00 03 07 00 FC 01 01 FF 00 01 00 09 07 00 03 01 01 07 01 48 01 01 01 07 00 AB 07 00 FC 00 02 07 00 FC 07 00 80 FF 00 01 00 0A 07 00 03 01 01 07 01 48 01 01 01 01 07 00 AB 07 00 6D 00 01 07 00 6D FF 00 01 00 0A 07 00 03 01 01 07 01 48 01 01 01 07 00 AB 07 00 FC 01 00 03 07 00 FC 07 00 AB 07 00 81 FF 00 01 00 0A 07 00 03 01 01 07 01 48 01 01 01 01 07 00 AB 07 00 6D 00 00 FF 00 01 00 08 07 00 03 01 01 07 01 48 01 01 01 07 00 AB 00 01 07 00 FC FF 00 01 00 0A 07 00 03 01 01 07 01 48 01 01 01 01 07 00 AB 07 00 6D 00 01 07 00 6D 01 41 01 FF 00 01 00 08 07 00 03 01 01 07 01 48 01 01 01 01 00 04 08 03 C8 08 03 C8 01 07 00 03 FF 00 01 00 09 07 00 03 01 01 07 01 48 01 01 01 07 00 AB 07 00 FC 00 07 07 00 FC 08 04 B5 08 04 B5 01 01 01 01 FF 00 01 00 0A 07 00 03 01 01 07 01 48 01 01 01 01 07 00 AB 07 00 6D 00 01 07 00 03 FF 00 01 00 09 07 00 03 01 01 07 01 48 01 01 01 07 00 AB 07 00 FC 00 01 07 00 FC FF 00 01 00 0A 07 00 03 01 01 07 01 48 01 01 01 01 07 00 AB 07 00 6D 00 02 07 00 81 01 FF 00 01 00 0A 07 00 03 01 01 07 01 48 01 01 01 07 00 AB 07 00 FC 01 00 01 07 01 48 FF 00 01 00 09 07 00 03 01 01 07 01 48 01 01 01 01 07 00 AB 00 06 08 00 40 08 00 40 01 01 01 07 00 AB FF 00 01 00 0A 07 00 03 01 01 07 01 48 01 01 01 07 00 AB 07 00 FC 01 00 04 07 00 FC 07 00 AB 01 07 00 03 FF 00 01 00 03 07 00 03 01 01 00 01 07 00 A9 43 05 44 07 00 A9 47 05 FF 00 07 00 07 07 00 03 01 01 07 01 48 01 01 01 00 01 07 00 A9
        //    Exceptions:
        //  Try           Handler
        //  Start  End    Start  End    Type                                       
        //  -----  -----  -----  -----  -------------------------------------------
        //  8      20     1890   1898   Ljava/lang/IllegalStateException;
        //  1890   1898   1890   1898   Any
        //  1906   1908   3      8      Any
        //  54     61     61     62     Any
        //  54     61     54     55     Ljava/lang/EnumConstantNotPresentException;
        //  55     61     61     62     Ljava/lang/ArrayIndexOutOfBoundsException;
        //  55     61     3      8      Any
        //  54     61     3      8      Any
        //  77     84     84     85     Any
        //  78     84     3      8      Ljava/lang/RuntimeException;
        //  77     84     3      8      Ljava/util/NoSuchElementException;
        //  78     84     77     78     Any
        //  77     84     77     78     Ljava/lang/RuntimeException;
        //  132    138    138    139    Any
        //  132    138    138    139    Any
        //  132    138    138    139    Ljava/lang/NumberFormatException;
        //  132    138    3      8      Ljava/lang/AssertionError;
        //  132    138    138    139    Ljava/lang/StringIndexOutOfBoundsException;
        //  143    149    149    150    Any
        //  143    149    149    150    Ljava/lang/IndexOutOfBoundsException;
        //  143    149    149    150    Ljava/lang/StringIndexOutOfBoundsException;
        //  143    149    3      8      Any
        //  143    149    3      8      Ljava/lang/NegativeArraySizeException;
        //  243    250    250    251    Any
        //  243    250    250    251    Ljava/lang/IndexOutOfBoundsException;
        //  244    250    3      8      Any
        //  243    250    243    244    Ljava/lang/ClassCastException;
        //  244    250    243    244    Any
        //  306    313    313    314    Any
        //  306    313    306    307    Any
        //  306    313    3      8      Ljava/lang/ArithmeticException;
        //  306    313    306    307    Ljava/lang/UnsupportedOperationException;
        //  307    313    3      8      Any
        //  322    329    329    330    Any
        //  323    329    329    330    Any
        //  323    329    322    323    Ljava/lang/RuntimeException;
        //  323    329    322    323    Any
        //  322    329    322    323    Ljava/lang/IllegalStateException;
        //  383    390    390    391    Any
        //  383    390    383    384    Any
        //  383    390    383    384    Ljava/lang/StringIndexOutOfBoundsException;
        //  384    390    3      8      Ljava/lang/NegativeArraySizeException;
        //  383    390    383    384    Ljava/lang/IndexOutOfBoundsException;
        //  713    720    720    721    Any
        //  713    720    713    714    Any
        //  713    720    3      8      Ljava/lang/IllegalArgumentException;
        //  714    720    720    721    Any
        //  713    720    3      8      Ljava/lang/EnumConstantNotPresentException;
        //  1027   1034   1034   1035   Any
        //  1028   1034   1034   1035   Ljava/lang/ClassCastException;
        //  1027   1034   3      8      Any
        //  1027   1034   3      8      Ljava/lang/NumberFormatException;
        //  1028   1034   1027   1028   Any
        //  1042   1049   1049   1050   Any
        //  1043   1049   3      8      Any
        //  1043   1049   1049   1050   Any
        //  1042   1049   1042   1043   Any
        //  1043   1049   1049   1050   Any
        //  1195   1202   1202   1203   Any
        //  1196   1202   1195   1196   Any
        //  1195   1202   3      8      Any
        //  1195   1202   1202   1203   Any
        //  1195   1202   1202   1203   Any
        //  1267   1274   1274   1275   Any
        //  1267   1274   1274   1275   Any
        //  1268   1274   1267   1268   Ljava/lang/NullPointerException;
        //  1267   1274   1267   1268   Ljava/lang/NumberFormatException;
        //  1268   1274   3      8      Ljava/lang/NegativeArraySizeException;
        //  1278   1285   1285   1286   Any
        //  1279   1285   1285   1286   Ljava/lang/NegativeArraySizeException;
        //  1279   1285   3      8      Ljava/util/ConcurrentModificationException;
        //  1278   1285   1278   1279   Ljava/lang/UnsupportedOperationException;
        //  1278   1285   1278   1279   Any
        //  1347   1354   1354   1355   Any
        //  1348   1354   3      8      Any
        //  1347   1354   1347   1348   Any
        //  1348   1354   3      8      Ljava/lang/IllegalArgumentException;
        //  1347   1354   3      8      Any
        //  1364   1370   1370   1371   Any
        //  1364   1370   1370   1371   Ljava/lang/UnsupportedOperationException;
        //  1364   1370   3      8      Ljava/lang/AssertionError;
        //  1364   1370   3      8      Ljava/lang/ArrayIndexOutOfBoundsException;
        //  1364   1370   3      8      Ljava/lang/EnumConstantNotPresentException;
        //  1662   1669   1669   1670   Any
        //  1663   1669   1662   1663   Ljava/lang/StringIndexOutOfBoundsException;
        //  1663   1669   1662   1663   Ljava/lang/NumberFormatException;
        //  1663   1669   3      8      Any
        //  1663   1669   1669   1670   Any
        //  1772   1778   1778   1779   Any
        //  1772   1778   1778   1779   Ljava/lang/IndexOutOfBoundsException;
        //  1772   1778   3      8      Any
        //  1772   1778   3      8      Any
        //  1772   1778   1778   1779   Ljava/lang/IllegalStateException;
        //  1783   1790   1790   1791   Any
        //  1783   1790   1790   1791   Any
        //  1784   1790   3      8      Ljava/lang/StringIndexOutOfBoundsException;
        //  1783   1790   1783   1784   Ljava/lang/UnsupportedOperationException;
        //  1783   1790   1783   1784   Any
        //  1803   1809   1809   1810   Any
        //  1803   1809   1809   1810   Any
        //  1803   1809   3      8      Any
        //  1803   1809   3      8      Ljava/lang/ClassCastException;
        //  1803   1809   3      8      Ljava/lang/StringIndexOutOfBoundsException;
        //  1818   1824   1824   1825   Any
        //  1818   1824   1824   1825   Any
        //  1818   1824   1824   1825   Any
        //  1818   1824   1824   1825   Any
        //  1818   1824   3      8      Ljava/util/NoSuchElementException;
        // 
        // The error that occurred was:
        // 
        // java.lang.IllegalArgumentException: Argument 'offset' must be in the range [0, 0], but value was: 4.
        //     at com.strobel.core.VerifyArgument.inRange(VerifyArgument.java:347)
        //     at com.strobel.assembler.ir.StackMappingVisitor.getStackValue(StackMappingVisitor.java:67)
        //     at com.strobel.assembler.ir.StackMappingVisitor$InstructionAnalyzer.execute(StackMappingVisitor.java:691)
        //     at com.strobel.assembler.ir.StackMappingVisitor$InstructionAnalyzer.visit(StackMappingVisitor.java:398)
        //     at com.strobel.decompiler.ast.AstBuilder.performStackAnalysis(AstBuilder.java:2030)
        //     at com.strobel.decompiler.ast.AstBuilder.build(AstBuilder.java:108)
        //     at com.strobel.decompiler.languages.java.ast.AstMethodBodyBuilder.createMethodBody(AstMethodBodyBuilder.java:211)
        //     at com.strobel.decompiler.languages.java.ast.AstMethodBodyBuilder.createMethodBody(AstMethodBodyBuilder.java:99)
        //     at com.strobel.decompiler.languages.java.ast.AstBuilder.createMethodBody(AstBuilder.java:782)
        //     at com.strobel.decompiler.languages.java.ast.AstBuilder.createMethod(AstBuilder.java:675)
        //     at com.strobel.decompiler.languages.java.ast.AstBuilder.addTypeMembers(AstBuilder.java:552)
        //     at com.strobel.decompiler.languages.java.ast.AstBuilder.createTypeCore(AstBuilder.java:519)
        //     at com.strobel.decompiler.languages.java.ast.AstBuilder.createTypeNoCache(AstBuilder.java:161)
        //     at com.strobel.decompiler.languages.java.ast.AstBuilder.createType(AstBuilder.java:150)
        //     at com.strobel.decompiler.languages.java.ast.AstBuilder.addType(AstBuilder.java:125)
        //     at com.strobel.decompiler.languages.java.JavaLanguage.buildAst(JavaLanguage.java:71)
        //     at com.strobel.decompiler.languages.java.JavaLanguage.decompileType(JavaLanguage.java:59)
        //     at com.strobel.decompiler.DecompilerDriver.decompileType(DecompilerDriver.java:330)
        //     at com.strobel.decompiler.DecompilerDriver.decompileJar(DecompilerDriver.java:251)
        //     at com.strobel.decompiler.DecompilerDriver.main(DecompilerDriver.java:126)
        // 
        throw new IllegalStateException("An error occurred while decompiling this method.");
    }
    
    public int c(final String s) {
        return fbS.92(this, 1005652132, s);
    }
    
    public void c() {
        // 
        // This method could not be decompiled.
        // 
        // Original Bytecode:
        // 
        //     3: dup            
        //     4: ifnull          269
        //     7: athrow         
        //     8: aconst_null    
        //     9: getstatic       dev/nuker/pyro/fc.1:I
        //    12: ifgt            261
        //    15: pop            
        //    16: aconst_null    
        //    17: goto            253
        //    20: nop            
        //    21: nop            
        //    22: nop            
        //    23: athrow         
        //    24: goto            28
        //    27: athrow         
        //    28: invokestatic    java/lang/System.currentTimeMillis:()J
        //    31: goto            35
        //    34: athrow         
        //    35: lstore_1       
        //    36: aload_0        
        //    37: getfield        dev/nuker/pyro/fbE.c:Ljava/util/HashMap;
        //    40: goto            44
        //    43: athrow         
        //    44: invokevirtual   java/util/HashMap.entrySet:()Ljava/util/Set;
        //    47: goto            51
        //    50: athrow         
        //    51: getstatic       dev/nuker/pyro/fc.1:I
        //    54: ifeq            63
        //    57: ldc_w           1421646327
        //    60: goto            66
        //    63: ldc_w           -1583268201
        //    66: ldc_w           -1369210654
        //    69: ixor           
        //    70: lookupswitch {
        //          -86042347: 63
        //          264420981: 96
        //          default: 238
        //        }
        //    96: goto            100
        //    99: athrow         
        //   100: invokeinterface java/util/Set.stream:()Ljava/util/stream/Stream;
        //   105: goto            109
        //   108: athrow         
        //   109: lload_1        
        //   110: invokedynamic   BootstrapMethod #0, test:(J)Ljava/util/function/Predicate;
        //   115: goto            119
        //   118: athrow         
        //   119: invokeinterface java/util/stream/Stream.filter:(Ljava/util/function/Predicate;)Ljava/util/stream/Stream;
        //   124: goto            128
        //   127: athrow         
        //   128: getstatic       dev/nuker/pyro/fc.1:I
        //   131: ifeq            140
        //   134: ldc_w           2046811539
        //   137: goto            143
        //   140: ldc_w           1153583348
        //   143: ldc_w           -420553259
        //   146: ixor           
        //   147: lookupswitch {
        //          -1626275770: 242
        //          1490204746: 140
        //          default: 172
        //        }
        //   172: aload_0        
        //   173: invokedynamic   BootstrapMethod #1, accept:(Ldev/nuker/pyro/fbE;)Ljava/util/function/Consumer;
        //   178: getstatic       dev/nuker/pyro/fc.c:I
        //   181: ifge            190
        //   184: ldc_w           745447350
        //   187: goto            193
        //   190: ldc_w           870599751
        //   193: ldc_w           414152509
        //   196: ixor           
        //   197: lookupswitch {
        //          726350714: 224
        //          885123211: 190
        //          default: 240
        //        }
        //   224: goto            228
        //   227: athrow         
        //   228: invokeinterface java/util/stream/Stream.forEach:(Ljava/util/function/Consumer;)V
        //   233: goto            237
        //   236: athrow         
        //   237: return         
        //   238: aconst_null    
        //   239: athrow         
        //   240: aconst_null    
        //   241: athrow         
        //   242: aconst_null    
        //   243: athrow         
        //   244: pop            
        //   245: goto            24
        //   248: pop            
        //   249: aconst_null    
        //   250: goto            244
        //   253: dup            
        //   254: ifnull          244
        //   257: checkcast       Ljava/lang/Throwable;
        //   260: athrow         
        //   261: dup            
        //   262: ifnull          248
        //   265: checkcast       Ljava/lang/Throwable;
        //   268: athrow         
        //   269: aconst_null    
        //   270: athrow         
        //    StackMapTable: 00 29 43 07 00 A9 04 FF 00 0B 00 00 00 01 07 00 A9 FC 00 03 07 00 03 42 07 00 A9 00 45 07 00 A9 40 04 FF 00 07 00 00 00 01 07 00 A9 FF 00 00 00 02 07 00 03 04 00 01 07 00 3F 45 07 00 A9 40 07 01 5F 4B 07 01 5F FF 00 02 00 02 07 00 03 04 00 02 07 01 5F 01 5D 07 01 5F FF 00 02 00 00 00 01 07 00 A9 FF 00 00 00 02 07 00 03 04 00 01 07 01 5F 47 07 00 A9 40 07 01 76 48 07 00 A9 FF 00 00 00 02 07 00 03 04 00 02 07 01 76 07 01 90 47 07 00 A9 40 07 01 76 4B 07 01 76 FF 00 02 00 02 07 00 03 04 00 02 07 01 76 01 5C 07 01 76 FF 00 11 00 02 07 00 03 04 00 02 07 01 76 07 01 92 FF 00 02 00 02 07 00 03 04 00 03 07 01 76 07 01 92 01 FF 00 1E 00 02 07 00 03 04 00 02 07 01 76 07 01 92 42 07 00 A1 FF 00 00 00 02 07 00 03 04 00 02 07 01 76 07 01 92 47 07 00 A9 00 40 07 01 5F FF 00 01 00 02 07 00 03 04 00 02 07 01 76 07 01 92 41 07 01 76 FF 00 01 00 01 07 00 03 00 01 07 00 A9 43 05 44 07 00 A9 47 05 47 07 00 A9
        //    Exceptions:
        //  Try           Handler
        //  Start  End    Start  End    Type                                       
        //  -----  -----  -----  -----  -------------------------------------------
        //  8      20     253    261    Ljava/lang/AssertionError;
        //  253    261    253    261    Any
        //  269    271    3      8      Any
        //  27     34     34     35     Any
        //  27     34     27     28     Ljava/lang/UnsupportedOperationException;
        //  28     34     27     28     Any
        //  27     34     3      8      Any
        //  28     34     3      8      Any
        //  44     50     50     51     Any
        //  44     50     50     51     Ljava/lang/NumberFormatException;
        //  44     50     3      8      Ljava/lang/IllegalArgumentException;
        //  44     50     50     51     Ljava/lang/ArrayIndexOutOfBoundsException;
        //  44     50     50     51     Ljava/lang/NegativeArraySizeException;
        //  100    108    108    109    Any
        //  100    108    3      8      Any
        //  100    108    3      8      Ljava/lang/NumberFormatException;
        //  100    108    108    109    Any
        //  100    108    108    109    Any
        //  118    127    127    128    Any
        //  118    127    118    119    Ljava/lang/AssertionError;
        //  118    127    118    119    Ljava/lang/AssertionError;
        //  119    127    118    119    Ljava/lang/NullPointerException;
        //  119    127    127    128    Ljava/lang/StringIndexOutOfBoundsException;
        //  227    236    236    237    Any
        //  228    236    227    228    Ljava/lang/UnsupportedOperationException;
        //  227    236    3      8      Ljava/lang/StringIndexOutOfBoundsException;
        //  227    236    236    237    Ljava/lang/NegativeArraySizeException;
        //  227    236    236    237    Any
        // 
        // The error that occurred was:
        // 
        // java.lang.IndexOutOfBoundsException: Index 86 out of bounds for length 86
        //     at java.base/jdk.internal.util.Preconditions.outOfBounds(Preconditions.java:64)
        //     at java.base/jdk.internal.util.Preconditions.outOfBoundsCheckIndex(Preconditions.java:70)
        //     at java.base/jdk.internal.util.Preconditions.checkIndex(Preconditions.java:248)
        //     at java.base/java.util.Objects.checkIndex(Objects.java:372)
        //     at java.base/java.util.ArrayList.get(ArrayList.java:458)
        //     at com.strobel.decompiler.ast.AstBuilder.convertToAst(AstBuilder.java:3321)
        //     at com.strobel.decompiler.ast.AstBuilder.convertToAst(AstBuilder.java:3569)
        //     at com.strobel.decompiler.ast.AstBuilder.convertToAst(AstBuilder.java:3435)
        //     at com.strobel.decompiler.ast.AstBuilder.convertToAst(AstBuilder.java:3435)
        //     at com.strobel.decompiler.ast.AstBuilder.convertToAst(AstBuilder.java:3435)
        //     at com.strobel.decompiler.ast.AstBuilder.convertToAst(AstBuilder.java:3435)
        //     at com.strobel.decompiler.ast.AstBuilder.build(AstBuilder.java:113)
        //     at com.strobel.decompiler.languages.java.ast.AstMethodBodyBuilder.createMethodBody(AstMethodBodyBuilder.java:211)
        //     at com.strobel.decompiler.languages.java.ast.AstMethodBodyBuilder.createMethodBody(AstMethodBodyBuilder.java:99)
        //     at com.strobel.decompiler.languages.java.ast.AstBuilder.createMethodBody(AstBuilder.java:782)
        //     at com.strobel.decompiler.languages.java.ast.AstBuilder.createMethod(AstBuilder.java:675)
        //     at com.strobel.decompiler.languages.java.ast.AstBuilder.addTypeMembers(AstBuilder.java:552)
        //     at com.strobel.decompiler.languages.java.ast.AstBuilder.createTypeCore(AstBuilder.java:519)
        //     at com.strobel.decompiler.languages.java.ast.AstBuilder.createTypeNoCache(AstBuilder.java:161)
        //     at com.strobel.decompiler.languages.java.ast.AstBuilder.createType(AstBuilder.java:150)
        //     at com.strobel.decompiler.languages.java.ast.AstBuilder.addType(AstBuilder.java:125)
        //     at com.strobel.decompiler.languages.java.JavaLanguage.buildAst(JavaLanguage.java:71)
        //     at com.strobel.decompiler.languages.java.JavaLanguage.decompileType(JavaLanguage.java:59)
        //     at com.strobel.decompiler.DecompilerDriver.decompileType(DecompilerDriver.java:330)
        //     at com.strobel.decompiler.DecompilerDriver.decompileJar(DecompilerDriver.java:251)
        //     at com.strobel.decompiler.DecompilerDriver.main(DecompilerDriver.java:126)
        // 
        throw new IllegalStateException("An error occurred while decompiling this method.");
    }
    
    public static void 2() {
        // 
        // This method could not be decompiled.
        // 
        // Original Bytecode:
        // 
        //     3: dup            
        //     4: ifnull          135
        //     7: athrow         
        //     8: aconst_null    
        //     9: getstatic       dev/nuker/pyro/fc.1:I
        //    12: ifgt            127
        //    15: pop            
        //    16: aconst_null    
        //    17: goto            119
        //    20: nop            
        //    21: nop            
        //    22: nop            
        //    23: athrow         
        //    24: getstatic       dev/nuker/pyro/fbE.c:I
        //    27: dup            
        //    28: iconst_1       
        //    29: iadd           
        //    30: putstatic       dev/nuker/pyro/fbE.c:I
        //    33: sipush          600
        //    36: if_icmple       107
        //    39: getstatic       dev/nuker/pyro/fbE.c:Ljava/util/ArrayList;
        //    42: invokedynamic   BootstrapMethod #2, accept:()Ljava/util/function/Consumer;
        //    47: goto            51
        //    50: athrow         
        //    51: invokevirtual   java/util/ArrayList.forEach:(Ljava/util/function/Consumer;)V
        //    54: goto            58
        //    57: athrow         
        //    58: iconst_0       
        //    59: getstatic       dev/nuker/pyro/fc.0:I
        //    62: ifeq            71
        //    65: ldc_w           -700244714
        //    68: goto            74
        //    71: ldc_w           1570455536
        //    74: ldc_w           407729793
        //    77: ixor           
        //    78: lookupswitch {
        //          -837915753: 71
        //          1171671409: 104
        //          default: 108
        //        }
        //   104: putstatic       dev/nuker/pyro/fbE.c:I
        //   107: return         
        //   108: aconst_null    
        //   109: athrow         
        //   110: pop            
        //   111: goto            24
        //   114: pop            
        //   115: aconst_null    
        //   116: goto            110
        //   119: dup            
        //   120: ifnull          110
        //   123: checkcast       Ljava/lang/Throwable;
        //   126: athrow         
        //   127: dup            
        //   128: ifnull          114
        //   131: checkcast       Ljava/lang/Throwable;
        //   134: athrow         
        //   135: aconst_null    
        //   136: athrow         
        //    StackMapTable: 00 12 43 07 00 8F 04 4B 07 00 A9 03 59 07 00 A9 FF 00 00 00 00 00 02 07 00 7A 07 01 92 45 07 00 A9 00 4C 01 FF 00 02 00 00 00 02 01 01 5D 01 02 40 01 41 07 00 8F 43 05 44 07 00 8F 47 05 47 07 00 8F
        //    Exceptions:
        //  Try           Handler
        //  Start  End    Start  End    Type                                       
        //  -----  -----  -----  -----  -------------------------------------------
        //  8      20     119    127    Ljava/lang/NullPointerException;
        //  119    127    119    127    Ljava/lang/NegativeArraySizeException;
        //  135    137    3      7      Ljava/lang/ClassCastException;
        //  50     57     57     58     Any
        //  50     57     50     51     Any
        //  51     57     57     58     Any
        //  50     57     3      7      Ljava/lang/EnumConstantNotPresentException;
        //  50     57     57     58     Any
        // 
        // The error that occurred was:
        // 
        // java.lang.IndexOutOfBoundsException: Index 52 out of bounds for length 52
        //     at java.base/jdk.internal.util.Preconditions.outOfBounds(Preconditions.java:64)
        //     at java.base/jdk.internal.util.Preconditions.outOfBoundsCheckIndex(Preconditions.java:70)
        //     at java.base/jdk.internal.util.Preconditions.checkIndex(Preconditions.java:248)
        //     at java.base/java.util.Objects.checkIndex(Objects.java:372)
        //     at java.base/java.util.ArrayList.get(ArrayList.java:458)
        //     at com.strobel.decompiler.ast.AstBuilder.convertToAst(AstBuilder.java:3321)
        //     at com.strobel.decompiler.ast.AstBuilder.convertToAst(AstBuilder.java:3569)
        //     at com.strobel.decompiler.ast.AstBuilder.convertToAst(AstBuilder.java:3435)
        //     at com.strobel.decompiler.ast.AstBuilder.build(AstBuilder.java:113)
        //     at com.strobel.decompiler.languages.java.ast.AstMethodBodyBuilder.createMethodBody(AstMethodBodyBuilder.java:211)
        //     at com.strobel.decompiler.languages.java.ast.AstMethodBodyBuilder.createMethodBody(AstMethodBodyBuilder.java:99)
        //     at com.strobel.decompiler.languages.java.ast.AstBuilder.createMethodBody(AstBuilder.java:782)
        //     at com.strobel.decompiler.languages.java.ast.AstBuilder.createMethod(AstBuilder.java:675)
        //     at com.strobel.decompiler.languages.java.ast.AstBuilder.addTypeMembers(AstBuilder.java:552)
        //     at com.strobel.decompiler.languages.java.ast.AstBuilder.createTypeCore(AstBuilder.java:519)
        //     at com.strobel.decompiler.languages.java.ast.AstBuilder.createTypeNoCache(AstBuilder.java:161)
        //     at com.strobel.decompiler.languages.java.ast.AstBuilder.createType(AstBuilder.java:150)
        //     at com.strobel.decompiler.languages.java.ast.AstBuilder.addType(AstBuilder.java:125)
        //     at com.strobel.decompiler.languages.java.JavaLanguage.buildAst(JavaLanguage.java:71)
        //     at com.strobel.decompiler.languages.java.JavaLanguage.decompileType(JavaLanguage.java:59)
        //     at com.strobel.decompiler.DecompilerDriver.decompileType(DecompilerDriver.java:330)
        //     at com.strobel.decompiler.DecompilerDriver.decompileJar(DecompilerDriver.java:251)
        //     at com.strobel.decompiler.DecompilerDriver.main(DecompilerDriver.java:126)
        // 
        throw new IllegalStateException("An error occurred while decompiling this method.");
    }
    
    public void c(final String p0, final double p1, final double p2, final int p3) {
        // 
        // This method could not be decompiled.
        // 
        // Original Bytecode:
        // 
        //     3: dup            
        //     4: ifnull          1949
        //     7: athrow         
        //     8: aconst_null    
        //     9: getstatic       dev/nuker/pyro/fc.1:I
        //    12: ifgt            1941
        //    15: pop            
        //    16: aconst_null    
        //    17: goto            1933
        //    20: nop            
        //    21: nop            
        //    22: nop            
        //    23: athrow         
        //    24: ldc2_w          0.25
        //    27: dstore          7
        //    29: ldc2_w          4.0
        //    32: getstatic       dev/nuker/pyro/fc.0:I
        //    35: ifeq            44
        //    38: ldc_w           1474732614
        //    41: goto            47
        //    44: ldc_w           2065207604
        //    47: ldc_w           1555311273
        //    50: ixor           
        //    51: lookupswitch {
        //          189958383: 44
        //          665631645: 76
        //          default: 1888
        //        }
        //    76: dstore          9
        //    78: goto            82
        //    81: athrow         
        //    82: invokestatic    net/minecraft/client/renderer/GlStateManager.func_179094_E:()V
        //    85: goto            89
        //    88: athrow         
        //    89: ldc2_w          0.25
        //    92: ldc2_w          0.25
        //    95: ldc2_w          0.25
        //    98: goto            102
        //   101: athrow         
        //   102: invokestatic    net/minecraft/client/renderer/GlStateManager.func_179139_a:(DDD)V
        //   105: goto            109
        //   108: athrow         
        //   109: dload_2        
        //   110: ldc2_w          2.0
        //   113: dmul           
        //   114: dload           4
        //   116: ldc2_w          2.0
        //   119: dmul           
        //   120: ldc2_w          2.0
        //   123: dsub           
        //   124: dconst_0       
        //   125: goto            129
        //   128: athrow         
        //   129: invokestatic    org/lwjgl/opengl/GL11.glTranslated:(DDD)V
        //   132: goto            136
        //   135: athrow         
        //   136: aload_0        
        //   137: getstatic       dev/nuker/pyro/fc.0:I
        //   140: ifeq            149
        //   143: ldc_w           -675872693
        //   146: goto            152
        //   149: ldc_w           -816277886
        //   152: ldc_w           -1414788768
        //   155: ixor           
        //   156: lookupswitch {
        //          -484641385: 149
        //          2082146603: 1890
        //          default: 184
        //        }
        //   184: getfield        dev/nuker/pyro/fbE.5:I
        //   187: goto            191
        //   190: athrow         
        //   191: invokestatic    net/minecraft/client/renderer/GlStateManager.func_179144_i:(I)V
        //   194: goto            198
        //   197: athrow         
        //   198: iload           6
        //   200: bipush          16
        //   202: ishr           
        //   203: sipush          255
        //   206: iand           
        //   207: i2f            
        //   208: ldc_w           255.0
        //   211: fdiv           
        //   212: fstore          11
        //   214: getstatic       dev/nuker/pyro/fc.1:I
        //   217: ifeq            226
        //   220: ldc_w           1501882765
        //   223: goto            229
        //   226: ldc_w           -2137954808
        //   229: ldc_w           1775681902
        //   232: ixor           
        //   233: lookupswitch {
        //          -1711456161: 226
        //          810690787: 1882
        //          default: 260
        //        }
        //   260: iload           6
        //   262: bipush          8
        //   264: ishr           
        //   265: sipush          255
        //   268: iand           
        //   269: i2f            
        //   270: ldc_w           255.0
        //   273: fdiv           
        //   274: fstore          12
        //   276: getstatic       dev/nuker/pyro/fc.1:I
        //   279: ifeq            288
        //   282: ldc_w           478591412
        //   285: goto            291
        //   288: ldc_w           1018469086
        //   291: ldc_w           1835143049
        //   294: ixor           
        //   295: lookupswitch {
        //          1024402507: 288
        //          1910814269: 1886
        //          default: 320
        //        }
        //   320: iload           6
        //   322: sipush          255
        //   325: iand           
        //   326: i2f            
        //   327: ldc_w           255.0
        //   330: fdiv           
        //   331: fstore          13
        //   333: getstatic       dev/nuker/pyro/fc.1:I
        //   336: ifeq            345
        //   339: ldc_w           258678873
        //   342: goto            348
        //   345: ldc_w           -1919089987
        //   348: ldc_w           -583475837
        //   351: ixor           
        //   352: lookupswitch {
        //          -766247462: 1898
        //          -634796921: 345
        //          default: 380
        //        }
        //   380: iload           6
        //   382: bipush          24
        //   384: ishr           
        //   385: sipush          255
        //   388: iand           
        //   389: i2f            
        //   390: ldc_w           255.0
        //   393: fdiv           
        //   394: fstore          14
        //   396: getstatic       dev/nuker/pyro/fc.c:I
        //   399: ifge            408
        //   402: ldc_w           1712931659
        //   405: goto            411
        //   408: ldc_w           -253499268
        //   411: ldc_w           2137908170
        //   414: ixor           
        //   415: lookupswitch {
        //          427073665: 1878
        //          2139759691: 408
        //          default: 440
        //        }
        //   440: fload           11
        //   442: fload           12
        //   444: fload           13
        //   446: fload           14
        //   448: goto            452
        //   451: athrow         
        //   452: invokestatic    net/minecraft/client/renderer/GlStateManager.func_179131_c:(FFFF)V
        //   455: goto            459
        //   458: athrow         
        //   459: dconst_0       
        //   460: dstore          15
        //   462: aload_0        
        //   463: getfield        dev/nuker/pyro/fbE.c:Ljava/util/HashMap;
        //   466: aload_1        
        //   467: goto            471
        //   470: athrow         
        //   471: invokevirtual   java/util/HashMap.get:(Ljava/lang/Object;)Ljava/lang/Object;
        //   474: goto            478
        //   477: athrow         
        //   478: checkcast       Ldev/nuker/pyro/fbF;
        //   481: getstatic       dev/nuker/pyro/fc.c:I
        //   484: ifge            493
        //   487: ldc_w           -498796417
        //   490: goto            496
        //   493: ldc_w           -1229989104
        //   496: ldc_w           -1014442311
        //   499: ixor           
        //   500: lookupswitch {
        //          389050031: 493
        //          567029446: 1900
        //          default: 528
        //        }
        //   528: astore          17
        //   530: aload           17
        //   532: ifnull          639
        //   535: aload           17
        //   537: goto            541
        //   540: athrow         
        //   541: invokevirtual   dev/nuker/pyro/fbF.1:()I
        //   544: goto            548
        //   547: athrow         
        //   548: getstatic       dev/nuker/pyro/fc.0:I
        //   551: ifeq            560
        //   554: ldc_w           -1955696589
        //   557: goto            563
        //   560: ldc_w           859266856
        //   563: ldc_w           -1234657296
        //   566: ixor           
        //   567: lookupswitch {
        //          -1245886279: 560
        //          1023864771: 1880
        //          default: 592
        //        }
        //   592: goto            596
        //   595: athrow         
        //   596: invokestatic    org/lwjgl/opengl/GL11.glCallList:(I)V
        //   599: goto            603
        //   602: athrow         
        //   603: aload           17
        //   605: goto            609
        //   608: athrow         
        //   609: invokestatic    java/lang/System.currentTimeMillis:()J
        //   612: goto            616
        //   615: athrow         
        //   616: goto            620
        //   619: athrow         
        //   620: invokevirtual   dev/nuker/pyro/fbF.c:(J)V
        //   623: goto            627
        //   626: athrow         
        //   627: goto            631
        //   630: athrow         
        //   631: invokestatic    net/minecraft/client/renderer/GlStateManager.func_179121_F:()V
        //   634: goto            638
        //   637: athrow         
        //   638: return         
        //   639: iconst_m1      
        //   640: istore          18
        //   642: getstatic       dev/nuker/pyro/fbE.c:Z
        //   645: ifeq            678
        //   648: iconst_1       
        //   649: goto            653
        //   652: athrow         
        //   653: invokestatic    org/lwjgl/opengl/GL11.glGenLists:(I)I
        //   656: goto            660
        //   659: athrow         
        //   660: istore          18
        //   662: iload           18
        //   664: sipush          4865
        //   667: goto            671
        //   670: athrow         
        //   671: invokestatic    org/lwjgl/opengl/GL11.glNewList:(II)V
        //   674: goto            678
        //   677: athrow         
        //   678: bipush          7
        //   680: goto            684
        //   683: athrow         
        //   684: invokestatic    org/lwjgl/opengl/GL11.glBegin:(I)V
        //   687: goto            691
        //   690: athrow         
        //   691: aload_1        
        //   692: goto            696
        //   695: athrow         
        //   696: invokevirtual   java/lang/String.toCharArray:()[C
        //   699: goto            703
        //   702: athrow         
        //   703: getstatic       dev/nuker/pyro/fc.0:I
        //   706: ifeq            715
        //   709: ldc_w           -1081848157
        //   712: goto            718
        //   715: ldc_w           189849327
        //   718: ldc_w           357911045
        //   721: ixor           
        //   722: lookupswitch {
        //          -1429142362: 715
        //          503682282: 748
        //          default: 1918
        //        }
        //   748: astore          19
        //   750: aload           19
        //   752: arraylength    
        //   753: istore          20
        //   755: iconst_0       
        //   756: istore          21
        //   758: iload           21
        //   760: iload           20
        //   762: if_icmpge       1697
        //   765: aload           19
        //   767: iload           21
        //   769: caload         
        //   770: getstatic       dev/nuker/pyro/fc.1:I
        //   773: ifeq            782
        //   776: ldc_w           -916356867
        //   779: goto            785
        //   782: ldc_w           2069597852
        //   785: ldc_w           -2105824092
        //   788: ixor           
        //   789: lookupswitch {
        //          1260006489: 1896
        //          1637805225: 782
        //          default: 816
        //        }
        //   816: istore          22
        //   818: iload           22
        //   820: goto            824
        //   823: athrow         
        //   824: invokestatic    java/lang/Character.getNumericValue:(C)I
        //   827: goto            831
        //   830: athrow         
        //   831: getstatic       dev/nuker/pyro/fc.1:I
        //   834: ifeq            843
        //   837: ldc_w           -1938640211
        //   840: goto            846
        //   843: ldc_w           -382337666
        //   846: ldc_w           -1396166162
        //   849: ixor           
        //   850: lookupswitch {
        //          431435137: 843
        //          549094211: 1894
        //          default: 876
        //        }
        //   876: aload_0        
        //   877: getfield        dev/nuker/pyro/fbE.c:[Ldev/nuker/pyro/fbD;
        //   880: arraylength    
        //   881: if_icmplt       890
        //   884: ldc_w           -347811100
        //   887: goto            893
        //   890: ldc_w           -347811099
        //   893: ldc_w           -475876950
        //   896: ixor           
        //   897: tableswitch {
        //          298632860: 920
        //          298632861: 1438
        //          default: 884
        //        }
        //   920: getstatic       dev/nuker/pyro/fc.c:I
        //   923: ifge            932
        //   926: ldc_w           -193950225
        //   929: goto            935
        //   932: ldc_w           -2058803068
        //   935: ldc_w           1000884636
        //   938: ixor           
        //   939: lookupswitch {
        //          -807877517: 1910
        //          1353051441: 932
        //          default: 964
        //        }
        //   964: goto            968
        //   967: athrow         
        //   968: invokestatic    org/lwjgl/opengl/GL11.glEnd:()V
        //   971: goto            975
        //   974: athrow         
        //   975: ldc2_w          4.0
        //   978: ldc2_w          4.0
        //   981: ldc2_w          4.0
        //   984: goto            988
        //   987: athrow         
        //   988: invokestatic    net/minecraft/client/renderer/GlStateManager.func_179139_a:(DDD)V
        //   991: goto            995
        //   994: athrow         
        //   995: goto            999
        //   998: athrow         
        //   999: invokestatic    net/minecraft/client/Minecraft.func_71410_x:()Lnet/minecraft/client/Minecraft;
        //  1002: goto            1006
        //  1005: athrow         
        //  1006: getstatic       dev/nuker/pyro/fc.1:I
        //  1009: ifeq            1018
        //  1012: ldc_w           -940304892
        //  1015: goto            1021
        //  1018: ldc_w           1729672791
        //  1021: ldc_w           252028456
        //  1024: ixor           
        //  1025: lookupswitch {
        //          -923684820: 1018
        //          1746735231: 1052
        //          default: 1884
        //        }
        //  1052: getfield        net/minecraft/client/Minecraft.field_71466_p:Lnet/minecraft/client/gui/FontRenderer;
        //  1055: iload           22
        //  1057: goto            1061
        //  1060: athrow         
        //  1061: invokestatic    java/lang/String.valueOf:(C)Ljava/lang/String;
        //  1064: goto            1068
        //  1067: athrow         
        //  1068: getstatic       dev/nuker/pyro/fc.0:I
        //  1071: ifeq            1080
        //  1074: ldc_w           -690983389
        //  1077: goto            1083
        //  1080: ldc_w           -1285675036
        //  1083: ldc_w           -1536814426
        //  1086: ixor           
        //  1087: lookupswitch {
        //          887586213: 1080
        //          1924562053: 1906
        //          default: 1112
        //        }
        //  1112: dload           15
        //  1114: d2f            
        //  1115: ldc_w           0.25
        //  1118: fmul           
        //  1119: fconst_1       
        //  1120: fadd           
        //  1121: fconst_2       
        //  1122: iload           6
        //  1124: iconst_0       
        //  1125: getstatic       dev/nuker/pyro/fc.c:I
        //  1128: ifge            1137
        //  1131: ldc_w           1027711955
        //  1134: goto            1140
        //  1137: ldc_w           -2065021118
        //  1140: ldc_w           -1803846136
        //  1143: ixor           
        //  1144: lookupswitch {
        //          -1455759909: 1902
        //          -129714853: 1137
        //          default: 1172
        //        }
        //  1172: goto            1176
        //  1175: athrow         
        //  1176: invokevirtual   net/minecraft/client/gui/FontRenderer.func_175065_a:(Ljava/lang/String;FFIZ)I
        //  1179: goto            1183
        //  1182: athrow         
        //  1183: pop            
        //  1184: dload           15
        //  1186: getstatic       dev/nuker/pyro/fc.c:I
        //  1189: ifge            1198
        //  1192: ldc_w           1701775276
        //  1195: goto            1201
        //  1198: ldc_w           1342767913
        //  1201: ldc_w           489812105
        //  1204: ixor           
        //  1205: lookupswitch {
        //          -700630036: 1198
        //          2019489573: 1904
        //          default: 1232
        //        }
        //  1232: goto            1236
        //  1235: athrow         
        //  1236: invokestatic    net/minecraft/client/Minecraft.func_71410_x:()Lnet/minecraft/client/Minecraft;
        //  1239: goto            1243
        //  1242: athrow         
        //  1243: getfield        net/minecraft/client/Minecraft.field_71466_p:Lnet/minecraft/client/gui/FontRenderer;
        //  1246: iload           22
        //  1248: goto            1252
        //  1251: athrow         
        //  1252: invokestatic    java/lang/String.valueOf:(C)Ljava/lang/String;
        //  1255: goto            1259
        //  1258: athrow         
        //  1259: goto            1263
        //  1262: athrow         
        //  1263: invokevirtual   net/minecraft/client/gui/FontRenderer.func_78256_a:(Ljava/lang/String;)I
        //  1266: goto            1270
        //  1269: athrow         
        //  1270: i2d            
        //  1271: ldc2_w          4.0
        //  1274: dmul           
        //  1275: dadd           
        //  1276: dstore          15
        //  1278: ldc2_w          0.25
        //  1281: ldc2_w          0.25
        //  1284: ldc2_w          0.25
        //  1287: goto            1291
        //  1290: athrow         
        //  1291: invokestatic    net/minecraft/client/renderer/GlStateManager.func_179139_a:(DDD)V
        //  1294: goto            1298
        //  1297: athrow         
        //  1298: aload_0        
        //  1299: getfield        dev/nuker/pyro/fbE.5:I
        //  1302: goto            1306
        //  1305: athrow         
        //  1306: invokestatic    net/minecraft/client/renderer/GlStateManager.func_179144_i:(I)V
        //  1309: goto            1313
        //  1312: athrow         
        //  1313: fload           11
        //  1315: getstatic       dev/nuker/pyro/fc.1:I
        //  1318: ifeq            1327
        //  1321: ldc_w           -59959771
        //  1324: goto            1330
        //  1327: ldc_w           -2101416996
        //  1330: ldc_w           732273515
        //  1333: ixor           
        //  1334: lookupswitch {
        //          -674722482: 1920
        //          1651284565: 1327
        //          default: 1360
        //        }
        //  1360: fload           12
        //  1362: fload           13
        //  1364: fload           14
        //  1366: goto            1370
        //  1369: athrow         
        //  1370: invokestatic    net/minecraft/client/renderer/GlStateManager.func_179131_c:(FFFF)V
        //  1373: goto            1377
        //  1376: athrow         
        //  1377: bipush          7
        //  1379: getstatic       dev/nuker/pyro/fc.0:I
        //  1382: ifeq            1391
        //  1385: ldc_w           -858289844
        //  1388: goto            1394
        //  1391: ldc_w           1658804393
        //  1394: ldc_w           -1271739554
        //  1397: ixor           
        //  1398: lookupswitch {
        //          191040638: 1391
        //          2028290578: 1908
        //          default: 1424
        //        }
        //  1424: goto            1428
        //  1427: athrow         
        //  1428: invokestatic    org/lwjgl/opengl/GL11.glBegin:(I)V
        //  1431: goto            1435
        //  1434: athrow         
        //  1435: goto            1691
        //  1438: aload_0        
        //  1439: getfield        dev/nuker/pyro/fbE.c:[Ldev/nuker/pyro/fbD;
        //  1442: arraylength    
        //  1443: iload           22
        //  1445: if_icmpgt       1451
        //  1448: goto            1691
        //  1451: aload_0        
        //  1452: getfield        dev/nuker/pyro/fbE.c:[Ldev/nuker/pyro/fbD;
        //  1455: getstatic       dev/nuker/pyro/fc.0:I
        //  1458: ifeq            1467
        //  1461: ldc_w           1493883554
        //  1464: goto            1470
        //  1467: ldc_w           1376146276
        //  1470: ldc_w           175946080
        //  1473: ixor           
        //  1474: lookupswitch {
        //          1400267714: 1892
        //          1418813117: 1467
        //          default: 1500
        //        }
        //  1500: iload           22
        //  1502: aaload         
        //  1503: astore          23
        //  1505: aload           23
        //  1507: ifnonnull       1513
        //  1510: goto            1691
        //  1513: aload_0        
        //  1514: getstatic       dev/nuker/pyro/fc.1:I
        //  1517: ifeq            1526
        //  1520: ldc_w           -1328774957
        //  1523: goto            1529
        //  1526: ldc_w           -926157793
        //  1529: ldc_w           473937936
        //  1532: ixor           
        //  1533: lookupswitch {
        //          -1393346365: 1526
        //          -722187249: 1560
        //          default: 1914
        //        }
        //  1560: aload           23
        //  1562: getstatic       dev/nuker/pyro/fc.1:I
        //  1565: ifeq            1574
        //  1568: ldc_w           1639398061
        //  1571: goto            1577
        //  1574: ldc_w           764136258
        //  1577: ldc_w           -213472502
        //  1580: ixor           
        //  1581: lookupswitch {
        //          -1829662297: 1876
        //          -1456185560: 1574
        //          default: 1608
        //        }
        //  1608: dload           15
        //  1610: d2f            
        //  1611: fconst_0       
        //  1612: goto            1616
        //  1615: athrow         
        //  1616: invokespecial   dev/nuker/pyro/fbE.c:(Ldev/nuker/pyro/fbD;FF)V
        //  1619: goto            1623
        //  1622: athrow         
        //  1623: getstatic       dev/nuker/pyro/fc.0:I
        //  1626: ifeq            1635
        //  1629: ldc_w           646620471
        //  1632: goto            1638
        //  1635: ldc_w           738698967
        //  1638: ldc_w           2144543187
        //  1641: ixor           
        //  1642: lookupswitch {
        //          1406437124: 1668
        //          1499038948: 1635
        //          default: 1916
        //        }
        //  1668: dload           15
        //  1670: aload           23
        //  1672: goto            1676
        //  1675: athrow         
        //  1676: invokestatic    dev/nuker/pyro/fbD.2:(Ldev/nuker/pyro/fbD;)I
        //  1679: goto            1683
        //  1682: athrow         
        //  1683: i2d            
        //  1684: ldc2_w          8.0
        //  1687: dsub           
        //  1688: dadd           
        //  1689: dstore          15
        //  1691: iinc            21, 1
        //  1694: goto            758
        //  1697: getstatic       dev/nuker/pyro/fc.c:I
        //  1700: ifge            1709
        //  1703: ldc_w           -998243366
        //  1706: goto            1712
        //  1709: ldc_w           -1954240081
        //  1712: ldc_w           684962318
        //  1715: ixor           
        //  1716: lookupswitch {
        //          -330059308: 1912
        //          283956721: 1709
        //          default: 1744
        //        }
        //  1744: goto            1748
        //  1747: athrow         
        //  1748: invokestatic    org/lwjgl/opengl/GL11.glEnd:()V
        //  1751: goto            1755
        //  1754: athrow         
        //  1755: getstatic       dev/nuker/pyro/fbE.c:Z
        //  1758: ifeq            1817
        //  1761: aload_0        
        //  1762: getfield        dev/nuker/pyro/fbE.c:Ljava/util/HashMap;
        //  1765: aload_1        
        //  1766: new             Ldev/nuker/pyro/fbF;
        //  1769: dup            
        //  1770: iload           18
        //  1772: goto            1776
        //  1775: athrow         
        //  1776: invokestatic    java/lang/System.currentTimeMillis:()J
        //  1779: goto            1783
        //  1782: athrow         
        //  1783: goto            1787
        //  1786: athrow         
        //  1787: invokespecial   dev/nuker/pyro/fbF.<init>:(IJ)V
        //  1790: goto            1794
        //  1793: athrow         
        //  1794: goto            1798
        //  1797: athrow         
        //  1798: invokevirtual   java/util/HashMap.put:(Ljava/lang/Object;Ljava/lang/Object;)Ljava/lang/Object;
        //  1801: goto            1805
        //  1804: athrow         
        //  1805: pop            
        //  1806: goto            1810
        //  1809: athrow         
        //  1810: invokestatic    org/lwjgl/opengl/GL11.glEndList:()V
        //  1813: goto            1817
        //  1816: athrow         
        //  1817: getstatic       dev/nuker/pyro/fc.1:I
        //  1820: ifeq            1829
        //  1823: ldc_w           428120873
        //  1826: goto            1832
        //  1829: ldc_w           1549033413
        //  1832: ldc_w           -161367556
        //  1835: ixor           
        //  1836: lookupswitch {
        //          -270196011: 1922
        //          1478097052: 1829
        //          default: 1864
        //        }
        //  1864: goto            1868
        //  1867: athrow         
        //  1868: invokestatic    net/minecraft/client/renderer/GlStateManager.func_179121_F:()V
        //  1871: goto            1875
        //  1874: athrow         
        //  1875: return         
        //  1876: aconst_null    
        //  1877: athrow         
        //  1878: aconst_null    
        //  1879: athrow         
        //  1880: aconst_null    
        //  1881: athrow         
        //  1882: aconst_null    
        //  1883: athrow         
        //  1884: aconst_null    
        //  1885: athrow         
        //  1886: aconst_null    
        //  1887: athrow         
        //  1888: aconst_null    
        //  1889: athrow         
        //  1890: aconst_null    
        //  1891: athrow         
        //  1892: aconst_null    
        //  1893: athrow         
        //  1894: aconst_null    
        //  1895: athrow         
        //  1896: aconst_null    
        //  1897: athrow         
        //  1898: aconst_null    
        //  1899: athrow         
        //  1900: aconst_null    
        //  1901: athrow         
        //  1902: aconst_null    
        //  1903: athrow         
        //  1904: aconst_null    
        //  1905: athrow         
        //  1906: aconst_null    
        //  1907: athrow         
        //  1908: aconst_null    
        //  1909: athrow         
        //  1910: aconst_null    
        //  1911: athrow         
        //  1912: aconst_null    
        //  1913: athrow         
        //  1914: aconst_null    
        //  1915: athrow         
        //  1916: aconst_null    
        //  1917: athrow         
        //  1918: aconst_null    
        //  1919: athrow         
        //  1920: aconst_null    
        //  1921: athrow         
        //  1922: aconst_null    
        //  1923: athrow         
        //  1924: pop            
        //  1925: goto            24
        //  1928: pop            
        //  1929: aconst_null    
        //  1930: goto            1924
        //  1933: dup            
        //  1934: ifnull          1924
        //  1937: checkcast       Ljava/lang/Throwable;
        //  1940: athrow         
        //  1941: dup            
        //  1942: ifnull          1928
        //  1945: checkcast       Ljava/lang/Throwable;
        //  1948: athrow         
        //  1949: aconst_null    
        //  1950: athrow         
        //    StackMapTable: 01 04 FF 00 03 00 07 07 00 03 07 01 F4 03 03 01 03 03 00 01 07 00 A9 F9 00 04 FF 00 0B 00 00 00 01 07 00 A9 FF 00 03 00 05 07 00 03 07 01 F4 03 03 01 00 00 FF 00 13 00 06 07 00 03 07 01 F4 03 03 01 03 00 01 03 FF 00 02 00 06 07 00 03 07 01 F4 03 03 01 03 00 02 03 01 5C 03 FF 00 04 00 07 07 00 03 07 01 F4 03 03 01 03 03 00 01 07 00 A9 00 45 07 00 A9 00 4B 07 00 A9 FF 00 00 00 07 07 00 03 07 01 F4 03 03 01 03 03 00 03 03 03 03 45 07 00 A9 00 FF 00 12 00 00 00 01 07 00 A9 FF 00 00 00 07 07 00 03 07 01 F4 03 03 01 03 03 00 03 03 03 03 45 07 00 A9 00 4C 07 00 03 FF 00 02 00 07 07 00 03 07 01 F4 03 03 01 03 03 00 02 07 00 03 01 5F 07 00 03 45 07 00 8F 40 01 45 07 00 A9 00 FC 00 1B 02 42 01 1E FC 00 1B 02 42 01 1C FC 00 18 02 42 01 1F FC 00 1B 02 42 01 1C FF 00 0A 00 00 00 01 07 00 A9 FF 00 00 00 0B 07 00 03 07 01 F4 03 03 01 03 03 02 02 02 02 00 04 02 02 02 02 45 07 00 A9 00 FF 00 0A 00 00 00 01 07 00 A9 FF 00 00 00 0C 07 00 03 07 01 F4 03 03 01 03 03 02 02 02 02 03 00 02 07 00 3F 07 01 F4 45 07 00 A9 40 07 00 05 4E 07 01 D5 FF 00 02 00 0C 07 00 03 07 01 F4 03 03 01 03 03 02 02 02 02 03 00 02 07 01 D5 01 5F 07 01 D5 FF 00 0B 00 00 00 01 07 00 A9 FF 00 00 00 0D 07 00 03 07 01 F4 03 03 01 03 03 02 02 02 02 03 07 01 D5 00 01 07 01 D5 45 07 00 A9 40 01 4B 01 FF 00 02 00 0D 07 00 03 07 01 F4 03 03 01 03 03 02 02 02 02 03 07 01 D5 00 02 01 01 5C 01 42 07 00 95 40 01 45 07 00 A9 00 44 07 00 93 40 07 01 D5 45 07 00 A9 FF 00 00 00 0D 07 00 03 07 01 F4 03 03 01 03 03 02 02 02 02 03 07 01 D5 00 02 07 01 D5 04 42 07 00 A9 FF 00 00 00 0D 07 00 03 07 01 F4 03 03 01 03 03 02 02 02 02 03 07 01 D5 00 02 07 01 D5 04 45 07 00 A9 00 42 07 00 A9 00 45 07 00 A9 00 00 FF 00 0C 00 0E 07 00 03 07 01 F4 03 03 01 03 03 02 02 02 02 03 07 01 D5 01 00 01 07 00 A9 40 01 45 07 00 A9 40 01 FF 00 09 00 00 00 01 07 00 A9 FF 00 00 00 0E 07 00 03 07 01 F4 03 03 01 03 03 02 02 02 02 03 07 01 D5 01 00 02 01 01 45 07 00 A9 00 44 07 00 A1 40 01 45 07 00 A9 00 43 07 00 99 40 07 01 F4 45 07 00 A9 40 07 02 5D 4B 07 02 5D FF 00 02 00 0E 07 00 03 07 01 F4 03 03 01 03 03 02 02 02 02 03 07 01 D5 01 00 02 07 02 5D 01 5D 07 02 5D FE 00 09 07 02 5D 01 01 57 01 FF 00 02 00 11 07 00 03 07 01 F4 03 03 01 03 03 02 02 02 02 03 07 01 D5 01 07 02 5D 01 01 00 02 01 01 5E 01 FF 00 06 00 12 07 00 03 07 01 F4 03 03 01 03 03 02 02 02 02 03 07 01 D5 01 07 02 5D 01 01 01 00 01 07 00 8F 40 01 45 07 00 A9 40 01 4B 01 FF 00 02 00 12 07 00 03 07 01 F4 03 03 01 03 03 02 02 02 02 03 07 01 D5 01 07 02 5D 01 01 01 00 02 01 01 5D 01 07 05 42 01 1A 0B 42 01 1C 42 07 00 A9 00 45 07 00 A9 00 4B 07 00 A9 FF 00 00 00 12 07 00 03 07 01 F4 03 03 01 03 03 02 02 02 02 03 07 01 D5 01 07 02 5D 01 01 01 00 03 03 03 03 45 07 00 A9 00 42 07 00 93 00 45 07 00 A9 40 07 02 12 4B 07 02 12 FF 00 02 00 12 07 00 03 07 01 F4 03 03 01 03 03 02 02 02 02 03 07 01 D5 01 07 02 5D 01 01 01 00 02 07 02 12 01 5E 07 02 12 47 07 00 A9 FF 00 00 00 12 07 00 03 07 01 F4 03 03 01 03 03 02 02 02 02 03 07 01 D5 01 07 02 5D 01 01 01 00 02 07 02 2A 01 45 07 00 A9 FF 00 00 00 12 07 00 03 07 01 F4 03 03 01 03 03 02 02 02 02 03 07 01 D5 01 07 02 5D 01 01 01 00 02 07 02 2A 07 01 F4 FF 00 0B 00 12 07 00 03 07 01 F4 03 03 01 03 03 02 02 02 02 03 07 01 D5 01 07 02 5D 01 01 01 00 02 07 02 2A 07 01 F4 FF 00 02 00 12 07 00 03 07 01 F4 03 03 01 03 03 02 02 02 02 03 07 01 D5 01 07 02 5D 01 01 01 00 03 07 02 2A 07 01 F4 01 FF 00 1C 00 12 07 00 03 07 01 F4 03 03 01 03 03 02 02 02 02 03 07 01 D5 01 07 02 5D 01 01 01 00 02 07 02 2A 07 01 F4 FF 00 18 00 12 07 00 03 07 01 F4 03 03 01 03 03 02 02 02 02 03 07 01 D5 01 07 02 5D 01 01 01 00 06 07 02 2A 07 01 F4 02 02 01 01 FF 00 02 00 12 07 00 03 07 01 F4 03 03 01 03 03 02 02 02 02 03 07 01 D5 01 07 02 5D 01 01 01 00 07 07 02 2A 07 01 F4 02 02 01 01 01 FF 00 1F 00 12 07 00 03 07 01 F4 03 03 01 03 03 02 02 02 02 03 07 01 D5 01 07 02 5D 01 01 01 00 06 07 02 2A 07 01 F4 02 02 01 01 42 07 00 8F FF 00 00 00 12 07 00 03 07 01 F4 03 03 01 03 03 02 02 02 02 03 07 01 D5 01 07 02 5D 01 01 01 00 06 07 02 2A 07 01 F4 02 02 01 01 45 07 00 A9 40 01 4E 03 FF 00 02 00 12 07 00 03 07 01 F4 03 03 01 03 03 02 02 02 02 03 07 01 D5 01 07 02 5D 01 01 01 00 02 03 01 5E 03 42 07 00 A1 40 03 45 07 00 A9 FF 00 00 00 12 07 00 03 07 01 F4 03 03 01 03 03 02 02 02 02 03 07 01 D5 01 07 02 5D 01 01 01 00 02 03 07 02 12 47 07 00 8F FF 00 00 00 12 07 00 03 07 01 F4 03 03 01 03 03 02 02 02 02 03 07 01 D5 01 07 02 5D 01 01 01 00 03 03 07 02 2A 01 45 07 00 A9 FF 00 00 00 12 07 00 03 07 01 F4 03 03 01 03 03 02 02 02 02 03 07 01 D5 01 07 02 5D 01 01 01 00 03 03 07 02 2A 07 01 F4 42 07 00 91 FF 00 00 00 12 07 00 03 07 01 F4 03 03 01 03 03 02 02 02 02 03 07 01 D5 01 07 02 5D 01 01 01 00 03 03 07 02 2A 07 01 F4 45 07 00 A9 FF 00 00 00 12 07 00 03 07 01 F4 03 03 01 03 03 02 02 02 02 03 07 01 D5 01 07 02 5D 01 01 01 00 02 03 01 53 07 00 A9 FF 00 00 00 12 07 00 03 07 01 F4 03 03 01 03 03 02 02 02 02 03 07 01 D5 01 07 02 5D 01 01 01 00 03 03 03 03 45 07 00 A9 00 FF 00 06 00 00 00 01 07 00 A9 FF 00 00 00 12 07 00 03 07 01 F4 03 03 01 03 03 02 02 02 02 03 07 01 D5 01 07 02 5D 01 01 01 00 01 01 45 07 00 A9 00 4D 02 FF 00 02 00 12 07 00 03 07 01 F4 03 03 01 03 03 02 02 02 02 03 07 01 D5 01 07 02 5D 01 01 01 00 02 02 01 5D 02 48 07 00 A9 FF 00 00 00 12 07 00 03 07 01 F4 03 03 01 03 03 02 02 02 02 03 07 01 D5 01 07 02 5D 01 01 01 00 04 02 02 02 02 45 07 00 A9 00 4D 01 FF 00 02 00 12 07 00 03 07 01 F4 03 03 01 03 03 02 02 02 02 03 07 01 D5 01 07 02 5D 01 01 01 00 02 01 01 5D 01 42 07 00 A5 40 01 45 07 00 A9 00 02 0C 4F 07 00 81 FF 00 02 00 12 07 00 03 07 01 F4 03 03 01 03 03 02 02 02 02 03 07 01 D5 01 07 02 5D 01 01 01 00 02 07 00 81 01 5D 07 00 81 FC 00 0C 07 00 6D 4C 07 00 03 FF 00 02 00 13 07 00 03 07 01 F4 03 03 01 03 03 02 02 02 02 03 07 01 D5 01 07 02 5D 01 01 01 07 00 6D 00 02 07 00 03 01 5E 07 00 03 FF 00 0D 00 13 07 00 03 07 01 F4 03 03 01 03 03 02 02 02 02 03 07 01 D5 01 07 02 5D 01 01 01 07 00 6D 00 02 07 00 03 07 00 6D FF 00 02 00 13 07 00 03 07 01 F4 03 03 01 03 03 02 02 02 02 03 07 01 D5 01 07 02 5D 01 01 01 07 00 6D 00 03 07 00 03 07 00 6D 01 FF 00 1E 00 13 07 00 03 07 01 F4 03 03 01 03 03 02 02 02 02 03 07 01 D5 01 07 02 5D 01 01 01 07 00 6D 00 02 07 00 03 07 00 6D 46 07 00 A9 FF 00 00 00 13 07 00 03 07 01 F4 03 03 01 03 03 02 02 02 02 03 07 01 D5 01 07 02 5D 01 01 01 07 00 6D 00 04 07 00 03 07 00 6D 02 02 45 07 00 A9 00 0B 42 01 1D 46 07 00 A9 FF 00 00 00 13 07 00 03 07 01 F4 03 03 01 03 03 02 02 02 02 03 07 01 D5 01 07 02 5D 01 01 01 07 00 6D 00 02 03 07 00 6D 45 07 00 A9 FF 00 00 00 13 07 00 03 07 01 F4 03 03 01 03 03 02 02 02 02 03 07 01 D5 01 07 02 5D 01 01 01 07 00 6D 00 02 03 01 FA 00 07 FA 00 05 0B 42 01 1F 42 07 00 A9 00 45 07 00 A9 00 53 07 00 A9 FF 00 00 00 11 07 00 03 07 01 F4 03 03 01 03 03 02 02 02 02 03 07 01 D5 01 07 02 5D 01 01 00 05 07 00 3F 07 01 F4 08 06 E6 08 06 E6 01 45 07 00 A9 FF 00 00 00 11 07 00 03 07 01 F4 03 03 01 03 03 02 02 02 02 03 07 01 D5 01 07 02 5D 01 01 00 06 07 00 3F 07 01 F4 08 06 E6 08 06 E6 01 04 42 07 00 A3 FF 00 00 00 11 07 00 03 07 01 F4 03 03 01 03 03 02 02 02 02 03 07 01 D5 01 07 02 5D 01 01 00 06 07 00 3F 07 01 F4 08 06 E6 08 06 E6 01 04 45 07 00 A9 FF 00 00 00 11 07 00 03 07 01 F4 03 03 01 03 03 02 02 02 02 03 07 01 D5 01 07 02 5D 01 01 00 03 07 00 3F 07 01 F4 07 01 D5 42 07 00 8B FF 00 00 00 11 07 00 03 07 01 F4 03 03 01 03 03 02 02 02 02 03 07 01 D5 01 07 02 5D 01 01 00 03 07 00 3F 07 01 F4 07 01 D5 45 07 00 A9 40 07 00 05 FF 00 03 00 00 00 01 07 00 A9 FF 00 00 00 11 07 00 03 07 01 F4 03 03 01 03 03 02 02 02 02 03 07 01 D5 01 07 02 5D 01 01 00 00 45 07 00 A9 00 0B 42 01 1F 42 07 00 97 00 45 07 00 A9 00 FF 00 00 00 13 07 00 03 07 01 F4 03 03 01 03 03 02 02 02 02 03 07 01 D5 01 07 02 5D 01 01 01 07 00 6D 00 02 07 00 03 07 00 6D FF 00 01 00 0B 07 00 03 07 01 F4 03 03 01 03 03 02 02 02 02 00 00 FF 00 01 00 0D 07 00 03 07 01 F4 03 03 01 03 03 02 02 02 02 03 07 01 D5 00 01 01 FF 00 01 00 08 07 00 03 07 01 F4 03 03 01 03 03 02 00 00 FF 00 01 00 12 07 00 03 07 01 F4 03 03 01 03 03 02 02 02 02 03 07 01 D5 01 07 02 5D 01 01 01 00 01 07 02 12 FF 00 01 00 09 07 00 03 07 01 F4 03 03 01 03 03 02 02 00 00 FF 00 01 00 06 07 00 03 07 01 F4 03 03 01 03 00 01 03 FF 00 01 00 07 07 00 03 07 01 F4 03 03 01 03 03 00 01 07 00 03 FF 00 01 00 12 07 00 03 07 01 F4 03 03 01 03 03 02 02 02 02 03 07 01 D5 01 07 02 5D 01 01 01 00 01 07 00 81 41 01 FF 00 01 00 11 07 00 03 07 01 F4 03 03 01 03 03 02 02 02 02 03 07 01 D5 01 07 02 5D 01 01 00 01 01 FF 00 01 00 0A 07 00 03 07 01 F4 03 03 01 03 03 02 02 02 00 00 FF 00 01 00 0C 07 00 03 07 01 F4 03 03 01 03 03 02 02 02 02 03 00 01 07 01 D5 FF 00 01 00 12 07 00 03 07 01 F4 03 03 01 03 03 02 02 02 02 03 07 01 D5 01 07 02 5D 01 01 01 00 06 07 02 2A 07 01 F4 02 02 01 01 41 03 FF 00 01 00 12 07 00 03 07 01 F4 03 03 01 03 03 02 02 02 02 03 07 01 D5 01 07 02 5D 01 01 01 00 02 07 02 2A 07 01 F4 41 01 01 FA 00 01 FF 00 01 00 13 07 00 03 07 01 F4 03 03 01 03 03 02 02 02 02 03 07 01 D5 01 07 02 5D 01 01 01 07 00 6D 00 01 07 00 03 01 FF 00 01 00 0E 07 00 03 07 01 F4 03 03 01 03 03 02 02 02 02 03 07 01 D5 01 00 01 07 02 5D FF 00 01 00 12 07 00 03 07 01 F4 03 03 01 03 03 02 02 02 02 03 07 01 D5 01 07 02 5D 01 01 01 00 01 02 FA 00 01 FF 00 01 00 05 07 00 03 07 01 F4 03 03 01 00 01 07 00 8F 43 05 44 07 00 8F 47 05 FF 00 07 00 07 07 00 03 07 01 F4 03 03 01 03 03 00 01 07 00 A9
        //    Exceptions:
        //  Try           Handler
        //  Start  End    Start  End    Type                                       
        //  -----  -----  -----  -----  -------------------------------------------
        //  8      20     1933   1941   Ljava/lang/IndexOutOfBoundsException;
        //  1933   1941   1933   1941   Ljava/lang/NumberFormatException;
        //  1949   1951   3      8      Any
        //  81     88     88     89     Any
        //  81     88     3      8      Any
        //  81     88     3      8      Ljava/lang/NumberFormatException;
        //  82     88     3      8      Ljava/lang/NegativeArraySizeException;
        //  82     88     81     82     Any
        //  101    108    108    109    Any
        //  102    108    108    109    Ljava/lang/RuntimeException;
        //  101    108    101    102    Any
        //  102    108    3      8      Ljava/lang/RuntimeException;
        //  101    108    108    109    Ljava/lang/RuntimeException;
        //  129    135    135    136    Any
        //  129    135    135    136    Any
        //  129    135    135    136    Ljava/lang/ArrayIndexOutOfBoundsException;
        //  129    135    135    136    Ljava/lang/ClassCastException;
        //  129    135    3      8      Any
        //  190    197    197    198    Any
        //  191    197    190    191    Ljava/lang/IllegalStateException;
        //  191    197    3      8      Any
        //  191    197    3      8      Ljava/lang/NumberFormatException;
        //  191    197    190    191    Ljava/lang/UnsupportedOperationException;
        //  452    458    458    459    Any
        //  452    458    458    459    Ljava/lang/ArithmeticException;
        //  452    458    458    459    Ljava/lang/UnsupportedOperationException;
        //  452    458    3      8      Any
        //  452    458    3      8      Ljava/lang/UnsupportedOperationException;
        //  471    477    477    478    Any
        //  471    477    477    478    Ljava/lang/EnumConstantNotPresentException;
        //  471    477    477    478    Ljava/lang/ArithmeticException;
        //  471    477    477    478    Ljava/lang/ClassCastException;
        //  471    477    477    478    Ljava/lang/NullPointerException;
        //  541    547    547    548    Any
        //  541    547    547    548    Ljava/lang/ArrayIndexOutOfBoundsException;
        //  541    547    3      8      Ljava/util/ConcurrentModificationException;
        //  541    547    547    548    Ljava/util/NoSuchElementException;
        //  541    547    547    548    Any
        //  595    602    602    603    Any
        //  595    602    595    596    Ljava/lang/AssertionError;
        //  595    602    602    603    Ljava/lang/IndexOutOfBoundsException;
        //  595    602    602    603    Ljava/lang/UnsupportedOperationException;
        //  595    602    3      8      Ljava/lang/ArithmeticException;
        //  608    615    615    616    Any
        //  609    615    3      8      Ljava/util/ConcurrentModificationException;
        //  608    615    608    609    Ljava/lang/NumberFormatException;
        //  609    615    3      8      Ljava/lang/AssertionError;
        //  609    615    3      8      Any
        //  619    626    626    627    Any
        //  619    626    619    620    Ljava/lang/ArithmeticException;
        //  620    626    619    620    Any
        //  620    626    3      8      Any
        //  620    626    619    620    Any
        //  630    637    637    638    Any
        //  631    637    637    638    Any
        //  631    637    3      8      Any
        //  631    637    637    638    Any
        //  630    637    630    631    Any
        //  652    659    659    660    Any
        //  652    659    652    653    Any
        //  653    659    652    653    Ljava/lang/NegativeArraySizeException;
        //  653    659    3      8      Ljava/lang/NumberFormatException;
        //  652    659    652    653    Ljava/lang/IllegalArgumentException;
        //  671    677    677    678    Any
        //  671    677    677    678    Ljava/lang/IllegalArgumentException;
        //  671    677    677    678    Any
        //  671    677    3      8      Ljava/lang/ArrayIndexOutOfBoundsException;
        //  671    677    3      8      Ljava/lang/ClassCastException;
        //  683    690    690    691    Any
        //  684    690    690    691    Ljava/lang/IllegalStateException;
        //  684    690    683    684    Ljava/lang/UnsupportedOperationException;
        //  684    690    3      8      Ljava/lang/ArithmeticException;
        //  683    690    690    691    Any
        //  695    702    702    703    Any
        //  696    702    3      8      Any
        //  695    702    3      8      Any
        //  696    702    695    696    Ljava/lang/IndexOutOfBoundsException;
        //  696    702    3      8      Ljava/lang/ArrayIndexOutOfBoundsException;
        //  823    830    830    831    Any
        //  824    830    3      8      Any
        //  823    830    823    824    Ljava/lang/RuntimeException;
        //  824    830    823    824    Ljava/lang/IndexOutOfBoundsException;
        //  823    830    3      8      Ljava/lang/ClassCastException;
        //  967    974    974    975    Any
        //  968    974    3      8      Any
        //  968    974    3      8      Any
        //  967    974    967    968    Any
        //  968    974    974    975    Ljava/util/NoSuchElementException;
        //  987    994    994    995    Any
        //  988    994    987    988    Any
        //  988    994    3      8      Ljava/lang/NullPointerException;
        //  988    994    3      8      Ljava/util/ConcurrentModificationException;
        //  987    994    987    988    Ljava/lang/NullPointerException;
        //  998    1005   1005   1006   Any
        //  998    1005   1005   1006   Any
        //  998    1005   998    999    Ljava/lang/NumberFormatException;
        //  998    1005   1005   1006   Any
        //  999    1005   1005   1006   Any
        //  1060   1067   1067   1068   Any
        //  1061   1067   1067   1068   Ljava/lang/AssertionError;
        //  1060   1067   1060   1061   Any
        //  1061   1067   1060   1061   Ljava/util/ConcurrentModificationException;
        //  1060   1067   3      8      Any
        //  1175   1182   1182   1183   Any
        //  1176   1182   1175   1176   Ljava/lang/IllegalStateException;
        //  1175   1182   1175   1176   Ljava/lang/ClassCastException;
        //  1175   1182   1182   1183   Ljava/lang/IllegalStateException;
        //  1176   1182   1182   1183   Ljava/util/ConcurrentModificationException;
        //  1235   1242   1242   1243   Any
        //  1235   1242   1242   1243   Any
        //  1235   1242   1242   1243   Any
        //  1235   1242   3      8      Ljava/util/ConcurrentModificationException;
        //  1236   1242   1235   1236   Ljava/lang/UnsupportedOperationException;
        //  1251   1258   1258   1259   Any
        //  1251   1258   1251   1252   Ljava/lang/RuntimeException;
        //  1251   1258   1258   1259   Ljava/lang/IllegalArgumentException;
        //  1252   1258   1258   1259   Ljava/lang/ArrayIndexOutOfBoundsException;
        //  1252   1258   3      8      Any
        //  1262   1269   1269   1270   Any
        //  1263   1269   1262   1263   Ljava/util/NoSuchElementException;
        //  1262   1269   1269   1270   Any
        //  1262   1269   3      8      Any
        //  1262   1269   3      8      Any
        //  1290   1297   1297   1298   Any
        //  1290   1297   1297   1298   Any
        //  1290   1297   1297   1298   Any
        //  1290   1297   1297   1298   Ljava/lang/ClassCastException;
        //  1291   1297   1290   1291   Any
        //  1306   1312   1312   1313   Any
        //  1306   1312   3      8      Any
        //  1306   1312   3      8      Any
        //  1306   1312   1312   1313   Any
        //  1306   1312   1312   1313   Any
        //  1369   1376   1376   1377   Any
        //  1370   1376   1376   1377   Ljava/lang/NumberFormatException;
        //  1369   1376   3      8      Ljava/lang/StringIndexOutOfBoundsException;
        //  1370   1376   1369   1370   Any
        //  1370   1376   1369   1370   Any
        //  1427   1434   1434   1435   Any
        //  1427   1434   3      8      Any
        //  1427   1434   1434   1435   Ljava/lang/ClassCastException;
        //  1428   1434   1434   1435   Ljava/util/ConcurrentModificationException;
        //  1428   1434   1427   1428   Ljava/lang/NullPointerException;
        //  1615   1622   1622   1623   Any
        //  1616   1622   3      8      Ljava/lang/ArrayIndexOutOfBoundsException;
        //  1615   1622   1615   1616   Any
        //  1615   1622   1622   1623   Any
        //  1616   1622   1615   1616   Ljava/lang/NullPointerException;
        //  1675   1682   1682   1683   Any
        //  1675   1682   1675   1676   Ljava/lang/EnumConstantNotPresentException;
        //  1675   1682   1675   1676   Ljava/lang/NegativeArraySizeException;
        //  1676   1682   3      8      Any
        //  1676   1682   1675   1676   Any
        //  1747   1754   1754   1755   Any
        //  1748   1754   3      8      Any
        //  1748   1754   1754   1755   Any
        //  1748   1754   1754   1755   Any
        //  1747   1754   1747   1748   Any
        //  1775   1782   1782   1783   Any
        //  1776   1782   1775   1776   Ljava/util/NoSuchElementException;
        //  1775   1782   1782   1783   Ljava/lang/ArrayIndexOutOfBoundsException;
        //  1776   1782   1782   1783   Ljava/lang/ArithmeticException;
        //  1775   1782   1775   1776   Ljava/lang/AssertionError;
        //  1786   1793   1793   1794   Any
        //  1787   1793   1786   1787   Ljava/lang/IllegalArgumentException;
        //  1786   1793   3      8      Ljava/util/ConcurrentModificationException;
        //  1787   1793   3      8      Any
        //  1786   1793   1793   1794   Ljava/lang/ClassCastException;
        //  1797   1804   1804   1805   Any
        //  1797   1804   1804   1805   Any
        //  1797   1804   1804   1805   Any
        //  1797   1804   1797   1798   Ljava/lang/EnumConstantNotPresentException;
        //  1797   1804   1804   1805   Any
        //  1810   1816   1816   1817   Any
        //  1810   1816   1816   1817   Ljava/lang/NumberFormatException;
        //  1810   1816   3      8      Any
        //  1810   1816   1816   1817   Any
        //  1810   1816   1816   1817   Ljava/lang/IllegalArgumentException;
        //  1867   1874   1874   1875   Any
        //  1867   1874   1874   1875   Any
        //  1867   1874   3      8      Ljava/lang/IndexOutOfBoundsException;
        //  1868   1874   3      8      Any
        //  1867   1874   1867   1868   Ljava/lang/StringIndexOutOfBoundsException;
        // 
        // The error that occurred was:
        // 
        // java.lang.IndexOutOfBoundsException: Index -1 out of bounds for length 0
        //     at java.base/jdk.internal.util.Preconditions.outOfBounds(Preconditions.java:64)
        //     at java.base/jdk.internal.util.Preconditions.outOfBoundsCheckIndex(Preconditions.java:70)
        //     at java.base/jdk.internal.util.Preconditions.checkIndex(Preconditions.java:248)
        //     at java.base/java.util.Objects.checkIndex(Objects.java:372)
        //     at java.base/java.util.ArrayList.remove(ArrayList.java:535)
        //     at com.strobel.assembler.ir.StackMappingVisitor.pop(StackMappingVisitor.java:267)
        //     at com.strobel.assembler.ir.StackMappingVisitor$InstructionAnalyzer.execute(StackMappingVisitor.java:595)
        //     at com.strobel.assembler.ir.StackMappingVisitor$InstructionAnalyzer.visit(StackMappingVisitor.java:398)
        //     at com.strobel.decompiler.ast.AstBuilder.performStackAnalysis(AstBuilder.java:2030)
        //     at com.strobel.decompiler.ast.AstBuilder.build(AstBuilder.java:108)
        //     at com.strobel.decompiler.languages.java.ast.AstMethodBodyBuilder.createMethodBody(AstMethodBodyBuilder.java:211)
        //     at com.strobel.decompiler.languages.java.ast.AstMethodBodyBuilder.createMethodBody(AstMethodBodyBuilder.java:99)
        //     at com.strobel.decompiler.languages.java.ast.AstBuilder.createMethodBody(AstBuilder.java:782)
        //     at com.strobel.decompiler.languages.java.ast.AstBuilder.createMethod(AstBuilder.java:675)
        //     at com.strobel.decompiler.languages.java.ast.AstBuilder.addTypeMembers(AstBuilder.java:552)
        //     at com.strobel.decompiler.languages.java.ast.AstBuilder.createTypeCore(AstBuilder.java:519)
        //     at com.strobel.decompiler.languages.java.ast.AstBuilder.createTypeNoCache(AstBuilder.java:161)
        //     at com.strobel.decompiler.languages.java.ast.AstBuilder.createType(AstBuilder.java:150)
        //     at com.strobel.decompiler.languages.java.ast.AstBuilder.addType(AstBuilder.java:125)
        //     at com.strobel.decompiler.languages.java.JavaLanguage.buildAst(JavaLanguage.java:71)
        //     at com.strobel.decompiler.languages.java.JavaLanguage.decompileType(JavaLanguage.java:59)
        //     at com.strobel.decompiler.DecompilerDriver.decompileType(DecompilerDriver.java:330)
        //     at com.strobel.decompiler.DecompilerDriver.decompileJar(DecompilerDriver.java:251)
        //     at com.strobel.decompiler.DecompilerDriver.main(DecompilerDriver.java:126)
        // 
        throw new IllegalStateException("An error occurred while decompiling this method.");
    }
    
    public Font 1() {
        // 
        // This method could not be decompiled.
        // 
        // Original Bytecode:
        // 
        //     1: getstatic       dev/nuker/pyro/fc.1:I
        //     4: ifgt            38
        //     7: pop            
        //     8: aconst_null    
        //     9: goto            30
        //    12: nop            
        //    13: nop            
        //    14: nop            
        //    15: athrow         
        //    16: aload_0        
        //    17: getfield        dev/nuker/pyro/fbE.c:Ljava/awt/Font;
        //    20: areturn        
        //    21: pop            
        //    22: goto            16
        //    25: pop            
        //    26: aconst_null    
        //    27: goto            21
        //    30: dup            
        //    31: ifnull          21
        //    34: checkcast       Ljava/lang/Throwable;
        //    37: athrow         
        //    38: dup            
        //    39: ifnull          25
        //    42: checkcast       Ljava/lang/Throwable;
        //    45: athrow         
        //    StackMapTable: 00 06 FF 00 0C 00 00 00 01 07 00 A9 FC 00 03 07 00 03 44 07 00 A9 43 05 44 07 00 A9 47 05
        //    Exceptions:
        //  Try           Handler
        //  Start  End    Start  End    Type
        //  -----  -----  -----  -----  ----
        //  0      12     30     38     Any
        //  30     38     30     38     Any
        // 
        // The error that occurred was:
        // 
        // java.lang.IndexOutOfBoundsException: Index -1 out of bounds for length 0
        //     at java.base/jdk.internal.util.Preconditions.outOfBounds(Preconditions.java:64)
        //     at java.base/jdk.internal.util.Preconditions.outOfBoundsCheckIndex(Preconditions.java:70)
        //     at java.base/jdk.internal.util.Preconditions.checkIndex(Preconditions.java:248)
        //     at java.base/java.util.Objects.checkIndex(Objects.java:372)
        //     at java.base/java.util.ArrayList.remove(ArrayList.java:535)
        //     at com.strobel.assembler.ir.StackMappingVisitor.pop(StackMappingVisitor.java:267)
        //     at com.strobel.assembler.ir.StackMappingVisitor$InstructionAnalyzer.execute(StackMappingVisitor.java:543)
        //     at com.strobel.assembler.ir.StackMappingVisitor$InstructionAnalyzer.visit(StackMappingVisitor.java:398)
        //     at com.strobel.decompiler.ast.AstBuilder.performStackAnalysis(AstBuilder.java:2030)
        //     at com.strobel.decompiler.ast.AstBuilder.build(AstBuilder.java:108)
        //     at com.strobel.decompiler.languages.java.ast.AstMethodBodyBuilder.createMethodBody(AstMethodBodyBuilder.java:211)
        //     at com.strobel.decompiler.languages.java.ast.AstMethodBodyBuilder.createMethodBody(AstMethodBodyBuilder.java:99)
        //     at com.strobel.decompiler.languages.java.ast.AstBuilder.createMethodBody(AstBuilder.java:782)
        //     at com.strobel.decompiler.languages.java.ast.AstBuilder.createMethod(AstBuilder.java:675)
        //     at com.strobel.decompiler.languages.java.ast.AstBuilder.addTypeMembers(AstBuilder.java:552)
        //     at com.strobel.decompiler.languages.java.ast.AstBuilder.createTypeCore(AstBuilder.java:519)
        //     at com.strobel.decompiler.languages.java.ast.AstBuilder.createTypeNoCache(AstBuilder.java:161)
        //     at com.strobel.decompiler.languages.java.ast.AstBuilder.createType(AstBuilder.java:150)
        //     at com.strobel.decompiler.languages.java.ast.AstBuilder.addType(AstBuilder.java:125)
        //     at com.strobel.decompiler.languages.java.JavaLanguage.buildAst(JavaLanguage.java:71)
        //     at com.strobel.decompiler.languages.java.JavaLanguage.decompileType(JavaLanguage.java:59)
        //     at com.strobel.decompiler.DecompilerDriver.decompileType(DecompilerDriver.java:330)
        //     at com.strobel.decompiler.DecompilerDriver.decompileJar(DecompilerDriver.java:251)
        //     at com.strobel.decompiler.DecompilerDriver.main(DecompilerDriver.java:126)
        // 
        throw new IllegalStateException("An error occurred while decompiling this method.");
    }
    
    public int 0() {
        return fbS.bK(this, 1198215374);
    }
    
    public void c(final fbD p0, final float p1, final float p2) {
        // 
        // This method could not be decompiled.
        // 
        // Original Bytecode:
        // 
        //     3: dup            
        //     4: ifnull          1103
        //     7: athrow         
        //     8: aconst_null    
        //     9: getstatic       dev/nuker/pyro/fc.0:I
        //    12: ifgt            1095
        //    15: pop            
        //    16: aconst_null    
        //    17: goto            1087
        //    20: nop            
        //    21: nop            
        //    22: nop            
        //    23: athrow         
        //    24: aload_1        
        //    25: goto            29
        //    28: athrow         
        //    29: invokestatic    dev/nuker/pyro/fbD.2:(Ldev/nuker/pyro/fbD;)I
        //    32: goto            36
        //    35: athrow         
        //    36: i2f            
        //    37: fstore          4
        //    39: getstatic       dev/nuker/pyro/fc.1:I
        //    42: ifeq            51
        //    45: ldc_w           1616556531
        //    48: goto            54
        //    51: ldc_w           1020417273
        //    54: ldc_w           -848787489
        //    57: ixor           
        //    58: lookupswitch {
        //          -1389218260: 1074
        //          1406415453: 51
        //          default: 84
        //        }
        //    84: aload_1        
        //    85: getstatic       dev/nuker/pyro/fc.c:I
        //    88: ifge            97
        //    91: ldc_w           -1507675502
        //    94: goto            100
        //    97: ldc_w           -787953278
        //   100: ldc_w           1545215959
        //   103: ixor           
        //   104: lookupswitch {
        //          -358713934: 97
        //          -96948923: 1056
        //          default: 132
        //        }
        //   132: goto            136
        //   135: athrow         
        //   136: invokestatic    dev/nuker/pyro/fbD.c:(Ldev/nuker/pyro/fbD;)I
        //   139: goto            143
        //   142: athrow         
        //   143: i2f            
        //   144: fstore          5
        //   146: getstatic       dev/nuker/pyro/fc.1:I
        //   149: ifeq            158
        //   152: ldc_w           28028438
        //   155: goto            161
        //   158: ldc_w           -482208441
        //   161: ldc_w           -1996774788
        //   164: ixor           
        //   165: lookupswitch {
        //          -1991242646: 1064
        //          -276375502: 158
        //          default: 192
        //        }
        //   192: aload_1        
        //   193: goto            197
        //   196: athrow         
        //   197: invokestatic    dev/nuker/pyro/fbD.0:(Ldev/nuker/pyro/fbD;)I
        //   200: goto            204
        //   203: athrow         
        //   204: i2f            
        //   205: fstore          6
        //   207: aload_1        
        //   208: getstatic       dev/nuker/pyro/fc.0:I
        //   211: ifeq            220
        //   214: ldc_w           -742690648
        //   217: goto            223
        //   220: ldc_w           1066259140
        //   223: ldc_w           1425958920
        //   226: ixor           
        //   227: lookupswitch {
        //          -2025514848: 1066
        //          -1725356085: 220
        //          default: 252
        //        }
        //   252: goto            256
        //   255: athrow         
        //   256: invokestatic    dev/nuker/pyro/fbD.1:(Ldev/nuker/pyro/fbD;)I
        //   259: goto            263
        //   262: athrow         
        //   263: i2f            
        //   264: fstore          7
        //   266: fload           6
        //   268: aload_0        
        //   269: getstatic       dev/nuker/pyro/fc.0:I
        //   272: ifeq            281
        //   275: ldc_w           -1247013443
        //   278: goto            284
        //   281: ldc_w           -1205096470
        //   284: ldc_w           1901805704
        //   287: ixor           
        //   288: lookupswitch {
        //          -990423755: 1044
        //          -558762489: 281
        //          default: 316
        //        }
        //   316: getfield        dev/nuker/pyro/fbE.6:I
        //   319: i2f            
        //   320: fdiv           
        //   321: fstore          8
        //   323: fload           7
        //   325: aload_0        
        //   326: getfield        dev/nuker/pyro/fbE.7:I
        //   329: i2f            
        //   330: fdiv           
        //   331: fstore          9
        //   333: getstatic       dev/nuker/pyro/fc.1:I
        //   336: ifeq            345
        //   339: ldc_w           -1196497008
        //   342: goto            348
        //   345: ldc_w           1600872245
        //   348: ldc_w           -1974380613
        //   351: ixor           
        //   352: lookupswitch {
        //          -717617010: 380
        //          855617579: 345
        //          default: 1070
        //        }
        //   380: fload           4
        //   382: getstatic       dev/nuker/pyro/fc.1:I
        //   385: ifeq            394
        //   388: ldc_w           1720281915
        //   391: goto            397
        //   394: ldc_w           1168586070
        //   397: ldc_w           1615603703
        //   400: ixor           
        //   401: lookupswitch {
        //          -501027833: 394
        //          113593548: 1062
        //          default: 428
        //        }
        //   428: aload_0        
        //   429: getstatic       dev/nuker/pyro/fc.c:I
        //   432: ifge            441
        //   435: ldc_w           -399854207
        //   438: goto            444
        //   441: ldc_w           1637966263
        //   444: ldc_w           224803808
        //   447: ixor           
        //   448: lookupswitch {
        //          -447967647: 441
        //          1825004119: 476
        //          default: 1046
        //        }
        //   476: getfield        dev/nuker/pyro/fbE.6:I
        //   479: i2f            
        //   480: fdiv           
        //   481: fstore          10
        //   483: fload           5
        //   485: getstatic       dev/nuker/pyro/fc.1:I
        //   488: ifeq            497
        //   491: ldc_w           682489271
        //   494: goto            500
        //   497: ldc_w           2058089900
        //   500: ldc_w           -273885928
        //   503: ixor           
        //   504: lookupswitch {
        //          -1068413506: 497
        //          -956227409: 1052
        //          default: 532
        //        }
        //   532: aload_0        
        //   533: getfield        dev/nuker/pyro/fbE.7:I
        //   536: i2f            
        //   537: fdiv           
        //   538: fstore          11
        //   540: fload           8
        //   542: fload           9
        //   544: goto            548
        //   547: athrow         
        //   548: invokestatic    org/lwjgl/opengl/GL11.glTexCoord2f:(FF)V
        //   551: goto            555
        //   554: athrow         
        //   555: fload_2        
        //   556: fload_3        
        //   557: getstatic       dev/nuker/pyro/fc.1:I
        //   560: ifeq            569
        //   563: ldc_w           -1552169085
        //   566: goto            572
        //   569: ldc_w           -592989980
        //   572: ldc_w           261102131
        //   575: ixor           
        //   576: lookupswitch {
        //          -1393828432: 569
        //          -751326505: 604
        //          default: 1050
        //        }
        //   604: goto            608
        //   607: athrow         
        //   608: invokestatic    org/lwjgl/opengl/GL11.glVertex2f:(FF)V
        //   611: goto            615
        //   614: athrow         
        //   615: fload           8
        //   617: getstatic       dev/nuker/pyro/fc.1:I
        //   620: ifeq            629
        //   623: ldc_w           -1916372896
        //   626: goto            632
        //   629: ldc_w           345501883
        //   632: ldc_w           902360682
        //   635: ixor           
        //   636: lookupswitch {
        //          -1207003638: 629
        //          559881937: 664
        //          default: 1072
        //        }
        //   664: fload           9
        //   666: fload           11
        //   668: fadd           
        //   669: getstatic       dev/nuker/pyro/fc.c:I
        //   672: ifge            681
        //   675: ldc_w           1573782455
        //   678: goto            684
        //   681: ldc_w           -562854925
        //   684: ldc_w           1229465064
        //   687: ixor           
        //   688: lookupswitch {
        //          -1757698533: 716
        //          344335967: 681
        //          default: 1068
        //        }
        //   716: goto            720
        //   719: athrow         
        //   720: invokestatic    org/lwjgl/opengl/GL11.glTexCoord2f:(FF)V
        //   723: goto            727
        //   726: athrow         
        //   727: fload_2        
        //   728: fload_3        
        //   729: fload           5
        //   731: fadd           
        //   732: goto            736
        //   735: athrow         
        //   736: invokestatic    org/lwjgl/opengl/GL11.glVertex2f:(FF)V
        //   739: goto            743
        //   742: athrow         
        //   743: fload           8
        //   745: fload           10
        //   747: fadd           
        //   748: fload           9
        //   750: fload           11
        //   752: fadd           
        //   753: goto            757
        //   756: athrow         
        //   757: invokestatic    org/lwjgl/opengl/GL11.glTexCoord2f:(FF)V
        //   760: goto            764
        //   763: athrow         
        //   764: getstatic       dev/nuker/pyro/fc.c:I
        //   767: ifge            776
        //   770: ldc_w           1210794041
        //   773: goto            779
        //   776: ldc_w           1635317355
        //   779: ldc_w           -161295700
        //   782: ixor           
        //   783: lookupswitch {
        //          -1759894329: 808
        //          -1102474603: 776
        //          default: 1048
        //        }
        //   808: fload_2        
        //   809: fload           4
        //   811: fadd           
        //   812: getstatic       dev/nuker/pyro/fc.c:I
        //   815: ifge            824
        //   818: ldc_w           -1700644465
        //   821: goto            827
        //   824: ldc_w           1313113674
        //   827: ldc_w           239476268
        //   830: ixor           
        //   831: lookupswitch {
        //          -1796986973: 1054
        //          1180352931: 824
        //          default: 856
        //        }
        //   856: fload_3        
        //   857: fload           5
        //   859: fadd           
        //   860: goto            864
        //   863: athrow         
        //   864: invokestatic    org/lwjgl/opengl/GL11.glVertex2f:(FF)V
        //   867: goto            871
        //   870: athrow         
        //   871: getstatic       dev/nuker/pyro/fc.1:I
        //   874: ifeq            883
        //   877: ldc_w           -75226553
        //   880: goto            886
        //   883: ldc_w           -1466677189
        //   886: ldc_w           -478948708
        //   889: ixor           
        //   890: lookupswitch {
        //          -1393411759: 883
        //          418902235: 1076
        //          default: 916
        //        }
        //   916: fload           8
        //   918: getstatic       dev/nuker/pyro/fc.0:I
        //   921: ifeq            930
        //   924: ldc_w           -637819186
        //   927: goto            933
        //   930: ldc_w           1266229059
        //   933: ldc_w           -1825356816
        //   936: ixor           
        //   937: lookupswitch {
        //          655592215: 930
        //          1254679870: 1058
        //          default: 964
        //        }
        //   964: fload           10
        //   966: fadd           
        //   967: fload           9
        //   969: goto            973
        //   972: athrow         
        //   973: invokestatic    org/lwjgl/opengl/GL11.glTexCoord2f:(FF)V
        //   976: goto            980
        //   979: athrow         
        //   980: fload_2        
        //   981: getstatic       dev/nuker/pyro/fc.1:I
        //   984: ifeq            993
        //   987: ldc_w           -1760278249
        //   990: goto            996
        //   993: ldc_w           1552324141
        //   996: ldc_w           -668598059
        //   999: ixor           
        //  1000: lookupswitch {
        //          506292329: 993
        //          1328695746: 1060
        //          default: 1028
        //        }
        //  1028: fload           4
        //  1030: fadd           
        //  1031: fload_3        
        //  1032: goto            1036
        //  1035: athrow         
        //  1036: invokestatic    org/lwjgl/opengl/GL11.glVertex2f:(FF)V
        //  1039: goto            1043
        //  1042: athrow         
        //  1043: return         
        //  1044: aconst_null    
        //  1045: athrow         
        //  1046: aconst_null    
        //  1047: athrow         
        //  1048: aconst_null    
        //  1049: athrow         
        //  1050: aconst_null    
        //  1051: athrow         
        //  1052: aconst_null    
        //  1053: athrow         
        //  1054: aconst_null    
        //  1055: athrow         
        //  1056: aconst_null    
        //  1057: athrow         
        //  1058: aconst_null    
        //  1059: athrow         
        //  1060: aconst_null    
        //  1061: athrow         
        //  1062: aconst_null    
        //  1063: athrow         
        //  1064: aconst_null    
        //  1065: athrow         
        //  1066: aconst_null    
        //  1067: athrow         
        //  1068: aconst_null    
        //  1069: athrow         
        //  1070: aconst_null    
        //  1071: athrow         
        //  1072: aconst_null    
        //  1073: athrow         
        //  1074: aconst_null    
        //  1075: athrow         
        //  1076: aconst_null    
        //  1077: athrow         
        //  1078: pop            
        //  1079: goto            24
        //  1082: pop            
        //  1083: aconst_null    
        //  1084: goto            1078
        //  1087: dup            
        //  1088: ifnull          1078
        //  1091: checkcast       Ljava/lang/Throwable;
        //  1094: athrow         
        //  1095: dup            
        //  1096: ifnull          1082
        //  1099: checkcast       Ljava/lang/Throwable;
        //  1102: athrow         
        //  1103: aconst_null    
        //  1104: athrow         
        //    StackMapTable: 00 7D 43 07 00 A9 04 FF 00 0B 00 00 00 01 07 00 A9 FF 00 03 00 04 07 00 03 07 00 6D 02 02 00 00 43 07 00 A9 40 07 00 6D 45 07 00 A9 40 01 FC 00 0E 02 42 01 1D 4C 07 00 6D FF 00 02 00 05 07 00 03 07 00 6D 02 02 02 00 02 07 00 6D 01 5F 07 00 6D 42 07 00 A9 40 07 00 6D 45 07 00 A9 40 01 FC 00 0E 02 42 01 1E 43 07 00 A9 40 07 00 6D 45 07 00 A9 40 01 FF 00 0F 00 07 07 00 03 07 00 6D 02 02 02 02 02 00 01 07 00 6D FF 00 02 00 07 07 00 03 07 00 6D 02 02 02 02 02 00 02 07 00 6D 01 5C 07 00 6D 42 07 00 93 40 07 00 6D 45 07 00 A9 40 01 FF 00 11 00 08 07 00 03 07 00 6D 02 02 02 02 02 02 00 02 02 07 00 03 FF 00 02 00 08 07 00 03 07 00 6D 02 02 02 02 02 02 00 03 02 07 00 03 01 FF 00 1F 00 08 07 00 03 07 00 6D 02 02 02 02 02 02 00 02 02 07 00 03 FD 00 1C 02 02 42 01 1F 4D 02 FF 00 02 00 0A 07 00 03 07 00 6D 02 02 02 02 02 02 02 02 00 02 02 01 5E 02 FF 00 0C 00 0A 07 00 03 07 00 6D 02 02 02 02 02 02 02 02 00 02 02 07 00 03 FF 00 02 00 0A 07 00 03 07 00 6D 02 02 02 02 02 02 02 02 00 03 02 07 00 03 01 FF 00 1F 00 0A 07 00 03 07 00 6D 02 02 02 02 02 02 02 02 00 02 02 07 00 03 FF 00 14 00 0B 07 00 03 07 00 6D 02 02 02 02 02 02 02 02 02 00 01 02 FF 00 02 00 0B 07 00 03 07 00 6D 02 02 02 02 02 02 02 02 02 00 02 02 01 5F 02 FF 00 0E 00 0C 07 00 03 07 00 6D 02 02 02 02 02 02 02 02 02 02 00 01 07 00 A9 FF 00 00 00 0C 07 00 03 07 00 6D 02 02 02 02 02 02 02 02 02 02 00 02 02 02 45 07 00 A9 00 FF 00 0D 00 0C 07 00 03 07 00 6D 02 02 02 02 02 02 02 02 02 02 00 02 02 02 FF 00 02 00 0C 07 00 03 07 00 6D 02 02 02 02 02 02 02 02 02 02 00 03 02 02 01 FF 00 1F 00 0C 07 00 03 07 00 6D 02 02 02 02 02 02 02 02 02 02 00 02 02 02 42 07 00 A9 FF 00 00 00 0C 07 00 03 07 00 6D 02 02 02 02 02 02 02 02 02 02 00 02 02 02 45 07 00 A9 00 4D 02 FF 00 02 00 0C 07 00 03 07 00 6D 02 02 02 02 02 02 02 02 02 02 00 02 02 01 5F 02 FF 00 10 00 0C 07 00 03 07 00 6D 02 02 02 02 02 02 02 02 02 02 00 02 02 02 FF 00 02 00 0C 07 00 03 07 00 6D 02 02 02 02 02 02 02 02 02 02 00 03 02 02 01 FF 00 1F 00 0C 07 00 03 07 00 6D 02 02 02 02 02 02 02 02 02 02 00 02 02 02 FF 00 02 00 00 00 01 07 00 A9 FF 00 00 00 0C 07 00 03 07 00 6D 02 02 02 02 02 02 02 02 02 02 00 02 02 02 45 07 00 A9 00 47 07 00 A9 FF 00 00 00 0C 07 00 03 07 00 6D 02 02 02 02 02 02 02 02 02 02 00 02 02 02 45 07 00 A9 00 FF 00 0C 00 00 00 01 07 00 A9 FF 00 00 00 0C 07 00 03 07 00 6D 02 02 02 02 02 02 02 02 02 02 00 02 02 02 45 07 00 A9 00 0B 42 01 1C 4F 02 FF 00 02 00 0C 07 00 03 07 00 6D 02 02 02 02 02 02 02 02 02 02 00 02 02 01 5C 02 46 07 00 A7 FF 00 00 00 0C 07 00 03 07 00 6D 02 02 02 02 02 02 02 02 02 02 00 02 02 02 45 07 00 A9 00 0B 42 01 1D 4D 02 FF 00 02 00 0C 07 00 03 07 00 6D 02 02 02 02 02 02 02 02 02 02 00 02 02 01 5E 02 FF 00 07 00 00 00 01 07 00 A9 FF 00 00 00 0C 07 00 03 07 00 6D 02 02 02 02 02 02 02 02 02 02 00 02 02 02 45 07 00 A9 00 4C 02 FF 00 02 00 0C 07 00 03 07 00 6D 02 02 02 02 02 02 02 02 02 02 00 02 02 01 5F 02 46 07 00 A9 FF 00 00 00 0C 07 00 03 07 00 6D 02 02 02 02 02 02 02 02 02 02 00 02 02 02 45 07 00 A9 00 FF 00 00 00 08 07 00 03 07 00 6D 02 02 02 02 02 02 00 02 02 07 00 03 FF 00 01 00 0A 07 00 03 07 00 6D 02 02 02 02 02 02 02 02 00 02 02 07 00 03 FD 00 01 02 02 FF 00 01 00 0C 07 00 03 07 00 6D 02 02 02 02 02 02 02 02 02 02 00 02 02 02 FF 00 01 00 0B 07 00 03 07 00 6D 02 02 02 02 02 02 02 02 02 00 01 02 FF 00 01 00 0C 07 00 03 07 00 6D 02 02 02 02 02 02 02 02 02 02 00 01 02 FF 00 01 00 05 07 00 03 07 00 6D 02 02 02 00 01 07 00 6D FF 00 01 00 0C 07 00 03 07 00 6D 02 02 02 02 02 02 02 02 02 02 00 01 02 41 02 FF 00 01 00 0A 07 00 03 07 00 6D 02 02 02 02 02 02 02 02 00 01 02 FF 00 01 00 06 07 00 03 07 00 6D 02 02 02 02 00 00 FF 00 01 00 07 07 00 03 07 00 6D 02 02 02 02 02 00 01 07 00 6D FF 00 01 00 0C 07 00 03 07 00 6D 02 02 02 02 02 02 02 02 02 02 00 02 02 02 F9 00 01 FF 00 01 00 0C 07 00 03 07 00 6D 02 02 02 02 02 02 02 02 02 02 00 01 02 FF 00 01 00 05 07 00 03 07 00 6D 02 02 02 00 00 FF 00 01 00 0C 07 00 03 07 00 6D 02 02 02 02 02 02 02 02 02 02 00 00 FF 00 01 00 04 07 00 03 07 00 6D 02 02 00 01 07 00 A9 43 05 44 07 00 A9 47 05 47 07 00 A9
        //    Exceptions:
        //  Try           Handler
        //  Start  End    Start  End    Type                                       
        //  -----  -----  -----  -----  -------------------------------------------
        //  8      20     1087   1095   Any
        //  1087   1095   1087   1095   Any
        //  1103   1105   3      8      Ljava/lang/IndexOutOfBoundsException;
        //  28     35     35     36     Any
        //  28     35     28     29     Ljava/lang/ArithmeticException;
        //  28     35     28     29     Ljava/lang/IllegalStateException;
        //  29     35     28     29     Any
        //  28     35     3      8      Any
        //  135    142    142    143    Any
        //  136    142    3      8      Ljava/lang/RuntimeException;
        //  136    142    3      8      Ljava/lang/IllegalStateException;
        //  135    142    142    143    Any
        //  136    142    135    136    Any
        //  196    203    203    204    Any
        //  196    203    196    197    Ljava/lang/IndexOutOfBoundsException;
        //  196    203    196    197    Any
        //  197    203    196    197    Ljava/lang/IndexOutOfBoundsException;
        //  197    203    203    204    Ljava/lang/RuntimeException;
        //  255    262    262    263    Any
        //  255    262    262    263    Ljava/lang/AssertionError;
        //  255    262    262    263    Ljava/lang/StringIndexOutOfBoundsException;
        //  256    262    262    263    Ljava/lang/StringIndexOutOfBoundsException;
        //  256    262    255    256    Ljava/lang/NumberFormatException;
        //  547    554    554    555    Any
        //  548    554    3      8      Ljava/util/NoSuchElementException;
        //  547    554    547    548    Any
        //  547    554    3      8      Any
        //  548    554    554    555    Any
        //  607    614    614    615    Any
        //  608    614    607    608    Any
        //  607    614    3      8      Ljava/lang/EnumConstantNotPresentException;
        //  607    614    607    608    Ljava/lang/ArrayIndexOutOfBoundsException;
        //  608    614    607    608    Ljava/util/ConcurrentModificationException;
        //  720    726    726    727    Any
        //  720    726    726    727    Ljava/lang/ArithmeticException;
        //  720    726    3      8      Any
        //  720    726    3      8      Ljava/lang/EnumConstantNotPresentException;
        //  720    726    726    727    Any
        //  735    742    742    743    Any
        //  735    742    735    736    Ljava/lang/StringIndexOutOfBoundsException;
        //  735    742    735    736    Any
        //  736    742    735    736    Any
        //  736    742    3      8      Any
        //  757    763    763    764    Any
        //  757    763    3      8      Ljava/lang/EnumConstantNotPresentException;
        //  757    763    763    764    Any
        //  757    763    3      8      Ljava/lang/ArrayIndexOutOfBoundsException;
        //  757    763    3      8      Ljava/lang/ClassCastException;
        //  863    870    870    871    Any
        //  864    870    863    864    Ljava/util/ConcurrentModificationException;
        //  863    870    3      8      Any
        //  864    870    3      8      Any
        //  864    870    870    871    Any
        //  973    979    979    980    Any
        //  973    979    3      8      Ljava/lang/UnsupportedOperationException;
        //  973    979    3      8      Any
        //  973    979    3      8      Ljava/lang/ArrayIndexOutOfBoundsException;
        //  973    979    979    980    Ljava/lang/RuntimeException;
        //  1035   1042   1042   1043   Any
        //  1035   1042   1035   1036   Ljava/lang/IndexOutOfBoundsException;
        //  1035   1042   1035   1036   Any
        //  1036   1042   1035   1036   Ljava/lang/StringIndexOutOfBoundsException;
        //  1035   1042   1035   1036   Any
        // 
        // The error that occurred was:
        // 
        // java.lang.IndexOutOfBoundsException: Index -1 out of bounds for length 0
        //     at java.base/jdk.internal.util.Preconditions.outOfBounds(Preconditions.java:64)
        //     at java.base/jdk.internal.util.Preconditions.outOfBoundsCheckIndex(Preconditions.java:70)
        //     at java.base/jdk.internal.util.Preconditions.checkIndex(Preconditions.java:248)
        //     at java.base/java.util.Objects.checkIndex(Objects.java:372)
        //     at java.base/java.util.ArrayList.remove(ArrayList.java:535)
        //     at com.strobel.assembler.ir.StackMappingVisitor.pop(StackMappingVisitor.java:267)
        //     at com.strobel.assembler.ir.StackMappingVisitor$InstructionAnalyzer.execute(StackMappingVisitor.java:577)
        //     at com.strobel.assembler.ir.StackMappingVisitor$InstructionAnalyzer.visit(StackMappingVisitor.java:398)
        //     at com.strobel.decompiler.ast.AstBuilder.performStackAnalysis(AstBuilder.java:2030)
        //     at com.strobel.decompiler.ast.AstBuilder.build(AstBuilder.java:108)
        //     at com.strobel.decompiler.languages.java.ast.AstMethodBodyBuilder.createMethodBody(AstMethodBodyBuilder.java:211)
        //     at com.strobel.decompiler.languages.java.ast.AstMethodBodyBuilder.createMethodBody(AstMethodBodyBuilder.java:99)
        //     at com.strobel.decompiler.languages.java.ast.AstBuilder.createMethodBody(AstBuilder.java:782)
        //     at com.strobel.decompiler.languages.java.ast.AstBuilder.createMethod(AstBuilder.java:675)
        //     at com.strobel.decompiler.languages.java.ast.AstBuilder.addTypeMembers(AstBuilder.java:552)
        //     at com.strobel.decompiler.languages.java.ast.AstBuilder.createTypeCore(AstBuilder.java:519)
        //     at com.strobel.decompiler.languages.java.ast.AstBuilder.createTypeNoCache(AstBuilder.java:161)
        //     at com.strobel.decompiler.languages.java.ast.AstBuilder.createType(AstBuilder.java:150)
        //     at com.strobel.decompiler.languages.java.ast.AstBuilder.addType(AstBuilder.java:125)
        //     at com.strobel.decompiler.languages.java.JavaLanguage.buildAst(JavaLanguage.java:71)
        //     at com.strobel.decompiler.languages.java.JavaLanguage.decompileType(JavaLanguage.java:59)
        //     at com.strobel.decompiler.DecompilerDriver.decompileType(DecompilerDriver.java:330)
        //     at com.strobel.decompiler.DecompilerDriver.decompileJar(DecompilerDriver.java:251)
        //     at com.strobel.decompiler.DecompilerDriver.main(DecompilerDriver.java:126)
        // 
        throw new IllegalStateException("An error occurred while decompiling this method.");
    }
    
    static {
        final int 1 = 30000;
        while (true) {
            int n = 0;
            Label_0018: {
                if (fc.0 != 0) {
                    n = 1568136227;
                    break Label_0018;
                }
                n = 1391654776;
            }
            switch (n ^ 0xFE5E6349) {
                case -1557545110: {
                    continue;
                }
                case -1397976015: {
                    fbE.1 = 1;
                    fbE.0 = 600;
                    fbE.c = false;
                    while (true) {
                        int n2 = 0;
                        Label_0080: {
                            if (fc.1 != 0) {
                                n2 = -18369423;
                                break Label_0080;
                            }
                            n2 = 1387400684;
                        }
                        switch (n2 ^ 0x876248FF) {
                            case -644617829: {
                                continue;
                            }
                            default: {
                                final ArrayList<fbE> c = new ArrayList<fbE>();
                                while (true) {
                                    int n3 = 0;
                                    Label_0130: {
                                        if (fc.0 != 0) {
                                            n3 = -1833302158;
                                            break Label_0130;
                                        }
                                        n3 = 2080021267;
                                    }
                                    switch (n3 ^ 0x5F27DAC3) {
                                        case -845292111: {
                                            continue;
                                        }
                                        case 618480080: {
                                            fbE.c = c;
                                            fbE.c = 0;
                                            return;
                                        }
                                        default: {
                                            throw null;
                                        }
                                    }
                                    break;
                                }
                                break;
                            }
                            case 2038824078: {
                                throw null;
                            }
                        }
                        break;
                    }
                    break;
                }
                default: {
                    throw null;
                }
            }
            break;
        }
    }
    
    public BufferedImage c(final char p0) {
        // 
        // This method could not be decompiled.
        // 
        // Original Bytecode:
        // 
        //     3: dup            
        //     4: ifnull          843
        //     7: athrow         
        //     8: aconst_null    
        //     9: getstatic       dev/nuker/pyro/fc.1:I
        //    12: ifgt            835
        //    15: pop            
        //    16: aconst_null    
        //    17: goto            827
        //    20: nop            
        //    21: nop            
        //    22: nop            
        //    23: athrow         
        //    24: new             Ljava/awt/image/BufferedImage;
        //    27: dup            
        //    28: iconst_1       
        //    29: iconst_1       
        //    30: iconst_2       
        //    31: goto            35
        //    34: athrow         
        //    35: invokespecial   java/awt/image/BufferedImage.<init>:(III)V
        //    38: goto            42
        //    41: athrow         
        //    42: goto            46
        //    45: athrow         
        //    46: invokevirtual   java/awt/image/BufferedImage.getGraphics:()Ljava/awt/Graphics;
        //    49: goto            53
        //    52: athrow         
        //    53: checkcast       Ljava/awt/Graphics2D;
        //    56: astore_2       
        //    57: aload_2        
        //    58: getstatic       java/awt/RenderingHints.KEY_TEXT_ANTIALIASING:Ljava/awt/RenderingHints$Key;
        //    61: getstatic       dev/nuker/pyro/fc.c:I
        //    64: ifge            73
        //    67: ldc_w           404184722
        //    70: goto            76
        //    73: ldc_w           657550773
        //    76: ldc_w           720820424
        //    79: ixor           
        //    80: lookupswitch {
        //          366390871: 73
        //          853640794: 800
        //          default: 108
        //        }
        //   108: getstatic       java/awt/RenderingHints.VALUE_TEXT_ANTIALIAS_ON:Ljava/lang/Object;
        //   111: goto            115
        //   114: athrow         
        //   115: invokevirtual   java/awt/Graphics2D.setRenderingHint:(Ljava/awt/RenderingHints$Key;Ljava/lang/Object;)V
        //   118: goto            122
        //   121: athrow         
        //   122: aload_2        
        //   123: aload_0        
        //   124: getfield        dev/nuker/pyro/fbE.c:Ljava/awt/Font;
        //   127: goto            131
        //   130: athrow         
        //   131: invokevirtual   java/awt/Graphics2D.setFont:(Ljava/awt/Font;)V
        //   134: goto            138
        //   137: athrow         
        //   138: aload_2        
        //   139: goto            143
        //   142: athrow         
        //   143: invokevirtual   java/awt/Graphics2D.getFontMetrics:()Ljava/awt/FontMetrics;
        //   146: goto            150
        //   149: athrow         
        //   150: astore_3       
        //   151: aload_3        
        //   152: iload_1        
        //   153: goto            157
        //   156: athrow         
        //   157: invokevirtual   java/awt/FontMetrics.charWidth:(C)I
        //   160: goto            164
        //   163: athrow         
        //   164: bipush          8
        //   166: iadd           
        //   167: istore          4
        //   169: iload           4
        //   171: bipush          8
        //   173: if_icmpgt       182
        //   176: ldc_w           912669363
        //   179: goto            185
        //   182: ldc_w           912669360
        //   185: ldc_w           276691742
        //   188: ixor           
        //   189: tableswitch {
        //          1278706522: 212
        //          1278706523: 262
        //          default: 176
        //        }
        //   212: bipush          7
        //   214: getstatic       dev/nuker/pyro/fc.0:I
        //   217: ifeq            226
        //   220: ldc_w           -562654905
        //   223: goto            229
        //   226: ldc_w           -1533087806
        //   229: ldc_w           285205842
        //   232: ixor           
        //   233: lookupswitch {
        //          -2016660773: 226
        //          -829852651: 806
        //          default: 260
        //        }
        //   260: istore          4
        //   262: aload_3        
        //   263: goto            267
        //   266: athrow         
        //   267: invokevirtual   java/awt/FontMetrics.getHeight:()I
        //   270: goto            274
        //   273: athrow         
        //   274: iconst_3       
        //   275: iadd           
        //   276: istore          5
        //   278: iload           5
        //   280: ifgt            345
        //   283: getstatic       dev/nuker/pyro/fc.0:I
        //   286: ifeq            295
        //   289: ldc_w           -971112561
        //   292: goto            298
        //   295: ldc_w           1692365095
        //   298: ldc_w           1618434697
        //   301: ixor           
        //   302: lookupswitch {
        //          -1502960378: 808
        //          -993703155: 295
        //          default: 328
        //        }
        //   328: aload_0        
        //   329: getfield        dev/nuker/pyro/fbE.c:Ljava/awt/Font;
        //   332: goto            336
        //   335: athrow         
        //   336: invokevirtual   java/awt/Font.getSize:()I
        //   339: goto            343
        //   342: athrow         
        //   343: istore          5
        //   345: new             Ljava/awt/image/BufferedImage;
        //   348: dup            
        //   349: iload           4
        //   351: iload           5
        //   353: iconst_2       
        //   354: goto            358
        //   357: athrow         
        //   358: invokespecial   java/awt/image/BufferedImage.<init>:(III)V
        //   361: goto            365
        //   364: athrow         
        //   365: astore          6
        //   367: getstatic       dev/nuker/pyro/fc.1:I
        //   370: ifeq            379
        //   373: ldc_w           -339476347
        //   376: goto            382
        //   379: ldc_w           1012573959
        //   382: ldc_w           1069703594
        //   385: ixor           
        //   386: lookupswitch {
        //          -1556817153: 379
        //          -737779409: 804
        //          default: 412
        //        }
        //   412: aload           6
        //   414: getstatic       dev/nuker/pyro/fc.1:I
        //   417: ifeq            426
        //   420: ldc_w           -1726529332
        //   423: goto            429
        //   426: ldc_w           -2104268629
        //   429: ldc_w           936104097
        //   432: ixor           
        //   433: lookupswitch {
        //          -1361276819: 798
        //          -858144406: 426
        //          default: 460
        //        }
        //   460: goto            464
        //   463: athrow         
        //   464: invokevirtual   java/awt/image/BufferedImage.getGraphics:()Ljava/awt/Graphics;
        //   467: goto            471
        //   470: athrow         
        //   471: checkcast       Ljava/awt/Graphics2D;
        //   474: astore          7
        //   476: getstatic       dev/nuker/pyro/fc.0:I
        //   479: ifeq            488
        //   482: ldc_w           -1626287116
        //   485: goto            491
        //   488: ldc_w           -2045893252
        //   491: ldc_w           -1534763532
        //   494: ixor           
        //   495: lookupswitch {
        //          -1381542512: 488
        //          999656960: 810
        //          default: 520
        //        }
        //   520: aload           7
        //   522: getstatic       java/awt/RenderingHints.KEY_TEXT_ANTIALIASING:Ljava/awt/RenderingHints$Key;
        //   525: getstatic       dev/nuker/pyro/fc.c:I
        //   528: ifge            537
        //   531: ldc_w           1805228280
        //   534: goto            540
        //   537: ldc_w           -207399286
        //   540: ldc_w           150025140
        //   543: ixor           
        //   544: lookupswitch {
        //          -1894486490: 537
        //          1667803980: 814
        //          default: 572
        //        }
        //   572: getstatic       java/awt/RenderingHints.VALUE_TEXT_ANTIALIAS_ON:Ljava/lang/Object;
        //   575: getstatic       dev/nuker/pyro/fc.1:I
        //   578: ifeq            587
        //   581: ldc_w           -903289035
        //   584: goto            590
        //   587: ldc_w           874833903
        //   590: ldc_w           2090558801
        //   593: ixor           
        //   594: lookupswitch {
        //          -1229749660: 802
        //          1953013024: 587
        //          default: 620
        //        }
        //   620: goto            624
        //   623: athrow         
        //   624: invokevirtual   java/awt/Graphics2D.setRenderingHint:(Ljava/awt/RenderingHints$Key;Ljava/lang/Object;)V
        //   627: goto            631
        //   630: athrow         
        //   631: aload           7
        //   633: aload_0        
        //   634: getfield        dev/nuker/pyro/fbE.c:Ljava/awt/Font;
        //   637: goto            641
        //   640: athrow         
        //   641: invokevirtual   java/awt/Graphics2D.setFont:(Ljava/awt/Font;)V
        //   644: goto            648
        //   647: athrow         
        //   648: aload           7
        //   650: getstatic       java/awt/Color.WHITE:Ljava/awt/Color;
        //   653: goto            657
        //   656: athrow         
        //   657: invokevirtual   java/awt/Graphics2D.setColor:(Ljava/awt/Color;)V
        //   660: goto            664
        //   663: athrow         
        //   664: aload           7
        //   666: iload_1        
        //   667: getstatic       dev/nuker/pyro/fc.c:I
        //   670: ifge            679
        //   673: ldc_w           1622420304
        //   676: goto            682
        //   679: ldc_w           367192742
        //   682: ldc_w           2139941697
        //   685: ixor           
        //   686: lookupswitch {
        //          394944334: 679
        //          523812881: 812
        //          default: 712
        //        }
        //   712: goto            716
        //   715: athrow         
        //   716: invokestatic    java/lang/String.valueOf:(C)Ljava/lang/String;
        //   719: goto            723
        //   722: athrow         
        //   723: iconst_3       
        //   724: iconst_1       
        //   725: aload_3        
        //   726: goto            730
        //   729: athrow         
        //   730: invokevirtual   java/awt/FontMetrics.getAscent:()I
        //   733: goto            737
        //   736: athrow         
        //   737: iadd           
        //   738: getstatic       dev/nuker/pyro/fc.1:I
        //   741: ifeq            750
        //   744: ldc_w           -1652045563
        //   747: goto            753
        //   750: ldc_w           1841635301
        //   753: ldc_w           1963308519
        //   756: ixor           
        //   757: lookupswitch {
        //          -394101534: 750
        //          415279618: 784
        //          default: 816
        //        }
        //   784: goto            788
        //   787: athrow         
        //   788: invokevirtual   java/awt/Graphics2D.drawString:(Ljava/lang/String;II)V
        //   791: goto            795
        //   794: athrow         
        //   795: aload           6
        //   797: areturn        
        //   798: aconst_null    
        //   799: athrow         
        //   800: aconst_null    
        //   801: athrow         
        //   802: aconst_null    
        //   803: athrow         
        //   804: aconst_null    
        //   805: athrow         
        //   806: aconst_null    
        //   807: athrow         
        //   808: aconst_null    
        //   809: athrow         
        //   810: aconst_null    
        //   811: athrow         
        //   812: aconst_null    
        //   813: athrow         
        //   814: aconst_null    
        //   815: athrow         
        //   816: aconst_null    
        //   817: athrow         
        //   818: pop            
        //   819: goto            24
        //   822: pop            
        //   823: aconst_null    
        //   824: goto            818
        //   827: dup            
        //   828: ifnull          818
        //   831: checkcast       Ljava/lang/Throwable;
        //   834: athrow         
        //   835: dup            
        //   836: ifnull          822
        //   839: checkcast       Ljava/lang/Throwable;
        //   842: athrow         
        //   843: aconst_null    
        //   844: athrow         
        //    StackMapTable: 00 77 43 07 00 A9 04 FF 00 0B 00 00 00 01 07 00 A9 FD 00 03 07 00 03 01 49 07 00 8F FF 00 00 00 02 07 00 03 01 00 05 08 00 18 08 00 18 01 01 01 45 07 00 A9 40 07 00 AB 42 07 00 A9 40 07 00 AB 45 07 00 A9 40 07 01 4A FF 00 13 00 03 07 00 03 01 07 00 FC 00 02 07 00 FC 07 02 EF FF 00 02 00 03 07 00 03 01 07 00 FC 00 03 07 00 FC 07 02 EF 01 FF 00 1F 00 03 07 00 03 01 07 00 FC 00 02 07 00 FC 07 02 EF FF 00 05 00 00 00 01 07 00 A9 FF 00 00 00 03 07 00 03 01 07 00 FC 00 03 07 00 FC 07 02 EF 07 00 05 45 07 00 A9 00 47 07 00 A9 FF 00 00 00 03 07 00 03 01 07 00 FC 00 02 07 00 FC 07 00 80 45 07 00 A9 00 43 07 00 A9 40 07 00 FC 45 07 00 A9 40 07 02 C1 FF 00 05 00 04 07 00 03 01 07 00 FC 07 02 C1 00 01 07 00 A9 FF 00 00 00 04 07 00 03 01 07 00 FC 07 02 C1 00 02 07 02 C1 01 45 07 00 A9 40 01 FC 00 0B 01 05 42 01 1A 4D 01 FF 00 02 00 05 07 00 03 01 07 00 FC 07 02 C1 01 00 02 01 01 5E 01 01 43 07 00 8F 40 07 02 C1 45 07 00 A9 40 01 FC 00 14 01 42 01 1D FF 00 06 00 00 00 01 07 00 A9 FF 00 00 00 06 07 00 03 01 07 00 FC 07 02 C1 01 01 00 01 07 00 80 45 07 00 A9 40 01 01 FF 00 0B 00 00 00 01 07 00 A9 FF 00 00 00 06 07 00 03 01 07 00 FC 07 02 C1 01 01 00 05 08 01 59 08 01 59 01 01 01 45 07 00 A9 40 07 00 AB FC 00 0D 07 00 AB 42 01 1D 4D 07 00 AB FF 00 02 00 07 07 00 03 01 07 00 FC 07 02 C1 01 01 07 00 AB 00 02 07 00 AB 01 5E 07 00 AB 42 07 00 A9 40 07 00 AB 45 07 00 A9 40 07 01 4A FC 00 10 07 00 FC 42 01 1C FF 00 10 00 08 07 00 03 01 07 00 FC 07 02 C1 01 01 07 00 AB 07 00 FC 00 02 07 00 FC 07 02 EF FF 00 02 00 08 07 00 03 01 07 00 FC 07 02 C1 01 01 07 00 AB 07 00 FC 00 03 07 00 FC 07 02 EF 01 FF 00 1F 00 08 07 00 03 01 07 00 FC 07 02 C1 01 01 07 00 AB 07 00 FC 00 02 07 00 FC 07 02 EF FF 00 0E 00 08 07 00 03 01 07 00 FC 07 02 C1 01 01 07 00 AB 07 00 FC 00 03 07 00 FC 07 02 EF 07 00 05 FF 00 02 00 08 07 00 03 01 07 00 FC 07 02 C1 01 01 07 00 AB 07 00 FC 00 04 07 00 FC 07 02 EF 07 00 05 01 FF 00 1D 00 08 07 00 03 01 07 00 FC 07 02 C1 01 01 07 00 AB 07 00 FC 00 03 07 00 FC 07 02 EF 07 00 05 FF 00 02 00 00 00 01 07 00 A9 FF 00 00 00 08 07 00 03 01 07 00 FC 07 02 C1 01 01 07 00 AB 07 00 FC 00 03 07 00 FC 07 02 EF 07 00 05 45 07 00 A9 00 FF 00 08 00 00 00 01 07 00 A9 FF 00 00 00 08 07 00 03 01 07 00 FC 07 02 C1 01 01 07 00 AB 07 00 FC 00 02 07 00 FC 07 00 80 45 07 00 A9 00 FF 00 07 00 00 00 01 07 00 A9 FF 00 00 00 08 07 00 03 01 07 00 FC 07 02 C1 01 01 07 00 AB 07 00 FC 00 02 07 00 FC 07 01 0B 45 07 00 A9 00 FF 00 0E 00 08 07 00 03 01 07 00 FC 07 02 C1 01 01 07 00 AB 07 00 FC 00 02 07 00 FC 01 FF 00 02 00 08 07 00 03 01 07 00 FC 07 02 C1 01 01 07 00 AB 07 00 FC 00 03 07 00 FC 01 01 FF 00 1D 00 08 07 00 03 01 07 00 FC 07 02 C1 01 01 07 00 AB 07 00 FC 00 02 07 00 FC 01 42 07 00 A9 FF 00 00 00 08 07 00 03 01 07 00 FC 07 02 C1 01 01 07 00 AB 07 00 FC 00 02 07 00 FC 01 45 07 00 A9 FF 00 00 00 08 07 00 03 01 07 00 FC 07 02 C1 01 01 07 00 AB 07 00 FC 00 02 07 00 FC 07 01 F4 45 07 00 A9 FF 00 00 00 08 07 00 03 01 07 00 FC 07 02 C1 01 01 07 00 AB 07 00 FC 00 05 07 00 FC 07 01 F4 01 01 07 02 C1 45 07 00 A9 FF 00 00 00 08 07 00 03 01 07 00 FC 07 02 C1 01 01 07 00 AB 07 00 FC 00 05 07 00 FC 07 01 F4 01 01 01 FF 00 0C 00 08 07 00 03 01 07 00 FC 07 02 C1 01 01 07 00 AB 07 00 FC 00 04 07 00 FC 07 01 F4 01 01 FF 00 02 00 08 07 00 03 01 07 00 FC 07 02 C1 01 01 07 00 AB 07 00 FC 00 05 07 00 FC 07 01 F4 01 01 01 FF 00 1E 00 08 07 00 03 01 07 00 FC 07 02 C1 01 01 07 00 AB 07 00 FC 00 04 07 00 FC 07 01 F4 01 01 FF 00 02 00 00 00 01 07 00 A9 FF 00 00 00 08 07 00 03 01 07 00 FC 07 02 C1 01 01 07 00 AB 07 00 FC 00 04 07 00 FC 07 01 F4 01 01 45 07 00 A9 00 FF 00 02 00 07 07 00 03 01 07 00 FC 07 02 C1 01 01 07 00 AB 00 01 07 00 AB FF 00 01 00 03 07 00 03 01 07 00 FC 00 02 07 00 FC 07 02 EF FF 00 01 00 08 07 00 03 01 07 00 FC 07 02 C1 01 01 07 00 AB 07 00 FC 00 03 07 00 FC 07 02 EF 07 00 05 FA 00 01 FF 00 01 00 05 07 00 03 01 07 00 FC 07 02 C1 01 00 01 01 FC 00 01 01 FD 00 01 07 00 AB 07 00 FC FF 00 01 00 08 07 00 03 01 07 00 FC 07 02 C1 01 01 07 00 AB 07 00 FC 00 02 07 00 FC 01 FF 00 01 00 08 07 00 03 01 07 00 FC 07 02 C1 01 01 07 00 AB 07 00 FC 00 02 07 00 FC 07 02 EF FF 00 01 00 08 07 00 03 01 07 00 FC 07 02 C1 01 01 07 00 AB 07 00 FC 00 04 07 00 FC 07 01 F4 01 01 FF 00 01 00 02 07 00 03 01 00 01 07 00 A9 43 05 44 07 00 A9 47 05 47 07 00 A9
        //    Exceptions:
        //  Try           Handler
        //  Start  End    Start  End    Type                                       
        //  -----  -----  -----  -----  -------------------------------------------
        //  8      20     827    835    Ljava/lang/AssertionError;
        //  827    835    827    835    Ljava/lang/RuntimeException;
        //  843    845    3      8      Any
        //  34     41     41     42     Any
        //  34     41     3      8      Ljava/lang/StringIndexOutOfBoundsException;
        //  35     41     34     35     Ljava/lang/ArithmeticException;
        //  34     41     41     42     Any
        //  35     41     34     35     Ljava/lang/NegativeArraySizeException;
        //  45     52     52     53     Any
        //  46     52     3      8      Any
        //  45     52     45     46     Ljava/lang/NullPointerException;
        //  46     52     45     46     Any
        //  45     52     3      8      Ljava/lang/RuntimeException;
        //  115    121    121    122    Any
        //  115    121    121    122    Ljava/lang/NegativeArraySizeException;
        //  115    121    121    122    Any
        //  115    121    3      8      Any
        //  115    121    121    122    Ljava/util/NoSuchElementException;
        //  130    137    137    138    Any
        //  130    137    137    138    Any
        //  131    137    137    138    Any
        //  131    137    130    131    Any
        //  130    137    3      8      Ljava/util/ConcurrentModificationException;
        //  142    149    149    150    Any
        //  143    149    142    143    Any
        //  143    149    149    150    Any
        //  143    149    149    150    Ljava/lang/NegativeArraySizeException;
        //  143    149    149    150    Ljava/lang/RuntimeException;
        //  156    163    163    164    Any
        //  156    163    3      8      Ljava/lang/NegativeArraySizeException;
        //  157    163    3      8      Any
        //  156    163    156    157    Any
        //  157    163    163    164    Ljava/lang/ClassCastException;
        //  266    273    273    274    Any
        //  267    273    273    274    Any
        //  266    273    266    267    Ljava/lang/ArithmeticException;
        //  267    273    273    274    Any
        //  266    273    266    267    Ljava/util/ConcurrentModificationException;
        //  336    342    342    343    Any
        //  336    342    342    343    Ljava/lang/NumberFormatException;
        //  336    342    342    343    Any
        //  336    342    342    343    Ljava/lang/EnumConstantNotPresentException;
        //  336    342    342    343    Any
        //  358    364    364    365    Any
        //  358    364    3      8      Ljava/lang/EnumConstantNotPresentException;
        //  358    364    3      8      Ljava/lang/RuntimeException;
        //  358    364    364    365    Ljava/util/ConcurrentModificationException;
        //  358    364    364    365    Any
        //  463    470    470    471    Any
        //  463    470    3      8      Any
        //  463    470    463    464    Any
        //  463    470    3      8      Ljava/lang/UnsupportedOperationException;
        //  463    470    3      8      Ljava/lang/IndexOutOfBoundsException;
        //  624    630    630    631    Any
        //  624    630    630    631    Any
        //  624    630    3      8      Any
        //  624    630    630    631    Any
        //  624    630    630    631    Ljava/lang/IllegalStateException;
        //  641    647    647    648    Any
        //  641    647    647    648    Any
        //  641    647    647    648    Ljava/lang/AssertionError;
        //  641    647    647    648    Any
        //  641    647    3      8      Ljava/lang/AssertionError;
        //  657    663    663    664    Any
        //  657    663    3      8      Ljava/lang/StringIndexOutOfBoundsException;
        //  657    663    663    664    Ljava/lang/NegativeArraySizeException;
        //  657    663    663    664    Ljava/lang/NumberFormatException;
        //  657    663    663    664    Any
        //  715    722    722    723    Any
        //  715    722    3      8      Any
        //  716    722    715    716    Ljava/lang/NumberFormatException;
        //  715    722    715    716    Any
        //  715    722    3      8      Any
        //  729    736    736    737    Any
        //  730    736    3      8      Ljava/lang/IndexOutOfBoundsException;
        //  730    736    3      8      Ljava/lang/IndexOutOfBoundsException;
        //  730    736    736    737    Any
        //  730    736    729    730    Any
        //  788    794    794    795    Any
        //  788    794    3      8      Ljava/lang/EnumConstantNotPresentException;
        //  788    794    3      8      Any
        //  788    794    3      8      Ljava/lang/NegativeArraySizeException;
        //  788    794    794    795    Any
        // 
        // The error that occurred was:
        // 
        // java.lang.IndexOutOfBoundsException: Index -1 out of bounds for length 0
        //     at java.base/jdk.internal.util.Preconditions.outOfBounds(Preconditions.java:64)
        //     at java.base/jdk.internal.util.Preconditions.outOfBoundsCheckIndex(Preconditions.java:70)
        //     at java.base/jdk.internal.util.Preconditions.checkIndex(Preconditions.java:248)
        //     at java.base/java.util.Objects.checkIndex(Objects.java:372)
        //     at java.base/java.util.ArrayList.remove(ArrayList.java:535)
        //     at com.strobel.assembler.ir.StackMappingVisitor.pop(StackMappingVisitor.java:267)
        //     at com.strobel.assembler.ir.StackMappingVisitor$InstructionAnalyzer.execute(StackMappingVisitor.java:776)
        //     at com.strobel.assembler.ir.StackMappingVisitor$InstructionAnalyzer.visit(StackMappingVisitor.java:398)
        //     at com.strobel.decompiler.ast.AstBuilder.performStackAnalysis(AstBuilder.java:2030)
        //     at com.strobel.decompiler.ast.AstBuilder.build(AstBuilder.java:108)
        //     at com.strobel.decompiler.languages.java.ast.AstMethodBodyBuilder.createMethodBody(AstMethodBodyBuilder.java:211)
        //     at com.strobel.decompiler.languages.java.ast.AstMethodBodyBuilder.createMethodBody(AstMethodBodyBuilder.java:99)
        //     at com.strobel.decompiler.languages.java.ast.AstBuilder.createMethodBody(AstBuilder.java:782)
        //     at com.strobel.decompiler.languages.java.ast.AstBuilder.createMethod(AstBuilder.java:675)
        //     at com.strobel.decompiler.languages.java.ast.AstBuilder.addTypeMembers(AstBuilder.java:552)
        //     at com.strobel.decompiler.languages.java.ast.AstBuilder.createTypeCore(AstBuilder.java:519)
        //     at com.strobel.decompiler.languages.java.ast.AstBuilder.createTypeNoCache(AstBuilder.java:161)
        //     at com.strobel.decompiler.languages.java.ast.AstBuilder.createType(AstBuilder.java:150)
        //     at com.strobel.decompiler.languages.java.ast.AstBuilder.addType(AstBuilder.java:125)
        //     at com.strobel.decompiler.languages.java.JavaLanguage.buildAst(JavaLanguage.java:71)
        //     at com.strobel.decompiler.languages.java.JavaLanguage.decompileType(JavaLanguage.java:59)
        //     at com.strobel.decompiler.DecompilerDriver.decompileType(DecompilerDriver.java:330)
        //     at com.strobel.decompiler.DecompilerDriver.decompileJar(DecompilerDriver.java:251)
        //     at com.strobel.decompiler.DecompilerDriver.main(DecompilerDriver.java:126)
        // 
        throw new IllegalStateException("An error occurred while decompiling this method.");
    }
    
    public fbE(final Font font) {
        this(font, 0, 255);
    }
}
