// 
// Decompiled by Procyon v0.5.36
// 

package dev.nuker.pyro;

import net.minecraft.entity.Entity;

public class fbM extends fbk
{
    public static Entity c(final double p0, final fbL p1) {
        // 
        // This method could not be decompiled.
        // 
        // Original Bytecode:
        // 
        //     3: dup            
        //     4: ifnull          156
        //     7: athrow         
        //     8: aconst_null    
        //     9: getstatic       dev/nuker/pyro/fc.1:I
        //    12: ifgt            148
        //    15: pop            
        //    16: aconst_null    
        //    17: goto            140
        //    20: nop            
        //    21: nop            
        //    22: nop            
        //    23: athrow         
        //    24: dload_0        
        //    25: goto            29
        //    28: athrow         
        //    29: invokestatic    dev/nuker/pyro/fbP.1:()Ldev/nuker/pyro/fbP;
        //    32: goto            36
        //    35: athrow         
        //    36: getfield        dev/nuker/pyro/fbP.0:Ldev/nuker/pyro/fbN;
        //    39: getstatic       dev/nuker/pyro/fc.c:I
        //    42: ifge            50
        //    45: ldc             -1268794131
        //    47: goto            52
        //    50: ldc             1751330818
        //    52: ldc             -1088956948
        //    54: ixor           
        //    55: lookupswitch {
        //          -680204818: 80
        //          189294849: 50
        //          default: 129
        //        }
        //    80: goto            84
        //    83: athrow         
        //    84: invokevirtual   dev/nuker/pyro/fbN.c:()F
        //    87: goto            91
        //    90: athrow         
        //    91: goto            95
        //    94: athrow         
        //    95: invokestatic    dev/nuker/pyro/fbP.1:()Ldev/nuker/pyro/fbP;
        //    98: goto            102
        //   101: athrow         
        //   102: getfield        dev/nuker/pyro/fbP.0:Ldev/nuker/pyro/fbN;
        //   105: goto            109
        //   108: athrow         
        //   109: invokevirtual   dev/nuker/pyro/fbN.2:()F
        //   112: goto            116
        //   115: athrow         
        //   116: aload_2        
        //   117: goto            121
        //   120: athrow         
        //   121: invokestatic    dev/nuker/pyro/fbM.c:(DFFLdev/nuker/pyro/fbL;)Lnet/minecraft/entity/Entity;
        //   124: goto            128
        //   127: athrow         
        //   128: areturn        
        //   129: aconst_null    
        //   130: athrow         
        //   131: pop            
        //   132: goto            24
        //   135: pop            
        //   136: aconst_null    
        //   137: goto            131
        //   140: dup            
        //   141: ifnull          131
        //   144: checkcast       Ljava/lang/Throwable;
        //   147: athrow         
        //   148: dup            
        //   149: ifnull          135
        //   152: checkcast       Ljava/lang/Throwable;
        //   155: athrow         
        //   156: aconst_null    
        //   157: athrow         
        //    StackMapTable: 00 21 43 07 00 1F 04 FF 00 0B 00 00 00 01 07 00 1F FD 00 03 03 07 00 3A FF 00 03 00 00 00 01 07 00 1F FF 00 00 00 02 03 07 00 3A 00 01 03 45 07 00 1F FF 00 00 00 02 03 07 00 3A 00 02 03 07 00 21 FF 00 0D 00 02 03 07 00 3A 00 02 03 07 00 2F FF 00 01 00 02 03 07 00 3A 00 03 03 07 00 2F 01 FF 00 1B 00 02 03 07 00 3A 00 02 03 07 00 2F 42 07 00 1F FF 00 00 00 02 03 07 00 3A 00 02 03 07 00 2F 45 07 00 1F FF 00 00 00 02 03 07 00 3A 00 02 03 02 FF 00 02 00 00 00 01 07 00 1F FF 00 00 00 02 03 07 00 3A 00 02 03 02 45 07 00 1F FF 00 00 00 02 03 07 00 3A 00 03 03 02 07 00 21 45 07 00 1F FF 00 00 00 02 03 07 00 3A 00 03 03 02 07 00 2F 45 07 00 1F FF 00 00 00 02 03 07 00 3A 00 03 03 02 02 43 07 00 1F FF 00 00 00 02 03 07 00 3A 00 04 03 02 02 07 00 3A 45 07 00 1F 40 07 00 3C FF 00 00 00 02 03 07 00 3A 00 02 03 07 00 2F 41 07 00 3E 43 05 44 07 00 3E 47 05 47 07 00 1F
        //    Exceptions:
        //  Try           Handler
        //  Start  End    Start  End    Type                                       
        //  -----  -----  -----  -----  -------------------------------------------
        //  8      20     140    148    Ljava/lang/ClassCastException;
        //  140    148    140    148    Ljava/lang/EnumConstantNotPresentException;
        //  156    158    3      8      Any
        //  29     35     35     36     Any
        //  29     35     3      8      Any
        //  29     35     35     36     Any
        //  29     35     35     36     Any
        //  29     35     35     36     Ljava/util/NoSuchElementException;
        //  83     90     90     91     Any
        //  83     90     83     84     Any
        //  83     90     3      8      Any
        //  83     90     90     91     Ljava/lang/IllegalArgumentException;
        //  84     90     83     84     Ljava/lang/ArithmeticException;
        //  95     101    101    102    Any
        //  95     101    101    102    Any
        //  95     101    3      8      Any
        //  95     101    101    102    Ljava/lang/NegativeArraySizeException;
        //  95     101    3      8      Ljava/lang/NumberFormatException;
        //  108    115    115    116    Any
        //  108    115    108    109    Any
        //  108    115    115    116    Ljava/lang/ArrayIndexOutOfBoundsException;
        //  109    115    108    109    Any
        //  108    115    108    109    Any
        //  120    127    127    128    Any
        //  121    127    127    128    Any
        //  120    127    120    121    Any
        //  120    127    3      8      Ljava/lang/ClassCastException;
        //  120    127    127    128    Any
        // 
        // The error that occurred was:
        // 
        // java.lang.IndexOutOfBoundsException: Index -1 out of bounds for length 0
        //     at java.base/jdk.internal.util.Preconditions.outOfBounds(Preconditions.java:64)
        //     at java.base/jdk.internal.util.Preconditions.outOfBoundsCheckIndex(Preconditions.java:70)
        //     at java.base/jdk.internal.util.Preconditions.checkIndex(Preconditions.java:248)
        //     at java.base/java.util.Objects.checkIndex(Objects.java:372)
        //     at java.base/java.util.ArrayList.remove(ArrayList.java:535)
        //     at com.strobel.assembler.ir.StackMappingVisitor.pop(StackMappingVisitor.java:267)
        //     at com.strobel.assembler.ir.StackMappingVisitor$InstructionAnalyzer.execute(StackMappingVisitor.java:595)
        //     at com.strobel.assembler.ir.StackMappingVisitor$InstructionAnalyzer.visit(StackMappingVisitor.java:398)
        //     at com.strobel.decompiler.ast.AstBuilder.performStackAnalysis(AstBuilder.java:2030)
        //     at com.strobel.decompiler.ast.AstBuilder.build(AstBuilder.java:108)
        //     at com.strobel.decompiler.languages.java.ast.AstMethodBodyBuilder.createMethodBody(AstMethodBodyBuilder.java:211)
        //     at com.strobel.decompiler.languages.java.ast.AstMethodBodyBuilder.createMethodBody(AstMethodBodyBuilder.java:99)
        //     at com.strobel.decompiler.languages.java.ast.AstBuilder.createMethodBody(AstBuilder.java:782)
        //     at com.strobel.decompiler.languages.java.ast.AstBuilder.createMethod(AstBuilder.java:675)
        //     at com.strobel.decompiler.languages.java.ast.AstBuilder.addTypeMembers(AstBuilder.java:552)
        //     at com.strobel.decompiler.languages.java.ast.AstBuilder.createTypeCore(AstBuilder.java:519)
        //     at com.strobel.decompiler.languages.java.ast.AstBuilder.createTypeNoCache(AstBuilder.java:161)
        //     at com.strobel.decompiler.languages.java.ast.AstBuilder.createType(AstBuilder.java:150)
        //     at com.strobel.decompiler.languages.java.ast.AstBuilder.addType(AstBuilder.java:125)
        //     at com.strobel.decompiler.languages.java.JavaLanguage.buildAst(JavaLanguage.java:71)
        //     at com.strobel.decompiler.languages.java.JavaLanguage.decompileType(JavaLanguage.java:59)
        //     at com.strobel.decompiler.DecompilerDriver.decompileType(DecompilerDriver.java:330)
        //     at com.strobel.decompiler.DecompilerDriver.decompileJar(DecompilerDriver.java:251)
        //     at com.strobel.decompiler.DecompilerDriver.main(DecompilerDriver.java:126)
        // 
        throw new IllegalStateException("An error occurred while decompiling this method.");
    }
    
    static {
        throw t;
    }
    
    public fbM() {
        while (true) {
            int n = 0;
            Label_0014: {
                if (fc.0 != 0) {
                    n = 1567983791;
                    break Label_0014;
                }
                n = -423199754;
            }
            switch (n ^ 0x77683068) {
                case 706590919: {
                    continue;
                }
                case -1850848354: {}
                default: {
                    throw null;
                }
            }
            break;
        }
    }
    
    public static Entity c(final double p0, final float p1, final float p2, final fbL p3) {
        // 
        // This method could not be decompiled.
        // 
        // Original Bytecode:
        // 
        //     3: dup            
        //     4: ifnull          1934
        //     7: athrow         
        //     8: aconst_null    
        //     9: getstatic       dev/nuker/pyro/fc.0:I
        //    12: ifgt            1926
        //    15: pop            
        //    16: aconst_null    
        //    17: goto            1918
        //    20: nop            
        //    21: nop            
        //    22: nop            
        //    23: athrow         
        //    24: getstatic       dev/nuker/pyro/fbM.c:Lnet/minecraft/client/Minecraft;
        //    27: getfield        net/minecraft/client/Minecraft.field_71439_g:Lnet/minecraft/client/entity/EntityPlayerSP;
        //    30: getstatic       dev/nuker/pyro/fc.0:I
        //    33: ifeq            41
        //    36: ldc             -1540368128
        //    38: goto            43
        //    41: ldc             -1636137995
        //    43: ldc             704646100
        //    45: ixor           
        //    46: lookupswitch {
        //          -1909468460: 1879
        //          133161416: 41
        //          default: 72
        //        }
        //    72: astore          5
        //    74: aload           5
        //    76: ifnull          1859
        //    79: getstatic       dev/nuker/pyro/fbM.c:Lnet/minecraft/client/Minecraft;
        //    82: getfield        net/minecraft/client/Minecraft.field_71441_e:Lnet/minecraft/client/multiplayer/WorldClient;
        //    85: ifnull          93
        //    88: ldc             992577825
        //    90: goto            95
        //    93: ldc             992577824
        //    95: ldc             -240854339
        //    97: ixor           
        //    98: tableswitch {
        //          -1793415368: 120
        //          -1793415367: 1859
        //          default: 88
        //        }
        //   120: dload_0        
        //   121: dstore          6
        //   123: aload           5
        //   125: fconst_1       
        //   126: goto            130
        //   129: athrow         
        //   130: invokevirtual   net/minecraft/entity/Entity.func_174824_e:(F)Lnet/minecraft/util/math/Vec3d;
        //   133: goto            137
        //   136: athrow         
        //   137: getstatic       dev/nuker/pyro/fc.1:I
        //   140: ifeq            148
        //   143: ldc             -1198595675
        //   145: goto            150
        //   148: ldc             -1367855208
        //   150: ldc             324375879
        //   152: ixor           
        //   153: lookupswitch {
        //          -1411681054: 1905
        //          25592053: 148
        //          default: 180
        //        }
        //   180: astore          8
        //   182: fload_2        
        //   183: fneg           
        //   184: ldc             0.017453292
        //   186: fmul           
        //   187: ldc             3.1415927
        //   189: fsub           
        //   190: goto            194
        //   193: athrow         
        //   194: invokestatic    net/minecraft/util/math/MathHelper.func_76134_b:(F)F
        //   197: goto            201
        //   200: athrow         
        //   201: getstatic       dev/nuker/pyro/fc.c:I
        //   204: ifge            212
        //   207: ldc             -2116695581
        //   209: goto            214
        //   212: ldc             1176185029
        //   214: ldc             -103864337
        //   216: ixor           
        //   217: lookupswitch {
        //          602214188: 212
        //          2015030796: 1881
        //          default: 244
        //        }
        //   244: fstore          9
        //   246: fload_2        
        //   247: fneg           
        //   248: ldc             0.017453292
        //   250: fmul           
        //   251: ldc             3.1415927
        //   253: fsub           
        //   254: goto            258
        //   257: athrow         
        //   258: invokestatic    net/minecraft/util/math/MathHelper.func_76126_a:(F)F
        //   261: goto            265
        //   264: athrow         
        //   265: getstatic       dev/nuker/pyro/fc.c:I
        //   268: ifge            276
        //   271: ldc             1037033337
        //   273: goto            278
        //   276: ldc             -326242541
        //   278: ldc             -1058899438
        //   280: ixor           
        //   281: lookupswitch {
        //          -85658879: 276
        //          -47340181: 1867
        //          default: 308
        //        }
        //   308: fstore          10
        //   310: getstatic       dev/nuker/pyro/fc.1:I
        //   313: ifeq            321
        //   316: ldc             1574264768
        //   318: goto            323
        //   321: ldc             1428887035
        //   323: ldc             1441566269
        //   325: ixor           
        //   326: lookupswitch {
        //          138007037: 1893
        //          1971165426: 321
        //          default: 352
        //        }
        //   352: fload_3        
        //   353: fneg           
        //   354: ldc             0.017453292
        //   356: fmul           
        //   357: goto            361
        //   360: athrow         
        //   361: invokestatic    net/minecraft/util/math/MathHelper.func_76134_b:(F)F
        //   364: goto            368
        //   367: athrow         
        //   368: fneg           
        //   369: fstore          11
        //   371: fload_3        
        //   372: fneg           
        //   373: ldc             0.017453292
        //   375: fmul           
        //   376: getstatic       dev/nuker/pyro/fc.1:I
        //   379: ifeq            387
        //   382: ldc             -969423868
        //   384: goto            389
        //   387: ldc             1320563438
        //   389: ldc             -1417575898
        //   391: ixor           
        //   392: lookupswitch {
        //          -449335096: 420
        //          1840662050: 387
        //          default: 1901
        //        }
        //   420: goto            424
        //   423: athrow         
        //   424: invokestatic    net/minecraft/util/math/MathHelper.func_76126_a:(F)F
        //   427: goto            431
        //   430: athrow         
        //   431: fstore          12
        //   433: new             Lnet/minecraft/util/math/Vec3d;
        //   436: dup            
        //   437: fload           10
        //   439: fload           11
        //   441: fmul           
        //   442: f2d            
        //   443: fload           12
        //   445: f2d            
        //   446: fload           9
        //   448: fload           11
        //   450: fmul           
        //   451: f2d            
        //   452: goto            456
        //   455: athrow         
        //   456: invokespecial   net/minecraft/util/math/Vec3d.<init>:(DDD)V
        //   459: goto            463
        //   462: athrow         
        //   463: astore          13
        //   465: aload           8
        //   467: aload           13
        //   469: getstatic       dev/nuker/pyro/fc.1:I
        //   472: ifeq            480
        //   475: ldc             474060132
        //   477: goto            482
        //   480: ldc             -385461604
        //   482: ldc             2093834041
        //   484: ixor           
        //   485: lookupswitch {
        //          -1781854811: 512
        //          1619839581: 480
        //          default: 1899
        //        }
        //   512: getfield        net/minecraft/util/math/Vec3d.field_72450_a:D
        //   515: dload           6
        //   517: dmul           
        //   518: getstatic       dev/nuker/pyro/fc.1:I
        //   521: ifeq            529
        //   524: ldc             -1009001498
        //   526: goto            531
        //   529: ldc             -387256100
        //   531: ldc             1113301982
        //   533: ixor           
        //   534: lookupswitch {
        //          -2122287048: 1903
        //          -53070433: 529
        //          default: 560
        //        }
        //   560: aload           13
        //   562: getfield        net/minecraft/util/math/Vec3d.field_72448_b:D
        //   565: dload           6
        //   567: dmul           
        //   568: aload           13
        //   570: getfield        net/minecraft/util/math/Vec3d.field_72449_c:D
        //   573: dload           6
        //   575: dmul           
        //   576: goto            580
        //   579: athrow         
        //   580: invokevirtual   net/minecraft/util/math/Vec3d.func_72441_c:(DDD)Lnet/minecraft/util/math/Vec3d;
        //   583: goto            587
        //   586: athrow         
        //   587: astore          14
        //   589: getstatic       dev/nuker/pyro/fbM.c:Lnet/minecraft/client/Minecraft;
        //   592: getfield        net/minecraft/client/Minecraft.field_71441_e:Lnet/minecraft/client/multiplayer/WorldClient;
        //   595: getstatic       dev/nuker/pyro/fc.c:I
        //   598: ifge            606
        //   601: ldc             398195374
        //   603: goto            608
        //   606: ldc             912420064
        //   608: ldc             28408796
        //   610: ixor           
        //   611: lookupswitch {
        //          369787250: 606
        //          936580924: 636
        //          default: 1889
        //        }
        //   636: aload           5
        //   638: aload           5
        //   640: goto            644
        //   643: athrow         
        //   644: invokevirtual   net/minecraft/entity/Entity.func_174813_aQ:()Lnet/minecraft/util/math/AxisAlignedBB;
        //   647: goto            651
        //   650: athrow         
        //   651: aload           13
        //   653: getstatic       dev/nuker/pyro/fc.0:I
        //   656: ifeq            664
        //   659: ldc             493184556
        //   661: goto            666
        //   664: ldc             2007785520
        //   666: ldc             -1883609617
        //   668: ixor           
        //   669: lookupswitch {
        //          -1966531567: 664
        //          -1830878269: 1897
        //          default: 696
        //        }
        //   696: getfield        net/minecraft/util/math/Vec3d.field_72450_a:D
        //   699: dload           6
        //   701: dmul           
        //   702: aload           13
        //   704: getfield        net/minecraft/util/math/Vec3d.field_72448_b:D
        //   707: dload           6
        //   709: dmul           
        //   710: aload           13
        //   712: getfield        net/minecraft/util/math/Vec3d.field_72449_c:D
        //   715: dload           6
        //   717: dmul           
        //   718: getstatic       dev/nuker/pyro/fc.c:I
        //   721: ifge            729
        //   724: ldc             1294903177
        //   726: goto            731
        //   729: ldc             -301559552
        //   731: ldc             1522224214
        //   733: ixor           
        //   734: lookupswitch {
        //          -1262625450: 760
        //          395701215: 729
        //          default: 1907
        //        }
        //   760: goto            764
        //   763: athrow         
        //   764: invokevirtual   net/minecraft/util/math/AxisAlignedBB.func_72321_a:(DDD)Lnet/minecraft/util/math/AxisAlignedBB;
        //   767: goto            771
        //   770: athrow         
        //   771: dconst_1       
        //   772: dconst_1       
        //   773: dconst_1       
        //   774: goto            778
        //   777: athrow         
        //   778: invokevirtual   net/minecraft/util/math/AxisAlignedBB.func_72321_a:(DDD)Lnet/minecraft/util/math/AxisAlignedBB;
        //   781: goto            785
        //   784: athrow         
        //   785: getstatic       dev/nuker/pyro/fc.c:I
        //   788: ifge            796
        //   791: ldc             1982630077
        //   793: goto            798
        //   796: ldc             637151990
        //   798: ldc             1916078980
        //   800: ixor           
        //   801: lookupswitch {
        //          68780857: 796
        //          1473192306: 828
        //          default: 1861
        //        }
        //   828: getstatic       net/minecraft/util/EntitySelectors.field_180132_d:Lcom/google/common/base/Predicate;
        //   831: invokedynamic   BootstrapMethod #0, apply:()Lcom/google/common/base/Predicate;
        //   836: goto            840
        //   839: athrow         
        //   840: invokestatic    com/google/common/base/Predicates.and:(Lcom/google/common/base/Predicate;Lcom/google/common/base/Predicate;)Lcom/google/common/base/Predicate;
        //   843: goto            847
        //   846: athrow         
        //   847: goto            851
        //   850: athrow         
        //   851: invokevirtual   net/minecraft/client/multiplayer/WorldClient.func_175674_a:(Lnet/minecraft/entity/Entity;Lnet/minecraft/util/math/AxisAlignedBB;Lcom/google/common/base/Predicate;)Ljava/util/List;
        //   854: goto            858
        //   857: athrow         
        //   858: astore          15
        //   860: aconst_null    
        //   861: astore          16
        //   863: aload           15
        //   865: getstatic       dev/nuker/pyro/fc.c:I
        //   868: ifge            876
        //   871: ldc             -638328934
        //   873: goto            878
        //   876: ldc             2146293287
        //   878: ldc             -2064672656
        //   880: ixor           
        //   881: lookupswitch {
        //          -83734953: 908
        //          1562134506: 876
        //          default: 1869
        //        }
        //   908: goto            912
        //   911: athrow         
        //   912: invokeinterface java/util/List.iterator:()Ljava/util/Iterator;
        //   917: goto            921
        //   920: athrow         
        //   921: astore          17
        //   923: aload           17
        //   925: getstatic       dev/nuker/pyro/fc.0:I
        //   928: ifeq            936
        //   931: ldc             682475949
        //   933: goto            938
        //   936: ldc             -1046457656
        //   938: ldc             291551247
        //   940: ixor           
        //   941: lookupswitch {
        //          -1812548575: 936
        //          969767330: 1891
        //          default: 968
        //        }
        //   968: goto            972
        //   971: athrow         
        //   972: invokeinterface java/util/Iterator.hasNext:()Z
        //   977: goto            981
        //   980: athrow         
        //   981: ifeq            989
        //   984: ldc             -3129349
        //   986: goto            991
        //   989: ldc             -3129352
        //   991: ldc             941325586
        //   993: ixor           
        //   994: tableswitch {
        //          -1885960750: 1016
        //          -1885960749: 1811
        //          default: 984
        //        }
        //  1016: aload           17
        //  1018: getstatic       dev/nuker/pyro/fc.1:I
        //  1021: ifeq            1029
        //  1024: ldc             146265618
        //  1026: goto            1031
        //  1029: ldc             -159019873
        //  1031: ldc             734497315
        //  1033: ixor           
        //  1034: lookupswitch {
        //          -450114710: 1029
        //          594566193: 1873
        //          default: 1060
        //        }
        //  1060: goto            1064
        //  1063: athrow         
        //  1064: invokeinterface java/util/Iterator.next:()Ljava/lang/Object;
        //  1069: goto            1073
        //  1072: athrow         
        //  1073: checkcast       Lnet/minecraft/entity/Entity;
        //  1076: astore          18
        //  1078: aload           4
        //  1080: aload           18
        //  1082: goto            1086
        //  1085: athrow         
        //  1086: invokeinterface dev/nuker/pyro/fbL.c:(Lnet/minecraft/entity/Entity;)Z
        //  1091: goto            1095
        //  1094: athrow         
        //  1095: ifne            1101
        //  1098: goto            923
        //  1101: aload           18
        //  1103: goto            1107
        //  1106: athrow         
        //  1107: invokevirtual   net/minecraft/entity/Entity.func_70111_Y:()F
        //  1110: goto            1114
        //  1113: athrow         
        //  1114: fstore          19
        //  1116: aload           18
        //  1118: goto            1122
        //  1121: athrow         
        //  1122: invokevirtual   net/minecraft/entity/Entity.func_174813_aQ:()Lnet/minecraft/util/math/AxisAlignedBB;
        //  1125: goto            1129
        //  1128: athrow         
        //  1129: getstatic       dev/nuker/pyro/fc.0:I
        //  1132: ifeq            1140
        //  1135: ldc             1729999584
        //  1137: goto            1142
        //  1140: ldc             889988350
        //  1142: ldc_w           -910840350
        //  1145: ixor           
        //  1146: lookupswitch {
        //          -1364713726: 1877
        //          -768890450: 1140
        //          default: 1172
        //        }
        //  1172: fload           19
        //  1174: f2d            
        //  1175: fload           19
        //  1177: f2d            
        //  1178: fload           19
        //  1180: f2d            
        //  1181: goto            1185
        //  1184: athrow         
        //  1185: invokevirtual   net/minecraft/util/math/AxisAlignedBB.func_72321_a:(DDD)Lnet/minecraft/util/math/AxisAlignedBB;
        //  1188: goto            1192
        //  1191: athrow         
        //  1192: astore          20
        //  1194: aload           20
        //  1196: aload           8
        //  1198: aload           14
        //  1200: goto            1204
        //  1203: athrow         
        //  1204: invokevirtual   net/minecraft/util/math/AxisAlignedBB.func_72327_a:(Lnet/minecraft/util/math/Vec3d;Lnet/minecraft/util/math/Vec3d;)Lnet/minecraft/util/math/RayTraceResult;
        //  1207: goto            1211
        //  1210: athrow         
        //  1211: astore          21
        //  1213: aload           20
        //  1215: getstatic       dev/nuker/pyro/fc.c:I
        //  1218: ifge            1227
        //  1221: ldc_w           686971117
        //  1224: goto            1230
        //  1227: ldc_w           73321218
        //  1230: ldc_w           -1037292403
        //  1233: ixor           
        //  1234: lookupswitch {
        //          -354519968: 1887
        //          687640273: 1227
        //          default: 1260
        //        }
        //  1260: aload           8
        //  1262: goto            1266
        //  1265: athrow         
        //  1266: invokevirtual   net/minecraft/util/math/AxisAlignedBB.func_72318_a:(Lnet/minecraft/util/math/Vec3d;)Z
        //  1269: goto            1273
        //  1272: athrow         
        //  1273: ifeq            1293
        //  1276: dload           6
        //  1278: dconst_0       
        //  1279: dcmpl          
        //  1280: iflt            1808
        //  1283: aload           18
        //  1285: astore          16
        //  1287: dconst_0       
        //  1288: dstore          6
        //  1290: goto            1808
        //  1293: aload           21
        //  1295: ifnull          1808
        //  1298: aload           8
        //  1300: getstatic       dev/nuker/pyro/fc.1:I
        //  1303: ifeq            1312
        //  1306: ldc_w           -1609535582
        //  1309: goto            1315
        //  1312: ldc_w           6722405
        //  1315: ldc_w           -822763337
        //  1318: ixor           
        //  1319: lookupswitch {
        //          -829213742: 1344
        //          1860554517: 1312
        //          default: 1863
        //        }
        //  1344: aload           21
        //  1346: getfield        net/minecraft/util/math/RayTraceResult.field_72307_f:Lnet/minecraft/util/math/Vec3d;
        //  1349: getstatic       dev/nuker/pyro/fc.c:I
        //  1352: ifge            1361
        //  1355: ldc_w           -2069638436
        //  1358: goto            1364
        //  1361: ldc_w           1532275325
        //  1364: ldc_w           -259182593
        //  1367: ixor           
        //  1368: lookupswitch {
        //          -2079218110: 1361
        //          1949236515: 1871
        //          default: 1396
        //        }
        //  1396: goto            1400
        //  1399: athrow         
        //  1400: invokevirtual   net/minecraft/util/math/Vec3d.func_72438_d:(Lnet/minecraft/util/math/Vec3d;)D
        //  1403: goto            1407
        //  1406: athrow         
        //  1407: dstore          22
        //  1409: getstatic       dev/nuker/pyro/fc.0:I
        //  1412: ifeq            1421
        //  1415: ldc_w           1432249292
        //  1418: goto            1424
        //  1421: ldc_w           -1706467904
        //  1424: ldc_w           1604115590
        //  1427: ixor           
        //  1428: lookupswitch {
        //          180535114: 1883
        //          387455470: 1421
        //          default: 1456
        //        }
        //  1456: dload           22
        //  1458: dload           6
        //  1460: dcmpg          
        //  1461: iflt            1470
        //  1464: ldc_w           -1581723993
        //  1467: goto            1473
        //  1470: ldc_w           -1581723996
        //  1473: ldc_w           412181546
        //  1476: ixor           
        //  1477: tableswitch {
        //          1918063898: 1500
        //          1918063899: 1588
        //          default: 1464
        //        }
        //  1500: getstatic       dev/nuker/pyro/fc.c:I
        //  1503: ifge            1512
        //  1506: ldc_w           914023949
        //  1509: goto            1515
        //  1512: ldc_w           -770390920
        //  1515: ldc_w           1847312979
        //  1518: ixor           
        //  1519: lookupswitch {
        //          623020441: 1512
        //          1482761310: 1885
        //          default: 1544
        //        }
        //  1544: dload           6
        //  1546: dconst_0       
        //  1547: dcmpl          
        //  1548: ifne            1557
        //  1551: ldc_w           -530575507
        //  1554: goto            1560
        //  1557: ldc_w           -530575510
        //  1560: ldc_w           -688197346
        //  1563: ixor           
        //  1564: tableswitch {
        //          1832254694: 1588
        //          1832254695: 1808
        //          default: 1551
        //        }
        //  1588: aload           18
        //  1590: aload           5
        //  1592: goto            1596
        //  1595: athrow         
        //  1596: invokevirtual   net/minecraft/entity/Entity.func_184187_bx:()Lnet/minecraft/entity/Entity;
        //  1599: goto            1603
        //  1602: athrow         
        //  1603: if_acmpne       1612
        //  1606: ldc_w           1214913113
        //  1609: goto            1615
        //  1612: ldc_w           1214913114
        //  1615: ldc_w           -1695041348
        //  1618: ixor           
        //  1619: tableswitch {
        //          -1522842166: 1640
        //          -1522842165: 1707
        //          default: 1606
        //        }
        //  1640: aload           5
        //  1642: goto            1646
        //  1645: athrow         
        //  1646: invokevirtual   net/minecraft/entity/Entity.canRiderInteract:()Z
        //  1649: goto            1653
        //  1652: athrow         
        //  1653: ifne            1707
        //  1656: dload           6
        //  1658: dconst_0       
        //  1659: dcmpl          
        //  1660: ifne            1669
        //  1663: ldc_w           -1157849774
        //  1666: goto            1672
        //  1669: ldc_w           -1157849773
        //  1672: ldc_w           24952464
        //  1675: ixor           
        //  1676: tableswitch {
        //          1996507012: 1700
        //          1996507013: 1808
        //          default: 1663
        //        }
        //  1700: aload           18
        //  1702: astore          16
        //  1704: goto            1808
        //  1707: aload           18
        //  1709: getstatic       dev/nuker/pyro/fc.0:I
        //  1712: ifeq            1721
        //  1715: ldc_w           253419020
        //  1718: goto            1724
        //  1721: ldc_w           150971572
        //  1724: ldc_w           -1898107375
        //  1727: ixor           
        //  1728: lookupswitch {
        //          -2117603299: 1721
        //          -2044556635: 1756
        //          default: 1895
        //        }
        //  1756: astore          16
        //  1758: getstatic       dev/nuker/pyro/fc.0:I
        //  1761: ifeq            1770
        //  1764: ldc_w           1247288375
        //  1767: goto            1773
        //  1770: ldc_w           1902012863
        //  1773: ldc_w           1772224425
        //  1776: ixor           
        //  1777: lookupswitch {
        //          520809444: 1770
        //          603579294: 1865
        //          default: 1804
        //        }
        //  1804: dload           22
        //  1806: dstore          6
        //  1808: goto            923
        //  1811: getstatic       dev/nuker/pyro/fc.1:I
        //  1814: ifeq            1823
        //  1817: ldc_w           -832096343
        //  1820: goto            1826
        //  1823: ldc_w           925263345
        //  1826: ldc_w           1128087985
        //  1829: ixor           
        //  1830: lookupswitch {
        //          -1923451368: 1875
        //          598602414: 1823
        //          default: 1856
        //        }
        //  1856: aload           16
        //  1858: areturn        
        //  1859: aconst_null    
        //  1860: areturn        
        //  1861: aconst_null    
        //  1862: athrow         
        //  1863: aconst_null    
        //  1864: athrow         
        //  1865: aconst_null    
        //  1866: athrow         
        //  1867: aconst_null    
        //  1868: athrow         
        //  1869: aconst_null    
        //  1870: athrow         
        //  1871: aconst_null    
        //  1872: athrow         
        //  1873: aconst_null    
        //  1874: athrow         
        //  1875: aconst_null    
        //  1876: athrow         
        //  1877: aconst_null    
        //  1878: athrow         
        //  1879: aconst_null    
        //  1880: athrow         
        //  1881: aconst_null    
        //  1882: athrow         
        //  1883: aconst_null    
        //  1884: athrow         
        //  1885: aconst_null    
        //  1886: athrow         
        //  1887: aconst_null    
        //  1888: athrow         
        //  1889: aconst_null    
        //  1890: athrow         
        //  1891: aconst_null    
        //  1892: athrow         
        //  1893: aconst_null    
        //  1894: athrow         
        //  1895: aconst_null    
        //  1896: athrow         
        //  1897: aconst_null    
        //  1898: athrow         
        //  1899: aconst_null    
        //  1900: athrow         
        //  1901: aconst_null    
        //  1902: athrow         
        //  1903: aconst_null    
        //  1904: athrow         
        //  1905: aconst_null    
        //  1906: athrow         
        //  1907: aconst_null    
        //  1908: athrow         
        //  1909: pop            
        //  1910: goto            24
        //  1913: pop            
        //  1914: aconst_null    
        //  1915: goto            1909
        //  1918: dup            
        //  1919: ifnull          1909
        //  1922: checkcast       Ljava/lang/Throwable;
        //  1925: athrow         
        //  1926: dup            
        //  1927: ifnull          1913
        //  1930: checkcast       Ljava/lang/Throwable;
        //  1933: athrow         
        //  1934: aconst_null    
        //  1935: athrow         
        //    StackMapTable: 00 E8 FF 00 03 00 07 03 02 02 07 00 3A 07 01 3F 03 07 00 8A 00 01 07 00 1F F8 00 04 FF 00 0B 00 00 00 01 07 00 1F FF 00 03 00 04 03 02 02 07 00 3A 00 00 50 07 01 3F FF 00 01 00 04 03 02 02 07 00 3A 00 02 07 01 3F 01 5C 07 01 3F FC 00 0F 07 01 3F 04 41 01 18 FF 00 08 00 06 03 02 02 07 00 3A 07 01 3F 03 00 01 07 00 1F FF 00 00 00 06 03 02 02 07 00 3A 07 01 3F 03 00 02 07 01 3F 02 45 07 00 1F 40 07 00 8A 4A 07 00 8A FF 00 01 00 06 03 02 02 07 00 3A 07 01 3F 03 00 02 07 00 8A 01 5D 07 00 8A FF 00 0C 00 00 00 01 07 00 1F FF 00 00 00 07 03 02 02 07 00 3A 07 01 3F 03 07 00 8A 00 01 02 45 07 00 1F 40 02 4A 02 FF 00 01 00 07 03 02 02 07 00 3A 07 01 3F 03 07 00 8A 00 02 02 01 5D 02 FF 00 0C 00 08 03 02 02 07 00 3A 07 01 3F 03 07 00 8A 02 00 01 07 00 1F 40 02 45 07 00 1F 40 02 4A 02 FF 00 01 00 08 03 02 02 07 00 3A 07 01 3F 03 07 00 8A 02 00 02 02 01 5D 02 FC 00 0C 02 41 01 1C 47 07 00 1F 40 02 45 07 00 1F 40 02 FF 00 12 00 0A 03 02 02 07 00 3A 07 01 3F 03 07 00 8A 02 02 02 00 01 02 FF 00 01 00 0A 03 02 02 07 00 3A 07 01 3F 03 07 00 8A 02 02 02 00 02 02 01 5E 02 42 07 00 3E 40 02 45 07 00 1F 40 02 FF 00 17 00 0B 03 02 02 07 00 3A 07 01 3F 03 07 00 8A 02 02 02 02 00 01 07 00 51 FF 00 00 00 0B 03 02 02 07 00 3A 07 01 3F 03 07 00 8A 02 02 02 02 00 05 08 01 B1 08 01 B1 03 03 03 45 07 00 1F 40 07 00 8A FF 00 10 00 0C 03 02 02 07 00 3A 07 01 3F 03 07 00 8A 02 02 02 02 07 00 8A 00 02 07 00 8A 07 00 8A FF 00 01 00 0C 03 02 02 07 00 3A 07 01 3F 03 07 00 8A 02 02 02 02 07 00 8A 00 03 07 00 8A 07 00 8A 01 FF 00 1D 00 0C 03 02 02 07 00 3A 07 01 3F 03 07 00 8A 02 02 02 02 07 00 8A 00 02 07 00 8A 07 00 8A FF 00 10 00 0C 03 02 02 07 00 3A 07 01 3F 03 07 00 8A 02 02 02 02 07 00 8A 00 02 07 00 8A 03 FF 00 01 00 0C 03 02 02 07 00 3A 07 01 3F 03 07 00 8A 02 02 02 02 07 00 8A 00 03 07 00 8A 03 01 FF 00 1C 00 0C 03 02 02 07 00 3A 07 01 3F 03 07 00 8A 02 02 02 02 07 00 8A 00 02 07 00 8A 03 52 07 00 0F FF 00 00 00 0C 03 02 02 07 00 3A 07 01 3F 03 07 00 8A 02 02 02 02 07 00 8A 00 04 07 00 8A 03 03 03 45 07 00 1F 40 07 00 8A FF 00 12 00 0D 03 02 02 07 00 3A 07 01 3F 03 07 00 8A 02 02 02 02 07 00 8A 07 00 8A 00 01 07 00 D9 FF 00 01 00 0D 03 02 02 07 00 3A 07 01 3F 03 07 00 8A 02 02 02 02 07 00 8A 07 00 8A 00 02 07 00 D9 01 5B 07 00 D9 46 07 00 0B FF 00 00 00 0D 03 02 02 07 00 3A 07 01 3F 03 07 00 8A 02 02 02 02 07 00 8A 07 00 8A 00 03 07 00 D9 07 01 3F 07 01 3F 45 07 00 1F FF 00 00 00 0D 03 02 02 07 00 3A 07 01 3F 03 07 00 8A 02 02 02 02 07 00 8A 07 00 8A 00 03 07 00 D9 07 01 3F 07 00 B0 FF 00 0C 00 0D 03 02 02 07 00 3A 07 01 3F 03 07 00 8A 02 02 02 02 07 00 8A 07 00 8A 00 04 07 00 D9 07 01 3F 07 00 B0 07 00 8A FF 00 01 00 0D 03 02 02 07 00 3A 07 01 3F 03 07 00 8A 02 02 02 02 07 00 8A 07 00 8A 00 05 07 00 D9 07 01 3F 07 00 B0 07 00 8A 01 FF 00 1D 00 0D 03 02 02 07 00 3A 07 01 3F 03 07 00 8A 02 02 02 02 07 00 8A 07 00 8A 00 04 07 00 D9 07 01 3F 07 00 B0 07 00 8A FF 00 20 00 0D 03 02 02 07 00 3A 07 01 3F 03 07 00 8A 02 02 02 02 07 00 8A 07 00 8A 00 06 07 00 D9 07 01 3F 07 00 B0 03 03 03 FF 00 01 00 0D 03 02 02 07 00 3A 07 01 3F 03 07 00 8A 02 02 02 02 07 00 8A 07 00 8A 00 07 07 00 D9 07 01 3F 07 00 B0 03 03 03 01 FF 00 1C 00 0D 03 02 02 07 00 3A 07 01 3F 03 07 00 8A 02 02 02 02 07 00 8A 07 00 8A 00 06 07 00 D9 07 01 3F 07 00 B0 03 03 03 42 07 00 1F FF 00 00 00 0D 03 02 02 07 00 3A 07 01 3F 03 07 00 8A 02 02 02 02 07 00 8A 07 00 8A 00 06 07 00 D9 07 01 3F 07 00 B0 03 03 03 45 07 00 1F FF 00 00 00 0D 03 02 02 07 00 3A 07 01 3F 03 07 00 8A 02 02 02 02 07 00 8A 07 00 8A 00 03 07 00 D9 07 01 3F 07 00 B0 FF 00 05 00 00 00 01 07 00 1F FF 00 00 00 0D 03 02 02 07 00 3A 07 01 3F 03 07 00 8A 02 02 02 02 07 00 8A 07 00 8A 00 06 07 00 D9 07 01 3F 07 00 B0 03 03 03 45 07 00 1F FF 00 00 00 0D 03 02 02 07 00 3A 07 01 3F 03 07 00 8A 02 02 02 02 07 00 8A 07 00 8A 00 03 07 00 D9 07 01 3F 07 00 B0 FF 00 0A 00 0D 03 02 02 07 00 3A 07 01 3F 03 07 00 8A 02 02 02 02 07 00 8A 07 00 8A 00 03 07 00 D9 07 01 3F 07 00 B0 FF 00 01 00 0D 03 02 02 07 00 3A 07 01 3F 03 07 00 8A 02 02 02 02 07 00 8A 07 00 8A 00 04 07 00 D9 07 01 3F 07 00 B0 01 FF 00 1D 00 0D 03 02 02 07 00 3A 07 01 3F 03 07 00 8A 02 02 02 02 07 00 8A 07 00 8A 00 03 07 00 D9 07 01 3F 07 00 B0 4A 07 00 55 FF 00 00 00 0D 03 02 02 07 00 3A 07 01 3F 03 07 00 8A 02 02 02 02 07 00 8A 07 00 8A 00 05 07 00 D9 07 01 3F 07 00 B0 07 01 41 07 01 41 45 07 00 1F FF 00 00 00 0D 03 02 02 07 00 3A 07 01 3F 03 07 00 8A 02 02 02 02 07 00 8A 07 00 8A 00 04 07 00 D9 07 01 3F 07 00 B0 07 01 41 42 07 00 3E FF 00 00 00 0D 03 02 02 07 00 3A 07 01 3F 03 07 00 8A 02 02 02 02 07 00 8A 07 00 8A 00 04 07 00 D9 07 01 3F 07 00 B0 07 01 41 45 07 00 1F 40 07 00 E2 FF 00 11 00 0F 03 02 02 07 00 3A 07 01 3F 03 07 00 8A 02 02 02 02 07 00 8A 07 00 8A 07 00 E2 05 00 01 07 00 E2 FF 00 01 00 0F 03 02 02 07 00 3A 07 01 3F 03 07 00 8A 02 02 02 02 07 00 8A 07 00 8A 07 00 E2 05 00 02 07 00 E2 01 5D 07 00 E2 42 07 00 1F 40 07 00 E2 47 07 00 1F 40 07 00 EB FF 00 01 00 10 03 02 02 07 00 3A 07 01 3F 03 07 00 8A 02 02 02 02 07 00 8A 07 00 8A 07 00 E2 07 00 3C 07 00 EB 00 00 4C 07 00 EB FF 00 01 00 10 03 02 02 07 00 3A 07 01 3F 03 07 00 8A 02 02 02 02 07 00 8A 07 00 8A 07 00 E2 07 00 3C 07 00 EB 00 02 07 00 EB 01 5D 07 00 EB 42 07 00 1F 40 07 00 EB 47 07 00 1F 40 01 02 04 41 01 18 4C 07 00 EB FF 00 01 00 10 03 02 02 07 00 3A 07 01 3F 03 07 00 8A 02 02 02 02 07 00 8A 07 00 8A 07 00 E2 07 00 3C 07 00 EB 00 02 07 00 EB 01 5C 07 00 EB 42 07 00 3E 40 07 00 EB 47 07 00 1F 40 07 01 43 FF 00 0B 00 11 03 02 02 07 00 3A 07 01 3F 03 07 00 8A 02 02 02 02 07 00 8A 07 00 8A 07 00 E2 07 00 3C 07 00 EB 07 00 3C 00 01 07 00 1F FF 00 00 00 11 03 02 02 07 00 3A 07 01 3F 03 07 00 8A 02 02 02 02 07 00 8A 07 00 8A 07 00 E2 07 00 3C 07 00 EB 07 00 3C 00 02 07 00 3A 07 00 3C 47 07 00 1F 40 01 05 44 07 00 1F 40 07 00 3C 45 07 00 1F 40 02 FF 00 06 00 12 03 02 02 07 00 3A 07 01 3F 03 07 00 8A 02 02 02 02 07 00 8A 07 00 8A 07 00 E2 07 00 3C 07 00 EB 07 00 3C 02 00 01 07 00 1F 40 07 00 3C 45 07 00 1F 40 07 00 B0 4A 07 00 B0 FF 00 01 00 12 03 02 02 07 00 3A 07 01 3F 03 07 00 8A 02 02 02 02 07 00 8A 07 00 8A 07 00 E2 07 00 3C 07 00 EB 07 00 3C 02 00 02 07 00 B0 01 5D 07 00 B0 4B 07 00 1F FF 00 00 00 12 03 02 02 07 00 3A 07 01 3F 03 07 00 8A 02 02 02 02 07 00 8A 07 00 8A 07 00 E2 07 00 3C 07 00 EB 07 00 3C 02 00 04 07 00 B0 03 03 03 45 07 00 1F 40 07 00 B0 FF 00 0A 00 13 03 02 02 07 00 3A 07 01 3F 03 07 00 8A 02 02 02 02 07 00 8A 07 00 8A 07 00 E2 07 00 3C 07 00 EB 07 00 3C 02 07 00 B0 00 01 07 00 1F FF 00 00 00 13 03 02 02 07 00 3A 07 01 3F 03 07 00 8A 02 02 02 02 07 00 8A 07 00 8A 07 00 E2 07 00 3C 07 00 EB 07 00 3C 02 07 00 B0 00 03 07 00 B0 07 00 8A 07 00 8A 45 07 00 1F 40 07 01 10 FF 00 0F 00 14 03 02 02 07 00 3A 07 01 3F 03 07 00 8A 02 02 02 02 07 00 8A 07 00 8A 07 00 E2 07 00 3C 07 00 EB 07 00 3C 02 07 00 B0 07 01 10 00 01 07 00 B0 FF 00 02 00 14 03 02 02 07 00 3A 07 01 3F 03 07 00 8A 02 02 02 02 07 00 8A 07 00 8A 07 00 E2 07 00 3C 07 00 EB 07 00 3C 02 07 00 B0 07 01 10 00 02 07 00 B0 01 5D 07 00 B0 44 07 00 1F FF 00 00 00 14 03 02 02 07 00 3A 07 01 3F 03 07 00 8A 02 02 02 02 07 00 8A 07 00 8A 07 00 E2 07 00 3C 07 00 EB 07 00 3C 02 07 00 B0 07 01 10 00 02 07 00 B0 07 00 8A 45 07 00 1F 40 01 13 52 07 00 8A FF 00 02 00 14 03 02 02 07 00 3A 07 01 3F 03 07 00 8A 02 02 02 02 07 00 8A 07 00 8A 07 00 E2 07 00 3C 07 00 EB 07 00 3C 02 07 00 B0 07 01 10 00 02 07 00 8A 01 5C 07 00 8A FF 00 10 00 14 03 02 02 07 00 3A 07 01 3F 03 07 00 8A 02 02 02 02 07 00 8A 07 00 8A 07 00 E2 07 00 3C 07 00 EB 07 00 3C 02 07 00 B0 07 01 10 00 02 07 00 8A 07 00 8A FF 00 02 00 14 03 02 02 07 00 3A 07 01 3F 03 07 00 8A 02 02 02 02 07 00 8A 07 00 8A 07 00 E2 07 00 3C 07 00 EB 07 00 3C 02 07 00 B0 07 01 10 00 03 07 00 8A 07 00 8A 01 FF 00 1F 00 14 03 02 02 07 00 3A 07 01 3F 03 07 00 8A 02 02 02 02 07 00 8A 07 00 8A 07 00 E2 07 00 3C 07 00 EB 07 00 3C 02 07 00 B0 07 01 10 00 02 07 00 8A 07 00 8A 42 07 00 1F FF 00 00 00 14 03 02 02 07 00 3A 07 01 3F 03 07 00 8A 02 02 02 02 07 00 8A 07 00 8A 07 00 E2 07 00 3C 07 00 EB 07 00 3C 02 07 00 B0 07 01 10 00 02 07 00 8A 07 00 8A 45 07 00 1F 40 03 FC 00 0D 03 42 01 1F 07 05 42 01 1A 0B 42 01 1C 06 05 42 01 1B 46 07 00 1F FF 00 00 00 15 03 02 02 07 00 3A 07 01 3F 03 07 00 8A 02 02 02 02 07 00 8A 07 00 8A 07 00 E2 07 00 3C 07 00 EB 07 00 3C 02 07 00 B0 07 01 10 03 00 02 07 00 3C 07 01 3F 45 07 00 1F FF 00 00 00 15 03 02 02 07 00 3A 07 01 3F 03 07 00 8A 02 02 02 02 07 00 8A 07 00 8A 07 00 E2 07 00 3C 07 00 EB 07 00 3C 02 07 00 B0 07 01 10 03 00 02 07 00 3C 07 00 3C 02 05 42 01 18 44 07 00 15 40 07 01 3F 45 07 00 1F 40 01 09 05 42 01 1B 06 4D 07 00 3C FF 00 02 00 15 03 02 02 07 00 3A 07 01 3F 03 07 00 8A 02 02 02 02 07 00 8A 07 00 8A 07 00 E2 07 00 3C 07 00 EB 07 00 3C 02 07 00 B0 07 01 10 03 00 02 07 00 3C 01 5F 07 00 3C 0D 42 01 1E FA 00 03 FF 00 02 00 10 03 02 02 07 00 3A 07 01 3F 03 07 00 8A 02 02 02 02 07 00 8A 07 00 8A 07 00 E2 07 00 3C 07 00 EB 00 00 0B 42 01 1D FF 00 02 00 05 03 02 02 07 00 3A 07 01 3F 00 00 FF 00 01 00 0D 03 02 02 07 00 3A 07 01 3F 03 07 00 8A 02 02 02 02 07 00 8A 07 00 8A 00 03 07 00 D9 07 01 3F 07 00 B0 FF 00 01 00 14 03 02 02 07 00 3A 07 01 3F 03 07 00 8A 02 02 02 02 07 00 8A 07 00 8A 07 00 E2 07 00 3C 07 00 EB 07 00 3C 02 07 00 B0 07 01 10 00 01 07 00 8A FC 00 01 03 FF 00 01 00 08 03 02 02 07 00 3A 07 01 3F 03 07 00 8A 02 00 01 02 FF 00 01 00 0F 03 02 02 07 00 3A 07 01 3F 03 07 00 8A 02 02 02 02 07 00 8A 07 00 8A 07 00 E2 05 00 01 07 00 E2 FF 00 01 00 14 03 02 02 07 00 3A 07 01 3F 03 07 00 8A 02 02 02 02 07 00 8A 07 00 8A 07 00 E2 07 00 3C 07 00 EB 07 00 3C 02 07 00 B0 07 01 10 00 02 07 00 8A 07 00 8A FF 00 01 00 10 03 02 02 07 00 3A 07 01 3F 03 07 00 8A 02 02 02 02 07 00 8A 07 00 8A 07 00 E2 07 00 3C 07 00 EB 00 01 07 00 EB 01 FF 00 01 00 12 03 02 02 07 00 3A 07 01 3F 03 07 00 8A 02 02 02 02 07 00 8A 07 00 8A 07 00 E2 07 00 3C 07 00 EB 07 00 3C 02 00 01 07 00 B0 FF 00 01 00 04 03 02 02 07 00 3A 00 01 07 01 3F FF 00 01 00 07 03 02 02 07 00 3A 07 01 3F 03 07 00 8A 00 01 02 FF 00 01 00 15 03 02 02 07 00 3A 07 01 3F 03 07 00 8A 02 02 02 02 07 00 8A 07 00 8A 07 00 E2 07 00 3C 07 00 EB 07 00 3C 02 07 00 B0 07 01 10 03 00 00 01 FF 00 01 00 14 03 02 02 07 00 3A 07 01 3F 03 07 00 8A 02 02 02 02 07 00 8A 07 00 8A 07 00 E2 07 00 3C 07 00 EB 07 00 3C 02 07 00 B0 07 01 10 00 01 07 00 B0 FF 00 01 00 0D 03 02 02 07 00 3A 07 01 3F 03 07 00 8A 02 02 02 02 07 00 8A 07 00 8A 00 01 07 00 D9 FF 00 01 00 10 03 02 02 07 00 3A 07 01 3F 03 07 00 8A 02 02 02 02 07 00 8A 07 00 8A 07 00 E2 07 00 3C 07 00 EB 00 01 07 00 EB FF 00 01 00 09 03 02 02 07 00 3A 07 01 3F 03 07 00 8A 02 02 00 00 FF 00 01 00 15 03 02 02 07 00 3A 07 01 3F 03 07 00 8A 02 02 02 02 07 00 8A 07 00 8A 07 00 E2 07 00 3C 07 00 EB 07 00 3C 02 07 00 B0 07 01 10 03 00 01 07 00 3C FF 00 01 00 0D 03 02 02 07 00 3A 07 01 3F 03 07 00 8A 02 02 02 02 07 00 8A 07 00 8A 00 04 07 00 D9 07 01 3F 07 00 B0 07 00 8A FF 00 01 00 0C 03 02 02 07 00 3A 07 01 3F 03 07 00 8A 02 02 02 02 07 00 8A 00 02 07 00 8A 07 00 8A FF 00 01 00 0A 03 02 02 07 00 3A 07 01 3F 03 07 00 8A 02 02 02 00 01 02 FF 00 01 00 0C 03 02 02 07 00 3A 07 01 3F 03 07 00 8A 02 02 02 02 07 00 8A 00 02 07 00 8A 03 FF 00 01 00 06 03 02 02 07 00 3A 07 01 3F 03 00 01 07 00 8A FF 00 01 00 0D 03 02 02 07 00 3A 07 01 3F 03 07 00 8A 02 02 02 02 07 00 8A 07 00 8A 00 06 07 00 D9 07 01 3F 07 00 B0 03 03 03 FF 00 01 00 04 03 02 02 07 00 3A 00 01 07 00 1F 43 05 44 07 00 1F 47 05 FF 00 07 00 07 03 02 02 07 00 3A 07 01 3F 03 07 00 8A 00 01 07 00 1F
        //    Exceptions:
        //  Try           Handler
        //  Start  End    Start  End    Type                                       
        //  -----  -----  -----  -----  -------------------------------------------
        //  8      20     1918   1926   Any
        //  1918   1926   1918   1926   Ljava/lang/UnsupportedOperationException;
        //  1934   1936   3      8      Any
        //  129    136    136    137    Any
        //  130    136    129    130    Ljava/lang/AssertionError;
        //  129    136    136    137    Any
        //  129    136    136    137    Ljava/util/NoSuchElementException;
        //  129    136    129    130    Ljava/lang/IndexOutOfBoundsException;
        //  194    200    200    201    Any
        //  194    200    200    201    Ljava/lang/ClassCastException;
        //  194    200    3      8      Ljava/lang/AssertionError;
        //  194    200    3      8      Any
        //  194    200    200    201    Ljava/lang/IllegalArgumentException;
        //  257    264    264    265    Any
        //  257    264    3      8      Any
        //  257    264    257    258    Any
        //  257    264    257    258    Ljava/lang/IndexOutOfBoundsException;
        //  258    264    264    265    Ljava/lang/IndexOutOfBoundsException;
        //  360    367    367    368    Any
        //  361    367    360    361    Any
        //  360    367    367    368    Ljava/lang/NumberFormatException;
        //  361    367    360    361    Ljava/lang/ArithmeticException;
        //  361    367    360    361    Ljava/lang/UnsupportedOperationException;
        //  423    430    430    431    Any
        //  424    430    423    424    Ljava/lang/ArithmeticException;
        //  423    430    430    431    Any
        //  424    430    423    424    Ljava/lang/IllegalStateException;
        //  424    430    430    431    Any
        //  455    462    462    463    Any
        //  455    462    3      8      Any
        //  456    462    455    456    Ljava/lang/IllegalStateException;
        //  455    462    462    463    Any
        //  455    462    3      8      Ljava/util/ConcurrentModificationException;
        //  579    586    586    587    Any
        //  579    586    586    587    Any
        //  580    586    579    580    Ljava/lang/IllegalArgumentException;
        //  580    586    586    587    Ljava/lang/ClassCastException;
        //  579    586    586    587    Any
        //  643    650    650    651    Any
        //  644    650    3      8      Ljava/lang/NegativeArraySizeException;
        //  644    650    643    644    Ljava/lang/EnumConstantNotPresentException;
        //  643    650    3      8      Any
        //  643    650    3      8      Ljava/lang/ArrayIndexOutOfBoundsException;
        //  763    770    770    771    Any
        //  764    770    763    764    Any
        //  763    770    770    771    Ljava/lang/RuntimeException;
        //  763    770    770    771    Any
        //  763    770    763    764    Any
        //  778    784    784    785    Any
        //  778    784    3      8      Ljava/lang/UnsupportedOperationException;
        //  778    784    784    785    Ljava/lang/IllegalStateException;
        //  778    784    784    785    Any
        //  778    784    3      8      Ljava/lang/RuntimeException;
        //  839    846    846    847    Any
        //  840    846    839    840    Ljava/lang/StringIndexOutOfBoundsException;
        //  839    846    846    847    Ljava/lang/UnsupportedOperationException;
        //  840    846    846    847    Ljava/lang/NumberFormatException;
        //  840    846    846    847    Ljava/lang/ClassCastException;
        //  850    857    857    858    Any
        //  851    857    850    851    Ljava/lang/NullPointerException;
        //  850    857    850    851    Ljava/util/ConcurrentModificationException;
        //  851    857    3      8      Ljava/lang/ClassCastException;
        //  850    857    850    851    Ljava/lang/ClassCastException;
        //  911    920    920    921    Any
        //  911    920    3      8      Any
        //  911    920    911    912    Any
        //  911    920    911    912    Any
        //  911    920    920    921    Ljava/lang/NegativeArraySizeException;
        //  971    980    980    981    Any
        //  971    980    971    972    Ljava/lang/IllegalArgumentException;
        //  972    980    971    972    Any
        //  972    980    980    981    Ljava/lang/NumberFormatException;
        //  972    980    3      8      Ljava/lang/ClassCastException;
        //  1063   1072   1072   1073   Any
        //  1064   1072   1072   1073   Any
        //  1064   1072   3      8      Ljava/lang/IllegalArgumentException;
        //  1064   1072   1063   1064   Ljava/util/ConcurrentModificationException;
        //  1063   1072   1063   1064   Ljava/lang/IllegalStateException;
        //  1085   1094   1094   1095   Any
        //  1086   1094   3      8      Ljava/lang/StringIndexOutOfBoundsException;
        //  1086   1094   1085   1086   Any
        //  1085   1094   1094   1095   Ljava/lang/ArithmeticException;
        //  1085   1094   3      8      Ljava/lang/NumberFormatException;
        //  1106   1113   1113   1114   Any
        //  1107   1113   1113   1114   Ljava/lang/IndexOutOfBoundsException;
        //  1107   1113   1113   1114   Any
        //  1106   1113   1106   1107   Ljava/lang/IndexOutOfBoundsException;
        //  1107   1113   1106   1107   Any
        //  1121   1128   1128   1129   Any
        //  1122   1128   3      8      Any
        //  1122   1128   1121   1122   Any
        //  1121   1128   1121   1122   Ljava/lang/RuntimeException;
        //  1122   1128   1121   1122   Any
        //  1184   1191   1191   1192   Any
        //  1185   1191   1191   1192   Any
        //  1184   1191   3      8      Any
        //  1185   1191   1184   1185   Any
        //  1184   1191   3      8      Any
        //  1203   1210   1210   1211   Any
        //  1204   1210   1210   1211   Ljava/lang/StringIndexOutOfBoundsException;
        //  1203   1210   1210   1211   Ljava/lang/StringIndexOutOfBoundsException;
        //  1203   1210   1203   1204   Any
        //  1203   1210   1210   1211   Any
        //  1265   1272   1272   1273   Any
        //  1265   1272   1272   1273   Any
        //  1265   1272   1272   1273   Ljava/lang/NullPointerException;
        //  1266   1272   1265   1266   Any
        //  1266   1272   1265   1266   Any
        //  1399   1406   1406   1407   Any
        //  1399   1406   3      8      Ljava/lang/ClassCastException;
        //  1399   1406   3      8      Ljava/lang/ArrayIndexOutOfBoundsException;
        //  1399   1406   3      8      Ljava/lang/IndexOutOfBoundsException;
        //  1400   1406   1399   1400   Any
        //  1595   1602   1602   1603   Any
        //  1596   1602   3      8      Any
        //  1595   1602   1595   1596   Any
        //  1595   1602   3      8      Ljava/lang/RuntimeException;
        //  1596   1602   1602   1603   Ljava/lang/ClassCastException;
        //  1645   1652   1652   1653   Any
        //  1645   1652   1645   1646   Ljava/lang/NumberFormatException;
        //  1645   1652   3      8      Ljava/lang/IllegalStateException;
        //  1646   1652   1652   1653   Any
        //  1646   1652   1652   1653   Any
        // 
        // The error that occurred was:
        // 
        // java.lang.IndexOutOfBoundsException: Index -1 out of bounds for length 0
        //     at java.base/jdk.internal.util.Preconditions.outOfBounds(Preconditions.java:64)
        //     at java.base/jdk.internal.util.Preconditions.outOfBoundsCheckIndex(Preconditions.java:70)
        //     at java.base/jdk.internal.util.Preconditions.checkIndex(Preconditions.java:248)
        //     at java.base/java.util.Objects.checkIndex(Objects.java:372)
        //     at java.base/java.util.ArrayList.remove(ArrayList.java:535)
        //     at com.strobel.assembler.ir.StackMappingVisitor.pop(StackMappingVisitor.java:267)
        //     at com.strobel.assembler.ir.StackMappingVisitor$InstructionAnalyzer.execute(StackMappingVisitor.java:586)
        //     at com.strobel.assembler.ir.StackMappingVisitor$InstructionAnalyzer.visit(StackMappingVisitor.java:398)
        //     at com.strobel.decompiler.ast.AstBuilder.performStackAnalysis(AstBuilder.java:2030)
        //     at com.strobel.decompiler.ast.AstBuilder.build(AstBuilder.java:108)
        //     at com.strobel.decompiler.languages.java.ast.AstMethodBodyBuilder.createMethodBody(AstMethodBodyBuilder.java:211)
        //     at com.strobel.decompiler.languages.java.ast.AstMethodBodyBuilder.createMethodBody(AstMethodBodyBuilder.java:99)
        //     at com.strobel.decompiler.languages.java.ast.AstBuilder.createMethodBody(AstBuilder.java:782)
        //     at com.strobel.decompiler.languages.java.ast.AstBuilder.createMethod(AstBuilder.java:675)
        //     at com.strobel.decompiler.languages.java.ast.AstBuilder.addTypeMembers(AstBuilder.java:552)
        //     at com.strobel.decompiler.languages.java.ast.AstBuilder.createTypeCore(AstBuilder.java:519)
        //     at com.strobel.decompiler.languages.java.ast.AstBuilder.createTypeNoCache(AstBuilder.java:161)
        //     at com.strobel.decompiler.languages.java.ast.AstBuilder.createType(AstBuilder.java:150)
        //     at com.strobel.decompiler.languages.java.ast.AstBuilder.addType(AstBuilder.java:125)
        //     at com.strobel.decompiler.languages.java.JavaLanguage.buildAst(JavaLanguage.java:71)
        //     at com.strobel.decompiler.languages.java.JavaLanguage.decompileType(JavaLanguage.java:59)
        //     at com.strobel.decompiler.DecompilerDriver.decompileType(DecompilerDriver.java:330)
        //     at com.strobel.decompiler.DecompilerDriver.decompileJar(DecompilerDriver.java:251)
        //     at com.strobel.decompiler.DecompilerDriver.main(DecompilerDriver.java:126)
        // 
        throw new IllegalStateException("An error occurred while decompiling this method.");
    }
}
